Workbook

Sheet BD_Sales
E1: BD sales 1000 m3 | F1: https://www.gov.br/anp/pt-br/assuntos/distribuicao-e-revenda/leiloes-biodiesel/dados-de-aquisicoes-por-distribuidores
B2: SBO Sales | C2: Mandate | D2: BD sales 1000 m3 | F2: 2018 | G2: 2019 | H2: 2020 | I2: 2021 | J2: 2022 | K2: 2023 | L2: 2024 | M2: 2025 | N2: 5 year average
A3: 43466 | B3: ='[1]Brazil Soy Complex'!CA344 -> 0 | C3: 0.11 | D3: =G3 -> 441.01887 | E3: January | F3: 329.97954 | G3: 441.01887 | H3: 482.97002 | I3: 534.07068 | J3: 426.07239 | K3: 461.59658 | L3: 610.60124 | M3: 679.14378 | N3: =AVERAGE(F3:J3) -> 442.8223
A4: 43497 | B4: ='[1]Brazil Soy Complex'!CA345 -> 0 | C4: 0.11 | D4: =G4 -> 429.33544 | E4: February | F4: 342.8358 | G4: 429.33544 | H4: 483.90427 | I4: 568.84573 | J4: 476.59421 | K4: 463.95434 | L4: 638.04677 | N4: =AVERAGE(F4:J4) -> 460.30309
A5: 43525 | B5: ='[1]Brazil Soy Complex'!CA346 -> 0 | C5: 0.11 | D5: =G5 -> 451.49698 | E5: March | F5: 443.5426 | G5: 451.49698 | H5: 523.97607 | I5: 650.71251 | J5: 501.51706 | K5: 572.24609 | L5: 723.37591 | N5: =AVERAGE(F5:J5) -> 514.24904
A6: 43556 | B6: ='[1]Brazil Soy Complex'!CA347 -> 0 | C6: 0.11 | D6: =G6 -> 469.61133 | E6: April | F6: 453.04355 | G6: 469.61133 | H6: 467.53579 | I6: 648.16135 | J6: 478.94075 | K6: 574.80328 | L6: 790.09309 | N6: =AVERAGE(F6:J6) -> 503.45855
A7: 43586 | B7: ='[1]Brazil Soy Complex'!CA348 -> 0 | C7: 0.11 | D7: =G7 -> 441.69862 | E7: May | F7: 347.73022 | G7: 441.69862 | H7: 499.41171 | I7: 505.12482 | J7: 543.88262 | K7: 622.51179 | L7: 714.62889 | N7: =AVERAGE(F7:J7) -> 467.5696
A8: 43617 | B8: ='[1]Brazil Soy Complex'!CA349 -> 0 | C8: 0.11 | D8: =G8 -> 453.31061 | E8: June | F8: 489.9667 | G8: 453.31061 | H8: 520.99211 | I8: 512.98949 | J8: 511.12819 | K8: 644.08139 | L8: 758.13495 | N8: =AVERAGE(F8:J8) -> 497.67742
A9: 43647 | B9: ='[1]Brazil Soy Complex'!CA350 -> 0 | C9: 0.11 | D9: =G9 -> 480.28392 | E9: July | F9: 483.28767 | G9: 480.28392 | H9: 624.65514 | I9: 539.26004 | J9: 529.6971 | K9: 683.00927 | L9: 843.78541 | N9: =AVERAGE(F9:J9) -> 531.43677
A10: 43678 | B10: ='[1]Brazil Soy Complex'!CA351 -> 0 | C10: 0.11 | D10: =G10 -> 503.08711 | E10: August | F10: 511.62187 | G10: 503.08711 | H10: 615.21859 | I10: 558.58613 | J10: 615.81538 | K10: 725.01403 | L10: 843.87142 | N10: =AVERAGE(F10:J10) -> 560.86582
A11: 43709 | B11: ='[1]Brazil Soy Complex'!CA352 -> 0 | C11: 0.11 | D11: =G11 -> 554.91683 | E11: September | F11: 474.58569 | G11: 554.91683 | H11: 581.02135 | I11: 613.04014 | J11: 550.05392 | K11: 652.2184 | L11: 791.57268 | N11: =AVERAGE(F11:J11) -> 554.72358
A12: 43739 | B12: ='[1]Brazil Soy Complex'!CA353 -> 0 | C12: 0.11 | D12: =G12 -> 603.61058 | E12: October | F12: 505.46134 | G12: 603.61058 | H12: 583.35535 | I12: 637.6943 | J12: 540.69067 | K12: 691.93089 | L12: 883.14745 | N12: =AVERAGE(F12:J12) -> 574.16245
A13: 43770 | B13: ='[1]Brazil Soy Complex'!CA354 -> 0 | C13: 0.11 | D13: =G13 -> 527.93825 | E13: November | F13: 488.76996 | G13: 527.93825 | H13: 520.84735 | I13: 522.97856 | J13: 538.46977 | K13: 666.75299 | L13: 778.6057 | N13: =AVERAGE(F13:J13) -> 519.80078
A14: 43800 | B14: ='[1]Brazil Soy Complex'!CA355 -> 0 | C14: 0.11 | D14: =G14 -> 491.03322 | E14: December | F14: 457.84764 | G14: 491.03322 | H14: 489.03423 | I14: 525.37547 | J14: 480.99526 | K14: 645.31691 | L14: 655.15654 | N14: =AVERAGE(F14:J14) -> 488.85716
A15: 43831 | B15: ='[1]Brazil Soy Complex'!CB344 -> 0 | C15: 0.11 | D15: =H3 -> 482.97002 | F15: =SUM(F3:F14) -> 5328.6726 | G15: =SUM(G3:G14) -> 5847.3417 | H15: =SUM(H3:H14) -> 6392.922 | I15: =SUM(I3:I14) -> 6816.8392 | J15: =SUM(J3:J14) -> 6193.8573 | K15: =SUM(K3:K14) -> 7403.436 | L15: =SUM(L3:L14) -> 9031.02
A16: 43862 | B16: ='[1]Brazil Soy Complex'!CB345 -> 0 | C16: 0.11 | D16: =H4 -> 483.90427 | K16: =(K15/J15)-1 -> 0.19528681
A17: 43891 | B17: ='[1]Brazil Soy Complex'!CB346 -> 0 | C17: 0.12 | D17: =H5 -> 523.97607 | F17: 1000
A18: 43922 | B18: ='[1]Brazil Soy Complex'!CB347 -> 0 | C18: 0.12 | D18: =H6 -> 467.53579
A19: 43952 | B19: ='[1]Brazil Soy Complex'!CB348 -> 0 | C19: 0.12 | D19: =H7 -> 499.41171
A20: 43983 | B20: ='[1]Brazil Soy Complex'!CB349 -> 0 | C20: 0.12 | D20: =H8 -> 520.99211
A21: 44013 | B21: ='[1]Brazil Soy Complex'!CB350 -> 0 | C21: 0.12 | D21: =H9 -> 624.65514
A22: 44044 | B22: ='[1]Brazil Soy Complex'!CB351 -> 0 | C22: 0.12 | D22: =H10 -> 615.21859
A23: 44075 | B23: ='[1]Brazil Soy Complex'!CB352 -> 0 | C23: 0.12 | D23: =H11 -> 581.02135
A24: 44105 | B24: ='[1]Brazil Soy Complex'!CB353 -> 0 | C24: 0.12 | D24: =H12 -> 583.35535
A25: 44136 | B25: ='[1]Brazil Soy Complex'!CB354 -> 0 | C25: 0.12 | D25: =H13 -> 520.84735
A26: 44166 | B26: ='[1]Brazil Soy Complex'!CB355 -> 0 | C26: 0.12 | D26: =H14 -> 489.03423
A27: 44197 | B27: ='[1]Brazil Soy Complex'!CC344 -> January | C27: 0.12 | D27: =I3 -> 534.07068
A28: 44228 | B28: ='[1]Brazil Soy Complex'!CC345 -> February | C28: 0.12 | D28: =I4 -> 568.84573
A29: 44256 | B29: ='[1]Brazil Soy Complex'!CC346 -> March | C29: 0.13 | D29: =I5 -> 650.71251
A30: 44287 | B30: ='[1]Brazil Soy Complex'!CC347 -> April | C30: 0.13 | D30: =I6 -> 648.16135
A31: 44317 | B31: ='[1]Brazil Soy Complex'!CC348 -> May | C31: 0.1 | D31: =I7 -> 505.12482
A32: 44348 | B32: ='[1]Brazil Soy Complex'!CC349 -> June | C32: 0.1 | D32: =I8 -> 512.98949
A33: 44378 | B33: ='[1]Brazil Soy Complex'!CC350 -> July | C33: 0.1 | D33: =I9 -> 539.26004
A34: 44409 | B34: ='[1]Brazil Soy Complex'!CC351 -> August | C34: 0.1 | D34: =I10 -> 558.58613
A35: 44440 | B35: ='[1]Brazil Soy Complex'!CC352 -> September | C35: 0.12 | D35: =I11 -> 613.04014
A36: 44470 | B36: ='[1]Brazil Soy Complex'!CC353 -> October | C36: 0.12 | D36: =I12 -> 637.6943
A37: 44501 | B37: ='[1]Brazil Soy Complex'!CC354 -> November | C37: 0.1 | D37: =I13 -> 522.97856
A38: 44531 | B38: ='[1]Brazil Soy Complex'!CC355 -> December | C38: 0.1 | D38: =I14 -> 525.37547
A39: 44562 | B39: ='[1]Brazil Soy Complex'!CD344 -> 662.11633 | C39: 0.1 | D39: =J3 -> 426.07239
A40: 44593 | B40: ='[1]Brazil Soy Complex'!CD345 -> 598.09369 | C40: 0.1 | D40: =J4 -> 476.59421
A41: 44621 | B41: ='[1]Brazil Soy Complex'!CD346 -> 670.45213 | C41: 0.1 | D41: =J5 -> 501.51706
A42: 44652 | B42: ='[1]Brazil Soy Complex'!CD347 -> 697.29184 | C42: 0.1 | D42: =J6 -> 478.94075
A43: 44682 | B43: ='[1]Brazil Soy Complex'!CD348 -> 588.08384 | C43: 0.1 | D43: =J7 -> 543.88262
A44: 44713 | B44: ='[1]Brazil Soy Complex'!CD349 -> 550.28051 | C44: 0.1 | D44: =J8 -> 511.12819
A45: 44743 | B45: ='[1]Brazil Soy Complex'!CD350 -> 716.37203 | C45: 0.1 | D45: =J9 -> 529.6971
A46: 44774 | B46: ='[1]Brazil Soy Complex'!CD351 -> 632.81482 | C46: 0.1 | D46: =J10 -> 615.81538
A47: 44805 | B47: ='[1]Brazil Soy Complex'!CD352 -> 671.25343 | C47: 0.1 | D47: =J11 -> 550.05392
A48: 44835 | B48: ='[1]Brazil Soy Complex'!CD353 -> 741.78571 | C48: 0.1 | D48: =J12 -> 540.69067
A49: 44866 | B49: ='[1]Brazil Soy Complex'!CD354 -> 680.07585 | C49: 0.1 | D49: =J13 -> 538.46977
A50: 44896 | B50: ='[1]Brazil Soy Complex'!CD355 -> 699.92628 | C50: 0.1 | D50: =J14 -> 480.99526
A51: 44927 | B51: ='[1]Brazil Soy Complex'!CE344 -> 573.00333 | C51: 0.1 | D51: =K3 -> 461.59658
A52: 44958 | B52: ='[1]Brazil Soy Complex'!CE345 -> 620.29302 | C52: 0.1 | D52: =K4 -> 463.95434
A53: 44986 | B53: ='[1]Brazil Soy Complex'!CE346 -> 766.58124 | C53: 0.12 | D53: =K5 -> 572.24609
A54: 45017 | B54: ='[1]Brazil Soy Complex'!CE347 -> 668.71528 | C54: 0.12 | D54: =K6 -> 574.80328
A55: 45047 | B55: ='[1]Brazil Soy Complex'!CE348 -> 688.46132 | C55: 0.12 | D55: =K7 -> 622.51179
A56: 45078 | B56: ='[1]Brazil Soy Complex'!CE349 -> 704.64105 | C56: 0.12 | D56: =K8 -> 644.08139
A57: 45108 | B57: ='[1]Brazil Soy Complex'!CE350 -> 784.39322 | C57: 0.12 | D57: =K9 -> 683.00927
A58: 45139 | B58: ='[1]Brazil Soy Complex'!CE351 -> 776.09945 | C58: 0.12 | D58: =K10 -> 725.01403
A59: 45170 | B59: ='[1]Brazil Soy Complex'!CE352 -> 759.98152 | C59: 0.12 | D59: =K11 -> 652.2184

Sheet Production
A1: https://www.gov.br/anp/pt-br/centrais-de-conteudo/dados-abertos/producao-de-biocombustiveis
A3: Biodiesel Production (thousand m3)
B4: 2005 | C4: 2006 | D4: 2007 | E4: 2008 | F4: 2009 | G4: 2010 | H4: 2011 | I4: 2012 | J4: 2013 | K4: 2014 | L4: 2015 | M4: 2016 | N4: 2017 | O4: 2018 | P4: 2019 | Q4: 2020 | R4: 2021 | S4: 2022 | T4: 2023 | U4: 2024 | V4: 2025 | W4: 2026 | X4: 2027 | Y4: 2028 | Z4: 2029 | AA4: 2030 | AB4: 2031 | AC4: 2032 | AD4: 2033 | AE4: 2034
A5: Jan | B5: 0 | C5: 1075.3 | D5: 17108.739 | E5: 76784.443 | F5: 90352.389 | G5: 147434.67 | H5: 186327.4 | I5: 193006.36 | J5: 226505.27 | K5: 245215.44 | L5: 319546.49 | M5: 271387.9 | N5: 255360.69 | O5: 337255.96 | P5: 446507.77 | Q5: 467595.51 | R5: 506705.18 | S5: 453891.48 | T5: 454949.48 | U5: 615733.2 | V5: 626077.43 | W5: =(SUM(Q5:U5)/SUM(Q$17:U$17))*W$17 -> 713860.9 | X5: =(SUM(R5:V5)/SUM(R$17:V$17))*X$17 -> 761845.69 | Y5: =(SUM(S5:W5)/SUM(S$17:W$17))*Y$17 -> 828434.4 | Z5: =(SUM(T5:X5)/SUM(T$17:X$17))*Z$17 -> 908092.12 | AA5: =(SUM(U5:Y5)/SUM(U$17:Y$17))*AA$17 -> 986288.23 | AB5: =(SUM(V5:Z5)/SUM(V$17:Z$17))*AB$17 -> 1001866.4 | AC5: =(SUM(W5:AA5)/SUM(W$17:AA$17))*AC$17 -> 1026678 | AD5: =(SUM(X5:AB5)/SUM(X$17:AB$17))*AD$17 -> 1041998.4 | AE5: =(SUM(Y5:AC5)/SUM(Y$17:AC$17))*AE$17 -> 1062443
A6: Feb | B6: 0 | C6: 1043.21 | D6: 16932.741 | E6: 77085.038 | F6: 80224.338 | G6: 178049.49 | H6: 176783.19 | I6: 214606.98 | J6: 205738.14 | K6: 240528.55 | L6: 303594.39 | M6: 300065.39 | N6: 259812.09 | O6: 338321.05 | P6: 415248.8 | Q6: 483199.41 | R6: 528605.93 | S6: 489514.39 | T6: 455451.88 | U6: 636556.55 | V6: =(SUM(P6:T6)/SUM(P$17:T$17))*V$17 -> 688129.52 | W6: =(SUM(Q6:U6)/SUM(Q$17:U$17))*W$17 -> 740843.65 | X6: =(SUM(R6:V6)/SUM(R$17:V$17))*X$17 -> 802241.17 | Y6: =(SUM(S6:W6)/SUM(S$17:W$17))*Y$17 -> 870653.72 | Z6: =(SUM(T6:X6)/SUM(T$17:X$17))*Z$17 -> 951244.79 | AA6: =(SUM(U6:Y6)/SUM(U$17:Y$17))*AA$17 -> 1039823.6 | AB6: =(SUM(V6:Z6)/SUM(V$17:Z$17))*AB$17 -> 1057933.5 | AC6: =(SUM(W6:AA6)/SUM(W$17:AA$17))*AC$17 -> 1077121.7 | ... AE6: =(SUM(Y6:AC6)/SUM(Y$17:AC$17))*AE$17 -> 1117320.6
A7: Mar | B7: 7.8 | C7: 1724.84 | D7: 22636.872 | E7: 63679.682 | F7: 131991.44 | G7: 214149.88 | H7: 233464.68 | I7: 220871.82 | J7: 230752.36 | K7: 271838.88 | L7: 322692.03 | M7: 323157.66 | N7: 335069.06 | O7: 455038.97 | P7: 462133.91 | Q7: 550297.8 | R7: 643058.2 | S7: 500195.66 | T7: 552702.51 | U7: 744617.57 | V7: =(SUM(P7:T7)/SUM(P$17:T$17))*V$17 -> 785710.69 | W7: =(SUM(Q7:U7)/SUM(Q$17:U$17))*W$17 -> 854411.09 | X7: =(SUM(R7:V7)/SUM(R$17:V$17))*X$17 -> 924953.35 | Y7: =(SUM(S7:W7)/SUM(S$17:W$17))*Y$17 -> 994185.65 | Z7: =(SUM(T7:X7)/SUM(T$17:X$17))*Z$17 -> 1105578.4 | AA7: =(SUM(U7:Y7)/SUM(U$17:Y$17))*AA$17 -> 1197101.6 | AB7: =(SUM(V7:Z7)/SUM(V$17:Z$17))*AB$17 -> 1217604.8 | AC7: =(SUM(W7:AA7)/SUM(W$17:AA$17))*AC$17 -> 1241307 | ... AE7: =(SUM(Y7:AC7)/SUM(Y$17:AC$17))*AE$17 -> 1287039.2
A8: Apr | B8: 13.1 | C8: 1785.51 | D8: 18772.794 | E8: 64349.825 | F8: 105457.98 | G8: 184896.78 | H8: 200381.09 | I8: 182372.24 | J8: 253591.02 | K8: 253224.47 | L8: 324526.23 | M8: 348485.12 | N8: 347603.11 | O8: 448705.74 | P8: 464901.56 | Q8: 439526.83 | R8: 630955.26 | S8: 479670.36 | T8: 578413.6 | U8: 754333.83 | V8: =(SUM(P8:T8)/SUM(P$17:T$17))*V$17 -> 752371.95 | W8: =(SUM(Q8:U8)/SUM(Q$17:U$17))*W$17 -> 823566.46 | X8: =(SUM(R8:V8)/SUM(R$17:V$17))*X$17 -> 916197.85 | Y8: =(SUM(S8:W8)/SUM(S$17:W$17))*Y$17 -> 979933.19 | Z8: =(SUM(T8:X8)/SUM(T$17:X$17))*Z$17 -> 1094841 | AA8: =(SUM(U8:Y8)/SUM(U$17:Y$17))*AA$17 -> 1175552.4 | AB8: =(SUM(V8:Z8)/SUM(V$17:Z$17))*AB$17 -> 1192043.7 | AC8: =(SUM(W8:AA8)/SUM(W$17:AA$17))*AC$17 -> 1220243.1 | ... AE8: =(SUM(Y8:AC8)/SUM(Y$17:AC$17))*AE$17 -> 1266207
A9: May | B9: 25.75 | C9: 2577.6 | D9: 26004.666 | E9: 75998.89 | F9: 103662.64 | G9: 202728.62 | H9: 220483.98 | I9: 213020.86 | J9: 245933.93 | K9: 242525.6 | L9: 338850.55 | M9: 328814.3 | N9: 369315.73 | O9: 382497.49 | P9: 448352.26 | Q9: 481494.36 | R9: 541733.02 | S9: 536096.95 | T9: 648757.88 | U9: 726908.84 | V9: =(SUM(P9:T9)/SUM(P$17:T$17))*V$17 -> 770638.8 | W9: =(SUM(Q9:U9)/SUM(Q$17:U$17))*W$17 -> 838447.49 | X9: =(SUM(R9:V9)/SUM(R$17:V$17))*X$17 -> 924337.2 | Y9: =(SUM(S9:W9)/SUM(S$17:W$17))*Y$17 -> 1018251.2 | Z9: =(SUM(T9:X9)/SUM(T$17:X$17))*Z$17 -> 1118944.5 | AA9: =(SUM(U9:Y9)/SUM(U$17:Y$17))*AA$17 -> 1190066 | AB9: =(SUM(V9:Z9)/SUM(V$17:Z$17))*AB$17 -> 1219113.5 | AC9: =(SUM(W9:AA9)/SUM(W$17:AA$17))*AC$17 -> 1244685.5 | ... AE9: =(SUM(Y9:AC9)/SUM(Y$17:AC$17))*AE$17 -> 1294928.9
A10: Jun | B10: 22.812 | C10: 6490.31 | D10: 27157.918 | E10: 102766.72 | F10: 141138.84 | G10: 204939.78 | H10: 231572.7 | I10: 214897.82 | J10: 236440.99 | K10: 251517.29 | L10: 322185.27 | M10: 292772.39 | N10: 359235.99 | O10: 466891.51 | P10: 461613.41 | Q10: 533311.34 | R10: 527665.79 | S10: 507868.46 | T10: 657257.06 | U10: 770378.09 | V10: =(SUM(P10:T10)/SUM(P$17:T$17))*V$17 -> 779713.68 | W10: =(SUM(Q10:U10)/SUM(Q$17:U$17))*W$17 -> 856013.43 | X10: =(SUM(R10:V10)/SUM(R$17:V$17))*X$17 -> 929712.01 | Y10: =(SUM(S10:W10)/SUM(S$17:W$17))*Y$17 -> 1032821.6 | Z10: =(SUM(T10:X10)/SUM(T$17:X$17))*Z$17 -> 1142984.2 | AA10: =(SUM(U10:Y10)/SUM(U$17:Y$17))*AA$17 -> 1215114.4 | AB10: =(SUM(V10:Z10)/SUM(V$17:Z$17))*AB$17 -> 1237548.1 | AC10: =(SUM(W10:AA10)/SUM(W$17:AA$17))*AC$17 -> 1265861.9 | ... AE10: =(SUM(Y10:AC10)/SUM(Y$17:AC$17))*AE$17 -> 1318020.8
A11: Jul | B11: 7.178 | C11: 3330.8 | D11: 26718.323 | E11: 107786.27 | F11: 154556.54 | G11: 207433.58 | H11: 249897.1 | I11: 230340.29 | J11: 260670.64 | K11: 302971.29 | L11: 341093.84 | M11: 337435.2 | N11: 387236.43 | O11: 489079.3 | P11: 495344.17 | Q11: 602029.3 | R11: 560642.47 | S11: 568759.54 | T11: 717390.48 | U11: 822084.62 | V11: =(SUM(P11:T11)/SUM(P$17:T$17))*V$17 -> 854110.48 | W11: =(SUM(Q11:U11)/SUM(Q$17:U$17))*W$17 -> 934409.41 | X11: =(SUM(R11:V11)/SUM(R$17:V$17))*X$17 -> 1010016 | Y11: =(SUM(S11:W11)/SUM(S$17:W$17))*Y$17 -> 1126965.1 | Z11: =(SUM(T11:X11)/SUM(T$17:X$17))*Z$17 -> 1241719.5 | AA11: =(SUM(U11:Y11)/SUM(U$17:Y$17))*AA$17 -> 1320516.6 | AB11: =(SUM(V11:Z11)/SUM(V$17:Z$17))*AB$17 -> 1348735.1 | AC11: =(SUM(W11:AA11)/SUM(W$17:AA$17))*AC$17 -> 1377608.9 | ... AE11: =(SUM(Y11:AC11)/SUM(Y$17:AC$17))*AE$17 -> 1434568.7
A12: Aug | B12: 57.12 | C12: 5101.6 | D12: 43958.85 | E12: 109534.49 | F12: 167086.07 | G12: 231159.52 | H12: 247934.29 | I12: 254426.05 | J12: 247610.47 | K12: 314532.08 | L12: 344037.8 | M12: 327183.08 | N12: 399996.84 | O12: 485842.7 | P12: 503145.55 | Q12: 623117.82 | R12: 572322.04 | S12: 582853.12 | T12: 707780.58 | U12: 840448.72 | V12: =(SUM(P12:T12)/SUM(P$17:T$17))*V$17 -> 867180.52 | W12: =(SUM(Q12:U12)/SUM(Q$17:U$17))*W$17 -> 950297.37 | X12: =(SUM(R12:V12)/SUM(R$17:V$17))*X$17 -> 1023661.9 | Y12: =(SUM(S12:W12)/SUM(S$17:W$17))*Y$17 -> 1141947.6 | Z12: =(SUM(T12:X12)/SUM(T$17:X$17))*Z$17 -> 1256420.3 | AA12: =(SUM(U12:Y12)/SUM(U$17:Y$17))*AA$17 -> 1341641.8 | AB12: =(SUM(V12:Z12)/SUM(V$17:Z$17))*AB$17 -> 1367603.4 | AC12: =(SUM(W12:AA12)/SUM(W$17:AA$17))*AC$17 -> 1397255.3 | ... AE12: =(SUM(Y12:AC12)/SUM(Y$17:AC$17))*AE$17 -> 1454542.1
A13: Sep | B13: 2 | C13: 6735.344 | D13: 46013.394 | E13: 132258.43 | F13: 160537.95 | G13: 219987.6 | H13: 233971.4 | I13: 252242.54 | J13: 252713.66 | K13: 312664.82 | L13: 330388.28 | M13: 313309.16 | N13: 398707.43 | O13: 479744.61 | P13: 558226.37 | Q13: 594001.5 | R13: 574625.58 | S13: 549842.54 | T13: 672663.67 | U13: 816106 | V13: =(SUM(P13:T13)/SUM(P$17:T$17))*V$17 -> 855617.19 | W13: =(SUM(Q13:U13)/SUM(Q$17:U$17))*W$17 -> 916221.45 | X13: =(SUM(R13:V13)/SUM(R$17:V$17))*X$17 -> 994496.58 | Y13: =(SUM(S13:W13)/SUM(S$17:W$17))*Y$17 -> 1102005.5 | Z13: =(SUM(T13:X13)/SUM(T$17:X$17))*Z$17 -> 1217988.3 | AA13: =(SUM(U13:Y13)/SUM(U$17:Y$17))*AA$17 -> 1302954.8 | AB13: =(SUM(V13:Z13)/SUM(V$17:Z$17))*AB$17 -> 1327621.1 | AC13: =(SUM(W13:AA13)/SUM(W$17:AA$17))*AC$17 -> 1353165.4 | ... AE13: =(SUM(Y13:AC13)/SUM(Y$17:AC$17))*AE$17 -> 1409567.1
A14: Oct | B14: 33.93 | C14: 8581.441 | D14: 53608.53 | E14: 126817.25 | F14: 156810.6 | G14: 199894.9 | H14: 237885.14 | I14: 251416.18 | J14: 277992.01 | K14: 321602.68 | L14: 359165.72 | M14: 341024.12 | N14: 409343.99 | O14: 500375.91 | P14: 583724.59 | Q14: 587707.62 | R14: 617990.74 | S14: 569334.15 | T14: 704201.3 | U14: 845548.55 | V14: =(SUM(P14:T14)/SUM(P$17:T$17))*V$17 -> 888572.49 | W14: =(SUM(Q14:U14)/SUM(Q$17:U$17))*W$17 -> 949800.31 | X14: =(SUM(R14:V14)/SUM(R$17:V$17))*X$17 -> 1039447.8 | Y14: =(SUM(S14:W14)/SUM(S$17:W$17))*Y$17 -> 1144520.5 | Z14: =(SUM(T14:X14)/SUM(T$17:X$17))*Z$17 -> 1267355.1 | AA14: =(SUM(U14:Y14)/SUM(U$17:Y$17))*AA$17 -> 1353978.5 | AB14: =(SUM(V14:Z14)/SUM(V$17:Z$17))*AB$17 -> 1380703.5 | AC14: =(SUM(W14:AA14)/SUM(W$17:AA$17))*AC$17 -> 1407313.8 | ... AE14: =(SUM(Y14:AC14)/SUM(Y$17:AC$17))*AE$17 -> 1465499.6
A15: Nov | B15: 281.3 | C15: 16024.925 | D15: 56400.565 | E15: 118014.44 | F15: 166192.15 | G15: 207867.65 | H15: 237188.92 | I15: 245320.59 | J15: 265175.51 | K15: 316626.57 | L15: 324662.15 | M15: 321559.97 | N15: 386930.46 | O15: 479104.56 | P15: 539819.53 | Q15: 554070.92 | R15: 528353.33 | S15: 519208.52 | T15: 700224.08 | U15: 815212.82 | V15: =(SUM(P15:T15)/SUM(P$17:T$17))*V$17 -> 824377.98 | W15: =(SUM(Q15:U15)/SUM(Q$17:U$17))*W$17 -> 890462.42 | X15: =(SUM(R15:V15)/SUM(R$17:V$17))*X$17 -> 971137.33 | Y15: =(SUM(S15:W15)/SUM(S$17:W$17))*Y$17 -> 1084374.1 | Z15: =(SUM(T15:X15)/SUM(T$17:X$17))*Z$17 -> 1202619.9 | AA15: =(SUM(U15:Y15)/SUM(U$17:Y$17))*AA$17 -> 1275451.2 | AB15: =(SUM(V15:Z15)/SUM(V$17:Z$17))*AB$17 -> 1298032.8 | AC15: =(SUM(W15:AA15)/SUM(W$17:AA$17))*AC$17 -> 1326359.3 | ... AE15: =(SUM(Y15:AC15)/SUM(Y$17:AC$17))*AE$17 -> 1383427.8
A16: Dec | B16: 285.16957 | C16: 14531.101 | D16: 49015.748 | E16: 112052.94 | F16: 150437.49 | G16: 187856.06 | H16: 216870.04 | I16: 244961.76 | J16: 214364.27 | K16: 348962.24 | L16: 306525.79 | M16: 296144.68 | N16: 381227.85 | O16: 473670.88 | P16: 523443.19 | Q16: 515656.04 | R16: 525724.82 | S16: 497475.09 | T16: 677866.13 | U16: 695109.51 | V16: =(SUM(P16:T16)/SUM(P$17:T$17))*V$17 -> 794929.33 | W16: =(SUM(Q16:U16)/SUM(Q$17:U$17))*W$17 -> 831831.46 | X16: =(SUM(R16:V16)/SUM(R$17:V$17))*X$17 -> 914867.56 | Y16: =(SUM(S16:W16)/SUM(S$17:W$17))*Y$17 -> 1011414.8 | Z16: =(SUM(T16:X16)/SUM(T$17:X$17))*Z$17 -> 1120522.7 | AA16: =(SUM(U16:Y16)/SUM(U$17:Y$17))*AA$17 -> 1181601.8 | AB16: =(SUM(V16:Z16)/SUM(V$17:Z$17))*AB$17 -> 1219882.6 | AC16: =(SUM(W16:AA16)/SUM(W$17:AA$17))*AC$17 -> 1237396.5 | ... AE16: =(SUM(Y16:AC16)/SUM(Y$17:AC$17))*AE$17 -> 1290402.5
A17: Total | B17: =SUM(B5:B16) -> 736.15957 | C17: =SUM(C5:C16) -> 69001.981 | D17: =SUM(D5:D16) -> 404329.14 | E17: =SUM(E5:E16) -> 1167128.4 | F17: =SUM(F5:F16) -> 1608448.4 | G17: =SUM(G5:G16) -> 2386398.5 | H17: =SUM(H5:H16) -> 2672759.9 | I17: =SUM(I5:I16) -> 2717483.5 | ... U17: =SUM(U5:U16) -> 9083038.3 | V17: =U17*1.05 -> 9537190.2 | W17: =V17*1.08 -> 10300165 | X17: =W17*1.09 -> 11227180 | Y17: =X17*1.1 -> 12349898 | Z17: =Y17*1.105 -> 13646638 | AA17: =Z17*1.07 -> 14601902 | AB17: =AA17*1.02 -> 14893940 | AC17: =AB17*1.02 -> 15191819 | AD17: =AC17*1.02 -> 15495656 | AE17: =AD17*1.02 -> 15805569
T18: =(T17/S17)-1 -> 0.20351836 | U18: =(U17/T17)-1 -> 0.20662197 | V18: =(V17/U17)-1 -> 0.05 | W18: =(W17/V17)-1 -> 0.08 | X18: =(X17/W17)-1 -> 0.09 | Y18: =(Y17/X17)-1 -> 0.1 | Z18: =(Z17/Y17)-1 -> 0.105 | AA18: =(AA17/Z17)-1 -> 0.07 | ... AE18: =(AE17/AD17)-1 -> 0.02
A19: Blend Raete (%) | S19: =(S17/1000)/Diesel_Sales!N15 -> 0.098925 | T19: =(T17/1000)/Diesel_Sales!O$15 -> 0.11490769 | U19: =(U17/1000)/Diesel_Sales!P15 -> 0.13597686 | V19: =(V17/1000)/Diesel_Sales!Q15 -> 0.13997618 | W19: =(W17/1000)/Diesel_Sales!R15 -> 0.14821007 | X19: =(X17/1000)/Diesel_Sales!S15 -> 0.15838135 | Y19: =(Y17/1000)/Diesel_Sales!T15 -> 0.17080342 | Z19: =(Z17/1000)/Diesel_Sales!U15 -> 0.18503704 | AA19: =(AA17/1000)/Diesel_Sales!V15 -> 0.19410748 | AB19: =(AB17/1000)/Diesel_Sales!W15 -> 0.19410748 | ... AE19: =(AE17/1000)/Diesel_Sales!Z15 -> 0.19410748
V20: =500*0.98 -> 490
A22: BD/Diesel Sales | G22: =G4 -> 2010 | H22: =H4 -> 2011 | I22: =I4 -> 2012 | J22: =J4 -> 2013 | K22: =K4 -> 2014 | L22: =L4 -> 2015 | M22: =M4 -> 2016 | N22: =N4 -> 2017 | ... AE22: =AE4 -> 2034
A23: January | G23: =(Production!G5/1000)/Diesel_Sales!B3 -> 0.044018051 | H23: =(Production!H5/1000)/Diesel_Sales!C3 -> 0.052389015 | I23: =(Production!I5/1000)/Diesel_Sales!D3 -> 0.04913928 | J23: =(Production!J5/1000)/Diesel_Sales!E3 -> 0.050823757 | K23: =(Production!K5/1000)/Diesel_Sales!F3 -> 0.05370103 | L23: =(Production!L5/1000)/Diesel_Sales!G3 -> 0.067514734 | M23: =(Production!M5/1000)/Diesel_Sales!H3 -> 0.068830267 | N23: =(Production!N5/1000)/Diesel_Sales!I3 -> 0.064498803 | ... AE23: =(Production!AE5/1000)/Diesel_Sales!Z3 -> 0.17751412
A24: February | G24: =(Production!G6/1000)/Diesel_Sales!B4 -> 0.050238748 | H24: =(Production!H6/1000)/Diesel_Sales!C4 -> 0.046036702 | I24: =(Production!I6/1000)/Diesel_Sales!D4 -> 0.051348274 | J24: =(Production!J6/1000)/Diesel_Sales!E4 -> 0.048114535 | K24: =(Production!K6/1000)/Diesel_Sales!F4 -> 0.05139969 | L24: =(Production!L6/1000)/Diesel_Sales!G4 -> 0.074563756 | M24: =(Production!M6/1000)/Diesel_Sales!H4 -> 0.070034186 | N24: =(Production!N6/1000)/Diesel_Sales!I4 -> 0.0643907 | ... AE24: =(Production!AE6/1000)/Diesel_Sales!Z4 -> 0.18220293
A25: March | G25: =(Production!G7/1000)/Diesel_Sales!B5 -> 0.050085021 | H25: =(Production!H7/1000)/Diesel_Sales!C5 -> 0.054324596 | I25: =(Production!I7/1000)/Diesel_Sales!D5 -> 0.046491901 | J25: =(Production!J7/1000)/Diesel_Sales!E5 -> 0.049130314 | K25: =(Production!K7/1000)/Diesel_Sales!F5 -> 0.056455594 | L25: =(Production!L7/1000)/Diesel_Sales!G5 -> 0.064360936 | M25: =(Production!M7/1000)/Diesel_Sales!H5 -> 0.068013933 | N25: =(Production!N7/1000)/Diesel_Sales!I5 -> 0.069056731 | ... AE25: =(Production!AE7/1000)/Diesel_Sales!Z5 -> 0.18541993
A26: April | G26: =(Production!G8/1000)/Diesel_Sales!B6 -> 0.046612253 | H26: =(Production!H8/1000)/Diesel_Sales!C6 -> 0.048980022 | I26: =(Production!I8/1000)/Diesel_Sales!D6 -> 0.042284333 | J26: =(Production!J8/1000)/Diesel_Sales!E6 -> 0.051301554 | K26: =(Production!K8/1000)/Diesel_Sales!F6 -> 0.051835769 | L26: =(Production!L8/1000)/Diesel_Sales!G6 -> 0.068481183 | M26: =(Production!M8/1000)/Diesel_Sales!H6 -> 0.076206074 | N26: =(Production!N8/1000)/Diesel_Sales!I6 -> 0.083828262 | ... AE26: =(Production!AE8/1000)/Diesel_Sales!Z6 -> 0.1970196
A27: May | G27: =(Production!G9/1000)/Diesel_Sales!B7 -> 0.049595529 | H27: =(Production!H9/1000)/Diesel_Sales!C7 -> 0.049727825 | I27: =(Production!I9/1000)/Diesel_Sales!D7 -> 0.045623724 | J27: =(Production!J9/1000)/Diesel_Sales!E7 -> 0.049902011 | K27: =(Production!K9/1000)/Diesel_Sales!F7 -> 0.047258388 | L27: =(Production!L9/1000)/Diesel_Sales!G7 -> 0.073082571 | M27: =(Production!M9/1000)/Diesel_Sales!H7 -> 0.073074392 | N27: =(Production!N9/1000)/Diesel_Sales!I7 -> 0.080030748 | ... AE27: =(Production!AE9/1000)/Diesel_Sales!Z7 -> 0.19019387
A28: June | G28: =(Production!G10/1000)/Diesel_Sales!B8 -> 0.049644449 | H28: =(Production!H10/1000)/Diesel_Sales!C8 -> 0.052807616 | I28: =(Production!I10/1000)/Diesel_Sales!D8 -> 0.04709058 | J28: =(Production!J10/1000)/Diesel_Sales!E8 -> 0.05021407 | K28: =(Production!K10/1000)/Diesel_Sales!F8 -> 0.053426652 | L28: =(Production!L10/1000)/Diesel_Sales!G8 -> 0.066248309 | M28: =(Production!M10/1000)/Diesel_Sales!H8 -> 0.063418926 | N28: =(Production!N10/1000)/Diesel_Sales!I8 -> 0.076801823 | ... AE28: =(Production!AE10/1000)/Diesel_Sales!Z8 -> 0.1952139
A29: July | G29: =(Production!G11/1000)/Diesel_Sales!B9 -> 0.047913275 | H29: =(Production!H11/1000)/Diesel_Sales!C9 -> 0.055296229 | I29: =(Production!I11/1000)/Diesel_Sales!D9 -> 0.048189614 | J29: =(Production!J11/1000)/Diesel_Sales!E9 -> 0.050917237 | K29: =(Production!K11/1000)/Diesel_Sales!F9 -> 0.058414362 | L29: =(Production!L11/1000)/Diesel_Sales!G9 -> 0.068721979 | M29: =(Production!M11/1000)/Diesel_Sales!H9 -> 0.071839937 | N29: =(Production!N11/1000)/Diesel_Sales!I9 -> 0.080315331 | ... AE29: =(Production!AE11/1000)/Diesel_Sales!Z9 -> 0.19754411
A30: August | G30: =(Production!G12/1000)/Diesel_Sales!B10 -> 0.052212878 | H30: =(Production!H12/1000)/Diesel_Sales!C10 -> 0.050980606 | I30: =(Production!I12/1000)/Diesel_Sales!D10 -> 0.048753428 | J30: =(Production!J12/1000)/Diesel_Sales!E10 -> 0.046115488 | K30: =(Production!K12/1000)/Diesel_Sales!F10 -> 0.058780341 | L30: =(Production!L12/1000)/Diesel_Sales!G10 -> 0.068566247 | M30: =(Production!M12/1000)/Diesel_Sales!H10 -> 0.066726152 | N30: =(Production!N12/1000)/Diesel_Sales!I10 -> 0.079974256 | ... AE30: =(Production!AE12/1000)/Diesel_Sales!Z10 -> 0.19331134
A31: September | G31: =(Production!G13/1000)/Diesel_Sales!B11 -> 0.050825815 | H31: =(Production!H13/1000)/Diesel_Sales!C11 -> 0.04880396 | I31: =(Production!I13/1000)/Diesel_Sales!D11 -> 0.053273372 | J31: =(Production!J13/1000)/Diesel_Sales!E11 -> 0.050243183 | K31: =(Production!K13/1000)/Diesel_Sales!F11 -> 0.058380226 | L31: =(Production!L13/1000)/Diesel_Sales!G11 -> 0.066987807 | M31: =(Production!M13/1000)/Diesel_Sales!H11 -> 0.065606447 | N31: =(Production!N13/1000)/Diesel_Sales!I11 -> 0.082096522 | ... AE31: =(Production!AE13/1000)/Diesel_Sales!Z11 -> 0.19886575
A32: October | G32: =(Production!G14/1000)/Diesel_Sales!B12 -> 0.045292385 | H32: =(Production!H14/1000)/Diesel_Sales!C12 -> 0.051126254 | I32: =(Production!I14/1000)/Diesel_Sales!D12 -> 0.047799852 | J32: =(Production!J14/1000)/Diesel_Sales!E12 -> 0.050697605 | K32: =(Production!K14/1000)/Diesel_Sales!F12 -> 0.056099462 | L32: =(Production!L14/1000)/Diesel_Sales!G12 -> 0.069317621 | M32: =(Production!M14/1000)/Diesel_Sales!H12 -> 0.073632115 | N32: =(Production!N14/1000)/Diesel_Sales!I12 -> 0.083271694 | ... AE32: =(Production!AE14/1000)/Diesel_Sales!Z12 -> 0.19899634
A33: November | G33: =(Production!G15/1000)/Diesel_Sales!B13 -> 0.04837396 | H33: =(Production!H15/1000)/Diesel_Sales!C13 -> 0.052213559 | I33: =(Production!I15/1000)/Diesel_Sales!D13 -> 0.049060145 | J33: =(Production!J15/1000)/Diesel_Sales!E13 -> 0.052080959 | K33: =(Production!K15/1000)/Diesel_Sales!F13 -> 0.064483383 | L33: =(Production!L15/1000)/Diesel_Sales!G13 -> 0.071228767 | M33: =(Production!M15/1000)/Diesel_Sales!H13 -> 0.073081264 | N33: =(Production!N15/1000)/Diesel_Sales!I13 -> 0.083378164 | ... AE33: =(Production!AE15/1000)/Diesel_Sales!Z13 -> 0.20472411
A34: December | G34: =(Production!G16/1000)/Diesel_Sales!B14 -> 0.045910518 | H34: =(Production!H16/1000)/Diesel_Sales!C14 -> 0.05058592 | I34: =(Production!I16/1000)/Diesel_Sales!D14 -> 0.054398074 | J34: =(Production!J16/1000)/Diesel_Sales!E14 -> 0.047965033 | K34: =(Production!K16/1000)/Diesel_Sales!F14 -> 0.074096145 | L34: =(Production!L16/1000)/Diesel_Sales!G14 -> 0.068100755 | M34: =(Production!M16/1000)/Diesel_Sales!H14 -> 0.070459807 | N34: =(Production!N16/1000)/Diesel_Sales!I14 -> 0.089675076 | ... AE34: =(Production!AE16/1000)/Diesel_Sales!Z14 -> 0.20210079
G35: =AVERAGE(G23:G34) -> 0.048393573 | H35: =AVERAGE(H23:H34) -> 0.051106025 | I35: =AVERAGE(I23:I34) -> 0.048621048 | J35: =AVERAGE(J23:J34) -> 0.049792146 | K35: =AVERAGE(K23:K34) -> 0.057027587 | L35: =AVERAGE(L23:L34) -> 0.068931222 | M35: =AVERAGE(M23:M34) -> 0.070076958 | N35: =AVERAGE(N23:N34) -> 0.078109842 | ... AE35: =AVERAGE(AE23:AE34) -> 0.19359223

Sheet Diesel_Sales
A1: 1000m3 | B1: 1000
B2: 2010 | C2: 2011 | D2: 2012 | E2: 2013 | F2: 2014 | G2: 2015 | H2: 2016 | I2: 2017 | J2: 2018 | K2: 2019 | L2: 2020 | M2: 2021 | N2: 2022 | O2: 2023 | P2: 2024 | Q2: 2025 | R2: 2026 | S2: 2027 | T2: 2028 | U2: 2029 | V2: 2030 | W2: 2031 | X2: 2032 | Y2: 2033 | Z2: 2034 | AD2: 5 year average
A3: January | B3: 3349.414 | C3: 3556.612 | D3: 3927.741 | E3: 4456.681 | F3: 4566.308 | G3: 4732.989 | H3: 3942.857 | I3: 3959.154 | J3: 4135.727 | K3: 4391.489 | L3: 4432.958 | M3: 4523.801 | N3: 4636.949 | O3: 4542.37 | P3: 5098.249 | Q3: =(SUM(K3:O3)/SUM(K$15:O$15))*Q$15 -> 5022.2741 | R3: =(SUM(L3:P3)/SUM(L$15:P$15))*R$15 -> 5124.1517 | S3: =(SUM(M3:Q3)/SUM(M$15:Q$15))*S$15 -> 5183.8023 | T3: =(SUM(N3:R3)/SUM(N$15:R$15))*T$15 -> 5300.555 | U3: =(SUM(O3:S3)/SUM(O$15:S$15))*U$15 -> 5403.3839 | V3: =(SUM(P3:T3)/SUM(P$15:T$15))*V$15 -> 5567.8028 | W3: =(SUM(Q3:U3)/SUM(Q$15:U$15))*W$15 -> 5633.8344 | X3: =(SUM(R3:V3)/SUM(R$15:V$15))*X$15 -> 5751.8877 | ... Z3: =(SUM(T3:X3)/SUM(T$15:X$15))*Z$15 -> 5985.1184 | AD3: =AVERAGE(J3:N3) -> 4424.1848
A4: February | B4: 3544.067 | C4: 3840.049 | D4: 4179.439 | E4: 4276.008 | F4: 4679.572 | G4: 4071.608 | H4: 4284.556 | I4: 4034.932 | J4: 4120.469 | K4: 4375.209 | L4: 4514.217 | M4: 4440.432 | N4: 4929.314 | O4: 4805.24 | P4: 5069.895 | Q4: =(SUM(K4:O4)/SUM(K$15:O$15))*Q$15 -> 5141.9578 | R4: =(SUM(L4:P4)/SUM(L$15:P$15))*R$15 -> 5239.8859 | S4: =(SUM(M4:Q4)/SUM(M$15:Q$15))*S$15 -> 5306.3485 | T4: =(SUM(N4:R4)/SUM(N$15:R$15))*T$15 -> 5465.991 | U4: =(SUM(O4:S4)/SUM(O$15:S$15))*U$15 -> 5531.5893 | V4: =(SUM(P4:T4)/SUM(P$15:T$15))*V$15 -> 5674.9315 | W4: =(SUM(Q4:U4)/SUM(Q$15:U$15))*W$15 -> 5774.8429 | X4: =(SUM(R4:V4)/SUM(R$15:V$15))*X$15 -> 5890.1792 | ... Z4: =(SUM(T4:X4)/SUM(T$15:X$15))*Z$15 -> 6132.2866 | AD4: =AVERAGE(J4:N4) -> 4475.9282
A5: March | B5: 4275.727 | C5: 4297.587 | D5: 4750.759 | E5: 4696.741 | F5: 4815.092 | G5: 5013.787 | H5: 4751.345 | I5: 4852.084 | J5: 4825.763 | K5: 4554.74 | L5: 4710.553 | M5: 5496.583 | N5: 5461.768 | O5: 5848.364 | P5: 5396.876 | Q5: =(SUM(K5:O5)/SUM(K$15:O$15))*Q$15 -> 5812.4684 | R5: =(SUM(L5:P5)/SUM(L$15:P$15))*R$15 -> 5935.707 | S5: =(SUM(M5:Q5)/SUM(M$15:Q$15))*S$15 -> 6096.033 | T5: =(SUM(N5:R5)/SUM(N$15:R$15))*T$15 -> 6175.4137 | U5: =(SUM(O5:S5)/SUM(O$15:S$15))*U$15 -> 6294.5985 | V5: =(SUM(P5:T5)/SUM(P$15:T$15))*V$15 -> 6365.7761 | W5: =(SUM(Q5:U5)/SUM(Q$15:U$15))*W$15 -> 6560.0447 | X5: =(SUM(R5:V5)/SUM(R$15:V$15))*X$15 -> 6679.7814 | ... Z5: =(SUM(T5:X5)/SUM(T$15:X$15))*Z$15 -> 6941.2131 | AD5: =AVERAGE(J5:N5) -> 5009.8814
A6: April | B6: 3966.699 | C6: 4091.078 | D6: 4312.998 | E6: 4943.145 | F6: 4885.13 | G6: 4738.911 | H6: 4572.931 | I6: 4146.61 | J6: 4618.456 | K6: 4653.643 | L6: 4004.803 | M6: 5085.837 | N6: 4989.82 | O6: 4903.261 | P6: 5637.889 | Q6: =(SUM(K6:O6)/SUM(K$15:O$15))*Q$15 -> 5269.6912 | R6: =(SUM(L6:P6)/SUM(L$15:P$15))*R$15 -> 5430.1063 | S6: =(SUM(M6:Q6)/SUM(M$15:Q$15))*S$15 -> 5632.6603 | T6: =(SUM(N6:R6)/SUM(N$15:R$15))*T$15 -> 5692.6655 | U6: =(SUM(O6:S6)/SUM(O$15:S$15))*U$15 -> 5815.1179 | V6: =(SUM(P6:T6)/SUM(P$15:T$15))*V$15 -> 5986.3191 | W6: =(SUM(Q6:U6)/SUM(Q$15:U$15))*W$15 -> 6024.6717 | X6: =(SUM(R6:V6)/SUM(R$15:V$15))*X$15 -> 6179.7511 | ... Z6: =(SUM(T6:X6)/SUM(T$15:X$15))*Z$15 -> 6426.8073 | AD6: =AVERAGE(J6:N6) -> 4670.5118
A7: May | B7: 4087.639 | C7: 4433.815 | D7: 4669.081 | E7: 4928.337 | F7: 5131.906 | G7: 4636.544 | H7: 4499.72 | I7: 4614.673 | J7: 3772.591 | K7: 4796.704 | L7: 4360.336 | M7: 5022.14 | N7: 5345.129 | O7: 5644.844 | P7: 5646.661 | Q7: =(SUM(K7:O7)/SUM(K$15:O$15))*Q$15 -> 5611.1868 | R7: =(SUM(L7:P7)/SUM(L$15:P$15))*R$15 -> 5738.3142 | S7: =(SUM(M7:Q7)/SUM(M$15:Q$15))*S$15 -> 5933.6889 | T7: =(SUM(N7:R7)/SUM(N$15:R$15))*T$15 -> 6073.6196 | U7: =(SUM(O7:S7)/SUM(O$15:S$15))*U$15 -> 6183.2122 | V7: =(SUM(P7:T7)/SUM(P$15:T$15))*V$15 -> 6276.3963 | W7: =(SUM(Q7:U7)/SUM(Q$15:U$15))*W$15 -> 6392.5068 | X7: =(SUM(R7:V7)/SUM(R$15:V$15))*X$15 -> 6536.4592 | ... Z7: =(SUM(T7:X7)/SUM(T$15:X$15))*Z$15 -> 6808.468 | AD7: =AVERAGE(J7:N7) -> 4659.38
A8: June | B8: 4128.151 | C8: 4385.214 | D8: 4563.499 | E8: 4708.66 | F8: 4707.712 | G8: 4863.298 | H8: 4616.483 | I8: 4677.441 | J8: 5011.739 | K8: 4653.197 | L8: 4696.031 | M8: 5116.07 | N8: 5139.338 | O8: 5458.491 | P8: 5664.523 | Q8: =(SUM(K8:O8)/SUM(K$15:O$15))*Q$15 -> 5587.5494 | R8: =(SUM(L8:P8)/SUM(L$15:P$15))*R$15 -> 5750.5196 | S8: =(SUM(M8:Q8)/SUM(M$15:Q$15))*S$15 -> 5867.5436 | T8: =(SUM(N8:R8)/SUM(N$15:R$15))*T$15 -> 5989.9111 | U8: =(SUM(O8:S8)/SUM(O$15:S$15))*U$15 -> 6129.9661 | V8: =(SUM(P8:T8)/SUM(P$15:T$15))*V$15 -> 6245.3592 | W8: =(SUM(Q8:U8)/SUM(Q$15:U$15))*W$15 -> 6346.0818 | X8: =(SUM(R8:V8)/SUM(R$15:V$15))*X$15 -> 6488.4329 | ... Z8: =(SUM(T8:X8)/SUM(T$15:X$15))*Z$15 -> 6751.6749 | AD8: =AVERAGE(J8:N8) -> 4923.275
A9: July | B9: 4329.355 | C9: 4519.243 | D9: 4779.874 | E9: 5119.497 | F9: 5186.589 | G9: 4963.388 | H9: 4697.042 | I9: 4821.451 | J9: 4982.141 | K9: 5187.02 | L9: 5231.133 | M9: 5617.498 | N9: 5531.483 | O9: 5717.406 | P9: 6069.687 | Q9: =(SUM(K9:O9)/SUM(K$15:O$15))*Q$15 -> 6082.7891 | R9: =(SUM(L9:P9)/SUM(L$15:P$15))*R$15 -> 6212.0604 | S9: =(SUM(M9:Q9)/SUM(M$15:Q$15))*S$15 -> 6314.2337 | T9: =(SUM(N9:R9)/SUM(N$15:R$15))*T$15 -> 6426.7782 | U9: =(SUM(O9:S9)/SUM(O$15:S$15))*U$15 -> 6577.3584 | V9: =(SUM(P9:T9)/SUM(P$15:T$15))*V$15 -> 6731.2893 | W9: =(SUM(Q9:U9)/SUM(Q$15:U$15))*W$15 -> 6841.1501 | X9: =(SUM(R9:V9)/SUM(R$15:V$15))*X$15 -> 6981.4866 | ... Z9: =(SUM(T9:X9)/SUM(T$15:X$15))*Z$15 -> 7262.0172 | AD9: =AVERAGE(J9:N9) -> 5309.855
A10: August | B10: 4427.251 | C10: 4863.306 | D10: 5218.629 | E10: 5369.356 | F10: 5350.974 | G10: 5017.597 | H10: 4903.371 | I10: 5001.57 | J10: 5197.639 | K10: 5284.068 | L10: 5164.411 | M10: 5727.312 | N10: 5811.122 | O10: 6216.33 | P10: 6100.81 | Q10: =(SUM(K10:O10)/SUM(K$15:O$15))*Q$15 -> 6287.6039 | R10: =(SUM(L10:P10)/SUM(L$15:P$15))*R$15 -> 6400.134 | S10: =(SUM(M10:Q10)/SUM(M$15:Q$15))*S$15 -> 6558.8741 | T10: =(SUM(N10:R10)/SUM(N$15:R$15))*T$15 -> 6687.7639 | U10: =(SUM(O10:S10)/SUM(O$15:S$15))*U$15 -> 6830.0074 | V10: =(SUM(P10:T10)/SUM(P$15:T$15))*V$15 -> 6932.4643 | W10: =(SUM(Q10:U10)/SUM(Q$15:U$15))*W$15 -> 7090.2637 | X10: =(SUM(R10:V10)/SUM(R$15:V$15))*X$15 -> 7229.8125 | ... Z10: =(SUM(T10:X10)/SUM(T$15:X$15))*Z$15 -> 7524.3498 | AD10: =AVERAGE(J10:N10) -> 5436.9104
A11: September | B11: 4328.265 | C11: 4794.107 | D11: 4734.871 | E11: 5029.81 | F11: 5355.663 | G11: 4932.066 | H11: 4775.585 | I11: 4856.569 | J11: 4759.687 | K11: 4891.095 | L11: 5237.164 | M11: 5417.722 | N11: 5492.708 | O11: 5761.834 | P11: 5678.938 | Q11: =(SUM(K11:O11)/SUM(K$15:O$15))*Q$15 -> 5974.8828 | R11: =(SUM(L11:P11)/SUM(L$15:P$15))*R$15 -> 6084.4015 | S11: =(SUM(M11:Q11)/SUM(M$15:Q$15))*S$15 -> 6163.4916 | T11: =(SUM(N11:R11)/SUM(N$15:R$15))*T$15 -> 6292.0808 | U11: =(SUM(O11:S11)/SUM(O$15:S$15))*U$15 -> 6418.8266 | V11: =(SUM(P11:T11)/SUM(P$15:T$15))*V$15 -> 6533.9843 | W11: =(SUM(Q11:U11)/SUM(Q$15:U$15))*W$15 -> 6694.0974 | X11: =(SUM(R11:V11)/SUM(R$15:V$15))*X$15 -> 6815.0878 | ... Z11: =(SUM(T11:X11)/SUM(T$15:X$15))*Z$15 -> 7088.0334 | AD11: =AVERAGE(J11:N11) -> 5159.6752
A12: October | B12: 4413.433 | C12: 4652.896 | D12: 5259.769 | E12: 5483.336 | F12: 5732.723 | G12: 5181.449 | H12: 4631.459 | I12: 4915.764 | J12: 5058.806 | K12: 5415.759 | L12: 5537.455 | M12: 5623.056 | N12: 5616.152 | O12: 5755.603 | P12: 6105.772 | Q12: =(SUM(K12:O12)/SUM(K$15:O$15))*Q$15 -> 6230.7058 | R12: =(SUM(L12:P12)/SUM(L$15:P$15))*R$15 -> 6315.8986 | S12: =(SUM(M12:Q12)/SUM(M$15:Q$15))*S$15 -> 6382.2146 | T12: =(SUM(N12:R12)/SUM(N$15:R$15))*T$15 -> 6515.9106 | U12: =(SUM(O12:S12)/SUM(O$15:S$15))*U$15 -> 6662.619 | V12: =(SUM(P12:T12)/SUM(P$15:T$15))*V$15 -> 6827.5778 | W12: =(SUM(Q12:U12)/SUM(Q$15:U$15))*W$15 -> 6948.0804 | X12: =(SUM(R12:V12)/SUM(R$15:V$15))*X$15 -> 7077.2444 | ... Z12: =(SUM(T12:X12)/SUM(T$15:X$15))*Z$15 -> 7364.4551 | AD12: =AVERAGE(J12:N12) -> 5450.2456
A13: November | B13: 4297.098 | C13: 4542.669 | D13: 5000.405 | E13: 5091.602 | F13: 4910.204 | G13: 4558.02 | H13: 4400.033 | I13: 4640.669 | J13: 4738.239 | K13: 4808.772 | L13: 4900.934 | M13: 5106.468 | N13: 5235.23 | O13: 5515.553 | P13: 5433.184 | Q13: =(SUM(K13:O13)/SUM(K$15:O$15))*Q$15 -> 5699.8728 | R13: =(SUM(L13:P13)/SUM(L$15:P$15))*R$15 -> 5776.3046 | S13: =(SUM(M13:Q13)/SUM(M$15:Q$15))*S$15 -> 5872.839 | T13: =(SUM(N13:R13)/SUM(N$15:R$15))*T$15 -> 6002.8724 | U13: =(SUM(O13:S13)/SUM(O$15:S$15))*U$15 -> 6123.2855 | V13: =(SUM(P13:T13)/SUM(P$15:T$15))*V$15 -> 6229.1347 | W13: =(SUM(Q13:U13)/SUM(Q$15:U$15))*W$15 -> 6378.4737 | X13: =(SUM(R13:V13)/SUM(R$15:V$15))*X$15 -> 6493.0068 | ... Z13: =(SUM(T13:X13)/SUM(T$15:X$15))*Z$15 -> 6757.5225 | AD13: =AVERAGE(J13:N13) -> 4957.9286
A14: December | B14: 4091.787 | C14: 4287.162 | D14: 4503.133 | E14: 4469.178 | F14: 4709.587 | G14: 4501.063 | H14: 4203.03 | I14: 4251.213 | J14: 4408.05 | K14: 4286.596 | L14: 4681.908 | M14: 4934.493 | N14: 5037.778 | O14: 5341.191 | P14: 4895.928 | Q14: =Q15-SUM(Q3:Q13) -> 5413.3981 | R14: =R15-SUM(R3:R13) -> 5489.5839 | S14: =S15-SUM(S3:S13) -> 5575.2795 | T14: =T15-SUM(T3:T13) -> 5681.1875 | U14: =U15-SUM(U3:U13) -> 5780.8795 | V14: =V15-SUM(V3:V13) -> 5854.8259 | W14: =W15-SUM(W3:W13) -> 6046.3307 | X14: =X15-SUM(X3:X13) -> 6141.8564 | ... Z14: =Z15-SUM(Z3:Z13) -> 6384.9454 | AD14: =AVERAGE(J14:N14) -> 4669.765
B15: =SUM(B3:B14) -> 49238.886 | C15: =SUM(C3:C14) -> 52263.738 | D15: =SUM(D3:D14) -> 55900.198 | E15: =SUM(E3:E14) -> 58572.351 | F15: =SUM(F3:F14) -> 60031.46 | G15: =SUM(G3:G14) -> 57210.72 | H15: =SUM(H3:H14) -> 54278.412 | I15: =SUM(I3:I14) -> 54772.13 | ... P15: =SUM(P3:P14) -> 66798.412 | Q15: =P15*1.02 -> 68134.38 | R15: =Q15*1.02 -> 69497.068 | S15: =R15*1.02 -> 70887.009 | T15: =S15*1.02 -> 72304.749 | U15: =T15*1.02 -> 73750.844 | V15: =U15*1.02 -> 75225.861 | W15: =V15*1.02 -> 76730.378 | X15: =W15*1.02 -> 78264.986 | ... Z15: =Y15*1.02 -> 81426.891
F16: =(F15/E15)-1 -> 0.024911225 | G16: =(G15/F15)-1 -> -0.046987696 | H16: =(H15/G15)-1 -> -0.05125452 | I16: =(I15/H15)-1 -> 0.0090960288 | J16: =(J15/I15)-1 -> 0.015649875 | K16: =(K15/J15)-1 -> 0.030001902 | L16: =(L15/K15)-1 -> 0.0030299507 | M16: =(M15/L15)-1 -> 0.08072656 | ... P16: =(P15/O15)-1 -> 0.019659829
N18: B12 | O18: =SUM(O3:O4)*0.1+SUM(O5:O14)*0.12 -> 7674.3062 | P18: =SUM(P3:P5)*0.12+SUM(P6:P14)*0.14 -> 9040.4773 | Q18: =SUM(Q3:Q5)*0.14+SUM(Q6:Q14)*0.15 -> 10060.39 | R18: =SUM(R3:R5)*0.15+SUM(R6:R14)*0.16 -> 10956.533 | S18: =SUM(S3:S5)*0.16+SUM(S6:S14)*0.17 -> 11884.93 | T18: =SUM(T3:T5)*0.17+SUM(T6:T14)*0.18 -> 12845.435 | U18: =SUM(U3:U5)*0.18+SUM(U6:U14)*0.19 -> 13840.365 | V18: =SUM(V3:V5)*0.19+SUM(V6:V14)*0.2 -> 14869.087 | W18: =SUM(W3:W5)*0.16+SUM(W6:W14)*0.17 -> 12864.477 | X18: =SUM(X3:X5)*0.12+SUM(X6:X14)*0.14 -> 10590.661 | Y18: =SUM(Y3:Y5)*0.12+SUM(Y6:Y14)*0.14 -> 10802.58 | Z18: =SUM(Z3:Z5)*0.12+SUM(Z6:Z14)*0.14 -> 11018.592
A20: https://www.gov.br/anp/pt-br/centrais-de-conteudo/dados-abertos/vendas-de-derivados-de-petroleo-e-biocombustiveis

Sheet Feedstocks
A1: (1000 ton) | C1: Palm Oil Acid | D1: Soybean Oil Acid | E1: Tallow | F1: Poultry Fat | G1: Choice White Grease | H1: Cotton Oil | I1: Canola Oil | J1: UCO | K1: Sunflower Oil | L1: DCO | M1: Palm Oil | N1: CPKO | O1: Soybean Oil | P1: Yellow Grease | Q1: VegOils | R1: Fats and Greases | S1: Total feedstock consumption | U1: yield
A2: 2017 | B2: Jan | E2: 35.751664 | F2: 1.1373553 | G2: 7.8450616 | H2: 1.021328 | I2: 2.0447101 | J2: 1.8142133 | K2: 0 | L2: 0 | M2: 5.6986655 | N2: 0 | O2: 139.52652 | P2: 24.222632 | Q2: =C2+D2+H2+I2+K2+L2+M2+N2+O2 -> 148.29122 | R2: =S2-Q2 -> 70.770926 | S2: =SUM(C2:P2) -> 219.06215 | V2: =Feedstocks!S2/Production!N5*100 -> 0.085785382 | AJ2: =P2*(P2/$S2)/Production!$N5 -> 1.0488691e-05 | AK2: =Q2*(Q2/$S2)/Production!$N5 -> 0.00039310583 | AL2: =R2*(R2/$S2)/Production!$N5 -> 8.9534079e-05 | AM2: =S2*(S2/$S2)/Production!$N5 -> 0.00085785382
A3: 2017 | B3: Feb | E3: 35.796088 | F3: 2.1295486 | G3: 7.2070782 | H3: 0.046994416 | I3: 1.1531335 | J3: 1.9126844 | K3: 0 | L3: 0 | M3: 3.9364985 | N3: 0 | O3: 145.68293 | P3: 25.229078 | Q3: =C3+D3+H3+I3+K3+L3+M3+N3+O3 -> 150.81956 | R3: =S3-Q3 -> 72.274476 | S3: =SUM(C3:P3) -> 223.09404 | V3: =Feedstocks!S3/Production!N6*100 -> 0.085867457
A4: 2017 | B4: Mar | E4: 28.360328 | F4: 3.734796 | G4: 4.65098 | H4: 0.72368173 | I4: 0.5889334 | J4: 0.89576669 | K4: 0 | L4: 0 | M4: 1.0005086 | N4: 0 | O4: 210.72135 | P4: 34.86658 | Q4: =C4+D4+H4+I4+K4+L4+M4+N4+O4 -> 213.03447 | R4: =S4-Q4 -> 72.508451 | S4: =SUM(C4:P4) -> 285.54293 | V4: =Feedstocks!S4/Production!N7*100 -> 0.085219126
A5: 2017 | B5: Apr | E5: 34.758845 | F5: 2.1126775 | G5: 6.2724883 | H5: 0 | I5: 0.71148752 | J5: 3.5933925 | K5: 0 | L5: 0 | M5: 0.23145963 | N5: 0 | O5: 216.95733 | P5: 34.250445 | Q5: =C5+D5+H5+I5+K5+L5+M5+N5+O5 -> 217.90028 | R5: =S5-Q5 -> 80.987848 | S5: =SUM(C5:P5) -> 298.88813 | V5: =Feedstocks!S5/Production!N8*100 -> 0.085985459
A6: 2017 | B6: May | E6: 40.336298 | F6: 3.5047759 | G6: 5.3843387 | H6: 0.02418129 | I6: 0.52360236 | J6: 6.0933682 | K6: 0 | L6: 0 | M6: 0.32326758 | N6: 0 | O6: 220.17981 | P6: 38.624583 | Q6: =C6+D6+H6+I6+K6+L6+M6+N6+O6 -> 221.05087 | R6: =S6-Q6 -> 93.943364 | S6: =SUM(C6:P6) -> 314.99423 | V6: =Feedstocks!S6/Production!N9*100 -> 0.085291311
A7: 2017 | B7: Jun | E7: 44.515723 | F7: 3.4465424 | G7: 4.6150306 | H7: 0.42023359 | I7: 0.48044332 | J7: 8.0065249 | K7: 0 | L7: 0 | M7: 2.2059442 | N7: 0 | O7: 208.29776 | P7: 38.374779 | Q7: =C7+D7+H7+I7+K7+L7+M7+N7+O7 -> 211.40438 | R7: =S7-Q7 -> 98.9586 | S7: =SUM(C7:P7) -> 310.36298 | V7: =Feedstocks!S7/Production!N10*100 -> 0.08639529
A8: 2017 | B8: Jul | E8: 44.566312 | F8: 4.8478053 | G8: 4.8088177 | H8: 0.67887894 | I8: 0 | J8: 4.7247983 | K8: 0 | L8: 0 | M8: 3.3431862 | N8: 0 | O8: 234.7258 | P8: 26.532267 | Q8: =C8+D8+H8+I8+K8+L8+M8+N8+O8 -> 238.74787 | R8: =S8-Q8 -> 85.48 | S8: =SUM(C8:P8) -> 324.22787 | V8: =Feedstocks!S8/Production!N11*100 -> 0.083728658
A9: 2017 | B9: Aug | E9: 54.465452 | F9: 4.5637773 | G9: 5.1589289 | H9: 0.29706765 | I9: 0 | J9: 2.8349357 | K9: 0 | L9: 0 | M9: 0.55017842 | N9: 0 | O9: 247.60325 | P9: 30.733865 | Q9: =C9+D9+H9+I9+K9+L9+M9+N9+O9 -> 248.4505 | R9: =S9-Q9 -> 97.756959 | S9: =SUM(C9:P9) -> 346.20746 | V9: =Feedstocks!S9/Production!N12*100 -> 0.086552548
A10: 2017 | B10: Sep | E10: 51.51762 | F10: 3.6775953 | G10: 6.9066438 | H10: 0.89656741 | I10: 0 | J10: 4.9263305 | K10: 0 | L10: 0 | M10: 3.6037435 | N10: 0 | O10: 236.80492 | P10: 34.907721 | Q10: =C10+D10+H10+I10+K10+L10+M10+N10+O10 -> 241.30523 | R10: =S10-Q10 -> 101.93591 | S10: =SUM(C10:P10) -> 343.24115 | V10: =Feedstocks!S10/Production!N13*100 -> 0.086088476
A11: 2017 | B11: Oct | E11: 61.507741 | F11: 3.8816573 | G11: 6.8281357 | H11: 2.2753127 | I11: 0 | J11: 5.7586838 | K11: 0 | L11: 0 | M11: 0.13224688 | N11: 0 | O11: 241.66652 | P11: 38.030044 | Q11: =C11+D11+H11+I11+K11+L11+M11+N11+O11 -> 244.07408 | R11: =S11-Q11 -> 116.00626 | S11: =SUM(C11:P11) -> 360.08034 | V11: =Feedstocks!S11/Production!N14*100 -> 0.087965219
A12: 2017 | B12: Nov | D12: 0.0487599 | E12: 49.161135 | F12: 3.7487282 | G12: 8.7742066 | H12: 3.0518723 | I12: 0.50722636 | J12: 6.0175515 | K12: 0 | L12: 0 | M12: 6.003333 | N12: 0 | O12: 220.54683 | P12: 35.344633 | Q12: =C12+D12+H12+I12+K12+L12+M12+N12+O12 -> 230.15803 | R12: =S12-Q12 -> 103.04625 | S12: =SUM(C12:P12) -> 333.20428 | V12: =Feedstocks!S12/Production!N15*100 -> 0.086114771
A13: 2017 | B13: Dec | D13: 0.10695 | E13: 50.152182 | F13: 3.0675461 | G13: 9.1738172 | H13: 2.2239698 | I13: 0.63110988 | J13: 6.6683863 | K13: 0 | L13: 0 | M13: 3.6206045 | N13: 0 | O13: 218.9083 | P13: 29.001647 | Q13: =C13+D13+H13+I13+K13+L13+M13+N13+O13 -> 225.49094 | R13: =S13-Q13 -> 98.063578 | S13: =SUM(C13:P13) -> 323.55451 | V13: =Feedstocks!S13/Production!N16*100 -> 0.084871689
A14: 2018 | B14: Jan | D14: 0.16461 | E14: 56.623924 | F14: 2.7627616 | G14: 7.2273835 | H14: 1.5975516 | I14: 0.23613364 | J14: 3.726561 | K14: 0 | L14: 0.33435284 | M14: 3.9630757 | N14: 0 | O14: 195.72769 | P14: 28.422731 | Q14: =C14+D14+H14+I14+K14+L14+M14+N14+O14 -> 202.02341 | R14: =S14-Q14 -> 98.76336 | S14: =SUM(C14:P14) -> 300.78677 | V14: =Feedstocks!S14/Production!O5*100 -> 0.089186496
A15: 2018 | B15: Feb | D15: 0.1361985 | E15: 43.792283 | F15: 3.8155625 | G15: 6.77072 | H15: 0.50922752 | I15: 0.054832 | J15: 5.5712884 | K15: 0 | L15: 0.6319664 | M15: 4.3260417 | N15: 0 | O15: 195.76561 | P15: 32.141482 | Q15: =C15+D15+H15+I15+K15+L15+M15+N15+O15 -> 201.42388 | R15: =S15-Q15 -> 92.091336 | S15: =SUM(C15:P15) -> 293.51522 | V15: =Feedstocks!S15/Production!O6*100 -> 0.086756416
A16: 2018 | B16: Mar | D16: 0.146475 | E16: 60.003392 | F16: 4.8856459 | G16: 7.8947921 | H16: 0.055424397 | I16: 0 | J16: 7.5181443 | K16: 0 | L16: 0.44178952 | M16: 3.4273437 | N16: 0 | O16: 275.05745 | P16: 36.936883 | Q16: =C16+D16+H16+I16+K16+L16+M16+N16+O16 -> 279.12848 | R16: =S16-Q16 -> 117.23886 | S16: =SUM(C16:P16) -> 396.36734 | V16: =Feedstocks!S16/Production!O7*100 -> 0.087106239
A17: 2018 | B17: Apr | D17: 0.34354479 | E17: 53.034118 | F17: 5.3110899 | G17: 7.9393574 | H17: 0.03165484 | I17: 0 | J17: 7.6960893 | K17: 0 | L17: 0.85415928 | M17: 4.6635377 | N17: 0 | O17: 285.31288 | P17: 39.435307 | Q17: =C17+D17+H17+I17+K17+L17+M17+N17+O17 -> 291.20578 | R17: =S17-Q17 -> 113.41596 | S17: =SUM(C17:P17) -> 404.62174 | V17: =Feedstocks!S17/Production!O8*100 -> 0.0901753
A18: 2018 | B18: May | D18: 0.19344 | E18: 43.658055 | F18: 3.032914 | G18: 5.8803822 | H18: 0.032164692 | I18: 0 | J18: 6.3920074 | K18: 0 | L18: 0.3437396 | M18: 3.2698289 | N18: 0 | O18: 266.81045 | P18: 29.559875 | Q18: =C18+D18+H18+I18+K18+L18+M18+N18+O18 -> 270.64963 | R18: =S18-Q18 -> 88.523234 | S18: =SUM(C18:P18) -> 359.17286 | V18: =Feedstocks!S18/Production!O9*100 -> 0.093902017
A19: 2018 | B19: Jun | D19: 0.405015 | E19: 54.292932 | F19: 4.1439361 | G19: 9.4037387 | H19: 0.27991883 | I19: 0 | J19: 7.2948394 | K19: 0 | L19: 0.42943208 | M19: 2.1517352 | N19: 0 | O19: 312.65322 | P19: 35.430886 | Q19: =C19+D19+H19+I19+K19+L19+M19+N19+O19 -> 315.91932 | R19: =S19-Q19 -> 110.56633 | S19: =SUM(C19:P19) -> 426.48566 | V19: =Feedstocks!S19/Production!O10*100 -> 0.091345772
A20: 2018 | B20: Jul | D20: 0.90111513 | E20: 54.170514 | F20: 5.0037197 | G20: 9.3669467 | H20: 4.1540604 | I20: 0 | J20: 8.5913264 | K20: 0 | L20: 0.69289524 | M20: 5.2545796 | N20: 0 | O20: 320.94376 | P20: 39.55919 | Q20: =C20+D20+H20+I20+K20+L20+M20+N20+O20 -> 331.94641 | R20: =S20-Q20 -> 116.6917 | S20: =SUM(C20:P20) -> 448.63811 | V20: =Feedstocks!S20/Production!O11*100 -> 0.091731159
A21: 2018 | B21: Aug | D21: 0.75599607 | E21: 54.525735 | F21: 2.7940407 | G21: 9.0052133 | H21: 6.6052335 | I21: 0 | J21: 7.9253875 | K21: 0 | L21: 0.95220276 | M21: 2.8465911 | N21: 0 | O21: 316.49982 | P21: 32.732877 | Q21: =C21+D21+H21+I21+K21+L21+M21+N21+O21 -> 327.65984 | R21: =S21-Q21 -> 106.98325 | S21: =SUM(C21:P21) -> 434.6431 | V21: =Feedstocks!S21/Production!O12*100 -> 0.089461692
A22: 2018 | B22: Sep | D22: 0.44453256 | E22: 58.419285 | F22: 1.3502383 | G22: 8.349553 | H22: 8.8060876 | I22: 0.31300424 | J22: 6.64393 | K22: 0 | L22: 0.1595004 | M22: 4.3067145 | N22: 0 | O22: 307.4535 | P22: 44.723105 | Q22: =C22+D22+H22+I22+K22+L22+M22+N22+O22 -> 321.48334 | R22: =S22-Q22 -> 119.48611 | S22: =SUM(C22:P22) -> 440.96945 | V22: =Feedstocks!S22/Production!O13*100 -> 0.091917542
A23: 2018 | B23: Oct | D23: 0.67446204 | E23: 58.776934 | F23: 1.5234326 | G23: 6.1752466 | H23: 9.4932407 | I23: 1.8696442 | J23: 6.1798273 | K23: 0 | L23: 0.28618164 | M23: 5.1096075 | N23: 0 | O23: 314.47068 | P23: 53.288433 | Q23: =C23+D23+H23+I23+K23+L23+M23+N23+O23 -> 331.90381 | R23: =S23-Q23 -> 125.94387 | S23: =SUM(C23:P23) -> 457.84769 | V23: =Feedstocks!S23/Production!O14*100 -> 0.091500745
A24: 2018 | B24: Nov | D24: 0.30762912 | E24: 55.16033 | F24: 1.4381953 | G24: 7.7636782 | H24: 7.7347364 | I24: 0.89843336 | J24: 5.6457838 | K24: 0 | L24: 0.0336398 | M24: 10.263142 | N24: 0 | O24: 293.61906 | P24: 51.833107 | Q24: =C24+D24+H24+I24+K24+L24+M24+N24+O24 -> 312.85664 | R24: =S24-Q24 -> 121.84109 | S24: =SUM(C24:P24) -> 434.69773 | V24: =Feedstocks!S24/Production!O15*100 -> 0.090731287
A25: 2018 | B25: Dec | D25: 0.3748365 | E25: 54.008755 | F25: 1.72003 | G25: 7.6526915 | H25: 5.1630264 | I25: 0.36258212 | J25: 5.4561771 | K25: 0 | L25: 0 | M25: 13.343329 | N25: 0 | O25: 294.30193 | P25: 49.468382 | Q25: =C25+D25+H25+I25+K25+L25+M25+N25+O25 -> 313.5457 | R25: =S25-Q25 -> 118.30604 | S25: =SUM(C25:P25) -> 431.85174 | V25: =Feedstocks!S25/Production!O16*100 -> 0.091171268
A26: 2019 | B26: Jan | D26: 0.7254 | E26: 50.68302 | F26: 1.3990496 | G26: 7.4206079 | H26: 2.239656 | I26: 0 | J26: 7.5627616 | K26: 0 | L26: 0.2326036 | M26: 11.892099 | N26: 0 | O26: 272.72244 | P26: 50.181472 | Q26: =C26+D26+H26+I26+K26+L26+M26+N26+O26 -> 287.8122 | R26: =S26-Q26 -> 117.24691 | S26: =SUM(C26:P26) -> 405.05911 | V26: =Feedstocks!S26/Production!P5*100 -> 0.090717147
A27: 2019 | B27: Feb | D27: 0.3519306 | E27: 50.689763 | F27: 1.9651177 | G27: 6.9238882 | H27: 2.1172714 | I27: 0 | J27: 7.415641 | K27: 0 | L27: 0.03410808 | M27: 6.1141184 | N27: 0 | O27: 250.82995 | P27: 46.591442 | Q27: =C27+D27+H27+I27+K27+L27+M27+N27+O27 -> 259.44738 | R27: =S27-Q27 -> 113.58585 | S27: =SUM(C27:P27) -> 373.03323 | V27: =Feedstocks!S27/Production!P6*100 -> 0.08983367
A28: 2019 | B28: Mar | D28: 0.3859407 | E28: 53.4469 | F28: 1.742095 | G28: 7.7002136 | H28: 2.5304468 | I28: 0 | J28: 5.882988 | K28: 0 | L28: 0.22360784 | M28: 5.2142911 | N28: 0 | O28: 282.86747 | P28: 51.611798 | Q28: =C28+D28+H28+I28+K28+L28+M28+N28+O28 -> 291.22176 | R28: =S28-Q28 -> 120.38399 | S28: =SUM(C28:P28) -> 411.60576 | V28: =Feedstocks!S28/Production!P7*100 -> 0.08906634
A29: 2019 | B29: Apr | D29: 0.43535811 | E29: 49.392806 | F29: 1.997058 | G29: 8.3464147 | H29: 1.4071613 | I29: 0 | J29: 8.0211359 | K29: 0 | L29: 0.0567916 | M29: 5.3145869 | N29: 0 | O29: 293.49728 | P29: 48.55665 | Q29: =C29+D29+H29+I29+K29+L29+M29+N29+O29 -> 300.71118 | R29: =S29-Q29 -> 116.31406 | S29: =SUM(C29:P29) -> 417.02525 | V29: =Feedstocks!S29/Production!P8*100 -> 0.089701839
A30: 2019 | B30: May | D30: 0.36259863 | E30: 43.472103 | F30: 1.5766532 | G30: 5.6252969 | H30: 1.8095088 | I30: 0 | J30: 3.8179223 | K30: 0 | L30: 0 | M30: 8.3432721 | N30: 0 | O30: 299.80909 | P30: 41.793928 | Q30: =C30+D30+H30+I30+K30+L30+M30+N30+O30 -> 310.32447 | R30: =S30-Q30 -> 96.285903 | S30: =SUM(C30:P30) -> 406.61038 | V30: =Feedstocks!S30/Production!P9*100 -> 0.090689936
A31: 2019 | B31: Jun | D31: 0.63798 | E31: 49.34453 | F31: 1.7452974 | G31: 6.9087354 | H31: 1.5286757 | I31: 0 | J31: 7.0336566 | K31: 0 | L31: 0.03626088 | M31: 8.9320062 | N31: 0 | O31: 303.03044 | P31: 44.347856 | Q31: =C31+D31+H31+I31+K31+L31+M31+N31+O31 -> 314.16537 | R31: =S31-Q31 -> 109.38008 | S31: =SUM(C31:P31) -> 423.54544 | V31: =Feedstocks!S31/Production!P10*100 -> 0.091753279
A32: 2019 | B32: Jul | D32: 1.2290508 | E32: 36.719646 | F32: 3.4515501 | G32: 8.4384972 | H32: 2.4641807 | I32: 0 | J32: 6.6545643 | K32: 0 | L32: 0.34286652 | M32: 7.8886316 | N32: 0 | O32: 332.50354 | P32: 52.350853 | Q32: =C32+D32+H32+I32+K32+L32+M32+N32+O32 -> 344.42827 | R32: =S32-Q32 -> 107.61511 | S32: =SUM(C32:P32) -> 452.04338 | V32: =Feedstocks!S32/Production!P11*100 -> 0.091258443
A33: 2019 | B33: Aug | D33: 0.2467848 | E33: 47.139099 | F33: 3.8010091 | G33: 9.4676963 | H33: 5.2953155 | I33: 0 | J33: 8.8064422 | K33: 0 | L33: 0 | M33: 8.9504505 | N33: 0 | O33: 329.06346 | P33: 51.010791 | Q33: =C33+D33+H33+I33+K33+L33+M33+N33+O33 -> 343.55601 | R33: =S33-Q33 -> 120.22504 | S33: =SUM(C33:P33) -> 463.78105 | V33: =Feedstocks!S33/Production!P12*100 -> 0.09217632
A34: 2019 | B34: Sep | D34: 0.28535655 | E34: 62.600245 | F34: 3.0927421 | G34: 9.1135657 | H34: 11.312201 | I34: 0.52266212 | J34: 7.4968212 | K34: 0 | L34: 0.16216104 | M34: 11.44463 | N34: 0 | O34: 346.12277 | P34: 62.299181 | Q34: =C34+D34+H34+I34+K34+L34+M34+N34+O34 -> 369.84978 | R34: =S34-Q34 -> 144.60255 | S34: =SUM(C34:P34) -> 514.45234 | V34: =Feedstocks!S34/Production!P13*100 -> 0.092158372
A35: 2019 | B35: Oct | D35: 0.57296463 | E35: 73.763542 | F35: 2.8659697 | G35: 9.0358708 | H35: 11.790749 | I35: 0.24658576 | J35: 7.6739435 | K35: 0 | L35: 2.436643 | M35: 8.4386827 | N35: 0 | O35: 361.45122 | P35: 66.124264 | Q35: =C35+D35+H35+I35+K35+L35+M35+N35+O35 -> 384.93685 | R35: =S35-Q35 -> 159.46359 | S35: =SUM(C35:P35) -> 544.40044 | V35: =Feedstocks!S35/Production!P14*100 -> 0.093263235
A36: 2019 | B36: Nov | D36: 0.27043005 | E36: 56.645124 | F36: 3.1034188 | G36: 8.708259 | H36: 9.6607692 | I36: 2.11477 | J36: 6.8933246 | K36: 0 | L36: 140.44673 | M36: 12.390253 | N36: 0 | O36: 342.93378 | P36: 50.815666 | Q36: =C36+D36+H36+I36+K36+L36+M36+N36+O36 -> 507.81673 | R36: =S36-Q36 -> 126.16579 | S36: =SUM(C36:P36) -> 633.98252 | V36: =Feedstocks!S36/Production!P15*100 -> 0.11744342
A37: 2019 | B37: Dec | D37: 0.32076723 | E37: 53.417001 | F37: 3.131746 | G37: 9.2750994 | H37: 9.2613479 | I37: 0 | J37: 6.7658919 | K37: 0 | L37: 1.7435463 | M37: 13.385904 | N37: 0 | O37: 333.97066 | P37: 41.813302 | Q37: =C37+D37+H37+I37+K37+L37+M37+N37+O37 -> 358.68223 | R37: =S37-Q37 -> 114.40304 | S37: =SUM(C37:P37) -> 473.08527 | V37: =Feedstocks!S37/Production!P16*100 -> 0.090379487
A38: 2020 | B38: Jan | D38: 1.1651468 | E38: 54.13974 | F38: 3.7474102 | G38: 7.4336606 | H38: 7.9876688 | I38: 1.068488 | J38: 6.6490306 | K38: 0 | L38: 2.0219604 | M38: 11.053948 | N38: 0 | O38: 284.05003 | P38: 48.206121 | Q38: =C38+D38+H38+I38+K38+L38+M38+N38+O38 -> 307.34725 | R38: =S38-Q38 -> 120.17596 | S38: =SUM(C38:P38) -> 427.52321 | V38: =Feedstocks!S38/Production!Q5*100 -> 0.091430135
A39: 2020 | B39: Feb | C39: 0.06954188 | D39: 0.70484421 | E39: 48.462146 | F39: 2.8804186 | G39: 8.5819474 | H39: 7.6979408 | I39: 0 | J39: 7.8983759 | K39: 0 | L39: 1.196518 | M39: 7.5930786 | N39: 0 | O39: 305.94183 | P39: 50.810672 | Q39: =C39+D39+H39+I39+K39+L39+M39+N39+O39 -> 323.20375 | R39: =S39-Q39 -> 118.63356 | S39: =SUM(C39:P39) -> 441.83731 | V39: =Feedstocks!S39/Production!Q6*100 -> 0.091439952
A40: 2020 | B40: Mar | C40: 0.0399694 | D40: 0.93717216 | E40: 41.220544 | F40: 4.95206 | G40: 7.6837362 | H40: 4.7852214 | I40: 0 | J40: 8.5394591 | K40: 0 | L40: 2.0874165 | M40: 9.5866225 | N40: 0 | O40: 359.20272 | P40: 56.43246 | Q40: =C40+D40+H40+I40+K40+L40+M40+N40+O40 -> 376.63912 | R40: =S40-Q40 -> 118.82826 | S40: =SUM(C40:P40) -> 495.46738 | V40: =Feedstocks!S40/Production!Q7*100 -> 0.090036227
A41: 2020 | B41: Apr | C41: 0 | D41: 0.79803114 | E41: 35.106974 | F41: 2.3537058 | G41: 9.4793479 | H41: 2.4062218 | I41: 0 | J41: 4.0969674 | K41: 0 | L41: 1.9926206 | M41: 4.4123138 | N41: 0 | O41: 306.49935 | P41: 39.190215 | Q41: =C41+D41+H41+I41+K41+L41+M41+N41+O41 -> 316.10853 | R41: =S41-Q41 -> 90.22721 | S41: =SUM(C41:P41) -> 406.33574 | V41: =Feedstocks!S41/Production!Q8*100 -> 0.09244845
A42: 2020 | B42: May | C42: 0.15472744 | D42: 0.45821007 | E42: 34.723719 | F42: 2.9325873 | G42: 10.725661 | H42: 4.2697547 | I42: 0 | J42: 4.2378318 | K42: 0 | L42: 0.91641292 | M42: 9.3598683 | N42: 0 | O42: 345.33703 | P42: 42.18528 | Q42: =C42+D42+H42+I42+K42+L42+M42+N42+O42 -> 360.496 | R42: =S42-Q42 -> 94.805079 | S42: =SUM(C42:P42) -> 455.30108 | V42: =Feedstocks!S42/Production!Q9*100 -> 0.094560002
A43: 2020 | B43: Jun | C43: 0.05478692 | D43: 1.0385143 | E43: 47.582883 | F43: 2.9082116 | G43: 12.631445 | H43: 4.1829579 | I43: 0 | J43: 5.1541863 | K43: 0 | L43: 0.68535584 | M43: 16.265133 | N43: 0 | O43: 350.43128 | P43: 61.06508 | Q43: =C43+D43+H43+I43+K43+L43+M43+N43+O43 -> 372.65803 | R43: =S43-Q43 -> 129.34181 | S43: =SUM(C43:P43) -> 501.99983 | V43: =Feedstocks!S43/Production!Q10*100 -> 0.09412885
A44: 2020 | B44: Jul | C44: 0.02074968 | D44: 1.3220238 | E44: 41.989854 | F44: 3.2286439 | G44: 12.478888 | H44: 7.6137877 | I44: 0 | J44: 4.889299 | K44: 0 | L44: 0.93576972 | M44: 20.569825 | N44: 0 | O44: 401.32509 | P44: 58.687158 | Q44: =C44+D44+H44+I44+K44+L44+M44+N44+O44 -> 431.78725 | R44: =S44-Q44 -> 121.27384 | S44: =SUM(C44:P44) -> 553.06109 | V44: =Feedstocks!S44/Production!Q11*100 -> 0.091866143
A45: 2020 | B45: Aug | C45: 2.4363992 | D45: 0.93048546 | E45: 40.069244 | F45: 4.7051653 | G45: 9.6795661 | H45: 12.981377 | I45: 0 | J45: 5.2624308 | K45: 0 | L45: 0.78293196 | M45: 14.629784 | N45: 0.097416 | O45: 419.82487 | P45: 67.717402 | Q45: =C45+D45+H45+I45+K45+L45+M45+N45+O45 -> 451.68327 | R45: =S45-Q45 -> 127.43381 | S45: =SUM(C45:P45) -> 579.11707 | V45: =Feedstocks!S45/Production!Q12*100 -> 0.092938615
A46: 2020 | B46: Sep | C46: 0 | D46: 1.6233345 | E46: 42.510905 | F46: 3.2796399 | G46: 8.4111392 | H46: 13.473824 | I46: 0.43923284 | J46: 6.7639945 | K46: 1.2966071 | L46: 1.1487258 | M46: 10.478233 | N46: 0.2065545 | O46: 396.74455 | P46: 62.047872 | Q46: =C46+D46+H46+I46+K46+L46+M46+N46+O46 -> 425.41106 | R46: =S46-Q46 -> 123.01355 | S46: =SUM(C46:P46) -> 548.42461 | V46: =Feedstocks!S46/Production!Q13*100 -> 0.092327142
A47: 2020 | B47: Oct | C47: 0 | D47: 1.827185 | E47: 41.725082 | F47: 1.5913866 | G47: 7.2371594 | H47: 13.234362 | I47: 0.6984042 | J47: 6.0260528 | K47: 0 | L47: 1.0716418 | M47: 12.289168 | N47: 0 | O47: 405.70908 | P47: 67.008488 | Q47: =C47+D47+H47+I47+K47+L47+M47+N47+O47 -> 434.82984 | R47: =S47-Q47 -> 123.58817 | S47: =SUM(C47:P47) -> 558.41801 | V47: =Feedstocks!S47/Production!Q14*100 -> 0.095016295
A48: 2020 | B48: Nov | C48: 0 | D48: 0.50908107 | E48: 39.725443 | F48: 1.2384702 | G48: 6.2031665 | H48: 11.225138 | I48: 0.6574136 | J48: 5.6961759 | K48: 0 | L48: 0.43563104 | M48: 14.205719 | N48: 0 | O48: 380.21778 | P48: 62.477966 | Q48: =C48+D48+H48+I48+K48+L48+M48+N48+O48 -> 407.25076 | R48: =S48-Q48 -> 115.34122 | S48: =SUM(C48:P48) -> 522.59199 | V48: =Feedstocks!S48/Production!Q15*100 -> 0.09431861
A49: 2020 | B49: Dec | C49: 0.14725244 | D49: 1.0059345 | E49: 53.759561 | F49: 1.7661331 | G49: 9.1674064 | H49: 11.316718 | I49: 0.6019928 | J49: 5.5178705 | K49: 0 | L49: 0.40177872 | M49: 17.676992 | N49: 0 | O49: 334.0053 | P49: 53.64024 | Q49: =C49+D49+H49+I49+K49+L49+M49+N49+O49 -> 365.15597 | R49: =S49-Q49 -> 123.85121 | S49: =SUM(C49:P49) -> 489.00718 | V49: =Feedstocks!S49/Production!Q16*100 -> 0.094832048
A50: 2021 | B50: Jan | C50: 0 | D50: 0.97543608 | E50: 56.175509 | F50: 3.0299577 | G50: 9.1060166 | H50: 11.631197 | I50: 0.2685204 | J50: 5.3926063 | K50: 0 | L50: 0.24747908 | M50: 14.01386 | N50: 0 | O50: 326.95941 | P50: 49.221006 | Q50: =C50+D50+H50+I50+K50+L50+M50+N50+O50 -> 354.0959 | R50: =S50-Q50 -> 122.9251 | S50: =SUM(C50:P50) -> 477.021 | V50: =Feedstocks!S50/Production!R5*100 -> 0.094141725
A51: 2021 | B51: Feb | C51: 0 | D51: 0.84165186 | E51: 42.515734 | F51: 0.77868915 | G51: 9.335366 | H51: 10.374941 | I51: 0.2276632 | J51: 8.3206178 | K51: 0 | L51: 0.34777104 | M51: 14.821274 | N51: 0 | O51: 338.8494 | P51: 52.79712 | Q51: =C51+D51+H51+I51+K51+L51+M51+N51+O51 -> 365.4627 | R51: =S51-Q51 -> 113.74753 | S51: =SUM(C51:P51) -> 479.21023 | V51: =Feedstocks!S51/Production!R6*100 -> 0.090655477
A52: 2021 | B52: Mar | C52: 0 | D52: 1.103378 | E52: 48.831055 | F52: 4.1445243 | G52: 6.9902062 | H52: 10.315233 | I52: 0.03788284 | J52: 8.1849759 | K52: 0 | L52: 0.26245484 | M52: 13.866889 | N52: 0 | O52: 419.70613 | P52: 65.386742 | Q52: =C52+D52+H52+I52+K52+L52+M52+N52+O52 -> 445.29197 | R52: =S52-Q52 -> 133.5375 | S52: =SUM(C52:P52) -> 578.82947 | V52: =Feedstocks!S52/Production!R7*100 -> 0.090011988
A53: 2021 | B53: Apr | C53: 0 | D53: 2.1159992 | E53: 42.32628 | F53: 4.023469 | G53: 6.3767491 | H53: 3.0375579 | I53: 0 | J53: 9.466558 | K53: 0 | L53: 0.97180704 | M53: 14.903447 | N53: 0.1227258 | O53: 430.84062 | P53: 64.082788 | Q53: =C53+D53+H53+I53+K53+L53+M53+N53+O53 -> 451.99215 | R53: =S53-Q53 -> 126.27584 | S53: =SUM(C53:P53) -> 578.268 | V53: =Feedstocks!S53/Production!R8*100 -> 0.091649604
A54: 2021 | B54: May | C54: 0 | D54: 1.0829069 | E54: 35.153716 | F54: 1.6408026 | G54: 10.166491 | H54: 3.6143051 | I54: 0 | J54: 8.2474974 | K54: 0 | L54: 0.25383996 | M54: 14.836741 | N54: 0 | O54: 357.31997 | P54: 64.9423 | Q54: =C54+D54+H54+I54+K54+L54+M54+N54+O54 -> 377.10776 | R54: =S54-Q54 -> 120.15081 | S54: =SUM(C54:P54) -> 497.25857 | V54: =Feedstocks!S54/Production!R9*100 -> 0.091790338
A55: 2021 | B55: Jun | C55: 0 | D55: 1.2607108 | E55: 31.646141 | F55: 1.9130761 | G55: 7.5322582 | H55: 5.0948428 | I55: 0 | J55: 6.797154 | K55: 0 | L55: 0.6572986 | M55: 9.3976631 | N55: 0 | O55: 359.79323 | P55: 55.321968 | Q55: =C55+D55+H55+I55+K55+L55+M55+N55+O55 -> 376.20374 | R55: =S55-Q55 -> 103.2106 | S55: =SUM(C55:P55) -> 479.41434 | V55: =Feedstocks!S55/Production!R10*100 -> 0.090855679
A56: 2021 | B56: Jul | C56: 0 | D56: 0.77082864 | E56: 30.432301 | F56: 2.8290643 | G56: 13.353028 | H56: 5.5904492 | I56: 0 | J56: 8.5324184 | K56: 0 | L56: 0.32804348 | M56: 8.3809903 | N56: 0 | O56: 397.91064 | P56: 55.461216 | Q56: =C56+D56+H56+I56+K56+L56+M56+N56+O56 -> 412.98095 | R56: =S56-Q56 -> 110.60803 | S56: =SUM(C56:P56) -> 523.58898 | V56: =Feedstocks!S56/Production!R11*100 -> 0.093390887
A57: 2021 | B57: Aug | C57: 0 | D57: 0.8384973 | E57: 29.575442 | F57: 4.6935804 | G57: 12.520222 | H57: 5.4032327 | I57: 0 | J57: 8.0618001 | K57: 0 | L57: 0.50608372 | M57: 8.9514117 | N57: 0 | O57: 399.99276 | P57: 60.674853 | Q57: =C57+D57+H57+I57+K57+L57+M57+N57+O57 -> 415.69199 | R57: =S57-Q57 -> 115.5259 | S57: =SUM(C57:P57) -> 531.21789 | V57: =Feedstocks!S57/Production!R12*100 -> 0.092818002
A58: 2021 | B58: Sep | C58: 0.1445136 | D58: 0.73244568 | E58: 39.675059 | F58: 6.4324259 | G58: 11.906472 | H58: 9.1651188 | I58: 0 | J58: 10.320362 | K58: 0 | L58: 0 | M58: 10.690396 | N58: 0 | O58: 370.52328 | P58: 63.728743 | Q58: =C58+D58+H58+I58+K58+L58+M58+N58+O58 -> 391.25575 | R58: =S58-Q58 -> 132.06306 | S58: =SUM(C58:P58) -> 523.31882 | V58: =Feedstocks!S58/Production!R13*100 -> 0.09107127
A59: 2021 | B59: Oct | C59: 0 | D59: 0.69926421 | E59: 40.293876 | F59: 7.0934545 | G59: 10.014246 | H59: 10.486385 | I59: 1.1145809 | J59: 11.15584 | K59: 0 | L59: 0.06878012 | M59: 13.317835 | N59: 0 | O59: 404.94928 | P59: 67.794495 | Q59: =C59+D59+H59+I59+K59+L59+M59+N59+O59 -> 430.63613 | R59: =S59-Q59 -> 136.35191 | S59: =SUM(C59:P59) -> 566.98804 | V59: =Feedstocks!S59/Production!R14*100 -> 0.091747013
A60: 2021 | B60: Nov | C60: 0.15472744 | D60: 0.78258756 | E60: 41.57165 | F60: 7.2703507 | G60: 7.7947195 | H60: 9.222932 | I60: 1.4299036 | J60: 9.3236188 | K60: 0 | L60: 0.62140204 | M60: 13.944483 | N60: 0 | O60: 349.47803 | P60: 60.959256 | Q60: =C60+D60+H60+I60+K60+L60+M60+N60+O60 -> 375.63406 | R60: =S60-Q60 -> 126.91959 | S60: =SUM(C60:P60) -> 502.55366 | V60: =Feedstocks!S60/Production!R15*100 -> 0.095116966
A61: 2021 | B61: Dec | C61: 0.20909116 | D61: 1.0044614 | E61: 44.022394 | F61: 5.4810287 | G61: 6.9513167 | H61: 10.13304 | I61: 0.4194648 | J61: 9.9122615 | K61: 0 | L61: 0.37407936 | M61: 13.41588 | N61: 0 | O61: 354.89669 | P61: 45.649143 | Q61: =C61+D61+H61+I61+K61+L61+M61+N61+O61 -> 380.45271 | R61: =S61-Q61 -> 112.01614 | S61: =SUM(C61:P61) -> 492.46885 | V61: =Feedstocks!S61/Production!R16*100 -> 0.093674264
A62: 2022 | B62: Jan | C62: 0.13590884 | D62: 0.38120421 | E62: 40.737573 | F62: 5.6400029 | G62: 10.769862 | H62: 5.7648709 | I62: 0.27044688 | J62: 11.210521 | K62: 0 | L62: 0.2548722 | M62: 12.205716 | N62: 0 | O62: 281.43781 | P62: 65.227449 | Q62: =C62+D62+H62+I62+K62+L62+M62+N62+O62 -> 300.45083 | R62: =S62-Q62 -> 133.58541 | S62: =SUM(C62:P62) -> 434.03624 | V62: =Feedstocks!S62/Production!S5*100 -> 0.095625554
A63: 2022 | B63: Feb | C63: 0.0855692 | D63: 0.36343749 | E63: 39.957473 | F63: 5.7742396 | G63: 9.0589321 | H63: 8.8869386 | I63: 0.0571734 | J63: 9.9957967 | K63: 0 | L63: 0.35109592 | M63: 8.4086773 | N63: 0 | O63: 308.27332 | P63: 63.075121 | Q63: =C63+D63+H63+I63+K63+L63+M63+N63+O63 -> 326.42622 | R63: =S63-Q63 -> 127.86156 | S63: =SUM(C63:P63) -> 454.28778 | V63: =Feedstocks!S63/Production!S6*100 -> 0.092803763
A64: 2022 | B64: Mar | C64: 0 | D64: 1.0989996 | E64: 35.211615 | F64: 8.1803586 | G64: 13.652855 | H64: 6.1295425 | I64: 0.46904268 | J64: 8.5184818 | K64: 0 | L64: 0.89636888 | M64: 12.834635 | N64: 0 | O64: 301.72247 | P64: 76.538814 | Q64: =C64+D64+H64+I64+K64+L64+M64+N64+O64 -> 323.15106 | R64: =S64-Q64 -> 142.10213 | S64: =SUM(C64:P64) -> 465.25318 | V64: =Feedstocks!S64/Production!S7*100 -> 0.093014237
A65: 2022 | B65: Apr | C65: 0 | D65: 0.49784853 | E65: 31.374575 | F65: 7.1351005 | G65: 12.128669 | H65: 3.4170941 | I65: 0.0299276 | J65: 8.0222952 | K65: 0 | L65: 0.34701388 | M65: 12.582493 | N65: 0 | O65: 300.01168 | P65: 76.503481 | Q65: =C65+D65+H65+I65+K65+L65+M65+N65+O65 -> 316.88606 | R65: =S65-Q65 -> 135.16412 | S65: =SUM(C65:P65) -> 452.05018 | V65: =Feedstocks!S65/Production!S8*100 -> 0.094241841
A66: 2022 | B66: May | C66: 0.03164616 | D66: 0.45550191 | E66: 36.447757 | F66: 4.5042423 | G66: 10.196596 | H66: 1.5162916 | I66: 0 | J66: 10.908596 | K66: 0 | L66: 0.38850036 | M66: 8.2950581 | N66: 0 | O66: 349.12505 | P66: 87.729146 | Q66: =C66+D66+H66+I66+K66+L66+M66+N66+O66 -> 359.81205 | R66: =S66-Q66 -> 149.78634 | S66: =SUM(C66:P66) -> 509.59839 | V66: =Feedstocks!S66/Production!S9*100 -> 0.095057132
A67: 2022 | B67: Jun | C67: 0.07222 | D67: 0.4692315 | E67: 35.679917 | F67: 3.8650194 | G67: 9.5212807 | H67: 1.962866 | I67: 0 | J67: 9.6146878 | K67: 0 | L67: 0.80796884 | M67: 8.2362389 | N67: 0 | O67: 332.27653 | P67: 81.080435 | Q67: =C67+D67+H67+I67+K67+L67+M67+N67+O67 -> 343.82506 | R67: =S67-Q67 -> 139.76134 | S67: =SUM(C67:P67) -> 483.58639 | V67: =Feedstocks!S67/Production!S10*100 -> 0.095218827
A68: 2022 | B68: Jul | C68: 0.03425988 | D68: 0.43355484 | E68: 41.938036 | F68: 3.3391548 | G68: 11.740133 | H68: 3.2410851 | I68: 0 | J68: 13.639644 | K68: 0 | L68: 0.20612324 | M68: 12.280588 | N68: 0 | O68: 356.90801 | P68: 88.478867 | Q68: =C68+D68+H68+I68+K68+L68+M68+N68+O68 -> 373.10362 | R68: =S68-Q68 -> 159.13584 | S68: =SUM(C68:P68) -> 532.23946 | V68: =Feedstocks!S68/Production!S11*100 -> 0.093578994
A69: 2022 | B69: Aug | D69: 0.89333847 | E69: 37.860452 | F69: 4.3859032 | G69: 14.725264 | H69: 4.6522289 | I69: 0 | J69: 11.914355 | K69: 0 | L69: 0.36823552 | M69: 14.292434 | N69: 0 | O69: 362.84432 | P69: 90.104426 | Q69: =C69+D69+H69+I69+K69+L69+M69+N69+O69 -> 383.05056 | R69: =S69-Q69 -> 158.9904 | S69: =SUM(C69:P69) -> 542.04096 | V69: =Feedstocks!S69/Production!S12*100 -> 0.092997865
A70: 2022 | B70: Sep | D70: 1.2738917 | E70: 35.483428 | F70: 4.908393 | G70: 17.635535 | H70: 7.230479 | I70: 0 | J70: 14.541992 | K70: 0 | L70: 0.4876138 | M70: 11.048636 | N70: 0 | O70: 340.86756 | P70: 85.869063 | Q70: =C70+D70+H70+I70+K70+L70+M70+N70+O70 -> 360.90819 | R70: =S70-Q70 -> 158.43841 | S70: =SUM(C70:P70) -> 519.3466 | V70: =Feedstocks!S70/Production!S13*100 -> 0.094453694
A71: 2022 | B71: Oct | D71: 1.0984714 | E71: 38.650678 | F71: 4.5582423 | G71: 14.551217 | H71: 9.5241546 | I71: 0.23426512 | J71: 9.1833059 | K71: 0 | L71: 0.57392268 | M71: 6.5117731 | N71: 0 | O71: 360.58512 | P71: 79.707708 | Q71: =C71+D71+H71+I71+K71+L71+M71+N71+O71 -> 378.52771 | R71: =S71-Q71 -> 146.65115 | S71: =SUM(C71:P71) -> 525.17886 | V71: =Feedstocks!S71/Production!S14*100 -> 0.092244398
A72: 2022 | B72: Nov | D72: 1.0313096 | E72: 48.953534 | F72: 7.5930781 | G72: 20.936862 | H72: 9.8998036 | I72: 0.83082256 | J72: 12.378073 | K72: 0 | L72: 2.0221407 | M72: 5.9377204 | N72: 0 | O72: 300.47121 | P72: 73.248549 | Q72: =C72+D72+H72+I72+K72+L72+M72+N72+O72 -> 320.193 | R72: =S72-Q72 -> 163.1101 | S72: =SUM(C72:P72) -> 483.3031 | V72: =Feedstocks!S72/Production!S15*100 -> 0.093084585
A73: 2022 | B73: Dec | D73: 0.86474004 | E73: 46.797463 | F73: 6.2760425 | G73: 16.716679 | H73: 9.103159 | I73: 0.9405758 | J73: 15.167433 | K73: 0 | L73: 4.8499355 | M73: 9.7963582 | N73: 0.5079978 | O73: 279.54532 | P73: 71.496585 | Q73: =C73+D73+H73+I73+K73+L73+M73+N73+O73 -> 305.60808 | R73: =S73-Q73 -> 156.4542 | S73: =SUM(C73:P73) -> 462.06228 | V73: =Feedstocks!S73/Production!S16*100 -> 0.092881492
A74: 2023 | B74: Jan | D74: 0.66244923 | E74: 43.432702 | F74: 5.9864378 | G74: 18.574599 | H74: 7.5885033 | I74: 1.0812125 | J74: 13.117239 | K74: 0 | L74: 0.41671032 | M74: 12.927684 | N74: 0 | O74: 258.75439 | P74: 58.981325 | Q74: =C74+D74+H74+I74+K74+L74+M74+N74+O74 -> 281.43095 | R74: =S74-Q74 -> 140.0923 | S74: =SUM(C74:P74) -> 421.52326 | V74: =Feedstocks!S74/Production!T5*100 -> 0.092652762 | X74: =J74/S74 -> 0.03111866
A75: 2023 | B75: Feb | D75: 0.37825239 | E75: 41.380766 | F75: 6.8807239 | G75: 12.890195 | H75: 5.6326147 | I75: 1.5220995 | J75: 12.52206 | K75: 0 | L75: 0.69481712 | M75: 7.578318 | N75: 0 | O75: 274.86626 | P75: 62.555679 | Q75: =C75+D75+H75+I75+K75+L75+M75+N75+O75 -> 290.67236 | R75: =S75-Q75 -> 136.22942 | S75: =SUM(C75:P75) -> 426.90179 | V75: =Feedstocks!S75/Production!T6*100 -> 0.093731479
A76: 2023 | B76: Mar | D76: 0.47205126 | E76: 28.700267 | F76: 4.1854212 | G76: 11.349624 | H76: 6.2499639 | I76: 0 | J76: 13.668934 | K76: 0 | L76: 0.64111764 | M76: 15.677738 | N76: 0.4778208 | O76: 342.0472 | P76: 90.738906 | Q76: =C76+D76+H76+I76+K76+L76+M76+N76+O76 -> 365.56589 | R76: =S76-Q76 -> 148.64315 | S76: =SUM(C76:P76) -> 514.20904 | V76: =Feedstocks!S76/Production!T7*100 -> 0.093035409
A77: 2023 | B77: Apr | D77: 0.68581269 | E77: 23.799234 | F77: 7.7535792 | G77: 13.027819 | H77: 6.3376428 | I77: 0.50162724 | J77: 11.232341 | K77: 0 | L77: 0.49324788 | M77: 11.340919 | N77: 0 | O77: 382.00077 | P77: 85.701355 | Q77: =C77+D77+H77+I77+K77+L77+M77+N77+O77 -> 401.36002 | R77: =S77-Q77 -> 141.51433 | S77: =SUM(C77:P77) -> 542.87434 | V77: =Feedstocks!S77/Production!T8*100 -> 0.093855736
A78: 2023 | B78: May | D78: 0.97753416 | E78: 36.427836 | F78: 4.9542698 | G78: 11.808922 | H78: 4.4490337 | I78: 0 | J78: 9.5878255 | K78: 0 | L78: 1.3078941 | M78: 8.4092789 | N78: 0 | O78: 447.20014 | P78: 77.879259 | Q78: =C78+D78+H78+I78+K78+L78+M78+N78+O78 -> 462.34388 | R78: =S78-Q78 -> 140.65811 | S78: =SUM(C78:P78) -> 603.002 | V78: =Feedstocks!S78/Production!T9*100 -> 0.092947156
A79: 2023 | B79: Jun | D79: 1.0934094 | E79: 38.358796 | F79: 3.3767475 | G79: 10.462112 | H79: 1.1846732 | I79: 0 | J79: 10.531492 | K79: 0 | L79: 1.4816434 | M79: 14.22037 | N79: 0.0201366 | O79: 415.87001 | P79: 85.06963 | Q79: =C79+D79+H79+I79+K79+L79+M79+N79+O79 -> 433.87025 | R79: =S79-Q79 -> 147.79878 | S79: =SUM(C79:P79) -> 581.66902 | V79: =Feedstocks!S79/Production!T10*100 -> 0.088499471
A80: 2023 | B80: Jul | D80: 1.890265 | E80: 33.802568 | F80: 1.9489166 | G80: 11.747886 | H80: 3.1592722 | I80: 0.16692112 | J80: 6.891582 | K80: 0 | L80: 1.5932689 | M80: 16.85249 | N80: 0.0109584 | O80: 452.06024 | P80: 97.785093 | Q80: =C80+D80+H80+I80+K80+L80+M80+N80+O80 -> 475.73341 | R80: =S80-Q80 -> 152.17605 | S80: =SUM(C80:P80) -> 627.90946 | V80: =Feedstocks!S80/Production!T11*100 -> 0.087526873
A81: 2023 | B81: Aug | D81: 1.9727699 | E81: 33.282819 | F81: 3.9152819 | G81: 8.8933799 | H81: 7.5306598 | I81: 0.18764964 | J81: 7.2780681 | K81: 0 | L81: 2.0126665 | M81: 17.828568 | O81: 459.6642 | P81: 107.32144 | Q81: =C81+D81+H81+I81+K81+L81+M81+N81+O81 -> 489.19651 | R81: =S81-Q81 -> 160.69099 | S81: =SUM(C81:P81) -> 649.8875 | V81: =Feedstocks!S81/Production!T12*100 -> 0.091820476
A82: 2023 | B82: Sep | D82: 1.5493456 | E82: 27.455904 | F82: 0.09386169 | G82: 2.8834302 | H82: 13.203437 | I82: 0.60418424 | J82: 5.9382196 | K82: 0 | L82: 2.2606516 | M82: 15.691091 | O82: 444.32553 | P82: 114.79892 | Q82: =C82+D82+H82+I82+K82+L82+M82+N82+O82 -> 477.63424 | R82: =S82-Q82 -> 151.17034 | S82: =SUM(C82:P82) -> 628.80458 | V82: =Feedstocks!S82/Production!T13*100 -> 0.093479788
A83: 2023 | B83: Oct | D83: 2.0802342 | E83: 29.948883 | F83: 3.3085961 | G83: 5.5000193 | H83: 14.093806 | I83: 0.15208428 | J83: 8.3635825 | K83: 0 | L83: 3.388786 | M83: 16.836692 | O83: 458.45175 | P83: 107.67196 | Q83: =C83+D83+H83+I83+K83+L83+M83+N83+O83 -> 495.00335 | R83: =S83-Q83 -> 154.79304 | S83: =SUM(C83:P83) -> 649.79639 | V83: =Feedstocks!S83/Production!T14*100 -> 0.092274239
A84: 2023 | B84: Nov | D84: 1.4981909 | E84: 35.595967 | F84: 0.75559674 | G84: 8.208359 | H84: 16.485511 | I84: 1.3715636 | J84: 8.3041304 | K84: 0 | L84: 2.8244018 | M84: 12.868421 | O84: 445.95731 | P84: 109.23736 | Q84: =C84+D84+H84+I84+K84+L84+M84+N84+O84 -> 481.0054 | R84: =S84-Q84 -> 162.10141 | S84: =SUM(C84:P84) -> 643.10681 | V84: =Feedstocks!S84/Production!T15*100 -> 0.091843001
A85: 2023 | B85: Dec | D85: 1.8436469 | E85: 33.81681 | F85: 1.6181869 | G85: 7.3040008 | H85: 16.386253 | I85: 1.3689241 | J85: 8.0213233 | K85: 0 | L85: 4.8119671 | M85: 16.096408 | O85: 403.70235 | P85: 108.66288 | Q85: =C85+D85+H85+I85+K85+L85+M85+N85+O85 -> 444.20954 | R85: =S85-Q85 -> 159.4232 | S85: =SUM(C85:P85) -> 603.63274 | V85: =Feedstocks!S85/Production!T16*100 -> 0.08904896
A86: 2024 | B86: Jan | D86: 2.3751763 | E86: 37.688958 | F86: 1.0074469 | G86: 4.6467473 | H86: 8.501827 | I86: 2.2395946 | J86: 7.9919977 | K86: 0.3960968 | L86: 0.7673168 | M86: 12.551077 | O86: 384.31848 | P86: 96.602168 | Q86: =C86+D86+H86+I86+K86+L86+M86+N86+O86 -> 411.14957 | R86: =S86-Q86 -> 147.93732 | S86: =SUM(C86:P86) -> 559.08689 | V86: =Feedstocks!S86/Production!U5*100 -> 0.090800185
A87: 2024 | B87: Feb | D87: 2.7318704 | E87: 41.66847 | F87: 0.88981425 | G87: 7.8353722 | H87: 8.4845865 | I87: 2.2001625 | J87: 8.2472608 | K87: 0.096468948 | L87: 1.9034864 | M87: 7.1259149 | O87: 397.25038 | P87: 85.657937 | Q87: =C87+D87+H87+I87+K87+L87+M87+N87+O87 -> 419.79287 | R87: =S87-Q87 -> 144.29885 | S87: =SUM(C87:P87) -> 564.09172 | V87: =Feedstocks!S87/Production!U6*100 -> 0.088616121
A88: 2024 | B88: Mar | C88: 0.03425988 | D88: 1.483244 | E88: 42.306785 | F88: 3.455909 | G88: 9.75613 | H88: 7.384835 | I88: 4.211518 | J88: 9.894311 | K88: 0 | L88: 2.890439 | M88: 10.060822 | N88: 0 | O88: 546.38561 | P88: 114.15901 | Q88: 572.45072 | R88: =S88-Q88 -> 179.57214 | S88: =SUM(C88:P88) -> 752.02287 | V88: =Feedstocks!S88/Production!U7*100 -> 0.10099451
A89: 2024 | B89: Apr | C89: 0.044117618 | D89: 1.339539 | E89: 39.529781 | F89: 3.526734 | G89: 11.609371 | H89: 5.871274 | I89: 1.660103 | J89: 8.216107 | K89: 0.0274803 | L89: 2.394526 | M89: 6.127795 | N89: 0.067237198 | O89: 583.44592 | P89: 90.189689 | Q89: 600.978 | R89: =S89-Q89 -> 153.07168 | S89: =SUM(C89:P89) -> 754.04968 | V89: =Feedstocks!S89/Production!U8*100 -> 0.09996233 | W89: mom change
A90: 2024 | B90: May | C90: 0.041500307 | D90: 1.638437 | E90: 44.740532 | F90: 0.96465 | G90: 17.348231 | H90: 7.399896 | I90: 0.404615 | J90: 8.033616 | K90: 0.025850011 | L90: 2.067407 | M90: 1.525891 | N90: 0.0632483 | O90: 542.87116 | P90: 99.510747 | Q90: 556.03801 | R90: =S90-Q90 -> 170.59778 | S90: =SUM(C90:P90) -> 726.63578 | V90: =Feedstocks!S90/Production!U9*100 -> 0.099962436
A91: 2024 | B91: Jun | C91: 0.04015838 | D91: 1.414895 | E91: 55.029264 | F91: 1.258599 | G91: 15.992581 | H91: 12.405861 | I91: 0.786714 | J91: 4.92162 | K91: 0.025014142 | L91: 2.360214 | M91: 3.842324 | N91: 0.061203146 | O91: 574.18468 | P91: 109.02744 | Q91: 595.12107 | R91: =S91-Q91 -> 186.2295 | S91: =SUM(C91:P91) -> 781.35057 | V91: =Feedstocks!S91/Production!U10*100 -> 0.1014243
A92: 2024 | B92: Jul | D92: 1.622503 | E92: 51.613701 | F92: 0.231878 | G92: 16.686189 | H92: 10.920022 | I92: 0 | J92: 10.629332 | K92: 0 | L92: 4.69696 | M92: 4.259763 | N92: 0.061203146 | O92: 529.5167 | P92: 112.89354 | Q92: 595.12107 | R92: =S92-Q92 -> 148.01073 | S92: =SUM(D92:P92) -> 743.13179 | V92: =Feedstocks!S92/Production!U11*100 -> 0.090396022
A93: 2024 | B93: Aug | D93: 1.64828 | E93: 55.831122 | F93: 1.78567 | G93: 17.257036 | H93: 18.901981 | I93: 0 | J93: 8.909114 | K93: 0 | L93: 7.735974 | M93: 2.087948 | N93: 0.061203146 | O93: 519.45456 | P93: 119.16655 | Q93: 595.12107 | R93: =S93-Q93 -> 157.71837 | S93: =SUM(C93:P93) -> 752.83944 | T93: =J93/S93 -> 0.011834016 | V93: =Feedstocks!S93/Production!U12*100 -> 0.089575892
A94: 2024 | B94: Sep | D94: 1.633183 | E94: 55.504838 | F94: 0.663694 | G94: 16.160613 | H94: 20.887074 | I94: 0 | J94: 7.765114 | K94: 0 | L94: 6.411431 | M94: 1.703836 | N94: 0.061203146 | O94: 700.42477 | P94: 115.15349 | Q94: 595.12107 | R94: =S94-Q94 -> 331.24817 | S94: =SUM(C94:P94) -> 926.36924 | V94: =Feedstocks!S94/Production!U13*100 -> 0.1135109
A95: 2024 | B95: Oct | D95: 1.914244 | E95: 57.138116 | F95: 0.923482 | G95: 17.198254 | H95: 16.435314 | I95: 2.416901 | J95: 8.937913 | K95: 0 | L95: 9.411502 | M95: 4.572806 | N95: 0.061203146 | O95: 739.73087 | P95: 129.32475 | Q95: 595.12107 | R95: =S95-Q95 -> 392.94429 | S95: =SUM(C95:P95) -> 988.06536 | V95: =Feedstocks!S95/Production!U14*100 -> 0.11685495
A96: 2024 | B96: Nov | D96: 1.998181 | E96: 59.375174 | F96: 1.547838 | G96: 15.728017 | H96: 22.731119 | I96: 2.368003 | J96: 9.206009 | K96: 0 | L96: 9.277729 | M96: 5.626281 | N96: 0.061203146 | O96: 634.6081 | P96: 119.0314 | Q96: 595.12107 | R96: =S96-Q96 -> 286.43799 | S96: =SUM(C96:P96) -> 881.55906 | V96: =Feedstocks!S96/Production!U15*100 -> 0.10813852
A97: 2024 | B97: Dec | D97: 2.015552 | E97: 41.978428 | F97: 1.870651 | G97: 13.129696 | H97: 14.981023 | I97: 1.463581 | J97: 7.514201 | K97: 0 | L97: 4.493672 | M97: 5.686076 | N97: 0.061203146 | O97: 563.94587 | P97: 101.43329 | Q97: 595.12107 | R97: =S97-Q97 -> 163.45217 | S97: =SUM(C97:P97) -> 758.57324 | V97: =Feedstocks!S97/Production!U16*100 -> 0.10913003
A98: 2025 | B98: Jan | D98: =$S98*D$318 -> 1.652091 | E98: =$S98*E$318 -> 34.408531 | F98: =$S98*F$318 -> 1.5333198 | G98: =$S98*G$318 -> 10.762041 | H98: =$S98*H$318 -> 12.279521 | I98: =$S98*I$318 -> 1.199656 | J98: =$S98*J$318 -> 6.1591782 | K98: =$S98*K$318 -> 0 | ... P98: =$S98*P$318 -> 83.141998 | Q98: =C98+D98+H98+I98+K98+L98+M98+N98+O98 -> 485.77597 | R98: =S98-Q98 -> 145.1881 | S98: =Production!V5*Feedstocks!V98/100 -> 630.96407 | V98: =AVERAGE(V86:V97) -> 0.10078052
A99: 2025 | B99: Feb | D99: =$S99*D$318 -> 1.8308191 | E99: =$S99*E$318 -> 38.130947 | F99: =$S99*F$318 -> 1.6991988 | G99: =$S99*G$318 -> 11.92631 | H99: =$S99*H$318 -> 13.607956 | I99: =$S99*I$318 -> 1.3294383 | J99: =$S99*J$318 -> 6.8254962 | K99: =$S99*K$318 -> 0 | ... P99: =$S99*P$318 -> 92.136544 | Q99: =C99+D99+H99+I99+K99+L99+M99+N99+O99 -> 538.32864 | R99: =S99-Q99 -> 160.89497 | S99: =Production!V6*Feedstocks!V99/100 -> 699.22362 | V99: =AVERAGE(V87:V98) -> 0.10161221
A100: 2025 | B100: Mar | D100: =$S100*D$318 -> 2.1127213 | E100: =$S100*E$318 -> 44.002199 | F100: =$S100*F$318 -> 1.9608347 | G100: =$S100*G$318 -> 13.762676 | H100: =$S100*H$318 -> 15.703255 | I100: =$S100*I$318 -> 1.5341399 | J100: =$S100*J$318 -> 7.8764591 | K100: =$S100*K$318 -> 0 | ... P100: =$S100*P$318 -> 106.32336 | Q100: =C100+D100+H100+I100+K100+L100+M100+N100+O100 -> 621.21836 | R100: =S100-Q100 -> 185.66894 | S100: =Production!V7*Feedstocks!V100/100 -> 806.8873 | V100: =AVERAGE(V88:V99) -> 0.10269522
...

Sheet Capacity
B1: Bahia | C1: Ceará | D1: Goiás | E1: Mato Grosso | F1: Mato Grosso do Sul | G1: Minas Gerais | H1: Pará | I1: Paraná | J1: Piauí | K1: Rio de Janeiro | L1: Rio Grande do Sul | M1: Rondônia | N1: Santa Catarina | O1: São Paulo | P1: Tocantins | Q1: (blank) | R1: Grand Total | T1: https://www.gov.br/anp/pt-br/centrais-de-conteudo/paineis-dinamicos-da-anp/paineis-e-mapa-dinamicos-de-produtores-de-combustiveis-e-derivados/painel-dinamico-de-produtores-de-biodiesel
A2: 2018-1 | B2: 1103 | C2: 301 | D2: 3345 | E2: 3977 | F2: 1000 | G2: 422 | I2: 1983 | K2: 616 | L2: 6033 | M2: 90 | N2: 510 | O2: 1521 | P2: 881 | R2: 21782
A3: 2018-2 | B3: 1103 | C3: 301 | D3: 3345 | E3: 3977 | F3: 1000 | G3: 422 | I3: 1983 | K3: 616 | L3: 6033 | M3: 90 | N3: 510 | O3: 1521 | P3: 881 | R3: 21782
A4: 2018-3 | B4: 1103 | C4: 301 | D4: 3345 | E4: 3977 | F4: 1000 | G4: 422 | I4: 1983 | K4: 616 | L4: 6033 | M4: 90 | N4: 510 | O4: 1521 | P4: 881 | R4: 21782
A5: 2018-4 | B5: 1103 | C5: 301 | D5: 3345 | E5: 4577 | F5: 1000 | G5: 422 | I5: 1983 | K5: 616 | L5: 6033 | M5: 90 | N5: 510 | O5: 1521 | P5: 881 | R5: 22382
A6: 2018-5 | B6: 1103 | C6: 301 | D6: 3345 | E6: 4661 | F6: 1000 | G6: 422 | I6: 1983 | K6: 616 | L6: 6283 | M6: 90 | N6: 510 | O6: 1521 | P6: 881 | R6: 22716
A7: 2018-6 | B7: 1103 | C7: 301 | D7: 3345 | E7: 4661 | F7: 1000 | G7: 422 | I7: 1983 | K7: 616 | L7: 6283 | M7: 90 | N7: 510 | O7: 1521 | P7: 881 | R7: 22716
A8: 2018-7 | B8: 1103 | C8: 301 | D8: 3345 | E8: 4661 | F8: 1000 | G8: 422 | I8: 1983 | K8: 616 | L8: 6283 | M8: 90 | N8: 510 | O8: 1721 | P8: 881 | R8: 22916
A9: 2018-8 | B9: 1103 | C9: 301 | D9: 3345 | E9: 4911 | F9: 1000 | G9: 422 | I9: 1983 | K9: 616 | L9: 6283 | M9: 90 | N9: 510 | O9: 1721 | P9: 881 | R9: 23166
A10: 2018-9 | B10: 1403 | C10: 301 | D10: 3345 | E10: 4911 | F10: 1000 | G10: 422 | I10: 1983 | K10: 616 | L10: 6283 | M10: 90 | N10: 510 | O10: 1721 | P10: 881 | R10: 23466
A11: 2018-10 | B11: 1403 | C11: 301 | D11: 3345 | E11: 4911 | F11: 1000 | G11: 422 | I11: 1983 | K11: 616 | L11: 6283 | M11: 90 | N11: 510 | O11: 1721 | P11: 881 | R11: 23466
A12: 2018-11 | B12: 1403 | C12: 301 | D12: 3345 | E12: 4911 | F12: 1000 | G12: 422 | I12: 1983 | K12: 616 | L12: 6283 | M12: 90 | N12: 510 | O12: 1721 | P12: 881 | R12: 23466
A13: 2018-12 | B13: 1403 | C13: 301 | D13: 3345 | E13: 4911 | F13: 1000 | G13: 422 | I13: 1983 | K13: 616 | L13: 6533 | M13: 90 | N13: 510 | O13: 1721 | P13: 881 | R13: 23716
... A22: 2019-9 | B22: 1403 | C22: 301 | D22: 3500 | E22: 5993 | F22: 1300 | G22: 422 | I22: 2213 | K22: 616 | L22: 6733 | M22: 90 | N22: 510 | O22: 1321 | P22: 881 | R22: 25283
A23: 2019-10 | B23: 1403 | C23: 301 | D23: 3500 | E23: 5993 | F23: 1300 | G23: 422 | I23: 2213 | J23: 250 | K23: 616 | L23: 6733 | M23: 90 | N23: 510 | O23: 1321 | P23: 881 | R23: 25533
A24: 2019-11 | B24: 1645 | C24: 301 | D24: 3500 | E24: 5993 | F24: 1300 | G24: 463 | I24: 2213 | J24: 250 | K24: 616 | L24: 6733 | M24: 90 | N24: 510 | O24: 1321 | P24: 881 | R24: 25816
A25: 2019-12 | B25: 1645 | C25: 50 | D25: 3500 | E25: 5693 | F25: 1300 | G25: 463 | I25: 2213 | J25: 250 | K25: 616 | L25: 6733 | M25: 90 | N25: 510 | O25: 1321 | P25: 881 | R25: 25265
A26: 2020-1 | B26: 1645 | C26: 50 | D26: 3500 | E26: 5993 | F26: 1300 | G26: 463 | I26: 2213 | J26: 250 | K26: 616 | L26: 7083 | M26: 90 | N26: 510 | O26: 1321 | P26: 881 | R26: 25915
A27: 2020-2 | B27: 1645 | C27: 50 | D27: 3500 | E27: 5993 | F27: 1300 | G27: 463 | I27: 2213 | J27: 250 | K27: 616 | L27: 7083 | M27: 90 | N27: 510 | O27: 1321 | P27: 881 | R27: 25915
A28: 2020-3 | B28: 1645 | C28: 50 | D28: 3500 | E28: 6173 | F28: 1300 | G28: 463 | I28: 2277 | J28: 250 | K28: 616 | L28: 7433 | M28: 90 | N28: 510 | O28: 1321 | P28: 881 | R28: 26509
A29: 2020-4 | B29: 1645 | C29: 50 | D29: 3500 | E29: 6263 | F29: 1300 | G29: 463 | I29: 2277 | J29: 250 | K29: 616 | L29: 7433 | M29: 90 | N29: 510 | O29: 1321 | P29: 881 | R29: 26599
A30: 2020-5 | B30: 1645 | C30: 50 | D30: 3500 | E30: 6263 | F30: 1300 | G30: 463 | I30: 2277 | J30: 250 | K30: 616 | L30: 8033 | M30: 90 | N30: 510 | O30: 1321 | P30: 881 | R30: 27199
A31: 2020-6 | B31: 1645 | C31: 50 | D31: 3500 | E31: 6263 | F31: 1300 | G31: 463 | I31: 2277 | J31: 250 | K31: 616 | L31: 8033 | M31: 90 | N31: 510 | O31: 1321 | P31: 881 | R31: 27199
A32: 2020-7 | B32: 1645 | C32: 50 | D32: 3500 | E32: 6263 | F32: 1300 | G32: 463 | I32: 2277 | J32: 250 | K32: 616 | L32: 8033 | M32: 90 | N32: 510 | O32: 1321 | P32: 881 | R32: 27199
A33: 2020-8 | B33: 1645 | C33: 50 | D33: 3500 | E33: 6263 | F33: 1300 | G33: 463 | I33: 2277 | J33: 250 | K33: 616 | L33: 8033 | M33: 90 | N33: 510 | O33: 1127 | P33: 800 | R33: 26924
A34: 2020-9 | B34: 1645 | C34: 50 | D34: 3500 | E34: 6263 | F34: 1300 | G34: 463 | I34: 2277 | J34: 250 | K34: 616 | L34: 8033 | M34: 90 | N34: 510 | O34: 1127 | P34: 800 | R34: 26924
... A51: 2022-2 | B51: 3145 | C51: 50 | D51: 5995 | E51: 6495 | F51: 1565 | G51: 545 | I51: 3800 | J51: 250 | K51: 616 | L51: 8183 | M51: 90 | N51: 1535 | O51: 1127 | P51: 800 | R51: 34196
A52: 2022-3 | B52: 3145 | C52: 50 | D52: 5995 | E52: 7175 | F52: 1565 | G52: 545 | H52: 800 | I52: 3800 | J52: 250 | K52: 616 | L52: 8183 | M52: 90 | N52: 1535 | O52: 1127 | P52: 800 | R52: 35676
A53: 2022-4 | B53: 3145 | C53: 50 | D53: 5995 | E53: 7175 | F53: 1565 | G53: 545 | H53: 800 | I53: 3800 | J53: 250 | K53: 616 | L53: 8183 | M53: 90 | N53: 1535 | O53: 1127 | P53: 800 | R53: 35676
A54: 2022-5 | B54: 3145 | C54: 50 | D54: 5995 | E54: 7175 | F54: 1565 | G54: 545 | H54: 800 | I54: 3800 | J54: 250 | K54: 616 | L54: 8183 | M54: 90 | N54: 1535 | O54: 1127 | P54: 800 | R54: 35676
A55: 2022-6 | B55: 3145 | C55: 50 | D55: 5995 | E55: 7175 | F55: 1565 | G55: 545 | H55: 1050 | I55: 3800 | J55: 250 | K55: 616 | L55: 8183 | M55: 690 | N55: 1535 | O55: 1127 | P55: 800 | R55: 36526
A56: 2022-7 | B56: 3145 | C56: 50 | D56: 5995 | E56: 7125 | F56: 1565 | G56: 545 | H56: 1050 | I56: 4153 | J56: 250 | K56: 616 | L56: 8183 | M56: 690 | N56: 1535 | O56: 1127 | P56: 800 | R56: 36829
A57: 2022-8 | B57: 3145 | C57: 50 | D57: 5995 | E57: 7125 | F57: 1565 | G57: 545 | H57: 1050 | I57: 4153 | J57: 250 | K57: 616 | L57: 8183 | M57: 690 | N57: 1535 | O57: 1127 | P57: 800 | R57: 36829
A58: 2022-9 | B58: 3145 | C58: 50 | D58: 5995 | E58: 7125 | F58: 1565 | G58: 545 | H58: 1050 | I58: 4153 | J58: 250 | K58: 616 | L58: 8183 | M58: 690 | N58: 1535 | O58: 1127 | P58: 800 | R58: 36829
A59: 2022-10 | B59: 3145 | C59: 50 | D59: 6195 | E59: 7125 | F59: 1565 | G59: 545 | H59: 1050 | I59: 4153 | J59: 250 | K59: 616 | L59: 8183 | M59: 690 | N59: 1535 | O59: 1127 | P59: 800 | R59: 37029
A60: 2022-11 | B60: 3145 | C60: 50 | D60: 6195 | E60: 7125 | F60: 1565 | G60: 545 | H60: 1050 | I60: 4153 | J60: 250 | K60: 616 | L60: 8183 | M60: 690 | N60: 1535 | O60: 1127 | P60: 800 | R60: 37029
A61: 2022-12 | B61: 3145 | C61: 50 | D61: 6195 | E61: 7125 | F61: 1965 | G61: 545 | H61: 1050 | I61: 4153 | J61: 250 | K61: 616 | L61: 8183 | M61: 690 | N61: 1535 | O61: 1127 | P61: 800 | R61: 37429
A62: 2023-1 | B62: 3145 | C62: 50 | D62: 6195 | E62: 7125 | F62: 1965 | G62: 545 | H62: 1050 | I62: 4153 | J62: 250 | K62: 616 | L62: 8183 | M62: 690 | N62: 1535 | O62: 1127 | P62: 800 | R62: 37429
A63: 2023-2 | B63: 3145 | C63: 50 | D63: 6195 | E63: 7125 | F63: 1965 | G63: 545 | H63: 1050 | I63: 4153 | J63: 250 | K63: 616 | L63: 8183 | M63: 690 | N63: 1535 | O63: 1127 | P63: 800 | R63: 37429
... A72: 2023-11 | B72: 3145 | C72: 50 | D72: 6195 | E72: 9147 | F72: 1965 | G72: 545 | H72: 1050 | I72: 4253 | J72: 250 | K72: 616 | L72: 8183 | M72: 690 | N72: 1535 | O72: 1127 | P72: 800 | R72: 39551
A73: 2023-12 | B73: 3145 | D73: 6195 | E73: 9147 | F73: 1965 | G73: 545 | H73: 1050 | I73: 4253 | J73: 250 | K73: 616 | L73: 8383 | M73: 690 | N73: 1535 | O73: 1311 | P73: 800 | R73: 39885
A74: 2024-1 | B74: 3145 | D74: 6145 | E74: 8567 | F74: 1965 | G74: 545 | H74: 1050 | I74: 4253 | J74: 250 | K74: 616 | L74: 8383 | M74: 690 | N74: 1535 | O74: 1311 | P74: 800 | R74: 39255
A75: 2024-2 | B75: 3145 | D75: 6145 | E75: 9247 | F75: 1965 | G75: 545 | H75: 1050 | I75: 4253 | J75: 250 | K75: 616 | L75: 8383 | M75: 690 | N75: 1535 | O75: 1311 | P75: 800 | R75: 39935
A76: 2024-3 | B76: 3145 | D76: 6145 | E76: 9247 | F76: 1965 | G76: 545 | H76: 1050 | I76: 4253 | J76: 250 | K76: 616 | L76: 8383 | M76: 690 | N76: 1535 | O76: 1311 | P76: 800 | R76: 39935
A77: 2024-4 | B77: 3145 | D77: 6145 | E77: 9247 | F77: 1965 | G77: 545 | H77: 1050 | I77: 4253 | J77: 250 | K77: 616 | L77: 8383 | M77: 690 | N77: 1535 | O77: 1311 | P77: 800 | R77: 39935
A78: 2024-5 | B78: 3145 | D78: 6145 | E78: 9247 | F78: 1965 | G78: 545 | H78: 1050 | I78: 4253 | J78: 250 | K78: 616 | L78: 8383 | M78: 690 | N78: 1535 | O78: 1311 | P78: 800 | R78: 39935
A79: 2024-6 | B79: 3145 | D79: 6145 | E79: 9427 | F79: 1965 | G79: 545 | H79: 1050 | I79: 4253 | J79: 250 | K79: 616 | L79: 8383 | M79: 690 | N79: 1535 | O79: 1311 | P79: 800 | R79: 40115
A80: 2024-7 | B80: 3145 | D80: 6145 | E80: 9327 | F80: 1965 | G80: 545 | H80: 1050 | I80: 4253 | J80: 250 | K80: 1016 | L80: 8383 | M80: 690 | N80: 1535 | O80: 1311 | P80: 800 | R80: 40415
A81: 2024-8 | B81: 3145 | D81: 6145 | E81: 9427 | F81: 1965 | G81: 545 | H81: 1050 | I81: 4453 | J81: 250 | K81: 1016 | L81: 8383 | M81: 690 | N81: 1535 | O81: 1311 | P81: 800 | R81: 40715
A82: 2024-9 | B82: 3145 | D82: 6145 | E82: 9427 | F82: 1965 | G82: 545 | H82: 1050 | I82: 4453 | J82: 250 | K82: 1016 | L82: 8383 | M82: 690 | N82: 1535 | O82: 1311 | P82: 800 | R82: 40715
A83: 2024-10 | B83: 3145 | D83: 6195 | E83: 10007 | F83: 1965 | G83: 545 | H83: 1050 | I83: 4453 | J83: 250 | K83: 1016 | L83: 8383 | M83: 690 | N83: 1535 | O83: 1311 | P83: 800 | R83: 41345
A84: 2024-11 | B84: 3145 | D84: 6195 | E84: 10007 | F84: 1965 | G84: 545 | H84: 1050 | I84: 4453 | J84: 250 | K84: 1016 | L84: 8383 | M84: 690 | N84: 1535 | O84: 1311 | P84: 800 | R84: 41345
... A86: 2025-1 | B86: 3145 | D86: 6195 | E86: 10007 | F86: 1965 | G86: 545 | H86: 1050 | I86: 4453 | J86: 250 | K86: 1016 | L86: 8383 | M86: 690 | N86: 1535 | O86: 1311 | P86: 800 | R86: 41345

Sheet Plant_List
A1: million litters | B1: Potencial - PR - Lapa | C1: Olfar GO - GO - Porangatu | D1: Granol GO - GO - Anápolis | E1: Be8 RS - RS - Passo Fundo | F1: Be8 PR - PR - Marialva | G1: ADM MT - MT - Rondonópolis | H1: Oleoplan BA - BA - Iraquara | I1: Oleoplan RS - RS - Veranópolis | J1: Olfar RS - RS - Erechim | K1: FRCB - MT - Várzea Grande | L1: 3Tentos MT - MT - Vera | M1: Bianchini - RS - Canoas | N1: Cofco - MT - Rondonópolis | O1: Seara - SC - Mafra | P1: Amaggi MT - MT - Lucas do Rio Verde | Q1: Binatural BA - BA - Simões Filho | R1: Delta MT - MT - Cuiaba | S1: Cargill - MS - Três Lagoas | T1: Granol RS - RS - Cachoeira do Sul | U1: 3Tentos RS - RS - Ijuí | V1: Olfar RJ - RJ - Porto Real | W1: PBio BA - BA - Candeias | X1: Granol TO - TO - Porto Nacional | Y1: Oleoplan PA - PA - Tomé-Açu | Z1: JBS SP - SP - Lins | AA1: Fênix - MT - Alta Araguaia | AB1: Camera IJ - RS - Ijuí | AC1: Binatural GO - GO - Formosa | AD1: Caramuru IP - GO - Ipameri | AE1: Caramuru SS - GO - São Simão | AF1: Minerva - GO - Palmeiras de Goiás | AG1: Delta MS - MS - Rio Brilhante | AH1: Oleoplan - RO - Cacoal | AI1: Cereal - GO - Rio Verde | AJ1: Fiagril - MT - Lucas do Rio Verde | AK1: Pbio MG - MG - Montes Claros | AL1: ADM SC - SC - Joaçaba | AM1: Bocchi - RS - Muitos Capões | AN1: Biofuga - RS - Camargo | AO1: Bunge - MT - Nova Mutum | AP1: JBS CV - MT - Campo Verde | AQ1: Lar - MS - Caarapó | AR1: Brejeiro - SP - Orlândia | AS1: Cocamar - PR - Maringá | AT1: Aroma - SP - Piracicaba | AU1: Amazonbio AM - AM - Manaus | AV1: Biopar MT - MT - Nova Marilândia | AW1: Caramuru MT - MT - Sorriso | AX1: Biopar PA - PA - Santo Antonio do Tauá | AY1: Caibiense - MT - Rondonópolis | AZ1: Unibras PI - PI - Floriano | BA1: Bio Oeste - MT - Várzea Grande | BB1: Prisma - SP - Sumaré | BC1: Amazonbio RO - RO - Di-Paraná | BD1: Binhardi - SP - Batatais | BE1: Barralcool - MT - Barra dos Bugres | BF1: Cesbra - RJ - Volta Redonda | BG1: Biovida - MT - Várzea Grande | BH1: Bio Óleo - MT - Cuiabá | BI1: Tauá - MT - Nova Mutum | BJ1: Agropalma - PA - Belém | BK1: Petrobio - PR - Umuarama | BL1: Cooperfeliz - MT - Feliz Natal | BM1: Bionorte - GO - São Miguel do Araguaia | BN1: Aliança - MT - Rondonópolis | BO1: Agropaulo - CE - Jaguaruana | BP1: Jataí Ecodiesel - GO - Jataí | BQ1: Biobras - PR - Nova Esperança
A2: Feedstock Mix
A3: Start Date
A4: Name Plate Capacity (million litters) | B4: 900 | C4: 648 | D4: 558 | E4: 540 | F4: 540 | G4: 486.7 | H4: 468 | I4: 468 | J4: 432 | K4: 432 | L4: 432 | M4: 414 | N4: 396 | O4: 369 | P4: 368.3 | Q4: 360 | R4: 360 | S4: 347.4 | T4: 335.9 | U4: 306 | V4: 306 | W4: 304.2 | X4: 288 | Y4: 288 | Z4: 267.8 | AA4: 244.8 | AB4: 234 | AC4: 234 | AD4: 225 | AE4: 225 | AF4: 216 | AG4: 216 | AH4: 216 | AI4: 216 | AJ4: 202.7 | AK4: 196.2 | AL4: 183.6 | AM4: 180 | AN4: 180 | AO4: 178.9 | AP4: 147.6 | AQ4: 144 | AR4: 132.1 | AS4: 127.1 | AT4: 108 | AU4: 108 | AV4: 103.7 | AW4: 102.6 | AX4: 90 | AY4: 90 | AZ4: 90 | BA4: 81 | BB4: 72 | BC4: 72 | BD4: 72 | BE4: 68.4 | BF4: 60.1 | BG4: 54 | BH4: 54 | BI4: 36 | BJ4: 36 | BK4: 36 | BL4: 36 | BM4: 34.2 | BN4: 28.8 | BO4: 18 | BP4: 18 | BQ4: 0
A5: Pre-Treatment
A6: Pre-Treatment Tech
A7: Pre-Treatment Start Date
A8: Pre-Treatment Capacity
A9: SAF
A10: Probability
A12: 44562 | B12: 900 | C12: 648 | D12: 558 | E12: 540 | F12: 540 | G12: 486.7 | H12: 468 | I12: 468 | J12: 432 | K12: 432 | L12: 432 | M12: 414 | N12: 396 | O12: 369 | P12: 368.3 | Q12: 360 | R12: 360 | S12: 347.4 | T12: 335.9 | U12: 306 | V12: 306 | W12: 304.2 | X12: 288 | Y12: 288 | Z12: 267.8 | AA12: 244.8 | AB12: 234 | AC12: 234 | AD12: 225 | AE12: 225 | AF12: 216 | AG12: 216 | AH12: 216 | AI12: 216 | AJ12: 202.7 | AK12: 196.2 | AL12: 183.6 | AM12: 180 | AN12: 180 | AO12: 178.9 | AP12: 147.6 | AQ12: 144 | AR12: 132.1 | AS12: 127.1 | AT12: 108 | AU12: 108 | AV12: 103.7 | AW12: 102.6 | AX12: 90 | AY12: 90 | AZ12: 90 | BA12: 81 | BB12: 72 | BC12: 72 | BD12: 72 | BE12: 68.4 | BF12: 60.1 | BG12: 54 | BH12: 54 | BI12: 36 | BJ12: 36 | BK12: 36 | BL12: 36 | BM12: 34.2 | BN12: 28.8 | BO12: 18 | BP12: 18 | BQ12: 0 | BR12: =SUM(B12:BP12) -> 15783.1
A13: 44593 | B13: 900 | C13: 648 | D13: 558 | E13: 540 | F13: 540 | G13: 486.7 | H13: 468 | I13: 468 | J13: 432 | K13: 432 | L13: 432 | M13: 414 | N13: 396 | O13: 369 | P13: 368.3 | Q13: 360 | R13: 360 | S13: 347.4 | T13: 335.9 | U13: 306 | V13: 306 | W13: 304.2 | X13: 288 | Y13: 288 | Z13: 267.8 | AA13: 244.8 | AB13: 234 | AC13: 234 | AD13: 225 | AE13: 225 | AF13: 216 | AG13: 216 | AH13: 216 | AI13: 216 | AJ13: 202.7 | AK13: 196.2 | AL13: 183.6 | AM13: 180 | AN13: 180 | AO13: 178.9 | AP13: 147.6 | AQ13: 144 | AR13: 132.1 | AS13: 127.1 | AT13: 108 | AU13: 108 | AV13: 103.7 | AW13: 102.6 | AX13: 90 | AY13: 90 | AZ13: 90 | BA13: 81 | BB13: 72 | BC13: 72 | BD13: 72 | BE13: 68.4 | BF13: 60.1 | BG13: 54 | BH13: 54 | BI13: 36 | BJ13: 36 | BK13: 36 | BL13: 36 | BM13: 34.2 | BN13: 28.8 | BO13: 18 | BP13: 18 | BQ13: 0 | BR13: =SUM(B13:BP13) -> 15783.1
A14: 44621 | B14: 900 | C14: 648 | D14: 558 | E14: 540 | F14: 540 | G14: 486.7 | H14: 468 | I14: 468 | J14: 432 | K14: 432 | L14: 432 | M14: 414 | N14: 396 | O14: 369 | P14: 368.3 | Q14: 360 | R14: 360 | S14: 347.4 | T14: 335.9 | U14: 306 | V14: 306 | W14: 304.2 | X14: 288 | Y14: 288 | Z14: 267.8 | AA14: 244.8 | AB14: 234 | AC14: 234 | AD14: 225 | AE14: 225 | AF14: 216 | AG14: 216 | AH14: 216 | AI14: 216 | AJ14: 202.7 | AK14: 196.2 | AL14: 183.6 | AM14: 180 | AN14: 180 | AO14: 178.9 | AP14: 147.6 | AQ14: 144 | AR14: 132.1 | AS14: 127.1 | AT14: 108 | AU14: 108 | AV14: 103.7 | AW14: 102.6 | AX14: 90 | AY14: 90 | AZ14: 90 | BA14: 81 | BB14: 72 | BC14: 72 | BD14: 72 | BE14: 68.4 | BF14: 60.1 | BG14: 54 | BH14: 54 | BI14: 36 | BJ14: 36 | BK14: 36 | BL14: 36 | BM14: 34.2 | BN14: 28.8 | BO14: 18 | BP14: 18 | BQ14: 0 | BR14: =SUM(B14:BP14) -> 15783.1
A15: 44652 | B15: 900 | C15: 648 | D15: 558 | E15: 540 | F15: 540 | G15: 486.7 | H15: 468 | I15: 468 | J15: 432 | K15: 432 | L15: 432 | M15: 414 | N15: 396 | O15: 369 | P15: 368.3 | Q15: 360 | R15: 360 | S15: 347.4 | T15: 335.9 | U15: 306 | V15: 306 | W15: 304.2 | X15: 288 | Y15: 288 | Z15: 267.8 | AA15: 244.8 | AB15: 234 | AC15: 234 | AD15: 225 | AE15: 225 | AF15: 216 | AG15: 216 | AH15: 216 | AI15: 216 | AJ15: 202.7 | AK15: 196.2 | AL15: 183.6 | AM15: 180 | AN15: 180 | AO15: 178.9 | AP15: 147.6 | AQ15: 144 | AR15: 132.1 | AS15: 127.1 | AT15: 108 | AU15: 108 | AV15: 103.7 | AW15: 102.6 | AX15: 90 | AY15: 90 | AZ15: 90 | BA15: 81 | BB15: 72 | BC15: 72 | BD15: 72 | BE15: 68.4 | BF15: 60.1 | BG15: 54 | BH15: 54 | BI15: 36 | BJ15: 36 | BK15: 36 | BL15: 36 | BM15: 34.2 | BN15: 28.8 | BO15: 18 | BP15: 18 | BQ15: 0 | BR15: =SUM(B15:BP15) -> 15783.1
A16: 44682 | B16: 900 | C16: 648 | D16: 558 | E16: 540 | F16: 540 | G16: 486.7 | H16: 468 | I16: 468 | J16: 432 | K16: 432 | L16: 432 | M16: 414 | N16: 396 | O16: 369 | P16: 368.3 | Q16: 360 | R16: 360 | S16: 347.4 | T16: 335.9 | U16: 306 | V16: 306 | W16: 304.2 | X16: 288 | Y16: 288 | Z16: 267.8 | AA16: 244.8 | AB16: 234 | AC16: 234 | AD16: 225 | AE16: 225 | AF16: 216 | AG16: 216 | AH16: 216 | AI16: 216 | AJ16: 202.7 | AK16: 196.2 | AL16: 183.6 | AM16: 180 | AN16: 180 | AO16: 178.9 | AP16: 147.6 | AQ16: 144 | AR16: 132.1 | AS16: 127.1 | AT16: 108 | AU16: 108 | AV16: 103.7 | AW16: 102.6 | AX16: 90 | AY16: 90 | AZ16: 90 | BA16: 81 | BB16: 72 | BC16: 72 | BD16: 72 | BE16: 68.4 | BF16: 60.1 | BG16: 54 | BH16: 54 | BI16: 36 | BJ16: 36 | BK16: 36 | BL16: 36 | BM16: 34.2 | BN16: 28.8 | BO16: 18 | BP16: 18 | BQ16: 0 | BR16: =SUM(B16:BP16) -> 15783.1
A17: 44713 | B17: 900 | C17: 648 | D17: 558 | E17: 540 | F17: 540 | G17: 486.7 | H17: 468 | I17: 468 | J17: 432 | K17: 432 | L17: 432 | M17: 414 | N17: 396 | O17: 369 | P17: 368.3 | Q17: 360 | R17: 360 | S17: 347.4 | T17: 335.9 | U17: 306 | V17: 306 | W17: 304.2 | X17: 288 | Y17: 288 | Z17: 267.8 | AA17: 244.8 | AB17: 234 | AC17: 234 | AD17: 225 | AE17: 225 | AF17: 216 | AG17: 216 | AH17: 216 | AI17: 216 | AJ17: 202.7 | AK17: 196.2 | AL17: 183.6 | AM17: 180 | AN17: 180 | AO17: 178.9 | AP17: 147.6 | AQ17: 144 | AR17: 132.1 | AS17: 127.1 | AT17: 108 | AU17: 108 | AV17: 103.7 | AW17: 102.6 | AX17: 90 | AY17: 90 | AZ17: 90 | BA17: 81 | BB17: 72 | BC17: 72 | BD17: 72 | BE17: 68.4 | BF17: 60.1 | BG17: 54 | BH17: 54 | BI17: 36 | BJ17: 36 | BK17: 36 | BL17: 36 | BM17: 34.2 | BN17: 28.8 | BO17: 18 | BP17: 18 | BQ17: 0 | BR17: =SUM(B17:BP17) -> 15783.1
A18: 44743 | B18: 900 | C18: 648 | D18: 558 | E18: 540 | F18: 540 | G18: 486.7 | H18: 468 | I18: 468 | J18: 432 | K18: 432 | L18: 432 | M18: 414 | N18: 396 | O18: 369 | P18: 368.3 | Q18: 360 | R18: 360 | S18: 347.4 | T18: 335.9 | U18: 306 | V18: 306 | W18: 304.2 | X18: 288 | Y18: 288 | Z18: 267.8 | AA18: 244.8 | AB18: 234 | AC18: 234 | AD18: 225 | AE18: 225 | AF18: 216 | AG18: 216 | AH18: 216 | AI18: 216 | AJ18: 202.7 | AK18: 196.2 | AL18: 183.6 | AM18: 180 | AN18: 180 | AO18: 178.9 | AP18: 147.6 | AQ18: 144 | AR18: 132.1 | AS18: 127.1 | AT18: 108 | AU18: 108 | AV18: 103.7 | AW18: 102.6 | AX18: 90 | AY18: 90 | AZ18: 90 | BA18: 81 | BB18: 72 | BC18: 72 | BD18: 72 | BE18: 68.4 | BF18: 60.1 | BG18: 54 | BH18: 54 | BI18: 36 | BJ18: 36 | BK18: 36 | BL18: 36 | BM18: 34.2 | BN18: 28.8 | BO18: 18 | BP18: 18 | BQ18: 0 | BR18: =SUM(B18:BP18) -> 15783.1
A19: 44774 | B19: 900 | C19: 648 | D19: 558 | E19: 540 | F19: 540 | G19: 486.7 | H19: 468 | I19: 468 | J19: 432 | K19: 432 | L19: 432 | M19: 414 | N19: 396 | O19: 369 | P19: 368.3 | Q19: 360 | R19: 360 | S19: 347.4 | T19: 335.9 | U19: 306 | V19: 306 | W19: 304.2 | X19: 288 | Y19: 288 | Z19: 267.8 | AA19: 244.8 | AB19: 234 | AC19: 234 | AD19: 225 | AE19: 225 | AF19: 216 | AG19: 216 | AH19: 216 | AI19: 216 | AJ19: 202.7 | AK19: 196.2 | AL19: 183.6 | AM19: 180 | AN19: 180 | AO19: 178.9 | AP19: 147.6 | AQ19: 144 | AR19: 132.1 | AS19: 127.1 | AT19: 108 | AU19: 108 | AV19: 103.7 | AW19: 102.6 | AX19: 90 | AY19: 90 | AZ19: 90 | BA19: 81 | BB19: 72 | BC19: 72 | BD19: 72 | BE19: 68.4 | BF19: 60.1 | BG19: 54 | BH19: 54 | BI19: 36 | BJ19: 36 | BK19: 36 | BL19: 36 | BM19: 34.2 | BN19: 28.8 | BO19: 18 | BP19: 18 | BQ19: 0 | BR19: =SUM(B19:BP19) -> 15783.1
A20: 44805 | B20: 900 | C20: 648 | D20: 558 | E20: 540 | F20: 540 | G20: 486.7 | H20: 468 | I20: 468 | J20: 432 | K20: 432 | L20: 432 | M20: 414 | N20: 396 | O20: 369 | P20: 368.3 | Q20: 360 | R20: 360 | S20: 347.4 | T20: 335.9 | U20: 306 | V20: 306 | W20: 304.2 | X20: 288 | Y20: 288 | Z20: 267.8 | AA20: 244.8 | AB20: 234 | AC20: 234 | AD20: 225 | AE20: 225 | AF20: 216 | AG20: 216 | AH20: 216 | AI20: 216 | AJ20: 202.7 | AK20: 196.2 | AL20: 183.6 | AM20: 180 | AN20: 180 | AO20: 178.9 | AP20: 147.6 | AQ20: 144 | AR20: 132.1 | AS20: 127.1 | AT20: 108 | AU20: 108 | AV20: 103.7 | AW20: 102.6 | AX20: 90 | AY20: 90 | AZ20: 90 | BA20: 81 | BB20: 72 | BC20: 72 | BD20: 72 | BE20: 68.4 | BF20: 60.1 | BG20: 54 | BH20: 54 | BI20: 36 | BJ20: 36 | BK20: 36 | BL20: 36 | BM20: 34.2 | BN20: 28.8 | BO20: 18 | BP20: 18 | BQ20: 0 | BR20: =SUM(B20:BP20) -> 15783.1
A21: 44835 | B21: 900 | C21: 648 | D21: 558 | E21: 540 | F21: 540 | G21: 486.7 | H21: 468 | I21: 468 | J21: 432 | K21: 432 | L21: 432 | M21: 414 | N21: 396 | O21: 369 | P21: 368.3 | Q21: 360 | R21: 360 | S21: 347.4 | T21: 335.9 | U21: 306 | V21: 306 | W21: 304.2 | X21: 288 | Y21: 288 | Z21: 267.8 | AA21: 244.8 | AB21: 234 | AC21: 234 | AD21: 225 | AE21: 225 | AF21: 216 | AG21: 216 | AH21: 216 | AI21: 216 | AJ21: 202.7 | AK21: 196.2 | AL21: 183.6 | AM21: 180 | AN21: 180 | AO21: 178.9 | AP21: 147.6 | AQ21: 144 | AR21: 132.1 | AS21: 127.1 | AT21: 108 | AU21: 108 | AV21: 103.7 | AW21: 102.6 | AX21: 90 | AY21: 90 | AZ21: 90 | BA21: 81 | BB21: 72 | BC21: 72 | BD21: 72 | BE21: 68.4 | BF21: 60.1 | BG21: 54 | BH21: 54 | BI21: 36 | BJ21: 36 | BK21: 36 | BL21: 36 | BM21: 34.2 | BN21: 28.8 | BO21: 18 | BP21: 18 | BQ21: 0 | BR21: =SUM(B21:BP21) -> 15783.1
A22: 44866 | B22: 900 | C22: 648 | D22: 558 | E22: 540 | F22: 540 | G22: 486.7 | H22: 468 | I22: 468 | J22: 432 | K22: 432 | L22: 432 | M22: 414 | N22: 396 | O22: 369 | P22: 368.3 | Q22: 360 | R22: 360 | S22: 347.4 | T22: 335.9 | U22: 306 | V22: 306 | W22: 304.2 | X22: 288 | Y22: 288 | Z22: 267.8 | AA22: 244.8 | AB22: 234 | AC22: 234 | AD22: 225 | AE22: 225 | AF22: 216 | AG22: 216 | AH22: 216 | AI22: 216 | AJ22: 202.7 | AK22: 196.2 | AL22: 183.6 | AM22: 180 | AN22: 180 | AO22: 178.9 | AP22: 147.6 | AQ22: 144 | AR22: 132.1 | AS22: 127.1 | AT22: 108 | AU22: 108 | AV22: 103.7 | AW22: 102.6 | AX22: 90 | AY22: 90 | AZ22: 90 | BA22: 81 | BB22: 72 | BC22: 72 | BD22: 72 | BE22: 68.4 | BF22: 60.1 | BG22: 54 | BH22: 54 | BI22: 36 | BJ22: 36 | BK22: 36 | BL22: 36 | BM22: 34.2 | BN22: 28.8 | BO22: 18 | BP22: 18 | BQ22: 0 | BR22: =SUM(B22:BP22) -> 15783.1
A23: 44896 | B23: 900 | C23: 648 | D23: 558 | E23: 540 | F23: 540 | G23: 486.7 | H23: 468 | I23: 468 | J23: 432 | K23: 432 | L23: 432 | M23: 414 | N23: 396 | O23: 369 | P23: 368.3 | Q23: 360 | R23: 360 | S23: 347.4 | T23: 335.9 | U23: 306 | V23: 306 | W23: 304.2 | X23: 288 | Y23: 288 | Z23: 267.8 | AA23: 244.8 | AB23: 234 | AC23: 234 | AD23: 225 | AE23: 225 | AF23: 216 | AG23: 216 | AH23: 216 | AI23: 216 | AJ23: 202.7 | AK23: 196.2 | AL23: 183.6 | AM23: 180 | AN23: 180 | AO23: 178.9 | AP23: 147.6 | AQ23: 144 | AR23: 132.1 | AS23: 127.1 | AT23: 108 | AU23: 108 | AV23: 103.7 | AW23: 102.6 | AX23: 90 | AY23: 90 | AZ23: 90 | BA23: 81 | BB23: 72 | BC23: 72 | BD23: 72 | BE23: 68.4 | BF23: 60.1 | BG23: 54 | BH23: 54 | BI23: 36 | BJ23: 36 | BK23: 36 | BL23: 36 | BM23: 34.2 | BN23: 28.8 | BO23: 18 | BP23: 18 | BQ23: 0 | BR23: =SUM(B23:BP23) -> 15783.1
... A86: 46813 | B86: 900 | C86: 648 | D86: 558 | E86: 540 | F86: 540 | G86: 486.7 | H86: 468 | I86: 468 | J86: 432 | K86: 432 | L86: 432 | M86: 414 | N86: 396 | O86: 369 | P86: 368.3 | Q86: 360 | R86: 360 | S86: 347.4 | T86: 335.9 | U86: 306 | V86: 306 | W86: 304.2 | X86: 288 | Y86: 288 | Z86: 267.8 | AA86: 244.8 | AB86: 234 | AC86: 234 | AD86: 225 | AE86: 225 | AF86: 216 | AG86: 216 | AH86: 216 | AI86: 216 | AJ86: 202.7 | AK86: 196.2 | AL86: 183.6 | AM86: 180 | AN86: 180 | AO86: 178.9 | AP86: 147.6 | AQ86: 144 | AR86: 132.1 | AS86: 127.1 | AT86: 108 | AU86: 108 | AV86: 103.7 | AW86: 102.6 | AX86: 90 | AY86: 90 | AZ86: 90 | BA86: 81 | BB86: 72 | BC86: 72 | BD86: 72 | BE86: 68.4 | BF86: 60.1 | BG86: 54 | BH86: 54 | BI86: 36 | BJ86: 36 | BK86: 36 | BL86: 36 | BM86: 34.2 | BN86: 28.8 | BO86: 18 | BP86: 18 | BQ86: 0 | BR86: =SUM(B86:BP86) -> 15783.1

Sheet BD_Feedstock_Breakdown
A1: (million pounds) | B1: Potencial - PR - Lapa | J1: Olfar GO - GO - Porangatu | R1: Granol GO - GO - Anápolis | T1: Be8 RS - RS - Passo Fundo | Y1: Be8 PR - PR - Marialva | AC1: ADM MT - MT - Rondonópolis | AG1: Oleoplan BA - BA - Iraquara | AK1: Oleoplan RS - RS - Veranópolis | AM1: Olfar RS - RS - Erechim | AP1: FRCB - MT - Várzea Grande | AS1: 3Tentos MT - MT - Vera | AV1: Cofco - MT - Rondonópolis | AY1: Seara - SC - Mafra | BB1: Amaggi MT - MT - Lucas do Rio Verde | BF1: Binatural BA - BA - Simões Filho | BH1: Delta MT - MT - Cuiaba | BJ1: Cargill - MS - Três Lagoas | BO1: Granol RS - RS - Cachoeira do Sul | BQ1: 3Tentos RS - RS - Ijuí | BT1: Olfar RJ - RJ - Porto Real | BW1: PBio BA - BA - Candeias | CB1: Granol TO - TO - Porto Nacional | CD1: Oleoplan PA - PA - Tomé-Açu | CG1: JBS SP - SP - Lins | CI1: Fênix - MT - Alta Araguaia | CL1: Camera IJ - RS - Ijuí | CP1: Binatural GO - GO - Formosa | CT1: Caramuru IP - GO - Ipameri | CV1: Caramuru SS - GO - São Simão | CX1: Minerva - GO - Palmeiras de Goiás | DA1: Delta MS - MS - Rio Brilhante | DD1: Cereal - GO - Rio Verde | DF1: Fiagril - MT - Lucas do Rio Verde | DH1: Pbio MG - MG - Montes Claros | DJ1: ADM SC - SC - Joaçaba | DO1: Bocchi - RS - Muitos Capões | DP1: Total Monthly Potential Demand | EA1: Percent of Total | EK1: RD Feedstock Usage (million pounds)
A2: Feedstock Mix | B2: Soybean Oil | C2: Canola Oil | D2: Poultry Fat | E2: Yellow Grease | F2: Choice White Grease | G2: Distillers' Corn Oil | H2: Used Cooking Oil | I2: Total | J2: SBO | K2: Canola Oil | L2: Poultry Fat | M2: Yellow Grease | N2: Choice White Grease | O2: Distillers' Corn Oil | P2: Used Cooking Oil | Q2: Total | R2: Distillers' Corn Oil | S2: Total | T2: Canola Oil | U2: SBO | V2: Tallow | W2: Choice White Grease | X2: Total | Y2: Soybean Oil | Z2: Tallow | AA2: Distillers' Corn Oil | AB2: Total | AC2: Canola Oil | AD2: Soybean Oil | AE2: Tallow | AF2: Total | AG2: Canola Oil | AH2: SBO | AI2: Tech Tallow | AJ2: Total | AK2: Soybean Oil | AL2: Total | AM2: Soybean Oil | AN2: Low CI Mix (Tallow) | AO2: Total | AP2: Soybean Oil | AQ2: Low CI Mix (Tallow) | AR2: Total | AS2: Soybean Oil | AT2: Canola Oil | AU2: Total | AV2: Soybean Oil | AW2: Distillers' Corn Oil | AX2: Total | AY2: Soybean Oil | AZ2: Used Cooking Oil | BA2: Total | BB2: Soybean Oil | BC2: Used Cooking Oil | BD2: Tallow | BE2: Total | BF2: Soybean Oil | BG2: Total | BH2: Distillers' Corn Oil | BI2: Total | BJ2: Soybean Oil | BK2: Used Cooking Oil | BL2: Tallow | BM2: Distillers' Corn Oil | BN2: Total | BO2: Soybean Oil | BP2: Total | BQ2: Soybean Oil | BR2: Distillers' Corn Oil | BS2: Total | BT2: Soybean Oil | BU2: Distillers' Corn Oil | BV2: Total | BW2: Soybean Oil | BX2: Canola Oil | BY2: Distillers' Corn Oil | BZ2: Used Cooking Oil | CA2: Total | CB2: Soybean Oil | CC2: Total | CD2: Tallow | CE2: Soybean Oil | CF2: Total | CG2: Soybean Oil | CH2: Total | CI2: Canola Oil | CJ2: Soybean Oil | CK2: Total | CL2: Used Cooking Oil | CM2: Tallow | CN2: Soybean Oil | CO2: Total | CP2: Used Cooking Oil | CQ2: Tallow | CR2: Soybean Oil | CS2: Total | CT2: Soybean Oil | CU2: Total | CV2: UCO | CW2: Total | CX2: UCO | CY2: Tallow | CZ2: Total | DA2: UCO | DB2: Tallow | DC2: Total | DD2: Canola Oil | DE2: Total | DF2: SBO | DG2: Total | DH2: SBO | DI2: Total | DJ2: Canola Oil | DK2: UCO | DL2: Tallow | DM2: CWG | DN2: Total | DP2: Yellow Grease | DQ2: Used Cooking Oil | DR2: Soybean Oil | DS2: Canola Oil | DT2: Tallow | DU2: Distillers' Corn Oil | DV2: Choice White Grease | DW2: Poultry Fat | DX2: Total | EA2: Yellow Grease | EB2: Used Cooking Oil | EC2: Soybean Oil | ED2: Canola Oil | EE2: Tallow | EF2: Distillers' Corn Oil | EG2: Choice White Grease | EH2: Poultry Fat | EI2: Total | EK2: Yellow Grease | EL2: Used Cooking Oil | EM2: Soybean Oil | EN2: Canola Oil | EO2: Tallow | EP2: Distillers' Corn Oil | EQ2: Choice White Grease | ER2: Poultry Fat | ES2: Total
A3: Composition | B3: As needed | C3: As needed | D3: Minimal | E3: 0.184 | F3: 0.1 | G3: 0.333 | H3: 0.383 | I3: =SUM(E3:H3) -> 1 | J3: As needed | K3: As needed | L3: Minimal | M3: 0.234 | N3: 0.1 | O3: 0.333 | P3: 0.333 | Q3: =SUM(M3:P3) -> 1 | R3: 1 | S3: =R3 -> 1 | T3: As needed | U3: As needed | V3: 0.666 | W3: 0.334 | X3: =SUM(V3:W3) -> 1 | Y3: As needed | Z3: 0.6 | AA3: 0.4 | AB3: =SUM(Z3:AA3) -> 1 | AC3: 0.5 | AD3: 0.25 | AE3: 0.25 | AF3: =SUM(AC3:AE3) -> 1 | AG3: As needed | AH3: As needed | AI3: 1 | AJ3: =AI3 -> 1 | AK3: 1 | AL3: =AK3 -> 1 | AM3: 0.75 | AN3: 0.25 | AO3: =SUM(AM3:AN3) -> 1 | AP3: 0.75 | AQ3: 0.25 | AR3: =SUM(AP3:AQ3) -> 1 | AS3: 1 | AT3: =1-AS3 -> 0 | AU3: =SUM(AS3:AT3) -> 1 | AV3: 0.7 | AW3: 0.3 | AX3: =SUM(AV3:AW3) -> 1 | AY3: 0.9 | AZ3: 0.1 | BA3: =SUM(AY3:AZ3) -> 1 | BB3: 0.85 | BC3: 0.1 | BD3: 0.05 | BE3: =SUM(BB3:BD3) -> 1 | BF3: 1 | BG3: =BF3 -> 1 | BH3: 1 | BI3: =BH3 -> 1 | BJ3: 0.6 | BK3: 0.1 | BL3: 0.2 | BM3: 0.1 | BN3: =SUM(BJ3:BM3) -> 1 | BO3: 1 | BP3: =BO3 -> 1 | BQ3: 0.75 | BR3: 0.25 | BS3: =SUM(BQ3:BR3) -> 1 | BT3: As Needed | BU3: 1 | BV3: =BU3 -> 1 | BW3: 0.5 | BX3: 0.05 | BY3: 0.35 | BZ3: 0.1 | CA3: =SUM(BW3:BZ3) -> 1 | CB3: 1 | CC3: =CB3 -> 1 | CD3: 0.7 | CE3: 0.3 | CF3: =SUM(CD3:CE3) -> 1 | CG3: 1 | CH3: =CG3 -> 1 | CI3: 0.5 | CJ3: 0.5 | CK3: =SUM(CI3:CJ3) -> 1 | CL3: 0.5 | CM3: 0.25 | CN3: 0.25 | CO3: =SUM(CL3:CN3) -> 1 | CP3: 0.5 | CQ3: 0.25 | CR3: 0.25 | CS3: =SUM(CP3:CR3) -> 1 | CT3: 1 | CU3: =CT3 -> 1 | CV3: 1 | CW3: =CV3 -> 1 | CX3: 0.5 | CY3: 0.5 | CZ3: =SUM(CX3:CY3) -> 1 | DA3: 0.5 | DB3: 0.5 | DC3: =SUM(DA3:DB3) -> 1 | DD3: 1 | DE3: 1 | DF3: 1 | DG3: 1 | DH3: 1 | DI3: 1 | DJ3: As needed | DK3: 0.5 | DL3: 0.25 | DM3: 0.25 | DN3: =SUM(DK3:DM3) -> 1 | DY3: Check
A4: 40544
A5: 40575
A6: 40603
A7: 40634
A8: 40664
A9: 40695
A10: 40725
A11: 40756
A12: 40787 | D12: 0 | E12: =('[2]Renewable Diesel'!B21*E$3*'[2]Feedstock Conversion Rates'!$B$2)/12 -> 5.2133333 | F12: =('[2]Renewable Diesel'!B21*'[2]RD Feedstock Breakdown'!F$3*'[2]Feedstock Conversion Rates'!B$8)/12 -> 3.125 | G12: =('[2]Renewable Diesel'!B21*'[2]RD Feedstock Breakdown'!G$3*'[2]Feedstock Conversion Rates'!B$7)/12 -> 10.212 | H12: =('[2]Renewable Diesel'!B21*'[2]RD Feedstock Breakdown'!H$3*'[2]Feedstock Conversion Rates'!B$3)/12 -> 10.2261 | I12: =SUM(B12:H12) -> 28.776433 | DP12: =E12+M12 -> 5.2133333 | DQ12: =H12+P12+AZ12+BC12+BK12+BZ12+CL12+CP12+CV12+CX12+DA12+DK12 -> 10.2261 | DR12: =AD12+AK12+AM12+AP12+AV12+AY12+BB12+BF12+BJ12+Y12+B12+BO12+BQ12+BW12+CB12+CE12+CG12+CJ12+BT12+CN12+CR12+CT12+DF12+DH12+AS12+J12+U12+AH12 -> 0 | DT12: =V12+Z12+AE12+AI12+BD12+BL12+AN12+AQ12+CD12+CM12+CQ12+CY12+DB12+DL12 -> 0 | DU12: =G12+O12+R12+AA12+AW12+BH12+BM12+BR12+BU12+BY12 -> 10.212 | DV12: =F12+N12+W12+DM12 -> 3.125 | DW12: =D12+L12 -> 0 | DX12: =SUM(DP12:DW12) -> 28.776433 | DY12: =I12+Q12+S12+X12+AB12+AF12+AJ12+AL12+AO12+AR12+AU12+AX12+BA12+BE12+BG12+BI12+BN12-DX12+BP12+BS12+BV12+CA12+CC12+CF12+CH12+CK12+CO12+CS12+CU12+CW12+CZ12+DN12+DG12+DI12 -> 3.5527137e-15 | EA12: =DP12/$DX12 -> 0.18116676 | EB12: =DQ12/$DX12 -> 0.35536371 | EC12: =DR12/$DX12 -> 0 | EE12: =DT12/$DX12 -> 0 | EF12: =DU12/$DX12 -> 0.35487372 | EG12: =DV12/$DX12 -> 0.10859581 | EH12: =DW12/DX12 -> 0 | EI12: =SUM(EA12:EH12) -> 1 | EK12: =EA12*'[2]Renewable Diesel'!BF21*'[2]Feedstock Conversion Rates'!B$2 -> 6.1743115 | EL12: =EB12*'[2]Renewable Diesel'!BF21*'[2]Feedstock Conversion Rates'!B$3 -> 11.412917 | EM12: =EC12*'[2]Renewable Diesel'!BF21*'[2]Feedstock Conversion Rates'!B$4 -> 0 | EO12: =EE12*'[2]Renewable Diesel'!BF21*'[2]Feedstock Conversion Rates'!B$6 -> 0 | EP12: =EF12*'[2]Renewable Diesel'!BF21*'[2]Feedstock Conversion Rates'!B$7 -> 13.090395 | EQ12: =EG12*'[2]Renewable Diesel'!BF21*'[2]Feedstock Conversion Rates'!B$8 -> 4.0820227 | ER12: =EH12*'[2]Renewable Diesel'!BF21*'[2]Feedstock Conversion Rates'!B$9 -> 0 | ES12: =SUM(EK12:ER12) -> 34.759647
A13: 40817 | D13: 0 | E13: =('[2]Renewable Diesel'!B22*E$3*'[2]Feedstock Conversion Rates'!$B$2)/12 -> 5.2133333 | F13: =('[2]Renewable Diesel'!B22*'[2]RD Feedstock Breakdown'!F$3*'[2]Feedstock Conversion Rates'!B$8)/12 -> 3.125 | G13: =('[2]Renewable Diesel'!B22*'[2]RD Feedstock Breakdown'!G$3*'[2]Feedstock Conversion Rates'!B$7)/12 -> 10.212 | H13: =('[2]Renewable Diesel'!B22*'[2]RD Feedstock Breakdown'!H$3*'[2]Feedstock Conversion Rates'!B$3)/12 -> 10.2261 | I13: =SUM(B13:H13) -> 28.776433 | DP13: =E13+M13 -> 5.2133333 | DQ13: =H13+P13+AZ13+BC13+BK13+BZ13+CL13+CP13+CV13+CX13+DA13+DK13 -> 10.2261 | DR13: =AD13+AK13+AM13+AP13+AV13+AY13+BB13+BF13+BJ13+Y13+B13+BO13+BQ13+BW13+CB13+CE13+CG13+CJ13+BT13+CN13+CR13+CT13+DF13+DH13+AS13+J13+U13+AH13 -> 0 | DT13: =V13+Z13+AE13+AI13+BD13+BL13+AN13+AQ13+CD13+CM13+CQ13+CY13+DB13+DL13 -> 0 | DU13: =G13+O13+R13+AA13+AW13+BH13+BM13+BR13+BU13+BY13 -> 10.212 | DV13: =F13+N13+W13+DM13 -> 3.125 | DW13: =D13+L13 -> 0 | DX13: =SUM(DP13:DW13) -> 28.776433 | DY13: =I13+Q13+S13+X13+AB13+AF13+AJ13+AL13+AO13+AR13+AU13+AX13+BA13+BE13+BG13+BI13+BN13-DX13+BP13+BS13+BV13+CA13+CC13+CF13+CH13+CK13+CO13+CS13+CU13+CW13+CZ13+DN13+DG13+DI13 -> 3.5527137e-15 | EA13: =DP13/$DX13 -> 0.18116676 | EB13: =DQ13/$DX13 -> 0.35536371 | EC13: =DR13/$DX13 -> 0 | EE13: =DT13/$DX13 -> 0 | EF13: =DU13/$DX13 -> 0.35487372 | EG13: =DV13/$DX13 -> 0.10859581 | EH13: =DW13/DX13 -> 0 | EI13: =SUM(EA13:EG13) -> 1 | EK13: =EA13*'[2]Renewable Diesel'!BF22*'[2]Feedstock Conversion Rates'!B$2 -> 8.8824043 | EL13: =EB13*'[2]Renewable Diesel'!BF22*'[2]Feedstock Conversion Rates'!B$3 -> 16.418696 | EM13: =EC13*'[2]Renewable Diesel'!BF22*'[2]Feedstock Conversion Rates'!B$4 -> 0 | EO13: =EE13*'[2]Renewable Diesel'!BF22*'[2]Feedstock Conversion Rates'!B$6 -> 0 | EP13: =EF13*'[2]Renewable Diesel'!BF22*'[2]Feedstock Conversion Rates'!B$7 -> 18.831927 | EQ13: =EG13*'[2]Renewable Diesel'!BF22*'[2]Feedstock Conversion Rates'!B$8 -> 5.8724241 | ER13: =EH13*'[2]Renewable Diesel'!BF22*'[2]Feedstock Conversion Rates'!B$9 -> 0 | ES13: =SUM(EK13:ER13) -> 50.005451
A14: 40848 | D14: 0 | E14: =('[2]Renewable Diesel'!B23*E$3*'[2]Feedstock Conversion Rates'!$B$2)/12 -> 15.64 | F14: =('[2]Renewable Diesel'!B23*'[2]RD Feedstock Breakdown'!F$3*'[2]Feedstock Conversion Rates'!B$8)/12 -> 9.375 | G14: =('[2]Renewable Diesel'!B23*'[2]RD Feedstock Breakdown'!G$3*'[2]Feedstock Conversion Rates'!B$7)/12 -> 30.636 | H14: =('[2]Renewable Diesel'!B23*'[2]RD Feedstock Breakdown'!H$3*'[2]Feedstock Conversion Rates'!B$3)/12 -> 30.6783 | I14: =SUM(B14:H14) -> 86.3293 | DP14: =E14+M14 -> 15.64 | DQ14: =H14+P14+AZ14+BC14+BK14+BZ14+CL14+CP14+CV14+CX14+DA14+DK14 -> 30.6783 | DR14: =AD14+AK14+AM14+AP14+AV14+AY14+BB14+BF14+BJ14+Y14+B14+BO14+BQ14+BW14+CB14+CE14+CG14+CJ14+BT14+CN14+CR14+CT14+DF14+DH14+AS14+J14+U14+AH14 -> 0 | DT14: =V14+Z14+AE14+AI14+BD14+BL14+AN14+AQ14+CD14+CM14+CQ14+CY14+DB14+DL14 -> 0 | DU14: =G14+O14+R14+AA14+AW14+BH14+BM14+BR14+BU14+BY14 -> 30.636 | DV14: =F14+N14+W14+DM14 -> 9.375 | DW14: =D14+L14 -> 0 | DX14: =SUM(DP14:DW14) -> 86.3293 | DY14: =I14+Q14+S14+X14+AB14+AF14+AJ14+AL14+AO14+AR14+AU14+AX14+BA14+BE14+BG14+BI14+BN14-DX14+BP14+BS14+BV14+CA14+CC14+CF14+CH14+CK14+CO14+CS14+CU14+CW14+CZ14+DN14+DG14+DI14 -> 0 | EA14: =DP14/$DX14 -> 0.18116676 | EB14: =DQ14/$DX14 -> 0.35536371 | EC14: =DR14/$DX14 -> 0 | EE14: =DT14/$DX14 -> 0 | EF14: =DU14/$DX14 -> 0.35487372 | EG14: =DV14/$DX14 -> 0.10859581 | EH14: =DW14/DX14 -> 0 | EI14: =SUM(EA14:EG14) -> 1 | EK14: =EA14*'[2]Renewable Diesel'!BF23*'[2]Feedstock Conversion Rates'!B$2 -> 5.6983092 | EL14: =EB14*'[2]Renewable Diesel'!BF23*'[2]Feedstock Conversion Rates'!B$3 -> 10.53305 | EM14: =EC14*'[2]Renewable Diesel'!BF23*'[2]Feedstock Conversion Rates'!B$4 -> 0 | EO14: =EE14*'[2]Renewable Diesel'!BF23*'[2]Feedstock Conversion Rates'!B$6 -> 0 | EP14: =EF14*'[2]Renewable Diesel'!BF23*'[2]Feedstock Conversion Rates'!B$7 -> 12.081204 | EQ14: =EG14*'[2]Renewable Diesel'!BF23*'[2]Feedstock Conversion Rates'!B$8 -> 3.7673233 | ER14: =EH14*'[2]Renewable Diesel'!BF23*'[2]Feedstock Conversion Rates'!B$9 -> 0 | ES14: =SUM(EK14:ER14) -> 32.079887
A15: 40878 | D15: 0 | E15: =('[2]Renewable Diesel'!B24*E$3*'[2]Feedstock Conversion Rates'!$B$2)/12 -> 15.64 | F15: =('[2]Renewable Diesel'!B24*'[2]RD Feedstock Breakdown'!F$3*'[2]Feedstock Conversion Rates'!B$8)/12 -> 9.375 | G15: =('[2]Renewable Diesel'!B24*'[2]RD Feedstock Breakdown'!G$3*'[2]Feedstock Conversion Rates'!B$7)/12 -> 30.636 | H15: =('[2]Renewable Diesel'!B24*'[2]RD Feedstock Breakdown'!H$3*'[2]Feedstock Conversion Rates'!B$3)/12 -> 30.6783 | I15: =SUM(B15:H15) -> 86.3293 | DP15: =E15+M15 -> 15.64 | DQ15: =H15+P15+AZ15+BC15+BK15+BZ15+CL15+CP15+CV15+CX15+DA15+DK15 -> 30.6783 | DR15: =AD15+AK15+AM15+AP15+AV15+AY15+BB15+BF15+BJ15+Y15+B15+BO15+BQ15+BW15+CB15+CE15+CG15+CJ15+BT15+CN15+CR15+CT15+DF15+DH15+AS15+J15+U15+AH15 -> 0 | DT15: =V15+Z15+AE15+AI15+BD15+BL15+AN15+AQ15+CD15+CM15+CQ15+CY15+DB15+DL15 -> 0 | DU15: =G15+O15+R15+AA15+AW15+BH15+BM15+BR15+BU15+BY15 -> 30.636 | DV15: =F15+N15+W15+DM15 -> 9.375 | DW15: =D15+L15 -> 0 | DX15: =SUM(DP15:DW15) -> 86.3293 | DY15: =I15+Q15+S15+X15+AB15+AF15+AJ15+AL15+AO15+AR15+AU15+AX15+BA15+BE15+BG15+BI15+BN15-DX15+BP15+BS15+BV15+CA15+CC15+CF15+CH15+CK15+CO15+CS15+CU15+CW15+CZ15+DN15+DG15+DI15 -> 0 | EA15: =DP15/$DX15 -> 0.18116676 | EB15: =DQ15/$DX15 -> 0.35536371 | EC15: =DR15/$DX15 -> 0 | EE15: =DT15/$DX15 -> 0 | EF15: =DU15/$DX15 -> 0.35487372 | EG15: =DV15/$DX15 -> 0.10859581 | EH15: =DW15/DX15 -> 0 | EI15: =SUM(EA15:EG15) -> 1 | EK15: =EA15*'[2]Renewable Diesel'!BF24*'[2]Feedstock Conversion Rates'!B$2 -> 8.5263415 | EL15: =EB15*'[2]Renewable Diesel'!BF24*'[2]Feedstock Conversion Rates'!B$3 -> 15.760531 | EM15: =EC15*'[2]Renewable Diesel'!BF24*'[2]Feedstock Conversion Rates'!B$4 -> 0 | EO15: =EE15*'[2]Renewable Diesel'!BF24*'[2]Feedstock Conversion Rates'!B$6 -> 0 | EP15: =EF15*'[2]Renewable Diesel'!BF24*'[2]Feedstock Conversion Rates'!B$7 -> 18.077024 | EQ15: =EG15*'[2]Renewable Diesel'!BF24*'[2]Feedstock Conversion Rates'!B$8 -> 5.6370203 | ER15: =EH15*'[2]Renewable Diesel'!BF24*'[2]Feedstock Conversion Rates'!B$9 -> 0 | ES15: =SUM(EK15:ER15) -> 48.000917
A16: 40909 | D16: 0 | E16: =('[2]Renewable Diesel'!B25*E$3*'[2]Feedstock Conversion Rates'!$B$2)/12 -> 20.853333 | F16: =('[2]Renewable Diesel'!B25*'[2]RD Feedstock Breakdown'!F$3*'[2]Feedstock Conversion Rates'!B$8)/12 -> 12.5 | G16: =('[2]Renewable Diesel'!B25*'[2]RD Feedstock Breakdown'!G$3*'[2]Feedstock Conversion Rates'!B$7)/12 -> 40.848 | H16: =('[2]Renewable Diesel'!B25*'[2]RD Feedstock Breakdown'!H$3*'[2]Feedstock Conversion Rates'!B$3)/12 -> 40.9044 | I16: =SUM(B16:H16) -> 115.10573 | DP16: =E16+M16 -> 20.853333 | DQ16: =H16+P16+AZ16+BC16+BK16+BZ16+CL16+CP16+CV16+CX16+DA16+DK16 -> 40.9044 | DR16: =AD16+AK16+AM16+AP16+AV16+AY16+BB16+BF16+BJ16+Y16+B16+BO16+BQ16+BW16+CB16+CE16+CG16+CJ16+BT16+CN16+CR16+CT16+DF16+DH16+AS16+J16+U16+AH16 -> 0 | DT16: =V16+Z16+AE16+AI16+BD16+BL16+AN16+AQ16+CD16+CM16+CQ16+CY16+DB16+DL16 -> 0 | DU16: =G16+O16+R16+AA16+AW16+BH16+BM16+BR16+BU16+BY16 -> 40.848 | DV16: =F16+N16+W16+DM16 -> 12.5 | DW16: =D16+L16 -> 0 | DX16: =SUM(DP16:DW16) -> 115.10573 | DY16: =I16+Q16+S16+X16+AB16+AF16+AJ16+AL16+AO16+AR16+AU16+AX16+BA16+BE16+BG16+BI16+BN16-DX16+BP16+BS16+BV16+CA16+CC16+CF16+CH16+CK16+CO16+CS16+CU16+CW16+CZ16+DN16+DG16+DI16 -> 1.4210855e-14 | EA16: =DP16/$DX16 -> 0.18116676 | EB16: =DQ16/$DX16 -> 0.35536371 | EC16: =DR16/$DX16 -> 0 | EE16: =DT16/$DX16 -> 0 | EF16: =DU16/$DX16 -> 0.35487372 | EG16: =DV16/$DX16 -> 0.10859581 | EH16: =DW16/DX16 -> 0 | EI16: =SUM(EA16:EG16) -> 1 | EK16: =EA16*'[2]Renewable Diesel'!BF25*'[2]Feedstock Conversion Rates'!B$2 -> 5.7048261 | EL16: =EB16*'[2]Renewable Diesel'!BF25*'[2]Feedstock Conversion Rates'!B$3 -> 10.545096 | EM16: =EC16*'[2]Renewable Diesel'!BF25*'[2]Feedstock Conversion Rates'!B$4 -> 0 | EO16: =EE16*'[2]Renewable Diesel'!BF25*'[2]Feedstock Conversion Rates'!B$6 -> 0 | EP16: =EF16*'[2]Renewable Diesel'!BF25*'[2]Feedstock Conversion Rates'!B$7 -> 12.095021 | EQ16: =EG16*'[2]Renewable Diesel'!BF25*'[2]Feedstock Conversion Rates'!B$8 -> 3.7716318 | ER16: =EH16*'[2]Renewable Diesel'!BF25*'[2]Feedstock Conversion Rates'!B$9 -> 0 | ES16: =SUM(EK16:ER16) -> 32.116575
A17: 40940 | D17: 0 | E17: =('[2]Renewable Diesel'!B26*E$3*'[2]Feedstock Conversion Rates'!$B$2)/12 -> 20.853333 | F17: =('[2]Renewable Diesel'!B26*'[2]RD Feedstock Breakdown'!F$3*'[2]Feedstock Conversion Rates'!B$8)/12 -> 12.5 | G17: =('[2]Renewable Diesel'!B26*'[2]RD Feedstock Breakdown'!G$3*'[2]Feedstock Conversion Rates'!B$7)/12 -> 40.848 | H17: =('[2]Renewable Diesel'!B26*'[2]RD Feedstock Breakdown'!H$3*'[2]Feedstock Conversion Rates'!B$3)/12 -> 40.9044 | I17: =SUM(B17:H17) -> 115.10573 | DP17: =E17+M17 -> 20.853333 | DQ17: =H17+P17+AZ17+BC17+BK17+BZ17+CL17+CP17+CV17+CX17+DA17+DK17 -> 40.9044 | DR17: =AD17+AK17+AM17+AP17+AV17+AY17+BB17+BF17+BJ17+Y17+B17+BO17+BQ17+BW17+CB17+CE17+CG17+CJ17+BT17+CN17+CR17+CT17+DF17+DH17+AS17+J17+U17+AH17 -> 0 | DT17: =V17+Z17+AE17+AI17+BD17+BL17+AN17+AQ17+CD17+CM17+CQ17+CY17+DB17+DL17 -> 0 | DU17: =G17+O17+R17+AA17+AW17+BH17+BM17+BR17+BU17+BY17 -> 40.848 | DV17: =F17+N17+W17+DM17 -> 12.5 | DW17: =D17+L17 -> 0 | DX17: =SUM(DP17:DW17) -> 115.10573 | DY17: =I17+Q17+S17+X17+AB17+AF17+AJ17+AL17+AO17+AR17+AU17+AX17+BA17+BE17+BG17+BI17+BN17-DX17+BP17+BS17+BV17+CA17+CC17+CF17+CH17+CK17+CO17+CS17+CU17+CW17+CZ17+DN17+DG17+DI17 -> 1.4210855e-14 | EA17: =DP17/$DX17 -> 0.18116676 | EB17: =DQ17/$DX17 -> 0.35536371 | EC17: =DR17/$DX17 -> 0 | EE17: =DT17/$DX17 -> 0 | EF17: =DU17/$DX17 -> 0.35487372 | EG17: =DV17/$DX17 -> 0.10859581 | EH17: =DW17/DX17 -> 0 | EI17: =SUM(EA17:EG17) -> 1 | EK17: =EA17*'[2]Renewable Diesel'!BF26*'[2]Feedstock Conversion Rates'!B$2 -> 2.2584476 | EL17: =EB17*'[2]Renewable Diesel'!BF26*'[2]Feedstock Conversion Rates'!B$3 -> 4.1746316 | EM17: =EC17*'[2]Renewable Diesel'!BF26*'[2]Feedstock Conversion Rates'!B$4 -> 0 | EO17: =EE17*'[2]Renewable Diesel'!BF26*'[2]Feedstock Conversion Rates'!B$6 -> 0 | EP17: =EF17*'[2]Renewable Diesel'!BF26*'[2]Feedstock Conversion Rates'!B$7 -> 4.7882216 | EQ17: =EG17*'[2]Renewable Diesel'!BF26*'[2]Feedstock Conversion Rates'!B$8 -> 1.4931275 | ER17: =EH17*'[2]Renewable Diesel'!BF26*'[2]Feedstock Conversion Rates'!B$9 -> 0 | ES17: =SUM(EK17:ER17) -> 12.714428
A18: 40969 | D18: 0 | E18: =('[2]Renewable Diesel'!B27*E$3*'[2]Feedstock Conversion Rates'!$B$2)/12 -> 20.853333 | F18: =('[2]Renewable Diesel'!B27*'[2]RD Feedstock Breakdown'!F$3*'[2]Feedstock Conversion Rates'!B$8)/12 -> 12.5 | G18: =('[2]Renewable Diesel'!B27*'[2]RD Feedstock Breakdown'!G$3*'[2]Feedstock Conversion Rates'!B$7)/12 -> 40.848 | H18: =('[2]Renewable Diesel'!B27*'[2]RD Feedstock Breakdown'!H$3*'[2]Feedstock Conversion Rates'!B$3)/12 -> 40.9044 | I18: =SUM(B18:H18) -> 115.10573 | DP18: =E18+M18 -> 20.853333 | DQ18: =H18+P18+AZ18+BC18+BK18+BZ18+CL18+CP18+CV18+CX18+DA18+DK18 -> 40.9044 | DR18: =AD18+AK18+AM18+AP18+AV18+AY18+BB18+BF18+BJ18+Y18+B18+BO18+BQ18+BW18+CB18+CE18+CG18+CJ18+BT18+CN18+CR18+CT18+DF18+DH18+AS18+J18+U18+AH18 -> 0 | DT18: =V18+Z18+AE18+AI18+BD18+BL18+AN18+AQ18+CD18+CM18+CQ18+CY18+DB18+DL18 -> 0 | DU18: =G18+O18+R18+AA18+AW18+BH18+BM18+BR18+BU18+BY18 -> 40.848 | DV18: =F18+N18+W18+DM18 -> 12.5 | DW18: =D18+L18 -> 0 | DX18: =SUM(DP18:DW18) -> 115.10573 | DY18: =I18+Q18+S18+X18+AB18+AF18+AJ18+AL18+AO18+AR18+AU18+AX18+BA18+BE18+BG18+BI18+BN18-DX18+BP18+BS18+BV18+CA18+CC18+CF18+CH18+CK18+CO18+CS18+CU18+CW18+CZ18+DN18+DG18+DI18 -> 1.4210855e-14 | EA18: =DP18/$DX18 -> 0.18116676 | EB18: =DQ18/$DX18 -> 0.35536371 | EC18: =DR18/$DX18 -> 0 | EE18: =DT18/$DX18 -> 0 | EF18: =DU18/$DX18 -> 0.35487372 | EG18: =DV18/$DX18 -> 0.10859581 | EH18: =DW18/DX18 -> 0 | EI18: =SUM(EA18:EG18) -> 1 | EK18: =EA18*'[2]Renewable Diesel'!BF27*'[2]Feedstock Conversion Rates'!B$2 -> 7.2446281 | EL18: =EB18*'[2]Renewable Diesel'!BF27*'[2]Feedstock Conversion Rates'!B$3 -> 13.391346 | EM18: =EC18*'[2]Renewable Diesel'!BF27*'[2]Feedstock Conversion Rates'!B$4 -> 0 | EO18: =EE18*'[2]Renewable Diesel'!BF27*'[2]Feedstock Conversion Rates'!B$6 -> 0 | EP18: =EF18*'[2]Renewable Diesel'!BF27*'[2]Feedstock Conversion Rates'!B$7 -> 15.359614 | EQ18: =EG18*'[2]Renewable Diesel'!BF27*'[2]Feedstock Conversion Rates'!B$8 -> 4.7896411 | ER18: =EH18*'[2]Renewable Diesel'!BF27*'[2]Feedstock Conversion Rates'!B$9 -> 0 | ES18: =SUM(EK18:ER18) -> 40.78523
A19: 41000 | D19: 0 | E19: =('[2]Renewable Diesel'!B28*E$3*'[2]Feedstock Conversion Rates'!$B$2)/12 -> 20.853333 | F19: =('[2]Renewable Diesel'!B28*'[2]RD Feedstock Breakdown'!F$3*'[2]Feedstock Conversion Rates'!B$8)/12 -> 12.5 | G19: =('[2]Renewable Diesel'!B28*'[2]RD Feedstock Breakdown'!G$3*'[2]Feedstock Conversion Rates'!B$7)/12 -> 40.848 | H19: =('[2]Renewable Diesel'!B28*'[2]RD Feedstock Breakdown'!H$3*'[2]Feedstock Conversion Rates'!B$3)/12 -> 40.9044 | I19: =SUM(B19:H19) -> 115.10573 | DP19: =E19+M19 -> 20.853333 | DQ19: =H19+P19+AZ19+BC19+BK19+BZ19+CL19+CP19+CV19+CX19+DA19+DK19 -> 40.9044 | DR19: =AD19+AK19+AM19+AP19+AV19+AY19+BB19+BF19+BJ19+Y19+B19+BO19+BQ19+BW19+CB19+CE19+CG19+CJ19+BT19+CN19+CR19+CT19+DF19+DH19+AS19+J19+U19+AH19 -> 0 | DT19: =V19+Z19+AE19+AI19+BD19+BL19+AN19+AQ19+CD19+CM19+CQ19+CY19+DB19+DL19 -> 0 | DU19: =G19+O19+R19+AA19+AW19+BH19+BM19+BR19+BU19+BY19 -> 40.848 | DV19: =F19+N19+W19+DM19 -> 12.5 | DW19: =D19+L19 -> 0 | DX19: =SUM(DP19:DW19) -> 115.10573 | DY19: =I19+Q19+S19+X19+AB19+AF19+AJ19+AL19+AO19+AR19+AU19+AX19+BA19+BE19+BG19+BI19+BN19-DX19+BP19+BS19+BV19+CA19+CC19+CF19+CH19+CK19+CO19+CS19+CU19+CW19+CZ19+DN19+DG19+DI19 -> 1.4210855e-14 | EA19: =DP19/$DX19 -> 0.18116676 | EB19: =DQ19/$DX19 -> 0.35536371 | EC19: =DR19/$DX19 -> 0 | EE19: =DT19/$DX19 -> 0 | EF19: =DU19/$DX19 -> 0.35487372 | EG19: =DV19/$DX19 -> 0.10859581 | EH19: =DW19/DX19 -> 0 | EI19: =SUM(EA19:EG19) -> 1 | EK19: =EA19*'[2]Renewable Diesel'!BF28*'[2]Feedstock Conversion Rates'!B$2 -> 4.9000883 | EL19: =EB19*'[2]Renewable Diesel'!BF28*'[2]Feedstock Conversion Rates'!B$3 -> 9.0575771 | EM19: =EC19*'[2]Renewable Diesel'!BF28*'[2]Feedstock Conversion Rates'!B$4 -> 0 | EO19: =EE19*'[2]Renewable Diesel'!BF28*'[2]Feedstock Conversion Rates'!B$6 -> 0 | EP19: =EF19*'[2]Renewable Diesel'!BF28*'[2]Feedstock Conversion Rates'!B$7 -> 10.388865 | EQ19: =EG19*'[2]Renewable Diesel'!BF28*'[2]Feedstock Conversion Rates'!B$8 -> 3.2395955 | ER19: =EH19*'[2]Renewable Diesel'!BF28*'[2]Feedstock Conversion Rates'!B$9 -> 0 | ES19: =SUM(EK19:ER19) -> 27.586126
A20: 41030 | D20: 0 | E20: =('[2]Renewable Diesel'!B29*E$3*'[2]Feedstock Conversion Rates'!$B$2)/12 -> 20.853333 | F20: =('[2]Renewable Diesel'!B29*'[2]RD Feedstock Breakdown'!F$3*'[2]Feedstock Conversion Rates'!B$8)/12 -> 12.5 | G20: =('[2]Renewable Diesel'!B29*'[2]RD Feedstock Breakdown'!G$3*'[2]Feedstock Conversion Rates'!B$7)/12 -> 40.848 | H20: =('[2]Renewable Diesel'!B29*'[2]RD Feedstock Breakdown'!H$3*'[2]Feedstock Conversion Rates'!B$3)/12 -> 40.9044 | I20: =SUM(B20:H20) -> 115.10573 | DP20: =E20+M20 -> 20.853333 | DQ20: =H20+P20+AZ20+BC20+BK20+BZ20+CL20+CP20+CV20+CX20+DA20+DK20 -> 40.9044 | DR20: =AD20+AK20+AM20+AP20+AV20+AY20+BB20+BF20+BJ20+Y20+B20+BO20+BQ20+BW20+CB20+CE20+CG20+CJ20+BT20+CN20+CR20+CT20+DF20+DH20+AS20+J20+U20+AH20 -> 0 | DT20: =V20+Z20+AE20+AI20+BD20+BL20+AN20+AQ20+CD20+CM20+CQ20+CY20+DB20+DL20 -> 0 | DU20: =G20+O20+R20+AA20+AW20+BH20+BM20+BR20+BU20+BY20 -> 40.848 | DV20: =F20+N20+W20+DM20 -> 12.5 | DW20: =D20+L20 -> 0 | DX20: =SUM(DP20:DW20) -> 115.10573 | DY20: =I20+Q20+S20+X20+AB20+AF20+AJ20+AL20+AO20+AR20+AU20+AX20+BA20+BE20+BG20+BI20+BN20-DX20+BP20+BS20+BV20+CA20+CC20+CF20+CH20+CK20+CO20+CS20+CU20+CW20+CZ20+DN20+DG20+DI20 -> 1.4210855e-14 | EA20: =DP20/$DX20 -> 0.18116676 | EB20: =DQ20/$DX20 -> 0.35536371 | EC20: =DR20/$DX20 -> 0 | EE20: =DT20/$DX20 -> 0 | EF20: =DU20/$DX20 -> 0.35487372 | EG20: =DV20/$DX20 -> 0.10859581 | EH20: =DW20/DX20 -> 0 | EI20: =SUM(EA20:EG20) -> 1 | EK20: =EA20*'[2]Renewable Diesel'!BF29*'[2]Feedstock Conversion Rates'!B$2 -> 5.1706518 | EL20: =EB20*'[2]Renewable Diesel'!BF29*'[2]Feedstock Conversion Rates'!B$3 -> 9.5577007 | EM20: =EC20*'[2]Renewable Diesel'!BF29*'[2]Feedstock Conversion Rates'!B$4 -> 0 | EO20: =EE20*'[2]Renewable Diesel'!BF29*'[2]Feedstock Conversion Rates'!B$6 -> 0 | EP20: =EF20*'[2]Renewable Diesel'!BF29*'[2]Feedstock Conversion Rates'!B$7 -> 10.962498 | EQ20: =EG20*'[2]Renewable Diesel'!BF29*'[2]Feedstock Conversion Rates'!B$8 -> 3.4184732 | ER20: =EH20*'[2]Renewable Diesel'!BF29*'[2]Feedstock Conversion Rates'!B$9 -> 0 | ES20: =SUM(EK20:ER20) -> 29.109323
A21: 41061 | D21: 0 | E21: =('[2]Renewable Diesel'!B30*E$3*'[2]Feedstock Conversion Rates'!$B$2)/12 -> 20.853333 | F21: =('[2]Renewable Diesel'!B30*'[2]RD Feedstock Breakdown'!F$3*'[2]Feedstock Conversion Rates'!B$8)/12 -> 12.5 | G21: =('[2]Renewable Diesel'!B30*'[2]RD Feedstock Breakdown'!G$3*'[2]Feedstock Conversion Rates'!B$7)/12 -> 40.848 | H21: =('[2]Renewable Diesel'!B30*'[2]RD Feedstock Breakdown'!H$3*'[2]Feedstock Conversion Rates'!B$3)/12 -> 40.9044 | I21: =SUM(B21:H21) -> 115.10573 | DP21: =E21+M21 -> 20.853333 | DQ21: =H21+P21+AZ21+BC21+BK21+BZ21+CL21+CP21+CV21+CX21+DA21+DK21 -> 40.9044 | DR21: =AD21+AK21+AM21+AP21+AV21+AY21+BB21+BF21+BJ21+Y21+B21+BO21+BQ21+BW21+CB21+CE21+CG21+CJ21+BT21+CN21+CR21+CT21+DF21+DH21+AS21+J21+U21+AH21 -> 0 | DT21: =V21+Z21+AE21+AI21+BD21+BL21+AN21+AQ21+CD21+CM21+CQ21+CY21+DB21+DL21 -> 0 | DU21: =G21+O21+R21+AA21+AW21+BH21+BM21+BR21+BU21+BY21 -> 40.848 | DV21: =F21+N21+W21+DM21 -> 12.5 | DW21: =D21+L21 -> 0 | DX21: =SUM(DP21:DW21) -> 115.10573 | DY21: =I21+Q21+S21+X21+AB21+AF21+AJ21+AL21+AO21+AR21+AU21+AX21+BA21+BE21+BG21+BI21+BN21-DX21+BP21+BS21+BV21+CA21+CC21+CF21+CH21+CK21+CO21+CS21+CU21+CW21+CZ21+DN21+DG21+DI21 -> 1.4210855e-14 | EA21: =DP21/$DX21 -> 0.18116676 | EB21: =DQ21/$DX21 -> 0.35536371 | EC21: =DR21/$DX21 -> 0 | EE21: =DT21/$DX21 -> 0 | EF21: =DU21/$DX21 -> 0.35487372 | EG21: =DV21/$DX21 -> 0.10859581 | EH21: =DW21/DX21 -> 0 | EI21: =SUM(EA21:EG21) -> 1 | EK21: =EA21*'[2]Renewable Diesel'!BF30*'[2]Feedstock Conversion Rates'!B$2 -> 4.7463245 | EL21: =EB21*'[2]Renewable Diesel'!BF30*'[2]Feedstock Conversion Rates'!B$3 -> 8.7733521 | EM21: =EC21*'[2]Renewable Diesel'!BF30*'[2]Feedstock Conversion Rates'!B$4 -> 0 | EO21: =EE21*'[2]Renewable Diesel'!BF30*'[2]Feedstock Conversion Rates'!B$6 -> 0 | EP21: =EF21*'[2]Renewable Diesel'!BF30*'[2]Feedstock Conversion Rates'!B$7 -> 10.062865 | EQ21: =EG21*'[2]Renewable Diesel'!BF30*'[2]Feedstock Conversion Rates'!B$8 -> 3.1379376 | ER21: =EH21*'[2]Renewable Diesel'!BF30*'[2]Feedstock Conversion Rates'!B$9 -> 0 | ES21: =SUM(EK21:ER21) -> 26.720479
A22: 41091 | D22: 0 | E22: =('[2]Renewable Diesel'!B31*E$3*'[2]Feedstock Conversion Rates'!$B$2)/12 -> 20.853333 | F22: =('[2]Renewable Diesel'!B31*'[2]RD Feedstock Breakdown'!F$3*'[2]Feedstock Conversion Rates'!B$8)/12 -> 12.5 | G22: =('[2]Renewable Diesel'!B31*'[2]RD Feedstock Breakdown'!G$3*'[2]Feedstock Conversion Rates'!B$7)/12 -> 40.848 | H22: =('[2]Renewable Diesel'!B31*'[2]RD Feedstock Breakdown'!H$3*'[2]Feedstock Conversion Rates'!B$3)/12 -> 40.9044 | I22: =SUM(B22:H22) -> 115.10573 | DP22: =E22+M22 -> 20.853333 | DQ22: =H22+P22+AZ22+BC22+BK22+BZ22+CL22+CP22+CV22+CX22+DA22+DK22 -> 40.9044 | DR22: =AD22+AK22+AM22+AP22+AV22+AY22+BB22+BF22+BJ22+Y22+B22+BO22+BQ22+BW22+CB22+CE22+CG22+CJ22+BT22+CN22+CR22+CT22+DF22+DH22+AS22+J22+U22+AH22 -> 0 | DT22: =V22+Z22+AE22+AI22+BD22+BL22+AN22+AQ22+CD22+CM22+CQ22+CY22+DB22+DL22 -> 0 | DU22: =G22+O22+R22+AA22+AW22+BH22+BM22+BR22+BU22+BY22 -> 40.848 | DV22: =F22+N22+W22+DM22 -> 12.5 | DW22: =D22+L22 -> 0 | DX22: =SUM(DP22:DW22) -> 115.10573 | DY22: =I22+Q22+S22+X22+AB22+AF22+AJ22+AL22+AO22+AR22+AU22+AX22+BA22+BE22+BG22+BI22+BN22-DX22+BP22+BS22+BV22+CA22+CC22+CF22+CH22+CK22+CO22+CS22+CU22+CW22+CZ22+DN22+DG22+DI22 -> 1.4210855e-14 | EA22: =DP22/$DX22 -> 0.18116676 | EB22: =DQ22/$DX22 -> 0.35536371 | EC22: =DR22/$DX22 -> 0 | EE22: =DT22/$DX22 -> 0 | EF22: =DU22/$DX22 -> 0.35487372 | EG22: =DV22/$DX22 -> 0.10859581 | EH22: =DW22/DX22 -> 0 | EI22: =SUM(EA22:EG22) -> 1 | EK22: =EA22*'[2]Renewable Diesel'!BF31*'[2]Feedstock Conversion Rates'!B$2 -> 8.8148835 | EL22: =EB22*'[2]Renewable Diesel'!BF31*'[2]Feedstock Conversion Rates'!B$3 -> 16.293887 | EM22: =EC22*'[2]Renewable Diesel'!BF31*'[2]Feedstock Conversion Rates'!B$4 -> 0 | EO22: =EE22*'[2]Renewable Diesel'!BF31*'[2]Feedstock Conversion Rates'!B$6 -> 0 | EP22: =EF22*'[2]Renewable Diesel'!BF31*'[2]Feedstock Conversion Rates'!B$7 -> 18.688773 | EQ22: =EG22*'[2]Renewable Diesel'!BF31*'[2]Feedstock Conversion Rates'!B$8 -> 5.8277841 | ER22: =EH22*'[2]Renewable Diesel'!BF31*'[2]Feedstock Conversion Rates'!B$9 -> 0 | ES22: =SUM(EK22:ER22) -> 49.625328
A23: 41122 | D23: 0 | E23: =('[2]Renewable Diesel'!B32*E$3*'[2]Feedstock Conversion Rates'!$B$2)/12 -> 20.853333 | F23: =('[2]Renewable Diesel'!B32*'[2]RD Feedstock Breakdown'!F$3*'[2]Feedstock Conversion Rates'!B$8)/12 -> 12.5 | G23: =('[2]Renewable Diesel'!B32*'[2]RD Feedstock Breakdown'!G$3*'[2]Feedstock Conversion Rates'!B$7)/12 -> 40.848 | H23: =('[2]Renewable Diesel'!B32*'[2]RD Feedstock Breakdown'!H$3*'[2]Feedstock Conversion Rates'!B$3)/12 -> 40.9044 | I23: =SUM(B23:H23) -> 115.10573 | DP23: =E23+M23 -> 20.853333 | DQ23: =H23+P23+AZ23+BC23+BK23+BZ23+CL23+CP23+CV23+CX23+DA23+DK23 -> 40.9044 | DR23: =AD23+AK23+AM23+AP23+AV23+AY23+BB23+BF23+BJ23+Y23+B23+BO23+BQ23+BW23+CB23+CE23+CG23+CJ23+BT23+CN23+CR23+CT23+DF23+DH23+AS23+J23+U23+AH23 -> 0 | DT23: =V23+Z23+AE23+AI23+BD23+BL23+AN23+AQ23+CD23+CM23+CQ23+CY23+DB23+DL23 -> 0 | DU23: =G23+O23+R23+AA23+AW23+BH23+BM23+BR23+BU23+BY23 -> 40.848 | DV23: =F23+N23+W23+DM23 -> 12.5 | DW23: =D23+L23 -> 0 | DX23: =SUM(DP23:DW23) -> 115.10573 | DY23: =I23+Q23+S23+X23+AB23+AF23+AJ23+AL23+AO23+AR23+AU23+AX23+BA23+BE23+BG23+BI23+BN23-DX23+BP23+BS23+BV23+CA23+CC23+CF23+CH23+CK23+CO23+CS23+CU23+CW23+CZ23+DN23+DG23+DI23 -> 1.4210855e-14 | EA23: =DP23/$DX23 -> 0.18116676 | EB23: =DQ23/$DX23 -> 0.35536371 | EC23: =DR23/$DX23 -> 0 | EE23: =DT23/$DX23 -> 0 | EF23: =DU23/$DX23 -> 0.35487372 | EG23: =DV23/$DX23 -> 0.10859581 | EH23: =DW23/DX23 -> 0 | EI23: =SUM(EA23:EG23) -> 1 | EK23: =EA23*'[2]Renewable Diesel'!BF32*'[2]Feedstock Conversion Rates'!B$2 -> 6.5408812 | EL23: =EB23*'[2]Renewable Diesel'!BF32*'[2]Feedstock Conversion Rates'!B$3 -> 12.090504 | EM23: =EC23*'[2]Renewable Diesel'!BF32*'[2]Feedstock Conversion Rates'!B$4 -> 0 | EO23: =EE23*'[2]Renewable Diesel'!BF32*'[2]Feedstock Conversion Rates'!B$6 -> 0 | EP23: =EF23*'[2]Renewable Diesel'!BF32*'[2]Feedstock Conversion Rates'!B$7 -> 13.867573 | EQ23: =EG23*'[2]Renewable Diesel'!BF32*'[2]Feedstock Conversion Rates'!B$8 -> 4.3243729 | ER23: =EH23*'[2]Renewable Diesel'!BF32*'[2]Feedstock Conversion Rates'!B$9 -> 0 | ES23: =SUM(EK23:ER23) -> 36.823331
A24: 41153 | D24: 0 | E24: =('[2]Renewable Diesel'!B33*E$3*'[2]Feedstock Conversion Rates'!$B$2)/12 -> 20.853333 | F24: =('[2]Renewable Diesel'!B33*'[2]RD Feedstock Breakdown'!F$3*'[2]Feedstock Conversion Rates'!B$8)/12 -> 12.5 | G24: =('[2]Renewable Diesel'!B33*'[2]RD Feedstock Breakdown'!G$3*'[2]Feedstock Conversion Rates'!B$7)/12 -> 40.848 | H24: =('[2]Renewable Diesel'!B33*'[2]RD Feedstock Breakdown'!H$3*'[2]Feedstock Conversion Rates'!B$3)/12 -> 40.9044 | I24: =SUM(B24:H24) -> 115.10573 | DP24: =E24+M24 -> 20.853333 | DQ24: =H24+P24+AZ24+BC24+BK24+BZ24+CL24+CP24+CV24+CX24+DA24+DK24 -> 40.9044 | DR24: =AD24+AK24+AM24+AP24+AV24+AY24+BB24+BF24+BJ24+Y24+B24+BO24+BQ24+BW24+CB24+CE24+CG24+CJ24+BT24+CN24+CR24+CT24+DF24+DH24+AS24+J24+U24+AH24 -> 0 | DT24: =V24+Z24+AE24+AI24+BD24+BL24+AN24+AQ24+CD24+CM24+CQ24+CY24+DB24+DL24 -> 0 | DU24: =G24+O24+R24+AA24+AW24+BH24+BM24+BR24+BU24+BY24 -> 40.848 | DV24: =F24+N24+W24+DM24 -> 12.5 | DW24: =D24+L24 -> 0 | DX24: =SUM(DP24:DW24) -> 115.10573 | DY24: =I24+Q24+S24+X24+AB24+AF24+AJ24+AL24+AO24+AR24+AU24+AX24+BA24+BE24+BG24+BI24+BN24-DX24+BP24+BS24+BV24+CA24+CC24+CF24+CH24+CK24+CO24+CS24+CU24+CW24+CZ24+DN24+DG24+DI24 -> 1.4210855e-14 | EA24: =DP24/$DX24 -> 0.18116676 | EB24: =DQ24/$DX24 -> 0.35536371 | EC24: =DR24/$DX24 -> 0 | EE24: =DT24/$DX24 -> 0 | EF24: =DU24/$DX24 -> 0.35487372 | EG24: =DV24/$DX24 -> 0.10859581 | EH24: =DW24/DX24 -> 0 | EI24: =SUM(EA24:EG24) -> 1 | EK24: =EA24*'[2]Renewable Diesel'!BF33*'[2]Feedstock Conversion Rates'!B$2 -> 4.155917 | EL24: =EB24*'[2]Renewable Diesel'!BF33*'[2]Feedstock Conversion Rates'!B$3 -> 7.6820123 | EM24: =EC24*'[2]Renewable Diesel'!BF33*'[2]Feedstock Conversion Rates'!B$4 -> 0 | EO24: =EE24*'[2]Renewable Diesel'!BF33*'[2]Feedstock Conversion Rates'!B$6 -> 0 | EP24: =EF24*'[2]Renewable Diesel'!BF33*'[2]Feedstock Conversion Rates'!B$7 -> 8.8111193 | EQ24: =EG24*'[2]Renewable Diesel'!BF33*'[2]Feedstock Conversion Rates'!B$8 -> 2.7476015 | ER24: =EH24*'[2]Renewable Diesel'!BF33*'[2]Feedstock Conversion Rates'!B$9 -> 0 | ES24: =SUM(EK24:ER24) -> 23.39665
... A49: 41913 | D49: 0 | E49: =('[2]Renewable Diesel'!B58*E$3*'[2]Feedstock Conversion Rates'!$B$2)/12 -> 20.853333 | F49: =('[2]Renewable Diesel'!B58*'[2]RD Feedstock Breakdown'!F$3*'[2]Feedstock Conversion Rates'!B$8)/12 -> 12.5 | G49: =('[2]Renewable Diesel'!B58*'[2]RD Feedstock Breakdown'!G$3*'[2]Feedstock Conversion Rates'!B$7)/12 -> 40.848 | H49: =('[2]Renewable Diesel'!B58*'[2]RD Feedstock Breakdown'!H$3*'[2]Feedstock Conversion Rates'!B$3)/12 -> 40.9044 | I49: =SUM(B49:H49) -> 115.10573 | DP49: =E49+M49 -> 20.853333 | DQ49: =H49+P49+AZ49+BC49+BK49+BZ49+CL49+CP49+CV49+CX49+DA49+DK49 -> 40.9044 | DR49: =AD49+AK49+AM49+AP49+AV49+AY49+BB49+BF49+BJ49+Y49+B49+BO49+BQ49+BW49+CB49+CE49+CG49+CJ49+BT49+CN49+CR49+CT49+DF49+DH49+AS49+J49+U49+AH49 -> 0 | DT49: =V49+Z49+AE49+AI49+BD49+BL49+AN49+AQ49+CD49+CM49+CQ49+CY49+DB49+DL49 -> 0 | DU49: =G49+O49+R49+AA49+AW49+BH49+BM49+BR49+BU49+BY49 -> 40.848 | DV49: =F49+N49+W49+DM49 -> 12.5 | DW49: =D49+L49 -> 0 | DX49: =SUM(DP49:DW49) -> 115.10573 | DY49: =I49+Q49+S49+X49+AB49+AF49+AJ49+AL49+AO49+AR49+AU49+AX49+BA49+BE49+BG49+BI49+BN49-DX49+BP49+BS49+BV49+CA49+CC49+CF49+CH49+CK49+CO49+CS49+CU49+CW49+CZ49+DN49+DG49+DI49 -> 1.4210855e-14 | EA49: =DP49/$DX49 -> 0.18116676 | EB49: =DQ49/$DX49 -> 0.35536371 | EC49: =DR49/$DX49 -> 0 | EE49: =DT49/$DX49 -> 0 | EF49: =DU49/$DX49 -> 0.35487372 | EG49: =DV49/$DX49 -> 0.10859581 | EH49: =DW49/DX49 -> 0 | EI49: =SUM(EA49:EG49) -> 1 | EK49: =EA49*'[2]Renewable Diesel'!BF58*'[2]Feedstock Conversion Rates'!B$2 -> 21.372945 | EL49: =EB49*'[2]Renewable Diesel'!BF58*'[2]Feedstock Conversion Rates'!B$3 -> 39.506858 | EM49: =EC49*'[2]Renewable Diesel'!BF58*'[2]Feedstock Conversion Rates'!B$4 -> 0 | EO49: =EE49*'[2]Renewable Diesel'!BF58*'[2]Feedstock Conversion Rates'!B$6 -> 0 | EP49: =EF49*'[2]Renewable Diesel'!BF58*'[2]Feedstock Conversion Rates'!B$7 -> 45.313601 | EQ49: =EG49*'[2]Renewable Diesel'!BF58*'[2]Feedstock Conversion Rates'!B$8 -> 14.130295 | ER49: =EH49*'[2]Renewable Diesel'!BF58*'[2]Feedstock Conversion Rates'!B$9 -> 0 | ES49: =SUM(EK49:ER49) -> 120.3237
A50: 41944 | D50: 0 | E50: =('[2]Renewable Diesel'!B59*E$3*'[2]Feedstock Conversion Rates'!$B$2)/12 -> 20.853333 | F50: =('[2]Renewable Diesel'!B59*'[2]RD Feedstock Breakdown'!F$3*'[2]Feedstock Conversion Rates'!B$8)/12 -> 12.5 | G50: =('[2]Renewable Diesel'!B59*'[2]RD Feedstock Breakdown'!G$3*'[2]Feedstock Conversion Rates'!B$7)/12 -> 40.848 | H50: =('[2]Renewable Diesel'!B59*'[2]RD Feedstock Breakdown'!H$3*'[2]Feedstock Conversion Rates'!B$3)/12 -> 40.9044 | I50: =SUM(B50:H50) -> 115.10573 | Z50: =('[2]Renewable Diesel'!F59*'[2]RD Feedstock Breakdown'!Z$3*'[2]Feedstock Conversion Rates'!B$6)/12 -> 11.725 | AA50: =('[2]Renewable Diesel'!F59*'[2]RD Feedstock Breakdown'!AA$3*'[2]Feedstock Conversion Rates'!B$7)/12 -> 7.6666667 | AB50: =SUM(Y50:AA50) -> 19.391667 | DP50: =E50+M50 -> 20.853333 | DQ50: =H50+P50+AZ50+BC50+BK50+BZ50+CL50+CP50+CV50+CX50+DA50+DK50 -> 40.9044 | DR50: =AD50+AK50+AM50+AP50+AV50+AY50+BB50+BF50+BJ50+Y50+B50+BO50+BQ50+BW50+CB50+CE50+CG50+CJ50+BT50+CN50+CR50+CT50+DF50+DH50+AS50+J50+U50+AH50 -> 0 | DT50: =V50+Z50+AE50+AI50+BD50+BL50+AN50+AQ50+CD50+CM50+CQ50+CY50+DB50+DL50 -> 11.725 | DU50: =G50+O50+R50+AA50+AW50+BH50+BM50+BR50+BU50+BY50 -> 48.514667 | DV50: =F50+N50+W50+DM50 -> 12.5 | DW50: =D50+L50 -> 0 | DX50: =SUM(DP50:DW50) -> 134.4974 | DY50: =I50+Q50+S50+X50+AB50+AF50+AJ50+AL50+AO50+AR50+AU50+AX50+BA50+BE50+BG50+BI50+BN50-DX50+BP50+BS50+BV50+CA50+CC50+CF50+CH50+CK50+CO50+CS50+CU50+CW50+CZ50+DN50+DG50+DI50 -> 2.8421709e-14 | EA50: =DP50/$DX50 -> 0.15504637 | EB50: =DQ50/$DX50 -> 0.30412781 | EC50: =DR50/$DX50 -> 0 | EE50: =DT50/$DX50 -> 0.087176406 | EF50: =DU50/$DX50 -> 0.36071081 | EG50: =DV50/$DX50 -> 0.0929386 | EH50: =DW50/DX50 -> 0 | EI50: =SUM(EA50:EG50) -> 1 | EK50: =EA50*'[2]Renewable Diesel'!BF59*'[2]Feedstock Conversion Rates'!B$2 -> 21.011708 | EL50: =EB50*'[2]Renewable Diesel'!BF59*'[2]Feedstock Conversion Rates'!B$3 -> 38.839129 | EM50: =EC50*'[2]Renewable Diesel'!BF59*'[2]Feedstock Conversion Rates'!B$4 -> 0 | EO50: =EE50*'[2]Renewable Diesel'!BF59*'[2]Feedstock Conversion Rates'!B$6 -> 13.037149 | EP50: =EF50*'[2]Renewable Diesel'!BF59*'[2]Feedstock Conversion Rates'!B$7 -> 52.908789 | EQ50: =EG50*'[2]Renewable Diesel'!BF59*'[2]Feedstock Conversion Rates'!B$8 -> 13.891471 | ER50: =EH50*'[2]Renewable Diesel'!BF59*'[2]Feedstock Conversion Rates'!B$9 -> 0 | ES50: =SUM(EK50:ER50) -> 139.68825
A51: 41974 | D51: 0 | E51: =('[2]Renewable Diesel'!B60*E$3*'[2]Feedstock Conversion Rates'!$B$2)/12 -> 20.853333 | F51: =('[2]Renewable Diesel'!B60*'[2]RD Feedstock Breakdown'!F$3*'[2]Feedstock Conversion Rates'!B$8)/12 -> 12.5 | G51: =('[2]Renewable Diesel'!B60*'[2]RD Feedstock Breakdown'!G$3*'[2]Feedstock Conversion Rates'!B$7)/12 -> 40.848 | H51: =('[2]Renewable Diesel'!B60*'[2]RD Feedstock Breakdown'!H$3*'[2]Feedstock Conversion Rates'!B$3)/12 -> 40.9044 | I51: =SUM(B51:H51) -> 115.10573 | Z51: =('[2]Renewable Diesel'!F60*'[2]RD Feedstock Breakdown'!Z$3*'[2]Feedstock Conversion Rates'!B$6)/12 -> 23.45 | AA51: =('[2]Renewable Diesel'!F60*'[2]RD Feedstock Breakdown'!AA$3*'[2]Feedstock Conversion Rates'!B$7)/12 -> 15.333333 | AB51: =SUM(Y51:AA51) -> 38.783333 | DP51: =E51+M51 -> 20.853333 | DQ51: =H51+P51+AZ51+BC51+BK51+BZ51+CL51+CP51+CV51+CX51+DA51+DK51 -> 40.9044 | DR51: =AD51+AK51+AM51+AP51+AV51+AY51+BB51+BF51+BJ51+Y51+B51+BO51+BQ51+BW51+CB51+CE51+CG51+CJ51+BT51+CN51+CR51+CT51+DF51+DH51+AS51+J51+U51+AH51 -> 0 | DT51: =V51+Z51+AE51+AI51+BD51+BL51+AN51+AQ51+CD51+CM51+CQ51+CY51+DB51+DL51 -> 23.45 | DU51: =G51+O51+R51+AA51+AW51+BH51+BM51+BR51+BU51+BY51 -> 56.181333 | DV51: =F51+N51+W51+DM51 -> 12.5 | DW51: =D51+L51 -> 0 | DX51: =SUM(DP51:DW51) -> 153.88907 | DY51: =I51+Q51+S51+X51+AB51+AF51+AJ51+AL51+AO51+AR51+AU51+AX51+BA51+BE51+BG51+BI51+BN51-DX51+BP51+BS51+BV51+CA51+CC51+CF51+CH51+CK51+CO51+CS51+CU51+CW51+CZ51+DN51+DG51+DI51 -> 0 | EA51: =DP51/$DX51 -> 0.13550887 | EB51: =DQ51/$DX51 -> 0.26580446 | EC51: =DR51/$DX51 -> 0 | EE51: =DT51/$DX51 -> 0.1523825 | EF51: =DU51/$DX51 -> 0.36507683 | EG51: =DV51/$DX51 -> 0.081227343 | EH51: =DW51/DX51 -> 0 | EI51: =SUM(EA51:EG51) -> 1 | EK51: =EA51*'[2]Renewable Diesel'!BF60*'[2]Feedstock Conversion Rates'!B$2 -> 25.386776 | EL51: =EB51*'[2]Renewable Diesel'!BF60*'[2]Feedstock Conversion Rates'!B$3 -> 46.926232 | EM51: =EC51*'[2]Renewable Diesel'!BF60*'[2]Feedstock Conversion Rates'!B$4 -> 0 | EO51: =EE51*'[2]Renewable Diesel'!BF60*'[2]Feedstock Conversion Rates'!B$6 -> 31.503502 | EP51: =EF51*'[2]Renewable Diesel'!BF60*'[2]Feedstock Conversion Rates'!B$7 -> 74.027488 | EQ51: =EG51*'[2]Renewable Diesel'!BF60*'[2]Feedstock Conversion Rates'!B$8 -> 16.78396 | ER51: =EH51*'[2]Renewable Diesel'!BF60*'[2]Feedstock Conversion Rates'!B$9 -> 0 | ES51: =SUM(EK51:ER51) -> 194.62796
A52: 42005 | D52: 0 | E52: =('[2]Renewable Diesel'!B61*E$3*'[2]Feedstock Conversion Rates'!$B$2)/12 -> 20.853333 | F52: =('[2]Renewable Diesel'!B61*'[2]RD Feedstock Breakdown'!F$3*'[2]Feedstock Conversion Rates'!B$8)/12 -> 12.5 | G52: =('[2]Renewable Diesel'!B61*'[2]RD Feedstock Breakdown'!G$3*'[2]Feedstock Conversion Rates'!B$7)/12 -> 40.848 | H52: =('[2]Renewable Diesel'!B61*'[2]RD Feedstock Breakdown'!H$3*'[2]Feedstock Conversion Rates'!B$3)/12 -> 40.9044 | I52: =SUM(B52:H52) -> 115.10573 | Z52: =('[2]Renewable Diesel'!F61*'[2]RD Feedstock Breakdown'!Z$3*'[2]Feedstock Conversion Rates'!B$6)/12 -> 44.555 | AA52: =('[2]Renewable Diesel'!F61*'[2]RD Feedstock Breakdown'!AA$3*'[2]Feedstock Conversion Rates'!B$7)/12 -> 29.133333 | AB52: =SUM(Y52:AA52) -> 73.688333 | DP52: =E52+M52 -> 20.853333 | DQ52: =H52+P52+AZ52+BC52+BK52+BZ52+CL52+CP52+CV52+CX52+DA52+DK52 -> 40.9044 | DR52: =AD52+AK52+AM52+AP52+AV52+AY52+BB52+BF52+BJ52+Y52+B52+BO52+BQ52+BW52+CB52+CE52+CG52+CJ52+BT52+CN52+CR52+CT52+DF52+DH52+AS52+J52+U52+AH52 -> 0 | DT52: =V52+Z52+AE52+AI52+BD52+BL52+AN52+AQ52+CD52+CM52+CQ52+CY52+DB52+DL52 -> 44.555 | DU52: =G52+O52+R52+AA52+AW52+BH52+BM52+BR52+BU52+BY52 -> 69.981333 | DV52: =F52+N52+W52+DM52 -> 12.5 | DW52: =D52+L52 -> 0 | DX52: =SUM(DP52:DW52) -> 188.79407 | DY52: =I52+Q52+S52+X52+AB52+AF52+AJ52+AL52+AO52+AR52+AU52+AX52+BA52+BE52+BG52+BI52+BN52-DX52+BP52+BS52+BV52+CA52+CC52+CF52+CH52+CK52+CO52+CS52+CU52+CW52+CZ52+DN52+DG52+DI52 -> 2.8421709e-14 | EA52: =DP52/$DX52 -> 0.11045545 | EB52: =DQ52/$DX52 -> 0.21666147 | EC52: =DR52/$DX52 -> 0 | EE52: =DT52/$DX52 -> 0.23599788 | EF52: =DU52/$DX52 -> 0.37067549 | EG52: =DV52/$DX52 -> 0.066209708 | EH52: =DW52/DX52 -> 0 | EI52: =SUM(EA52:EG52) -> 1 | EK52: =EA52*'[2]Renewable Diesel'!BF61*'[2]Feedstock Conversion Rates'!B$2 -> 16.278741 | EL52: =EB52*'[2]Renewable Diesel'!BF61*'[2]Feedstock Conversion Rates'!B$3 -> 30.090469 | EM52: =EC52*'[2]Renewable Diesel'!BF61*'[2]Feedstock Conversion Rates'!B$4 -> 0 | EO52: =EE52*'[2]Renewable Diesel'!BF61*'[2]Feedstock Conversion Rates'!B$6 -> 38.381832 | EP52: =EF52*'[2]Renewable Diesel'!BF61*'[2]Feedstock Conversion Rates'!B$7 -> 59.128444 | EQ52: =EG52*'[2]Renewable Diesel'!BF61*'[2]Feedstock Conversion Rates'!B$8 -> 10.762365 | ER52: =EH52*'[2]Renewable Diesel'!BF61*'[2]Feedstock Conversion Rates'!B$9 -> 0 | ES52: =SUM(EK52:ER52) -> 154.64185
A53: 42036 | D53: 0 | E53: =('[2]Renewable Diesel'!B62*E$3*'[2]Feedstock Conversion Rates'!$B$2)/12 -> 20.853333 | F53: =('[2]Renewable Diesel'!B62*'[2]RD Feedstock Breakdown'!F$3*'[2]Feedstock Conversion Rates'!B$8)/12 -> 12.5 | G53: =('[2]Renewable Diesel'!B62*'[2]RD Feedstock Breakdown'!G$3*'[2]Feedstock Conversion Rates'!B$7)/12 -> 40.848 | H53: =('[2]Renewable Diesel'!B62*'[2]RD Feedstock Breakdown'!H$3*'[2]Feedstock Conversion Rates'!B$3)/12 -> 40.9044 | I53: =SUM(B53:H53) -> 115.10573 | Z53: =('[2]Renewable Diesel'!F62*'[2]RD Feedstock Breakdown'!Z$3*'[2]Feedstock Conversion Rates'!B$6)/12 -> 44.555 | AA53: =('[2]Renewable Diesel'!F62*'[2]RD Feedstock Breakdown'!AA$3*'[2]Feedstock Conversion Rates'!B$7)/12 -> 29.133333 | AB53: =SUM(Y53:AA53) -> 73.688333 | DP53: =E53+M53 -> 20.853333 | DQ53: =H53+P53+AZ53+BC53+BK53+BZ53+CL53+CP53+CV53+CX53+DA53+DK53 -> 40.9044 | DR53: =AD53+AK53+AM53+AP53+AV53+AY53+BB53+BF53+BJ53+Y53+B53+BO53+BQ53+BW53+CB53+CE53+CG53+CJ53+BT53+CN53+CR53+CT53+DF53+DH53+AS53+J53+U53+AH53 -> 0 | DT53: =V53+Z53+AE53+AI53+BD53+BL53+AN53+AQ53+CD53+CM53+CQ53+CY53+DB53+DL53 -> 44.555 | DU53: =G53+O53+R53+AA53+AW53+BH53+BM53+BR53+BU53+BY53 -> 69.981333 | DV53: =F53+N53+W53+DM53 -> 12.5 | DW53: =D53+L53 -> 0 | DX53: =SUM(DP53:DW53) -> 188.79407 | DY53: =I53+Q53+S53+X53+AB53+AF53+AJ53+AL53+AO53+AR53+AU53+AX53+BA53+BE53+BG53+BI53+BN53-DX53+BP53+BS53+BV53+CA53+CC53+CF53+CH53+CK53+CO53+CS53+CU53+CW53+CZ53+DN53+DG53+DI53 -> 2.8421709e-14 | EA53: =DP53/$DX53 -> 0.11045545 | EB53: =DQ53/$DX53 -> 0.21666147 | EC53: =DR53/$DX53 -> 0 | EE53: =DT53/$DX53 -> 0.23599788 | EF53: =DU53/$DX53 -> 0.37067549 | EG53: =DV53/$DX53 -> 0.066209708 | EH53: =DW53/DX53 -> 0 | EI53: =SUM(EA53:EG53) -> 1 | EK53: =EA53*'[2]Renewable Diesel'!BF62*'[2]Feedstock Conversion Rates'!B$2 -> 12.290185 | EL53: =EB53*'[2]Renewable Diesel'!BF62*'[2]Feedstock Conversion Rates'!B$3 -> 22.717815 | EM53: =EC53*'[2]Renewable Diesel'!BF62*'[2]Feedstock Conversion Rates'!B$4 -> 0 | EO53: =EE53*'[2]Renewable Diesel'!BF62*'[2]Feedstock Conversion Rates'!B$6 -> 28.977659 | EP53: =EF53*'[2]Renewable Diesel'!BF62*'[2]Feedstock Conversion Rates'!B$7 -> 44.641014 | EQ53: =EG53*'[2]Renewable Diesel'!BF62*'[2]Feedstock Conversion Rates'!B$8 -> 8.1254103 | ER53: =EH53*'[2]Renewable Diesel'!BF62*'[2]Feedstock Conversion Rates'!B$9 -> 0 | ES53: =SUM(EK53:ER53) -> 116.75208
A54: 42064 | D54: 0 | E54: =('[2]Renewable Diesel'!B63*E$3*'[2]Feedstock Conversion Rates'!$B$2)/12 -> 20.853333 | F54: =('[2]Renewable Diesel'!B63*'[2]RD Feedstock Breakdown'!F$3*'[2]Feedstock Conversion Rates'!B$8)/12 -> 12.5 | G54: =('[2]Renewable Diesel'!B63*'[2]RD Feedstock Breakdown'!G$3*'[2]Feedstock Conversion Rates'!B$7)/12 -> 40.848 | H54: =('[2]Renewable Diesel'!B63*'[2]RD Feedstock Breakdown'!H$3*'[2]Feedstock Conversion Rates'!B$3)/12 -> 40.9044 | I54: =SUM(B54:H54) -> 115.10573 | Z54: =('[2]Renewable Diesel'!F63*'[2]RD Feedstock Breakdown'!Z$3*'[2]Feedstock Conversion Rates'!B$6)/12 -> 44.555 | AA54: =('[2]Renewable Diesel'!F63*'[2]RD Feedstock Breakdown'!AA$3*'[2]Feedstock Conversion Rates'!B$7)/12 -> 29.133333 | AB54: =SUM(Y54:AA54) -> 73.688333 | DP54: =E54+M54 -> 20.853333 | DQ54: =H54+P54+AZ54+BC54+BK54+BZ54+CL54+CP54+CV54+CX54+DA54+DK54 -> 40.9044 | DR54: =AD54+AK54+AM54+AP54+AV54+AY54+BB54+BF54+BJ54+Y54+B54+BO54+BQ54+BW54+CB54+CE54+CG54+CJ54+BT54+CN54+CR54+CT54+DF54+DH54+AS54+J54+U54+AH54 -> 0 | DT54: =V54+Z54+AE54+AI54+BD54+BL54+AN54+AQ54+CD54+CM54+CQ54+CY54+DB54+DL54 -> 44.555 | DU54: =G54+O54+R54+AA54+AW54+BH54+BM54+BR54+BU54+BY54 -> 69.981333 | DV54: =F54+N54+W54+DM54 -> 12.5 | DW54: =D54+L54 -> 0 | DX54: =SUM(DP54:DW54) -> 188.79407 | DY54: =I54+Q54+S54+X54+AB54+AF54+AJ54+AL54+AO54+AR54+AU54+AX54+BA54+BE54+BG54+BI54+BN54-DX54+BP54+BS54+BV54+CA54+CC54+CF54+CH54+CK54+CO54+CS54+CU54+CW54+CZ54+DN54+DG54+DI54 -> 2.8421709e-14 | EA54: =DP54/$DX54 -> 0.11045545 | EB54: =DQ54/$DX54 -> 0.21666147 | EC54: =DR54/$DX54 -> 0 | EE54: =DT54/$DX54 -> 0.23599788 | EF54: =DU54/$DX54 -> 0.37067549 | EG54: =DV54/$DX54 -> 0.066209708 | EH54: =DW54/DX54 -> 0 | EI54: =SUM(EA54:EG54) -> 1 | EK54: =EA54*'[2]Renewable Diesel'!BF63*'[2]Feedstock Conversion Rates'!B$2 -> 14.466581 | EL54: =EB54*'[2]Renewable Diesel'!BF63*'[2]Feedstock Conversion Rates'!B$3 -> 26.740777 | EM54: =EC54*'[2]Renewable Diesel'!BF63*'[2]Feedstock Conversion Rates'!B$4 -> 0 | EO54: =EE54*'[2]Renewable Diesel'!BF63*'[2]Feedstock Conversion Rates'!B$6 -> 34.10914 | EP54: =EF54*'[2]Renewable Diesel'!BF63*'[2]Feedstock Conversion Rates'!B$7 -> 52.546226 | EQ54: =EG54*'[2]Renewable Diesel'!BF63*'[2]Feedstock Conversion Rates'!B$8 -> 9.5642909 | ER54: =EH54*'[2]Renewable Diesel'!BF63*'[2]Feedstock Conversion Rates'!B$9 -> 0 | ES54: =SUM(EK54:ER54) -> 137.42701
A55: 42095 | D55: 0 | E55: =('[2]Renewable Diesel'!B64*E$3*'[2]Feedstock Conversion Rates'!$B$2)/12 -> 20.853333 | F55: =('[2]Renewable Diesel'!B64*'[2]RD Feedstock Breakdown'!F$3*'[2]Feedstock Conversion Rates'!B$8)/12 -> 12.5 | G55: =('[2]Renewable Diesel'!B64*'[2]RD Feedstock Breakdown'!G$3*'[2]Feedstock Conversion Rates'!B$7)/12 -> 40.848 | H55: =('[2]Renewable Diesel'!B64*'[2]RD Feedstock Breakdown'!H$3*'[2]Feedstock Conversion Rates'!B$3)/12 -> 40.9044 | I55: =SUM(B55:H55) -> 115.10573 | Z55: =('[2]Renewable Diesel'!F64*'[2]RD Feedstock Breakdown'!Z$3*'[2]Feedstock Conversion Rates'!B$6)/12 -> 44.555 | AA55: =('[2]Renewable Diesel'!F64*'[2]RD Feedstock Breakdown'!AA$3*'[2]Feedstock Conversion Rates'!B$7)/12 -> 29.133333 | AB55: =SUM(Y55:AA55) -> 73.688333 | DP55: =E55+M55 -> 20.853333 | DQ55: =H55+P55+AZ55+BC55+BK55+BZ55+CL55+CP55+CV55+CX55+DA55+DK55 -> 40.9044 | DR55: =AD55+AK55+AM55+AP55+AV55+AY55+BB55+BF55+BJ55+Y55+B55+BO55+BQ55+BW55+CB55+CE55+CG55+CJ55+BT55+CN55+CR55+CT55+DF55+DH55+AS55+J55+U55+AH55 -> 0 | DT55: =V55+Z55+AE55+AI55+BD55+BL55+AN55+AQ55+CD55+CM55+CQ55+CY55+DB55+DL55 -> 44.555 | DU55: =G55+O55+R55+AA55+AW55+BH55+BM55+BR55+BU55+BY55 -> 69.981333 | DV55: =F55+N55+W55+DM55 -> 12.5 | DW55: =D55+L55 -> 0 | DX55: =SUM(DP55:DW55) -> 188.79407 | DY55: =I55+Q55+S55+X55+AB55+AF55+AJ55+AL55+AO55+AR55+AU55+AX55+BA55+BE55+BG55+BI55+BN55-DX55+BP55+BS55+BV55+CA55+CC55+CF55+CH55+CK55+CO55+CS55+CU55+CW55+CZ55+DN55+DG55+DI55 -> 2.8421709e-14 | EA55: =DP55/$DX55 -> 0.11045545 | EB55: =DQ55/$DX55 -> 0.21666147 | EC55: =DR55/$DX55 -> 0 | EE55: =DT55/$DX55 -> 0.23599788 | EF55: =DU55/$DX55 -> 0.37067549 | EG55: =DV55/$DX55 -> 0.066209708 | EH55: =DW55/DX55 -> 0 | EI55: =SUM(EA55:EG55) -> 1 | EK55: =EA55*'[2]Renewable Diesel'!BF64*'[2]Feedstock Conversion Rates'!B$2 -> 14.246982 | EL55: =EB55*'[2]Renewable Diesel'!BF64*'[2]Feedstock Conversion Rates'!B$3 -> 26.334859 | EM55: =EC55*'[2]Renewable Diesel'!BF64*'[2]Feedstock Conversion Rates'!B$4 -> 0 | EO55: =EE55*'[2]Renewable Diesel'!BF64*'[2]Feedstock Conversion Rates'!B$6 -> 33.591372 | EP55: =EF55*'[2]Renewable Diesel'!BF64*'[2]Feedstock Conversion Rates'!B$7 -> 51.748587 | EQ55: =EG55*'[2]Renewable Diesel'!BF64*'[2]Feedstock Conversion Rates'!B$8 -> 9.4191073 | ER55: =EH55*'[2]Renewable Diesel'!BF64*'[2]Feedstock Conversion Rates'!B$9 -> 0 | ES55: =SUM(EK55:ER55) -> 135.34091
A56: 42125 | D56: 0 | E56: =('[2]Renewable Diesel'!B65*E$3*'[2]Feedstock Conversion Rates'!$B$2)/12 -> 20.853333 | F56: =('[2]Renewable Diesel'!B65*'[2]RD Feedstock Breakdown'!F$3*'[2]Feedstock Conversion Rates'!B$8)/12 -> 12.5 | G56: =('[2]Renewable Diesel'!B65*'[2]RD Feedstock Breakdown'!G$3*'[2]Feedstock Conversion Rates'!B$7)/12 -> 40.848 | H56: =('[2]Renewable Diesel'!B65*'[2]RD Feedstock Breakdown'!H$3*'[2]Feedstock Conversion Rates'!B$3)/12 -> 40.9044 | I56: =SUM(B56:H56) -> 115.10573 | Z56: =('[2]Renewable Diesel'!F65*'[2]RD Feedstock Breakdown'!Z$3*'[2]Feedstock Conversion Rates'!B$6)/12 -> 44.555 | AA56: =('[2]Renewable Diesel'!F65*'[2]RD Feedstock Breakdown'!AA$3*'[2]Feedstock Conversion Rates'!B$7)/12 -> 29.133333 | AB56: =SUM(Y56:AA56) -> 73.688333 | DP56: =E56+M56 -> 20.853333 | DQ56: =H56+P56+AZ56+BC56+BK56+BZ56+CL56+CP56+CV56+CX56+DA56+DK56 -> 40.9044 | DR56: =AD56+AK56+AM56+AP56+AV56+AY56+BB56+BF56+BJ56+Y56+B56+BO56+BQ56+BW56+CB56+CE56+CG56+CJ56+BT56+CN56+CR56+CT56+DF56+DH56+AS56+J56+U56+AH56 -> 0 | DT56: =V56+Z56+AE56+AI56+BD56+BL56+AN56+AQ56+CD56+CM56+CQ56+CY56+DB56+DL56 -> 44.555 | DU56: =G56+O56+R56+AA56+AW56+BH56+BM56+BR56+BU56+BY56 -> 69.981333 | DV56: =F56+N56+W56+DM56 -> 12.5 | DW56: =D56+L56 -> 0 | DX56: =SUM(DP56:DW56) -> 188.79407 | DY56: =I56+Q56+S56+X56+AB56+AF56+AJ56+AL56+AO56+AR56+AU56+AX56+BA56+BE56+BG56+BI56+BN56-DX56+BP56+BS56+BV56+CA56+CC56+CF56+CH56+CK56+CO56+CS56+CU56+CW56+CZ56+DN56+DG56+DI56 -> 2.8421709e-14 | EA56: =DP56/$DX56 -> 0.11045545 | EB56: =DQ56/$DX56 -> 0.21666147 | EC56: =DR56/$DX56 -> 0 | EE56: =DT56/$DX56 -> 0.23599788 | EF56: =DU56/$DX56 -> 0.37067549 | EG56: =DV56/$DX56 -> 0.066209708 | EH56: =DW56/DX56 -> 0 | EI56: =SUM(EA56:EG56) -> 1 | EK56: =EA56*'[2]Renewable Diesel'!BF65*'[2]Feedstock Conversion Rates'!B$2 -> 14.458706 | EL56: =EB56*'[2]Renewable Diesel'!BF65*'[2]Feedstock Conversion Rates'!B$3 -> 26.72622 | EM56: =EC56*'[2]Renewable Diesel'!BF65*'[2]Feedstock Conversion Rates'!B$4 -> 0 | EO56: =EE56*'[2]Renewable Diesel'!BF65*'[2]Feedstock Conversion Rates'!B$6 -> 34.090572 | EP56: =EF56*'[2]Renewable Diesel'!BF65*'[2]Feedstock Conversion Rates'!B$7 -> 52.517621 | EQ56: =EG56*'[2]Renewable Diesel'!BF65*'[2]Feedstock Conversion Rates'!B$8 -> 9.5590843 | ER56: =EH56*'[2]Renewable Diesel'!BF65*'[2]Feedstock Conversion Rates'!B$9 -> 0 | ES56: =SUM(EK56:ER56) -> 137.3522
A57: 42156 | D57: 0 | E57: =('[2]Renewable Diesel'!B66*E$3*'[2]Feedstock Conversion Rates'!$B$2)/12 -> 20.853333 | F57: =('[2]Renewable Diesel'!B66*'[2]RD Feedstock Breakdown'!F$3*'[2]Feedstock Conversion Rates'!B$8)/12 -> 12.5 | G57: =('[2]Renewable Diesel'!B66*'[2]RD Feedstock Breakdown'!G$3*'[2]Feedstock Conversion Rates'!B$7)/12 -> 40.848 | H57: =('[2]Renewable Diesel'!B66*'[2]RD Feedstock Breakdown'!H$3*'[2]Feedstock Conversion Rates'!B$3)/12 -> 40.9044 | I57: =SUM(B57:H57) -> 115.10573 | Z57: =('[2]Renewable Diesel'!F66*'[2]RD Feedstock Breakdown'!Z$3*'[2]Feedstock Conversion Rates'!B$6)/12 -> 44.555 | AA57: =('[2]Renewable Diesel'!F66*'[2]RD Feedstock Breakdown'!AA$3*'[2]Feedstock Conversion Rates'!B$7)/12 -> 29.133333 | AB57: =SUM(Y57:AA57) -> 73.688333 | DP57: =E57+M57 -> 20.853333 | DQ57: =H57+P57+AZ57+BC57+BK57+BZ57+CL57+CP57+CV57+CX57+DA57+DK57 -> 40.9044 | DR57: =AD57+AK57+AM57+AP57+AV57+AY57+BB57+BF57+BJ57+Y57+B57+BO57+BQ57+BW57+CB57+CE57+CG57+CJ57+BT57+CN57+CR57+CT57+DF57+DH57+AS57+J57+U57+AH57 -> 0 | DT57: =V57+Z57+AE57+AI57+BD57+BL57+AN57+AQ57+CD57+CM57+CQ57+CY57+DB57+DL57 -> 44.555 | DU57: =G57+O57+R57+AA57+AW57+BH57+BM57+BR57+BU57+BY57 -> 69.981333 | DV57: =F57+N57+W57+DM57 -> 12.5 | DW57: =D57+L57 -> 0 | DX57: =SUM(DP57:DW57) -> 188.79407 | DY57: =I57+Q57+S57+X57+AB57+AF57+AJ57+AL57+AO57+AR57+AU57+AX57+BA57+BE57+BG57+BI57+BN57-DX57+BP57+BS57+BV57+CA57+CC57+CF57+CH57+CK57+CO57+CS57+CU57+CW57+CZ57+DN57+DG57+DI57 -> 2.8421709e-14 | EA57: =DP57/$DX57 -> 0.11045545 | EB57: =DQ57/$DX57 -> 0.21666147 | EC57: =DR57/$DX57 -> 0 | EE57: =DT57/$DX57 -> 0.23599788 | EF57: =DU57/$DX57 -> 0.37067549 | EG57: =DV57/$DX57 -> 0.066209708 | EH57: =DW57/DX57 -> 0 | EI57: =SUM(EA57:EG57) -> 1 | EK57: =EA57*'[2]Renewable Diesel'!BF66*'[2]Feedstock Conversion Rates'!B$2 -> 13.027718 | EL57: =EB57*'[2]Renewable Diesel'!BF66*'[2]Feedstock Conversion Rates'!B$3 -> 24.081109 | EM57: =EC57*'[2]Renewable Diesel'!BF66*'[2]Feedstock Conversion Rates'!B$4 -> 0 | EO57: =EE57*'[2]Renewable Diesel'!BF66*'[2]Feedstock Conversion Rates'!B$6 -> 30.716606 | EP57: =EF57*'[2]Renewable Diesel'!BF66*'[2]Feedstock Conversion Rates'!B$7 -> 47.319918 | EQ57: =EG57*'[2]Renewable Diesel'!BF66*'[2]Feedstock Conversion Rates'!B$8 -> 8.6130156 | ER57: =EH57*'[2]Renewable Diesel'!BF66*'[2]Feedstock Conversion Rates'!B$9 -> 0 | ES57: =SUM(EK57:ER57) -> 123.75837
A58: 42186 | D58: 0 | E58: =('[2]Renewable Diesel'!B67*E$3*'[2]Feedstock Conversion Rates'!$B$2)/12 -> 20.853333 | F58: =('[2]Renewable Diesel'!B67*'[2]RD Feedstock Breakdown'!F$3*'[2]Feedstock Conversion Rates'!B$8)/12 -> 12.5 | G58: =('[2]Renewable Diesel'!B67*'[2]RD Feedstock Breakdown'!G$3*'[2]Feedstock Conversion Rates'!B$7)/12 -> 40.848 | H58: =('[2]Renewable Diesel'!B67*'[2]RD Feedstock Breakdown'!H$3*'[2]Feedstock Conversion Rates'!B$3)/12 -> 40.9044 | I58: =SUM(B58:H58) -> 115.10573 | Z58: =('[2]Renewable Diesel'!F67*'[2]RD Feedstock Breakdown'!Z$3*'[2]Feedstock Conversion Rates'!B$6)/12 -> 44.555 | AA58: =('[2]Renewable Diesel'!F67*'[2]RD Feedstock Breakdown'!AA$3*'[2]Feedstock Conversion Rates'!B$7)/12 -> 29.133333 | AB58: =SUM(Y58:AA58) -> 73.688333 | DP58: =E58+M58 -> 20.853333 | DQ58: =H58+P58+AZ58+BC58+BK58+BZ58+CL58+CP58+CV58+CX58+DA58+DK58 -> 40.9044 | DR58: =AD58+AK58+AM58+AP58+AV58+AY58+BB58+BF58+BJ58+Y58+B58+BO58+BQ58+BW58+CB58+CE58+CG58+CJ58+BT58+CN58+CR58+CT58+DF58+DH58+AS58+J58+U58+AH58 -> 0 | DT58: =V58+Z58+AE58+AI58+BD58+BL58+AN58+AQ58+CD58+CM58+CQ58+CY58+DB58+DL58 -> 44.555 | DU58: =G58+O58+R58+AA58+AW58+BH58+BM58+BR58+BU58+BY58 -> 69.981333 | DV58: =F58+N58+W58+DM58 -> 12.5 | DW58: =D58+L58 -> 0 | DX58: =SUM(DP58:DW58) -> 188.79407 | DY58: =I58+Q58+S58+X58+AB58+AF58+AJ58+AL58+AO58+AR58+AU58+AX58+BA58+BE58+BG58+BI58+BN58-DX58+BP58+BS58+BV58+CA58+CC58+CF58+CH58+CK58+CO58+CS58+CU58+CW58+CZ58+DN58+DG58+DI58 -> 2.8421709e-14 | EA58: =DP58/$DX58 -> 0.11045545 | EB58: =DQ58/$DX58 -> 0.21666147 | EC58: =DR58/$DX58 -> 0 | EE58: =DT58/$DX58 -> 0.23599788 | EF58: =DU58/$DX58 -> 0.37067549 | EG58: =DV58/$DX58 -> 0.066209708 | EH58: =DW58/DX58 -> 0 | EI58: =SUM(EA58:EG58) -> 1 | EK58: =EA58*'[2]Renewable Diesel'!BF67*'[2]Feedstock Conversion Rates'!B$2 -> 14.125382 | EL58: =EB58*'[2]Renewable Diesel'!BF67*'[2]Feedstock Conversion Rates'!B$3 -> 26.110088 | EM58: =EC58*'[2]Renewable Diesel'!BF67*'[2]Feedstock Conversion Rates'!B$4 -> 0 | EO58: =EE58*'[2]Renewable Diesel'!BF67*'[2]Feedstock Conversion Rates'!B$6 -> 33.304665 | EP58: =EF58*'[2]Renewable Diesel'!BF67*'[2]Feedstock Conversion Rates'!B$7 -> 51.306906 | EQ58: =EG58*'[2]Renewable Diesel'!BF67*'[2]Feedstock Conversion Rates'!B$8 -> 9.338714 | ER58: =EH58*'[2]Renewable Diesel'!BF67*'[2]Feedstock Conversion Rates'!B$9 -> 0 | ES58: =SUM(EK58:ER58) -> 134.18575
A59: 42217 | D59: 0 | E59: =('[2]Renewable Diesel'!B68*E$3*'[2]Feedstock Conversion Rates'!$B$2)/12 -> 20.853333 | F59: =('[2]Renewable Diesel'!B68*'[2]RD Feedstock Breakdown'!F$3*'[2]Feedstock Conversion Rates'!B$8)/12 -> 12.5 | G59: =('[2]Renewable Diesel'!B68*'[2]RD Feedstock Breakdown'!G$3*'[2]Feedstock Conversion Rates'!B$7)/12 -> 40.848 | H59: =('[2]Renewable Diesel'!B68*'[2]RD Feedstock Breakdown'!H$3*'[2]Feedstock Conversion Rates'!B$3)/12 -> 40.9044 | I59: =SUM(B59:H59) -> 115.10573 | Z59: =('[2]Renewable Diesel'!F68*'[2]RD Feedstock Breakdown'!Z$3*'[2]Feedstock Conversion Rates'!B$6)/12 -> 44.555 | AA59: =('[2]Renewable Diesel'!F68*'[2]RD Feedstock Breakdown'!AA$3*'[2]Feedstock Conversion Rates'!B$7)/12 -> 29.133333 | AB59: =SUM(Y59:AA59) -> 73.688333 | DP59: =E59+M59 -> 20.853333 | DQ59: =H59+P59+AZ59+BC59+BK59+BZ59+CL59+CP59+CV59+CX59+DA59+DK59 -> 40.9044 | DR59: =AD59+AK59+AM59+AP59+AV59+AY59+BB59+BF59+BJ59+Y59+B59+BO59+BQ59+BW59+CB59+CE59+CG59+CJ59+BT59+CN59+CR59+CT59+DF59+DH59+AS59+J59+U59+AH59 -> 0 | DT59: =V59+Z59+AE59+AI59+BD59+BL59+AN59+AQ59+CD59+CM59+CQ59+CY59+DB59+DL59 -> 44.555 | DU59: =G59+O59+R59+AA59+AW59+BH59+BM59+BR59+BU59+BY59 -> 69.981333 | DV59: =F59+N59+W59+DM59 -> 12.5 | DW59: =D59+L59 -> 0 | DX59: =SUM(DP59:DW59) -> 188.79407 | DY59: =I59+Q59+S59+X59+AB59+AF59+AJ59+AL59+AO59+AR59+AU59+AX59+BA59+BE59+BG59+BI59+BN59-DX59+BP59+BS59+BV59+CA59+CC59+CF59+CH59+CK59+CO59+CS59+CU59+CW59+CZ59+DN59+DG59+DI59 -> 2.8421709e-14 | EA59: =DP59/$DX59 -> 0.11045545 | EB59: =DQ59/$DX59 -> 0.21666147 | EC59: =DR59/$DX59 -> 0 | EE59: =DT59/$DX59 -> 0.23599788 | EF59: =DU59/$DX59 -> 0.37067549 | EG59: =DV59/$DX59 -> 0.066209708 | EH59: =DW59/DX59 -> 0 | EI59: =SUM(EA59:EG59) -> 1 | EK59: =EA59*'[2]Renewable Diesel'!BF68*'[2]Feedstock Conversion Rates'!B$2 -> 13.759508 | EL59: =EB59*'[2]Renewable Diesel'!BF68*'[2]Feedstock Conversion Rates'!B$3 -> 25.433788 | EM59: =EC59*'[2]Renewable Diesel'!BF68*'[2]Feedstock Conversion Rates'!B$4 -> 0 | EO59: =EE59*'[2]Renewable Diesel'!BF68*'[2]Feedstock Conversion Rates'!B$6 -> 32.442013 | EP59: =EF59*'[2]Renewable Diesel'!BF68*'[2]Feedstock Conversion Rates'!B$7 -> 49.977962 | EQ59: =EG59*'[2]Renewable Diesel'!BF68*'[2]Feedstock Conversion Rates'!B$8 -> 9.0968241 | ER59: =EH59*'[2]Renewable Diesel'!BF68*'[2]Feedstock Conversion Rates'!B$9 -> 0 | ES59: =SUM(EK59:ER59) -> 130.7101
A60: 42248 | D60: 0 | E60: =('[2]Renewable Diesel'!B69*E$3*'[2]Feedstock Conversion Rates'!$B$2)/12 -> 20.853333 | F60: =('[2]Renewable Diesel'!B69*'[2]RD Feedstock Breakdown'!F$3*'[2]Feedstock Conversion Rates'!B$8)/12 -> 12.5 | G60: =('[2]Renewable Diesel'!B69*'[2]RD Feedstock Breakdown'!G$3*'[2]Feedstock Conversion Rates'!B$7)/12 -> 40.848 | H60: =('[2]Renewable Diesel'!B69*'[2]RD Feedstock Breakdown'!H$3*'[2]Feedstock Conversion Rates'!B$3)/12 -> 40.9044 | I60: =SUM(B60:H60) -> 115.10573 | Z60: =('[2]Renewable Diesel'!F69*'[2]RD Feedstock Breakdown'!Z$3*'[2]Feedstock Conversion Rates'!B$6)/12 -> 44.555 | AA60: =('[2]Renewable Diesel'!F69*'[2]RD Feedstock Breakdown'!AA$3*'[2]Feedstock Conversion Rates'!B$7)/12 -> 29.133333 | AB60: =SUM(Y60:AA60) -> 73.688333 | DP60: =E60+M60 -> 20.853333 | DQ60: =H60+P60+AZ60+BC60+BK60+BZ60+CL60+CP60+CV60+CX60+DA60+DK60 -> 40.9044 | DR60: =AD60+AK60+AM60+AP60+AV60+AY60+BB60+BF60+BJ60+Y60+B60+BO60+BQ60+BW60+CB60+CE60+CG60+CJ60+BT60+CN60+CR60+CT60+DF60+DH60+AS60+J60+U60+AH60 -> 0 | DT60: =V60+Z60+AE60+AI60+BD60+BL60+AN60+AQ60+CD60+CM60+CQ60+CY60+DB60+DL60 -> 44.555 | DU60: =G60+O60+R60+AA60+AW60+BH60+BM60+BR60+BU60+BY60 -> 69.981333 | DV60: =F60+N60+W60+DM60 -> 12.5 | DW60: =D60+L60 -> 0 | DX60: =SUM(DP60:DW60) -> 188.79407 | DY60: =I60+Q60+S60+X60+AB60+AF60+AJ60+AL60+AO60+AR60+AU60+AX60+BA60+BE60+BG60+BI60+BN60-DX60+BP60+BS60+BV60+CA60+CC60+CF60+CH60+CK60+CO60+CS60+CU60+CW60+CZ60+DN60+DG60+DI60 -> 2.8421709e-14 | EA60: =DP60/$DX60 -> 0.11045545 | EB60: =DQ60/$DX60 -> 0.21666147 | EC60: =DR60/$DX60 -> 0 | EE60: =DT60/$DX60 -> 0.23599788 | EF60: =DU60/$DX60 -> 0.37067549 | EG60: =DV60/$DX60 -> 0.066209708 | EH60: =DW60/DX60 -> 0 | EI60: =SUM(EA60:EG60) -> 1 | EK60: =EA60*'[2]Renewable Diesel'!BF69*'[2]Feedstock Conversion Rates'!B$2 -> 12.65214 | EL60: =EB60*'[2]Renewable Diesel'!BF69*'[2]Feedstock Conversion Rates'!B$3 -> 23.38687 | EM60: =EC60*'[2]Renewable Diesel'!BF69*'[2]Feedstock Conversion Rates'!B$4 -> 0 | EO60: =EE60*'[2]Renewable Diesel'!BF69*'[2]Feedstock Conversion Rates'!B$6 -> 29.831072 | EP60: =EF60*'[2]Renewable Diesel'!BF69*'[2]Feedstock Conversion Rates'!B$7 -> 45.955723 | EQ60: =EG60*'[2]Renewable Diesel'!BF69*'[2]Feedstock Conversion Rates'!B$8 -> 8.3647094 | ER60: =EH60*'[2]Renewable Diesel'!BF69*'[2]Feedstock Conversion Rates'!B$9 -> 0 | ES60: =SUM(EK60:ER60) -> 120.19051
A61: 42278 | D61: 0 | E61: =('[2]Renewable Diesel'!B70*E$3*'[2]Feedstock Conversion Rates'!$B$2)/12 -> 20.853333 | F61: =('[2]Renewable Diesel'!B70*'[2]RD Feedstock Breakdown'!F$3*'[2]Feedstock Conversion Rates'!B$8)/12 -> 12.5 | G61: =('[2]Renewable Diesel'!B70*'[2]RD Feedstock Breakdown'!G$3*'[2]Feedstock Conversion Rates'!B$7)/12 -> 40.848 | H61: =('[2]Renewable Diesel'!B70*'[2]RD Feedstock Breakdown'!H$3*'[2]Feedstock Conversion Rates'!B$3)/12 -> 40.9044 | I61: =SUM(B61:H61) -> 115.10573 | Z61: =('[2]Renewable Diesel'!F70*'[2]RD Feedstock Breakdown'!Z$3*'[2]Feedstock Conversion Rates'!B$6)/12 -> 44.555 | AA61: =('[2]Renewable Diesel'!F70*'[2]RD Feedstock Breakdown'!AA$3*'[2]Feedstock Conversion Rates'!B$7)/12 -> 29.133333 | AB61: =SUM(Y61:AA61) -> 73.688333 | DP61: =E61+M61 -> 20.853333 | DQ61: =H61+P61+AZ61+BC61+BK61+BZ61+CL61+CP61+CV61+CX61+DA61+DK61 -> 40.9044 | DR61: =AD61+AK61+AM61+AP61+AV61+AY61+BB61+BF61+BJ61+Y61+B61+BO61+BQ61+BW61+CB61+CE61+CG61+CJ61+BT61+CN61+CR61+CT61+DF61+DH61+AS61+J61+U61+AH61 -> 0 | DT61: =V61+Z61+AE61+AI61+BD61+BL61+AN61+AQ61+CD61+CM61+CQ61+CY61+DB61+DL61 -> 44.555 | DU61: =G61+O61+R61+AA61+AW61+BH61+BM61+BR61+BU61+BY61 -> 69.981333 | DV61: =F61+N61+W61+DM61 -> 12.5 | DW61: =D61+L61 -> 0 | DX61: =SUM(DP61:DW61) -> 188.79407 | DY61: =I61+Q61+S61+X61+AB61+AF61+AJ61+AL61+AO61+AR61+AU61+AX61+BA61+BE61+BG61+BI61+BN61-DX61+BP61+BS61+BV61+CA61+CC61+CF61+CH61+CK61+CO61+CS61+CU61+CW61+CZ61+DN61+DG61+DI61 -> 2.8421709e-14 | EA61: =DP61/$DX61 -> 0.11045545 | EB61: =DQ61/$DX61 -> 0.21666147 | EC61: =DR61/$DX61 -> 0 | EE61: =DT61/$DX61 -> 0.23599788 | EF61: =DU61/$DX61 -> 0.37067549 | EG61: =DV61/$DX61 -> 0.066209708 | EH61: =DW61/DX61 -> 0 | EI61: =SUM(EA61:EG61) -> 1 | EK61: =EA61*'[2]Renewable Diesel'!BF70*'[2]Feedstock Conversion Rates'!B$2 -> 12.240491 | EL61: =EB61*'[2]Renewable Diesel'!BF70*'[2]Feedstock Conversion Rates'!B$3 -> 22.625957 | EM61: =EC61*'[2]Renewable Diesel'!BF70*'[2]Feedstock Conversion Rates'!B$4 -> 0 | EO61: =EE61*'[2]Renewable Diesel'!BF70*'[2]Feedstock Conversion Rates'!B$6 -> 28.86049 | EP61: =EF61*'[2]Renewable Diesel'!BF70*'[2]Feedstock Conversion Rates'!B$7 -> 44.460511 | EQ61: =EG61*'[2]Renewable Diesel'!BF70*'[2]Feedstock Conversion Rates'!B$8 -> 8.0925558 | ER61: =EH61*'[2]Renewable Diesel'!BF70*'[2]Feedstock Conversion Rates'!B$9 -> 0 | ES61: =SUM(EK61:ER61) -> 116.28
... A63: 42339 | D63: 0 | E63: =('[2]Renewable Diesel'!B72*E$3*'[2]Feedstock Conversion Rates'!$B$2)/12 -> 20.853333 | F63: =('[2]Renewable Diesel'!B72*'[2]RD Feedstock Breakdown'!F$3*'[2]Feedstock Conversion Rates'!B$8)/12 -> 12.5 | G63: =('[2]Renewable Diesel'!B72*'[2]RD Feedstock Breakdown'!G$3*'[2]Feedstock Conversion Rates'!B$7)/12 -> 40.848 | H63: =('[2]Renewable Diesel'!B72*'[2]RD Feedstock Breakdown'!H$3*'[2]Feedstock Conversion Rates'!B$3)/12 -> 40.9044 | I63: =SUM(B63:H63) -> 115.10573 | Z63: =('[2]Renewable Diesel'!F72*'[2]RD Feedstock Breakdown'!Z$3*'[2]Feedstock Conversion Rates'!B$6)/12 -> 44.555 | AA63: =('[2]Renewable Diesel'!F72*'[2]RD Feedstock Breakdown'!AA$3*'[2]Feedstock Conversion Rates'!B$7)/12 -> 29.133333 | AB63: =SUM(Y63:AA63) -> 73.688333 | DP63: =E63+M63 -> 20.853333 | DQ63: =H63+P63+AZ63+BC63+BK63+BZ63+CL63+CP63+CV63+CX63+DA63+DK63 -> 40.9044 | DR63: =AD63+AK63+AM63+AP63+AV63+AY63+BB63+BF63+BJ63+Y63+B63+BO63+BQ63+BW63+CB63+CE63+CG63+CJ63+BT63+CN63+CR63+CT63+DF63+DH63+AS63+J63+U63+AH63 -> 0 | DT63: =V63+Z63+AE63+AI63+BD63+BL63+AN63+AQ63+CD63+CM63+CQ63+CY63+DB63+DL63 -> 44.555 | DU63: =G63+O63+R63+AA63+AW63+BH63+BM63+BR63+BU63+BY63 -> 69.981333 | DV63: =F63+N63+W63+DM63 -> 12.5 | DW63: =D63+L63 -> 0 | DX63: =SUM(DP63:DW63) -> 188.79407 | DY63: =I63+Q63+S63+X63+AB63+AF63+AJ63+AL63+AO63+AR63+AU63+AX63+BA63+BE63+BG63+BI63+BN63-DX63+BP63+BS63+BV63+CA63+CC63+CF63+CH63+CK63+CO63+CS63+CU63+CW63+CZ63+DN63+DG63+DI63 -> 2.8421709e-14 | EA63: =DP63/$DX63 -> 0.11045545 | EB63: =DQ63/$DX63 -> 0.21666147 | EC63: =DR63/$DX63 -> 0 | EE63: =DT63/$DX63 -> 0.23599788 | EF63: =DU63/$DX63 -> 0.37067549 | EG63: =DV63/$DX63 -> 0.066209708 | EH63: =DW63/DX63 -> 0 | EI63: =SUM(EA63:EG63) -> 1 | EK63: =EA63*'[2]Renewable Diesel'!BF72*'[2]Feedstock Conversion Rates'!B$2 -> 12.225688 | EL63: =EB63*'[2]Renewable Diesel'!BF72*'[2]Feedstock Conversion Rates'!B$3 -> 22.598596 | EM63: =EC63*'[2]Renewable Diesel'!BF72*'[2]Feedstock Conversion Rates'!B$4 -> 0 | EO63: =EE63*'[2]Renewable Diesel'!BF72*'[2]Feedstock Conversion Rates'!B$6 -> 28.825589 | EP63: =EF63*'[2]Renewable Diesel'!BF72*'[2]Feedstock Conversion Rates'!B$7 -> 44.406746 | EQ63: =EG63*'[2]Renewable Diesel'!BF72*'[2]Feedstock Conversion Rates'!B$8 -> 8.0827696 | ER63: =EH63*'[2]Renewable Diesel'!BF72*'[2]Feedstock Conversion Rates'!B$9 -> 0 | ES63: =SUM(EK63:ER63) -> 116.13939
A64: 42370 | D64: 0 | E64: =('[2]Renewable Diesel'!B73*E$3*'[2]Feedstock Conversion Rates'!$B$2)/12 -> 20.853333 | F64: =('[2]Renewable Diesel'!B73*'[2]RD Feedstock Breakdown'!F$3*'[2]Feedstock Conversion Rates'!B$8)/12 -> 12.5 | G64: =('[2]Renewable Diesel'!B73*'[2]RD Feedstock Breakdown'!G$3*'[2]Feedstock Conversion Rates'!B$7)/12 -> 40.848 | H64: =('[2]Renewable Diesel'!B73*'[2]RD Feedstock Breakdown'!H$3*'[2]Feedstock Conversion Rates'!B$3)/12 -> 40.9044 | I64: =SUM(B64:H64) -> 115.10573 | R64: =('[2]Renewable Diesel'!D73*'[2]RD Feedstock Breakdown'!R$3*'[2]Feedstock Conversion Rates'!B$7)/12 -> 0.76666667 | S64: =R64 -> 0.76666667 | Z64: =('[2]Renewable Diesel'!F73*'[2]RD Feedstock Breakdown'!Z$3*'[2]Feedstock Conversion Rates'!B$6)/12 -> 44.555 | AA64: =('[2]Renewable Diesel'!F73*'[2]RD Feedstock Breakdown'!AA$3*'[2]Feedstock Conversion Rates'!B$7)/12 -> 29.133333 | AB64: =SUM(Y64:AA64) -> 73.688333 | AI64: =('[2]Renewable Diesel'!H73*'[2]RD Feedstock Breakdown'!AI$3*'[2]Feedstock Conversion Rates'!B$6)/12 -> 7.8166667 | AJ64: =AI64+AG64 -> 7.8166667 | DP64: =E64+M64 -> 20.853333 | DQ64: =H64+P64+AZ64+BC64+BK64+BZ64+CL64+CP64+CV64+CX64+DA64+DK64 -> 40.9044 | DR64: =AD64+AK64+AM64+AP64+AV64+AY64+BB64+BF64+BJ64+Y64+B64+BO64+BQ64+BW64+CB64+CE64+CG64+CJ64+BT64+CN64+CR64+CT64+DF64+DH64+AS64+J64+U64+AH64 -> 0 | DT64: =V64+Z64+AE64+AI64+BD64+BL64+AN64+AQ64+CD64+CM64+CQ64+CY64+DB64+DL64 -> 52.371667 | DU64: =G64+O64+R64+AA64+AW64+BH64+BM64+BR64+BU64+BY64 -> 70.748 | DV64: =F64+N64+W64+DM64 -> 12.5 | DW64: =D64+L64 -> 0 | DX64: =SUM(DP64:DW64) -> 197.3774 | DY64: =I64+Q64+S64+X64+AB64+AF64+AJ64+AL64+AO64+AR64+AU64+AX64+BA64+BE64+BG64+BI64+BN64-DX64+BP64+BS64+BV64+CA64+CC64+CF64+CH64+CK64+CO64+CS64+CU64+CW64+CZ64+DN64+DG64+DI64 -> 2.8421709e-14 | EA64: =DP64/$DX64 -> 0.10565208 | EB64: =DQ64/$DX64 -> 0.20723953 | EC64: =DR64/$DX64 -> 0 | EE64: =DT64/$DX64 -> 0.26533771 | EF64: =DU64/$DX64 -> 0.35844023 | EG64: =DV64/$DX64 -> 0.063330452 | EH64: =DW64/DX64 -> 0 | EI64: =SUM(EA64:EG64) -> 1 | EK64: =EA64*'[2]Renewable Diesel'!BF73*'[2]Feedstock Conversion Rates'!B$2 -> 10.347996 | EL64: =EB64*'[2]Renewable Diesel'!BF73*'[2]Feedstock Conversion Rates'!B$3 -> 19.127772 | EM64: =EC64*'[2]Renewable Diesel'!BF73*'[2]Feedstock Conversion Rates'!B$4 -> 0 | EO64: =EE64*'[2]Renewable Diesel'!BF73*'[2]Feedstock Conversion Rates'!B$6 -> 28.678807 | EP64: =EF64*'[2]Renewable Diesel'!BF73*'[2]Feedstock Conversion Rates'!B$7 -> 37.998271 | EQ64: =EG64*'[2]Renewable Diesel'!BF73*'[2]Feedstock Conversion Rates'!B$8 -> 6.8413709 | ER64: =EH64*'[2]Renewable Diesel'!BF73*'[2]Feedstock Conversion Rates'!B$9 -> 0 | ES64: =SUM(EK64:ER64) -> 102.99422
A65: 42401 | D65: 0 | E65: =('[2]Renewable Diesel'!B74*E$3*'[2]Feedstock Conversion Rates'!$B$2)/12 -> 20.853333 | F65: =('[2]Renewable Diesel'!B74*'[2]RD Feedstock Breakdown'!F$3*'[2]Feedstock Conversion Rates'!B$8)/12 -> 12.5 | G65: =('[2]Renewable Diesel'!B74*'[2]RD Feedstock Breakdown'!G$3*'[2]Feedstock Conversion Rates'!B$7)/12 -> 40.848 | H65: =('[2]Renewable Diesel'!B74*'[2]RD Feedstock Breakdown'!H$3*'[2]Feedstock Conversion Rates'!B$3)/12 -> 40.9044 | I65: =SUM(B65:H65) -> 115.10573 | R65: =('[2]Renewable Diesel'!D74*'[2]RD Feedstock Breakdown'!R$3*'[2]Feedstock Conversion Rates'!B$7)/12 -> 1.5333333 | S65: =R65 -> 1.5333333 | Z65: =('[2]Renewable Diesel'!F74*'[2]RD Feedstock Breakdown'!Z$3*'[2]Feedstock Conversion Rates'!B$6)/12 -> 44.555 | AA65: =('[2]Renewable Diesel'!F74*'[2]RD Feedstock Breakdown'!AA$3*'[2]Feedstock Conversion Rates'!B$7)/12 -> 29.133333 | AB65: =SUM(Y65:AA65) -> 73.688333 | AI65: =('[2]Renewable Diesel'!H74*'[2]RD Feedstock Breakdown'!AI$3*'[2]Feedstock Conversion Rates'!B$6)/12 -> 15.633333 | AJ65: =AI65+AG65 -> 15.633333 | DP65: =E65+M65 -> 20.853333 | DQ65: =H65+P65+AZ65+BC65+BK65+BZ65+CL65+CP65+CV65+CX65+DA65+DK65 -> 40.9044 | DR65: =AD65+AK65+AM65+AP65+AV65+AY65+BB65+BF65+BJ65+Y65+B65+BO65+BQ65+BW65+CB65+CE65+CG65+CJ65+BT65+CN65+CR65+CT65+DF65+DH65+AS65+J65+U65+AH65 -> 0 | DT65: =V65+Z65+AE65+AI65+BD65+BL65+AN65+AQ65+CD65+CM65+CQ65+CY65+DB65+DL65 -> 60.188333 | DU65: =G65+O65+R65+AA65+AW65+BH65+BM65+BR65+BU65+BY65 -> 71.514667 | DV65: =F65+N65+W65+DM65 -> 12.5 | DW65: =D65+L65 -> 0 | DX65: =SUM(DP65:DW65) -> 205.96073 | DY65: =I65+Q65+S65+X65+AB65+AF65+AJ65+AL65+AO65+AR65+AU65+AX65+BA65+BE65+BG65+BI65+BN65-DX65+BP65+BS65+BV65+CA65+CC65+CF65+CH65+CK65+CO65+CS65+CU65+CW65+CZ65+DN65+DG65+DI65 -> 0 | EA65: =DP65/$DX65 -> 0.10124907 | EB65: =DQ65/$DX65 -> 0.19860291 | EC65: =DR65/$DX65 -> 0 | EE65: =DT65/$DX65 -> 0.29223208 | EF65: =DU65/$DX65 -> 0.34722476 | EG65: =DV65/$DX65 -> 0.06069118 | EH65: =DW65/DX65 -> 0 | EI65: =SUM(EA65:EG65) -> 1 | EK65: =EA65*'[2]Renewable Diesel'!BF74*'[2]Feedstock Conversion Rates'!B$2 -> 6.0695702 | EL65: =EB65*'[2]Renewable Diesel'!BF74*'[2]Feedstock Conversion Rates'!B$3 -> 11.219308 | EM65: =EC65*'[2]Renewable Diesel'!BF74*'[2]Feedstock Conversion Rates'!B$4 -> 0 | EO65: =EE65*'[2]Renewable Diesel'!BF74*'[2]Feedstock Conversion Rates'!B$6 -> 19.332085 | EP65: =EF65*'[2]Renewable Diesel'!BF74*'[2]Feedstock Conversion Rates'!B$7 -> 22.529237 | EQ65: =EG65*'[2]Renewable Diesel'!BF74*'[2]Feedstock Conversion Rates'!B$8 -> 4.0127751 | ER65: =EH65*'[2]Renewable Diesel'!BF74*'[2]Feedstock Conversion Rates'!B$9 -> 0 | ES65: =SUM(EK65:ER65) -> 63.162975
A66: 42430 | D66: 0 | E66: =('[2]Renewable Diesel'!B75*E$3*'[2]Feedstock Conversion Rates'!$B$2)/12 -> 20.853333 | F66: =('[2]Renewable Diesel'!B75*'[2]RD Feedstock Breakdown'!F$3*'[2]Feedstock Conversion Rates'!B$8)/12 -> 12.5 | G66: =('[2]Renewable Diesel'!B75*'[2]RD Feedstock Breakdown'!G$3*'[2]Feedstock Conversion Rates'!B$7)/12 -> 40.848 | H66: =('[2]Renewable Diesel'!B75*'[2]RD Feedstock Breakdown'!H$3*'[2]Feedstock Conversion Rates'!B$3)/12 -> 40.9044 | I66: =SUM(B66:H66) -> 115.10573 | R66: =('[2]Renewable Diesel'!D75*'[2]RD Feedstock Breakdown'!R$3*'[2]Feedstock Conversion Rates'!B$7)/12 -> 2.3 | S66: =R66 -> 2.3 | Z66: =('[2]Renewable Diesel'!F75*'[2]RD Feedstock Breakdown'!Z$3*'[2]Feedstock Conversion Rates'!B$6)/12 -> 44.555 | AA66: =('[2]Renewable Diesel'!F75*'[2]RD Feedstock Breakdown'!AA$3*'[2]Feedstock Conversion Rates'!B$7)/12 -> 29.133333 | AB66: =SUM(Y66:AA66) -> 73.688333 | AI66: =('[2]Renewable Diesel'!H75*'[2]RD Feedstock Breakdown'!AI$3*'[2]Feedstock Conversion Rates'!B$6)/12 -> 39.083333 | AJ66: =AI66+AG66 -> 39.083333 | DP66: =E66+M66 -> 20.853333 | DQ66: =H66+P66+AZ66+BC66+BK66+BZ66+CL66+CP66+CV66+CX66+DA66+DK66 -> 40.9044 | DR66: =AD66+AK66+AM66+AP66+AV66+AY66+BB66+BF66+BJ66+Y66+B66+BO66+BQ66+BW66+CB66+CE66+CG66+CJ66+BT66+CN66+CR66+CT66+DF66+DH66+AS66+J66+U66+AH66 -> 0 | DT66: =V66+Z66+AE66+AI66+BD66+BL66+AN66+AQ66+CD66+CM66+CQ66+CY66+DB66+DL66 -> 83.638333 | DU66: =G66+O66+R66+AA66+AW66+BH66+BM66+BR66+BU66+BY66 -> 72.281333 | DV66: =F66+N66+W66+DM66 -> 12.5 | DW66: =D66+L66 -> 0 | DX66: =SUM(DP66:DW66) -> 230.1774 | DY66: =I66+Q66+S66+X66+AB66+AF66+AJ66+AL66+AO66+AR66+AU66+AX66+BA66+BE66+BG66+BI66+BN66-DX66+BP66+BS66+BV66+CA66+CC66+CF66+CH66+CK66+CO66+CS66+CU66+CW66+CZ66+DN66+DG66+DI66 -> 0 | EA66: =DP66/$DX66 -> 0.090596789 | EB66: =DQ66/$DX66 -> 0.17770815 | EC66: =DR66/$DX66 -> 0 | EE66: =DT66/$DX66 -> 0.36336466 | EF66: =DU66/$DX66 -> 0.31402446 | EG66: =DV66/$DX66 -> 0.05430594 | EH66: =DW66/DX66 -> 0 | EI66: =SUM(EA66:EG66) -> 1 | EK66: =EA66*'[2]Renewable Diesel'!BF75*'[2]Feedstock Conversion Rates'!B$2 -> 13.454216 | EL66: =EB66*'[2]Renewable Diesel'!BF75*'[2]Feedstock Conversion Rates'!B$3 -> 24.86947 | EM66: =EC66*'[2]Renewable Diesel'!BF75*'[2]Feedstock Conversion Rates'!B$4 -> 0 | EO66: =EE66*'[2]Renewable Diesel'!BF75*'[2]Feedstock Conversion Rates'!B$6 -> 59.548687 | EP66: =EF66*'[2]Renewable Diesel'!BF75*'[2]Feedstock Conversion Rates'!B$7 -> 50.47519 | EQ66: =EG66*'[2]Renewable Diesel'!BF75*'[2]Feedstock Conversion Rates'!B$8 -> 8.8949861 | ER66: =EH66*'[2]Renewable Diesel'!BF75*'[2]Feedstock Conversion Rates'!B$9 -> 0 | ES66: =SUM(EK66:ER66) -> 157.24255
A67: 42461 | D67: 0 | E67: =('[2]Renewable Diesel'!B76*E$3*'[2]Feedstock Conversion Rates'!$B$2)/12 -> 20.853333 | F67: =('[2]Renewable Diesel'!B76*'[2]RD Feedstock Breakdown'!F$3*'[2]Feedstock Conversion Rates'!B$8)/12 -> 12.5 | G67: =('[2]Renewable Diesel'!B76*'[2]RD Feedstock Breakdown'!G$3*'[2]Feedstock Conversion Rates'!B$7)/12 -> 40.848 | H67: =('[2]Renewable Diesel'!B76*'[2]RD Feedstock Breakdown'!H$3*'[2]Feedstock Conversion Rates'!B$3)/12 -> 40.9044 | I67: =SUM(B67:H67) -> 115.10573 | R67: =('[2]Renewable Diesel'!D76*'[2]RD Feedstock Breakdown'!R$3*'[2]Feedstock Conversion Rates'!B$7)/12 -> 2.3 | S67: =R67 -> 2.3 | Z67: =('[2]Renewable Diesel'!F76*'[2]RD Feedstock Breakdown'!Z$3*'[2]Feedstock Conversion Rates'!B$6)/12 -> 44.555 | AA67: =('[2]Renewable Diesel'!F76*'[2]RD Feedstock Breakdown'!AA$3*'[2]Feedstock Conversion Rates'!B$7)/12 -> 29.133333 | AB67: =SUM(Y67:AA67) -> 73.688333 | AI67: =('[2]Renewable Diesel'!H76*'[2]RD Feedstock Breakdown'!AI$3*'[2]Feedstock Conversion Rates'!B$6)/12 -> 39.083333 | AJ67: =AI67+AG67 -> 39.083333 | AK67: =('[2]Renewable Diesel'!J76*'[2]RD Feedstock Breakdown'!AK$3*'[2]Feedstock Conversion Rates'!B$4)/12 -> 15.625 | AL67: =AK67 -> 15.625 | DP67: =E67+M67 -> 20.853333 | DQ67: =H67+P67+AZ67+BC67+BK67+BZ67+CL67+CP67+CV67+CX67+DA67+DK67 -> 40.9044 | DR67: =AD67+AK67+AM67+AP67+AV67+AY67+BB67+BF67+BJ67+Y67+B67+BO67+BQ67+BW67+CB67+CE67+CG67+CJ67+BT67+CN67+CR67+CT67+DF67+DH67+AS67+J67+U67+AH67 -> 15.625 | DT67: =V67+Z67+AE67+AI67+BD67+BL67+AN67+AQ67+CD67+CM67+CQ67+CY67+DB67+DL67 -> 83.638333 | DU67: =G67+O67+R67+AA67+AW67+BH67+BM67+BR67+BU67+BY67 -> 72.281333 | DV67: =F67+N67+W67+DM67 -> 12.5 | DW67: =D67+L67 -> 0 | DX67: =SUM(DP67:DW67) -> 245.8024 | DY67: =I67+Q67+S67+X67+AB67+AF67+AJ67+AL67+AO67+AR67+AU67+AX67+BA67+BE67+BG67+BI67+BN67-DX67+BP67+BS67+BV67+CA67+CC67+CF67+CH67+CK67+CO67+CS67+CU67+CW67+CZ67+DN67+DG67+DI67 -> 0 | EA67: =DP67/$DX67 -> 0.084837794 | EB67: =DQ67/$DX67 -> 0.16641172 | EC67: =DR67/$DX67 -> 0.063567321 | EE67: =DT67/$DX67 -> 0.34026654 | EF67: =DU67/$DX67 -> 0.29406276 | EG67: =DV67/$DX67 -> 0.050853857 | EH67: =DW67/DX67 -> 0 | EI67: =SUM(EA67:EG67) -> 1 | EK67: =EA67*'[2]Renewable Diesel'!BF76*'[2]Feedstock Conversion Rates'!B$2 -> 15.044109 | EL67: =EB67*'[2]Renewable Diesel'!BF76*'[2]Feedstock Conversion Rates'!B$3 -> 27.80831 | EM67: =EC67*'[2]Renewable Diesel'!BF76*'[2]Feedstock Conversion Rates'!B$4 -> 9.9461119 | EO67: =EE67*'[2]Renewable Diesel'!BF76*'[2]Feedstock Conversion Rates'!B$6 -> 66.585591 | EP67: =EF67*'[2]Renewable Diesel'!BF76*'[2]Feedstock Conversion Rates'!B$7 -> 56.439874 | EQ67: =EG67*'[2]Renewable Diesel'!BF76*'[2]Feedstock Conversion Rates'!B$8 -> 9.9461119 | ER67: =EH67*'[2]Renewable Diesel'!BF76*'[2]Feedstock Conversion Rates'!B$9 -> 0 | ES67: =SUM(EK67:ER67) -> 185.77011
A68: 42491 | D68: 0 | E68: =('[2]Renewable Diesel'!B77*E$3*'[2]Feedstock Conversion Rates'!$B$2)/12 -> 20.853333 | F68: =('[2]Renewable Diesel'!B77*'[2]RD Feedstock Breakdown'!F$3*'[2]Feedstock Conversion Rates'!B$8)/12 -> 12.5 | G68: =('[2]Renewable Diesel'!B77*'[2]RD Feedstock Breakdown'!G$3*'[2]Feedstock Conversion Rates'!B$7)/12 -> 40.848 | H68: =('[2]Renewable Diesel'!B77*'[2]RD Feedstock Breakdown'!H$3*'[2]Feedstock Conversion Rates'!B$3)/12 -> 40.9044 | I68: =SUM(B68:H68) -> 115.10573 | R68: =('[2]Renewable Diesel'!D77*'[2]RD Feedstock Breakdown'!R$3*'[2]Feedstock Conversion Rates'!B$7)/12 -> 2.3 | S68: =R68 -> 2.3 | Z68: =('[2]Renewable Diesel'!F77*'[2]RD Feedstock Breakdown'!Z$3*'[2]Feedstock Conversion Rates'!B$6)/12 -> 44.555 | AA68: =('[2]Renewable Diesel'!F77*'[2]RD Feedstock Breakdown'!AA$3*'[2]Feedstock Conversion Rates'!B$7)/12 -> 29.133333 | AB68: =SUM(Y68:AA68) -> 73.688333 | AI68: =('[2]Renewable Diesel'!H77*'[2]RD Feedstock Breakdown'!AI$3*'[2]Feedstock Conversion Rates'!B$6)/12 -> 39.083333 | AJ68: =AI68+AG68 -> 39.083333 | AK68: =('[2]Renewable Diesel'!J77*'[2]RD Feedstock Breakdown'!AK$3*'[2]Feedstock Conversion Rates'!B$4)/12 -> 31.25 | AL68: =AK68 -> 31.25 | DP68: =E68+M68 -> 20.853333 | DQ68: =H68+P68+AZ68+BC68+BK68+BZ68+CL68+CP68+CV68+CX68+DA68+DK68 -> 40.9044 | DR68: =AD68+AK68+AM68+AP68+AV68+AY68+BB68+BF68+BJ68+Y68+B68+BO68+BQ68+BW68+CB68+CE68+CG68+CJ68+BT68+CN68+CR68+CT68+DF68+DH68+AS68+J68+U68+AH68 -> 31.25 | DT68: =V68+Z68+AE68+AI68+BD68+BL68+AN68+AQ68+CD68+CM68+CQ68+CY68+DB68+DL68 -> 83.638333 | DU68: =G68+O68+R68+AA68+AW68+BH68+BM68+BR68+BU68+BY68 -> 72.281333 | DV68: =F68+N68+W68+DM68 -> 12.5 | DW68: =D68+L68 -> 0 | DX68: =SUM(DP68:DW68) -> 261.4274 | DY68: =I68+Q68+S68+X68+AB68+AF68+AJ68+AL68+AO68+AR68+AU68+AX68+BA68+BE68+BG68+BI68+BN68-DX68+BP68+BS68+BV68+CA68+CC68+CF68+CH68+CK68+CO68+CS68+CU68+CW68+CZ68+DN68+DG68+DI68 -> 0 | EA68: =DP68/$DX68 -> 0.079767206 | EB68: =DQ68/$DX68 -> 0.15646562 | EC68: =DR68/$DX68 -> 0.11953605 | EE68: =DT68/$DX68 -> 0.31992948 | EF68: =DU68/$DX68 -> 0.27648721 | EG68: =DV68/$DX68 -> 0.047814422 | EH68: =DW68/DX68 -> 0 | EI68: =SUM(EA68:EG68) -> 1 | EK68: =EA68*'[2]Renewable Diesel'!BF77*'[2]Feedstock Conversion Rates'!B$2 -> 14.661797 | EL68: =EB68*'[2]Renewable Diesel'!BF77*'[2]Feedstock Conversion Rates'!B$3 -> 27.101626 | EM68: =EC68*'[2]Renewable Diesel'!BF77*'[2]Feedstock Conversion Rates'!B$4 -> 19.386709 | EO68: =EE68*'[2]Renewable Diesel'!BF77*'[2]Feedstock Conversion Rates'!B$6 -> 64.893472 | EP68: =EF68*'[2]Renewable Diesel'!BF77*'[2]Feedstock Conversion Rates'!B$7 -> 55.005585 | EQ68: =EG68*'[2]Renewable Diesel'!BF77*'[2]Feedstock Conversion Rates'!B$8 -> 9.6933544 | ER68: =EH68*'[2]Renewable Diesel'!BF77*'[2]Feedstock Conversion Rates'!B$9 -> 0 | ES68: =SUM(EK68:ER68) -> 190.74254
A69: 42522 | D69: 0 | E69: =('[2]Renewable Diesel'!B78*E$3*'[2]Feedstock Conversion Rates'!$B$2)/12 -> 20.853333 | F69: =('[2]Renewable Diesel'!B78*'[2]RD Feedstock Breakdown'!F$3*'[2]Feedstock Conversion Rates'!B$8)/12 -> 12.5 | G69: =('[2]Renewable Diesel'!B78*'[2]RD Feedstock Breakdown'!G$3*'[2]Feedstock Conversion Rates'!B$7)/12 -> 40.848 | H69: =('[2]Renewable Diesel'!B78*'[2]RD Feedstock Breakdown'!H$3*'[2]Feedstock Conversion Rates'!B$3)/12 -> 40.9044 | I69: =SUM(B69:H69) -> 115.10573 | R69: =('[2]Renewable Diesel'!D78*'[2]RD Feedstock Breakdown'!R$3*'[2]Feedstock Conversion Rates'!B$7)/12 -> 2.3 | S69: =R69 -> 2.3 | Z69: =('[2]Renewable Diesel'!F78*'[2]RD Feedstock Breakdown'!Z$3*'[2]Feedstock Conversion Rates'!B$6)/12 -> 44.555 | AA69: =('[2]Renewable Diesel'!F78*'[2]RD Feedstock Breakdown'!AA$3*'[2]Feedstock Conversion Rates'!B$7)/12 -> 29.133333 | AB69: =SUM(Y69:AA69) -> 73.688333 | AI69: =('[2]Renewable Diesel'!H78*'[2]RD Feedstock Breakdown'!AI$3*'[2]Feedstock Conversion Rates'!B$6)/12 -> 39.083333 | AJ69: =AI69+AG69 -> 39.083333 | AK69: =('[2]Renewable Diesel'!J78*'[2]RD Feedstock Breakdown'!AK$3*'[2]Feedstock Conversion Rates'!B$4)/12 -> 62.5 | AL69: =AK69 -> 62.5 | DP69: =E69+M69 -> 20.853333 | DQ69: =H69+P69+AZ69+BC69+BK69+BZ69+CL69+CP69+CV69+CX69+DA69+DK69 -> 40.9044 | DR69: =AD69+AK69+AM69+AP69+AV69+AY69+BB69+BF69+BJ69+Y69+B69+BO69+BQ69+BW69+CB69+CE69+CG69+CJ69+BT69+CN69+CR69+CT69+DF69+DH69+AS69+J69+U69+AH69 -> 62.5 | DT69: =V69+Z69+AE69+AI69+BD69+BL69+AN69+AQ69+CD69+CM69+CQ69+CY69+DB69+DL69 -> 83.638333 | DU69: =G69+O69+R69+AA69+AW69+BH69+BM69+BR69+BU69+BY69 -> 72.281333 | DV69: =F69+N69+W69+DM69 -> 12.5 | DW69: =D69+L69 -> 0 | DX69: =SUM(DP69:DW69) -> 292.6774 | DY69: =I69+Q69+S69+X69+AB69+AF69+AJ69+AL69+AO69+AR69+AU69+AX69+BA69+BE69+BG69+BI69+BN69-DX69+BP69+BS69+BV69+CA69+CC69+CF69+CH69+CK69+CO69+CS69+CU69+CW69+CZ69+DN69+DG69+DI69 -> 0 | EA69: =DP69/$DX69 -> 0.071250234 | EB69: =DQ69/$DX69 -> 0.13975934 | EC69: =DR69/$DX69 -> 0.2135457 | EE69: =DT69/$DX69 -> 0.2857697 | EF69: =DU69/$DX69 -> 0.24696589 | EG69: =DV69/$DX69 -> 0.04270914 | EH69: =DW69/DX69 -> 0 | EI69: =SUM(EA69:EG69) -> 1 | EK69: =EA69*'[2]Renewable Diesel'!BF78*'[2]Feedstock Conversion Rates'!B$2 -> 13.349964 | EL69: =EB69*'[2]Renewable Diesel'!BF78*'[2]Feedstock Conversion Rates'!B$3 -> 24.676764 | EM69: =EC69*'[2]Renewable Diesel'!BF78*'[2]Feedstock Conversion Rates'!B$4 -> 35.304247 | EO69: =EE69*'[2]Renewable Diesel'!BF78*'[2]Feedstock Conversion Rates'!B$6 -> 59.087264 | EP69: =EF69*'[2]Renewable Diesel'!BF78*'[2]Feedstock Conversion Rates'!B$7 -> 50.084074 | EQ69: =EG69*'[2]Renewable Diesel'!BF78*'[2]Feedstock Conversion Rates'!B$8 -> 8.8260617 | ER69: =EH69*'[2]Renewable Diesel'!BF78*'[2]Feedstock Conversion Rates'!B$9 -> 0 | ES69: =SUM(EK69:ER69) -> 191.32837
A70: 42552 | D70: 0 | E70: =('[2]Renewable Diesel'!B79*E$3*'[2]Feedstock Conversion Rates'!$B$2)/12 -> 20.853333 | F70: =('[2]Renewable Diesel'!B79*'[2]RD Feedstock Breakdown'!F$3*'[2]Feedstock Conversion Rates'!B$8)/12 -> 12.5 | G70: =('[2]Renewable Diesel'!B79*'[2]RD Feedstock Breakdown'!G$3*'[2]Feedstock Conversion Rates'!B$7)/12 -> 40.848 | H70: =('[2]Renewable Diesel'!B79*'[2]RD Feedstock Breakdown'!H$3*'[2]Feedstock Conversion Rates'!B$3)/12 -> 40.9044 | I70: =SUM(B70:H70) -> 115.10573 | R70: =('[2]Renewable Diesel'!D79*'[2]RD Feedstock Breakdown'!R$3*'[2]Feedstock Conversion Rates'!B$7)/12 -> 2.3 | S70: =R70 -> 2.3 | Z70: =('[2]Renewable Diesel'!F79*'[2]RD Feedstock Breakdown'!Z$3*'[2]Feedstock Conversion Rates'!B$6)/12 -> 44.555 | AA70: =('[2]Renewable Diesel'!F79*'[2]RD Feedstock Breakdown'!AA$3*'[2]Feedstock Conversion Rates'!B$7)/12 -> 29.133333 | AB70: =SUM(Y70:AA70) -> 73.688333 | AI70: =('[2]Renewable Diesel'!H79*'[2]RD Feedstock Breakdown'!AI$3*'[2]Feedstock Conversion Rates'!B$6)/12 -> 39.083333 | AJ70: =AI70+AG70 -> 39.083333 | AK70: =('[2]Renewable Diesel'!J79*'[2]RD Feedstock Breakdown'!AK$3*'[2]Feedstock Conversion Rates'!B$4)/12 -> 62.5 | AL70: =AK70 -> 62.5 | DP70: =E70+M70 -> 20.853333 | DQ70: =H70+P70+AZ70+BC70+BK70+BZ70+CL70+CP70+CV70+CX70+DA70+DK70 -> 40.9044 | DR70: =AD70+AK70+AM70+AP70+AV70+AY70+BB70+BF70+BJ70+Y70+B70+BO70+BQ70+BW70+CB70+CE70+CG70+CJ70+BT70+CN70+CR70+CT70+DF70+DH70+AS70+J70+U70+AH70 -> 62.5 | DT70: =V70+Z70+AE70+AI70+BD70+BL70+AN70+AQ70+CD70+CM70+CQ70+CY70+DB70+DL70 -> 83.638333 | DU70: =G70+O70+R70+AA70+AW70+BH70+BM70+BR70+BU70+BY70 -> 72.281333 | DV70: =F70+N70+W70+DM70 -> 12.5 | DW70: =D70+L70 -> 0 | DX70: =SUM(DP70:DW70) -> 292.6774 | DY70: =I70+Q70+S70+X70+AB70+AF70+AJ70+AL70+AO70+AR70+AU70+AX70+BA70+BE70+BG70+BI70+BN70-DX70+BP70+BS70+BV70+CA70+CC70+CF70+CH70+CK70+CO70+CS70+CU70+CW70+CZ70+DN70+DG70+DI70 -> 0 | EA70: =DP70/$DX70 -> 0.071250234 | EB70: =DQ70/$DX70 -> 0.13975934 | EC70: =DR70/$DX70 -> 0.2135457 | EE70: =DT70/$DX70 -> 0.2857697 | EF70: =DU70/$DX70 -> 0.24696589 | EG70: =DV70/$DX70 -> 0.04270914 | EH70: =DW70/DX70 -> 0 | EI70: =SUM(EA70:EG70) -> 1 | EK70: =EA70*'[2]Renewable Diesel'!BF79*'[2]Feedstock Conversion Rates'!B$2 -> 11.564335 | EL70: =EB70*'[2]Renewable Diesel'!BF79*'[2]Feedstock Conversion Rates'!B$3 -> 21.376117 | EM70: =EC70*'[2]Renewable Diesel'!BF79*'[2]Feedstock Conversion Rates'!B$4 -> 30.582117 | EO70: =EE70*'[2]Renewable Diesel'!BF79*'[2]Feedstock Conversion Rates'!B$6 -> 51.18403 | EP70: =EF70*'[2]Renewable Diesel'!BF79*'[2]Feedstock Conversion Rates'!B$7 -> 43.385065 | EQ70: =EG70*'[2]Renewable Diesel'!BF79*'[2]Feedstock Conversion Rates'!B$8 -> 7.6455293 | ER70: =EH70*'[2]Renewable Diesel'!BF79*'[2]Feedstock Conversion Rates'!B$9 -> 0 | ES70: =SUM(EK70:ER70) -> 165.73719
A71: 42583 | D71: 0 | E71: =('[2]Renewable Diesel'!B80*E$3*'[2]Feedstock Conversion Rates'!$B$2)/12 -> 20.853333 | F71: =('[2]Renewable Diesel'!B80*'[2]RD Feedstock Breakdown'!F$3*'[2]Feedstock Conversion Rates'!B$8)/12 -> 12.5 | G71: =('[2]Renewable Diesel'!B80*'[2]RD Feedstock Breakdown'!G$3*'[2]Feedstock Conversion Rates'!B$7)/12 -> 40.848 | H71: =('[2]Renewable Diesel'!B80*'[2]RD Feedstock Breakdown'!H$3*'[2]Feedstock Conversion Rates'!B$3)/12 -> 40.9044 | I71: =SUM(B71:H71) -> 115.10573 | R71: =('[2]Renewable Diesel'!D80*'[2]RD Feedstock Breakdown'!R$3*'[2]Feedstock Conversion Rates'!B$7)/12 -> 2.3 | S71: =R71 -> 2.3 | Z71: =('[2]Renewable Diesel'!F80*'[2]RD Feedstock Breakdown'!Z$3*'[2]Feedstock Conversion Rates'!B$6)/12 -> 44.555 | AA71: =('[2]Renewable Diesel'!F80*'[2]RD Feedstock Breakdown'!AA$3*'[2]Feedstock Conversion Rates'!B$7)/12 -> 29.133333 | AB71: =SUM(Y71:AA71) -> 73.688333 | AI71: =('[2]Renewable Diesel'!H80*'[2]RD Feedstock Breakdown'!AI$3*'[2]Feedstock Conversion Rates'!B$6)/12 -> 39.083333 | AJ71: =AI71+AG71 -> 39.083333 | AK71: =('[2]Renewable Diesel'!J80*'[2]RD Feedstock Breakdown'!AK$3*'[2]Feedstock Conversion Rates'!B$4)/12 -> 62.5 | AL71: =AK71 -> 62.5 | DP71: =E71+M71 -> 20.853333 | DQ71: =H71+P71+AZ71+BC71+BK71+BZ71+CL71+CP71+CV71+CX71+DA71+DK71 -> 40.9044 | DR71: =AD71+AK71+AM71+AP71+AV71+AY71+BB71+BF71+BJ71+Y71+B71+BO71+BQ71+BW71+CB71+CE71+CG71+CJ71+BT71+CN71+CR71+CT71+DF71+DH71+AS71+J71+U71+AH71 -> 62.5 | DT71: =V71+Z71+AE71+AI71+BD71+BL71+AN71+AQ71+CD71+CM71+CQ71+CY71+DB71+DL71 -> 83.638333 | DU71: =G71+O71+R71+AA71+AW71+BH71+BM71+BR71+BU71+BY71 -> 72.281333 | DV71: =F71+N71+W71+DM71 -> 12.5 | DW71: =D71+L71 -> 0 | DX71: =SUM(DP71:DW71) -> 292.6774 | DY71: =I71+Q71+S71+X71+AB71+AF71+AJ71+AL71+AO71+AR71+AU71+AX71+BA71+BE71+BG71+BI71+BN71-DX71+BP71+BS71+BV71+CA71+CC71+CF71+CH71+CK71+CO71+CS71+CU71+CW71+CZ71+DN71+DG71+DI71 -> 0 | EA71: =DP71/$DX71 -> 0.071250234 | EB71: =DQ71/$DX71 -> 0.13975934 | EC71: =DR71/$DX71 -> 0.2135457 | EE71: =DT71/$DX71 -> 0.2857697 | EF71: =DU71/$DX71 -> 0.24696589 | EG71: =DV71/$DX71 -> 0.04270914 | EH71: =DW71/DX71 -> 0 | EI71: =SUM(EA71:EG71) -> 1 | EK71: =EA71*'[2]Renewable Diesel'!BF80*'[2]Feedstock Conversion Rates'!B$2 -> 14.731967 | EL71: =EB71*'[2]Renewable Diesel'!BF80*'[2]Feedstock Conversion Rates'!B$3 -> 27.231331 | EM71: =EC71*'[2]Renewable Diesel'!BF80*'[2]Feedstock Conversion Rates'!B$4 -> 38.958982 | EO71: =EE71*'[2]Renewable Diesel'!BF80*'[2]Feedstock Conversion Rates'!B$6 -> 65.204044 | EP71: =EF71*'[2]Renewable Diesel'!BF80*'[2]Feedstock Conversion Rates'!B$7 -> 55.268834 | EQ71: =EG71*'[2]Renewable Diesel'!BF80*'[2]Feedstock Conversion Rates'!B$8 -> 9.7397455 | ER71: =EH71*'[2]Renewable Diesel'!BF80*'[2]Feedstock Conversion Rates'!B$9 -> 0 | ES71: =SUM(EK71:ER71) -> 211.1349
A72: 42614 | D72: 0 | E72: =('[2]Renewable Diesel'!B81*E$3*'[2]Feedstock Conversion Rates'!$B$2)/12 -> 20.853333 | F72: =('[2]Renewable Diesel'!B81*'[2]RD Feedstock Breakdown'!F$3*'[2]Feedstock Conversion Rates'!B$8)/12 -> 12.5 | G72: =('[2]Renewable Diesel'!B81*'[2]RD Feedstock Breakdown'!G$3*'[2]Feedstock Conversion Rates'!B$7)/12 -> 40.848 | H72: =('[2]Renewable Diesel'!B81*'[2]RD Feedstock Breakdown'!H$3*'[2]Feedstock Conversion Rates'!B$3)/12 -> 40.9044 | I72: =SUM(B72:H72) -> 115.10573 | R72: =('[2]Renewable Diesel'!D81*'[2]RD Feedstock Breakdown'!R$3*'[2]Feedstock Conversion Rates'!B$7)/12 -> 2.3 | S72: =R72 -> 2.3 | Z72: =('[2]Renewable Diesel'!F81*'[2]RD Feedstock Breakdown'!Z$3*'[2]Feedstock Conversion Rates'!B$6)/12 -> 44.555 | AA72: =('[2]Renewable Diesel'!F81*'[2]RD Feedstock Breakdown'!AA$3*'[2]Feedstock Conversion Rates'!B$7)/12 -> 29.133333 | AB72: =SUM(Y72:AA72) -> 73.688333 | AI72: =('[2]Renewable Diesel'!H81*'[2]RD Feedstock Breakdown'!AI$3*'[2]Feedstock Conversion Rates'!B$6)/12 -> 39.083333 | AJ72: =AI72+AG72 -> 39.083333 | AK72: =('[2]Renewable Diesel'!J81*'[2]RD Feedstock Breakdown'!AK$3*'[2]Feedstock Conversion Rates'!B$4)/12 -> 62.5 | AL72: =AK72 -> 62.5 | DP72: =E72+M72 -> 20.853333 | DQ72: =H72+P72+AZ72+BC72+BK72+BZ72+CL72+CP72+CV72+CX72+DA72+DK72 -> 40.9044 | DR72: =AD72+AK72+AM72+AP72+AV72+AY72+BB72+BF72+BJ72+Y72+B72+BO72+BQ72+BW72+CB72+CE72+CG72+CJ72+BT72+CN72+CR72+CT72+DF72+DH72+AS72+J72+U72+AH72 -> 62.5 | DT72: =V72+Z72+AE72+AI72+BD72+BL72+AN72+AQ72+CD72+CM72+CQ72+CY72+DB72+DL72 -> 83.638333 | DU72: =G72+O72+R72+AA72+AW72+BH72+BM72+BR72+BU72+BY72 -> 72.281333 | DV72: =F72+N72+W72+DM72 -> 12.5 | DW72: =D72+L72 -> 0 | DX72: =SUM(DP72:DW72) -> 292.6774 | DY72: =I72+Q72+S72+X72+AB72+AF72+AJ72+AL72+AO72+AR72+AU72+AX72+BA72+BE72+BG72+BI72+BN72-DX72+BP72+BS72+BV72+CA72+CC72+CF72+CH72+CK72+CO72+CS72+CU72+CW72+CZ72+DN72+DG72+DI72 -> 0 | EA72: =DP72/$DX72 -> 0.071250234 | EB72: =DQ72/$DX72 -> 0.13975934 | EC72: =DR72/$DX72 -> 0.2135457 | EE72: =DT72/$DX72 -> 0.2857697 | EF72: =DU72/$DX72 -> 0.24696589 | EG72: =DV72/$DX72 -> 0.04270914 | EH72: =DW72/DX72 -> 0 | EI72: =SUM(EA72:EG72) -> 1 | EK72: =EA72*'[2]Renewable Diesel'!BF81*'[2]Feedstock Conversion Rates'!B$2 -> 11.562221 | EL72: =EB72*'[2]Renewable Diesel'!BF81*'[2]Feedstock Conversion Rates'!B$3 -> 21.372209 | EM72: =EC72*'[2]Renewable Diesel'!BF81*'[2]Feedstock Conversion Rates'!B$4 -> 30.576526 | EO72: =EE72*'[2]Renewable Diesel'!BF81*'[2]Feedstock Conversion Rates'!B$6 -> 51.174672 | EP72: =EF72*'[2]Renewable Diesel'!BF81*'[2]Feedstock Conversion Rates'!B$7 -> 43.377133 | EQ72: =EG72*'[2]Renewable Diesel'!BF81*'[2]Feedstock Conversion Rates'!B$8 -> 7.6441315 | ER72: =EH72*'[2]Renewable Diesel'!BF81*'[2]Feedstock Conversion Rates'!B$9 -> 0 | ES72: =SUM(EK72:ER72) -> 165.70689
A73: 42644 | D73: 0 | E73: =('[2]Renewable Diesel'!B82*E$3*'[2]Feedstock Conversion Rates'!$B$2)/12 -> 20.853333 | F73: =('[2]Renewable Diesel'!B82*'[2]RD Feedstock Breakdown'!F$3*'[2]Feedstock Conversion Rates'!B$8)/12 -> 12.5 | G73: =('[2]Renewable Diesel'!B82*'[2]RD Feedstock Breakdown'!G$3*'[2]Feedstock Conversion Rates'!B$7)/12 -> 40.848 | H73: =('[2]Renewable Diesel'!B82*'[2]RD Feedstock Breakdown'!H$3*'[2]Feedstock Conversion Rates'!B$3)/12 -> 40.9044 | I73: =SUM(B73:H73) -> 115.10573 | R73: =('[2]Renewable Diesel'!D82*'[2]RD Feedstock Breakdown'!R$3*'[2]Feedstock Conversion Rates'!B$7)/12 -> 2.3 | S73: =R73 -> 2.3 | Z73: =('[2]Renewable Diesel'!F82*'[2]RD Feedstock Breakdown'!Z$3*'[2]Feedstock Conversion Rates'!B$6)/12 -> 44.555 | AA73: =('[2]Renewable Diesel'!F82*'[2]RD Feedstock Breakdown'!AA$3*'[2]Feedstock Conversion Rates'!B$7)/12 -> 29.133333 | AB73: =SUM(Y73:AA73) -> 73.688333 | AI73: =('[2]Renewable Diesel'!H82*'[2]RD Feedstock Breakdown'!AI$3*'[2]Feedstock Conversion Rates'!B$6)/12 -> 39.083333 | AJ73: =AI73+AG73 -> 39.083333 | AK73: =('[2]Renewable Diesel'!J82*'[2]RD Feedstock Breakdown'!AK$3*'[2]Feedstock Conversion Rates'!B$4)/12 -> 62.5 | AL73: =AK73 -> 62.5 | DP73: =E73+M73 -> 20.853333 | DQ73: =H73+P73+AZ73+BC73+BK73+BZ73+CL73+CP73+CV73+CX73+DA73+DK73 -> 40.9044 | DR73: =AD73+AK73+AM73+AP73+AV73+AY73+BB73+BF73+BJ73+Y73+B73+BO73+BQ73+BW73+CB73+CE73+CG73+CJ73+BT73+CN73+CR73+CT73+DF73+DH73+AS73+J73+U73+AH73 -> 62.5 | DT73: =V73+Z73+AE73+AI73+BD73+BL73+AN73+AQ73+CD73+CM73+CQ73+CY73+DB73+DL73 -> 83.638333 | DU73: =G73+O73+R73+AA73+AW73+BH73+BM73+BR73+BU73+BY73 -> 72.281333 | DV73: =F73+N73+W73+DM73 -> 12.5 | DW73: =D73+L73 -> 0 | DX73: =SUM(DP73:DW73) -> 292.6774 | DY73: =I73+Q73+S73+X73+AB73+AF73+AJ73+AL73+AO73+AR73+AU73+AX73+BA73+BE73+BG73+BI73+BN73-DX73+BP73+BS73+BV73+CA73+CC73+CF73+CH73+CK73+CO73+CS73+CU73+CW73+CZ73+DN73+DG73+DI73 -> 0 | EA73: =DP73/$DX73 -> 0.071250234 | EB73: =DQ73/$DX73 -> 0.13975934 | EC73: =DR73/$DX73 -> 0.2135457 | EE73: =DT73/$DX73 -> 0.2857697 | EF73: =DU73/$DX73 -> 0.24696589 | EG73: =DV73/$DX73 -> 0.04270914 | EH73: =DW73/DX73 -> 0 | EI73: =SUM(EA73:EG73) -> 1 | EK73: =EA73*'[2]Renewable Diesel'!BF82*'[2]Feedstock Conversion Rates'!B$2 -> 12.287952 | EL73: =EB73*'[2]Renewable Diesel'!BF82*'[2]Feedstock Conversion Rates'!B$3 -> 22.713688 | EM73: =EC73*'[2]Renewable Diesel'!BF82*'[2]Feedstock Conversion Rates'!B$4 -> 32.495737 | EO73: =EE73*'[2]Renewable Diesel'!BF82*'[2]Feedstock Conversion Rates'!B$6 -> 54.386776 | EP73: =EF73*'[2]Renewable Diesel'!BF82*'[2]Feedstock Conversion Rates'!B$7 -> 46.099805 | EQ73: =EG73*'[2]Renewable Diesel'!BF82*'[2]Feedstock Conversion Rates'!B$8 -> 8.1239342 | ER73: =EH73*'[2]Renewable Diesel'!BF82*'[2]Feedstock Conversion Rates'!B$9 -> 0 | ES73: =SUM(EK73:ER73) -> 176.10789
A74: 42675 | D74: 0 | E74: =('[2]Renewable Diesel'!B83*E$3*'[2]Feedstock Conversion Rates'!$B$2)/12 -> 20.853333 | F74: =('[2]Renewable Diesel'!B83*'[2]RD Feedstock Breakdown'!F$3*'[2]Feedstock Conversion Rates'!B$8)/12 -> 12.5 | G74: =('[2]Renewable Diesel'!B83*'[2]RD Feedstock Breakdown'!G$3*'[2]Feedstock Conversion Rates'!B$7)/12 -> 40.848 | H74: =('[2]Renewable Diesel'!B83*'[2]RD Feedstock Breakdown'!H$3*'[2]Feedstock Conversion Rates'!B$3)/12 -> 40.9044 | I74: =SUM(B74:H74) -> 115.10573 | R74: =('[2]Renewable Diesel'!D83*'[2]RD Feedstock Breakdown'!R$3*'[2]Feedstock Conversion Rates'!B$7)/12 -> 2.3 | S74: =R74 -> 2.3 | Z74: =('[2]Renewable Diesel'!F83*'[2]RD Feedstock Breakdown'!Z$3*'[2]Feedstock Conversion Rates'!B$6)/12 -> 44.555 | AA74: =('[2]Renewable Diesel'!F83*'[2]RD Feedstock Breakdown'!AA$3*'[2]Feedstock Conversion Rates'!B$7)/12 -> 29.133333 | AB74: =SUM(Y74:AA74) -> 73.688333 | AI74: =('[2]Renewable Diesel'!H83*'[2]RD Feedstock Breakdown'!AI$3*'[2]Feedstock Conversion Rates'!B$6)/12 -> 39.083333 | AJ74: =AI74+AG74 -> 39.083333 | AK74: =('[2]Renewable Diesel'!J83*'[2]RD Feedstock Breakdown'!AK$3*'[2]Feedstock Conversion Rates'!B$4)/12 -> 62.5 | AL74: =AK74 -> 62.5 | DP74: =E74+M74 -> 20.853333 | DQ74: =H74+P74+AZ74+BC74+BK74+BZ74+CL74+CP74+CV74+CX74+DA74+DK74 -> 40.9044 | DR74: =AD74+AK74+AM74+AP74+AV74+AY74+BB74+BF74+BJ74+Y74+B74+BO74+BQ74+BW74+CB74+CE74+CG74+CJ74+BT74+CN74+CR74+CT74+DF74+DH74+AS74+J74+U74+AH74 -> 62.5 | DT74: =V74+Z74+AE74+AI74+BD74+BL74+AN74+AQ74+CD74+CM74+CQ74+CY74+DB74+DL74 -> 83.638333 | DU74: =G74+O74+R74+AA74+AW74+BH74+BM74+BR74+BU74+BY74 -> 72.281333 | DV74: =F74+N74+W74+DM74 -> 12.5 | DW74: =D74+L74 -> 0 | DX74: =SUM(DP74:DW74) -> 292.6774 | DY74: =I74+Q74+S74+X74+AB74+AF74+AJ74+AL74+AO74+AR74+AU74+AX74+BA74+BE74+BG74+BI74+BN74-DX74+BP74+BS74+BV74+CA74+CC74+CF74+CH74+CK74+CO74+CS74+CU74+CW74+CZ74+DN74+DG74+DI74 -> 0 | EA74: =DP74/$DX74 -> 0.071250234 | EB74: =DQ74/$DX74 -> 0.13975934 | EC74: =DR74/$DX74 -> 0.2135457 | EE74: =DT74/$DX74 -> 0.2857697 | EF74: =DU74/$DX74 -> 0.24696589 | EG74: =DV74/$DX74 -> 0.04270914 | EH74: =DW74/DX74 -> 0 | EI74: =SUM(EA74:EG74) -> 1 | EK74: =EA74*'[2]Renewable Diesel'!BF83*'[2]Feedstock Conversion Rates'!B$2 -> 16.455311 | EL74: =EB74*'[2]Renewable Diesel'!BF83*'[2]Feedstock Conversion Rates'!B$3 -> 30.416848 | EM74: =EC74*'[2]Renewable Diesel'!BF83*'[2]Feedstock Conversion Rates'!B$4 -> 43.516399 | EO74: =EE74*'[2]Renewable Diesel'!BF83*'[2]Feedstock Conversion Rates'!B$6 -> 72.831605 | EP74: =EF74*'[2]Renewable Diesel'!BF83*'[2]Feedstock Conversion Rates'!B$7 -> 61.734176 | EQ74: =EG74*'[2]Renewable Diesel'!BF83*'[2]Feedstock Conversion Rates'!B$8 -> 10.8791 | ER74: =EH74*'[2]Renewable Diesel'!BF83*'[2]Feedstock Conversion Rates'!B$9 -> 0 | ES74: =SUM(EK74:ER74) -> 235.83344
