Workbook
Name Quarter: '[6]Formula Inputs'!#REF!

Sheet Source Data
A1: Statistics Canada Renewable Fuel Plant Statistics, Supply and Disposition
A3: ** Use ending stocks data as preliminary estimate for current month and replace with beginning stocks data from subsequent report.
A7: Adjusted Report

Sheet Data
B1: Production | E1: Shipments | H1: Losses and Adjustments | K1: Ending Stocks | N1: Trade | R1: Feedstock Receipts | U1: Feedstock Used in Production | X1: Co-Product Production | AB1: Co-Product Shipments | AE1: Feedstock/Co-Products Ending Stocks | AN1: Loss/Adjustments
B2: Renewable fuels | C2: Fuel ethanol | D2: Renewable fuels except fuel ethanol | E2: Renewable fuels, total | F2: Fuel ethanol | G2: Renewable fuels except fuel ethanol | H2: Renewable fuels, total | I2: Fuel ethanol | J2: Renewable fuels except fuel ethanol | K2: Renewable fuels, total | L2: Fuel ethanol | M2: Renewable fuels except fuel ethanol | N2: Ethanol Imports | O2: Ethanol Exports | P2: Biodiesel Imports | Q2: Biodiesel Exports | R2: Cereal Grains | S2: Vegetable Oils | T2: Other Renewable Feedstocks | U2: Cereal Grains | V2: Vegetable Oils | W2: Other Renewable Feedstock | X2: Renewable fuel plant co-products, total | Y2: Distillers grains | Z2: Renewable fuel plant co-products except distillers grains | AA2: Other co-products | AB2: Renewable fuel plant co-products | AC2: Distillers grains | AD2: Renewable fuel plant co-products except distillers grains | AE2: Cereal grains | AF2: Vegetable oils | AG2: Other renewable fuel plant feedstocks | AH2: Renewable fuel plant co-products, total | AI2: Distillers grains, total | AJ2: Renewable fuel plant co-products except distillers grains | AK2: eth_can_bsto | AL2: eth_can_prod | AM2: eth_can_impo | AN2: Cereal grains | AO2: Vegetable oils | AP2: Other renewable fuel plant feedstocks
A3: 43831 | B3: 196779 | C3: 158166 | D3: 38613 | E3: 194345 | F3: 160038 | G3: 34307 | H3: -531 | I3: -216 | J3: -315 | K3: 28205 | L3: 16878 | M3: 11327 | N3: 94908.617 | O3: 7426.356 | P3: 34120 | Q3: 26447 | R3: 398535 | S3: 27984 | T3: 9231 | U3: 378741 | V3: 27402 | W3: 9388 | X3: 138343 | Y3: 125292 | Z3: 12689 | AA3: =X3-Y3-Z3 -> 362 | AB3: 145659 | AC3: 131008 | AD3: 13978 | AE3: 137947 | AF3: 1158 | AG3: 3145 | AH3: 12044 | AI3: 9005 | AJ3: 2706 | AK3: 18534 | AL3: 158166 | AN3: -529 | AO3: 25 | AP3: -17
A4: 43862 | B4: 185483 | C4: 149497 | D4: 35986 | E4: 184445 | F4: 149754 | G4: 34691 | H4: 322 | I4: 256 | J4: 66 | K4: 28931 | L4: 16688 | M4: 12243 | N4: 112277.58 | O4: 5814.774 | P4: 21916 | Q4: 29236 | R4: 353506 | S4: 26051 | T4: 8103 | U4: 364425 | V4: 26020 | W4: 8753 | X4: 127961 | Y4: 117402 | Z4: 9435 | AA4: =X4-Y4-Z4 -> 1124 | AB4: 124247 | AC4: 113438 | AD4: 9837 | AE4: 104808 | AF4: 1189 | AG4: 2651 | AH4: 17003 | AI4: 13271 | AJ4: 2935 | AK4: 17126 | AL4: 149497 | AN4: -38 | AO4: 0 | AP4: 16
A5: 43891 | B5: 179660 | C5: 147191 | D5: 32469 | E5: 177722 | F5: 143033 | G5: 34689 | H5: -1226 | I5: -1269 | J5: 43 | K5: 33400 | L5: 22467 | M5: 10933 | N5: 110572.91 | O5: 12713.091 | P5: 29616 | Q5: 27373 | R5: 373750 | S5: 20897 | T5: 10456 | U5: 358112 | V5: 20715 | W5: 10108 | X5: 183942 | Y5: 118072 | Z5: 64746 | AA5: =X5-Y5-Z5 -> 1124 | AB5: 190413 | AC5: 122673 | AD5: 66768 | AE5: 117759 | AF5: 1371 | AG5: 3374 | AH5: 11255 | AI5: 8029 | AJ5: 2429 | AK5: 16945 | AL5: 147191 | AN5: -2265 | AO5: 0 | AP5: -165
A6: 43922 | B6: 120718 | C6: 85451 | D6: 35267 | E6: 120175 | F6: 82274 | G6: 37901 | H6: 109 | I6: 66 | J6: 43 | K6: 36317 | L6: 25673 | M6: 10644 | N6: 53356.275 | O6: 4930.68 | P6: 67499 | Q6: 32180 | R6: 217699 | S6: 27453 | T6: 7557 | U6: 230969 | V6: 27255 | W6: 8047 | X6: 91794 | Y6: 75875 | Z6: 14153 | AA6: =X6-Y6-Z6 -> 1766 | AB6: 98190 | AC6: 79766 | AD6: 16217 | AE6: 104383 | AF6: 1569 | AG6: 3246 | AH6: 7275 | AI6: 4124 | AJ6: 2795 | AK6: 22467 | AL6: 85451 | AN6: 106 | AO6: 0 | AP6: -146
A7: 43952 | B7: 128789 | C7: 88331 | D7: 40458 | E7: 138982 | F7: 95645 | G7: 43337 | H7: -11 | I7: -72 | J7: 61 | K7: 29093 | L7: 18492 | M7: 10601 | N7: 68132.247 | O7: 15642.688 | P7: 78563 | Q7: 36405 | R7: 211810 | S7: 30366 | T7: 7792 | U7: 225932 | V7: 30777 | W7: 8666 | X7: 77852 | Y7: 67378 | Z7: 8544 | AA7: =X7-Y7-Z7 -> 1930 | AB7: 77161 | AC7: 66100 | AD7: 9122 | AE7: 91104 | AF7: 1158 | AG7: 2695 | AH7: 14670 | AI7: 11076 | AJ7: 3247 | AK7: 25673 | AL7: 88331 | AN7: -1451 | AO7: 0 | AP7: -327
A8: 43983 | B8: 167467 | C8: 129908 | D8: 37559 | E8: 168495 | F8: 128724 | G8: 39771 | H8: 240 | I8: 315 | J8: -75 | K8: 30786 | L8: 19373 | M8: 11413 | N8: 111304.13 | O8: 16964.847 | P8: 72714 | Q8: 32326 | R8: 337486 | S8: 27864 | T8: 10810 | U8: 318577 | V8: 28136 | W8: 9254 | X8: 115571 | Y8: 103386 | Z8: 10716 | AA8: =X8-Y8-Z8 -> 1469 | AB8: 117361 | AC8: 102469 | AD8: 13209 | AE8: 89969 | AF8: 886 | AG8: 4071 | AH8: 13666 | AI8: 11161 | AJ8: 2372 | AK8: 18492 | AL8: 129908 | AN8: -712 | AO8: 0 | AP8: 20
A9: 44013 | B9: 196548 | C9: 150008 | D9: 46540 | E9: 198451 | F9: 149814 | G9: 48637 | H9: 251 | I9: 211 | J9: 40 | K9: 31188 | L9: 19389 | M9: 11799 | N9: 117285.9 | O9: 15926.055 | P9: 50027 | Q9: 39141 | R9: 378781 | S9: 35225 | T9: 15312 | U9: 371659 | V9: 35169 | W9: 13804 | X9: 136315 | Y9: 120928 | Z9: 13615 | AA9: =X9-Y9-Z9 -> 1772 | AB9: 139078 | AC9: 123650 | AD9: 13984 | AE9: 94652 | AF9: 942 | AG9: 4003 | AH9: 11016 | AI9: 7532 | AJ9: 3023 | AK9: 19380 | AL9: 150008 | AN9: 2439 | AO9: 0 | AP9: 1570
A10: 44044 | B10: 183950 | C10: 146424 | D10: 37526 | E10: 186344 | F10: 145546 | G10: 40798 | H10: 253 | I10: 175 | J10: 78 | K10: 30791 | L10: 20127 | M10: 10664 | N10: 138643.58 | O10: 5705.319 | P10: 70569 | Q10: 37440 | R10: 357568 | S10: 23611 | T10: 14014 | U10: 360641 | V10: 23555 | W10: 12296 | X10: 126666 | Y10: 114377 | Z10: 12289 | AA10: =X10-Y10-Z10 -> 0 | AB10: 123815 | AC10: 109960 | AD10: 13855 | AE10: 91674 | AF10: 998 | AG10: 4902 | AH10: 15238 | AI10: 11485 | AJ10: 3753 | AK10: 19389 | AL10: 146424 | AN10: -95 | AO10: 0 | AP10: 789
A11: 44075 | B11: 170448 | C11: 134745 | D11: 35703 | E11: 173784 | F11: 137427 | G11: 36357 | H11: 2117 | I11: 354 | J11: 1763 | K11: 27441 | L11: 17134 | M11: 10307 | N11: 123555.01 | O11: 19069.946 | P11: 68116 | Q11: 32930 | R11: 338582 | S11: 26390 | T11: 11064 | U11: 326873 | V11: 26715 | W11: 10899 | X11: 113981 | Y11: 104546 | Z11: 9435 | AA11: =X11-Y11-Z11 -> 0 | AB11: 123151 | AC11: 110420 | AD11: 12731 | AE11: 102713 | AF11: 673 | AG11: 4342 | AH11: 10252 | AI11: 7406 | AJ11: 2846 | AK11: 20127 | AL11: 134745 | AN11: 670 | AO11: 0 | AP11: 841
A12: 44105 | B12: 176267 | C12: 139203 | D12: 37064 | E12: 177884 | F12: 138374 | G12: 39510 | H12: 356 | I12: 283 | J12: 73 | K12: 26043 | L12: 17714 | M12: 8329 | N12: 135922.41 | O12: 17988.743 | P12: 12195 | Q12: 34438 | R12: 296525 | S12: 26908 | T12: 10854 | U12: 325261 | V12: 26569 | W12: 10929 | X12: 120390 | Y12: 109318 | Z12: 11072 | AA12: =X12-Y12-Z12 -> 0 | AB12: 120149 | AC12: 107577 | AD12: 12572 | AE12: 74903 | AF12: 1012 | AG12: 3577 | AH12: 10328 | AI12: 6849 | AJ12: 3479 | AK12: 17134 | AL12: 139203 | AN12: -926 | AO12: 0 | AP12: 884
A13: 44136 | B13: 199116 | C13: 155234 | D13: 43882 | E13: 190125 | F13: 149425 | G13: 40700 | H13: 413 | I13: 322 | J13: 91 | K13: 34921 | L13: 23238 | M13: 11683 | N13: 134392.94 | O13: 4343.367 | P13: 6055 | Q13: 36924 | R13: 380251 | S13: 29732 | T13: 13046 | U13: 371642 | V13: 30094 | W13: 12601 | X13: 130996 | Y13: 119815 | Z13: 11181 | AA13: =X13-Y13-Z13 -> 0 | AB13: 130007 | AC13: 116981 | AD13: 13026 | AE13: 83228 | AF13: 650 | AG13: 4341 | AH13: 12925 | AI13: 9222 | AJ13: 3703 | AK13: 17714 | AL13: 155234 | AN13: 342 | AO13: 0 | AP13: 601
A14: 44166 | B14: 175813 | C14: 139070 | D14: 36743 | E14: 182787 | F14: 142964 | G14: 39823 | H14: 158 | I14: 228 | J14: -70 | K14: 28017 | L14: 19153 | M14: 8864 | N14: 88434.599 | O14: 16497.334 | P14: 5013 | Q14: 32181 | R14: 364763 | S14: 27381 | T14: 9274 | U14: 333253 | V14: 26962 | W14: 10318 | X14: 107417 | Y14: 97268 | Z14: 10149 | AA14: =X14-Y14-Z14 -> 0 | AB14: 109328 | AC14: 98675 | AD14: 10653 | AE14: 115321 | AF14: 1070 | AG14: 4008 | AH14: 9778 | AI14: 6038 | AJ14: 3740 | AK14: 23238 | AL14: 139070 | AN14: -583 | AO14: -26 | AP14: -601
... A64: 45689 | B64: 177464 | C64: 139170 | D64: 38294 | E64: 170549 | F64: 133497 | G64: 37052 | H64: 612 | I64: 561 | J64: 51 | K64: 41079 | L64: 32155 | M64: 8924 | N64: 194783.23 | O64: 8416.134 | P64: 4572 | Q64: 21823 | R64: 343135 | S64: 29473 | T64: 3244 | U64: 337221 | V64: 34305 | W64: 3225 | X64: 110638 | Y64: 98935 | Z64: 11703 | AA64: =X64-Y64-Z64 -> 0 | AB64: 111097 | AC64: 98365 | AD64: 12732 | AE64: 105934 | AF64: 1768 | AG64: 1270 | AH64: 10195 | AI64: 6104 | AJ64: 4091 | AK64: 27005 | AL64: 139170 | AN64: 30 | AO64: -18 | AP64: 64
A65: 45717 | N65: 246498.4 | O65: 34277.392 | P65: 10270 | Q65: 14924
A66: 45748
A67: 45778
A68: 45809
A69: 45839
A70: 45870
A71: 45901
A72: 45931
A73: 45962
A74: 45992
A75: 46023
A76: 46054
A77: 46082
... A82: 46235

Sheet Mandates
B16: 2010 | C16: 2011 | D16: 2012 | E16: 2013 | F16: 2014 | G16: 2015 | H16: 2016 | I16: 2017 | J16: 2018 | K16: 2019 | L16: 2020 | M16: 2021 | N16: 2022 | O16: 2023 | P16: 2024 | Q16: 2025 | R16: 2026 | S16: 2027 | T16: 2028 | U16: 2029 | V16: 2030 | W16: 2031 | X16: 2032 | Y16: 2033 | Z16: 2034 | AA16: 2035 | AB16: 2036 | AC16: 2037 | AD16: 2038 | AE16: 2039 | AF16: 2040 | AG16: 2041 | AH16: 2042 | AI16: 2043
A18: Yukon | D18: 0.02
A19: British Columbia* | B19: 0.05 | D19: 0.02 | N19: 0.04
A20: Northwest Terrirories | D20: 0.02
A21: Alberta1 | C21: 0.02 | D21: 0.02
A22: Nunavut | C22: 0.02 | D22: 0.02
A23: Saskatchewan2 | C23: 0.02 | D23: 0.02 | E23: 0.02
A24: Manitoba | C24: 0.02 | D24: 0.02
A25: Ontario | C25: 0.02 | D25: 0.02
A26: Quebec | D26: 0 | E26: 0.02
A27: Newfoundland and Labrador | D27: 0 | E27: 0 | F27: 0 | G27: 0
A28: New Brunswick | D28: 0 | E28: 0.02
A29: Price Edward Island | D29: 0 | E29: 0.02
A30: Nova Scotia | D30: 0 | E30: 0.02
A31: Canada3 | C31: 0.02
A33: * - LCFS program started in 2013
A34: 1 - Started April 1, 2011
A35: 2 - Started July 1, 2012
A36: 3 - Started on July 1, 2011

Sheet Mandate Table
A1: Canadian Biofuel Mandates
C2: Alberta | D2: Manitoba | E2: Ontario | I2: Saskatchewan | K2: British Columbia | L2: Quebec
B3: Ethanol | C3: 0.05 | D3: 0.1 | E3: 0.1 | F3: 0.11 | G3: 0.13 | H3: 0.15 | I3: 0.01 | J3: 0.075 | K3: 0.05 | L3: 0.1 | M3: 0.12 | N3: 0.14 | O3: 0.15
B4: Biomass-Based Diesel | C4: 0.02 | D4: 0.05 | E4: 0.04 | F4: 0.04 | G4: 0.04 | H4: 0.04 | I4: 0.02 | J4: 0.02 | K4: 0.04 | L4: 0.03 | M4: 0.05 | N4: 0.05 | O4: 0.1
B5: Start Date | C5: 40634 | D5: 44562 | E5: 43831 | F5: 45658 | G5: 46753 | H5: 10959 | I5: 38657 | J5: 39097 | K5: 44562 | L5: 44927 | M5: 45658 | N5: 46753 | O5: 10959
B6: Starting in Dec 2012, 2% for Quebec, New Brunswick, Nova Scotia, and Prince Edward Island (heating oils sold in Newfoundland and Labrador are exempt) - In 2010, 5% ethanol blend

Sheet Credit Data
A1: Monthly | R1: Quarterly | Z1: Annual
A2: Time Period | B2: Transfers (Number) | C2: Total Volume (Credits - MTs) | D2: Average Price ($ per Credit) | E2: Price Range ($ per Credit) | G2: Category A- Date of Agreement Within 6 Months Before CTP | J2: Category B -Date of Agreement Between 6 months to a year before CTP | M2: Category C- Date of Agreement Reached 1 year+ before CTP | P2: Category D- Transfer Reported with Zero/Net Zero | R2: Time Period | S2: Transfers (Number) | T2: Total Volume (Credits - MTs) | U2: Average Price ($ per Credit) | V2: Price Range ($ per Credit) | Z2: Time Period | AA2: Transfers (Number) | AB2: Total Volume (Credits - MTs) | AC2: Average Price ($ per Credit) | AD2: Total Value ($) | AE2: Price Range ($ per Credit)
E4: Min | F4: Max | G4: Transfers (Number) | H4: Volume (Credits) | I4: Average $ | J4: Transfers (Number) | K4: Volume (Credits) | L4: Average $ | M4: Transfers (Number) | N4: Volume (Credits) | O4: Average $ | P4: Transfers (Number) | V4: Min | W4: Max | AE4: Min | AF4: Max
A5: 42309 | B5: 1 | C5: 14349 | D5: 170 | E5: 170 | F5: 170 | G5: - | J5: - | M5: - | P5: - | R5: Q4 2015 | S5: 2 | T5: 14354 | U5: 169.94775 | V5: 20 | W5: 170 | X5: 42339 | Y5: =U5*T5 -> 2439430 | Z5: 2015 | AA5: 2 | AB5: 14354 | AC5: 169.94775 | AD5: 2439430 | AE5: 20 | AF5: 170
A6: 42339 | B6: 1 | C6: 5 | D6: 20 | E6: 20 | F6: 20 | G6: - | J6: - | M6: - | P6: - | R6: Q1 2016 | S6: 4 | T6: 57000 | U6: 163.42105 | V6: 155 | W6: 170 | X6: 42430 | Y6: =U6*T6 -> 9315000 | Z6: 2016 | AA6: 15 | AB6: 198705 | AC6: 170.93103 | AD6: 33964850 | AE6: 100 | AF6: 190
A7: 42370 | B7: 0 | C7: 0 | D7: 0 | E7: 0 | F7: 0 | G7: - | J7: - | M7: - | P7: - | R7: Q2 2016 | S7: 5 | T7: 18705 | U7: 171.06923 | V7: 160 | W7: 190 | X7: 42522 | Y7: =U7*T7 -> 3199850 | Z7: 2017 | AA7: 31 | AB7: 240164 | AC7: 164.30448 | AD7: 39460022 | AE7: 60 | AF7: 185
A8: 42401 | B8: 0 | C8: 0 | D8: 0 | E8: 0 | F8: 0 | G8: - | J8: - | M8: - | P8: - | R8: Q3 2016 | S8: 6 | T8: 123000 | U8: 174.39024 | V8: 100 | W8: 185 | X8: 42614 | Y8: =U8*T8 -> 21450000 | Z8: 2018 | AA8: 48 | AB8: 435221 | AC8: 193.45163 | AD8: 84194210 | AE8: 55 | AF8: 210.5
A9: 42430 | B9: 4 | C9: 57000 | D9: 163.42105 | E9: 155 | F9: 170 | G9: - | J9: - | M9: - | P9: - | R9: Q4 2016 | S9: 0 | T9: 0 | U9: 0 | V9: 0 | W9: 0 | X9: 42705 | Y9: =U9*T9 -> 0 | Z9: 2019 | AA9: 35 | AB9: 263512 | AC9: 269.33226 | AD9: 70972284 | AE9: 32.93 | AF9: 324.08
A10: 42461 | B10: 0 | C10: 0 | D10: 0 | E10: 0 | F10: 0 | G10: - | J10: - | M10: - | P10: - | R10: Q1 2017 | S10: 1 | T10: 382 | U10: 60 | V10: 60 | W10: 60 | X10: 42795 | Y10: =U10*T10 -> 22920 | Z10: 2020 | AA10: 32 | AB10: 102890 | AC10: 250.44096 | AD10: 25767870 | AE10: 32.5 | AF10: 385.2
A11: 42491 | B11: 0 | C11: 0 | D11: 0 | E11: 0 | F11: 0 | G11: - | J11: - | M11: - | P11: - | R11: Q2 2017 | S11: 1 | T11: 3000 | U11: 100 | V11: 100 | W11: 100 | X11: 42887 | Y11: =U11*T11 -> 300000 | Z11: 2021 | AA11: 85 | AB11: 551906 | AC11: 447.23628 | AD11: 2.4683238e+08 | AE11: 85 | AF11: 519.19
A12: 42522 | B12: 5 | C12: 18705 | D12: 171.06923 | E12: 160 | F12: 190 | G12: - | J12: - | M12: - | P12: - | R12: Q3 2017 | S12: 17 | T12: 173059 | U12: 166.69272 | V12: 91 | W12: 185 | X12: 42979 | Y12: =U12*T12 -> 28847676 | Z12: 2022 | AA12: 118 | AB12: 948177 | AC12: 450.37327 | AD12: 4.2703358e+08 | AE12: 340 | AF12: 497.77
A13: 42552 | B13: 5 | C13: 120000 | D13: 176.25 | E13: 165 | F13: 185 | G13: - | J13: - | M13: - | P13: - | R13: Q4 2017 | S13: 12 | T13: 63723 | U13: 161.47114 | V13: 150 | W13: 170 | X13: 43070 | Y13: =U13*T13 -> 10289426 | Z13: 2023 | AA13: 154 | AB13: 1040608 | AC13: 471.5977 | AD13: 4.9074834e+08 | AE13: 200 | AF13: 510
A14: 42583 | B14: 0 | C14: 0 | D14: 0 | E14: 0 | F14: 0 | G14: - | J14: - | M14: - | P14: - | R14: Q1 2018 | S14: 7 | T14: 71092 | U14: 159.23381 | V14: 55 | W14: 176 | X14: 43160 | Y14: =U14*T14 -> 11320250 | Z14: All Years | AA14: 520 | AB14: 3795537 | AC14: 374.49588 | AD14: 1.421413e+09 | AE14: 20 | AF14: 519.19
A15: 42614 | B15: 1 | C15: 3000 | D15: 100 | E15: 100 | F15: 100 | G15: - | J15: - | M15: - | P15: - | R15: Q2 2018 | S15: 2 | T15: 2741 | U15: 170.30427 | V15: 165 | W15: 172 | X15: 43252 | Y15: =U15*T15 -> 466804
A16: 42644 | B16: 0 | C16: 0 | D16: 0 | E16: 0 | F16: 0 | G16: - | J16: - | M16: - | P16: - | R16: Q3 2018 | S16: 9 | T16: 149571 | U16: 199.96451 | V16: 55 | W16: 207 | X16: 43344 | Y16: =U16*T16 -> 29908891
A17: 42675 | B17: 0 | C17: 0 | D17: 0 | E17: 0 | F17: 0 | G17: - | J17: - | M17: - | P17: - | R17: Q4 2018 | S17: 30 | T17: 211817 | U17: 200.6367 | V17: 164.3 | W17: 210.5 | X17: 43435 | Y17: =U17*T17 -> 42498265
A18: 42705 | B18: 0 | C18: 0 | D18: 0 | E18: 0 | F18: 0 | G18: - | J18: - | M18: - | P18: - | R18: Q1 2019 | S18: 6 | T18: 48475 | U18: 178.46044 | V18: 32.93 | W18: 200 | X18: 43525 | Y18: =U18*T18 -> 8650870
A19: 42736 | B19: 0 | C19: 0 | D19: 0 | E19: 0 | F19: 0 | G19: - | J19: - | M19: - | P19: - | R19: Q2 2019 | S19: 4 | T19: 9412 | U19: 187.25032 | V19: 176 | W19: 200 | X19: 43617 | Y19: =U19*T19 -> 1762400
A20: 42767 | B20: 0 | C20: 0 | D20: 0 | E20: 0 | F20: 0 | G20: - | J20: - | M20: - | P20: - | R20: Q3 2019 | S20: 2 | T20: 5500 | U20: 178.18182 | V20: 176 | W20: 200 | X20: 43709 | Y20: =U20*T20 -> 980000
A21: 42795 | B21: 1 | C21: 382 | D21: 60 | E21: 60 | F21: 60 | G21: - | J21: - | M21: - | P21: - | R21: Q4 2019 | S21: 23 | T21: 200125 | U21: 297.709 | V21: 176 | W21: 324.08 | X21: 43800 | Y21: =U21*T21 -> 59579014
A22: 42826 | B22: 0 | C22: 0 | D22: 0 | E22: 0 | F22: 0 | G22: - | J22: - | M22: - | P22: - | R22: Q1 2020 | S22: 9 | T22: 30233 | U22: 235.48953 | V22: 32.5 | W22: 345 | X22: 43891 | Y22: =U22*T22 -> 7119555
A23: 42856 | B23: 1 | C23: 3000 | D23: 100 | E23: 100 | F23: 100 | G23: - | J23: - | M23: - | P23: - | R23: Q2 2020 | S23: 8 | T23: 41630 | U23: 206.23473 | V23: 85 | W23: 330.45 | X23: 43983 | Y23: =U23*T23 -> 8585551.7
A24: 42887 | B24: 0 | C24: 0 | D24: 0 | E24: 0 | F24: 0 | G24: - | J24: - | M24: - | P24: - | R24: Q3 2020 | S24: 2 | T24: 6762 | U24: 337.50444 | V24: 335 | W24: 340 | X24: 44075 | Y24: =U24*T24 -> 2282205
A25: 42917 | B25: 10 | C25: 134000 | D25: 169.56716 | E25: 162 | F25: 185 | G25: - | J25: - | M25: - | P25: - | R25: Q4 2020 | S25: 13 | T25: 24265 | U25: 320.64944 | V25: 147.5 | W25: 385.2 | X25: 44166 | Y25: =U25*T25 -> 7780558.6
A26: 42948 | B26: 7 | C26: 39059 | D26: 156.83136 | E26: 91 | F26: 170.5 | G26: - | J26: - | M26: - | P26: - | R26: Q1 2021 | S26: 30 | T26: 214263 | U26: 410.7252 | V26: 85 | W26: 457 | X26: 44256 | Y26: =U26*T26 -> 88003214
... A37: 43282 | B37: 8 | C37: 149064 | D37: 200.09193 | E37: 55 | F37: 207 | G37: - | J37: - | M37: - | P37: - | R37: Q4 2023 | S37: 26 | T37: 193863 | U37: 496.36258 | V37: 450 | W37: 510 | X37: 45261 | Y37: =U37*T37 -> 96226340
A38: 43313 | B38: 0 | C38: 0 | D38: 0 | E38: 0 | F38: 0 | G38: - | J38: - | M38: - | P38: -
A39: 43344 | B39: 1 | C39: 507 | D39: 162.5 | E39: 162.5 | F39: 162.5 | G39: - | J39: - | M39: - | P39: -
A40: 43374 | B40: 1 | C40: 17499 | D40: 170 | E40: 170 | F40: 170 | G40: - | J40: - | M40: - | P40: - | U40: =U30*T30 -> 1.1578082e+08
A41: 43405 | B41: 8 | C41: 7287 | D41: 165.70401 | E41: 164.3 | F41: 175 | G41: - | J41: - | M41: - | P41: - | U41: =U31*T31 -> 11296685
A42: 43435 | B42: 21 | C42: 187031 | D42: 204.86416 | E42: 176 | F42: 210.5 | G42: - | J42: - | M42: - | P42: - | U42: =U32*T32 -> 163455120
A43: 43466 | B43: 0 | C43: 0 | D43: 0 | E43: 0 | F43: 0 | G43: - | J43: - | M43: - | P43: - | U43: =U33*T33 -> 1.3650095e+08
A44: 43497 | B44: 3 | C44: 10250 | D44: 106.67317 | E44: 32.93 | F44: 195 | G44: - | J44: - | M44: - | P44: - | U44: =U34*T34 -> 1.6345613e+08
A45: 43525 | B45: 3 | C45: 38225 | D45: 197.71014 | E45: 190 | F45: 200 | G45: - | J45: - | M45: - | P45: - | U45: =U35*T35 -> 1.0466772e+08
A46: 43556 | B46: 0 | C46: 0 | D46: 0 | E46: 0 | F46: 0 | G46: - | J46: - | M46: - | P46: - | U46: =U36*T36 -> 1.2639815e+08
A47: 43586 | B47: 4 | C47: 9412 | D47: 187.25032 | E47: 176 | F47: 200 | G47: - | J47: - | M47: - | P47: -
A48: 43617 | B48: 0 | C48: 0 | D48: 0 | E48: 0 | F48: 0 | G48: - | J48: - | M48: - | P48: -
A49: 43647 | B49: 0 | C49: 0 | D49: 0 | E49: 0 | F49: 0 | G49: - | J49: - | M49: - | P49: -
A50: 43678 | B50: 0 | C50: 0 | D50: 0 | E50: 0 | F50: 0 | G50: - | J50: - | M50: - | P50: -
A51: 43709 | B51: 2 | C51: 5500 | D51: 178.18182 | E51: 176 | F51: 200 | G51: - | J51: - | M51: - | P51: -
A52: 43739 | B52: 10 | C52: 156766 | D52: 308.15257 | E52: 292.58 | F52: 324.08 | G52: - | J52: - | M52: - | P52: -
A53: 43770 | B53: 10 | C53: 14928 | D53: 208.51201 | E53: 176 | F53: 322.25 | G53: - | J53: - | M53: - | P53: -
A54: 43800 | B54: 3 | C54: 28431 | D54: 286.9579 | E54: 200 | F54: 323.6 | G54: - | J54: - | M54: - | P54: -
A55: 43831 | B55: 0 | C55: 0 | D55: 0 | E55: 0 | F55: 0 | G55: - | J55: - | M55: - | P55: -
A56: 43862 | B56: 5 | C56: 26416 | D56: 222.96525 | E56: 32.5 | F56: 345 | G56: - | J56: - | M56: - | P56: -
A57: 43891 | B57: 4 | C57: 3817 | D57: 322.16531 | E57: 185 | F57: 345 | G57: - | J57: - | M57: - | P57: -
A58: 43922 | B58: 4 | C58: 22967 | D58: 225.61493 | E58: 200 | F58: 310 | G58: - | J58: - | M58: - | P58: -
... A83: 44682 | B83: 0 | C83: 0 | D83: 0 | E83: 0 | F83: 0 | G83: - | J83: - | M83: - | P83: -
A84: 44713 | B84: 6 | C84: 24934 | D84: 406.30845 | E84: 340 | F84: 485 | G84: 2 | H84: 1093 | I84: 475.48 | J84: 2 | K84: 18000 | L84: 422.5 | M84: 2 | N84: 5841 | O84: 343.47 | P84: 0
A85: 44743 | B85: 26 | C85: 233833 | D85: 444.85316 | E85: 400 | F85: 490 | G85: 26 | H85: 233833 | I85: 444.85 | J85: 0 | K85: - | L85: - | M85: 0 | N85: - | O85: - | P85: 0
A86: 44774 | B86: 4 | C86: 26049 | D86: 472.32216 | E86: 460 | F86: 480 | G86: 4 | H86: 26049 | I86: 472.32 | J86: 0 | K86: - | L86: - | M86: 0 | N86: - | O86: - | P86: 0
A87: 44805 | B87: 7 | C87: 105000 | D87: 448.85952 | E87: 435.5 | F87: 478.01 | G87: 6 | H87: 80000 | I87: 439.75 | J87: 1 | K87: 25000 | L87: 478.01 | M87: 0 | N87: - | O87: - | P87: 0
A88: 44835 | B88: 11 | C88: 102966 | D88: 436.58305 | E88: 425 | F88: 451 | G88: 10 | H88: 82966 | I88: 433.11 | J88: 0 | K88: - | L88: - | M88: 1 | N88: 20000 | O88: 451 | P88: 0
A89: 44866 | B89: 24 | C89: 125500 | D89: 450.03473 | E89: 340 | F89: 465.01 | G89: 21 | H89: 116207 | I89: 453.91 | J89: 0 | K89: - | L89: - | M89: 3 | N89: 9293 | O89: 401.61 | P89: 0
A90: 44896 | B90: 11 | C90: 79014 | D90: 443.8249 | E90: 422 | F90: 480 | G90: 8 | H90: 43014 | I90: 449.12 | J90: 2 | K90: 11000 | L90: 472.73 | M90: 1 | N90: 25000 | O90: 422 | P90: 0
A91: 44927 | B91: 2 | C91: 35098 | D91: 425.0698 | E91: 425 | F91: 450 | G91: 1 | H91: 98 | I91: 450 | J91: 0 | K91: - | L91: - | M91: 1 | N91: 35000 | O91: 425 | P91: 0
A92: 44958 | B92: 4 | C92: 23856 | D92: 460.69584 | E92: 310 | F92: 475 | G92: 3 | H92: 23000 | I92: 466.3 | J92: 0 | K92: - | L92: - | M92: 1 | N92: 856 | O92: 310 | P92: 0
A93: 44986 | B93: 31 | C93: 304927 | D93: 451.08065 | E93: 345 | F93: 482 | G93: 23 | H93: 137629 | I93: 458.92 | J93: 3 | K93: 15018 | L93: 443.94 | M93: 5 | N93: 152280 | O93: 444.7 | P93: 0
A94: 45017 | B94: 5 | C94: 112000 | D94: 476.80893 | E94: 460 | F94: 481 | G94: 5 | H94: 112000 | I94: 476.81 | J94: 0 | K94: - | L94: - | M94: 0 | N94: - | O94: - | P94: 0
A95: 45047 | B95: 3 | C95: 7538 | D95: 471.63306 | E95: 455 | F95: 480 | G95: 3 | H95: 7538 | I95: 471.63 | J95: 0 | K95: - | L95: - | M95: 0 | N95: - | O95: - | P95: 0
A96: 45078 | B96: 11 | C96: 103260 | D96: 462.03709 | E96: 422 | F96: 480 | G96: 8 | H96: 71248 | I96: 478.66 | J96: 0 | K96: - | L96: - | M96: 3 | N96: 32012 | O96: 425.03 | P96: 0
A97: 45108 | B97: 7 | C97: 61632 | D97: 456.55491 | E97: 200 | F97: 485 | G97: 6 | H97: 56632 | I97: 479.21 | J97: 0 | K97: - | L97: - | M97: 1 | N97: 5000 | O97: 200 | P97: 0
A98: 45139 | B98: 24 | C98: 2533 | D98: 475 | E98: 475 | F98: 475 | G98: 24 | H98: 2533 | I98: 475 | J98: 0 | K98: - | L98: - | M98: 0 | N98: - | O98: - | P98: 0
A99: 45170 | B99: 41 | C99: 195901 | D99: 495.43692 | E99: 440 | F99: 510 | G99: 39 | H99: 194669 | I99: 495.74 | J99: 1 | K99: 366 | L99: 440 | M99: 1 | N99: 866 | O99: 450 | P99: 0
A100: 45200 | B100: 7 | C100: 20703 | D100: 492.44554 | E100: 470 | F100: 495 | G100: 7 | H100: 20703 | I100: 492.45 | J100: 0 | K100: 0 | L100: - | M100: 0 | N100: - | O100: - | P100: 0
A101: 45231 | B101: 19 | C101: 173160 | D101: 496.83091 | E101: 450 | F101: 510 | G101: 17 | H101: 151498 | I101: 501.99 | J101: 2 | K101: 21662 | L101: 460.75 | M101: 0 | N101: - | O101: - | P101: 0
A102: 45261
A103: 45292
A104: 45323
A105: 45352
A106: 45383
A107: 45413
A108: 45444
A109: 45474
A110: 45505
A111: 45536
A112: 45566
A113: 45597
... A118: 45748

Sheet Total Biofuels
A1: CANADA - RENEWABLE FUEL SUPPLY AND DEMAND
A2: (cubic meters) | B2: 2009 | C2: 2010 | D2: 2011 | E2: 2012 | F2: 2013 | G2: 2014 | H2: 2015 | I2: 2016 | J2: 2017 | K2: 2018 | L2: 2019 | M2: 2020 | N2: 2021 | O2: 2022 | P2: 2023 | Q2: 2024 | R2: 2025 | S2: 2026 | T2: 2027 | U2: 2028 | V2: 2029 | W2: 2030 | X2: 2031 | Y2: 2032 | Z2: 2033 | AA2: 2034 | AB2: 2035 | AC2: 2036 | AD2: 2037 | AE2: 2038 | AF2: 2039 | AG2: 2040 | AH2: 2041 | AI2: 2042
A3: Beginning Stocks | M3: 24325 | N3: =M12 -> 28017 | O3: =N12 -> 26588 | P3: =O12 -> 31126 | Q3: =P12 -> 39289 | R3: =Q12 -> 30000
A4: Production | C4: 115000 | D4: 120000 | E4: 100000 | F4: 159000 | G4: 351000 | H4: 307000 | I4: 463000 | J4: 397000 | K4: 300000 | L4: 375000 | M4: =M28 -> 2081038 | N4: =N28 -> 2073213 | O4: =O28 -> 2060745 | P4: =P28 -> 2224904 | Q4: 2000000 | R4: 2000000
A5: Imports | M5: =M44 -> 1740483.9 | N5: =N44 -> 1826969.1 | O5: =O44 -> 2495215.6 | P5: =P44 -> 3366482.8 | Q5: 3000000 | R5: 3000000
A6: Total Supply | C6: =SUM(C3:C5) -> 115000 | D6: =SUM(D3:D5) -> 120000 | E6: =SUM(E3:E5) -> 100000 | F6: =SUM(F3:F5) -> 159000 | G6: =SUM(G3:G5) -> 351000 | H6: =SUM(H3:H5) -> 307000 | I6: =SUM(I3:I5) -> 463000 | J6: =SUM(J3:J5) -> 397000 | ... R6: =SUM(R3:R5) -> 5030000
A7: Shipments | M7: =M76 -> 2093539 | N7: =N76 -> 2092089 | O7: =O76 -> 2071095 | P7: =P76 -> 2238358 | Q7: =Q11-Q10-Q9-Q8 -> 2255289 | R7: =R11-R10-R9-R8 -> 2246000
A8: Exports | M8: =M60 -> 490297.47 | N8: =N60 -> 517553.64 | O8: =O60 -> 443516.36 | P8: =P60 -> 581807.86 | Q8: 500000 | R8: 500000
A9: Losses and adjustments | M9: =M92 -> 2451 | N9: =N92 -> 1256 | O9: =O92 -> 4039 | P9: =P92 -> 3464 | Q9: 4000 | R9: 4000
A10: Residual | M10: =M11-SUM(M7:M9) -> 1231542.4 | N10: =N11-SUM(N7:N9) -> 1290712.4 | O10: =O11-SUM(O7:O9) -> 2032772.2 | P10: =P11-SUM(P7:P9) -> 2759593.9 | Q10: 2250000 | R10: 2250000
A11: Total Use | M11: =M6-M12 -> 3817829.9 | N11: =N6-N12 -> 3901611.1 | O11: =O6-O12 -> 4551422.6 | P11: =P6-P12 -> 5583223.8 | Q11: =Q6-Q12 -> 5009289 | R11: =R6-R12 -> 5000000
A12: Ending stocks | M12: =M123 -> 28017 | N12: =N123 -> 26588 | O12: =O123 -> 31126 | P12: =P123 -> 39289 | Q12: 30000 | R12: 30000
A14: PRODUCTION
B15: =B2 -> 2009 | C15: =C2 -> 2010 | D15: =D2 -> 2011 | E15: =E2 -> 2012 | F15: =F2 -> 2013 | G15: =G2 -> 2014 | H15: =H2 -> 2015 | I15: =I2 -> 2016 | ... AI15: =AI2 -> 2042
A16: January | L16: 104669 | M16: =Data!$B3 -> 196779 | N16: =Data!$B15 -> 145465 | O16: =Data!$B27 -> 161880 | P16: =Data!$B39 -> 186459 | Q16: =Data!$B51 -> 193761 | R16: =Data!$B63 -> 179569
A17: February | L17: 71040 | M17: =Data!$B4 -> 185483 | N17: =Data!$B16 -> 139836 | O17: =Data!$B28 -> 149830 | P17: =Data!$B40 -> 169618 | Q17: =Data!$B52 -> 207087 | R17: =Data!$B64 -> 177464
A18: March | M18: =Data!$B5 -> 179660 | N18: =Data!$B17 -> 172532 | O18: =Data!$B29 -> 174887 | P18: =Data!$B41 -> 198113 | Q18: =Data!$B53 -> 264096 | R18: =R$28*((SUM(M18:Q18)/SUM(M$28:Q$28))) -> 174822.19
A19: April | M19: =Data!$B6 -> 120718 | N19: =Data!$B18 -> 165461 | O19: =Data!$B30 -> 161664 | P19: =Data!$B42 -> 168701 | Q19: =Data!$B54 -> 232420 | R19: =R$28*((SUM(M19:Q19)/SUM(M$28:Q$28))) -> 150024.81
A20: May | M20: =Data!$B7 -> 128789 | N20: =Data!$B19 -> 172229 | O20: =Data!$B31 -> 170845 | P20: =Data!$B43 -> 173685 | Q20: =Data!$B55 -> 243770 | R20: =R$28*((SUM(M20:Q20)/SUM(M$28:Q$28))) -> 157155.97
A21: June | M21: =Data!$B8 -> 167467 | N21: =Data!$B20 -> 175038 | O21: =Data!$B32 -> 166163 | P21: =Data!$B44 -> 185836 | Q21: =Data!$B56 -> 274627 | R21: =R$28*((SUM(M21:Q21)/SUM(M$28:Q$28))) -> 171260.14
A22: July | M22: =Data!$B9 -> 196548 | N22: =Data!$B21 -> 193086 | O22: =Data!$B33 -> 175691 | P22: =Data!$B45 -> 199442 | Q22: =Data!$B57 -> 261637 | R22: =R$28*((SUM(M22:Q22)/SUM(M$28:Q$28))) -> 181381.15
A23: August | M23: =Data!$B10 -> 183950 | N23: =Data!$B22 -> 185513 | O23: =Data!$B34 -> 175345 | P23: =Data!$B46 -> 193325 | Q23: =Data!$B58 -> 252024 | R23: =R$28*((SUM(M23:Q23)/SUM(M$28:Q$28))) -> 174975.75
A24: September | M24: =Data!$B11 -> 170448 | N24: =Data!$B23 -> 179772 | O24: =Data!$B35 -> 164119 | P24: =Data!$B47 -> 174900 | Q24: =Data!$B59 -> 242116 | R24: =R$28*((SUM(M24:Q24)/SUM(M$28:Q$28))) -> 164584.55
A25: October | M25: =Data!$B12 -> 176267 | N25: =Data!$B24 -> 156941 | O25: =Data!$B36 -> 179931 | P25: =Data!$B48 -> 170099 | Q25: =Data!$B60 -> 207847 | R25: =R$28*((SUM(M25:Q25)/SUM(M$28:Q$28))) -> 157468.23
A26: November | M26: =Data!$B13 -> 199116 | N26: =Data!$B25 -> 194209 | O26: =Data!$B37 -> 192198 | P26: =Data!$B49 -> 205948 | Q26: =Data!$B61 -> 243174 | R26: =R$28*((SUM(M26:Q26)/SUM(M$28:Q$28))) -> 182837.46
A27: December | M27: =Data!$B14 -> 175813 | N27: =Data!$B26 -> 193131 | O27: =Data!$B38 -> 188192 | P27: =Data!$B50 -> 198778 | Q27: =Data!$B62 -> 255189 | R27: =R28-SUM(R16:R26) -> 128456.74
A28: Total | M28: =SUM(M16:M27) -> 2081038 | N28: =SUM(N16:N27) -> 2073213 | O28: =SUM(O16:O27) -> 2060745 | P28: =SUM(P16:P27) -> 2224904 | Q28: =SUM(Q16:Q27) -> 2877748 | R28: =R4 -> 2000000
A30: IMPORTS
B31: =B2 -> 2009 | C31: =C2 -> 2010 | D31: =D2 -> 2011 | E31: =E2 -> 2012 | F31: =F2 -> 2013 | G31: =G2 -> 2014 | H31: =H2 -> 2015 | I31: =I2 -> 2016 | ... AI31: =AI2 -> 2042
A32: January | M32: ='Fuel Ethanol'!M42+'Renewable Fuel Ex Ethanol'!I38 -> 124753.38 | N32: ='Fuel Ethanol'!N42+'Renewable Fuel Ex Ethanol'!J38 -> 110240.21 | O32: ='Fuel Ethanol'!O42+'Renewable Fuel Ex Ethanol'!K38 -> 160009.38 | P32: ='Fuel Ethanol'!P42+'Renewable Fuel Ex Ethanol'!L38 -> 192100.08 | Q32: ='Fuel Ethanol'!Q42+'Renewable Fuel Ex Ethanol'!M38 -> 232664.62
A33: February | M33: ='Fuel Ethanol'!M43+'Renewable Fuel Ex Ethanol'!I39 -> 131447.51 | N33: ='Fuel Ethanol'!N43+'Renewable Fuel Ex Ethanol'!J39 -> 78238.817 | O33: ='Fuel Ethanol'!O43+'Renewable Fuel Ex Ethanol'!K39 -> 126852.46 | P33: ='Fuel Ethanol'!P43+'Renewable Fuel Ex Ethanol'!L39 -> 177065.28 | Q33: ='Fuel Ethanol'!Q43+'Renewable Fuel Ex Ethanol'!M39 -> 207148.55
A34: March | M34: ='Fuel Ethanol'!M44+'Renewable Fuel Ex Ethanol'!I40 -> 136478.03 | N34: ='Fuel Ethanol'!N44+'Renewable Fuel Ex Ethanol'!J40 -> 136753.15 | O34: ='Fuel Ethanol'!O44+'Renewable Fuel Ex Ethanol'!K40 -> 143595.23 | P34: ='Fuel Ethanol'!P44+'Renewable Fuel Ex Ethanol'!L40 -> 301144.96 | Q34: ='Fuel Ethanol'!Q44+'Renewable Fuel Ex Ethanol'!M40 -> 248629.98
A35: April | M35: ='Fuel Ethanol'!M45+'Renewable Fuel Ex Ethanol'!I41 -> 112397.65 | N35: ='Fuel Ethanol'!N45+'Renewable Fuel Ex Ethanol'!J41 -> 158152.18 | O35: ='Fuel Ethanol'!O45+'Renewable Fuel Ex Ethanol'!K41 -> 198254.49 | P35: ='Fuel Ethanol'!P45+'Renewable Fuel Ex Ethanol'!L41 -> 312110.92 | Q35: ='Fuel Ethanol'!Q45+'Renewable Fuel Ex Ethanol'!M41 -> 302048.02
A36: May | M36: ='Fuel Ethanol'!M46+'Renewable Fuel Ex Ethanol'!I42 -> 136851.3 | N36: ='Fuel Ethanol'!N46+'Renewable Fuel Ex Ethanol'!J42 -> 165006.47 | O36: ='Fuel Ethanol'!O46+'Renewable Fuel Ex Ethanol'!K42 -> 217919.64 | P36: ='Fuel Ethanol'!P46+'Renewable Fuel Ex Ethanol'!L42 -> 345263.44 | Q36: ='Fuel Ethanol'!Q46+'Renewable Fuel Ex Ethanol'!M42 -> 334987.98
A37: June | M37: ='Fuel Ethanol'!M47+'Renewable Fuel Ex Ethanol'!I43 -> 174907.07 | N37: ='Fuel Ethanol'!N47+'Renewable Fuel Ex Ethanol'!J43 -> 199963.98 | O37: ='Fuel Ethanol'!O47+'Renewable Fuel Ex Ethanol'!K43 -> 214218.09 | P37: ='Fuel Ethanol'!P47+'Renewable Fuel Ex Ethanol'!L43 -> 302244.47 | Q37: ='Fuel Ethanol'!Q47+'Renewable Fuel Ex Ethanol'!M43 -> 231836.63
A38: July | M38: ='Fuel Ethanol'!M48+'Renewable Fuel Ex Ethanol'!I44 -> 161044.51 | N38: ='Fuel Ethanol'!N48+'Renewable Fuel Ex Ethanol'!J44 -> 162143.01 | O38: ='Fuel Ethanol'!O48+'Renewable Fuel Ex Ethanol'!K44 -> 220826.45 | P38: ='Fuel Ethanol'!P48+'Renewable Fuel Ex Ethanol'!L44 -> 373091.58
A39: August | M39: ='Fuel Ethanol'!M49+'Renewable Fuel Ex Ethanol'!I45 -> 200370.28 | N39: ='Fuel Ethanol'!N49+'Renewable Fuel Ex Ethanol'!J45 -> 191299.64 | O39: ='Fuel Ethanol'!O49+'Renewable Fuel Ex Ethanol'!K45 -> 272197.61 | P39: ='Fuel Ethanol'!P49+'Renewable Fuel Ex Ethanol'!L45 -> 308404.41
A40: September | M40: ='Fuel Ethanol'!M50+'Renewable Fuel Ex Ethanol'!I46 -> 183136.07 | N40: ='Fuel Ethanol'!N50+'Renewable Fuel Ex Ethanol'!J46 -> 168865.1 | O40: ='Fuel Ethanol'!O50+'Renewable Fuel Ex Ethanol'!K46 -> 241913.4 | P40: ='Fuel Ethanol'!P50+'Renewable Fuel Ex Ethanol'!L46 -> 280636.39
A41: October | M41: ='Fuel Ethanol'!M51+'Renewable Fuel Ex Ethanol'!I47 -> 146589.37 | N41: ='Fuel Ethanol'!N51+'Renewable Fuel Ex Ethanol'!J47 -> 164043.33 | O41: ='Fuel Ethanol'!O51+'Renewable Fuel Ex Ethanol'!K47 -> 247839.78 | P41: ='Fuel Ethanol'!P51+'Renewable Fuel Ex Ethanol'!L47 -> 333466.83
A42: November | M42: ='Fuel Ethanol'!M52+'Renewable Fuel Ex Ethanol'!I48 -> 139689.25 | N42: ='Fuel Ethanol'!N52+'Renewable Fuel Ex Ethanol'!J48 -> 149797.37 | O42: ='Fuel Ethanol'!O52+'Renewable Fuel Ex Ethanol'!K48 -> 208834.23 | P42: ='Fuel Ethanol'!P52+'Renewable Fuel Ex Ethanol'!L48 -> 230080.57
A43: December | M43: ='Fuel Ethanol'!M53+'Renewable Fuel Ex Ethanol'!I49 -> 92819.47 | N43: ='Fuel Ethanol'!N53+'Renewable Fuel Ex Ethanol'!J49 -> 142465.82 | O43: ='Fuel Ethanol'!O53+'Renewable Fuel Ex Ethanol'!K49 -> 242754.84 | P43: ='Fuel Ethanol'!P53+'Renewable Fuel Ex Ethanol'!L49 -> 210873.83
A44: Total | M44: =SUM(M32:M43) -> 1740483.9 | N44: =SUM(N32:N43) -> 1826969.1 | O44: =SUM(O32:O43) -> 2495215.6 | P44: =SUM(P32:P43) -> 3366482.8
A46: EXPORTS
B47: =B2 -> 2009 | C47: =C2 -> 2010 | D47: =D2 -> 2011 | E47: =E2 -> 2012 | F47: =F2 -> 2013 | G47: =G2 -> 2014 | H47: =H2 -> 2015 | I47: =I2 -> 2016 | ... AI47: =AI2 -> 2042
A48: January | M48: ='Fuel Ethanol'!M58+'Renewable Fuel Ex Ethanol'!I54 -> 30559.547 | N48: ='Fuel Ethanol'!N58+'Renewable Fuel Ex Ethanol'!J54 -> 32008.029 | O48: ='Fuel Ethanol'!O58+'Renewable Fuel Ex Ethanol'!K54 -> 27324.007 | P48: ='Fuel Ethanol'!P58+'Renewable Fuel Ex Ethanol'!L54 -> 35319.977 | Q48: ='Fuel Ethanol'!Q58+'Renewable Fuel Ex Ethanol'!M54 -> 39222.322
A49: February | M49: ='Fuel Ethanol'!M59+'Renewable Fuel Ex Ethanol'!I55 -> 31387.503 | N49: ='Fuel Ethanol'!N59+'Renewable Fuel Ex Ethanol'!J55 -> 45586.622 | O49: ='Fuel Ethanol'!O59+'Renewable Fuel Ex Ethanol'!K55 -> 33262.673 | P49: ='Fuel Ethanol'!P59+'Renewable Fuel Ex Ethanol'!L55 -> 47291.044 | Q49: ='Fuel Ethanol'!Q59+'Renewable Fuel Ex Ethanol'!M55 -> 55309.909
A50: March | M50: ='Fuel Ethanol'!M60+'Renewable Fuel Ex Ethanol'!I56 -> 36656.254 | N50: ='Fuel Ethanol'!N60+'Renewable Fuel Ex Ethanol'!J56 -> 35579.935 | O50: ='Fuel Ethanol'!O60+'Renewable Fuel Ex Ethanol'!K56 -> 29514.535 | P50: ='Fuel Ethanol'!P60+'Renewable Fuel Ex Ethanol'!L56 -> 40936.22 | Q50: ='Fuel Ethanol'!Q60+'Renewable Fuel Ex Ethanol'!M56 -> 58938.659
A51: April | M51: ='Fuel Ethanol'!M61+'Renewable Fuel Ex Ethanol'!I57 -> 33078.526 | N51: ='Fuel Ethanol'!N61+'Renewable Fuel Ex Ethanol'!J57 -> 48385.288 | O51: ='Fuel Ethanol'!O61+'Renewable Fuel Ex Ethanol'!K57 -> 41025.742 | P51: ='Fuel Ethanol'!P61+'Renewable Fuel Ex Ethanol'!L57 -> 50252.1 | Q51: ='Fuel Ethanol'!Q61+'Renewable Fuel Ex Ethanol'!M57 -> 42491.892
A52: May | M52: ='Fuel Ethanol'!M62+'Renewable Fuel Ex Ethanol'!I58 -> 47486.141 | N52: ='Fuel Ethanol'!N62+'Renewable Fuel Ex Ethanol'!J58 -> 43613.292 | O52: ='Fuel Ethanol'!O62+'Renewable Fuel Ex Ethanol'!K58 -> 40248.157 | P52: ='Fuel Ethanol'!P62+'Renewable Fuel Ex Ethanol'!L58 -> 49423.902 | Q52: ='Fuel Ethanol'!Q62+'Renewable Fuel Ex Ethanol'!M58 -> 51936.634
A53: June | M53: ='Fuel Ethanol'!M63+'Renewable Fuel Ex Ethanol'!I59 -> 45240.399 | N53: ='Fuel Ethanol'!N63+'Renewable Fuel Ex Ethanol'!J59 -> 46736.916 | O53: ='Fuel Ethanol'!O63+'Renewable Fuel Ex Ethanol'!K59 -> 26915.739 | P53: ='Fuel Ethanol'!P63+'Renewable Fuel Ex Ethanol'!L59 -> 53570.941 | Q53: ='Fuel Ethanol'!Q63+'Renewable Fuel Ex Ethanol'!M59 -> 49792.119
A54: July | M54: ='Fuel Ethanol'!M64+'Renewable Fuel Ex Ethanol'!I60 -> 50162.688 | N54: ='Fuel Ethanol'!N64+'Renewable Fuel Ex Ethanol'!J60 -> 36695.839 | O54: ='Fuel Ethanol'!O64+'Renewable Fuel Ex Ethanol'!K60 -> 41197.793 | P54: ='Fuel Ethanol'!P64+'Renewable Fuel Ex Ethanol'!L60 -> 45169.115
A55: August | M55: ='Fuel Ethanol'!M65+'Renewable Fuel Ex Ethanol'!I61 -> 38454.087 | N55: ='Fuel Ethanol'!N65+'Renewable Fuel Ex Ethanol'!J61 -> 55082.058 | O55: ='Fuel Ethanol'!O65+'Renewable Fuel Ex Ethanol'!K61 -> 29662.251 | P55: ='Fuel Ethanol'!P65+'Renewable Fuel Ex Ethanol'!L61 -> 58516.983
A56: September | M56: ='Fuel Ethanol'!M66+'Renewable Fuel Ex Ethanol'!I62 -> 47873.817 | N56: ='Fuel Ethanol'!N66+'Renewable Fuel Ex Ethanol'!J62 -> 44409.346 | O56: ='Fuel Ethanol'!O66+'Renewable Fuel Ex Ethanol'!K62 -> 41081.376 | P56: ='Fuel Ethanol'!P66+'Renewable Fuel Ex Ethanol'!L62 -> 47958.273
A57: October | M57: ='Fuel Ethanol'!M67+'Renewable Fuel Ex Ethanol'!I63 -> 48111.662 | N57: ='Fuel Ethanol'!N67+'Renewable Fuel Ex Ethanol'!J63 -> 35531.029 | O57: ='Fuel Ethanol'!O67+'Renewable Fuel Ex Ethanol'!K63 -> 38562.12 | P57: ='Fuel Ethanol'!P67+'Renewable Fuel Ex Ethanol'!L63 -> 40827.199
A58: November | M58: ='Fuel Ethanol'!M68+'Renewable Fuel Ex Ethanol'!I64 -> 36640.79 | N58: ='Fuel Ethanol'!N68+'Renewable Fuel Ex Ethanol'!J64 -> 46722.183 | O58: ='Fuel Ethanol'!O68+'Renewable Fuel Ex Ethanol'!K64 -> 50257.25 | P58: ='Fuel Ethanol'!P68+'Renewable Fuel Ex Ethanol'!L64 -> 53165.811
A59: December | M59: ='Fuel Ethanol'!M69+'Renewable Fuel Ex Ethanol'!I65 -> 44646.055 | N59: ='Fuel Ethanol'!N69+'Renewable Fuel Ex Ethanol'!J65 -> 47203.101 | O59: ='Fuel Ethanol'!O69+'Renewable Fuel Ex Ethanol'!K65 -> 44464.718 | P59: ='Fuel Ethanol'!P69+'Renewable Fuel Ex Ethanol'!L65 -> 59376.293
A60: Total | M60: =SUM(M48:M59) -> 490297.47 | N60: =SUM(N48:N59) -> 517553.64 | O60: =SUM(O48:O59) -> 443516.36 | P60: =SUM(P48:P59) -> 581807.86
A62: SHIPMENTS
B63: =B2 -> 2009 | C63: =C2 -> 2010 | D63: =D2 -> 2011 | E63: =E2 -> 2012 | F63: =F2 -> 2013 | G63: =G2 -> 2014 | H63: =H2 -> 2015 | I63: =I2 -> 2016 | ... AI63: =AI2 -> 2042
A64: January | M64: =Data!$E3 -> 194345 | N64: =Data!$E15 -> 145870 | O64: =Data!$E27 -> 163583 | P64: =Data!$E39 -> 188621 | Q64: =Data!$E51 -> 202410 | R64: =Data!$E63 -> 210641
A65: February | M65: =Data!$E4 -> 184445 | N65: =Data!$E16 -> 144739 | O65: =Data!$E28 -> 142733 | P65: =Data!$E40 -> 171189 | Q65: =Data!$E52 -> 189922 | R65: =Data!$E64 -> 170549
A66: March | M66: =Data!$E5 -> 177722 | N66: =Data!$E17 -> 173666 | O66: =Data!$E29 -> 180351 | P66: =Data!$E41 -> 196533 | Q66: =Data!$E53 -> 258112 | R66: =R$76*((SUM(M66:Q66)/SUM(M$76:Q$76))) -> 196027.32
A67: April | M67: =Data!$E6 -> 120175 | N67: =Data!$E18 -> 168279 | O67: =Data!$E30 -> 157071 | P67: =Data!$E42 -> 167529 | Q67: =Data!$E54 -> 198512 | R67: =R$76*((SUM(M67:Q67)/SUM(M$76:Q$76))) -> 161285.17
A68: May | M68: =Data!$E7 -> 138982 | N68: =Data!$E19 -> 170759 | O68: =Data!$E31 -> 175488 | P68: =Data!$E43 -> 178633 | Q68: =Data!$E55 -> 252000 | R68: =R$76*((SUM(M68:Q68)/SUM(M$76:Q$76))) -> 182012.25
A69: June | M69: =Data!$E8 -> 168495 | N69: =Data!$E20 -> 183265 | O69: =Data!$E32 -> 173920 | P69: =Data!$E44 -> 188658 | Q69: =Data!$E56 -> 289832 | R69: =R$76*((SUM(M69:Q69)/SUM(M$76:Q$76))) -> 199561.99
A70: July | M70: =Data!$E9 -> 198451 | N70: =Data!$E21 -> 193613 | O70: =Data!$E33 -> 173801 | P70: =Data!$E45 -> 202770 | Q70: =Data!$E57 -> 272513 | R70: =R$76*((SUM(M70:Q70)/SUM(M$76:Q$76))) -> 206910.75
A71: August | M71: =Data!$E10 -> 186344 | N71: =Data!$E22 -> 191096 | O71: =Data!$E34 -> 181175 | P71: =Data!$E46 -> 201212 | Q71: =Data!$E58 -> 230587 | R71: =R$76*((SUM(M71:Q71)/SUM(M$76:Q$76))) -> 196828.22
A72: September | M72: =Data!$E11 -> 173784 | N72: =Data!$E23 -> 185199 | O72: =Data!$E35 -> 168619 | P72: =Data!$E47 -> 172283 | Q72: =Data!$E59 -> 281133 | R72: =R$76*((SUM(M72:Q72)/SUM(M$76:Q$76))) -> 194960.92
A73: October | M73: =Data!$E12 -> 177884 | N73: =Data!$E24 -> 153511 | O73: =Data!$E36 -> 175776 | P73: =Data!$E48 -> 176690 | Q73: =Data!$E60 -> 195215 | R73: =R$76*((SUM(M73:Q73)/SUM(M$76:Q$76))) -> 174701.65
A74: November | M74: =Data!$E13 -> 190125 | N74: =Data!$E25 -> 189327 | O74: =Data!$E37 -> 199851 | P74: =Data!$E49 -> 201272 | Q74: =Data!$E61 -> 244442 | R74: =R$76*((SUM(M74:Q74)/SUM(M$76:Q$76))) -> 203704.99
A75: December | M75: =Data!$E14 -> 182787 | N75: =Data!$E26 -> 192765 | O75: =Data!$E38 -> 178727 | P75: =Data!$E50 -> 192968 | Q75: =Data!$E62 -> 238562 | R75: =R76-SUM(R64:R74) -> 158105.73
A76: Total | M76: =SUM(M64:M75) -> 2093539 | N76: =SUM(N64:N75) -> 2092089 | O76: =SUM(O64:O75) -> 2071095 | P76: =SUM(P64:P75) -> 2238358 | Q76: =SUM(Q64:Q75) -> 2853240 | R76: =Q7 -> 2255289
A78: LOSSES AND ADJUSTMENTS
B79: =B2 -> 2009 | C79: =C2 -> 2010 | D79: =D2 -> 2011 | E79: =E2 -> 2012 | F79: =F2 -> 2013 | G79: =G2 -> 2014 | H79: =H2 -> 2015 | I79: =I2 -> 2016 | ... AI79: =AI2 -> 2042
A80: January | M80: =Data!$H3 -> -531 | N80: =Data!$H15 -> 53 | O80: =Data!$H27 -> 95 | P80: =Data!$H39 -> 396 | Q80: =Data!$H51 -> 2 | R80: =Data!$H63 -> -61
A81: February | M81: =Data!$H4 -> 322 | N81: =Data!$H16 -> 25 | O81: =Data!$H28 -> 190 | P81: =Data!$H40 -> 285 | Q81: =Data!$H52 -> 685 | R81: =Data!$H64 -> 612
A82: March | M82: =Data!$H5 -> -1226 | N82: =Data!$H17 -> 79 | O82: =Data!$H29 -> 335 | P82: =Data!$H41 -> 390 | Q82: =Data!$H53 -> 607 | R82: =R$92*((SUM(M82:Q82)/SUM(M$92:Q$92))) -> 51.175657
A83: April | M83: =Data!$H6 -> 109 | N83: =Data!$H18 -> 216 | O83: =Data!$H30 -> 629 | P83: =Data!$H42 -> 92 | Q83: =Data!$H54 -> -498 | R83: =R$92*((SUM(M83:Q83)/SUM(M$92:Q$92))) -> 151.59059
A84: May | M84: =Data!$H7 -> -11 | N84: =Data!$H19 -> 71 | O84: =Data!$H31 -> -178 | P84: =Data!$H43 -> 279 | Q84: =Data!$H55 -> 190 | R84: =R$92*((SUM(M84:Q84)/SUM(M$92:Q$92))) -> 97.095436
A85: June | M85: =Data!$H8 -> 240 | N85: =Data!$H20 -> -72 | O85: =Data!$H32 -> 454 | P85: =Data!$H44 -> 69 | Q85: =Data!$H56 -> 209 | R85: =R$92*((SUM(M85:Q85)/SUM(M$92:Q$92))) -> 248.96266
A86: July | M86: =Data!$H9 -> 251 | N86: =Data!$H21 -> 426 | O86: =Data!$H33 -> 587 | P86: =Data!$H45 -> -580 | Q86: =Data!$H57 -> 437 | R86: =R$92*((SUM(M86:Q86)/SUM(M$92:Q$92))) -> 310.09682
A87: August | M87: =Data!$H10 -> 253 | N87: =Data!$H22 -> 361 | O87: =Data!$H34 -> 212 | P87: =Data!$H46 -> 789 | Q87: =Data!$H58 -> 659 | R87: =R$92*((SUM(M87:Q87)/SUM(M$92:Q$92))) -> 629.04564
A88: September | M88: =Data!$H11 -> 2117 | N88: =Data!$H23 -> -171 | O88: =Data!$H35 -> 319 | P88: =Data!$H47 -> 315 | Q88: =Data!$H59 -> 32 | R88: =R$92*((SUM(M88:Q88)/SUM(M$92:Q$92))) -> 722.54495
A89: October | M89: =Data!$H12 -> 356 | N89: =Data!$H24 -> 195 | O89: =Data!$H36 -> 376 | P89: =Data!$H48 -> -524 | Q89: =Data!$H60 -> 380 | R89: =R$92*((SUM(M89:Q89)/SUM(M$92:Q$92))) -> 216.59751
A90: November | M90: =Data!$H13 -> 413 | N90: =Data!$H25 -> 9 | O90: =Data!$H37 -> 391 | P90: =Data!$H49 -> 698 | Q90: =Data!$H61 -> 261 | R90: =R$92*((SUM(M90:Q90)/SUM(M$92:Q$92))) -> 490.17981
A91: December | M91: =Data!$H14 -> 158 | N91: =Data!$H26 -> 64 | O91: =Data!$H38 -> 629 | P91: =Data!$H50 -> 1255 | Q91: =Data!$H62 -> 286 | R91: =R92-SUM(R80:R90) -> 531.71093
A92: Total | M92: =SUM(M80:M91) -> 2451 | N92: =SUM(N80:N91) -> 1256 | O92: =SUM(O80:O91) -> 4039 | P92: =SUM(P80:P91) -> 3464 | Q92: =SUM(Q80:Q91) -> 3250 | R92: =R9 -> 4000
A94: RESIDUAL USE
B95: =B2 -> 2009 | C95: =C2 -> 2010 | D95: =D2 -> 2011 | E95: =E2 -> 2012 | F95: =F2 -> 2013 | G95: =G2 -> 2014 | H95: =H2 -> 2015 | I95: =I2 -> 2016 | ... AI95: =AI2 -> 2042
A96: January | M96: =((M3+M16)-M112)-(M64+M80) -> -915 | N96: =((M123+N16)-N112)-(N64+N80) -> -165 | O96: =((N123+O16)-O112)-(O64+O80) -> 18 | P96: =((O123+P16)-P112)-(P64+P80) -> -185 | Q96: =((P123+Q16)-Q112)-(Q64+Q80) -> -5987 | R96: =((Q123+R16)-R112)-(R64+R80) -> -1602
A97: February | M97: =((M112+M17)-M113)-(M65+M81) -> -10 | N97: =((N112+N17)-N113)-(N65+N81) -> -155 | O97: =((O112+O17)-O113)-(O65+O81) -> -38 | P97: =((P112+P17)-P113)-(P65+P81) -> -287 | Q97: =((Q112+Q17)-Q113)-(Q65+Q81) -> -87 | R97: =((R112+R17)-R113)-(R65+R81) -> 14462
A98: March | M98: =((M113+M18)-M114)-(M66+M82) -> -1305 | N98: =((N113+N18)-N114)-(N66+N82) -> -1600 | O98: =((O113+O18)-O114)-(O66+O82) -> -853 | P98: =((P113+P18)-P114)-(P66+P82) -> -906 | Q98: =((Q113+Q18)-Q114)-(Q66+Q82) -> -34 | R98: =R$108*(SUM(M98:Q98)/SUM(M$108:Q$108)) -> -850.27399
A99: April | M99: =((M114+M19)-M115)-(M67+M83) -> -2483 | N99: =((N114+N19)-N115)-(N67+N83) -> -2745 | O99: =((O114+O19)-O115)-(O67+O83) -> -763 | P99: =((P114+P19)-P115)-(P67+P83) -> -1710 | Q99: =((Q114+Q19)-Q115)-(Q67+Q83) -> 150 | R99: =R$108*(SUM(M99:Q99)/SUM(M$108:Q$108)) -> -1366.6281
A100: May | M100: =((M115+M20)-M116)-(M68+M84) -> -2958 | N100: =((N115+N20)-N116)-(N68+N84) -> -3031 | O100: =((O115+O20)-O116)-(O68+O84) -> -1004 | P100: =((P115+P20)-P116)-(P68+P84) -> -2317 | Q100: =((Q115+Q20)-Q116)-(Q68+Q84) -> -1383 | R100: =R$108*(SUM(M100:Q100)/SUM(M$108:Q$108)) -> -1935.2873
A101: June | M101: =((M116+M21)-M117)-(M69+M85) -> -2961 | N101: =((N116+N21)-N117)-(N69+N85) -> -3353 | O101: =((O116+O21)-O117)-(O69+O85) -> -1453 | P101: =((P116+P21)-P117)-(P69+P85) -> -3004 | Q101: =((Q116+Q21)-Q117)-(Q69+Q85) -> -2257 | R101: =R$108*(SUM(M101:Q101)/SUM(M$108:Q$108)) -> -2357.8905
A102: July | M102: =((M117+M22)-M118)-(M70+M86) -> -2556 | N102: =((N117+N22)-N118)-(N70+N86) -> -2457 | O102: =((O117+O22)-O118)-(O70+O86) -> -2595 | P102: =((P117+P22)-P118)-(P70+P86) -> -2756 | Q102: =((Q117+Q22)-Q118)-(Q70+Q86) -> -2865 | R102: =R$108*(SUM(M102:Q102)/SUM(M$108:Q$108)) -> -2394.2688
A103: August | M103: =((M118+M23)-M119)-(M71+M87) -> -2250 | N103: =((N118+N23)-N119)-(N71+N87) -> -1815 | O103: =((O118+O23)-O119)-(O71+O87) -> -3099 | P103: =((P118+P23)-P119)-(P71+P87) -> -2938 | Q103: =((Q118+Q23)-Q119)-(Q71+Q87) -> -1737 | R103: =R$108*(SUM(M103:Q103)/SUM(M$108:Q$108)) -> -2142.6977
A104: September | M104: =((M119+M24)-M120)-(M72+M88) -> -2103 | N104: =((N119+N24)-N120)-(N72+N88) -> -2052 | O104: =((O119+O24)-O120)-(O72+O88) -> -4517 | P104: =((P119+P24)-P120)-(P72+P88) -> -1994 | Q104: =((Q119+Q24)-Q120)-(Q72+Q88) -> -2258 | R104: =R$108*(SUM(M104:Q104)/SUM(M$108:Q$108)) -> -2339.0679
A105: October | M105: =((M120+M25)-M121)-(M73+M89) -> -575 | N105: =((N120+N25)-N121)-(N73+N89) -> -786 | O105: =((O120+O25)-O121)-(O73+O89) -> -2272 | P105: =((P120+P25)-P121)-(P73+P89) -> -2099 | Q105: =((Q120+Q25)-Q121)-(Q73+Q89) -> -1594 | R105: =R$108*(SUM(M105:Q105)/SUM(M$108:Q$108)) -> -1325.9062
A106: November | M106: =((M121+M26)-M122)-(M74+M90) -> -300 | N106: =((N121+N26)-N122)-(N74+N90) -> -139 | O106: =((O121+O26)-O122)-(O74+O90) -> -2021 | P106: =((P121+P26)-P122)-(P74+P90) -> -6730 | Q106: =((Q121+Q26)-Q122)-(Q74+Q90) -> -23 | R106: =R$108*(SUM(M106:Q106)/SUM(M$108:Q$108)) -> -1667.4275
...

Sheet Fuel Ethanol
A1: CANADA - RENEWABLE FUEL SUPPLY AND DEMAND
A2: (cubic meters) | B2: 2009 | C2: 2010 | D2: 2011 | E2: 2012 | F2: 2013 | G2: 2014 | H2: 2015 | I2: 2016 | J2: 2017 | K2: 2018 | L2: 2019 | M2: 2020 | N2: 2021 | O2: 2022 | P2: 2023 | Q2: 2024 | R2: 2025 | S2: 2026 | T2: 2027 | U2: 2028 | V2: 2029 | W2: 2030 | X2: 2031 | Y2: 2032 | Z2: 2033 | AA2: 2034 | AB2: 2035 | AC2: 2036 | AD2: 2037 | AE2: 2038 | AF2: 2039 | AG2: 2040 | AH2: 2041 | AI2: 2042 | AJ2: 2043 | AK2: 2044 | AL2: 2045 | AM2: 2046 | AN2: 2047 | AO2: 2048 | AP2: 2049 | AQ2: 2050
A3: Beginning Stocks | M3: 14893 | N3: =M10 -> 19153 | O3: =N10 -> 19662 | P3: =O10 -> 26067 | Q3: =P10 -> 28150 | R3: =Q10 -> 29597 | S3: =R10 -> 30000 | T3: =S10 -> 30000 | U3: =T10 -> 30000 | ... AQ3: =AP10 -> 30000
A4: Production | C4: 1530000 | D4: 1790000 | E4: 1780000 | F4: 1800000 | G4: 1845000 | H4: 1815000 | I4: 1860000 | J4: 1890000 | K4: 1900000 | L4: =L38 -> 1209968 | M4: =M38 -> 1623228 | N4: =N38 -> 1642471 | O4: =O38 -> 1691553 | P4: =P38 -> 1716798 | Q4: =Q38 -> 1757444 | R4: =R12*R13*1000000+162500 -> 1665251.2 | S4: =S12*S13*1000000+225000 -> 1615044.9 | T4: =T12*T13*1000000+262500 -> 1583042.6 | U4: =U12*U13*1000000+280000 -> 1567529.1 | V4: =V12*V13*1000000+297500 -> 1552840.8 | W4: =W12*W13*1000000+314500 -> 1538457.3 | X4: =X12*X13*1000000+331500 -> 1524858.4 | Y4: =Y12*Y13*1000000+348500 -> 1512024.4 | Z4: =Z12*Z13*1000000+365000 -> 1499436.3 | AA4: =AA12*AA13*1000000+380000 -> 1486075.4 | AB4: =AB12*AB13*1000000+395000 -> 1473423.5 | AC4: =AC12*AC13*1000000+410000 -> 1461462.9 | AD4: =AD12*AD13*1000000+425000 -> 1450176.4 | AE4: =AE12*AE13*1000000+438000 -> 1437547 | AF4: =AF12*AF13*1000000+452000 -> 1426558.3 | AG4: =AG12*AG13*1000000+465000 -> 1415194.3 | AH4: =AH12*AH13*1000000+480000 -> 1406439.5 | AI4: =AI12*AI13*1000000+491000 -> 1394278.5 | AJ4: =AJ12*AJ13*1000000+503500 -> 1384196.5 | AK4: =AK12*AK13*1000000+516000 -> 1374679.1 | AL4: =AL12*AL13*1000000+528000 -> 1365212.1 | AM4: =AM12*AM13*1000000+540000 -> 1356281.8 | AN4: =AN12*AN13*1000000+550000 -> 1345874.8 | AO4: =AO12*AO13*1000000+561500 -> 1337477.9 | AP4: =AP12*AP13*1000000+572500 -> 1329078.5 | AQ4: =AQ12*AQ13*1000000+582500 -> 1320164
A5: Imports | B5: =B54 -> 297357.28 | C5: =C54 -> 553853.06 | D5: =D54 -> 1008480.1 | E5: =E54 -> 1087013.4 | F5: =F54 -> 1118542.3 | G5: =G54 -> 1204183.8 | H5: =H54 -> 1270910.2 | I5: =I54 -> 1241617.3 | ... Q5: =Q54 -> 2730714.5 | R5: =R4/R21 -> 2561925 | S5: =S4/S21 -> 2484684.4 | T5: =T4/T21 -> 2435450.2 | U5: =U4/U21 -> 2411583.2 | V5: =V4/V21 -> 2388985.9 | W5: =W4/W21 -> 2366857.4 | X5: =X4/X21 -> 2345936 | Y5: =Y4/Y21 -> 2326191.4 | ... AQ5: =AQ4/AQ21 -> 2031021.5
A6: Total Supply | H6: =SUM(H3:H5) -> 3085910.2 | I6: =SUM(I3:I5) -> 3101617.3 | J6: =SUM(J3:J5) -> 3192393.3 | K6: =SUM(K3:K5) -> 3299796.2 | L6: =SUM(L3:L5) -> 2492937 | M6: =SUM(M3:M5) -> 2926907.2 | N6: =SUM(N3:N5) -> 3046898.4 | O6: =SUM(O3:O5) -> 3615054.7 | ... AQ6: =SUM(AQ3:AQ5) -> 3381185.5
A7: Domestic Use | M7: =M9-M8 -> 2764731 | N7: =N9-N8 -> 2848950.9 | O7: =O9-O8 -> 3437241.5 | P7: =P9-P8 -> 4203876.9 | Q7: =Q9-Q8 -> 4245576.4 | R7: =R9-R8 -> 4009073.2 | S7: =S9-S8 -> 3898329.3 | T7: =T9-T8 -> 3827192.9 | ... AQ7: =AQ9-AQ8 -> 3244185.5
A8: Exports | B8: =B70 -> 74348.404 | C8: =C70 -> 94006.205 | D8: =D70 -> 76964.205 | E8: =E70 -> 53978.931 | F8: =F70 -> 57964.135 | G8: =G70 -> 63449.017 | H8: =H70 -> 68189.477 | I8: =I70 -> 75783.633 | ... Q8: =Q70 -> 241135.07 | R8: =MROUND(Q8*(1+R20),100) -> 217700 | S8: =MROUND(R8*(1+S20),100) -> 201400 | T8: =MROUND(S8*(1+T20),100) -> 191300 | U8: =MROUND(T8*(1+U20),100) -> 186500 | V8: =MROUND(U8*(1+V20),100) -> 181800 | W8: =MROUND(V8*(1+W20),100) -> 177300 | X8: =MROUND(W8*(1+X20),100) -> 172900 | Y8: =MROUND(X8*(1+Y20),100) -> 168600 | ... AQ8: =MROUND(AP8*(1+AQ20),100) -> 107000
A9: Total Use | M9: =M6-M10 -> 2907754.2 | N9: =N6-N10 -> 3027236.4 | O9: =O6-O10 -> 3588987.7 | P9: =P6-P10 -> 4386792.7 | Q9: =Q6-Q10 -> 4486711.5 | R9: =R6-R10 -> 4226773.2 | S9: =S6-S10 -> 4099729.3 | T9: =T6-T10 -> 4018492.9 | ... AQ9: =AQ6-AQ10 -> 3351185.5
A10: Ending stocks | M10: =M101 -> 19153 | N10: =N101 -> 19662 | O10: =O101 -> 26067 | P10: =P101 -> 28150 | Q10: =Q101 -> 29597 | R10: 30000 | S10: 30000 | T10: 30000 | U10: 30000 | V10: 30000 | W10: 30000 | X10: 30000 | Y10: 30000 | Z10: 30000 | AA10: 30000 | AB10: 30000 | AC10: 30000 | AD10: 30000 | AE10: 30000 | AF10: 30000 | AG10: 30000 | AH10: 30000 | AI10: 30000 | AJ10: 30000 | AK10: 30000 | AL10: 30000 | AM10: 30000 | AN10: 30000 | AO10: 30000 | AP10: 30000 | AQ10: 30000
A11: No | M11: =M10/M9 -> 0.0065868704 | N11: =N10/N9 -> 0.0064950328 | O11: =O10/O9 -> 0.0072630508 | P11: =P10/P9 -> 0.0064169889 | Q11: =Q10/Q9 -> 0.0065965909 | R11: =R10/R9 -> 0.0070976129 | S11: =S10/S9 -> 0.0073175563 | T11: =T10/T9 -> 0.0074654855 | ... AQ11: =AQ10/AQ9 -> 0.0089520558
A12: Gasolien Conumption (bil gal/yr) | B12: 10.838576 | C12: 10.95065 | D12: 11.115417 | E12: 11.103823 | F12: 11.333649 | G12: 11.267416 | H12: 11.775912 | I12: 11.910583 | J12: 11.878991 | K12: 11.834056 | L12: 11.406434 | M12: 9.8438232 | N12: 10.565692 | O12: 10.998638 | P12: 11.304993 | Q12: 11.094726 | R12: 10.018342 | S12: 9.2669659 | T12: 8.8036176 | U12: 8.5835272 | V12: 8.368939 | W12: 8.1597155 | X12: 7.9557226 | Y12: 7.7568296 | Z12: 7.5629088 | AA12: 7.3738361 | AB12: 7.1894902 | AC12: 7.0097529 | AD12: 6.8345091 | AE12: 6.6636464 | AF12: 6.4970552 | AG12: 6.3346289 | AH12: 6.1762631 | AI12: 6.0218566 | AJ12: 5.8713101 | AK12: 5.7245274 | AL12: 5.5814142 | AM12: 5.4418788 | AN12: 5.3058319 | AO12: 5.1731861 | AP12: 5.0438564 | AQ12: 4.91776
A13: Implied Blending Rate | M13: =(M16/1000000)/M12 -> 0.16487679 | N13: =(N16/1000000)/N12 -> 0.15541803 | O13: =(O16/1000000)/O12 -> 0.15307195 | P13: =(P16/1000000)/P12 -> 0.15156683 | Q13: =(Q16/1000000)/Q12 -> 0.15812279 | R13: 0.15 | S13: 0.15 | T13: 0.15 | U13: 0.15 | V13: 0.15 | W13: 0.15 | X13: 0.15 | Y13: 0.15 | Z13: 0.15 | AA13: 0.15 | AB13: 0.15 | AC13: 0.15 | AD13: 0.15 | AE13: 0.15 | AF13: 0.15 | AG13: 0.15 | AH13: 0.15 | AI13: 0.15 | AJ13: 0.15 | AK13: 0.15 | AL13: 0.15 | AM13: 0.15 | AN13: 0.15 | AO13: 0.15 | AP13: 0.15 | AQ13: 0.15
A16: Shipments | M16: =M134 -> 1623018 | N16: =N134 -> 1642099 | O16: =O134 -> 1683583 | P16: =P134 -> 1713462 | Q16: =Q134 -> 1754329 | R16: =R12*1000000*R13 -> 1502751.2 | S16: =S12*1000000*S13 -> 1390044.9 | T16: =T12*1000000*T13 -> 1320542.6 | U16: =U12*1000000*U13 -> 1287529.1 | V16: =V12*1000000*V13 -> 1255340.8 | W16: =W12*1000000*W13 -> 1223957.3 | X16: =X12*1000000*X13 -> 1193358.4 | Y16: =Y12*1000000*Y13 -> 1163524.4 | ... AQ16: =AQ12*1000000*AQ13 -> 737664
A17: Losses and adjustments | M17: =M150 -> 653 | N17: =N150 -> 668 | O17: =O150 -> 3256 | P17: =P150 -> 2035 | Q17: =Q150 -> 2334 | R17: =R9-R18-R16-R8 -> 6321.9671 | S17: =S9-S18-S16-S8 -> 8284.4407 | T17: =T9-T18-T16-T8 -> 6650.2187 | U17: =U9-U18-U16-U8 -> 5083.194 | V17: =V9-V18-V16-V8 -> 4685.9218 | W17: =W9-W18-W16-W8 -> 4057.4276 | X17: =X9-X18-X16-X8 -> 4535.9919 | Y17: =Y9-Y18-Y16-Y8 -> 6091.4383 | ... AQ17: =AQ9-AQ18-AQ16-AQ8 -> 6521.5426
A18: Residual | M18: =M9-M16-M8-M17 -> 1141060 | N18: =N9-N16-N8-N17 -> 1206183.9 | O18: =O9-O16-O8-O17 -> 1750402.5 | P18: =P9-P16-P8-P17 -> 2488379.9 | Q18: =Q9-Q16-Q8-Q17 -> 2488913.4 | R18: 2500000 | S18: 2500000 | T18: 2500000 | U18: 2500000 | V18: 2500000 | W18: 2500000 | X18: 2500000 | Y18: 2500000 | Z18: 2500000 | AA18: 2500000 | AB18: 2500000 | AC18: 2500000 | AD18: 2500000 | AE18: 2500000 | AF18: 2500000 | AG18: 2500000 | AH18: 2500000 | AI18: 2500000 | AJ18: 2500000 | AK18: 2500000 | AL18: 2500000 | AM18: 2500000 | AN18: 2500000 | AO18: 2500000 | AP18: 2500000 | AQ18: 2500000
M19: =SUM(M16:M18) -> 2764731 | N19: =SUM(N16:N18) -> 2848950.9 | O19: =SUM(O16:O18) -> 3437241.5 | P19: =SUM(P16:P18) -> 4203876.9 | Q19: =SUM(Q16:Q18) -> 4245576.4 | R19: =SUM(R16:R18) -> 4009073.2 | S19: =SUM(S16:S18) -> 3898329.3 | T19: =SUM(T16:T18) -> 3827192.9 | ... Y19: =SUM(Y16:Y18) -> 3669615.9
A20: Gasoline Sales Growth | C20: =C12/B12-1 -> 0.010340263 | D20: =D12/C12-1 -> 0.015046354 | E20: =E12/D12-1 -> -0.0010430785 | F20: =F12/E12-1 -> 0.020697901 | G20: =G12/F12-1 -> -0.0058439009 | H20: =H12/G12-1 -> 0.045129783 | I20: =I12/H12-1 -> 0.011436165 | J20: =J12/I12-1 -> -0.0026524161 | ... AQ20: =AQ12/AP12-1 -> -0.025
A21: Production vs. Imports | C21: =C4/C5 -> 2.7624656 | D21: =D4/D5 -> 1.7749482 | E21: =E4/E5 -> 1.6375144 | F21: =F4/F5 -> 1.6092373 | G21: =G4/G5 -> 1.5321581 | H21: =H4/H5 -> 1.4281103 | I21: =I4/I5 -> 1.4980461 | J21: =J4/J5 -> 1.4511745 | ... Q21: =Q4/Q5 -> 0.64358395 | R21: 0.65 | S21: 0.65 | T21: 0.65 | U21: 0.65 | V21: 0.65 | W21: 0.65 | X21: 0.65 | Y21: 0.65 | Z21: 0.65 | AA21: 0.65 | AB21: 0.65 | AC21: 0.65 | AD21: 0.65 | AE21: 0.65 | AF21: 0.65 | AG21: 0.65 | AH21: 0.65 | AI21: 0.65 | AJ21: 0.65 | AK21: 0.65 | AL21: 0.65 | AM21: 0.65 | AN21: 0.65 | AO21: 0.65 | AP21: 0.65 | AQ21: 0.65
A22: Production in mgy | C22: =C4*264.17/1000000 -> 404.1801 | D22: =D4*264.17/1000000 -> 472.8643 | E22: =E4*264.17/1000000 -> 470.2226 | F22: =F4*264.17/1000000 -> 475.506 | G22: =G4*264.17/1000000 -> 487.39365 | H22: =H4*264.17/1000000 -> 479.46855 | I22: =I4*264.17/1000000 -> 491.3562 | J22: =J4*264.17/1000000 -> 499.2813 | ... R22: =R4*264.17/1000000 -> 439.90942 | S22: =R22*(1+S23) -> 462.12474 | T22: =S22*(1+T23) -> 476.80523 | U22: =T22*(1+U23) -> 483.10986 | V22: =U22*(1+V23) -> 487.9768 | W22: =V22*(1+W23) -> 491.94804 | X22: =W22*(1+X23) -> 495.38437 | Y22: =X22*(1+Y23) -> 514.3616 | Z22: =Y22*(1+Z23) -> 521.92708 | ... AQ22: =AP22*(1+AQ23) -> 698.16611
D23: =D22/C22-1 -> 0.16993464 | E23: =E22/D22-1 -> -0.0055865922 | F23: =F22/E22-1 -> 0.011235955 | G23: =G22/F22-1 -> 0.025 | H23: =H22/G22-1 -> -0.016260163 | I23: =I22/H22-1 -> 0.024793388 | J23: =J22/I22-1 -> 0.016129032 | K23: =K22/J22-1 -> 0.0052910053 | ... R23: =R22/Q22-1 -> -0.05245844 | S23: =FORECAST(S20,G23:R23,G20:R20) -> 0.050499763 | T23: =FORECAST(T20,H23:S23,H20:S20) -> 0.031767372 | U23: =FORECAST(U20,I23:T23,I20:T20) -> 0.013222654 | V23: =FORECAST(V20,J23:U23,J20:U20) -> 0.010074196 | W23: =FORECAST(W20,K23:V23,K20:V20) -> 0.0081381703 | X23: =FORECAST(X20,L23:W23,L20:W20) -> 0.0069851507 | Y23: =FORECAST(Y20,M23:X23,M20:X20) -> 0.038308088 | Z23: =FORECAST(Z20,N23:Y23,N20:Y20) -> 0.014708481 | ... AQ23: =FORECAST(AQ20,AE23:AP23,AE20:AP20) -> 0.020019531
A24: PRODUCTION
B25: =B2 -> 2009 | C25: =C2 -> 2010 | D25: =D2 -> 2011 | E25: =E2 -> 2012 | F25: =F2 -> 2013 | G25: =G2 -> 2014 | H25: =H2 -> 2015 | I25: =I2 -> 2016 | ... AQ25: =AQ2 -> 2050
A26: January | L26: 76891 | M26: =Data!$C3 -> 158166 | N26: =Data!$C15 -> 116631 | O26: =Data!$C27 -> 139729 | P26: =Data!$C39 -> 149788 | Q26: =Data!$C51 -> 148957 | R26: =Data!$C63 -> 141528 | S26: =S$38*(SUM(O26:R26)/SUM(O$38:R$38)) -> 137128.23 | T26: =T$38*(SUM(P26:S26)/SUM(P$38:S$38)) -> 135323.95 | U26: =U$38*(SUM(Q26:T26)/SUM(Q$38:T$38)) -> 133280.37 | V26: =V$38*(SUM(R26:U26)/SUM(R$38:U$38)) -> 132145.23 | W26: =W$38*(SUM(S26:V26)/SUM(S$38:V$38)) -> 130965.83 | X26: =X$38*(SUM(T26:W26)/SUM(T$38:W$38)) -> 129895.48 | Y26: =Y$38*(SUM(U26:X26)/SUM(U$38:X$38)) -> 128686.79 | Z26: =Z$38*(SUM(V26:Y26)/SUM(V$38:Y$38)) -> 127647.33 | ... AQ26: =AQ$38*(SUM(AM26:AP26)/SUM(AM$38:AP$38)) -> 112391.72
A27: February | L27: 62850 | M27: =Data!$C4 -> 149497 | N27: =Data!$C16 -> 108904 | O27: =Data!$C28 -> 128540 | P27: =Data!$C40 -> 132431 | Q27: =Data!$C52 -> 142598 | R27: =Data!$C64 -> 139170 | S27: =S$38*(SUM(O27:R27)/SUM(O$38:R$38)) -> 128318.24 | T27: =T$38*(SUM(P27:S27)/SUM(P$38:S$38)) -> 127148.28 | U27: =U$38*(SUM(Q27:T27)/SUM(Q$38:T$38)) -> 127195.04 | V27: =V$38*(SUM(R27:U27)/SUM(R$38:U$38)) -> 126004.98 | W27: =W$38*(SUM(S27:V27)/SUM(S$38:V$38)) -> 123853.3 | X27: =X$38*(SUM(T27:W27)/SUM(T$38:W$38)) -> 123173.99 | Y27: =Y$38*(SUM(U27:X27)/SUM(U$38:X$38)) -> 122314.74 | Z27: =Z$38*(SUM(V27:Y27)/SUM(V$38:Y$38)) -> 121200.94 | ... AQ27: =AQ$38*(SUM(AM27:AP27)/SUM(AM$38:AP$38)) -> 106677.75
A28: March | L28: 84270 | M28: =Data!$C5 -> 147191 | N28: =Data!$C17 -> 137014 | O28: =Data!$C29 -> 147011 | P28: =Data!$C41 -> 155281 | Q28: =Data!$C53 -> 153372 | R28: =R$38*(SUM(N28:Q28)/SUM(N$38:Q$38)) -> 144964.63 | S28: =S$38*(SUM(O28:R28)/SUM(O$38:R$38)) -> 142004.92 | T28: =T$38*(SUM(P28:S28)/SUM(P$38:S$38)) -> 139594.43 | U28: =U$38*(SUM(Q28:T28)/SUM(Q$38:T$38)) -> 137304.99 | V28: =V$38*(SUM(R28:U28)/SUM(R$38:U$38)) -> 136155.62 | W28: =W$38*(SUM(S28:V28)/SUM(S$38:V$38)) -> 135149.45 | X28: =X$38*(SUM(T28:W28)/SUM(T$38:W$38)) -> 133923.69 | Y28: =Y$38*(SUM(U28:X28)/SUM(U$38:X$38)) -> 132659.44 | ... AQ28: =AQ$38*(SUM(AM28:AP28)/SUM(AM$38:AP$38)) -> 115884.38
A29: April | L29: 119100 | M29: =Data!$C6 -> 85451 | N29: =Data!$C18 -> 130068 | O29: =Data!$C30 -> 134215 | P29: =Data!$C42 -> 134197 | Q29: =Data!$C54 -> 140027 | R29: =R$38*(SUM(N29:Q29)/SUM(N$38:Q$38)) -> 131714.81 | S29: =S$38*(SUM(O29:R29)/SUM(O$38:R$38)) -> 127707.03 | T29: =T$38*(SUM(P29:S29)/SUM(P$38:S$38)) -> 125069.12 | U29: =U$38*(SUM(Q29:T29)/SUM(Q$38:T$38)) -> 124184.28 | V29: =V$38*(SUM(R29:U29)/SUM(R$38:U$38)) -> 122828.16 | W29: =W$38*(SUM(S29:V29)/SUM(S$38:V$38)) -> 121691.64 | X29: =X$38*(SUM(T29:W29)/SUM(T$38:W$38)) -> 120626.39 | Y29: =Y$38*(SUM(U29:X29)/SUM(U$38:X$38)) -> 119650.26 | ... AQ29: =AQ$38*(SUM(AM29:AP29)/SUM(AM$38:AP$38)) -> 104444.49
A30: May | L30: 82226 | M30: =Data!$C7 -> 88331 | N30: =Data!$C19 -> 143350 | O30: =Data!$C31 -> 143661 | P30: =Data!$C43 -> 131166 | Q30: =Data!$C55 -> 144909 | R30: =R$38*(SUM(N30:Q30)/SUM(N$38:Q$38)) -> 137726.65 | S30: =S$38*(SUM(O30:R30)/SUM(O$38:R$38)) -> 131799.31 | T30: =T$38*(SUM(P30:S30)/SUM(P$38:S$38)) -> 127871.01 | U30: =U$38*(SUM(Q30:T30)/SUM(Q$38:T$38)) -> 128395.75 | V30: =V$38*(SUM(R30:U30)/SUM(R$38:U$38)) -> 126961.47 | W30: =W$38*(SUM(S30:V30)/SUM(S$38:V$38)) -> 125402.11 | X30: =X$38*(SUM(T30:W30)/SUM(T$38:W$38)) -> 124255.91 | Y30: =Y$38*(SUM(U30:X30)/SUM(U$38:X$38)) -> 123485.48 | ... AQ30: =AQ$38*(SUM(AM30:AP30)/SUM(AM$38:AP$38)) -> 107714.82
A31: June | L31: 106400 | M31: =Data!$C8 -> 129908 | N31: =Data!$C20 -> 134140 | O31: =Data!$C32 -> 138122 | P31: =Data!$C44 -> 138214 | Q31: =Data!$C56 -> 142682 | R31: =R$38*(SUM(N31:Q31)/SUM(N$38:Q$38)) -> 135298.33 | S31: =S$38*(SUM(O31:R31)/SUM(O$38:R$38)) -> 131055.44 | T31: =T$38*(SUM(P31:S31)/SUM(P$38:S$38)) -> 128257.43 | U31: =U$38*(SUM(Q31:T31)/SUM(Q$38:T$38)) -> 127208.93 | V31: =V$38*(SUM(R31:U31)/SUM(R$38:U$38)) -> 126002.22 | W31: =W$38*(SUM(S31:V31)/SUM(S$38:V$38)) -> 124792.54 | X31: =X$38*(SUM(T31:W31)/SUM(T$38:W$38)) -> 123677.13 | Y31: =Y$38*(SUM(U31:X31)/SUM(U$38:X$38)) -> 122670.15 | ... AQ31: =AQ$38*(SUM(AM31:AP31)/SUM(AM$38:AP$38)) -> 107093.63
A32: July | L32: 126724 | M32: =Data!$C9 -> 150008 | N32: =Data!$C21 -> 155200 | O32: =Data!$C33 -> 148829 | P32: =Data!$C45 -> 153288 | Q32: =Data!$C57 -> 154666 | R32: =R$38*(SUM(N32:Q32)/SUM(N$38:Q$38)) -> 149686.49 | S32: =S$38*(SUM(O32:R32)/SUM(O$38:R$38)) -> 143385.86 | T32: =T$38*(SUM(P32:S32)/SUM(P$38:S$38)) -> 140860.9 | U32: =U$38*(SUM(Q32:T32)/SUM(Q$38:T$38)) -> 139356.1 | V32: =V$38*(SUM(R32:U32)/SUM(R$38:U$38)) -> 138430.33 | W32: =W$38*(SUM(S32:V32)/SUM(S$38:V$38)) -> 136847.34 | X32: =X$38*(SUM(T32:W32)/SUM(T$38:W$38)) -> 135704.64 | Y32: =Y$38*(SUM(U32:X32)/SUM(U$38:X$38)) -> 134567.82 | ... AQ32: =AQ$38*(SUM(AM32:AP32)/SUM(AM$38:AP$38)) -> 117498.29
A33: August | L33: 113403 | M33: =Data!$C10 -> 146424 | N33: =Data!$C22 -> 148267 | O33: =Data!$C34 -> 147066 | P33: =Data!$C46 -> 151728 | Q33: =Data!$C58 -> 160518 | R33: =R$38*(SUM(N33:Q33)/SUM(N$38:Q$38)) -> 148609.3 | S33: =S$38*(SUM(O33:R33)/SUM(O$38:R$38)) -> 143729.11 | T33: =T$38*(SUM(P33:S33)/SUM(P$38:S$38)) -> 141694.8 | U33: =U$38*(SUM(Q33:T33)/SUM(Q$38:T$38)) -> 140765.28 | V33: =V$38*(SUM(R33:U33)/SUM(R$38:U$38)) -> 138794.73 | W33: =W$38*(SUM(S33:V33)/SUM(S$38:V$38)) -> 137565.8 | X33: =X$38*(SUM(T33:W33)/SUM(T$38:W$38)) -> 136517.15 | Y33: =Y$38*(SUM(U33:X33)/SUM(U$38:X$38)) -> 135375.85 | ... AQ33: =AQ$38*(SUM(AM33:AP33)/SUM(AM$38:AP$38)) -> 118145.38
A34: September | L34: 117434 | M34: =Data!$C11 -> 134745 | N34: =Data!$C23 -> 142231 | O34: =Data!$C35 -> 127518 | P34: =Data!$C47 -> 136625 | Q34: =Data!$C59 -> 136191 | R34: =R$38*(SUM(N34:Q34)/SUM(N$38:Q$38)) -> 132707.36 | S34: =S$38*(SUM(O34:R34)/SUM(O$38:R$38)) -> 126025.46 | T34: =T$38*(SUM(P34:S34)/SUM(P$38:S$38)) -> 124577.64 | U34: =U$38*(SUM(Q34:T34)/SUM(Q$38:T$38)) -> 122996.58 | V34: =V$38*(SUM(R34:U34)/SUM(R$38:U$38)) -> 122256.33 | W34: =W$38*(SUM(S34:V34)/SUM(S$38:V$38)) -> 120734.11 | X34: =X$38*(SUM(T34:W34)/SUM(T$38:W$38)) -> 119842.56 | Y34: =Y$38*(SUM(U34:X34)/SUM(U$38:X$38)) -> 118794.23 | ... AQ34: =AQ$38*(SUM(AM34:AP34)/SUM(AM$38:AP$38)) -> 103729.16
A35: October | L35: 107915 | M35: =Data!$C12 -> 139203 | N35: =Data!$C24 -> 121464 | O35: =Data!$C36 -> 138048 | P35: =Data!$C48 -> 129366 | Q35: =Data!$C60 -> 139687 | R35: =R$38*(SUM(N35:Q35)/SUM(N$38:Q$38)) -> 129283.07 | S35: =S$38*(SUM(O35:R35)/SUM(O$38:R$38)) -> 126815.76 | T35: =T$38*(SUM(P35:S35)/SUM(P$38:S$38)) -> 123078.4 | U35: =U$38*(SUM(Q35:T35)/SUM(Q$38:T$38)) -> 122845.71 | V35: =V$38*(SUM(R35:U35)/SUM(R$38:U$38)) -> 121221.86 | W35: =W$38*(SUM(S35:V35)/SUM(S$38:V$38)) -> 120272.88 | X35: =X$38*(SUM(T35:W35)/SUM(T$38:W$38)) -> 119074.05 | Y35: =Y$38*(SUM(U35:X35)/SUM(U$38:X$38)) -> 118203.7 | ... AQ35: =AQ$38*(SUM(AM35:AP35)/SUM(AM$38:AP$38)) -> 103155.99
A36: November | L36: 96916 | M36: =Data!$C13 -> 155234 | N36: =Data!$C25 -> 154607 | O36: =Data!$C37 -> 148365 | P36: =Data!$C49 -> 152552 | Q36: =Data!$C61 -> 149096 | R36: =R$38*(SUM(N36:Q36)/SUM(N$38:Q$38)) -> 147885.56 | S36: =S$38*(SUM(O36:R36)/SUM(O$38:R$38)) -> 141359.46 | T36: =T$38*(SUM(P36:S36)/SUM(P$38:S$38)) -> 138485.98 | U36: =U$38*(SUM(Q36:T36)/SUM(Q$38:T$38)) -> 136568.91 | V36: =V$38*(SUM(R36:U36)/SUM(R$38:U$38)) -> 136259.67 | W36: =W$38*(SUM(S36:V36)/SUM(S$38:V$38)) -> 134568.51 | X36: =X$38*(SUM(T36:W36)/SUM(T$38:W$38)) -> 133356.57 | Y36: =Y$38*(SUM(U36:X36)/SUM(U$38:X$38)) -> 132224.18 | ... AQ36: =AQ$38*(SUM(AM36:AP36)/SUM(AM$38:AP$38)) -> 115494.54
A37: December | L37: 115839 | M37: =Data!$C14 -> 139070 | N37: =Data!$C26 -> 150595 | O37: =Data!$C38 -> 150449 | P37: =Data!$C50 -> 152162 | Q37: =Data!$C62 -> 144741 | R37: =R38-SUM(R26:R36) -> 126677.03 | S37: =S38-SUM(S26:S36) -> 135716.06 | T37: =T38-SUM(T26:T36) -> 131080.69 | U37: =U38-SUM(U26:U36) -> 127427.13 | V37: =V38-SUM(V26:V36) -> 125780.26 | W37: =W38-SUM(W26:W36) -> 126613.84 | X37: =X38-SUM(X26:X36) -> 124810.85 | Y37: =Y38-SUM(Y26:Y36) -> 123391.79 | ... AQ37: =AQ38-SUM(AQ26:AQ36) -> 107933.84
A38: Total | L38: =SUM(L26:L37) -> 1209968 | M38: =SUM(M26:M37) -> 1623228 | N38: =SUM(N26:N37) -> 1642471 | O38: =SUM(O26:O37) -> 1691553 | P38: =SUM(P26:P37) -> 1716798 | Q38: =SUM(Q26:Q37) -> 1757444 | R38: =R4 -> 1665251.2 | S38: =S4 -> 1615044.9 | T38: =T4 -> 1583042.6 | U38: =U4 -> 1567529.1 | V38: =V4 -> 1552840.8 | W38: =W4 -> 1538457.3 | X38: =X4 -> 1524858.4 | Y38: =Y4 -> 1512024.4 | ... AQ38: =AQ4 -> 1320164
A40: IMPORTS (HS codes - 220710, 220720, divide lpa by 1,000 to get meters3)
B41: =B2 -> 2009 | C41: =C2 -> 2010 | D41: =D2 -> 2011 | E41: =E2 -> 2012 | F41: =F2 -> 2013 | G41: =G2 -> 2014 | H41: =H2 -> 2015 | I41: =I2 -> 2016 | ... AQ41: =AQ2 -> 2050
A42: January | B42: 32148.784 | C42: 29363.055 | D42: 74472.915 | E42: 80737.325 | F42: 83056.094 | G42: 68590.55 | H42: 87869.912 | I42: 79847.564 | J42: 94496.537 | K42: 84637.724 | L42: 82003.432 | M42: =Data!$N3 -> 94908.617 | N42: =Data!$N15 -> 70883.08 | O42: =Data!$N27 -> 136531.56 | P42: =Data!$N39 -> 182644.57 | Q42: =Data!$N51 -> 221982.78 | R42: =Data!$N63 -> 207598.86 | S42: =S$54*(SUM(O42:R42)/SUM(O$54:R$54)) -> 188520.65 | T42: =T$54*(SUM(P42:S42)/SUM(P$54:S$54)) -> 186630.7 | U42: =U$54*(SUM(Q42:T42)/SUM(Q$54:T$54)) -> 190024.82 | V42: =V$54*(SUM(R42:U42)/SUM(R$54:U$54)) -> 186599.49 | W42: =W$54*(SUM(S42:V42)/SUM(S$54:V$54)) -> 183047.01 | X42: =X$54*(SUM(T42:W42)/SUM(T$54:W$54)) -> 182317.95 | Y42: =Y$54*(SUM(U42:X42)/SUM(U$54:X$54)) -> 181429.97 | Z42: =Z$54*(SUM(V42:Y42)/SUM(V$54:Y$54)) -> 179446.11 | ... AQ42: =AQ$54*(SUM(AM42:AP42)/SUM(AM$54:AP$54)) -> 157994.48
A43: February | B43: 16448.894 | C43: 30071.148 | D43: 54180.815 | E43: 63253.252 | F43: 72689.808 | G43: 60021.797 | H43: 70657.642 | I43: 76358.402 | J43: 96558.84 | K43: 94949.339 | L43: 68507.214 | M43: =Data!$N4 -> 112277.58 | N43: =Data!$N16 -> 70695.404 | O43: =Data!$N28 -> 116790.78 | P43: =Data!$N40 -> 162738.57 | Q43: =Data!$N52 -> 184534.93 | R43: =Data!$N64 -> 194783.23 | S43: =S$54*(SUM(O43:R43)/SUM(O$54:R$54)) -> 165883.24 | T43: =T$54*(SUM(P43:S43)/SUM(P$54:S$54)) -> 165000.12 | U43: =U$54*(SUM(Q43:T43)/SUM(Q$54:T$54)) -> 167702.73 | V43: =V$54*(SUM(R43:U43)/SUM(R$54:U$54)) -> 167425.65 | W43: =W$54*(SUM(S43:V43)/SUM(S$54:V$54)) -> 162164.68 | X43: =X$54*(SUM(T43:W43)/SUM(T$54:W$54)) -> 161794.99 | Y43: =Y$54*(SUM(U43:X43)/SUM(U$54:X$54)) -> 161159.1 | Z43: =Z$54*(SUM(V43:Y43)/SUM(V$54:Y$54)) -> 159663.82 | ... AQ43: =AQ$54*(SUM(AM43:AP43)/SUM(AM$54:AP$54)) -> 140371.72
A44: March | B44: 34027.53 | C44: 36738.422 | D44: 64414.5 | E44: 80832.092 | F44: 81064.967 | G44: 87665.096 | H44: 89851.397 | I44: 83442.957 | J44: 96204.04 | K44: 97447.156 | L44: 89432.814 | M44: =Data!$N5 -> 110572.91 | N44: =Data!$N17 -> 110386.19 | O44: =Data!$N29 -> 125499.44 | P44: =Data!$N41 -> 273200.92 | Q44: =Data!$N53 -> 183540.05 | R44: =Data!$N65 -> 246498.4 | S44: =S$54*(SUM(O44:R44)/SUM(O$54:R$54)) -> 208658.11 | T44: =T$54*(SUM(P44:S44)/SUM(P$54:S$54)) -> 212536.66 | U44: =U$54*(SUM(Q44:T44)/SUM(Q$54:T$54)) -> 201005.11 | V44: =V$54*(SUM(R44:U44)/SUM(R$54:U$54)) -> 209761.76 | W44: =W$54*(SUM(S44:V44)/SUM(S$54:V$54)) -> 202571.2 | X44: =X$54*(SUM(T44:W44)/SUM(T$54:W$54)) -> 201757.17 | Y44: =Y$54*(SUM(U44:X44)/SUM(U$54:X$54)) -> 199305.72 | Z44: =Z$54*(SUM(V44:Y44)/SUM(V$54:Y$54)) -> 199020.77 | ... AQ44: =AQ$54*(SUM(AM44:AP44)/SUM(AM$54:AP$54)) -> 174610.83
A45: April | B45: 23107.793 | C45: 44746.762 | D45: 79304.506 | E45: 64626.492 | F45: 80681.442 | G45: 133829.68 | H45: 108140.05 | I45: 84144.067 | J45: 76778.265 | K45: 109358.09 | L45: 125593.27 | M45: =Data!$N6 -> 53356.275 | N45: =Data!$N18 -> 105097.25 | O45: =Data!$N30 -> 145242.42 | P45: =Data!$N42 -> 196419.6 | Q45: =Data!$N54 -> 254428.47 | R45: =R$54*(SUM(N45:Q45)/SUM(N$54:Q$54)) -> 206673.93 | S45: =S$54*(SUM(O45:R45)/SUM(O$54:R$54)) -> 202118.34 | T45: =T$54*(SUM(P45:S45)/SUM(P$54:S$54)) -> 200357.05 | U45: =U$54*(SUM(Q45:T45)/SUM(Q$54:T$54)) -> 203920.08 | V45: =V$54*(SUM(R45:U45)/SUM(R$54:U$54)) -> 196329.24 | W45: =W$54*(SUM(S45:V45)/SUM(S$54:V$54)) -> 195452.4 | X45: =X$54*(SUM(T45:W45)/SUM(T$54:W$54)) -> 194473.28 | Y45: =Y$54*(SUM(U45:X45)/SUM(U$54:X$54)) -> 193212.26 | ... AQ45: =AQ$54*(SUM(AM45:AP45)/SUM(AM$54:AP$54)) -> 168221.17
A46: May | B46: 19205.609 | C46: 37777.117 | D46: 65675.099 | E46: 82865.654 | F46: 95845.992 | G46: 108818.46 | H46: 100374.71 | I46: 115115.74 | J46: 127088.9 | K46: 125514.84 | L46: 89557.818 | M46: =Data!$N7 -> 68132.247 | N46: =Data!$N19 -> 103236.03 | O46: =Data!$N31 -> 157236.46 | P46: =Data!$N43 -> 255115.98 | Q46: =Data!$N55 -> 264117.17 | R46: =R$54*(SUM(N46:Q46)/SUM(N$54:Q$54)) -> 229816.94 | S46: =S$54*(SUM(O46:R46)/SUM(O$54:R$54)) -> 228182.92 | T46: =T$54*(SUM(P46:S46)/SUM(P$54:S$54)) -> 227764.47 | U46: =U$54*(SUM(Q46:T46)/SUM(Q$54:T$54)) -> 224299.32 | V46: =V$54*(SUM(R46:U46)/SUM(R$54:U$54)) -> 219750.12 | W46: =W$54*(SUM(S46:V46)/SUM(S$54:V$54)) -> 219136.83 | X46: =X$54*(SUM(T46:W46)/SUM(T$54:W$54)) -> 217654.92 | Y46: =Y$54*(SUM(U46:X46)/SUM(U$54:X$54)) -> 215381.81 | ... AQ46: =AQ$54*(SUM(AM46:AP46)/SUM(AM$54:AP$54)) -> 188041.85
A47: June | B47: 24339.278 | C47: 36002.826 | D47: 89925.659 | E47: 97732.609 | F47: 98698.369 | G47: 115183.69 | H47: 123031.87 | I47: 103797.6 | J47: 97644.086 | K47: 130887.85 | L47: 112991.28 | M47: =Data!$N8 -> 111304.13 | N47: =Data!$N20 -> 127174.95 | O47: =Data!$N32 -> 154693.88 | P47: =Data!$N44 -> 195468.09 | Q47: =Data!$N56 -> 173908.74 | R47: =R$54*(SUM(N47:Q47)/SUM(N$54:Q$54)) -> 191953.58 | S47: =S$54*(SUM(O47:R47)/SUM(O$54:R$54)) -> 180279.09 | T47: =T$54*(SUM(P47:S47)/SUM(P$54:S$54)) -> 172847.51 | U47: =U$54*(SUM(Q47:T47)/SUM(Q$54:T$54)) -> 169777.73 | V47: =V$54*(SUM(R47:U47)/SUM(R$54:U$54)) -> 172614.43 | W47: =W$54*(SUM(S47:V47)/SUM(S$54:V$54)) -> 169349.23 | X47: =X$54*(SUM(T47:W47)/SUM(T$54:W$54)) -> 167241.73 | Y47: =Y$54*(SUM(U47:X47)/SUM(U$54:X$54)) -> 166023.81 | ... AQ47: =AQ$54*(SUM(AM47:AP47)/SUM(AM$54:AP$54)) -> 145161.18
A48: July | B48: 25699.49 | C48: 50540.996 | D48: 110080.2 | E48: 96857.535 | F48: 110862.4 | G48: 113895.76 | H48: 132944.41 | I48: 113237.2 | J48: 151089.24 | K48: 144969.28 | L48: 132580.54 | M48: =Data!$N9 -> 117285.9 | N48: =Data!$N21 -> 112227.38 | O48: =Data!$N33 -> 157883.91 | P48: =Data!$N45 -> 293358.31 | Q48: =Data!$N57 -> 238981.24 | R48: =R$54*(SUM(N48:Q48)/SUM(N$54:Q$54)) -> 236521.06 | S48: =S$54*(SUM(O48:R48)/SUM(O$54:R$54)) -> 233333.78 | T48: =T$54*(SUM(P48:S48)/SUM(P$54:S$54)) -> 233582.23 | U48: =U$54*(SUM(Q48:T48)/SUM(Q$54:T$54)) -> 222537.01 | V48: =V$54*(SUM(R48:U48)/SUM(R$54:U$54)) -> 223591.96 | W48: =W$54*(SUM(S48:V48)/SUM(S$54:V$54)) -> 222313.87 | X48: =X$54*(SUM(T48:W48)/SUM(T$54:W$54)) -> 220360.33 | Y48: =Y$54*(SUM(U48:X48)/SUM(U$54:X$54)) -> 217328.66 | ... AQ48: =AQ$54*(SUM(AM48:AP48)/SUM(AM$54:AP$54)) -> 190298.5
A49: August | B49: 23182.155 | C49: 52717.602 | D49: 86746.726 | E49: 117513.41 | F49: 105595.66 | G49: 112958.25 | H49: 111992.2 | I49: 134883.62 | J49: 119648.33 | K49: 117640.96 | L49: 120578.33 | M49: =Data!$N10 -> 138643.58 | N49: =Data!$N22 -> 130033.9 | O49: =Data!$N34 -> 201135.23 | P49: =Data!$N46 -> 239400.2 | Q49: =Data!$N58 -> 219191.7 | R49: =R$54*(SUM(N49:Q49)/SUM(N$54:Q$54)) -> 232780.76 | S49: =S$54*(SUM(O49:R49)/SUM(O$54:R$54)) -> 224713.76 | T49: =T$54*(SUM(P49:S49)/SUM(P$54:S$54)) -> 213512.98 | U49: =U$54*(SUM(Q49:T49)/SUM(Q$54:T$54)) -> 210206.3 | V49: =V$54*(SUM(R49:U49)/SUM(R$54:U$54)) -> 212783.84 | W49: =W$54*(SUM(S49:V49)/SUM(S$54:V$54)) -> 209694.44 | X49: =X$54*(SUM(T49:W49)/SUM(T$54:W$54)) -> 206721.94 | Y49: =Y$54*(SUM(U49:X49)/SUM(U$54:X$54)) -> 205250.27 | ... AQ49: =AQ$54*(SUM(AM49:AP49)/SUM(AM$54:AP$54)) -> 179454.3
A50: September | B50: 18410.095 | C50: 57900.224 | D50: 93009.981 | E50: 86508.207 | F50: 94635.846 | G50: 101153.92 | H50: 142767.32 | I50: 107231.33 | J50: 112970.56 | K50: 138777.16 | L50: 123917.23 | M50: =Data!$N11 -> 123555.01 | N50: =Data!$N23 -> 137686.41 | O50: =Data!$N35 -> 163468.55 | P50: =Data!$N47 -> 231954.09 | Q50: =Data!$N59 -> 263322.7 | R50: =R$54*(SUM(N50:Q50)/SUM(N$54:Q$54)) -> 234746.94 | S50: =S$54*(SUM(O50:R50)/SUM(O$54:R$54)) -> 224961.6 | T50: =T$54*(SUM(P50:S50)/SUM(P$54:S$54)) -> 222579.18 | U50: =U$54*(SUM(Q50:T50)/SUM(Q$54:T$54)) -> 223290.77 | V50: =V$54*(SUM(R50:U50)/SUM(R$54:U$54)) -> 218667.11 | W50: =W$54*(SUM(S50:V50)/SUM(S$54:V$54)) -> 216580.67 | X50: =X$54*(SUM(T50:W50)/SUM(T$54:W$54)) -> 215252.77 | Y50: =Y$54*(SUM(U50:X50)/SUM(U$54:X$54)) -> 213657.99 | ... AQ50: =AQ$54*(SUM(AM50:AP50)/SUM(AM$54:AP$54)) -> 186285.12
A51: October | B51: 17704.917 | C51: 56185.28 | D51: 77663.612 | E51: 102742.23 | F51: 90024.89 | G51: 96288.827 | H51: 103754.79 | I51: 133935.27 | J51: 132695 | K51: 125559.82 | L51: 114043.75 | M51: =Data!$N12 -> 135922.41 | N51: =Data!$N24 -> 142367.39 | O51: =Data!$N36 -> 170523.3 | P51: =Data!$N48 -> 282177.92 | Q51: =Data!$N60 -> 247893.65 | R51: =R$54*(SUM(N51:Q51)/SUM(N$54:Q$54)) -> 248461.73 | S51: =S$54*(SUM(O51:R51)/SUM(O$54:R$54)) -> 238951.47 | T51: =T$54*(SUM(P51:S51)/SUM(P$54:S$54)) -> 237145.97 | U51: =U$54*(SUM(Q51:T51)/SUM(Q$54:T$54)) -> 229629.18 | V51: =V$54*(SUM(R51:U51)/SUM(R$54:U$54)) -> 230404.77 | W51: =W$54*(SUM(S51:V51)/SUM(S$54:V$54)) -> 227935.1 | X51: =X$54*(SUM(T51:W51)/SUM(T$54:W$54)) -> 226001.09 | Y51: =Y$54*(SUM(U51:X51)/SUM(U$54:X$54)) -> 223482.44 | ... AQ51: =AQ$54*(SUM(AM51:AP51)/SUM(AM$54:AP$54)) -> 195456.61
A52: November | B52: 22688.388 | C52: 58427.381 | D52: 91510.156 | E52: 95257.562 | F52: 108039.17 | G52: 89975.405 | H52: 113550.38 | I52: 109313.01 | J52: 103751.42 | K52: 114116.45 | L52: 102998.53 | M52: =Data!$N13 -> 134392.94 | N52: =Data!$N25 -> 141202.57 | O52: =Data!$N37 -> 186583.61 | P52: =Data!$N49 -> 192161.45 | Q52: =Data!$N61 -> 231729.54 | R52: =R$54*(SUM(N52:Q52)/SUM(N$54:Q$54)) -> 221555.6 | S52: =S$54*(SUM(O52:R52)/SUM(O$54:R$54)) -> 209486.81 | T52: =T$54*(SUM(P52:S52)/SUM(P$54:S$54)) -> 199260 | U52: =U$54*(SUM(Q52:T52)/SUM(Q$54:T$54)) -> 203555.05 | V52: =V$54*(SUM(R52:U52)/SUM(R$54:U$54)) -> 201348.86 | W52: =W$54*(SUM(S52:V52)/SUM(S$54:V$54)) -> 198112.74 | X52: =X$54*(SUM(T52:W52)/SUM(T$54:W$54)) -> 195992.28 | Y52: =Y$54*(SUM(U52:X52)/SUM(U$54:X$54)) -> 195372.32 | ... AQ52: =AQ$54*(SUM(AM52:AP52)/SUM(AM$54:AP$54)) -> 170255.86
A53: December | B53: 40394.347 | C53: 63382.244 | D53: 121495.95 | E53: 118087 | F53: 97347.658 | G53: 115802.42 | H53: 85975.535 | I53: 100310.56 | J53: 93468.088 | K53: 115937.51 | L53: 120764.84 | M53: =Data!$N14 -> 88434.599 | N53: =Data!$N26 -> 134283.87 | O53: =Data!$N38 -> 188250.53 | P53: =Data!$N50 -> 167437.98 | Q53: =Data!$N62 -> 247083.48 | R53: =R54-SUM(R42:R52) -> 110533.94 | S53: =S54-SUM(S42:S52) -> 179594.66 | T53: =T54-SUM(T42:T52) -> 164233.34 | U53: =U54-SUM(U42:U52) -> 165635.11 | V53: =V54-SUM(V42:V52) -> 149708.68 | W53: =W54-SUM(W42:W52) -> 160499.25 | X53: =X54-SUM(X42:X52) -> 156367.54 | Y53: =Y54-SUM(Y42:Y52) -> 154587.07 | ... AQ53: =AQ54-SUM(AQ42:AQ52) -> 134869.93
A54: Total | B54: =SUM(B42:B53) -> 297357.28 | C54: =SUM(C42:C53) -> 553853.06 | D54: =SUM(D42:D53) -> 1008480.1 | E54: =SUM(E42:E53) -> 1087013.4 | F54: =SUM(F42:F53) -> 1118542.3 | G54: =SUM(G42:G53) -> 1204183.8 | H54: =SUM(H42:H53) -> 1270910.2 | I54: =SUM(I42:I53) -> 1241617.3 | ... Q54: =SUM(Q42:Q53) -> 2730714.5 | R54: =R5 -> 2561925 | S54: =S5 -> 2484684.4 | T54: =T5 -> 2435450.2 | U54: =U5 -> 2411583.2 | V54: =V5 -> 2388985.9 | W54: =W5 -> 2366857.4 | X54: =X5 -> 2345936 | Y54: =Y5 -> 2326191.4 | ... AQ54: =AQ5 -> 2031021.5
A56: EXPORTS
B57: =B2 -> 2009 | C57: =C2 -> 2010 | D57: =D2 -> 2011 | E57: =E2 -> 2012 | F57: =F2 -> 2013 | G57: =G2 -> 2014 | H57: =H2 -> 2015 | I57: =I2 -> 2016 | ... AQ57: =AQ2 -> 2050
A58: January | B58: 5635.738 | C58: 8910.259 | D58: 6054.982 | E58: 5955.74 | F58: 4200.83 | G58: 4823.497 | H58: 6899.181 | I58: 5466.709 | J58: 7316.414 | K58: 7616.538 | L58: 7157.314 | M58: =Data!$O3 -> 7426.356 | N58: =Data!$O15 -> 6872.65 | O58: =Data!$O27 -> 6723.073 | P58: =Data!$O39 -> 5629.16 | Q58: =Data!$O51 -> 7666.645 | R58: =Data!$O63 -> 22394.393 | S58: =S$70*(SUM(O58:R58)/SUM(O$70:R$70)) -> 10765.047 | T58: =T$70*(SUM(P58:S58)/SUM(P$70:S$70)) -> 10540.093 | U58: =U$70*(SUM(Q58:T58)/SUM(Q$70:T$70)) -> 11250.026 | V58: =V$70*(SUM(R58:U58)/SUM(R$70:U$70)) -> 12535.864 | W58: =W$70*(SUM(S58:V58)/SUM(S$70:V$70)) -> 10505.44 | X58: =X$70*(SUM(T58:W58)/SUM(T$70:W$70)) -> 10518.867 | Y58: =Y$70*(SUM(U58:X58)/SUM(U$70:X$70)) -> 10514.961 | Z58: =Z$70*(SUM(V58:Y58)/SUM(V$70:Y$70)) -> 10342.494 | ... AQ58: =AQ$70*(SUM(AM58:AP58)/SUM(AM$70:AP$70)) -> 6628.89
A59: February | B59: 4251.881 | C59: 9014.713 | D59: 6220.115 | E59: 5237.539 | F59: 4079.752 | G59: 4734.725 | H59: 5808.303 | I59: 6026.516 | J59: 6873.383 | K59: 7315.715 | L59: 6119.349 | M59: =Data!$O4 -> 5814.774 | N59: =Data!$O16 -> 20679.539 | O59: =Data!$O28 -> 17518.948 | P59: =Data!$O40 -> 16439.5 | Q59: =Data!$O52 -> 23655.391 | R59: =Data!$O64 -> 8416.134 | S59: =S$70*(SUM(O59:R59)/SUM(O$70:R$70)) -> 16759.277 | T59: =T$70*(SUM(P59:S59)/SUM(P$70:S$70)) -> 14808.985 | U59: =U$70*(SUM(Q59:T59)/SUM(Q$70:T$70)) -> 13938.146 | V59: =V$70*(SUM(R59:U59)/SUM(R$70:U$70)) -> 12301.566 | W59: =W$70*(SUM(S59:V59)/SUM(S$70:V$70)) -> 13468.27 | X59: =X$70*(SUM(T59:W59)/SUM(T$70:W$70)) -> 12791.401 | Y59: =Y$70*(SUM(U59:X59)/SUM(U$70:X$70)) -> 12319.271 | Z59: =Z$70*(SUM(V59:Y59)/SUM(V$70:Y$70)) -> 11939.417 | ... AQ59: =AQ$70*(SUM(AM59:AP59)/SUM(AM$70:AP$70)) -> 7851.0927
A60: March | B60: 5741.218 | C60: 9303.188 | D60: 7256.083 | E60: 4577.359 | F60: 5365.778 | G60: 5022.436 | H60: 6952.304 | I60: 5312.039 | J60: 8313.873 | K60: 7251.418 | L60: 6386.024 | M60: =Data!$O5 -> 12713.091 | N60: =Data!$O17 -> 6559.138 | O60: =Data!$O29 -> 7686.396 | P60: =Data!$O41 -> 5274.701 | Q60: =Data!$O53 -> 26098.922 | R60: =Data!$O65 -> 34277.392 | S60: =S$70*(SUM(O60:R60)/SUM(O$70:R$70)) -> 18614.001 | T60: =T$70*(SUM(P60:S60)/SUM(P$70:S$70)) -> 19118.64 | U60: =U$70*(SUM(Q60:T60)/SUM(Q$70:T$70)) -> 21487.453 | V60: =V$70*(SUM(R60:U60)/SUM(R$70:U$70)) -> 21329.957 | W60: =W$70*(SUM(S60:V60)/SUM(S$70:V$70)) -> 18766.786 | X60: =X$70*(SUM(T60:W60)/SUM(T$70:W$70)) -> 18935.433 | Y60: =Y$70*(SUM(U60:X60)/SUM(U$70:X$70)) -> 18894.376 | Z60: =Z$70*(SUM(V60:Y60)/SUM(V$70:Y$70)) -> 18285.934 | ... AQ60: =AQ$70*(SUM(AM60:AP60)/SUM(AM$70:AP$70)) -> 11832.217
A61: April | B61: 5536.164 | C61: 8155.943 | D61: 7953.206 | E61: 4833.638 | F61: 4870.422 | G61: 4762.271 | H61: 5857.468 | I61: 4794.504 | J61: 7001.841 | K61: 6148.153 | L61: 5385.212 | M61: =Data!$O6 -> 4930.68 | N61: =Data!$O18 -> 20526.968 | O61: =Data!$O30 -> 17496.312 | P61: =Data!$O42 -> 20157.172 | Q61: =Data!$O54 -> 9131.709 | R61: =R$70*(SUM(N61:Q61)/SUM(N$70:Q$70)) -> 19432.697 | S61: =S$70*(SUM(O61:R61)/SUM(O$70:R$70)) -> 16806.972 | T61: =T$70*(SUM(P61:S61)/SUM(P$70:S$70)) -> 14867.578 | U61: =U$70*(SUM(Q61:T61)/SUM(Q$70:T$70)) -> 13193.309 | V61: =V$70*(SUM(R61:U61)/SUM(R$70:U$70)) -> 14669.144 | W61: =W$70*(SUM(S61:V61)/SUM(S$70:V$70)) -> 13871.105 | X61: =X$70*(SUM(T61:W61)/SUM(T$70:W$70)) -> 13280.413 | Y61: =Y$70*(SUM(U61:X61)/SUM(U$70:X$70)) -> 12909.333 | ... AQ61: =AQ$70*(SUM(AM61:AP61)/SUM(AM$70:AP$70)) -> 8281.7955
A62: May | B62: 7397.514 | C62: 8724.693 | D62: 6290.446 | E62: 5804.644 | F62: 5400.604 | G62: 5089.629 | H62: 4205.783 | I62: 5479.166 | J62: 5873.874 | K62: 4226.638 | L62: 4542.631 | M62: =Data!$O7 -> 15642.688 | N62: =Data!$O19 -> 18244.368 | O62: =Data!$O31 -> 19803.794 | P62: =Data!$O43 -> 16869.317 | Q62: =Data!$O55 -> 24891.785 | R62: =R$70*(SUM(N62:Q62)/SUM(N$70:Q$70)) -> 23040.55 | S62: =S$70*(SUM(O62:R62)/SUM(O$70:R$70)) -> 21473.976 | T62: =T$70*(SUM(P62:S62)/SUM(P$70:S$70)) -> 19574.822 | U62: =U$70*(SUM(Q62:T62)/SUM(Q$70:T$70)) -> 19488.312 | V62: =V$70*(SUM(R62:U62)/SUM(R$70:U$70)) -> 19066.908 | W62: =W$70*(SUM(S62:V62)/SUM(S$70:V$70)) -> 18546.376 | X62: =X$70*(SUM(T62:W62)/SUM(T$70:W$70)) -> 17990.708 | Y62: =Y$70*(SUM(U62:X62)/SUM(U$70:X$70)) -> 17620.825 | ... AQ62: =AQ$70*(SUM(AM62:AP62)/SUM(AM$70:AP$70)) -> 11174.083
A63: June | B63: 6645.946 | C63: 10865.701 | D63: 7503.356 | E63: 4190.709 | F63: 4502.622 | G63: 6302.214 | H63: 5139.858 | I63: 6678.536 | J63: 7569.292 | K63: 5814.285 | L63: 6011.106 | M63: =Data!$O8 -> 16964.847 | N63: =Data!$O20 -> 20268.494 | O63: =Data!$O32 -> 5013.251 | P63: =Data!$O44 -> 16858.907 | Q63: =Data!$O56 -> 17304.012 | R63: =R$70*(SUM(N63:Q63)/SUM(N$70:Q$70)) -> 17161.388 | S63: =S$70*(SUM(O63:R63)/SUM(O$70:R$70)) -> 14299.214 | T63: =T$70*(SUM(P63:S63)/SUM(P$70:S$70)) -> 14889.126 | U63: =U$70*(SUM(Q63:T63)/SUM(Q$70:T$70)) -> 13941.202 | V63: =V$70*(SUM(R63:U63)/SUM(R$70:U$70)) -> 13754.412 | W63: =W$70*(SUM(S63:V63)/SUM(S$70:V$70)) -> 13252.99 | X63: =X$70*(SUM(T63:W63)/SUM(T$70:W$70)) -> 13101.294 | Y63: =Y$70*(SUM(U63:X63)/SUM(U$70:X$70)) -> 12683.108 | ... AQ63: =AQ$70*(SUM(AM63:AP63)/SUM(AM$70:AP$70)) -> 8061.1602
A64: July | B64: 7398.493 | C64: 7460.757 | D64: 6609.336 | E64: 4740.311 | F64: 4379.712 | G64: 6304.89 | H64: 4821.196 | I64: 6522.128 | J64: 7231.941 | K64: 6759.906 | L64: 7256.876 | M64: =Data!$O9 -> 15926.055 | N64: =Data!$O21 -> 6681.383 | O64: =Data!$O33 -> 17620.254 | P64: =Data!$O45 -> 6490.756 | Q64: =Data!$O57 -> 9690.777 | R64: =R$70*(SUM(N64:Q64)/SUM(N$70:Q$70)) -> 11687.296 | S64: =S$70*(SUM(O64:R64)/SUM(O$70:R$70)) -> 11545.728 | T64: =T$70*(SUM(P64:S64)/SUM(P$70:S$70)) -> 8942.6521 | U64: =U$70*(SUM(Q64:T64)/SUM(Q$70:T$70)) -> 9169.4328 | V64: =V$70*(SUM(R64:U64)/SUM(R$70:U$70)) -> 9432.226 | W64: =W$70*(SUM(S64:V64)/SUM(S$70:V$70)) -> 9107.3114 | X64: =X$70*(SUM(T64:W64)/SUM(T$70:W$70)) -> 8599.6275 | Y64: =Y$70*(SUM(U64:X64)/SUM(U$70:X$70)) -> 8520.0133 | ... AQ64: =AQ$70*(SUM(AM64:AP64)/SUM(AM$70:AP$70)) -> 5414.3776
A65: August | B65: 9461.328 | C65: 5843.245 | D65: 5563.167 | E65: 4171.405 | F65: 5624.543 | G65: 5058.2 | H65: 5845.216 | I65: 7721.733 | J65: 8164.129 | K65: 6641.38 | L65: 11496.346 | M65: =Data!$O10 -> 5705.319 | N65: =Data!$O22 -> 22090.998 | O65: =Data!$O34 -> 6101.332 | P65: =Data!$O46 -> 21560.033 | Q65: =Data!$O58 -> 26393.871 | R65: =R$70*(SUM(N65:Q65)/SUM(N$70:Q$70)) -> 21983.051 | S65: =S$70*(SUM(O65:R65)/SUM(O$70:R$70)) -> 19299.519 | T65: =T$70*(SUM(P65:S65)/SUM(P$70:S$70)) -> 20246.599 | U65: =U$70*(SUM(Q65:T65)/SUM(Q$70:T$70)) -> 19256.572 | V65: =V$70*(SUM(R65:U65)/SUM(R$70:U$70)) -> 18429.976 | W65: =W$70*(SUM(S65:V65)/SUM(S$70:V$70)) -> 17993.892 | X65: =X$70*(SUM(T65:W65)/SUM(T$70:W$70)) -> 17814.88 | Y65: =Y$70*(SUM(U65:X65)/SUM(U$70:X$70)) -> 17246.083 | ... AQ65: =AQ$70*(SUM(AM65:AP65)/SUM(AM$70:AP$70)) -> 10941.579
A66: September | B66: 5164.149 | C66: 4328.775 | D66: 6535.039 | E66: 1819.179 | F66: 3705.741 | G66: 4518.816 | H66: 4671.934 | I66: 7387.831 | J66: 8374.828 | K66: 5733.163 | L66: 7452.37 | M66: =Data!$O11 -> 19069.946 | N66: =Data!$O23 -> 17127.453 | O66: =Data!$O35 -> 17856.342 | P66: =Data!$O47 -> 22189.611 | Q66: =Data!$O59 -> 10274.927 | R66: =R$70*(SUM(N66:Q66)/SUM(N$70:Q$70)) -> 19472.009 | S66: =S$70*(SUM(O66:R66)/SUM(O$70:R$70)) -> 17714.354 | T66: =T$70*(SUM(P66:S66)/SUM(P$70:S$70)) -> 15802.886 | U66: =U$70*(SUM(Q66:T66)/SUM(Q$70:T$70)) -> 13855.881 | V66: =V$70*(SUM(R66:U66)/SUM(R$70:U$70)) -> 15249.648 | W66: =W$70*(SUM(S66:V66)/SUM(S$70:V$70)) -> 14590.036 | X66: =X$70*(SUM(T66:W66)/SUM(T$70:W$70)) -> 13960.215 | Y66: =Y$70*(SUM(U66:X66)/SUM(U$70:X$70)) -> 13529.248 | ... AQ66: =AQ$70*(SUM(AM66:AP66)/SUM(AM$70:AP$70)) -> 8686.2865
A67: October | B67: 5157.185 | C67: 7965.424 | D67: 6467.258 | E67: 4199.038 | F67: 4952.794 | G67: 5105.442 | H67: 6303.257 | I67: 6865.772 | J67: 7748.837 | K67: 5122.678 | L67: 5955.021 | M67: =Data!$O12 -> 17988.743 | N67: =Data!$O24 -> 5567.306 | O67: =Data!$O36 -> 4985.886 | P67: =Data!$O48 -> 6043.879 | Q67: =Data!$O60 -> 26071.746 | R67: =R$70*(SUM(N67:Q67)/SUM(N$70:Q$70)) -> 12318.282 | S67: =S$70*(SUM(O67:R67)/SUM(O$70:R$70)) -> 12543.394 | T67: =T$70*(SUM(P67:S67)/SUM(P$70:S$70)) -> 12927.411 | U67: =U$70*(SUM(Q67:T67)/SUM(Q$70:T$70)) -> 13986.559 | V67: =V$70*(SUM(R67:U67)/SUM(R$70:U$70)) -> 11811.786 | W67: =W$70*(SUM(S67:V67)/SUM(S$70:V$70)) -> 11944.836 | X67: =X$70*(SUM(T67:W67)/SUM(T$70:W$70)) -> 11888.92 | Y67: =Y$70*(SUM(U67:X67)/SUM(U$70:X$70)) -> 11646.447 | ... AQ67: =AQ$70*(SUM(AM67:AP67)/SUM(AM$70:AP$70)) -> 7299.1882
A68: November | B68: 5995.883 | C68: 7470.879 | D68: 6199.753 | E68: 4401.821 | F68: 5362.838 | G68: 5620.768 | H68: 4906.277 | I68: 5861.449 | J68: 7541.571 | K68: 4036.01 | L68: 5626.693 | M68: =Data!$O13 -> 4343.367 | N68: =Data!$O25 -> 16988.506 | O68: =Data!$O37 -> 14845.02 | P68: =Data!$O49 -> 21123.801 | Q68: =Data!$O61 -> 25598.999 | R68: =R$70*(SUM(N68:Q68)/SUM(N$70:Q$70)) -> 22678.833 | S68: =S$70*(SUM(O68:R68)/SUM(O$70:R$70)) -> 21382.91 | T68: =T$70*(SUM(P68:S68)/SUM(P$70:S$70)) -> 20597.836 | U68: =U$70*(SUM(Q68:T68)/SUM(Q$70:T$70)) -> 19768.093 | V68: =V$70*(SUM(R68:U68)/SUM(R$70:U$70)) -> 19260.824 | W68: =W$70*(SUM(S68:V68)/SUM(S$70:V$70)) -> 18873.868 | X68: =X$70*(SUM(T68:W68)/SUM(T$70:W$70)) -> 18418.723 | Y68: =Y$70*(SUM(U68:X68)/SUM(U$70:X$70)) -> 17909.264 | ... AQ68: =AQ$70*(SUM(AM68:AP68)/SUM(AM$70:AP$70)) -> 11377.58
A69: December | B69: 5962.905 | C69: 5962.628 | D69: 4311.464 | E69: 4047.548 | F69: 5518.499 | G69: 6106.129 | H69: 6778.7 | I69: 7667.25 | J69: 6089.491 | K69: 6485.345 | L69: 9226.026 | M69: =Data!$O14 -> 16497.334 | N69: =Data!$O26 -> 16678.695 | O69: =Data!$O38 -> 16095.573 | P69: =Data!$O50 -> 24278.956 | Q69: =Data!$O62 -> 34356.29 | R69: =R70-SUM(R58:R68) -> 4837.9744 | S69: =S70-SUM(S58:S68) -> 20195.608 | T69: =T70-SUM(T58:T68) -> 18983.372 | U69: =U70-SUM(U58:U68) -> 17165.012 | V69: =V70-SUM(V58:V68) -> 13957.688 | W69: =W70-SUM(W58:W68) -> 16379.091 | X69: =X70-SUM(X58:X68) -> 15599.518 | Y69: =Y70-SUM(Y58:Y68) -> 14807.071 | ... AQ69: =AQ70-SUM(AQ58:AQ68) -> 9451.75
A70: Total | B70: =SUM(B58:B69) -> 74348.404 | C70: =SUM(C58:C69) -> 94006.205 | D70: =SUM(D58:D69) -> 76964.205 | E70: =SUM(E58:E69) -> 53978.931 | F70: =SUM(F58:F69) -> 57964.135 | G70: =SUM(G58:G69) -> 63449.017 | H70: =SUM(H58:H69) -> 68189.477 | I70: =SUM(I58:I69) -> 75783.633 | ... Q70: =SUM(Q58:Q69) -> 241135.07 | R70: =R8 -> 217700 | S70: =S8 -> 201400 | T70: =T8 -> 191300 | U70: =U8 -> 186500 | V70: =V8 -> 181800 | W70: =W8 -> 177300 | X70: =X8 -> 172900 | Y70: =Y8 -> 168600 | ... AQ70: =AQ8 -> 107000
A72: DOMESTIC USE
B73: =B2 -> 2009 | C73: =C2 -> 2010 | D73: =D2 -> 2011 | E73: =E2 -> 2012 | F73: =F2 -> 2013 | G73: =G2 -> 2014 | H73: =H2 -> 2015 | I73: =I2 -> 2016 | ... AQ73: =AQ2 -> 2050
A74: January | M74: =L101+M26+M42-M58-M90 -> 247304.26 | N74: =M101+N26+N42-N58-N90 -> 179668.43 | O74: =N101+O26+O42-O58-O90 -> 267771.49 | P74: =O101+P26+P42-P58-P90 -> 329041.41 | Q74: =P101+Q26+Q42-Q58-Q90 -> 366629.14 | R74: =Q101+R26+R42-R58-R90 -> 329775.47 | S74: =S$86*(SUM(N74:R74)/SUM(N$86:R$86)) -> 306315.31 | T74: =T$86*(SUM(O74:S74)/SUM(O$86:S$86)) -> 309270 | U74: =U$86*(SUM(P74:T74)/SUM(P$86:T$86)) -> 308352.19 | V74: =V$86*(SUM(Q74:U74)/SUM(Q$86:U$86)) -> 308127.05 | W74: =W$86*(SUM(R74:V74)/SUM(R$86:V$86)) -> 301886.86 | X74: =X$86*(SUM(S74:W74)/SUM(S$86:W$86)) -> 298449.85 | Y74: =Y$86*(SUM(T74:X74)/SUM(T$86:X$86)) -> 297789.34 | Z74: =Z$86*(SUM(U74:Y74)/SUM(U$86:Y$86)) -> 295792.26 | ... AQ74: =AQ$86*(SUM(AL74:AP74)/SUM(AL$86:AP$86)) -> 263152.51
A75: February | M75: =M90+M27+M43-M59-M91 -> 256149.81 | N75: =N90+N27+N43-N59-N91 -> 162474.86 | O75: =O90+O27+O43-O59-O91 -> 223105.83 | P75: =P90+P27+P43-P59-P91 -> 279621.07 | Q75: =Q90+Q27+Q43-Q59-Q91 -> 302318.54 | R75: =R90+R27+R43-R59-R91 -> 319936.1 | S75: =S$86*(SUM(N75:R75)/SUM(N$86:R$86)) -> 267751.63 | T75: =T$86*(SUM(O75:S75)/SUM(O$86:S$86)) -> 269285.25 | U75: =U$86*(SUM(P75:T75)/SUM(P$86:T$86)) -> 270373.78 | V75: =V$86*(SUM(Q75:U75)/SUM(Q$86:U$86)) -> 271867.62 | W75: =W$86*(SUM(R75:V75)/SUM(R$86:V$86)) -> 270453.07 | X75: =X$86*(SUM(S75:W75)/SUM(S$86:W$86)) -> 262607.48 | Y75: =Y$86*(SUM(T75:X75)/SUM(T$86:X$86)) -> 262372.99 | Z75: =Z$86*(SUM(U75:Y75)/SUM(U$86:Y$86)) -> 261238.95 | ... AQ75: =AQ$86*(SUM(AL75:AP75)/SUM(AL$86:AP$86)) -> 232522.66
A76: March | M76: =M91+M28+M44-M60-M92 -> 239271.82 | N76: =N91+N28+N44-N60-N92 -> 239261.05 | O76: =O91+O28+O44-O60-O92 -> 268666.04 | P76: =P91+P28+P44-P60-P92 -> 423021.22 | Q76: =Q91+Q28+Q44-Q60-Q92 -> 308327.13 | R76: =R$86*(SUM(M76:Q76)/SUM(M$86:Q$86)) -> 338642.49 | S76: =S$86*(SUM(N76:R76)/SUM(N$86:R$86)) -> 328158.76 | T76: =T$86*(SUM(O76:S76)/SUM(O$86:S$86)) -> 322279.16 | U76: =U$86*(SUM(P76:T76)/SUM(P$86:T$86)) -> 323271.08 | V76: =V$86*(SUM(Q76:U76)/SUM(Q$86:U$86)) -> 308191.05 | W76: =W$86*(SUM(R76:V76)/SUM(R$86:V$86)) -> 313233.43 | X76: =X$86*(SUM(S76:W76)/SUM(S$86:W$86)) -> 310353.6 | Y76: =Y$86*(SUM(T76:X76)/SUM(T$86:X$86)) -> 307788.4 | ... AQ76: =AQ$86*(SUM(AL76:AP76)/SUM(AL$86:AP$86)) -> 271713.87
A77: April | M77: =M92+M29+M45-M61-M93 -> 130670.6 | N77: =N92+N29+N45-N61-N93 -> 215915.28 | O77: =O92+O29+O45-O61-O93 -> 256711.11 | P77: =P92+P29+P45-P61-P93 -> 306679.43 | Q77: =Q92+Q29+Q45-Q61-Q93 -> 386434.76 | R77: =R$86*(SUM(M77:Q77)/SUM(M$86:Q$86)) -> 296926.54 | S77: =S$86*(SUM(N77:R77)/SUM(N$86:R$86)) -> 304190.11 | T77: =T$86*(SUM(O77:S77)/SUM(O$86:S$86)) -> 299874.95 | U77: =U$86*(SUM(P77:T77)/SUM(P$86:T$86)) -> 299534.81 | V77: =V$86*(SUM(Q77:U77)/SUM(Q$86:U$86)) -> 301779.28 | W77: =W$86*(SUM(R77:V77)/SUM(R$86:V$86)) -> 290379.52 | X77: =X$86*(SUM(S77:W77)/SUM(S$86:W$86)) -> 291018.96 | Y77: =Y$86*(SUM(T77:X77)/SUM(T$86:X$86)) -> 289301.37 | ... AQ77: =AQ$86*(SUM(AL77:AP77)/SUM(AL$86:AP$86)) -> 255677.25
A78: May | M78: =M93+M30+M46-M62-M94 -> 148001.56 | N78: =N93+N30+N46-N62-N94 -> 222168.66 | O78: =O93+O30+O46-O62-O94 -> 285158.66 | P78: =P93+P30+P46-P62-P94 -> 372737.67 | Q78: =Q93+Q30+Q46-Q62-Q94 -> 387909.38 | R78: =R$86*(SUM(M78:Q78)/SUM(M$86:Q$86)) -> 324311.32 | S78: =S$86*(SUM(N78:R78)/SUM(N$86:R$86)) -> 331146.82 | T78: =T$86*(SUM(O78:S78)/SUM(O$86:S$86)) -> 328939.72 | U78: =U$86*(SUM(P78:T78)/SUM(P$86:T$86)) -> 327896.49 | V78: =V$86*(SUM(Q78:U78)/SUM(Q$86:U$86)) -> 323313.68 | W78: =W$86*(SUM(R78:V78)/SUM(R$86:V$86)) -> 316145.42 | X78: =X$86*(SUM(S78:W78)/SUM(S$86:W$86)) -> 316639.66 | Y78: =Y$86*(SUM(T78:X78)/SUM(T$86:X$86)) -> 314736.43 | ... AQ78: =AQ$86*(SUM(AL78:AP78)/SUM(AL$86:AP$86)) -> 277744.47
A79: June | M79: =M94+M31+M47-M63-M95 -> 223366.28 | N79: =N94+N31+N47-N63-N95 -> 247155.45 | O79: =O94+O31+O47-O63-O95 -> 294341.63 | P79: =P94+P31+P47-P63-P95 -> 317820.18 | Q79: =Q94+Q31+Q47-Q63-Q95 -> 297971.73 | R79: =R$86*(SUM(M79:Q79)/SUM(M$86:Q$86)) -> 316221.58 | S79: =S$86*(SUM(N79:R79)/SUM(N$86:R$86)) -> 306445.22 | T79: =T$86*(SUM(O79:S79)/SUM(O$86:S$86)) -> 296367.27 | U79: =U$86*(SUM(P79:T79)/SUM(P$86:T$86)) -> 288396.05 | V79: =V$86*(SUM(Q79:U79)/SUM(Q$86:U$86)) -> 286269.82 | W79: =W$86*(SUM(R79:V79)/SUM(R$86:V$86)) -> 288716.11 | X79: =X$86*(SUM(S79:W79)/SUM(S$86:W$86)) -> 285266.87 | Y79: =Y$86*(SUM(T79:X79)/SUM(T$86:X$86)) -> 281969.96 | ... AQ79: =AQ$86*(SUM(AL79:AP79)/SUM(AL$86:AP$86)) -> 249455.97
A80: July | M80: =M95+M32+M48-M64-M96 -> 251351.84 | N80: =N95+N32+N48-N64-N96 -> 258684 | O80: =O95+O32+O48-O64-O96 -> 284444.66 | P80: =P95+P32+P48-P64-P96 -> 438954.55 | Q80: =Q95+Q32+Q48-Q64-Q96 -> 388019.46 | R80: =R$86*(SUM(M80:Q80)/SUM(M$86:Q$86)) -> 371373.59 | S80: =S$86*(SUM(N80:R80)/SUM(N$86:R$86)) -> 362173.9 | T80: =T$86*(SUM(O80:S80)/SUM(O$86:S$86)) -> 356724.59 | U80: =U$86*(SUM(P80:T80)/SUM(P$86:T$86)) -> 360253.35 | V80: =V$86*(SUM(Q80:U80)/SUM(Q$86:U$86)) -> 349620.87 | W80: =W$86*(SUM(R80:V80)/SUM(R$86:V$86)) -> 347948.9 | X80: =X$86*(SUM(S80:W80)/SUM(S$86:W$86)) -> 345683.89 | Y80: =Y$86*(SUM(T80:X80)/SUM(T$86:X$86)) -> 343478.82 | ... AQ80: =AQ$86*(SUM(AL80:AP80)/SUM(AL$86:AP$86)) -> 303416.71
A81: August | M81: =M96+M33+M49-M65-M97 -> 278624.26 | N81: =N96+N33+N49-N65-N97 -> 260055.9 | O81: =O96+O33+O49-O65-O97 -> 343398.9 | P81: =P96+P33+P49-P65-P97 -> 372367.16 | Q81: =Q96+Q33+Q49-Q65-Q97 -> 348567.83 | R81: =R$86*(SUM(M81:Q81)/SUM(M$86:Q$86)) -> 367150.03 | S81: =S$86*(SUM(N81:R81)/SUM(N$86:R$86)) -> 351788.65 | T81: =T$86*(SUM(O81:S81)/SUM(O$86:S$86)) -> 344796.13 | U81: =U$86*(SUM(P81:T81)/SUM(P$86:T$86)) -> 335342.07 | V81: =V$86*(SUM(Q81:U81)/SUM(Q$86:U$86)) -> 332335.14 | W81: =W$86*(SUM(R81:V81)/SUM(R$86:V$86)) -> 334663.3 | X81: =X$86*(SUM(S81:W81)/SUM(S$86:W$86)) -> 330547.62 | Y81: =Y$86*(SUM(T81:X81)/SUM(T$86:X$86)) -> 327371.13 | ... AQ81: =AQ$86*(SUM(AL81:AP81)/SUM(AL$86:AP$86)) -> 289401.78
A82: September | M82: =M97+M34+M50-M66-M98 -> 242223.06 | N82: =N97+N34+N50-N66-N98 -> 265002.96 | O82: =O97+O34+O50-O66-O98 -> 276534.21 | P82: =P97+P34+P50-P66-P98 -> 344695.48 | Q82: =Q97+Q34+Q50-Q66-Q98 -> 393491.77 | R82: =R$86*(SUM(M82:Q82)/SUM(M$86:Q$86)) -> 348582.76 | S82: =S$86*(SUM(N82:R82)/SUM(N$86:R$86)) -> 338638.19 | T82: =T$86*(SUM(O82:S82)/SUM(O$86:S$86)) -> 329070.92 | U82: =U$86*(SUM(P82:T82)/SUM(P$86:T$86)) -> 329669.19 | V82: =V$86*(SUM(Q82:U82)/SUM(Q$86:U$86)) -> 330777.36 | W82: =W$86*(SUM(R82:V82)/SUM(R$86:V$86)) -> 324095.49 | X82: =X$86*(SUM(S82:W82)/SUM(S$86:W$86)) -> 321466.57 | Y82: =Y$86*(SUM(T82:X82)/SUM(T$86:X$86)) -> 319057.56 | ... AQ82: =AQ$86*(SUM(AL82:AP82)/SUM(AL$86:AP$86)) -> 282491.09
A83: October | M83: =M98+M35+M51-M67-M99 -> 256556.66 | N83: =N98+N35+N51-N67-N99 -> 254599.08 | O83: =O98+O35+O51-O67-O99 -> 297541.41 | P83: =P98+P35+P51-P67-P99 -> 408353.04 | Q83: =Q98+Q35+Q51-Q67-Q99 -> 355773.91 | R83: =R$86*(SUM(M83:Q83)/SUM(M$86:Q$86)) -> 360235.41 | S83: =S$86*(SUM(N83:R83)/SUM(N$86:R$86)) -> 348661.41 | T83: =T$86*(SUM(O83:S83)/SUM(O$86:S$86)) -> 342339.15 | U83: =U$86*(SUM(P83:T83)/SUM(P$86:T$86)) -> 341109.35 | V83: =V$86*(SUM(Q83:U83)/SUM(Q$86:U$86)) -> 332425.37 | W83: =W$86*(SUM(R83:V83)/SUM(R$86:V$86)) -> 333379.6 | X83: =X$86*(SUM(S83:W83)/SUM(S$86:W$86)) -> 330351.04 | Y83: =Y$86*(SUM(T83:X83)/SUM(T$86:X$86)) -> 327745.84 | ... AQ83: =AQ$86*(SUM(AL83:AP83)/SUM(AL$86:AP$86)) -> 289585.3
A84: November | M84: =M99+M36+M52-M68-M100 -> 279759.57 | N84: =N99+N36+N52-N68-N100 -> 274062.07 | O84: =O99+O36+O52-O68-O100 -> 325412.59 | P84: =P99+P36+P52-P68-P100 -> 319220.65 | Q84: =Q99+Q36+Q52-Q68-Q100 -> 352443.54 | R84: =R$86*(SUM(M84:Q84)/SUM(M$86:Q$86)) -> 355213.61 | S84: =S$86*(SUM(N84:R84)/SUM(N$86:R$86)) -> 338231.66 | T84: =T$86*(SUM(O84:S84)/SUM(O$86:S$86)) -> 326862.79 | U84: =U$86*(SUM(P84:T84)/SUM(P$86:T$86)) -> 317924.06 | V84: =V$86*(SUM(Q84:U84)/SUM(Q$86:U$86)) -> 321501.81 | W84: =W$86*(SUM(R84:V84)/SUM(R$86:V$86)) -> 320808.7 | X84: =X$86*(SUM(S84:W84)/SUM(S$86:W$86)) -> 316228.53 | Y84: =Y$86*(SUM(T84:X84)/SUM(T$86:X$86)) -> 312861.38 | ... AQ84: =AQ$86*(SUM(AL84:AP84)/SUM(AL$86:AP$86)) -> 277125.93
A85: December | M85: =M100+M37+M53-M69-M101 -> 215092.26 | N85: =N100+N37+N53-N69-N101 -> 269903.18 | O85: =O100+O37+O53-O69-O101 -> 314154.96 | P85: =P100+P37+P53-P69-P101 -> 291365.02 | Q85: =Q100+Q37+Q53-Q69-Q101 -> 357689.19 | R85: =R86-SUM(R74:R84) -> 280704.3 | S85: =S86-SUM(S74:S84) -> 314827.65 | T85: =T86-SUM(T74:T84) -> 301382.92 | U85: =U86-SUM(U74:U84) -> 290489.85 | V85: =V86-SUM(V74:V84) -> 293817.73 | W85: =W86-SUM(W74:W84) -> 286304.35 | X85: =X86-SUM(X74:X84) -> 289280.32 | Y85: =Y86-SUM(Y74:Y84) -> 285142.64 | ... AQ85: =AQ86-SUM(AQ74:AQ84) -> 251898.01
A86: Total | M86: =SUM(M74:M85) -> 2768372 | N86: =SUM(N74:N85) -> 2848950.9 | O86: =SUM(O74:O85) -> 3437241.5 | P86: =SUM(P74:P85) -> 4203876.9 | Q86: =SUM(Q74:Q85) -> 4245576.4 | R86: =R7 -> 4009073.2 | S86: =S7 -> 3898329.3 | T86: =T7 -> 3827192.9 | U86: =U7 -> 3792612.3 | V86: =V7 -> 3760026.8 | W86: =W7 -> 3728014.8 | X86: =X7 -> 3697894.4 | Y86: =Y7 -> 3669615.9 | ... AQ86: =AQ7 -> 3244185.5
A88: END-OF-MONTH STOCKS
B89: =B2 -> 2009 | C89: =C2 -> 2010 | D89: =D2 -> 2011 | E89: =E2 -> 2012 | F89: =F2 -> 2013 | G89: =G2 -> 2014 | H89: =H2 -> 2015 | I89: =I2 -> 2016 | ... AQ89: =AQ2 -> 2050
A90: January | M90: =Data!$L3 -> 16878 | N90: =Data!$L15 -> 20126 | O90: =Data!$L27 -> 21428 | P90: =Data!$L39 -> 23829 | Q90: =Data!$L51 -> 24794 | R90: =Data!$L63 -> 26554 | S90: =R101+S26+S42-S58-S74 -> 38568.524 | T90: =S101+T26+T42-T58-T74 -> 32144.551 | U90: =T101+U26+U42-U58-U74 -> 33702.979 | V90: =U101+V26+V42-V58-V74 -> 28081.804 | W90: =V101+W26+W42-W58-W74 -> 31620.543 | X90: =W101+X26+X42-X58-X74 -> 33244.709 | Y90: =X101+Y26+Y42-Y58-Y74 -> 31812.461 | Z90: =Y101+Z26+Z42-Z58-Z74 -> 30958.681 | ... AQ90: =AP101+AQ26+AQ42-AQ58-AQ74 -> 30604.798
A91: February | M91: =Data!$L4 -> 16688 | N91: =Data!$L16 -> 16571 | O91: =Data!$L28 -> 26134 | P91: =Data!$L40 -> 22938 | Q91: =Data!$L52 -> 25953 | R91: =Data!$L64 -> 32155 | S91: =S90+S27+S43-S59-S75 -> 48259.097 | T91: =T90+T27+T43-T59-T75 -> 40198.724 | U91: =U90+U27+U43-U59-U75 -> 44288.821 | V91: =V90+V27+V43-V59-V75 -> 37343.242 | W91: =W90+W27+W43-W59-W75 -> 33717.174 | X91: =X90+X27+X43-X59-X75 -> 42814.815 | Y91: =Y90+Y27+Y43-Y59-Y75 -> 40594.043 | Z91: =Z90+Z27+Z43-Z59-Z75 -> 38645.078 | ... AQ91: =AQ90+AQ27+AQ43-AQ59-AQ75 -> 37280.517
A92: March | M92: =Data!$L5 -> 22467 | N92: =Data!$L17 -> 18151 | O92: =Data!$L29 -> 22292 | P92: =Data!$L41 -> 23124 | Q92: =Data!$L53 -> 28439 | R92: =R91+R28+R44-R60-R76 -> 50698.147 | S92: =S91+S28+S44-S60-S76 -> 52149.37 | T92: =T91+T28+T44-T60-T76 -> 50932.022 | U92: =U91+U28+U44-U60-U76 -> 37840.386 | V92: =V91+V28+V44-V60-V76 -> 53739.62 | W92: =W91+W28+W44-W60-W76 -> 39437.613 | X92: =X91+X28+X44-X60-X76 -> 49206.641 | Y92: =Y91+Y28+Y44-Y60-Y76 -> 45876.425 | ... AQ92: =AQ91+AQ28+AQ44-AQ60-AQ76 -> 44229.641
A93: April | M93: =Data!$L6 -> 25673 | N93: =Data!$L18 -> 16874 | O93: =Data!$L30 -> 27542 | P93: =Data!$L42 -> 26904 | Q93: =Data!$L54 -> 27328 | R93: =R92+R29+R45-R61-R77 -> 72727.65 | S93: =S92+S29+S45-S61-S77 -> 60977.654 | T93: =T92+T29+T45-T61-T77 -> 61615.658 | U93: =U92+U29+U45-U61-U77 -> 53216.624 | V93: =V92+V29+V45-V61-V77 -> 56448.596 | W93: =W92+W29+W45-W61-W77 -> 52331.033 | X93: =X92+X29+X45-X61-X77 -> 60006.929 | Y93: =Y92+Y29+Y45-Y61-Y77 -> 56528.248 | ... AQ93: =AQ92+AQ29+AQ45-AQ61-AQ77 -> 52936.26
A94: May | M94: =Data!$L7 -> 18492 | N94: =Data!$L19 -> 23047 | O94: =Data!$L31 -> 23477 | P94: =Data!$L43 -> 23579 | Q94: =Data!$L55 -> 23553 | R94: =R93+R30+R46-R62-R78 -> 92919.368 | S94: =S93+S30+S46-S62-S78 -> 68339.091 | T94: =T93+T30+T46-T62-T78 -> 68736.585 | U94: =U93+U30+U46-U62-U78 -> 58526.887 | V94: =V93+V30+V46-V62-V78 -> 60779.599 | W94: =W93+W30+W46-W62-W78 -> 62178.167 | X94: =X93+X30+X46-X62-X78 -> 67287.392 | Y94: =Y93+Y30+Y46-Y62-Y78 -> 63038.279 | ... AQ94: =AQ93+AQ30+AQ46-AQ62-AQ78 -> 59774.38
A95: June | M95: =Data!$L8 -> 19373 | N95: =Data!$L20 -> 16938 | O95: =Data!$L32 -> 16938 | P95: =Data!$L44 -> 22582 | Q95: =Data!$L56 -> 24868 | R95: =R94+R31+R47-R63-R79 -> 86788.316 | S95: =S94+S31+S47-S63-S79 -> 58929.185 | T95: =T94+T31+T47-T63-T79 -> 58585.134 | U95: =U94+U31+U47-U63-U79 -> 53176.303 | V95: =V94+V31+V47-V63-V79 -> 59372.018 | W95: =W94+W31+W47-W63-W79 -> 54350.836 | X95: =X94+X31+X47-X63-X79 -> 59838.089 | Y95: =Y94+Y31+Y47-Y63-Y79 -> 57079.177 | ... AQ95: =AQ94+AQ31+AQ47-AQ63-AQ79 -> 54512.066
A96: July | M96: =Data!$L9 -> 19389 | N96: =Data!$L21 -> 19000 | O96: =Data!$L33 -> 21586 | P96: =Data!$L45 -> 23783 | Q96: =Data!$L57 -> 20805 | R96: =R95+R32+R48-R64-R80 -> 89934.979 | S96: =S95+S32+S48-S64-S80 -> 61929.199 | T96: =T95+T32+T48-T64-T80 -> 67361.024 | U96: =U95+U32+U48-U64-U80 -> 45646.626 | V96: =V95+V32+V48-V64-V80 -> 62341.209 | W96: =W95+W32+W48-W64-W80 -> 56455.835 | X96: =X95+X32+X48-X64-X80 -> 61619.538 | Y96: =Y95+Y32+Y48-Y64-Y80 -> 56976.82 | ... AQ96: =AQ95+AQ32+AQ48-AQ64-AQ80 -> 53477.765
A97: August | M97: =Data!$L10 -> 20127 | N97: =Data!$L22 -> 15154 | O97: =Data!$L34 -> 20287 | P97: =Data!$L46 -> 20984 | Q97: =Data!$L58 -> 25553 | R97: =R96+R33+R49-R65-R81 -> 82191.954 | S97: =S96+S33+S49-S65-S81 -> 59283.897 | T97: =T96+T33+T49-T65-T81 -> 57526.074 | U97: =U96+U33+U49-U65-U81 -> 42019.559 | V97: =V96+V33+V49-V65-V81 -> 63154.669 | W97: =W96+W33+W49-W65-W81 -> 51058.883 | X97: =X96+X33+X49-X65-X81 -> 56496.126 | Y97: =Y96+Y33+Y49-Y65-Y81 -> 52985.722 | ... AQ97: =AQ96+AQ33+AQ49-AQ65-AQ81 -> 50734.084
A98: September | M98: =Data!$L11 -> 17134 | N98: =Data!$L23 -> 12941 | O98: =Data!$L35 -> 16883 | P98: =Data!$L47 -> 22678 | Q98: =Data!$L59 -> 21300 | R98: =R97+R34+R50-R66-R82 -> 81591.486 | S98: =S97+S34+S50-S66-S82 -> 53918.417 | T98: =T97+T34+T50-T66-T82 -> 59809.091 | U98: =U97+U34+U50-U66-U82 -> 44781.838 | V98: =V97+V34+V50-V66-V82 -> 58051.099 | W98: =W97+W34+W50-W66-W82 -> 49688.137 | X98: =X97+X34+X50-X66-X82 -> 56164.662 | Y98: =Y97+Y34+Y50-Y66-Y82 -> 52851.134 | ... AQ98: =AQ97+AQ34+AQ50-AQ66-AQ82 -> 49570.993
A99: October | M99: =Data!$L12 -> 17714 | N99: =Data!$L24 -> 16606 | O99: =Data!$L36 -> 22927 | P99: =Data!$L48 -> 19825 | Q99: =Data!$L60 -> 27035 | R99: =R98+R35+R51-R67-R83 -> 86782.593 | S99: =S98+S35+S51-S67-S83 -> 58480.843 | T99: =T98+T35+T51-T67-T83 -> 64766.905 | U99: =U98+U35+U51-U67-U83 -> 42160.818 | V99: =V98+V35+V51-V67-V83 -> 65440.57 | W99: =W98+W35+W51-W67-W83 -> 52571.668 | X99: =X98+X35+X51-X67-X83 -> 58999.844 | Y99: =Y98+Y35+Y51-Y67-Y83 -> 55144.991 | ... AQ99: =AQ98+AQ35+AQ51-AQ67-AQ83 -> 51299.113
A100: November | M100: =Data!$L13 -> 23238 | N100: =Data!$L25 -> 21365 | O100: =Data!$L37 -> 17618 | P100: =Data!$L49 -> 24194 | Q100: =Data!$L61 -> 29818 | R100: =R99+R36+R52-R68-R84 -> 78331.308 | S100: =S99+S36+S52-S68-S84 -> 49712.54 | T100: =T99+T36+T52-T68-T84 -> 55052.258 | U100: =U99+U36+U52-U68-U84 -> 44592.627 | V100: =V99+V36+V52-V68-V84 -> 62286.477 | W100: =W99+W36+W52-W68-W84 -> 45570.351 | X100: =X99+X36+X52-X68-X84 -> 53701.443 | Y100: =Y99+Y36+Y52-Y68-Y84 -> 51970.848 | ... AQ100: =AQ99+AQ36+AQ52-AQ68-AQ84 -> 48545.994
A101: December | L101: 18534 | M101: =Data!$L14 -> 19153 | N101: =Data!$L26 -> 19662 | O101: =Data!$L38 -> 26067 | P101: =Data!$L50 -> 28150 | Q101: =Data!$L62 -> 29597 | R101: =R100+R37+R53-R69-R85 -> 30000 | S101: =S100+S37+S53-S69-S85 -> 30000 | T101: =T100+T37+T53-T69-T85 -> 30000 | U101: =U100+U37+U53-U69-U85 -> 30000 | V101: =V100+V37+V53-V69-V85 -> 30000 | W101: =W100+W37+W53-W69-W85 -> 30000 | X101: =X100+X37+X53-X69-X85 -> 30000 | Y101: =Y100+Y37+Y53-Y69-Y85 -> 30000 | ... AQ101: =AQ100+AQ37+AQ53-AQ69-AQ85 -> 30000
A103: FUEL USE
A104: GASOLINE USE
B105: =B2 -> 2009 | C105: =C2 -> 2010 | D105: =D2 -> 2011 | E105: =E2 -> 2012 | F105: =F2 -> 2013 | G105: =G2 -> 2014 | H105: =H2 -> 2015 | I105: =I2 -> 2016 | ... AQ105: =AQ2 -> 2050
A106: January
A107: February | R107: =R90+R27+R43-R59-R139 -> 351530.1
...

Sheet Ethanol Plant List
B1: Co-Op Ethanol Complex | C1: Enerkem Alberta Biofuels LP | D1: Greenfield Global | E1: Greenfield Global | F1: Greenfield Global | G1: Greenfield Global | H1: Husky Energy (Cenovus) | I1: Husky Energy (Cenovus) | J1: IGCP Ethanol Inc | K1: Kawartha Ethanol Inc | L1: North West Pure Alcohol & Sprirts | M1: Permolex Ltd. | N1: Pound-Maker Agventures Ltd. | O1: Suncor | P1: Total Capacity
R2: Monthly Production | S2: Monthly Production | T2: Capacity Utilization
B3: SK | C3: AB | D3: Chatham, ON | E3: Johnston, ON | F3: Tiverton, ON | G3: Varennes. QC | H3: Lloydminster, AB | I3: Minnedosa, MB | J3: ON | K3: ON | L3: SK | M3: AB | N3: SK | O3: St. Clair, ON
B4: 40 | C4: 10 | D4: 56 | E4: 70 | F4: 9 | G4: 50 | H4: 39 | I4: 39 | J4: 100 | K4: 26 | L4: 7 | M4: 12 | N4: 10 | O4: 105 | R4: cubic meters | S4: million gallons | AE4: DDG Production | AF4: Cereal Grain Use | AG4: Corn Use | AH4: Corn Use | AI4: DDG Production | AJ4: Implied DG Yield | AK4: Implied DCO Production | AL4: DCO Limit | AM4: DCO Yield (lbs/bu) | AN4: Ethanol Production | AO4: Ethanol Yield
B5: Other Grains | C5: Other | D5: Corn | E5: Corn | F5: Corn | G5: Corn | H5: Other Grains | I5: Corn | J5: Corn | K5: Corn | L5: Other Grains | M5: Other Grains | N5: Other Grains | O5: Corn | R5: (change red to Fuel Ethanol Sheet) | V5: Corn | W5: Other Grains | X5: Other | Y5: Total | AA5: Corn | AB5: Other Grains | AC5: Other
AE6: (tonnes) | AF6: (tonnes) | AG6: (tonnes) | AH6: (mbu) | AI6: (mlbs) | AJ6: (lb/bu) | AK6: (mlbs) | AL6: 0.1 | AM6: 0.95 | AN6: (tonnes)
A7: ='BD Plant List'!A6 -> 39814
A8: ='BD Plant List'!A7 -> 39845
A9: ='BD Plant List'!A8 -> 39873
A10: ='BD Plant List'!A9 -> 39904
A11: ='BD Plant List'!A10 -> 39934
A12: ='BD Plant List'!A11 -> 39965
A13: ='BD Plant List'!A12 -> 39995
A14: ='BD Plant List'!A13 -> 40026
A15: ='BD Plant List'!A14 -> 40057
A16: ='BD Plant List'!A15 -> 40087
A17: ='BD Plant List'!A16 -> 40118
A18: ='BD Plant List'!A17 -> 40148
... A126: ='BD Plant List'!A125 -> 43435
A127: ='BD Plant List'!A126 -> 43466 | B127: =B$4 -> 40 | C127: =C$4 -> 10 | D127: =D$4 -> 56 | E127: =E$4 -> 70 | F127: =F$4 -> 9 | G127: =G$4 -> 50 | H127: =H$4 -> 39 | I127: =I$4 -> 39 | ... O127: =O$4 -> 105 | P127: =SUM(B127:O127) -> 573 | R127: ='Fuel Ethanol'!L26 -> 76891 | S127: =R127*264.17/1000000 -> 20.312295 | T127: =S127/((P127/365)*(A127-A126)) -> 0.41738377 | V127: =O127+K127+J127+I127+G127+F127+E127+D127 -> 455 | W127: =B127+H127+L127+M127+N127 -> 108 | X127: =C127 -> 10 | Y127: =SUM(V127:X127) -> 573 | AA127: =V127/$Y127 -> 0.79406632 | AB127: =W127/$Y127 -> 0.18848168 | AC127: =X127/$Y127 -> 0.017452007
A128: ='BD Plant List'!A127 -> 43497 | B128: =B$4 -> 40 | C128: =C$4 -> 10 | D128: =D$4 -> 56 | E128: =E$4 -> 70 | F128: =F$4 -> 9 | G128: =G$4 -> 50 | H128: =H$4 -> 39 | I128: =I$4 -> 39 | ... O128: =O$4 -> 105 | P128: =SUM(B128:O128) -> 573 | R128: ='Fuel Ethanol'!L27 -> 62850 | S128: =R128*264.17/1000000 -> 16.603085 | T128: =S128/((P128/365)*(A128-A127)) -> 0.34116567 | V128: =O128+K128+J128+I128+G128+F128+E128+D128 -> 455 | W128: =B128+H128+L128+M128+N128 -> 108 | X128: =C128 -> 10 | Y128: =SUM(V128:X128) -> 573 | AA128: =V128/$Y128 -> 0.79406632 | AB128: =W128/$Y128 -> 0.18848168 | AC128: =X128/$Y128 -> 0.017452007
A129: ='BD Plant List'!A128 -> 43525 | B129: =B$4 -> 40 | C129: =C$4 -> 10 | D129: =D$4 -> 56 | E129: =E$4 -> 70 | F129: =F$4 -> 9 | G129: =G$4 -> 50 | H129: =H$4 -> 39 | I129: =I$4 -> 39 | ... O129: =O$4 -> 105 | P129: =SUM(B129:O129) -> 573 | R129: ='Fuel Ethanol'!L28 -> 84270 | S129: =R129*264.17/1000000 -> 22.261606 | T129: =S129/((P129/365)*(A129-A128)) -> 0.50645015 | V129: =O129+K129+J129+I129+G129+F129+E129+D129 -> 455 | W129: =B129+H129+L129+M129+N129 -> 108 | X129: =C129 -> 10 | Y129: =SUM(V129:X129) -> 573 | AA129: =V129/$Y129 -> 0.79406632 | AB129: =W129/$Y129 -> 0.18848168 | AC129: =X129/$Y129 -> 0.017452007
A130: ='BD Plant List'!A129 -> 43556 | B130: =B$4 -> 40 | C130: =C$4 -> 10 | D130: =D$4 -> 56 | E130: =E$4 -> 70 | F130: =F$4 -> 9 | G130: =G$4 -> 50 | H130: =H$4 -> 39 | I130: =I$4 -> 39 | ... O130: =O$4 -> 105 | P130: =SUM(B130:O130) -> 573 | R130: ='Fuel Ethanol'!L29 -> 119100 | S130: =R130*264.17/1000000 -> 31.462647 | T130: =S130/((P130/365)*(A130-A129)) -> 0.64650488 | V130: =O130+K130+J130+I130+G130+F130+E130+D130 -> 455 | W130: =B130+H130+L130+M130+N130 -> 108 | X130: =C130 -> 10 | Y130: =SUM(V130:X130) -> 573 | AA130: =V130/$Y130 -> 0.79406632 | AB130: =W130/$Y130 -> 0.18848168 | AC130: =X130/$Y130 -> 0.017452007
A131: ='BD Plant List'!A130 -> 43586 | B131: =B$4 -> 40 | C131: =C$4 -> 10 | D131: =D$4 -> 56 | E131: =E$4 -> 70 | F131: =F$4 -> 9 | G131: =G$4 -> 50 | H131: =H$4 -> 39 | I131: =I$4 -> 39 | ... O131: =O$4 -> 105 | P131: =SUM(B131:O131) -> 573 | R131: ='Fuel Ethanol'!L30 -> 82226 | S131: =R131*264.17/1000000 -> 21.721642 | T131: =S131/((P131/365)*(A131-A130)) -> 0.46122161 | V131: =O131+K131+J131+I131+G131+F131+E131+D131 -> 455 | W131: =B131+H131+L131+M131+N131 -> 108 | X131: =C131 -> 10 | Y131: =SUM(V131:X131) -> 573 | AA131: =V131/$Y131 -> 0.79406632 | AB131: =W131/$Y131 -> 0.18848168 | AC131: =X131/$Y131 -> 0.017452007
A132: ='BD Plant List'!A131 -> 43617 | B132: =B$4 -> 40 | C132: =C$4 -> 10 | D132: =D$4 -> 56 | E132: =E$4 -> 70 | F132: =F$4 -> 9 | G132: =G$4 -> 50 | H132: =H$4 -> 39 | I132: =I$4 -> 39 | ... O132: =O$4 -> 105 | P132: =SUM(B132:O132) -> 573 | R132: ='Fuel Ethanol'!L31 -> 106400 | S132: =R132*264.17/1000000 -> 28.107688 | T132: =S132/((P132/365)*(A132-A131)) -> 0.57756607 | V132: =O132+K132+J132+I132+G132+F132+E132+D132 -> 455 | W132: =B132+H132+L132+M132+N132 -> 108 | X132: =C132 -> 10 | Y132: =SUM(V132:X132) -> 573 | AA132: =V132/$Y132 -> 0.79406632 | AB132: =W132/$Y132 -> 0.18848168 | AC132: =X132/$Y132 -> 0.017452007
A133: ='BD Plant List'!A132 -> 43647 | B133: =B$4 -> 40 | C133: =C$4 -> 10 | D133: =D$4 -> 56 | E133: =E$4 -> 70 | F133: =F$4 -> 9 | G133: =G$4 -> 50 | H133: =H$4 -> 39 | I133: =I$4 -> 39 | ... O133: =O$4 -> 105 | P133: =SUM(B133:O133) -> 573 | R133: ='Fuel Ethanol'!L32 -> 126724 | S133: =R133*264.17/1000000 -> 33.476679 | T133: =S133/((P133/365)*(A133-A132)) -> 0.71081954 | V133: =O133+K133+J133+I133+G133+F133+E133+D133 -> 455 | W133: =B133+H133+L133+M133+N133 -> 108 | X133: =C133 -> 10 | Y133: =SUM(V133:X133) -> 573 | AA133: =V133/$Y133 -> 0.79406632 | AB133: =W133/$Y133 -> 0.18848168 | AC133: =X133/$Y133 -> 0.017452007
A134: ='BD Plant List'!A133 -> 43678 | B134: =B$4 -> 40 | C134: =C$4 -> 10 | D134: =D$4 -> 56 | E134: =E$4 -> 70 | F134: =F$4 -> 9 | G134: =G$4 -> 50 | H134: =H$4 -> 39 | I134: =I$4 -> 39 | ... O134: =O$4 -> 105 | P134: =SUM(B134:O134) -> 573 | R134: ='Fuel Ethanol'!L33 -> 113403 | S134: =R134*264.17/1000000 -> 29.957671 | T134: =S134/((P134/365)*(A134-A133)) -> 0.61558012 | V134: =O134+K134+J134+I134+G134+F134+E134+D134 -> 455 | W134: =B134+H134+L134+M134+N134 -> 108 | X134: =C134 -> 10 | Y134: =SUM(V134:X134) -> 573 | AA134: =V134/$Y134 -> 0.79406632 | AB134: =W134/$Y134 -> 0.18848168 | AC134: =X134/$Y134 -> 0.017452007
A135: ='BD Plant List'!A134 -> 43709 | B135: =B$4 -> 40 | C135: =C$4 -> 10 | D135: =D$4 -> 56 | E135: =E$4 -> 70 | F135: =F$4 -> 9 | G135: =G$4 -> 50 | H135: =H$4 -> 39 | I135: =I$4 -> 39 | ... O135: =O$4 -> 105 | P135: =SUM(B135:O135) -> 573 | R135: ='Fuel Ethanol'!L34 -> 117434 | S135: =R135*264.17/1000000 -> 31.02254 | T135: =S135/((P135/365)*(A135-A134)) -> 0.63746141 | V135: =O135+K135+J135+I135+G135+F135+E135+D135 -> 455 | W135: =B135+H135+L135+M135+N135 -> 108 | X135: =C135 -> 10 | Y135: =SUM(V135:X135) -> 573 | AA135: =V135/$Y135 -> 0.79406632 | AB135: =W135/$Y135 -> 0.18848168 | AC135: =X135/$Y135 -> 0.017452007
A136: ='BD Plant List'!A135 -> 43739 | B136: =B$4 -> 40 | C136: =C$4 -> 10 | D136: =D$4 -> 56 | E136: =E$4 -> 70 | F136: =F$4 -> 9 | G136: =G$4 -> 50 | H136: =H$4 -> 39 | I136: =I$4 -> 39 | ... O136: =O$4 -> 105 | P136: =SUM(B136:O136) -> 573 | R136: ='Fuel Ethanol'!L35 -> 107915 | S136: =R136*264.17/1000000 -> 28.507906 | T136: =S136/((P136/365)*(A136-A135)) -> 0.6053162 | V136: =O136+K136+J136+I136+G136+F136+E136+D136 -> 455 | W136: =B136+H136+L136+M136+N136 -> 108 | X136: =C136 -> 10 | Y136: =SUM(V136:X136) -> 573 | AA136: =V136/$Y136 -> 0.79406632 | AB136: =W136/$Y136 -> 0.18848168 | AC136: =X136/$Y136 -> 0.017452007
A137: ='BD Plant List'!A136 -> 43770 | B137: =B$4 -> 40 | C137: =C$4 -> 10 | D137: =D$4 -> 56 | E137: =E$4 -> 70 | F137: =F$4 -> 9 | G137: =G$4 -> 50 | H137: =H$4 -> 39 | I137: =I$4 -> 39 | ... O137: =O$4 -> 105 | P137: =SUM(B137:O137) -> 573 | R137: ='Fuel Ethanol'!L36 -> 96916 | S137: =R137*264.17/1000000 -> 25.6023 | T137: =S137/((P137/365)*(A137-A136)) -> 0.52608452 | V137: =O137+K137+J137+I137+G137+F137+E137+D137 -> 455 | W137: =B137+H137+L137+M137+N137 -> 108 | X137: =C137 -> 10 | Y137: =SUM(V137:X137) -> 573 | AA137: =V137/$Y137 -> 0.79406632 | AB137: =W137/$Y137 -> 0.18848168 | AC137: =X137/$Y137 -> 0.017452007
A138: ='BD Plant List'!A137 -> 43800 | B138: =B$4 -> 40 | C138: =C$4 -> 10 | D138: =D$4 -> 56 | E138: =E$4 -> 70 | F138: =F$4 -> 9 | G138: =G$4 -> 50 | H138: =H$4 -> 39 | I138: =I$4 -> 39 | ... O138: =O$4 -> 105 | P138: =SUM(B138:O138) -> 573 | R138: ='Fuel Ethanol'!L37 -> 115839 | S138: =R138*264.17/1000000 -> 30.601189 | T138: =S138/((P138/365)*(A138-A137)) -> 0.64976346 | V138: =O138+K138+J138+I138+G138+F138+E138+D138 -> 455 | W138: =B138+H138+L138+M138+N138 -> 108 | X138: =C138 -> 10 | Y138: =SUM(V138:X138) -> 573 | AA138: =V138/$Y138 -> 0.79406632 | AB138: =W138/$Y138 -> 0.18848168 | AC138: =X138/$Y138 -> 0.017452007
A139: ='BD Plant List'!A138 -> 43831 | B139: =B$4 -> 40 | C139: =C$4 -> 10 | D139: =D$4 -> 56 | E139: =E$4 -> 70 | F139: =F$4 -> 9 | G139: =G$4 -> 50 | H139: =H$4 -> 39 | I139: =I$4 -> 39 | ... O139: =O$4 -> 105 | P139: =SUM(B139:O139) -> 573 | R139: ='Fuel Ethanol'!M26 -> 158166 | S139: =R139*264.17/1000000 -> 41.782712 | T139: =S139/((P139/365)*(A139-A138)) -> 0.85856499 | V139: =O139+K139+J139+I139+G139+F139+E139+D139 -> 455 | W139: =B139+H139+L139+M139+N139 -> 108 | X139: =C139 -> 10 | Y139: =SUM(V139:X139) -> 573 | AA139: =V139/$Y139 -> 0.79406632 | AB139: =W139/$Y139 -> 0.18848168 | AC139: =X139/$Y139 -> 0.017452007 | AE139: 125292 | AF139: 378741 | AG139: =AF139*AA139 -> 300745.47 | AH139: =AG139*39.3679/1000000 -> 11.839718 | AI139: =AE139*2204.622/1000000 -> 276.2215 | AJ139: =AI139/AH139 -> 23.330075 | AK139: =AH139*$AM$6 -> 11.247732 | AN139: =R139*0.79 -> 124951.14 | AO139: =AN139/AF139 -> 0.32991184
A140: ='BD Plant List'!A139 -> 43862 | B140: =B$4 -> 40 | C140: =C$4 -> 10 | D140: =D$4 -> 56 | E140: =E$4 -> 70 | F140: =F$4 -> 9 | G140: =G$4 -> 50 | H140: =H$4 -> 39 | I140: =I$4 -> 39 | ... O140: =O$4 -> 105 | P140: =SUM(B140:O140) -> 573 | R140: ='Fuel Ethanol'!M27 -> 149497 | S140: =R140*264.17/1000000 -> 39.492622 | T140: =S140/((P140/365)*(A140-A139)) -> 0.81150747 | V140: =O140+K140+J140+I140+G140+F140+E140+D140 -> 455 | W140: =B140+H140+L140+M140+N140 -> 108 | X140: =C140 -> 10 | Y140: =SUM(V140:X140) -> 573 | AA140: =V140/$Y140 -> 0.79406632 | AB140: =W140/$Y140 -> 0.18848168 | AC140: =X140/$Y140 -> 0.017452007 | AE140: 117402 | AF140: 364425 | AG140: =AF140*AA140 -> 289377.62 | AH140: =AG140*39.3679/1000000 -> 11.392189 | AI140: =AE140*2204.622/1000000 -> 258.82703 | AJ140: =AI140/AH140 -> 22.719692 | AK140: =AH140*$AM$6 -> 10.82258 | AN140: =R140*0.79 -> 118102.63 | AO140: =AN140/AF140 -> 0.32407939
A141: ='BD Plant List'!A140 -> 43891 | B141: =B$4 -> 40 | C141: =C$4 -> 10 | D141: =D$4 -> 56 | E141: =E$4 -> 70 | F141: =F$4 -> 9 | G141: =G$4 -> 50 | H141: =H$4 -> 39 | I141: =I$4 -> 39 | ... O141: =O$4 -> 105 | P141: =SUM(B141:O141) -> 573 | R141: ='Fuel Ethanol'!M28 -> 147191 | S141: =R141*264.17/1000000 -> 38.883446 | T141: =S141/((P141/365)*(A141-A140)) -> 0.85409267 | V141: =O141+K141+J141+I141+G141+F141+E141+D141 -> 455 | W141: =B141+H141+L141+M141+N141 -> 108 | X141: =C141 -> 10 | Y141: =SUM(V141:X141) -> 573 | AA141: =V141/$Y141 -> 0.79406632 | AB141: =W141/$Y141 -> 0.18848168 | AC141: =X141/$Y141 -> 0.017452007 | AE141: 118072 | AF141: 358112 | AG141: =AF141*AA141 -> 284364.68 | AH141: =AG141*39.3679/1000000 -> 11.19484 | AI141: =AE141*2204.622/1000000 -> 260.30413 | AJ141: =AI141/AH141 -> 23.252152 | AK141: =AH141*$AM$6 -> 10.635098 | AN141: =R141*0.79 -> 116280.89 | AO141: =AN141/AF141 -> 0.32470537
A142: ='BD Plant List'!A141 -> 43922 | B142: =B$4 -> 40 | C142: =C$4 -> 10 | D142: =D$4 -> 56 | E142: =E$4 -> 70 | F142: =F$4 -> 9 | G142: =G$4 -> 50 | H142: =H$4 -> 39 | I142: =I$4 -> 39 | ... O142: =O$4 -> 105 | P142: =SUM(B142:O142) -> 573 | R142: ='Fuel Ethanol'!M29 -> 85451 | S142: =R142*264.17/1000000 -> 22.573591 | T142: =S142/((P142/365)*(A142-A141)) -> 0.46384961 | V142: =O142+K142+J142+I142+G142+F142+E142+D142 -> 455 | W142: =B142+H142+L142+M142+N142 -> 108 | X142: =C142 -> 10 | Y142: =SUM(V142:X142) -> 573 | AA142: =V142/$Y142 -> 0.79406632 | AB142: =W142/$Y142 -> 0.18848168 | AC142: =X142/$Y142 -> 0.017452007 | AE142: 75875 | AF142: 230969 | AG142: =AF142*AA142 -> 183404.7 | AH142: =AG142*39.3679/1000000 -> 7.220258 | AI142: =AE142*2204.622/1000000 -> 167.27569 | AJ142: =AI142/AH142 -> 23.167551 | AK142: =AH142*$AM$6 -> 6.8592451 | AN142: =R142*0.79 -> 67506.29 | AO142: =AN142/AF142 -> 0.29227424
A143: ='BD Plant List'!A142 -> 43952 | B143: =B$4 -> 40 | C143: =C$4 -> 10 | D143: =D$4 -> 56 | E143: =E$4 -> 70 | F143: =F$4 -> 9 | G143: =G$4 -> 50 | H143: =H$4 -> 39 | I143: =I$4 -> 39 | ... O143: =O$4 -> 105 | P143: =SUM(B143:O143) -> 573 | R143: ='Fuel Ethanol'!M30 -> 88331 | S143: =R143*264.17/1000000 -> 23.3344 | T143: =S143/((P143/365)*(A143-A142)) -> 0.49546574 | V143: =O143+K143+J143+I143+G143+F143+E143+D143 -> 455 | W143: =B143+H143+L143+M143+N143 -> 108 | X143: =C143 -> 10 | Y143: =SUM(V143:X143) -> 573 | AA143: =V143/$Y143 -> 0.79406632 | AB143: =W143/$Y143 -> 0.18848168 | AC143: =X143/$Y143 -> 0.017452007 | AE143: 67378 | AF143: 225932 | AG143: =AF143*AA143 -> 179404.99 | AH143: =AG143*39.3679/1000000 -> 7.0627978 | AI143: =AE143*2204.622/1000000 -> 148.54302 | AJ143: =AI143/AH143 -> 21.031753 | AK143: =AH143*$AM$6 -> 6.7096579 | AN143: =R143*0.79 -> 69781.49 | AO143: =AN143/AF143 -> 0.30886059
A144: ='BD Plant List'!A143 -> 43983 | B144: =B$4 -> 40 | C144: =C$4 -> 10 | D144: =D$4 -> 56 | E144: =E$4 -> 70 | F144: =F$4 -> 9 | G144: =G$4 -> 50 | H144: =H$4 -> 39 | I144: =I$4 -> 39 | ... O144: =O$4 -> 105 | P144: =SUM(B144:O144) -> 573 | R144: ='Fuel Ethanol'!M31 -> 129908 | S144: =R144*264.17/1000000 -> 34.317796 | T144: =S144/((P144/365)*(A144-A143)) -> 0.70517343 | V144: =O144+K144+J144+I144+G144+F144+E144+D144 -> 455 | W144: =B144+H144+L144+M144+N144 -> 108 | X144: =C144 -> 10 | Y144: =SUM(V144:X144) -> 573 | AA144: =V144/$Y144 -> 0.79406632 | AB144: =W144/$Y144 -> 0.18848168 | AC144: =X144/$Y144 -> 0.017452007 | AE144: 103386 | AF144: 318577 | AG144: =AF144*AA144 -> 252971.27 | AH144: =AG144*39.3679/1000000 -> 9.9589475 | AI144: =AE144*2204.622/1000000 -> 227.92705 | AJ144: =AI144/AH144 -> 22.886661 | AK144: =AH144*$AM$6 -> 9.4610001 | AN144: =R144*0.79 -> 102627.32 | AO144: =AN144/AF144 -> 0.3221429
A145: ='BD Plant List'!A144 -> 44013 | B145: =B$4 -> 40 | C145: =C$4 -> 10 | D145: =D$4 -> 56 | E145: =E$4 -> 70 | F145: =F$4 -> 9 | G145: =G$4 -> 50 | H145: =H$4 -> 39 | I145: =I$4 -> 39 | ... O145: =O$4 -> 105 | P145: =SUM(B145:O145) -> 573 | R145: ='Fuel Ethanol'!M32 -> 150008 | S145: =R145*264.17/1000000 -> 39.627613 | T145: =S145/((P145/365)*(A145-A144)) -> 0.84142402 | V145: =O145+K145+J145+I145+G145+F145+E145+D145 -> 455 | W145: =B145+H145+L145+M145+N145 -> 108 | X145: =C145 -> 10 | Y145: =SUM(V145:X145) -> 573 | AA145: =V145/$Y145 -> 0.79406632 | AB145: =W145/$Y145 -> 0.18848168 | AC145: =X145/$Y145 -> 0.017452007 | AE145: 120928 | AF145: 371659 | AG145: =AF145*AA145 -> 295121.89 | AH145: =AG145*39.3679/1000000 -> 11.618329 | AI145: =AE145*2204.622/1000000 -> 266.60053 | AJ145: =AI145/AH145 -> 22.946546 | AK145: =AH145*$AM$6 -> 11.037413 | AN145: =R145*0.79 -> 118506.32 | AO145: =AN145/AF145 -> 0.31885766
A146: ='BD Plant List'!A145 -> 44044 | B146: =B$4 -> 40 | C146: =C$4 -> 10 | D146: =D$4 -> 56 | E146: =E$4 -> 70 | F146: =F$4 -> 9 | G146: =G$4 -> 50 | H146: =H$4 -> 39 | I146: =I$4 -> 39 | ... O146: =O$4 -> 105 | P146: =SUM(B146:O146) -> 573 | R146: ='Fuel Ethanol'!M33 -> 146424 | S146: =R146*264.17/1000000 -> 38.680828 | T146: =S146/((P146/365)*(A146-A145)) -> 0.79482645 | V146: =O146+K146+J146+I146+G146+F146+E146+D146 -> 455 | W146: =B146+H146+L146+M146+N146 -> 108 | X146: =C146 -> 10 | Y146: =SUM(V146:X146) -> 573 | AA146: =V146/$Y146 -> 0.79406632 | AB146: =W146/$Y146 -> 0.18848168 | AC146: =X146/$Y146 -> 0.017452007 | AE146: 114377 | AF146: 360641 | AG146: =AF146*AA146 -> 286372.87 | AH146: =AG146*39.3679/1000000 -> 11.273899 | AI146: =AE146*2204.622/1000000 -> 252.15805 | AJ146: =AI146/AH146 -> 22.366535 | AK146: =AH146*$AM$6 -> 10.710204 | AN146: =R146*0.79 -> 115674.96 | AO146: =AN146/AF146 -> 0.32074822
A147: ='BD Plant List'!A146 -> 44075 | B147: =B$4 -> 40 | C147: =C$4 -> 10 | D147: =D$4 -> 56 | E147: =E$4 -> 70 | F147: =F$4 -> 9 | G147: =G$4 -> 50 | H147: =H$4 -> 39 | I147: =I$4 -> 39 | ... O147: =O$4 -> 105 | P147: =SUM(B147:O147) -> 573 | R147: ='Fuel Ethanol'!M34 -> 134745 | S147: =R147*264.17/1000000 -> 35.595587 | T147: =S147/((P147/365)*(A147-A146)) -> 0.73142989 | V147: =O147+K147+J147+I147+G147+F147+E147+D147 -> 455 | W147: =B147+H147+L147+M147+N147 -> 108 | X147: =C147 -> 10 | Y147: =SUM(V147:X147) -> 573 | AA147: =V147/$Y147 -> 0.79406632 | AB147: =W147/$Y147 -> 0.18848168 | AC147: =X147/$Y147 -> 0.017452007 | AE147: 104546 | AF147: 326873 | AG147: =AF147*AA147 -> 259558.84 | AH147: =AG147*39.3679/1000000 -> 10.218286 | AI147: =AE147*2204.622/1000000 -> 230.48441 | AJ147: =AI147/AH147 -> 22.556073 | AK147: =AH147*$AM$6 -> 9.7073721 | AN147: =R147*0.79 -> 106448.55 | AO147: =AN147/AF147 -> 0.32565721
A148: ='BD Plant List'!A147 -> 44105 | B148: =B$4 -> 40 | C148: =C$4 -> 10 | D148: =D$4 -> 56 | E148: =E$4 -> 70 | F148: =F$4 -> 9 | G148: =G$4 -> 50 | H148: =H$4 -> 39 | I148: =I$4 -> 39 | ... O148: =O$4 -> 105 | P148: =SUM(B148:O148) -> 573 | R148: ='Fuel Ethanol'!M35 -> 139203 | S148: =R148*264.17/1000000 -> 36.773257 | T148: =S148/((P148/365)*(A148-A147)) -> 0.78081667 | V148: =O148+K148+J148+I148+G148+F148+E148+D148 -> 455 | W148: =B148+H148+L148+M148+N148 -> 108 | X148: =C148 -> 10 | Y148: =SUM(V148:X148) -> 573 | AA148: =V148/$Y148 -> 0.79406632 | AB148: =W148/$Y148 -> 0.18848168 | AC148: =X148/$Y148 -> 0.017452007 | AE148: 109318 | AF148: 325261 | AG148: =AF148*AA148 -> 258278.8 | AH148: =AG148*39.3679/1000000 -> 10.167894 | AI148: =AE148*2204.622/1000000 -> 241.00487 | AJ148: =AI148/AH148 -> 23.702535 | AK148: =AH148*$AM$6 -> 9.6594994 | AN148: =R148*0.79 -> 109970.37 | AO148: =AN148/AF148 -> 0.33809885
A149: ='BD Plant List'!A148 -> 44136 | B149: =B$4 -> 40 | C149: =C$4 -> 10 | D149: =D$4 -> 56 | E149: =E$4 -> 70 | F149: =F$4 -> 9 | G149: =G$4 -> 50 | H149: =H$4 -> 39 | I149: =I$4 -> 39 | ... O149: =O$4 -> 105 | P149: =SUM(B149:O149) -> 573 | R149: ='Fuel Ethanol'!M36 -> 155234 | S149: =R149*264.17/1000000 -> 41.008166 | T149: =S149/((P149/365)*(A149-A148)) -> 0.84264936 | V149: =O149+K149+J149+I149+G149+F149+E149+D149 -> 455 | W149: =B149+H149+L149+M149+N149 -> 108 | X149: =C149 -> 10 | Y149: =SUM(V149:X149) -> 573 | AA149: =V149/$Y149 -> 0.79406632 | AB149: =W149/$Y149 -> 0.18848168 | AC149: =X149/$Y149 -> 0.017452007 | AE149: 119815 | AF149: 371642 | AG149: =AF149*AA149 -> 295108.39 | AH149: =AG149*39.3679/1000000 -> 11.617798 | AI149: =AE149*2204.622/1000000 -> 264.14678 | AJ149: =AI149/AH149 -> 22.73639 | AK149: =AH149*$AM$6 -> 11.036908 | AN149: =R149*0.79 -> 122634.86 | AO149: =AN149/AF149 -> 0.32998116
A150: ='BD Plant List'!A149 -> 44166 | B150: =B$4 -> 40 | C150: =C$4 -> 10 | D150: =D$4 -> 56 | E150: =E$4 -> 70 | F150: =F$4 -> 9 | G150: =G$4 -> 50 | H150: =H$4 -> 39 | I150: =I$4 -> 39 | ... O150: =O$4 -> 105 | P150: =SUM(B150:O150) -> 573 | R150: ='Fuel Ethanol'!M37 -> 139070 | S150: =R150*264.17/1000000 -> 36.738122 | T150: =S150/((P150/365)*(A150-A149)) -> 0.78007065 | V150: =O150+K150+J150+I150+G150+F150+E150+D150 -> 455 | W150: =B150+H150+L150+M150+N150 -> 108 | X150: =C150 -> 10 | Y150: =SUM(V150:X150) -> 573 | AA150: =V150/$Y150 -> 0.79406632 | AB150: =W150/$Y150 -> 0.18848168 | AC150: =X150/$Y150 -> 0.017452007 | AE150: 97268 | AF150: 333253 | AG150: =AF150*AA150 -> 264624.98 | AH150: =AG150*39.3679/1000000 -> 10.41773 | AI150: =AE150*2204.622/1000000 -> 214.43917 | AJ150: =AI150/AH150 -> 20.58406 | AK150: =AH150*$AM$6 -> 9.8968434 | AN150: =R150*0.79 -> 109865.3 | AO150: =AN150/AF150 -> 0.32967535
A151: ='BD Plant List'!A150 -> 44197 | B151: =B$4 -> 40 | C151: =C$4 -> 10 | D151: =D$4 -> 56 | E151: =E$4 -> 70 | F151: =F$4 -> 9 | G151: =G$4 -> 50 | H151: =H$4 -> 39 | I151: =I$4 -> 39 | ... O151: =O$4 -> 105 | P151: =SUM(B151:O151) -> 573 | R151: ='Fuel Ethanol'!N26 -> 116631 | S151: =R151*264.17/1000000 -> 30.810411 | T151: =S151/((P151/365)*(A151-A150)) -> 0.63310252 | V151: =O151+K151+J151+I151+G151+F151+E151+D151 -> 455 | W151: =B151+H151+L151+M151+N151 -> 108 | X151: =C151 -> 10 | Y151: =SUM(V151:X151) -> 573 | AA151: =V151/$Y151 -> 0.79406632 | AB151: =W151/$Y151 -> 0.18848168 | AC151: =X151/$Y151 -> 0.017452007 | AE151: 89492 | AF151: 276701 | AG151: =AF151*AA151 -> 219718.94 | AH151: =AG151*39.3679/1000000 -> 8.6498734 | AI151: =AE151*2204.622/1000000 -> 197.29603 | AJ151: =AI151/AH151 -> 22.809124 | AK151: =AH151*$AM$6 -> 8.2173798 | AN151: =R151*0.79 -> 92138.49 | AO151: =AN151/AF151 -> 0.33298936
A152: ='BD Plant List'!A151 -> 44228 | B152: =B$4 -> 40 | C152: =C$4 -> 10 | D152: =D$4 -> 56 | E152: =E$4 -> 70 | F152: =F$4 -> 9 | G152: =G$4 -> 50 | H152: =H$4 -> 39 | I152: =I$4 -> 39 | ... O152: =O$4 -> 105 | P152: =SUM(B152:O152) -> 573 | R152: ='Fuel Ethanol'!N27 -> 108904 | S152: =R152*264.17/1000000 -> 28.76917 | T152: =S152/((P152/365)*(A152-A151)) -> 0.59115842 | V152: =O152+K152+J152+I152+G152+F152+E152+D152 -> 455 | W152: =B152+H152+L152+M152+N152 -> 108 | X152: =C152 -> 10 | Y152: =SUM(V152:X152) -> 573 | AA152: =V152/$Y152 -> 0.79406632 | AB152: =W152/$Y152 -> 0.18848168 | AC152: =X152/$Y152 -> 0.017452007 | AE152: 82510 | AF152: 258007 | AG152: =AF152*AA152 -> 204874.67 | AH152: =AG152*39.3679/1000000 -> 8.0654855 | AI152: =AE152*2204.622/1000000 -> 181.90336 | AJ152: =AI152/AH152 -> 22.553306 | AK152: =AH152*$AM$6 -> 7.6622112 | AN152: =R152*0.79 -> 86034.16 | AO152: =AN152/AF152 -> 0.33345669
A153: ='BD Plant List'!A152 -> 44256 | B153: =B$4 -> 40 | C153: =C$4 -> 10 | D153: =D$4 -> 56 | E153: =E$4 -> 70 | F153: =F$4 -> 9 | G153: =G$4 -> 50 | H153: =H$4 -> 39 | I153: =I$4 -> 39 | ... O153: =O$4 -> 105 | P153: =SUM(B153:O153) -> 573 | R153: ='Fuel Ethanol'!N28 -> 137014 | S153: =R153*264.17/1000000 -> 36.194988 | T153: =S153/((P153/365)*(A153-A152)) -> 0.82343373 | V153: =O153+K153+J153+I153+G153+F153+E153+D153 -> 455 | W153: =B153+H153+L153+M153+N153 -> 108 | X153: =C153 -> 10 | Y153: =SUM(V153:X153) -> 573 | AA153: =V153/$Y153 -> 0.79406632 | AB153: =W153/$Y153 -> 0.18848168 | AC153: =X153/$Y153 -> 0.017452007 | AE153: 105454 | AF153: 330050 | AG153: =AF153*AA153 -> 262081.59 | AH153: =AG153*39.3679/1000000 -> 10.317602 | AI153: =AE153*2204.622/1000000 -> 232.48621 | AJ153: =AI153/AH153 -> 22.53297 | AK153: =AH153*$AM$6 -> 9.8017217 | AN153: =R153*0.79 -> 108241.06 | AO153: =AN153/AF153 -> 0.32795352
A154: ='BD Plant List'!A153 -> 44287 | B154: =B$4 -> 40 | C154: =C$4 -> 10 | D154: =D$4 -> 56 | E154: =E$4 -> 70 | F154: =F$4 -> 9 | G154: =G$4 -> 50 | H154: =H$4 -> 39 | I154: =I$4 -> 39 | ... O154: =O$4 -> 105 | P154: =SUM(B154:O154) -> 573 | R154: ='Fuel Ethanol'!N29 -> 130068 | S154: =R154*264.17/1000000 -> 34.360064 | T154: =S154/((P154/365)*(A154-A153)) -> 0.70604195 | V154: =O154+K154+J154+I154+G154+F154+E154+D154 -> 455 | W154: =B154+H154+L154+M154+N154 -> 108 | X154: =C154 -> 10 | Y154: =SUM(V154:X154) -> 573 | AA154: =V154/$Y154 -> 0.79406632 | AB154: =W154/$Y154 -> 0.18848168 | AC154: =X154/$Y154 -> 0.017452007 | AE154: 99970 | AF154: 309729 | AG154: =AF154*AA154 -> 245945.37 | AH154: =AG154*39.3679/1000000 -> 9.6823526 | AI154: =AE154*2204.622/1000000 -> 220.39606 | AJ154: =AI154/AH154 -> 22.762656 | AK154: =AH154*$AM$6 -> 9.198235 | AN154: =R154*0.79 -> 102753.72 | AO154: =AN154/AF154 -> 0.33175363
A155: ='BD Plant List'!A154 -> 44317 | B155: =B$4 -> 40 | C155: =C$4 -> 10 | D155: =D$4 -> 56 | E155: =E$4 -> 70 | F155: =F$4 -> 9 | G155: =G$4 -> 50 | H155: =H$4 -> 39 | I155: =I$4 -> 39 | ... O155: =O$4 -> 105 | P155: =SUM(B155:O155) -> 573 | R155: ='Fuel Ethanol'!N30 -> 143350 | S155: =R155*264.17/1000000 -> 37.868769 | T155: =S155/((P155/365)*(A155-A154)) -> 0.804078 | V155: =O155+K155+J155+I155+G155+F155+E155+D155 -> 455 | W155: =B155+H155+L155+M155+N155 -> 108 | X155: =C155 -> 10 | Y155: =SUM(V155:X155) -> 573 | AA155: =V155/$Y155 -> 0.79406632 | AB155: =W155/$Y155 -> 0.18848168 | AC155: =X155/$Y155 -> 0.017452007 | AE155: 109562 | AF155: 342690 | AG155: =AF155*AA155 -> 272118.59 | AH155: =AG155*39.3679/1000000 -> 10.712737 | AI155: =AE155*2204.622/1000000 -> 241.5428 | AJ155: =AI155/AH155 -> 22.547253 | AK155: =AH155*$AM$6 -> 10.1771 | AN155: =R155*0.79 -> 113246.5 | AO155: =AN155/AF155 -> 0.33046339
A156: ='BD Plant List'!A155 -> 44348 | B156: =B$4 -> 40 | C156: =C$4 -> 10 | D156: =D$4 -> 56 | E156: =E$4 -> 70 | F156: =F$4 -> 9 | G156: =G$4 -> 50 | H156: =H$4 -> 39 | I156: =I$4 -> 39 | ... O156: =O$4 -> 105 | P156: =SUM(B156:O156) -> 573 | R156: ='Fuel Ethanol'!N31 -> 134140 | S156: =R156*264.17/1000000 -> 35.435764 | T156: =S156/((P156/365)*(A156-A155)) -> 0.7281458 | V156: =O156+K156+J156+I156+G156+F156+E156+D156 -> 455 | W156: =B156+H156+L156+M156+N156 -> 108 | X156: =C156 -> 10 | Y156: =SUM(V156:X156) -> 573 | AA156: =V156/$Y156 -> 0.79406632 | AB156: =W156/$Y156 -> 0.18848168 | AC156: =X156/$Y156 -> 0.017452007 | AE156: 106738 | AF156: 322587 | AG156: =AF156*AA156 -> 256155.47 | AH156: =AG156*39.3679/1000000 -> 10.084303 | AI156: =AE156*2204.622/1000000 -> 235.31694 | AJ156: =AI156/AH156 -> 23.334974 | AK156: =AH156*$AM$6 -> 9.5800878 | AN156: =R156*0.79 -> 105970.6 | AO156: =AN156/AF156 -> 0.32850239
A157: ='BD Plant List'!A156 -> 44378 | B157: =B$4 -> 40 | C157: =C$4 -> 10 | D157: =D$4 -> 56 | E157: =E$4 -> 70 | F157: =F$4 -> 9 | G157: =G$4 -> 50 | H157: =H$4 -> 39 | I157: =I$4 -> 39 | ... O157: =O$4 -> 105 | P157: =SUM(B157:O157) -> 573 | R157: ='Fuel Ethanol'!N32 -> 155200 | S157: =R157*264.17/1000000 -> 40.999184 | T157: =S157/((P157/365)*(A157-A156)) -> 0.87054696 | V157: =O157+K157+J157+I157+G157+F157+E157+D157 -> 455 | W157: =B157+H157+L157+M157+N157 -> 108 | X157: =C157 -> 10 | Y157: =SUM(V157:X157) -> 573 | AA157: =V157/$Y157 -> 0.79406632 | AB157: =W157/$Y157 -> 0.18848168 | AC157: =X157/$Y157 -> 0.017452007 | AE157: 118842 | AF157: 375282 | AG157: =AF157*AA157 -> 297998.8 | AH157: =AG157*39.3679/1000000 -> 11.731587 | AI157: =AE157*2204.622/1000000 -> 262.00169 | AJ157: =AI157/AH157 -> 22.333014 | AK157: =AH157*$AM$6 -> 11.145007 | AN157: =R157*0.79 -> 122608 | AO157: =AN157/AF157 -> 0.32670898
A158: ='BD Plant List'!A157 -> 44409 | B158: =B$4 -> 40 | C158: =C$4 -> 10 | D158: =D$4 -> 56 | E158: =E$4 -> 70 | F158: =F$4 -> 9 | G158: =G$4 -> 50 | H158: =H$4 -> 39 | I158: =I$4 -> 39 | ... O158: =O$4 -> 105 | P158: =SUM(B158:O158) -> 573 | R158: ='Fuel Ethanol'!N33 -> 148267 | S158: =R158*264.17/1000000 -> 39.167693 | T158: =S158/((P158/365)*(A158-A157)) -> 0.80483072 | V158: =O158+K158+J158+I158+G158+F158+E158+D158 -> 455 | W158: =B158+H158+L158+M158+N158 -> 108 | X158: =C158 -> 10 | Y158: =SUM(V158:X158) -> 573 | AA158: =V158/$Y158 -> 0.79406632 | AB158: =W158/$Y158 -> 0.18848168 | AC158: =X158/$Y158 -> 0.017452007 | AE158: 112527 | AF158: 350079 | AG158: =AF158*AA158 -> 277985.94 | AH158: =AG158*39.3679/1000000 -> 10.943723 | AI158: =AE158*2204.622/1000000 -> 248.0795 | AJ158: =AI158/AH158 -> 22.668657 | AK158: =AH158*$AM$6 -> 10.396537 | AN158: =R158*0.79 -> 117130.93 | AO158: =AN158/AF158 -> 0.33458428
A159: ='BD Plant List'!A158 -> 44440 | B159: =B$4 -> 40 | C159: =C$4 -> 10 | D159: =D$4 -> 56 | E159: =E$4 -> 70 | F159: =F$4 -> 9 | G159: =G$4 -> 50 | H159: =H$4 -> 39 | I159: =I$4 -> 39 | ... O159: =O$4 -> 105 | P159: =SUM(B159:O159) -> 573 | R159: ='Fuel Ethanol'!N34 -> 142231 | S159: =R159*264.17/1000000 -> 37.573163 | T159: =S159/((P159/365)*(A159-A158)) -> 0.77206579 | V159: =O159+K159+J159+I159+G159+F159+E159+D159 -> 455 | W159: =B159+H159+L159+M159+N159 -> 108 | X159: =C159 -> 10 | Y159: =SUM(V159:X159) -> 573 | AA159: =V159/$Y159 -> 0.79406632 | AB159: =W159/$Y159 -> 0.18848168 | AC159: =X159/$Y159 -> 0.017452007 | AE159: 109738 | AF159: 346711 | AG159: =AF159*AA159 -> 275311.53 | AH159: =AG159*39.3679/1000000 -> 10.838437 | AI159: =AE159*2204.622/1000000 -> 241.93081 | AJ159: =AI159/AH159 -> 22.32156 | AK159: =AH159*$AM$6 -> 10.296515 | AN159: =R159*0.79 -> 112362.49 | AO159: =AN159/AF159 -> 0.32408112
A160: ='BD Plant List'!A159 -> 44470 | B160: =B$4 -> 40 | C160: =C$4 -> 10 | D160: =D$4 -> 56 | E160: =E$4 -> 70 | F160: =F$4 -> 9 | G160: =G$4 -> 50 | H160: =H$4 -> 39 | I160: =I$4 -> 39 | ... O160: =O$4 -> 105 | P160: =SUM(B160:O160) -> 573 | R160: ='Fuel Ethanol'!N35 -> 121464 | S160: =R160*264.17/1000000 -> 32.087145 | T160: =S160/((P160/365)*(A160-A159)) -> 0.68131518 | V160: =O160+K160+J160+I160+G160+F160+E160+D160 -> 455 | W160: =B160+H160+L160+M160+N160 -> 108 | X160: =C160 -> 10 | Y160: =SUM(V160:X160) -> 573 | AA160: =V160/$Y160 -> 0.79406632 | AB160: =W160/$Y160 -> 0.18848168 | AC160: =X160/$Y160 -> 0.017452007 | AE160: 100938 | AF160: 294105 | AG160: =AF160*AA160 -> 233538.87 | AH160: =AG160*39.3679/1000000 -> 9.1939351 | AI160: =AE160*2204.622/1000000 -> 222.53014 | AJ160: =AI160/AH160 -> 24.204014 | AK160: =AH160*$AM$6 -> 8.7342383 | AN160: =R160*0.79 -> 95956.56 | AO160: =AN160/AF160 -> 0.32626633
A161: ='BD Plant List'!A160 -> 44501 | B161: =B$4 -> 40 | C161: =C$4 -> 10 | D161: =D$4 -> 56 | E161: =E$4 -> 70 | F161: =F$4 -> 9 | G161: =G$4 -> 50 | H161: =H$4 -> 39 | I161: =I$4 -> 39 | ... O161: =O$4 -> 105 | P161: =SUM(B161:O161) -> 573 | R161: ='Fuel Ethanol'!N36 -> 154607 | S161: =R161*264.17/1000000 -> 40.842531 | T161: =S161/((P161/365)*(A161-A160)) -> 0.83924584 | V161: =O161+K161+J161+I161+G161+F161+E161+D161 -> 455 | W161: =B161+H161+L161+M161+N161 -> 108 | X161: =C161 -> 10 | Y161: =SUM(V161:X161) -> 573 | AA161: =V161/$Y161 -> 0.79406632 | AB161: =W161/$Y161 -> 0.18848168 | AC161: =X161/$Y161 -> 0.017452007 | AE161: 116592 | AF161: 369616 | AG161: =AF161*AA161 -> 293499.62 | AH161: =AG161*39.3679/1000000 -> 11.554464 | AI161: =AE161*2204.622/1000000 -> 257.04129 | AJ161: =AI161/AH161 -> 22.24606 | AK161: =AH161*$AM$6 -> 10.97674 | AN161: =R161*0.79 -> 122139.53 | AO161: =AN161/AF161 -> 0.33044979
A162: ='BD Plant List'!A161 -> 44531 | B162: =B$4 -> 40 | C162: =C$4 -> 10 | D162: =D$4 -> 56 | E162: =E$4 -> 70 | F162: =F$4 -> 9 | G162: =G$4 -> 50 | H162: =H$4 -> 39 | I162: =I$4 -> 39 | ... O162: =O$4 -> 105 | P162: =SUM(B162:O162) -> 573 | R162: ='Fuel Ethanol'!N37 -> 150595 | S162: =R162*264.17/1000000 -> 39.782681 | T162: =S162/((P162/365)*(A162-A161)) -> 0.84471662 | V162: =O162+K162+J162+I162+G162+F162+E162+D162 -> 455 | W162: =B162+H162+L162+M162+N162 -> 108 | X162: =C162 -> 10 | Y162: =SUM(V162:X162) -> 573 | AA162: =V162/$Y162 -> 0.79406632 | AB162: =W162/$Y162 -> 0.18848168 | AC162: =X162/$Y162 -> 0.017452007 | AE162: 112185 | AF162: 365542 | AG162: =AF162*AA162 -> 290264.59 | AH162: =AG162*39.3679/1000000 -> 11.427107 | AI162: =AE162*2204.622/1000000 -> 247.32552 | AJ162: =AI162/AH162 -> 21.643756 | AK162: =AH162*$AM$6 -> 10.855752 | AN162: =R162*0.79 -> 118970.05 | AO162: =AN162/AF162 -> 0.32546205
A163: ='BD Plant List'!A162 -> 44562 | B163: =B$4 -> 40 | C163: =C$4 -> 10 | D163: =D$4 -> 56 | E163: =E$4 -> 70 | F163: =F$4 -> 9 | G163: =G$4 -> 50 | H163: =H$4 -> 39 | I163: =I$4 -> 39 | ... O163: =O$4 -> 105 | P163: =SUM(B163:O163) -> 573 | R163: ='Fuel Ethanol'!O26 -> 139729 | S163: =R163*264.17/1000000 -> 36.91221 | T163: =S163/((P163/365)*(A163-A162)) -> 0.7584843 | V163: =O163+K163+J163+I163+G163+F163+E163+D163 -> 455 | W163: =B163+H163+L163+M163+N163 -> 108 | X163: =C163 -> 10 | Y163: =SUM(V163:X163) -> 573 | AA163: =V163/$Y163 -> 0.79406632 | AB163: =W163/$Y163 -> 0.18848168 | AC163: =X163/$Y163 -> 0.017452007 | AE163: 106057 | AF163: 334774 | AG163: =AF163*AA163 -> 265832.76 | AH163: =AG163*39.3679/1000000 -> 10.465277 | AI163: =AE163*2204.622/1000000 -> 233.8156 | AJ163: =AI163/AH163 -> 22.342035 | AK163: =AH163*$AM$6 -> 9.9420135 | AN163: =R163*0.79 -> 110385.91 | AO163: =AN163/AF163 -> 0.32973263
A164: ='BD Plant List'!A163 -> 44593 | B164: =B$4 -> 40 | C164: =C$4 -> 10 | D164: =D$4 -> 56 | E164: =E$4 -> 70 | F164: =F$4 -> 9 | G164: =G$4 -> 50 | H164: =H$4 -> 39 | I164: =I$4 -> 39 | ... O164: =O$4 -> 105 | P164: =SUM(B164:O164) -> 573 | R164: ='Fuel Ethanol'!O27 -> 128540 | S164: =R164*264.17/1000000 -> 33.956412 | T164: =S164/((P164/365)*(A164-A163)) -> 0.69774758 | V164: =O164+K164+J164+I164+G164+F164+E164+D164 -> 455 | W164: =B164+H164+L164+M164+N164 -> 108 | X164: =C164 -> 10 | Y164: =SUM(V164:X164) -> 573 | AA164: =V164/$Y164 -> 0.79406632 | AB164: =W164/$Y164 -> 0.18848168 | AC164: =X164/$Y164 -> 0.017452007 | AE164: 96914 | AF164: 306133 | AG164: =AF164*AA164 -> 243089.9 | AH164: =AG164*39.3679/1000000 -> 9.569939 | AI164: =AE164*2204.622/1000000 -> 213.65874 | AJ164: =AI164/AH164 -> 22.326029 | AK164: =AH164*$AM$6 -> 9.0914421 | AN164: =R164*0.79 -> 101546.6 | AO164: =AN164/AF164 -> 0.33170746
A165: ='BD Plant List'!A164 -> 44621 | B165: =B$4 -> 40 | C165: =C$4 -> 10 | D165: =D$4 -> 56 | E165: =E$4 -> 70 | F165: =F$4 -> 9 | G165: =G$4 -> 50 | H165: =H$4 -> 39 | I165: =I$4 -> 39 | ... O165: =O$4 -> 105 | P165: =SUM(B165:O165) -> 573 | R165: ='Fuel Ethanol'!O28 -> 147011 | S165: =R165*264.17/1000000 -> 38.835896 | T165: =S165/((P165/365)*(A165-A164)) -> 0.88351421 | V165: =O165+K165+J165+I165+G165+F165+E165+D165 -> 455 | W165: =B165+H165+L165+M165+N165 -> 108 | X165: =C165 -> 10 | Y165: =SUM(V165:X165) -> 573 | AA165: =V165/$Y165 -> 0.79406632 | AB165: =W165/$Y165 -> 0.18848168 | AC165: =X165/$Y165 -> 0.017452007 | AE165: 109810 | AF165: 354342 | AG165: =AF165*AA165 -> 281371.05 | AH165: =AG165*39.3679/1000000 -> 11.076987 | AI165: =AE165*2204.622/1000000 -> 242.08954 | AJ165: =AI165/AH165 -> 21.855179 | AK165: =AH165*$AM$6 -> 10.523138 | AN165: =R165*0.79 -> 116138.69 | AO165: =AN165/AF165 -> 0.32775875
A166: ='BD Plant List'!A165 -> 44652 | B166: =B$4 -> 40 | C166: =C$4 -> 10 | D166: =D$4 -> 56 | E166: =E$4 -> 70 | F166: =F$4 -> 9 | G166: =G$4 -> 50 | H166: =H$4 -> 39 | I166: =I$4 -> 39 | ... O166: =O$4 -> 105 | P166: =SUM(B166:O166) -> 573 | R166: ='Fuel Ethanol'!O29 -> 134215 | S166: =R166*264.17/1000000 -> 35.455577 | T166: =S166/((P166/365)*(A166-A165)) -> 0.72855292 | V166: =O166+K166+J166+I166+G166+F166+E166+D166 -> 455 | W166: =B166+H166+L166+M166+N166 -> 108 | X166: =C166 -> 10 | Y166: =SUM(V166:X166) -> 573 | AA166: =V166/$Y166 -> 0.79406632 | AB166: =W166/$Y166 -> 0.18848168 | AC166: =X166/$Y166 -> 0.017452007 | AE166: 97426 | AF166: 318471 | AG166: =AF166*AA166 -> 252887.09 | AH166: =AG166*39.3679/1000000 -> 9.9556338 | AI166: =AE166*2204.622/1000000 -> 214.7875 | AJ166: =AI166/AH166 -> 21.574468 | AK166: =AH166*$AM$6 -> 9.4578521 | AN166: =R166*0.79 -> 106029.85 | AO166: =AN166/AF166 -> 0.33293408
A167: ='BD Plant List'!A166 -> 44682 | B167: =B$4 -> 40 | C167: =C$4 -> 10 | D167: =D$4 -> 56 | E167: =E$4 -> 70 | F167: =F$4 -> 9 | G167: =G$4 -> 50 | H167: =H$4 -> 39 | I167: =I$4 -> 39 | ... O167: =O$4 -> 105 | P167: =SUM(B167:O167) -> 573 | R167: ='Fuel Ethanol'!O30 -> 143661 | S167: =R167*264.17/1000000 -> 37.950926 | T167: =S167/((P167/365)*(A167-A166)) -> 0.80582246 | V167: =O167+K167+J167+I167+G167+F167+E167+D167 -> 455 | W167: =B167+H167+L167+M167+N167 -> 108 | X167: =C167 -> 10 | Y167: =SUM(V167:X167) -> 573 | AA167: =V167/$Y167 -> 0.79406632 | AB167: =W167/$Y167 -> 0.18848168 | AC167: =X167/$Y167 -> 0.017452007 | AE167: 106239 | AF167: 345483 | AG167: =AF167*AA167 -> 274336.41 | AH167: =AG167*39.3679/1000000 -> 10.800048 | AI167: =AE167*2204.622/1000000 -> 234.21684 | AJ167: =AI167/AH167 -> 21.686647 | AK167: =AH167*$AM$6 -> 10.260046 | AN167: =R167*0.79 -> 113492.19 | AO167: =AN167/AF167 -> 0.32850297
A168: ='BD Plant List'!A167 -> 44713 | B168: =B$4 -> 40 | C168: =C$4 -> 10 | D168: =D$4 -> 56 | E168: =E$4 -> 70 | F168: =F$4 -> 9 | G168: =G$4 -> 50 | H168: =H$4 -> 39 | I168: =I$4 -> 39 | ... O168: =O$4 -> 105 | P168: =SUM(B168:O168) -> 573 | R168: ='Fuel Ethanol'!O31 -> 138122 | S168: =R168*264.17/1000000 -> 36.487689 | T168: =S168/((P168/365)*(A168-A167)) -> 0.7497611 | V168: =O168+K168+J168+I168+G168+F168+E168+D168 -> 455 | W168: =B168+H168+L168+M168+N168 -> 108 | X168: =C168 -> 10 | Y168: =SUM(V168:X168) -> 573 | AA168: =V168/$Y168 -> 0.79406632 | AB168: =W168/$Y168 -> 0.18848168 | AC168: =X168/$Y168 -> 0.017452007 | AE168: 102213 | AF168: 332897 | AG168: =AF168*AA168 -> 264342.29 | AH168: =AG168*39.3679/1000000 -> 10.406601 | AI168: =AE168*2204.622/1000000 -> 225.34103 | AJ168: =AI168/AH168 -> 21.653663 | AK168: =AH168*$AM$6 -> 9.886271 | AN168: =R168*0.79 -> 109116.38 | AO168: =AN168/AF168 -> 0.3277782
A169: ='BD Plant List'!A168 -> 44743 | B169: =B$4 -> 40 | C169: =C$4 -> 10 | D169: =D$4 -> 56 | E169: =E$4 -> 70 | F169: =F$4 -> 9 | G169: =G$4 -> 50 | H169: =H$4 -> 39 | I169: =I$4 -> 39 | ... O169: =O$4 -> 105 | P169: =SUM(B169:O169) -> 573 | R169: ='Fuel Ethanol'!O32 -> 148829 | S169: =R169*264.17/1000000 -> 39.316157 | T169: =S169/((P169/365)*(A169-A168)) -> 0.83481078 | V169: =O169+K169+J169+I169+G169+F169+E169+D169 -> 455 | W169: =B169+H169+L169+M169+N169 -> 108 | X169: =C169 -> 10 | Y169: =SUM(V169:X169) -> 573 | AA169: =V169/$Y169 -> 0.79406632 | AB169: =W169/$Y169 -> 0.18848168 | AC169: =X169/$Y169 -> 0.017452007 | AE169: 112755 | AF169: 357801 | AG169: =AF169*AA169 -> 284117.72 | AH169: =AG169*39.3679/1000000 -> 11.185118 | AI169: =AE169*2204.622/1000000 -> 248.58215 | AJ169: =AI169/AH169 -> 22.224366 | AK169: =AH169*$AM$6 -> 10.625862 | AN169: =R169*0.79 -> 117574.91 | AO169: =AN169/AF169 -> 0.3286042
A170: ='BD Plant List'!A169 -> 44774 | B170: =B$4 -> 40 | C170: =C$4 -> 10 | D170: =D$4 -> 56 | E170: =E$4 -> 70 | F170: =F$4 -> 9 | G170: =G$4 -> 50 | H170: =H$4 -> 39 | I170: =I$4 -> 39 | ... O170: =O$4 -> 105 | P170: =SUM(B170:O170) -> 573 | R170: ='Fuel Ethanol'!O33 -> 147066 | S170: =R170*264.17/1000000 -> 38.850425 | T170: =S170/((P170/365)*(A170-A169)) -> 0.79831139 | V170: =O170+K170+J170+I170+G170+F170+E170+D170 -> 455 | W170: =B170+H170+L170+M170+N170 -> 108 | X170: =C170 -> 10 | Y170: =SUM(V170:X170) -> 573 | AA170: =V170/$Y170 -> 0.79406632 | AB170: =W170/$Y170 -> 0.18848168 | AC170: =X170/$Y170 -> 0.017452007 | AE170: 110254 | AF170: 356357 | AG170: =AF170*AA170 -> 282971.09 | AH170: =AG170*39.3679/1000000 -> 11.139978 | AI170: =AE170*2204.622/1000000 -> 243.06839 | AJ170: =AI170/AH170 -> 21.819469 | AK170: =AH170*$AM$6 -> 10.582979 | AN170: =R170*0.79 -> 116182.14 | AO170: =AN170/AF170 -> 0.32602738
A171: ='BD Plant List'!A170 -> 44805 | B171: =B$4 -> 40 | C171: =C$4 -> 10 | D171: =D$4 -> 56 | E171: =E$4 -> 70 | F171: =F$4 -> 9 | G171: =G$4 -> 50 | H171: =H$4 -> 39 | I171: =I$4 -> 39 | ... O171: =O$4 -> 105 | P171: =SUM(B171:O171) -> 573 | R171: ='Fuel Ethanol'!O34 -> 127518 | S171: =R171*264.17/1000000 -> 33.68643 | T171: =S171/((P171/365)*(A171-A170)) -> 0.69219991 | V171: =O171+K171+J171+I171+G171+F171+E171+D171 -> 455 | W171: =B171+H171+L171+M171+N171 -> 108 | X171: =C171 -> 10 | Y171: =SUM(V171:X171) -> 573 | AA171: =V171/$Y171 -> 0.79406632 | AB171: =W171/$Y171 -> 0.18848168 | AC171: =X171/$Y171 -> 0.017452007 | AE171: 99088 | AF171: 309156 | AG171: =AF171*AA171 -> 245490.37 | AH171: =AG171*39.3679/1000000 -> 9.6644402 | AI171: =AE171*2204.622/1000000 -> 218.45158 | AJ171: =AI171/AH171 -> 22.603646 | AK171: =AH171*$AM$6 -> 9.1812182 | AN171: =R171*0.79 -> 100739.22 | AO171: =AN171/AF171 -> 0.32585239
A172: ='BD Plant List'!A171 -> 44835 | B172: =B$4 -> 40 | C172: =C$4 -> 10 | D172: =D$4 -> 56 | E172: =E$4 -> 70 | F172: =F$4 -> 9 | G172: =G$4 -> 50 | H172: =H$4 -> 39 | I172: =I$4 -> 39 | ... O172: =O$4 -> 105 | P172: =SUM(B172:O172) -> 573 | R172: ='Fuel Ethanol'!O35 -> 138048 | S172: =R172*264.17/1000000 -> 36.46814 | T172: =S172/((P172/365)*(A172-A171)) -> 0.77433805 | V172: =O172+K172+J172+I172+G172+F172+E172+D172 -> 455 | W172: =B172+H172+L172+M172+N172 -> 108 | X172: =C172 -> 10 | Y172: =SUM(V172:X172) -> 573 | AA172: =V172/$Y172 -> 0.79406632 | AB172: =W172/$Y172 -> 0.18848168 | AC172: =X172/$Y172 -> 0.017452007 | AE172: 108175 | AF172: 333649 | AG172: =AF172*AA172 -> 264939.43 | AH172: =AG172*39.3679/1000000 -> 10.430109 | AI172: =AE172*2204.622/1000000 -> 238.48498 | AJ172: =AI172/AH172 -> 22.865052 | AK172: =AH172*$AM$6 -> 9.9086036 | AN172: =R172*0.79 -> 109057.92 | AO172: =AN172/AF172 -> 0.32686422
A173: ='BD Plant List'!A172 -> 44866 | B173: =B$4 -> 40 | C173: =C$4 -> 10 | D173: =D$4 -> 56 | E173: =E$4 -> 70 | F173: =F$4 -> 9 | G173: =G$4 -> 50 | H173: =H$4 -> 39 | I173: =I$4 -> 39 | ... O173: =O$4 -> 105 | P173: =SUM(B173:O173) -> 573 | R173: ='Fuel Ethanol'!O36 -> 148365 | S173: =R173*264.17/1000000 -> 39.193582 | T173: =S173/((P173/365)*(A173-A172)) -> 0.80536269 | V173: =O173+K173+J173+I173+G173+F173+E173+D173 -> 455 | W173: =B173+H173+L173+M173+N173 -> 108 | X173: =C173 -> 10 | Y173: =SUM(V173:X173) -> 573 | AA173: =V173/$Y173 -> 0.79406632 | AB173: =W173/$Y173 -> 0.18848168 | AC173: =X173/$Y173 -> 0.017452007 | AE173: 114234 | AF173: 358635 | AG173: =AF173*AA173 -> 284779.97 | AH173: =AG173*39.3679/1000000 -> 11.21119 | AI173: =AE173*2204.622/1000000 -> 251.84279 | AJ173: =AI173/AH173 -> 22.463521 | AK173: =AH173*$AM$6 -> 10.65063 | AN173: =R173*0.79 -> 117208.35 | AO173: =AN173/AF173 -> 0.32681793
A174: ='BD Plant List'!A173 -> 44896 | B174: =B$4 -> 40 | C174: =C$4 -> 10 | D174: =D$4 -> 56 | E174: =E$4 -> 70 | F174: =F$4 -> 9 | G174: =G$4 -> 50 | H174: =H$4 -> 39 | I174: =I$4 -> 39 | ... O174: =O$4 -> 105 | P174: =SUM(B174:O174) -> 573 | R174: ='Fuel Ethanol'!O37 -> 150449 | S174: =R174*264.17/1000000 -> 39.744112 | T174: =S174/((P174/365)*(A174-A173)) -> 0.84389767 | V174: =O174+K174+J174+I174+G174+F174+E174+D174 -> 455 | W174: =B174+H174+L174+M174+N174 -> 108 | X174: =C174 -> 10 | Y174: =SUM(V174:X174) -> 573 | AA174: =V174/$Y174 -> 0.79406632 | AB174: =W174/$Y174 -> 0.18848168 | AC174: =X174/$Y174 -> 0.017452007 | AE174: 116925 | AF174: 365518 | AG174: =AF174*AA174 -> 290245.53 | AH174: =AG174*39.3679/1000000 -> 11.426357 | AI174: =AE174*2204.622/1000000 -> 257.77543 | AJ174: =AI174/AH174 -> 22.559721 | AK174: =AH174*$AM$6 -> 10.855039 | AN174: =R174*0.79 -> 118854.71 | AO174: =AN174/AF174 -> 0.32516787
A175: ='BD Plant List'!A174 -> 44927 | B175: =B$4 -> 40 | C175: =C$4 -> 10 | D175: =D$4 -> 56 | E175: =E$4 -> 70 | F175: =F$4 -> 9 | G175: =G$4 -> 50 | H175: =H$4 -> 39 | I175: =I$4 -> 39 | ... O175: =O$4 -> 105 | P175: =SUM(B175:O175) -> 573 | R175: ='Fuel Ethanol'!P26 -> 149788 | S175: =R175*264.17/1000000 -> 39.569496 | T175: =S175/((P175/365)*(A175-A174)) -> 0.81308709 | V175: =O175+K175+J175+I175+G175+F175+E175+D175 -> 455 | W175: =B175+H175+L175+M175+N175 -> 108 | X175: =C175 -> 10 | Y175: =SUM(V175:X175) -> 573 | AA175: =V175/$Y175 -> 0.79406632 | AB175: =W175/$Y175 -> 0.18848168 | AC175: =X175/$Y175 -> 0.017452007 | AE175: 119833 | AF175: 366358 | AG175: =AF175*AA175 -> 290912.55 | AH175: =AG175*39.3679/1000000 -> 11.452616 | AI175: =AE175*2204.622/1000000 -> 264.18647 | AJ175: =AI175/AH175 -> 23.067783 | AK175: =AH175*$AM$6 -> 10.879985 | AN175: =R175*0.79 -> 118332.52 | AO175: =AN175/AF175 -> 0.32299696
A176: ='BD Plant List'!A175 -> 44958 | B176: =B$4 -> 40 | C176: =C$4 -> 10 | D176: =D$4 -> 56 | E176: =E$4 -> 70 | F176: =F$4 -> 9 | G176: =G$4 -> 50 | H176: =H$4 -> 39 | I176: =I$4 -> 39 | ... O176: =O$4 -> 105 | P176: =SUM(B176:O176) -> 573 | R176: ='Fuel Ethanol'!P27 -> 132431 | S176: =R176*264.17/1000000 -> 34.984297 | T176: =S176/((P176/365)*(A176-A175)) -> 0.71886891 | V176: =O176+K176+J176+I176+G176+F176+E176+D176 -> 455 | W176: =B176+H176+L176+M176+N176 -> 108 | X176: =C176 -> 10 | Y176: =SUM(V176:X176) -> 573 | AA176: =V176/$Y176 -> 0.79406632 | AB176: =W176/$Y176 -> 0.18848168 | AC176: =X176/$Y176 -> 0.017452007 | AE176: 103666 | AF176: 320582 | AG176: =AF176*AA176 -> 254563.37 | AH176: =AG176*39.3679/1000000 -> 10.021625 | AI176: =AE176*2204.622/1000000 -> 228.54434 | AJ176: =AI176/AH176 -> 22.805118 | AK176: =AH176*$AM$6 -> 9.520544 | AN176: =R176*0.79 -> 104620.49 | AO176: =AN176/AF176 -> 0.32634549
A177: ='BD Plant List'!A176 -> 44986 | B177: =B$4 -> 40 | C177: =C$4 -> 10 | D177: =D$4 -> 56 | E177: =E$4 -> 70 | F177: =F$4 -> 9 | G177: =G$4 -> 50 | H177: =H$4 -> 39 | I177: =I$4 -> 39 | ... O177: =O$4 -> 105 | P177: =SUM(B177:O177) -> 573 | R177: ='Fuel Ethanol'!P28 -> 155281 | S177: =R177*264.17/1000000 -> 41.020582 | T177: =S177/((P177/365)*(A177-A176)) -> 0.93321568 | V177: =O177+K177+J177+I177+G177+F177+E177+D177 -> 455 | W177: =B177+H177+L177+M177+N177 -> 108 | X177: =C177 -> 10 | Y177: =SUM(V177:X177) -> 573 | AA177: =V177/$Y177 -> 0.79406632 | AB177: =W177/$Y177 -> 0.18848168 | AC177: =X177/$Y177 -> 0.017452007 | AE177: 120665 | AF177: 377267 | AG177: =AF177*AA177 -> 299575.02 | AH177: =AG177*39.3679/1000000 -> 11.793639 | AI177: =AE177*2204.622/1000000 -> 266.02071 | AJ177: =AI177/AH177 -> 22.556287 | AK177: =AH177*$AM$6 -> 11.203957 | AN177: =R177*0.79 -> 122671.99 | AO177: =AN177/AF177 -> 0.32515961
A178: ='BD Plant List'!A177 -> 45017 | B178: =B$4 -> 40 | C178: =C$4 -> 10 | D178: =D$4 -> 56 | E178: =E$4 -> 70 | F178: =F$4 -> 9 | G178: =G$4 -> 50 | H178: =H$4 -> 39 | I178: =I$4 -> 39 | ... O178: =O$4 -> 105 | P178: =SUM(B178:O178) -> 573 | R178: ='Fuel Ethanol'!P29 -> 134197 | S178: =R178*264.17/1000000 -> 35.450821 | T178: =S178/((P178/365)*(A178-A177)) -> 0.72845521 | V178: =O178+K178+J178+I178+G178+F178+E178+D178 -> 455 | W178: =B178+H178+L178+M178+N178 -> 108 | X178: =C178 -> 10 | Y178: =SUM(V178:X178) -> 573 | AA178: =V178/$Y178 -> 0.79406632 | AB178: =W178/$Y178 -> 0.18848168 | AC178: =X178/$Y178 -> 0.017452007 | AE178: 103493 | AF178: 327601 | AG178: =AF178*AA178 -> 260136.92 | AH178: =AG178*39.3679/1000000 -> 10.241044 | AI178: =AE178*2204.622/1000000 -> 228.16294 | AJ178: =AI178/AH178 -> 22.279266 | AK178: =AH178*$AM$6 -> 9.728992 | AN178: =R178*0.79 -> 106015.63 | AO178: =AN178/AF178 -> 0.32361205
A179: ='BD Plant List'!A178 -> 45047 | B179: =B$4 -> 40 | C179: =C$4 -> 10 | D179: =D$4 -> 56 | E179: =E$4 -> 70 | F179: =F$4 -> 9 | G179: =G$4 -> 50 | H179: =H$4 -> 39 | I179: =I$4 -> 39 | ... O179: =O$4 -> 105 | P179: =SUM(B179:O179) -> 573 | R179: ='Fuel Ethanol'!P30 -> 131166 | S179: =R179*264.17/1000000 -> 34.650122 | T179: =S179/((P179/365)*(A179-A178)) -> 0.73573558 | V179: =O179+K179+J179+I179+G179+F179+E179+D179 -> 455 | W179: =B179+H179+L179+M179+N179 -> 108 | X179: =C179 -> 10 | Y179: =SUM(V179:X179) -> 573 | AA179: =V179/$Y179 -> 0.79406632 | AB179: =W179/$Y179 -> 0.18848168 | AC179: =X179/$Y179 -> 0.017452007 | AE179: 101573 | AF179: 317948 | AG179: =AF179*AA179 -> 252471.8 | AH179: =AG179*39.3679/1000000 -> 9.9392845 | AI179: =AE179*2204.622/1000000 -> 223.93007 | AJ179: =AI179/AH179 -> 22.529798 | AK179: =AH179*$AM$6 -> 9.4423203 | AN179: =R179*0.79 -> 103621.14 | AO179: =AN179/AF179 -> 0.32590593
A180: ='BD Plant List'!A179 -> 45078 | B180: =B$4 -> 40 | C180: =C$4 -> 10 | D180: =D$4 -> 56 | E180: =E$4 -> 70 | F180: =F$4 -> 9 | G180: =G$4 -> 50 | H180: =H$4 -> 39 | I180: =I$4 -> 39 | ... O180: =O$4 -> 105 | P180: =SUM(B180:O180) -> 573 | R180: ='Fuel Ethanol'!P31 -> 138214 | S180: =R180*264.17/1000000 -> 36.511992 | T180: =S180/((P180/365)*(A180-A179)) -> 0.7502605 | V180: =O180+K180+J180+I180+G180+F180+E180+D180 -> 455 | W180: =B180+H180+L180+M180+N180 -> 108 | X180: =C180 -> 10 | Y180: =SUM(V180:X180) -> 573 | AA180: =V180/$Y180 -> 0.79406632 | AB180: =W180/$Y180 -> 0.18848168 | AC180: =X180/$Y180 -> 0.017452007 | AE180: 100593 | AF180: 336240 | AG180: =AF180*AA180 -> 266996.86 | AH180: =AG180*39.3679/1000000 -> 10.511106 | AI180: =AE180*2204.622/1000000 -> 221.76954 | AJ180: =AI180/AH180 -> 21.098593 | AK180: =AH180*$AM$6 -> 9.9855503 | AN180: =R180*0.79 -> 109189.06 | AO180: =AN180/AF180 -> 0.32473549
A181: ='BD Plant List'!A180 -> 45108 | B181: =B$4 -> 40 | C181: =C$4 -> 10 | D181: =D$4 -> 56 | E181: =E$4 -> 70 | F181: =F$4 -> 9 | G181: =G$4 -> 50 | H181: =H$4 -> 39 | I181: =I$4 -> 39 | ... O181: =O$4 -> 105 | P181: =SUM(B181:O181) -> 573 | R181: ='Fuel Ethanol'!P32 -> 153288 | S181: =R181*264.17/1000000 -> 40.494091 | T181: =S181/((P181/365)*(A181-A180)) -> 0.85982218 | V181: =O181+K181+J181+I181+G181+F181+E181+D181 -> 455 | W181: =B181+H181+L181+M181+N181 -> 108 | X181: =C181 -> 10 | Y181: =SUM(V181:X181) -> 573 | AA181: =V181/$Y181 -> 0.79406632 | AB181: =W181/$Y181 -> 0.18848168 | AC181: =X181/$Y181 -> 0.017452007 | AE181: 115510 | AF181: 366776 | AG181: =AF181*AA181 -> 291244.47 | AH181: =AG181*39.3679/1000000 -> 11.465683 | AI181: =AE181*2204.622/1000000 -> 254.65589 | AJ181: =AI181/AH181 -> 22.210267 | AK181: =AH181*$AM$6 -> 10.892399 | AN181: =R181*0.79 -> 121097.52 | AO181: =AN181/AF181 -> 0.33016751
A182: ='BD Plant List'!A181 -> 45139 | B182: =B$4 -> 40 | C182: =C$4 -> 10 | D182: =D$4 -> 56 | E182: =E$4 -> 70 | F182: =F$4 -> 9 | G182: =G$4 -> 50 | H182: =H$4 -> 39 | I182: =I$4 -> 39 | ... O182: =O$4 -> 105 | P182: =SUM(B182:O182) -> 573 | R182: ='Fuel Ethanol'!P33 -> 151728 | S182: =R182*264.17/1000000 -> 40.081986 | T182: =S182/((P182/365)*(A182-A181)) -> 0.8236179 | V182: =O182+K182+J182+I182+G182+F182+E182+D182 -> 455 | W182: =B182+H182+L182+M182+N182 -> 108 | X182: =C182 -> 10 | Y182: =SUM(V182:X182) -> 573 | AA182: =V182/$Y182 -> 0.79406632 | AB182: =W182/$Y182 -> 0.18848168 | AC182: =X182/$Y182 -> 0.017452007 | AE182: 114594 | AF182: 363285 | AG182: =AF182*AA182 -> 288472.38 | AH182: =AG182*39.3679/1000000 -> 11.356552 | AI182: =AE182*2204.622/1000000 -> 252.63645 | AJ182: =AI182/AH182 -> 22.245877 | AK182: =AH182*$AM$6 -> 10.788724 | AN182: =R182*0.79 -> 119865.12
A183: ='BD Plant List'!A182 -> 45170 | B183: =B$4 -> 40 | C183: =C$4 -> 10 | D183: =D$4 -> 56 | E183: =E$4 -> 70 | F183: =F$4 -> 9 | G183: =G$4 -> 50 | H183: =H$4 -> 39 | I183: =I$4 -> 39 | ... O183: =O$4 -> 105 | P183: =SUM(B183:O183) -> 573 | R183: ='Fuel Ethanol'!P34 -> 136625 | S183: =R183*264.17/1000000 -> 36.092226 | T183: =S183/((P183/365)*(A183-A182)) -> 0.741635 | V183: =O183+K183+J183+I183+G183+F183+E183+D183 -> 455 | W183: =B183+H183+L183+M183+N183 -> 108 | X183: =C183 -> 10 | Y183: =SUM(V183:X183) -> 573 | AA183: =V183/$Y183 -> 0.79406632 | AB183: =W183/$Y183 -> 0.18848168 | AC183: =X183/$Y183 -> 0.017452007 | AE183: 105889 | AF183: 331540 | AG183: =AF183*AA183 -> 263264.75 | AH183: =AG183*39.3679/1000000 -> 10.36418 | AI183: =AE183*2204.622/1000000 -> 233.44522 | AJ183: =AI183/AH183 -> 22.524234 | AK183: =AH183*$AM$6 -> 9.8459712 | AN183: =R183*0.79 -> 107933.75
A184: ='BD Plant List'!A183 -> 45200 | B184: =B$4 -> 40 | C184: =C$4 -> 10 | D184: =D$4 -> 56 | E184: =E$4 -> 70 | F184: =F$4 -> 9 | G184: =G$4 -> 50 | H184: =H$4 -> 39 | I184: =I$4 -> 39 | ... O184: =O$4 -> 105 | P184: =SUM(B184:O184) -> 573 | R184: ='Fuel Ethanol'!P35 -> 129366 | S184: =R184*264.17/1000000 -> 34.174616 | T184: =S184/((P184/365)*(A184-A183)) -> 0.72563903 | V184: =O184+K184+J184+I184+G184+F184+E184+D184 -> 455 | W184: =B184+H184+L184+M184+N184 -> 108 | X184: =C184 -> 10 | Y184: =SUM(V184:X184) -> 573 | AA184: =V184/$Y184 -> 0.79406632 | AB184: =W184/$Y184 -> 0.18848168 | AC184: =X184/$Y184 -> 0.017452007 | AE184: 102886 | AF184: 311868 | AG184: =AF184*AA184 -> 247643.87 | AH184: =AG184*39.3679/1000000 -> 9.7492193 | AI184: =AE184*2204.622/1000000 -> 226.82474 | AJ184: =AI184/AH184 -> 23.265939 | AK184: =AH184*$AM$6 -> 9.2617583 | AN184: =R184*0.79 -> 102199.14
A185: ='BD Plant List'!A184 -> 45231 | B185: =B$4 -> 40 | C185: =C$4 -> 10 | D185: =D$4 -> 56 | E185: =E$4 -> 70 | F185: =F$4 -> 9 | G185: =G$4 -> 50 | H185: =H$4 -> 39 | I185: =I$4 -> 39 | ... O185: =O$4 -> 105 | P185: =SUM(B185:O185) -> 573 | R185: ='Fuel Ethanol'!P36 -> 152552 | S185: =R185*264.17/1000000 -> 40.299662 | T185: =S185/((P185/365)*(A185-A184)) -> 0.82809078 | V185: =O185+K185+J185+I185+G185+F185+E185+D185 -> 455 | W185: =B185+H185+L185+M185+N185 -> 108 | X185: =C185 -> 10 | Y185: =SUM(V185:X185) -> 573 | AA185: =V185/$Y185 -> 0.79406632 | AB185: =W185/$Y185 -> 0.18848168 | AC185: =X185/$Y185 -> 0.017452007 | AE185: 112464 | AF185: 362961 | AG185: =AF185*AA185 -> 288215.1 | AH185: =AG185*39.3679/1000000 -> 11.346423 | AI185: =AE185*2204.622/1000000 -> 247.94061 | AJ185: =AI185/AH185 -> 21.851873 | AK185: =AH185*$AM$6 -> 10.779102 | AN185: =R185*0.79 -> 120516.08
A186: ='BD Plant List'!A185 -> 45261 | B186: =B$4 -> 40 | C186: =C$4 -> 10 | D186: =D$4 -> 56 | E186: =E$4 -> 70 | F186: =F$4 -> 9 | G186: =G$4 -> 50 | H186: =H$4 -> 39 | I186: =I$4 -> 39 | ... O186: =O$4 -> 105 | P186: =SUM(B186:O186) -> 573 | R186: ='Fuel Ethanol'!P37 -> 152162 | S186: =R186*264.17/1000000 -> 40.196636 | T186: =S186/((P186/365)*(A186-A185)) -> 0.85350622 | V186: =O186+K186+J186+I186+G186+F186+E186+D186 -> 455 | W186: =B186+H186+L186+M186+N186 -> 108 | X186: =C186 -> 10 | Y186: =SUM(V186:X186) -> 573 | AA186: =V186/$Y186 -> 0.79406632 | AB186: =W186/$Y186 -> 0.18848168 | AC186: =X186/$Y186 -> 0.017452007 | AE186: 112601 | AF186: 363354 | AG186: =AF186*AA186 -> 288527.17 | AH186: =AG186*39.3679/1000000 -> 11.358709 | AI186: =AE186*2204.622/1000000 -> 248.24264 | AJ186: =AI186/AH186 -> 21.854829 | AK186: =AH186*$AM$6 -> 10.790773 | AN186: =R186*0.79 -> 120207.98
A187: ='BD Plant List'!A186 -> 45292 | B187: =B$4 -> 40 | C187: =C$4 -> 10 | D187: =D$4 -> 56 | E187: =E$4 -> 70 | F187: =F$4 -> 9 | G187: =G$4 -> 50 | H187: =H$4 -> 39 | I187: =I$4 -> 39 | ... O187: =O$4 -> 105 | P187: =SUM(B187:O187) -> 573 | R187: ='Fuel Ethanol'!Q26 -> 148957 | S187: =R187*264.17/1000000 -> 39.349971 | T187: =S187/((P187/365)*(A187-A186)) -> 0.80857621 | V187: =O187+K187+J187+I187+G187+F187+E187+D187 -> 455 | W187: =B187+H187+L187+M187+N187 -> 108 | X187: =C187 -> 10 | Y187: =SUM(V187:X187) -> 573 | AA187: =V187/$Y187 -> 0.79406632 | AB187: =W187/$Y187 -> 0.18848168 | AC187: =X187/$Y187 -> 0.017452007 | AE187: 118431 | AF187: 353410 | AG187: =AF187*AA187 -> 280630.98 | AH187: =AG187*39.3679/1000000 -> 11.047852 | AI187: =AE187*2204.622/1000000 -> 261.09559 | AJ187: =AI187/AH187 -> 23.633153 | AK187: =AH187*$AM$6 -> 10.49546 | AN187: =R187*0.79 -> 117676.03
A188: ='BD Plant List'!A187 -> 45323 | B188: =B$4 -> 40 | C188: =C$4 -> 10 | D188: =D$4 -> 56 | E188: =E$4 -> 70 | F188: =F$4 -> 9 | G188: =G$4 -> 50 | H188: =H$4 -> 39 | I188: =I$4 -> 39 | ... O188: =O$4 -> 105 | P188: =SUM(B188:O188) -> 573 | R188: ='Fuel Ethanol'!Q27 -> 142598 | S188: =R188*264.17/1000000 -> 37.670114 | T188: =S188/((P188/365)*(A188-A187)) -> 0.77405796 | V188: =O188+K188+J188+I188+G188+F188+E188+D188 -> 455 | W188: =B188+H188+L188+M188+N188 -> 108 | X188: =C188 -> 10 | Y188: =SUM(V188:X188) -> 573 | AA188: =V188/$Y188 -> 0.79406632 | AB188: =W188/$Y188 -> 0.18848168 | AC188: =X188/$Y188 -> 0.017452007 | AE188: 109074 | AF188: 347905 | AG188: =AF188*AA188 -> 276259.64 | AH188: =AG188*39.3679/1000000 -> 10.875762 | AI188: =AE188*2204.622/1000000 -> 240.46694 | AJ188: =AI188/AH188 -> 22.110353 | AK188: =AH188*$AM$6 -> 10.331974 | AN188: =R188*0.79 -> 112652.42
A189: ='BD Plant List'!A188 -> 45352 | B189: =B$4 -> 40 | C189: =C$4 -> 10 | D189: =D$4 -> 56 | E189: =E$4 -> 70 | F189: =F$4 -> 9 | G189: =G$4 -> 50 | H189: =H$4 -> 39 | I189: =I$4 -> 39 | ... O189: =O$4 -> 105 | P189: =SUM(B189:O189) -> 573 | R189: ='Fuel Ethanol'!Q28 -> 153372 | S189: =R189*264.17/1000000 -> 40.516281 | T189: =S189/((P189/365)*(A189-A188)) -> 0.88995864 | V189: =O189+K189+J189+I189+G189+F189+E189+D189 -> 455 | W189: =B189+H189+L189+M189+N189 -> 108 | X189: =C189 -> 10 | Y189: =SUM(V189:X189) -> 573 | AA189: =V189/$Y189 -> 0.79406632 | AB189: =W189/$Y189 -> 0.18848168 | AC189: =X189/$Y189 -> 0.017452007 | AE189: 108285 | AF189: 371867 | AG189: =AF189*AA189 -> 295287.06 | AH189: =AG189*39.3679/1000000 -> 11.624831 | AI189: =AE189*2204.622/1000000 -> 238.72749 | AJ189: =AI189/AH189 -> 20.535996 | AK189: =AH189*$AM$6 -> 11.04359 | AN189: =R189*0.79 -> 121163.88
A190: ='BD Plant List'!A189 -> 45383 | B190: =B$4 -> 40 | C190: =C$4 -> 10 | D190: =D$4 -> 56 | E190: =E$4 -> 70 | F190: =F$4 -> 9 | G190: =G$4 -> 50 | H190: =H$4 -> 39 | I190: =I$4 -> 39 | ... O190: =O$4 -> 105 | P190: =SUM(B190:O190) -> 573 | R190: ='Fuel Ethanol'!Q29 -> 140027 | S190: =R190*264.17/1000000 -> 36.990933 | T190: =S190/((P190/365)*(A190-A189)) -> 0.76010192 | V190: =O190+K190+J190+I190+G190+F190+E190+D190 -> 455 | W190: =B190+H190+L190+M190+N190 -> 108 | X190: =C190 -> 10 | Y190: =SUM(V190:X190) -> 573 | AA190: =V190/$Y190 -> 0.79406632 | AB190: =W190/$Y190 -> 0.18848168 | AC190: =X190/$Y190 -> 0.017452007 | AE190: 104764 | AF190: 335534 | AG190: =AF190*AA190 -> 266436.25 | AH190: =AG190*39.3679/1000000 -> 10.489036 | AI190: =AE190*2204.622/1000000 -> 230.96502 | AJ190: =AI190/AH190 -> 22.019662 | AK190: =AH190*$AM$6 -> 9.9645838 | AN190: =R190*0.79 -> 110621.33
A191: ='BD Plant List'!A190 -> 45413 | B191: =B$4 -> 40 | C191: =C$4 -> 10 | D191: =D$4 -> 56 | E191: =E$4 -> 70 | F191: =F$4 -> 9 | G191: =G$4 -> 50 | H191: =H$4 -> 39 | I191: =I$4 -> 39 | ... O191: =O$4 -> 105 | P191: =SUM(B191:O191) -> 573 | R191: ='Fuel Ethanol'!Q30 -> 144909 | S191: =R191*264.17/1000000 -> 38.280611 | T191: =S191/((P191/365)*(A191-A190)) -> 0.81282274 | V191: =O191+K191+J191+I191+G191+F191+E191+D191 -> 455 | W191: =B191+H191+L191+M191+N191 -> 108 | X191: =C191 -> 10 | Y191: =SUM(V191:X191) -> 573 | AA191: =V191/$Y191 -> 0.79406632 | AB191: =W191/$Y191 -> 0.18848168 | AC191: =X191/$Y191 -> 0.017452007 | AE191: 108197 | AF191: 335979 | AG191: =AF191*AA191 -> 266789.61 | AH191: =AG191*39.3679/1000000 -> 10.502947 | AI191: =AE191*2204.622/1000000 -> 238.53349 | AJ191: =AI191/AH191 -> 22.711102 | AK191: =AH191*$AM$6 -> 9.9777993 | AN191: =R191*0.79 -> 114478.11
A192: ='BD Plant List'!A191 -> 45444 | B192: =B$4 -> 40 | C192: =C$4 -> 10 | D192: =D$4 -> 56 | E192: =E$4 -> 70 | F192: =F$4 -> 9 | G192: =G$4 -> 50 | H192: =H$4 -> 39 | I192: =I$4 -> 39 | ... O192: =O$4 -> 105 | P192: =SUM(B192:O192) -> 573 | R192: ='Fuel Ethanol'!Q31 -> 142682 | S192: =R192*264.17/1000000 -> 37.692304 | T192: =S192/((P192/365)*(A192-A191)) -> 0.77451393 | V192: =O192+K192+J192+I192+G192+F192+E192+D192 -> 455 | W192: =B192+H192+L192+M192+N192 -> 108 | X192: =C192 -> 10 | Y192: =SUM(V192:X192) -> 573 | AA192: =V192/$Y192 -> 0.79406632 | AB192: =W192/$Y192 -> 0.18848168 | AC192: =X192/$Y192 -> 0.017452007 | AE192: 101597 | AF192: 335862 | AG192: =AF192*AA192 -> 266696.7 | AH192: =AG192*39.3679/1000000 -> 10.499289 | AI192: =AE192*2204.622/1000000 -> 223.98298 | AJ192: =AI192/AH192 -> 21.333157 | AK192: =AH192*$AM$6 -> 9.9743246 | AN192: =R192*0.79 -> 112718.78
A193: ='BD Plant List'!A192 -> 45474 | B193: =B$4 -> 40 | C193: =C$4 -> 10 | D193: =D$4 -> 56 | E193: =E$4 -> 70 | F193: =F$4 -> 9 | G193: =G$4 -> 50 | H193: =H$4 -> 39 | I193: =I$4 -> 39 | ... O193: =O$4 -> 105 | P193: =SUM(B193:O193) -> 573 | R193: ='Fuel Ethanol'!Q32 -> 154666 | S193: =R193*264.17/1000000 -> 40.858117 | T193: =S193/((P193/365)*(A193-A192)) -> 0.86755165 | V193: =O193+K193+J193+I193+G193+F193+E193+D193 -> 455 | W193: =B193+H193+L193+M193+N193 -> 108 | X193: =C193 -> 10 | Y193: =SUM(V193:X193) -> 573 | AA193: =V193/$Y193 -> 0.79406632 | AB193: =W193/$Y193 -> 0.18848168 | AC193: =X193/$Y193 -> 0.017452007 | AE193: 115356 | AF193: 381749 | AG193: =AF193*AA193 -> 303134.02 | AH193: =AG193*39.3679/1000000 -> 11.93375 | AI193: =AE193*2204.622/1000000 -> 254.31638 | AJ193: =AI193/AH193 -> 21.310684 | AK193: =AH193*$AM$6 -> 11.337062 | AN193: =R193*0.79 -> 122186.14
A194: ='BD Plant List'!A193 -> 45505 | B194: =B$4 -> 40 | C194: =C$4 -> 10 | D194: =D$4 -> 56 | E194: =E$4 -> 70 | F194: =F$4 -> 9 | G194: =G$4 -> 50 | H194: =H$4 -> 39 | I194: =I$4 -> 39 | ... O194: =O$4 -> 105 | P194: =SUM(B194:O194) -> 573 | R194: ='Fuel Ethanol'!Q33 -> 160518 | S194: =R194*264.17/1000000 -> 42.40404 | T194: =S194/((P194/365)*(A194-A193)) -> 0.87133224 | V194: =O194+K194+J194+I194+G194+F194+E194+D194 -> 455 | W194: =B194+H194+L194+M194+N194 -> 108 | X194: =C194 -> 10 | Y194: =SUM(V194:X194) -> 573 | AA194: =V194/$Y194 -> 0.79406632 | AB194: =W194/$Y194 -> 0.18848168 | AC194: =X194/$Y194 -> 0.017452007 | AE194: 119890 | AF194: 392334 | AG194: =AF194*AA194 -> 311539.21 | AH194: =AG194*39.3679/1000000 -> 12.264645 | AI194: =AE194*2204.622/1000000 -> 264.31213 | AJ194: =AI194/AH194 -> 21.550737 | AK194: =AH194*$AM$6 -> 11.651412 | AN194: =R194*0.79 -> 126809.22
A195: ='BD Plant List'!A194 -> 45536 | B195: =B$4 -> 40 | C195: =C$4 -> 10 | D195: =D$4 -> 56 | E195: =E$4 -> 70 | F195: =F$4 -> 9 | G195: =G$4 -> 50 | H195: =H$4 -> 39 | I195: =I$4 -> 39 | ... O195: =O$4 -> 105 | P195: =SUM(B195:O195) -> 573 | R195: ='Fuel Ethanol'!Q34 -> 136191 | S195: =R195*264.17/1000000 -> 35.977576 | T195: =S195/((P195/365)*(A195-A194)) -> 0.73927914 | V195: =O195+K195+J195+I195+G195+F195+E195+D195 -> 455 | W195: =B195+H195+L195+M195+N195 -> 108 | X195: =C195 -> 10 | Y195: =SUM(V195:X195) -> 573 | AA195: =V195/$Y195 -> 0.79406632 | AB195: =W195/$Y195 -> 0.18848168 | AC195: =X195/$Y195 -> 0.017452007 | AE195: 102005 | AF195: 330767 | AG195: =AF195*AA195 -> 262650.93 | AH195: =AG195*39.3679/1000000 -> 10.340016 | AI195: =AE195*2204.622/1000000 -> 224.88247 | AJ195: =AI195/AH195 -> 21.748755 | AK195: =AH195*$AM$6 -> 9.8230149 | AN195: =R195*0.79 -> 107590.89
A196: ='BD Plant List'!A195 -> 45566 | B196: =B$4 -> 40 | C196: =C$4 -> 10 | D196: =D$4 -> 56 | E196: =E$4 -> 70 | F196: =F$4 -> 9 | G196: =G$4 -> 50 | H196: =H$4 -> 39 | I196: =I$4 -> 39 | ... O196: =O$4 -> 105 | P196: =SUM(B196:O196) -> 573 | R196: ='Fuel Ethanol'!Q35 -> 139687 | S196: =R196*264.17/1000000 -> 36.901115 | T196: =S196/((P196/365)*(A196-A195)) -> 0.78353152 | V196: =O196+K196+J196+I196+G196+F196+E196+D196 -> 455 | W196: =B196+H196+L196+M196+N196 -> 108 | X196: =C196 -> 10 | Y196: =SUM(V196:X196) -> 573 | AA196: =V196/$Y196 -> 0.79406632 | AB196: =W196/$Y196 -> 0.18848168 | AC196: =X196/$Y196 -> 0.017452007 | AE196: 99714 | AF196: 328336 | AG196: =AF196*AA196 -> 260720.56 | AH196: =AG196*39.3679/1000000 -> 10.264021 | AI196: =AE196*2204.622/1000000 -> 219.83168 | AJ196: =AI196/AH196 -> 21.417696 | AK196: =AH196*$AM$6 -> 9.7508198 | AN196: =R196*0.79 -> 110352.73
A197: ='BD Plant List'!A196 -> 45597 | B197: =B$4 -> 40 | C197: =C$4 -> 10 | D197: =D$4 -> 56 | E197: =E$4 -> 70 | F197: =F$4 -> 9 | G197: =G$4 -> 50 | H197: =H$4 -> 39 | I197: =I$4 -> 39 | ... O197: =O$4 -> 105 | P197: =SUM(B197:O197) -> 573 | R197: ='Fuel Ethanol'!Q36 -> 149096 | S197: =R197*264.17/1000000 -> 39.38669 | T197: =S197/((P197/365)*(A197-A196)) -> 0.80933074 | V197: =O197+K197+J197+I197+G197+F197+E197+D197 -> 455 | W197: =B197+H197+L197+M197+N197 -> 108 | X197: =C197 -> 10 | Y197: =SUM(V197:X197) -> 573 | AA197: =V197/$Y197 -> 0.79406632 | AB197: =W197/$Y197 -> 0.18848168 | AC197: =X197/$Y197 -> 0.017452007 | AE197: 106518 | AF197: 357808 | AG197: =AF197*AA197 -> 284123.28 | AH197: =AG197*39.3679/1000000 -> 11.185337 | AI197: =AE197*2204.622/1000000 -> 234.83193 | AJ197: =AI197/AH197 -> 20.994623 | AK197: =AH197*$AM$6 -> 10.62607 | AN197: =R197*0.79 -> 117785.84
A198: ='BD Plant List'!A197 -> 45627 | B198: =B$4 -> 40 | C198: =C$4 -> 10 | D198: =D$4 -> 56 | E198: =E$4 -> 70 | F198: =F$4 -> 9 | G198: =G$4 -> 50 | H198: =H$4 -> 39 | I198: =I$4 -> 39 | ... O198: =O$4 -> 105 | P198: =SUM(B198:O198) -> 573 | R198: ='Fuel Ethanol'!Q37 -> 144741 | S198: =R198*264.17/1000000 -> 38.23623 | T198: =S198/((P198/365)*(A198-A197)) -> 0.81188039 | V198: =O198+K198+J198+I198+G198+F198+E198+D198 -> 455 | W198: =B198+H198+L198+M198+N198 -> 108 | X198: =C198 -> 10 | Y198: =SUM(V198:X198) -> 573 | AA198: =V198/$Y198 -> 0.79406632 | AB198: =W198/$Y198 -> 0.18848168 | AC198: =X198/$Y198 -> 0.017452007 | AE198: 101245 | AF198: 345456 | AG198: =AF198*AA198 -> 274314.97 | AH198: =AG198*39.3679/1000000 -> 10.799204 | AI198: =AE198*2204.622/1000000 -> 223.20695 | AJ198: =AI198/AH198 -> 20.668833 | AK198: =AH198*$AM$6 -> 10.259244 | AN198: =R198*0.79 -> 114345.39
A199: ='BD Plant List'!A198 -> 45658 | B199: =B$4 -> 40 | C199: =C$4 -> 10 | D199: =D$4 -> 56 | E199: =E$4 -> 70 | F199: =F$4 -> 9 | G199: =G$4 -> 50 | H199: =H$4 -> 39 | I199: =I$4 -> 39 | ... O199: =O$4 -> 105 | P199: =SUM(B199:O199) -> 573 | R199: ='Fuel Ethanol'!R26 -> 141528 | S199: =R199*264.17/1000000 -> 37.387452 | T199: =S199/((P199/365)*(A199-A198)) -> 0.76824973 | V199: =O199+K199+J199+I199+G199+F199+E199+D199 -> 455 | W199: =B199+H199+L199+M199+N199 -> 108 | X199: =C199 -> 10 | Y199: =SUM(V199:X199) -> 573 | AA199: =V199/$Y199 -> 0.79406632 | AB199: =W199/$Y199 -> 0.18848168 | AC199: =X199/$Y199 -> 0.017452007 | AE199: 102062 | AF199: 338279 | AG199: =AF199*AA199 -> 268615.96 | AH199: =AG199*39.3679/1000000 -> 10.574846 | AI199: =AE199*2204.622/1000000 -> 225.00813 | AJ199: =AI199/AH199 -> 21.277674 | AK199: =AH199*$AM$6 -> 10.046104 | AN199: =R199*0.79 -> 111807.12
A200: ='BD Plant List'!A199 -> 45689 | B200: =B$4 -> 40 | C200: =C$4 -> 10 | D200: =D$4 -> 56 | E200: =E$4 -> 70 | F200: =F$4 -> 9 | G200: =G$4 -> 50 | H200: =H$4 -> 39 | I200: =I$4 -> 39 | ... O200: =O$4 -> 105 | P200: =SUM(B200:O200) -> 573 | R200: ='Fuel Ethanol'!R27 -> 139170 | S200: =R200*264.17/1000000 -> 36.764539 | T200: =S200/((P200/365)*(A200-A199)) -> 0.75544991 | V200: =O200+K200+J200+I200+G200+F200+E200+D200 -> 455 | W200: =B200+H200+L200+M200+N200 -> 108 | X200: =C200 -> 10 | Y200: =SUM(V200:X200) -> 573 | AA200: =V200/$Y200 -> 0.79406632 | AB200: =W200/$Y200 -> 0.18848168 | AC200: =X200/$Y200 -> 0.017452007 | AE200: 98935 | AF200: 337221 | AG200: =AF200*AA200 -> 267775.84 | AH200: =AG200*39.3679/1000000 -> 10.541772 | AI200: =AE200*2204.622/1000000 -> 218.11428 | AJ200: =AI200/AH200 -> 20.690475 | AK200: =AH200*$AM$6 -> 10.014684 | AN200: =R200*0.79 -> 109944.3
A201: ='BD Plant List'!A200 -> 45717 | B201: =B$4 -> 40 | C201: =C$4 -> 10 | D201: =D$4 -> 56 | E201: =E$4 -> 70 | F201: =F$4 -> 9 | G201: =G$4 -> 50 | H201: =H$4 -> 39 | I201: =I$4 -> 39 | ... O201: =O$4 -> 105 | P201: =SUM(B201:O201) -> 573 | R201: ='Fuel Ethanol'!R28 -> 144964.63 | S201: =R201*264.17/1000000 -> 38.295307 | T201: =S201/((P201/365)*(A201-A200)) -> 0.87121584 | V201: =O201+K201+J201+I201+G201+F201+E201+D201 -> 455 | W201: =B201+H201+L201+M201+N201 -> 108 | X201: =C201 -> 10 | Y201: =SUM(V201:X201) -> 573 | AA201: =V201/$Y201 -> 0.79406632 | AB201: =W201/$Y201 -> 0.18848168 | AC201: =X201/$Y201 -> 0.017452007 | AF201: =AN201/0.3 -> 381740.19 | AG201: =AF201*AA201 -> 303127.03 | AH201: =AG201*39.3679/1000000 -> 11.933475 | AK201: =AH201*$AM$6 -> 11.336801 | AN201: =R201*0.79 -> 114522.06
A202: ='BD Plant List'!A201 -> 45748 | B202: =B$4 -> 40 | C202: =C$4 -> 10 | D202: =D$4 -> 56 | E202: =E$4 -> 70 | F202: =F$4 -> 9 | G202: =G$4 -> 50 | H202: =H$4 -> 39 | I202: =I$4 -> 39 | ... O202: =O$4 -> 105 | P202: =SUM(B202:O202) -> 573 | R202: ='Fuel Ethanol'!R29 -> 131714.81 | S202: =R202*264.17/1000000 -> 34.795101 | T202: =S202/((P202/365)*(A202-A201)) -> 0.71498124 | V202: =O202+K202+J202+I202+G202+F202+E202+D202 -> 455 | W202: =B202+H202+L202+M202+N202 -> 108 | X202: =C202 -> 10 | Y202: =SUM(V202:X202) -> 573 | AA202: =V202/$Y202 -> 0.79406632 | AB202: =W202/$Y202 -> 0.18848168 | AC202: =X202/$Y202 -> 0.017452007 | AF202: =AN202/0.3 -> 346848.99 | AG202: =AF202*AA202 -> 275421.1 | AH202: =AG202*39.3679/1000000 -> 10.84275 | AK202: =AH202*$AM$6 -> 10.300613 | AN202: =R202*0.79 -> 104054.7
A203: ='BD Plant List'!A202 -> 45778 | B203: =B$4 -> 40 | C203: =C$4 -> 10 | D203: =D$4 -> 56 | E203: =E$4 -> 70 | F203: =F$4 -> 9 | G203: =G$4 -> 50 | H203: =H$4 -> 39 | I203: =I$4 -> 39 | ... O203: =O$4 -> 105 | P203: =SUM(B203:O203) -> 573 | R203: ='Fuel Ethanol'!R30 -> 137726.65 | S203: =R203*264.17/1000000 -> 36.383249 | T203: =S203/((P203/365)*(A203-A202)) -> 0.77253553 | V203: =O203+K203+J203+I203+G203+F203+E203+D203 -> 455 | W203: =B203+H203+L203+M203+N203 -> 108 | X203: =C203 -> 10 | Y203: =SUM(V203:X203) -> 573 | AA203: =V203/$Y203 -> 0.79406632 | AB203: =W203/$Y203 -> 0.18848168 | AC203: =X203/$Y203 -> 0.017452007 | AF203: =AN203/0.3 -> 362680.17 | AG203: =AF203*AA203 -> 287992.11 | AH203: =AG203*39.3679/1000000 -> 11.337645 | AK203: =AH203*$AM$6 -> 10.770762 | AN203: =R203*0.79 -> 108804.05
A204: ='BD Plant List'!A203 -> 45809 | B204: =B$4 -> 40 | C204: =C$4 -> 10 | D204: =D$4 -> 56 | E204: =E$4 -> 70 | F204: =F$4 -> 9 | G204: =G$4 -> 50 | H204: =H$4 -> 39 | I204: =I$4 -> 39 | ... O204: =O$4 -> 105 | P204: =SUM(B204:O204) -> 573 | R204: ='Fuel Ethanol'!R31 -> 135298.33 | S204: =R204*264.17/1000000 -> 35.741761 | T204: =S204/((P204/365)*(A204-A203)) -> 0.73443352 | V204: =O204+K204+J204+I204+G204+F204+E204+D204 -> 455 | W204: =B204+H204+L204+M204+N204 -> 108 | X204: =C204 -> 10 | Y204: =SUM(V204:X204) -> 573 | AA204: =V204/$Y204 -> 0.79406632 | AB204: =W204/$Y204 -> 0.18848168 | AC204: =X204/$Y204 -> 0.017452007 | AF204: =AN204/0.3 -> 356285.61 | AG204: =AF204*AA204 -> 282914.4 | AH204: =AG204*39.3679/1000000 -> 11.137746 | AK204: =AH204*$AM$6 -> 10.580859 | AN204: =R204*0.79 -> 106885.68
A205: ='BD Plant List'!A204 -> 45839 | B205: =B$4 -> 40 | C205: =C$4 -> 10 | D205: =D$4 -> 56 | E205: =E$4 -> 70 | F205: =F$4 -> 9 | G205: =G$4 -> 50 | H205: =H$4 -> 39 | I205: =I$4 -> 39 | ... O205: =O$4 -> 105 | P205: =SUM(B205:O205) -> 573 | R205: ='Fuel Ethanol'!R32 -> 149686.49 | S205: =R205*264.17/1000000 -> 39.54268 | T205: =S205/((P205/365)*(A205-A204)) -> 0.83962061 | V205: =O205+K205+J205+I205+G205+F205+E205+D205 -> 455 | W205: =B205+H205+L205+M205+N205 -> 108 | X205: =C205 -> 10 | Y205: =SUM(V205:X205) -> 573 | AA205: =V205/$Y205 -> 0.79406632 | AB205: =W205/$Y205 -> 0.18848168 | AC205: =X205/$Y205 -> 0.017452007 | AF205: =AN205/0.3 -> 394174.42 | AG205: =AF205*AA205 -> 313000.63 | AH205: =AG205*39.3679/1000000 -> 12.322178 | AK205: =AH205*$AM$6 -> 11.706069 | AN205: =R205*0.79 -> 118252.33
A206: ='BD Plant List'!A205 -> 45870 | B206: =B$4 -> 40 | C206: =C$4 -> 10 | D206: =D$4 -> 56 | E206: =E$4 -> 70 | F206: =F$4 -> 9 | G206: =G$4 -> 50 | H206: =H$4 -> 39 | I206: =I$4 -> 39 | ... O206: =O$4 -> 105 | P206: =SUM(B206:O206) -> 573 | R206: ='Fuel Ethanol'!R33 -> 148609.3 | S206: =R206*264.17/1000000 -> 39.25812 | T206: =S206/((P206/365)*(A206-A205)) -> 0.80668884 | V206: =O206+K206+J206+I206+G206+F206+E206+D206 -> 455 | W206: =B206+H206+L206+M206+N206 -> 108 | X206: =C206 -> 10 | Y206: =SUM(V206:X206) -> 573 | AA206: =V206/$Y206 -> 0.79406632 | AB206: =W206/$Y206 -> 0.18848168 | AC206: =X206/$Y206 -> 0.017452007 | AF206: =AN206/0.3 -> 391337.84 | AG206: =AF206*AA206 -> 310748.19 | AH206: =AG206*39.3679/1000000 -> 12.233504 | AK206: =AH206*$AM$6 -> 11.621829 | AN206: =R206*0.79 -> 117401.35
A207: ='BD Plant List'!A206 -> 45901 | B207: =B$4 -> 40 | C207: =C$4 -> 10 | D207: =D$4 -> 56 | E207: =E$4 -> 70 | F207: =F$4 -> 9 | G207: =G$4 -> 50 | H207: =H$4 -> 39 | I207: =I$4 -> 39 | ... O207: =O$4 -> 105 | P207: =SUM(B207:O207) -> 573 | R207: ='Fuel Ethanol'!R34 -> 132707.36 | S207: =R207*264.17/1000000 -> 35.057304 | T207: =S207/((P207/365)*(A207-A206)) -> 0.72036909 | V207: =O207+K207+J207+I207+G207+F207+E207+D207 -> 455 | W207: =B207+H207+L207+M207+N207 -> 108 | X207: =C207 -> 10 | Y207: =SUM(V207:X207) -> 573 | AA207: =V207/$Y207 -> 0.79406632 | AB207: =W207/$Y207 -> 0.18848168 | AC207: =X207/$Y207 -> 0.017452007 | AF207: =AN207/0.3 -> 349462.72 | AG207: =AF207*AA207 -> 277496.58 | AH207: =AG207*39.3679/1000000 -> 10.924458 | AK207: =AH207*$AM$6 -> 10.378235 | AN207: =R207*0.79 -> 104838.82
...

Sheet Ethanol Feedstock Use
B1: Co-Op Ethanol Complex | C1: Enerkem Alberta Biofuels LP | D1: Greenfield Global | E1: Greenfield Global | F1: Greenfield Global | G1: Greenfield Global | H1: Husky Energy (Cenovus) | I1: Husky Energy (Cenovus) | J1: IGCP Ethanol Inc | K1: Kawartha Ethanol Inc | L1: North West Pure Alcohol & Sprirts | M1: Permolex Ltd. | N1: Pound-Maker Agventures Ltd. | O1: Suncor
B3: SK | C3: AB | D3: Chatham, ON | E3: Johnston, ON | F3: Tiverton, ON | G3: Varennes. QC | H3: Lloydminster, AB | I3: Minnedosa, MB | J3: ON | K3: ON | L3: SK | M3: AB | N3: SK | O3: St. Clair, ON
B4: 40 | C4: 10 | D4: 56 | E4: 70 | F4: 9 | G4: 50 | H4: 39 | I4: 39 | J4: 100 | K4: 26 | L4: 7 | M4: 12 | N4: 10 | O4: 105
B5: Other Grains | C5: Other | D5: Corn | E5: Corn | F5: Corn | G5: Corn | H5: Other Grains | I5: Corn | J5: Corn | K5: Corn | L5: Other Grains | M5: Other Grains | N5: Other Grains | O5: Corn
A7: ='Ethanol Plant List'!A7 -> 39814
A8: ='Ethanol Plant List'!A8 -> 39845
A9: ='Ethanol Plant List'!A9 -> 39873
A10: ='Ethanol Plant List'!A10 -> 39904
A11: ='Ethanol Plant List'!A11 -> 39934
A12: ='Ethanol Plant List'!A12 -> 39965
A13: ='Ethanol Plant List'!A13 -> 39995
A14: ='Ethanol Plant List'!A14 -> 40026
A15: ='Ethanol Plant List'!A15 -> 40057
A16: ='Ethanol Plant List'!A16 -> 40087
A17: ='Ethanol Plant List'!A17 -> 40118
A18: ='Ethanol Plant List'!A18 -> 40148
... A426: ='Ethanol Plant List'!A426 -> 52566

Sheet Ethanol Conversion
B1: gal/bu. | C1: bu/gal | D1: tonnes/gal | E1: tonnes per cubic meter
A2: Corn | B2: 2.8 | C2: =1/B2 -> 0.35714286 | D2: =C2/39.3679 -> 0.0090719306 | E2: =D2*264.17 -> 2.3965319

Sheet Renewable Fuel Ex Ethanol
A1: CANADA - RENEWABLE FUEL (ex. ETHANOL) SUPPLY AND DEMAND
A2: mmg | B2: 2013 | C2: 2014 | D2: 2015 | E2: 2016 | F2: 2017 | G2: 2018 | H2: 2019 | I2: 2020 | J2: 2021 | K2: 2022 | L2: 2023 | M2: 2024 | N2: 2025 | O2: 2026 | P2: 2027 | Q2: 2028 | R2: 2029 | S2: 2030 | T2: 2031 | U2: 2032 | V2: 2033 | W2: 2034 | X2: 2035 | Y2: 2036 | Z2: 2037 | AA2: 2038 | AB2: 2039 | AC2: 2040 | AD2: 2041 | AE2: 2042 | AF2: 2043 | AG2: 2044 | AH2: 2045 | AI2: 2046 | AJ2: 2047 | AK2: 2048 | AL2: 2049 | AM2: 2050 | AP2: .87 tonnes per cubic meters
A3: Beginning Stocks | I3: 6227 | J3: =I10 -> 8864 | K3: =J10 -> 6926 | L3: =K10 -> 5059 | M3: =L10 -> 11139 | N3: =M10 -> 49050 | O3: =N10 -> 45000 | P3: =O10 -> 50000 | Q3: =P10 -> 50000 | ... AM3: =AL10 -> 60000
A4: Production | B4: =B103/$I$121*1000000 -> 159000.05 | C4: =C103/$I$121*1000000 -> 351000.1 | D4: =D103/$I$121*1000000 -> 397000.12 | E4: =E103/$I$121*1000000 -> 464000.13 | F4: =F103/$I$121*1000000 -> 397000.12 | G4: =G103/$I$121*1000000 -> 308000.09 | H4: =H103/$I$121*1000000 -> 359000.1 | I4: =I34 -> 457810 | J4: =J34 -> 430742 | K4: =K34 -> 369192 | L4: =L34 -> 508106 | M4: =M34 -> 1120304 | N4: =N103/$I$121*1000000 -> 1135623.3 | O4: =O103/$I$121*1000000 -> 1400602.1 | P4: =P103/$I$121*1000000 -> 1835924.4 | Q4: =Q103/$I$121*1000000 -> 2044122 | R4: =R103/$I$121*1000000 -> 2044122 | S4: =S103/$I$121*1000000 -> 2157684.3 | T4: =T103/$I$121*1000000 -> 2195538.4 | U4: =U103/$I$121*1000000 -> 2233392.5 | ... AM4: =AM103/$I$121*1000000 -> 2365881.9
A5: Imports | I5: =I50 -> 451697.7 | J5: =J50 -> 441694.63 | K5: =K50 -> 591375.92 | L5: =L50 -> 694405.09 | M5: =M50 -> 508803.37 | N5: 450000 | O5: 400000 | P5: 350000 | Q5: 350000 | R5: 300000 | S5: 275000 | T5: 250000 | U5: 200000 | V5: 200000 | W5: 175000 | X5: 175000 | Y5: 150000 | Z5: 150000 | AA5: 150000 | AB5: 125000 | AC5: 125000 | AD5: 125000 | AE5: 125000 | AF5: 125000 | AG5: 125000 | AH5: 100000 | AI5: 100000 | AJ5: 100000 | AK5: 100000 | AL5: 100000 | AM5: 100000
A6: Total Supply | I6: =SUM(I3:I5) -> 915734.7 | J6: =SUM(J3:J5) -> 881300.63 | K6: =SUM(K3:K5) -> 967493.92 | L6: =SUM(L3:L5) -> 1207570.1 | M6: =SUM(M3:M5) -> 1640246.4 | N6: =SUM(N3:N5) -> 1634673.3 | O6: =SUM(O3:O5) -> 1845602.1 | P6: =SUM(P3:P5) -> 2235924.4 | ... AM6: =SUM(AM3:AM5) -> 2525881.9
A7: Domestic Use | I7: =I9-I8 -> 559596.44 | J7: =J9-J8 -> 535106.5 | K7: =K9-K8 -> 670664.74 | L7: =L9-L8 -> 797539.02 | M7: =M9-M8 -> 1213563 | N7: =N9-N8 -> 1202673.3 | O7: =O9-O8 -> 1391602.1 | P7: =P9-P8 -> 1748924.4 | ... AM7: =AM9-AM8 -> 2004881.9
A8: Exports | I8: =I66 -> 347274.27 | J8: =J66 -> 339268.14 | K8: =K66 -> 291770.18 | L8: =L66 -> 398892.07 | M8: =M66 -> 377633.36 | N8: =MROUND(M8*1.025,1000) -> 387000 | O8: =MROUND(FORECAST(O6,I8:N8,I6:N6),1000) -> 404000 | P8: =MROUND(FORECAST(P6,J8:O8,J6:O6),1000) -> 437000 | Q8: =MROUND(FORECAST(Q6,K8:P8,K6:P6),1000) -> 459000 | R8: =MROUND(FORECAST(R6,L8:Q8,L6:Q6),1000) -> 443000 | S8: =MROUND(FORECAST(S6,M8:R8,M6:R6),1000) -> 458000 | T8: =MROUND(FORECAST(T6,N8:S8,N6:S6),1000) -> 458000 | U8: =MROUND(FORECAST(U6,O8:T8,O6:T6),1000) -> 457000 | V8: =MROUND(FORECAST(V6,P8:U8,P6:U6),1000) -> 461000 | ... AG8: =MROUND(FORECAST(AG6,AA8:AF8,AA6:AF6),1000) -> 465000 | AH8: =MROUND(FORECAST(AH6,V8:AG8,V6:AG6),1000) -> 461000 | AI8: =MROUND(FORECAST(AI6,W8:AH8,W6:AH6),1000) -> 461000 | AJ8: =MROUND(FORECAST(AJ6,X8:AI8,X6:AI6),1000) -> 461000 | AK8: =MROUND(FORECAST(AK6,Y8:AJ8,Y6:AJ6),1000) -> 461000 | AL8: =MROUND(FORECAST(AL6,Z8:AK8,Z6:AK6),1000) -> 461000 | AM8: =MROUND(FORECAST(AM6,AA8:AL8,AA6:AL6),1000) -> 461000
A9: Total Use | I9: =I6-I10 -> 906870.7 | J9: =J6-J10 -> 874374.63 | K9: =K6-K10 -> 962434.92 | L9: =L6-L10 -> 1196431.1 | M9: =M6-M10 -> 1591196.4 | N9: =N6-N10 -> 1589673.3 | O9: =O6-O10 -> 1795602.1 | P9: =P6-P10 -> 2185924.4 | ... AM9: =AM6-AM10 -> 2465881.9
A10: Ending stocks | I10: =I97 -> 8864 | J10: =J97 -> 6926 | K10: =K97 -> 5059 | L10: =L97 -> 11139 | M10: =M97 -> 49050 | N10: 45000 | O10: 50000 | P10: 50000 | Q10: 52000 | R10: 55000 | S10: 55000 | T10: 55000 | U10: 55000 | V10: 55000 | W10: 60000 | X10: 60000 | Y10: 60000 | Z10: 60000 | AA10: 60000 | AB10: 60000 | AC10: 60000 | AD10: 60000 | AE10: 60000 | AF10: 60000 | AG10: 60000 | AH10: 60000 | AI10: 60000 | AJ10: 60000 | AK10: 60000 | AL10: 60000 | AM10: 60000
A12: Stocks to Use | I12: =I10/I9 -> 0.009774271 | J12: =J10/J9 -> 0.0079210898 | K12: =K10/K9 -> 0.0052564593 | L12: =L10/L9 -> 0.0093101894 | M12: =M10/M9 -> 0.030825862 | N12: =N10/N9 -> 0.028307703 | O12: =O10/O9 -> 0.027845813 | P12: =P10/P9 -> 0.022873618 | ... AM12: =AM10/AM9 -> 0.024332065
A13: Net Trade From Diesel Sales Tab | K13: =('Annual Diesel Sales'!AE7-'Annual Diesel Sales'!AE8)/$I$121*1000000 -> 167720.35 | L13: =('Annual Diesel Sales'!AF7-'Annual Diesel Sales'!AF8)/$I$121*1000000 -> 73828.158 | M13: =('Annual Diesel Sales'!AG7-'Annual Diesel Sales'!AG8)/$I$121*1000000 -> -530463.16 | N13: =('Annual Diesel Sales'!AH7-'Annual Diesel Sales'!AH8)/$I$121*1000000 -> -538078.31 | O13: =('Annual Diesel Sales'!AI7-'Annual Diesel Sales'!AI8)/$I$121*1000000 -> -795503.83 | P13: =('Annual Diesel Sales'!AJ7-'Annual Diesel Sales'!AJ8)/$I$121*1000000 -> -1223425 | Q13: =('Annual Diesel Sales'!AK7-'Annual Diesel Sales'!AK8)/$I$121*1000000 -> -1424380.6 | R13: =('Annual Diesel Sales'!AL7-'Annual Diesel Sales'!AL8)/$I$121*1000000 -> -1417304.2 | ... AM13: =('Annual Diesel Sales'!BG7-'Annual Diesel Sales'!BG8)/$I$121*1000000 -> -1186300.7
A14: Required for Mandate | Q14: =Q83 -> 619740.66 | R14: =R83 -> 626816.97 | S14: =S83 -> 928409.09 | T14: =T83 -> 940030.19 | U14: =U83 -> 951545.58 | V14: =V83 -> 963150.84 | W14: =W83 -> 974845.7 | X14: =X83 -> 986632.57 | ... AM14: =AM83 -> 1179580.3
A15: NONSENSE
A16: Shipments | I16: =I174 -> 455166 | J16: =J174 -> 435053 | K16: =K174 -> 375686 | L16: =L174 -> 514036 | M16: =M174 -> 1120304 | N16: =N7*$I$122 -> 1051978.4 | O16: =O7*$I$122 -> 1217234.4 | P16: =P7*$I$122 -> 1529784.2 | Q16: =Q7*$I$122 -> 1690901.8 | R16: =R7*$I$122 -> 1660287.3 | S16: =S7*$I$122 -> 1727256.4 | T16: =T7*$I$122 -> 1738499.9 | U16: =U7*$I$122 -> 1728750.6 | ... AM16: =AM7*$I$122 -> 1753670.2
A17: Losses and adjustments | I17: =I190 -> 1796 | J17: =J190 -> 588 | K17: =K190 -> 783 | L17: =L190 -> 1429 | M17: =M190 -> 916 | N17: =N9-N8-N18-N16 -> 148021.64 | O17: =O9-O8-O18-O16 -> 24765.637 | P17: =P9-P8-P18-P16 -> -244784.16 | Q17: =Q9-Q8-Q18-Q16 -> -360901.81 | R17: =R9-R8-R18-R16 -> -283287.31 | S17: =S9-S8-S18-S16 -> -302256.38 | T17: =T9-T8-T18-T16 -> -263499.87 | U17: =U9-U8-U18-U16 -> -201750.56 | ... AM17: =AM9-AM8-AM18-AM16 -> -728656.23
A18: Residual | I18: =I9-SUM(I16:I17) -> 449908.7 | J18: =J9-SUM(J16:J17) -> 438733.63 | K18: =K9-SUM(K16:K17) -> 585965.92 | L18: =L9-SUM(L16:L17) -> 680966.09 | M18: =M9-SUM(M16:M17) -> 469976.37 | N18: =N7-N82 -> 2673.3304 | O18: =O7-O82 -> 149602.11 | P18: =P7-P82 -> 463924.38 | Q18: =Q7-Q82 -> 603121.99 | R18: =R7-R82 -> 521121.99 | S18: =S7-S82 -> 549684.33 | T18: =T7-T82 -> 512538.44 | U18: =U7-U82 -> 449392.55 | ... AM18: =AM7-AM82 -> 979867.94
I19: =I16/I7 -> 0.81338259 | J19: =J16/J7 -> 0.81302134 | K19: =K16/K7 -> 0.5601696 | L19: =L16/L7 -> 0.64452771 | M19: =M16/M7 -> 0.92315272 | N19: =N16/N7 -> 0.8747 | O19: =O16/O7 -> 0.8747 | P19: =P16/P7 -> 0.8747 | ... S19: =S16/S7 -> 0.8747
A20: PRODUCTION | AP20: Quarterly
I21: =I2 -> 2020 | J21: =J2 -> 2021 | K21: =K2 -> 2022 | L21: =L2 -> 2023 | M21: =M2 -> 2024 | N21: =N2 -> 2025 | O21: =O2 -> 2026 | P21: =P2 -> 2027 | ... AM21: =AM2 -> 2050 | AQ21: 2019 | AR21: 2020 | AS21: 2021 | AT21: 2022 | AU21: 2023 | AV21: 2024 | AW21: 2025 | AX21: 2026 | AY21: 2027 | AZ21: 2028 | BA21: 2029 | BB21: 2030 | BC21: 2031 | BD21: 2032 | BE21: 2033 | BF21: 2034
A22: January | B22: =B$34*(SUM(C22:E22)/SUM(C$34:E$34)) -> 11960.518 | C22: =C$34*(SUM(D22:F22)/SUM(D$34:F$34)) -> 26599.014 | D22: =D$34*(SUM(E22:G22)/SUM(E$34:G$34)) -> 29989.841 | E22: =E$34*(SUM(F22:H22)/SUM(F$34:H$34)) -> 34581.888 | F22: =F$34*(SUM(G22:I22)/SUM(G$34:I$34)) -> 30760.347 | G22: =G$34*(SUM(H22:J22)/SUM(H$34:J$34)) -> 22965.383 | H22: =H$34*(SUM(I22:K22)/SUM(I$34:K$34)) -> 25574.116 | I22: =Data!$D3 -> 38613 | J22: =Data!$D15 -> 28834 | K22: =Data!$D27 -> 22151 | L22: =Data!$D39 -> 36671 | M22: =Data!$D51 -> 44804 | N22: =Data!$D63 -> 38041 | O22: =O$34*(SUM(L22:N22)/SUM(L$34:N$34)) -> 60561.629 | P22: =P$34*(SUM(M22:O22)/SUM(M$34:O$34)) -> 72003.721 | Q22: =Q$34*(SUM(N22:P22)/SUM(N$34:P$34)) -> 79764.008 | R22: =R$34*(SUM(O22:Q22)/SUM(O$34:Q$34)) -> 82192.01 | S22: =S$34*(SUM(P22:R22)/SUM(P$34:R$34)) -> 85212.173 | T22: =T$34*(SUM(Q22:S22)/SUM(Q$34:S$34)) -> 86883.364 | U22: =U$34*(SUM(R22:T22)/SUM(R$34:T$34)) -> 88774.943 | V22: =V$34*(SUM(S22:U22)/SUM(S$34:U$34)) -> 89955.338 | ... AM22: =AM$34*(SUM(AJ22:AL22)/SUM(AJ$34:AL$34)) -> 93802.741 | AP22: Q1 | AQ22: =SUM(H22:H24) -> 78113.829 | AR22: =SUM(I22:I24) -> 107068 | AS22: =SUM(J22:J24) -> 95284 | AT22: =SUM(K22:K24) -> 71317 | AU22: =SUM(L22:L24) -> 116690 | AV22: =SUM(M22:M24) -> 220017 | AW22: =SUM(N22:N24) -> 174474.61 | AX22: =SUM(O22:O24) -> 259028.01 | ... BF22: =SUM(W22:W24) -> 408858.45
A23: February | B23: =B$34*(SUM(C23:E23)/SUM(C$34:E$34)) -> 11666.255 | C23: =C$34*(SUM(D23:F23)/SUM(D$34:F$34)) -> 25859.283 | D23: =D$34*(SUM(E23:G23)/SUM(E$34:G$34)) -> 29259.782 | E23: =E$34*(SUM(F23:H23)/SUM(F$34:H$34)) -> 33808.614 | F23: =F$34*(SUM(G23:I23)/SUM(G$34:I$34)) -> 29612.452 | G23: =G$34*(SUM(H23:J23)/SUM(H$34:J$34)) -> 22736.831 | H23: =H$34*(SUM(I23:K23)/SUM(I$34:K$34)) -> 25177.366 | I23: =Data!$D4 -> 35986 | J23: =Data!$D16 -> 30932 | K23: =Data!$D28 -> 21290 | L23: =Data!$D40 -> 37187 | M23: =Data!$D52 -> 64489 | N23: =Data!$D64 -> 38294 | O23: =O$34*(SUM(L23:N23)/SUM(L$34:N$34)) -> 70926.162 | P23: =P$34*(SUM(M23:O23)/SUM(M$34:O$34)) -> 87218.466 | Q23: =Q$34*(SUM(N23:P23)/SUM(N$34:P$34)) -> 91841.436 | R23: =R$34*(SUM(O23:Q23)/SUM(O$34:Q$34)) -> 96768.799 | S23: =S$34*(SUM(P23:R23)/SUM(P$34:R$34)) -> 100461.57 | T23: =T$34*(SUM(Q23:S23)/SUM(Q$34:S$34)) -> 101613.12 | U23: =U$34*(SUM(R23:T23)/SUM(R$34:T$34)) -> 104329.98 | V23: =V$34*(SUM(S23:U23)/SUM(S$34:U$34)) -> 105656.78 | ... AM23: =AM$34*(SUM(AJ23:AL23)/SUM(AJ$34:AL$34)) -> 110119.46 | AP23: Q2 | AQ23: =SUM(H25:H27) -> 85951.5 | AR23: =SUM(I25:I27) -> 113284 | AS23: =SUM(J25:J27) -> 105170 | AT23: =SUM(K25:K27) -> 82674 | AU23: =SUM(L25:L27) -> 124645 | AV23: =SUM(M25:M27) -> 323199 | AW23: =SUM(N25:N27) -> 294700.17 | AX23: =SUM(O25:O27) -> 376264.97 | ... BF23: =SUM(W25:W27) -> 621428.95
A24: March | B24: =B$34*(SUM(C24:E24)/SUM(C$34:E$34)) -> 11969.202 | C24: =C$34*(SUM(D24:F24)/SUM(D$34:F$34)) -> 26322.338 | D24: =D$34*(SUM(E24:G24)/SUM(E$34:G$34)) -> 29884.174 | E24: =E$34*(SUM(F24:H24)/SUM(F$34:H$34)) -> 35030.426 | F24: =F$34*(SUM(G24:I24)/SUM(G$34:I$34)) -> 29425.86 | G24: =G$34*(SUM(H24:J24)/SUM(H$34:J$34)) -> 23540.185 | H24: =H$34*(SUM(I24:K24)/SUM(I$34:K$34)) -> 27362.346 | I24: =Data!$D5 -> 32469 | J24: =Data!$D17 -> 35518 | K24: =Data!$D29 -> 27876 | L24: =Data!$D41 -> 42832 | M24: =Data!$D53 -> 110724 | N24: =N$34*(SUM(I24:M24)/SUM(I$34:M$34)) -> 98139.613 | O24: =O$34*(SUM(L24:N24)/SUM(L$34:N$34)) -> 127540.22 | P24: =P$34*(SUM(M24:O24)/SUM(M$34:O$34)) -> 168906.61 | Q24: =Q$34*(SUM(N24:P24)/SUM(N$34:P$34)) -> 184481.97 | R24: =R$34*(SUM(O24:Q24)/SUM(O$34:Q$34)) -> 186165.99 | S24: =S$34*(SUM(P24:R24)/SUM(P$34:R$34)) -> 196515.08 | T24: =T$34*(SUM(Q24:S24)/SUM(Q$34:S$34)) -> 199366.4 | U24: =U$34*(SUM(R24:T24)/SUM(R$34:T$34)) -> 203200 | V24: =V$34*(SUM(S24:U24)/SUM(S$34:U$34)) -> 206579.82 | ... AM24: =AM$34*(SUM(AJ24:AL24)/SUM(AJ$34:AL$34)) -> 215151.47 | AP24: Q3 | AQ24: =SUM(H28:H30) -> 92532.415 | AR24: =SUM(I28:I30) -> 119769 | AS24: =SUM(J28:J30) -> 112673 | AT24: =SUM(K28:K30) -> 91742 | AU24: =SUM(L28:L30) -> 126026 | AV24: =SUM(M28:M30) -> 304402 | AW24: =SUM(N28:N30) -> 296919.36 | AX24: =SUM(O28:O30) -> 368564.38 | ... BF24: =SUM(W28:W30) -> 609740.39
A25: April | B25: =B$34*(SUM(C25:E25)/SUM(C$34:E$34)) -> 12446.777 | C25: =C$34*(SUM(D25:F25)/SUM(D$34:F$34)) -> 27444.268 | D25: =D$34*(SUM(E25:G25)/SUM(E$34:G$34)) -> 31110.979 | E25: =E$34*(SUM(F25:H25)/SUM(F$34:H$34)) -> 36322.069 | F25: =F$34*(SUM(G25:I25)/SUM(G$34:I$34)) -> 30928.458 | G25: =G$34*(SUM(H25:J25)/SUM(H$34:J$34)) -> 24358.377 | H25: =H$34*(SUM(I25:K25)/SUM(I$34:K$34)) -> 28003.426 | I25: =Data!$D6 -> 35267 | J25: =Data!$D18 -> 35393 | K25: =Data!$D30 -> 27449 | L25: =Data!$D42 -> 34504 | M25: =Data!$D54 -> 92393 | N25: =N$34*(SUM(I25:M25)/SUM(I$34:M$34)) -> 88533.759 | O25: =O$34*(SUM(L25:N25)/SUM(L$34:N$34)) -> 109163.94 | P25: =P$34*(SUM(M25:O25)/SUM(M$34:O$34)) -> 145653.03 | Q25: =Q$34*(SUM(N25:P25)/SUM(N$34:P$34)) -> 160527.61 | R25: =R$34*(SUM(O25:Q25)/SUM(O$34:Q$34)) -> 160778.55 | S25: =S$34*(SUM(P25:R25)/SUM(P$34:R$34)) -> 170074.59 | T25: =T$34*(SUM(Q25:S25)/SUM(Q$34:S$34)) -> 172727.78 | U25: =U$34*(SUM(R25:T25)/SUM(R$34:T$34)) -> 175806.36 | V25: =V$34*(SUM(S25:U25)/SUM(S$34:U$34)) -> 178830.6 | ... AM25: =AM$34*(SUM(AJ25:AL25)/SUM(AJ$34:AL$34)) -> 186241.31 | AP25: Q4 | AQ25: =SUM(H31:H33) -> 102402.36 | AR25: =SUM(I31:I33) -> 117689 | AS25: =SUM(J31:J33) -> 117615 | AT25: =SUM(K31:K33) -> 123459 | AU25: =SUM(L31:L33) -> 140745 | AV25: =SUM(M31:M33) -> 272686 | AW25: =SUM(N31:N33) -> 369529.19 | AX25: =SUM(O31:O33) -> 396744.74 | ... BF25: =SUM(W31:W33) -> 669072.98
A26: May | B26: =B$34*(SUM(C26:E26)/SUM(C$34:E$34)) -> 12625.118 | C26: =C$34*(SUM(D26:F26)/SUM(D$34:F$34)) -> 28071.843 | D26: =D$34*(SUM(E26:G26)/SUM(E$34:G$34)) -> 31570.02 | E26: =E$34*(SUM(F26:H26)/SUM(F$34:H$34)) -> 36594.887 | F26: =F$34*(SUM(G26:I26)/SUM(G$34:I$34)) -> 32445.856 | G26: =G$34*(SUM(H26:J26)/SUM(H$34:J$34)) -> 23919.846 | H26: =H$34*(SUM(I26:K26)/SUM(I$34:K$34)) -> 27550.161 | I26: =Data!$D7 -> 40458 | J26: =Data!$D19 -> 28879 | K26: =Data!$D31 -> 27184 | L26: =Data!$D43 -> 42519 | M26: =Data!$D55 -> 98861 | N26: =N$34*(SUM(I26:M26)/SUM(I$34:M$34)) -> 93607.592 | O26: =O$34*(SUM(L26:N26)/SUM(L$34:N$34)) -> 119073.86 | P26: =P$34*(SUM(M26:O26)/SUM(M$34:O$34)) -> 156423.84 | Q26: =Q$34*(SUM(N26:P26)/SUM(N$34:P$34)) -> 172568.71 | R26: =R$34*(SUM(O26:Q26)/SUM(O$34:Q$34)) -> 173445.06 | S26: =S$34*(SUM(P26:R26)/SUM(P$34:R$34)) -> 182996.45 | T26: =T$34*(SUM(Q26:S26)/SUM(Q$34:S$34)) -> 185955.11 | U26: =U$34*(SUM(R26:T26)/SUM(R$34:T$34)) -> 189357.4 | V26: =V$34*(SUM(S26:U26)/SUM(S$34:U$34)) -> 192520.33 | ... AM26: =AM$34*(SUM(AJ26:AL26)/SUM(AJ$34:AL$34)) -> 200531.88 | AP26: Total | AQ26: =SUM(AQ22:AQ25) -> 359000.1 | AR26: =SUM(AR22:AR25) -> 457810 | AS26: =SUM(AS22:AS25) -> 430742 | AT26: =SUM(AT22:AT25) -> 369192 | AU26: =SUM(AU22:AU25) -> 508106 | AV26: =SUM(AV22:AV24) -> 847618 | AW26: =SUM(AW22:AW24) -> 766094.14 | AX26: =SUM(AX22:AX24) -> 1003857.4 | AY26: =SUM(AY22:AY24) -> 1314268 | AZ26: =SUM(AZ22:AZ24) -> 1441972.8 | BA26: =SUM(BA22:BA24) -> 1455521.9 | BB26: =SUM(BB22:BB24) -> 1533996.6 | BC26: =SUM(BC22:BC24) -> 1557736.3 | ... BF26: =SUM(BF22:BF24) -> 1640027.8 | BG26: =(BF26/AW26)^(1/10)-1 -> 0.079088108
A27: June | B27: =B$34*(SUM(C27:E27)/SUM(C$34:E$34)) -> 13558.595 | C27: =C$34*(SUM(D27:F27)/SUM(D$34:F$34)) -> 29847.634 | D27: =D$34*(SUM(E27:G27)/SUM(E$34:G$34)) -> 33932.541 | E27: =E$34*(SUM(F27:H27)/SUM(F$34:H$34)) -> 39572.137 | F27: =F$34*(SUM(G27:I27)/SUM(G$34:I$34)) -> 33470.604 | G27: =G$34*(SUM(H27:J27)/SUM(H$34:J$34)) -> 26874.487 | H27: =H$34*(SUM(I27:K27)/SUM(I$34:K$34)) -> 30397.913 | I27: =Data!$D8 -> 37559 | J27: =Data!$D20 -> 40898 | K27: =Data!$D32 -> 28041 | L27: =Data!$D44 -> 47622 | M27: =Data!$D56 -> 131945 | N27: =N$34*(SUM(I27:M27)/SUM(I$34:M$34)) -> 112558.82 | O27: =O$34*(SUM(L27:N27)/SUM(L$34:N$34)) -> 148027.17 | P27: =P$34*(SUM(M27:O27)/SUM(M$34:O$34)) -> 197087.77 | Q27: =Q$34*(SUM(N27:P27)/SUM(N$34:P$34)) -> 213977.34 | R27: =R$34*(SUM(O27:Q27)/SUM(O$34:Q$34)) -> 216422.82 | S27: =S$34*(SUM(P27:R27)/SUM(P$34:R$34)) -> 228541.93 | T27: =T$34*(SUM(Q27:S27)/SUM(Q$34:S$34)) -> 231628.13 | U27: =U$34*(SUM(R27:T27)/SUM(R$34:T$34)) -> 236206.98 | V27: =V$34*(SUM(S27:U27)/SUM(S$34:U$34)) -> 240130.01 | ... AM27: =AM$34*(SUM(AJ27:AL27)/SUM(AJ$34:AL$34)) -> 250075.01 | AU27: =(AU26/AT26)-1 -> 0.37626492
A28: July | B28: =B$34*(SUM(C28:E28)/SUM(C$34:E$34)) -> 14795.672 | C28: =C$34*(SUM(D28:F28)/SUM(D$34:F$34)) -> 32840.938 | D28: =D$34*(SUM(E28:G28)/SUM(E$34:G$34)) -> 37111.412 | E28: =E$34*(SUM(F28:H28)/SUM(F$34:H$34)) -> 42829.756 | F28: =F$34*(SUM(G28:I28)/SUM(G$34:I$34)) -> 37762.25 | G28: =G$34*(SUM(H28:J28)/SUM(H$34:J$34)) -> 28685.679 | H28: =H$34*(SUM(I28:K28)/SUM(I$34:K$34)) -> 31765.132 | I28: =Data!$D9 -> 46540 | J28: =Data!$D21 -> 37886 | K28: =Data!$D33 -> 26862 | L28: =Data!$D45 -> 46154 | M28: =Data!$D57 -> 106971 | N28: =N$34*(SUM(I28:M28)/SUM(I$34:M$34)) -> 104039.34 | O28: =O$34*(SUM(L28:N28)/SUM(L$34:N$34)) -> 130311.35 | P28: =P$34*(SUM(M28:O28)/SUM(M$34:O$34)) -> 171375.85 | Q28: =Q$34*(SUM(N28:P28)/SUM(N$34:P$34)) -> 189690.33 | R28: =R$34*(SUM(O28:Q28)/SUM(O$34:Q$34)) -> 190210.66 | S28: =S$34*(SUM(P28:R28)/SUM(P$34:R$34)) -> 200784.53 | T28: =T$34*(SUM(Q28:S28)/SUM(Q$34:S$34)) -> 204119.76 | U28: =U$34*(SUM(R28:T28)/SUM(R$34:T$34)) -> 207762.03 | V28: =V$34*(SUM(S28:U28)/SUM(S$34:U$34)) -> 211264.25 | ... AM28: =AM$34*(SUM(AJ28:AL28)/SUM(AJ$34:AL$34)) -> 220055.4 | AP28: Mo-Mo Change | AQ28: =AQ24/AQ23-1 -> 0.076565447 | AR28: =AR24/AR23-1 -> 0.057245507 | AS28: =AS24/AS23-1 -> 0.071341637 | AT28: =AT24/AT23-1 -> 0.10968382 | AU28: =AU24/AU23-1 -> 0.011079466 | AV28: =AV24/AV23-1 -> -0.058159215 | AW28: =AW24/AW23-1 -> 0.0075303216 | AX28: =AX24/AX23-1 -> -0.020465871 | ... BF28: =BF24/BF23-1 -> -0.018809167
A29: August | B29: =B$34*(SUM(C29:E29)/SUM(C$34:E$34)) -> 13136.761 | C29: =C$34*(SUM(D29:F29)/SUM(D$34:F$34)) -> 28979.137 | D29: =D$34*(SUM(E29:G29)/SUM(E$34:G$34)) -> 32851.208 | E29: =E$34*(SUM(F29:H29)/SUM(F$34:H$34)) -> 38306.475 | F29: =F$34*(SUM(G29:I29)/SUM(G$34:I$34)) -> 32704.863 | G29: =G$34*(SUM(H29:J29)/SUM(H$34:J$34)) -> 25721.817 | H29: =H$34*(SUM(I29:K29)/SUM(I$34:K$34)) -> 29414.03 | I29: =Data!$D10 -> 37526 | J29: =Data!$D22 -> 37246 | K29: =Data!$D34 -> 28279 | L29: =Data!$D46 -> 41597 | M29: =Data!$D58 -> 91506 | N29: =N$34*(SUM(I29:M29)/SUM(I$34:M$34)) -> 92920.195 | O29: =O$34*(SUM(L29:N29)/SUM(L$34:N$34)) -> 114531.38 | P29: =P$34*(SUM(M29:O29)/SUM(M$34:O$34)) -> 150105.04 | Q29: =Q$34*(SUM(N29:P29)/SUM(N$34:P$34)) -> 167169.33 | R29: =R$34*(SUM(O29:Q29)/SUM(O$34:Q$34)) -> 167150.62 | S29: =S$34*(SUM(P29:R29)/SUM(P$34:R$34)) -> 176435.94 | T29: =T$34*(SUM(Q29:S29)/SUM(Q$34:S$34)) -> 179538.43 | U29: =U$34*(SUM(R29:T29)/SUM(R$34:T$34)) -> 182629.43 | V29: =V$34*(SUM(S29:U29)/SUM(S$34:U$34)) -> 185725.45 | ... AM29: =AM$34*(SUM(AJ29:AL29)/SUM(AJ$34:AL$34)) -> 193464.48 | AQ29: =AQ24-AQ23 -> 6580.915 | AR29: =AR24-AR23 -> 6485 | AS29: =AS24-AS23 -> 7503 | AT29: =AT24-AT23 -> 9068 | AU29: =AU24-AU23 -> 1381 | AV29: =AV24-AV23 -> -18797 | AW29: =AW24-AW23 -> 2219.1871 | AX29: =AX24-AX23 -> -7700.5903 | ... BF29: =BF24-BF23 -> -11688.561
A30: September | B30: =B$34*(SUM(C30:E30)/SUM(C$34:E$34)) -> 13357.31 | C30: =C$34*(SUM(D30:F30)/SUM(D$34:F$34)) -> 29362.645 | D30: =D$34*(SUM(E30:G30)/SUM(E$34:G$34)) -> 33225.402 | E30: =E$34*(SUM(F30:H30)/SUM(F$34:H$34)) -> 39229.94 | F30: =F$34*(SUM(G30:I30)/SUM(G$34:I$34)) -> 32781.717 | G30: =G$34*(SUM(H30:J30)/SUM(H$34:J$34)) -> 25823.341 | H30: =H$34*(SUM(I30:K30)/SUM(I$34:K$34)) -> 31353.254 | I30: =Data!$D11 -> 35703 | J30: =Data!$D23 -> 37541 | K30: =Data!$D35 -> 36601 | L30: =Data!$D47 -> 38275 | M30: =Data!$D59 -> 105925 | N30: =N$34*(SUM(I30:M30)/SUM(I$34:M$34)) -> 99959.818 | O30: =O$34*(SUM(L30:N30)/SUM(L$34:N$34)) -> 123721.65 | P30: =P$34*(SUM(M30:O30)/SUM(M$34:O$34)) -> 165493.69 | Q30: =Q$34*(SUM(N30:P30)/SUM(N$34:P$34)) -> 181952.02 | R30: =R$34*(SUM(O30:Q30)/SUM(O$34:Q$34)) -> 182387.36 | S30: =S$34*(SUM(P30:R30)/SUM(P$34:R$34)) -> 192974.35 | T30: =T$34*(SUM(Q30:S30)/SUM(Q$34:S$34)) -> 195904.22 | U30: =U$34*(SUM(R30:T30)/SUM(R$34:T$34)) -> 199436.03 | V30: =V$34*(SUM(S30:U30)/SUM(S$34:U$34)) -> 202867.1 | ... AM30: =AM$34*(SUM(AJ30:AL30)/SUM(AJ$34:AL$34)) -> 211266.71 | AP30: Yr-Yr Change | AQ30: =AQ24/#REF!-1 -> #REF! | AR30: =AR24/AQ24-1 -> 0.29434642 | AS30: =AS24/AR24-1 -> -0.059247385 | AT30: =AT24/AS24-1 -> -0.18576766 | AU30: =AU24/AT24-1 -> 0.37370016 | AV30: =AV24/AU24-1 -> 1.4153905 | AW30: =AW24/AV24-1 -> -0.024581448 | AX30: =AX24/AW24-1 -> 0.24129456 | AY30: =AY24/AX24-1 -> 0.32127411 | ... BF30: =BF24/BE24-1 -> 0.016476581
A31: October | B31: =B$34*(SUM(C31:E31)/SUM(C$34:E$34)) -> 13699.053 | C31: =C$34*(SUM(D31:F31)/SUM(D$34:F$34)) -> 30147.82 | D31: =D$34*(SUM(E31:G31)/SUM(E$34:G$34)) -> 33976.613 | E31: =E$34*(SUM(F31:H31)/SUM(F$34:H$34)) -> 40298.537 | F31: =F$34*(SUM(G31:I31)/SUM(G$34:I$34)) -> 33776.011 | G31: =G$34*(SUM(H31:J31)/SUM(H$34:J$34)) -> 25972.457 | H31: =H$34*(SUM(I31:K31)/SUM(I$34:K$34)) -> 32660.246 | I31: =Data!$D12 -> 37064 | J31: =Data!$D24 -> 35477 | K31: =Data!$D36 -> 41883 | L31: =Data!$D48 -> 40733 | M31: =Data!$D60 -> 68160 | N31: =N$34*(SUM(I31:M31)/SUM(I$34:M$34)) -> 87869.183 | O31: =O$34*(SUM(L31:N31)/SUM(L$34:N$34)) -> 99704.126 | P31: =P$34*(SUM(M31:O31)/SUM(M$34:O$34)) -> 128402.36 | Q31: =Q$34*(SUM(N31:P31)/SUM(N$34:P$34)) -> 147728.89 | R31: =R$34*(SUM(O31:Q31)/SUM(O$34:Q$34)) -> 145484.66 | S31: =S$34*(SUM(P31:R31)/SUM(P$34:R$34)) -> 153559.79 | T31: =T$34*(SUM(Q31:S31)/SUM(Q$34:S$34)) -> 157047.6 | U31: =U$34*(SUM(R31:T31)/SUM(R$34:T$34)) -> 159227.4 | V31: =V$34*(SUM(S31:U31)/SUM(S$34:U$34)) -> 162012 | ... AM31: =AM$34*(SUM(AJ31:AL31)/SUM(AJ$34:AL$34)) -> 168810.14 | AQ31: =AQ24-#REF! -> #REF! | AR31: =AR24-AQ24 -> 27236.585 | AS31: =AS24-AR24 -> -7096 | AT31: =AT24-AS24 -> -20931 | AU31: =AU24-AT24 -> 34284 | AV31: =AV24-AU24 -> 178376 | AW31: =AW24-AV24 -> -7482.6421 | AX31: =AX24-AW24 -> 71645.026 | AY31: =AY24-AX24 -> 118410.19 | ... BF31: =BF24-BE24 -> 9883.5889
