Workbook

Sheet Notes
A1: Notes
A2: This sheet explains the data in each tab and provides definitions and acronyms for terms used in this spreadsheet.
A4: Tab "Fuels"
A5: This tab contains total credits, deficits, and volume for each fuel reported under the LCFS program.
A6: Credits and Deficits are calculated using the equation in section 95486(b)(3) of the LCFS regulation.
A7: For Diesel and CARBOB, deficits shown are generated due to production, import and purchase, etc. while any credits shown are generated due to sale of inventory, exports outside CA, etc.
A8: For alternative fuels that displace Diesel and CARBOB, credits are generated by low-CI fuels due to production, imports and purchase, etc. while any deficits generated are either due to a higher carbon intensity (CI) than the CI standard or due to sale of inventories, exports outside of CA, etc.
A9: Volumes represent the "total obligated amount" (TOA) which is the sum of all fuel transactions (reported in LRT-CBTS) with a positive obligation indicator (+) (i.e., production in California, production for import, import, purchased with obligation, gain in inventory) minus the sum of all transactions with a negative obligation indicator (-) (i.e., export, sold with obligation, loss of inventory, not used for transportation)
A10: TOA is converted to gge by multiplying it with the ratio of the energy density of the fuel divided by energy density of CaRFG. Energy densities of LCFS fuels and blendstocks are listed in the table below:
A11: Beginning in Q1 2020, CARBOB/Diesel Incremental Deficits were generated due to the latest 3 year average of crude oil supply having a higher CI average than the baseline standard.
A12: Beginning in Q1 2019, Electricity credit and fuel volume data has been further broken out into subcategories. Previously “Electricity- Onroad” category is broken out into “Electricity - Onroad - LDV/MDV” and “Electricity - Onroad – HDV;” and “Electricity- Offroad” category is broken out into Fixed Guideway Systems, eOGVs, eForklifts, and eCHE/eTRU. “Electricity – Incremental” category has been renamed as “(LDV/MDV – Onroad) Residential EV Charging with Low-CI (Incremental Credits).” Prior to 2019, Electricity was only available for “Electricity - Onroad - LDV/MDV” and “Electricity - Onroad – HDV”.
A14: Fuel (units) | B14: Energy Density and Conversion Factors
A15: CARBOB (gal) | B15: 119.53 (MJ/gal)
A16: CaRFG (gal) | B16: 115.83 (MJ/gal)
A17: Diesel fuel (gal) | B17: 134.47 (MJ/gal)
A18: CNG (scf) | B18: 105.50 (MJ/Therm)
A19: LNG (gal) | B19: 78.83 (MJ/gal)
A20: Electricity (KWh) | B20: 3.60 (MJ/KWh)
A21: Hydrogen (kg) | B21: 120.00 (MJ/kg)
A22: Undenatured Anhydrous Ethanol (gal) | B22: 80.53 (MJ/gal)
A23: Denatured Ethanol (gal) | B23: 81.51 (MJ/gal)
A24: FAME Biodiesel (gal) | B24: 126.13 (MJ/gal)
A25: Renewable Diesel (gal) | B25: 129.65 (MJ/gal)
... A28: Propane (gal) | B28: 89.63 (MJ/gal)
A30: Administratively Adjusted Credits reflect corrections to inaccurately reported data discovered through audits or self reported to CARB (Note: Data shown denotes net credits and deficits adjustments in each quarter) pursuant to LCFS regulation section 95491(h) | N30: LCFS Enforcement Webpage
A31: Innovative crude includes: crude produced and supplied to California refineries using solar steam generation (55 percent quality or greater), solar or wind electricity generation, solar heat generation, or carbon capture and storage (CCS) at the crude oil production facilities pursuant to LCFS regulation section 95489(c)
A32: Low Complexity/Low Energy Use Refinery is offered to a refiner that meets both of the following criteria; a Modified Nelson Complexity Score equal to or less than 5, and total annual energy use equal to or less than 5 million MMBtu pursuant to LCFS regulation section 95489(d).
A33: Refinery Investment Credit is offered to refiners that can demonstrate reduction of greenhouse gas emissions in its facility pursuant to LCFS regulation section 95489€.
A34: Renewable Hydrogen Refinery Credit is offered to a refiner that produces CARBOB or diesel fuel that is partially derived from renewable hydrogen pursuant to LCFS regulation section 95489(f).
A35: ZEV Infrastructure Credits shows total credits generated for Hydrogen Refueling Infrastructure (HRI) pathways and DC Fast Charging Infrastructure (FCI) pathways pursuant to LCFS regulation section 95486.2(a) & (b).
A36: Buffer Account shows number of credits deposited in the buffer account pursuant to the LCFS regulation section 95486 (a)(3).
A37: Cummulative Bank shows the net credit/deficit balance as of the most recent quarter
A38: Estimated Petroleum Fuel Displaced by Alternative Fuels Supported by LCFS represents the total amount of gasoline and diesel (expressed in units of gasoline gallon equivalents or GGE) that was displaced by the alternative fuels reported into LCFS each quarter since the beginning of the program. It is calculated as a sum of the quarterly total obligated amount (TOA) of each alternative fuel multiplied by the energy density of the fuel and by the applicable energy economy ratio (EER) and divided by energy density of CaRFG in order to convert it to GGE.
A40: Tab "Feedstock"
A41: This tab contains total credits, deficits, and volume for each feedstock of ethanol, biodiesel, renewable diesel, natural gas, and electricity.
A42: Credits and deficits are calculated using the equation in section 95486(b)(3) of the LCFS regulation.
A43: Volumes represent the "total obligated amount" (TOA) which is the sum of all fuel transactions (reported in LRT-CBTS) with the plus sign (e.g., production, import, purchased with obligation) minus the sum of all transactions with the minus sign (e.g., export, sold with obligation);
... A53: For archive purposes as the categories have been revised in the Tab "Feedstock" to no longer include CA-GREET2.0 and CA-GREET1.8B feedstock designations.
A55: Definitions and Acronyms: | B55: Please refer to LCFS regulation section 95481 | C55: https://ww2.arb.ca.gov/sites/default/files/2020-07/2020_lcfs_fro_oal-approved_unofficial_06302020.pdf
A61: Quarterly Update Data

Sheet EMTS-CARB Forecast
A2: Bio-CNG
A3: EMTS | B3: 2011 | C3: 2012 | D3: 2013 | E3: 2014 | F3: 2015 | G3: 2016 | H3: 2017 | I3: 2018 | J3: 2019 | K3: 2020 | L3: 2021 | M3: 2022 | N3: 2023 | O3: 2024 | P3: 2025 | Q3: 2026 | R3: 2027 | S3: 2028 | T3: 2029 | U3: 2030 | V3: 2031 | W3: 2032 | X3: 2033 | Y3: 2034 | Z3: 2035 | AA3: 2036 | AB3: 2037 | AC3: 2038 | AD3: 2039 | AE3: 2040 | AF3: 2041 | AG3: 2042 | AH3: 2043 | AI3: 2044 | AJ3: 2045 | AK3: 2046 | AL3: 2047 | AM3: 2048 | AN3: 2049 | AO3: 2050
A4: Q1 | B4: =SUM('[2]D3 Gallon Forecast'!C$105:C$107) -> 0 | C4: =SUM('[2]D3 Gallon Forecast'!D$105:D$107) -> 0 | D4: =SUM('[2]D3 Gallon Forecast'!E$105:E$107) -> 0 | E4: =SUM('[2]D3 Gallon Forecast'!F$105:F$107) -> 0 | F4: =SUM('[2]D3 Gallon Forecast'!G$105:G$107) -> 9276870 | G4: =SUM('[2]D3 Gallon Forecast'!H$105:H$107) -> 18277043 | H4: =SUM('[2]D3 Gallon Forecast'!I$105:I$107) -> 20064702 | I4: =SUM('[2]D3 Gallon Forecast'!J$105:J$107) -> 24321761 | ... AO4: =SUM('[2]D3 Gallon Forecast'!AP$105:AP$107) -> #NUM!
A5: Q2 | B5: =SUM('[2]D3 Gallon Forecast'!C$108:C$110) -> 0 | C5: =SUM('[2]D3 Gallon Forecast'!D$108:D$110) -> 0 | D5: =SUM('[2]D3 Gallon Forecast'!E$108:E$110) -> 0 | E5: =SUM('[2]D3 Gallon Forecast'!F$108:F$110) -> 0 | F5: =SUM('[2]D3 Gallon Forecast'!G$108:G$110) -> 16147638 | G5: =SUM('[2]D3 Gallon Forecast'!H$108:H$110) -> 25802022 | H5: =SUM('[2]D3 Gallon Forecast'!I$108:I$110) -> 36919736 | I5: =SUM('[2]D3 Gallon Forecast'!J$108:J$110) -> 46897800 | ... AO5: =SUM('[2]D3 Gallon Forecast'!AP$108:AP$110) -> #NUM!
A6: Q3 | B6: =SUM('[2]D3 Gallon Forecast'!C$111:C$113) -> 0 | C6: =SUM('[2]D3 Gallon Forecast'!D$111:D$113) -> 0 | D6: =SUM('[2]D3 Gallon Forecast'!E$111:E$113) -> 0 | E6: =SUM('[2]D3 Gallon Forecast'!F$111:F$113) -> 5117631 | F6: =SUM('[2]D3 Gallon Forecast'!G$111:G$113) -> 17974757 | G6: =SUM('[2]D3 Gallon Forecast'!H$111:H$113) -> 29917811 | H6: =SUM('[2]D3 Gallon Forecast'!I$111:I$113) -> 39823316 | I6: =SUM('[2]D3 Gallon Forecast'!J$111:J$113) -> 60850692 | ... AO6: =SUM('[2]D3 Gallon Forecast'!AP$111:AP$113) -> #NUM!
A7: Q4 | B7: =SUM('[2]D3 Gallon Forecast'!C$114:C$116) -> 0 | C7: =SUM('[2]D3 Gallon Forecast'!D$114:D$116) -> 0 | D7: =SUM('[2]D3 Gallon Forecast'!E$114:E$116) -> 0 | E7: =SUM('[2]D3 Gallon Forecast'!F$114:F$116) -> 10090437 | F7: =SUM('[2]D3 Gallon Forecast'!G$114:G$116) -> 27055467 | G7: =SUM('[2]D3 Gallon Forecast'!H$114:H$116) -> 42418389 | H7: =SUM('[2]D3 Gallon Forecast'!I$114:I$116) -> 58677054 | I7: =SUM('[2]D3 Gallon Forecast'!J$114:J$116) -> 81121978 | ... AO7: =SUM('[2]D3 Gallon Forecast'!AP$114:AP$116) -> #NUM!
A8: Total | B8: =SUM(B4:B7) -> 0 | C8: =SUM(C4:C7) -> 0 | D8: =SUM(D4:D7) -> 0 | E8: =SUM(E4:E7) -> 15208068 | F8: =SUM(F4:F7) -> 70454732 | G8: =SUM(G4:G7) -> 116415265 | H8: =SUM(H4:H7) -> 155484808 | I8: =SUM(I4:I7) -> 213192231 | ... AO8: =SUM(AO4:AO7) -> #NUM!
A10: CARB | B10: =B3 -> 2011 | C10: =C3 -> 2012 | D10: =D3 -> 2013 | E10: =E3 -> 2014 | F10: =F3 -> 2015 | G10: =G3 -> 2016 | H10: =H3 -> 2017 | I10: =I3 -> 2018 | ... AO10: =AO3 -> 2050
A11: Q1 | B11: ='Fuel Vol and Credit Gen'!C$5 -> 0 | C11: ='Fuel Vol and Credit Gen'!G$5 -> 0 | D11: ='Fuel Vol and Credit Gen'!K$5 -> 0 | E11: ='Fuel Vol and Credit Gen'!O$5 -> 2726000 | F11: ='Fuel Vol and Credit Gen'!S$5 -> 6720568 | G11: ='Fuel Vol and Credit Gen'!W$5 -> 14450356 | H11: ='Fuel Vol and Credit Gen'!AA$5 -> 16917328 | I11: ='Fuel Vol and Credit Gen'!AE$5 -> 23996868 | J11: ='Fuel Vol and Credit Gen'!AI$5 -> 28550655 | K11: ='Fuel Vol and Credit Gen'!AM$5 -> 32763027 | L11: ='Fuel Vol and Credit Gen'!AQ$5 -> 34313995 | M11: ='Fuel Vol and Credit Gen'!AU$5 -> 41745891 | N11: ='Fuel Vol and Credit Gen'!AY$5 -> 44983298 | O11: ='Fuel Vol and Credit Gen'!BC$5 -> 48258163 | P11: =FORECAST(P4,I11:O11,I4:O4) -> 28116124 | Q11: =FORECAST(Q4,J11:P11,J4:P4) -> 33557179 | R11: =FORECAST(R4,K11:Q11,K4:Q4) -> 33705427 | S11: =FORECAST(S4,L11:R11,L4:R4) -> 33624019 | T11: =FORECAST(T4,M11:S11,M4:S4) -> #NUM! | U11: =FORECAST(U4,N11:T11,N4:T4) -> #NUM! | V11: =FORECAST(V4,O11:U11,O4:U4) -> #NUM! | W11: =FORECAST(W4,P11:V11,P4:V4) -> #NUM! | ... AO11: =FORECAST(AO4,AH11:AN11,AH4:AN4) -> #NUM!
A12: Q2 | B12: ='Fuel Vol and Credit Gen'!D$5 -> 0 | C12: ='Fuel Vol and Credit Gen'!H$5 -> 0 | D12: ='Fuel Vol and Credit Gen'!L$5 -> 7532 | E12: ='Fuel Vol and Credit Gen'!P$5 -> 2881044 | F12: ='Fuel Vol and Credit Gen'!T$5 -> 9981749 | G12: ='Fuel Vol and Credit Gen'!X$5 -> 14575659 | H12: ='Fuel Vol and Credit Gen'!AB$5 -> 21283092 | I12: ='Fuel Vol and Credit Gen'!AF$5 -> 24647401 | J12: ='Fuel Vol and Credit Gen'!AJ$5 -> 31338196 | K12: ='Fuel Vol and Credit Gen'!AN$5 -> 28814425 | L12: ='Fuel Vol and Credit Gen'!AR$5 -> 39658233 | M12: ='Fuel Vol and Credit Gen'!AV$5 -> 43453489 | N12: ='Fuel Vol and Credit Gen'!AZ$5 -> 47131654 | O12: ='Fuel Vol and Credit Gen'!BD$5 -> 50933328 | P12: =FORECAST(P5,I12:O12,I5:O5) -> 36123964 | Q12: =FORECAST(Q5,J12:P12,J5:P5) -> 39436476 | R12: =FORECAST(R5,K12:Q12,K5:Q5) -> 40041474 | S12: =FORECAST(S5,L12:R12,L5:R5) -> 41685783 | T12: =FORECAST(T5,M12:S12,M5:S5) -> #NUM! | U12: =FORECAST(U5,N12:T12,N5:T5) -> #NUM! | V12: =FORECAST(V5,O12:U12,O5:U5) -> #NUM! | W12: =FORECAST(W5,P12:V12,P5:V5) -> #NUM! | ... AO12: =FORECAST(AO5,AH12:AN12,AH5:AN5) -> #NUM!
A13: Q3 | B13: ='Fuel Vol and Credit Gen'!E$5 -> 0 | C13: ='Fuel Vol and Credit Gen'!I$5 -> 0 | D13: ='Fuel Vol and Credit Gen'!M$5 -> 2583509 | E13: ='Fuel Vol and Credit Gen'!Q$5 -> 4617725 | F13: ='Fuel Vol and Credit Gen'!U$5 -> 11049178 | G13: ='Fuel Vol and Credit Gen'!Y$5 -> 15378044 | H13: ='Fuel Vol and Credit Gen'!AC$5 -> 24185491 | I13: ='Fuel Vol and Credit Gen'!AG$5 -> 27435046 | J13: ='Fuel Vol and Credit Gen'!AK$5 -> 32016663 | K13: ='Fuel Vol and Credit Gen'!AO$5 -> 35738973 | L13: ='Fuel Vol and Credit Gen'!AS$5 -> 42853248 | M13: ='Fuel Vol and Credit Gen'!AW$5 -> 45784675 | N13: ='Fuel Vol and Credit Gen'!BA$5 -> 48708311 | O13: =FORECAST(O6,H13:N13,H6:N6) -> 63075176 | P13: =FORECAST(P6,I13:O13,I6:O6) -> 39533562 | Q13: =FORECAST(Q6,J13:P13,J6:P6) -> 47912764 | R13: =FORECAST(R6,K13:Q13,K6:Q6) -> 49755756 | S13: =FORECAST(S6,L13:R13,L6:R6) -> 51745467 | T13: =FORECAST(T6,M13:S13,M6:S6) -> #NUM! | U13: =FORECAST(U6,N13:T13,N6:T6) -> #NUM! | V13: =FORECAST(V6,O13:U13,O6:U6) -> #NUM! | ... AO13: =FORECAST(AO6,AH13:AN13,AH6:AN6) -> #NUM!
A14: Q4 | B14: ='Fuel Vol and Credit Gen'!F$5 -> 0 | C14: ='Fuel Vol and Credit Gen'!J$5 -> 0 | D14: ='Fuel Vol and Credit Gen'!N$5 -> 2995901 | E14: ='Fuel Vol and Credit Gen'!R$5 -> 5258002 | F14: ='Fuel Vol and Credit Gen'!V$5 -> 11447850 | G14: ='Fuel Vol and Credit Gen'!Z$5 -> 15905540 | H14: ='Fuel Vol and Credit Gen'!AD$5 -> 24066273 | I14: ='Fuel Vol and Credit Gen'!AH$5 -> 29113530 | J14: ='Fuel Vol and Credit Gen'!AL$5 -> 30980609 | K14: ='Fuel Vol and Credit Gen'!AP$5 -> 36289300 | L14: ='Fuel Vol and Credit Gen'!AT$5 -> 41459320 | M14: ='Fuel Vol and Credit Gen'!AX$5 -> 44727479 | N14: ='Fuel Vol and Credit Gen'!BB$5 -> 48171958 | O14: =FORECAST(O7,H14:N14,H7:N7) -> 48364678 | P14: =FORECAST(P7,I14:O14,I7:O7) -> 41431115 | Q14: =FORECAST(Q7,J14:P14,J7:P7) -> 45943284 | R14: =FORECAST(R7,K14:Q14,K7:Q7) -> 46836940 | S14: =FORECAST(S7,L14:R14,L7:R7) -> 47834469 | T14: =FORECAST(T7,M14:S14,M7:S7) -> #NUM! | U14: =FORECAST(U7,N14:T14,N7:T7) -> #NUM! | V14: =FORECAST(V7,O14:U14,O7:U7) -> #NUM! | ... AO14: =FORECAST(AO7,AH14:AN14,AH7:AN7) -> #NUM!
A15: Total | B15: =SUM(B11:B14) -> 0 | C15: =SUM(C11:C14) -> 0 | D15: =SUM(D11:D14) -> 5586942 | E15: =SUM(E11:E14) -> 15482771 | F15: =SUM(F11:F14) -> 39199345 | G15: =SUM(G11:G14) -> 60309599 | H15: =SUM(H11:H14) -> 86452184 | I15: =SUM(I11:I14) -> 105192845 | ... AO15: =SUM(AO11:AO14) -> #NUM!
A17: Bio-LNG
A18: EMTS | B18: =B3 -> 2011 | C18: =C3 -> 2012 | D18: =D3 -> 2013 | E18: =E3 -> 2014 | F18: =F3 -> 2015 | G18: =G3 -> 2016 | H18: =H3 -> 2017 | I18: =I3 -> 2018 | ... AO18: =AO3 -> 2050
A19: Q1 | B19: =SUM('[2]D3 Gallon Forecast'!C$153:C$155) -> 0 | C19: =SUM('[2]D3 Gallon Forecast'!D$153:D$155) -> 0 | D19: =SUM('[2]D3 Gallon Forecast'!E$153:E$155) -> 0 | E19: =SUM('[2]D3 Gallon Forecast'!F$153:F$155) -> 0 | F19: =SUM('[2]D3 Gallon Forecast'!G$153:G$155) -> 10299108 | G19: =SUM('[2]D3 Gallon Forecast'!H$153:H$155) -> 9614472 | H19: =SUM('[2]D3 Gallon Forecast'!I$153:I$155) -> 8273562 | I19: =SUM('[2]D3 Gallon Forecast'!J$153:J$155) -> 8168260 | ... AO19: =SUM('[2]D3 Gallon Forecast'!AP$153:AP$155) -> #NUM!
A20: Q2 | B20: =SUM('[2]D3 Gallon Forecast'!C$156:C$158) -> 0 | C20: =SUM('[2]D3 Gallon Forecast'!D$156:D$158) -> 0 | D20: =SUM('[2]D3 Gallon Forecast'!E$156:E$158) -> 0 | E20: =SUM('[2]D3 Gallon Forecast'!F$156:F$158) -> 0 | F20: =SUM('[2]D3 Gallon Forecast'!G$156:G$158) -> 9508588 | G20: =SUM('[2]D3 Gallon Forecast'!H$156:H$158) -> 14794458 | H20: =SUM('[2]D3 Gallon Forecast'!I$156:I$158) -> 15683104 | I20: =SUM('[2]D3 Gallon Forecast'!J$156:J$158) -> 10173098 | ... AO20: =SUM('[2]D3 Gallon Forecast'!AP$156:AP$158) -> #NUM!
A21: Q3 | B21: =SUM('[2]D3 Gallon Forecast'!C$159:C$161) -> 0 | C21: =SUM('[2]D3 Gallon Forecast'!D$159:D$161) -> 0 | D21: =SUM('[2]D3 Gallon Forecast'!E$159:E$161) -> 0 | E21: =SUM('[2]D3 Gallon Forecast'!F$159:F$161) -> 5927176 | F21: =SUM('[2]D3 Gallon Forecast'!G$159:G$161) -> 9647053 | G21: =SUM('[2]D3 Gallon Forecast'!H$159:H$161) -> 12331458 | H21: =SUM('[2]D3 Gallon Forecast'!I$159:I$161) -> 12469503 | I21: =SUM('[2]D3 Gallon Forecast'!J$159:J$161) -> 14922765 | ... AO21: =SUM('[2]D3 Gallon Forecast'!AP$159:AP$161) -> #NUM!
A22: Q4 | B22: =SUM('[2]D3 Gallon Forecast'!C$162:C$164) -> 0 | C22: =SUM('[2]D3 Gallon Forecast'!D$162:D$164) -> 0 | D22: =SUM('[2]D3 Gallon Forecast'!E$162:E$164) -> 0 | E22: =SUM('[2]D3 Gallon Forecast'!F$162:F$164) -> 11452639 | F22: =SUM('[2]D3 Gallon Forecast'!G$162:G$164) -> 15118720 | G22: =SUM('[2]D3 Gallon Forecast'!H$162:H$164) -> 14484260 | H22: =SUM('[2]D3 Gallon Forecast'!I$162:I$164) -> 16297711 | I22: =SUM('[2]D3 Gallon Forecast'!J$162:J$164) -> 21910168 | ... AO22: =SUM('[2]D3 Gallon Forecast'!AP$162:AP$164) -> #NUM!
A23: Total | B23: =SUM(B19:B22) -> 0 | C23: =SUM(C19:C22) -> 0 | D23: =SUM(D19:D22) -> 0 | E23: =SUM(E19:E22) -> 17379815 | F23: =SUM(F19:F22) -> 44573469 | G23: =SUM(G19:G22) -> 51224648 | H23: =SUM(H19:H22) -> 52723880 | I23: =SUM(I19:I22) -> 55174291 | ... AO23: =SUM(AO19:AO22) -> #NUM!
A25: CARB | B25: =B3 -> 2011 | C25: =C3 -> 2012 | D25: =D3 -> 2013 | E25: =E3 -> 2014 | F25: =F3 -> 2015 | G25: =G3 -> 2016 | H25: =H3 -> 2017 | I25: =I3 -> 2018 | ... AO25: =AO3 -> 2050
A26: Q1 | B26: ='Fuel Vol and Credit Gen'!C$6 -> 236835 | C26: ='Fuel Vol and Credit Gen'!G$6 -> 468876 | D26: ='Fuel Vol and Credit Gen'!K$6 -> 439275 | E26: ='Fuel Vol and Credit Gen'!O$6 -> 1639132 | F26: ='Fuel Vol and Credit Gen'!S$6 -> 5277303 | G26: ='Fuel Vol and Credit Gen'!W$6 -> 6595776 | H26: ='Fuel Vol and Credit Gen'!AA$6 -> 6712351 | I26: ='Fuel Vol and Credit Gen'!AE$6 -> 3637857 | J26: ='Fuel Vol and Credit Gen'!AI$6 -> 3621779 | K26: ='Fuel Vol and Credit Gen'!AM$6 -> 4573936 | L26: ='Fuel Vol and Credit Gen'!AQ$6 -> 4123135 | M26: ='Fuel Vol and Credit Gen'!AU$6 -> 3668607 | N26: ='Fuel Vol and Credit Gen'!AY$6 -> 3488791 | O26: ='Fuel Vol and Credit Gen'!BC$6 -> 3416751 | P26: =FORECAST(P19,I26:O26,I19:O19) -> 3121094.1 | Q26: =FORECAST(Q19,J26:P26,J19:P19) -> 3039684.5 | R26: =FORECAST(R19,K26:Q26,K19:Q19) -> 3051915.6 | S26: =FORECAST(S19,L26:R26,L19:R19) -> 3173426.1 | T26: =FORECAST(T19,M26:S26,M19:S19) -> #NUM! | U26: =FORECAST(U19,N26:T26,N19:T19) -> #NUM! | V26: =FORECAST(V19,O26:U26,O19:U19) -> #NUM! | W26: =FORECAST(W19,P26:V26,P19:V19) -> #NUM! | ... AO26: =FORECAST(AO19,AH26:AN26,AH19:AN19) -> #NUM!
A27: Q2 | B27: ='Fuel Vol and Credit Gen'!D$6 -> 328532 | C27: ='Fuel Vol and Credit Gen'!H$6 -> 453202 | D27: ='Fuel Vol and Credit Gen'!L$6 -> 612128 | E27: ='Fuel Vol and Credit Gen'!P$6 -> 1064074 | F27: ='Fuel Vol and Credit Gen'!T$6 -> 6367592 | G27: ='Fuel Vol and Credit Gen'!X$6 -> 7661496 | H27: ='Fuel Vol and Credit Gen'!AB$6 -> 6146649 | I27: ='Fuel Vol and Credit Gen'!AF$6 -> 3678466 | J27: ='Fuel Vol and Credit Gen'!AJ$6 -> 3620430 | K27: ='Fuel Vol and Credit Gen'!AN$6 -> 4396610 | L27: ='Fuel Vol and Credit Gen'!AR$6 -> 4146664 | M27: ='Fuel Vol and Credit Gen'!AV$6 -> 3893434 | N27: ='Fuel Vol and Credit Gen'!AZ$6 -> 3664461 | O27: ='Fuel Vol and Credit Gen'!BD$6 -> 3233384 | P27: =FORECAST(P20,I27:O27,I20:O20) -> 3467909.1 | Q27: =FORECAST(Q20,J27:P27,J20:P20) -> 2988210.3 | R27: =FORECAST(R20,K27:Q27,K20:Q20) -> 2979320.2 | S27: =FORECAST(S20,L27:R27,L20:R20) -> 3265296.7 | T27: =FORECAST(T20,M27:S27,M20:S20) -> #NUM! | U27: =FORECAST(U20,N27:T27,N20:T20) -> #NUM! | V27: =FORECAST(V20,O27:U27,O20:U20) -> #NUM! | W27: =FORECAST(W20,P27:V27,P20:V20) -> #NUM! | ... AO27: =FORECAST(AO20,AH27:AN27,AH20:AN20) -> #NUM!
A28: Q3 | B28: ='Fuel Vol and Credit Gen'!E$6 -> 530962 | C28: ='Fuel Vol and Credit Gen'!I$6 -> 384063 | D28: ='Fuel Vol and Credit Gen'!M$6 -> 2546125 | E28: ='Fuel Vol and Credit Gen'!Q$6 -> 4714630 | F28: ='Fuel Vol and Credit Gen'!U$6 -> 7259890 | G28: ='Fuel Vol and Credit Gen'!Y$6 -> 7645395 | H28: ='Fuel Vol and Credit Gen'!AC$6 -> 3943161 | I28: ='Fuel Vol and Credit Gen'!AG$6 -> 3844316 | J28: ='Fuel Vol and Credit Gen'!AK$6 -> 4599876 | K28: ='Fuel Vol and Credit Gen'!AO$6 -> 4566252 | L28: ='Fuel Vol and Credit Gen'!AS$6 -> 4033042 | M28: ='Fuel Vol and Credit Gen'!AW$6 -> 3960769 | N28: ='Fuel Vol and Credit Gen'!BA$6 -> 3463640 | O28: =FORECAST(O21,H28:N28,H21:N21) -> 3859488.1 | P28: =FORECAST(P21,I28:O28,I21:O21) -> 3914148.2 | Q28: =FORECAST(Q21,J28:P28,J21:P21) -> 3730083.6 | R28: =FORECAST(R21,K28:Q28,K21:Q21) -> 3634355.2 | S28: =FORECAST(S21,L28:R28,L21:R21) -> 3763851.4 | T28: =FORECAST(T21,M28:S28,M21:S21) -> #NUM! | U28: =FORECAST(U21,N28:T28,N21:T21) -> #NUM! | V28: =FORECAST(V21,O28:U28,O21:U21) -> #NUM! | ... AO28: =FORECAST(AO21,AH28:AN28,AH21:AN21) -> #NUM!
A29: Q4 | B29: ='Fuel Vol and Credit Gen'!F$6 -> 478928 | C29: ='Fuel Vol and Credit Gen'!J$6 -> 287824 | D29: ='Fuel Vol and Credit Gen'!N$6 -> 1052125 | E29: ='Fuel Vol and Credit Gen'!R$6 -> 5841140 | F29: ='Fuel Vol and Credit Gen'!V$6 -> 8307511 | G29: ='Fuel Vol and Credit Gen'!Z$6 -> 7035914 | H29: ='Fuel Vol and Credit Gen'!AD$6 -> 3529130 | I29: ='Fuel Vol and Credit Gen'!AH$6 -> 3532362 | J29: ='Fuel Vol and Credit Gen'!AL$6 -> 4554189 | K29: ='Fuel Vol and Credit Gen'!AP$6 -> 4446816 | L29: ='Fuel Vol and Credit Gen'!AT$6 -> 3968462 | M29: ='Fuel Vol and Credit Gen'!AX$6 -> 3224680 | N29: ='Fuel Vol and Credit Gen'!BB$6 -> 3490514 | O29: =FORECAST(O22,H29:N29,H22:N22) -> 3667027.9 | P29: =FORECAST(P22,I29:O29,I22:O22) -> 3777522.8 | Q29: =FORECAST(Q22,J29:P29,J22:P22) -> 3602067.8 | R29: =FORECAST(R22,K29:Q29,K22:Q22) -> 3506067.7 | S29: =FORECAST(S22,L29:R29,L22:R22) -> 3594417.9 | T29: =FORECAST(T22,M29:S29,M22:S22) -> #NUM! | U29: =FORECAST(U22,N29:T29,N22:T22) -> #NUM! | V29: =FORECAST(V22,O29:U29,O22:U22) -> #NUM! | ... AO29: =FORECAST(AO22,AH29:AN29,AH22:AN22) -> #NUM!
A30: Total | B30: =SUM(B26:B29) -> 1575257 | C30: =SUM(C26:C29) -> 1593965 | D30: =SUM(D26:D29) -> 4649653 | E30: =SUM(E26:E29) -> 13258976 | F30: =SUM(F26:F29) -> 27212296 | G30: =SUM(G26:G29) -> 28938581 | H30: =SUM(H26:H29) -> 20331291 | I30: =SUM(I26:I29) -> 14693001 | ... AO30: =SUM(AO26:AO29) -> #NUM!
A32: Ethanol
A33: EMTS | B33: =B3 -> 2011 | C33: =C3 -> 2012 | D33: =D3 -> 2013 | E33: =E3 -> 2014 | F33: =F3 -> 2015 | G33: =G3 -> 2016 | H33: =H3 -> 2017 | I33: =I3 -> 2018 | ... AO33: =AO3 -> 2050
A34: Q1 | B34: =SUM('[2]D6 Gallon Forecast'!C$106:C$108) -> 3423730827 | C34: =SUM('[2]D6 Gallon Forecast'!D$106:D$108) -> 3139093639 | D34: =SUM('[2]D6 Gallon Forecast'!E$106:E$108) -> 3476087103 | E34: =SUM('[2]D6 Gallon Forecast'!F$106:F$108) -> 3560910822 | F34: =SUM('[2]D6 Gallon Forecast'!G$106:G$108) -> 3710178925 | G34: =SUM('[2]D6 Gallon Forecast'!H$106:H$108) -> 3714618777 | H34: =SUM('[2]D6 Gallon Forecast'!I$106:I$108) -> 3809147158 | I34: =SUM('[2]D6 Gallon Forecast'!J$106:J$108) -> 3736010400 | ... AO34: =SUM('[2]D6 Gallon Forecast'!AP$106:AP$108) -> 4.5464763e+09
A35: Q2 | B35: =SUM('[2]D6 Gallon Forecast'!C$109:C$111) -> 13609057120 | C35: =SUM('[2]D6 Gallon Forecast'!D$109:D$111) -> 1.2986723e+10 | D35: =SUM('[2]D6 Gallon Forecast'!E$109:E$111) -> 1.3098971e+10 | E35: =SUM('[2]D6 Gallon Forecast'!F$109:F$111) -> 1.4021921e+10 | F35: =SUM('[2]D6 Gallon Forecast'!G$109:G$111) -> 1.4393319e+10 | G35: =SUM('[2]D6 Gallon Forecast'!H$109:H$111) -> 1.4724613e+10 | H35: =SUM('[2]D6 Gallon Forecast'!I$109:I$111) -> 1.486422e+10 | I35: =SUM('[2]D6 Gallon Forecast'!J$109:J$111) -> 1.4967243e+10 | ... AO35: =SUM('[2]D6 Gallon Forecast'!AP$109:AP$111) -> 1.777271e+10
A36: Q3 | B36: =SUM('[2]D6 Gallon Forecast'!C$112:C$114) -> 2214375968 | C36: =SUM('[2]D6 Gallon Forecast'!D$112:D$114) -> 2257984896 | D36: =SUM('[2]D6 Gallon Forecast'!E$112:E$114) -> 1967676776 | E36: =SUM('[2]D6 Gallon Forecast'!F$112:F$114) -> 2170741905 | F36: =SUM('[2]D6 Gallon Forecast'!G$112:G$114) -> 2270207336 | G36: =SUM('[2]D6 Gallon Forecast'!H$112:H$114) -> 2378095946 | H36: =SUM('[2]D6 Gallon Forecast'!I$112:I$114) -> 2368741243 | I36: =SUM('[2]D6 Gallon Forecast'!J$112:J$114) -> 2354227525 | ... AO36: =SUM('[2]D6 Gallon Forecast'!AP$112:AP$114) -> 2.8283204e+09
A37: Q4 | B37: =SUM('[2]D6 Gallon Forecast'!C$115:C$117) -> 3435283055 | C37: =SUM('[2]D6 Gallon Forecast'!D$115:D$117) -> 3364985786 | D37: =SUM('[2]D6 Gallon Forecast'!E$115:E$117) -> 3260761189 | E37: =SUM('[2]D6 Gallon Forecast'!F$115:F$117) -> 3522503268 | F37: =SUM('[2]D6 Gallon Forecast'!G$115:G$117) -> 3556734847 | G37: =SUM('[2]D6 Gallon Forecast'!H$115:H$117) -> 3612391732 | H37: =SUM('[2]D6 Gallon Forecast'!I$115:I$117) -> 3678597704 | I37: =SUM('[2]D6 Gallon Forecast'!J$115:J$117) -> 3726526946 | ... AO37: =SUM('[2]D6 Gallon Forecast'!AP$115:AP$117) -> 4.3338009e+09
A38: Total | B38: =SUM(B34:B37) -> 22682446970 | C38: =SUM(C34:C37) -> 2.1748787e+10 | D38: =SUM(D34:D37) -> 2.1803496e+10 | E38: =SUM(E34:E37) -> 2.3276077e+10 | F38: =SUM(F34:F37) -> 2.393044e+10 | G38: =SUM(G34:G37) -> 2.442972e+10 | H38: =SUM(H34:H37) -> 2.4720706e+10 | I38: =SUM(I34:I37) -> 2.4784008e+10 | ... AO38: =SUM(AO34:AO37) -> 2.9481307e+10
A39: =N42/N35 -> 0.020198025
A40: CARB | B40: =B3 -> 2011 | C40: =C3 -> 2012 | D40: =D3 -> 2013 | E40: =E3 -> 2014 | F40: =F3 -> 2015 | G40: =G3 -> 2016 | H40: =H3 -> 2017 | I40: =I3 -> 2018 | ... AO40: =AO3 -> 2050
A41: Q1 | B41: ='Fuel Vol and Credit Gen'!C$11 -> 355943296 | C41: ='Fuel Vol and Credit Gen'!G$11 -> 370292343 | D41: ='Fuel Vol and Credit Gen'!K$11 -> 368807852 | E41: ='Fuel Vol and Credit Gen'!O$11 -> 350786119 | F41: ='Fuel Vol and Credit Gen'!S$11 -> 372469285 | G41: ='Fuel Vol and Credit Gen'!W$11 -> 414527490 | H41: ='Fuel Vol and Credit Gen'!AA$11 -> 376822538 | I41: ='Fuel Vol and Credit Gen'!AE$11 -> 380940912 | J41: ='Fuel Vol and Credit Gen'!AI$11 -> 355104114 | K41: ='Fuel Vol and Credit Gen'!AM$11 -> 375148591 | L41: ='Fuel Vol and Credit Gen'!AQ$11 -> 285646782 | M41: ='Fuel Vol and Credit Gen'!AU$11 -> 350873873 | N41: ='Fuel Vol and Credit Gen'!AY$11 -> 347939242 | O41: ='Fuel Vol and Credit Gen'!BC$11 -> 344225384 | P41: =FORECAST(P34,I41:O41,I34:O34)-25000000 -> 3.1801297e+08 | Q41: =FORECAST(Q34,J41:P41,J34:P34)-12500000 -> 3.1734357e+08 | R41: =FORECAST(R34,K41:Q41,K34:Q34)-12500000 -> 3.1292269e+08 | S41: =FORECAST(S34,L41:R41,L34:R34)-12500000 -> 3.0963975e+08 | T41: =FORECAST(T34,M41:S41,M34:S34)-12500000 -> 3.0009783e+08 | U41: =FORECAST(U34,N41:T41,N34:T34)-5000000 -> 2.896558e+08 | V41: =FORECAST(V34,O41:U41,O34:U34)-5000000 -> 2.7153037e+08 | W41: =FORECAST(W34,P41:V41,P34:V34) -> 2.6775517e+08 | X41: =FORECAST(X34,Q41:W41,Q34:W34) -> 2.5692098e+08 | Y41: =FORECAST(Y34,R41:X41,R34:X34) -> 2.4737726e+08 | Z41: =FORECAST(Z34,S41:Y41,S34:Y34) -> 2.3469626e+08 | AA41: =FORECAST(AA34,T41:Z41,T34:Z34) -> 2.2421204e+08 | AB41: =FORECAST(AB34,U41:AA41,U34:AA34) -> 2.1405894e+08 | AC41: =FORECAST(AC34,V41:AB41,V34:AB34) -> 2.0407167e+08 | AD41: =FORECAST(AD34,W41:AC41,W34:AC34) -> 1.9237729e+08 | ... AO41: =FORECAST(AO34,AH41:AN41,AH34:AN34) -> 66869665
A42: Q2 | B42: ='Fuel Vol and Credit Gen'!D$11 -> 387851229 | C42: ='Fuel Vol and Credit Gen'!H$11 -> 374917388 | D42: ='Fuel Vol and Credit Gen'!L$11 -> 358046201 | E42: ='Fuel Vol and Credit Gen'!P$11 -> 364681336 | F42: ='Fuel Vol and Credit Gen'!T$11 -> 390499794 | G42: ='Fuel Vol and Credit Gen'!X$11 -> 397227736 | H42: ='Fuel Vol and Credit Gen'!AB$11 -> 401825385 | I42: ='Fuel Vol and Credit Gen'!AF$11 -> 386000352 | J42: ='Fuel Vol and Credit Gen'!AJ$11 -> 416323940 | K42: ='Fuel Vol and Credit Gen'!AN$11 -> 228754963 | L42: ='Fuel Vol and Credit Gen'!AR$11 -> 402071258 | M42: ='Fuel Vol and Credit Gen'!AV$11 -> 366259568 | N42: ='Fuel Vol and Credit Gen'!AZ$11 -> 296481588 | O42: ='Fuel Vol and Credit Gen'!BD$11 -> 365945518 | P42: =FORECAST(P35,I42:O42,I35:O35)-25000000 -> 3.4095609e+08 | Q42: =FORECAST(Q35,J42:P42,J35:P35)-12500000 -> 3.5473746e+08 | R42: =FORECAST(R35,K42:Q42,K35:Q35)-12500000 -> 3.4539447e+08 | S42: =FORECAST(S35,L42:R42,L35:R35)-12500000 -> 3.1951615e+08 | T42: =FORECAST(T35,M42:S42,M35:S35)-12500000 -> 3.1765528e+08 | U42: =FORECAST(U35,N42:T42,N35:T35)-5000000 -> 3.2409095e+08 | V42: =FORECAST(V35,O42:U42,O35:U35)-5000000 -> 3.102829e+08 | W42: =FORECAST(W35,P42:V42,P35:V35) -> 3.0105523e+08 | X42: =FORECAST(X35,Q42:W42,Q35:W35) -> 2.90816e+08 | Y42: =FORECAST(Y35,R42:X42,R35:X35) -> 2.8525636e+08 | Z42: =FORECAST(Z35,S42:Y42,S35:Y35) -> 2.8061531e+08 | AA42: =FORECAST(AA35,T42:Z42,T35:Z35) -> 2.7104597e+08 | AB42: =FORECAST(AB35,U42:AA42,U35:AA35) -> 2.6112684e+08 | AC42: =FORECAST(AC35,V42:AB42,V35:AB35) -> 2.5407438e+08 | AD42: =FORECAST(AD35,W42:AC42,W35:AC35) -> 2.4671492e+08 | ... AO42: =FORECAST(AO35,AH42:AN42,AH35:AN35) -> 1.5373919e+08
A43: Q3 | B43: ='Fuel Vol and Credit Gen'!E$11 -> 388872431 | C43: ='Fuel Vol and Credit Gen'!I$11 -> 366019124 | D43: ='Fuel Vol and Credit Gen'!M$11 -> 389863889 | E43: ='Fuel Vol and Credit Gen'!Q$11 -> 392531450 | F43: ='Fuel Vol and Credit Gen'!U$11 -> 383972772 | G43: ='Fuel Vol and Credit Gen'!Y$11 -> 404071329 | H43: ='Fuel Vol and Credit Gen'!AC$11 -> 418522596 | I43: ='Fuel Vol and Credit Gen'!AG$11 -> 433159405 | J43: ='Fuel Vol and Credit Gen'!AK$11 -> 392894297 | K43: ='Fuel Vol and Credit Gen'!AO$11 -> 365721128 | L43: ='Fuel Vol and Credit Gen'!AS$11 -> 379076451 | M43: ='Fuel Vol and Credit Gen'!AW$11 -> 383805193 | N43: ='Fuel Vol and Credit Gen'!BA$11 -> 382422796 | O43: =FORECAST(O36,H43:N43,H36:N36)-25000000 -> 3.7521711e+08 | P43: =FORECAST(P36,I43:O43,I36:O36)-25000000 -> 3.6376218e+08 | Q43: =FORECAST(Q36,J43:P43,J36:P36)-12500000 -> 3.6512709e+08 | R43: =FORECAST(R36,K43:Q43,K36:Q36)-12500000 -> 3.5993301e+08 | S43: =FORECAST(S36,L43:R43,L36:R36)-12500000 -> 3.5827389e+08 | T43: =FORECAST(T36,M43:S43,M36:S36)-12500000 -> 3.5353706e+08 | U43: =FORECAST(U36,N43:T43,N36:T36)-5000000 -> 3.58618e+08 | V43: =FORECAST(V36,O43:U43,O36:U36)-5000000 -> 3.5747898e+08 | W43: =FORECAST(W36,P43:V43,P36:V36) -> 3.5447378e+08 | X43: =FORECAST(X36,Q43:W43,Q36:W36) -> 3.5276594e+08 | Y43: =FORECAST(Y36,R43:X43,R36:X36) -> 3.5238712e+08 | Z43: =FORECAST(Z36,S43:Y43,S36:Y36) -> 3.5158912e+08 | AA43: =FORECAST(AA36,T43:Z43,T36:Z36) -> 3.5068781e+08 | AB43: =FORECAST(AB36,U43:AA43,U36:AA36) -> 3.4856546e+08 | AC43: =FORECAST(AC36,V43:AB43,V36:AB36) -> 3.47441e+08 | AD43: =FORECAST(AD36,W43:AC43,W36:AC36) -> 3.4657787e+08 | ... AO43: =FORECAST(AO36,AH43:AN43,AH36:AN36) -> 3.3233952e+08
A44: Q4 | B44: ='Fuel Vol and Credit Gen'!F$11 -> 357487052 | C44: ='Fuel Vol and Credit Gen'!J$11 -> 363269339 | D44: ='Fuel Vol and Credit Gen'!N$11 -> 362161026 | E44: ='Fuel Vol and Credit Gen'!R$11 -> 376855202 | F44: ='Fuel Vol and Credit Gen'!V$11 -> 352283939 | G44: ='Fuel Vol and Credit Gen'!Z$11 -> 381748251 | H44: ='Fuel Vol and Credit Gen'!AD$11 -> 377787880 | I44: ='Fuel Vol and Credit Gen'!AH$11 -> 400757236 | J44: ='Fuel Vol and Credit Gen'!AL$11 -> 393077295 | K44: ='Fuel Vol and Credit Gen'!AP$11 -> 329435151 | L44: ='Fuel Vol and Credit Gen'!AT$11 -> 354054243 | M44: ='Fuel Vol and Credit Gen'!AX$11 -> 355730406 | N44: ='Fuel Vol and Credit Gen'!BB$11 -> 354633081 | O44: =FORECAST(O37,H44:N44,H37:N37)-25000000 -> 3.4810719e+08 | P44: =FORECAST(P37,I44:O44,I37:O37)-25000000 -> 3.3712382e+08 | Q44: =FORECAST(Q37,J44:P44,J37:P37)-12500000 -> 3.4579361e+08 | R44: =FORECAST(R37,K44:Q44,K37:Q37)-12500000 -> 3.372922e+08 | S44: =FORECAST(S37,L44:R44,L37:R37)-12500000 -> 3.3731115e+08 | T44: =FORECAST(T37,M44:S44,M37:S37)-12500000 -> 3.3588965e+08 | U44: =FORECAST(U37,N44:T44,N37:T37)-5000000 -> 3.3909289e+08 | V44: =FORECAST(V37,O44:U44,O37:U37)-5000000 -> 3.3698341e+08 | W44: =FORECAST(W37,P44:V44,P37:V37) -> 3.3826064e+08 | X44: =FORECAST(X37,Q44:W44,Q37:W37) -> 3.3663782e+08 | Y44: =FORECAST(Y37,R44:X44,R37:X37) -> 3.3740727e+08 | Z44: =FORECAST(Z37,S44:Y44,S37:Y37) -> 3.3741335e+08 | AA44: =FORECAST(AA37,T44:Z44,T37:Z37) -> 3.3741536e+08 | AB44: =FORECAST(AB37,U44:AA44,U37:AA37) -> 3.368107e+08 | AC44: =FORECAST(AC37,V44:AB44,V37:AB37) -> 3.3705115e+08 | AD44: =FORECAST(AD37,W44:AC44,W37:AC37) -> 3.3682189e+08 | ... AO44: =FORECAST(AO37,AH44:AN44,AH37:AN37) -> 3.3590318e+08
A45: Total | B45: =SUM(B41:B44) -> 1490154008 | C45: =SUM(C41:C44) -> 1474498194 | D45: =SUM(D41:D44) -> 1478878968 | E45: =SUM(E41:E44) -> 1484854107 | F45: =SUM(F41:F44) -> 1499225790 | G45: =SUM(G41:G44) -> 1597574806 | H45: =SUM(H41:H44) -> 1574958399 | I45: =SUM(I41:I44) -> 1600857905 | ... AO45: =SUM(AO41:AO44) -> 8.8885156e+08
B46: =B45/B38 -> 0.065696351 | C46: =C45/C38 -> 0.0677968 | D46: =D45/D38 -> 0.067827607 | E46: =E45/E38 -> 0.063793142 | F46: =F45/F38 -> 0.06264932 | G46: =G45/G38 -> 0.065394725 | H46: =H45/H38 -> 0.063710089 | I46: =I45/I38 -> 0.064592373 | ... AO46: =AO45/AO38 -> 0.030149666
A47: Biodiesel
A48: EMTS | B48: =B3 -> 2011 | C48: =C3 -> 2012 | D48: =D3 -> 2013 | E48: =E3 -> 2014 | F48: =F3 -> 2015 | G48: =G3 -> 2016 | H48: =H3 -> 2017 | I48: =I3 -> 2018 | ... AO48: =AO3 -> 2050
A49: Q1 | B49: =SUM('[2]D4 Gallon Forecast'!C$69:C$71) -> 137756014 | C49: =SUM('[2]D4 Gallon Forecast'!D$69:D$71) -> 227779932 | D49: =SUM('[2]D4 Gallon Forecast'!E$69:E$71) -> 246699633 | E49: =SUM('[2]D4 Gallon Forecast'!F$69:F$71) -> 217366175 | F49: =SUM('[2]D4 Gallon Forecast'!G$69:G$71) -> 211086333 | G49: =SUM('[2]D4 Gallon Forecast'!H$69:H$71) -> 312534835 | H49: =SUM('[2]D4 Gallon Forecast'!I$69:I$71) -> 255907141 | I49: =SUM('[2]D4 Gallon Forecast'!J$69:J$71) -> 371227062 | ... AO49: =SUM('[2]D4 Gallon Forecast'!AP$69:AP$71) -> 86532435
A50: Q2 | B50: =SUM('[2]D4 Gallon Forecast'!C$72:C$74) -> 225644132 | C50: =SUM('[2]D4 Gallon Forecast'!D$72:D$74) -> 306750001 | D50: =SUM('[2]D4 Gallon Forecast'!E$72:E$74) -> 347357820 | E50: =SUM('[2]D4 Gallon Forecast'!F$72:F$74) -> 326456435 | F50: =SUM('[2]D4 Gallon Forecast'!G$72:G$74) -> 358942587 | G50: =SUM('[2]D4 Gallon Forecast'!H$72:H$74) -> 404080273 | H50: =SUM('[2]D4 Gallon Forecast'!I$72:I$74) -> 416409298 | I50: =SUM('[2]D4 Gallon Forecast'!J$72:J$74) -> 471421342 | ... AO50: =SUM('[2]D4 Gallon Forecast'!AP$72:AP$74) -> 1.073861e+08
A51: Q3 | B51: =SUM('[2]D4 Gallon Forecast'!C$75:C$77) -> 301706279 | C51: =SUM('[2]D4 Gallon Forecast'!D$75:D$77) -> 274935859 | D51: =SUM('[2]D4 Gallon Forecast'!E$75:E$77) -> 385745942 | E51: =SUM('[2]D4 Gallon Forecast'!F$75:F$77) -> 379930478 | F51: =SUM('[2]D4 Gallon Forecast'!G$75:G$77) -> 372603090 | G51: =SUM('[2]D4 Gallon Forecast'!H$75:H$77) -> 446206361 | H51: =SUM('[2]D4 Gallon Forecast'!I$75:I$77) -> 456160275 | I51: =SUM('[2]D4 Gallon Forecast'!J$75:J$77) -> 507417523 | ... AO51: =SUM('[2]D4 Gallon Forecast'!AP$75:AP$77) -> 1.0775977e+08
A52: Q4 | B52: =SUM('[2]D4 Gallon Forecast'!C$78:C$80) -> 367811522 | C52: =SUM('[2]D4 Gallon Forecast'!D$78:D$80) -> 206736209 | D52: =SUM('[2]D4 Gallon Forecast'!E$78:E$80) -> 398782967 | E52: =SUM('[2]D4 Gallon Forecast'!F$78:F$80) -> 382156602 | F52: =SUM('[2]D4 Gallon Forecast'!G$78:G$80) -> 311596284 | G52: =SUM('[2]D4 Gallon Forecast'!H$78:H$80) -> 469931153 | H52: =SUM('[2]D4 Gallon Forecast'!I$78:I$80) -> 459773026 | I52: =SUM('[2]D4 Gallon Forecast'!J$78:J$80) -> 505054896 | ... AO52: =SUM('[2]D4 Gallon Forecast'!AP$78:AP$80) -> 1.1341722e+08
A53: Total | B53: =SUM(B49:B52) -> 1032917947 | C53: =SUM(C49:C52) -> 1016202001 | D53: =SUM(D49:D52) -> 1378586362 | E53: =SUM(E49:E52) -> 1305909690 | F53: =SUM(F49:F52) -> 1254228294 | G53: =SUM(G49:G52) -> 1632752622 | H53: =SUM(H49:H52) -> 1588249740 | I53: =SUM(I49:I52) -> 1855120823 | ... AO53: =SUM(AO49:AO52) -> 4.1509552e+08
A54: =N57/N50 -> 0.13381692 | B54: =B56/B49 -> 0.014187032 | C54: =C56/C49 -> 0.02197824 | D54: =D56/D49 -> 0.022219457 | E54: =E56/E49 -> 0.073780642 | F54: =F56/F49 -> 0.093008442 | G54: =G56/G49 -> 0.092412924 | H54: =H56/H49 -> 0.14918423 | I54: =I56/I49 -> 0.098581027 | ... M54: =M56/M49 -> 0.20667516 | N54: =N53/M53 -> 1.0302676
A55: CARB | B55: =B3 -> 2011 | C55: =C3 -> 2012 | D55: =D3 -> 2013 | E55: =E3 -> 2014 | F55: =F3 -> 2015 | G55: =G3 -> 2016 | H55: =H3 -> 2017 | I55: =I3 -> 2018 | ... AO55: =AO3 -> 2050
A56: Q1 | B56: ='Fuel Vol and Credit Gen'!C$12 -> 1954349 | C56: ='Fuel Vol and Credit Gen'!G$12 -> 5006202 | D56: ='Fuel Vol and Credit Gen'!K$12 -> 5481532 | E56: ='Fuel Vol and Credit Gen'!O$12 -> 16037416 | F56: ='Fuel Vol and Credit Gen'!S$12 -> 19632811 | G56: ='Fuel Vol and Credit Gen'!W$12 -> 28882258 | H56: ='Fuel Vol and Credit Gen'!AA$12 -> 38177310 | I56: ='Fuel Vol and Credit Gen'!AE$12 -> 36595945 | J56: ='Fuel Vol and Credit Gen'!AI$12 -> 41827876 | K56: ='Fuel Vol and Credit Gen'!AM$12 -> 56349932 | L56: ='Fuel Vol and Credit Gen'!AQ$12 -> 61422026 | M56: ='Fuel Vol and Credit Gen'!AU$12 -> 69654714 | N56: ='Fuel Vol and Credit Gen'!AY$12 -> 68541019 | O56: ='Fuel Vol and Credit Gen'!BC$12 -> 64404789 | P56: =FORECAST(P49,I56:O56,I49:O49)-2500000-10000000 -> 78891431 | Q56: =FORECAST(Q49,J56:P56,J49:P49)-7000000 -> 61120944 | R56: =FORECAST(R49,K56:Q56,K49:Q49)-5000000 -> 65205969 | S56: =FORECAST(S49,L56:R56,L49:R49)-5000000 -> 69218675 | T56: =FORECAST(T49,M56:S56,M49:S49)-5000000 -> 64986054 | U56: =FORECAST(U49,N56:T56,N49:T49)-5000000 -> 63933862 | V56: =FORECAST(V49,O56:U56,O49:U49)-5000000 -> 61613427 | W56: =FORECAST(W49,P56:V56,P49:V49) -> 62515031 | X56: =FORECAST(X49,Q56:W56,Q49:W49)+2000000 -> 64994081 | Y56: =FORECAST(Y49,R56:X56,R49:X49)+2000000 -> 66525986 | Z56: =FORECAST(Z49,S56:Y56,S49:Y49)+2000000 -> 67344341 | AA56: =FORECAST(AA49,T56:Z56,T49:Z49)+2000000 -> 72914767 | AB56: =FORECAST(AB49,U56:AA56,U49:AA49)+2000000 -> 81125387 | AC56: =FORECAST(AC49,V56:AB56,V49:AB49)+2000000 -> 83290336 | AD56: =FORECAST(AD49,W56:AC56,W49:AC49)+2000000 -> 89481839 | AE56: =FORECAST(AE49,X56:AD56,X49:AD49)+2000000 -> 1.004549e+08 | ... AO56: =FORECAST(AO49,AH56:AN56,AH49:AN49)+2000000 -> 1.1071247e+08
A57: Q2 | B57: ='Fuel Vol and Credit Gen'!D$12 -> 2623187 | C57: ='Fuel Vol and Credit Gen'!H$12 -> 6502404 | D57: ='Fuel Vol and Credit Gen'!L$12 -> 13975203 | E57: ='Fuel Vol and Credit Gen'!P$12 -> 16122376 | F57: ='Fuel Vol and Credit Gen'!T$12 -> 28502517 | G57: ='Fuel Vol and Credit Gen'!X$12 -> 35790526 | H57: ='Fuel Vol and Credit Gen'!AB$12 -> 37575247 | I57: ='Fuel Vol and Credit Gen'!AF$12 -> 40693700 | J57: ='Fuel Vol and Credit Gen'!AJ$12 -> 57413156 | K57: ='Fuel Vol and Credit Gen'!AN$12 -> 59271313 | L57: ='Fuel Vol and Credit Gen'!AR$12 -> 78153595 | M57: ='Fuel Vol and Credit Gen'!AV$12 -> 68309582 | N57: ='Fuel Vol and Credit Gen'!AZ$12 -> 60275869 | O57: ='Fuel Vol and Credit Gen'!BD$12 -> 55754578 | P57: =FORECAST(P50,I57:O57,I50:O50)-2500000-15000000 -> 48998068 | Q57: =FORECAST(Q50,J57:P57,J50:P50)-1250000 -> 51963504 | R57: =FORECAST(R50,K57:Q57,K50:Q50)-1250000 -> 49932352 | S57: =FORECAST(S50,L57:R57,L50:R50)-1250000 -> 26680625 | T57: =FORECAST(T50,M57:S57,M50:S50)-1250000 -> 40727703 | U57: =FORECAST(U50,N57:T57,N50:T50)-1250000 -> 43098929 | V57: =FORECAST(V50,O57:U57,O50:U50)+2000000 -> 46802554 | W57: =FORECAST(W50,P57:V57,P50:V50) -> 48433052 | X57: =FORECAST(X50,Q57:W57,Q50:W50) -> 41830533 | Y57: =FORECAST(Y50,R57:X57,R50:X50) -> 40427168 | Z57: =FORECAST(Z50,S57:Y57,S50:Y50) -> 36961093 | AA57: =FORECAST(AA50,T57:Z57,T50:Z50) -> 22332641 | AB57: =FORECAST(AB50,U57:AA57,U50:AA50) -> 6989393.2 | AC57: =FORECAST(AC50,V57:AB57,V50:AB50) -> 5217503 | AD57: =FORECAST(AD50,W57:AC57,W50:AC50) -> -5809937.3 | ... AO57: =FORECAST(AO50,AH57:AN57,AH50:AN50) -> -27770933
A58: Q3 | B58: ='Fuel Vol and Credit Gen'!E$12 -> 3477614 | C58: ='Fuel Vol and Credit Gen'!I$12 -> 4240695 | D58: ='Fuel Vol and Credit Gen'!M$12 -> 13936349 | E58: ='Fuel Vol and Credit Gen'!Q$12 -> 13880356 | F58: ='Fuel Vol and Credit Gen'!U$12 -> 42889152 | G58: ='Fuel Vol and Credit Gen'!Y$12 -> 45225506 | H58: ='Fuel Vol and Credit Gen'!AC$12 -> 50257498 | I58: ='Fuel Vol and Credit Gen'!AG$12 -> 49904077 | J58: ='Fuel Vol and Credit Gen'!AK$12 -> 56880071 | K58: ='Fuel Vol and Credit Gen'!AO$12 -> 69710273 | L58: ='Fuel Vol and Credit Gen'!AS$12 -> 77619602 | M58: ='Fuel Vol and Credit Gen'!AW$12 -> 72306900 | N58: ='Fuel Vol and Credit Gen'!BA$12 -> 67129512 | O58: =FORECAST(O51,H58:N58,H51:N51)+5000000-15000000 -> 61646249 | P58: =FORECAST(P51,I58:O58,I51:O51)-2500000-15000000 -> 52553265 | Q58: =FORECAST(Q51,J58:P58,J51:P51)-3500000 -> 57303009 | R58: =FORECAST(R51,K58:Q58,K51:Q51)-3500000 -> 55531148 | S58: =FORECAST(S51,L58:R58,L51:R51)-1500000 -> 32050653 | T58: =FORECAST(T51,M58:S58,M51:S51)-1500000 -> 45884709 | U58: =FORECAST(U51,N58:T58,N51:T51)-1500000 -> 48413287 | V58: =FORECAST(V51,O58:U58,O51:U51)-1500000 -> 48184918 | W58: =FORECAST(W51,P58:V58,P51:V51)+1000000 -> 53331248 | X58: =FORECAST(X51,Q58:W58,Q51:W51)+5000000 -> 51734623 | Y58: =FORECAST(Y51,R58:X58,R51:X51)+4000000 -> 50006052 | Z58: =FORECAST(Z51,S58:Y58,S51:Y51)+3000000 -> 46278507 | AA58: =FORECAST(AA51,T58:Z58,T51:Z51)+2000000 -> 42440328 | AB58: =FORECAST(AB51,U58:AA58,U51:AA51)+1000000 -> 37893611 | AC58: =FORECAST(AC51,V58:AB58,V51:AB51)+2000000 -> 38905883 | AD58: =FORECAST(AD51,W58:AC58,W51:AC51)+2000000 -> 35788353 | AE58: =FORECAST(AE51,X58:AD58,X51:AD51)+2000000 -> 30208261 | AF58: =FORECAST(AF51,Y58:AE58,Y51:AE51)+2000000 -> 32627740 | AG58: =FORECAST(AG51,Z58:AF58,Z51:AF51)+2000000 -> 33486260 | AH58: =FORECAST(AH51,AA58:AG58,AA51:AG51)+2000000 -> 32867807 | AI58: =FORECAST(AI51,AB58:AH58,AB51:AH51)+2000000 -> 33662034 | AJ58: =FORECAST(AJ51,AC58:AI58,AC51:AI51)+2000000 -> 34138381 | ... AO58: =FORECAST(AO51,AH58:AN58,AH51:AN51)+2000000 -> 40076244
A59: Q4 | B59: ='Fuel Vol and Credit Gen'!F$12 -> 4482442 | C59: ='Fuel Vol and Credit Gen'!J$12 -> 4226644 | D59: ='Fuel Vol and Credit Gen'!N$12 -> 26508045 | E59: ='Fuel Vol and Credit Gen'!R$12 -> 20757948 | F59: ='Fuel Vol and Credit Gen'!V$12 -> 35425955 | G59: ='Fuel Vol and Credit Gen'!Z$12 -> 53450453 | H59: ='Fuel Vol and Credit Gen'!AD$12 -> 43756532 | I59: ='Fuel Vol and Credit Gen'!AH$12 -> 57231365 | J59: ='Fuel Vol and Credit Gen'!AL$12 -> 55445419 | K59: ='Fuel Vol and Credit Gen'!AP$12 -> 81113099 | L59: ='Fuel Vol and Credit Gen'!AT$12 -> 72876457 | M59: ='Fuel Vol and Credit Gen'!AX$12 -> 70892771 | N59: ='Fuel Vol and Credit Gen'!BB$12 -> 72940256 | O59: =FORECAST(O52,H59:N59,H52:N52)+5000000-15000000 -> 54434656 | P59: =FORECAST(P52,I59:O59,I52:O52)-2500000-5000000 -> 57058040 | Q59: =FORECAST(Q52,J59:P59,J52:P52) -> 68800426 | R59: =FORECAST(R52,K59:Q59,K52:Q52) -> 71347685 | S59: =FORECAST(S52,L59:R59,L52:R52) -> 79235565 | T59: =FORECAST(T52,M59:S59,M52:S52) -> 70688920 | U59: =FORECAST(U52,N59:T59,N52:T52)+15000000 -> 83351574 | V59: =FORECAST(V52,O59:U59,O52:U52)+7000000 -> 78418645 | W59: =FORECAST(W52,P59:V59,P52:V52)+2000000 -> 73398807 | X59: =FORECAST(X52,Q59:W59,Q52:W52)+2000000 -> 77573857 | Y59: =FORECAST(Y52,R59:X59,R52:X52)+2000000 -> 78839880 | Z59: =FORECAST(Z52,S59:Y59,S52:Y52)+2000000 -> 80059581 | AA59: =FORECAST(AA52,T59:Z59,T52:Z52) -> 81265345 | AB59: =FORECAST(AB52,U59:AA59,U52:AA52) -> 83018171 | AC59: =FORECAST(AC52,V59:AB59,V52:AB52) -> 84186465 | AD59: =FORECAST(AD52,W59:AC59,W52:AC52) -> 86351066 | AE59: =FORECAST(AE52,X59:AD59,X52:AD52) -> 89229089 | AF59: =FORECAST(AF52,Y59:AE59,Y52:AE52) -> 88554018 | AG59: =FORECAST(AG52,Z59:AF59,Z52:AF52) -> 88643964 | AH59: =FORECAST(AH52,AA59:AG59,AA52:AG52) -> 89724022 | ... AO59: =FORECAST(AO52,AH59:AN59,AH52:AN52) -> 89234362
A60: Total | B60: =SUM(B56:B59) -> 12537592 | C60: =SUM(C56:C59) -> 19975945 | D60: =SUM(D56:D59) -> 59901129 | E60: =SUM(E56:E59) -> 66798096 | F60: =SUM(F56:F59) -> 126450435 | G60: =SUM(G56:G59) -> 163348743 | H60: =SUM(H56:H59) -> 169766587 | I60: =SUM(I56:I59) -> 184425087 | ... AO60: =SUM(AO56:AO59) -> 2.1225214e+08 | BC60: =(X60/O60)^(1/10)-1 -> -4.5377354e-05
B61: =B60/B53 -> 0.012138033 | C61: =C60/C53 -> 0.019657455 | D61: =D60/D53 -> 0.043451125 | E61: =E60/E53 -> 0.051150624 | F61: =F60/F53 -> 0.10081931 | G61: =G58/G51 -> 0.10135558 | H61: =H58/H51 -> 0.11017509 | I61: =I58/I51 -> 0.09834914 | J61: =J58/J51 -> 0.12187425 | K61: =K58/K51 -> 0.13883826 | L61: =L58/L51 -> 0.17584574 | M61: =M60/M53 -> 0.17353561 | N61: =N60/N53 -> 0.16108242 | O61: =O60/O53 -> 0.14224774 | P61: =P60/P53 -> 0.15022987 | Q61: =Q60/Q53 -> 0.1642448 | R61: =R60/R53 -> 0.16417918 | S61: =S60/S53 -> 0.1741001 | T61: =T60/T53 -> 0.15949017 | ... AO61: =AO60/AO53 -> 0.51133324
A62: Renewable Diesel
A63: EMTS | B63: =B3 -> 2011 | C63: =C3 -> 2012 | D63: =D3 -> 2013 | E63: =E3 -> 2014 | F63: =F3 -> 2015 | G63: =G3 -> 2016 | H63: =H3 -> 2017 | I63: =I3 -> 2018 | ... AO63: =AO3 -> 2050
A64: Q1 | B64: =SUM('[2]D4 Gallon Forecast'!C$133:C$135)+SUM('[2]D5 Gallon Forecast'!C$120:C$122)+SUM('[2]D6 Gallon Forecast'!C$218:C$220)+SUM('[2]D4 Gallon Forecast'!C$197:C$199) -> 8541444 | C64: =SUM('[2]D4 Gallon Forecast'!D$133:D$135)+SUM('[2]D5 Gallon Forecast'!D$120:D$122)+SUM('[2]D6 Gallon Forecast'!D$218:D$220)+SUM('[2]D4 Gallon Forecast'!D$197:D$199) -> 15879546 | D64: =SUM('[2]D4 Gallon Forecast'!E$133:E$135)+SUM('[2]D5 Gallon Forecast'!E$120:E$122)+SUM('[2]D6 Gallon Forecast'!E$218:E$220)+SUM('[2]D4 Gallon Forecast'!E$197:E$199) -> 24175969 | E64: =SUM('[2]D4 Gallon Forecast'!F$133:F$135)+SUM('[2]D5 Gallon Forecast'!F$120:F$122)+SUM('[2]D6 Gallon Forecast'!F$218:F$220)+SUM('[2]D4 Gallon Forecast'!F$197:F$199) -> 92593746 | F64: =SUM('[2]D4 Gallon Forecast'!G$133:G$135)+SUM('[2]D5 Gallon Forecast'!G$120:G$122)+SUM('[2]D6 Gallon Forecast'!G$218:G$220)+SUM('[2]D4 Gallon Forecast'!G$197:G$199) -> 73535181 | G64: =SUM('[2]D4 Gallon Forecast'!H$133:H$135)+SUM('[2]D5 Gallon Forecast'!H$120:H$122)+SUM('[2]D6 Gallon Forecast'!H$218:H$220)+SUM('[2]D4 Gallon Forecast'!H$197:H$199) -> 69724240 | H64: =SUM('[2]D4 Gallon Forecast'!I$133:I$135)+SUM('[2]D5 Gallon Forecast'!I$120:I$122)+SUM('[2]D6 Gallon Forecast'!I$218:I$220)+SUM('[2]D4 Gallon Forecast'!I$197:I$199) -> 102422003 | I64: =SUM('[2]D4 Gallon Forecast'!J$133:J$135)+SUM('[2]D5 Gallon Forecast'!J$120:J$122)+SUM('[2]D6 Gallon Forecast'!J$218:J$220)+SUM('[2]D4 Gallon Forecast'!J$197:J$199) -> 105722953 | ... R64: =SUM('[2]D4 Gallon Forecast'!S$133:S$135)+SUM('[2]D5 Gallon Forecast'!S$120:S$122)+SUM('[2]D6 Gallon Forecast'!S$218:S$220)+SUM('[2]D4 Gallon Forecast'!S$197:S$199) -> 6.8204162e+08 | S64: =SUM('[2]Monthly Gallon Summary'!T$83:T$85) -> 6.3351793e+08 | T64: =SUM('[2]Monthly Gallon Summary'!U$83:U$85) -> 6.3891406e+08 | U64: =SUM('[2]Monthly Gallon Summary'!V$83:V$85) -> 6.6977406e+08 | V64: =SUM('[2]Monthly Gallon Summary'!W$83:W$85) -> 7.2546454e+08 | W64: =SUM('[2]Monthly Gallon Summary'!X$83:X$85) -> 8.6027412e+08 | X64: =SUM('[2]Monthly Gallon Summary'!Y$83:Y$85) -> 8.5625783e+08 | Y64: =SUM('[2]Monthly Gallon Summary'!Z$83:Z$85) -> 8.3281158e+08 | Z64: =SUM('[2]D4 Gallon Forecast'!AA$133:AA$135)+SUM('[2]D5 Gallon Forecast'!AA$120:AA$122)+SUM('[2]D6 Gallon Forecast'!AA$218:AA$220)+SUM('[2]D4 Gallon Forecast'!AA$197:AA$199) -> 9.1610944e+08 | AA64: =SUM('[2]D4 Gallon Forecast'!AB$133:AB$135)+SUM('[2]D5 Gallon Forecast'!AB$120:AB$122)+SUM('[2]D6 Gallon Forecast'!AB$218:AB$220)+SUM('[2]D4 Gallon Forecast'!AB$197:AB$199) -> 9.6725428e+08 | AB64: =SUM('[2]D4 Gallon Forecast'!AC$133:AC$135)+SUM('[2]D5 Gallon Forecast'!AC$120:AC$122)+SUM('[2]D6 Gallon Forecast'!AC$218:AC$220)+SUM('[2]D4 Gallon Forecast'!AC$197:AC$199) -> 1.0937927e+09 | AC64: =SUM('[2]D4 Gallon Forecast'!AD$133:AD$135)+SUM('[2]D5 Gallon Forecast'!AD$120:AD$122)+SUM('[2]D6 Gallon Forecast'!AD$218:AD$220)+SUM('[2]D4 Gallon Forecast'!AD$197:AD$199) -> 1.205473e+09 | AD64: =SUM('[2]D4 Gallon Forecast'!AE$133:AE$135)+SUM('[2]D5 Gallon Forecast'!AE$120:AE$122)+SUM('[2]D6 Gallon Forecast'!AE$218:AE$220)+SUM('[2]D4 Gallon Forecast'!AE$197:AE$199) -> 1.209727e+09 | AE64: =SUM('[2]D4 Gallon Forecast'!AF$133:AF$135)+SUM('[2]D5 Gallon Forecast'!AF$120:AF$122)+SUM('[2]D6 Gallon Forecast'!AF$218:AF$220)+SUM('[2]D4 Gallon Forecast'!AF$197:AF$199) -> 1.0652483e+09 | AF64: =SUM('[2]D4 Gallon Forecast'!AG$133:AG$135)+SUM('[2]D5 Gallon Forecast'!AG$120:AG$122)+SUM('[2]D6 Gallon Forecast'!AG$218:AG$220)+SUM('[2]D4 Gallon Forecast'!AG$197:AG$199) -> 1.1262718e+09 | AG64: =SUM('[2]D4 Gallon Forecast'!AH$133:AH$135)+SUM('[2]D5 Gallon Forecast'!AH$120:AH$122)+SUM('[2]D6 Gallon Forecast'!AH$218:AH$220)+SUM('[2]D4 Gallon Forecast'!AH$197:AH$199) -> 1.1898748e+09 | ... AO64: =SUM('[2]D4 Gallon Forecast'!AP$133:AP$135)+SUM('[2]D5 Gallon Forecast'!AP$120:AP$122)+SUM('[2]D6 Gallon Forecast'!AP$218:AP$220)+SUM('[2]D4 Gallon Forecast'!AP$197:AP$199) -> 1.4542302e+09
A65: Q2 | B65: =SUM('[2]D4 Gallon Forecast'!C$136:C$138)+SUM('[2]D5 Gallon Forecast'!C$123:C$125)+SUM('[2]D6 Gallon Forecast'!C$221:C$223)+SUM('[2]D4 Gallon Forecast'!C$200:C$202) -> 14056277 | C65: =SUM('[2]D4 Gallon Forecast'!D$136:D$138)+SUM('[2]D5 Gallon Forecast'!D$123:D$125)+SUM('[2]D6 Gallon Forecast'!D$221:D$223)+SUM('[2]D4 Gallon Forecast'!D$200:D$202) -> 17687939 | D65: =SUM('[2]D4 Gallon Forecast'!E$136:E$138)+SUM('[2]D5 Gallon Forecast'!E$123:E$125)+SUM('[2]D6 Gallon Forecast'!E$221:E$223)+SUM('[2]D4 Gallon Forecast'!E$200:E$202) -> 42942735 | E65: =SUM('[2]D4 Gallon Forecast'!F$136:F$138)+SUM('[2]D5 Gallon Forecast'!F$123:F$125)+SUM('[2]D6 Gallon Forecast'!F$221:F$223)+SUM('[2]D4 Gallon Forecast'!F$200:F$202) -> 107349936 | F65: =SUM('[2]D4 Gallon Forecast'!G$136:G$138)+SUM('[2]D5 Gallon Forecast'!G$123:G$125)+SUM('[2]D6 Gallon Forecast'!G$221:G$223)+SUM('[2]D4 Gallon Forecast'!G$200:G$202) -> 90583827 | G65: =SUM('[2]D4 Gallon Forecast'!H$136:H$138)+SUM('[2]D5 Gallon Forecast'!H$123:H$125)+SUM('[2]D6 Gallon Forecast'!H$221:H$223)+SUM('[2]D4 Gallon Forecast'!H$200:H$202) -> 120453116 | H65: =SUM('[2]D4 Gallon Forecast'!I$136:I$138)+SUM('[2]D5 Gallon Forecast'!I$123:I$125)+SUM('[2]D6 Gallon Forecast'!I$221:I$223)+SUM('[2]D4 Gallon Forecast'!I$200:I$202) -> 117666041 | I65: =SUM('[2]D4 Gallon Forecast'!J$136:J$138)+SUM('[2]D5 Gallon Forecast'!J$123:J$125)+SUM('[2]D6 Gallon Forecast'!J$221:J$223)+SUM('[2]D4 Gallon Forecast'!J$200:J$202) -> 125328487 | ... R65: =SUM('[2]D4 Gallon Forecast'!S$136:S$138)+SUM('[2]D5 Gallon Forecast'!S$123:S$125)+SUM('[2]D6 Gallon Forecast'!S$221:S$223)+SUM('[2]D4 Gallon Forecast'!S$200:S$202) -> 7.6793764e+08 | S65: =SUM('[2]Monthly Gallon Summary'!T$86:T$88) -> 7.0368026e+08 | T65: =SUM('[2]Monthly Gallon Summary'!U$86:U$88) -> 7.079259e+08 | U65: =SUM('[2]Monthly Gallon Summary'!V$86:V$88) -> 7.4252242e+08 | V65: =SUM('[2]Monthly Gallon Summary'!W$86:W$88) -> 8.0510498e+08 | W65: =SUM('[2]Monthly Gallon Summary'!X$86:X$88) -> 9.549658e+08 | X65: =SUM('[2]Monthly Gallon Summary'!Y$86:Y$88) -> 9.5003805e+08 | Y65: =SUM('[2]Monthly Gallon Summary'!Z$86:Z$88) -> 9.2355625e+08 | Z65: =SUM('[2]D4 Gallon Forecast'!AA$136:AA$138)+SUM('[2]D5 Gallon Forecast'!AA$123:AA$125)+SUM('[2]D6 Gallon Forecast'!AA$221:AA$223)+SUM('[2]D4 Gallon Forecast'!AA$200:AA$202) -> 1.0249309e+09 | AA65: =SUM('[2]D4 Gallon Forecast'!AB$136:AB$138)+SUM('[2]D5 Gallon Forecast'!AB$123:AB$125)+SUM('[2]D6 Gallon Forecast'!AB$221:AB$223)+SUM('[2]D4 Gallon Forecast'!AB$200:AB$202) -> 1.0767823e+09 | AB65: =SUM('[2]D4 Gallon Forecast'!AC$136:AC$138)+SUM('[2]D5 Gallon Forecast'!AC$123:AC$125)+SUM('[2]D6 Gallon Forecast'!AC$221:AC$223)+SUM('[2]D4 Gallon Forecast'!AC$200:AC$202) -> 1.2162004e+09 | AC65: =SUM('[2]D4 Gallon Forecast'!AD$136:AD$138)+SUM('[2]D5 Gallon Forecast'!AD$123:AD$125)+SUM('[2]D6 Gallon Forecast'!AD$221:AD$223)+SUM('[2]D4 Gallon Forecast'!AD$200:AD$202) -> 1.3402484e+09 | AD65: =SUM('[2]D4 Gallon Forecast'!AE$136:AE$138)+SUM('[2]D5 Gallon Forecast'!AE$123:AE$125)+SUM('[2]D6 Gallon Forecast'!AE$221:AE$223)+SUM('[2]D4 Gallon Forecast'!AE$200:AE$202) -> 1.3446074e+09 | AE65: =SUM('[2]D4 Gallon Forecast'!AF$136:AF$138)+SUM('[2]D5 Gallon Forecast'!AF$123:AF$125)+SUM('[2]D6 Gallon Forecast'!AF$221:AF$223)+SUM('[2]D4 Gallon Forecast'!AF$200:AF$202) -> 1.183675e+09 | AF65: =SUM('[2]D4 Gallon Forecast'!AG$136:AG$138)+SUM('[2]D5 Gallon Forecast'!AG$123:AG$125)+SUM('[2]D6 Gallon Forecast'!AG$221:AG$223)+SUM('[2]D4 Gallon Forecast'!AG$200:AG$202) -> 1.2514673e+09 | AG65: =SUM('[2]D4 Gallon Forecast'!AH$136:AH$138)+SUM('[2]D5 Gallon Forecast'!AH$123:AH$125)+SUM('[2]D6 Gallon Forecast'!AH$221:AH$223)+SUM('[2]D4 Gallon Forecast'!AH$200:AH$202) -> 1.3221141e+09 | ... AO65: =SUM('[2]D4 Gallon Forecast'!AP$136:AP$138)+SUM('[2]D5 Gallon Forecast'!AP$123:AP$125)+SUM('[2]D6 Gallon Forecast'!AP$221:AP$223)+SUM('[2]D4 Gallon Forecast'!AP$200:AP$202) -> 1.6156508e+09
A66: Q3 | B66: =SUM('[2]D4 Gallon Forecast'!C$139:C$141)+SUM('[2]D5 Gallon Forecast'!C$126:C$128)+SUM('[2]D6 Gallon Forecast'!C$224:C$226)+SUM('[2]D4 Gallon Forecast'!C$203:C$205) -> 20812802 | C66: =SUM('[2]D4 Gallon Forecast'!D$139:D$141)+SUM('[2]D5 Gallon Forecast'!D$126:D$128)+SUM('[2]D6 Gallon Forecast'!D$224:D$226)+SUM('[2]D4 Gallon Forecast'!D$203:D$205) -> 28430772 | D66: =SUM('[2]D4 Gallon Forecast'!E$139:E$141)+SUM('[2]D5 Gallon Forecast'!E$126:E$128)+SUM('[2]D6 Gallon Forecast'!E$224:E$226)+SUM('[2]D4 Gallon Forecast'!E$203:E$205) -> 106605373 | E66: =SUM('[2]D4 Gallon Forecast'!F$139:F$141)+SUM('[2]D5 Gallon Forecast'!F$126:F$128)+SUM('[2]D6 Gallon Forecast'!F$224:F$226)+SUM('[2]D4 Gallon Forecast'!F$203:F$205) -> 87034577 | F66: =SUM('[2]D4 Gallon Forecast'!G$139:G$141)+SUM('[2]D5 Gallon Forecast'!G$126:G$128)+SUM('[2]D6 Gallon Forecast'!G$224:G$226)+SUM('[2]D4 Gallon Forecast'!G$203:G$205) -> 116911339 | G66: =SUM('[2]D4 Gallon Forecast'!H$139:H$141)+SUM('[2]D5 Gallon Forecast'!H$126:H$128)+SUM('[2]D6 Gallon Forecast'!H$224:H$226)+SUM('[2]D4 Gallon Forecast'!H$203:H$205) -> 148583669 | H66: =SUM('[2]D4 Gallon Forecast'!I$139:I$141)+SUM('[2]D5 Gallon Forecast'!I$126:I$128)+SUM('[2]D6 Gallon Forecast'!I$224:I$226)+SUM('[2]D4 Gallon Forecast'!I$203:I$205) -> 140702116 | I66: =SUM('[2]D4 Gallon Forecast'!J$139:J$141)+SUM('[2]D5 Gallon Forecast'!J$126:J$128)+SUM('[2]D6 Gallon Forecast'!J$224:J$226)+SUM('[2]D4 Gallon Forecast'!J$203:J$205) -> 148817810 | ... R66: =SUM('[2]D4 Gallon Forecast'!S$139:S$141)+SUM('[2]D5 Gallon Forecast'!S$126:S$128)+SUM('[2]D6 Gallon Forecast'!S$224:S$226)+SUM('[2]D4 Gallon Forecast'!S$203:S$205) -> 7.5785892e+08 | S66: =SUM('[2]Monthly Gallon Summary'!T$89:T$91) -> 7.2703023e+08 | T66: =SUM('[2]Monthly Gallon Summary'!U$89:U$91) -> 7.3352638e+08 | U66: =SUM('[2]Monthly Gallon Summary'!V$89:V$91) -> 7.6811567e+08 | V66: =SUM('[2]Monthly Gallon Summary'!W$89:W$91) -> 8.3263427e+08 | W66: =SUM('[2]Monthly Gallon Summary'!X$89:X$91) -> 9.8718406e+08 | X66: =SUM('[2]Monthly Gallon Summary'!Y$89:Y$91) -> 9.8256173e+08 | Y66: =SUM('[2]Monthly Gallon Summary'!Z$89:Z$91) -> 9.5595094e+08 | Z66: =SUM('[2]D4 Gallon Forecast'!AA$139:AA$141)+SUM('[2]D5 Gallon Forecast'!AA$126:AA$128)+SUM('[2]D6 Gallon Forecast'!AA$224:AA$226)+SUM('[2]D4 Gallon Forecast'!AA$203:AA$205) -> 1.0408776e+09 | AA66: =SUM('[2]D4 Gallon Forecast'!AB$139:AB$141)+SUM('[2]D5 Gallon Forecast'!AB$126:AB$128)+SUM('[2]D6 Gallon Forecast'!AB$224:AB$226)+SUM('[2]D4 Gallon Forecast'!AB$203:AB$205) -> 1.1050319e+09 | AB66: =SUM('[2]D4 Gallon Forecast'!AC$139:AC$141)+SUM('[2]D5 Gallon Forecast'!AC$126:AC$128)+SUM('[2]D6 Gallon Forecast'!AC$224:AC$226)+SUM('[2]D4 Gallon Forecast'!AC$203:AC$205) -> 1.251402e+09 | AC66: =SUM('[2]D4 Gallon Forecast'!AD$139:AD$141)+SUM('[2]D5 Gallon Forecast'!AD$126:AD$128)+SUM('[2]D6 Gallon Forecast'!AD$224:AD$226)+SUM('[2]D4 Gallon Forecast'!AD$203:AD$205) -> 1.3797056e+09 | AD66: =SUM('[2]D4 Gallon Forecast'!AE$139:AE$141)+SUM('[2]D5 Gallon Forecast'!AE$126:AE$128)+SUM('[2]D6 Gallon Forecast'!AE$224:AE$226)+SUM('[2]D4 Gallon Forecast'!AE$203:AE$205) -> 1.3852111e+09 | AE66: =SUM('[2]D4 Gallon Forecast'!AF$139:AF$141)+SUM('[2]D5 Gallon Forecast'!AF$126:AF$128)+SUM('[2]D6 Gallon Forecast'!AF$224:AF$226)+SUM('[2]D4 Gallon Forecast'!AF$203:AF$205) -> 1.2201908e+09 | AF66: =SUM('[2]D4 Gallon Forecast'!AG$139:AG$141)+SUM('[2]D5 Gallon Forecast'!AG$126:AG$128)+SUM('[2]D6 Gallon Forecast'!AG$224:AG$226)+SUM('[2]D4 Gallon Forecast'!AG$203:AG$205) -> 1.2896881e+09 | AG66: =SUM('[2]D4 Gallon Forecast'!AH$139:AH$141)+SUM('[2]D5 Gallon Forecast'!AH$126:AH$128)+SUM('[2]D6 Gallon Forecast'!AH$224:AH$226)+SUM('[2]D4 Gallon Forecast'!AH$203:AH$205) -> 1.3627464e+09 | ... AO66: =SUM('[2]D4 Gallon Forecast'!AP$139:AP$141)+SUM('[2]D5 Gallon Forecast'!AP$126:AP$128)+SUM('[2]D6 Gallon Forecast'!AP$224:AP$226)+SUM('[2]D4 Gallon Forecast'!AP$203:AP$205) -> 1.6659057e+09
A67: Q4 | B67: =SUM('[2]D4 Gallon Forecast'!C$142:C$144)+SUM('[2]D5 Gallon Forecast'!C$129:C$131)+SUM('[2]D6 Gallon Forecast'!C$227:C$229)+SUM('[2]D4 Gallon Forecast'!C$206:C$208) -> 18632778 | C67: =SUM('[2]D4 Gallon Forecast'!D$142:D$144)+SUM('[2]D5 Gallon Forecast'!D$129:D$131)+SUM('[2]D6 Gallon Forecast'!D$227:D$229)+SUM('[2]D4 Gallon Forecast'!D$206:D$208) -> 40677779 | D67: =SUM('[2]D4 Gallon Forecast'!E$142:E$144)+SUM('[2]D5 Gallon Forecast'!E$129:E$131)+SUM('[2]D6 Gallon Forecast'!E$227:E$229)+SUM('[2]D4 Gallon Forecast'!E$206:E$208) -> 119303125 | E67: =SUM('[2]D4 Gallon Forecast'!F$142:F$144)+SUM('[2]D5 Gallon Forecast'!F$129:F$131)+SUM('[2]D6 Gallon Forecast'!F$227:F$229)+SUM('[2]D4 Gallon Forecast'!F$206:F$208) -> 114632520 | F67: =SUM('[2]D4 Gallon Forecast'!G$142:G$144)+SUM('[2]D5 Gallon Forecast'!G$129:G$131)+SUM('[2]D6 Gallon Forecast'!G$227:G$229)+SUM('[2]D4 Gallon Forecast'!G$206:G$208) -> 115051020 | G67: =SUM('[2]D4 Gallon Forecast'!H$142:H$144)+SUM('[2]D5 Gallon Forecast'!H$129:H$131)+SUM('[2]D6 Gallon Forecast'!H$227:H$229)+SUM('[2]D4 Gallon Forecast'!H$206:H$208) -> 162723745 | H67: =SUM('[2]D4 Gallon Forecast'!I$142:I$144)+SUM('[2]D5 Gallon Forecast'!I$129:I$131)+SUM('[2]D6 Gallon Forecast'!I$227:I$229)+SUM('[2]D4 Gallon Forecast'!I$206:I$208) -> 156907344 | I67: =SUM('[2]D4 Gallon Forecast'!J$142:J$144)+SUM('[2]D5 Gallon Forecast'!J$129:J$131)+SUM('[2]D6 Gallon Forecast'!J$227:J$229)+SUM('[2]D4 Gallon Forecast'!J$206:J$208) -> 193027991 | ... R67: =SUM('[2]D4 Gallon Forecast'!S$142:S$144)+SUM('[2]D5 Gallon Forecast'!S$129:S$131)+SUM('[2]D6 Gallon Forecast'!S$227:S$229)+SUM('[2]D4 Gallon Forecast'!S$206:S$208) -> 1.011075e+09 | S67: =SUM('[2]Monthly Gallon Summary'!T$92:T$94) -> 9.5903548e+08 | T67: =SUM('[2]Monthly Gallon Summary'!U$92:U$94) -> 9.6698106e+08 | U67: =SUM('[2]Monthly Gallon Summary'!V$92:V$94) -> 1.0126342e+09 | V67: =SUM('[2]Monthly Gallon Summary'!W$92:W$94) -> 1.0984724e+09 | W67: =SUM('[2]Monthly Gallon Summary'!X$92:X$94) -> 1.3030502e+09 | X67: =SUM('[2]Monthly Gallon Summary'!Y$92:Y$94) -> 1.2962079e+09 | Y67: =SUM('[2]Monthly Gallon Summary'!Z$92:Z$94) -> 1.2597858e+09 | Z67: =SUM('[2]D4 Gallon Forecast'!AA$142:AA$144)+SUM('[2]D5 Gallon Forecast'!AA$129:AA$131)+SUM('[2]D6 Gallon Forecast'!AA$227:AA$229)+SUM('[2]D4 Gallon Forecast'!AA$206:AA$208) -> 1.3778815e+09 | AA67: =SUM('[2]D4 Gallon Forecast'!AB$142:AB$144)+SUM('[2]D5 Gallon Forecast'!AB$129:AB$131)+SUM('[2]D6 Gallon Forecast'!AB$227:AB$229)+SUM('[2]D4 Gallon Forecast'!AB$206:AB$208) -> 1.460718e+09 | AB67: =SUM('[2]D4 Gallon Forecast'!AC$142:AC$144)+SUM('[2]D5 Gallon Forecast'!AC$129:AC$131)+SUM('[2]D6 Gallon Forecast'!AC$227:AC$229)+SUM('[2]D4 Gallon Forecast'!AC$206:AC$208) -> 1.654228e+09 | AC67: =SUM('[2]D4 Gallon Forecast'!AD$142:AD$144)+SUM('[2]D5 Gallon Forecast'!AD$129:AD$131)+SUM('[2]D6 Gallon Forecast'!AD$227:AD$229)+SUM('[2]D4 Gallon Forecast'!AD$206:AD$208) -> 1.8236436e+09 | AD67: =SUM('[2]D4 Gallon Forecast'!AE$142:AE$144)+SUM('[2]D5 Gallon Forecast'!AE$129:AE$131)+SUM('[2]D6 Gallon Forecast'!AE$227:AE$229)+SUM('[2]D4 Gallon Forecast'!AE$206:AE$208) -> 1.8287357e+09 | AE67: =SUM('[2]D4 Gallon Forecast'!AF$142:AF$144)+SUM('[2]D5 Gallon Forecast'!AF$129:AF$131)+SUM('[2]D6 Gallon Forecast'!AF$227:AF$229)+SUM('[2]D4 Gallon Forecast'!AF$206:AF$208) -> 1.6081631e+09 | AF67: =SUM('[2]D4 Gallon Forecast'!AG$142:AG$144)+SUM('[2]D5 Gallon Forecast'!AG$129:AG$131)+SUM('[2]D6 Gallon Forecast'!AG$227:AG$229)+SUM('[2]D4 Gallon Forecast'!AG$206:AG$208) -> 1.700913e+09 | AG67: =SUM('[2]D4 Gallon Forecast'!AH$142:AH$144)+SUM('[2]D5 Gallon Forecast'!AH$129:AH$131)+SUM('[2]D6 Gallon Forecast'!AH$227:AH$229)+SUM('[2]D4 Gallon Forecast'!AH$206:AH$208) -> 1.7973368e+09 | ... AO67: =SUM('[2]D4 Gallon Forecast'!AP$142:AP$144)+SUM('[2]D5 Gallon Forecast'!AP$129:AP$131)+SUM('[2]D6 Gallon Forecast'!AP$227:AP$229)+SUM('[2]D4 Gallon Forecast'!AP$206:AP$208) -> 2.1982992e+09
A68: Total | B68: =SUM(B64:B67) -> 62043301 | C68: =SUM(C64:C67) -> 102676036 | D68: =SUM(D64:D67) -> 293027202 | E68: =SUM(E64:E67) -> 401610779 | F68: =SUM(F64:F67) -> 396081367 | G68: =SUM(G64:G67) -> 501484770 | H68: =SUM(H64:H67) -> 517697504 | I68: =SUM(I64:I67) -> 572897241 | ... AO68: =SUM(AO64:AO67) -> 6.9340859e+09
A69: =N72/N65 -> 0.66691633 | H69: =H60+H75 -> 505230981 | I69: =I60+I75 -> 567991140 | J69: =J60+J75 -> 829456712 | K69: =K60+K75 -> 855435848 | L69: =L60+L75 -> 1231078520 | M69: =M60+M75 -> 1675209277 | N69: =N60+N75 -> 2234052013 | O69: =O60+O75 -> 2.4552455e+09 | ... AO69: =AO60+AO75 -> 3.9140737e+09
A70: CARB | B70: =B3 -> 2011 | C70: =C3 -> 2012 | D70: =D3 -> 2013 | E70: =E3 -> 2014 | F70: =F3 -> 2015 | G70: =G3 -> 2016 | H70: =H3 -> 2017 | I70: =I3 -> 2018 | ... AO70: =AO3 -> 2050
A71: Q1 | B71: ='Fuel Vol and Credit Gen'!C$13 -> 325266 | C71: ='Fuel Vol and Credit Gen'!G$13 -> 712233 | D71: ='Fuel Vol and Credit Gen'!K$13 -> 8182191 | E71: ='Fuel Vol and Credit Gen'!O$13 -> 25871987 | F71: ='Fuel Vol and Credit Gen'!S$13 -> 27058770 | G71: ='Fuel Vol and Credit Gen'!W$13 -> 43663408 | H71: ='Fuel Vol and Credit Gen'!AA$13 -> 68700606 | I71: ='Fuel Vol and Credit Gen'!AE$13 -> 93949619 | J71: ='Fuel Vol and Credit Gen'!AI$13 -> 159583033 | K71: ='Fuel Vol and Credit Gen'!AM$13 -> 130973476 | L71: ='Fuel Vol and Credit Gen'!AQ$13 -> 199089761 | M71: ='Fuel Vol and Credit Gen'!AU$13 -> 320411961 | N71: ='Fuel Vol and Credit Gen'!AY$13 -> 404778818 | O71: ='Fuel Vol and Credit Gen'!BC$13 -> 518276102 | P71: =FORECAST(P64,K71:O71,K64:O64) -> 4.413921e+08 | Q71: =FORECAST(Q64,L71:P71,L64:P64) -> 4.352427e+08 | R71: =FORECAST(R64,K71:Q71,K64:Q64) -> 4.6845238e+08 | S71: =FORECAST(S64,L71:R71,L64:R64) -> 4.3749973e+08 | T71: =FORECAST(T64,M71:S71,M64:S64) -> 4.4165395e+08 | U71: =FORECAST(U64,N71:T71,N64:T64) -> 4.5790599e+08 | V71: =FORECAST(V64,O71:U71,O64:U64) -> 4.8836337e+08 | W71: =FORECAST(W64,P71:V71,P64:V64) -> 5.6598749e+08 | X71: =FORECAST(X64,Q71:W71,Q64:W64) -> 5.6369421e+08 | Y71: =FORECAST(Y64,R71:X71,R64:X64) -> 5.5042342e+08 | ... AO71: =FORECAST(AO64,AH71:AN71,AH64:AN64) -> 9.0352633e+08
A72: Q2 | B72: ='Fuel Vol and Credit Gen'!D$13 -> 356935 | C72: ='Fuel Vol and Credit Gen'!H$13 -> 723231 | D72: ='Fuel Vol and Credit Gen'!L$13 -> 23562582 | E72: ='Fuel Vol and Credit Gen'!P$13 -> 26668165 | F72: ='Fuel Vol and Credit Gen'!T$13 -> 40776364 | G72: ='Fuel Vol and Credit Gen'!X$13 -> 75711296 | H72: ='Fuel Vol and Credit Gen'!AB$13 -> 94202959 | I72: ='Fuel Vol and Credit Gen'!AF$13 -> 100488727 | J72: ='Fuel Vol and Credit Gen'!AJ$13 -> 160308777 | K72: ='Fuel Vol and Credit Gen'!AN$13 -> 151994539 | L72: ='Fuel Vol and Credit Gen'!AR$13 -> 218785737 | M72: ='Fuel Vol and Credit Gen'!AV$13 -> 349244307 | N72: ='Fuel Vol and Credit Gen'!AZ$13 -> 481200270 | O72: ='Fuel Vol and Credit Gen'!BD$13 -> 603001119 | P72: =FORECAST(P65,K72:O72,K65:O65) -> 4.4804863e+08 | Q72: =FORECAST(Q65,L72:P72,L65:P65) -> 4.8168551e+08 | R72: =FORECAST(R65,K72:Q72,K65:Q65) -> 5.2003729e+08 | S72: =FORECAST(S65,L72:R72,L65:R65) -> 4.7981696e+08 | T72: =FORECAST(T65,M72:S72,M65:S65) -> 4.8299392e+08 | U72: =FORECAST(U65,N72:T72,N65:T65) -> 5.0267639e+08 | V72: =FORECAST(V65,O72:U72,O65:U65) -> 5.4325302e+08 | W72: =FORECAST(W65,P72:V72,P65:V65) -> 6.3763877e+08 | X72: =FORECAST(X65,Q72:W72,Q65:W65) -> 6.3437328e+08 | Y72: =FORECAST(Y65,R72:X72,R65:X65) -> 6.1772884e+08 | ... AO72: =FORECAST(AO65,AH72:AN72,AH65:AN65) -> 1.0540494e+09
A73: Q3 | B73: ='Fuel Vol and Credit Gen'!E$13 -> 462226 | C73: ='Fuel Vol and Credit Gen'!I$13 -> 843696 | D73: ='Fuel Vol and Credit Gen'!M$13 -> 40409392 | E73: ='Fuel Vol and Credit Gen'!Q$13 -> 36487197 | F73: ='Fuel Vol and Credit Gen'!U$13 -> 51165569 | G73: ='Fuel Vol and Credit Gen'!Y$13 -> 63846512 | H73: ='Fuel Vol and Credit Gen'!AC$13 -> 95429959 | I73: ='Fuel Vol and Credit Gen'!AG$13 -> 79736407 | J73: ='Fuel Vol and Credit Gen'!AK$13 -> 133219894 | K73: ='Fuel Vol and Credit Gen'!AO$13 -> 140072718 | L73: ='Fuel Vol and Credit Gen'!AS$13 -> 250252477 | M73: ='Fuel Vol and Credit Gen'!AW$13 -> 352249753 | N73: ='Fuel Vol and Credit Gen'!BA$13 -> 531797418 | O73: =FORECAST(O66,J73:N73,J66:N66)*0+O66*0.6 -> 524507607 | P73: =FORECAST(P66,K73:O73,K66:O66)+150000000 -> 5.8014271e+08 | Q73: =FORECAST(Q66,L73:P73,L66:P66) -> 5.0147819e+08 | R73: =FORECAST(R66,K73:Q73,K66:Q66) -> 5.3934415e+08 | S73: =FORECAST(S66,L73:R73,L66:R66) -> 5.1923073e+08 | T73: =FORECAST(T66,M73:S73,M66:S66) -> 5.2255749e+08 | U73: =FORECAST(U66,N73:T73,N66:T66) -> 5.2692367e+08 | V73: =FORECAST(V66,O73:U73,O66:U66) -> 5.1805559e+08 | W73: =FORECAST(W66,P73:V73,P66:V66) -> 4.7645718e+08 | X73: =FORECAST(X66,Q73:W73,Q66:W66) -> 4.8812794e+08 | Y73: =FORECAST(Y66,R73:X73,R66:X66) -> 4.8971743e+08 | ... AO73: =FORECAST(AO66,AH73:AN73,AH66:AN66) -> 3.4856449e+08
A74: Q4 | B74: ='Fuel Vol and Credit Gen'!F$13 -> 659061 | C74: ='Fuel Vol and Credit Gen'!J$13 -> 6535747 | D74: ='Fuel Vol and Credit Gen'!N$13 -> 44784857 | E74: ='Fuel Vol and Credit Gen'!R$13 -> 23817520 | F74: ='Fuel Vol and Credit Gen'!V$13 -> 46155232 | G74: ='Fuel Vol and Credit Gen'!Z$13 -> 72449941 | H74: ='Fuel Vol and Credit Gen'!AD$13 -> 77130870 | I74: ='Fuel Vol and Credit Gen'!AH$13 -> 109391300 | J74: ='Fuel Vol and Credit Gen'!AL$13 -> 164778486 | K74: ='Fuel Vol and Credit Gen'!AP$13 -> 165950498 | L74: ='Fuel Vol and Credit Gen'!AT$13 -> 272878865 | M74: ='Fuel Vol and Credit Gen'!AX$13 -> 372139289 | N74: ='Fuel Vol and Credit Gen'!BB$13 -> 547388851 | O74: =FORECAST(O67,J74:N74,J67:N67) -> 5.7322041e+08 | P74: =FORECAST(P67,K74:O74,K67:O67) -> 5.3249525e+08 | Q74: =FORECAST(Q67,L74:P74,L67:P67) -> 5.9357418e+08 | R74: =FORECAST(R67,K74:Q74,K67:Q67) -> 6.4663458e+08 | S74: =FORECAST(S67,L74:R74,L67:R67) -> 6.1229948e+08 | T74: =FORECAST(T67,M74:S74,M67:S67) -> 6.1504973e+08 | U74: =FORECAST(U67,N74:T74,N67:T67) -> 6.4647463e+08 | V74: =FORECAST(V67,O74:U74,O67:U67) -> 7.0007441e+08 | W74: =FORECAST(W67,P74:V74,P67:V67) -> 8.292686e+08 | X74: =FORECAST(X67,Q74:W74,Q67:W67) -> 8.252197e+08 | Y74: =FORECAST(Y67,R74:X74,R67:X67) -> 8.0217491e+08 | ... AO74: =FORECAST(AO67,AH74:AN74,AH67:AN67) -> 1.3956814e+09
A75: Total | B75: =SUM(B71:B74) -> 1803488 | C75: =SUM(C71:C74) -> 8814907 | D75: =SUM(D71:D74) -> 116939022 | E75: =SUM(E71:E74) -> 112844869 | F75: =SUM(F71:F74) -> 165155935 | G75: =SUM(G71:G74) -> 255671157 | H75: =SUM(H71:H74) -> 335464394 | I75: =SUM(I71:I74) -> 383566053 | ... AO75: =SUM(AO71:AO74) -> 3.7018216e+09
B76: =B75/B68 -> 0.029068215 | C76: =C75/C68 -> 0.085851649 | D76: =D75/D68 -> 0.39907224 | E76: =E75/E68 -> 0.28098068 | F76: =F75/F68 -> 0.41697477 | G76: =G75/G68 -> 0.50982836 | H76: =H73/H66 -> 0.67824111 | I76: =I73/I66 -> 0.53579882 | J76: =J73/J66 -> 0.61317091 | K76: =K73/K66 -> 0.54714239 | L76: =L73/L66 -> 0.86063897 | M76: =M73/M66 -> 0.82085389 | N76: =N74/N67 -> 0.63105134 | O76: =O75/O68 -> 0.64291975 | P76: =P75/P68 -> 0.72493918 | Q76: =Q75/Q68 -> 0.67908181 | R76: =R75/R68 -> 0.67552874 | S76: =S75/S68 -> 0.6776937 | T76: =T75/T68 -> 0.67673777 | U76: =U75/U68 -> 0.66832124 | V76: =V75/V68 -> 0.64990088 | ... AO76: =AO75/AO68 -> 0.53385863
A77: Alternative Jet Fuel | N77: =N75/M75-1 -> 0.40968543
A78: EMTS | B78: =B3 -> 2011 | C78: =C3 -> 2012 | D78: =D3 -> 2013 | E78: =E3 -> 2014 | F78: =F3 -> 2015 | G78: =G3 -> 2016 | H78: =H3 -> 2017 | I78: =I3 -> 2018 | ... AO78: =AO3 -> 2050
A79: Q1 | B79: =SUM('[2]D4 Gallon Forecast'!C$325:C$327) -> 0 | C79: =SUM('[2]D4 Gallon Forecast'!D$325:D$327) -> 0 | D79: =SUM('[2]D4 Gallon Forecast'!E$325:E$327) -> 0 | E79: =SUM('[2]D4 Gallon Forecast'!F$325:F$327) -> 0 | F79: =SUM('[2]D4 Gallon Forecast'!G$325:G$327) -> 0 | G79: =SUM('[2]D4 Gallon Forecast'!H$325:H$327) -> 0 | H79: =SUM('[2]D4 Gallon Forecast'!I$325:I$327) -> 585778 | I79: =SUM('[2]D4 Gallon Forecast'!J$325:J$327) -> 481500 | ... AO79: =SUM('[2]D4 Gallon Forecast'!AP$325:AP$327) -> 1.4500134e+09
A80: Q2 | B80: =SUM('[2]D4 Gallon Forecast'!C$328:C$330) -> 0 | C80: =SUM('[2]D4 Gallon Forecast'!D$328:D$330) -> 0 | D80: =SUM('[2]D4 Gallon Forecast'!E$328:E$330) -> 0 | E80: =SUM('[2]D4 Gallon Forecast'!F$328:F$330) -> 0 | F80: =SUM('[2]D4 Gallon Forecast'!G$328:G$330) -> 0 | G80: =SUM('[2]D4 Gallon Forecast'!H$328:H$330) -> 0 | H80: =SUM('[2]D4 Gallon Forecast'!I$328:I$330) -> 261956 | I80: =SUM('[2]D4 Gallon Forecast'!J$328:J$330) -> 389017 | ... AO80: =SUM('[2]D4 Gallon Forecast'!AP$328:AP$330) -> 1.7223343e+09
A81: Q3 | B81: =SUM('[2]D4 Gallon Forecast'!C$331:C$333) -> 0 | C81: =SUM('[2]D4 Gallon Forecast'!D$331:D$333) -> 0 | D81: =SUM('[2]D4 Gallon Forecast'!E$331:E$333) -> 0 | E81: =SUM('[2]D4 Gallon Forecast'!F$331:F$333) -> 0 | F81: =SUM('[2]D4 Gallon Forecast'!G$331:G$333) -> 0 | G81: =SUM('[2]D4 Gallon Forecast'!H$331:H$333) -> 230790 | H81: =SUM('[2]D4 Gallon Forecast'!I$331:I$333) -> 432788 | I81: =SUM('[2]D4 Gallon Forecast'!J$331:J$333) -> 303549 | ... AO81: =SUM('[2]D4 Gallon Forecast'!AP$331:AP$333) -> 2.258935e+09
A82: Q4 | B82: =SUM('[2]D4 Gallon Forecast'!C$334:C$336) -> 0 | C82: =SUM('[2]D4 Gallon Forecast'!D$334:D$336) -> 0 | D82: =SUM('[2]D4 Gallon Forecast'!E$334:E$336) -> 0 | E82: =SUM('[2]D4 Gallon Forecast'!F$334:F$336) -> 0 | F82: =SUM('[2]D4 Gallon Forecast'!G$334:G$336) -> 0 | G82: =SUM('[2]D4 Gallon Forecast'!H$334:H$336) -> 552856 | H82: =SUM('[2]D4 Gallon Forecast'!I$334:I$336) -> 430495 | I82: =SUM('[2]D4 Gallon Forecast'!J$334:J$336) -> 654112 | ... AO82: =SUM('[2]D4 Gallon Forecast'!AP$334:AP$336) -> 2.2544034e+09
A83: Total | B83: =SUM(B79:B82) -> 0 | C83: =SUM(C79:C82) -> 0 | D83: =SUM(D79:D82) -> 0 | E83: =SUM(E79:E82) -> 0 | F83: =SUM(F79:F82) -> 0 | G83: =SUM(G79:G82) -> 783646 | H83: =SUM(H79:H82) -> 1711017 | I83: =SUM(I79:I82) -> 1828178 | ... AO83: =SUM(AO79:AO82) -> 7.6856861e+09
N84: =(X83/N83)-1 -> 239.81317
A85: CARB | B85: =B3 -> 2011 | C85: =C3 -> 2012 | D85: =D3 -> 2013 | E85: =E3 -> 2014 | F85: =F3 -> 2015 | G85: =G3 -> 2016 | H85: =H3 -> 2017 | I85: =I3 -> 2018 | ... AO85: =AO3 -> 2050
A86: Q1 | B86: ='Fuel Vol and Credit Gen'!C$14 -> 0 | C86: ='Fuel Vol and Credit Gen'!G$14 -> 0 | D86: ='Fuel Vol and Credit Gen'!K$14 -> 0 | E86: ='Fuel Vol and Credit Gen'!O$14 -> 0 | F86: ='Fuel Vol and Credit Gen'!S$14 -> 0 | G86: ='Fuel Vol and Credit Gen'!W$14 -> 0 | H86: ='Fuel Vol and Credit Gen'!AA$14 -> 0 | I86: ='Fuel Vol and Credit Gen'!AE$14 -> 0 | J86: ='Fuel Vol and Credit Gen'!AI$14 -> 0 | K86: ='Fuel Vol and Credit Gen'!AM$14 -> 284190 | L86: ='Fuel Vol and Credit Gen'!AQ$14 -> 873456 | M86: ='Fuel Vol and Credit Gen'!AU$14 -> 993399 | N86: ='Fuel Vol and Credit Gen'!AY$14 -> 4696266 | O86: ='Fuel Vol and Credit Gen'!BC$14 -> 10703076 | P86: =FORECAST(P79,I86:O86,I79:O79) -> 23161222 | Q86: =FORECAST(Q79,J86:P86,J79:P79)+20000000 -> 1.0248113e+08 | R86: =FORECAST(R79,K86:Q86,K79:Q79) -> 2.6507927e+08 | S86: =FORECAST(S79,L86:R86,L79:R79) -> 3.4731688e+08 | T86: =FORECAST(T79,M86:S86,M79:S79) -> 4.1670043e+08 | U86: =FORECAST(U79,N86:T86,N79:T79) -> 5.3205824e+08 | V86: =FORECAST(V79,O86:U86,O79:U79) -> 5.8554955e+08 | W86: =FORECAST(W79,P86:V86,P79:V79) -> 7.3362791e+08 | X86: =FORECAST(X79,Q86:W86,Q79:W79) -> 7.8481618e+08 | Y86: =FORECAST(Y79,R86:X86,R79:X79) -> 8.61228e+08 | ... AO86: =FORECAST(AO79,AH86:AN86,AH79:AN79) -> 1.0248196e+09
A87: Q2 | B87: ='Fuel Vol and Credit Gen'!D$14 -> 0 | C87: ='Fuel Vol and Credit Gen'!H$14 -> 0 | D87: ='Fuel Vol and Credit Gen'!L$14 -> 0 | E87: ='Fuel Vol and Credit Gen'!P$14 -> 0 | F87: ='Fuel Vol and Credit Gen'!T$14 -> 0 | G87: ='Fuel Vol and Credit Gen'!X$14 -> 0 | H87: ='Fuel Vol and Credit Gen'!AB$14 -> 0 | I87: ='Fuel Vol and Credit Gen'!AF$14 -> 0 | J87: ='Fuel Vol and Credit Gen'!AJ$14 -> 723542 | K87: ='Fuel Vol and Credit Gen'!AN$14 -> 1315875 | L87: ='Fuel Vol and Credit Gen'!AR$14 -> 2528070 | M87: ='Fuel Vol and Credit Gen'!AV$14 -> 4923344 | N87: ='Fuel Vol and Credit Gen'!AZ$14 -> 6897301 | O87: ='Fuel Vol and Credit Gen'!BD$14 -> 23560446 | P87: =FORECAST(P80,I87:O87,I80:O80) -> 32342158 | Q87: =FORECAST(Q80,J87:P87,J80:P80) -> 1.1962998e+08 | R87: =FORECAST(R80,K87:Q87,K80:Q80)-250000 -> 3.0811672e+08 | S87: =FORECAST(S80,L87:R87,L80:R80) -> 4.0295993e+08 | T87: =FORECAST(T80,M87:S87,M80:S80) -> 4.8325759e+08 | U87: =FORECAST(U80,N87:T87,N80:T80) -> 6.1347424e+08 | V87: =FORECAST(V80,O87:U87,O80:U80) -> 6.7501126e+08 | W87: =FORECAST(W80,P87:V87,P80:V80) -> 8.4403993e+08 | X87: =FORECAST(X80,Q87:W87,Q80:W80) -> 9.0366013e+08 | Y87: =FORECAST(Y80,R87:X87,R80:X80) -> 9.9061769e+08 | Z87: =FORECAST(Z80,S87:Y87,S80:Y80) -> 1.0380002e+09 | ... AO87: =FORECAST(AO80,AH87:AN87,AH80:AN80) -> 1.1776633e+09
A88: Q3 | B88: ='Fuel Vol and Credit Gen'!E$14 -> 0 | C88: ='Fuel Vol and Credit Gen'!I$14 -> 0 | D88: ='Fuel Vol and Credit Gen'!M$14 -> 0 | E88: ='Fuel Vol and Credit Gen'!Q$14 -> 0 | F88: ='Fuel Vol and Credit Gen'!U$14 -> 0 | G88: ='Fuel Vol and Credit Gen'!Y$14 -> 0 | H88: ='Fuel Vol and Credit Gen'!AC$14 -> 0 | I88: ='Fuel Vol and Credit Gen'!AG$14 -> 0 | J88: ='Fuel Vol and Credit Gen'!AK$14 -> 693621 | K88: ='Fuel Vol and Credit Gen'!AO$14 -> 2388230 | L88: ='Fuel Vol and Credit Gen'!AS$14 -> 1717347 | M88: ='Fuel Vol and Credit Gen'!AW$14 -> 4078887 | N88: ='Fuel Vol and Credit Gen'!BA$14 -> 4177769 | O88: =FORECAST(O81,H88:N88,H81:N81)+5000000 -> 31472071 | P88: =FORECAST(P81,I88:O88,I81:O81) -> 42037598 | Q88: =FORECAST(Q81,J88:P88,J81:P81)-6000000 -> 1.6194491e+08 | R88: =FORECAST(R81,K88:Q88,K81:Q81)-450000 -> 4.2027111e+08 | S88: =FORECAST(S81,L88:R88,L81:R81)-450000 -> 5.4993682e+08 | T88: =FORECAST(T81,M88:S88,M81:S81) -> 6.5943255e+08 | U88: =FORECAST(U81,N88:T88,N81:T81) -> 8.3729717e+08 | V88: =FORECAST(V81,O88:U88,O81:U81) -> 9.2165706e+08 | W88: =FORECAST(W81,P88:V88,P81:V81) -> 1.1528293e+09 | X88: =FORECAST(X81,Q88:W88,Q81:W81) -> 1.2345417e+09 | Y88: =FORECAST(Y81,R88:X88,R81:X81) -> 1.3532518e+09 | Z88: =FORECAST(Z81,S88:Y88,S81:Y81) -> 1.4180292e+09 | AA88: =FORECAST(AA81,T88:Z88,T81:Z81) -> 1.0420632e+09 | ... AO88: =FORECAST(AO81,AH88:AN88,AH81:AN81) -> 1.6091059e+09
A89: Q4 | B89: ='Fuel Vol and Credit Gen'!F$14 -> 0 | C89: ='Fuel Vol and Credit Gen'!J$14 -> 0 | D89: ='Fuel Vol and Credit Gen'!N$14 -> 0 | E89: ='Fuel Vol and Credit Gen'!R$14 -> 0 | F89: ='Fuel Vol and Credit Gen'!V$14 -> 0 | G89: ='Fuel Vol and Credit Gen'!Z$14 -> 0 | H89: ='Fuel Vol and Credit Gen'!AD$14 -> 0 | I89: ='Fuel Vol and Credit Gen'!AH$14 -> 0 | J89: ='Fuel Vol and Credit Gen'!AL$14 -> 445027 | K89: ='Fuel Vol and Credit Gen'!AP$14 -> 570655 | L89: ='Fuel Vol and Credit Gen'!AT$14 -> 3078857 | M89: ='Fuel Vol and Credit Gen'!AX$14 -> 1608959 | N89: ='Fuel Vol and Credit Gen'!BB$14 -> 7266054 | O89: =FORECAST(O82,H89:N89,H82:N82)-18000000 -> 3618110.2 | P89: =FORECAST(P82,I89:O89,I82:O82) -> 11506899 | Q89: =FORECAST(Q82,J89:P89,J82:P82) -> 39138483 | R89: =FORECAST(R82,K89:Q89,K82:Q82) -> 97521340 | S89: =FORECAST(S82,L89:R89,L82:R82) -> 1.2701563e+08 | T89: =FORECAST(T82,M89:S89,M82:S82) -> 1.5075503e+08 | U89: =FORECAST(U82,N89:T89,N82:T82) -> 1.9167224e+08 | V89: =FORECAST(V82,O89:U89,O82:U82) -> 2.1135229e+08 | W89: =FORECAST(W82,P89:V89,P82:V82) -> 2.6374127e+08 | ... AO89: =FORECAST(AO82,AH89:AN89,AH82:AN82) -> 3.6736263e+08
A90: Total | B90: =SUM(B86:B89) -> 0 | C90: =SUM(C86:C89) -> 0 | D90: =SUM(D86:D89) -> 0 | E90: =SUM(E86:E89) -> 0 | F90: =SUM(F86:F89) -> 0 | G90: =SUM(G86:G89) -> 0 | H90: =SUM(H86:H89) -> 0 | I90: =SUM(I86:I89) -> 0 | ... AO90: =SUM(AO86:AO89) -> 4.1789515e+09
J91: =J90/J83 -> 0.76674289 | K91: =K90/K83 -> 0.98926981 | L91: =L90/L83 -> 1.6147998 | M91: =M90/M83 -> 0.73354483 | N91: =N90/N83 -> 0.94127022 | O91: =O90/O83 -> 0.6202197 | P91: =P90/P83 -> 0.54648304 | Q91: =Q90/Q83 -> 0.54916777 | ... AO91: =AO90/AO83 -> 0.54373174
A92: Renewable Gasoline Blendstocks
A93: EMTS | B93: =B3 -> 2011 | C93: =C3 -> 2012 | D93: =D3 -> 2013 | E93: =E3 -> 2014 | F93: =F3 -> 2015 | G93: =G3 -> 2016 | H93: =H3 -> 2017 | I93: =I3 -> 2018 | ... AO93: =AO3 -> 2050
A94: Q1 | B94: =SUM('[2]D5 Gallon Forecast'!C$312:C$314)+SUM('[2]D5 Gallon Forecast'!C$296:C$298) -> 0 | C94: =SUM('[2]D5 Gallon Forecast'!D$312:D$314)+SUM('[2]D5 Gallon Forecast'!D$296:D$298) -> 0 | D94: =SUM('[2]D5 Gallon Forecast'!E$312:E$314)+SUM('[2]D5 Gallon Forecast'!E$296:E$298) -> 0 | E94: =SUM('[2]D5 Gallon Forecast'!F$312:F$314)+SUM('[2]D5 Gallon Forecast'!F$296:F$298) -> 2795339 | F94: =SUM('[2]D5 Gallon Forecast'!G$312:G$314)+SUM('[2]D5 Gallon Forecast'!G$296:G$298) -> 4123200 | G94: =SUM('[2]D5 Gallon Forecast'!H$312:H$314)+SUM('[2]D5 Gallon Forecast'!H$296:H$298) -> 2768038 | H94: =SUM('[2]D5 Gallon Forecast'!I$312:I$314)+SUM('[2]D5 Gallon Forecast'!I$296:I$298) -> 4269904 | I94: =SUM('[2]D5 Gallon Forecast'!J$312:J$314)+SUM('[2]D5 Gallon Forecast'!J$296:J$298) -> 6080337 | ... AO94: =SUM('[2]D5 Gallon Forecast'!AP$312:AP$314)+SUM('[2]D5 Gallon Forecast'!AP$296:AP$298) -> 99995617
A95: Q2 | B95: =SUM('[2]D5 Gallon Forecast'!C$299:C$301,'[2]D5 Gallon Forecast'!C$315:C$317) -> 0 | C95: =SUM('[2]D5 Gallon Forecast'!D$299:D$301,'[2]D5 Gallon Forecast'!D$315:D$317) -> 0 | D95: =SUM('[2]D5 Gallon Forecast'!E$299:E$301,'[2]D5 Gallon Forecast'!E$315:E$317) -> 0 | E95: =SUM('[2]D5 Gallon Forecast'!F$299:F$301,'[2]D5 Gallon Forecast'!F$315:F$317) -> 2752617 | F95: =SUM('[2]D5 Gallon Forecast'!G$299:G$301,'[2]D5 Gallon Forecast'!G$315:G$317) -> 3810900 | G95: =SUM('[2]D5 Gallon Forecast'!H$299:H$301,'[2]D5 Gallon Forecast'!H$315:H$317) -> 4226884 | H95: =SUM('[2]D5 Gallon Forecast'!I$299:I$301,'[2]D5 Gallon Forecast'!I$315:I$317) -> 5737694 | I95: =SUM('[2]D5 Gallon Forecast'!J$299:J$301,'[2]D5 Gallon Forecast'!J$315:J$317) -> 3948079 | ... AO95: =SUM('[2]D5 Gallon Forecast'!AP$299:AP$301,'[2]D5 Gallon Forecast'!AP$315:AP$317) -> 82732221
A96: Q3 | B96: =SUM('[2]D5 Gallon Forecast'!C$302:C$304,'[2]D5 Gallon Forecast'!C$318:C$320) -> 0 | C96: =SUM('[2]D5 Gallon Forecast'!D$302:D$304,'[2]D5 Gallon Forecast'!D$318:D$320) -> 0 | D96: =SUM('[2]D5 Gallon Forecast'!E$302:E$304,'[2]D5 Gallon Forecast'!E$318:E$320) -> 631775 | E96: =SUM('[2]D5 Gallon Forecast'!F$302:F$304,'[2]D5 Gallon Forecast'!F$318:F$320) -> 1882945 | F96: =SUM('[2]D5 Gallon Forecast'!G$302:G$304,'[2]D5 Gallon Forecast'!G$318:G$320) -> 4437089 | G96: =SUM('[2]D5 Gallon Forecast'!H$302:H$304,'[2]D5 Gallon Forecast'!H$318:H$320) -> 4826074 | H96: =SUM('[2]D5 Gallon Forecast'!I$302:I$304,'[2]D5 Gallon Forecast'!I$318:I$320) -> 5101244 | I96: =SUM('[2]D5 Gallon Forecast'!J$302:J$304,'[2]D5 Gallon Forecast'!J$318:J$320) -> 4626604 | ... AO96: =SUM('[2]D5 Gallon Forecast'!AP$302:AP$304,'[2]D5 Gallon Forecast'!AP$318:AP$320) -> 1.0494947e+08
A97: Q4 | B97: =SUM('[2]D5 Gallon Forecast'!C$305:C$307,'[2]D5 Gallon Forecast'!C$321:C$323) -> 0 | C97: =SUM('[2]D5 Gallon Forecast'!D$305:D$307,'[2]D5 Gallon Forecast'!D$321:D$323) -> 0 | D97: =SUM('[2]D5 Gallon Forecast'!E$305:E$307,'[2]D5 Gallon Forecast'!E$321:E$323) -> 1679382 | E97: =SUM('[2]D5 Gallon Forecast'!F$305:F$307,'[2]D5 Gallon Forecast'!F$321:F$323) -> 4663018 | F97: =SUM('[2]D5 Gallon Forecast'!G$305:G$307,'[2]D5 Gallon Forecast'!G$321:G$323) -> 3621050 | G97: =SUM('[2]D5 Gallon Forecast'!H$305:H$307,'[2]D5 Gallon Forecast'!H$321:H$323) -> 6290191 | H97: =SUM('[2]D5 Gallon Forecast'!I$305:I$307,'[2]D5 Gallon Forecast'!I$321:I$323) -> 5910524 | I97: =SUM('[2]D5 Gallon Forecast'!J$305:J$307,'[2]D5 Gallon Forecast'!J$321:J$323) -> 6746260 | ... AO97: =SUM('[2]D5 Gallon Forecast'!AP$305:AP$307,'[2]D5 Gallon Forecast'!AP$321:AP$323) -> 1.3959146e+08
A98: Total | B98: =SUM(B94:B97) -> 0 | C98: =SUM(C94:C97) -> 0 | D98: =SUM(D94:D97) -> 2311157 | E98: =SUM(E94:E97) -> 12093919 | F98: =SUM(F94:F97) -> 15992239 | G98: =SUM(G94:G97) -> 18111187 | H98: =SUM(H94:H97) -> 21019366 | I98: =SUM(I94:I97) -> 21401280 | ... AO98: =SUM(AO94:AO97) -> 4.2726876e+08
A100: CARB | B100: =B3 -> 2011 | C100: =C3 -> 2012 | D100: =D3 -> 2013 | E100: =E3 -> 2014 | F100: =F3 -> 2015 | G100: =G3 -> 2016 | H100: =H3 -> 2017 | I100: =I3 -> 2018 | ... AO100: =AO3 -> 2050
A101: Q1 | B101: ='Fuel Vol and Credit Gen'!C$15 -> 0 | C101: ='Fuel Vol and Credit Gen'!G$15 -> 0 | D101: ='Fuel Vol and Credit Gen'!K$15 -> 0 | E101: ='Fuel Vol and Credit Gen'!O$15 -> 0 | F101: ='Fuel Vol and Credit Gen'!S$15 -> 0 | G101: ='Fuel Vol and Credit Gen'!W$15 -> 0 | H101: ='Fuel Vol and Credit Gen'!AA$15 -> 0 | I101: ='Fuel Vol and Credit Gen'!AE$15 -> 0 | J101: ='Fuel Vol and Credit Gen'!AI$15 -> 107933 | K101: ='Fuel Vol and Credit Gen'!AM$15 -> 352423 | L101: ='Fuel Vol and Credit Gen'!AQ$15 -> 2427368 | M101: ='Fuel Vol and Credit Gen'!AU$15 -> 3145585 | N101: ='Fuel Vol and Credit Gen'!AY$15 -> 3650982 | O101: ='Fuel Vol and Credit Gen'!BC$15 -> 7520995 | P101: =P94*0.5 -> 12750384 | Q101: =Q94*0.5 -> 10973809 | R101: =R94*0.5 -> 12088012 | S101: =S94*0.5 -> 12910551 | T101: =T94*0.5 -> 12641950 | U101: =U94*0.5 -> 14033814 | V101: =V94*0.5 -> 15320771 | W101: =W94*0.5 -> 16309625 | ... AO101: =AO94*0.5 -> 49997808
A102: Q2 | B102: ='Fuel Vol and Credit Gen'!D$15 -> 0 | C102: ='Fuel Vol and Credit Gen'!H$15 -> 0 | D102: ='Fuel Vol and Credit Gen'!L$15 -> 0 | E102: ='Fuel Vol and Credit Gen'!P$15 -> 0 | F102: ='Fuel Vol and Credit Gen'!T$15 -> 0 | G102: ='Fuel Vol and Credit Gen'!X$15 -> 0 | H102: ='Fuel Vol and Credit Gen'!AB$15 -> 0 | I102: ='Fuel Vol and Credit Gen'!AF$15 -> 0 | J102: ='Fuel Vol and Credit Gen'!AJ$15 -> 673134 | K102: ='Fuel Vol and Credit Gen'!AN$15 -> 447211 | L102: ='Fuel Vol and Credit Gen'!AR$15 -> 4222140 | M102: ='Fuel Vol and Credit Gen'!AV$15 -> 5145704 | N102: ='Fuel Vol and Credit Gen'!AZ$15 -> 7593875 | O102: ='Fuel Vol and Credit Gen'!BD$15 -> 7566471 | P102: =P95*0.5 -> 9120227.9 | Q102: =Q95*0.5 -> 8942452.6 | R102: =R95*0.5 -> 9877107.4 | S102: =S95*0.5 -> 10491115 | T102: =T95*0.5 -> 10227137 | U102: =U95*0.5 -> 11222782 | V102: =V95*0.5 -> 12557182 | W102: =W95*0.5 -> 13404041 | ... AO102: =AO95*0.5 -> 41366111
A103: Q3 | B103: ='Fuel Vol and Credit Gen'!E$15 -> 0 | C103: ='Fuel Vol and Credit Gen'!I$15 -> 0 | D103: ='Fuel Vol and Credit Gen'!M$15 -> 0 | E103: ='Fuel Vol and Credit Gen'!Q$15 -> 0 | F103: ='Fuel Vol and Credit Gen'!U$15 -> 0 | G103: ='Fuel Vol and Credit Gen'!Y$15 -> 0 | H103: ='Fuel Vol and Credit Gen'!AC$15 -> 0 | I103: ='Fuel Vol and Credit Gen'!AG$15 -> 0 | J103: ='Fuel Vol and Credit Gen'!AK$15 -> 175948 | K103: ='Fuel Vol and Credit Gen'!AO$15 -> 815855 | L103: ='Fuel Vol and Credit Gen'!AS$15 -> 2350926 | M103: ='Fuel Vol and Credit Gen'!AW$15 -> 1682809 | N103: ='Fuel Vol and Credit Gen'!BA$15 -> 13728337 | O103: =O96*0.5 -> 8524693.5 | P103: =P96*0.5 -> 11487555 | Q103: =Q96*0.5 -> 12382825 | R103: =R96*0.5 -> 13572267 | S103: =S96*0.5 -> 13837771 | T103: =T96*0.5 -> 14064596 | U103: =U96*0.5 -> 14836813 | V103: =V96*0.5 -> 16499915 | ... AO103: =AO96*0.5 -> 52474733
A104: Q4 | B104: ='Fuel Vol and Credit Gen'!F$15 -> 0 | C104: ='Fuel Vol and Credit Gen'!J$15 -> 0 | D104: ='Fuel Vol and Credit Gen'!N$15 -> 0 | E104: ='Fuel Vol and Credit Gen'!R$15 -> 0 | F104: ='Fuel Vol and Credit Gen'!V$15 -> 0 | G104: ='Fuel Vol and Credit Gen'!Z$15 -> 0 | H104: ='Fuel Vol and Credit Gen'!AD$15 -> 0 | I104: ='Fuel Vol and Credit Gen'!AH$15 -> 170876 | J104: ='Fuel Vol and Credit Gen'!AL$15 -> 290046 | K104: ='Fuel Vol and Credit Gen'!AP$15 -> 591098 | L104: ='Fuel Vol and Credit Gen'!AT$15 -> 2107524 | M104: ='Fuel Vol and Credit Gen'!AX$15 -> 2190902 | N104: ='Fuel Vol and Credit Gen'!BB$15 -> 6221948 | O104: =O97*0.5 -> 11959058 | P104: =P97*0.5 -> 14262989 | Q104: =Q97*0.5 -> 16253918 | R104: =R97*0.5 -> 17498359 | S104: =S97*0.5 -> 18240983 | T104: =T97*0.5 -> 18296166 | U104: =U97*0.5 -> 19319146 | V104: =V97*0.5 -> 21734550 | ... AO104: =AO97*0.5 -> 69795729
A105: Total | B105: =SUM(B101:B104) -> 0 | C105: =SUM(C101:C104) -> 0 | D105: =SUM(D101:D104) -> 0 | E105: =SUM(E101:E104) -> 0 | F105: =SUM(F101:F104) -> 0 | G105: =SUM(G101:G104) -> 0 | H105: =SUM(H101:H104) -> 0 | I105: =SUM(I101:I104) -> 170876 | ... AO105: =SUM(AO101:AO104) -> 2.1363438e+08
J106: =J105/J98 -> 0.050821626 | K106: =K105/K98 -> 0.099598345 | L106: =L105/L98 -> 0.49572536 | M106: =M105/M98 -> 0.19150799 | N106: =N105/N98 -> 0.59636954 | O106: =O105/O98 -> 0.55557703 | P106: =P105/P98 -> 0.5 | Q106: =Q105/Q98 -> 0.5 | ... AO106: =AO105/AO98 -> 0.5
...

Sheet Fuel Vol and Credit Gen
A1: Fig. 2 - Alternative Fuels Volumes and Credits
A3: Volume (quaterly) from "Fuels" tab
B4: Unit | C4: ='Qrtly Credit-Deficit Generation'!C76 -> 2011Q1 | D4: ='Qrtly Credit-Deficit Generation'!D76 -> Q2 | E4: ='Qrtly Credit-Deficit Generation'!E76 -> Q3 | F4: ='Qrtly Credit-Deficit Generation'!F76 -> Q4 | G4: ='Qrtly Credit-Deficit Generation'!G76 -> 2012Q1 | H4: ='Qrtly Credit-Deficit Generation'!H76 -> Q2 | I4: ='Qrtly Credit-Deficit Generation'!I76 -> Q3 | J4: ='Qrtly Credit-Deficit Generation'!J76 -> Q4 | ... AR4: ='Qrtly Credit-Deficit Generation'!AR76 -> Q2 | AS4: Q3 | AT4: Q4 | AU4: Q1 2022 | AV4: Q2 | AW4: Q3 | AX4: Q4 | AY4: Q1 2023 | AZ4: Q2 | BA4: Q3 | BB4: Q4 | BC4: Q1 2024 | BD4: Q2 | BE4: Q3 | BF4: Q4 | BG4: Q1 2025 | BH4: =BD4 -> Q2 | BI4: =BE4 -> Q3 | BJ4: =BF4 -> Q4 | BK4: Q1 2026 | BL4: =BH4 -> Q2 | BM4: =BI4 -> Q3 | BN4: =BJ4 -> Q4 | BO4: Q1 2027 | BP4: =BL4 -> Q2 | BQ4: =BM4 -> Q3 | BR4: =BN4 -> Q4 | BS4: Q1 2028 | BT4: =BP4 -> Q2 | BU4: =BQ4 -> Q3 | BV4: =BR4 -> Q4 | BW4: Q1 2029 | BX4: =BT4 -> Q2 | BY4: =BU4 -> Q3 | BZ4: =BV4 -> Q4 | CA4: Q1 2030 | CB4: =BX4 -> Q2 | CC4: =BY4 -> Q3 | CD4: =BZ4 -> Q4 | CE4: Q1 2031 | CF4: =CB4 -> Q2 | CG4: =CC4 -> Q3 | CH4: =CD4 -> Q4 | CI4: Q1 2032 | CJ4: =CF4 -> Q2 | CK4: =CG4 -> Q3 | CL4: =CH4 -> Q4 | CM4: Q1 2033 | CN4: =CJ4 -> Q2 | CO4: =CK4 -> Q3 | CP4: =CL4 -> Q4 | CQ4: Q1 2034 | CR4: =CN4 -> Q2 | CS4: =CO4 -> Q3 | CT4: =CP4 -> Q4 | CU4: Q1 2035 | CV4: =CR4 -> Q2 | CW4: =CS4 -> Q3 | CX4: =CT4 -> Q4 | CY4: Q1 2036 | CZ4: =CV4 -> Q2 | DA4: =CW4 -> Q3 | DB4: =CX4 -> Q4 | DC4: Q1 2037 | DD4: =CZ4 -> Q2 | DE4: =DA4 -> Q3 | DF4: =DB4 -> Q4 | DG4: Q1 2038 | DH4: =DD4 -> Q2 | DI4: =DE4 -> Q3 | DJ4: =DF4 -> Q4 | DK4: Q1 2039 | DL4: =DH4 -> Q2 | DM4: =DI4 -> Q3 | DN4: =DJ4 -> Q4 | DO4: Q1 2040 | DP4: =DL4 -> Q2 | DQ4: =DM4 -> Q3 | DR4: =DN4 -> Q4 | DS4: Q1 2041 | DT4: =DP4 -> Q2 | DU4: =DQ4 -> Q3 | DV4: =DR4 -> Q4 | DW4: Q1 2042 | DX4: =DT4 -> Q2 | DY4: =DU4 -> Q3 | DZ4: =DV4 -> Q4 | EA4: Q1 2043 | EB4: =DX4 -> Q2 | EC4: =DY4 -> Q3 | ED4: =DZ4 -> Q4 | EE4: Q1 2044 | EF4: =EB4 -> Q2 | EG4: =EC4 -> Q3 | EH4: =ED4 -> Q4 | EI4: Q1 2045 | EJ4: =EF4 -> Q2 | EK4: =EG4 -> Q3 | EL4: =EH4 -> Q4 | EM4: Q1 2046 | EN4: =EJ4 -> Q2 | EO4: =EK4 -> Q3 | EP4: =EL4 -> Q4 | EQ4: Q1 2047 | ER4: =EN4 -> Q2 | ES4: =EO4 -> Q3 | ET4: =EP4 -> Q4 | EU4: Q1 2048 | EV4: =ER4 -> Q2 | EW4: =ES4 -> Q3 | EX4: =ET4 -> Q4 | EY4: Q1 2049 | EZ4: =EV4 -> Q2 | FA4: =EW4 -> Q3 | FB4: =EX4 -> Q4 | FC4: Q1 2050 | FD4: =EZ4 -> Q2 | FE4: =FA4 -> Q3 | FF4: =FB4 -> Q4 | FG4: Q1 2051 | FH4: =FD4 -> Q2 | FI4: =FE4 -> Q3 | FJ4: =FF4 -> Q4
A5: Bio-CNG | B5: dge | C5: 0 | D5: 0 | E5: 0 | F5: 0 | G5: 0 | H5: 0 | I5: 0 | J5: 0 | K5: 0 | L5: 7532 | M5: 2583509 | N5: 2995901 | O5: 2726000 | P5: 2881044 | Q5: 4617725 | R5: 5258002 | S5: 6720568 | T5: 9981749 | U5: 11049178 | V5: 11447850 | W5: 14450356 | X5: 14575659 | Y5: 15378044 | Z5: 15905540 | AA5: 16917328 | AB5: 21283092 | AC5: 24185491 | AD5: 24066273 | AE5: 23996868 | AF5: 24647401 | AG5: 27435046 | AH5: 29113530 | AI5: 28550655 | AJ5: 31338196 | AK5: 32016663 | AL5: 30980609 | AM5: 32763027 | AN5: 28814425 | AO5: 35738973 | AP5: 36289300 | AQ5: 34313995 | AR5: 39658233 | AS5: 42853248 | AT5: 41459320 | AU5: 41745891 | AV5: 43453489 | AW5: 45784675 | AX5: 44727479 | AY5: 44983298 | AZ5: 47131654 | BA5: 48708311 | BB5: 48171958 | BC5: 48258163 | BD5: 50933328 | BE5: 53533091 | BF5: ='EMTS-CARB Forecast'!$M14 -> 44727479 | BG5: ='EMTS-CARB Forecast'!$M11 -> 41745891 | BH5: ='EMTS-CARB Forecast'!$M12 -> 43453489 | BI5: ='EMTS-CARB Forecast'!$M13 -> 45784675 | BJ5: ='EMTS-CARB Forecast'!$M14 -> 44727479 | BK5: ='EMTS-CARB Forecast'!$M11 -> 41745891 | BL5: ='EMTS-CARB Forecast'!$M12 -> 43453489 | BM5: ='EMTS-CARB Forecast'!$M13 -> 45784675 | BN5: ='EMTS-CARB Forecast'!$M14 -> 44727479 | BO5: ='EMTS-CARB Forecast'!$M11 -> 41745891 | BP5: ='EMTS-CARB Forecast'!$M12 -> 43453489 | BQ5: ='EMTS-CARB Forecast'!$M13 -> 45784675 | BR5: ='EMTS-CARB Forecast'!$M14 -> 44727479 | BS5: ='EMTS-CARB Forecast'!$M11 -> 41745891 | BT5: ='EMTS-CARB Forecast'!$M12 -> 43453489 | BU5: ='EMTS-CARB Forecast'!$M13 -> 45784675 | BV5: ='EMTS-CARB Forecast'!$M14 -> 44727479 | BW5: ='EMTS-CARB Forecast'!$M11 -> 41745891 | BX5: ='EMTS-CARB Forecast'!$M12 -> 43453489 | BY5: ='EMTS-CARB Forecast'!$M13 -> 45784675 | BZ5: ='EMTS-CARB Forecast'!$M14 -> 44727479 | CA5: ='EMTS-CARB Forecast'!$M11 -> 41745891 | CB5: ='EMTS-CARB Forecast'!$M12 -> 43453489 | CC5: ='EMTS-CARB Forecast'!$M13 -> 45784675 | CD5: ='EMTS-CARB Forecast'!$M14 -> 44727479 | CE5: ='EMTS-CARB Forecast'!$M11 -> 41745891 | CF5: ='EMTS-CARB Forecast'!$M12 -> 43453489 | CG5: ='EMTS-CARB Forecast'!$M13 -> 45784675 | CH5: ='EMTS-CARB Forecast'!$M14 -> 44727479 | CI5: ='EMTS-CARB Forecast'!$M11 -> 41745891 | CJ5: ='EMTS-CARB Forecast'!$M12 -> 43453489 | CK5: ='EMTS-CARB Forecast'!$M13 -> 45784675 | CL5: ='EMTS-CARB Forecast'!$M14 -> 44727479 | CM5: ='EMTS-CARB Forecast'!$M11 -> 41745891 | CN5: ='EMTS-CARB Forecast'!$M12 -> 43453489 | CO5: ='EMTS-CARB Forecast'!$M13 -> 45784675 | CP5: ='EMTS-CARB Forecast'!$M14 -> 44727479 | CQ5: ='EMTS-CARB Forecast'!$M11 -> 41745891 | CR5: ='EMTS-CARB Forecast'!$M12 -> 43453489 | CS5: ='EMTS-CARB Forecast'!$M13 -> 45784675 | CT5: ='EMTS-CARB Forecast'!$M14 -> 44727479 | CU5: ='EMTS-CARB Forecast'!$M11 -> 41745891 | CV5: ='EMTS-CARB Forecast'!$M12 -> 43453489 | CW5: ='EMTS-CARB Forecast'!$M13 -> 45784675 | CX5: ='EMTS-CARB Forecast'!$M14 -> 44727479 | CY5: ='EMTS-CARB Forecast'!$M11 -> 41745891 | CZ5: ='EMTS-CARB Forecast'!$M12 -> 43453489 | DA5: ='EMTS-CARB Forecast'!$M13 -> 45784675 | DB5: ='EMTS-CARB Forecast'!$M14 -> 44727479 | DC5: ='EMTS-CARB Forecast'!$M11 -> 41745891 | DD5: ='EMTS-CARB Forecast'!$M12 -> 43453489 | DE5: ='EMTS-CARB Forecast'!$M13 -> 45784675 | DF5: ='EMTS-CARB Forecast'!$M14 -> 44727479 | DG5: ='EMTS-CARB Forecast'!$M11 -> 41745891 | DH5: ='EMTS-CARB Forecast'!$M12 -> 43453489 | DI5: ='EMTS-CARB Forecast'!$M13 -> 45784675 | DJ5: ='EMTS-CARB Forecast'!$M14 -> 44727479 | DK5: ='EMTS-CARB Forecast'!$M11 -> 41745891 | DL5: ='EMTS-CARB Forecast'!$M12 -> 43453489 | DM5: ='EMTS-CARB Forecast'!$M13 -> 45784675 | DN5: ='EMTS-CARB Forecast'!$M14 -> 44727479 | DO5: ='EMTS-CARB Forecast'!$M11 -> 41745891 | DP5: ='EMTS-CARB Forecast'!$M12 -> 43453489 | DQ5: ='EMTS-CARB Forecast'!$M13 -> 45784675 | DR5: ='EMTS-CARB Forecast'!$M14 -> 44727479 | DS5: ='EMTS-CARB Forecast'!$M11 -> 41745891 | DT5: ='EMTS-CARB Forecast'!$M12 -> 43453489 | DU5: ='EMTS-CARB Forecast'!$M13 -> 45784675 | DV5: ='EMTS-CARB Forecast'!$M14 -> 44727479 | DW5: ='EMTS-CARB Forecast'!$M11 -> 41745891 | DX5: ='EMTS-CARB Forecast'!$M12 -> 43453489 | DY5: ='EMTS-CARB Forecast'!$M13 -> 45784675 | DZ5: ='EMTS-CARB Forecast'!$M13 -> 45784675 | EA5: ='EMTS-CARB Forecast'!$M11 -> 41745891 | EB5: ='EMTS-CARB Forecast'!$M12 -> 43453489 | EC5: ='EMTS-CARB Forecast'!$M13 -> 45784675 | ED5: ='EMTS-CARB Forecast'!$M13 -> 45784675 | EE5: ='EMTS-CARB Forecast'!$M11 -> 41745891 | EF5: ='EMTS-CARB Forecast'!$M12 -> 43453489 | EG5: ='EMTS-CARB Forecast'!$M13 -> 45784675 | EH5: ='EMTS-CARB Forecast'!$M13 -> 45784675 | EI5: ='EMTS-CARB Forecast'!$M11 -> 41745891 | EJ5: ='EMTS-CARB Forecast'!$M12 -> 43453489 | EK5: ='EMTS-CARB Forecast'!$M13 -> 45784675 | EL5: ='EMTS-CARB Forecast'!$M13 -> 45784675 | EM5: ='EMTS-CARB Forecast'!$M11 -> 41745891 | EN5: ='EMTS-CARB Forecast'!$M12 -> 43453489 | EO5: ='EMTS-CARB Forecast'!$M13 -> 45784675 | EP5: ='EMTS-CARB Forecast'!$M13 -> 45784675 | EQ5: ='EMTS-CARB Forecast'!$M11 -> 41745891 | ER5: ='EMTS-CARB Forecast'!$M12 -> 43453489 | ES5: ='EMTS-CARB Forecast'!$M13 -> 45784675 | ET5: ='EMTS-CARB Forecast'!$M13 -> 45784675 | EU5: ='EMTS-CARB Forecast'!$M11 -> 41745891 | EV5: ='EMTS-CARB Forecast'!$M12 -> 43453489 | EW5: ='EMTS-CARB Forecast'!$M13 -> 45784675 | EX5: ='EMTS-CARB Forecast'!$M13 -> 45784675 | EY5: ='EMTS-CARB Forecast'!$M11 -> 41745891 | EZ5: ='EMTS-CARB Forecast'!$M12 -> 43453489 | FA5: ='EMTS-CARB Forecast'!$M13 -> 45784675 | FB5: ='EMTS-CARB Forecast'!$M13 -> 45784675 | FC5: ='EMTS-CARB Forecast'!$M11 -> 41745891 | FD5: ='EMTS-CARB Forecast'!$M12 -> 43453489 | FE5: ='EMTS-CARB Forecast'!$M13 -> 45784675 | FF5: ='EMTS-CARB Forecast'!$M13 -> 45784675 | FG5: ='EMTS-CARB Forecast'!$M11 -> 41745891 | FH5: ='EMTS-CARB Forecast'!$M12 -> 43453489 | FI5: ='EMTS-CARB Forecast'!$M13 -> 45784675 | FJ5: ='EMTS-CARB Forecast'!$M13 -> 45784675
A6: Bio-LNG | B6: dge | C6: 236835 | D6: 328532 | E6: 530962 | F6: 478928 | G6: 468876 | H6: 453202 | I6: 384063 | J6: 287824 | K6: 439275 | L6: 612128 | M6: 2546125 | N6: 1052125 | O6: 1639132 | P6: 1064074 | Q6: 4714630 | R6: 5841140 | S6: 5277303 | T6: 6367592 | U6: 7259890 | V6: 8307511 | W6: 6595776 | X6: 7661496 | Y6: 7645395 | Z6: 7035914 | AA6: 6712351 | AB6: 6146649 | AC6: 3943161 | AD6: 3529130 | AE6: 3637857 | AF6: 3678466 | AG6: 3844316 | AH6: 3532362 | AI6: 3621779 | AJ6: 3620430 | AK6: 4599876 | AL6: 4554189 | AM6: 4573936 | AN6: 4396610 | AO6: 4566252 | AP6: 4446816 | AQ6: 4123135 | AR6: 4146664 | AS6: 4033042 | AT6: 3968462 | AU6: 3668607 | AV6: 3893434 | AW6: 3960769 | AX6: 3224680 | AY6: 3488791 | AZ6: 3664461 | BA6: 3463640 | BB6: 3490514 | BC6: 3416751 | BD6: 3233384 | BE6: 3409504 | BF6: ='EMTS-CARB Forecast'!$M29 -> 3224680 | BG6: ='EMTS-CARB Forecast'!$M26 -> 3668607 | BH6: ='EMTS-CARB Forecast'!$M27 -> 3893434 | BI6: ='EMTS-CARB Forecast'!$M28 -> 3960769 | BJ6: ='EMTS-CARB Forecast'!$M29 -> 3224680 | BK6: ='EMTS-CARB Forecast'!$M26 -> 3668607 | BL6: ='EMTS-CARB Forecast'!$M27 -> 3893434 | BM6: ='EMTS-CARB Forecast'!$M28 -> 3960769 | BN6: ='EMTS-CARB Forecast'!$M29 -> 3224680 | BO6: ='EMTS-CARB Forecast'!$M26 -> 3668607 | BP6: ='EMTS-CARB Forecast'!$M27 -> 3893434 | BQ6: ='EMTS-CARB Forecast'!$M28 -> 3960769 | BR6: ='EMTS-CARB Forecast'!$M29 -> 3224680 | BS6: ='EMTS-CARB Forecast'!$M26 -> 3668607 | BT6: ='EMTS-CARB Forecast'!$M27 -> 3893434 | BU6: ='EMTS-CARB Forecast'!$M28 -> 3960769 | BV6: ='EMTS-CARB Forecast'!$M29 -> 3224680 | BW6: ='EMTS-CARB Forecast'!$M26 -> 3668607 | BX6: ='EMTS-CARB Forecast'!$M27 -> 3893434 | BY6: ='EMTS-CARB Forecast'!$M28 -> 3960769 | BZ6: ='EMTS-CARB Forecast'!$M29 -> 3224680 | CA6: ='EMTS-CARB Forecast'!$M26 -> 3668607 | CB6: ='EMTS-CARB Forecast'!$M27 -> 3893434 | CC6: ='EMTS-CARB Forecast'!$M28 -> 3960769 | CD6: ='EMTS-CARB Forecast'!$M29 -> 3224680 | CE6: ='EMTS-CARB Forecast'!$M26 -> 3668607 | CF6: ='EMTS-CARB Forecast'!$M27 -> 3893434 | CG6: ='EMTS-CARB Forecast'!$M28 -> 3960769 | CH6: ='EMTS-CARB Forecast'!$M29 -> 3224680 | CI6: ='EMTS-CARB Forecast'!$M26 -> 3668607 | CJ6: ='EMTS-CARB Forecast'!$M27 -> 3893434 | CK6: ='EMTS-CARB Forecast'!$M28 -> 3960769 | CL6: ='EMTS-CARB Forecast'!$M29 -> 3224680 | CM6: ='EMTS-CARB Forecast'!$M26 -> 3668607 | CN6: ='EMTS-CARB Forecast'!$M27 -> 3893434 | CO6: ='EMTS-CARB Forecast'!$M28 -> 3960769 | CP6: ='EMTS-CARB Forecast'!$M29 -> 3224680 | CQ6: ='EMTS-CARB Forecast'!$M26 -> 3668607 | CR6: ='EMTS-CARB Forecast'!$M27 -> 3893434 | CS6: ='EMTS-CARB Forecast'!$M28 -> 3960769 | CT6: ='EMTS-CARB Forecast'!$M29 -> 3224680 | CU6: ='EMTS-CARB Forecast'!$M26 -> 3668607 | CV6: ='EMTS-CARB Forecast'!$M27 -> 3893434 | CW6: ='EMTS-CARB Forecast'!$M28 -> 3960769 | CX6: ='EMTS-CARB Forecast'!$M29 -> 3224680 | CY6: ='EMTS-CARB Forecast'!$M26 -> 3668607 | CZ6: ='EMTS-CARB Forecast'!$M27 -> 3893434 | DA6: ='EMTS-CARB Forecast'!$M28 -> 3960769 | DB6: ='EMTS-CARB Forecast'!$M29 -> 3224680 | DC6: ='EMTS-CARB Forecast'!$M26 -> 3668607 | DD6: ='EMTS-CARB Forecast'!$M27 -> 3893434 | DE6: ='EMTS-CARB Forecast'!$M28 -> 3960769 | DF6: ='EMTS-CARB Forecast'!$M29 -> 3224680 | DG6: ='EMTS-CARB Forecast'!$M26 -> 3668607 | DH6: ='EMTS-CARB Forecast'!$M27 -> 3893434 | DI6: ='EMTS-CARB Forecast'!$M28 -> 3960769 | DJ6: ='EMTS-CARB Forecast'!$M29 -> 3224680 | DK6: ='EMTS-CARB Forecast'!$M26 -> 3668607 | DL6: ='EMTS-CARB Forecast'!$M27 -> 3893434 | DM6: ='EMTS-CARB Forecast'!$M28 -> 3960769 | DN6: ='EMTS-CARB Forecast'!$M29 -> 3224680 | DO6: ='EMTS-CARB Forecast'!$M26 -> 3668607 | DP6: ='EMTS-CARB Forecast'!$M27 -> 3893434 | DQ6: ='EMTS-CARB Forecast'!$M28 -> 3960769 | DR6: ='EMTS-CARB Forecast'!$M29 -> 3224680 | DS6: ='EMTS-CARB Forecast'!$M26 -> 3668607 | DT6: ='EMTS-CARB Forecast'!$M27 -> 3893434 | DU6: ='EMTS-CARB Forecast'!$M28 -> 3960769 | DV6: ='EMTS-CARB Forecast'!$M29 -> 3224680 | DW6: ='EMTS-CARB Forecast'!$M26 -> 3668607 | DX6: ='EMTS-CARB Forecast'!$M27 -> 3893434 | DY6: ='EMTS-CARB Forecast'!$M28 -> 3960769 | DZ6: ='EMTS-CARB Forecast'!$M28 -> 3960769 | EA6: ='EMTS-CARB Forecast'!$M26 -> 3668607 | EB6: ='EMTS-CARB Forecast'!$M27 -> 3893434 | EC6: ='EMTS-CARB Forecast'!$M28 -> 3960769 | ED6: ='EMTS-CARB Forecast'!$M28 -> 3960769 | EE6: ='EMTS-CARB Forecast'!$M26 -> 3668607 | EF6: ='EMTS-CARB Forecast'!$M27 -> 3893434 | EG6: ='EMTS-CARB Forecast'!$M28 -> 3960769 | EH6: ='EMTS-CARB Forecast'!$M28 -> 3960769 | EI6: ='EMTS-CARB Forecast'!$M26 -> 3668607 | EJ6: ='EMTS-CARB Forecast'!$M27 -> 3893434 | EK6: ='EMTS-CARB Forecast'!$M28 -> 3960769 | EL6: ='EMTS-CARB Forecast'!$M28 -> 3960769 | EM6: ='EMTS-CARB Forecast'!$M26 -> 3668607 | EN6: ='EMTS-CARB Forecast'!$M27 -> 3893434 | EO6: ='EMTS-CARB Forecast'!$M28 -> 3960769 | EP6: ='EMTS-CARB Forecast'!$M28 -> 3960769 | EQ6: ='EMTS-CARB Forecast'!$M26 -> 3668607 | ER6: ='EMTS-CARB Forecast'!$M27 -> 3893434 | ES6: ='EMTS-CARB Forecast'!$M28 -> 3960769 | ET6: ='EMTS-CARB Forecast'!$M28 -> 3960769 | EU6: ='EMTS-CARB Forecast'!$M26 -> 3668607 | EV6: ='EMTS-CARB Forecast'!$M27 -> 3893434 | EW6: ='EMTS-CARB Forecast'!$M28 -> 3960769 | EX6: ='EMTS-CARB Forecast'!$M28 -> 3960769 | EY6: ='EMTS-CARB Forecast'!$M26 -> 3668607 | EZ6: ='EMTS-CARB Forecast'!$M27 -> 3893434 | FA6: ='EMTS-CARB Forecast'!$M28 -> 3960769 | FB6: ='EMTS-CARB Forecast'!$M28 -> 3960769 | FC6: ='EMTS-CARB Forecast'!$M26 -> 3668607 | FD6: ='EMTS-CARB Forecast'!$M27 -> 3893434 | FE6: ='EMTS-CARB Forecast'!$M28 -> 3960769 | FF6: ='EMTS-CARB Forecast'!$M28 -> 3960769 | FG6: ='EMTS-CARB Forecast'!$M26 -> 3668607 | FH6: ='EMTS-CARB Forecast'!$M27 -> 3893434 | FI6: ='EMTS-CARB Forecast'!$M28 -> 3960769 | FJ6: ='EMTS-CARB Forecast'!$M28 -> 3960769
A7: Fossil CNG | B7: dge | C7: 12882107 | D7: 13284682 | E7: 13100333 | F7: 12816759 | G7: 12797724 | H7: 13185688 | I7: 15819989 | J7: 15375874 | K7: 15442500 | L7: 15802030 | M7: 14502449 | N7: 14939119 | O7: 16653725 | P7: 20181754 | Q7: 19709585 | R7: 19332234 | S7: 18221747 | T7: 15299622 | U7: 15624093 | V7: 15225821 | W7: 13254354 | X7: 13751707 | Y7: 13280307 | Z7: 13057045 | AA7: 13579389 | AB7: 12297213 | AC7: 12146075 | AD7: 11480263 | AE7: 12387493 | AF7: 13341294 | AG7: 11894748 | AH7: 9083378 | AI7: 9695036 | AJ7: 9532882 | AK7: 10747480 | AL7: 9382934 | AM7: 5852559 | AN7: 3868435 | AO7: 2117873 | AP7: 754474 | AQ7: 747658 | AR7: 937198 | AS7: 896174 | AT7: 1542813 | AU7: 1172580 | AV7: 1762066 | AW7: 1583080 | AX7: 1491237 | AY7: 1453772 | AZ7: 1727616 | BA7: 2476243 | BB7: 1136609 | BC7: 669303 | BD7: 554319 | BE7: 512824 | BF7: =_xlfn.FORECAST.ETS(BF47,P7:BE7,P47:BE47)+500000 -> 505340.14 | BG7: =_xlfn.FORECAST.ETS(BG47,Q7:BF7,Q47:BF47)+500000 -> 514144.09 | BH7: =_xlfn.FORECAST.ETS(BH47,R7:BG7,R47:BG47)+500000 -> 540808.7 | BI7: =_xlfn.FORECAST.ETS(BI47,S7:BH7,S47:BH47)+400000 -> 487218.57 | BJ7: =_xlfn.FORECAST.ETS(BJ47,T7:BI7,T47:BI47)+400000 -> 452371.74 | BK7: =_xlfn.FORECAST.ETS(BK47,U7:BJ7,U47:BJ47)+400000 -> 691040.85 | BL7: =_xlfn.FORECAST.ETS(BL47,V7:BK7,V47:BK47)+400000 -> 968972.32 | BM7: =_xlfn.FORECAST.ETS(BM47,W7:BL7,W47:BL47)+400000 -> 978700.48 | BN7: =_xlfn.FORECAST.ETS(BN47,X7:BM7,X47:BM47)+400000 -> 1001507.6 | BO7: =_xlfn.FORECAST.ETS(BO47,Y7:BN7,Y47:BN47)+400000 -> 1041191.8 | BP7: =_xlfn.FORECAST.ETS(BP47,Z7:BO7,Z47:BO47)+400000 -> 1098308.7 | ... BS7: =_xlfn.FORECAST.ETS(BS47,AC7:BR7,AC47:BR47)+400000 -> 1392529.8 | BT7: =_xlfn.FORECAST.ETS(BT47,AD7:BS7,AD47:BS47)+300000 -> 1434389.1 | BU7: =_xlfn.FORECAST.ETS(BU47,AE7:BT7,AE47:BT47)+300000 -> 1498176.7 | BV7: =_xlfn.FORECAST.ETS(BV47,AF7:BU7,AF47:BU47)+200000 -> 1488893.7 | BW7: =_xlfn.FORECAST.ETS(BW47,AG7:BV7,AG47:BV47)+200000 -> 1511597.4 | BX7: =_xlfn.FORECAST.ETS(BX47,AH7:BW7,AH47:BW47)+200000 -> 1563243.7 | BY7: =_xlfn.FORECAST.ETS(BY47,AI7:BX7,AI47:BX47)+200000 -> 1635891.3 | BZ7: =_xlfn.FORECAST.ETS(BZ47,AJ7:BY7,AJ47:BY47)+100000 -> 1633131.3 | CA7: =_xlfn.FORECAST.ETS(CA47,AK7:BZ7,AK47:BZ47) -> 1555695.8 | CB7: =_xlfn.FORECAST.ETS(CB47,AL7:CA7,AL47:CA47) -> 1508839.8 | CC7: =_xlfn.FORECAST.ETS(CC47,AM7:CB7,AM47:CB47) -> 1489142.7 | CD7: =_xlfn.FORECAST.ETS(CD47,AN7:CC7,AN47:CC47) -> 1485514.2 | CE7: =_xlfn.FORECAST.ETS(CE47,AO7:CD7,AO47:CD47) -> 1492006.9 | CF7: =_xlfn.FORECAST.ETS(CF47,AP7:CE7,AP47:CE47) -> 1505559.5 | CG7: =_xlfn.FORECAST.ETS(CG47,AQ7:CF7,AQ47:CF47) -> 1515810.5 | CH7: =_xlfn.FORECAST.ETS(CH47,AR7:CG7,AR47:CG47) -> 1525188.9 | ... FJ7: =_xlfn.FORECAST.ETS(FJ47,DT7:FI7,DT47:FI47) -> 2703389.3
A8: Fossil LNG | B8: dge | C8: 4873272 | D8: 5280822 | E8: 5590548 | F8: 5575898 | G8: 5700917 | H8: 6766131 | I8: 7146246 | J8: 7770974 | K8: 9049261 | L8: 7133604 | M8: 5511333 | N8: 6737719 | O8: 6364147 | P8: 7378353 | Q8: 4195237 | R8: 2980243 | S8: 3242037 | T8: 2272593 | U8: 1516622 | V8: 496127 | W8: 826157 | X8: 701112 | Y8: 668756 | Z8: 696347 | AA8: 426898 | AB8: 75136 | AC8: 422474 | AD8: 616215 | AE8: 357360 | AF8: 373106 | AG8: 310021 | AH8: 416933 | AI8: 301992 | AJ8: 561969 | AK8: 190112 | AL8: 256572 | AM8: 28243 | AN8: 0 | AO8: 0 | AP8: 18901 | AQ8: 0 | AR8: 0 | AS8: 0 | AT8: 0 | AU8: 185544 | AV8: 126282 | AW8: 159800 | AX8: 510556 | AY8: 5 | AZ8: 9 | BA8: 10 | BB8: 14 | BC8: 6687 | BD8: 0 | BE8: =IF(_xlfn.FORECAST.ETS(BE$47,O8:BD8,O$47:BD$47)<0,0,_xlfn.FORECAST.ETS(BE$47,O8:BD8,O$47:BD$47)) -> 0 | BF8: =IF(_xlfn.FORECAST.ETS(BF$47,P8:BE8,P$47:BE$47)<0,0,_xlfn.FORECAST.ETS(BF$47,P8:BE8,P$47:BE$47)) -> 0 | BG8: =IF(_xlfn.FORECAST.ETS(BG$47,Q8:BF8,Q$47:BF$47)<0,0,_xlfn.FORECAST.ETS(BG$47,Q8:BF8,Q$47:BF$47)) -> 0 | BH8: =IF(_xlfn.FORECAST.ETS(BH$47,R8:BG8,R$47:BG$47)<0,0,_xlfn.FORECAST.ETS(BH$47,R8:BG8,R$47:BG$47)) -> 0 | BI8: =IF(_xlfn.FORECAST.ETS(BI$47,S8:BH8,S$47:BH$47)<0,0,_xlfn.FORECAST.ETS(BI$47,S8:BH8,S$47:BH$47)) -> 0 | BJ8: =IF(_xlfn.FORECAST.ETS(BJ$47,T8:BI8,T$47:BI$47)<0,0,_xlfn.FORECAST.ETS(BJ$47,T8:BI8,T$47:BI$47)) -> 0 | BK8: =IF(_xlfn.FORECAST.ETS(BK$47,U8:BJ8,U$47:BJ$47)<0,0,_xlfn.FORECAST.ETS(BK$47,U8:BJ8,U$47:BJ$47)) -> 0 | BL8: =IF(_xlfn.FORECAST.ETS(BL$47,V8:BK8,V$47:BK$47)<0,0,_xlfn.FORECAST.ETS(BL$47,V8:BK8,V$47:BK$47)) -> 0 | ... FJ8: =IF(_xlfn.FORECAST.ETS(FJ$47,DT8:FI8,DT$47:FI$47)<0,0,_xlfn.FORECAST.ETS(FJ$47,DT8:FI8,DT$47:FI$47)) -> 249219.94
A9: Hydrogen | B9: gge | C9: 0 | D9: 0 | E9: 0 | F9: 0 | G9: 0 | H9: 0 | I9: 0 | J9: 0 | K9: 0 | L9: 0 | M9: 0 | N9: 0 | O9: 0 | P9: 0 | Q9: 0 | R9: 0 | S9: 0 | T9: 0 | U9: 2364 | V9: 1113 | W9: 1519 | X9: 1255 | Y9: 41 | Z9: 88 | AA9: 43492 | AB9: 63903 | AC9: 76453 | AD9: 84347 | AE9: 113659 | AF9: 133239 | AG9: 142747 | AH9: 169048 | AI9: 238089 | AJ9: 277324 | AK9: 328143 | AL9: 353700 | AM9: 329375 | AN9: 244951 | AO9: 355412 | AP9: 399905 | AQ9: 363821 | AR9: 496037 | AS9: 505765 | AT9: 565849 | AU9: 599197 | AV9: 754006 | AW9: 778336 | AX9: 787611 | AY9: 711810 | AZ9: 768618 | BA9: 742122 | BB9: 691559 | BC9: 673609 | BD9: 677824 | BE9: 615517 | BF9: =IF(_xlfn.FORECAST.ETS(BF$47,P9:BE9,P$47:BE$47)<0,0,_xlfn.FORECAST.ETS(BF$47,P9:BE9,P$47:BE$47)) -> 646118.72 | BG9: =IF(_xlfn.FORECAST.ETS(BG$47,Q9:BF9,Q$47:BF$47)<0,0,_xlfn.FORECAST.ETS(BG$47,Q9:BF9,Q$47:BF$47)) -> 752855.25 | BH9: =IF(_xlfn.FORECAST.ETS(BH$47,R9:BG9,R$47:BG$47)<0,0,_xlfn.FORECAST.ETS(BH$47,R9:BG9,R$47:BG$47)) -> 734366.65 | BI9: =IF(_xlfn.FORECAST.ETS(BI$47,S9:BH9,S$47:BH$47)<0,0,_xlfn.FORECAST.ETS(BI$47,S9:BH9,S$47:BH$47)) -> 778068.88 | BJ9: =IF(_xlfn.FORECAST.ETS(BJ$47,T9:BI9,T$47:BI$47)<0,0,_xlfn.FORECAST.ETS(BJ$47,T9:BI9,T$47:BI$47)) -> 808042.12 | BK9: =IF(_xlfn.FORECAST.ETS(BK$47,U9:BJ9,U$47:BJ$47)<0,0,_xlfn.FORECAST.ETS(BK$47,U9:BJ9,U$47:BJ$47)) -> 871288.04 | BL9: =IF(_xlfn.FORECAST.ETS(BL$47,V9:BK9,V$47:BK$47)<0,0,_xlfn.FORECAST.ETS(BL$47,V9:BK9,V$47:BK$47)) -> 914699.33 | BM9: =IF(_xlfn.FORECAST.ETS(BM$47,W9:BL9,W$47:BL$47)<0,0,_xlfn.FORECAST.ETS(BM$47,W9:BL9,W$47:BL$47)) -> 939309.75 | ... FJ9: =IF(_xlfn.FORECAST.ETS(FJ$47,DT9:FI9,DT$47:FI$47)<0,0,_xlfn.FORECAST.ETS(FJ$47,DT9:FI9,DT$47:FI$47)) -> 3121335.7
A10: Electricity | B10: gge | C10: =C36 -> 21816 | D10: =D36 -> 62215 | E10: =E36 -> 119059 | F10: =F36 -> 171607 | G10: =G36 -> 220891 | H10: =H36 -> 271183 | I10: =I36 -> 355146 | J10: =J36 -> 468250 | ... AV10: =AV36 -> 53780109 | AW10: 56391807 | AX10: 62105823 | AY10: 58942175 | AZ10: 64379991 | BA10: 70631807 | BB10: 71798523 | BC10: =BC36 -> 73568495 | BD10: =BD36 -> 81038158 | BE10: =BE36 -> 85316361 | BF10: =BF36 -> 76236905 | BG10: =BG36 -> 79922135 | BH10: =BH36 -> 83769900 | BI10: =BI36 -> 87528166 | BJ10: =BJ36 -> 91617581 | ... FJ10: =FJ36 -> 5.3505529e+08
A11: Ethanol | B11: gal | C11: 355943296 | D11: 387851229 | E11: 388872431 | F11: 357487052 | G11: 370292343 | H11: 374917388 | I11: 366019124 | J11: 363269339 | K11: 368807852 | L11: 358046201 | M11: 389863889 | N11: 362161026 | O11: 350786119 | P11: 364681336 | Q11: 392531450 | R11: 376855202 | S11: 372469285 | T11: 390499794 | U11: 383972772 | V11: 352283939 | W11: 414527490 | X11: 397227736 | Y11: 404071329 | Z11: 381748251 | AA11: 376822538 | AB11: 401825385 | AC11: 418522596 | AD11: 377787880 | AE11: 380940912 | AF11: 386000352 | AG11: 433159405 | AH11: 400757236 | AI11: 355104114 | AJ11: 416323940 | AK11: 392894297 | AL11: 393077295 | AM11: 375148591 | AN11: 228754963 | AO11: 365721128 | AP11: 329435151 | AQ11: 285646782 | AR11: 402071258 | AS11: 379076451 | AT11: 354054243 | AU11: 350873873 | AV11: 366259568 | AW11: 383805193 | AX11: 355730406 | AY11: 347939242 | AZ11: 296481588 | BA11: 382422796 | BB11: 354633081 | BC11: 344225384 | BD11: 365945518 | BE11: 368259292 | BF11: ='EMTS-CARB Forecast'!$M44 -> 355730406 | BG11: ='EMTS-CARB Forecast'!$M41 -> 350873873 | BH11: ='EMTS-CARB Forecast'!$M42 -> 366259568 | BI11: ='EMTS-CARB Forecast'!$M43 -> 383805193 | BJ11: ='EMTS-CARB Forecast'!$M44 -> 355730406 | BK11: ='EMTS-CARB Forecast'!$M41 -> 350873873 | BL11: ='EMTS-CARB Forecast'!$M42 -> 366259568 | BM11: ='EMTS-CARB Forecast'!$M43 -> 383805193 | BN11: ='EMTS-CARB Forecast'!$M44 -> 355730406 | BO11: ='EMTS-CARB Forecast'!$M41 -> 350873873 | BP11: ='EMTS-CARB Forecast'!$M42 -> 366259568 | BQ11: ='EMTS-CARB Forecast'!$M43 -> 383805193 | BR11: ='EMTS-CARB Forecast'!$M44 -> 355730406 | BS11: ='EMTS-CARB Forecast'!$M41 -> 350873873 | BT11: ='EMTS-CARB Forecast'!$M42 -> 366259568 | BU11: ='EMTS-CARB Forecast'!$M43 -> 383805193 | BV11: ='EMTS-CARB Forecast'!$M44 -> 355730406 | BW11: ='EMTS-CARB Forecast'!$M41 -> 350873873 | BX11: ='EMTS-CARB Forecast'!$M42 -> 366259568 | BY11: ='EMTS-CARB Forecast'!$M43 -> 383805193 | BZ11: ='EMTS-CARB Forecast'!$M44 -> 355730406 | CA11: ='EMTS-CARB Forecast'!$M41 -> 350873873 | CB11: ='EMTS-CARB Forecast'!$M42 -> 366259568 | CC11: ='EMTS-CARB Forecast'!$M43 -> 383805193 | CD11: ='EMTS-CARB Forecast'!$M44 -> 355730406 | CE11: ='EMTS-CARB Forecast'!$M41 -> 350873873 | CF11: ='EMTS-CARB Forecast'!$M42 -> 366259568 | CG11: ='EMTS-CARB Forecast'!$M43 -> 383805193 | CH11: ='EMTS-CARB Forecast'!$M44 -> 355730406 | CI11: ='EMTS-CARB Forecast'!$M41 -> 350873873 | CJ11: ='EMTS-CARB Forecast'!$M42 -> 366259568 | CK11: ='EMTS-CARB Forecast'!$M43 -> 383805193 | CL11: ='EMTS-CARB Forecast'!$M44 -> 355730406 | CM11: ='EMTS-CARB Forecast'!$M41 -> 350873873 | CN11: ='EMTS-CARB Forecast'!$M42 -> 366259568 | CO11: ='EMTS-CARB Forecast'!$M43 -> 383805193 | CP11: ='EMTS-CARB Forecast'!$M44 -> 355730406 | CQ11: ='EMTS-CARB Forecast'!$M41 -> 350873873 | CR11: ='EMTS-CARB Forecast'!$M42 -> 366259568 | CS11: ='EMTS-CARB Forecast'!$M43 -> 383805193 | CT11: ='EMTS-CARB Forecast'!$M44 -> 355730406 | CU11: ='EMTS-CARB Forecast'!$M41 -> 350873873 | CV11: ='EMTS-CARB Forecast'!$M42 -> 366259568 | CW11: ='EMTS-CARB Forecast'!$M43 -> 383805193 | CX11: ='EMTS-CARB Forecast'!$M44 -> 355730406 | CY11: ='EMTS-CARB Forecast'!$M41 -> 350873873 | CZ11: ='EMTS-CARB Forecast'!$M42 -> 366259568 | DA11: ='EMTS-CARB Forecast'!$M43 -> 383805193 | DB11: ='EMTS-CARB Forecast'!$M44 -> 355730406 | DC11: ='EMTS-CARB Forecast'!$M41 -> 350873873 | DD11: ='EMTS-CARB Forecast'!$M42 -> 366259568 | DE11: ='EMTS-CARB Forecast'!$M43 -> 383805193 | DF11: ='EMTS-CARB Forecast'!$M44 -> 355730406 | DG11: ='EMTS-CARB Forecast'!$M41 -> 350873873 | DH11: ='EMTS-CARB Forecast'!$M42 -> 366259568 | DI11: ='EMTS-CARB Forecast'!$M43 -> 383805193 | DJ11: ='EMTS-CARB Forecast'!$M44 -> 355730406 | DK11: ='EMTS-CARB Forecast'!$M41 -> 350873873 | DL11: ='EMTS-CARB Forecast'!$M42 -> 366259568 | DM11: ='EMTS-CARB Forecast'!$M43 -> 383805193 | DN11: ='EMTS-CARB Forecast'!$M44 -> 355730406 | DO11: ='EMTS-CARB Forecast'!$M41 -> 350873873 | DP11: ='EMTS-CARB Forecast'!$M42 -> 366259568 | DQ11: ='EMTS-CARB Forecast'!$M43 -> 383805193 | DR11: ='EMTS-CARB Forecast'!$M44 -> 355730406 | DS11: ='EMTS-CARB Forecast'!$M41 -> 350873873 | DT11: ='EMTS-CARB Forecast'!$M42 -> 366259568 | DU11: ='EMTS-CARB Forecast'!$M43 -> 383805193 | DV11: ='EMTS-CARB Forecast'!$M44 -> 355730406 | DW11: ='EMTS-CARB Forecast'!$M41 -> 350873873 | DX11: ='EMTS-CARB Forecast'!$M42 -> 366259568 | DY11: ='EMTS-CARB Forecast'!$M43 -> 383805193 | DZ11: ='EMTS-CARB Forecast'!$M43 -> 383805193 | EA11: ='EMTS-CARB Forecast'!$M41 -> 350873873 | EB11: ='EMTS-CARB Forecast'!$M42 -> 366259568 | EC11: ='EMTS-CARB Forecast'!$M43 -> 383805193 | ED11: ='EMTS-CARB Forecast'!$M43 -> 383805193 | EE11: ='EMTS-CARB Forecast'!$M41 -> 350873873 | EF11: ='EMTS-CARB Forecast'!$M42 -> 366259568 | EG11: ='EMTS-CARB Forecast'!$M43 -> 383805193 | EH11: ='EMTS-CARB Forecast'!$M43 -> 383805193 | EI11: ='EMTS-CARB Forecast'!$M41 -> 350873873 | EJ11: ='EMTS-CARB Forecast'!$M42 -> 366259568 | EK11: ='EMTS-CARB Forecast'!$M43 -> 383805193 | EL11: ='EMTS-CARB Forecast'!$M43 -> 383805193 | EM11: ='EMTS-CARB Forecast'!$M41 -> 350873873 | EN11: ='EMTS-CARB Forecast'!$M42 -> 366259568 | EO11: ='EMTS-CARB Forecast'!$M43 -> 383805193 | EP11: ='EMTS-CARB Forecast'!$M43 -> 383805193 | EQ11: ='EMTS-CARB Forecast'!$M41 -> 350873873 | ER11: ='EMTS-CARB Forecast'!$M42 -> 366259568 | ES11: ='EMTS-CARB Forecast'!$M43 -> 383805193 | ET11: ='EMTS-CARB Forecast'!$M43 -> 383805193 | EU11: ='EMTS-CARB Forecast'!$M41 -> 350873873 | EV11: ='EMTS-CARB Forecast'!$M42 -> 366259568 | EW11: ='EMTS-CARB Forecast'!$M43 -> 383805193 | EX11: ='EMTS-CARB Forecast'!$M43 -> 383805193 | EY11: ='EMTS-CARB Forecast'!$M41 -> 350873873 | EZ11: ='EMTS-CARB Forecast'!$M42 -> 366259568 | FA11: ='EMTS-CARB Forecast'!$M43 -> 383805193 | FB11: ='EMTS-CARB Forecast'!$M43 -> 383805193 | FC11: ='EMTS-CARB Forecast'!$M41 -> 350873873 | FD11: ='EMTS-CARB Forecast'!$M42 -> 366259568 | FE11: ='EMTS-CARB Forecast'!$M43 -> 383805193 | FF11: ='EMTS-CARB Forecast'!$M43 -> 383805193 | FG11: ='EMTS-CARB Forecast'!$M41 -> 350873873 | FH11: ='EMTS-CARB Forecast'!$M42 -> 366259568 | FI11: ='EMTS-CARB Forecast'!$M43 -> 383805193 | FJ11: ='EMTS-CARB Forecast'!$M43 -> 383805193
A12: Biodiesel | B12: gal | C12: 1954349 | D12: 2623187 | E12: 3477614 | F12: 4482442 | G12: 5006202 | H12: 6502404 | I12: 4240695 | J12: 4226644 | K12: 5481532 | L12: 13975203 | M12: 13936349 | N12: 26508045 | O12: 16037416 | P12: 16122376 | Q12: 13880356 | R12: 20757948 | S12: 19632811 | T12: 28502517 | U12: 42889152 | V12: 35425955 | W12: 28882258 | X12: 35790526 | Y12: 45225506 | Z12: 53450453 | AA12: 38177310 | AB12: 37575247 | AC12: 50257498 | AD12: 43756532 | AE12: 36595945 | AF12: 40693700 | AG12: 49904077 | AH12: 57231365 | AI12: 41827876 | AJ12: 57413156 | AK12: 56880071 | AL12: 55445419 | AM12: 56349932 | AN12: 59271313 | AO12: 69710273 | AP12: 81113099 | AQ12: 61422026 | AR12: 78153595 | AS12: 77619602 | AT12: 72876457 | AU12: 69654714 | AV12: 68309582 | AW12: 72306900 | AX12: 70892771 | AY12: 68541019 | AZ12: 60275869 | BA12: 67129512 | BB12: 72940256 | BC12: 64404789 | BD12: 55754578 | BE12: 58423071 | BF12: ='EMTS-CARB Forecast'!$O59 -> 54434656 | BG12: ='EMTS-CARB Forecast'!$P56 -> 78891431 | BH12: ='EMTS-CARB Forecast'!$P57 -> 48998068 | BI12: ='EMTS-CARB Forecast'!$P58 -> 52553265 | BJ12: ='EMTS-CARB Forecast'!$P59 -> 57058040 | BK12: ='EMTS-CARB Forecast'!$Q56 -> 61120944 | BL12: ='EMTS-CARB Forecast'!$Q57 -> 51963504 | BM12: ='EMTS-CARB Forecast'!$Q58 -> 57303009 | BN12: ='EMTS-CARB Forecast'!$Q59 -> 68800426 | BO12: ='EMTS-CARB Forecast'!$R56 -> 65205969 | BP12: ='EMTS-CARB Forecast'!$R57 -> 49932352 | BQ12: ='EMTS-CARB Forecast'!$R58 -> 55531148 | BR12: ='EMTS-CARB Forecast'!$R59 -> 71347685 | BS12: ='EMTS-CARB Forecast'!$S56 -> 69218675 | BT12: ='EMTS-CARB Forecast'!$S57 -> 26680625 | BU12: ='EMTS-CARB Forecast'!$S58 -> 32050653 | BV12: ='EMTS-CARB Forecast'!$S59 -> 79235565 | BW12: ='EMTS-CARB Forecast'!$T56 -> 64986054 | BX12: ='EMTS-CARB Forecast'!$T57 -> 40727703 | BY12: ='EMTS-CARB Forecast'!$T58 -> 45884709 | BZ12: ='EMTS-CARB Forecast'!$T59 -> 70688920 | CA12: ='EMTS-CARB Forecast'!$U56 -> 63933862 | CB12: ='EMTS-CARB Forecast'!$U57 -> 43098929 | CC12: ='EMTS-CARB Forecast'!$U58 -> 48413287 | CD12: ='EMTS-CARB Forecast'!$U59 -> 83351574 | CE12: ='EMTS-CARB Forecast'!$V56 -> 61613427 | CF12: ='EMTS-CARB Forecast'!$V57 -> 46802554 | CG12: ='EMTS-CARB Forecast'!$V58 -> 48184918 | CH12: ='EMTS-CARB Forecast'!$V59 -> 78418645 | CI12: ='EMTS-CARB Forecast'!$W56 -> 62515031 | CJ12: ='EMTS-CARB Forecast'!$W57 -> 48433052 | CK12: ='EMTS-CARB Forecast'!$W58 -> 53331248 | CL12: ='EMTS-CARB Forecast'!$W59 -> 73398807 | CM12: ='EMTS-CARB Forecast'!$X56 -> 64994081 | CN12: ='EMTS-CARB Forecast'!$X57 -> 41830533 | CO12: ='EMTS-CARB Forecast'!$X58 -> 51734623 | CP12: ='EMTS-CARB Forecast'!$X59 -> 77573857 | CQ12: ='EMTS-CARB Forecast'!$Y56 -> 66525986 | CR12: ='EMTS-CARB Forecast'!$Y57 -> 40427168 | CS12: ='EMTS-CARB Forecast'!$Y58 -> 50006052 | CT12: ='EMTS-CARB Forecast'!$Y59 -> 78839880 | CU12: ='EMTS-CARB Forecast'!$Z56 -> 67344341 | CV12: ='EMTS-CARB Forecast'!$Z57 -> 36961093 | CW12: ='EMTS-CARB Forecast'!$Z58 -> 46278507 | CX12: ='EMTS-CARB Forecast'!$Z59 -> 80059581 | CY12: ='EMTS-CARB Forecast'!$AA56 -> 72914767 | CZ12: ='EMTS-CARB Forecast'!$AA57 -> 22332641 | DA12: ='EMTS-CARB Forecast'!$AA58 -> 42440328 | DB12: ='EMTS-CARB Forecast'!$AA59 -> 81265345 | DC12: ='EMTS-CARB Forecast'!$AB56 -> 81125387 | DD12: ='EMTS-CARB Forecast'!$AB57 -> 6989393.2 | DE12: ='EMTS-CARB Forecast'!$AB58 -> 37893611 | DF12: ='EMTS-CARB Forecast'!$AB59 -> 83018171 | DG12: ='EMTS-CARB Forecast'!$AC56 -> 83290336 | DH12: ='EMTS-CARB Forecast'!$AC57 -> 5217503 | DI12: ='EMTS-CARB Forecast'!$AC58 -> 38905883 | DJ12: ='EMTS-CARB Forecast'!$AC59 -> 84186465 | DK12: ='EMTS-CARB Forecast'!$AD56 -> 89481839 | DL12: ='EMTS-CARB Forecast'!$AD57 -> -5809937.3 | DM12: ='EMTS-CARB Forecast'!$AD58 -> 35788353 | DN12: ='EMTS-CARB Forecast'!$AD59 -> 86351066 | DO12: ='EMTS-CARB Forecast'!$AE56 -> 1.004549e+08 | DP12: ='EMTS-CARB Forecast'!$AE57 -> -27148927 | DQ12: ='EMTS-CARB Forecast'!$AE58 -> 30208261 | DR12: ='EMTS-CARB Forecast'!$AE59 -> 89229089 | DS12: ='EMTS-CARB Forecast'!$AE59 -> 89229089 | DT12: ='EMTS-CARB Forecast'!$AE59 -> 89229089 | DU12: ='EMTS-CARB Forecast'!$AE59 -> 89229089 | DV12: ='EMTS-CARB Forecast'!$AE59 -> 89229089 | DW12: ='EMTS-CARB Forecast'!$AE59 -> 89229089 | DX12: ='EMTS-CARB Forecast'!$AE59 -> 89229089 | DY12: ='EMTS-CARB Forecast'!$AE59 -> 89229089 | ... FJ12: ='EMTS-CARB Forecast'!$AE59 -> 89229089
A13: Renewable Diesel | B13: gal | C13: 325266 | D13: 356935 | E13: 462226 | F13: 659061 | G13: 712233 | H13: 723231 | I13: 843696 | J13: 6535747 | K13: 8182191 | L13: 23562582 | M13: 40409392 | N13: 44784857 | O13: 25871987 | P13: 26668165 | Q13: 36487197 | R13: 23817520 | S13: 27058770 | T13: 40776364 | U13: 51165569 | V13: 46155232 | W13: 43663408 | X13: 75711296 | Y13: 63846512 | Z13: 72449941 | AA13: 68700606 | AB13: 94202959 | AC13: 95429959 | AD13: 77130870 | AE13: 93949619 | AF13: 100488727 | AG13: 79736407 | AH13: 109391300 | AI13: 159583033 | AJ13: 160308777 | AK13: 133219894 | AL13: 164778486 | AM13: 130973476 | AN13: 151994539 | AO13: 140072718 | AP13: 165950498 | AQ13: 199089761 | AR13: 218785737 | AS13: 250252477 | AT13: 272878865 | AU13: 320411961 | AV13: 349244307 | AW13: 352249753 | AX13: 372139289 | AY13: 404778818 | AZ13: 481200270 | BA13: 531797418 | BB13: 547388851 | BC13: 518276102 | BD13: 603001119 | BE13: 652057695 | BF13: ='EMTS-CARB Forecast'!$O74 -> 5.7322041e+08 | BG13: ='EMTS-CARB Forecast'!$P71 -> 4.413921e+08 | BH13: ='EMTS-CARB Forecast'!$P72 -> 4.4804863e+08 | BI13: ='EMTS-CARB Forecast'!$P73 -> 5.8014271e+08 | BJ13: ='EMTS-CARB Forecast'!$P74 -> 5.3249525e+08 | BK13: ='EMTS-CARB Forecast'!$Q71 -> 4.352427e+08 | BL13: ='EMTS-CARB Forecast'!$Q72 -> 4.8168551e+08 | BM13: ='EMTS-CARB Forecast'!$Q73 -> 5.0147819e+08 | BN13: ='EMTS-CARB Forecast'!$Q74 -> 5.9357418e+08 | BO13: ='EMTS-CARB Forecast'!$R71 -> 4.6845238e+08 | BP13: ='EMTS-CARB Forecast'!$R72 -> 5.2003729e+08 | BQ13: ='EMTS-CARB Forecast'!$R73 -> 5.3934415e+08 | BR13: ='EMTS-CARB Forecast'!$R74 -> 6.4663458e+08 | BS13: ='EMTS-CARB Forecast'!$S71 -> 4.3749973e+08 | BT13: ='EMTS-CARB Forecast'!$S72 -> 4.7981696e+08 | BU13: ='EMTS-CARB Forecast'!$S73 -> 5.1923073e+08 | BV13: ='EMTS-CARB Forecast'!$S74 -> 6.1229948e+08 | BW13: ='EMTS-CARB Forecast'!$T71 -> 4.4165395e+08 | BX13: ='EMTS-CARB Forecast'!$T72 -> 4.8299392e+08 | BY13: ='EMTS-CARB Forecast'!$T73 -> 5.2255749e+08 | BZ13: ='EMTS-CARB Forecast'!$T74 -> 6.1504973e+08 | CA13: ='EMTS-CARB Forecast'!$U71 -> 4.5790599e+08 | CB13: ='EMTS-CARB Forecast'!$U72 -> 5.0267639e+08 | CC13: ='EMTS-CARB Forecast'!$U73 -> 5.2692367e+08 | CD13: ='EMTS-CARB Forecast'!$U74 -> 6.4647463e+08 | CE13: ='EMTS-CARB Forecast'!$V71 -> 4.8836337e+08 | CF13: ='EMTS-CARB Forecast'!$V72 -> 5.4325302e+08 | CG13: ='EMTS-CARB Forecast'!$V73 -> 5.1805559e+08 | CH13: ='EMTS-CARB Forecast'!$V74 -> 7.0007441e+08 | CI13: ='EMTS-CARB Forecast'!$W71 -> 5.6598749e+08 | CJ13: ='EMTS-CARB Forecast'!$W72 -> 6.3763877e+08 | CK13: ='EMTS-CARB Forecast'!$W73 -> 4.7645718e+08 | CL13: ='EMTS-CARB Forecast'!$W74 -> 8.292686e+08 | CM13: ='EMTS-CARB Forecast'!$X71 -> 5.6369421e+08 | CN13: ='EMTS-CARB Forecast'!$X72 -> 6.3437328e+08 | CO13: ='EMTS-CARB Forecast'!$X73 -> 4.8812794e+08 | CP13: ='EMTS-CARB Forecast'!$X74 -> 8.252197e+08 | CQ13: ='EMTS-CARB Forecast'!$Y71 -> 5.5042342e+08 | CR13: ='EMTS-CARB Forecast'!$Y72 -> 6.1772884e+08 | CS13: ='EMTS-CARB Forecast'!$Y73 -> 4.8971743e+08 | CT13: ='EMTS-CARB Forecast'!$Y74 -> 8.0217491e+08 | CU13: ='EMTS-CARB Forecast'!$Z71 -> 5.973559e+08 | CV13: ='EMTS-CARB Forecast'!$Z72 -> 6.8143726e+08 | CW13: ='EMTS-CARB Forecast'!$Z73 -> 4.754541e+08 | CX13: ='EMTS-CARB Forecast'!$Z74 -> 8.7691968e+08 | CY13: ='EMTS-CARB Forecast'!$AA71 -> 6.2624055e+08 | CZ13: ='EMTS-CARB Forecast'!$AA72 -> 7.1410047e+08 | DA13: ='EMTS-CARB Forecast'!$AA73 -> 4.6291557e+08 | DB13: ='EMTS-CARB Forecast'!$AA74 -> 9.2957283e+08 | DC13: ='EMTS-CARB Forecast'!$AB71 -> 6.983522e+08 | DD13: ='EMTS-CARB Forecast'!$AB72 -> 8.023914e+08 | DE13: ='EMTS-CARB Forecast'!$AB73 -> 4.3215102e+08 | DF13: ='EMTS-CARB Forecast'!$AB74 -> 1.051518e+09 | DG13: ='EMTS-CARB Forecast'!$AC71 -> 7.6203883e+08 | DH13: ='EMTS-CARB Forecast'!$AC72 -> 8.8033258e+08 | DI13: ='EMTS-CARB Forecast'!$AC73 -> 4.0623551e+08 | DJ13: ='EMTS-CARB Forecast'!$AC74 -> 1.1588562e+09 | DK13: ='EMTS-CARB Forecast'!$AD71 -> 7.6424799e+08 | DL13: ='EMTS-CARB Forecast'!$AD72 -> 8.8313298e+08 | DM13: ='EMTS-CARB Forecast'!$AD73 -> 4.060974e+08 | DN13: ='EMTS-CARB Forecast'!$AD74 -> 1.1620697e+09 | DO13: ='EMTS-CARB Forecast'!$AE71 -> 6.8221134e+08 | DP13: ='EMTS-CARB Forecast'!$AE72 -> 7.816615e+08 | DQ13: ='EMTS-CARB Forecast'!$AE73 -> 4.3887897e+08 | DR13: ='EMTS-CARB Forecast'!$AE74 -> 1.0225604e+09 | DS13: ='EMTS-CARB Forecast'!$AE74 -> 1.0225604e+09 | DT13: ='EMTS-CARB Forecast'!$AE74 -> 1.0225604e+09 | DU13: ='EMTS-CARB Forecast'!$AE74 -> 1.0225604e+09 | DV13: ='EMTS-CARB Forecast'!$AE74 -> 1.0225604e+09 | DW13: ='EMTS-CARB Forecast'!$AE74 -> 1.0225604e+09 | DX13: ='EMTS-CARB Forecast'!$AE74 -> 1.0225604e+09 | DY13: ='EMTS-CARB Forecast'!$AE74 -> 1.0225604e+09 | ... FJ13: ='EMTS-CARB Forecast'!$AE74 -> 1.0225604e+09
A14: Alternative Jet Fuel | B14: gal | C14: 0 | D14: 0 | E14: 0 | F14: 0 | G14: 0 | H14: 0 | I14: 0 | J14: 0 | K14: 0 | L14: 0 | M14: 0 | N14: 0 | O14: 0 | P14: 0 | Q14: 0 | R14: 0 | S14: 0 | T14: 0 | U14: 0 | V14: 0 | W14: 0 | X14: 0 | Y14: 0 | Z14: 0 | AA14: 0 | AB14: 0 | AC14: 0 | AD14: 0 | AE14: 0 | AF14: 0 | AG14: 0 | AH14: 0 | AI14: 0 | AJ14: 723542 | AK14: 693621 | AL14: 445027 | AM14: 284190 | AN14: 1315875 | AO14: 2388230 | AP14: 570655 | AQ14: 873456 | AR14: 2528070 | AS14: 1717347 | AT14: 3078857 | AU14: 993399 | AV14: 4923344 | AW14: 4078887 | AX14: 1608959 | AY14: 4696266 | AZ14: 6897301 | BA14: 4177769 | BB14: 7266054 | BC14: 10703076 | BD14: 23560446 | BE14: 24478866 | BF14: ='EMTS-CARB Forecast'!$O89 -> 3618110.2 | BG14: ='EMTS-CARB Forecast'!$P86 -> 23161222 | BH14: ='EMTS-CARB Forecast'!$P87 -> 32342158 | BI14: ='EMTS-CARB Forecast'!$P88 -> 42037598 | BJ14: ='EMTS-CARB Forecast'!$P89 -> 11506899 | BK14: ='EMTS-CARB Forecast'!$Q86 -> 1.0248113e+08 | BL14: ='EMTS-CARB Forecast'!$Q87 -> 1.1962998e+08 | BM14: ='EMTS-CARB Forecast'!$Q88 -> 1.6194491e+08 | BN14: ='EMTS-CARB Forecast'!$Q89 -> 39138483 | BO14: ='EMTS-CARB Forecast'!$R86 -> 2.6507927e+08 | BP14: ='EMTS-CARB Forecast'!$R87 -> 3.0811672e+08 | BQ14: ='EMTS-CARB Forecast'!$R88 -> 4.2027111e+08 | BR14: ='EMTS-CARB Forecast'!$R89 -> 97521340 | BS14: ='EMTS-CARB Forecast'!$S86 -> 3.4731688e+08 | BT14: ='EMTS-CARB Forecast'!$S87 -> 4.0295993e+08 | BU14: ='EMTS-CARB Forecast'!$S88 -> 5.4993682e+08 | BV14: ='EMTS-CARB Forecast'!$S89 -> 1.2701563e+08 | BW14: ='EMTS-CARB Forecast'!$T86 -> 4.1670043e+08 | BX14: ='EMTS-CARB Forecast'!$T87 -> 4.8325759e+08 | BY14: ='EMTS-CARB Forecast'!$T88 -> 6.5943255e+08 | BZ14: ='EMTS-CARB Forecast'!$T89 -> 1.5075503e+08 | CA14: ='EMTS-CARB Forecast'!$U86 -> 5.3205824e+08 | CB14: ='EMTS-CARB Forecast'!$U87 -> 6.1347424e+08 | CC14: ='EMTS-CARB Forecast'!$U88 -> 8.3729717e+08 | CD14: ='EMTS-CARB Forecast'!$U89 -> 1.9167224e+08 | CE14: ='EMTS-CARB Forecast'!$V86 -> 5.8554955e+08 | CF14: ='EMTS-CARB Forecast'!$V87 -> 6.7501126e+08 | CG14: ='EMTS-CARB Forecast'!$V88 -> 9.2165706e+08 | CH14: ='EMTS-CARB Forecast'!$V89 -> 2.1135229e+08 | CI14: ='EMTS-CARB Forecast'!$W86 -> 7.3362791e+08 | CJ14: ='EMTS-CARB Forecast'!$W87 -> 8.4403993e+08 | CK14: ='EMTS-CARB Forecast'!$W88 -> 1.1528293e+09 | CL14: ='EMTS-CARB Forecast'!$W89 -> 2.6374127e+08 | CM14: ='EMTS-CARB Forecast'!$X86 -> 7.8481618e+08 | CN14: ='EMTS-CARB Forecast'!$X87 -> 9.0366013e+08 | CO14: ='EMTS-CARB Forecast'!$X88 -> 1.2345417e+09 | CP14: ='EMTS-CARB Forecast'!$X89 -> 2.8219417e+08 | CQ14: ='EMTS-CARB Forecast'!$Y86 -> 8.61228e+08 | CR14: ='EMTS-CARB Forecast'!$Y87 -> 9.9061769e+08 | CS14: ='EMTS-CARB Forecast'!$Y88 -> 1.3532518e+09 | CT14: ='EMTS-CARB Forecast'!$Y89 -> 3.0906987e+08 | CU14: ='EMTS-CARB Forecast'!$Z86 -> 9.0288107e+08 | CV14: ='EMTS-CARB Forecast'!$Z87 -> 1.0380002e+09 | CW14: ='EMTS-CARB Forecast'!$Z88 -> 1.4180292e+09 | CX14: ='EMTS-CARB Forecast'!$Z89 -> 3.2393206e+08 | CY14: ='EMTS-CARB Forecast'!$AA86 -> 6.6230495e+08 | CZ14: ='EMTS-CARB Forecast'!$AA87 -> 7.6297966e+08 | DA14: ='EMTS-CARB Forecast'!$AA88 -> 1.0420632e+09 | DB14: ='EMTS-CARB Forecast'!$AA89 -> 2.3843734e+08 | DC14: ='EMTS-CARB Forecast'!$AB86 -> 6.8746669e+08 | DD14: ='EMTS-CARB Forecast'!$AB87 -> 7.9177829e+08 | DE14: ='EMTS-CARB Forecast'!$AB88 -> 1.0814088e+09 | DF14: ='EMTS-CARB Forecast'!$AB89 -> 2.4739806e+08 | DG14: ='EMTS-CARB Forecast'!$AC86 -> 7.2042955e+08 | DH14: ='EMTS-CARB Forecast'!$AC87 -> 8.2939169e+08 | DI14: ='EMTS-CARB Forecast'!$AC88 -> 1.132779e+09 | DJ14: ='EMTS-CARB Forecast'!$AC89 -> 2.5919306e+08 | DK14: ='EMTS-CARB Forecast'!$AD86 -> 7.1311654e+08 | DL14: ='EMTS-CARB Forecast'!$AD87 -> 8.2094926e+08 | DM14: ='EMTS-CARB Forecast'!$AD88 -> 1.1212632e+09 | DN14: ='EMTS-CARB Forecast'!$AD89 -> 2.5661165e+08 | DO14: ='EMTS-CARB Forecast'!$AE86 -> 7.8281661e+08 | DP14: ='EMTS-CARB Forecast'!$AE87 -> 9.0076074e+08 | DQ14: ='EMTS-CARB Forecast'!$AE88 -> 1.2304441e+09 | DR14: ='EMTS-CARB Forecast'!$AE89 -> 2.8141442e+08 | DS14: ='EMTS-CARB Forecast'!$AE89 -> 2.8141442e+08 | DT14: ='EMTS-CARB Forecast'!$AE89 -> 2.8141442e+08 | DU14: ='EMTS-CARB Forecast'!$AE89 -> 2.8141442e+08 | DV14: ='EMTS-CARB Forecast'!$AE89 -> 2.8141442e+08 | DW14: ='EMTS-CARB Forecast'!$AE89 -> 2.8141442e+08 | DX14: ='EMTS-CARB Forecast'!$AE89 -> 2.8141442e+08 | DY14: ='EMTS-CARB Forecast'!$AE89 -> 2.8141442e+08 | ... FJ14: ='EMTS-CARB Forecast'!$AE89 -> 2.8141442e+08
A15: Renewable Gasoline Blendstocks | B15: gal | C15: 0 | D15: 0 | E15: 0 | F15: 0 | G15: 0 | H15: 0 | I15: 0 | J15: 0 | K15: 0 | L15: 0 | M15: 0 | N15: 0 | O15: 0 | P15: 0 | Q15: 0 | R15: 0 | S15: 0 | T15: 0 | U15: 0 | V15: 0 | W15: 0 | X15: 0 | Y15: 0 | Z15: 0 | AA15: 0 | AB15: 0 | AC15: 0 | AD15: 0 | AE15: 0 | AF15: 0 | AG15: 0 | AH15: 170876 | AI15: 107933 | AJ15: 673134 | AK15: 175948 | AL15: 290046 | AM15: 352423 | AN15: 447211 | AO15: 815855 | AP15: 591098 | AQ15: 2427368 | AR15: 4222140 | AS15: 2350926 | AT15: 2107524 | AU15: 3145585 | AV15: 5145704 | AW15: 1682809 | AX15: 2190902 | AY15: 3650982 | AZ15: 7593875 | BA15: 13728337 | BB15: 6221948 | BC15: 7520995 | BD15: 7566471 | BE15: 5966715 | BF15: ='EMTS-CARB Forecast'!$O104 -> 11959058 | BG15: ='EMTS-CARB Forecast'!$P101 -> 12750384 | BH15: ='EMTS-CARB Forecast'!$P102 -> 9120227.9 | BI15: ='EMTS-CARB Forecast'!$P103 -> 11487555 | BJ15: ='EMTS-CARB Forecast'!$P104 -> 14262989 | BK15: ='EMTS-CARB Forecast'!$Q101 -> 10973809 | BL15: ='EMTS-CARB Forecast'!$Q102 -> 8942452.6 | BM15: ='EMTS-CARB Forecast'!$Q103 -> 12382825 | BN15: ='EMTS-CARB Forecast'!$Q104 -> 16253918 | BO15: ='EMTS-CARB Forecast'!$R101 -> 12088012 | BP15: ='EMTS-CARB Forecast'!$R102 -> 9877107.4 | BQ15: ='EMTS-CARB Forecast'!$R103 -> 13572267 | BR15: ='EMTS-CARB Forecast'!$R104 -> 17498359 | BS15: ='EMTS-CARB Forecast'!$S101 -> 12910551 | BT15: ='EMTS-CARB Forecast'!$S102 -> 10491115 | BU15: ='EMTS-CARB Forecast'!$S103 -> 13837771 | BV15: ='EMTS-CARB Forecast'!$S104 -> 18240983 | BW15: ='EMTS-CARB Forecast'!$T101 -> 12641950 | BX15: ='EMTS-CARB Forecast'!$T102 -> 10227137 | BY15: ='EMTS-CARB Forecast'!$T103 -> 14064596 | BZ15: ='EMTS-CARB Forecast'!$T104 -> 18296166 | CA15: ='EMTS-CARB Forecast'!$U101 -> 14033814 | CB15: ='EMTS-CARB Forecast'!$U102 -> 11222782 | CC15: ='EMTS-CARB Forecast'!$U103 -> 14836813 | CD15: ='EMTS-CARB Forecast'!$U104 -> 19319146 | CE15: ='EMTS-CARB Forecast'!$V101 -> 15320771 | CF15: ='EMTS-CARB Forecast'!$V102 -> 12557182 | CG15: ='EMTS-CARB Forecast'!$V103 -> 16499915 | CH15: ='EMTS-CARB Forecast'!$V104 -> 21734550 | CI15: ='EMTS-CARB Forecast'!$W101 -> 16309625 | CJ15: ='EMTS-CARB Forecast'!$W102 -> 13404041 | CK15: ='EMTS-CARB Forecast'!$W103 -> 17391415 | CL15: ='EMTS-CARB Forecast'!$W104 -> 22945108 | CM15: ='EMTS-CARB Forecast'!$X101 -> 17573790 | CN15: ='EMTS-CARB Forecast'!$X102 -> 14485302 | CO15: ='EMTS-CARB Forecast'!$X103 -> 18514715 | CP15: ='EMTS-CARB Forecast'!$X104 -> 24574673 | CQ15: ='EMTS-CARB Forecast'!$Y101 -> 19052931 | CR15: ='EMTS-CARB Forecast'!$Y102 -> 15784519 | CS15: ='EMTS-CARB Forecast'!$Y103 -> 19962262 | CT15: ='EMTS-CARB Forecast'!$Y104 -> 26580397 | CU15: ='EMTS-CARB Forecast'!$Z101 -> 19822429 | CV15: ='EMTS-CARB Forecast'!$Z102 -> 16431685 | CW15: ='EMTS-CARB Forecast'!$Z103 -> 20676091 | CX15: ='EMTS-CARB Forecast'!$Z104 -> 27562649 | CY15: ='EMTS-CARB Forecast'!$AA101 -> 18981899 | CZ15: ='EMTS-CARB Forecast'!$AA102 -> 15660829 | DA15: ='EMTS-CARB Forecast'!$AA103 -> 20049170 | DB15: ='EMTS-CARB Forecast'!$AA104 -> 26591635 | DC15: ='EMTS-CARB Forecast'!$AB101 -> 19286493 | DD15: ='EMTS-CARB Forecast'!$AB102 -> 15890314 | DE15: ='EMTS-CARB Forecast'!$AB103 -> 20379547 | DF15: ='EMTS-CARB Forecast'!$AB104 -> 27004518 | DG15: ='EMTS-CARB Forecast'!$AC101 -> 19322399 | DH15: ='EMTS-CARB Forecast'!$AC102 -> 15879043 | DI15: ='EMTS-CARB Forecast'!$AC103 -> 20475693 | DJ15: ='EMTS-CARB Forecast'!$AC104 -> 27083401 | DK15: ='EMTS-CARB Forecast'!$AD101 -> 19991834 | DL15: ='EMTS-CARB Forecast'!$AD102 -> 16447931 | DM15: ='EMTS-CARB Forecast'!$AD103 -> 21153642 | DN15: ='EMTS-CARB Forecast'!$AD104 -> 28002628 | DO15: ='EMTS-CARB Forecast'!$AE101 -> 22308820 | DP15: ='EMTS-CARB Forecast'!$AE102 -> 18514952 | DQ15: ='EMTS-CARB Forecast'!$AE103 -> 23299648 | DR15: ='EMTS-CARB Forecast'!$AE104 -> 31074991 | DS15: ='EMTS-CARB Forecast'!$AE104 -> 31074991 | DT15: ='EMTS-CARB Forecast'!$AE104 -> 31074991 | DU15: ='EMTS-CARB Forecast'!$AE104 -> 31074991 | DV15: ='EMTS-CARB Forecast'!$AE104 -> 31074991 | DW15: ='EMTS-CARB Forecast'!$AE104 -> 31074991 | DX15: ='EMTS-CARB Forecast'!$AE104 -> 31074991 | DY15: ='EMTS-CARB Forecast'!$AE104 -> 31074991 | ... FJ15: ='EMTS-CARB Forecast'!$AE104 -> 31074991
A16: Propane | B16: gal | C16: 0 | D16: 0 | E16: 0 | F16: 0 | G16: 0 | H16: 0 | I16: 0 | J16: 0 | K16: 0 | L16: 0 | M16: 0 | N16: 0 | O16: 0 | P16: 0 | Q16: 0 | R16: 0 | S16: 0 | T16: 0 | U16: 0 | V16: 0 | W16: 0 | X16: 0 | Y16: 0 | Z16: 0 | AA16: 0 | AB16: 0 | AC16: 0 | AD16: 0 | AE16: 0 | AF16: 0 | AG16: 0 | AH16: 0 | AI16: 190467 | AJ16: 960366 | AK16: 1724129 | AL16: 1798336 | AM16: 6001038 | AN16: 8440645 | AO16: 8606498 | AP16: 8556202 | AQ16: 9846959 | AR16: 9328671 | AS16: 10414518 | AT16: 10926053 | AU16: 10848871 | AV16: 10918742 | AW16: 10330318 | AX16: 10876569 | AY16: 9925855 | AZ16: 9481514 | BA16: 9739520 | BB16: 9710622 | BC16: 9352107 | BD16: 9024625 | BE16: 8286227 | BF16: ='EMTS-CARB Forecast'!$O119 -> 8492399.7 | BG16: ='EMTS-CARB Forecast'!$P116 -> 7349697.1 | BH16: ='EMTS-CARB Forecast'!$P117 -> 5041984.4 | BI16: ='EMTS-CARB Forecast'!$P118 -> 5146633 | BJ16: ='EMTS-CARB Forecast'!$P119 -> 4486518.6 | BK16: ='EMTS-CARB Forecast'!$Q116 -> 0 | BL16: ='EMTS-CARB Forecast'!$Q117 -> 0 | BM16: ='EMTS-CARB Forecast'!$Q118 -> 0 | BN16: ='EMTS-CARB Forecast'!$Q119 -> 0 | BO16: ='EMTS-CARB Forecast'!$R116 -> 0 | BP16: ='EMTS-CARB Forecast'!$R117 -> 0 | BQ16: ='EMTS-CARB Forecast'!$R118 -> 0 | BR16: ='EMTS-CARB Forecast'!$R119 -> 0 | BS16: ='EMTS-CARB Forecast'!$S116 -> 0 | BT16: ='EMTS-CARB Forecast'!$S117 -> 0 | BU16: ='EMTS-CARB Forecast'!$S118 -> 0 | BV16: ='EMTS-CARB Forecast'!$S119 -> 0 | BW16: ='EMTS-CARB Forecast'!$T116 -> 0 | BX16: ='EMTS-CARB Forecast'!$T117 -> 0 | BY16: ='EMTS-CARB Forecast'!$T118 -> 0 | BZ16: ='EMTS-CARB Forecast'!$T119 -> 0 | CA16: ='EMTS-CARB Forecast'!$U116 -> 0 | CB16: ='EMTS-CARB Forecast'!$U117 -> 0 | CC16: ='EMTS-CARB Forecast'!$U118 -> 0 | CD16: ='EMTS-CARB Forecast'!$U119 -> 0 | CE16: ='EMTS-CARB Forecast'!$V116 -> 0 | CF16: ='EMTS-CARB Forecast'!$V117 -> 0 | CG16: ='EMTS-CARB Forecast'!$V117 -> 0 | CH16: ='EMTS-CARB Forecast'!$V117 -> 0 | CI16: ='EMTS-CARB Forecast'!$V117 -> 0 | CJ16: ='EMTS-CARB Forecast'!$V117 -> 0 | CK16: ='EMTS-CARB Forecast'!$W118 -> 0 | CL16: ='EMTS-CARB Forecast'!$W119 -> 0 | CM16: ='EMTS-CARB Forecast'!$X116 -> 0 | CN16: ='EMTS-CARB Forecast'!$X117 -> 0 | CO16: ='EMTS-CARB Forecast'!$X118 -> 0 | CP16: ='EMTS-CARB Forecast'!$X119 -> 0 | CQ16: ='EMTS-CARB Forecast'!$Y116 -> 0 | CR16: ='EMTS-CARB Forecast'!$Y117 -> 0 | CS16: ='EMTS-CARB Forecast'!$Y118 -> 0 | CT16: ='EMTS-CARB Forecast'!$Y119 -> 0 | CU16: ='EMTS-CARB Forecast'!$Z116 -> 0 | CV16: ='EMTS-CARB Forecast'!$Z117 -> 0 | CW16: ='EMTS-CARB Forecast'!$Z118 -> 0 | CX16: ='EMTS-CARB Forecast'!$Z119 -> 0 | CY16: ='EMTS-CARB Forecast'!$AA116 -> 0 | CZ16: ='EMTS-CARB Forecast'!$AA117 -> 0 | DA16: ='EMTS-CARB Forecast'!$AA118 -> 0 | DB16: ='EMTS-CARB Forecast'!$AA119 -> 0 | DC16: ='EMTS-CARB Forecast'!$AB116 -> 0 | DD16: ='EMTS-CARB Forecast'!$AB117 -> 0 | DE16: ='EMTS-CARB Forecast'!$AB118 -> 0 | DF16: ='EMTS-CARB Forecast'!$AB119 -> 0 | DG16: ='EMTS-CARB Forecast'!$AC116 -> 0 | DH16: ='EMTS-CARB Forecast'!$AC117 -> 0 | DI16: ='EMTS-CARB Forecast'!$AC118 -> 0 | DJ16: ='EMTS-CARB Forecast'!$AC119 -> 0 | DK16: ='EMTS-CARB Forecast'!$AD116 -> 0 | DL16: ='EMTS-CARB Forecast'!$AD117 -> 0 | DM16: ='EMTS-CARB Forecast'!$AD118 -> 0 | DN16: ='EMTS-CARB Forecast'!$AD119 -> 0 | DO16: ='EMTS-CARB Forecast'!$AE116 -> 0 | DP16: ='EMTS-CARB Forecast'!$AE117 -> 0 | DQ16: ='EMTS-CARB Forecast'!$AE118 -> 0 | DR16: ='EMTS-CARB Forecast'!$AE119 -> 0 | DS16: ='EMTS-CARB Forecast'!$BC116 -> 0 | DT16: ='EMTS-CARB Forecast'!$BC117 -> 0 | DU16: ='EMTS-CARB Forecast'!$BC118 -> 0 | DV16: ='EMTS-CARB Forecast'!$BC119 -> 0 | DW16: ='EMTS-CARB Forecast'!$BD116 -> 0 | DX16: ='EMTS-CARB Forecast'!$BD117 -> 0 | DY16: ='EMTS-CARB Forecast'!$BD118 -> 0 | DZ16: ='EMTS-CARB Forecast'!$BD118 -> 0 | EA16: ='EMTS-CARB Forecast'!$BD116 -> 0 | EB16: ='EMTS-CARB Forecast'!$BD117 -> 0 | EC16: ='EMTS-CARB Forecast'!$BD118 -> 0 | ED16: ='EMTS-CARB Forecast'!$BD118 -> 0 | EE16: ='EMTS-CARB Forecast'!$BD116 -> 0 | EF16: ='EMTS-CARB Forecast'!$BD117 -> 0 | EG16: ='EMTS-CARB Forecast'!$BD118 -> 0 | EH16: ='EMTS-CARB Forecast'!$BD118 -> 0 | EI16: ='EMTS-CARB Forecast'!$BD116 -> 0 | EJ16: ='EMTS-CARB Forecast'!$BD117 -> 0 | EK16: ='EMTS-CARB Forecast'!$BD118 -> 0 | EL16: ='EMTS-CARB Forecast'!$BD118 -> 0 | EM16: ='EMTS-CARB Forecast'!$BD116 -> 0 | EN16: ='EMTS-CARB Forecast'!$BD117 -> 0 | EO16: ='EMTS-CARB Forecast'!$BD118 -> 0 | EP16: ='EMTS-CARB Forecast'!$BD118 -> 0 | EQ16: ='EMTS-CARB Forecast'!$BD116 -> 0 | ER16: ='EMTS-CARB Forecast'!$BD117 -> 0 | ES16: ='EMTS-CARB Forecast'!$BD118 -> 0 | ET16: ='EMTS-CARB Forecast'!$BD118 -> 0 | EU16: ='EMTS-CARB Forecast'!$BD116 -> 0 | EV16: ='EMTS-CARB Forecast'!$BD117 -> 0 | EW16: ='EMTS-CARB Forecast'!$BD118 -> 0 | EX16: ='EMTS-CARB Forecast'!$BD118 -> 0 | EY16: ='EMTS-CARB Forecast'!$BD116 -> 0 | EZ16: ='EMTS-CARB Forecast'!$BD117 -> 0 | FA16: ='EMTS-CARB Forecast'!$BD118 -> 0 | FB16: ='EMTS-CARB Forecast'!$BD118 -> 0 | FC16: ='EMTS-CARB Forecast'!$BD116 -> 0 | FD16: ='EMTS-CARB Forecast'!$BD117 -> 0 | FE16: ='EMTS-CARB Forecast'!$BD118 -> 0 | FF16: ='EMTS-CARB Forecast'!$BD118 -> 0 | FG16: ='EMTS-CARB Forecast'!$BD116 -> 0 | FH16: ='EMTS-CARB Forecast'!$BD117 -> 0 | FI16: ='EMTS-CARB Forecast'!$BD118 -> 0 | FJ16: ='EMTS-CARB Forecast'!$BD118 -> 0
A17: CARBOB | B17: gal | C17: 3187578208 | D17: 3294107893 | E17: 3320247258 | F17: 3323012827 | G17: 3189895483 | H17: 3273254068 | I17: 3298505633 | J17: 3449039221 | K17: 2991042519 | L17: 3298305567 | M17: 3336711067 | N17: 3347165477 | O17: 3118899568 | P17: 3279279406 | Q17: 3395731910 | R17: 3539912317 | S17: 3158733458 | T17: 3433573365 | U17: 3514621395 | V17: 3337634199 | W17: 3435633723 | X17: 3478700777 | Y17: 3566483826 | Z17: 3572453275 | AA17: 3341219548 | AB17: 3529939560 | AC17: 3617739626 | AD17: 3579790158 | AE17: 3314263901 | AF17: 3500848195 | AG17: 3521521071 | AH17: 3442349061 | AI17: 3311327792 | AJ17: 3490625083 | AK17: 3427420016 | AL17: 3508158465 | AM17: 3139225686 | AN17: 2376026761 | AO17: 2927129520 | AP17: 2896415790 | AQ17: 2799387705 | AR17: 3139905796 | AS17: 3318341379 | AT17: 3136312673 | AU17: 2984051294 | AV17: 3133122469 | AW17: 3035442626 | AX17: 3178353552 | AY17: 2877639926 | AZ17: 3101909762 | BA17: 3117814822 | BB17: 3011760731 | BC17: 2923005317 | BD17: 3126653399 | BE17: 2920630023
A18: Diesel | B18: gal | C18: 806819602 | D18: 898714606 | E18: 969964838 | F18: 909161464 | G18: 771973725 | H18: 891135601 | I18: 990066549 | J18: 922317155 | K18: 801458731 | L18: 933891967 | M18: 914337244 | N18: 848422498 | O18: 782052674 | P18: 853357445 | Q18: 928242072 | R18: 923253715 | S18: 780306276 | T18: 891669978 | U18: 945127593 | V18: 848568072 | W18: 771524952 | X18: 852507840 | Y18: 995644592 | Z18: 762491040 | AA18: 758909481 | AB18: 811130582 | AC18: 878738400 | AD18: 893171901 | AE18: 711401767 | AF18: 849679238 | AG18: 861843804 | AH18: 787497672 | AI18: 684643231 | AJ18: 757142167 | AK18: 791474334 | AL18: 754020517 | AM18: 621673074 | AN18: 679469633 | AO18: 723665358 | AP18: 701111104 | AQ18: 574933496 | AR18: 672080316 | AS18: 688878020 | AT18: 581035867 | AU18: 500665522 | AV18: 521594545 | AW18: 486403394 | AX18: 496321609 | AY18: 350392323 | AZ18: 344959500 | BA18: 392693153 | BB18: 320738602 | BC18: 217083416 | BD18: 214595114 | BE18: 307009591
A20: Electricity Total Volume
A21: Fuel Application Type | B21: Units | C21: =C4 -> 2011Q1 | D21: =D4 -> Q2 | E21: =E4 -> Q3 | F21: =F4 -> Q4 | G21: =G4 -> 2012Q1 | H21: =H4 -> Q2 | I21: =I4 -> Q3 | J21: =J4 -> Q4 | ... FJ21: =FJ4 -> Q4
A22: Electricity – Onroad EV charging – LDV/MDV | B22: gge | C22: 21816 | D22: 60591 | E22: 119059 | F22: 171607 | G22: 220891 | H22: 271183 | I22: 355146 | J22: 468250 | K22: 575617 | L22: 746463 | M22: 957652 | N22: 1320154 | O22: 1595430 | P22: 1950333 | Q22: 2266455 | R22: 2640450 | S22: 2820481 | T22: 2990668 | U22: 3498333 | V22: 3652731 | W22: 4872477 | X22: 5167531 | Y22: 5538669 | Z22: 6455415 | AA22: 7501199 | AB22: 7582920 | AC22: 8034459 | AD22: 8638298 | AE22: 10704547 | AF22: 11940226 | AG22: 13760081 | AH22: 15097403 | AI22: 0 | AJ22: 0 | AK22: 0 | AL22: 0 | AM22: 0 | AN22: 0 | AO22: 0 | AP22: 0 | AQ22: 0 | AR22: 0 | AS22: 0 | AT22: 0 | AU22: 0 | AV22: 0 | AW22: 0 | AX22: 0 | AY22: 0 | AZ22: 0 | BA22: 0 | BB22: 0 | BC22: 0 | BD22: 0 | BE22: 0 | BF22: 0 | BG22: 0 | BH22: 0 | BI22: 0 | BJ22: 0 | BK22: 0 | BL22: 0 | BM22: 0 | BN22: 0 | BO22: 0 | BP22: 0 | BQ22: 0 | BR22: 0 | BS22: 0 | BT22: 0 | BU22: 0 | BV22: 0 | BW22: 0 | BX22: 0 | BY22: 0 | BZ22: 0 | CA22: 0 | CB22: 0 | CC22: 0 | CD22: 0 | CE22: 0 | CF22: 0 | CG22: 0 | CH22: 0 | CI22: 0 | CJ22: 0 | CK22: 0 | CL22: 0 | CM22: 0 | CN22: 0 | CO22: 0 | CP22: 0 | CQ22: 0 | CR22: 0 | CS22: 0 | CT22: 0 | CU22: 0 | CV22: 0 | CW22: 0 | CX22: 0 | CY22: 0 | CZ22: 0 | DA22: 0 | DB22: 0 | DC22: 0 | DD22: 0 | DE22: 0 | DF22: 0 | DG22: 0 | DH22: 0 | DI22: 0 | DJ22: 0 | DK22: 0 | DL22: 0 | DM22: 0 | DN22: 0 | DO22: 0 | DP22: 0 | DQ22: 0 | DR22: 0 | DS22: 0 | DT22: 0 | DU22: 0 | DV22: 0 | DW22: 0 | DX22: 0 | DY22: 0 | DZ22: 0 | EA22: 0 | EB22: 0 | EC22: 0 | ED22: 0 | EE22: 0 | EF22: 0 | EG22: 0 | EH22: 0 | EI22: 0 | EJ22: 0 | EK22: 0 | EL22: 0 | EM22: 0 | EN22: 0 | EO22: 0 | EP22: 0 | EQ22: 0 | ER22: 0 | ES22: 0 | ET22: 0 | EU22: 0 | EV22: 0 | EW22: 0 | EX22: 0 | EY22: 0 | EZ22: 0 | FA22: 0 | FB22: 0 | FC22: 0 | FD22: 0 | FE22: 0 | FF22: 0 | FG22: 0 | FH22: 0 | FI22: 0 | FJ22: 0
A23: Electricity – Onroad EV charging – HDV | B23: gge | C23: 0 | D23: 1624 | E23: 0 | F23: 0 | G23: 0 | H23: 0 | I23: 0 | J23: 0 | K23: 0 | L23: 0 | M23: 0 | N23: 0 | O23: 0 | P23: 0 | Q23: 0 | R23: 0 | S23: 0 | T23: 0 | U23: 7186 | V23: 6427 | W23: 8685 | X23: 10049 | Y23: 10519 | Z23: 10947 | AA23: 13207 | AB23: 13775 | AC23: 14705 | AD23: 17400 | AE23: 24451 | AF23: 24140 | AG23: 39552 | AH23: 51069 | AI23: 0 | AJ23: 0 | AK23: 0 | AL23: 0 | AM23: 0 | AN23: 0 | AO23: 0 | AP23: 0 | AQ23: 0 | AR23: 0 | AS23: 0 | AT23: 0 | AU23: 0 | AV23: 0 | AW23: 0 | AX23: 0 | AY23: 0 | AZ23: 0 | BA23: 0 | BB23: 0 | BC23: 0 | BD23: 0 | BE23: 0 | BF23: 0 | BG23: 0 | BH23: 0 | BI23: 0 | BJ23: 0 | BK23: 0 | BL23: 0 | BM23: 0 | BN23: 0 | BO23: 0 | BP23: 0 | BQ23: 0 | BR23: 0 | BS23: 0 | BT23: 0 | BU23: 0 | BV23: 0 | BW23: 0 | BX23: 0 | BY23: 0 | BZ23: 0 | CA23: 0 | CB23: 0 | CC23: 0 | CD23: 0 | CE23: 0 | CF23: 0 | CG23: 0 | CH23: 0 | CI23: 0 | CJ23: 0 | CK23: 0 | CL23: 0 | CM23: 0 | CN23: 0 | CO23: 0 | CP23: 0 | CQ23: 0 | CR23: 0 | CS23: 0 | CT23: 0 | CU23: 0 | CV23: 0 | CW23: 0 | CX23: 0 | CY23: 0 | CZ23: 0 | DA23: 0 | DB23: 0 | DC23: 0 | DD23: 0 | DE23: 0 | DF23: 0 | DG23: 0 | DH23: 0 | DI23: 0 | DJ23: 0 | DK23: 0 | DL23: 0 | DM23: 0 | DN23: 0 | DO23: 0 | DP23: 0 | DQ23: 0 | DR23: 0 | DS23: 0 | DT23: 0 | DU23: 0 | DV23: 0 | DW23: 0 | DX23: 0 | DY23: 0 | DZ23: 0 | EA23: 0 | EB23: 0 | EC23: 0 | ED23: 0 | EE23: 0 | EF23: 0 | EG23: 0 | EH23: 0 | EI23: 0 | EJ23: 0 | EK23: 0 | EL23: 0 | EM23: 0 | EN23: 0 | EO23: 0 | EP23: 0 | EQ23: 0 | ER23: 0 | ES23: 0 | ET23: 0 | EU23: 0 | EV23: 0 | EW23: 0 | EX23: 0 | EY23: 0 | EZ23: 0 | FA23: 0 | FB23: 0 | FC23: 0 | FD23: 0 | FE23: 0 | FF23: 0 | FG23: 0 | FH23: 0 | FI23: 0 | FJ23: 0
A24: Electricity – Onroad residential grid EV charging | B24: gge | C24: 0 | D24: 0 | E24: 0 | F24: 0 | G24: 0 | H24: 0 | I24: 0 | J24: 0 | K24: 0 | L24: 0 | M24: 0 | N24: 0 | O24: 0 | P24: 0 | Q24: 0 | R24: 0 | S24: 0 | T24: 0 | U24: 0 | V24: 0 | W24: 0 | X24: 0 | Y24: 0 | Z24: 0 | AA24: 0 | AB24: 0 | AC24: 0 | AD24: 0 | AE24: 0 | AF24: 0 | AG24: 0 | AH24: 0 | AI24: 14112490 | AJ24: 12387189 | AK24: 13722414 | AL24: 15357142 | AM24: 15430193 | AN24: 8803013 | AO24: 10981770 | AP24: 12182757 | AQ24: 12434539 | AR24: 15637758 | AS24: 17451974 | AT24: 19182187 | AU24: 23609406 | AV24: 25876915 | AW24: 27214649 | AX24: 31700136 | AY24: 28795362 | AZ24: 31633494 | BA24: 34677815 | BB24: 36026305 | BC24: 37038729 | BD24: 42639004 | BE24: 44951709 | BF24: =IF(_xlfn.FORECAST.ETS(BF$47,P24:BE24,P$47:BE$47)<0,0,_xlfn.FORECAST.ETS(BF$47,P24:BE24,P$47:BE$47)) -> 47049696 | BG24: =IF(_xlfn.FORECAST.ETS(BG$47,Q24:BF24,Q$47:BF$47)<0,0,_xlfn.FORECAST.ETS(BG$47,Q24:BF24,Q$47:BF$47)) -> 49553397 | BH24: =IF(_xlfn.FORECAST.ETS(BH$47,R24:BG24,R$47:BG$47)<0,0,_xlfn.FORECAST.ETS(BH$47,R24:BG24,R$47:BG$47)) -> 52057097 | BI24: =IF(_xlfn.FORECAST.ETS(BI$47,S24:BH24,S$47:BH$47)<0,0,_xlfn.FORECAST.ETS(BI$47,S24:BH24,S$47:BH$47)) -> 54050704 | BJ24: =IF(_xlfn.FORECAST.ETS(BJ$47,T24:BI24,T$47:BI$47)<0,0,_xlfn.FORECAST.ETS(BJ$47,T24:BI24,T$47:BI$47)) -> 56639419 | BK24: =IF(_xlfn.FORECAST.ETS(BK$47,U24:BJ24,U$47:BJ$47)<0,0,_xlfn.FORECAST.ETS(BK$47,U24:BJ24,U$47:BJ$47)) -> 59550400 | BL24: =IF(_xlfn.FORECAST.ETS(BL$47,V24:BK24,V$47:BK$47)<0,0,_xlfn.FORECAST.ETS(BL$47,V24:BK24,V$47:BK$47)) -> 62213779 | BM24: =IF(_xlfn.FORECAST.ETS(BM$47,W24:BL24,W$47:BL$47)<0,0,_xlfn.FORECAST.ETS(BM$47,W24:BL24,W$47:BL$47)) -> 65046528 | ... FJ24: =IF(_xlfn.FORECAST.ETS(FJ$47,DT24:FI24,DT$47:FI$47)<0,0,_xlfn.FORECAST.ETS(FJ$47,DT24:FI24,DT$47:FI$47)) -> 3.3758117e+08
A25: Electricity – Onroad non-residential grid EV charging – LDV/MDV | B25: gge | C25: 0 | D25: 0 | E25: 0 | F25: 0 | G25: 0 | H25: 0 | I25: 0 | J25: 0 | K25: 0 | L25: 0 | M25: 0 | N25: 0 | O25: 0 | P25: 0 | Q25: 0 | R25: 0 | S25: 0 | T25: 0 | U25: 0 | V25: 0 | W25: 0 | X25: 0 | Y25: 0 | Z25: 0 | AA25: 0 | AB25: 0 | AC25: 0 | AD25: 0 | AE25: 0 | AF25: 0 | AG25: 0 | AH25: 0 | AI25: 439089 | AJ25: 537774 | AK25: 301091 | AL25: 320797 | AM25: 238962 | AN25: 63479 | AO25: 138562 | AP25: 95476 | AQ25: 90615 | AR25: 113852 | AS25: 173650 | AT25: 180062 | AU25: 184899 | AV25: 189191 | AW25: 562629 | AX25: 612670 | AY25: 395550.77 | AZ25: 969562.67 | BA25: 865020.05 | BB25: 541603.82 | BC25: 693451.66 | BD25: 645121 | BE25: 660402 | BF25: =IF(_xlfn.FORECAST.ETS(BF$47,P25:BE25,P$47:BE$47)<0,0,_xlfn.FORECAST.ETS(BF$47,P25:BE25,P$47:BE$47)) -> 712750.21 | BG25: =IF(_xlfn.FORECAST.ETS(BG$47,Q25:BF25,Q$47:BF$47)<0,0,_xlfn.FORECAST.ETS(BG$47,Q25:BF25,Q$47:BF$47)) -> 698225.58 | BH25: =IF(_xlfn.FORECAST.ETS(BH$47,R25:BG25,R$47:BG$47)<0,0,_xlfn.FORECAST.ETS(BH$47,R25:BG25,R$47:BG$47)) -> 688434.46 | BI25: =IF(_xlfn.FORECAST.ETS(BI$47,S25:BH25,S$47:BH$47)<0,0,_xlfn.FORECAST.ETS(BI$47,S25:BH25,S$47:BH$47)) -> 717899.25 | BJ25: =IF(_xlfn.FORECAST.ETS(BJ$47,T25:BI25,T$47:BI$47)<0,0,_xlfn.FORECAST.ETS(BJ$47,T25:BI25,T$47:BI$47)) -> 718729.98 | BK25: =IF(_xlfn.FORECAST.ETS(BK$47,U25:BJ25,U$47:BJ$47)<0,0,_xlfn.FORECAST.ETS(BK$47,U25:BJ25,U$47:BJ$47)) -> 1085750 | BL25: =IF(_xlfn.FORECAST.ETS(BL$47,V25:BK25,V$47:BK$47)<0,0,_xlfn.FORECAST.ETS(BL$47,V25:BK25,V$47:BK$47)) -> 1190520.2 | BM25: =IF(_xlfn.FORECAST.ETS(BM$47,W25:BL25,W$47:BL$47)<0,0,_xlfn.FORECAST.ETS(BM$47,W25:BL25,W$47:BL$47)) -> 986342.35 | ... FJ25: =IF(_xlfn.FORECAST.ETS(FJ$47,DT25:FI25,DT$47:FI$47)<0,0,_xlfn.FORECAST.ETS(FJ$47,DT25:FI25,DT$47:FI$47)) -> 2696439.2
A26: Electricity – Onroad non-residential low-CI EV charging – LDV/MDV | B26: gge | C26: 0 | D26: 0 | E26: 0 | F26: 0 | G26: 0 | H26: 0 | I26: 0 | J26: 0 | K26: 0 | L26: 0 | M26: 0 | N26: 0 | O26: 0 | P26: 0 | Q26: 0 | R26: 0 | S26: 0 | T26: 0 | U26: 0 | V26: 0 | W26: 0 | X26: 0 | Y26: 0 | Z26: 0 | AA26: 0 | AB26: 0 | AC26: 0 | AD26: 0 | AE26: 0 | AF26: 0 | AG26: 0 | AH26: 0 | AI26: 1597231 | AJ26: 1837329 | AK26: 2189362 | AL26: 2284298 | AM26: 1909164 | AN26: 1424745 | AO26: 1885721 | AP26: 1892124 | AQ26: 2236386 | AR26: 3198522 | AS26: 3944707 | AT26: 4410225 | AU26: 4652851 | AV26: 6291697 | AW26: 6724456 | AX26: 7061854 | AY26: 7779076.1 | AZ26: 8355981.8 | BA26: 9908784.6 | BB26: 11351677 | BC26: 12122888 | BD26: 13463425 | BE26: 14451547 | BF26: =IF(_xlfn.FORECAST.ETS(BF$47,P26:BE26,P$47:BE$47)<0,0,_xlfn.FORECAST.ETS(BF$47,P26:BE26,P$47:BE$47)) -> 15588899 | BG26: =IF(_xlfn.FORECAST.ETS(BG$47,Q26:BF26,Q$47:BF$47)<0,0,_xlfn.FORECAST.ETS(BG$47,Q26:BF26,Q$47:BF$47)) -> 16680579 | BH26: =IF(_xlfn.FORECAST.ETS(BH$47,R26:BG26,R$47:BG$47)<0,0,_xlfn.FORECAST.ETS(BH$47,R26:BG26,R$47:BG$47)) -> 17780959 | BI26: =IF(_xlfn.FORECAST.ETS(BI$47,S26:BH26,S$47:BH$47)<0,0,_xlfn.FORECAST.ETS(BI$47,S26:BH26,S$47:BH$47)) -> 19269276 | BJ26: =IF(_xlfn.FORECAST.ETS(BJ$47,T26:BI26,T$47:BI$47)<0,0,_xlfn.FORECAST.ETS(BJ$47,T26:BI26,T$47:BI$47)) -> 20487076 | BK26: =IF(_xlfn.FORECAST.ETS(BK$47,U26:BJ26,U$47:BJ$47)<0,0,_xlfn.FORECAST.ETS(BK$47,U26:BJ26,U$47:BJ$47)) -> 21676417 | BL26: =IF(_xlfn.FORECAST.ETS(BL$47,V26:BK26,V$47:BK$47)<0,0,_xlfn.FORECAST.ETS(BL$47,V26:BK26,V$47:BK$47)) -> 22899420 | BM26: =IF(_xlfn.FORECAST.ETS(BM$47,W26:BL26,W$47:BL$47)<0,0,_xlfn.FORECAST.ETS(BM$47,W26:BL26,W$47:BL$47)) -> 24122290 | ... FJ26: =IF(_xlfn.FORECAST.ETS(FJ$47,DT26:FI26,DT$47:FI$47)<0,0,_xlfn.FORECAST.ETS(FJ$47,DT26:FI26,DT$47:FI$47)) -> 1.467905e+08
A27: Electricity – Onroad non-residential grid EV charging – HDV | B27: gge | C27: 0 | D27: 0 | E27: 0 | F27: 0 | G27: 0 | H27: 0 | I27: 0 | J27: 0 | K27: 0 | L27: 0 | M27: 0 | N27: 0 | O27: 0 | P27: 0 | Q27: 0 | R27: 0 | S27: 0 | T27: 0 | U27: 0 | V27: 0 | W27: 0 | X27: 0 | Y27: 0 | Z27: 0 | AA27: 0 | AB27: 0 | AC27: 0 | AD27: 0 | AE27: 0 | AF27: 0 | AG27: 0 | AH27: 0 | AI27: 61670 | AJ27: 84295 | AK27: 71702 | AL27: 94717 | AM27: 98629 | AN27: 87326 | AO27: 80722 | AP27: 42292 | AQ27: 35111 | AR27: 33810 | AS27: 28774 | AT27: 29145 | AU27: 27822 | AV27: 36807 | AW27: 51820 | AX27: 105779 | AY27: 109757.67 | AZ27: 115086.09 | BA27: 165502.75 | BB27: 136757.67 | BC27: 144078.73 | BD27: 130680.19 | BE27: 151279 | BF27: =IF(_xlfn.FORECAST.ETS(BF$47,P27:BE27,P$47:BE$47)<0,0,_xlfn.FORECAST.ETS(BF$47,P27:BE27,P$47:BE$47)) -> 130564.53 | BG27: =IF(_xlfn.FORECAST.ETS(BG$47,Q27:BF27,Q$47:BF$47)<0,0,_xlfn.FORECAST.ETS(BG$47,Q27:BF27,Q$47:BF$47)) -> 130279.8 | BH27: =IF(_xlfn.FORECAST.ETS(BH$47,R27:BG27,R$47:BG$47)<0,0,_xlfn.FORECAST.ETS(BH$47,R27:BG27,R$47:BG$47)) -> 134848.61 | BI27: =IF(_xlfn.FORECAST.ETS(BI$47,S27:BH27,S$47:BH$47)<0,0,_xlfn.FORECAST.ETS(BI$47,S27:BH27,S$47:BH$47)) -> 119293.4 | BJ27: =IF(_xlfn.FORECAST.ETS(BJ$47,T27:BI27,T$47:BI$47)<0,0,_xlfn.FORECAST.ETS(BJ$47,T27:BI27,T$47:BI$47)) -> 103247.79 | BK27: =IF(_xlfn.FORECAST.ETS(BK$47,U27:BJ27,U$47:BJ$47)<0,0,_xlfn.FORECAST.ETS(BK$47,U27:BJ27,U$47:BJ$47)) -> 103581.49 | BL27: =IF(_xlfn.FORECAST.ETS(BL$47,V27:BK27,V$47:BK$47)<0,0,_xlfn.FORECAST.ETS(BL$47,V27:BK27,V$47:BK$47)) -> 119424.69 | BM27: =IF(_xlfn.FORECAST.ETS(BM$47,W27:BL27,W$47:BL$47)<0,0,_xlfn.FORECAST.ETS(BM$47,W27:BL27,W$47:BL$47)) -> 174368.88 | ... FJ27: =IF(_xlfn.FORECAST.ETS(FJ$47,DT27:FI27,DT$47:FI$47)<0,0,_xlfn.FORECAST.ETS(FJ$47,DT27:FI27,DT$47:FI$47)) -> 553510.1
A28: Electricity – Onroad non-residential low-CI EV charging – HDV | B28: gge | C28: 0 | D28: 0 | E28: 0 | F28: 0 | G28: 0 | H28: 0 | I28: 0 | J28: 0 | K28: 0 | L28: 0 | M28: 0 | N28: 0 | O28: 0 | P28: 0 | Q28: 0 | R28: 0 | S28: 0 | T28: 0 | U28: 0 | V28: 0 | W28: 0 | X28: 0 | Y28: 0 | Z28: 0 | AA28: 0 | AB28: 0 | AC28: 0 | AD28: 0 | AE28: 0 | AF28: 0 | AG28: 0 | AH28: 0 | AI28: 3995 | AJ28: 2385 | AK28: 50891 | AL28: 54537 | AM28: 57975 | AN28: 61093 | AO28: 102313 | AP28: 160968 | AQ28: 136123 | AR28: 162706 | AS28: 210459 | AT28: 233786 | AU28: 238700 | AV28: 265483 | AW28: 272236 | AX28: 259506 | AY28: 280569.39 | AZ28: 317096.1 | BA28: 354941.63 | BB28: 435852.65 | BC28: 496892.65 | BD28: 536213 | BE28: 538793 | BF28: =IF(_xlfn.FORECAST.ETS(BF$47,P28:BE28,P$47:BE$47)<0,0,_xlfn.FORECAST.ETS(BF$47,P28:BE28,P$47:BE$47)) -> 602045.4 | BG28: =IF(_xlfn.FORECAST.ETS(BG$47,Q28:BF28,Q$47:BF$47)<0,0,_xlfn.FORECAST.ETS(BG$47,Q28:BF28,Q$47:BF$47)) -> 653999.96 | BH28: =IF(_xlfn.FORECAST.ETS(BH$47,R28:BG28,R$47:BG$47)<0,0,_xlfn.FORECAST.ETS(BH$47,R28:BG28,R$47:BG$47)) -> 656464.73 | BI28: =IF(_xlfn.FORECAST.ETS(BI$47,S28:BH28,S$47:BH$47)<0,0,_xlfn.FORECAST.ETS(BI$47,S28:BH28,S$47:BH$47)) -> 705436.81 | BJ28: =IF(_xlfn.FORECAST.ETS(BJ$47,T28:BI28,T$47:BI$47)<0,0,_xlfn.FORECAST.ETS(BJ$47,T28:BI28,T$47:BI$47)) -> 754356.04 | BK28: =IF(_xlfn.FORECAST.ETS(BK$47,U28:BJ28,U$47:BJ$47)<0,0,_xlfn.FORECAST.ETS(BK$47,U28:BJ28,U$47:BJ$47)) -> 804294.89 | BL28: =IF(_xlfn.FORECAST.ETS(BL$47,V28:BK28,V$47:BK$47)<0,0,_xlfn.FORECAST.ETS(BL$47,V28:BK28,V$47:BK$47)) -> 855757.68 | BM28: =IF(_xlfn.FORECAST.ETS(BM$47,W28:BL28,W$47:BL$47)<0,0,_xlfn.FORECAST.ETS(BM$47,W28:BL28,W$47:BL$47)) -> 900438.36 | ... FJ28: =IF(_xlfn.FORECAST.ETS(FJ$47,DT28:FI28,DT$47:FI$47)<0,0,_xlfn.FORECAST.ETS(FJ$47,DT28:FI28,DT$47:FI$47)) -> 5547098.7
A29: Electricity – Offroad fixed guideways | B29: gge | C29: 0 | D29: 0 | E29: 0 | F29: 0 | G29: 0 | H29: 0 | I29: 0 | J29: 0 | K29: 0 | L29: 0 | M29: 0 | N29: 0 | O29: 0 | P29: 0 | Q29: 0 | R29: 0 | S29: 0 | T29: 0 | U29: 0 | V29: 0 | W29: 4120613 | X29: 4768068 | Y29: 4678241 | Z29: 5290607 | AA29: 5001004 | AB29: 5979420 | AC29: 5874243 | AD29: 6292520 | AE29: 5640429 | AF29: 5665532 | AG29: 5977296 | AH29: 6016955 | AI29: 5378515 | AJ29: 5602600 | AK29: 5744706 | AL29: 5875189 | AM29: 5504688 | AN29: 4039261 | AO29: 4448829 | AP29: 4140940 | AQ29: 4192790 | AR29: 4364180 | AS29: 4992017 | AT29: 4935359 | AU29: 4796369 | AV29: 4679212 | AW29: 5376856 | AX29: 5490893 | AY29: 5190520.9 | AZ29: 5705942 | BA29: 6243539.5 | BB29: 4994847.4 | BC29: 5258330.1 | BD29: 5407908 | BE29: 6209719 | BF29: =IF(_xlfn.FORECAST.ETS(BF$47,P29:BE29,P$47:BE$47)<0,0,_xlfn.FORECAST.ETS(BF$47,P29:BE29,P$47:BE$47)) -> 6247012.7 | BG29: =IF(_xlfn.FORECAST.ETS(BG$47,Q29:BF29,Q$47:BF$47)<0,0,_xlfn.FORECAST.ETS(BG$47,Q29:BF29,Q$47:BF$47)) -> 6344806 | BH29: =IF(_xlfn.FORECAST.ETS(BH$47,R29:BG29,R$47:BG$47)<0,0,_xlfn.FORECAST.ETS(BH$47,R29:BG29,R$47:BG$47)) -> 6433327.2 | BI29: =IF(_xlfn.FORECAST.ETS(BI$47,S29:BH29,S$47:BH$47)<0,0,_xlfn.FORECAST.ETS(BI$47,S29:BH29,S$47:BH$47)) -> 6511859.3 | BJ29: =IF(_xlfn.FORECAST.ETS(BJ$47,T29:BI29,T$47:BI$47)<0,0,_xlfn.FORECAST.ETS(BJ$47,T29:BI29,T$47:BI$47)) -> 6579639.1 | BK29: =IF(_xlfn.FORECAST.ETS(BK$47,U29:BJ29,U$47:BJ$47)<0,0,_xlfn.FORECAST.ETS(BK$47,U29:BJ29,U$47:BJ$47)) -> 6635856.2 | BL29: =IF(_xlfn.FORECAST.ETS(BL$47,V29:BK29,V$47:BK$47)<0,0,_xlfn.FORECAST.ETS(BL$47,V29:BK29,V$47:BK$47)) -> 6679652 | BM29: =IF(_xlfn.FORECAST.ETS(BM$47,W29:BL29,W$47:BL$47)<0,0,_xlfn.FORECAST.ETS(BM$47,W29:BL29,W$47:BL$47)) -> 6923060.3 | ... FJ29: =IF(_xlfn.FORECAST.ETS(FJ$47,DT29:FI29,DT$47:FI$47)<0,0,_xlfn.FORECAST.ETS(FJ$47,DT29:FI29,DT$47:FI$47)) -> 13947541
A30: Electricity – Offroad eOGV | B30: gge | C30: 0 | D30: 0 | E30: 0 | F30: 0 | G30: 0 | H30: 0 | I30: 0 | J30: 0 | K30: 0 | L30: 0 | M30: 0 | N30: 0 | O30: 0 | P30: 0 | Q30: 0 | R30: 0 | S30: 0 | T30: 0 | U30: 0 | V30: 0 | W30: 0 | X30: 0 | Y30: 0 | Z30: 0 | AA30: 0 | AB30: 0 | AC30: 0 | AD30: 0 | AE30: 0 | AF30: 0 | AG30: 0 | AH30: 0 | AI30: 924451 | AJ30: 1055976 | AK30: 1111870 | AL30: 1159630 | AM30: 1078105 | AN30: 1047001 | AO30: 1158909 | AP30: 1768879 | AQ30: 1795611 | AR30: 1994763 | AS30: 2059130 | AT30: 2074920 | AU30: 1869091 | AV30: 4383063 | AW30: 4014275 | AX30: 4325911 | AY30: 3800935.9 | AZ30: 4313970.4 | BA30: 5115869 | BB30: 4869784.5 | BC30: 4391637.9 | BD30: 4575722 | BE30: 4610999 | BF30: =IF(_xlfn.FORECAST.ETS(BF$47,P30:BE30,P$47:BE$47)<0,0,_xlfn.FORECAST.ETS(BF$47,P30:BE30,P$47:BE$47)) -> 5570236.1 | BG30: =IF(_xlfn.FORECAST.ETS(BG$47,Q30:BF30,Q$47:BF$47)<0,0,_xlfn.FORECAST.ETS(BG$47,Q30:BF30,Q$47:BF$47)) -> 5514671.1 | BH30: =IF(_xlfn.FORECAST.ETS(BH$47,R30:BG30,R$47:BG$47)<0,0,_xlfn.FORECAST.ETS(BH$47,R30:BG30,R$47:BG$47)) -> 5664676 | BI30: =IF(_xlfn.FORECAST.ETS(BI$47,S30:BH30,S$47:BH$47)<0,0,_xlfn.FORECAST.ETS(BI$47,S30:BH30,S$47:BH$47)) -> 5788565.9 | BJ30: =IF(_xlfn.FORECAST.ETS(BJ$47,T30:BI30,T$47:BI$47)<0,0,_xlfn.FORECAST.ETS(BJ$47,T30:BI30,T$47:BI$47)) -> 5959054.6 | BK30: =IF(_xlfn.FORECAST.ETS(BK$47,U30:BJ30,U$47:BJ$47)<0,0,_xlfn.FORECAST.ETS(BK$47,U30:BJ30,U$47:BJ$47)) -> 6127037.6 | BL30: =IF(_xlfn.FORECAST.ETS(BL$47,V30:BK30,V$47:BK$47)<0,0,_xlfn.FORECAST.ETS(BL$47,V30:BK30,V$47:BK$47)) -> 6303824.8 | BM30: =IF(_xlfn.FORECAST.ETS(BM$47,W30:BL30,W$47:BL$47)<0,0,_xlfn.FORECAST.ETS(BM$47,W30:BL30,W$47:BL$47)) -> 6484698.8 | ... FJ30: =IF(_xlfn.FORECAST.ETS(FJ$47,DT30:FI30,DT$47:FI$47)<0,0,_xlfn.FORECAST.ETS(FJ$47,DT30:FI30,DT$47:FI$47)) -> 26507633
A31: Electricity – Offroad eCHE | B31: gge | C31: 0 | D31: 0 | E31: 0 | F31: 0 | G31: 0 | H31: 0 | I31: 0 | J31: 0 | K31: 0 | L31: 0 | M31: 0 | N31: 0 | O31: 0 | P31: 0 | Q31: 0 | R31: 0 | S31: 0 | T31: 0 | U31: 0 | V31: 0 | W31: 0 | X31: 0 | Y31: 0 | Z31: 0 | AA31: 0 | AB31: 0 | AC31: 0 | AD31: 0 | AE31: 0 | AF31: 0 | AG31: 0 | AH31: 0 | AI31: 0 | AJ31: 141642 | AK31: 136066 | AL31: 151916 | AM31: 166761 | AN31: 192953 | AO31: 202275 | AP31: 206750 | AQ31: 235898 | AR31: 210608 | AS31: 258108 | AT31: 271518 | AU31: 324929 | AV31: 314599 | AW31: 293567 | AX31: 249895 | AY31: 277239.63 | AZ31: 248894.17 | BA31: 353679.29 | BB31: 343330.23 | BC31: 319769.54 | BD31: 290951 | BE31: 324199 | BF31: =IF(_xlfn.FORECAST.ETS(BF$47,P31:BE31,P$47:BE$47)<0,0,_xlfn.FORECAST.ETS(BF$47,P31:BE31,P$47:BE$47)) -> 335700.05 | BG31: =IF(_xlfn.FORECAST.ETS(BG$47,Q31:BF31,Q$47:BF$47)<0,0,_xlfn.FORECAST.ETS(BG$47,Q31:BF31,Q$47:BF$47)) -> 346176.87 | BH31: =IF(_xlfn.FORECAST.ETS(BH$47,R31:BG31,R$47:BG$47)<0,0,_xlfn.FORECAST.ETS(BH$47,R31:BG31,R$47:BG$47)) -> 354093.5 | BI31: =IF(_xlfn.FORECAST.ETS(BI$47,S31:BH31,S$47:BH$47)<0,0,_xlfn.FORECAST.ETS(BI$47,S31:BH31,S$47:BH$47)) -> 365131.06 | BJ31: =IF(_xlfn.FORECAST.ETS(BJ$47,T31:BI31,T$47:BI$47)<0,0,_xlfn.FORECAST.ETS(BJ$47,T31:BI31,T$47:BI$47)) -> 376057.9 | BK31: =IF(_xlfn.FORECAST.ETS(BK$47,U31:BJ31,U$47:BJ$47)<0,0,_xlfn.FORECAST.ETS(BK$47,U31:BJ31,U$47:BJ$47)) -> 387157.66 | BL31: =IF(_xlfn.FORECAST.ETS(BL$47,V31:BK31,V$47:BK$47)<0,0,_xlfn.FORECAST.ETS(BL$47,V31:BK31,V$47:BK$47)) -> 398552.85 | BM31: =IF(_xlfn.FORECAST.ETS(BM$47,W31:BL31,W$47:BL$47)<0,0,_xlfn.FORECAST.ETS(BM$47,W31:BL31,W$47:BL$47)) -> 409867.14 | ... FJ31: =IF(_xlfn.FORECAST.ETS(FJ$47,DT31:FI31,DT$47:FI$47)<0,0,_xlfn.FORECAST.ETS(FJ$47,DT31:FI31,DT$47:FI$47)) -> 1431394.4
A32: Electricity – Offroad eForklifts | B32: gge | C32: 0 | D32: 0 | E32: 0 | F32: 0 | G32: 0 | H32: 0 | I32: 0 | J32: 0 | K32: 0 | L32: 0 | M32: 0 | N32: 0 | O32: 0 | P32: 0 | Q32: 0 | R32: 0 | S32: 0 | T32: 0 | U32: 0 | V32: 0 | W32: 4684097 | X32: 4752638 | Y32: 4841054 | Z32: 5004280 | AA32: 4989228 | AB32: 5056098 | AC32: 5076687 | AD32: 5096041 | AE32: 5129549 | AF32: 5164110 | AG32: 5188442 | AH32: 5223272 | AI32: 5250727 | AJ32: 5277940 | AK32: 5291908 | AL32: 5282897 | AM32: 5316667 | AN32: 5602615 | AO32: 6660907 | AP32: 7147835 | AY32: 0 | AZ32: 0 | BE32: 0
A33: Electricity – Offroad eForklifts – EDU | B33: gge | C33: 0 | D33: 0 | E33: 0 | F33: 0 | G33: 0 | H33: 0 | I33: 0 | J33: 0 | K33: 0 | L33: 0 | M33: 0 | N33: 0 | O33: 0 | P33: 0 | Q33: 0 | R33: 0 | S33: 0 | T33: 0 | U33: 0 | V33: 0 | W33: 0 | X33: 0 | Y33: 0 | Z33: 0 | AA33: 0 | AB33: 0 | AC33: 0 | AD33: 0 | AE33: 3743846 | AF33: 3456255 | AG33: 3174942 | AH33: 2982760 | AI33: 2933204 | AJ33: 2640692 | AK33: 1825421 | AL33: 1313252 | AM33: 380989 | AN33: 0 | AO33: 0 | AP33: 0 | AQ33: 2422945 | AR33: 1571526 | AS33: 607109 | AT33: 161941 | AU33: =IF(_xlfn.FORECAST.ETS(AU$47,E33:AT33,E$47:AT$47)<0,0,_xlfn.FORECAST.ETS(AU$47,E33:AT33,E$47:AT$47)) -> 206831.94 | AV33: =IF(_xlfn.FORECAST.ETS(AV$47,F33:AU33,F$47:AU$47)<0,0,_xlfn.FORECAST.ETS(AV$47,F33:AU33,F$47:AU$47)) -> 247999.55 | AW33: =IF(_xlfn.FORECAST.ETS(AW$47,G33:AV33,G$47:AV$47)<0,0,_xlfn.FORECAST.ETS(AW$47,G33:AV33,G$47:AV$47)) -> 285547.08 | AX33: =IF(_xlfn.FORECAST.ETS(AX$47,H33:AW33,H$47:AW$47)<0,0,_xlfn.FORECAST.ETS(AX$47,H33:AW33,H$47:AW$47)) -> 317811.54 | AY33: =IF(_xlfn.FORECAST.ETS(AY$47,I33:AX33,I$47:AX$47)<0,0,_xlfn.FORECAST.ETS(AY$47,I33:AX33,I$47:AX$47)) -> 346941.47 | AZ33: =IF(_xlfn.FORECAST.ETS(AZ$47,J33:AY33,J$47:AY$47)<0,0,_xlfn.FORECAST.ETS(AZ$47,J33:AY33,J$47:AY$47)) -> 372831.29 | BF33: =IF(_xlfn.FORECAST.ETS(BF$47,P33:BE33,P$47:BE$47)<0,0,_xlfn.FORECAST.ETS(BF$47,P33:BE33,P$47:BE$47)) -> 474968.62 | BG33: =IF(_xlfn.FORECAST.ETS(BG$47,Q33:BF33,Q$47:BF$47)<0,0,_xlfn.FORECAST.ETS(BG$47,Q33:BF33,Q$47:BF$47)) -> 476944.5 | BH33: =IF(_xlfn.FORECAST.ETS(BH$47,R33:BG33,R$47:BG$47)<0,0,_xlfn.FORECAST.ETS(BH$47,R33:BG33,R$47:BG$47)) -> 476543.31 | BI33: =IF(_xlfn.FORECAST.ETS(BI$47,S33:BH33,S$47:BH$47)<0,0,_xlfn.FORECAST.ETS(BI$47,S33:BH33,S$47:BH$47)) -> 472827.53 | BJ33: =IF(_xlfn.FORECAST.ETS(BJ$47,T33:BI33,T$47:BI$47)<0,0,_xlfn.FORECAST.ETS(BJ$47,T33:BI33,T$47:BI$47)) -> 465545.96 | BK33: =IF(_xlfn.FORECAST.ETS(BK$47,U33:BJ33,U$47:BJ$47)<0,0,_xlfn.FORECAST.ETS(BK$47,U33:BJ33,U$47:BJ$47)) -> 454610.52 | BL33: =IF(_xlfn.FORECAST.ETS(BL$47,V33:BK33,V$47:BK$47)<0,0,_xlfn.FORECAST.ETS(BL$47,V33:BK33,V$47:BK$47)) -> 439909.18 | BM33: =IF(_xlfn.FORECAST.ETS(BM$47,W33:BL33,W$47:BL$47)<0,0,_xlfn.FORECAST.ETS(BM$47,W33:BL33,W$47:BL$47)) -> 421319.56 | BN33: =IF(_xlfn.FORECAST.ETS(BN$47,X33:BM33,X$47:BM$47)<0,0,_xlfn.FORECAST.ETS(BN$47,X33:BM33,X$47:BM$47)) -> 398709.1 | BO33: =IF(_xlfn.FORECAST.ETS(BO$47,Y33:BN33,Y$47:BN$47)<0,0,_xlfn.FORECAST.ETS(BO$47,Y33:BN33,Y$47:BN$47))+400000 -> 771935.23 | BP33: =IF(_xlfn.FORECAST.ETS(BP$47,Z33:BO33,Z$47:BO$47)<0,0,_xlfn.FORECAST.ETS(BP$47,Z33:BO33,Z$47:BO$47))+300000 -> 710237.42 | BQ33: =IF(_xlfn.FORECAST.ETS(BQ$47,AA33:BP33,AA$47:BP$47)<0,0,_xlfn.FORECAST.ETS(BQ$47,AA33:BP33,AA$47:BP$47))+400000 -> 1076825 | BR33: =IF(_xlfn.FORECAST.ETS(BR$47,AB33:BQ33,AB$47:BQ$47)<0,0,_xlfn.FORECAST.ETS(BR$47,AB33:BQ33,AB$47:BQ$47))+100000 -> 1102389.6 | BS33: =IF(_xlfn.FORECAST.ETS(BS$47,AC33:BR33,AC$47:BR$47)<0,0,_xlfn.FORECAST.ETS(BS$47,AC33:BR33,AC$47:BR$47)) -> 1055658.6 | BT33: =IF(_xlfn.FORECAST.ETS(BT$47,AD33:BS33,AD$47:BS$47)<0,0,_xlfn.FORECAST.ETS(BT$47,AD33:BS33,AD$47:BS$47))+50000 -> 1066184.2 | BU33: =IF(_xlfn.FORECAST.ETS(BU$47,AE33:BT33,AE$47:BT$47)<0,0,_xlfn.FORECAST.ETS(BU$47,AE33:BT33,AE$47:BT$47))+50000 -> 1071079.3 | BV33: =IF(_xlfn.FORECAST.ETS(BV$47,AF33:BU33,AF$47:BU$47)<0,0,_xlfn.FORECAST.ETS(BV$47,AF33:BU33,AF$47:BU$47)) -> 1035936.9 | BW33: =IF(_xlfn.FORECAST.ETS(BW$47,AG33:BV33,AG$47:BV$47)<0,0,_xlfn.FORECAST.ETS(BW$47,AG33:BV33,AG$47:BV$47))+50000 -> 1060071.1 | BX33: =IF(_xlfn.FORECAST.ETS(BX$47,AH33:BW33,AH$47:BW$47)<0,0,_xlfn.FORECAST.ETS(BX$47,AH33:BW33,AH$47:BW$47))+50000 -> 1087590.5 | BY33: =IF(_xlfn.FORECAST.ETS(BY$47,AI33:BX33,AI$47:BX$47)<0,0,_xlfn.FORECAST.ETS(BY$47,AI33:BX33,AI$47:BX$47))+50000 -> 1123372.5 | BZ33: =IF(_xlfn.FORECAST.ETS(BZ$47,AJ33:BY33,AJ$47:BY$47)<0,0,_xlfn.FORECAST.ETS(BZ$47,AJ33:BY33,AJ$47:BY$47))/3 -> 642162.81 | CA33: =IF(_xlfn.FORECAST.ETS(CA$47,AK33:BZ33,AK$47:BZ$47)<0,0,_xlfn.FORECAST.ETS(CA$47,AK33:BZ33,AK$47:BZ$47))+50000 -> 745709.67 | CB33: =IF(_xlfn.FORECAST.ETS(CB$47,AL33:CA33,AL$47:CA$47)<0,0,_xlfn.FORECAST.ETS(CB$47,AL33:CA33,AL$47:CA$47))+50000 -> 812185.79 | CC33: =IF(_xlfn.FORECAST.ETS(CC$47,AM33:CB33,AM$47:CB$47)<0,0,_xlfn.FORECAST.ETS(CC$47,AM33:CB33,AM$47:CB$47))+50000 -> 1128960.4 | CD33: =IF(_xlfn.FORECAST.ETS(CD$47,AN33:CC33,AN$47:CC$47)<0,0,_xlfn.FORECAST.ETS(CD$47,AN33:CC33,AN$47:CC$47)) -> 1108453.5 | CE33: =IF(_xlfn.FORECAST.ETS(CE$47,AO33:CD33,AO$47:CD$47)<0,0,_xlfn.FORECAST.ETS(CE$47,AO33:CD33,AO$47:CD$47)) -> 1212081.3 | CF33: =IF(_xlfn.FORECAST.ETS(CF$47,AP33:CE33,AP$47:CE$47)<0,0,_xlfn.FORECAST.ETS(CF$47,AP33:CE33,AP$47:CE$47)) -> 1201133 | CG33: =IF(_xlfn.FORECAST.ETS(CG$47,AQ33:CF33,AQ$47:CF$47)<0,0,_xlfn.FORECAST.ETS(CG$47,AQ33:CF33,AQ$47:CF$47)) -> 1213699.1 | CH33: =IF(_xlfn.FORECAST.ETS(CH$47,AR33:CG33,AR$47:CG$47)<0,0,_xlfn.FORECAST.ETS(CH$47,AR33:CG33,AR$47:CG$47)) -> 1207076.7 | CI33: =IF(_xlfn.FORECAST.ETS(CI$47,AS33:CH33,AS$47:CH$47)<0,0,_xlfn.FORECAST.ETS(CI$47,AS33:CH33,AS$47:CH$47)) -> 1234637.2 | CJ33: =IF(_xlfn.FORECAST.ETS(CJ$47,AT33:CI33,AT$47:CI$47)<0,0,_xlfn.FORECAST.ETS(CJ$47,AT33:CI33,AT$47:CI$47)) -> 1260879.6 | CK33: =IF(_xlfn.FORECAST.ETS(CK$47,AU33:CJ33,AU$47:CJ$47)<0,0,_xlfn.FORECAST.ETS(CK$47,AU33:CJ33,AU$47:CJ$47))+450000 -> 1740836.3 | CL33: =IF(_xlfn.FORECAST.ETS(CL$47,AV33:CK33,AV$47:CK$47)<0,0,_xlfn.FORECAST.ETS(CL$47,AV33:CK33,AV$47:CK$47))+450000 -> 1884423.1 | CM33: =IF(_xlfn.FORECAST.ETS(CM$47,AW33:CL33,AW$47:CL$47)<0,0,_xlfn.FORECAST.ETS(CM$47,AW33:CL33,AW$47:CL$47))+450000 -> 2363950.6 | CN33: =IF(_xlfn.FORECAST.ETS(CN$47,AX33:CM33,AX$47:CM$47)<0,0,_xlfn.FORECAST.ETS(CN$47,AX33:CM33,AX$47:CM$47))+450000 -> 2846804 | CO33: =IF(_xlfn.FORECAST.ETS(CO$47,AY33:CN33,AY$47:CN$47)<0,0,_xlfn.FORECAST.ETS(CO$47,AY33:CN33,AY$47:CN$47))+450000 -> 3334363.1 | CP33: =IF(_xlfn.FORECAST.ETS(CP$47,AZ33:CO33,AZ$47:CO$47)<0,0,_xlfn.FORECAST.ETS(CP$47,AZ33:CO33,AZ$47:CO$47))+450000 -> 3827939.3 | CQ33: =IF(_xlfn.FORECAST.ETS(CQ$47,BA33:CP33,BA$47:CP$47)<0,0,_xlfn.FORECAST.ETS(CQ$47,BA33:CP33,BA$47:CP$47))+450000 -> 4336076.8 | CR33: =IF(_xlfn.FORECAST.ETS(CR$47,BB33:CQ33,BB$47:CQ$47)<0,0,_xlfn.FORECAST.ETS(CR$47,BB33:CQ33,BB$47:CQ$47))+450000 -> 4852591.2 | ... CV33: =IF(_xlfn.FORECAST.ETS(CV$47,BF33:CU33,BF$47:CU$47)<0,0,_xlfn.FORECAST.ETS(CV$47,BF33:CU33,BF$47:CU$47))+450000 -> 7449925.7 | CW33: =IF(_xlfn.FORECAST.ETS(CW$47,BG33:CV33,BG$47:CV$47)<0,0,_xlfn.FORECAST.ETS(CW$47,BG33:CV33,BG$47:CV$47)) -> 7991873 | CX33: =IF(_xlfn.FORECAST.ETS(CX$47,BH33:CW33,BH$47:CW$47)<0,0,_xlfn.FORECAST.ETS(CX$47,BH33:CW33,BH$47:CW$47)) -> 8576415.2 | CY33: =IF(_xlfn.FORECAST.ETS(CY$47,BI33:CX33,BI$47:CX$47)<0,0,_xlfn.FORECAST.ETS(CY$47,BI33:CX33,BI$47:CX$47)) -> 9351612.8 | CZ33: =IF(_xlfn.FORECAST.ETS(CZ$47,BJ33:CY33,BJ$47:CY$47)<0,0,_xlfn.FORECAST.ETS(CZ$47,BJ33:CY33,BJ$47:CY$47)) -> 10031578 | DA33: =IF(_xlfn.FORECAST.ETS(DA$47,BK33:CZ33,BK$47:CZ$47)<0,0,_xlfn.FORECAST.ETS(DA$47,BK33:CZ33,BK$47:CZ$47)) -> 10707200 | DB33: =IF(_xlfn.FORECAST.ETS(DB$47,BL33:DA33,BL$47:DA$47)<0,0,_xlfn.FORECAST.ETS(DB$47,BL33:DA33,BL$47:DA$47)) -> 11450720 | DC33: =IF(_xlfn.FORECAST.ETS(DC$47,BM33:DB33,BM$47:DB$47)<0,0,_xlfn.FORECAST.ETS(DC$47,BM33:DB33,BM$47:DB$47)) -> 12194265 | DD33: =IF(_xlfn.FORECAST.ETS(DD$47,BN33:DC33,BN$47:DC$47)<0,0,_xlfn.FORECAST.ETS(DD$47,BN33:DC33,BN$47:DC$47)) -> 12937838 | ... FJ33: =IF(_xlfn.FORECAST.ETS(FJ$47,DT33:FI33,DT$47:FI$47)<0,0,_xlfn.FORECAST.ETS(FJ$47,DT33:FI33,DT$47:FI$47)) -> 53064782
A34: Electricity – Offroad eForklifts – Reported | B34: gge | C34: 0 | D34: 0 | E34: 0 | F34: 0 | G34: 0 | H34: 0 | I34: 0 | J34: 0 | K34: 0 | L34: 0 | M34: 0 | N34: 0 | O34: 0 | P34: 0 | Q34: 0 | R34: 0 | S34: 0 | T34: 0 | U34: 0 | V34: 0 | W34: 4684097 | X34: 4752638 | Y34: 4841054 | Z34: 5004280 | AA34: 4989228 | AB34: 5056098 | AC34: 5076687 | AD34: 5096041 | AE34: 5129549 | AF34: 5164110 | AG34: 5188442 | AH34: 5223272 | AI34: 5250727 | AJ34: 5277940 | AK34: 5291908 | AL34: 5282897 | AM34: 5316667 | AN34: 5602615 | AO34: 6660907 | AP34: 7146737 | AQ34: 10147094 | AR34: 10127077 | AS34: 10168994 | AT34: 10167338 | AU34: 10560373 | AV34: 11242201 | AW34: 12025518 | AX34: =IF(_xlfn.FORECAST.ETS(AX$47,H34:AW34,H$47:AW$47)<0,0,_xlfn.FORECAST.ETS(AX$47,H34:AW34,H$47:AW$47)) -> 10849649 | AY34: 12056644 | AZ34: 12390861 | BA34: 12642904 | BB34: 12857516 | BC34: 12878083 | BD34: 13073715 | BE34: 13131887 | BF34: =IF(_xlfn.FORECAST.ETS(BF$47,P34:BE34,P$47:BE$47)<0,0,_xlfn.FORECAST.ETS(BF$47,P34:BE34,P$47:BE$47)) -> 13493010 | BG34: =IF(_xlfn.FORECAST.ETS(BG$47,Q34:BF34,Q$47:BF$47)<0,0,_xlfn.FORECAST.ETS(BG$47,Q34:BF34,Q$47:BF$47)) -> 13824773 | BH34: =IF(_xlfn.FORECAST.ETS(BH$47,R34:BG34,R$47:BG$47)<0,0,_xlfn.FORECAST.ETS(BH$47,R34:BG34,R$47:BG$47)) -> 14158282 | BI34: =IF(_xlfn.FORECAST.ETS(BI$47,S34:BH34,S$47:BH$47)<0,0,_xlfn.FORECAST.ETS(BI$47,S34:BH34,S$47:BH$47)) -> 14485887 | BJ34: =IF(_xlfn.FORECAST.ETS(BJ$47,T34:BI34,T$47:BI$47)<0,0,_xlfn.FORECAST.ETS(BJ$47,T34:BI34,T$47:BI$47)) -> 14810173 | BK34: =IF(_xlfn.FORECAST.ETS(BK$47,U34:BJ34,U$47:BJ$47)<0,0,_xlfn.FORECAST.ETS(BK$47,U34:BJ34,U$47:BJ$47)) -> 15129601 | BL34: =IF(_xlfn.FORECAST.ETS(BL$47,V34:BK34,V$47:BK$47)<0,0,_xlfn.FORECAST.ETS(BL$47,V34:BK34,V$47:BK$47)) -> 15442879 | BM34: =IF(_xlfn.FORECAST.ETS(BM$47,W34:BL34,W$47:BL$47)<0,0,_xlfn.FORECAST.ETS(BM$47,W34:BL34,W$47:BL$47)) -> 15743117 | ... FJ34: =IF(_xlfn.FORECAST.ETS(FJ$47,DT34:FI34,DT$47:FI$47)<0,0,_xlfn.FORECAST.ETS(FJ$47,DT34:FI34,DT$47:FI$47)) -> 48226969
A35: Electricity – Offroad eTRU | B35: gge | C35: 0 | D35: 0 | E35: 0 | F35: 0 | G35: 0 | H35: 0 | I35: 0 | J35: 0 | K35: 0 | L35: 0 | M35: 0 | N35: 0 | O35: 0 | P35: 0 | Q35: 0 | R35: 0 | S35: 0 | T35: 0 | U35: 0 | V35: 0 | W35: 0 | X35: 0 | Y35: 0 | Z35: 0 | AA35: 0 | AB35: 0 | AC35: 0 | AD35: 0 | AE35: 0 | AF35: 0 | AG35: 0 | AH35: 0 | AI35: 0 | AJ35: 0 | AK35: 124937 | AL35: 98771 | AM35: 124010 | AN35: 143373 | AO35: 148388 | AP35: 136674 | AQ35: 180187 | AR35: 198924 | AS35: 212562 | AT35: 189810 | AU35: 196027 | AV35: 252941 | AW35: 271702 | AX35: =IF(_xlfn.FORECAST.ETS(AX$47,H35:AW35,H$47:AW$47)<0,0,_xlfn.FORECAST.ETS(AX$47,H35:AW35,H$47:AW$47)) -> 283563.25 | AY35: 240402 | AZ35: 319074 | BA35: 304873.04 | BB35: 244451.47 | BC35: 224634.78 | BD35: 275419 | BE35: 285827 | BF35: =IF(_xlfn.FORECAST.ETS(BF$47,P35:BE35,P$47:BE$47)<0,0,_xlfn.FORECAST.ETS(BF$47,P35:BE35,P$47:BE$47)) -> 292137.24 | BG35: =IF(_xlfn.FORECAST.ETS(BG$47,Q35:BF35,Q$47:BF$47)<0,0,_xlfn.FORECAST.ETS(BG$47,Q35:BF35,Q$47:BF$47)) -> 300591.21 | BH35: =IF(_xlfn.FORECAST.ETS(BH$47,R35:BG35,R$47:BG$47)<0,0,_xlfn.FORECAST.ETS(BH$47,R35:BG35,R$47:BG$47)) -> 309909.14 | BI35: =IF(_xlfn.FORECAST.ETS(BI$47,S35:BH35,S$47:BH$47)<0,0,_xlfn.FORECAST.ETS(BI$47,S35:BH35,S$47:BH$47)) -> 319354.35 | BJ35: =IF(_xlfn.FORECAST.ETS(BJ$47,T35:BI35,T$47:BI$47)<0,0,_xlfn.FORECAST.ETS(BJ$47,T35:BI35,T$47:BI$47)) -> 328925.82 | BK35: =IF(_xlfn.FORECAST.ETS(BK$47,U35:BJ35,U$47:BJ$47)<0,0,_xlfn.FORECAST.ETS(BK$47,U35:BJ35,U$47:BJ$47)) -> 338736 | BL35: =IF(_xlfn.FORECAST.ETS(BL$47,V35:BK35,V$47:BK$47)<0,0,_xlfn.FORECAST.ETS(BL$47,V35:BK35,V$47:BK$47)) -> 351244.82 | BM35: =IF(_xlfn.FORECAST.ETS(BM$47,W35:BL35,W$47:BL$47)<0,0,_xlfn.FORECAST.ETS(BM$47,W35:BL35,W$47:BL$47)) -> 361032.3 | ... CO35: =IF(_xlfn.FORECAST.ETS(CO$47,AY35:CN35,AY$47:CN$47)<0,0,_xlfn.FORECAST.ETS(CO$47,AY35:CN35,AY$47:CN$47)) -> 625546.02 | CP35: =IF(_xlfn.FORECAST.ETS(CP$47,BA35:CO35,AZ$47:CO$47)<0,0,_xlfn.FORECAST.ETS(CP$47,BA35:CO35,AZ$47:CO$47)) -> #N/A | CQ35: =IF(_xlfn.FORECAST.ETS(CQ$47,BA35:CP35,BA$47:CP$47)<0,0,_xlfn.FORECAST.ETS(CQ$47,BA35:CP35,BA$47:CP$47)) -> #N/A | CR35: =IF(_xlfn.FORECAST.ETS(CR$47,BB35:CQ35,BB$47:CQ$47)<0,0,_xlfn.FORECAST.ETS(CR$47,BB35:CQ35,BB$47:CQ$47)) -> #N/A | CS35: =IF(_xlfn.FORECAST.ETS(CS$47,BC35:CR35,BC$47:CR$47)<0,0,_xlfn.FORECAST.ETS(CS$47,BC35:CR35,BC$47:CR$47)) -> #N/A | CT35: =IF(_xlfn.FORECAST.ETS(CT$47,BD35:CS35,BD$47:CS$47)<0,0,_xlfn.FORECAST.ETS(CT$47,BD35:CS35,BD$47:CS$47)) -> #N/A | CU35: =IF(_xlfn.FORECAST.ETS(CU$47,BE35:CT35,BE$47:CT$47)<0,0,_xlfn.FORECAST.ETS(CU$47,BE35:CT35,BE$47:CT$47)) -> #N/A | CV35: =IF(_xlfn.FORECAST.ETS(CV$47,BF35:CU35,BF$47:CU$47)<0,0,_xlfn.FORECAST.ETS(CV$47,BF35:CU35,BF$47:CU$47)) -> #N/A | CW35: =IF(_xlfn.FORECAST.ETS(CW$47,BG35:CV35,BG$47:CV$47)<0,0,_xlfn.FORECAST.ETS(CW$47,BG35:CV35,BG$47:CV$47)) -> #N/A | CX35: =IF(_xlfn.FORECAST.ETS(CX$47,BH35:CW35,BH$47:CW$47)<0,0,_xlfn.FORECAST.ETS(CX$47,BH35:CW35,BH$47:CW$47)) -> #N/A | ... FJ35: =IF(_xlfn.FORECAST.ETS(FJ$47,DT35:FI35,DT$47:FI$47)<0,0,_xlfn.FORECAST.ETS(FJ$47,DT35:FI35,DT$47:FI$47)) -> #N/A
A36: Total Electricity | B36: gge | C36: =SUM(C22:C35)-C32 -> 21816 | D36: =SUM(D22:D35)-D32 -> 62215 | E36: =SUM(E22:E35)-E32 -> 119059 | F36: =SUM(F22:F35)-F32 -> 171607 | G36: =SUM(G22:G35)-G32 -> 220891 | H36: =SUM(H22:H35)-H32 -> 271183 | I36: =SUM(I22:I35)-I32 -> 355146 | J36: =SUM(J22:J35)-J32 -> 468250 | ... AW36: =SUM(AW22:AW35)-AW32 -> 57093255 | AX36: =SUM(AX22:AX32) -> 49806644 | AY36: =SUM(AY22:AY32) -> 46629012 | AZ36: =SUM(AZ22:AZ32) -> 51660027 | BA36: 70632929 | BB36: 71802127 | BC36: 73568495 | BD36: =SUM(BD23:BD35) -> 81038158 | BE36: 85316361 | BF36: =SUM(BF22:BF32) -> 76236905 | BG36: =SUM(BG22:BG32) -> 79922135 | BH36: =SUM(BH22:BH32) -> 83769900 | BI36: =SUM(BI22:BI32) -> 87528166 | BJ36: =SUM(BJ22:BJ32) -> 91617581 | BK36: =SUM(BK22:BK32) -> 96370495 | BL36: =SUM(BL22:BL32) -> 1.0066093e+08 | BM36: =SUM(BM22:BM32) -> 1.0504759e+08 | ... FJ36: =SUM(FJ22:FJ32) -> 5.3505529e+08
A38: Conversion to gge using energy density from Table 3 in the LCFS regulation
A39: Biodiesel | B39: gge | C39: =C12*(126.13/115.83) -> 2128136.4 | D39: =D12*(126.13/115.83) -> 2856449.8 | E39: =E12*(126.13/115.83) -> 3786855.3 | F39: =F12*(126.13/115.83) -> 4881036.1 | G39: =G12*(126.13/115.83) -> 5451370.6 | H39: =H12*(126.13/115.83) -> 7080620 | I39: =I12*(126.13/115.83) -> 4617792.1 | J39: =J12*(126.13/115.83) -> 4602491.6 | ... AZ39: =AZ12*(126.13/115.83) -> 65635806 | BA39: =BA13*(126.13/115.83) -> 5.7908666e+08 | BB39: =BB13*(126.13/115.83) -> 5.9606454e+08 | BC39: =BC12*(126.13/115.83) -> 70131883 | BD39: =BD12*(126.13/115.83) -> 60712466 | BE39: =BE12*(126.13/115.83) -> 63618250 | BF39: =BF12*(126.13/115.83) -> 59275172 | BG39: =BG12*(126.13/115.83) -> 85906727 | BH39: =BH12*(126.13/115.83) -> 53355144 | BI39: =BI12*(126.13/115.83) -> 57226481 | BJ39: =BJ12*(126.13/115.83) -> 62131836 | ... FJ39: =FJ12*(126.13/115.83) -> 97163645
A40: Biomethane | B40: gge | C40: =SUM(C5:C6)*134.47/115.83 -> 274947.79 | D40: =SUM(D5:D6)*134.47/115.83 -> 381401.17 | E40: =SUM(E5:E6)*134.47/115.83 -> 616407.32 | F40: =SUM(F5:F6)*134.47/115.83 -> 555999.73 | G40: =SUM(G5:G6)*134.47/115.83 -> 544330.1 | H40: =SUM(H5:H6)*134.47/115.83 -> 526133.76 | I40: =SUM(I5:I6)*134.47/115.83 -> 445868.53 | J40: =SUM(J5:J6)*134.47/115.83 -> 334142.22 | ... FJ40: =SUM(FJ5:FJ6)*134.47/115.83 -> 57750754
A41: Fossil Natural Gas | B41: gge | C41: =SUM(C7:C8)*134.47/115.83 -> 20612672 | D41: =SUM(D7:D8)*134.47/115.83 -> 21553167 | E41: =SUM(E7:E8)*134.47/115.83 -> 21698720 | F41: =SUM(F7:F8)*134.47/115.83 -> 21352504 | G41: =SUM(G7:G8)*134.47/115.83 -> 21475544 | H41: =SUM(H7:H8)*134.47/115.83 -> 23162575 | I41: =SUM(I7:I8)*134.47/115.83 -> 26662088 | J41: =SUM(J7:J8)*134.47/115.83 -> 26871766 | ... FJ41: =SUM(FJ7:FJ8)*134.47/115.83 -> 3427759.3
A42: Electricity | B42: gge | C42: =SUM(C10:C10) -> 21816 | D42: =SUM(D10:D10) -> 62215 | E42: =SUM(E10:E10) -> 119059 | F42: =SUM(F10:F10) -> 171607 | G42: =SUM(G10:G10) -> 220891 | H42: =SUM(H10:H10) -> 271183 | I42: =SUM(I10:I10) -> 355146 | J42: =SUM(J10:J10) -> 468250 | ... AZ42: =SUM(AZ10:AZ10) -> 64379991 | BA42: =SUM(BA11:BA11) -> 382422796 | BB42: =SUM(BB11:BB11) -> 354633081 | BC42: =SUM(BC10:BC10) -> 73568495 | BD42: =SUM(BD10:BD10) -> 81038158 | BE42: =SUM(BE10:BE10) -> 85316361 | BF42: =SUM(BF10:BF10) -> 76236905 | BG42: =SUM(BG10:BG10) -> 79922135 | BH42: =SUM(BH10:BH10) -> 83769900 | BI42: =SUM(BI10:BI10) -> 87528166 | BJ42: =SUM(BJ10:BJ10) -> 91617581 | ... FJ42: =SUM(FJ10:FJ10) -> 5.3505529e+08
A43: Ethanol | B43: gge | C43: =SUM(C11:C11)*(81.51/115.83) -> 2.5047862e+08 | D43: =SUM(D11:D11)*(81.51/115.83) -> 2.7293235e+08 | E43: =SUM(E11:E11)*(81.51/115.83) -> 2.7365097e+08 | F43: =SUM(F11:F11)*(81.51/115.83) -> 2.5156496e+08 | G43: =SUM(G11:G11)*(81.51/115.83) -> 2.6057609e+08 | H43: =SUM(H11:H11)*(81.51/115.83) -> 2.6383075e+08 | I43: =SUM(I11:I11)*(81.51/115.83) -> 2.5756901e+08 | J43: =SUM(J11:J11)*(81.51/115.83) -> 2.5563398e+08 | ... AZ43: =SUM(AZ11:AZ11)*(81.51/115.83) -> 2.0863519e+08 | BA43: =SUM(BA12:BA12)*(81.51/115.83) -> 47239286 | BB43: =SUM(BB12:BB12)*(81.51/115.83) -> 51328328 | BC43: =SUM(BC11:BC11)*(81.51/115.83) -> 2.4223268e+08 | BD43: =SUM(BD11:BD11)*(81.51/115.83) -> 2.5751722e+08 | BE43: =SUM(BE11:BE11)*(81.51/115.83) -> 2.5914543e+08 | BF43: =SUM(BF11:BF11)*(81.51/115.83) -> 2.503288e+08 | BG43: =SUM(BG11:BG11)*(81.51/115.83) -> 2.4691124e+08 | BH43: =SUM(BH11:BH11)*(81.51/115.83) -> 2.5773821e+08 | BI43: =SUM(BI11:BI11)*(81.51/115.83) -> 2.7008514e+08 | BJ43: =SUM(BJ11:BJ11)*(81.51/115.83) -> 2.503288e+08 | ... FJ43: =SUM(FJ11:FJ11)*(81.51/115.83) -> 2.7008514e+08
A44: Renewable Diesel | B44: gge | C44: =C13*(129.65/115.83) -> 364074.39 | D44: =D13*(129.65/115.83) -> 399521.91 | E44: =E13*(129.65/115.83) -> 517375.47 | F44: =F13*(129.65/115.83) -> 737695.4 | G44: =G13*(129.65/115.83) -> 797211.5 | H44: =H13*(129.65/115.83) -> 809521.71 | I44: =I13*(129.65/115.83) -> 944359.72 | J44: =J13*(129.65/115.83) -> 7315545.2 | ... AZ44: =AZ13*(129.65/115.83) -> 5.3861361e+08 | BA44: =BA14*(129.65/115.83) -> 4676230.3 | BB44: =BB14*(129.65/115.83) -> 8132987.1 | BC44: =BC13*(129.65/115.83) -> 5.8011307e+08 | BD44: =BD13*(129.65/115.83) -> 6.7494686e+08 | BE44: =BE13*(129.65/115.83) -> 7.2985652e+08 | BF44: =BF13*(129.65/115.83) -> 6.4161293e+08 | BG44: =BG13*(129.65/115.83) -> 4.9405582e+08 | BH44: =BH13*(129.65/115.83) -> 5.0150656e+08 | BI44: =BI13*(129.65/115.83) -> 6.4936115e+08 | BJ44: =BJ13*(129.65/115.83) -> 5.9602874e+08 | ... FJ44: =FJ13*(129.65/115.83) -> 1.1445649e+09
A45: Other (Hyrdrogen, AJF, Renewable Naphtha, Propane) | B45: gge | C45: =C9+(C14*(126.37/115.83))+(C15*(122.37/115.83))+(C16*(89.63/115.83)) -> 0 | D45: =D9+(D14*(126.37/115.83))+(D15*(122.37/115.83))+(D16*(89.63/115.83)) -> 0 | E45: =E9+(E14*(126.37/115.83))+(E15*(122.37/115.83))+(E16*(89.63/115.83)) -> 0 | F45: =F9+(F14*(126.37/115.83))+(F15*(122.37/115.83))+(F16*(89.63/115.83)) -> 0 | G45: =G9+(G14*(126.37/115.83))+(G15*(122.37/115.83))+(G16*(89.63/115.83)) -> 0 | H45: =H9+(H14*(126.37/115.83))+(H15*(122.37/115.83))+(H16*(89.63/115.83)) -> 0 | I45: =I9+(I14*(126.37/115.83))+(I15*(122.37/115.83))+(I16*(89.63/115.83)) -> 0 | J45: =J9+(J14*(126.37/115.83))+(J15*(122.37/115.83))+(J16*(89.63/115.83)) -> 0 | ... AZ45: =AZ9+(AZ14*(126.37/115.83))+(AZ15*(122.37/115.83))+(AZ16*(89.63/115.83)) -> 23653039 | BA45: =BA9+(BA15*(126.37/115.83))+(BA16*(122.37/115.83))+(BA17*(89.63/115.83)) -> 2.4385943e+09 | BB45: =BB9+(BB15*(126.37/115.83))+(BB16*(122.37/115.83))+(BB17*(89.63/115.83)) -> 2.3482584e+09 | BC45: =BC9+(BC14*(126.37/115.83))+(BC15*(122.37/115.83))+(BC16*(89.63/115.83)) -> 27532982 | BD45: =BD9+(BD14*(126.37/115.83))+(BD15*(122.37/115.83))+(BD16*(89.63/115.83)) -> 41359165 | BE45: =BE9+(BE14*(126.37/115.83))+(BE15*(122.37/115.83))+(BE16*(89.63/115.83)) -> 40037392 | BF45: =BF9+(BF14*(126.37/115.83))+(BF15*(122.37/115.83))+(BF16*(89.63/115.83)) -> 23799226 | BG45: =BG9+(BG14*(126.37/115.83))+(BG15*(122.37/115.83))+(BG16*(89.63/115.83)) -> 45179183 | BH45: =BH9+(BH14*(126.37/115.83))+(BH15*(122.37/115.83))+(BH16*(89.63/115.83)) -> 49556208 | BI45: =BI9+(BI14*(126.37/115.83))+(BI15*(122.37/115.83))+(BI16*(89.63/115.83)) -> 62759560 | BJ45: =BJ9+(BJ14*(126.37/115.83))+(BJ15*(122.37/115.83))+(BJ16*(89.63/115.83)) -> 31902021 | ... FJ45: =FJ9+(FJ14*(126.37/115.83))+(FJ15*(122.37/115.83))+(FJ16*(89.63/115.83)) -> 3.4297273e+08
C46: 2011.1 | D46: 2011.2 | E46: 2011.3 | F46: 2011.4 | G46: 2012.1 | H46: 2012.2 | I46: 2012.3 | J46: 2012.4 | K46: 2013.1 | L46: 2013.2 | M46: 2013.1 | N46: 2013.31 | O46: 2014.1 | P46: 2014.2 | Q46: 2014.3 | R46: 2014.4 | S46: 2015.1 | T46: 2015.2 | U46: 2015.3 | V46: 2015.4 | W46: 2016.1 | X46: 2016.2 | Y46: 2016.3 | Z46: 2016.4 | AA46: 2017.1 | AB46: 2017.2 | AC46: 2017.3 | AD46: 2017.4 | AE46: 2018.1 | AF46: 2018.2 | AG46: 2018.3 | AH46: 2018.4 | AI46: 2019.1 | AJ46: 2019.2 | AK46: 2019.3 | AL46: 2019.4 | AM46: 2020.1 | AN46: 2020.2 | AO46: 2020.3 | AP46: 2020.4 | AQ46: 2021.1 | AR46: 2021.2 | AS46: 2021.3 | AT46: 2021.4 | AU46: 2022.1 | AV46: 2022.2 | AW46: 2022.3 | AX46: 2022.4 | AY46: 2022.5 | AZ46: 2022.6 | BA46: 2022.7 | BB46: 2022.8
A47: Credits (MT) from "Fuels" tab | C47: 40603 | D47: 40695 | E47: 40787 | F47: 40878 | G47: 40969 | H47: 41061 | I47: 41153 | J47: 41244 | K47: 41334 | L47: 41426 | M47: 41518 | N47: 41609 | O47: 41699 | P47: 41791 | Q47: 41883 | R47: 41974 | S47: 42064 | T47: 42156 | U47: 42248 | V47: 42339 | W47: 42430 | X47: 42522 | Y47: 42614 | Z47: 42705 | AA47: 42795 | AB47: 42887 | AC47: 42979 | AD47: 43070 | AE47: 43160 | AF47: 43252 | AG47: 43344 | AH47: 43435 | AI47: 43525 | AJ47: 43617 | AK47: 43709 | AL47: 43800 | AM47: 43891 | AN47: 43983 | AO47: 44075 | AP47: 44166 | AQ47: 44256 | AR47: 44348 | AS47: 44440 | AT47: 44531 | AU47: 44621 | AV47: 44713 | AW47: 44805 | AX47: 44896 | AY47: 44986 | AZ47: 45078 | BA47: 45170 | BB47: 45261 | BC47: 45352 | BD47: 45444 | BE47: 45536 | BF47: 45627 | BG47: 45717 | BH47: 45809 | BI47: 45901 | BJ47: 45992 | BK47: 46082 | BL47: 46174 | BM47: 46266 | BN47: 46357 | BO47: 46447 | BP47: 46539 | BQ47: 46631 | BR47: 46722 | BS47: 46813 | BT47: 46905 | BU47: 46997 | BV47: 47088 | BW47: 47178 | BX47: 47270 | BY47: 47362 | BZ47: 47453 | CA47: 47543 | CB47: 47635 | CC47: 47727 | CD47: 47818 | CE47: 47908 | CF47: 48000 | CG47: 48092 | CH47: 48183 | CI47: 48274 | CJ47: 48366 | CK47: 48458 | CL47: 48549 | CM47: 48639 | CN47: 48731 | CO47: 48823 | CP47: 48914 | CQ47: 49004 | CR47: 49096 | CS47: 49188 | CT47: 49279 | CU47: 49369 | CV47: 49461 | CW47: 49553 | CX47: 49644 | CY47: 49735 | CZ47: 49827 | DA47: 49919 | DB47: 50010 | DC47: 50100 | DD47: 50192 | DE47: 50284 | DF47: 50375 | DG47: 50465 | DH47: 50557 | DI47: 50649 | DJ47: 50740 | DK47: 50830 | DL47: 50922 | DM47: 51014 | DN47: 51105 | DO47: 51196 | DP47: 51288 | DQ47: 51380 | DR47: 51471 | DS47: 51561 | DT47: 51653 | DU47: 51745 | DV47: 51836 | DW47: 51926 | DX47: 52018 | DY47: 52110 | DZ47: 52201 | EA47: 52291 | EB47: 52383 | EC47: 52475 | ED47: 52566 | EE47: 52657 | EF47: 52749 | EG47: 52841 | EH47: 52932 | EI47: 53022 | EJ47: 53114 | EK47: 53206 | EL47: 53297 | EM47: 53387 | EN47: 53479 | EO47: 53571 | EP47: 53662 | EQ47: 53752 | ER47: 53844 | ES47: 53936 | ET47: 54027 | EU47: 54118 | EV47: 54210 | EW47: 54302 | EX47: 54393 | EY47: 54483 | EZ47: 54575 | FA47: 54667 | FB47: 54758 | FC47: 54848 | FD47: 54940 | FE47: 55032 | FF47: 55123 | FG47: 55213 | FH47: 55305 | FI47: 55397 | FJ47: 55488
C48: ='Qrtly Credit-Deficit Generation'!C21 -> 2011Q1 | D48: ='Qrtly Credit-Deficit Generation'!D21 -> Q2 | E48: ='Qrtly Credit-Deficit Generation'!E21 -> Q3 | F48: ='Qrtly Credit-Deficit Generation'!F21 -> Q4 | G48: ='Qrtly Credit-Deficit Generation'!G21 -> 2012Q1 | H48: ='Qrtly Credit-Deficit Generation'!H21 -> Q2 | I48: ='Qrtly Credit-Deficit Generation'!I21 -> Q3 | J48: ='Qrtly Credit-Deficit Generation'!J21 -> Q4 | ... AR48: ='Qrtly Credit-Deficit Generation'!AR21 -> Q2 | AS48: =AS4 -> Q3 | AT48: =AT4 -> Q4 | AU48: ='Qrtly Credit-Deficit Generation'!AU21 -> 2022Q1 | AV48: ='Qrtly Credit-Deficit Generation'!AV21 -> Q2 | AW48: ='Qrtly Credit-Deficit Generation'!AW21 -> Q3 | AX48: ='Qrtly Credit-Deficit Generation'!AX21 -> Q4 | AY48: ='Qrtly Credit-Deficit Generation'!AY21 -> 2023Q1 | AZ48: ='Qrtly Credit-Deficit Generation'!AZ21 -> Q2 | BA48: =BA4 -> Q3 | BB48: =BB4 -> Q4 | BC48: ='Qrtly Credit-Deficit Generation'!BC21 -> 2024Q1 | BD48: ='Qrtly Credit-Deficit Generation'!BD21 -> Q2 | BE48: ='Qrtly Credit-Deficit Generation'!BE21 -> Q3 | BF48: ='Qrtly Credit-Deficit Generation'!BF21 -> Q4 | BG48: ='Qrtly Credit-Deficit Generation'!BG21 -> 2025Q1 | BH48: ='Qrtly Credit-Deficit Generation'!BH21 -> Q2 | BI48: =BE4 -> Q3 | BJ48: =BF4 -> Q4 | BK48: ='Qrtly Credit-Deficit Generation'!BK21 -> 2026Q1 | BL48: ='Qrtly Credit-Deficit Generation'!BL21 -> Q2 | BM48: ='Qrtly Credit-Deficit Generation'!BM21 -> Q3 | BN48: ='Qrtly Credit-Deficit Generation'!BN21 -> Q4 | BO48: ='Qrtly Credit-Deficit Generation'!BO21 -> 2027Q1 | BP48: ='Qrtly Credit-Deficit Generation'!BP21 -> Q2 | BQ48: =BM4 -> Q3 | BR48: =BN4 -> Q4 | BS48: ='Qrtly Credit-Deficit Generation'!BS21 -> 2028Q1 | BT48: ='Qrtly Credit-Deficit Generation'!BT21 -> Q2 | BU48: ='Qrtly Credit-Deficit Generation'!BU21 -> Q3 | BV48: ='Qrtly Credit-Deficit Generation'!BV21 -> Q4 | BW48: ='Qrtly Credit-Deficit Generation'!BW21 -> 2029Q1 | BX48: ='Qrtly Credit-Deficit Generation'!BX21 -> Q2 | BY48: =BU4 -> Q3 | BZ48: =BV4 -> Q4 | CA48: ='Qrtly Credit-Deficit Generation'!CA21 -> 2030Q1 | CB48: ='Qrtly Credit-Deficit Generation'!CB21 -> Q2 | CC48: ='Qrtly Credit-Deficit Generation'!CC21 -> Q3 | CD48: ='Qrtly Credit-Deficit Generation'!CD21 -> Q4 | CE48: ='Qrtly Credit-Deficit Generation'!CE21 -> 2031Q1 | CF48: ='Qrtly Credit-Deficit Generation'!CF21 -> Q2 | CG48: =CC4 -> Q3 | CH48: =CD4 -> Q4 | CI48: ='Qrtly Credit-Deficit Generation'!CI21 -> 2032Q1 | CJ48: ='Qrtly Credit-Deficit Generation'!CJ21 -> Q2 | CK48: ='Qrtly Credit-Deficit Generation'!CK21 -> Q3 | CL48: ='Qrtly Credit-Deficit Generation'!CL21 -> Q4 | CM48: ='Qrtly Credit-Deficit Generation'!CM21 -> 2033Q1 | CN48: ='Qrtly Credit-Deficit Generation'!CN21 -> Q2 | CO48: =CK4 -> Q3 | CP48: =CL4 -> Q4 | CQ48: ='Qrtly Credit-Deficit Generation'!CQ21 -> 2034Q1 | CR48: ='Qrtly Credit-Deficit Generation'!CR21 -> Q2 | CS48: ='Qrtly Credit-Deficit Generation'!CS21 -> Q3 | CT48: ='Qrtly Credit-Deficit Generation'!CT21 -> Q4 | CU48: ='Qrtly Credit-Deficit Generation'!CU21 -> 2035Q1 | CV48: ='Qrtly Credit-Deficit Generation'!CV21 -> Q2 | CW48: =CS4 -> Q3 | CX48: =CT4 -> Q4 | CY48: ='Qrtly Credit-Deficit Generation'!CY21 -> 2036Q1 | CZ48: ='Qrtly Credit-Deficit Generation'!CZ21 -> Q2 | DA48: ='Qrtly Credit-Deficit Generation'!DA21 -> Q3 | DB48: ='Qrtly Credit-Deficit Generation'!DB21 -> Q4 | DC48: ='Qrtly Credit-Deficit Generation'!DC21 -> 2037Q1 | DD48: ='Qrtly Credit-Deficit Generation'!DD21 -> Q2 | DE48: =DA4 -> Q3 | DF48: =DB4 -> Q4 | DG48: ='Qrtly Credit-Deficit Generation'!DG21 -> 2038Q1 | DH48: ='Qrtly Credit-Deficit Generation'!DH21 -> Q2 | DI48: ='Qrtly Credit-Deficit Generation'!DI21 -> Q3 | DJ48: ='Qrtly Credit-Deficit Generation'!DJ21 -> Q4 | DK48: ='Qrtly Credit-Deficit Generation'!DK21 -> 2039Q1 | DL48: ='Qrtly Credit-Deficit Generation'!DL21 -> Q2 | DM48: ='Qrtly Credit-Deficit Generation'!DM21 -> Q3 | DN48: ='Qrtly Credit-Deficit Generation'!DN21 -> Q4 | ... FJ48: ='Qrtly Credit-Deficit Generation'!FJ21 -> 0
A49: Bio-CNG | C49: ='Qrtly Credit-Deficit Generation'!C4 -> 0 | D49: ='Qrtly Credit-Deficit Generation'!D4 -> 0 | E49: ='Qrtly Credit-Deficit Generation'!E4 -> 0 | F49: ='Qrtly Credit-Deficit Generation'!F4 -> 0 | G49: ='Qrtly Credit-Deficit Generation'!G4 -> 0 | H49: ='Qrtly Credit-Deficit Generation'!H4 -> 0 | I49: ='Qrtly Credit-Deficit Generation'!I4 -> 0 | J49: ='Qrtly Credit-Deficit Generation'!J4 -> 0 | ... AX49: ='Qrtly Credit-Deficit Generation'!AX4 -> 1208871 | AY49: 1052639 | AZ49: 1341628 | BA49: 1394087 | BB49: 1478363 | BC49: 1526145 | BD49: 1848652 | BE49: 2098711 | BF49: =IF(FORECAST(BF5,AB49:BE49,AB5:BE5)<0,0,FORECAST(BF5,AB49:BE49,AB5:BE5)) -> 1166988.1 | BG49: =IF(FORECAST(BG5,AC49:BF49,AC5:BF5)<0,0,FORECAST(BG5,AC49:BF49,AC5:BF5)) -> 992292.14 | BH49: =IF(FORECAST(BH5,AD49:BG49,AD5:BG5)<0,0,FORECAST(BH5,AD49:BG49,AD5:BG5)) -> 1095076.3 | BI49: =IF(FORECAST(BI5,AE49:BH49,AE5:BH5)<0,0,FORECAST(BI5,AE49:BH49,AE5:BH5)) -> 1243474.3 | BJ49: =IF(FORECAST(BJ5,AF49:BI49,AF5:BI5)<0,0,FORECAST(BJ5,AF49:BI49,AF5:BI5)) -> 1179177.2 | BK49: =IF(FORECAST(BK5,AG49:BJ49,AG5:BJ5)<0,0,FORECAST(BK5,AG49:BJ49,AG5:BJ5)) -> 975650.25 | BL49: =IF(FORECAST(BL5,AH49:BK49,AH5:BK5)<0,0,FORECAST(BL5,AH49:BK49,AH5:BK5)) -> 1092076.7 | BM49: =IF(FORECAST(BM5,AI49:BL49,AI5:BL5)<0,0,FORECAST(BM5,AI49:BL49,AI5:BL5)) -> 1258418.7 | ... FJ49: =IF(FORECAST(FJ5,EF49:FI49,EF5:FI5)<0,0,FORECAST(FJ5,EF49:FI49,EF5:FI5)) -> 1277608.3
A50: Bio-LNG | C50: ='Qrtly Credit-Deficit Generation'!C5 -> 2212 | D50: ='Qrtly Credit-Deficit Generation'!D5 -> 3069 | E50: ='Qrtly Credit-Deficit Generation'!E5 -> 4960 | F50: ='Qrtly Credit-Deficit Generation'!F5 -> 4474 | G50: ='Qrtly Credit-Deficit Generation'!G5 -> 4367 | H50: ='Qrtly Credit-Deficit Generation'!H5 -> 4221 | I50: ='Qrtly Credit-Deficit Generation'!I5 -> 3577 | J50: ='Qrtly Credit-Deficit Generation'!J5 -> 2680 | ... AX50: ='Qrtly Credit-Deficit Generation'!AX5 -> 11715 | AY50: 14272 | AZ50: 15147 | BA50: 14739 | BB50: 14647 | BC50: 13919 | BD50: 14530 | BE50: 16471 | BF50: =IF(FORECAST(BF6,AB50:BE50,AB6:BE6)<0,0,FORECAST(BF6,AB50:BE50,AB6:BE6)) -> 12754.272 | BG50: =IF(FORECAST(BG6,AC50:BF50,AC6:BF6)<0,0,FORECAST(BG6,AC50:BF50,AC6:BF6)) -> 15101.009 | BH50: =IF(FORECAST(BH6,AD50:BG50,AD6:BG6)<0,0,FORECAST(BH6,AD50:BG50,AD6:BG6)) -> 15323.141 | BI50: =IF(FORECAST(BI6,AE50:BH50,AE6:BH6)<0,0,FORECAST(BI6,AE50:BH50,AE6:BH6)) -> 15329.054 | BJ50: =IF(FORECAST(BJ6,AF50:BI50,AF6:BI6)<0,0,FORECAST(BJ6,AF50:BI50,AF6:BI6)) -> 13868.097 | BK50: =IF(FORECAST(BK6,AG50:BJ50,AG6:BJ6)<0,0,FORECAST(BK6,AG50:BJ50,AG6:BJ6)) -> 14567.786 | BL50: =IF(FORECAST(BL6,AH50:BK50,AH6:BK6)<0,0,FORECAST(BL6,AH50:BK50,AH6:BK6)) -> 14877.474 | BM50: =IF(FORECAST(BM6,AI50:BL50,AI6:BL6)<0,0,FORECAST(BM6,AI50:BL50,AI6:BL6)) -> 14926.938 | ... FJ50: =IF(FORECAST(FJ6,EF50:FI50,EF6:FI6)<0,0,FORECAST(FJ6,EF50:FI50,EF6:FI6)) -> 14763.591
A51: Fossil CNG | C51: ='Qrtly Credit-Deficit Generation'!C6 -> 32732 | D51: ='Qrtly Credit-Deficit Generation'!D6 -> 34288 | E51: ='Qrtly Credit-Deficit Generation'!E6 -> 33231 | F51: ='Qrtly Credit-Deficit Generation'!F6 -> 32727 | G51: ='Qrtly Credit-Deficit Generation'!G6 -> 32327 | H51: ='Qrtly Credit-Deficit Generation'!H6 -> 33371 | I51: ='Qrtly Credit-Deficit Generation'!I6 -> 39529 | J51: ='Qrtly Credit-Deficit Generation'!J6 -> 38669 | ... AX51: ='Qrtly Credit-Deficit Generation'!AX6 -> 744 | AY51: 382 | AZ51: 405 | BA51: 520 | BB51: 329 | BC51: 168 | BD51: 178 | BE51: 100 | BF51: =IF(FORECAST(BF7,AB51:BE51,AB7:BE7)<0,0,FORECAST(BF7,AB51:BE51,AB7:BE7)) -> 0 | BG51: =IF(FORECAST(BG7,AC51:BF51,AC7:BF7)<0,0,FORECAST(BG7,AC51:BF51,AC7:BF7)) -> 0 | BH51: =IF(FORECAST(BH7,AD51:BG51,AD7:BG7)<0,0,FORECAST(BH7,AD51:BG51,AD7:BG7)) -> 0 | BI51: =IF(FORECAST(BI7,AE51:BH51,AE7:BH7)<0,0,FORECAST(BI7,AE51:BH51,AE7:BH7)) -> 0 | BJ51: =IF(FORECAST(BJ7,AF51:BI51,AF7:BI7)<0,0,FORECAST(BJ7,AF51:BI51,AF7:BI7)) -> 0 | BK51: =IF(FORECAST(BK7,AG51:BJ51,AG7:BJ7)<0,0,FORECAST(BK7,AG51:BJ51,AG7:BJ7)) -> 0 | BL51: =IF(FORECAST(BL7,AH51:BK51,AH7:BK7)<0,0,FORECAST(BL7,AH51:BK51,AH7:BK7)) -> 299.92986 | BM51: =IF(FORECAST(BM7,AI51:BL51,AI7:BL7)<0,0,FORECAST(BM7,AI51:BL51,AI7:BL7)) -> 314.6476 | ... FJ51: =IF(FORECAST(FJ7,EF51:FI51,EF7:FI7)<0,0,FORECAST(FJ7,EF51:FI51,EF7:FI7)) -> 865.97133
A52: Fossil LNG | C52: ='Qrtly Credit-Deficit Generation'!C7 -> 7202 | D52: ='Qrtly Credit-Deficit Generation'!D7 -> 7881 | E52: ='Qrtly Credit-Deficit Generation'!E7 -> 8212 | F52: ='Qrtly Credit-Deficit Generation'!F7 -> 8117 | G52: ='Qrtly Credit-Deficit Generation'!G7 -> 7899 | H52: ='Qrtly Credit-Deficit Generation'!H7 -> 9787 | I52: ='Qrtly Credit-Deficit Generation'!I7 -> 10413 | J52: ='Qrtly Credit-Deficit Generation'!J7 -> 11175 | ... AZ52: ='Qrtly Credit-Deficit Generation'!AZ7 -> 0 | BE52: 0
A53: Hydrogen | C53: ='Qrtly Credit-Deficit Generation'!C8 -> 0 | D53: ='Qrtly Credit-Deficit Generation'!D8 -> 0 | E53: ='Qrtly Credit-Deficit Generation'!E8 -> 0 | F53: ='Qrtly Credit-Deficit Generation'!F8 -> 0 | G53: ='Qrtly Credit-Deficit Generation'!G8 -> 0 | H53: ='Qrtly Credit-Deficit Generation'!H8 -> 0 | I53: ='Qrtly Credit-Deficit Generation'!I8 -> 0 | J53: ='Qrtly Credit-Deficit Generation'!J8 -> 0 | ... AX53: ='Qrtly Credit-Deficit Generation'!AX8 -> 16067 | AY53: 15098 | AZ53: 15828 | BA53: 15556 | BB53: 14298 | BC53: 13327 | BD53: 12287 | BE53: 11606 | BF53: =IF(FORECAST(BF9,AB53:BE53,AB9:BE9)<0,0,FORECAST(BF9,AB53:BE53,AB9:BE9)) -> 12854.678 | BG53: =IF(FORECAST(BG9,AC53:BF53,AC9:BF9)<0,0,FORECAST(BG9,AC53:BF53,AC9:BF9)) -> 15376.283 | BH53: =IF(FORECAST(BH9,AD53:BG53,AD9:BG9)<0,0,FORECAST(BH9,AD53:BG53,AD9:BG9)) -> 14987.966 | BI53: =IF(FORECAST(BI9,AE53:BH53,AE9:BH9)<0,0,FORECAST(BI9,AE53:BH53,AE9:BH9)) -> 16099.441 | BJ53: =IF(FORECAST(BJ9,AF53:BI53,AF9:BI9)<0,0,FORECAST(BJ9,AF53:BI53,AF9:BI9)) -> 16897.931 | BK53: =IF(FORECAST(BK9,AG53:BJ53,AG9:BJ9)<0,0,FORECAST(BK9,AG53:BJ53,AG9:BJ9)) -> 18555.752 | BL53: =IF(FORECAST(BL9,AH53:BK53,AH9:BK9)<0,0,FORECAST(BL9,AH53:BK53,AH9:BK9)) -> 19774.15 | BM53: =IF(FORECAST(BM9,AI53:BL53,AI9:BL9)<0,0,FORECAST(BM9,AI53:BL53,AI9:BL9)) -> 20535.843 | ... FJ53: =IF(FORECAST(FJ9,EF53:FI53,EF9:FI9)<0,0,FORECAST(FJ9,EF53:FI53,EF9:FI9)) -> 77512.627
A54: Electricity | C54: ='Qrtly Credit-Deficit Generation'!C37 -> 459 | D54: ='Qrtly Credit-Deficit Generation'!D37 -> 1293 | E54: ='Qrtly Credit-Deficit Generation'!E37 -> 2455 | F54: ='Qrtly Credit-Deficit Generation'!F37 -> 3536 | G54: ='Qrtly Credit-Deficit Generation'!G37 -> 4519 | H54: ='Qrtly Credit-Deficit Generation'!H37 -> 5560 | I54: ='Qrtly Credit-Deficit Generation'!I37 -> 7294 | J54: ='Qrtly Credit-Deficit Generation'!J37 -> 9611 | ... BE54: ='Qrtly Credit-Deficit Generation'!BE37 -> 2353377.3 | BF54: =IF(FORECAST(BF10,AB54:BE54,AB10:BE10)<0,0,FORECAST(BF10,AB54:BE54,AB10:BE10)) -> 2165994.5 | BG54: =IF(FORECAST(BG10,AC54:BF54,AC10:BF10)<0,0,FORECAST(BG10,AC54:BF54,AC10:BF10)) -> 2278383.3 | BH54: =IF(FORECAST(BH10,AD54:BG54,AD10:BG10)<0,0,FORECAST(BH10,AD54:BG54,AD10:BG10)) -> 2394459.3 | BI54: =IF(FORECAST(BI10,AE54:BH54,AE10:BH10)<0,0,FORECAST(BI10,AE54:BH54,AE10:BH10)) -> 2505901.7 | BJ54: =IF(FORECAST(BJ10,AF54:BI54,AF10:BI10)<0,0,FORECAST(BJ10,AF54:BI54,AF10:BI10)) -> 2623784 | BK54: =IF(FORECAST(BK10,AG54:BJ54,AG10:BJ10)<0,0,FORECAST(BK10,AG54:BJ54,AG10:BJ10)) -> 2759082.8 | BL54: =IF(FORECAST(BL10,AH54:BK54,AH10:BK10)<0,0,FORECAST(BL10,AH54:BK54,AH10:BK10)) -> 2877746.9 | BM54: =IF(FORECAST(BM10,AI54:BL54,AI10:BL10)<0,0,FORECAST(BM10,AI54:BL54,AI10:BL10)) -> 2996415.6 | ... FJ54: =IF(FORECAST(FJ10,EF54:FI54,EF10:FI10)<0,0,FORECAST(FJ10,EF54:FI54,EF10:FI10)) -> 15120972
A55: Ethanol | C55: ='Qrtly Credit-Deficit Generation'!C9 -> 217913 | D55: ='Qrtly Credit-Deficit Generation'!D9 -> 252550 | E55: ='Qrtly Credit-Deficit Generation'!E9 -> 282189 | F55: ='Qrtly Credit-Deficit Generation'!F9 -> 270901 | G55: ='Qrtly Credit-Deficit Generation'!G9 -> 261269 | H55: ='Qrtly Credit-Deficit Generation'!H9 -> 264615 | I55: ='Qrtly Credit-Deficit Generation'!I9 -> 358459 | J55: ='Qrtly Credit-Deficit Generation'!J9 -> 334751 | ... AX55: ='Qrtly Credit-Deficit Generation'!AX9 -> 927177 | AY55: 827472 | AZ55: 736436 | BA55: 882062 | BB55: 916926 | BC55: 810581 | BD55: 910853 | BE55: 866406 | BF55: =IF(FORECAST(BF11,AB55:BE55,AB11:BE11)<0,0,FORECAST(BF11,AB55:BE55,AB11:BE11)) -> 906093.05 | BG55: =IF(FORECAST(BG11,AC55:BF55,AC11:BF11)<0,0,FORECAST(BG11,AC55:BF55,AC11:BF11)) -> 900355.85 | BH55: =IF(FORECAST(BH11,AD55:BG55,AD11:BG11)<0,0,FORECAST(BH11,AD55:BG55,AD11:BG11)) -> 933213.05 | BI55: =IF(FORECAST(BI11,AE55:BH55,AE11:BH11)<0,0,FORECAST(BI11,AE55:BH55,AE11:BH11)) -> 970209.57 | BJ55: =IF(FORECAST(BJ11,AF55:BI55,AF11:BI11)<0,0,FORECAST(BJ11,AF55:BI55,AF11:BI11)) -> 918982.75 | BK55: =IF(FORECAST(BK11,AG55:BJ55,AG11:BJ11)<0,0,FORECAST(BK11,AG55:BJ55,AG11:BJ11)) -> 914457.74 | BL55: =IF(FORECAST(BL11,AH55:BK55,AH11:BK11)<0,0,FORECAST(BL11,AH55:BK55,AH11:BK11)) -> 955642.62 | BM55: =IF(FORECAST(BM11,AI55:BL55,AI11:BL11)<0,0,FORECAST(BM11,AI55:BL55,AI11:BL11)) -> 1004872.3 | ... FJ55: =IF(FORECAST(FJ11,EF55:FI55,EF11:FI11)<0,0,FORECAST(FJ11,EF55:FI55,EF11:FI11)) -> 980287.06
A56: Biodiesel | C56: ='Qrtly Credit-Deficit Generation'!C10 -> 12300 | D56: ='Qrtly Credit-Deficit Generation'!D10 -> 21555 | E56: ='Qrtly Credit-Deficit Generation'!E10 -> 22424 | F56: ='Qrtly Credit-Deficit Generation'!F10 -> 27988 | G56: ='Qrtly Credit-Deficit Generation'!G10 -> 35382 | H56: ='Qrtly Credit-Deficit Generation'!H10 -> 41919 | I56: ='Qrtly Credit-Deficit Generation'!I10 -> 34052 | J56: ='Qrtly Credit-Deficit Generation'!J10 -> 37994 | ... AX56: ='Qrtly Credit-Deficit Generation'!AX10 -> 542391 | AY56: 493424 | AZ56: 468031 | BA56: 497047 | BB56: 511698 | BC56: 460829 | BD56: 440431 | BE56: 441762 | BF56: =IF(FORECAST(BF12,AB56:BE56,AB12:BE12)<0,0,FORECAST(BF12,AB56:BE56,AB12:BE12)) -> 443691.89 | BG56: =IF(FORECAST(BG12,AC56:BF56,AC12:BF12)<0,0,FORECAST(BG12,AC56:BF56,AC12:BF12)) -> 612296.88 | BH56: =IF(FORECAST(BH12,AD56:BG56,AD12:BG12)<0,0,FORECAST(BH12,AD56:BG56,AD12:BG12)) -> 408217.64 | BI56: =IF(FORECAST(BI12,AE56:BH56,AE12:BH12)<0,0,FORECAST(BI12,AE56:BH56,AE12:BH12)) -> 433615.74 | BJ56: =IF(FORECAST(BJ12,AF56:BI56,AF12:BI12)<0,0,FORECAST(BJ12,AF56:BI56,AF12:BI12)) -> 465516.42 | BK56: =IF(FORECAST(BK12,AG56:BJ56,AG12:BJ12)<0,0,FORECAST(BK12,AG56:BJ56,AG12:BJ12)) -> 492305.33 | BL56: =IF(FORECAST(BL12,AH56:BK56,AH12:BK12)<0,0,FORECAST(BL12,AH56:BK56,AH12:BK12)) -> 429771.83 | BM56: =IF(FORECAST(BM12,AI56:BL56,AI12:BL12)<0,0,FORECAST(BM12,AI56:BL56,AI12:BL12)) -> 463938.72 | ... FJ56: =IF(FORECAST(FJ12,EF56:FI56,EF12:FI12)<0,0,FORECAST(FJ12,EF56:FI56,EF12:FI12)) -> #DIV/0!
A57: Renewable Diesel | C57: ='Qrtly Credit-Deficit Generation'!C11 -> 3070 | D57: ='Qrtly Credit-Deficit Generation'!D11 -> 3368 | E57: ='Qrtly Credit-Deficit Generation'!E11 -> 4362 | F57: ='Qrtly Credit-Deficit Generation'!F11 -> 6220 | G57: ='Qrtly Credit-Deficit Generation'!G11 -> 6701 | H57: ='Qrtly Credit-Deficit Generation'!H11 -> 6804 | I57: ='Qrtly Credit-Deficit Generation'!I11 -> 7938 | J57: ='Qrtly Credit-Deficit Generation'!J11 -> 51216 | ... AX57: ='Qrtly Credit-Deficit Generation'!AX11 -> 2557211 | AY57: 2504078 | AZ57: 2847161 | BA57: 3182501 | BB57: 3395112 | BC57: 3149540 | BD57: 3492934 | BE57: 3875405 | BF57: =IF(FORECAST(BF13,AB57:BE57,AB13:BE13)<0,0,FORECAST(BF13,AB57:BE57,AB13:BE13)) -> 3474023 | BG57: =IF(FORECAST(BG13,AC57:BF57,AC13:BF13)<0,0,FORECAST(BG13,AC57:BF57,AC13:BF13)) -> 2756924 | BH57: =IF(FORECAST(BH13,AD57:BG57,AD13:BG13)<0,0,FORECAST(BH13,AD57:BG57,AD13:BG13)) -> 2793118.9 | BI57: =IF(FORECAST(BI13,AE57:BH57,AE13:BH13)<0,0,FORECAST(BI13,AE57:BH57,AE13:BH13)) -> 3506334 | BJ57: =IF(FORECAST(BJ13,AF57:BI57,AF13:BI13)<0,0,FORECAST(BJ13,AF57:BI57,AF13:BI13)) -> 3247958.1 | BK57: =IF(FORECAST(BK13,AG57:BJ57,AG13:BJ13)<0,0,FORECAST(BK13,AG57:BJ57,AG13:BJ13)) -> 2724166.7 | BL57: =IF(FORECAST(BL13,AH57:BK57,AH13:BK13)<0,0,FORECAST(BL13,AH57:BK57,AH13:BK13)) -> 2973159.4 | BM57: =IF(FORECAST(BM13,AI57:BL57,AI13:BL13)<0,0,FORECAST(BM13,AI57:BL57,AI13:BL13)) -> 3079811.1 | ... FJ57: =IF(FORECAST(FJ13,EF57:FI57,EF13:FI13)<0,0,FORECAST(FJ13,EF57:FI57,EF13:FI13)) -> 5785375
A58: Alternative Jet Fuel | C58: ='Qrtly Credit-Deficit Generation'!C12 -> 0 | D58: ='Qrtly Credit-Deficit Generation'!D12 -> 0 | E58: ='Qrtly Credit-Deficit Generation'!E12 -> 0 | F58: ='Qrtly Credit-Deficit Generation'!F12 -> 0 | G58: ='Qrtly Credit-Deficit Generation'!G12 -> 0 | H58: ='Qrtly Credit-Deficit Generation'!H12 -> 0 | I58: ='Qrtly Credit-Deficit Generation'!I12 -> 0 | J58: ='Qrtly Credit-Deficit Generation'!J12 -> 0 | ... AX58: ='Qrtly Credit-Deficit Generation'!AX12 -> 9549 | AY58: 24919 | AZ58: 37258 | BA58: 22647 | BB58: 37508 | BC58: 59320 | BD58: 122696 | BE58: 126286 | BF58: =IF(FORECAST(BF14,AB58:BE58,AB14:BE14)<0,0,FORECAST(BF14,AB58:BE58,AB14:BE14)) -> 19811.246 | BG58: =IF(FORECAST(BG14,AC58:BF58,AC14:BF14)<0,0,FORECAST(BG14,AC58:BF58,AC14:BF14)) -> 121001.9 | BH58: =IF(FORECAST(BH14,AD58:BG58,AD14:BG14)<0,0,FORECAST(BH14,AD58:BG58,AD14:BG14)) -> 168461.2 | BI58: =IF(FORECAST(BI14,AE58:BH58,AE14:BH14)<0,0,FORECAST(BI14,AE58:BH58,AE14:BH14)) -> 218538.36 | BJ58: =IF(FORECAST(BJ14,AF58:BI58,AF14:BI14)<0,0,FORECAST(BJ14,AF58:BI58,AF14:BI14)) -> 60742.571 | BK58: =IF(FORECAST(BK14,AG58:BJ58,AG14:BJ14)<0,0,FORECAST(BK14,AG58:BJ58,AG14:BJ14)) -> 530568.4 | BL58: =IF(FORECAST(BL14,AH58:BK58,AH14:BK14)<0,0,FORECAST(BL14,AH58:BK58,AH14:BK14)) -> 619038.69 | BM58: =IF(FORECAST(BM14,AI58:BL58,AI14:BL14)<0,0,FORECAST(BM14,AI58:BL58,AI14:BL14)) -> 837418.68 | ... FJ58: =IF(FORECAST(FJ14,EF58:FI58,EF14:FI14)<0,0,FORECAST(FJ14,EF58:FI58,EF14:FI14)) -> 1453736.1
A59: Renewable Gasoline Blendstocks | C59: ='Qrtly Credit-Deficit Generation'!C13 -> 0 | D59: ='Qrtly Credit-Deficit Generation'!D13 -> 0 | E59: ='Qrtly Credit-Deficit Generation'!E13 -> 0 | F59: ='Qrtly Credit-Deficit Generation'!F13 -> 0 | G59: ='Qrtly Credit-Deficit Generation'!G13 -> 0 | H59: ='Qrtly Credit-Deficit Generation'!H13 -> 0 | I59: ='Qrtly Credit-Deficit Generation'!I13 -> 0 | J59: ='Qrtly Credit-Deficit Generation'!J13 -> 0 | ... AX59: ='Qrtly Credit-Deficit Generation'!AX13 -> 13683 | AY59: 20275 | AZ59: 27898 | BA59: 41231 | BB59: 24252 | BC59: 25423 | BD59: 26532 | BE59: 25231 | BF59: =IF(FORECAST(BF15,AB59:BE59,AB15:BE15)<0,0,FORECAST(BF15,AB59:BE59,AB15:BE15)) -> 42403.856 | BG59: =IF(FORECAST(BG15,AC59:BF59,AC15:BF15)<0,0,FORECAST(BG15,AC59:BF59,AC15:BF15)) -> 44951.362 | BH59: =IF(FORECAST(BH15,AD59:BG59,AD15:BG15)<0,0,FORECAST(BH15,AD59:BG59,AD15:BG15)) -> 32853.999 | BI59: =IF(FORECAST(BI15,AE59:BH59,AE15:BH15)<0,0,FORECAST(BI15,AE59:BH59,AE15:BH15)) -> 40616.3 | BJ59: =IF(FORECAST(BJ15,AF59:BI59,AF15:BI15)<0,0,FORECAST(BJ15,AF59:BI59,AF15:BI15)) -> 49611.294 | BK59: =IF(FORECAST(BK15,AG59:BJ59,AG15:BJ15)<0,0,FORECAST(BK15,AG59:BJ59,AG15:BJ15)) -> 38825.515 | BL59: =IF(FORECAST(BL15,AH59:BK59,AH15:BK15)<0,0,FORECAST(BL15,AH59:BK59,AH15:BK15)) -> 32244.598 | BM59: =IF(FORECAST(BM15,AI59:BL59,AI15:BL15)<0,0,FORECAST(BM15,AI59:BL59,AI15:BL15)) -> 43235.046 | ... FJ59: =IF(FORECAST(FJ15,EF59:FI59,EF15:FI15)<0,0,FORECAST(FJ15,EF59:FI59,EF15:FI15)) -> 98505.774
A60: Propane | C60: ='Qrtly Credit-Deficit Generation'!C14 -> 0 | D60: ='Qrtly Credit-Deficit Generation'!D14 -> 0 | E60: ='Qrtly Credit-Deficit Generation'!E14 -> 0 | F60: ='Qrtly Credit-Deficit Generation'!F14 -> 0 | G60: ='Qrtly Credit-Deficit Generation'!G14 -> 0 | H60: ='Qrtly Credit-Deficit Generation'!H14 -> 0 | I60: ='Qrtly Credit-Deficit Generation'!I14 -> 0 | J60: ='Qrtly Credit-Deficit Generation'!J14 -> 0 | ... AX60: ='Qrtly Credit-Deficit Generation'!AX14 -> 9585 | AY60: 7599 | AZ60: 6241 | BA60: 8067 | BB60: 7101 | BC60: 6301 | BD60: 4514 | BE60: 3843 | BF60: =IF(FORECAST(BF16,AB60:BE60,AB16:BE16)<0,0,FORECAST(BF16,AB60:BE60,AB16:BE16)) -> 6790.4044 | BG60: =IF(FORECAST(BG16,AC60:BF60,AC16:BF16)<0,0,FORECAST(BG16,AC60:BF60,AC16:BF16)) -> 5839.3454 | BH60: =IF(FORECAST(BH16,AD60:BG60,AD16:BG16)<0,0,FORECAST(BH16,AD60:BG60,AD16:BG16)) -> 3909.3436 | BI60: =IF(FORECAST(BI16,AE60:BH60,AE16:BH16)<0,0,FORECAST(BI16,AE60:BH60,AE16:BH16)) -> 3979.6367 | BJ60: =IF(FORECAST(BJ16,AF60:BI60,AF16:BI16)<0,0,FORECAST(BJ16,AF60:BI60,AF16:BI16)) -> 3402.1068 | BK60: =IF(FORECAST(BK16,AG60:BJ60,AG16:BJ16)<0,0,FORECAST(BK16,AG60:BJ60,AG16:BJ16)) -> 0 | BL60: =IF(FORECAST(BL16,AH60:BK60,AH16:BK16)<0,0,FORECAST(BL16,AH60:BK60,AH16:BK16)) -> 0 | BM60: =IF(FORECAST(BM16,AI60:BL60,AI16:BL16)<0,0,FORECAST(BM16,AI60:BL60,AI16:BL16)) -> 0 | ... CF60: =IF(FORECAST(CF16,BB60:CE60,BB16:CE16)<0,0,FORECAST(CF16,BB60:CE60,BB16:CE16)) -> 34.836708 | CG60: 0 | CH60: 0 | CI60: 0 | CJ60: 0 | CK60: 0 | CL60: 0 | CM60: 0 | CN60: 0 | CO60: 0 | CP60: 0 | CQ60: 0 | CR60: 0 | CS60: 0 | CT60: 0 | CU60: 0 | CV60: 0 | CW60: 0 | CX60: 0 | CY60: 0 | CZ60: 0 | DA60: 0 | DB60: 0 | DC60: 0 | DD60: 0 | DE60: 0 | DF60: 0 | DG60: 0 | DH60: 0 | DI60: 0 | DJ60: 0 | DK60: 0 | DL60: 0 | DM60: 0 | DN60: 0 | DO60: 0 | DP60: 0 | DQ60: 0 | DR60: 0 | DS60: 0 | DT60: 0 | DU60: 0 | DV60: 0 | DW60: 0 | DX60: 0 | DY60: 0 | DZ60: 0 | EA60: 0 | EB60: 0 | EC60: 0 | ED60: 0 | EE60: 0 | EF60: 0 | EG60: 0 | EH60: 0 | EI60: 0 | EJ60: 0 | EK60: 0 | EL60: 0 | EM60: 0 | EN60: 0 | EO60: 0 | EP60: 0 | EQ60: 0 | ER60: 0 | ES60: 0 | ET60: 0 | EU60: 0 | EV60: 0 | EW60: 0 | EX60: 0 | EY60: 0 | EZ60: 0 | FA60: 0 | FB60: 0 | FC60: 0 | FD60: 0 | FE60: 0 | FF60: 0 | FG60: 0 | FH60: 0 | FI60: 0 | FJ60: 0
