Workbook

Sheet Graph Dashboard
R1: Notes: Conversion Factors
R2: 1 ton = 1250 liters

Sheet Global Capacity Data
A1: Global Sustainable Aviation Fuel Production Capacity
A2: (mil gal/yr) | B2: < 2021 | C2: 2021 | D2: 2022 | E2: 2023 | F2: 2024 | G2: 2025 | H2: 2026 | I2: 2027 | J2: 2028 | K2: 2029 | L2: 2030 | M2: 2031 | N2: 2032 | O2: 2033 | P2: 2034 | Q2: 2035
A3: HEFA | B3: ='NAm Capacity Data'!B3+'SAm Capacity Data'!B3+'Europe Capacity Data'!B3+'Asia Capacity Data'!B3+'MEA Capacity Data'!B3 -> 247 | C3: ='NAm Capacity Data'!C3+'SAm Capacity Data'!C3+'Europe Capacity Data'!C3+'Asia Capacity Data'!C3+'MEA Capacity Data'!C3 -> 0.35 | D3: ='NAm Capacity Data'!D3+'SAm Capacity Data'!D3+'Europe Capacity Data'!D3+'Asia Capacity Data'!D3+'MEA Capacity Data'!D3 -> 473.65 | E3: ='NAm Capacity Data'!E3+'SAm Capacity Data'!E3+'Europe Capacity Data'!E3+'Asia Capacity Data'!E3+'MEA Capacity Data'!E3 -> 330 | F3: ='NAm Capacity Data'!F3+'SAm Capacity Data'!F3+'Europe Capacity Data'!F3+'Asia Capacity Data'!F3+'MEA Capacity Data'!F3 -> 989.80088 | G3: ='NAm Capacity Data'!G3+'SAm Capacity Data'!G3+'Europe Capacity Data'!G3+'Asia Capacity Data'!G3+'MEA Capacity Data'!G3 -> 1499.6063 | H3: ='NAm Capacity Data'!H3+'SAm Capacity Data'!H3+'Europe Capacity Data'!H3+'Asia Capacity Data'!H3+'MEA Capacity Data'!H3 -> 792.02468 | I3: ='NAm Capacity Data'!I3+'SAm Capacity Data'!I3+'Europe Capacity Data'!I3+'Asia Capacity Data'!I3+'MEA Capacity Data'!I3 -> 879.88688 | ... Q3: ='NAm Capacity Data'!Q3+'SAm Capacity Data'!Q3+'Europe Capacity Data'!Q3+'Asia Capacity Data'!Q3+'MEA Capacity Data'!Q3 -> 0
A4: ATJ | B4: ='NAm Capacity Data'!B4+'SAm Capacity Data'!B4+'Europe Capacity Data'!B4+'Asia Capacity Data'!B4+'MEA Capacity Data'!B4 -> 3.0001 | C4: ='NAm Capacity Data'!C4+'SAm Capacity Data'!C4+'Europe Capacity Data'!C4+'Asia Capacity Data'!C4+'MEA Capacity Data'!C4 -> 0 | D4: ='NAm Capacity Data'!D4+'SAm Capacity Data'!D4+'Europe Capacity Data'!D4+'Asia Capacity Data'!D4+'MEA Capacity Data'!D4 -> 0 | E4: ='NAm Capacity Data'!E4+'SAm Capacity Data'!E4+'Europe Capacity Data'!E4+'Asia Capacity Data'!E4+'MEA Capacity Data'!E4 -> 0 | F4: ='NAm Capacity Data'!F4+'SAm Capacity Data'!F4+'Europe Capacity Data'!F4+'Asia Capacity Data'!F4+'MEA Capacity Data'!F4 -> 9 | G4: ='NAm Capacity Data'!G4+'SAm Capacity Data'!G4+'Europe Capacity Data'!G4+'Asia Capacity Data'!G4+'MEA Capacity Data'!G4 -> 124.20063 | H4: ='NAm Capacity Data'!H4+'SAm Capacity Data'!H4+'Europe Capacity Data'!H4+'Asia Capacity Data'!H4+'MEA Capacity Data'!H4 -> 204.69 | I4: ='NAm Capacity Data'!I4+'SAm Capacity Data'!I4+'Europe Capacity Data'!I4+'Asia Capacity Data'!I4+'MEA Capacity Data'!I4 -> 347.86437 | ... Q4: ='NAm Capacity Data'!Q4+'SAm Capacity Data'!Q4+'Europe Capacity Data'!Q4+'Asia Capacity Data'!Q4+'MEA Capacity Data'!Q4 -> 0
A5: FT | B5: ='NAm Capacity Data'!B5+'SAm Capacity Data'!B5+'Europe Capacity Data'!B5+'Asia Capacity Data'!B5+'MEA Capacity Data'!B5 -> 0 | C5: ='NAm Capacity Data'!C5+'SAm Capacity Data'!C5+'Europe Capacity Data'!C5+'Asia Capacity Data'!C5+'MEA Capacity Data'!C5 -> 0 | D5: ='NAm Capacity Data'!D5+'SAm Capacity Data'!D5+'Europe Capacity Data'!D5+'Asia Capacity Data'!D5+'MEA Capacity Data'!D5 -> 0 | E5: ='NAm Capacity Data'!E5+'SAm Capacity Data'!E5+'Europe Capacity Data'!E5+'Asia Capacity Data'!E5+'MEA Capacity Data'!E5 -> 0 | F5: ='NAm Capacity Data'!F5+'SAm Capacity Data'!F5+'Europe Capacity Data'!F5+'Asia Capacity Data'!F5+'MEA Capacity Data'!F5 -> 0.2541 | G5: ='NAm Capacity Data'!G5+'SAm Capacity Data'!G5+'Europe Capacity Data'!G5+'Asia Capacity Data'!G5+'MEA Capacity Data'!G5 -> 80.0534 | H5: ='NAm Capacity Data'!H5+'SAm Capacity Data'!H5+'Europe Capacity Data'!H5+'Asia Capacity Data'!H5+'MEA Capacity Data'!H5 -> 96.954 | I5: ='NAm Capacity Data'!I5+'SAm Capacity Data'!I5+'Europe Capacity Data'!I5+'Asia Capacity Data'!I5+'MEA Capacity Data'!I5 -> 207.679 | ... Q5: ='NAm Capacity Data'!Q5+'SAm Capacity Data'!Q5+'Europe Capacity Data'!Q5+'Asia Capacity Data'!Q5+'MEA Capacity Data'!Q5 -> 0
A6: PTL | B6: ='NAm Capacity Data'!B6+'SAm Capacity Data'!B6+'Europe Capacity Data'!B6+'Asia Capacity Data'!B6+'MEA Capacity Data'!B6 -> 0 | C6: ='NAm Capacity Data'!C6+'SAm Capacity Data'!C6+'Europe Capacity Data'!C6+'Asia Capacity Data'!C6+'MEA Capacity Data'!C6 -> 0.0066 | D6: ='NAm Capacity Data'!D6+'SAm Capacity Data'!D6+'Europe Capacity Data'!D6+'Asia Capacity Data'!D6+'MEA Capacity Data'!D6 -> 0.067 | E6: ='NAm Capacity Data'!E6+'SAm Capacity Data'!E6+'Europe Capacity Data'!E6+'Asia Capacity Data'!E6+'MEA Capacity Data'!E6 -> 0 | F6: ='NAm Capacity Data'!F6+'SAm Capacity Data'!F6+'Europe Capacity Data'!F6+'Asia Capacity Data'!F6+'MEA Capacity Data'!F6 -> 0.8625127 | G6: ='NAm Capacity Data'!G6+'SAm Capacity Data'!G6+'Europe Capacity Data'!G6+'Asia Capacity Data'!G6+'MEA Capacity Data'!G6 -> 0.8860625 | H6: ='NAm Capacity Data'!H6+'SAm Capacity Data'!H6+'Europe Capacity Data'!H6+'Asia Capacity Data'!H6+'MEA Capacity Data'!H6 -> 46.71595 | I6: ='NAm Capacity Data'!I6+'SAm Capacity Data'!I6+'Europe Capacity Data'!I6+'Asia Capacity Data'!I6+'MEA Capacity Data'!I6 -> 45 | ... Q6: ='NAm Capacity Data'!Q6+'SAm Capacity Data'!Q6+'Europe Capacity Data'!Q6+'Asia Capacity Data'!Q6+'MEA Capacity Data'!Q6 -> 0.0205
A7: Pyrolysis | B7: ='NAm Capacity Data'!B7+'SAm Capacity Data'!B7+'Europe Capacity Data'!B7+'Asia Capacity Data'!B7+'MEA Capacity Data'!B7 -> 0 | C7: ='NAm Capacity Data'!C7+'SAm Capacity Data'!C7+'Europe Capacity Data'!C7+'Asia Capacity Data'!C7+'MEA Capacity Data'!C7 -> 0 | D7: ='NAm Capacity Data'!D7+'SAm Capacity Data'!D7+'Europe Capacity Data'!D7+'Asia Capacity Data'!D7+'MEA Capacity Data'!D7 -> 0 | E7: ='NAm Capacity Data'!E7+'SAm Capacity Data'!E7+'Europe Capacity Data'!E7+'Asia Capacity Data'!E7+'MEA Capacity Data'!E7 -> 0 | F7: ='NAm Capacity Data'!F7+'SAm Capacity Data'!F7+'Europe Capacity Data'!F7+'Asia Capacity Data'!F7+'MEA Capacity Data'!F7 -> 0 | G7: ='NAm Capacity Data'!G7+'SAm Capacity Data'!G7+'Europe Capacity Data'!G7+'Asia Capacity Data'!G7+'MEA Capacity Data'!G7 -> 5 | H7: ='NAm Capacity Data'!H7+'SAm Capacity Data'!H7+'Europe Capacity Data'!H7+'Asia Capacity Data'!H7+'MEA Capacity Data'!H7 -> 0.286225 | I7: ='NAm Capacity Data'!I7+'SAm Capacity Data'!I7+'Europe Capacity Data'!I7+'Asia Capacity Data'!I7+'MEA Capacity Data'!I7 -> 0 | ... Q7: ='NAm Capacity Data'!Q7+'SAm Capacity Data'!Q7+'Europe Capacity Data'!Q7+'Asia Capacity Data'!Q7+'MEA Capacity Data'!Q7 -> 0
A8: Co-Processing | B8: ='NAm Capacity Data'!B8+'SAm Capacity Data'!B8+'Europe Capacity Data'!B8+'Asia Capacity Data'!B8+'MEA Capacity Data'!B8 -> 15.33 | C8: ='NAm Capacity Data'!C8+'SAm Capacity Data'!C8+'Europe Capacity Data'!C8+'Asia Capacity Data'!C8+'MEA Capacity Data'!C8 -> 104.16 | D8: ='NAm Capacity Data'!D8+'SAm Capacity Data'!D8+'Europe Capacity Data'!D8+'Asia Capacity Data'!D8+'MEA Capacity Data'!D8 -> 249.17448 | E8: ='NAm Capacity Data'!E8+'SAm Capacity Data'!E8+'Europe Capacity Data'!E8+'Asia Capacity Data'!E8+'MEA Capacity Data'!E8 -> 11 | F8: ='NAm Capacity Data'!F8+'SAm Capacity Data'!F8+'Europe Capacity Data'!F8+'Asia Capacity Data'!F8+'MEA Capacity Data'!F8 -> 74.034375 | G8: ='NAm Capacity Data'!G8+'SAm Capacity Data'!G8+'Europe Capacity Data'!G8+'Asia Capacity Data'!G8+'MEA Capacity Data'!G8 -> 17.665 | H8: ='NAm Capacity Data'!H8+'SAm Capacity Data'!H8+'Europe Capacity Data'!H8+'Asia Capacity Data'!H8+'MEA Capacity Data'!H8 -> 19.21575 | I8: ='NAm Capacity Data'!I8+'SAm Capacity Data'!I8+'Europe Capacity Data'!I8+'Asia Capacity Data'!I8+'MEA Capacity Data'!I8 -> 18.375 | ... Q8: ='NAm Capacity Data'!Q8+'SAm Capacity Data'!Q8+'Europe Capacity Data'!Q8+'Asia Capacity Data'!Q8+'MEA Capacity Data'!Q8 -> 0
A9: Total Capacity | B9: =SUM(B3:B8) -> 265.3301 | C9: =SUM(C3:C8) -> 104.5166 | D9: =SUM(D3:D8) -> 722.89148 | E9: =SUM(E3:E8) -> 341 | F9: =SUM(F3:F8) -> 1073.9519 | G9: =SUM(G3:G8) -> 1727.4114 | H9: =SUM(H3:H8) -> 1159.8866 | I9: =SUM(I3:I8) -> 1498.8053 | ... Q9: =SUM(Q3:Q8) -> 0.0205
A11: Global Cumulative Probability Adjusted SAF Capacity
A12: (mil gal/yr) | B12: =B2 -> < 2021 | C12: =C2 -> 2021 | D12: =D2 -> 2022 | E12: =E2 -> 2023 | F12: =F2 -> 2024 | G12: =G2 -> 2025 | H12: =H2 -> 2026 | I12: =I2 -> 2027 | ... Q12: =Q2 -> 2035
A13: HEFA | B13: =B3 -> 247 | C13: =B13+C3 -> 247.35 | D13: =C13+D3 -> 721 | E13: =D13+E3 -> 1051 | F13: =E13+F3 -> 2040.8009 | G13: =F13+G3 -> 3540.4072 | H13: =G13+H3 -> 4332.4318 | I13: =H13+I3 -> 5212.3187 | J13: =I13+J3 -> 5427.3997 | ... Q13: =P13+Q3 -> 5630.0692
A14: ATJ | B14: =B4 -> 3.0001 | C14: =B14+C4 -> 3.0001 | D14: =C14+D4 -> 3.0001 | E14: =D14+E4 -> 3.0001 | F14: =E14+F4 -> 12.0001 | G14: =F14+G4 -> 136.20073 | H14: =G14+H4 -> 340.89072 | I14: =H14+I4 -> 688.7551 | J14: =I14+J4 -> 885.28705 | ... Q14: =P14+Q4 -> 1100.4674
A15: FT | B15: =B5 -> 0 | C15: =B15+C5 -> 0 | D15: =C15+D5 -> 0 | E15: =D15+E5 -> 0 | F15: =E15+F5 -> 0.2541 | G15: =F15+G5 -> 80.3075 | H15: =G15+H5 -> 177.2615 | I15: =H15+I5 -> 384.9405 | J15: =I15+J5 -> 460.388 | ... Q15: =P15+Q5 -> 577.1645
A16: PTL | B16: =B6 -> 0 | C16: =B16+C6 -> 0.0066 | D16: =C16+D6 -> 0.0736 | E16: =D16+E6 -> 0.0736 | F16: =E16+F6 -> 0.9361127 | G16: =F16+G6 -> 1.8221752 | H16: =G16+H6 -> 48.538125 | I16: =H16+I6 -> 93.538125 | J16: =I16+J6 -> 198.32213 | ... Q16: =P16+Q6 -> 638.01315
A17: Pyrolysis | B17: =B7 -> 0 | C17: =B17+C7 -> 0 | D17: =C17+D7 -> 0 | E17: =D17+E7 -> 0 | F17: =E17+F7 -> 0 | G17: =F17+G7 -> 5 | H17: =G17+H7 -> 5.286225 | I17: =H17+I7 -> 5.286225 | J17: =I17+J7 -> 5.286225 | ... Q17: =P17+Q7 -> 23.436225
A18: Co-Processing | B18: =B8 -> 15.33 | C18: =B18+C8 -> 119.49 | D18: =C18+D8 -> 368.66447 | E18: =D18+E8 -> 379.66447 | F18: =E18+F8 -> 453.69885 | G18: =F18+G8 -> 471.36385 | H18: =G18+H8 -> 490.5796 | I18: =H18+I8 -> 508.9546 | J18: =I18+J8 -> 546.18445 | ... Q18: =P18+Q8 -> 602.00945
A19: Total Capacity | B19: =SUM(B13:B18) -> 265.3301 | C19: =SUM(C13:C18) -> 369.8467 | D19: =SUM(D13:D18) -> 1092.7382 | E19: =SUM(E13:E18) -> 1433.7382 | F19: =SUM(F13:F18) -> 2507.69 | G19: =SUM(G13:G18) -> 4235.1014 | H19: =SUM(H13:H18) -> 5394.988 | I19: =SUM(I13:I18) -> 6893.7933 | ... Q19: =SUM(Q13:Q18) -> 8571.16
A21: Global Announced SAF Capacity
A22: (mil gal/yr) | B22: =B2 -> < 2021 | C22: =C2 -> 2021 | D22: =D2 -> 2022 | E22: =E2 -> 2023 | F22: =F2 -> 2024 | G22: =G2 -> 2025 | H22: =H2 -> 2026 | I22: =I2 -> 2027 | ... Q22: =Q2 -> 2035
A23: HEFA | B23: ='NAm Capacity Data'!B23+'SAm Capacity Data'!B23+'Europe Capacity Data'!B23+'Asia Capacity Data'!B23+'MEA Capacity Data'!B23 -> 247 | C23: ='NAm Capacity Data'!C23+'SAm Capacity Data'!C23+'Europe Capacity Data'!C23+'Asia Capacity Data'!C23+'MEA Capacity Data'!C23 -> 350 | D23: ='NAm Capacity Data'!D23+'SAm Capacity Data'!D23+'Europe Capacity Data'!D23+'Asia Capacity Data'!D23+'MEA Capacity Data'!D23 -> 473.65 | E23: ='NAm Capacity Data'!E23+'SAm Capacity Data'!E23+'Europe Capacity Data'!E23+'Asia Capacity Data'!E23+'MEA Capacity Data'!E23 -> 330 | F23: ='NAm Capacity Data'!F23+'SAm Capacity Data'!F23+'Europe Capacity Data'!F23+'Asia Capacity Data'!F23+'MEA Capacity Data'!F23 -> 1239.5375 | G23: ='NAm Capacity Data'!G23+'SAm Capacity Data'!G23+'Europe Capacity Data'!G23+'Asia Capacity Data'!G23+'MEA Capacity Data'!G23 -> 1652.3155 | H23: ='NAm Capacity Data'!H23+'SAm Capacity Data'!H23+'Europe Capacity Data'!H23+'Asia Capacity Data'!H23+'MEA Capacity Data'!H23 -> 1188.4545 | I23: ='NAm Capacity Data'!I23+'SAm Capacity Data'!I23+'Europe Capacity Data'!I23+'Asia Capacity Data'!I23+'MEA Capacity Data'!I23 -> 1776.1125 | ... Q23: ='NAm Capacity Data'!Q23+'SAm Capacity Data'!Q23+'Europe Capacity Data'!Q23+'Asia Capacity Data'!Q23+'MEA Capacity Data'!Q23 -> 0
A24: ATJ | B24: ='NAm Capacity Data'!B24+'SAm Capacity Data'!B24+'Europe Capacity Data'!B24+'Asia Capacity Data'!B24+'MEA Capacity Data'!B24 -> 60.1 | C24: ='NAm Capacity Data'!C24+'SAm Capacity Data'!C24+'Europe Capacity Data'!C24+'Asia Capacity Data'!C24+'MEA Capacity Data'!C24 -> 0 | D24: ='NAm Capacity Data'!D24+'SAm Capacity Data'!D24+'Europe Capacity Data'!D24+'Asia Capacity Data'!D24+'MEA Capacity Data'!D24 -> 0 | E24: ='NAm Capacity Data'!E24+'SAm Capacity Data'!E24+'Europe Capacity Data'!E24+'Asia Capacity Data'!E24+'MEA Capacity Data'!E24 -> 0 | F24: ='NAm Capacity Data'!F24+'SAm Capacity Data'!F24+'Europe Capacity Data'!F24+'Asia Capacity Data'!F24+'MEA Capacity Data'!F24 -> 9 | G24: ='NAm Capacity Data'!G24+'SAm Capacity Data'!G24+'Europe Capacity Data'!G24+'Asia Capacity Data'!G24+'MEA Capacity Data'!G24 -> 235.19125 | H24: ='NAm Capacity Data'!H24+'SAm Capacity Data'!H24+'Europe Capacity Data'!H24+'Asia Capacity Data'!H24+'MEA Capacity Data'!H24 -> 393.2 | I24: ='NAm Capacity Data'!I24+'SAm Capacity Data'!I24+'Europe Capacity Data'!I24+'Asia Capacity Data'!I24+'MEA Capacity Data'!I24 -> 701.6125 | ... Q24: ='NAm Capacity Data'!Q24+'SAm Capacity Data'!Q24+'Europe Capacity Data'!Q24+'Asia Capacity Data'!Q24+'MEA Capacity Data'!Q24 -> 0
A25: FT | B25: ='NAm Capacity Data'!B25+'SAm Capacity Data'!B25+'Europe Capacity Data'!B25+'Asia Capacity Data'!B25+'MEA Capacity Data'!B25 -> 0 | C25: ='NAm Capacity Data'!C25+'SAm Capacity Data'!C25+'Europe Capacity Data'!C25+'Asia Capacity Data'!C25+'MEA Capacity Data'!C25 -> 0 | D25: ='NAm Capacity Data'!D25+'SAm Capacity Data'!D25+'Europe Capacity Data'!D25+'Asia Capacity Data'!D25+'MEA Capacity Data'!D25 -> 0 | E25: ='NAm Capacity Data'!E25+'SAm Capacity Data'!E25+'Europe Capacity Data'!E25+'Asia Capacity Data'!E25+'MEA Capacity Data'!E25 -> 0 | F25: ='NAm Capacity Data'!F25+'SAm Capacity Data'!F25+'Europe Capacity Data'!F25+'Asia Capacity Data'!F25+'MEA Capacity Data'!F25 -> 0.462 | G25: ='NAm Capacity Data'!G25+'SAm Capacity Data'!G25+'Europe Capacity Data'!G25+'Asia Capacity Data'!G25+'MEA Capacity Data'!G25 -> 174.194 | H25: ='NAm Capacity Data'!H25+'SAm Capacity Data'!H25+'Europe Capacity Data'!H25+'Asia Capacity Data'!H25+'MEA Capacity Data'!H25 -> 176.28 | I25: ='NAm Capacity Data'!I25+'SAm Capacity Data'!I25+'Europe Capacity Data'!I25+'Asia Capacity Data'!I25+'MEA Capacity Data'!I25 -> 476.74 | ... Q25: ='NAm Capacity Data'!Q25+'SAm Capacity Data'!Q25+'Europe Capacity Data'!Q25+'Asia Capacity Data'!Q25+'MEA Capacity Data'!Q25 -> 0
A26: PTL | B26: ='NAm Capacity Data'!B26+'SAm Capacity Data'!B26+'Europe Capacity Data'!B26+'Asia Capacity Data'!B26+'MEA Capacity Data'!B26 -> 0 | C26: ='NAm Capacity Data'!C26+'SAm Capacity Data'!C26+'Europe Capacity Data'!C26+'Asia Capacity Data'!C26+'MEA Capacity Data'!C26 -> 0.0066 | D26: ='NAm Capacity Data'!D26+'SAm Capacity Data'!D26+'Europe Capacity Data'!D26+'Asia Capacity Data'!D26+'MEA Capacity Data'!D26 -> 0.067 | E26: ='NAm Capacity Data'!E26+'SAm Capacity Data'!E26+'Europe Capacity Data'!E26+'Asia Capacity Data'!E26+'MEA Capacity Data'!E26 -> 0 | F26: ='NAm Capacity Data'!F26+'SAm Capacity Data'!F26+'Europe Capacity Data'!F26+'Asia Capacity Data'!F26+'MEA Capacity Data'!F26 -> 1.4223773 | G26: ='NAm Capacity Data'!G26+'SAm Capacity Data'!G26+'Europe Capacity Data'!G26+'Asia Capacity Data'!G26+'MEA Capacity Data'!G26 -> 1.2195625 | H26: ='NAm Capacity Data'!H26+'SAm Capacity Data'!H26+'Europe Capacity Data'!H26+'Asia Capacity Data'!H26+'MEA Capacity Data'!H26 -> 82.900875 | I26: ='NAm Capacity Data'!I26+'SAm Capacity Data'!I26+'Europe Capacity Data'!I26+'Asia Capacity Data'!I26+'MEA Capacity Data'!I26 -> 62.664 | ... Q26: ='NAm Capacity Data'!Q26+'SAm Capacity Data'!Q26+'Europe Capacity Data'!Q26+'Asia Capacity Data'!Q26+'MEA Capacity Data'!Q26 -> 0.082
A27: Pyrolysis | B27: ='NAm Capacity Data'!B27+'SAm Capacity Data'!B27+'Europe Capacity Data'!B27+'Asia Capacity Data'!B27+'MEA Capacity Data'!B27 -> 0 | C27: ='NAm Capacity Data'!C27+'SAm Capacity Data'!C27+'Europe Capacity Data'!C27+'Asia Capacity Data'!C27+'MEA Capacity Data'!C27 -> 0 | D27: ='NAm Capacity Data'!D27+'SAm Capacity Data'!D27+'Europe Capacity Data'!D27+'Asia Capacity Data'!D27+'MEA Capacity Data'!D27 -> 0 | E27: ='NAm Capacity Data'!E27+'SAm Capacity Data'!E27+'Europe Capacity Data'!E27+'Asia Capacity Data'!E27+'MEA Capacity Data'!E27 -> 0 | F27: ='NAm Capacity Data'!F27+'SAm Capacity Data'!F27+'Europe Capacity Data'!F27+'Asia Capacity Data'!F27+'MEA Capacity Data'!F27 -> 0 | G27: ='NAm Capacity Data'!G27+'SAm Capacity Data'!G27+'Europe Capacity Data'!G27+'Asia Capacity Data'!G27+'MEA Capacity Data'!G27 -> 10 | H27: ='NAm Capacity Data'!H27+'SAm Capacity Data'!H27+'Europe Capacity Data'!H27+'Asia Capacity Data'!H27+'MEA Capacity Data'!H27 -> 1.4295 | I27: ='NAm Capacity Data'!I27+'SAm Capacity Data'!I27+'Europe Capacity Data'!I27+'Asia Capacity Data'!I27+'MEA Capacity Data'!I27 -> 0 | ... Q27: ='NAm Capacity Data'!Q27+'SAm Capacity Data'!Q27+'Europe Capacity Data'!Q27+'Asia Capacity Data'!Q27+'MEA Capacity Data'!Q27 -> 0
A28: Co-Processing | B28: ='NAm Capacity Data'!B28+'SAm Capacity Data'!B28+'Europe Capacity Data'!B28+'Asia Capacity Data'!B28+'MEA Capacity Data'!B28 -> 15.33 | C28: ='NAm Capacity Data'!C28+'SAm Capacity Data'!C28+'Europe Capacity Data'!C28+'Asia Capacity Data'!C28+'MEA Capacity Data'!C28 -> 104.16 | D28: ='NAm Capacity Data'!D28+'SAm Capacity Data'!D28+'Europe Capacity Data'!D28+'Asia Capacity Data'!D28+'MEA Capacity Data'!D28 -> 249.17448 | E28: ='NAm Capacity Data'!E28+'SAm Capacity Data'!E28+'Europe Capacity Data'!E28+'Asia Capacity Data'!E28+'MEA Capacity Data'!E28 -> 20 | F28: ='NAm Capacity Data'!F28+'SAm Capacity Data'!F28+'Europe Capacity Data'!F28+'Asia Capacity Data'!F28+'MEA Capacity Data'!F28 -> 111.1875 | G28: ='NAm Capacity Data'!G28+'SAm Capacity Data'!G28+'Europe Capacity Data'!G28+'Asia Capacity Data'!G28+'MEA Capacity Data'!G28 -> 22.665 | H28: ='NAm Capacity Data'!H28+'SAm Capacity Data'!H28+'Europe Capacity Data'!H28+'Asia Capacity Data'!H28+'MEA Capacity Data'!H28 -> 27.665 | I28: ='NAm Capacity Data'!I28+'SAm Capacity Data'!I28+'Europe Capacity Data'!I28+'Asia Capacity Data'!I28+'MEA Capacity Data'!I28 -> 73.5 | ... Q28: ='NAm Capacity Data'!Q28+'SAm Capacity Data'!Q28+'Europe Capacity Data'!Q28+'Asia Capacity Data'!Q28+'MEA Capacity Data'!Q28 -> 0
A29: Total Capacity | B29: =SUM(B23:B28) -> 322.43 | C29: =B29+SUM(C23:C28) -> 776.5966 | D29: =C29+SUM(D23:D28) -> 1499.4881 | E29: =D29+SUM(E23:E28) -> 1849.4881 | F29: =E29+SUM(F23:F28) -> 3211.0975 | G29: =F29+SUM(G23:G28) -> 5306.6828 | H29: =G29+SUM(H23:H28) -> 7176.6126 | I29: =H29+SUM(I23:I28) -> 10267.242 | J29: =I29+SUM(J23:J28) -> 11573.659 | ... Q29: =P29+SUM(Q23:Q28) -> 14086.069
A30: Probability of any announcement for the reference year | B30: =B19/B29 -> 0.82290761 | C30: =C19/C29 -> 0.47624043 | D30: =D19/D29 -> 0.72874082 | E30: =E19/E29 -> 0.77520812 | F30: =F19/F29 -> 0.78094486 | G30: =G19/G29 -> 0.79806945 | H30: =H19/H29 -> 0.75174574 | I30: =I19/I29 -> 0.67143577 | ... Q30: =Q19/Q29 -> 0.60848487
A31: Global Cumulative SAF Capacity by Technology
A32: (mil gal/yr) | B32: =B22 -> < 2021 | C32: =C22 -> 2021 | D32: =D22 -> 2022 | E32: =E22 -> 2023 | F32: =F22 -> 2024 | G32: =G22 -> 2025 | H32: =H22 -> 2026 | I32: =I22 -> 2027 | ... Q32: =Q22 -> 2035
A33: HEFA Cumulative | B33: =B23 -> 247 | C33: =B33+C23 -> 597 | D33: =C33+D23 -> 1070.65 | E33: =D33+E23 -> 1400.65 | F33: =E33+F23 -> 2640.1875 | G33: =F33+G23 -> 4292.503 | H33: =G33+H23 -> 5480.9575 | I33: =H33+I23 -> 7257.07 | J33: =I33+J23 -> 7747.795 | ... Q33: =P33+Q23 -> 8254.025 | R33: =L33/$L$39 -> 0.62010273
A34: ATJ Cumulative | B34: =B24 -> 60.1 | C34: =B34+C24 -> 60.1 | D34: =C34+D24 -> 60.1 | E34: =D34+E24 -> 60.1 | F34: =E34+F24 -> 69.1 | G34: =F34+G24 -> 304.29125 | H34: =G34+H24 -> 697.49125 | I34: =H34+I24 -> 1399.1037 | J34: =I34+J24 -> 1748.2528 | ... Q34: =P34+Q24 -> 2309.3588 | R34: =L34/$L$39 -> 0.16363294
A35: FT Cumulative | B35: =B25 -> 0 | C35: =B35+C25 -> 0 | D35: =C35+D25 -> 0 | E35: =D35+E25 -> 0 | F35: =E35+F25 -> 0.462 | G35: =F35+G25 -> 174.656 | H35: =G35+H25 -> 350.936 | I35: =H35+I25 -> 827.676 | J35: =I35+J25 -> 1024.826 | ... Q35: =P35+Q25 -> 1256.556 | R35: =L35/$L$39 -> 0.093931644
A36: PTL Cumulative | B36: =B26 -> 0 | C36: =C26+B36 -> 0.0066 | D36: =D26+C36 -> 0.0736 | E36: =E26+D36 -> 0.0736 | F36: =F26+E36 -> 1.4959773 | G36: =G26+F36 -> 2.7155398 | H36: =H26+G36 -> 85.616415 | I36: =I26+H36 -> 148.28041 | J36: =J26+I36 -> 337.11041 | ... Q36: =Q26+P36 -> 1415.9543 | R36: =L36/$L$39 -> 0.060491742
A37: Pyrolysis Cumulative | B37: =B27 -> 0 | C37: =B37+C27 -> 0 | D37: =C37+D27 -> 0 | E37: =D37+E27 -> 0 | F37: =E37+F27 -> 0 | G37: =F37+G27 -> 10 | H37: =G37+H27 -> 11.4295 | I37: =H37+I27 -> 11.4295 | J37: =I37+J27 -> 11.4295 | ... Q37: =P37+Q27 -> 44.4295 | R37: =L37/$L$39 -> 0.0008649446
A38: Co-Processing Cumulative | B38: =B28 -> 15.33 | C38: =B38+C28 -> 119.49 | D38: =C38+D28 -> 368.66447 | E38: =D38+E28 -> 388.66447 | F38: =E38+F28 -> 499.85197 | G38: =F38+G28 -> 522.51698 | H38: =G38+H28 -> 550.18197 | I38: =H38+I28 -> 623.68197 | J38: =I38+J28 -> 704.24547 | ... Q38: =P38+Q28 -> 805.74547 | R38: =L38/$L$39 -> 0.060976
A39: Total Capacity | B39: =SUM(B33:B38) -> 322.43 | C39: =SUM(C33:C38) -> 776.5966 | D39: =SUM(D33:D38) -> 1499.4881 | E39: =SUM(E33:E38) -> 1849.4881 | F39: =SUM(F33:F38) -> 3211.0975 | G39: =SUM(G33:G38) -> 5306.6828 | H39: =SUM(H33:H38) -> 7176.6126 | I39: =SUM(I33:I38) -> 10267.242 | ... Q39: =SUM(Q33:Q38) -> 14086.069
A41: Number of Plants by Technology
B42: =B22 -> < 2021 | C42: =C22 -> 2021 | D42: =D22 -> 2022 | E42: =E22 -> 2023 | F42: =F22 -> 2024 | G42: =G22 -> 2025 | H42: =H22 -> 2026 | I42: =I22 -> 2027 | ... Q42: =Q22 -> 2035 | R42: Check Total | S42: Check
A43: HEFA | B43: ='NAm Capacity Data'!B43+'SAm Capacity Data'!B43+'Europe Capacity Data'!B43+'Asia Capacity Data'!B43+'MEA Capacity Data'!B43 -> 3 | C43: ='NAm Capacity Data'!C43+'SAm Capacity Data'!C43+'Europe Capacity Data'!C43+'Asia Capacity Data'!C43+'MEA Capacity Data'!C43 -> 2 | D43: ='NAm Capacity Data'!D43+'SAm Capacity Data'!D43+'Europe Capacity Data'!D43+'Asia Capacity Data'!D43+'MEA Capacity Data'!D43 -> 7 | E43: ='NAm Capacity Data'!E43+'SAm Capacity Data'!E43+'Europe Capacity Data'!E43+'Asia Capacity Data'!E43+'MEA Capacity Data'!E43 -> 1 | F43: ='NAm Capacity Data'!F43+'SAm Capacity Data'!F43+'Europe Capacity Data'!F43+'Asia Capacity Data'!F43+'MEA Capacity Data'!F43 -> 16 | G43: ='NAm Capacity Data'!G43+'SAm Capacity Data'!G43+'Europe Capacity Data'!G43+'Asia Capacity Data'!G43+'MEA Capacity Data'!G43 -> 22 | H43: ='NAm Capacity Data'!H43+'SAm Capacity Data'!H43+'Europe Capacity Data'!H43+'Asia Capacity Data'!H43+'MEA Capacity Data'!H43 -> 16 | I43: ='NAm Capacity Data'!I43+'SAm Capacity Data'!I43+'Europe Capacity Data'!I43+'Asia Capacity Data'!I43+'MEA Capacity Data'!I43 -> 25 | ... Q43: ='NAm Capacity Data'!Q43+'SAm Capacity Data'!Q43+'Europe Capacity Data'!Q43+'Asia Capacity Data'!Q43+'MEA Capacity Data'!Q43 -> 0 | R43: =SUM(B43:P43) -> 118
A44: ATJ | B44: ='NAm Capacity Data'!B44+'SAm Capacity Data'!B44+'Europe Capacity Data'!B44+'Asia Capacity Data'!B44+'MEA Capacity Data'!B44 -> 4 | C44: ='NAm Capacity Data'!C44+'SAm Capacity Data'!C44+'Europe Capacity Data'!C44+'Asia Capacity Data'!C44+'MEA Capacity Data'!C44 -> 0 | D44: ='NAm Capacity Data'!D44+'SAm Capacity Data'!D44+'Europe Capacity Data'!D44+'Asia Capacity Data'!D44+'MEA Capacity Data'!D44 -> 0 | E44: ='NAm Capacity Data'!E44+'SAm Capacity Data'!E44+'Europe Capacity Data'!E44+'Asia Capacity Data'!E44+'MEA Capacity Data'!E44 -> 0 | F44: ='NAm Capacity Data'!F44+'SAm Capacity Data'!F44+'Europe Capacity Data'!F44+'Asia Capacity Data'!F44+'MEA Capacity Data'!F44 -> 2 | G44: ='NAm Capacity Data'!G44+'SAm Capacity Data'!G44+'Europe Capacity Data'!G44+'Asia Capacity Data'!G44+'MEA Capacity Data'!G44 -> 5 | H44: ='NAm Capacity Data'!H44+'SAm Capacity Data'!H44+'Europe Capacity Data'!H44+'Asia Capacity Data'!H44+'MEA Capacity Data'!H44 -> 6 | I44: ='NAm Capacity Data'!I44+'SAm Capacity Data'!I44+'Europe Capacity Data'!I44+'Asia Capacity Data'!I44+'MEA Capacity Data'!I44 -> 9 | ... Q44: ='NAm Capacity Data'!Q44+'SAm Capacity Data'!Q44+'Europe Capacity Data'!Q44+'Asia Capacity Data'!Q44+'MEA Capacity Data'!Q44 -> 0 | R44: =SUM(B44:P44) -> 50
A45: FT | B45: ='NAm Capacity Data'!B45+'SAm Capacity Data'!B45+'Europe Capacity Data'!B45+'Asia Capacity Data'!B45+'MEA Capacity Data'!B45 -> 0 | C45: ='NAm Capacity Data'!C45+'SAm Capacity Data'!C45+'Europe Capacity Data'!C45+'Asia Capacity Data'!C45+'MEA Capacity Data'!C45 -> 0 | D45: ='NAm Capacity Data'!D45+'SAm Capacity Data'!D45+'Europe Capacity Data'!D45+'Asia Capacity Data'!D45+'MEA Capacity Data'!D45 -> 0 | E45: ='NAm Capacity Data'!E45+'SAm Capacity Data'!E45+'Europe Capacity Data'!E45+'Asia Capacity Data'!E45+'MEA Capacity Data'!E45 -> 0 | F45: ='NAm Capacity Data'!F45+'SAm Capacity Data'!F45+'Europe Capacity Data'!F45+'Asia Capacity Data'!F45+'MEA Capacity Data'!F45 -> 1 | G45: ='NAm Capacity Data'!G45+'SAm Capacity Data'!G45+'Europe Capacity Data'!G45+'Asia Capacity Data'!G45+'MEA Capacity Data'!G45 -> 8 | H45: ='NAm Capacity Data'!H45+'SAm Capacity Data'!H45+'Europe Capacity Data'!H45+'Asia Capacity Data'!H45+'MEA Capacity Data'!H45 -> 4 | I45: ='NAm Capacity Data'!I45+'SAm Capacity Data'!I45+'Europe Capacity Data'!I45+'Asia Capacity Data'!I45+'MEA Capacity Data'!I45 -> 13 | ... Q45: ='NAm Capacity Data'!Q45+'SAm Capacity Data'!Q45+'Europe Capacity Data'!Q45+'Asia Capacity Data'!Q45+'MEA Capacity Data'!Q45 -> 0 | R45: =SUM(B45:P45) -> 43
A46: PTL | B46: ='NAm Capacity Data'!B46+'SAm Capacity Data'!B46+'Europe Capacity Data'!B46+'Asia Capacity Data'!B46+'MEA Capacity Data'!B46 -> 0 | C46: ='NAm Capacity Data'!C46+'SAm Capacity Data'!C46+'Europe Capacity Data'!C46+'Asia Capacity Data'!C46+'MEA Capacity Data'!C46 -> 1 | D46: ='NAm Capacity Data'!D46+'SAm Capacity Data'!D46+'Europe Capacity Data'!D46+'Asia Capacity Data'!D46+'MEA Capacity Data'!D46 -> 3 | E46: ='NAm Capacity Data'!E46+'SAm Capacity Data'!E46+'Europe Capacity Data'!E46+'Asia Capacity Data'!E46+'MEA Capacity Data'!E46 -> 0 | F46: ='NAm Capacity Data'!F46+'SAm Capacity Data'!F46+'Europe Capacity Data'!F46+'Asia Capacity Data'!F46+'MEA Capacity Data'!F46 -> 6 | G46: ='NAm Capacity Data'!G46+'SAm Capacity Data'!G46+'Europe Capacity Data'!G46+'Asia Capacity Data'!G46+'MEA Capacity Data'!G46 -> 8 | H46: ='NAm Capacity Data'!H46+'SAm Capacity Data'!H46+'Europe Capacity Data'!H46+'Asia Capacity Data'!H46+'MEA Capacity Data'!H46 -> 13 | I46: ='NAm Capacity Data'!I46+'SAm Capacity Data'!I46+'Europe Capacity Data'!I46+'Asia Capacity Data'!I46+'MEA Capacity Data'!I46 -> 6 | ... Q46: ='NAm Capacity Data'!Q46+'SAm Capacity Data'!Q46+'Europe Capacity Data'!Q46+'Asia Capacity Data'!Q46+'MEA Capacity Data'!Q46 -> 1 | R46: =SUM(B46:P46) -> 71
A47: Pyrolysis | B47: ='NAm Capacity Data'!B47+'SAm Capacity Data'!B47+'Europe Capacity Data'!B47+'Asia Capacity Data'!B47+'MEA Capacity Data'!B47 -> 0 | C47: ='NAm Capacity Data'!C47+'SAm Capacity Data'!C47+'Europe Capacity Data'!C47+'Asia Capacity Data'!C47+'MEA Capacity Data'!C47 -> 0 | D47: ='NAm Capacity Data'!D47+'SAm Capacity Data'!D47+'Europe Capacity Data'!D47+'Asia Capacity Data'!D47+'MEA Capacity Data'!D47 -> 0 | E47: ='NAm Capacity Data'!E47+'SAm Capacity Data'!E47+'Europe Capacity Data'!E47+'Asia Capacity Data'!E47+'MEA Capacity Data'!E47 -> 0 | F47: ='NAm Capacity Data'!F47+'SAm Capacity Data'!F47+'Europe Capacity Data'!F47+'Asia Capacity Data'!F47+'MEA Capacity Data'!F47 -> 2 | G47: ='NAm Capacity Data'!G47+'SAm Capacity Data'!G47+'Europe Capacity Data'!G47+'Asia Capacity Data'!G47+'MEA Capacity Data'!G47 -> 2 | H47: ='NAm Capacity Data'!H47+'SAm Capacity Data'!H47+'Europe Capacity Data'!H47+'Asia Capacity Data'!H47+'MEA Capacity Data'!H47 -> 3 | I47: ='NAm Capacity Data'!I47+'SAm Capacity Data'!I47+'Europe Capacity Data'!I47+'Asia Capacity Data'!I47+'MEA Capacity Data'!I47 -> 0 | ... Q47: ='NAm Capacity Data'!Q47+'SAm Capacity Data'!Q47+'Europe Capacity Data'!Q47+'Asia Capacity Data'!Q47+'MEA Capacity Data'!Q47 -> 0 | R47: =SUM(B47:P47) -> 8
A48: Co-Processing | B48: ='NAm Capacity Data'!B48+'SAm Capacity Data'!B48+'Europe Capacity Data'!B48+'Asia Capacity Data'!B48+'MEA Capacity Data'!B48 -> 2 | C48: ='NAm Capacity Data'!C48+'SAm Capacity Data'!C48+'Europe Capacity Data'!C48+'Asia Capacity Data'!C48+'MEA Capacity Data'!C48 -> 6 | D48: ='NAm Capacity Data'!D48+'SAm Capacity Data'!D48+'Europe Capacity Data'!D48+'Asia Capacity Data'!D48+'MEA Capacity Data'!D48 -> 4 | E48: ='NAm Capacity Data'!E48+'SAm Capacity Data'!E48+'Europe Capacity Data'!E48+'Asia Capacity Data'!E48+'MEA Capacity Data'!E48 -> 1 | F48: ='NAm Capacity Data'!F48+'SAm Capacity Data'!F48+'Europe Capacity Data'!F48+'Asia Capacity Data'!F48+'MEA Capacity Data'!F48 -> 6 | G48: ='NAm Capacity Data'!G48+'SAm Capacity Data'!G48+'Europe Capacity Data'!G48+'Asia Capacity Data'!G48+'MEA Capacity Data'!G48 -> 6 | H48: ='NAm Capacity Data'!H48+'SAm Capacity Data'!H48+'Europe Capacity Data'!H48+'Asia Capacity Data'!H48+'MEA Capacity Data'!H48 -> 3 | I48: ='NAm Capacity Data'!I48+'SAm Capacity Data'!I48+'Europe Capacity Data'!I48+'Asia Capacity Data'!I48+'MEA Capacity Data'!I48 -> 2 | ... Q48: ='NAm Capacity Data'!Q48+'SAm Capacity Data'!Q48+'Europe Capacity Data'!Q48+'Asia Capacity Data'!Q48+'MEA Capacity Data'!Q48 -> 0 | R48: =SUM(B48:P48) -> 36
A49: Total Plants | B49: =SUM(B43:B48) -> 9 | C49: =B49+SUM(C43:C48) -> 18 | D49: =C49+SUM(D43:D48) -> 32 | E49: =D49+SUM(E43:E48) -> 34 | F49: =E49+SUM(F43:F48) -> 67 | G49: =F49+SUM(G43:G48) -> 118 | H49: =G49+SUM(H43:H48) -> 163 | I49: =H49+SUM(I43:I48) -> 218 | J49: =I49+SUM(J43:J48) -> 260 | ... Q49: =P49+SUM(Q43:Q48) -> 327 | R49: =SUM(R43:R48) -> 326
A51: Global SAF Capacity by Feedstock
A52: =A22 -> (mil gal/yr) | B52: =B22 -> < 2021 | C52: =C22 -> 2021 | D52: =D22 -> 2022 | E52: =E22 -> 2023 | F52: =F22 -> 2024 | G52: =G22 -> 2025 | H52: =H22 -> 2026 | ... Q52: =Q22 -> 2035
A53: FOGs | B53: ='NAm Capacity Data'!B13+'SAm Capacity Data'!B53+'Europe Capacity Data'!B53+'Asia Capacity Data'!B62 -> 97.33 | C53: ='NAm Capacity Data'!C13+'SAm Capacity Data'!C53+'Europe Capacity Data'!C53+'Asia Capacity Data'!C62 -> 113.01 | D53: ='NAm Capacity Data'!D13+'SAm Capacity Data'!D53+'Europe Capacity Data'!D53+'Asia Capacity Data'!D62 -> 566.56038 | E53: ='NAm Capacity Data'!E13+'SAm Capacity Data'!E53+'Europe Capacity Data'!E53+'Asia Capacity Data'!E62 -> 886.75 | F53: ='NAm Capacity Data'!F13+'SAm Capacity Data'!F53+'Europe Capacity Data'!F53+'Asia Capacity Data'!F62 -> 2192.03 | G53: ='NAm Capacity Data'!G13+'SAm Capacity Data'!G53+'Europe Capacity Data'!G53+'Asia Capacity Data'!G62 -> 3535.9393 | H53: ='NAm Capacity Data'!H13+'SAm Capacity Data'!H53+'Europe Capacity Data'!H53+'Asia Capacity Data'!H62 -> 3657.9853 | I53: ='NAm Capacity Data'!I13+'SAm Capacity Data'!I53+'Europe Capacity Data'!I53+'Asia Capacity Data'!I62 -> 4341.0993 | ... Q53: ='NAm Capacity Data'!Q13+'SAm Capacity Data'!Q53+'Europe Capacity Data'!Q53+'Asia Capacity Data'!Q62 -> 4720.6993
A54: Ethanol | B54: ='NAm Capacity Data'!B14+'SAm Capacity Data'!B54+'Europe Capacity Data'!B54+'Asia Capacity Data'!B63 -> 3.0001 | C54: ='NAm Capacity Data'!C14+'SAm Capacity Data'!C54+'Europe Capacity Data'!C54+'Asia Capacity Data'!C63 -> 3.0001 | D54: ='NAm Capacity Data'!D14+'SAm Capacity Data'!D54+'Europe Capacity Data'!D54+'Asia Capacity Data'!D63 -> 3.0001 | E54: ='NAm Capacity Data'!E14+'SAm Capacity Data'!E54+'Europe Capacity Data'!E54+'Asia Capacity Data'!E63 -> 3.0001 | F54: ='NAm Capacity Data'!F14+'SAm Capacity Data'!F54+'Europe Capacity Data'!F54+'Asia Capacity Data'!F63 -> 12.0001 | G54: ='NAm Capacity Data'!G14+'SAm Capacity Data'!G54+'Europe Capacity Data'!G54+'Asia Capacity Data'!G63 -> 195.64572 | H54: ='NAm Capacity Data'!H14+'SAm Capacity Data'!H54+'Europe Capacity Data'!H54+'Asia Capacity Data'!H63 -> 284.24572 | I54: ='NAm Capacity Data'!I14+'SAm Capacity Data'!I54+'Europe Capacity Data'!I54+'Asia Capacity Data'!I63 -> 662.60822 | ... Q54: ='NAm Capacity Data'!Q14+'SAm Capacity Data'!Q54+'Europe Capacity Data'!Q54+'Asia Capacity Data'!Q63 -> 1004.3132
A55: Woody Biomass | B55: ='NAm Capacity Data'!B15+'SAm Capacity Data'!B55+'Europe Capacity Data'!B55+'Asia Capacity Data'!B64 -> 0 | C55: ='NAm Capacity Data'!C15+'SAm Capacity Data'!C55+'Europe Capacity Data'!C55+'Asia Capacity Data'!C64 -> 0 | D55: ='NAm Capacity Data'!D15+'SAm Capacity Data'!D55+'Europe Capacity Data'!D55+'Asia Capacity Data'!D64 -> 0 | E55: ='NAm Capacity Data'!E15+'SAm Capacity Data'!E55+'Europe Capacity Data'!E55+'Asia Capacity Data'!E64 -> 0 | F55: ='NAm Capacity Data'!F15+'SAm Capacity Data'!F55+'Europe Capacity Data'!F55+'Asia Capacity Data'!F64 -> 0 | G55: ='NAm Capacity Data'!G15+'SAm Capacity Data'!G55+'Europe Capacity Data'!G55+'Asia Capacity Data'!G64 -> 105.09 | H55: ='NAm Capacity Data'!H15+'SAm Capacity Data'!H55+'Europe Capacity Data'!H55+'Asia Capacity Data'!H64 -> 71.1275 | I55: ='NAm Capacity Data'!I15+'SAm Capacity Data'!I55+'Europe Capacity Data'!I55+'Asia Capacity Data'!I64 -> 258.933 | ... Q55: ='NAm Capacity Data'!Q15+'SAm Capacity Data'!Q55+'Europe Capacity Data'!Q55+'Asia Capacity Data'!Q64 -> 452.358
A56: CCS | B56: ='NAm Capacity Data'!B16+'SAm Capacity Data'!B56+'Europe Capacity Data'!B56+'Asia Capacity Data'!B65 -> 0 | C56: ='NAm Capacity Data'!C16+'SAm Capacity Data'!C56+'Europe Capacity Data'!C56+'Asia Capacity Data'!C65 -> 0.0066 | D56: ='NAm Capacity Data'!D16+'SAm Capacity Data'!D56+'Europe Capacity Data'!D56+'Asia Capacity Data'!D65 -> 0.067 | E56: ='NAm Capacity Data'!E16+'SAm Capacity Data'!E56+'Europe Capacity Data'!E56+'Asia Capacity Data'!E65 -> 0.001 | F56: ='NAm Capacity Data'!F16+'SAm Capacity Data'!F56+'Europe Capacity Data'!F56+'Asia Capacity Data'!F65 -> 1.3243127 | G56: ='NAm Capacity Data'!G16+'SAm Capacity Data'!G56+'Europe Capacity Data'!G56+'Asia Capacity Data'!G65 -> 1.4977562 | H56: ='NAm Capacity Data'!H16+'SAm Capacity Data'!H56+'Europe Capacity Data'!H56+'Asia Capacity Data'!H65 -> 78.993631 | I56: ='NAm Capacity Data'!I16+'SAm Capacity Data'!I56+'Europe Capacity Data'!I56+'Asia Capacity Data'!I65 -> 95.806756 | ... Q56: ='NAm Capacity Data'!Q16+'SAm Capacity Data'!Q56+'Europe Capacity Data'!Q56+'Asia Capacity Data'!Q65 -> 65.614756
A57: MSW | B57: ='NAm Capacity Data'!B17+'SAm Capacity Data'!B57+'Europe Capacity Data'!B57+'Asia Capacity Data'!B66 -> 0 | C57: ='NAm Capacity Data'!C17+'SAm Capacity Data'!C57+'Europe Capacity Data'!C57+'Asia Capacity Data'!C66 -> 0 | D57: ='NAm Capacity Data'!D17+'SAm Capacity Data'!D57+'Europe Capacity Data'!D57+'Asia Capacity Data'!D66 -> 0 | E57: ='NAm Capacity Data'!E17+'SAm Capacity Data'!E57+'Europe Capacity Data'!E57+'Asia Capacity Data'!E66 -> 0 | F57: ='NAm Capacity Data'!F17+'SAm Capacity Data'!F57+'Europe Capacity Data'!F57+'Asia Capacity Data'!F66 -> 0.462 | G57: ='NAm Capacity Data'!G17+'SAm Capacity Data'!G57+'Europe Capacity Data'!G57+'Asia Capacity Data'!G66 -> 35.086 | H57: ='NAm Capacity Data'!H17+'SAm Capacity Data'!H57+'Europe Capacity Data'!H57+'Asia Capacity Data'!H66 -> 9.65 | I57: ='NAm Capacity Data'!I17+'SAm Capacity Data'!I57+'Europe Capacity Data'!I57+'Asia Capacity Data'!I66 -> 70.6175 | ... Q57: ='NAm Capacity Data'!Q17+'SAm Capacity Data'!Q57+'Europe Capacity Data'!Q57+'Asia Capacity Data'!Q66 -> 12.95
A58: Total Capacity | B58: =SUM(B53:B57) -> 100.3301 | C58: =B58+SUM(C53:C57) -> 216.3468 | D58: =C58+SUM(D53:D57) -> 785.97428 | E58: =D58+SUM(E53:E57) -> 1675.7254 | F58: =E58+SUM(F53:F57) -> 3881.5418 | G58: =F58+SUM(G53:G57) -> 7754.8006 | H58: =G58+SUM(H53:H57) -> 11856.803 | I58: =H58+SUM(I53:I57) -> 17285.868 | J58: =I58+SUM(J53:J57) -> 23438.728 | ... Q58: =P58+SUM(Q53:Q57) -> 67752.804
A60: Global Cumulative SAF Capacity by Feedstock - do not use these numbers before checking with Tore | Z60: 10000
A61: =A22 -> (mil gal/yr) | B61: =B22 -> < 2021 | C61: =C22 -> 2021 | D61: =D22 -> 2022 | E61: =E22 -> 2023 | F61: =F22 -> 2024 | G61: =G22 -> 2025 | H61: =H22 -> 2026 | ... Q61: =Q22 -> 2035 | S61: =C61 -> 2021 | T61: =D61 -> 2022 | U61: =E61 -> 2023 | V61: =F61 -> 2024 | W61: =G61 -> 2025 | X61: =H61 -> 2026 | Y61: =I61 -> 2027 | Z61: =J61 -> 2028 | ... AD61: =N61 -> 2032
A62: Fats, Oils and Greases | B62: =B53 -> 97.33 | C62: =B62+C53 -> 210.34 | D62: =C62+D53 -> 776.90037 | E62: =D62+E53 -> 1663.6504 | F62: =E62+F53 -> 3855.6804 | G62: =F62+G53 -> 7391.6197 | H62: =G62+H53 -> 11049.605 | I62: =H62+I53 -> 15390.704 | J62: =I62+J53 -> 20160.322 | ... Q62: =P62+Q53 -> 53220.847 | R62: =A62 -> Fats, Oils and Greases | S62: =C71*0.000453592 -> 0.42289856 | T62: =D71*0.000453592 -> 2.1201448 | U62: =E71*0.000453592 -> 3.3183373 | V62: =F71*0.000453592 -> 8.20287 | W62: =G71*0.000453592 -> 13.231959 | X62: =H71*0.000453592 -> 13.688671 | Y62: =I71*0.000453592 -> 16.244975 | Z62: =J71*0.000453592 -> 17.848549 | AA62: 17.5 | AB62: =L71*0.000453592 -> 18.099315 | AC62: =M71*0.000453592 -> 17.628442 | AD62: =N71*0.000453592 -> 17.665489 | AE62: =15.14/5 -> 3.028
A63: Ethanol | B63: =B54 -> 3.0001 | C63: =B63+C54 -> 6.0002 | D63: =C63+D54 -> 9.0003 | E63: =D63+E54 -> 12.0004 | F63: =E63+F54 -> 24.0005 | G63: =F63+G54 -> 219.64623 | H63: =G63+H54 -> 503.89195 | I63: =H63+I54 -> 1166.5002 | J63: =I63+J54 -> 2047.4574 | ... Q63: =P63+Q54 -> 8940.274 | R63: =A63 -> Ethanol | S63: =C72*0.000453592 -> 0.027610868 | T63: =D72*0.000453592 -> 0.027610868 | U63: =E72*0.000453592 -> 0.027610868 | V63: =F72*0.000453592 -> 0.11044071 | W63: =G72*0.000453592 -> 1.8005894 | X63: =H72*0.000453592 -> 2.6160032 | Y63: =I72*0.000453592 -> 6.0981928 | Z63: =J72*0.000453592 -> 8.1077277 | ... AD63: =N72*0.000453592 -> 9.2430119
A64: Woody Biomass | B64: =B55 -> 0 | C64: =B64+C55 -> 0 | D64: =C64+D55 -> 0 | E64: =D64+E55 -> 0 | F64: =E64+F55 -> 0 | G64: =F64+G55 -> 105.09 | H64: =G64+H55 -> 176.2175 | I64: =H64+I55 -> 435.1505 | J64: =I64+J55 -> 679.4135 | ... Q64: =P64+Q55 -> 3697.3245 | R64: =A64 -> Woody Biomass | S64: =C73*0.000453592 -> 0 | T64: =D73*0.000453592 -> 0 | U64: =E73*0.000453592 -> 0 | V64: =F73*0.000453592 -> 0 | W64: =G73*0.000453592 -> 1.6683794 | X64: =H73*0.000453592 -> 1.1292003 | Y64: =I73*0.000453592 -> 4.1107478 | Z64: =J73*0.000453592 -> 3.877851 | ... AD64: =N73*0.000453592 -> 7.1815089
A65: CCS | B65: =B56 -> 0 | C65: =B65+C56 -> 0.0066 | D65: =C65+D56 -> 0.0736 | E65: =D65+E56 -> 0.0746 | F65: =E65+F56 -> 1.3989127 | G65: =F65+G56 -> 2.8966689 | H65: =G65+H56 -> 81.8903 | I65: =H65+I56 -> 177.69706 | J65: =I65+J56 -> 350.81981 | ... Q65: =P65+Q56 -> 1537.563 | R65: =A65 -> CCS | S65: =C74*0.000453592 -> 5.7548835e-05 | T65: =D74*0.000453592 -> 0.00058420787 | U65: =E74*0.000453592 -> 8.7195204e-06 | V65: =F74*0.000453592 -> 0.011547372 | W65: =G74*0.000453592 -> 0.013059716 | X65: =H74*0.000453592 -> 0.68878658 | Y65: =I74*0.000453592 -> 0.83538897 | Z65: =J74*0.000453592 -> 1.5095474 | ... AD65: =N74*0.000453592 -> 3.545381
A66: MSW | B66: =B57 -> 0 | C66: =B66+C57 -> 0 | D66: =C66+D57 -> 0 | E66: =D66+E57 -> 0 | F66: =E66+F57 -> 0.462 | G66: =F66+G57 -> 35.548 | H66: =G66+H57 -> 45.198 | I66: =H66+I57 -> 115.8155 | J66: =I66+J57 -> 200.7155 | ... Q66: =P66+Q57 -> 356.7955 | R66: =A66 -> MSW | S66: =C75*0.000453592 -> 0 | T66: =D75*0.000453592 -> 0 | U66: =E75*0.000453592 -> 0 | V66: =F75*0.000453592 -> 0.0083404683 | W66: =G75*0.000453592 -> 0.63340621 | X66: =H75*0.000453592 -> 0.17421108 | Y66: =I75*0.000453592 -> 1.274855 | Z66: =J75*0.000453592 -> 1.5326964 | ... AD66: =N75*0.000453592 -> 1.1062855
A67: Total Capacity | B67: =SUM(B62:B66) -> 100.3301 | C67: =SUM(C62:C66) -> 216.3468 | D67: =SUM(D62:D66) -> 785.97428 | E67: =SUM(E62:E66) -> 1675.7254 | F67: =SUM(F62:F66) -> 3881.5418 | G67: =SUM(G62:G66) -> 7754.8006 | H67: =SUM(H62:H66) -> 11856.803 | I67: =SUM(I62:I66) -> 17285.868 | ... Q67: =SUM(Q62:Q66) -> 67752.804 | R67: =A67 -> Total Capacity | S67: =SUM(S62:S66) -> 0.45056698 | T67: =SUM(T62:T66) -> 2.1483399 | U67: =SUM(U62:U66) -> 3.3459569 | V67: =SUM(V62:V66) -> 8.3331985 | W67: =SUM(W62:W66) -> 17.347393 | X67: =SUM(X62:X66) -> 18.296872 | Y67: =SUM(Y62:Y66) -> 28.56416 | Z67: =SUM(Z62:Z66) -> 32.876371 | ... AD67: =SUM(AD62:AD66) -> 38.741677
A69: Implied Feedstock Demand | B69: =B71/2204.622 -> 0.3642223 | C69: =C71/2204.622 -> 0.42289903 | D69: =D71/2204.622 -> 2.1201472 | E69: =E71/2204.622 -> 3.318341 | F69: =F71/2204.622 -> 8.202879 | G69: =G71/2204.622 -> 13.231973 | H69: =H71/2204.622 -> 13.688686 | I69: =I71/2204.622 -> 16.244993 | ... Q69: =Q71/2204.622 -> 17.665509 | S69: Feedstock Assumptions | U69: Range
A70: (mil lbs/yr) | B70: =B22 -> < 2021 | C70: =C22 -> 2021 | D70: =D22 -> 2022 | E70: =E22 -> 2023 | F70: =F22 -> 2024 | G70: =G22 -> 2025 | H70: =H22 -> 2026 | I70: =I22 -> 2027 | ... Q70: =Q22 -> 2035
A71: FOGs (mil lbs) | B71: =B53*$S71 -> 802.9725 | C71: =C53*$S71 -> 932.3325 | D71: =D53*$S71 -> 4674.1231 | E71: =E53*$S71 -> 7315.6875 | F71: =F53*$S71 -> 18084.247 | G71: =G53*$S71 -> 29171.499 | H71: =H53*$S71 -> 30178.379 | I71: =I53*$S71 -> 35814.069 | ... Q71: =Q53*$S71 -> 38945.769 | S71: 8.25 | T71: lbs/gal | U71: 7.5-8.3
A72: Grains (mil lbs) | B72: =B54*$S72 -> 60.871594 | C72: =C54*$S72 -> 60.871594 | D72: =D54*$S72 -> 60.871594 | E72: =E54*$S72 -> 60.871594 | F72: =F54*$S72 -> 243.48029 | G72: =G54*$S72 -> 3969.6234 | H72: =H54*$S72 -> 5767.3046 | I72: =I54*$S72 -> 13444.225 | ... Q72: =Q54*$S72 -> 20377.37 | S72: =S80*56 -> 20.289855 | T72: lbs/gal
A73: Woody Biomass (mil lbs) | B73: =B55*$S73 -> 0 | C73: =C55*$S73 -> 0 | D73: =D55*$S73 -> 0 | E73: =E55*$S73 -> 0 | F73: =F55*$S73 -> 0 | G73: =G55*$S73 -> 3678.15 | H73: =H55*$S73 -> 2489.4625 | I73: =I55*$S73 -> 9062.655 | ... Q73: =Q55*$S73 -> 15832.53 | S73: 35 | T73: lbs/gal | U73: 33-40
A74: CCS (mil lbs) | B74: =B56*$S74 -> 0 | C74: =C56*$S74 -> 0.12687357 | D74: =D56*$S74 -> 1.2879589 | E74: =E56*$S74 -> 0.019223268 | F74: =F56*$S74 -> 25.457617 | G74: =G56*$S74 -> 28.791768 | H74: =H56*$S74 -> 1518.5157 | I74: =I56*$S74 -> 1841.7189 | ... Q74: =Q56*$S74 -> 1261.33 | S74: 19.223268 | T74: lbs/gal | U74: 69 grams of CO2 per megajoule of SAF and 1 gallon of SAF is equal to a lower heating value (LHV) of 126.37 megajoules, so 69 g CO2/MJ X 126.37 MJ/gal = 8719.3 g CO2 /gallon and 8719.3 grams / 1000000 g / tonne = 0.00871953 tonnes CO2 per gallon
A75: MSW (mil lbs) | B75: =B57*$S75 -> 0 | C75: =C57*$S75 -> 0 | D75: =D57*$S75 -> 0 | E75: =E57*$S75 -> 0 | F75: =F57*$S75 -> 18.3876 | G75: =G57*$S75 -> 1396.4228 | H75: =H57*$S75 -> 384.07 | I75: =I57*$S75 -> 2810.5765 | ... Q75: =Q57*$S75 -> 515.41 | S75: 39.8 | T75: lbs/gal
B76: =B72/56 -> 1.0869928 | C76: =C72/56 -> 1.0869928 | D76: =D72/56 -> 1.0869928 | E76: =E72/56 -> 1.0869928 | F76: =F72/56 -> 4.3478623 | G76: =G72/56 -> 70.886132 | H76: =H72/56 -> 102.98758 | I76: =I72/56 -> 240.07544 | ... Q76: =Q72/56 -> 363.8816
A77: Corn to SAF Conversions | B77: =B76/39.3674 -> 0.027611495 | C77: =C76/39.3674 -> 0.027611495 | D77: =D76/39.3674 -> 0.027611495 | E77: =E76/39.3674 -> 0.027611495 | F77: =F76/39.3674 -> 0.11044322 | G77: =G76/39.3674 -> 1.8006303 | H77: =H76/39.3674 -> 2.6160626 | I77: =I76/39.3674 -> 6.0983312 | ... Q77: =Q76/39.3674 -> 9.2432216
A78: Ethanol (mil lbs) | B78: =B79*$S78 -> 33.017001 | C78: =C79*$S78 -> 66.034001 | D78: =D79*$S78 -> 99.051002 | E78: =E79*$S78 -> 132.068 | F78: =F79*$S78 -> 264.1327 | G78: =G79*$S78 -> 2417.2726 | H78: =H79*$S78 -> 5545.4821 | I78: =I79*$S78 -> 12837.684 | ... Q78: =Q79*$S78 -> 98390.397 | S78: 6.59 | T78: lbs/gal
A79: Ethanol (mil gal) | B79: =B63*$S79 -> 5.010167 | C79: =C63*$S79 -> 10.020334 | D79: =D63*$S79 -> 15.030501 | E79: =E63*$S79 -> 20.040668 | F79: =F63*$S79 -> 40.080835 | G79: =G63*$S79 -> 366.8092 | H79: =H63*$S79 -> 841.49956 | I79: =I63*$S79 -> 1948.0553 | ... Q79: =Q63*$S79 -> 14930.258 | S79: 1.67 | T79: gal/gal | U79: 1.5-1.7
A80: Corn (mil bu) | B80: =B79*$S80 -> 1.8152779 | C80: =C79*$S80 -> 3.6305558 | D80: =D79*$S80 -> 5.4458337 | E80: =E79*$S80 -> 7.2611116 | F80: =F79*$S80 -> 14.522042 | G80: =G79*$S80 -> 132.90188 | H80: =H79*$S80 -> 304.89114 | I80: =I79*$S80 -> 705.81713 | ... Q80: =Q79*$S80 -> 5409.5136 | S80: =1/S81 -> 0.36231884 | T80: bu/gal | U80: .3704-.3571
S81: 2.76 | T81: gal/bu | U81: 2.7-2.8
A82: Airline Miles | C82: ='NAm Capacity Data'!C82+'SAm Capacity Data'!C82+'Europe Capacity Data'!C82+'Asia Capacity Data'!C82+'MEA Capacity Data'!C82 -> 573403.84 | D82: ='NAm Capacity Data'!D82+'SAm Capacity Data'!D82+'Europe Capacity Data'!D82+'Asia Capacity Data'!D82+'MEA Capacity Data'!D82 -> 708959.96 | E82: ='NAm Capacity Data'!E82+'SAm Capacity Data'!E82+'Europe Capacity Data'!E82+'Asia Capacity Data'!E82+'MEA Capacity Data'!E82 -> 773411.56 | F82: ='NAm Capacity Data'!F82+'SAm Capacity Data'!F82+'Europe Capacity Data'!F82+'Asia Capacity Data'!F82+'MEA Capacity Data'!F82 -> 785786.14 | G82: ='NAm Capacity Data'!G82+'SAm Capacity Data'!G82+'Europe Capacity Data'!G82+'Asia Capacity Data'!G82+'MEA Capacity Data'!G82 -> 807002.37 | H82: ='NAm Capacity Data'!H82+'SAm Capacity Data'!H82+'Europe Capacity Data'!H82+'Asia Capacity Data'!H82+'MEA Capacity Data'!H82 -> 828791.43 | I82: ='NAm Capacity Data'!I82+'SAm Capacity Data'!I82+'Europe Capacity Data'!I82+'Asia Capacity Data'!I82+'MEA Capacity Data'!I82 -> 851168.8 | J82: ='NAm Capacity Data'!J82+'SAm Capacity Data'!J82+'Europe Capacity Data'!J82+'Asia Capacity Data'!J82+'MEA Capacity Data'!J82 -> 874150.36 | ... Q82: ='NAm Capacity Data'!Q82+'SAm Capacity Data'!Q82+'Europe Capacity Data'!Q82+'Asia Capacity Data'!Q82+'MEA Capacity Data'!Q82 -> 1053365.9
A83: Gallons of Fuel per Mile | C83: ='NAm Capacity Data'!C83+'SAm Capacity Data'!C83+'Europe Capacity Data'!C83+'Asia Capacity Data'!C83+'MEA Capacity Data'!C83 -> 2.2708233 | D83: ='NAm Capacity Data'!D83+'SAm Capacity Data'!D83+'Europe Capacity Data'!D83+'Asia Capacity Data'!D83+'MEA Capacity Data'!D83 -> 2.482136 | E83: ='NAm Capacity Data'!E83+'SAm Capacity Data'!E83+'Europe Capacity Data'!E83+'Asia Capacity Data'!E83+'MEA Capacity Data'!E83 -> 2.5555923 | F83: ='NAm Capacity Data'!F83+'SAm Capacity Data'!F83+'Europe Capacity Data'!F83+'Asia Capacity Data'!F83+'MEA Capacity Data'!F83 -> 2.4936488 | G83: ='NAm Capacity Data'!G83+'SAm Capacity Data'!G83+'Europe Capacity Data'!G83+'Asia Capacity Data'!G83+'MEA Capacity Data'!G83 -> 2.5439432 | H83: ='NAm Capacity Data'!H83+'SAm Capacity Data'!H83+'Europe Capacity Data'!H83+'Asia Capacity Data'!H83+'MEA Capacity Data'!H83 -> 2.6003747 | I83: ='NAm Capacity Data'!I83+'SAm Capacity Data'!I83+'Europe Capacity Data'!I83+'Asia Capacity Data'!I83+'MEA Capacity Data'!I83 -> 2.591866 | J83: ='NAm Capacity Data'!J83+'SAm Capacity Data'!J83+'Europe Capacity Data'!J83+'Asia Capacity Data'!J83+'MEA Capacity Data'!J83 -> 2.6054764 | ... Q83: ='NAm Capacity Data'!Q83+'SAm Capacity Data'!Q83+'Europe Capacity Data'!Q83+'Asia Capacity Data'!Q83+'MEA Capacity Data'!Q83 -> 2.7678637
A84: Blending Rate/Mandated
A85: Blending Rate/Possible
A86: Blending Rate Achieved | C86: =C89/C88 -> #REF! | D86: =D89/D88 -> #REF!
A88: Domestic Jet Fuel Consumption | C88: ='NAm Capacity Data'!C88+'SAm Capacity Data'!C88+'Europe Capacity Data'!C88+'Asia Capacity Data'!C88+'MEA Capacity Data'!C88 -> 252509.23 | D88: ='NAm Capacity Data'!D88+'SAm Capacity Data'!D88+'Europe Capacity Data'!D88+'Asia Capacity Data'!D88+'MEA Capacity Data'!D88 -> 285624.94 | E88: ='NAm Capacity Data'!E88+'SAm Capacity Data'!E88+'Europe Capacity Data'!E88+'Asia Capacity Data'!E88+'MEA Capacity Data'!E88 -> 302634.95 | F88: ='NAm Capacity Data'!F88+'SAm Capacity Data'!F88+'Europe Capacity Data'!F88+'Asia Capacity Data'!F88+'MEA Capacity Data'!F88 -> 315115 | G88: ='NAm Capacity Data'!G88+'SAm Capacity Data'!G88+'Europe Capacity Data'!G88+'Asia Capacity Data'!G88+'MEA Capacity Data'!G88 -> 317225 | H88: ='NAm Capacity Data'!H88+'SAm Capacity Data'!H88+'Europe Capacity Data'!H88+'Asia Capacity Data'!H88+'MEA Capacity Data'!H88 -> 318720 | I88: ='NAm Capacity Data'!I88+'SAm Capacity Data'!I88+'Europe Capacity Data'!I88+'Asia Capacity Data'!I88+'MEA Capacity Data'!I88 -> 328400 | J88: ='NAm Capacity Data'!J88+'SAm Capacity Data'!J88+'Europe Capacity Data'!J88+'Asia Capacity Data'!J88+'MEA Capacity Data'!J88 -> 335505 | ... Q88: ='NAm Capacity Data'!Q88+'SAm Capacity Data'!Q88+'Europe Capacity Data'!Q88+'Asia Capacity Data'!Q88+'MEA Capacity Data'!Q88 -> 380570
A89: Domestic SAF Consumption | C89: ='NAm Capacity Data'!C89+'SAm Capacity Data'!C89+'Europe Capacity Data'!C89+'Asia Capacity Data'!C89+'MEA Capacity Data'!C89 -> #REF! | D89: ='NAm Capacity Data'!D89+'SAm Capacity Data'!D89+'Europe Capacity Data'!D89+'Asia Capacity Data'!D89+'MEA Capacity Data'!D89 -> #REF! | E89: ='NAm Capacity Data'!E89+'SAm Capacity Data'!E89+'Europe Capacity Data'!E89+'Asia Capacity Data'!E89+'MEA Capacity Data'!E89 -> #REF! | F89: ='NAm Capacity Data'!F89+'SAm Capacity Data'!F89+'Europe Capacity Data'!F89+'Asia Capacity Data'!F89+'MEA Capacity Data'!F89 -> #REF! | G89: ='NAm Capacity Data'!G89+'SAm Capacity Data'!G89+'Europe Capacity Data'!G89+'Asia Capacity Data'!G89+'MEA Capacity Data'!G89 -> #REF! | H89: ='NAm Capacity Data'!H89+'SAm Capacity Data'!H89+'Europe Capacity Data'!H89+'Asia Capacity Data'!H89+'MEA Capacity Data'!H89 -> #REF! | I89: ='NAm Capacity Data'!I89+'SAm Capacity Data'!I89+'Europe Capacity Data'!I89+'Asia Capacity Data'!I89+'MEA Capacity Data'!I89 -> #REF! | J89: ='NAm Capacity Data'!J89+'SAm Capacity Data'!J89+'Europe Capacity Data'!J89+'Asia Capacity Data'!J89+'MEA Capacity Data'!J89 -> #REF! | ... Q89: ='NAm Capacity Data'!Q89+'SAm Capacity Data'!Q89+'Europe Capacity Data'!Q89+'Asia Capacity Data'!Q89+'MEA Capacity Data'!Q89 -> #REF!
A91: Madates
A92: =A22 -> (mil gal/yr) | B92: =B22 -> < 2021 | C92: =C22 -> 2021 | D92: =D22 -> 2022 | E92: =E22 -> 2023 | F92: =F22 -> 2024 | G92: =G22 -> 2025 | H92: =H22 -> 2026 | ... Q92: =Q22 -> 2035 | R92: 2050 | T92: Goals of the SAF Grand Challenge
A93: US Federal-Level Programs | T93: 1. Reduce cost of SAF
A94: SAF Grand Challenge | L94: 3000 | R94: 35000 | T94: 2. Enhance the sustainability of SAF
A95: US State-Level Programs
A96: Low Carbon Fuel Standard (LCFS) | T96: 3. Expand the production of SAF
A97: Clean Fuels Program (CFP) | T97: 4. Reduce life cycle GHG emissions by 50% from conventional fuel by 2030
A98: Clean Fuel Standard (CFS)
A99: Canada Federal-Level Programs
A100: Clean Fuel Regulation (CFR) | L100: =MROUND(1000/3.78541,5) -> 265 | R100: =MROUND(8000/3.78541,5) -> 2115
A101: Canada Province-Level Programs
A102: British Colombia
A103: CORSIA Programs
A104: SAF Grand Challenge
A105: Total Mandated Volume | B105: =SUM(B100,B96:B98,B94) -> 0 | C105: =SUM(C100,C96:C98,C94) -> 0 | D105: =SUM(D100,D96:D98,D94) -> 0 | E105: =SUM(E100,E96:E98,E94) -> 0 | F105: =SUM(F100,F96:F98,F94) -> 0 | G105: =SUM(G100,G96:G98,G94) -> 0 | H105: =SUM(H100,H96:H98,H94) -> 0 | I105: =SUM(I100,I96:I98,I94) -> 0 | ... R105: =SUM(R100,R96:R98,R94) -> 37115
A106: Notes:
A107: California Air Resources Board (CARB) is proposing an explicit SAF mandate to eliminate the existing exemption for intrastate fossil jet fuel from the LCFS regulations beginning in 2028
A108: The proposed legislation would only apply to intrastate flights, but the requirement would likely apply to intra and interstate flights and international flights
...

Sheet NAm
B1: Location | D1: Notes | F1: an amount that would meet about 40% of intrastate travel demand | J1: Nameplate Capacity
A2: Company | B2: City | C2: Country | D2: Website | E2: Comments | F2: Start Date | G2: Expansion Date | H2: Current Status | I2: % Chance | J2: start-up/operating mmgal/yr | K2: expansion mmgal/yr | L2: t/yr | M2: RD Estimated Nameplate | N2: SAF Estimated Nameplate | O2: RD Expansion | P2: SAF Expansion | Q2: Probability Adjusted RD Nameplate | R2: Probability Adjusted SAF Nameplate | S2: Probability Adjusted RD Expansion | T2: Probability Adjusted SAF Expansion | U2: Energy Technology | V2: Feedstock | W2: New / Old (Converted oil refinery) | X2: Investor Relations Sites
A3: Diamond Green Diesel | B3: Norco, LA | C3: USA | E3: RD & SAF - PRN Newswire article on Sep 17 2014 announced the start up of the facility on Sep 15 | F3: 2014 | H3: Operating | I3: 1 | J3: 982 | M3: 900 | N3: 82 | O3: =IF(K3="",0,(K3*(M3/J3))-M3) -> 0 | P3: =IF(K3="",0,(K3*(N3/J3))-N3) -> 0 | Q3: =M3*$I3 -> 900 | R3: =N3*$I3 -> 82 | S3: =O3*$I3 -> 0 | T3: =P3*$I3 -> 0 | U3: HEFA | V3: FOGs
A4: Phillips 66 Rodeo | B4: San Francisco, CA | C4: USA | D4: https://www.safinvestor.com/opinion/145765/saf/ | E4: Changed column F from "Apr-24" and changed column J from "800 RD/SAF" to automate capacity | F4: 2024 | H4: Operating | I4: 1 | J4: 750 | M4: =J4*0.5 -> 375 | N4: =J4*0.5 -> 375 | O4: =IF(K4="",0,(K4*(M4/J4))-M4) -> 0 | P4: =IF(K4="",0,(K4*(N4/J4))-N4) -> 0 | Q4: =M4*$I4 -> 375 | R4: =N4*$I4 -> 375 | S4: =O4*$I4 -> 0 | T4: =P4*$I4 -> 0 | U4: HEFA | V4: FOGs | W4: Old
A5: NXTClean Fuels | B5: Port Westward, OR | C5: USA | D5: https://nxtclean.com/projects-facilities/port-westward/;https://biodieselmagazine.com/articles/sojitz-next-renewable-fuels-partner-on-oregon-biorefinery-2518722;https://nxtclean.com/projects-facilities/port-westward/ | E5: Construction to start late 2024 - Changed column J from "750 (RD& SAF)" to automate capacity | F5: 2026 | H5: Construction | I5: 0.75 | J5: 750 | M5: 375 | N5: 375 | O5: =IF(K5="",0,(K5*(M5/J5))-M5) -> 0 | P5: =IF(K5="",0,(K5*(N5/J5))-N5) -> 0 | Q5: =M5*$I5 -> 281.25 | R5: =N5*$I5 -> 281.25 | S5: =O5*$I5 -> 0 | T5: =P5*$I5 -> 0 | U5: HEFA | V5: FOGs
A6: Martinez Renewables (Marathon/Neste) | B6: Martinez, CA | C6: USA | D6: https://www.safinvestor.com/opinion/145765/saf/ | E6: 730mmgal/yr | F6: 2027 | H6: operating at min SAF maybe 2026 | I6: 0.5 | J6: 730 | M6: 380 | N6: 350 | O6: =IF(K6="",0,(K6*(M6/J6))-M6) -> 0 | P6: =IF(K6="",0,(K6*(N6/J6))-N6) -> 0 | Q6: =M6*$I6 -> 190 | R6: =N6*$I6 -> 175 | S6: =O6*$I6 -> 0 | T6: =P6*$I6 -> 0 | U6: HEFA | V6: FOGs | W6: Old
A7: CVR Energy | B7: Coffeyville, KS | C7: USA | D7: https://www.ogj.com/energy-transition/article/14301683/cvr-energy-lets-contract-for-proposed-kansas-renewable-fuels-plant | E7: Changed column J from "500 (up to 250 SAF)" | F7: 2027 | H7: ON HOLD | I7: 0.01 | J7: 500 | M7: =J7/2 -> 250 | N7: =J7/2 -> 250 | O7: =IF(K7="",0,(K7*(M7/J7))-M7) -> 0 | P7: =IF(K7="",0,(K7*(N7/J7))-N7) -> 0 | Q7: =M7*$I7 -> 2.5 | R7: =N7*$I7 -> 2.5 | S7: =O7*$I7 -> 0 | T7: =P7*$I7 -> 0 | U7: HEFA | V7: FOGs
A8: Gron/Fidelis New Energy | B8: Baton Rouge, LA | C8: USA | D8: https://fidelisinfra.com/project/gron-fuels-llc/#;https://www.businessreport.com/business/heres-the-latest-on-baton-rouges-massive-gron-fuels-project | E8: Changed column J from "497 50/50 SAF/Other" to automate capacity | F8: 2027 | H8: 8/22 update: construction not started - way behind | I8: 0.75 | J8: 497 | M8: =J8/2 -> 248.5 | N8: =J8/2 -> 248.5 | O8: =IF(K8="",0,(K8*(M8/J8))-M8) -> 0 | P8: =IF(K8="",0,(K8*(N8/J8))-N8) -> 0 | Q8: =M8*$I8 -> 186.375 | R8: =N8*$I8 -> 186.375 | S8: =O8*$I8 -> 0 | T8: =P8*$I8 -> 0 | U8: HEFA | V8: FOGs
A9: Diamond Green Diesel | B9: Port Arthur, TX | C9: USA | D9: https://www.prnewswire.com/news-releases/diamond-green-diesel-dgd-approves-a-sustainable-aviation-fuel-project-at-port-arthur-texas-301735115.html; https://safmagazine.com/articles/valero-reports-strong-q2-for-renewables | E9: Converting already RD to 50/50 RD/SAF 470mn gal/yr - changed from Q4 2024 to automate capacity | F9: 2024 | H9: Operating | I9: 1 | J9: 470 | M9: =J9*0.1 -> 47 | N9: =J9*0.9 -> 423 | O9: =IF(K9="",0,(K9*(M9/J9))-M9) -> 0 | P9: =IF(K9="",0,(K9*(N9/J9))-N9) -> 0 | Q9: =M9*$I9 -> 47 | R9: =N9*$I9 -> 423 | S9: =O9*$I9 -> 0 | T9: =P9*$I9 -> 0 | U9: HEFA | V9: FOGs
A10: Texmark Chemicals | B10: Houston , TX | C10: USA | D10: https://advancedbiofuelsusa.info/epa-approves-rfs-fuel-pathway-filed-by-texmark-neste | E10: Neste RD from Koole Facility - Texmark filed for bankruptcy so not sure it is still open | F10: 2021 | H10: Operating/Closed | I10: 0.001 | J10: 350 | M10: 0 | N10: 350 | O10: =IF(K10="",0,(K10*(M10/J10))-M10) -> 0 | P10: =IF(K10="",0,(K10*(N10/J10))-N10) -> 0 | Q10: =M10*$I10 -> 0 | R10: =N10*$I10 -> 0.35 | S10: =O10*$I10 -> 0 | T10: =P10*$I10 -> 0 | U10: HEFA | V10: FOGs
A11: Azure | B11: Manitoba | C11: CA | D11: https://www.shell.com/business-customers/catalysts-technologies/resources-library/azure-sustainable-fuels-saf-focused-production-facility-canada.html | F11: 2027 | H11: FID scheduled 2025 | I11: 0.5 | J11: 328 | L11: 944000 | M11: 28 | N11: 300 | O11: =IF(K11="",0,(K11*(M11/J11))-M11) -> 0 | P11: =IF(K11="",0,(K11*(N11/J11))-N11) -> 0 | Q11: =M11*$I11 -> 14 | R11: =N11*$I11 -> 150 | S11: =O11*$I11 -> 0 | T11: =P11*$I11 -> 0 | U11: HEFA | V11: FOGs | W11: New | X11: https://www.shell.com/investors/financial-calendar.html
A12: Imperial | B12: Strathcona | C12: CA | D12: https://biodieselmagazine.com/articles/imperial-oil-strathcona-biorefinery-remains-on-track-for-2025-startup, https://biodieselmagazine.com/articles/imperial-oil-strathcona-project-on-track-for-mid-2025-startup | E12: 20,000bbl/d RD (how much SAF?) -- assume 50/50 - changed from 2Q 2025 to automate capacity. EM Q4 2024 call says lookinjg to start up unit in Q2 | F12: 2025 | H12: Construction | I12: 0.8 | J12: =(20000*365*42)*1.1/1000000 -> 337.26 | M12: =J12*0.9 -> 303.534 | N12: =J12*0.1 -> 33.726 | O12: =IF(K12="",0,(K12*(M12/J12))-M12) -> 0 | P12: =IF(K12="",0,(K12*(N12/J12))-N12) -> 0 | Q12: =M12*$I12 -> 242.8272 | R12: =N12*$I12 -> 26.9808 | S12: =O12*$I12 -> 0 | T12: =P12*$I12 -> 0 | U12: HEFA | V12: FOGs | W12: Old | X12: https://www.imperialoil.ca/investors/investor-relations
A13: Braya Renewable Fuels | B13: Come By Chance, Newfoundland | C13: CA | D13: https://brayafuels.com/; https://biofuels-news.com/news/braya-renewable-fuels-begins-commercial-operations/: https://www.renewableenergymagazine.com/biofuels/braya-renewable-fuels-commences-commercial-operations-20240222 | E13: Braya capacity is only listed for RD. not going to produce SAF yet - RD started Feb 2024 | F13: 2024 | H13: Operating | I13: 1 | J13: 275 | M13: =J13*0.9 -> 247.5 | N13: =J13*0.1 -> 27.5 | O13: =IF(K13="",0,(K13*(M13/J13))-M13) -> 0 | P13: =IF(K13="",0,(K13*(N13/J13))-N13) -> 0 | Q13: =M13*$I13 -> 247.5 | R13: =N13*$I13 -> 27.5 | S13: =O13*$I13 -> 0 | T13: =P13*$I13 -> 0 | U13: HEFA | V13: FOGs | W13: New
A14: Summit Next Gen | B14: Houston , TX | C14: USA | D14: https://www.safinvestor.com/news/145913/summit-next-gen/, https://www.prnewswire.com/news-releases/summit-agricultural-group-announces-the-creation-of-summit-next-gen-to-develop-the-worlds-largest-ethanol-to-jet-sustainable-aviation-fuel-facility-301824241.html, https://www.safinvestor.com/news/146889/summit-next-gen-2/ | E14: 60 acre site in Houston Ship Channel - Qualified for JETI tax incentive program in TX | F14: 2027 | H14: FID expected 2025 | I14: 0.5 | J14: 250 | M14: 0 | N14: =J14 -> 250 | O14: =IF(K14="",0,(K14*(M14/J14))-M14) -> 0 | P14: =IF(K14="",0,(K14*(N14/J14))-N14) -> 0 | Q14: =M14*$I14 -> 0 | R14: =N14*$I14 -> 125 | S14: =O14*$I14 -> 0 | T14: =P14*$I14 -> 0 | U14: ATJ | V14: Ethanol
A15: World Energy | B15: Houston , TX | C15: USA | D15: https://www.worldenergy.net/new-technologies | E15: Changed column O from ""HEFA (SAF)" to automate capacity | F15: 2027 | H15: Construction | I15: 0.5 | J15: 250 | M15: =J15/2 -> 125 | N15: =J15/2 -> 125 | O15: =IF(K15="",0,(K15*(M15/J15))-M15) -> 0 | P15: =IF(K15="",0,(K15*(N15/J15))-N15) -> 0 | Q15: =M15*$I15 -> 62.5 | R15: =N15*$I15 -> 62.5 | S15: =O15*$I15 -> 0 | T15: =P15*$I15 -> 0 | U15: HEFA | V15: FOGs
A16: Federated Co-operatives (FCL) | B16: Saskatchewan | C16: CA | D16: https://biodieselmagazine.com/articles/fcl-shelves-plans-for-saskatchewan-renewable-diesel-project | E16: RD Unit 15000bbl/d with adjacent canola crush planned but now paused | F16: 2027 | H16: Paused | I16: 0.01 | J16: =15000*42*365/1000000 -> 229.95 | M16: =J16 -> 229.95 | N16: 0 | O16: =IF(K16="",0,(K16*(M16/J16))-M16) -> 0 | P16: =IF(K16="",0,(K16*(N16/J16))-N16) -> 0 | Q16: =M16*$I16 -> 2.2995 | R16: =N16*$I16 -> 0 | S16: =O16*$I16 -> 0 | T16: =P16*$I16 -> 0 | U16: HEFA | V16: FOGs | W16: New
A17: Valley Green Fuels | B17: Kern County, CA | C17: USA | D17: https://ww2.arb.ca.gov/sites/default/files/classic/fuels/lcfs/fuelpathways/comments/tier2/b0079_report.pdf | E17: Looks like Kern Energy and only RD | F17: 2031 | H17: Planned | I17: 0.25 | J17: 220 | M17: =J17 -> 220 | N17: 0 | O17: =IF(K17="",0,(K17*(M17/J17))-M17) -> 0 | P17: =IF(K17="",0,(K17*(N17/J17))-N17) -> 0 | Q17: =M17*$I17 -> 55 | R17: =N17*$I17 -> 0 | S17: =O17*$I17 -> 0 | T17: =P17*$I17 -> 0 | U17: HEFA | V17: FOGs
A18: DG Fuels | B18: Moorhead, Clay County, MN | C18: USA | D18: https://dgfuels.com/2024/10/30/dg-fuels-to-launch-saf-plant-in-moorhead-minnesota-converting-biomass-into-high-value-fuel/ | F18: 2030 | H18: Planned | I18: 0.25 | J18: 193 | M18: 0 | N18: 193 | O18: =IF(K18="",0,(K18*(M18/J18))-M18) -> 0 | P18: =IF(K18="",0,(K18*(N18/J18))-N18) -> 0 | Q18: =M18*$I18 -> 0 | R18: =N18*$I18 -> 48.25 | S18: =O18*$I18 -> 0 | T18: =P18*$I18 -> 0
A19: DG Fuels | B19: Loring, Aroostock County, ME | C19: USA | D19: https://dgfuels.com/2023/09/07/the-largest-green-biofuels-project-in-the-state-of-maine-is-making-great-strides/, https://thecounty.me/2024/11/15/business-news/company-slated-to-break-ground-on-4b-loring-aviation-fuel-facility-next-year/ | E19: Nov 14 2022 press release from company stated "The project is currently expected to be completed in 2027." Construction listed as starting 2025 | F19: 2027 | H19: Planned | I19: 0.25 | J19: 190 | M19: 0 | N19: =J19 -> 190 | O19: =IF(K19="",0,(K19*(M19/J19))-M19) -> 0 | P19: =IF(K19="",0,(K19*(N19/J19))-N19) -> 0 | Q19: =M19*$I19 -> 0 | R19: =N19*$I19 -> 47.5 | S19: =O19*$I19 -> 0 | T19: =P19*$I19 -> 0 | U19: FT | V19: MSW
A20: HIF Global | B20: TX | C20: USA | D20: https://www.prnewswire.com/news-releases/hif-global-initiates-engineering-for-us-sustainable-aviation-fuel-facility-selects-johnson-matthey--honeywell-technologies-301820755.html, https://www.safinvestor.com/news/147186/hif-global-2/ | E20: HIF’s Tier II Design Pathway Certification includes e-SAF, e-Naphtha, and e-Diesel as opt-in fuels allowing producers to apply and generate credits for their e-Fuels | F20: 2030 | H20: Planned | I20: 0.25 | J20: 166 | M20: =J20/2 -> 83 | N20: =J20/2 -> 83 | O20: =IF(K20="",0,(K20*(M20/J20))-M20) -> 0 | P20: =IF(K20="",0,(K20*(N20/J20))-N20) -> 0 | Q20: =M20*$I20 -> 20.75 | R20: =N20*$I20 -> 20.75 | S20: =O20*$I20 -> 0 | T20: =P20*$I20 -> 0 | U20: PTL | V20: CCS
A21: Nacero | B21: Penwell, TX | C21: USA | D21: https://nacero.co/press-releases/nacero-inc-invited-to-submit-part-ii-application-to-the-u-s-department-of-energy | E21: Changed from "2024 or later" to automate capacity | F21: 2026 | H21: FID mid-2024? | I21: 0.5 | J21: 145 | M21: =J21*0.1 -> 14.5 | N21: =J21 -> 145 | O21: =IF(K21="",0,(K21*(M21/J21))-M21) -> 0 | P21: =IF(K21="",0,(K21*(N21/J21))-N21) -> 0 | Q21: =M21*$I21 -> 7.25 | R21: =N21*$I21 -> 72.5 | S21: =O21*$I21 -> 0 | T21: =P21*$I21 -> 0 | U21: ATJ | V21: Ethanol
A22: Shell | B22: Convent, LA | C22: USA | E22: Converting old refinery shut in 2020 | F22: 2029 | H22: Planned | I22: 0.5 | J22: 142 | M22: =J22/2 -> 71 | N22: =J22/2 -> 71 | O22: =IF(K22="",0,(K22*(M22/J22))-M22) -> 0 | P22: =IF(K22="",0,(K22*(N22/J22))-N22) -> 0 | Q22: =M22*$I22 -> 35.5 | R22: =N22*$I22 -> 35.5 | S22: =O22*$I22 -> 0 | T22: =P22*$I22 -> 0 | U22: HEFA | V22: FOGs | X22: https://www.shell.com/investors/financial-calendar.html
A23: Azure | B23: Cherryvale, KS | C23: USA | D23: https://www.prnewswire.com/news-releases/azure-announces-plans-to-develop-an-saf-production-facility-in-kansas-302019895.html | F23: 2027 | H23: FEED 2024; FID 2025 | I23: 0.5 | J23: 135 | M23: =J23/2 -> 67.5 | N23: =J23/2 -> 67.5 | O23: =IF(K23="",0,(K23*(M23/J23))-M23) -> 0 | P23: =IF(K23="",0,(K23*(N23/J23))-N23) -> 0 | Q23: =M23*$I23 -> 33.75 | R23: =N23*$I23 -> 33.75 | S23: =O23*$I23 -> 0 | T23: =P23*$I23 -> 0 | U23: HEFA | V23: FOGs
A24: DG Fuels | B24: St. James Parish, LA | C24: USA | D24: https://dgfuels.com/2024/04/10/dg-fuels-johnson-matthey-bp-partner-for-largest-fischer-tropsch-saf-plant/;https://www.greenairnews.com/?p=5570, https://thecounty.me/2024/11/15/business-news/company-slated-to-break-ground-on-4b-loring-aviation-fuel-facility-next-year/ | E24: The FT CANS technology is feedstock agnostic although the facility will use plant waste, primarily sugar cane bagasse. 450mm liters/yr - changed column P from "Resid biomass, MSW" and changed column O from "FT CANS" and changed column J from "120-135" to automate capacity. Construction listed as starting 2025 | F24: 2027 | H24: FEED Summer 2024; FID-2025; Construction start 2025 | I24: 0.75 | J24: 135 | M24: 0 | N24: =J24 -> 135 | O24: =IF(K24="",0,(K24*(M24/J24))-M24) -> 0 | P24: =IF(K24="",0,(K24*(N24/J24))-N24) -> 0 | Q24: =M24*$I24 -> 0 | R24: =N24*$I24 -> 101.25 | S24: =O24*$I24 -> 0 | T24: =P24*$I24 -> 0 | U24: FT | V24: MSW
A25: Blue Blade Energy (JV United Tallgrass & Green Plains) | B25: Midcontinent US TBD | C25: USA | D25: https://investor.gpreinc.com/news/news-details/2023/United-Tallgrass-and-Green-Plains-Form-Joint-Venture-to-Develop-New-Sustainable-Aviation-Fuel-Technology-Using-Ethanol/default.aspx | E25: United Airlines, Tallgrass, and Green Plains Inc. today announced a new joint venture – Blue Blade Energy – to develop and then commercialize a novel Sustainable Aviation Fuel (SAF) technology that uses ethanol as its feedstock. If the technology is successful, Blue Blade is expected to proceed with the construction of a pilot facility in 2024, followed by a full-scale facility that could begin commercial operations by 2028. The offtake agreement could provide for enough SAF to fly more than 50,000 flights annually between United's hub airports in Chicago and Denver.* | F25: 2028 | H25: Constuction | I25: 0.75 | J25: 135 | M25: 0 | N25: 135 | O25: =IF(K25="",0,(K25*(M25/J25))-M25) -> 0 | P25: =IF(K25="",0,(K25*(N25/J25))-N25) -> 0 | Q25: =M25*$I25 -> 0 | R25: =N25*$I25 -> 101.25 | S25: =O25*$I25 -> 0 | T25: =P25*$I25 -> 0 | U25: ATJ | V25: Ethanol
A26: Edgewood Renewables | B26: Clark County, NV | C26: USA | D26: https://biomassmagazine.com/articles/nevada-approves-tax-abatements-for-proposed-renewable-diesel-saf-project | E26: purchased from Ryze June 2023 (near Las Vegas) - Changed from Q4 2025 to automate capacity | F26: 2025 | H26: Construction | I26: 0.8 | J26: 120 | M26: 60 | N26: 60 | O26: =IF(K26="",0,(K26*(M26/J26))-M26) -> 0 | P26: =IF(K26="",0,(K26*(N26/J26))-N26) -> 0 | Q26: =M26*$I26 -> 48 | R26: =N26*$I26 -> 48 | S26: =O26*$I26 -> 0 | T26: =P26*$I26 -> 0 | U26: HEFA | V26: FOGs
A27: Marquis SAF & LanzaJet | B27: Hennepin, IL | C27: USA | D27: https://www.lanzajet.com/news-insights/lanzajet-and-marquis-sustainable-aviation-fuel-saf-partner-to-build-an-integrated-sustainable-fuels-plant-in-illinois, https://marquisinc.com/saf/, https://www.farmweeknow.com/environmental/ifb-carbon-team-tours-market-opportunities-with-marquis-energy/article_7f7ca10a-5275-11ee-9ab4-2f333d5f0e92.html | E27: Update for 2024 is delay to "as early as 2027" | F27: 2027 | I27: 0.5 | J27: 120 | M27: =J27*0.1 -> 12 | N27: =J27 -> 120 | O27: =IF(K27="",0,(K27*(M27/J27))-M27) -> 0 | P27: =IF(K27="",0,(K27*(N27/J27))-N27) -> 0 | Q27: =M27*$I27 -> 6 | R27: =N27*$I27 -> 60 | S27: =O27*$I27 -> 0 | T27: =P27*$I27 -> 0 | U27: ATJ | V27: Ethanol
A28: Avina Clean Hydrogen | B28: IL | C28: USA | D28: https://www.safinvestor.com/news/145693/avina/, https://swedishbiofuels.se/news/avina-selects-sustainable-aviation-fuel-technology-developed-by-swedish-biofuels | E28: PureSAF technology - Swedish Biofuels technology | F28: 2027 | H28: FEED 2Q 2024 | I28: 0.5 | J28: 120 | M28: 0 | N28: 120 | O28: =IF(K28="",0,(K28*(M28/J28))-M28) -> 0 | P28: =IF(K28="",0,(K28*(N28/J28))-N28) -> 0 | Q28: =M28*$I28 -> 0 | R28: =N28*$I28 -> 60 | S28: =O28*$I28 -> 0 | T28: =P28*$I28 -> 0 | U28: ATJ | V28: Ethanol
A29: DG Fuels | B29: Phelps County, NE | C29: USA | D29: https://www.safinvestor.com/news/145688/dg-fuels-to-build-193m-gallon-saf-plant-in-nebraska/, https://www.safinvestor.com/news/146550/maire/ | E29: MAIRE(NEXTCHEM) licensing tech - changed column P from "corn stover." MAIRE, through its subsidiary MyRechemical, awarded a contract to provide early engineering, licensing, and Process Design Package (PDP) services. Listed as 450 m liters annual | F29: 2029 | H29: Engineering contracts awarded | I29: 0.5 | J29: 119 | M29: 0 | N29: =J29 -> 119 | O29: =IF(K29="",0,(K29*(M29/J29))-M29) -> 0 | P29: =IF(K29="",0,(K29*(N29/J29))-N29) -> 0 | Q29: =M29*$I29 -> 0 | R29: =N29*$I29 -> 59.5 | S29: =O29*$I29 -> 0 | T29: =P29*$I29 -> 0 | U29: FT | V29: MSW
A30: Tidewater Renewables | B30: Prince George, BC | C30: CA | D30: https://biodieselmagazine.com/articles/tidewater-reports-strong-q2-operations-progress-with-saf-project, https://www.tidewater-renewables.com/investors/news-events/tidewater-renewables-ltd-announces-second-quarter-2024-results/, https://safmagazine.com/articles/tidewater-expects-to-make-final-investment-decision-on-proposed-saf-project-during-second-half-of-2025 | E30: 6500 bbl/d SAF project In 2025 they opened an RD unit. RD unit operating 88% for 44.91 mmgal. I think SAF would be a separate unit. | F30: 2026 | H30: FID expected 2025 | I30: 1 | J30: 100 | M30: 52 | N30: 100 | O30: =IF(K30="",0,(K30*(M30/J30))-M30) -> 0 | P30: =IF(K30="",0,(K30*(N30/J30))-N30) -> 0 | Q30: =M30*$I30 -> 52 | R30: =N30*$I30 -> 100 | S30: =O30*$I30 -> 0 | T30: =P30*$I30 -> 0 | U30: HEFA | V30: FOGs
A31: Green Energy Transformation | B31: Calgary | C31: CA | D31: https://www.biobased-diesel.com/post/new-partnership-to-develop-renewable-diesel-saf-projects-in-canada | F31: 2030 | H31: Planned | I31: 0.1 | J31: 100 | L31: 288000 | M31: =J31/2 -> 50 | N31: =J31/2 -> 50 | O31: =IF(K31="",0,(K31*(M31/J31))-M31) -> 0 | P31: =IF(K31="",0,(K31*(N31/J31))-N31) -> 0 | Q31: =M31*$I31 -> 5 | R31: =N31*$I31 -> 5 | S31: =O31*$I31 -> 0 | T31: =P31*$I31 -> 0 | U31: HEFA | V31: FOGs | W31: New
A32: CVR Energy | B32: Wynnewood, OK | C32: USA | D32: https://biomassmagazine.com/articles/cvr-energy-continues-to-consider-saf-projects-at-2-refineries | E32: The RD unit began operations in April 2022 at 50% capacity while CVR obtained certifications | F32: 2022 | H32: Operating | I32: 1 | J32: 100 | M32: =J32/2 -> 50 | N32: =J32/2 -> 50 | O32: =IF(K32="",0,(K32*(M32/J32))-M32) -> 0 | P32: =IF(K32="",0,(K32*(N32/J32))-N32) -> 0 | Q32: =M32*$I32 -> 50 | R32: =N32*$I32 -> 50 | S32: =O32*$I32 -> 0 | T32: =P32*$I32 -> 0 | U32: HEFA | V32: FOGs
A33: Slate Refining/ Starwood Energy Group | B33: Douglas, WY | C33: USA | E33: Under construction according to a PR Newswire article from Aug 2021 | F33: 2028 | H33: Announced in 2021 but no recent info | I33: 0.05 | J33: 100 | M33: =J33/2 -> 50 | N33: =J33/2 -> 50 | O33: =IF(K33="",0,(K33*(M33/J33))-M33) -> 0 | P33: =IF(K33="",0,(K33*(N33/J33))-N33) -> 0 | Q33: =M33*$I33 -> 2.5 | R33: =N33*$I33 -> 2.5 | S33: =O33*$I33 -> 0 | T33: =P33*$I33 -> 0 | U33: HEFA | V33: FOGs
A34: Covenant Energy | B34: Saskatchewan | C34: CA | D34: https://www.ogj.com/refining-processing/refining/article/14205421/covenant-energy-plans-renewable-diesel-refinery-in-saskatchewan | F34: 2024 | H34: Planned | I34: 0.5 | J34: 98 | L34: 134000 | M34: =J34 -> 98 | N34: 0 | O34: =IF(K34="",0,(K34*(M34/J34))-M34) -> 0 | P34: =IF(K34="",0,(K34*(N34/J34))-N34) -> 0 | Q34: =M34*$I34 -> 49 | R34: =N34*$I34 -> 0 | S34: =O34*$I34 -> 0 | T34: =P34*$I34 -> 0 | U34: HEFA | V34: FOGs | W34: New
A35: Indaba Renewable Fuels | B35: Imperial Valley, CA | C35: USA | D35: https://www.indabarenewablefuels.com/technology#our-progress | F35: 2024 | H35: Planned | I35: 0.05 | J35: 95 | M35: =J35/2 -> 47.5 | N35: =J35/2 -> 47.5 | O35: =IF(K35="",0,(K35*(M35/J35))-M35) -> 0 | P35: =IF(K35="",0,(K35*(N35/J35))-N35) -> 0 | Q35: =M35*$I35 -> 2.375 | R35: =N35*$I35 -> 2.375 | S35: =O35*$I35 -> 0 | T35: =P35*$I35 -> 0 | U35: HEFA | V35: FOGs
A36: Indaba Renewable Fuels | B36: West Memphis, AR | C36: USA | D36: https://www.indabarenewablefuels.com/technology#our-progress | E36: Moved to 2026 due to no news Mar 2025 --Once operational, West Memphis refinery produce around 79.5 mm gal of high-grade, low-sulphur, drop-in SAF a year using the Haldor Topsøe technology “HydroFlex”. Hydroflex is a process for producing renewable diesel that meets the ASTM D975 standard, and for producing HEFA jet fuel through hydrotreatment of any fatty-acid based feedstock. Indaba’s SAF will be produced using feedstock from 50% yellow grease – from UCO, and 50% brown grease – from fat, oil and grease (FOG). The facility will also contain the capacity to process FOG feedstock on site. The company has signed a 20-year feedstock supply agreement with supply manager Ecostrat, which will provide brown grease, yellow grease and DCO feedstock to Indaba. | F36: 2026 | H36: Planned | I36: 0.05 | J36: 95 | M36: =J36-N36 -> 15.2 | N36: 79.8 | O36: =IF(K36="",0,(K36*(M36/J36))-M36) -> 0 | P36: =IF(K36="",0,(K36*(N36/J36))-N36) -> 0 | Q36: =M36*$I36 -> 0.76 | R36: =N36*$I36 -> 3.99 | S36: =O36*$I36 -> 0 | T36: =P36*$I36 -> 0 | U36: HEFA | V36: FOGs
A37: Aemetis Carbon Zero | B37: Riverbank, CA | C37: USA | D37: https://www.aemetis.com/investors/presentation/; https://www.aemetis.com/aemetis-receives-key-permit-for-90-million-gallon-per-year-sustainable-aviation-fuel-and-renewable-diesel-plant-in-california/ | E37: 5/9/2024 Riverbank Sustainable Aviation Fuel project received the final Authority to Construct air permits. The plant is designed to produce 90 MMgy when allocating 50% to SAF and 50% to RD production, and 78 MMgy when allocating 100% SAF. Used 100% SAF in these calculations. | F37: 2025 | I37: 0.5 | J37: 78 | M37: 0 | N37: 78 | O37: =IF(K37="",0,(K37*(M37/J37))-M37) -> 0 | P37: =IF(K37="",0,(K37*(N37/J37))-N37) -> 0 | Q37: =M37*$I37 -> 0 | R37: =N37*$I37 -> 39 | S37: =O37*$I37 -> 0 | T37: =P37*$I37 -> 0 | U37: FT | V37: Woody Biomass | X37: https://www.aemetis.com/investors/conference-calls/
A38: Crysalis Bioscience | B38: IL | C38: USA | D38: https://www.safinvestor.com/news/146063/crysalis-biosciences/ | E38: 5,000-10,000 bbl/d SAF - co-located with ethanol unit | F38: 2031 | H38: Investigation | I38: 0.05 | J38: =5000*42*360/1000000 -> 75.6 | M38: =J38*0.1 -> 7.56 | N38: =J38*0.9 -> 68.04 | O38: =IF(K38="",0,(K38*(M38/J38))-M38) -> 0 | P38: =IF(K38="",0,(K38*(N38/J38))-N38) -> 0 | Q38: =M38*$I38 -> 0.378 | R38: =N38*$I38 -> 3.402 | S38: =O38*$I38 -> 0 | T38: =P38*$I38 -> 0 | U38: ATJ | V38: Ethanol
A39: HOBO Renewables #1 | B39: Clinton, IA | C39: USA | D39: https://hobord.com/projects/ | E39: Houston Home office - changed from "Q2 2027" and column O from "HEFA?" to automate capacity | F39: 2027 | H39: Planned | I39: 0.5 | J39: 65 | M39: =J39/2 -> 32.5 | N39: =J39/2 -> 32.5 | O39: =IF(K39="",0,(K39*(M39/J39))-M39) -> 0 | P39: =IF(K39="",0,(K39*(N39/J39))-N39) -> 0 | Q39: =M39*$I39 -> 16.25 | R39: =N39*$I39 -> 16.25 | S39: =O39*$I39 -> 0 | T39: =P39*$I39 -> 0 | U39: HEFA | V39: FOGs
A40: Gevo/Net-Zero1 | B40: Lake Preston, ND | C40: USA | D40: https://investors.gevo.com/static-files/7c7da5b7-8918-4d64-8cba-2bb7cfa5a7ee;https://mnbioeconomy.org/minnesotas-sustainable-aviation-fuel-opportunity-part-3/;https://safmagazine.com/articles/gevo-provides-update-of-rng-saf-projects | E40: Working to secure DOE loan guarantee; connected to proposed carbon pipeline project; Use of their own RNG allow the CI to be reduced - Changed column J from "55/62" and column O from "Axens ATJ" to automate capacity Change in start date based on WD conversation. They are waiting on permits for the CCS. | F40: 2028 | H40: Planned | I40: 0.25 | J40: 65 | M40: 5 | N40: 60 | O40: =IF(K40="",0,(K40*(M40/J40))-M40) -> 0 | P40: =IF(K40="",0,(K40*(N40/J40))-N40) -> 0 | Q40: =M40*$I40 -> 1.25 | R40: =N40*$I40 -> 15 | S40: =O40*$I40 -> 0 | T40: =P40*$I40 -> 0 | U40: ATJ | V40: Ethanol
A41: HOBO Renewables #2 | B41: TBD | C41: USA | D41: https://hobord.com/projects/ | E41: Changed from Q3 2028 and column O from "HEFA?" to automate capacity | F41: 2028 | H41: Planned | I41: 0.25 | J41: 65 | M41: =J41/2 -> 32.5 | N41: =J41/2 -> 32.5 | O41: =IF(K41="",0,(K41*(M41/J41))-M41) -> 0 | P41: =IF(K41="",0,(K41*(N41/J41))-N41) -> 0 | Q41: =M41*$I41 -> 8.125 | R41: =N41*$I41 -> 8.125 | S41: =O41*$I41 -> 0 | T41: =P41*$I41 -> 0 | U41: HEFA | V41: FOGs
A42: Northwest Advanced Bio-Fuels | B42: Scottsdale, AZ | C42: USA | D42: https://biomassmagazine.com/articles/ipsc-awarded-saf-project-by-northwest-advanced-bio-fuels-20248 | E42: Secured construction equity in Mar 2021. Partnership with Delta, which won Delta an award they did a press release about, so while this is a "second-generation" cellulosic plant with unproven or tested design and construction, at some point it will probably need to produce something or it will embaress Delta, not that it could not happen, but this is the Microsoft stuff we heard at the IATA Conference - Awarded SAF Project to IHI Power Services in Aug 2023 | F42: 2028 | I42: 0.25 | J42: 64 | M42: 0 | N42: =J42 -> 64 | O42: =IF(K42="",0,(K42*(M42/J42))-M42) -> 0 | P42: =IF(K42="",0,(K42*(N42/J42))-N42) -> 0 | Q42: =M42*$I42 -> 0 | R42: =N42*$I42 -> 16 | S42: =O42*$I42 -> 0 | T42: =P42*$I42 -> 0 | U42: FT | V42: Woody Biomass
A43: Par Pacific | B43: Kapolei, HI | C43: USA | D43: https://www.biobased-diesel.com/post/hawaii-oil-refinery-investing-90-million-to-produce-renewable-diesel-saf-by-2025 | E43: Changed column J from "36 (61T 60SAF/40RD -- but flex to 90RD)" to automate capacity | F43: 2025 | H43: Planned | I43: 0.75 | J43: 61 | M43: =J43*0.4 -> 24.4 | N43: =J43*0.6 -> 36.6 | O43: =IF(K43="",0,(K43*(M43/J43))-M43) -> 0 | P43: =IF(K43="",0,(K43*(N43/J43))-N43) -> 0 | Q43: =M43*$I43 -> 18.3 | R43: =N43*$I43 -> 27.45 | S43: =O43*$I43 -> 0 | T43: =P43*$I43 -> 0 | U43: HEFA | V43: FOGs
A44: Sugar Valley Energy | B44: Imperial Valley, CA | C44: USA | D44: https://www.californiaethanolpower.com/sve; https://www.ivpressonline.com/featured/sugar-valley-moves-forward-crop-commitments-secured-for-sugar-valley-energy-ethanol-bio-refinery-in/article_c2e68690-0815-11ee-b6fe-633bb56b44eb.html | E44: Changed column J from "61/200" to automate capacity | F44: 2026 | I44: 0.5 | J44: 61 | K44: 200 | M44: 0 | N44: =J44 -> 61 | O44: =IF(K44="",0,(K44*(M44/J44))-M44) -> 0 | P44: =IF(K44="",0,(K44*(N44/J44))-N44) -> 139 | Q44: =M44*$I44 -> 0 | R44: =N44*$I44 -> 30.5 | S44: =O44*$I44 -> 0 | T44: =P44*$I44 -> 69.5 | U44: ATJ | V44: Ethanol
A45: Suncor | B45: ?? | C45: CA | D45: https://www.suncor.com/en-ca/news-and-stories/suncors-response-to-recent-changes-competition-act | E45: June 2024 The federal government, through late changes to omnibus Bill C-59, passed amendments to the Competition Act with immediate effect that create significant uncertainty for Canadian companies that want to communicate publicly about the work they are doing to improve their environmental performance, including actions and plans to address climate change. To be clear, Suncor Energy remains fully committed to environmental performance, sustainable development, the work we are doing to reduce greenhouse gas emissions and our related ambitions. We believe we, along with industry, have a key role to play in helping Canada reduce its greenhouse gas emissions and meet its climate ambitions, while also supporting a vibrant economy, improving environmental performance and providing Canadians with secure access to affordable energy. There is uncertainty on how the new law will be interpreted and applied. Until the Competition Bureau provides clarity and specific guidance on what is required to comply with these new laws, given the associated risk of non-compliance, we have temporarily removed some environmental and climate content from our website, social media and other public communications. | F45: 1953 | I45: 0.05 | J45: 60 | L45: 172000 | M45: =J45*0.1 -> 6 | N45: =J45 -> 60 | O45: =IF(K45="",0,(K45*(M45/J45))-M45) -> 0 | P45: =IF(K45="",0,(K45*(N45/J45))-N45) -> 0 | Q45: =M45*$I45 -> 0.3 | R45: =N45*$I45 -> 3 | S45: =O45*$I45 -> 0 | T45: =P45*$I45 -> 0 | U45: ATJ | V45: Ethanol | W45: New | X45: https://www.suncor.com/en-ca/investors/events-and-presentations
A46: SAFuels X/ AIC Energy Corp | B46: Trenton, ND | C46: USA | D46: https://safuelsx.com/ | E46: 5/17/2024 request extension of 18 month on current permit to construct -- plan to start construction in 12 months | F46: 2027 | H46: May 2025 Construction | I46: 0.75 | J46: 55 | K46: 110 | M46: =J46/2 -> 27.5 | N46: =J46/2 -> 27.5 | O46: =IF(K46="",0,(K46*(M46/J46))-M46) -> 27.5 | P46: =IF(K46="",0,(K46*(N46/J46))-N46) -> 27.5 | Q46: =M46*$I46 -> 20.625 | R46: =N46*$I46 -> 20.625 | S46: =O46*$I46 -> 20.625 | T46: =P46*$I46 -> 20.625 | U46: HEFA | V46: FOGs
A47: Montana Renewables (Calumet) | B47: Great Falls, MT | C47: USA | D47: https://www.ogj.com/energy-transition/article/14296189/calumet-provides-operational-update-on-montana-renewables-great-falls-plant; https://biodieselmagazine.com/articles/calumet-montana-renewables-ramps-up-production-in-q1; https://www.eia.gov/todayinenergy/detail.php?id=62504, https://www.safinvestor.com/news/145975/montana-renewables/, https://safmagazine.com/articles/montana-renewables-receives-144-billion-conditional-commitment-from-doe-for-renewable-fuels-and-biomass-energy-facility, https://calumet.com/montana-renewables-llc-ships-sustainable-aviation-fuel-to-msp-airport/ | E47: The Cherry Point production will supply fuel to airports in the region through the Olympic Pipeline, which runs from Ferndale to Portland. 45 mmgal via email 10/8/2024. Expansion to 330 mmgal SAF/RD - max SAF at 300 mmgal S/U 2026?2028? Shipped SAF to Minn-St Paul Intl Airport Sept 24. Listing RD capacity as 15,000 bbl/d | F47: 2022 | G47: 2024 | H47: Operating | I47: 1 | J47: 50 | K47: 300 | M47: =15000*42*365/1000000 -> 229.95 | N47: =J47 -> 50 | O47: =P47*0.1 -> 30 | P47: =K47 -> 300 | Q47: =M47*$I47 -> 229.95 | R47: =N47*$I47 -> 50 | S47: =O47*$I47 -> 30 | T47: =P47*$I47 -> 300 | U47: HEFA | V47: FOGs | X47: https://calumet.investorroom.com/Events
A48: Simply Blue Group | B48: Goldboro, Nova Scotia | C48: CA | D48: https://simplybluegroup.com/news/simply-blue-group-to-develop-major-sustainable-aviation-fuel-hub-in-goldboro-nova-scotia/, https://safmagazine.com/articles/simply-blue-group-nova-scotia-mikmaw-chiefs-sign-mou-for-goldboro-saf-project | E48: Land purchased Sept 2024. Green biomass - expected to source 700,000 t/yr. Plan to provide to transportation sector with aviation and marine fuel. - Converted tonnes in column E to gal per year in column J and changed column P from "Wood mass, green biomass" for capacity calculation | F48: 2030 | H48: Planned | I48: 0.5 | J48: 49.5 | L48: 150000 | M48: 0 | N48: =J48 -> 49.5 | O48: =IF(K48="",0,(K48*(M48/J48))-M48) -> 0 | P48: =IF(K48="",0,(K48*(N48/J48))-N48) -> 0 | Q48: =M48*$I48 -> 0 | R48: =N48*$I48 -> 24.75 | S48: =O48*$I48 -> 0 | T48: =P48*$I48 -> 0 | U48: FT | V48: Woody Biomass | W48: New
A49: Refuel Energy Inc Refuel YYZ facility | B49: Toronto, Ontario | C49: CA | D49: http://refuelthefuture.com/; https://www.greencarcongress.com/2022/04/20220421-refuel.html | E49: Assume 50/50 RD/SAF | F49: 2025 | H49: Planned | I49: 0.75 | J49: 45 | L49: 125000 | M49: =J49/2 -> 22.5 | N49: =J49/2 -> 22.5 | O49: =IF(K49="",0,(K49*(M49/J49))-M49) -> 0 | P49: =IF(K49="",0,(K49*(N49/J49))-N49) -> 0 | Q49: =M49*$I49 -> 16.875 | R49: =N49*$I49 -> 16.875 | S49: =O49*$I49 -> 0 | T49: =P49*$I49 -> 0 | U49: HEFA | V49: FOGs | W49: New
A50: Santa Maria Renewable Resources (SMRR) | B50: Lufkin, TX | C50: USA | D50: https://bioenergyinternational.com/santa-maria-renewable-resources-selects-tech-suppliers/ | E50: Selected technology in Nov 23, (3,000 barrels per stream per day, meaning?) | F50: 2027 | H50: Planned | I50: 0.5 | J50: 45 | L50: 130000 | M50: =J50/2 -> 22.5 | N50: =J50/2 -> 22.5 | O50: =IF(K50="",0,(K50*(M50/J50))-M50) -> 0 | P50: =IF(K50="",0,(K50*(N50/J50))-N50) -> 0 | Q50: =M50*$I50 -> 11.25 | R50: =N50*$I50 -> 11.25 | S50: =O50*$I50 -> 0 | T50: =P50*$I50 -> 0 | U50: HEFA | V50: FOGs
A51: New Rise Renewables (XCF Global Capital) | B51: Reno, NV | C51: USA | D51: https://www.prnewswire.com/news-releases/new-rise-renewables-announces-conversion-of-state-of-the-art-renewable-diesel-facility-in-nevada-paving-the-way-for-sustainable-aviation-fuel-saf-production-302111060.html; https://www.safinvestor.com/news/144756/new-rise-renewables-inaugurates-3200bpd-saf-facility-in-nevada/; https://biodieselmagazine.com/articles/new-rise-renewables-pivots-to-saf-production,https://www.safinvestor.com/news/147019/new-rise/ https://www.nevadaappeal.com/news/2024/sep/18/tahoe-reno-industrial-center-refinery-sale-targets-new-aviation-fuel-market/ | E51: XCF Global announced it began SAF production at the New Rise Renewables site in Reno, Nevada in the US. Offtake agreement for 3m gallons of SAF with 3rd-party buyer for sale of neat SAF. 1st shipments of neat SAF are expected to begin in Feb 2025, with delivery anticipated to begin in early March. Listed as 3,000 bbl/d | F51: 2025 | H51: Operational | I51: 1 | J51: 45 | M51: =J51*0.1 -> 4.5 | N51: =J51*0.9 -> 40.5 | O51: =IF(K51="",0,(K51*(M51/J51))-M51) -> 0 | P51: =IF(K51="",0,(K51*(N51/J51))-N51) -> 0 | Q51: =M51*$I51 -> 4.5 | R51: =N51*$I51 -> 40.5 | S51: =O51*$I51 -> 0 | T51: =P51*$I51 -> 0 | U51: HEFA | V51: FOGs
A52: ReadiFuels - Iowa LLC | B52: Hull, IA | C52: USA | D52: https://biomassmagazine.com/articles/clg-ara-to-supply-technology-to-iowa-renewable-diesel-saf-plant-18056 | E52: Moved to 2026 due to no news Mar 2025 - Chevron Lummus and Applied Research Assoc technology contract for project 2021 | F52: 2026 | H52: Planned | I52: 0.25 | J52: 36 | M52: =J52/2 -> 18 | N52: =J52/2 -> 18 | O52: =IF(K52="",0,(K52*(M52/J52))-M52) -> 0 | P52: =IF(K52="",0,(K52*(N52/J52))-N52) -> 0 | Q52: =M52*$I52 -> 4.5 | R52: =N52*$I52 -> 4.5 | S52: =O52*$I52 -> 0 | T52: =P52*$I52 -> 0 | U52: HEFA | V52: FOGs
A53: Velocys (Bayou Fuels) | B53: Natchez, MS | C53: USA | D53: https://www.natchezdemocrat.com/2024/03/26/bayou-fuels-owner-velocys-goes-private-with-40m-investment/ | E53: Changed from ?/2027 to automate capacity | F53: 2027 | H53: construction not started 7/25/2024 | I53: 0.5 | J53: 36 | M53: 0 | N53: =J53 -> 36 | O53: =IF(K53="",0,(K53*(M53/J53))-M53) -> 0 | P53: =IF(K53="",0,(K53*(N53/J53))-N53) -> 0 | Q53: =M53*$I53 -> 0 | R53: =N53*$I53 -> 18 | S53: =O53*$I53 -> 0 | T53: =P53*$I53 -> 0 | U53: FT | V53: MSW
A54: Strategic Biofuels/ Magnolia Sustainable Energy | B54: Columbia, LA | C54: USA | D54: https://www.prnewswire.com/news-releases/strategic-biofuels-announces-strategic-investment-from-magnolia-sustainable-energy-partners-302109818.html; https://biodieselmagazine.com/articles/proposed-louisiana-green-fuels-project-pivots-to-saf | E54: Sumitomo & JX Nippon are Magnolia - Changed column J from "34 (RD&SAF)" and changed column O from "HEFA/CCS" and column P from "Forestry Biomass" to automate capacity | F54: 2027 | I54: 0.5 | J54: 34 | M54: 0 | N54: =J54 -> 34 | O54: =IF(K54="",0,(K54*(M54/J54))-M54) -> 0 | P54: =IF(K54="",0,(K54*(N54/J54))-N54) -> 0 | Q54: =M54*$I54 -> 0 | R54: =N54*$I54 -> 17 | S54: =O54*$I54 -> 0 | T54: =P54*$I54 -> 0 | U54: FT | V54: Woody Biomass
A55: USA BioEnergy | B55: Bon Weir, TX | C55: USA | D55: https://usabioenergy.com/pr-doe-program-2024/, https://www.safinvestor.com/news/146738/usa-bioenergy/, https://www.safinvestor.com/opinion/147194/usa-bioenergy/ | E55: Acquired land, convert 1mil tons of forest thinning into 65 mil gal of net-zero transportation fuel including SAF. 3/17: Andrews estimates approximately 18 more months of engineering activities before reaching FID, followed by 24 months of construction and 6-8 months of commissioning. Once operational, the East Texas facility will have a nameplate capacity of 65m gallons annually – 82% SAF and 18% renewable naphtha. | F55: 2028 | H55: Planned | I55: 0.1 | J55: 65 | M55: 0 | N55: =J55*0.82 -> 53.3 | O55: =IF(K55="",0,(K55*(M55/J55))-M55) -> 0 | P55: =IF(K55="",0,(K55*(N55/J55))-N55) -> 0 | Q55: =M55*$I55 -> 0 | R55: =N55*$I55 -> 5.33 | S55: =O55*$I55 -> 0 | T55: =P55*$I55 -> 0 | U55: FT | V55: Woody Biomass
A56: Fulcrum Bioenergy Centerpoint facility | B56: Gary, IN | C56: USA | D56: https://www.safinvestor.com/news/145909/fulcrum-bioenergy/, https://chicagocrusader.com/fulcrum-bioenergys-financial-woes-deflate-promises-for-clean-fuels/ | E56: Laid off nearly all of its staff in May 2024 and halted most of its operations, according to more than a half-dozen former employees. - Changed from 2025/2026 to automate capacity | F56: 2027 | H56: Cancelled | I56: 0.01 | J56: 33 | M56: =J56/2 -> 16.5 | N56: =J56/2 -> 16.5 | O56: =IF(K56="",0,(K56*(M56/J56))-M56) -> 0 | P56: =IF(K56="",0,(K56*(N56/J56))-N56) -> 0 | Q56: =M56*$I56 -> 0.165 | R56: =N56*$I56 -> 0.165 | S56: =O56*$I56 -> 0 | T56: =P56*$I56 -> 0 | U56: FT | V56: MSW
A57: Pathway | B57: Port Arthur, TX | C57: USA | D57: https://www.safinvestor.com/news/146618/drax-2/ | E57: Construction to start 2026; carbon negative SAF - Feedstock supplied by DRAX (supplies biomass pellets could this be an FT with CCS?) | F57: 2029 | H57: Planned | I57: 0.25 | J57: 30 | M57: 0 | N57: =J57 -> 30 | O57: =IF(K57="",0,(K57*(M57/J57))-M57) -> 0 | P57: =IF(K57="",0,(K57*(N57/J57))-N57) -> 0 | Q57: =M57*$I57 -> 0 | R57: =N57*$I57 -> 7.5 | S57: =O57*$I57 -> 0 | T57: =P57*$I57 -> 0 | U57: PTL | V57: CCS
A58: SkyNRG Project Wigeon | B58: Walla Walla, WA | C58: USA | D58: https://skynrg.com/producing-saf/skynrg-pacific-northwest/, https://biodieselmagazine.com/articles/skynrg-project-secures-15-million-grant | E58: Changed from 2028/2029 so we can automate the capacity by year calculations | F58: 2029 | H58: Planned | I58: 0.25 | J58: 30 | M58: 0 | N58: 30 | O58: =IF(K58="",0,(K58*(M58/J58))-M58) -> 0 | P58: =IF(K58="",0,(K58*(N58/J58))-N58) -> 0 | Q58: =M58*$I58 -> 0 | R58: =N58*$I58 -> 7.5 | S58: =O58*$I58 -> 0 | T58: =P58*$I58 -> 0 | U58: ATJ | V58: Ethanol
A59: Chevron El Segundo | B59: El Segundo, CA | C59: USA | D59: https://www.chevron.com/-/media/chevron/about/documents/chevron-history-brochure.pdf | E59: An Oil & Gas Journal article from Nov 7 2023 stated "Chevron completed the conversion and startup of an existing diesel hydrotreating unit for flexible…" | F59: 2021 | G59: 2023 | H59: Operating | I59: 1 | J59: =2000*42*350/1000000 -> 29.4 | K59: =10000*42*350/1000000 -> 147 | M59: =J59/2 -> 14.7 | N59: =J59/2 -> 14.7 | O59: =IF(K59="",0,(K59*(M59/J59))-M59) -> 58.8 | P59: =IF(K59="",0,(K59*(N59/J59))-N59) -> 58.8 | Q59: =M59*$I59 -> 14.7 | R59: =N59*$I59 -> 14.7 | S59: =O59*$I59 -> 58.8 | T59: =P59*$I59 -> 58.8 | U59: Co-Processing | V59: FOGs
A60: Chevron Pascagoula | B60: Pascagoula, MS | C60: USA | D60: https://www.ogj.com/refining-processing/refining/operations/article/14301208/chevron-commissions-unit-for-renewable-fuels-project-at-el-segundo-refinery | E60: An OGJ article from Nov 7 2023 stated "the operator said in its April statement that 'other [unidentified renewable fuels] conversion projects at El Segundo and [its 257,000 -b/d refinery in Richmond, Calif.] have intentionally been put on hold due to current economics…" The article also stated Chevron had completed concept selection and would be moving forward into front-end engineering and design for a renewable fuels project at Chevron USDA's 369,000-b/d refinery in Pascagoula, Miss." | F60: 2027 | G60: 2028 | I60: 0.25 | J60: 29 | K60: 147 | M60: =J60/2 -> 14.5 | N60: =J60/2 -> 14.5 | O60: =IF(K60="",0,(K60*(M60/J60))-M60) -> 59 | P60: =IF(K60="",0,(K60*(N60/J60))-N60) -> 59 | Q60: =M60*$I60 -> 3.625 | R60: =N60*$I60 -> 3.625 | S60: =O60*$I60 -> 14.75 | T60: =P60*$I60 -> 14.75 | U60: Co-Processing | V60: FOGs
A61: Arcadia eFuels - Project Arc | B61: Gregory, TX | C61: USA | D61: https://www.safinvestor.com/opinion/145765/saf/ | E61: 23.2 mn gal | F61: 2028 | H61: FEED funded Aug 2024 | I61: 0.5 | J61: 23.2 | M61: 0 | N61: 23.2 | O61: =IF(K61="",0,(K61*(M61/J61))-M61) -> 0 | P61: =IF(K61="",0,(K61*(N61/J61))-N61) -> 0 | Q61: =M61*$I61 -> 0 | R61: =N61*$I61 -> 11.6 | S61: =O61*$I61 -> 0 | T61: =P61*$I61 -> 0 | U61: PTL | V61: CCS
A62: CountryMark | B62: Indiana | C62: USA | D62: https://www.brownfieldagnews.com/news/countrymark-expects-to-co-process-renewable-diesel-by-2025/ | E62: Capacity listed is RD only (would need to add to get total with SAF) - Changed from Jan-25 to automate capacity | F62: 2025 | I62: 0.5 | J62: 22 | M62: =J62 -> 22 | N62: 0 | O62: =IF(K62="",0,(K62*(M62/J62))-M62) -> 0 | P62: =IF(K62="",0,(K62*(N62/J62))-N62) -> 0 | Q62: =M62*$I62 -> 11 | R62: =N62*$I62 -> 0 | S62: =O62*$I62 -> 0 | T62: =P62*$I62 -> 0 | U62: Co-Processing | V62: FOGs
A63: CastleRock Green Energy | B63: Shelton, WA | C63: USA | D63: https://www.energytech.com/renewables/article/21254437/castlerock-green-energy-to-build-two-biofuel-facilities-in-washington | E63: Plan to build 2-20mgy renewable fuel oils facilities - Changed column J from "? 20" and changed column O from "Ensyn RTP technology" to automate capacity | F63: 2025 | I63: 0.5 | J63: 20 | M63: =J63/2 -> 10 | N63: =J63/2 -> 10 | O63: =IF(K63="",0,(K63*(M63/J63))-M63) -> 0 | P63: =IF(K63="",0,(K63*(N63/J63))-N63) -> 0 | Q63: =M63*$I63 -> 5 | R63: =N63*$I63 -> 5 | S63: =O63*$I63 -> 0 | T63: =P63*$I63 -> 0 | U63: Pyrolysis | V63: Woody Biomass
A64: World Energy | B64: Paramount, CA | C64: USA | D64: https://www.worldenergy.net/new-technologies; https://www.eia.gov/todayinenergy/detail.php?id=62504 | E64: Changed column J from "20/250" to separate the expansion date out to automate capacity. Also changed column N from "250" to align the capacity data with the other data series | F64: 2025 | G64: 2027 | H64: Operating | I64: 1 | J64: 20 | K64: 250 | M64: 0 | N64: 20 | O64: =IF(K64="",0,(K64*(M64/J64))-M64) -> 0 | P64: =IF(K64="",0,(K64*(N64/J64))-N64) -> 230 | Q64: =M64*$I64 -> 0 | R64: =N64*$I64 -> 20 | S64: =O64*$I64 -> 0 | T64: =P64*$I64 -> 230 | U64: HEFA | V64: FOGs
A65: Freedom Pines (Suncor - Mitsui - Lanza Jet) | B65: Soperton, GA | C65: USA | D65: https://www.greenairnews.com/?p=5251;https://biofuelscentral.com/brazil-makes-first-shipment-of-sugar-cane-ethanol-to-us-jet-fuel-plant/ | E65: 5/2/24: imported ethanol from BR; said to be producing in Q4 at the IATA conference Sept 24 - Changed from Jan-24 to automate capacity | F65: 2024 | H65: Operating | I65: 1 | J65: 10 | M65: 1 | N65: 9 | O65: =IF(K65="",0,(K65*(M65/J65))-M65) -> 0 | P65: =IF(K65="",0,(K65*(N65/J65))-N65) -> 0 | Q65: =M65*$I65 -> 1 | R65: =N65*$I65 -> 9 | S65: =O65*$I65 -> 0 | T65: =P65*$I65 -> 0 | U65: ATJ | V65: Ethanol
A66: BP | B66: Cherry Point, WA | C66: USA | D66: https://www.thenorthernlight.com/stories/bp-cherry-point-to-receive-268-million-for-sustainable-aviation-fuel,34135 | E66: The $26.8 million will fund infrastructure and equipment for SAF production at bp Cherry Point. The project is anticipated to create 96 jobs and produce 10 million gallons of fuel annually, according to a news release from Cantwell’s office. | F66: 2025 | H66: Planned | I66: 0.5 | J66: 10 | M66: 0 | N66: 10 | O66: =IF(K66="",0,(K66*(M66/J66))-M66) -> 0 | P66: =IF(K66="",0,(K66*(N66/J66))-N66) -> 0 | Q66: =M66*$I66 -> 0 | R66: =N66*$I66 -> 5 | S66: =O66*$I66 -> 0 | T66: =P66*$I66 -> 0 | U66: Co-Processing | V66: FOGs
A67: SAF+ Consortium | B67: Quebec | C67: CA | F67: 2028 | H67: Planned | I67: 0.1 | J67: 8 | L67: 23000 | M67: 0 | N67: =J67 -> 8 | O67: =IF(K67="",0,(K67*(M67/J67))-M67) -> 0 | P67: =IF(K67="",0,(K67*(N67/J67))-N67) -> 0 | Q67: =M67*$I67 -> 0 | R67: =N67*$I67 -> 0.8 | S67: =O67*$I67 -> 0 | T67: =P67*$I67 -> 0 | U67: PTL | V67: CCS | W67: New
A68: Infinium (Project Roadrunner) | B68: West TX | C68: USA | D68: https://www.safinvestor.com/news/144636/infinium-starts-texas-efuels-facility/ | E68: Info in article about this project starting in 2026 | F68: 2026 | H68: Planned | I68: 0.25 | J68: 5 | M68: 0 | N68: =J68 -> 5 | O68: =IF(K68="",0,(K68*(M68/J68))-M68) -> 0 | P68: =IF(K68="",0,(K68*(N68/J68))-N68) -> 0 | Q68: =M68*$I68 -> 0 | R68: =N68*$I68 -> 1.25 | S68: =O68*$I68 -> 0 | T68: =P68*$I68 -> 0 | U68: PTL | V68: CCS
A69: Blue Biofuels | B69: Frostproof, FL | C69: USA | D69: https://safmagazine.com/articles/blue-biofuels-acquires-land-for-large-scale-renewable-fuel-production-in-florida, https://bluebiofuels.com/blue-biofuels-acquires-land-for-large-scale-renewable-fuel-production-in-florida/ | E69: Initial 3 mm gal/yr biofuel. Future expansion to 100 mm gal/yr of cellulosic ethanol and 100 mm gal/yr SAF. Used the 90SAF/10RD - based on LanzaJet to get RD info | F69: 2025 | G69: 2027 | H69: Purchased land & working engineering | I69: 0.5 | J69: 3 | K69: 100 | M69: =J69*0.1 -> 0.3 | N69: =J69 -> 3 | O69: =K69*0.1 -> 10 | P69: =K69 -> 100 | Q69: =M69*$I69 -> 0.15 | R69: =N69*$I69 -> 1.5 | S69: =O69*$I69 -> 5 | T69: =P69*$I69 -> 50 | U69: ATJ | V69: Ethanol | X69: Cellulosic ethanol (cellulose to sugar process)
A70: Sea Dragon Energy (Project Genesis) | B70: HI | C70: USA | D70: https://www.safinvestor.com/news/146847/eft/, https://www.prweb.com/releases/eft-awarded-sub-contract-in-support-of-sea-dragon-energys-contract-with-the-office-of-naval-research-to-demonstrate-co2-from-seawater-into-sustainable-aviation-efuels-302357067.html | E70: Emerging Fuel Technology awarded technology contract for CO2 from seawater for SAF. Sea Dragon Energy is also connected to the Office of Naval Research. Subsidiary of GALT Aerospace | F70: 2026 | H70: Planned - equipment delivery Q4 2025 | I70: 0.75 | J70: 2 | M70: 0 | N70: =J70 -> 2 | O70: =IF(K70="",0,(K70*(M70/J70))-M70) -> 0 | P70: =IF(K70="",0,(K70*(N70/J70))-N70) -> 0 | Q70: =M70*$I70 -> 0 | R70: =N70*$I70 -> 1.5 | S70: =O70*$I70 -> 0 | T70: =P70*$I70 -> 0 | U70: PtL | V70: Sea water to syngas to SAF
A71: Alder Fuels | B71: Southeast US TBD | C71: USA | D71: https://www.greenairnews.com/?p=3934 | E71: Demo plant Phase 1 Grant $2 mn USDOE for engineering design of 1st demonstration-scale plant to make renewable crude? Changed from 2026 or later to automate capacity | F71: 2026 | I71: 0.05 | J71: 2 | M71: =J71/2 -> 1 | N71: =J71/2 -> 1 | O71: =IF(K71="",0,(K71*(M71/J71))-M71) -> 0 | P71: =IF(K71="",0,(K71*(N71/J71))-N71) -> 0 | Q71: =M71*$I71 -> 0.05 | R71: =N71*$I71 -> 0.05 | S71: =O71*$I71 -> 0 | T71: =P71*$I71 -> 0 | U71: Pyrolysis | V71: Woody Biomass
A72: Alleo Energy | B72: Bay Minette, AL | C72: USA | D72: https://www.alleoenergy.com/investor-resources, https://www.businesswire.com/news/home/20230315005371/en/All%C3%A9o-Energy-Produces-D975-Certified-Over-the-Road-Diesel-From-Wood-Waste | E72: 40/60 RD/SAF Unit produced RD 3/15/23 - renewable crude? - changed column O from "Pyrolysis?" to automate capacity | F72: 2024 | H72: only makes RD but it can be upgraded to SAF | I72: 0.5 | J72: 1.3 | M72: =J72 -> 1.3 | N72: 0 | O72: =IF(K72="",0,(K72*(M72/J72))-M72) -> 0 | P72: =IF(K72="",0,(K72*(N72/J72))-N72) -> 0 | Q72: =M72*$I72 -> 0.65 | R72: =N72*$I72 -> 0 | S72: =O72*$I72 -> 0 | T72: =P72*$I72 -> 0 | U72: Pyrolysis | V72: Woody Biomass
A73: Infinium (Project Pathfinder) | B73: Corpus Christi, TX | C73: USA | D73: https://www.prnewswire.com/news-releases/infiniums-project-pathfinder-is-worlds-first-fully-operational-efuels-facility-302095002.html, https://www.safinvestor.com/news/144636/infinium-starts-texas-efuels-facility/ | E73: pilot plant - a "Hindustan Times" article from Apr 9 2024 reported the Infinium Corpus Christi facility can produce approximately 3 million liters of e-fuel per year at full capacity. | F73: 2024 | H73: Planned | I73: 0.75 | J73: =3000000/3.78541/1000000 -> 0.79251653 | M73: =J73/2 -> 0.39625827 | N73: =J73/2 -> 0.39625827 | O73: =IF(K73="",0,(K73*(M73/J73))-M73) -> 0 | P73: =IF(K73="",0,(K73*(N73/J73))-N73) -> 0 | Q73: =M73*$I73 -> 0.2971937 | R73: =N73*$I73 -> 0.2971937 | S73: =O73*$I73 -> 0 | T73: =P73*$I73 -> 0 | U73: PTL | V73: CCS
A74: SAFFiRE | B74: Liberal, KS | C74: USA | D74: https://www.saffirerenewables.com/post/saffire-renewables-celebrates-groundbreaking-of-pilot-plant-supporting-sustainable-aviation-fuel | E74: capable of processing 10 tons of corn stover every day, yielding cellulosic ethanol that can be upgraded into SAF with a carbon footprint at least 83% lower than conventional jet fuel. Q4 2025 start | F74: 2025 | H74: Planned | I74: 0.5 | J74: =500*365/1000000 -> 0.1825 | M74: =J74/2 -> 0.09125 | N74: =J74/2 -> 0.09125 | O74: =IF(K74="",0,(K74*(M74/J74))-M74) -> 0 | P74: =IF(K74="",0,(K74*(N74/J74))-N74) -> 0 | Q74: =M74*$I74 -> 0.045625 | R74: =N74*$I74 -> 0.045625 | S74: =O74*$I74 -> 0 | T74: =P74*$I74 -> 0 | U74: ATJ | V74: Ethanol | X74: Ethanol from Corn stover
A75: Trecora/ S Hampton Resources/ Gevo | B75: Silsbee, TX | C75: USA | D75: https://demoplants21.best-research.eu/projects/info/3912/VEcQZJ; https://gevo.com/wp-content/uploads/2023/05/Gevo_LakePreston_one-sheet_5.19.23.pdf;https://www.icao.int/environmental-protection/SAF/Lists/SAAFA/View.aspx | E75: Demo - closed. Looks like it was the Demo for the Gevo/Net Zero 1 unit | F75: 2020 | H75: Operating/Closed | I75: 0.001 | J75: 0.1 | M75: =J75*0.1 -> 0.01 | N75: =J75 -> 0.1 | O75: =IF(K75="",0,(K75*(M75/J75))-M75) -> 0 | P75: =IF(K75="",0,(K75*(N75/J75))-N75) -> 0 | Q75: =M75*$I75 -> 1e-05 | R75: =N75*$I75 -> 0.0001 | S75: =O75*$I75 -> 0 | T75: =P75*$I75 -> 0 | U75: ATJ | V75: Ethanol
A76: Twelve / Air Plant One | B76: Moses Lake, WA | C76: USA | D76: https://businessfacilities.com/twelve-breaks-ground-washington-sustainable-aviation-fuel-plant/;https://carbonherald.com/twelve-launches-first-commercial-scale-saf-production-facility/, https://www.safinvestor.com/news/145970/twelve/, https://www.safinvestor.com/news/146960/mol-switch/ | E76: Run on hydropower & use CO2 captured from nearby ethanol plant. The captured CO2 & water fed through OPUS & turned into synthetic gas, which is a basis of SAF. Many investors including MOL Switch, Mitsui & Co, Development Bank of Japan, Advantage Partners and Toppan Global Venture Partners | F76: 2025 | H76: Planned | I76: 0.5 | J76: 0.04 | M76: 0 | N76: 0.04 | O76: =IF(K76="",0,(K76*(M76/J76))-M76) -> 0 | P76: =IF(K76="",0,(K76*(N76/J76))-N76) -> 0 | Q76: =M76*$I76 -> 0 | R76: =N76*$I76 -> 0.02 | S76: =O76*$I76 -> 0 | T76: =P76*$I76 -> 0 | U76: PTL | V76: CCS
A77: Aether Fuels Aurora/ GTI Energy | B77: Chicago, IL | C77: USA | D77: https://aetherfuels.com/news-and-press/aether-fuels-signs-mou-with-jetblue, https://aetherfuels.com/news-and-press/electric-tri-converter-demo-results-a-breakthrough-for-aether-aurora-saf-solution | E77: constructing a 100 gallon-per-day (380l/day) pilot line that builds on the successful operation of an existing 1.5 gallon-per-day (6l/day) pilot line. | F77: 2025 | H77: Construction | I77: 0.5 | J77: 0.036 | M77: 0 | N77: 0.036 | O77: =IF(K77="",0,(K77*(M77/J77))-M77) -> 0 | P77: =IF(K77="",0,(K77*(N77/J77))-N77) -> 0 | Q77: =M77*$I77 -> 0 | R77: =N77*$I77 -> 0.018 | S77: =O77*$I77 -> 0 | T77: =P77*$I77 -> 0 | U77: FT | V77: MSW
A78: Parkland | B78: Burnaby | C78: CA | D78: https://www.safinvestor.com/news/146628/parkland/ | E78: 101,000 liters produced 12/24, uses canola & tallow as feedstock | F78: 2024 | H78: Produced 1st batch | I78: 1 | J78: 0.32 | L78: 1000 | M78: 0 | N78: =J78 -> 0.32 | O78: =IF(K78="",0,(K78*(M78/J78))-M78) -> 0 | P78: =IF(K78="",0,(K78*(N78/J78))-N78) -> 0 | Q78: =M78*$I78 -> 0 | R78: =N78*$I78 -> 0.32 | S78: =O78*$I78 -> 0 | T78: =P78*$I78 -> 0 | U78: Co-Processing | V78: FOGs | W78: Old
A79: Dimensional Energy/ Heliogen | B79: Lancaster, CA | C79: USA | D79: https://www.heliogen.com/press-releases/heliogen-and-dimensional-energy-announce-first-of-its-kind-collaboration-to-produce-carbon-free-sustainable-aviation-fuel-from-concentrated-sunlight-and-green-hydrogen/ | E79: Demo | F79: 2025 | H79: Operating? | I79: 1 | J79: 0.02 | M79: 0 | N79: =J79 -> 0.02 | O79: =IF(K79="",0,(K79*(M79/J79))-M79) -> 0 | P79: =IF(K79="",0,(K79*(N79/J79))-N79) -> 0 | Q79: =M79*$I79 -> 0 | R79: =N79*$I79 -> 0.02 | S79: =O79*$I79 -> 0 | T79: =P79*$I79 -> 0 | U79: PTL | V79: CCS
A80: Lydian | B80: NC | C80: USA | D80: https://www.prnewswire.com/news-releases/lydian-announces-successful-demonstration-of-novel-sustainable-aviation-fuel-technology-302360287.html | E80: Successful pilot demo plant uses captured CO2, water and renewable electricity. 25 gallons per day. Received DARPA award - connected to DoD. Commercial production scheduled to start 2027 | F80: 2025 | H80: Operational | I80: 1 | J80: =25*365/1000000 -> 0.009125 | M80: =J80/2 -> 0.0045625 | N80: =J80/2 -> 0.0045625 | O80: =IF(K80="",0,(K80*(M80/J80))-M80) -> 0 | P80: =IF(K80="",0,(K80*(N80/J80))-N80) -> 0 | Q80: =M80*$I80 -> 0.0045625 | R80: =N80*$I80 -> 0.0045625 | S80: =O80*$I80 -> 0 | T80: =P80*$I80 -> 0 | U80: PTL | V80: CCS
A81: Dimensional Energy | B81: Tuscon, AZ | C81: USA | D81: https://www.tucsonsentinel.com/local/report/120722_dimensional_energy/new-tucson-factory-may-help-solve-climate-crisis-by-creating-jet-fuel-from-co2/ | E81: Demo - process uses 3D-printed ceramics to create a chemical reactor turn CO2 into hydrocarbons | F81: 2022 | H81: Operating? | I81: 1 | J81: 0.002 | M81: =J81/2 -> 0.001 | N81: =J81/2 -> 0.001 | O81: =IF(K81="",0,(K81*(M81/J81))-M81) -> 0 | P81: =IF(K81="",0,(K81*(N81/J81))-N81) -> 0 | Q81: =M81*$I81 -> 0.001 | R81: =N81*$I81 -> 0.001 | S81: =O81*$I81 -> 0 | T81: =P81*$I81 -> 0 | U81: PTL | V81: CCS
A82: Rely | B82: Jesup, GA | C82: USA | D82: 20250307-MoU-Rely-and-Verso-Energy-Press-Release-EN.pdf | E82: MOU with Verso Energy for FID studies - note this unit is Methanol to Jet. | H82: Planning | I82: 0.25 | J82: 23.6 | L82: =500000/7 -> 71428.571 | M82: 0 | N82: =J82 -> 23.6 | O82: =K82/2 -> 0 | P82: =K82/2 -> 0 | Q82: =M82*$I82 -> 0 | R82: =N82*$I82 -> 5.9 | S82: =O82*$I82 -> 0 | T82: =P82*$I82 -> 0 | U82: PTL | V82: CCS
A84: IF YOU ADD NEW PLANTS, PLEASE ADD A ROW ABOVE THIS LINE. THAT WAY THE CAPACITY SUMMATIONS ON THE CAPACITY DATA TAB WILL CONTINUE TO WORK
T86: Number of Plants
T87: HEFA | U87: =COUNTIF($U$3:$U$82,T87) -> 34
T88: ATJ | U88: =COUNTIF($U$3:$U$82,T88) -> 14
T89: FT | U89: =COUNTIF($U$3:$U$82,T89) -> 11
T90: PTL | U90: =COUNTIF($U$3:$U$82,T90) -> 12
T91: Pyrolysis | U91: =COUNTIF($U$3:$U$82,T91) -> 3
T92: Co-Processing | U92: =COUNTIF($U$3:$U$82,T92) -> 5
U93: =SUM(U87:U92) -> 79

Sheet NAm Capacity Data
A1: North American Sustainable Aviation Fuel Production Capacity
A2: (mil gal/yr) | B2: < 2021 | C2: 2021 | D2: 2022 | E2: 2023 | F2: 2024 | G2: 2025 | H2: 2026 | I2: 2027 | J2: 2028 | K2: 2029 | L2: 2030 | M2: 2031 | N2: 2032 | O2: 2033 | P2: 2034 | Q2: 2035 | R2: 2036 | S2: 2037 | T2: 2038 | U2: 2039 | V2: 2040 | W2: 2041 | X2: 2042 | Y2: 2043 | Z2: 2044 | AA2: 2045 | AB2: 2046 | AC2: 2047 | AD2: 2048 | AE2: 2049 | AF2: 2050
A3: HEFA | B3: =SUMIFS(NAm!$R$3:$R$82,NAm!$F$3:$F$82,"<"&'NAm Capacity Data'!C$2,NAm!$U$3:$U$82,'NAm Capacity Data'!$A3)+SUMIFS(NAm!$T$3:$T$82,NAm!$F$3:$F$82,"<"&'NAm Capacity Data'!C$2,NAm!$U$3:$U$82,'NAm Capacity Data'!$A3) -> 82 | C3: =SUMIFS(NAm!$R$3:$R$82,NAm!$F$3:$F$82,'NAm Capacity Data'!C$2,NAm!$U$3:$U$82,'NAm Capacity Data'!$A3)+SUMIFS(NAm!$T$3:$T$82,NAm!$F$3:$F$82,'NAm Capacity Data'!C$22,NAm!$U$3:$U$82,'NAm Capacity Data'!$A3) -> 0.35 | D3: =SUMIFS(NAm!$R$3:$R$82,NAm!$F$3:$F$82,'NAm Capacity Data'!D$2,NAm!$U$3:$U$82,'NAm Capacity Data'!$A3)+SUMIFS(NAm!$T$3:$T$82,NAm!$F$3:$F$82,'NAm Capacity Data'!D$22,NAm!$U$3:$U$82,'NAm Capacity Data'!$A3) -> 400 | E3: =SUMIFS(NAm!$R$3:$R$82,NAm!$F$3:$F$82,'NAm Capacity Data'!E$2,NAm!$U$3:$U$82,'NAm Capacity Data'!$A3)+SUMIFS(NAm!$T$3:$T$82,NAm!$F$3:$F$82,'NAm Capacity Data'!E$22,NAm!$U$3:$U$82,'NAm Capacity Data'!$A3) -> 0 | F3: =SUMIFS(NAm!$R$3:$R$82,NAm!$F$3:$F$82,'NAm Capacity Data'!F$2,NAm!$U$3:$U$82,'NAm Capacity Data'!$A3)+SUMIFS(NAm!$T$3:$T$82,NAm!$F$3:$F$82,'NAm Capacity Data'!F$22,NAm!$U$3:$U$82,'NAm Capacity Data'!$A3) -> 827.875 | G3: =SUMIFS(NAm!$R$3:$R$82,NAm!$F$3:$F$82,'NAm Capacity Data'!G$2,NAm!$U$3:$U$82,'NAm Capacity Data'!$A3)+SUMIFS(NAm!$T$3:$T$82,NAm!$F$3:$F$82,'NAm Capacity Data'!G$22,NAm!$U$3:$U$82,'NAm Capacity Data'!$A3) -> 409.8058 | H3: =SUMIFS(NAm!$R$3:$R$82,NAm!$F$3:$F$82,'NAm Capacity Data'!H$2,NAm!$U$3:$U$82,'NAm Capacity Data'!$A3)+SUMIFS(NAm!$T$3:$T$82,NAm!$F$3:$F$82,'NAm Capacity Data'!H$22,NAm!$U$3:$U$82,'NAm Capacity Data'!$A3) -> 389.74 | I3: =SUMIFS(NAm!$R$3:$R$82,NAm!$F$3:$F$82,'NAm Capacity Data'!I$2,NAm!$U$3:$U$82,'NAm Capacity Data'!$A3)+SUMIFS(NAm!$T$3:$T$82,NAm!$F$3:$F$82,'NAm Capacity Data'!I$22,NAm!$U$3:$U$82,'NAm Capacity Data'!$A3) -> 678.875 | J3: =SUMIFS(NAm!$R$3:$R$82,NAm!$F$3:$F$82,'NAm Capacity Data'!J$2,NAm!$U$3:$U$82,'NAm Capacity Data'!$A3)+SUMIFS(NAm!$T$3:$T$82,NAm!$F$3:$F$82,'NAm Capacity Data'!J$22,NAm!$U$3:$U$82,'NAm Capacity Data'!$A3) -> 10.625 | ... AF3: =SUMIFS(NAm!$R$3:$R$82,NAm!$F$3:$F$82,'NAm Capacity Data'!AF$2,NAm!$U$3:$U$82,'NAm Capacity Data'!$A3)+SUMIFS(NAm!$T$3:$T$82,NAm!$F$3:$F$82,'NAm Capacity Data'!AF$22,NAm!$U$3:$U$82,'NAm Capacity Data'!$A3) -> 0
A4: ATJ | B4: =SUMIFS(NAm!$R$3:$R$82,NAm!$F$3:$F$82,"<"&'NAm Capacity Data'!C$2,NAm!$U$3:$U$82,'NAm Capacity Data'!$A4)+SUMIFS(NAm!$T$3:$T$82,NAm!$F$3:$F$82,"<"&'NAm Capacity Data'!C$2,NAm!$U$3:$U$82,'NAm Capacity Data'!$A4) -> 3.0001 | C4: =SUMIFS(NAm!$R$3:$R$82,NAm!$F$3:$F$82,'NAm Capacity Data'!C$2,NAm!$U$3:$U$82,'NAm Capacity Data'!$A4)+SUMIFS(NAm!$T$3:$T$82,NAm!$F$3:$F$82,'NAm Capacity Data'!C$22,NAm!$U$3:$U$82,'NAm Capacity Data'!$A4) -> 0 | D4: =SUMIFS(NAm!$R$3:$R$82,NAm!$F$3:$F$82,'NAm Capacity Data'!D$2,NAm!$U$3:$U$82,'NAm Capacity Data'!$A4)+SUMIFS(NAm!$T$3:$T$82,NAm!$F$3:$F$82,'NAm Capacity Data'!D$22,NAm!$U$3:$U$82,'NAm Capacity Data'!$A4) -> 0 | E4: =SUMIFS(NAm!$R$3:$R$82,NAm!$F$3:$F$82,'NAm Capacity Data'!E$2,NAm!$U$3:$U$82,'NAm Capacity Data'!$A4)+SUMIFS(NAm!$T$3:$T$82,NAm!$F$3:$F$82,'NAm Capacity Data'!E$22,NAm!$U$3:$U$82,'NAm Capacity Data'!$A4) -> 0 | F4: =SUMIFS(NAm!$R$3:$R$82,NAm!$F$3:$F$82,'NAm Capacity Data'!F$2,NAm!$U$3:$U$82,'NAm Capacity Data'!$A4)+SUMIFS(NAm!$T$3:$T$82,NAm!$F$3:$F$82,'NAm Capacity Data'!F$22,NAm!$U$3:$U$82,'NAm Capacity Data'!$A4) -> 9 | G4: =SUMIFS(NAm!$R$3:$R$82,NAm!$F$3:$F$82,'NAm Capacity Data'!G$2,NAm!$U$3:$U$82,'NAm Capacity Data'!$A4)+SUMIFS(NAm!$T$3:$T$82,NAm!$F$3:$F$82,'NAm Capacity Data'!G$22,NAm!$U$3:$U$82,'NAm Capacity Data'!$A4) -> 51.545625 | H4: =SUMIFS(NAm!$R$3:$R$82,NAm!$F$3:$F$82,'NAm Capacity Data'!H$2,NAm!$U$3:$U$82,'NAm Capacity Data'!$A4)+SUMIFS(NAm!$T$3:$T$82,NAm!$F$3:$F$82,'NAm Capacity Data'!H$22,NAm!$U$3:$U$82,'NAm Capacity Data'!$A4) -> 172.5 | I4: =SUMIFS(NAm!$R$3:$R$82,NAm!$F$3:$F$82,'NAm Capacity Data'!I$2,NAm!$U$3:$U$82,'NAm Capacity Data'!$A4)+SUMIFS(NAm!$T$3:$T$82,NAm!$F$3:$F$82,'NAm Capacity Data'!I$22,NAm!$U$3:$U$82,'NAm Capacity Data'!$A4) -> 245 | J4: =SUMIFS(NAm!$R$3:$R$82,NAm!$F$3:$F$82,'NAm Capacity Data'!J$2,NAm!$U$3:$U$82,'NAm Capacity Data'!$A4)+SUMIFS(NAm!$T$3:$T$82,NAm!$F$3:$F$82,'NAm Capacity Data'!J$22,NAm!$U$3:$U$82,'NAm Capacity Data'!$A4) -> 116.25 | ... AF4: =SUMIFS(NAm!$R$3:$R$82,NAm!$F$3:$F$82,'NAm Capacity Data'!AF$2,NAm!$U$3:$U$82,'NAm Capacity Data'!$A4)+SUMIFS(NAm!$T$3:$T$82,NAm!$F$3:$F$82,'NAm Capacity Data'!AF$22,NAm!$U$3:$U$82,'NAm Capacity Data'!$A4) -> 0
A5: FT | B5: =SUMIFS(NAm!$R$3:$R$82,NAm!$F$3:$F$82,"<"&'NAm Capacity Data'!C$2,NAm!$U$3:$U$82,'NAm Capacity Data'!$A5)+SUMIFS(NAm!$T$3:$T$82,NAm!$F$3:$F$82,"<"&'NAm Capacity Data'!C$2,NAm!$U$3:$U$82,'NAm Capacity Data'!$A5) -> 0 | C5: =SUMIFS(NAm!$R$3:$R$82,NAm!$F$3:$F$82,'NAm Capacity Data'!C$2,NAm!$U$3:$U$82,'NAm Capacity Data'!$A5)+SUMIFS(NAm!$T$3:$T$82,NAm!$F$3:$F$82,'NAm Capacity Data'!C$22,NAm!$U$3:$U$82,'NAm Capacity Data'!$A5) -> 0 | D5: =SUMIFS(NAm!$R$3:$R$82,NAm!$F$3:$F$82,'NAm Capacity Data'!D$2,NAm!$U$3:$U$82,'NAm Capacity Data'!$A5)+SUMIFS(NAm!$T$3:$T$82,NAm!$F$3:$F$82,'NAm Capacity Data'!D$22,NAm!$U$3:$U$82,'NAm Capacity Data'!$A5) -> 0 | E5: =SUMIFS(NAm!$R$3:$R$82,NAm!$F$3:$F$82,'NAm Capacity Data'!E$2,NAm!$U$3:$U$82,'NAm Capacity Data'!$A5)+SUMIFS(NAm!$T$3:$T$82,NAm!$F$3:$F$82,'NAm Capacity Data'!E$22,NAm!$U$3:$U$82,'NAm Capacity Data'!$A5) -> 0 | F5: =SUMIFS(NAm!$R$3:$R$82,NAm!$F$3:$F$82,'NAm Capacity Data'!F$2,NAm!$U$3:$U$82,'NAm Capacity Data'!$A5)+SUMIFS(NAm!$T$3:$T$82,NAm!$F$3:$F$82,'NAm Capacity Data'!F$22,NAm!$U$3:$U$82,'NAm Capacity Data'!$A5) -> 0 | G5: =SUMIFS(NAm!$R$3:$R$82,NAm!$F$3:$F$82,'NAm Capacity Data'!G$2,NAm!$U$3:$U$82,'NAm Capacity Data'!$A5)+SUMIFS(NAm!$T$3:$T$82,NAm!$F$3:$F$82,'NAm Capacity Data'!G$22,NAm!$U$3:$U$82,'NAm Capacity Data'!$A5) -> 39.018 | H5: =SUMIFS(NAm!$R$3:$R$82,NAm!$F$3:$F$82,'NAm Capacity Data'!H$2,NAm!$U$3:$U$82,'NAm Capacity Data'!$A5)+SUMIFS(NAm!$T$3:$T$82,NAm!$F$3:$F$82,'NAm Capacity Data'!H$22,NAm!$U$3:$U$82,'NAm Capacity Data'!$A5) -> 0 | I5: =SUMIFS(NAm!$R$3:$R$82,NAm!$F$3:$F$82,'NAm Capacity Data'!I$2,NAm!$U$3:$U$82,'NAm Capacity Data'!$A5)+SUMIFS(NAm!$T$3:$T$82,NAm!$F$3:$F$82,'NAm Capacity Data'!I$22,NAm!$U$3:$U$82,'NAm Capacity Data'!$A5) -> 183.915 | J5: =SUMIFS(NAm!$R$3:$R$82,NAm!$F$3:$F$82,'NAm Capacity Data'!J$2,NAm!$U$3:$U$82,'NAm Capacity Data'!$A5)+SUMIFS(NAm!$T$3:$T$82,NAm!$F$3:$F$82,'NAm Capacity Data'!J$22,NAm!$U$3:$U$82,'NAm Capacity Data'!$A5) -> 21.33 | ... AF5: =SUMIFS(NAm!$R$3:$R$82,NAm!$F$3:$F$82,'NAm Capacity Data'!AF$2,NAm!$U$3:$U$82,'NAm Capacity Data'!$A5)+SUMIFS(NAm!$T$3:$T$82,NAm!$F$3:$F$82,'NAm Capacity Data'!AF$22,NAm!$U$3:$U$82,'NAm Capacity Data'!$A5) -> 0
A6: PTL | B6: =SUMIFS(NAm!$R$3:$R$82,NAm!$F$3:$F$82,"<"&'NAm Capacity Data'!C$2,NAm!$U$3:$U$82,'NAm Capacity Data'!$A6)+SUMIFS(NAm!$T$3:$T$82,NAm!$F$3:$F$82,"<"&'NAm Capacity Data'!C$2,NAm!$U$3:$U$82,'NAm Capacity Data'!$A6) -> 0 | C6: =SUMIFS(NAm!$R$3:$R$82,NAm!$F$3:$F$82,'NAm Capacity Data'!C$2,NAm!$U$3:$U$82,'NAm Capacity Data'!$A6)+SUMIFS(NAm!$T$3:$T$82,NAm!$F$3:$F$82,'NAm Capacity Data'!C$22,NAm!$U$3:$U$82,'NAm Capacity Data'!$A6) -> 0 | D6: =SUMIFS(NAm!$R$3:$R$82,NAm!$F$3:$F$82,'NAm Capacity Data'!D$2,NAm!$U$3:$U$82,'NAm Capacity Data'!$A6)+SUMIFS(NAm!$T$3:$T$82,NAm!$F$3:$F$82,'NAm Capacity Data'!D$22,NAm!$U$3:$U$82,'NAm Capacity Data'!$A6) -> 0.001 | E6: =SUMIFS(NAm!$R$3:$R$82,NAm!$F$3:$F$82,'NAm Capacity Data'!E$2,NAm!$U$3:$U$82,'NAm Capacity Data'!$A6)+SUMIFS(NAm!$T$3:$T$82,NAm!$F$3:$F$82,'NAm Capacity Data'!E$22,NAm!$U$3:$U$82,'NAm Capacity Data'!$A6) -> 0 | F6: =SUMIFS(NAm!$R$3:$R$82,NAm!$F$3:$F$82,'NAm Capacity Data'!F$2,NAm!$U$3:$U$82,'NAm Capacity Data'!$A6)+SUMIFS(NAm!$T$3:$T$82,NAm!$F$3:$F$82,'NAm Capacity Data'!F$22,NAm!$U$3:$U$82,'NAm Capacity Data'!$A6) -> 0.2971937 | G6: =SUMIFS(NAm!$R$3:$R$82,NAm!$F$3:$F$82,'NAm Capacity Data'!G$2,NAm!$U$3:$U$82,'NAm Capacity Data'!$A6)+SUMIFS(NAm!$T$3:$T$82,NAm!$F$3:$F$82,'NAm Capacity Data'!G$22,NAm!$U$3:$U$82,'NAm Capacity Data'!$A6) -> 0.0445625 | H6: =SUMIFS(NAm!$R$3:$R$82,NAm!$F$3:$F$82,'NAm Capacity Data'!H$2,NAm!$U$3:$U$82,'NAm Capacity Data'!$A6)+SUMIFS(NAm!$T$3:$T$82,NAm!$F$3:$F$82,'NAm Capacity Data'!H$22,NAm!$U$3:$U$82,'NAm Capacity Data'!$A6) -> 2.75 | I6: =SUMIFS(NAm!$R$3:$R$82,NAm!$F$3:$F$82,'NAm Capacity Data'!I$2,NAm!$U$3:$U$82,'NAm Capacity Data'!$A6)+SUMIFS(NAm!$T$3:$T$82,NAm!$F$3:$F$82,'NAm Capacity Data'!I$22,NAm!$U$3:$U$82,'NAm Capacity Data'!$A6) -> 0 | J6: =SUMIFS(NAm!$R$3:$R$82,NAm!$F$3:$F$82,'NAm Capacity Data'!J$2,NAm!$U$3:$U$82,'NAm Capacity Data'!$A6)+SUMIFS(NAm!$T$3:$T$82,NAm!$F$3:$F$82,'NAm Capacity Data'!J$22,NAm!$U$3:$U$82,'NAm Capacity Data'!$A6) -> 12.4 | ... AF6: =SUMIFS(NAm!$R$3:$R$82,NAm!$F$3:$F$82,'NAm Capacity Data'!AF$2,NAm!$U$3:$U$82,'NAm Capacity Data'!$A6)+SUMIFS(NAm!$T$3:$T$82,NAm!$F$3:$F$82,'NAm Capacity Data'!AF$22,NAm!$U$3:$U$82,'NAm Capacity Data'!$A6) -> 0
A7: Pyrolysis | B7: =SUMIFS(NAm!$R$3:$R$82,NAm!$F$3:$F$82,"<"&'NAm Capacity Data'!C$2,NAm!$U$3:$U$82,'NAm Capacity Data'!$A7)+SUMIFS(NAm!$T$3:$T$82,NAm!$F$3:$F$82,"<"&'NAm Capacity Data'!C$2,NAm!$U$3:$U$82,'NAm Capacity Data'!$A7) -> 0 | C7: =SUMIFS(NAm!$R$3:$R$82,NAm!$F$3:$F$82,'NAm Capacity Data'!C$2,NAm!$U$3:$U$82,'NAm Capacity Data'!$A7)+SUMIFS(NAm!$T$3:$T$82,NAm!$F$3:$F$82,'NAm Capacity Data'!C$22,NAm!$U$3:$U$82,'NAm Capacity Data'!$A7) -> 0 | D7: =SUMIFS(NAm!$R$3:$R$82,NAm!$F$3:$F$82,'NAm Capacity Data'!D$2,NAm!$U$3:$U$82,'NAm Capacity Data'!$A7)+SUMIFS(NAm!$T$3:$T$82,NAm!$F$3:$F$82,'NAm Capacity Data'!D$22,NAm!$U$3:$U$82,'NAm Capacity Data'!$A7) -> 0 | E7: =SUMIFS(NAm!$R$3:$R$82,NAm!$F$3:$F$82,'NAm Capacity Data'!E$2,NAm!$U$3:$U$82,'NAm Capacity Data'!$A7)+SUMIFS(NAm!$T$3:$T$82,NAm!$F$3:$F$82,'NAm Capacity Data'!E$22,NAm!$U$3:$U$82,'NAm Capacity Data'!$A7) -> 0 | F7: =SUMIFS(NAm!$R$3:$R$82,NAm!$F$3:$F$82,'NAm Capacity Data'!F$2,NAm!$U$3:$U$82,'NAm Capacity Data'!$A7)+SUMIFS(NAm!$T$3:$T$82,NAm!$F$3:$F$82,'NAm Capacity Data'!F$22,NAm!$U$3:$U$82,'NAm Capacity Data'!$A7) -> 0 | G7: =SUMIFS(NAm!$R$3:$R$82,NAm!$F$3:$F$82,'NAm Capacity Data'!G$2,NAm!$U$3:$U$82,'NAm Capacity Data'!$A7)+SUMIFS(NAm!$T$3:$T$82,NAm!$F$3:$F$82,'NAm Capacity Data'!G$22,NAm!$U$3:$U$82,'NAm Capacity Data'!$A7) -> 5 | H7: =SUMIFS(NAm!$R$3:$R$82,NAm!$F$3:$F$82,'NAm Capacity Data'!H$2,NAm!$U$3:$U$82,'NAm Capacity Data'!$A7)+SUMIFS(NAm!$T$3:$T$82,NAm!$F$3:$F$82,'NAm Capacity Data'!H$22,NAm!$U$3:$U$82,'NAm Capacity Data'!$A7) -> 0.05 | I7: =SUMIFS(NAm!$R$3:$R$82,NAm!$F$3:$F$82,'NAm Capacity Data'!I$2,NAm!$U$3:$U$82,'NAm Capacity Data'!$A7)+SUMIFS(NAm!$T$3:$T$82,NAm!$F$3:$F$82,'NAm Capacity Data'!I$22,NAm!$U$3:$U$82,'NAm Capacity Data'!$A7) -> 0 | J7: =SUMIFS(NAm!$R$3:$R$82,NAm!$F$3:$F$82,'NAm Capacity Data'!J$2,NAm!$U$3:$U$82,'NAm Capacity Data'!$A7)+SUMIFS(NAm!$T$3:$T$82,NAm!$F$3:$F$82,'NAm Capacity Data'!J$22,NAm!$U$3:$U$82,'NAm Capacity Data'!$A7) -> 0 | ... AF7: =SUMIFS(NAm!$R$3:$R$82,NAm!$F$3:$F$82,'NAm Capacity Data'!AF$2,NAm!$U$3:$U$82,'NAm Capacity Data'!$A7)+SUMIFS(NAm!$T$3:$T$82,NAm!$F$3:$F$82,'NAm Capacity Data'!AF$22,NAm!$U$3:$U$82,'NAm Capacity Data'!$A7) -> 0
A8: Co-Processing | B8: =SUMIFS(NAm!$R$3:$R$82,NAm!$F$3:$F$82,"<"&'NAm Capacity Data'!C$2,NAm!$U$3:$U$82,'NAm Capacity Data'!$A8)+SUMIFS(NAm!$T$3:$T$82,NAm!$F$3:$F$82,"<"&'NAm Capacity Data'!C$2,NAm!$U$3:$U$82,'NAm Capacity Data'!$A8) -> 0 | C8: =SUMIFS(NAm!$R$3:$R$82,NAm!$F$3:$F$82,'NAm Capacity Data'!C$2,NAm!$U$3:$U$82,'NAm Capacity Data'!$A8)+SUMIFS(NAm!$T$3:$T$82,NAm!$F$3:$F$82,'NAm Capacity Data'!C$22,NAm!$U$3:$U$82,'NAm Capacity Data'!$A8) -> 73.5 | D8: =SUMIFS(NAm!$R$3:$R$82,NAm!$F$3:$F$82,'NAm Capacity Data'!D$2,NAm!$U$3:$U$82,'NAm Capacity Data'!$A8)+SUMIFS(NAm!$T$3:$T$82,NAm!$F$3:$F$82,'NAm Capacity Data'!D$22,NAm!$U$3:$U$82,'NAm Capacity Data'!$A8) -> 0 | E8: =SUMIFS(NAm!$R$3:$R$82,NAm!$F$3:$F$82,'NAm Capacity Data'!E$2,NAm!$U$3:$U$82,'NAm Capacity Data'!$A8)+SUMIFS(NAm!$T$3:$T$82,NAm!$F$3:$F$82,'NAm Capacity Data'!E$22,NAm!$U$3:$U$82,'NAm Capacity Data'!$A8) -> 0 | F8: =SUMIFS(NAm!$R$3:$R$82,NAm!$F$3:$F$82,'NAm Capacity Data'!F$2,NAm!$U$3:$U$82,'NAm Capacity Data'!$A8)+SUMIFS(NAm!$T$3:$T$82,NAm!$F$3:$F$82,'NAm Capacity Data'!F$22,NAm!$U$3:$U$82,'NAm Capacity Data'!$A8) -> 0.32 | G8: =SUMIFS(NAm!$R$3:$R$82,NAm!$F$3:$F$82,'NAm Capacity Data'!G$2,NAm!$U$3:$U$82,'NAm Capacity Data'!$A8)+SUMIFS(NAm!$T$3:$T$82,NAm!$F$3:$F$82,'NAm Capacity Data'!G$22,NAm!$U$3:$U$82,'NAm Capacity Data'!$A8) -> 5 | H8: =SUMIFS(NAm!$R$3:$R$82,NAm!$F$3:$F$82,'NAm Capacity Data'!H$2,NAm!$U$3:$U$82,'NAm Capacity Data'!$A8)+SUMIFS(NAm!$T$3:$T$82,NAm!$F$3:$F$82,'NAm Capacity Data'!H$22,NAm!$U$3:$U$82,'NAm Capacity Data'!$A8) -> 0 | I8: =SUMIFS(NAm!$R$3:$R$82,NAm!$F$3:$F$82,'NAm Capacity Data'!I$2,NAm!$U$3:$U$82,'NAm Capacity Data'!$A8)+SUMIFS(NAm!$T$3:$T$82,NAm!$F$3:$F$82,'NAm Capacity Data'!I$22,NAm!$U$3:$U$82,'NAm Capacity Data'!$A8) -> 18.375 | J8: =SUMIFS(NAm!$R$3:$R$82,NAm!$F$3:$F$82,'NAm Capacity Data'!J$2,NAm!$U$3:$U$82,'NAm Capacity Data'!$A8)+SUMIFS(NAm!$T$3:$T$82,NAm!$F$3:$F$82,'NAm Capacity Data'!J$22,NAm!$U$3:$U$82,'NAm Capacity Data'!$A8) -> 0 | ... AF8: =SUMIFS(NAm!$R$3:$R$82,NAm!$F$3:$F$82,'NAm Capacity Data'!AF$2,NAm!$U$3:$U$82,'NAm Capacity Data'!$A8)+SUMIFS(NAm!$T$3:$T$82,NAm!$F$3:$F$82,'NAm Capacity Data'!AF$22,NAm!$U$3:$U$82,'NAm Capacity Data'!$A8) -> 0
A9: Total Capacity | B9: =SUM(B3:B8) -> 85.0001 | C9: =SUM(C3:C8) -> 73.85 | D9: =SUM(D3:D8) -> 400.001 | E9: =SUM(E3:E8) -> 0 | F9: =SUM(F3:F8) -> 837.49219 | G9: =SUM(G3:G8) -> 510.41399 | H9: =SUM(H3:H8) -> 565.04 | I9: =SUM(I3:I8) -> 1126.165 | ... AF9: =SUM(AF3:AF8) -> 0
A11: North American Cumulative Probability Adjusted SAF Capacity
A12: (mil gal/yr) | B12: =B2 -> < 2021 | C12: =C2 -> 2021 | D12: =D2 -> 2022 | E12: =E2 -> 2023 | F12: =F2 -> 2024 | G12: =G2 -> 2025 | H12: =H2 -> 2026 | I12: =I2 -> 2027 | ... AF12: =AF2 -> 2050
A13: HEFA | B13: =B3 -> 82 | C13: =B13+C3 -> 82.35 | D13: =C13+D3 -> 482.35 | E13: =D13+E3 -> 482.35 | F13: =E13+F3 -> 1310.225 | G13: =F13+G3 -> 1720.0308 | H13: =G13+H3 -> 2109.7708 | I13: =H13+I3 -> 2788.6458 | J13: =I13+J3 -> 2799.2708 | ... AF13: =AE13+AF3 -> 2839.7708
A14: ATJ | B14: =B4 -> 3.0001 | C14: =B14+C4 -> 3.0001 | D14: =C14+D4 -> 3.0001 | E14: =D14+E4 -> 3.0001 | F14: =E14+F4 -> 12.0001 | G14: =F14+G4 -> 63.545725 | H14: =G14+H4 -> 236.04573 | I14: =H14+I4 -> 481.04573 | J14: =I14+J4 -> 597.29572 | ... AF14: =AE14+AF4 -> 608.19772
A15: FT | B15: =B5 -> 0 | C15: =B15+C5 -> 0 | D15: =C15+D5 -> 0 | E15: =D15+E5 -> 0 | F15: =E15+F5 -> 0 | G15: =F15+G5 -> 39.018 | H15: =G15+H5 -> 39.018 | I15: =H15+I5 -> 222.933 | J15: =I15+J5 -> 244.263 | ... AF15: =AE15+AF5 -> 328.513
A16: PTL | B16: =B6 -> 0 | C16: =B16+C6 -> 0 | D16: =C16+D6 -> 0.001 | E16: =D16+E6 -> 0.001 | F16: =E16+F6 -> 0.2981937 | G16: =F16+G6 -> 0.3427562 | H16: =G16+H6 -> 3.0927562 | I16: =H16+I6 -> 3.0927562 | J16: =I16+J6 -> 15.492756 | ... AF16: =AE16+AF6 -> 43.742756
A17: Pyrolysis | B17: =B7 -> 0 | C17: =B17+C7 -> 0 | D17: =C17+D7 -> 0 | E17: =D17+E7 -> 0 | F17: =E17+F7 -> 0 | G17: =F17+G7 -> 5 | H17: =G17+H7 -> 5.05 | I17: =H17+I7 -> 5.05 | J17: =I17+J7 -> 5.05 | ... AF17: =AE17+AF7 -> 5.05
A18: Co-Processing | B18: =B8 -> 0 | C18: =B18+C8 -> 73.5 | D18: =C18+D8 -> 73.5 | E18: =D18+E8 -> 73.5 | F18: =E18+F8 -> 73.82 | G18: =F18+G8 -> 78.82 | H18: =G18+H8 -> 78.82 | I18: =H18+I8 -> 97.195 | J18: =I18+J8 -> 97.195 | ... AF18: =AE18+AF8 -> 97.195
A19: Total Capacity | B19: =SUM(B13:B18) -> 85.0001 | C19: =SUM(C13:C18) -> 158.8501 | D19: =SUM(D13:D18) -> 558.8511 | E19: =SUM(E13:E18) -> 558.8511 | F19: =SUM(F13:F18) -> 1396.3433 | G19: =SUM(G13:G18) -> 1906.7573 | H19: =SUM(H13:H18) -> 2471.7973 | I19: =SUM(I13:I18) -> 3597.9623 | ... AF19: =SUM(AF13:AF18) -> 3922.4693
A21: North American Announced SAF Capacity
A22: (mil gal/yr) | B22: =B2 -> < 2021 | C22: =C2 -> 2021 | D22: =D2 -> 2022 | E22: =E2 -> 2023 | F22: =F2 -> 2024 | G22: =G2 -> 2025 | H22: =H2 -> 2026 | I22: =I2 -> 2027 | ... AF22: =AF2 -> 2050
A23: HEFA | B23: =SUMIFS(NAm!$N$3:$N$82,NAm!$F$3:$F$82,"<"&'NAm Capacity Data'!C$22,NAm!$U$3:$U$82,'NAm Capacity Data'!$A23)+SUMIFS(NAm!$P$3:$P$82,NAm!$F$3:$F$82,"<"&'NAm Capacity Data'!C$22,NAm!$U$3:$U$82,'NAm Capacity Data'!$A23) -> 82 | C23: =SUMIFS(NAm!$N$3:$N$82,NAm!$F$3:$F$82,'NAm Capacity Data'!C$22,NAm!$U$3:$U$82,'NAm Capacity Data'!$A23)+SUMIFS(NAm!$P$3:$P$82,NAm!$F$3:$F$82,'NAm Capacity Data'!C$22,NAm!$U$3:$U$82,'NAm Capacity Data'!$A23) -> 350 | D23: =SUMIFS(NAm!$N$3:$N$82,NAm!$F$3:$F$82,'NAm Capacity Data'!D$22,NAm!$U$3:$U$82,'NAm Capacity Data'!$A23)+SUMIFS(NAm!$P$3:$P$82,NAm!$F$3:$F$82,'NAm Capacity Data'!D$22,NAm!$U$3:$U$82,'NAm Capacity Data'!$A23) -> 400 | E23: =SUMIFS(NAm!$N$3:$N$82,NAm!$F$3:$F$82,'NAm Capacity Data'!E$22,NAm!$U$3:$U$82,'NAm Capacity Data'!$A23)+SUMIFS(NAm!$P$3:$P$82,NAm!$F$3:$F$82,'NAm Capacity Data'!E$22,NAm!$U$3:$U$82,'NAm Capacity Data'!$A23) -> 0 | F23: =SUMIFS(NAm!$N$3:$N$82,NAm!$F$3:$F$82,'NAm Capacity Data'!F$22,NAm!$U$3:$U$82,'NAm Capacity Data'!$A23)+SUMIFS(NAm!$P$3:$P$82,NAm!$F$3:$F$82,'NAm Capacity Data'!F$22,NAm!$U$3:$U$82,'NAm Capacity Data'!$A23) -> 873 | G23: =SUMIFS(NAm!$N$3:$N$82,NAm!$F$3:$F$82,'NAm Capacity Data'!G$22,NAm!$U$3:$U$82,'NAm Capacity Data'!$A23)+SUMIFS(NAm!$P$3:$P$82,NAm!$F$3:$F$82,'NAm Capacity Data'!G$22,NAm!$U$3:$U$82,'NAm Capacity Data'!$A23) -> 443.326 | H23: =SUMIFS(NAm!$N$3:$N$82,NAm!$F$3:$F$82,'NAm Capacity Data'!H$22,NAm!$U$3:$U$82,'NAm Capacity Data'!$A23)+SUMIFS(NAm!$P$3:$P$82,NAm!$F$3:$F$82,'NAm Capacity Data'!H$22,NAm!$U$3:$U$82,'NAm Capacity Data'!$A23) -> 572.8 | I23: =SUMIFS(NAm!$N$3:$N$82,NAm!$F$3:$F$82,'NAm Capacity Data'!I$22,NAm!$U$3:$U$82,'NAm Capacity Data'!$A23)+SUMIFS(NAm!$P$3:$P$82,NAm!$F$3:$F$82,'NAm Capacity Data'!I$22,NAm!$U$3:$U$82,'NAm Capacity Data'!$A23) -> 1451 | J23: =SUMIFS(NAm!$N$3:$N$82,NAm!$F$3:$F$82,'NAm Capacity Data'!J$22,NAm!$U$3:$U$82,'NAm Capacity Data'!$A23)+SUMIFS(NAm!$P$3:$P$82,NAm!$F$3:$F$82,'NAm Capacity Data'!J$22,NAm!$U$3:$U$82,'NAm Capacity Data'!$A23) -> 82.5 | ... AF23: =SUMIFS(NAm!$N$3:$N$82,NAm!$F$3:$F$82,'NAm Capacity Data'!AF$22,NAm!$U$3:$U$82,'NAm Capacity Data'!$A23)+SUMIFS(NAm!$P$3:$P$82,NAm!$F$3:$F$82,'NAm Capacity Data'!AF$22,NAm!$U$3:$U$82,'NAm Capacity Data'!$A23) -> 0
A24: ATJ | B24: =SUMIFS(NAm!$N$3:$N$82,NAm!$F$3:$F$82,"<"&'NAm Capacity Data'!C$22,NAm!$U$3:$U$82,'NAm Capacity Data'!$A24)+SUMIFS(NAm!$P$3:$P$82,NAm!$F$3:$F$82,"<"&'NAm Capacity Data'!C$22,NAm!$U$3:$U$82,'NAm Capacity Data'!$A24) -> 60.1 | C24: =SUMIFS(NAm!$N$3:$N$82,NAm!$F$3:$F$82,'NAm Capacity Data'!C$22,NAm!$U$3:$U$82,'NAm Capacity Data'!$A24)+SUMIFS(NAm!$P$3:$P$82,NAm!$F$3:$F$82,'NAm Capacity Data'!C$22,NAm!$U$3:$U$82,'NAm Capacity Data'!$A24) -> 0 | D24: =SUMIFS(NAm!$N$3:$N$82,NAm!$F$3:$F$82,'NAm Capacity Data'!D$22,NAm!$U$3:$U$82,'NAm Capacity Data'!$A24)+SUMIFS(NAm!$P$3:$P$82,NAm!$F$3:$F$82,'NAm Capacity Data'!D$22,NAm!$U$3:$U$82,'NAm Capacity Data'!$A24) -> 0 | E24: =SUMIFS(NAm!$N$3:$N$82,NAm!$F$3:$F$82,'NAm Capacity Data'!E$22,NAm!$U$3:$U$82,'NAm Capacity Data'!$A24)+SUMIFS(NAm!$P$3:$P$82,NAm!$F$3:$F$82,'NAm Capacity Data'!E$22,NAm!$U$3:$U$82,'NAm Capacity Data'!$A24) -> 0 | F24: =SUMIFS(NAm!$N$3:$N$82,NAm!$F$3:$F$82,'NAm Capacity Data'!F$22,NAm!$U$3:$U$82,'NAm Capacity Data'!$A24)+SUMIFS(NAm!$P$3:$P$82,NAm!$F$3:$F$82,'NAm Capacity Data'!F$22,NAm!$U$3:$U$82,'NAm Capacity Data'!$A24) -> 9 | G24: =SUMIFS(NAm!$N$3:$N$82,NAm!$F$3:$F$82,'NAm Capacity Data'!G$22,NAm!$U$3:$U$82,'NAm Capacity Data'!$A24)+SUMIFS(NAm!$P$3:$P$82,NAm!$F$3:$F$82,'NAm Capacity Data'!G$22,NAm!$U$3:$U$82,'NAm Capacity Data'!$A24) -> 103.09125 | H24: =SUMIFS(NAm!$N$3:$N$82,NAm!$F$3:$F$82,'NAm Capacity Data'!H$22,NAm!$U$3:$U$82,'NAm Capacity Data'!$A24)+SUMIFS(NAm!$P$3:$P$82,NAm!$F$3:$F$82,'NAm Capacity Data'!H$22,NAm!$U$3:$U$82,'NAm Capacity Data'!$A24) -> 345 | I24: =SUMIFS(NAm!$N$3:$N$82,NAm!$F$3:$F$82,'NAm Capacity Data'!I$22,NAm!$U$3:$U$82,'NAm Capacity Data'!$A24)+SUMIFS(NAm!$P$3:$P$82,NAm!$F$3:$F$82,'NAm Capacity Data'!I$22,NAm!$U$3:$U$82,'NAm Capacity Data'!$A24) -> 490 | J24: =SUMIFS(NAm!$N$3:$N$82,NAm!$F$3:$F$82,'NAm Capacity Data'!J$22,NAm!$U$3:$U$82,'NAm Capacity Data'!$A24)+SUMIFS(NAm!$P$3:$P$82,NAm!$F$3:$F$82,'NAm Capacity Data'!J$22,NAm!$U$3:$U$82,'NAm Capacity Data'!$A24) -> 195 | ... AF24: =SUMIFS(NAm!$N$3:$N$82,NAm!$F$3:$F$82,'NAm Capacity Data'!AF$22,NAm!$U$3:$U$82,'NAm Capacity Data'!$A24)+SUMIFS(NAm!$P$3:$P$82,NAm!$F$3:$F$82,'NAm Capacity Data'!AF$22,NAm!$U$3:$U$82,'NAm Capacity Data'!$A24) -> 0
A25: FT | B25: =SUMIFS(NAm!$N$3:$N$82,NAm!$F$3:$F$82,"<"&'NAm Capacity Data'!C$22,NAm!$U$3:$U$82,'NAm Capacity Data'!$A25)+SUMIFS(NAm!$P$3:$P$82,NAm!$F$3:$F$82,"<"&'NAm Capacity Data'!C$22,NAm!$U$3:$U$82,'NAm Capacity Data'!$A25) -> 0 | C25: =SUMIFS(NAm!$N$3:$N$82,NAm!$F$3:$F$82,'NAm Capacity Data'!C$22,NAm!$U$3:$U$82,'NAm Capacity Data'!$A25)+SUMIFS(NAm!$P$3:$P$82,NAm!$F$3:$F$82,'NAm Capacity Data'!C$22,NAm!$U$3:$U$82,'NAm Capacity Data'!$A25) -> 0 | D25: =SUMIFS(NAm!$N$3:$N$82,NAm!$F$3:$F$82,'NAm Capacity Data'!D$22,NAm!$U$3:$U$82,'NAm Capacity Data'!$A25)+SUMIFS(NAm!$P$3:$P$82,NAm!$F$3:$F$82,'NAm Capacity Data'!D$22,NAm!$U$3:$U$82,'NAm Capacity Data'!$A25) -> 0 | E25: =SUMIFS(NAm!$N$3:$N$82,NAm!$F$3:$F$82,'NAm Capacity Data'!E$22,NAm!$U$3:$U$82,'NAm Capacity Data'!$A25)+SUMIFS(NAm!$P$3:$P$82,NAm!$F$3:$F$82,'NAm Capacity Data'!E$22,NAm!$U$3:$U$82,'NAm Capacity Data'!$A25) -> 0 | F25: =SUMIFS(NAm!$N$3:$N$82,NAm!$F$3:$F$82,'NAm Capacity Data'!F$22,NAm!$U$3:$U$82,'NAm Capacity Data'!$A25)+SUMIFS(NAm!$P$3:$P$82,NAm!$F$3:$F$82,'NAm Capacity Data'!F$22,NAm!$U$3:$U$82,'NAm Capacity Data'!$A25) -> 0 | G25: =SUMIFS(NAm!$N$3:$N$82,NAm!$F$3:$F$82,'NAm Capacity Data'!G$22,NAm!$U$3:$U$82,'NAm Capacity Data'!$A25)+SUMIFS(NAm!$P$3:$P$82,NAm!$F$3:$F$82,'NAm Capacity Data'!G$22,NAm!$U$3:$U$82,'NAm Capacity Data'!$A25) -> 78.036 | H25: =SUMIFS(NAm!$N$3:$N$82,NAm!$F$3:$F$82,'NAm Capacity Data'!H$22,NAm!$U$3:$U$82,'NAm Capacity Data'!$A25)+SUMIFS(NAm!$P$3:$P$82,NAm!$F$3:$F$82,'NAm Capacity Data'!H$22,NAm!$U$3:$U$82,'NAm Capacity Data'!$A25) -> 0 | I25: =SUMIFS(NAm!$N$3:$N$82,NAm!$F$3:$F$82,'NAm Capacity Data'!I$22,NAm!$U$3:$U$82,'NAm Capacity Data'!$A25)+SUMIFS(NAm!$P$3:$P$82,NAm!$F$3:$F$82,'NAm Capacity Data'!I$22,NAm!$U$3:$U$82,'NAm Capacity Data'!$A25) -> 411.5 | J25: =SUMIFS(NAm!$N$3:$N$82,NAm!$F$3:$F$82,'NAm Capacity Data'!J$22,NAm!$U$3:$U$82,'NAm Capacity Data'!$A25)+SUMIFS(NAm!$P$3:$P$82,NAm!$F$3:$F$82,'NAm Capacity Data'!J$22,NAm!$U$3:$U$82,'NAm Capacity Data'!$A25) -> 117.3 | ... AF25: =SUMIFS(NAm!$N$3:$N$82,NAm!$F$3:$F$82,'NAm Capacity Data'!AF$22,NAm!$U$3:$U$82,'NAm Capacity Data'!$A25)+SUMIFS(NAm!$P$3:$P$82,NAm!$F$3:$F$82,'NAm Capacity Data'!AF$22,NAm!$U$3:$U$82,'NAm Capacity Data'!$A25) -> 0
A26: PTL | B26: =SUMIFS(NAm!$N$3:$N$82,NAm!$F$3:$F$82,"<"&'NAm Capacity Data'!C$22,NAm!$U$3:$U$82,'NAm Capacity Data'!$A26)+SUMIFS(NAm!$P$3:$P$82,NAm!$F$3:$F$82,"<"&'NAm Capacity Data'!C$22,NAm!$U$3:$U$82,'NAm Capacity Data'!$A26) -> 0 | C26: =SUMIFS(NAm!$N$3:$N$82,NAm!$F$3:$F$82,'NAm Capacity Data'!C$22,NAm!$U$3:$U$82,'NAm Capacity Data'!$A26)+SUMIFS(NAm!$P$3:$P$82,NAm!$F$3:$F$82,'NAm Capacity Data'!C$22,NAm!$U$3:$U$82,'NAm Capacity Data'!$A26) -> 0 | D26: =SUMIFS(NAm!$N$3:$N$82,NAm!$F$3:$F$82,'NAm Capacity Data'!D$22,NAm!$U$3:$U$82,'NAm Capacity Data'!$A26)+SUMIFS(NAm!$P$3:$P$82,NAm!$F$3:$F$82,'NAm Capacity Data'!D$22,NAm!$U$3:$U$82,'NAm Capacity Data'!$A26) -> 0.001 | E26: =SUMIFS(NAm!$N$3:$N$82,NAm!$F$3:$F$82,'NAm Capacity Data'!E$22,NAm!$U$3:$U$82,'NAm Capacity Data'!$A26)+SUMIFS(NAm!$P$3:$P$82,NAm!$F$3:$F$82,'NAm Capacity Data'!E$22,NAm!$U$3:$U$82,'NAm Capacity Data'!$A26) -> 0 | F26: =SUMIFS(NAm!$N$3:$N$82,NAm!$F$3:$F$82,'NAm Capacity Data'!F$22,NAm!$U$3:$U$82,'NAm Capacity Data'!$A26)+SUMIFS(NAm!$P$3:$P$82,NAm!$F$3:$F$82,'NAm Capacity Data'!F$22,NAm!$U$3:$U$82,'NAm Capacity Data'!$A26) -> 0.39625827 | G26: =SUMIFS(NAm!$N$3:$N$82,NAm!$F$3:$F$82,'NAm Capacity Data'!G$22,NAm!$U$3:$U$82,'NAm Capacity Data'!$A26)+SUMIFS(NAm!$P$3:$P$82,NAm!$F$3:$F$82,'NAm Capacity Data'!G$22,NAm!$U$3:$U$82,'NAm Capacity Data'!$A26) -> 0.0645625 | H26: =SUMIFS(NAm!$N$3:$N$82,NAm!$F$3:$F$82,'NAm Capacity Data'!H$22,NAm!$U$3:$U$82,'NAm Capacity Data'!$A26)+SUMIFS(NAm!$P$3:$P$82,NAm!$F$3:$F$82,'NAm Capacity Data'!H$22,NAm!$U$3:$U$82,'NAm Capacity Data'!$A26) -> 7 | I26: =SUMIFS(NAm!$N$3:$N$82,NAm!$F$3:$F$82,'NAm Capacity Data'!I$22,NAm!$U$3:$U$82,'NAm Capacity Data'!$A26)+SUMIFS(NAm!$P$3:$P$82,NAm!$F$3:$F$82,'NAm Capacity Data'!I$22,NAm!$U$3:$U$82,'NAm Capacity Data'!$A26) -> 0 | J26: =SUMIFS(NAm!$N$3:$N$82,NAm!$F$3:$F$82,'NAm Capacity Data'!J$22,NAm!$U$3:$U$82,'NAm Capacity Data'!$A26)+SUMIFS(NAm!$P$3:$P$82,NAm!$F$3:$F$82,'NAm Capacity Data'!J$22,NAm!$U$3:$U$82,'NAm Capacity Data'!$A26) -> 31.2 | ... AF26: =SUMIFS(NAm!$N$3:$N$82,NAm!$F$3:$F$82,'NAm Capacity Data'!AF$22,NAm!$U$3:$U$82,'NAm Capacity Data'!$A26)+SUMIFS(NAm!$P$3:$P$82,NAm!$F$3:$F$82,'NAm Capacity Data'!AF$22,NAm!$U$3:$U$82,'NAm Capacity Data'!$A26) -> 0
A27: Pyrolysis | B27: =SUMIFS(NAm!$N$3:$N$82,NAm!$F$3:$F$82,"<"&'NAm Capacity Data'!C$22,NAm!$U$3:$U$82,'NAm Capacity Data'!$A27)+SUMIFS(NAm!$P$3:$P$82,NAm!$F$3:$F$82,"<"&'NAm Capacity Data'!C$22,NAm!$U$3:$U$82,'NAm Capacity Data'!$A27) -> 0 | C27: =SUMIFS(NAm!$N$3:$N$82,NAm!$F$3:$F$82,'NAm Capacity Data'!C$22,NAm!$U$3:$U$82,'NAm Capacity Data'!$A27)+SUMIFS(NAm!$P$3:$P$82,NAm!$F$3:$F$82,'NAm Capacity Data'!C$22,NAm!$U$3:$U$82,'NAm Capacity Data'!$A27) -> 0 | D27: =SUMIFS(NAm!$N$3:$N$82,NAm!$F$3:$F$82,'NAm Capacity Data'!D$22,NAm!$U$3:$U$82,'NAm Capacity Data'!$A27)+SUMIFS(NAm!$P$3:$P$82,NAm!$F$3:$F$82,'NAm Capacity Data'!D$22,NAm!$U$3:$U$82,'NAm Capacity Data'!$A27) -> 0 | E27: =SUMIFS(NAm!$N$3:$N$82,NAm!$F$3:$F$82,'NAm Capacity Data'!E$22,NAm!$U$3:$U$82,'NAm Capacity Data'!$A27)+SUMIFS(NAm!$P$3:$P$82,NAm!$F$3:$F$82,'NAm Capacity Data'!E$22,NAm!$U$3:$U$82,'NAm Capacity Data'!$A27) -> 0 | F27: =SUMIFS(NAm!$N$3:$N$82,NAm!$F$3:$F$82,'NAm Capacity Data'!F$22,NAm!$U$3:$U$82,'NAm Capacity Data'!$A27)+SUMIFS(NAm!$P$3:$P$82,NAm!$F$3:$F$82,'NAm Capacity Data'!F$22,NAm!$U$3:$U$82,'NAm Capacity Data'!$A27) -> 0 | G27: =SUMIFS(NAm!$N$3:$N$82,NAm!$F$3:$F$82,'NAm Capacity Data'!G$22,NAm!$U$3:$U$82,'NAm Capacity Data'!$A27)+SUMIFS(NAm!$P$3:$P$82,NAm!$F$3:$F$82,'NAm Capacity Data'!G$22,NAm!$U$3:$U$82,'NAm Capacity Data'!$A27) -> 10 | H27: =SUMIFS(NAm!$N$3:$N$82,NAm!$F$3:$F$82,'NAm Capacity Data'!H$22,NAm!$U$3:$U$82,'NAm Capacity Data'!$A27)+SUMIFS(NAm!$P$3:$P$82,NAm!$F$3:$F$82,'NAm Capacity Data'!H$22,NAm!$U$3:$U$82,'NAm Capacity Data'!$A27) -> 1 | I27: =SUMIFS(NAm!$N$3:$N$82,NAm!$F$3:$F$82,'NAm Capacity Data'!I$22,NAm!$U$3:$U$82,'NAm Capacity Data'!$A27)+SUMIFS(NAm!$P$3:$P$82,NAm!$F$3:$F$82,'NAm Capacity Data'!I$22,NAm!$U$3:$U$82,'NAm Capacity Data'!$A27) -> 0 | J27: =SUMIFS(NAm!$N$3:$N$82,NAm!$F$3:$F$82,'NAm Capacity Data'!J$22,NAm!$U$3:$U$82,'NAm Capacity Data'!$A27)+SUMIFS(NAm!$P$3:$P$82,NAm!$F$3:$F$82,'NAm Capacity Data'!J$22,NAm!$U$3:$U$82,'NAm Capacity Data'!$A27) -> 0 | ... AF27: =SUMIFS(NAm!$N$3:$N$82,NAm!$F$3:$F$82,'NAm Capacity Data'!AF$22,NAm!$U$3:$U$82,'NAm Capacity Data'!$A27)+SUMIFS(NAm!$P$3:$P$82,NAm!$F$3:$F$82,'NAm Capacity Data'!AF$22,NAm!$U$3:$U$82,'NAm Capacity Data'!$A27) -> 0
A28: Co-Processing | B28: =SUMIFS(NAm!$N$3:$N$82,NAm!$F$3:$F$82,"<"&'NAm Capacity Data'!C$22,NAm!$U$3:$U$82,'NAm Capacity Data'!$A28)+SUMIFS(NAm!$P$3:$P$82,NAm!$F$3:$F$82,"<"&'NAm Capacity Data'!C$22,NAm!$U$3:$U$82,'NAm Capacity Data'!$A28) -> 0 | C28: =SUMIFS(NAm!$N$3:$N$82,NAm!$F$3:$F$82,'NAm Capacity Data'!C$22,NAm!$U$3:$U$82,'NAm Capacity Data'!$A28)+SUMIFS(NAm!$P$3:$P$82,NAm!$F$3:$F$82,'NAm Capacity Data'!C$22,NAm!$U$3:$U$82,'NAm Capacity Data'!$A28) -> 73.5 | D28: =SUMIFS(NAm!$N$3:$N$82,NAm!$F$3:$F$82,'NAm Capacity Data'!D$22,NAm!$U$3:$U$82,'NAm Capacity Data'!$A28)+SUMIFS(NAm!$P$3:$P$82,NAm!$F$3:$F$82,'NAm Capacity Data'!D$22,NAm!$U$3:$U$82,'NAm Capacity Data'!$A28) -> 0 | E28: =SUMIFS(NAm!$N$3:$N$82,NAm!$F$3:$F$82,'NAm Capacity Data'!E$22,NAm!$U$3:$U$82,'NAm Capacity Data'!$A28)+SUMIFS(NAm!$P$3:$P$82,NAm!$F$3:$F$82,'NAm Capacity Data'!E$22,NAm!$U$3:$U$82,'NAm Capacity Data'!$A28) -> 0 | F28: =SUMIFS(NAm!$N$3:$N$82,NAm!$F$3:$F$82,'NAm Capacity Data'!F$22,NAm!$U$3:$U$82,'NAm Capacity Data'!$A28)+SUMIFS(NAm!$P$3:$P$82,NAm!$F$3:$F$82,'NAm Capacity Data'!F$22,NAm!$U$3:$U$82,'NAm Capacity Data'!$A28) -> 0.32 | G28: =SUMIFS(NAm!$N$3:$N$82,NAm!$F$3:$F$82,'NAm Capacity Data'!G$22,NAm!$U$3:$U$82,'NAm Capacity Data'!$A28)+SUMIFS(NAm!$P$3:$P$82,NAm!$F$3:$F$82,'NAm Capacity Data'!G$22,NAm!$U$3:$U$82,'NAm Capacity Data'!$A28) -> 10 | H28: =SUMIFS(NAm!$N$3:$N$82,NAm!$F$3:$F$82,'NAm Capacity Data'!H$22,NAm!$U$3:$U$82,'NAm Capacity Data'!$A28)+SUMIFS(NAm!$P$3:$P$82,NAm!$F$3:$F$82,'NAm Capacity Data'!H$22,NAm!$U$3:$U$82,'NAm Capacity Data'!$A28) -> 0 | I28: =SUMIFS(NAm!$N$3:$N$82,NAm!$F$3:$F$82,'NAm Capacity Data'!I$22,NAm!$U$3:$U$82,'NAm Capacity Data'!$A28)+SUMIFS(NAm!$P$3:$P$82,NAm!$F$3:$F$82,'NAm Capacity Data'!I$22,NAm!$U$3:$U$82,'NAm Capacity Data'!$A28) -> 73.5 | J28: =SUMIFS(NAm!$N$3:$N$82,NAm!$F$3:$F$82,'NAm Capacity Data'!J$22,NAm!$U$3:$U$82,'NAm Capacity Data'!$A28)+SUMIFS(NAm!$P$3:$P$82,NAm!$F$3:$F$82,'NAm Capacity Data'!J$22,NAm!$U$3:$U$82,'NAm Capacity Data'!$A28) -> 0 | ... AF28: =SUMIFS(NAm!$N$3:$N$82,NAm!$F$3:$F$82,'NAm Capacity Data'!AF$22,NAm!$U$3:$U$82,'NAm Capacity Data'!$A28)+SUMIFS(NAm!$P$3:$P$82,NAm!$F$3:$F$82,'NAm Capacity Data'!AF$22,NAm!$U$3:$U$82,'NAm Capacity Data'!$A28) -> 0
A29: Total Capacity | B29: =SUM(B23:B28) -> 142.1 | C29: =B29+SUM(C23:C28) -> 565.6 | D29: =C29+SUM(D23:D28) -> 965.601 | E29: =D29+SUM(E23:E28) -> 965.601 | F29: =E29+SUM(F23:F28) -> 1848.3173 | G29: =F29+SUM(G23:G28) -> 2492.8351 | H29: =G29+SUM(H23:H28) -> 3418.6351 | I29: =H29+SUM(I23:I28) -> 5844.6351 | J29: =I29+SUM(J23:J28) -> 6270.6351 | ... AF29: =AE29+SUM(AF23:AF28) -> 6771.1751
B30: =B19/B29 -> 0.59817101 | C30: =C19/C29 -> 0.28085237 | D30: =D19/D29 -> 0.57875986 | E30: =E19/E29 -> 0.57875986 | F30: =F19/F29 -> 0.75546732 | G30: =G19/G29 -> 0.76489508 | H30: =H19/H29 -> 0.72303631 | I30: =I19/I29 -> 0.61560084 | ... AF30: =AF19/AF29 -> 0.5792893
A31: North American Cumulative SAF Capacity by Technology
A32: (mil gal/yr) | B32: =B22 -> < 2021 | C32: =C22 -> 2021 | D32: =D22 -> 2022 | E32: =E22 -> 2023 | F32: =F22 -> 2024 | G32: =G22 -> 2025 | H32: =H22 -> 2026 | I32: =I22 -> 2027 | ... AF32: =AF22 -> 2050
A33: HEFA Cumulative | B33: =B23 -> 82 | C33: =B33+C23 -> 432 | D33: =C33+D23 -> 832 | E33: =D33+E23 -> 832 | F33: =E33+F23 -> 1705 | G33: =F33+G23 -> 2148.326 | H33: =G33+H23 -> 2721.126 | I33: =H33+I23 -> 4172.126 | J33: =I33+J23 -> 4254.626 | ... AF33: =AE33+AF23 -> 4375.626 | AG33: =L33/$L$39 -> 0.65277306
A34: ATJ Cumulative | B34: =B24 -> 60.1 | C34: =B34+C24 -> 60.1 | D34: =C34+D24 -> 60.1 | E34: =D34+E24 -> 60.1 | F34: =E34+F24 -> 69.1 | G34: =F34+G24 -> 172.19125 | H34: =G34+H24 -> 517.19125 | I34: =H34+I24 -> 1007.1912 | J34: =I34+J24 -> 1202.1912 | ... AF34: =AE34+AF24 -> 1300.2312 | AG34: =L34/$L$39 -> 0.18382313
A35: FT Cumulative | B35: =B25 -> 0 | C35: =B35+C25 -> 0 | D35: =C35+D25 -> 0 | E35: =D35+E25 -> 0 | F35: =E35+F25 -> 0 | G35: =F35+G25 -> 78.036 | H35: =G35+H25 -> 78.036 | I35: =H35+I25 -> 489.536 | J35: =I35+J25 -> 606.836 | ... AF35: =AE35+AF25 -> 775.336 | AG35: =L35/$L$39 -> 0.11566767
A36: PTL Cumulative | B36: =B26 -> 0 | C36: =C26+B36 -> 0 | D36: =D26+C36 -> 0.001 | E36: =E26+D36 -> 0.001 | F36: =F26+E36 -> 0.39725827 | G36: =G26+F36 -> 0.46182077 | H36: =H26+G36 -> 7.4618208 | I36: =I26+H36 -> 7.4618208 | J36: =J26+I36 -> 38.661821 | ... AF36: =AF26+AE36 -> 151.66182 | AG36: =L36/$L$39 -> 0.022625506
A37: Pyrolysis Cumulative | B37: =B27 -> 0 | C37: =B37+C27 -> 0 | D37: =C37+D27 -> 0 | E37: =D37+E27 -> 0 | F37: =E37+F27 -> 0 | G37: =F37+G27 -> 10 | H37: =G37+H27 -> 11 | I37: =H37+I27 -> 11 | J37: =I37+J27 -> 11 | ... AF37: =AE37+AF27 -> 11 | AG37: =L37/$L$39 -> 0.0016410232
A38: Co-Processing Cumulative | B38: =B28 -> 0 | C38: =B38+C28 -> 73.5 | D38: =C38+D28 -> 73.5 | E38: =D38+E28 -> 73.5 | F38: =E38+F28 -> 73.82 | G38: =F38+G28 -> 83.82 | H38: =G38+H28 -> 83.82 | I38: =H38+I28 -> 157.32 | J38: =I38+J28 -> 157.32 | ... AF38: =AE38+AF28 -> 157.32 | AG38: =L38/$L$39 -> 0.023469615
A39: Total Capacity | B39: =SUM(B33:B38) -> 142.1 | C39: =SUM(C33:C38) -> 565.6 | D39: =SUM(D33:D38) -> 965.601 | E39: =SUM(E33:E38) -> 965.601 | F39: =SUM(F33:F38) -> 1848.3173 | G39: =SUM(G33:G38) -> 2492.8351 | H39: =SUM(H33:H38) -> 3418.6351 | I39: =SUM(I33:I38) -> 5844.6351 | ... AF39: =SUM(AF33:AF38) -> 6771.1751
A41: Number of Plants by Technology
B42: =B22 -> < 2021 | C42: =C22 -> 2021 | D42: =D22 -> 2022 | E42: =E22 -> 2023 | F42: =F22 -> 2024 | G42: =G22 -> 2025 | H42: =H22 -> 2026 | I42: =I22 -> 2027 | ... AF42: =AF22 -> 2050 | AG42: Check Total | AH42: Check | AI42: Should be one less than the check total because El Segundo shows up twice on the list
A43: HEFA | B43: =COUNTIFS(NAm!$F$3:$F$82,"<"&'NAm Capacity Data'!C$22,NAm!$U$3:$U$82,$A43) -> 1 | C43: =COUNTIFS(NAm!$F$3:$F$82,'NAm Capacity Data'!C$22,NAm!$U$3:$U$82,$A43) -> 1 | D43: =COUNTIFS(NAm!$F$3:$F$82,'NAm Capacity Data'!D$22,NAm!$U$3:$U$82,$A43) -> 2 | E43: =COUNTIFS(NAm!$F$3:$F$82,'NAm Capacity Data'!E$22,NAm!$U$3:$U$82,$A43) -> 0 | F43: =COUNTIFS(NAm!$F$3:$F$82,'NAm Capacity Data'!F$22,NAm!$U$3:$U$82,$A43) -> 5 | G43: =COUNTIFS(NAm!$F$3:$F$82,'NAm Capacity Data'!G$22,NAm!$U$3:$U$82,$A43) -> 6 | H43: =COUNTIFS(NAm!$F$3:$F$82,'NAm Capacity Data'!H$22,NAm!$U$3:$U$82,$A43) -> 4 | I43: =COUNTIFS(NAm!$F$3:$F$82,'NAm Capacity Data'!I$22,NAm!$U$3:$U$82,$A43) -> 10 | J43: =COUNTIFS(NAm!$F$3:$F$82,'NAm Capacity Data'!J$22,NAm!$U$3:$U$82,$A43) -> 2 | ... AF43: =COUNTIFS(NAm!$F$3:$F$82,'NAm Capacity Data'!AF$22,NAm!$U$3:$U$82,$A43) -> 0 | AG43: =SUM(B43:P43) -> 34 | AH43: =AG43-NAm!U87 -> 0
A44: ATJ | B44: =COUNTIFS(NAm!$F$3:$F$82,"<"&'NAm Capacity Data'!C$22,NAm!$U$3:$U$82,$A44) -> 2 | C44: =COUNTIFS(NAm!$F$3:$F$82,'NAm Capacity Data'!C$22,NAm!$U$3:$U$82,$A44) -> 0 | D44: =COUNTIFS(NAm!$F$3:$F$82,'NAm Capacity Data'!D$22,NAm!$U$3:$U$82,$A44) -> 0 | E44: =COUNTIFS(NAm!$F$3:$F$82,'NAm Capacity Data'!E$22,NAm!$U$3:$U$82,$A44) -> 0 | F44: =COUNTIFS(NAm!$F$3:$F$82,'NAm Capacity Data'!F$22,NAm!$U$3:$U$82,$A44) -> 1 | G44: =COUNTIFS(NAm!$F$3:$F$82,'NAm Capacity Data'!G$22,NAm!$U$3:$U$82,$A44) -> 2 | H44: =COUNTIFS(NAm!$F$3:$F$82,'NAm Capacity Data'!H$22,NAm!$U$3:$U$82,$A44) -> 2 | I44: =COUNTIFS(NAm!$F$3:$F$82,'NAm Capacity Data'!I$22,NAm!$U$3:$U$82,$A44) -> 3 | J44: =COUNTIFS(NAm!$F$3:$F$82,'NAm Capacity Data'!J$22,NAm!$U$3:$U$82,$A44) -> 2 | ... AF44: =COUNTIFS(NAm!$F$3:$F$82,'NAm Capacity Data'!AF$22,NAm!$U$3:$U$82,$A44) -> 0 | AG44: =SUM(B44:P44) -> 14 | AH44: =AG44-NAm!U88 -> 0
A45: FT | B45: =COUNTIFS(NAm!$F$3:$F$82,"<"&'NAm Capacity Data'!C$22,NAm!$U$3:$U$82,$A45) -> 0 | C45: =COUNTIFS(NAm!$F$3:$F$82,'NAm Capacity Data'!C$22,NAm!$U$3:$U$82,$A45) -> 0 | D45: =COUNTIFS(NAm!$F$3:$F$82,'NAm Capacity Data'!D$22,NAm!$U$3:$U$82,$A45) -> 0 | E45: =COUNTIFS(NAm!$F$3:$F$82,'NAm Capacity Data'!E$22,NAm!$U$3:$U$82,$A45) -> 0 | F45: =COUNTIFS(NAm!$F$3:$F$82,'NAm Capacity Data'!F$22,NAm!$U$3:$U$82,$A45) -> 0 | G45: =COUNTIFS(NAm!$F$3:$F$82,'NAm Capacity Data'!G$22,NAm!$U$3:$U$82,$A45) -> 2 | H45: =COUNTIFS(NAm!$F$3:$F$82,'NAm Capacity Data'!H$22,NAm!$U$3:$U$82,$A45) -> 0 | I45: =COUNTIFS(NAm!$F$3:$F$82,'NAm Capacity Data'!I$22,NAm!$U$3:$U$82,$A45) -> 5 | J45: =COUNTIFS(NAm!$F$3:$F$82,'NAm Capacity Data'!J$22,NAm!$U$3:$U$82,$A45) -> 2 | ... AF45: =COUNTIFS(NAm!$F$3:$F$82,'NAm Capacity Data'!AF$22,NAm!$U$3:$U$82,$A45) -> 0 | AG45: =SUM(B45:P45) -> 11 | AH45: =AG45-NAm!U89 -> 0
A46: PTL | B46: =COUNTIFS(NAm!$F$3:$F$82,"<"&'NAm Capacity Data'!C$22,NAm!$U$3:$U$82,$A46) -> 0 | C46: =COUNTIFS(NAm!$F$3:$F$82,'NAm Capacity Data'!C$22,NAm!$U$3:$U$82,$A46) -> 0 | D46: =COUNTIFS(NAm!$F$3:$F$82,'NAm Capacity Data'!D$22,NAm!$U$3:$U$82,$A46) -> 1 | E46: =COUNTIFS(NAm!$F$3:$F$82,'NAm Capacity Data'!E$22,NAm!$U$3:$U$82,$A46) -> 0 | F46: =COUNTIFS(NAm!$F$3:$F$82,'NAm Capacity Data'!F$22,NAm!$U$3:$U$82,$A46) -> 1 | G46: =COUNTIFS(NAm!$F$3:$F$82,'NAm Capacity Data'!G$22,NAm!$U$3:$U$82,$A46) -> 3 | H46: =COUNTIFS(NAm!$F$3:$F$82,'NAm Capacity Data'!H$22,NAm!$U$3:$U$82,$A46) -> 2 | I46: =COUNTIFS(NAm!$F$3:$F$82,'NAm Capacity Data'!I$22,NAm!$U$3:$U$82,$A46) -> 0 | J46: =COUNTIFS(NAm!$F$3:$F$82,'NAm Capacity Data'!J$22,NAm!$U$3:$U$82,$A46) -> 2 | ... AF46: =COUNTIFS(NAm!$F$3:$F$82,'NAm Capacity Data'!AF$22,NAm!$U$3:$U$82,$A46) -> 0 | AG46: =SUM(B46:P46) -> 11 | AH46: =AG46-NAm!U90 -> -1
A47: Pyrolysis | B47: =COUNTIFS(NAm!$F$3:$F$82,"<"&'NAm Capacity Data'!C$22,NAm!$U$3:$U$82,$A47) -> 0 | C47: =COUNTIFS(NAm!$F$3:$F$82,'NAm Capacity Data'!C$22,NAm!$U$3:$U$82,$A47) -> 0 | D47: =COUNTIFS(NAm!$F$3:$F$82,'NAm Capacity Data'!D$22,NAm!$U$3:$U$82,$A47) -> 0 | E47: =COUNTIFS(NAm!$F$3:$F$82,'NAm Capacity Data'!E$22,NAm!$U$3:$U$82,$A47) -> 0 | F47: =COUNTIFS(NAm!$F$3:$F$82,'NAm Capacity Data'!F$22,NAm!$U$3:$U$82,$A47) -> 1 | G47: =COUNTIFS(NAm!$F$3:$F$82,'NAm Capacity Data'!G$22,NAm!$U$3:$U$82,$A47) -> 1 | H47: =COUNTIFS(NAm!$F$3:$F$82,'NAm Capacity Data'!H$22,NAm!$U$3:$U$82,$A47) -> 1 | I47: =COUNTIFS(NAm!$F$3:$F$82,'NAm Capacity Data'!I$22,NAm!$U$3:$U$82,$A47) -> 0 | J47: =COUNTIFS(NAm!$F$3:$F$82,'NAm Capacity Data'!J$22,NAm!$U$3:$U$82,$A47) -> 0 | ... AF47: =COUNTIFS(NAm!$F$3:$F$82,'NAm Capacity Data'!AF$22,NAm!$U$3:$U$82,$A47) -> 0 | AG47: =SUM(B47:P47) -> 3 | AH47: =AG47-NAm!U91 -> 0
A48: Co-Processing | B48: =COUNTIFS(NAm!$F$3:$F$82,"<"&'NAm Capacity Data'!C$22,NAm!$U$3:$U$82,$A48) -> 0 | C48: =COUNTIFS(NAm!$F$3:$F$82,'NAm Capacity Data'!C$22,NAm!$U$3:$U$82,$A48) -> 1 | D48: =COUNTIFS(NAm!$F$3:$F$82,'NAm Capacity Data'!D$22,NAm!$U$3:$U$82,$A48) -> 0 | E48: =COUNTIFS(NAm!$F$3:$F$82,'NAm Capacity Data'!E$22,NAm!$U$3:$U$82,$A48) -> 0 | F48: =COUNTIFS(NAm!$F$3:$F$82,'NAm Capacity Data'!F$22,NAm!$U$3:$U$82,$A48) -> 1 | G48: =COUNTIFS(NAm!$F$3:$F$82,'NAm Capacity Data'!G$22,NAm!$U$3:$U$82,$A48) -> 2 | H48: =COUNTIFS(NAm!$F$3:$F$82,'NAm Capacity Data'!H$22,NAm!$U$3:$U$82,$A48) -> 0 | I48: =COUNTIFS(NAm!$F$3:$F$82,'NAm Capacity Data'!I$22,NAm!$U$3:$U$82,$A48) -> 1 | J48: =COUNTIFS(NAm!$F$3:$F$82,'NAm Capacity Data'!J$22,NAm!$U$3:$U$82,$A48) -> 0 | ... AF48: =COUNTIFS(NAm!$F$3:$F$82,'NAm Capacity Data'!AF$22,NAm!$U$3:$U$82,$A48) -> 0 | AG48: =SUM(B48:P48) -> 5 | AH48: =AG48-NAm!U92 -> 0
A49: Total Plants | B49: =SUM(B43:B48) -> 3 | C49: =B49+SUM(C43:C48) -> 5 | D49: =C49+SUM(D43:D48) -> 8 | E49: =D49+SUM(E43:E48) -> 8 | F49: =E49+SUM(F43:F48) -> 17 | G49: =F49+SUM(G43:G48) -> 33 | H49: =G49+SUM(H43:H48) -> 42 | I49: =H49+SUM(I43:I48) -> 61 | J49: =I49+SUM(J43:J48) -> 69 | ... AF49: =AE49+SUM(AF43:AF48) -> 78 | AG49: =SUM(AG43:AG48) -> 78
A51: North American SAF Capacity by Feedstock
A52: =A22 -> (mil gal/yr) | B52: =B22 -> < 2021 | C52: =C22 -> 2021 | D52: =D22 -> 2022 | E52: =E22 -> 2023 | F52: =F22 -> 2024 | G52: =G22 -> 2025 | H52: =H22 -> 2026 | ... AF52: =AF22 -> 2050
A53: FOGs | B53: =SUMIFS(NAm!$N$3:$N$82,NAm!$F$3:$F$82,"<"&'NAm Capacity Data'!C$22,NAm!$V$3:$V$82,'NAm Capacity Data'!$A53) -> 82 | C53: =SUMIFS(NAm!$N$3:$N$82,NAm!$F$3:$F$82,'NAm Capacity Data'!C$22,NAm!$V$3:$V$82,'NAm Capacity Data'!$A53) -> 364.7 | D53: =SUMIFS(NAm!$N$3:$N$82,NAm!$F$3:$F$82,'NAm Capacity Data'!D$22,NAm!$V$3:$V$82,'NAm Capacity Data'!$A53) -> 100 | E53: =SUMIFS(NAm!$N$3:$N$82,NAm!$F$3:$F$82,'NAm Capacity Data'!E$22,NAm!$V$3:$V$82,'NAm Capacity Data'!$A53) -> 0 | F53: =SUMIFS(NAm!$N$3:$N$82,NAm!$F$3:$F$82,'NAm Capacity Data'!F$22,NAm!$V$3:$V$82,'NAm Capacity Data'!$A53) -> 873.32 | G53: =SUMIFS(NAm!$N$3:$N$82,NAm!$F$3:$F$82,'NAm Capacity Data'!G$22,NAm!$V$3:$V$82,'NAm Capacity Data'!$A53) -> 223.326 | H53: =SUMIFS(NAm!$N$3:$N$82,NAm!$F$3:$F$82,'NAm Capacity Data'!H$22,NAm!$V$3:$V$82,'NAm Capacity Data'!$A53) -> 572.8 | I53: =SUMIFS(NAm!$N$3:$N$82,NAm!$F$3:$F$82,'NAm Capacity Data'!I$22,NAm!$V$3:$V$82,'NAm Capacity Data'!$A53) -> 1438 | J53: =SUMIFS(NAm!$N$3:$N$82,NAm!$F$3:$F$82,'NAm Capacity Data'!J$22,NAm!$V$3:$V$82,'NAm Capacity Data'!$A53) -> 82.5 | ... AF53: =SUMIFS(NAm!$N$3:$N$82,NAm!$F$3:$F$82,'NAm Capacity Data'!AF$22,NAm!$V$3:$V$82,'NAm Capacity Data'!$A53) -> 0
A54: Ethanol | B54: =SUMIFS(NAm!$N$3:$N$82,NAm!$F$3:$F$82,"<"&'NAm Capacity Data'!C$22,NAm!$V$3:$V$82,'NAm Capacity Data'!$A54) -> 60.1 | C54: =SUMIFS(NAm!$N$3:$N$82,NAm!$F$3:$F$82,'NAm Capacity Data'!C$22,NAm!$V$3:$V$82,'NAm Capacity Data'!$A54) -> 0 | D54: =SUMIFS(NAm!$N$3:$N$82,NAm!$F$3:$F$82,'NAm Capacity Data'!D$22,NAm!$V$3:$V$82,'NAm Capacity Data'!$A54) -> 0 | E54: =SUMIFS(NAm!$N$3:$N$82,NAm!$F$3:$F$82,'NAm Capacity Data'!E$22,NAm!$V$3:$V$82,'NAm Capacity Data'!$A54) -> 0 | F54: =SUMIFS(NAm!$N$3:$N$82,NAm!$F$3:$F$82,'NAm Capacity Data'!F$22,NAm!$V$3:$V$82,'NAm Capacity Data'!$A54) -> 9 | G54: =SUMIFS(NAm!$N$3:$N$82,NAm!$F$3:$F$82,'NAm Capacity Data'!G$22,NAm!$V$3:$V$82,'NAm Capacity Data'!$A54) -> 3.09125 | H54: =SUMIFS(NAm!$N$3:$N$82,NAm!$F$3:$F$82,'NAm Capacity Data'!H$22,NAm!$V$3:$V$82,'NAm Capacity Data'!$A54) -> 206 | I54: =SUMIFS(NAm!$N$3:$N$82,NAm!$F$3:$F$82,'NAm Capacity Data'!I$22,NAm!$V$3:$V$82,'NAm Capacity Data'!$A54) -> 490 | J54: =SUMIFS(NAm!$N$3:$N$82,NAm!$F$3:$F$82,'NAm Capacity Data'!J$22,NAm!$V$3:$V$82,'NAm Capacity Data'!$A54) -> 195 | ... AF54: =SUMIFS(NAm!$N$3:$N$82,NAm!$F$3:$F$82,'NAm Capacity Data'!AF$22,NAm!$V$3:$V$82,'NAm Capacity Data'!$A54) -> 0
A55: Woody Biomass | B55: =SUMIFS(NAm!$N$3:$N$82,NAm!$F$3:$F$82,"<"&'NAm Capacity Data'!C$22,NAm!$V$3:$V$82,'NAm Capacity Data'!$A55) -> 0 | C55: =SUMIFS(NAm!$N$3:$N$82,NAm!$F$3:$F$82,'NAm Capacity Data'!C$22,NAm!$V$3:$V$82,'NAm Capacity Data'!$A55) -> 0 | D55: =SUMIFS(NAm!$N$3:$N$82,NAm!$F$3:$F$82,'NAm Capacity Data'!D$22,NAm!$V$3:$V$82,'NAm Capacity Data'!$A55) -> 0 | E55: =SUMIFS(NAm!$N$3:$N$82,NAm!$F$3:$F$82,'NAm Capacity Data'!E$22,NAm!$V$3:$V$82,'NAm Capacity Data'!$A55) -> 0 | F55: =SUMIFS(NAm!$N$3:$N$82,NAm!$F$3:$F$82,'NAm Capacity Data'!F$22,NAm!$V$3:$V$82,'NAm Capacity Data'!$A55) -> 0 | G55: =SUMIFS(NAm!$N$3:$N$82,NAm!$F$3:$F$82,'NAm Capacity Data'!G$22,NAm!$V$3:$V$82,'NAm Capacity Data'!$A55) -> 88 | H55: =SUMIFS(NAm!$N$3:$N$82,NAm!$F$3:$F$82,'NAm Capacity Data'!H$22,NAm!$V$3:$V$82,'NAm Capacity Data'!$A55) -> 1 | I55: =SUMIFS(NAm!$N$3:$N$82,NAm!$F$3:$F$82,'NAm Capacity Data'!I$22,NAm!$V$3:$V$82,'NAm Capacity Data'!$A55) -> 34 | J55: =SUMIFS(NAm!$N$3:$N$82,NAm!$F$3:$F$82,'NAm Capacity Data'!J$22,NAm!$V$3:$V$82,'NAm Capacity Data'!$A55) -> 117.3 | ... AF55: =SUMIFS(NAm!$N$3:$N$82,NAm!$F$3:$F$82,'NAm Capacity Data'!AF$22,NAm!$V$3:$V$82,'NAm Capacity Data'!$A55) -> 0
A56: CCS | B56: =SUMIFS(NAm!$N$3:$N$82,NAm!$F$3:$F$82,"<"&'NAm Capacity Data'!C$22,NAm!$V$3:$V$82,'NAm Capacity Data'!$A56) -> 0 | C56: =SUMIFS(NAm!$N$3:$N$82,NAm!$F$3:$F$82,'NAm Capacity Data'!C$22,NAm!$V$3:$V$82,'NAm Capacity Data'!$A56) -> 0 | D56: =SUMIFS(NAm!$N$3:$N$82,NAm!$F$3:$F$82,'NAm Capacity Data'!D$22,NAm!$V$3:$V$82,'NAm Capacity Data'!$A56) -> 0.001 | E56: =SUMIFS(NAm!$N$3:$N$82,NAm!$F$3:$F$82,'NAm Capacity Data'!E$22,NAm!$V$3:$V$82,'NAm Capacity Data'!$A56) -> 0 | F56: =SUMIFS(NAm!$N$3:$N$82,NAm!$F$3:$F$82,'NAm Capacity Data'!F$22,NAm!$V$3:$V$82,'NAm Capacity Data'!$A56) -> 0.39625827 | G56: =SUMIFS(NAm!$N$3:$N$82,NAm!$F$3:$F$82,'NAm Capacity Data'!G$22,NAm!$V$3:$V$82,'NAm Capacity Data'!$A56) -> 0.0645625 | H56: =SUMIFS(NAm!$N$3:$N$82,NAm!$F$3:$F$82,'NAm Capacity Data'!H$22,NAm!$V$3:$V$82,'NAm Capacity Data'!$A56) -> 5 | I56: =SUMIFS(NAm!$N$3:$N$82,NAm!$F$3:$F$82,'NAm Capacity Data'!I$22,NAm!$V$3:$V$82,'NAm Capacity Data'!$A56) -> 0 | J56: =SUMIFS(NAm!$N$3:$N$82,NAm!$F$3:$F$82,'NAm Capacity Data'!J$22,NAm!$V$3:$V$82,'NAm Capacity Data'!$A56) -> 31.2 | ... AF56: =SUMIFS(NAm!$N$3:$N$82,NAm!$F$3:$F$82,'NAm Capacity Data'!AF$22,NAm!$V$3:$V$82,'NAm Capacity Data'!$A56) -> 0
A57: MSW | B57: =SUMIFS(NAm!$N$3:$N$82,NAm!$F$3:$F$82,"<"&'NAm Capacity Data'!C$22,NAm!$V$3:$V$82,'NAm Capacity Data'!$A57) -> 0 | C57: =SUMIFS(NAm!$N$3:$N$82,NAm!$F$3:$F$82,'NAm Capacity Data'!C$22,NAm!$V$3:$V$82,'NAm Capacity Data'!$A57) -> 0 | D57: =SUMIFS(NAm!$N$3:$N$82,NAm!$F$3:$F$82,'NAm Capacity Data'!D$22,NAm!$V$3:$V$82,'NAm Capacity Data'!$A57) -> 0 | E57: =SUMIFS(NAm!$N$3:$N$82,NAm!$F$3:$F$82,'NAm Capacity Data'!E$22,NAm!$V$3:$V$82,'NAm Capacity Data'!$A57) -> 0 | F57: =SUMIFS(NAm!$N$3:$N$82,NAm!$F$3:$F$82,'NAm Capacity Data'!F$22,NAm!$V$3:$V$82,'NAm Capacity Data'!$A57) -> 0 | G57: =SUMIFS(NAm!$N$3:$N$82,NAm!$F$3:$F$82,'NAm Capacity Data'!G$22,NAm!$V$3:$V$82,'NAm Capacity Data'!$A57) -> 0.036 | H57: =SUMIFS(NAm!$N$3:$N$82,NAm!$F$3:$F$82,'NAm Capacity Data'!H$22,NAm!$V$3:$V$82,'NAm Capacity Data'!$A57) -> 0 | I57: =SUMIFS(NAm!$N$3:$N$82,NAm!$F$3:$F$82,'NAm Capacity Data'!I$22,NAm!$V$3:$V$82,'NAm Capacity Data'!$A57) -> 377.5 | J57: =SUMIFS(NAm!$N$3:$N$82,NAm!$F$3:$F$82,'NAm Capacity Data'!J$22,NAm!$V$3:$V$82,'NAm Capacity Data'!$A57) -> 0 | ... AF57: =SUMIFS(NAm!$N$3:$N$82,NAm!$F$3:$F$82,'NAm Capacity Data'!AF$22,NAm!$V$3:$V$82,'NAm Capacity Data'!$A57) -> 0
A58: Total Capacity | B58: =SUM(B53:B57) -> 142.1 | C58: =B58+SUM(C53:C57) -> 506.8 | D58: =C58+SUM(D53:D57) -> 606.801 | E58: =D58+SUM(E53:E57) -> 606.801 | F58: =E58+SUM(F53:F57) -> 1489.5173 | G58: =F58+SUM(G53:G57) -> 1804.0351 | H58: =G58+SUM(H53:H57) -> 2588.8351 | I58: =H58+SUM(I53:I57) -> 4928.3351 | J58: =I58+SUM(J53:J57) -> 5354.3351 | ... AF58: =AE58+SUM(AF53:AF57) -> 5854.8751
A60: North American Cumulative SAF Capacity by Feedstock
A61: =A22 -> (mil gal/yr) | B61: =B22 -> < 2021 | C61: =C22 -> 2021 | D61: =D22 -> 2022 | E61: =E22 -> 2023 | F61: =F22 -> 2024 | G61: =G22 -> 2025 | H61: =H22 -> 2026 | ... AF61: =AF22 -> 2050
A62: FOGs | B62: =B53 -> 82 | C62: =B62+C53 -> 446.7 | D62: =C62+D53 -> 546.7 | E62: =D62+E53 -> 546.7 | F62: =E62+F53 -> 1420.02 | G62: =F62+G53 -> 1643.346 | H62: =G62+H53 -> 2216.146 | I62: =H62+I53 -> 3654.146 | J62: =I62+J53 -> 3736.646 | ... AF62: =AE62+AF53 -> 3857.646
A63: Ethanol | B63: =B54 -> 60.1 | C63: =B63+C54 -> 60.1 | D63: =C63+D54 -> 60.1 | E63: =D63+E54 -> 60.1 | F63: =E63+F54 -> 69.1 | G63: =F63+G54 -> 72.19125 | H63: =G63+H54 -> 278.19125 | I63: =H63+I54 -> 768.19125 | J63: =I63+J54 -> 963.19125 | ... AF63: =AE63+AF54 -> 1061.2313
A64: Woody Biomass | B64: =B55 -> 0 | C64: =B64+C55 -> 0 | D64: =C64+D55 -> 0 | E64: =D64+E55 -> 0 | F64: =E64+F55 -> 0 | G64: =F64+G55 -> 88 | H64: =G64+H55 -> 89 | I64: =H64+I55 -> 123 | J64: =I64+J55 -> 240.3 | ... AF64: =AE64+AF55 -> 289.8
A65: CCS | B65: =B56 -> 0 | C65: =B65+C56 -> 0 | D65: =C65+D56 -> 0.001 | E65: =D65+E56 -> 0.001 | F65: =E65+F56 -> 0.39725827 | G65: =F65+G56 -> 0.46182077 | H65: =G65+H56 -> 5.4618208 | I65: =H65+I56 -> 5.4618208 | J65: =I65+J56 -> 36.661821 | ... AF65: =AE65+AF56 -> 149.66182
A66: MSW | B66: =B57 -> 0 | C66: =B66+C57 -> 0 | D66: =C66+D57 -> 0 | E66: =D66+E57 -> 0 | F66: =E66+F57 -> 0 | G66: =F66+G57 -> 0.036 | H66: =G66+H57 -> 0.036 | I66: =H66+I57 -> 377.536 | J66: =I66+J57 -> 377.536 | ... AF66: =AE66+AF57 -> 496.536
A67: Total Capacity | B67: =SUM(B62:B66) -> 142.1 | C67: =SUM(C62:C66) -> 506.8 | D67: =SUM(D62:D66) -> 606.801 | E67: =SUM(E62:E66) -> 606.801 | F67: =SUM(F62:F66) -> 1489.5173 | G67: =SUM(G62:G66) -> 1804.0351 | H67: =SUM(H62:H66) -> 2588.8351 | I67: =SUM(I62:I66) -> 4928.3351 | ... AF67: =SUM(AF62:AF66) -> 5854.8751
A69: Implied Feedstock Demand | AH69: Feedstock Assumptions | AJ69: Range
A70: =A22 -> (mil gal/yr) | B70: =B22 -> < 2021 | C70: =C22 -> 2021 | D70: =D22 -> 2022 | E70: =E22 -> 2023 | F70: =F22 -> 2024 | G70: =G22 -> 2025 | H70: =H22 -> 2026 | ... AF70: =AF22 -> 2050
A71: FOGs (mil lbs) | B71: =B62*$AH71 -> 676.5 | C71: =C62*$AH71 -> 3685.275 | D71: =D62*$AH71 -> 4510.275 | E71: =E62*$AH71 -> 4510.275 | F71: =F62*$AH71 -> 11715.165 | G71: =G62*$AH71 -> 13557.604 | H71: =H62*$AH71 -> 18283.204 | I71: =I62*$AH71 -> 30146.704 | ... AF71: =AF62*$AH71 -> 31825.579 | AH71: 8.25 | AI71: lbs/gal | AJ71: 7.5-8.3
A72: Grains (mil lbs) | B72: =B79*$AH72 -> 2036.4319 | C72: =C79*$AH72 -> 2036.4319 | D72: =D79*$AH72 -> 2036.4319 | E72: =E79*$AH72 -> 2036.4319 | F72: =F79*$AH72 -> 2341.3884 | G72: =G79*$AH72 -> 2446.1325 | H72: =H79*$AH72 -> 9426.2484 | I72: =I79*$AH72 -> 26029.437 | ... AF72: =AF79*$AH72 -> 35958.821 | AH72: =AH80*56 -> 20.289855 | AI72: lbs/gal
A73: Woody Biomass (mil lbs) | B73: =B64*$AH73 -> 0 | C73: =C64*$AH73 -> 0 | D73: =D64*$AH73 -> 0 | E73: =E64*$AH73 -> 0 | F73: =F64*$AH73 -> 0 | G73: =G64*$AH73 -> 3080 | H73: =H64*$AH73 -> 3115 | I73: =I64*$AH73 -> 4305 | ... AF73: =AF64*$AH73 -> 10143 | AH73: 35 | AI73: lbs/gal | AJ73: 33-40
A74: CCS (mil lbs) | B74: =B65*$AH74 -> 0 | C74: =C65*$AH74 -> 0 | D74: =D65*$AH74 -> 0.019223268 | E74: =E65*$AH74 -> 0.019223268 | F74: =F65*$AH74 -> 7.636602 | G74: =G65*$AH74 -> 8.8777042 | H74: =H65*$AH74 -> 104.99404 | I74: =I65*$AH74 -> 104.99404 | ... AF74: =AF65*$AH74 -> 2876.9892 | AH74: 19.223268 | AI74: lbs/gal | AJ74: 69 grams of CO2 per megajoule of SAF and 1 gallon of SAF is equal to a lower heating value (LHV) of 126.37 megajoules, so 69 g CO2/MJ X 126.37 MJ/gal = 8719.3 g CO2 /gallon and 8719.3 grams / 1000000 g / tonne = 0.00871953 tonnes CO2 per gallon
A75: MSW (mil lbs) | B75: =B66*$AH75 -> 0 | C75: =C66*$AH75 -> 0 | D75: =D66*$AH75 -> 0 | E75: =E66*$AH75 -> 0 | F75: =F66*$AH75 -> 0 | G75: =G66*$AH75 -> 1.4328 | H75: =H66*$AH75 -> 1.4328 | I75: =I66*$AH75 -> 15025.933 | ... AF75: =AF66*$AH75 -> 19762.133 | AH75: 39.8 | AI75: lbs/gal
A77: Corn to SAF Conversions
A78: Ethanol (mil lbs) | B78: =B79*$AH78 -> 661.41853 | C78: =C79*$AH78 -> 661.41853 | D78: =D79*$AH78 -> 661.41853 | E78: =E79*$AH78 -> 661.41853 | F78: =F79*$AH78 -> 760.46623 | G78: =G79*$AH78 -> 794.48636 | H78: =H79*$AH78 -> 3061.5782 | I78: =I79*$AH78 -> 8454.1752 | ... AF78: =AF79*$AH78 -> 11679.168 | AH78: 6.59 | AI78: lbs/gal
A79: Ethanol (mil gal) | B79: =B63*$AH79 -> 100.367 | C79: =C63*$AH79 -> 100.367 | D79: =D63*$AH79 -> 100.367 | E79: =E63*$AH79 -> 100.367 | F79: =F63*$AH79 -> 115.397 | G79: =G63*$AH79 -> 120.55939 | H79: =H63*$AH79 -> 464.57939 | I79: =I63*$AH79 -> 1282.8794 | ... AF79: =AF63*$AH79 -> 1772.2562 | AH79: 1.67 | AI79: gal/gal | AJ79: 1.5-1.7
A80: Corn (mil bu) | B80: =B79*$AH80 -> 36.364855 | C80: =C79*$AH80 -> 36.364855 | D80: =D79*$AH80 -> 36.364855 | E80: =E79*$AH80 -> 36.364855 | F80: =F79*$AH80 -> 41.810507 | G80: =G79*$AH80 -> 43.680937 | H80: =H79*$AH80 -> 168.32587 | I80: =I79*$AH80 -> 464.81137 | ... AF80: =AF79*$AH80 -> 642.12181 | AH80: =1/AH81 -> 0.36231884 | AI80: bu/gal | AJ80: .3704-.3571
AH81: 2.76 | AI81: gal/bu | AJ81: 2.7-2.8
A82: Airline Miles | C82: ='[1]Jet Fuel'!E$17 -> 573403.84 | D82: ='[1]Jet Fuel'!F$17 -> 708959.96 | E82: ='[1]Jet Fuel'!G$17 -> 773411.56 | F82: ='[1]Jet Fuel'!H$17 -> 785786.14 | G82: ='[1]Jet Fuel'!I$17 -> 807002.37 | H82: ='[1]Jet Fuel'!J$17 -> 828791.43 | I82: ='[1]Jet Fuel'!K$17 -> 851168.8 | J82: ='[1]Jet Fuel'!L$17 -> 874150.36 | ... AF82: ='[1]Jet Fuel'!AH$17 -> 1570854.3
A83: Gallons of Fuel per Mile | C83: =C82/C88 -> 2.2708233 | D83: =D82/D88 -> 2.482136 | E83: =E82/E88 -> 2.5555923 | F83: =F82/F88 -> 2.4936488 | G83: =G82/G88 -> 2.5439432 | H83: =H82/H88 -> 2.6003747 | I83: =I82/I88 -> 2.591866 | J83: =J82/J88 -> 2.6054764 | ... AF83: =AF82/AF88 -> 3.0304019
A84: Blending Rate/Mandated
A85: Blending Rate/Possible
A86: Blending Rate Achieved | C86: =C89/C88 -> #REF! | D86: =D89/D88 -> #REF! | E86: =E89/E88 -> #REF! | F86: =F89/F88 -> #REF! | G86: =G89/G88 -> #REF! | H86: =H89/H88 -> #REF! | I86: =I89/I88 -> #REF! | J86: =J89/J88 -> #REF! | ... AF86: =AF89/AF88 -> #REF!
A88: Domestic Jet Fuel Consumption | C88: ='[1]Jet Fuel'!E$81/1000 -> 252509.23 | D88: ='[1]Jet Fuel'!F$81/1000 -> 285624.94 | E88: ='[1]Jet Fuel'!G$81/1000 -> 302634.95 | F88: ='[1]Jet Fuel'!H$81/1000 -> 315115 | G88: ='[1]Jet Fuel'!I$81/1000 -> 317225 | H88: ='[1]Jet Fuel'!J$81/1000 -> 318720 | I88: ='[1]Jet Fuel'!K$81/1000 -> 328400 | J88: ='[1]Jet Fuel'!L$81/1000 -> 335505 | ... AF88: ='[1]Jet Fuel'!AH$81/1000 -> 518365
A89: Domestic SAF Consumption | C89: =#REF!+#REF!-#REF! -> #REF! | D89: =#REF!+#REF!-#REF! -> #REF! | E89: =#REF!+#REF!-#REF! -> #REF! | F89: =#REF!+#REF!-#REF! -> #REF! | G89: =#REF!+#REF!-#REF! -> #REF! | H89: =#REF!+#REF!-#REF! -> #REF! | I89: =#REF!+#REF!-#REF! -> #REF! | J89: =#REF!+#REF!-#REF! -> #REF! | ... AF89: =#REF!+#REF!-#REF! -> #REF!
A91: North American Mandates
A92: =A22 -> (mil gal/yr) | B92: =B22 -> < 2021 | C92: =C22 -> 2021 | D92: =D22 -> 2022 | E92: =E22 -> 2023 | F92: =F22 -> 2024 | G92: =G22 -> 2025 | H92: =H22 -> 2026 | ... AF92: =AF22 -> 2050 | AG92: 2050 | AI92: Goals of the SAF Grand Challenge
A93: US Federal-Level Programs | AI93: 1. Reduce cost of SAF
A94: SAF Grand Challenge | L94: 3000 | AF94: 35000 | AG94: 35000 | AI94: 2. Enhance the sustainability of SAF
A95: US State-Level Programs
A96: Low Carbon Fuel Standard (LCFS) | AI96: 3. Expand the production of SAF
A97: Clean Fuels Program (CFP) | AI97: 4. Reduce life cycle GHG emissions by 50% from conventional fuel by 2030
A98: Clean Fuel Standard (CFS)
A99: Canada Federal-Level Programs
A100: Clean Fuel Regulation (CFR) | L100: =MROUND(1000/3.78541,5) -> 265 | AF100: =MROUND(8000/3.78541,5) -> 2115
A101: Canada Province-Level Programs
A102: British Colombia
A103: CORSIA Programs
A104: SAF Grand Challenge
A105: Total Mandated Volume | B105: =SUM(B100,B96:B98,B94) -> 0 | C105: =SUM(C100,C96:C98,C94) -> 0 | D105: =SUM(D100,D96:D98,D94) -> 0 | E105: =SUM(E100,E96:E98,E94) -> 0 | F105: =SUM(F100,F96:F98,F94) -> 0 | G105: =SUM(G100,G96:G98,G94) -> 0 | H105: =SUM(H100,H96:H98,H94) -> 0 | I105: =SUM(I100,I96:I98,I94) -> 0 | ... Q105: =SUM(Q100,Q96:Q98,Q94) -> 0 | AF105: =SUM(AF100,AF96:AF98,AF94) -> 37115
A106: Notes:
A107: California Air Resources Board (CARB) is proposing an explicit SAF mandate to eliminate the existing exemption for intrastate fossil jet fuel from the LCFS regulations beginning in 2028
A108: The proposed legislation would only apply to intrastate flights, but the requirement would likely apply to intra and interstate flights and international flights
A109: SAF consumption in California totalled 0.3% of LCFS credits sold in 2021(?)
...

Sheet SAm
B1: Location | D1: Notes | H1: Nameplate Capacity
A2: Company | B2: City | C2: Country | D2: Website | E2: Comments | F2: Start Date | G2: Expansion Date | H2: Current Status | I2: % Chance | J2: start-up/operating mmgal/yr | K2: expansion mmgal/yr | L2: t/yr | M2: RD Estimated Nameplate | N2: SAF Estimated Nameplate | O2: RD Expansion | P2: SAF Expansion | Q2: Probability Adjusted RD Nameplate | R2: Probability Adjusted SAF Nameplate | S2: Probability Adjusted RD Expansion | T2: Probability Adjusted SAF Expansion | U2: Energy Technology | V2: Feedstock | W2: New / Old | X2: Investor Relations Sites
A3: Acelen Renewables | B3: Mataripe, Bahia | C3: Brazil | D3: https://www.acelenrenovaveis.com.br/2023/11/30/acelen-and-bahia-government-sign-mou-providing-for-investment-in-an-innovative-energy-transition-project/ | E3: 20,000bbl/d SAF&RD (1bn liters/yr), Verified 500,000 m3/yr - Soybean, corn and macauba (future) | F3: 2027 | H3: Construction late 2024 | I3: 0.75 | J3: 164 | L3: 472000 | M3: =$J3/2 -> 82 | N3: =$J3/2 -> 82 | O3: =$K3/2 -> 0 | P3: =$K3/2 -> 0 | Q3: =M3*$I3 -> 61.5 | R3: =N3*$I3 -> 61.5 | S3: =O3*$I3 -> 0 | T3: =P3*$I3 -> 0 | U3: HEFA | V3: FOGs
A4: Brasil BioFuels (BBF) | B4: Manaus | C4: Brazil | D4: https://www.grupobbf.com.br/en/our-business/biofuels/ | E4: 500mm liters/yr SAF&RD, Verified HEFA production 250,000 m3/yr - Palm, soybean, & corn, possible breakdown? 250 mm liters/yr of HVO and 280 mm liters/yr of SAF | F4: 2026 | H4: Construction | I4: 0.75 | J4: 132 | L4: 400000 | M4: =$J4/2 -> 66 | N4: =$J4/2 -> 66 | O4: =$K4/2 -> 0 | P4: =$K4/2 -> 0 | Q4: =M4*$I4 -> 49.5 | R4: =N4*$I4 -> 49.5 | S4: =O4*$I4 -> 0 | T4: =P4*$I4 -> 0 | U4: HEFA | V4: FOGs
A5: Petrobras | B5: Cubatao | C5: Brazil | D5: https://renewablesnow.com/news/petrobras-contracts-hefa-tech-for-renewable-diesel-saf-844736/, https://www.bnamericas.com/en/news/petrobras-sets-saf-renewable-diesel-output-target | E5: 34,000bbl/d from 2029, Verified 350,000 m3/yr - Soybeans, beef tallow | F5: 2029 | H5: Planned | I5: 0.55 | J5: 91 | L5: 265000 | M5: =$J5/2 -> 45.5 | N5: =$J5/2 -> 45.5 | O5: =$K5/2 -> 0 | P5: =$K5/2 -> 0 | Q5: =M5*$I5 -> 25.025 | R5: =N5*$I5 -> 25.025 | S5: =O5*$I5 -> 0 | T5: =P5*$I5 -> 0 | U5: HEFA | V5: FOGs
A6: Geo Biogas | B6: Sao Paulo | C6: Brazil | D6: https://www.novacana.com/noticias/geo-giz-firmam-parceria-desenvolver-saf-biogas-brasil-101024, https://geobiogas.tech/produto/carbono-renovavel-e-biogenico/ | E6: Pilot 2025 establishing the first Brazilian demo plant to produce 100,000 liters/yr of SAF, commencing operation in 2025. The expected commercial-scale production is 750 liters/d. Using Biogas -- methane project looks to be attached | F6: 2025 | H6: Planned | I6: 0.75 | J6: 0.072 | L6: 219 | M6: 0 | N6: =$J6 -> 0.072 | O6: =$K6/2 -> 0 | P6: =$K6/2 -> 0 | Q6: =M6*$I6 -> 0 | R6: =N6*$I6 -> 0.054 | S6: =O6*$I6 -> 0 | T6: =P6*$I6 -> 0 | U6: FT | V6: Woody Biomass
A7: Refinaria Riograndense | B7: Rio Grande | C7: Brazil | D7: https://www.safinvestor.com/news/146419/topsoe/ | E7: Jointly controlled by Ultrapar Participações (33.3%), Braskem (33.3%) and Petrobras (33.3%), the last two the primary suppliers of raw materials for the company. Produce 16,000 bbl/d of RD and SAF, s/u 1H 2028. Selected Topsoe technology | F7: 2028 | H7: Planned | I7: 0.55 | J7: =16000*42*365/1000000 -> 245.28 | L7: 741860 | M7: =$J7/2 -> 122.64 | N7: =$J7/2 -> 122.64 | O7: =$K7/2 -> 0 | P7: =$K7/2 -> 0 | Q7: =M7*$I7 -> 67.452 | R7: =N7*$I7 -> 67.452 | S7: =O7*$I7 -> 0 | T7: =P7*$I7 -> 0 | U7: HEFA | V7: FOGs
A8: Copec/Ineratec | B8: Patagonia | C8: Chile | D8: https://www.ineratec.de/en/news/ineratec-and-copec-enter-strategic-partnership-spearhead-e-fuel-availability-chile | E8: 3,500t e-fuel | F8: 2031 | H8: Feasibility Study | I8: 0.55 | J8: =L8*347/1000000 -> 1.2145 | L8: 3500 | M8: 0 | N8: =$J8 -> 1.2145 | O8: =$K8/2 -> 0 | P8: =$K8/2 -> 0 | Q8: =M8*$I8 -> 0 | R8: =N8*$I8 -> 0.667975 | S8: =O8*$I8 -> 0 | T8: =P8*$I8 -> 0 | U8: PtL | V8: CCS
A9: BioD/LATAM Airlines | B9: Facatativa or E. Llanos | C9: Colombia | D9: https://aviacionline.com/2023/05/revolutionizing-aviation-in-colombia-latam-airlines-and-bio-d-partner-to-produce-sustainable-fuel/ | E9: Agricultural residuals | F9: 2027 | H9: FEED stage | I9: 0.6 | J9: 50 | L9: 144000 | M9: 0 | N9: =$J9 -> 50 | O9: =$K9/2 -> 0 | P9: =$K9/2 -> 0 | Q9: =M9*$I9 -> 0 | R9: =N9*$I9 -> 30 | S9: =O9*$I9 -> 0 | T9: =P9*$I9 -> 0 | U9: HEFA | V9: FOGs
A10: Ecopetrol | B10: Barrancabermeja | C10: Colombia | D10: https://www.reuters.com/sustainability/colombias-ecopetrol-invest-up-700-million-saf-production-plant-2025-04-02/ | E10: 6,000b/d SAF | F10: 2030 | H10: Planned | I10: 0.4 | J10: =6000*42*365/1000000 -> 91.98 | L10: 265000 | M10: 0 | N10: =J10 -> 91.98 | O10: =$K10/2 -> 0 | P10: =$K10/2 -> 0 | Q10: =M10*$I10 -> 0 | R10: =N10*$I10 -> 36.792 | S10: =O10*$I10 -> 0 | T10: =P10*$I10 -> 0 | U10: HEFA | V10: FOGs
A11: Refineria de Cartagena (Reficar) | B11: Cartagena | C11: Colombia | D11: https://www.ogj.com/refining-processing/refining/optimization/article/55241583/ecopetrol-wraps-testing-for-saf-production-at-cartagena-refinery | E11: Subsidiary of Ecopetrol SA - completed pilot testing, 32,000 bbl of jet fuel with renewable components in 7 days (4,500 b/d), Overall Refinery 210,000 b/d - assume 10% SAF to start) | F11: 2028 | H11: Planned | I11: 0.6 | J11: =450*42*365/1000000 -> 6.8985 | L11: 20000 | M11: 0 | N11: =$J11 -> 6.8985 | O11: =$K11/2 -> 0 | P11: =$K11/2 -> 0 | Q11: =M11*$I11 -> 0 | R11: =N11*$I11 -> 4.1391 | S11: =O11*$I11 -> 0 | T11: =P11*$I11 -> 0 | U11: Co-processing | V11: FOGs
A12: ECB Group -Omega Green project | B12: Villeta | C12: Paraguay | D12: https://www.ecbgroup.com.br/en/group/be8-paraguay/omega-green, https://dialogue.earth/en/business/55157-paraguay-biofuels-build-south-america-largest-plant/, https://www.spglobal.com/commodityinsights/es/oil/refined-products/jetfuel/051822-brazil-saf-mandate-to-target-emissions-reductions-starting-in-2027 | E12: Ômega Green is an integrated project designed to produce a total of 20,000 barrels/day (294 million gallons/year) of Renewable Diesel, Renewable Jet Fuel, and by-products. This facility will use UCO, tallow, and soybean oil that will be transformed via hydrotreating into diesel or jet fuel. | F12: 2025 | H12: Construction | I12: 0.8 | J12: 294 | L12: 890000 | M12: =$J12/2 -> 147 | N12: =$J12/2 -> 147 | O12: =$K12/2 -> 0 | P12: =$K12/2 -> 0 | Q12: =M12*$I12 -> 117.6 | R12: =N12*$I12 -> 117.6 | S12: =O12*$I12 -> 0 | T12: =P12*$I12 -> 0 | U12: HEFA | V12: FOGs
A13: Avalon BioEnergy | C13: Uruguay | D13: https://www.safinvestor.com/news/146026/uruguay/ | E13: Subsidiary of Avalon Energy Group; 50 MW solar power plant to produce green hydrogen - Non-edible oil seed crops & green H2 | F13: 2030 | H13: Announced | I13: 0.55 | J13: =L13*347/1000000 -> 34.7 | L13: 100000 | M13: =$J13/2 -> 17.35 | N13: =$J13/2 -> 17.35 | O13: =$K13/2 -> 0 | P13: =$K13/2 -> 0 | Q13: =M13*$I13 -> 9.5425 | R13: =N13*$I13 -> 9.5425 | S13: =O13*$I13 -> 0 | T13: =P13*$I13 -> 0 | U13: HEFA | V13: FOGs
A14: Eco-Refineries of the South (ERS) project | B14: Chubut | C14: Argentina | D14: https://www.ogj.com/energy-transition/article/55248814/german-developer-argentina-partner-for-large-scale-green-hydrogen-saf-project | E14: PtL + FT unit - uses wind for H2, Targeted for an initial SAF production capacity of 100,000 tpy, the project’s first phase; project’s maximum SAF production capacity of 500,000 tpy, will produce RD (FT processes produce RD as well as SAF) | F14: 2030 | H14: Announced | I14: 0.3 | J14: =L14*347/1000000 -> 34.7 | K14: =500000*347/1000000 -> 173.5 | L14: 100000 | M14: =J14/2 -> 17.35 | N14: =$J14 -> 34.7 | O14: =K14/2 -> 86.75 | P14: =$K14 -> 173.5 | Q14: =M14*$I14 -> 5.205 | R14: =N14*$I14 -> 10.41 | S14: =O14*$I14 -> 26.025 | T14: =P14*$I14 -> 52.05 | U14: PtL | V14: CCS
A15: Grupo Bahia Energia | B15: Bahia Blanca | C15: Argentina | D15: https://www.safinvestor.com/news/146125/argentina/ | E15: Let by subsidiary Biosanfe, No date listed placing it in 2030 per "5 yr schedule" - Bioethanol (corn-based ethanol feed) | F15: 2030 | H15: Announced | I15: 0.3 | J15: =L15*347/1000000 -> 52.05 | L15: 150000 | M15: 0 | N15: =$J15 -> 52.05 | O15: =$K15/2 -> 0 | P15: =$K15/2 -> 0 | Q15: =M15*$I15 -> 0 | R15: =N15*$I15 -> 15.615 | S15: =O15*$I15 -> 0 | T15: =P15*$I15 -> 0 | U15: ATJ | V15: Ethanol
A16: IF YOU ADD NEW PLANTS, PLEASE ADD A ROW ABOVE THIS LINE. THAT WAY THE CAPACITY SUMMATIONS ON THE CAPACITY DATA TAB WILL CONTINUE TO WORK

Sheet SAm Capacity Data
A1: South American Sustainable Aviation Fuel Production Capacity
A2: (mil gal/yr) | B2: < 2021 | C2: 2021 | D2: 2022 | E2: 2023 | F2: 2024 | G2: 2025 | H2: 2026 | I2: 2027 | J2: 2028 | K2: 2029 | L2: 2030 | M2: 2031 | N2: 2032 | O2: 2033 | P2: 2034 | Q2: 2035 | R2: 2036 | S2: 2037 | T2: 2038 | U2: 2039 | V2: 2040 | W2: 2041 | X2: 2042 | Y2: 2043 | Z2: 2044 | AA2: 2045 | AB2: 2046 | AC2: 2047 | AD2: 2048 | AE2: 2049 | AF2: 2050
A3: HEFA | B3: =SUMIFS(SAm!$R$3:$R$79,SAm!$F$3:$F$79,"<"&'SAm Capacity Data'!C$2,SAm!$U$3:$U$79,'SAm Capacity Data'!$A3)+SUMIFS(SAm!$T$3:$T$79,SAm!$F$3:$F$79,"<"&'SAm Capacity Data'!C$2,SAm!$U$3:$U$79,'SAm Capacity Data'!$A3) -> 0 | C3: =SUMIFS(SAm!$R$3:$R$79,SAm!$F$3:$F$79,'SAm Capacity Data'!C$2,SAm!$U$3:$U$79,'SAm Capacity Data'!$A3)+SUMIFS(SAm!$T$3:$T$79,SAm!$F$3:$F$79,'SAm Capacity Data'!C$22,SAm!$U$3:$U$79,'SAm Capacity Data'!$A3) -> 0 | D3: =SUMIFS(SAm!$R$3:$R$79,SAm!$F$3:$F$79,'SAm Capacity Data'!D$2,SAm!$U$3:$U$79,'SAm Capacity Data'!$A3)+SUMIFS(SAm!$T$3:$T$79,SAm!$F$3:$F$79,'SAm Capacity Data'!D$22,SAm!$U$3:$U$79,'SAm Capacity Data'!$A3) -> 0 | E3: =SUMIFS(SAm!$R$3:$R$79,SAm!$F$3:$F$79,'SAm Capacity Data'!E$2,SAm!$U$3:$U$79,'SAm Capacity Data'!$A3)+SUMIFS(SAm!$T$3:$T$79,SAm!$F$3:$F$79,'SAm Capacity Data'!E$22,SAm!$U$3:$U$79,'SAm Capacity Data'!$A3) -> 0 | F3: =SUMIFS(SAm!$R$3:$R$79,SAm!$F$3:$F$79,'SAm Capacity Data'!F$2,SAm!$U$3:$U$79,'SAm Capacity Data'!$A3)+SUMIFS(SAm!$T$3:$T$79,SAm!$F$3:$F$79,'SAm Capacity Data'!F$22,SAm!$U$3:$U$79,'SAm Capacity Data'!$A3) -> 0 | G3: =SUMIFS(SAm!$R$3:$R$79,SAm!$F$3:$F$79,'SAm Capacity Data'!G$2,SAm!$U$3:$U$79,'SAm Capacity Data'!$A3)+SUMIFS(SAm!$T$3:$T$79,SAm!$F$3:$F$79,'SAm Capacity Data'!G$22,SAm!$U$3:$U$79,'SAm Capacity Data'!$A3) -> 117.6 | H3: =SUMIFS(SAm!$R$3:$R$79,SAm!$F$3:$F$79,'SAm Capacity Data'!H$2,SAm!$U$3:$U$79,'SAm Capacity Data'!$A3)+SUMIFS(SAm!$T$3:$T$79,SAm!$F$3:$F$79,'SAm Capacity Data'!H$22,SAm!$U$3:$U$79,'SAm Capacity Data'!$A3) -> 49.5 | I3: =SUMIFS(SAm!$R$3:$R$79,SAm!$F$3:$F$79,'SAm Capacity Data'!I$2,SAm!$U$3:$U$79,'SAm Capacity Data'!$A3)+SUMIFS(SAm!$T$3:$T$79,SAm!$F$3:$F$79,'SAm Capacity Data'!I$22,SAm!$U$3:$U$79,'SAm Capacity Data'!$A3) -> 91.5 | J3: =SUMIFS(SAm!$R$3:$R$79,SAm!$F$3:$F$79,'SAm Capacity Data'!J$2,SAm!$U$3:$U$79,'SAm Capacity Data'!$A3)+SUMIFS(SAm!$T$3:$T$79,SAm!$F$3:$F$79,'SAm Capacity Data'!J$22,SAm!$U$3:$U$79,'SAm Capacity Data'!$A3) -> 67.452 | ... AF3: =SUMIFS(SAm!$R$3:$R$79,SAm!$F$3:$F$79,'SAm Capacity Data'!AF$2,SAm!$U$3:$U$79,'SAm Capacity Data'!$A3)+SUMIFS(SAm!$T$3:$T$79,SAm!$F$3:$F$79,'SAm Capacity Data'!AF$22,SAm!$U$3:$U$79,'SAm Capacity Data'!$A3) -> 0
A4: ATJ | B4: =SUMIFS(SAm!$R$3:$R$79,SAm!$F$3:$F$79,"<"&'SAm Capacity Data'!C$2,SAm!$U$3:$U$79,'SAm Capacity Data'!$A4)+SUMIFS(SAm!$T$3:$T$79,SAm!$F$3:$F$79,"<"&'SAm Capacity Data'!C$2,SAm!$U$3:$U$79,'SAm Capacity Data'!$A4) -> 0 | C4: =SUMIFS(SAm!$R$3:$R$79,SAm!$F$3:$F$79,'SAm Capacity Data'!C$2,SAm!$U$3:$U$79,'SAm Capacity Data'!$A4)+SUMIFS(SAm!$T$3:$T$79,SAm!$F$3:$F$79,'SAm Capacity Data'!C$22,SAm!$U$3:$U$79,'SAm Capacity Data'!$A4) -> 0 | D4: =SUMIFS(SAm!$R$3:$R$79,SAm!$F$3:$F$79,'SAm Capacity Data'!D$2,SAm!$U$3:$U$79,'SAm Capacity Data'!$A4)+SUMIFS(SAm!$T$3:$T$79,SAm!$F$3:$F$79,'SAm Capacity Data'!D$22,SAm!$U$3:$U$79,'SAm Capacity Data'!$A4) -> 0 | E4: =SUMIFS(SAm!$R$3:$R$79,SAm!$F$3:$F$79,'SAm Capacity Data'!E$2,SAm!$U$3:$U$79,'SAm Capacity Data'!$A4)+SUMIFS(SAm!$T$3:$T$79,SAm!$F$3:$F$79,'SAm Capacity Data'!E$22,SAm!$U$3:$U$79,'SAm Capacity Data'!$A4) -> 0 | F4: =SUMIFS(SAm!$R$3:$R$79,SAm!$F$3:$F$79,'SAm Capacity Data'!F$2,SAm!$U$3:$U$79,'SAm Capacity Data'!$A4)+SUMIFS(SAm!$T$3:$T$79,SAm!$F$3:$F$79,'SAm Capacity Data'!F$22,SAm!$U$3:$U$79,'SAm Capacity Data'!$A4) -> 0 | G4: =SUMIFS(SAm!$R$3:$R$79,SAm!$F$3:$F$79,'SAm Capacity Data'!G$2,SAm!$U$3:$U$79,'SAm Capacity Data'!$A4)+SUMIFS(SAm!$T$3:$T$79,SAm!$F$3:$F$79,'SAm Capacity Data'!G$22,SAm!$U$3:$U$79,'SAm Capacity Data'!$A4) -> 0 | H4: =SUMIFS(SAm!$R$3:$R$79,SAm!$F$3:$F$79,'SAm Capacity Data'!H$2,SAm!$U$3:$U$79,'SAm Capacity Data'!$A4)+SUMIFS(SAm!$T$3:$T$79,SAm!$F$3:$F$79,'SAm Capacity Data'!H$22,SAm!$U$3:$U$79,'SAm Capacity Data'!$A4) -> 0 | I4: =SUMIFS(SAm!$R$3:$R$79,SAm!$F$3:$F$79,'SAm Capacity Data'!I$2,SAm!$U$3:$U$79,'SAm Capacity Data'!$A4)+SUMIFS(SAm!$T$3:$T$79,SAm!$F$3:$F$79,'SAm Capacity Data'!I$22,SAm!$U$3:$U$79,'SAm Capacity Data'!$A4) -> 0 | J4: =SUMIFS(SAm!$R$3:$R$79,SAm!$F$3:$F$79,'SAm Capacity Data'!J$2,SAm!$U$3:$U$79,'SAm Capacity Data'!$A4)+SUMIFS(SAm!$T$3:$T$79,SAm!$F$3:$F$79,'SAm Capacity Data'!J$22,SAm!$U$3:$U$79,'SAm Capacity Data'!$A4) -> 0 | ... AF4: =SUMIFS(SAm!$R$3:$R$79,SAm!$F$3:$F$79,'SAm Capacity Data'!AF$2,SAm!$U$3:$U$79,'SAm Capacity Data'!$A4)+SUMIFS(SAm!$T$3:$T$79,SAm!$F$3:$F$79,'SAm Capacity Data'!AF$22,SAm!$U$3:$U$79,'SAm Capacity Data'!$A4) -> 0
A5: FT | B5: =SUMIFS(SAm!$R$3:$R$79,SAm!$F$3:$F$79,"<"&'SAm Capacity Data'!C$2,SAm!$U$3:$U$79,'SAm Capacity Data'!$A5)+SUMIFS(SAm!$T$3:$T$79,SAm!$F$3:$F$79,"<"&'SAm Capacity Data'!C$2,SAm!$U$3:$U$79,'SAm Capacity Data'!$A5) -> 0 | C5: =SUMIFS(SAm!$R$3:$R$79,SAm!$F$3:$F$79,'SAm Capacity Data'!C$2,SAm!$U$3:$U$79,'SAm Capacity Data'!$A5)+SUMIFS(SAm!$T$3:$T$79,SAm!$F$3:$F$79,'SAm Capacity Data'!C$22,SAm!$U$3:$U$79,'SAm Capacity Data'!$A5) -> 0 | D5: =SUMIFS(SAm!$R$3:$R$79,SAm!$F$3:$F$79,'SAm Capacity Data'!D$2,SAm!$U$3:$U$79,'SAm Capacity Data'!$A5)+SUMIFS(SAm!$T$3:$T$79,SAm!$F$3:$F$79,'SAm Capacity Data'!D$22,SAm!$U$3:$U$79,'SAm Capacity Data'!$A5) -> 0 | E5: =SUMIFS(SAm!$R$3:$R$79,SAm!$F$3:$F$79,'SAm Capacity Data'!E$2,SAm!$U$3:$U$79,'SAm Capacity Data'!$A5)+SUMIFS(SAm!$T$3:$T$79,SAm!$F$3:$F$79,'SAm Capacity Data'!E$22,SAm!$U$3:$U$79,'SAm Capacity Data'!$A5) -> 0 | F5: =SUMIFS(SAm!$R$3:$R$79,SAm!$F$3:$F$79,'SAm Capacity Data'!F$2,SAm!$U$3:$U$79,'SAm Capacity Data'!$A5)+SUMIFS(SAm!$T$3:$T$79,SAm!$F$3:$F$79,'SAm Capacity Data'!F$22,SAm!$U$3:$U$79,'SAm Capacity Data'!$A5) -> 0 | G5: =SUMIFS(SAm!$R$3:$R$79,SAm!$F$3:$F$79,'SAm Capacity Data'!G$2,SAm!$U$3:$U$79,'SAm Capacity Data'!$A5)+SUMIFS(SAm!$T$3:$T$79,SAm!$F$3:$F$79,'SAm Capacity Data'!G$22,SAm!$U$3:$U$79,'SAm Capacity Data'!$A5) -> 0.054 | H5: =SUMIFS(SAm!$R$3:$R$79,SAm!$F$3:$F$79,'SAm Capacity Data'!H$2,SAm!$U$3:$U$79,'SAm Capacity Data'!$A5)+SUMIFS(SAm!$T$3:$T$79,SAm!$F$3:$F$79,'SAm Capacity Data'!H$22,SAm!$U$3:$U$79,'SAm Capacity Data'!$A5) -> 0 | I5: =SUMIFS(SAm!$R$3:$R$79,SAm!$F$3:$F$79,'SAm Capacity Data'!I$2,SAm!$U$3:$U$79,'SAm Capacity Data'!$A5)+SUMIFS(SAm!$T$3:$T$79,SAm!$F$3:$F$79,'SAm Capacity Data'!I$22,SAm!$U$3:$U$79,'SAm Capacity Data'!$A5) -> 0 | J5: =SUMIFS(SAm!$R$3:$R$79,SAm!$F$3:$F$79,'SAm Capacity Data'!J$2,SAm!$U$3:$U$79,'SAm Capacity Data'!$A5)+SUMIFS(SAm!$T$3:$T$79,SAm!$F$3:$F$79,'SAm Capacity Data'!J$22,SAm!$U$3:$U$79,'SAm Capacity Data'!$A5) -> 0 | ... AF5: =SUMIFS(SAm!$R$3:$R$79,SAm!$F$3:$F$79,'SAm Capacity Data'!AF$2,SAm!$U$3:$U$79,'SAm Capacity Data'!$A5)+SUMIFS(SAm!$T$3:$T$79,SAm!$F$3:$F$79,'SAm Capacity Data'!AF$22,SAm!$U$3:$U$79,'SAm Capacity Data'!$A5) -> 0
A6: PTL | B6: =SUMIFS(SAm!$R$3:$R$79,SAm!$F$3:$F$79,"<"&'SAm Capacity Data'!C$2,SAm!$U$3:$U$79,'SAm Capacity Data'!$A6)+SUMIFS(SAm!$T$3:$T$79,SAm!$F$3:$F$79,"<"&'SAm Capacity Data'!C$2,SAm!$U$3:$U$79,'SAm Capacity Data'!$A6) -> 0 | C6: =SUMIFS(SAm!$R$3:$R$79,SAm!$F$3:$F$79,'SAm Capacity Data'!C$2,SAm!$U$3:$U$79,'SAm Capacity Data'!$A6)+SUMIFS(SAm!$T$3:$T$79,SAm!$F$3:$F$79,'SAm Capacity Data'!C$22,SAm!$U$3:$U$79,'SAm Capacity Data'!$A6) -> 0 | D6: =SUMIFS(SAm!$R$3:$R$79,SAm!$F$3:$F$79,'SAm Capacity Data'!D$2,SAm!$U$3:$U$79,'SAm Capacity Data'!$A6)+SUMIFS(SAm!$T$3:$T$79,SAm!$F$3:$F$79,'SAm Capacity Data'!D$22,SAm!$U$3:$U$79,'SAm Capacity Data'!$A6) -> 0 | E6: =SUMIFS(SAm!$R$3:$R$79,SAm!$F$3:$F$79,'SAm Capacity Data'!E$2,SAm!$U$3:$U$79,'SAm Capacity Data'!$A6)+SUMIFS(SAm!$T$3:$T$79,SAm!$F$3:$F$79,'SAm Capacity Data'!E$22,SAm!$U$3:$U$79,'SAm Capacity Data'!$A6) -> 0 | F6: =SUMIFS(SAm!$R$3:$R$79,SAm!$F$3:$F$79,'SAm Capacity Data'!F$2,SAm!$U$3:$U$79,'SAm Capacity Data'!$A6)+SUMIFS(SAm!$T$3:$T$79,SAm!$F$3:$F$79,'SAm Capacity Data'!F$22,SAm!$U$3:$U$79,'SAm Capacity Data'!$A6) -> 0 | G6: =SUMIFS(SAm!$R$3:$R$79,SAm!$F$3:$F$79,'SAm Capacity Data'!G$2,SAm!$U$3:$U$79,'SAm Capacity Data'!$A6)+SUMIFS(SAm!$T$3:$T$79,SAm!$F$3:$F$79,'SAm Capacity Data'!G$22,SAm!$U$3:$U$79,'SAm Capacity Data'!$A6) -> 0 | H6: =SUMIFS(SAm!$R$3:$R$79,SAm!$F$3:$F$79,'SAm Capacity Data'!H$2,SAm!$U$3:$U$79,'SAm Capacity Data'!$A6)+SUMIFS(SAm!$T$3:$T$79,SAm!$F$3:$F$79,'SAm Capacity Data'!H$22,SAm!$U$3:$U$79,'SAm Capacity Data'!$A6) -> 0 | I6: =SUMIFS(SAm!$R$3:$R$79,SAm!$F$3:$F$79,'SAm Capacity Data'!I$2,SAm!$U$3:$U$79,'SAm Capacity Data'!$A6)+SUMIFS(SAm!$T$3:$T$79,SAm!$F$3:$F$79,'SAm Capacity Data'!I$22,SAm!$U$3:$U$79,'SAm Capacity Data'!$A6) -> 0 | J6: =SUMIFS(SAm!$R$3:$R$79,SAm!$F$3:$F$79,'SAm Capacity Data'!J$2,SAm!$U$3:$U$79,'SAm Capacity Data'!$A6)+SUMIFS(SAm!$T$3:$T$79,SAm!$F$3:$F$79,'SAm Capacity Data'!J$22,SAm!$U$3:$U$79,'SAm Capacity Data'!$A6) -> 0 | ... AF6: =SUMIFS(SAm!$R$3:$R$79,SAm!$F$3:$F$79,'SAm Capacity Data'!AF$2,SAm!$U$3:$U$79,'SAm Capacity Data'!$A6)+SUMIFS(SAm!$T$3:$T$79,SAm!$F$3:$F$79,'SAm Capacity Data'!AF$22,SAm!$U$3:$U$79,'SAm Capacity Data'!$A6) -> 0
A7: Pyrolysis | B7: =SUMIFS(SAm!$R$3:$R$79,SAm!$F$3:$F$79,"<"&'SAm Capacity Data'!C$2,SAm!$U$3:$U$79,'SAm Capacity Data'!$A7)+SUMIFS(SAm!$T$3:$T$79,SAm!$F$3:$F$79,"<"&'SAm Capacity Data'!C$2,SAm!$U$3:$U$79,'SAm Capacity Data'!$A7) -> 0 | C7: =SUMIFS(SAm!$R$3:$R$79,SAm!$F$3:$F$79,'SAm Capacity Data'!C$2,SAm!$U$3:$U$79,'SAm Capacity Data'!$A7)+SUMIFS(SAm!$T$3:$T$79,SAm!$F$3:$F$79,'SAm Capacity Data'!C$22,SAm!$U$3:$U$79,'SAm Capacity Data'!$A7) -> 0 | D7: =SUMIFS(SAm!$R$3:$R$79,SAm!$F$3:$F$79,'SAm Capacity Data'!D$2,SAm!$U$3:$U$79,'SAm Capacity Data'!$A7)+SUMIFS(SAm!$T$3:$T$79,SAm!$F$3:$F$79,'SAm Capacity Data'!D$22,SAm!$U$3:$U$79,'SAm Capacity Data'!$A7) -> 0 | E7: =SUMIFS(SAm!$R$3:$R$79,SAm!$F$3:$F$79,'SAm Capacity Data'!E$2,SAm!$U$3:$U$79,'SAm Capacity Data'!$A7)+SUMIFS(SAm!$T$3:$T$79,SAm!$F$3:$F$79,'SAm Capacity Data'!E$22,SAm!$U$3:$U$79,'SAm Capacity Data'!$A7) -> 0 | F7: =SUMIFS(SAm!$R$3:$R$79,SAm!$F$3:$F$79,'SAm Capacity Data'!F$2,SAm!$U$3:$U$79,'SAm Capacity Data'!$A7)+SUMIFS(SAm!$T$3:$T$79,SAm!$F$3:$F$79,'SAm Capacity Data'!F$22,SAm!$U$3:$U$79,'SAm Capacity Data'!$A7) -> 0 | G7: =SUMIFS(SAm!$R$3:$R$79,SAm!$F$3:$F$79,'SAm Capacity Data'!G$2,SAm!$U$3:$U$79,'SAm Capacity Data'!$A7)+SUMIFS(SAm!$T$3:$T$79,SAm!$F$3:$F$79,'SAm Capacity Data'!G$22,SAm!$U$3:$U$79,'SAm Capacity Data'!$A7) -> 0 | H7: =SUMIFS(SAm!$R$3:$R$79,SAm!$F$3:$F$79,'SAm Capacity Data'!H$2,SAm!$U$3:$U$79,'SAm Capacity Data'!$A7)+SUMIFS(SAm!$T$3:$T$79,SAm!$F$3:$F$79,'SAm Capacity Data'!H$22,SAm!$U$3:$U$79,'SAm Capacity Data'!$A7) -> 0 | I7: =SUMIFS(SAm!$R$3:$R$79,SAm!$F$3:$F$79,'SAm Capacity Data'!I$2,SAm!$U$3:$U$79,'SAm Capacity Data'!$A7)+SUMIFS(SAm!$T$3:$T$79,SAm!$F$3:$F$79,'SAm Capacity Data'!I$22,SAm!$U$3:$U$79,'SAm Capacity Data'!$A7) -> 0 | J7: =SUMIFS(SAm!$R$3:$R$79,SAm!$F$3:$F$79,'SAm Capacity Data'!J$2,SAm!$U$3:$U$79,'SAm Capacity Data'!$A7)+SUMIFS(SAm!$T$3:$T$79,SAm!$F$3:$F$79,'SAm Capacity Data'!J$22,SAm!$U$3:$U$79,'SAm Capacity Data'!$A7) -> 0 | ... AF7: =SUMIFS(SAm!$R$3:$R$79,SAm!$F$3:$F$79,'SAm Capacity Data'!AF$2,SAm!$U$3:$U$79,'SAm Capacity Data'!$A7)+SUMIFS(SAm!$T$3:$T$79,SAm!$F$3:$F$79,'SAm Capacity Data'!AF$22,SAm!$U$3:$U$79,'SAm Capacity Data'!$A7) -> 0
A8: Co-Processing | B8: =SUMIFS(SAm!$R$3:$R$79,SAm!$F$3:$F$79,"<"&'SAm Capacity Data'!C$2,SAm!$U$3:$U$79,'SAm Capacity Data'!$A8)+SUMIFS(SAm!$T$3:$T$79,SAm!$F$3:$F$79,"<"&'SAm Capacity Data'!C$2,SAm!$U$3:$U$79,'SAm Capacity Data'!$A8) -> 0 | C8: =SUMIFS(SAm!$R$3:$R$79,SAm!$F$3:$F$79,'SAm Capacity Data'!C$2,SAm!$U$3:$U$79,'SAm Capacity Data'!$A8)+SUMIFS(SAm!$T$3:$T$79,SAm!$F$3:$F$79,'SAm Capacity Data'!C$22,SAm!$U$3:$U$79,'SAm Capacity Data'!$A8) -> 0 | D8: =SUMIFS(SAm!$R$3:$R$79,SAm!$F$3:$F$79,'SAm Capacity Data'!D$2,SAm!$U$3:$U$79,'SAm Capacity Data'!$A8)+SUMIFS(SAm!$T$3:$T$79,SAm!$F$3:$F$79,'SAm Capacity Data'!D$22,SAm!$U$3:$U$79,'SAm Capacity Data'!$A8) -> 0 | E8: =SUMIFS(SAm!$R$3:$R$79,SAm!$F$3:$F$79,'SAm Capacity Data'!E$2,SAm!$U$3:$U$79,'SAm Capacity Data'!$A8)+SUMIFS(SAm!$T$3:$T$79,SAm!$F$3:$F$79,'SAm Capacity Data'!E$22,SAm!$U$3:$U$79,'SAm Capacity Data'!$A8) -> 0 | F8: =SUMIFS(SAm!$R$3:$R$79,SAm!$F$3:$F$79,'SAm Capacity Data'!F$2,SAm!$U$3:$U$79,'SAm Capacity Data'!$A8)+SUMIFS(SAm!$T$3:$T$79,SAm!$F$3:$F$79,'SAm Capacity Data'!F$22,SAm!$U$3:$U$79,'SAm Capacity Data'!$A8) -> 0 | G8: =SUMIFS(SAm!$R$3:$R$79,SAm!$F$3:$F$79,'SAm Capacity Data'!G$2,SAm!$U$3:$U$79,'SAm Capacity Data'!$A8)+SUMIFS(SAm!$T$3:$T$79,SAm!$F$3:$F$79,'SAm Capacity Data'!G$22,SAm!$U$3:$U$79,'SAm Capacity Data'!$A8) -> 0 | H8: =SUMIFS(SAm!$R$3:$R$79,SAm!$F$3:$F$79,'SAm Capacity Data'!H$2,SAm!$U$3:$U$79,'SAm Capacity Data'!$A8)+SUMIFS(SAm!$T$3:$T$79,SAm!$F$3:$F$79,'SAm Capacity Data'!H$22,SAm!$U$3:$U$79,'SAm Capacity Data'!$A8) -> 0 | I8: =SUMIFS(SAm!$R$3:$R$79,SAm!$F$3:$F$79,'SAm Capacity Data'!I$2,SAm!$U$3:$U$79,'SAm Capacity Data'!$A8)+SUMIFS(SAm!$T$3:$T$79,SAm!$F$3:$F$79,'SAm Capacity Data'!I$22,SAm!$U$3:$U$79,'SAm Capacity Data'!$A8) -> 0 | J8: =SUMIFS(SAm!$R$3:$R$79,SAm!$F$3:$F$79,'SAm Capacity Data'!J$2,SAm!$U$3:$U$79,'SAm Capacity Data'!$A8)+SUMIFS(SAm!$T$3:$T$79,SAm!$F$3:$F$79,'SAm Capacity Data'!J$22,SAm!$U$3:$U$79,'SAm Capacity Data'!$A8) -> 4.1391 | ... AF8: =SUMIFS(SAm!$R$3:$R$79,SAm!$F$3:$F$79,'SAm Capacity Data'!AF$2,SAm!$U$3:$U$79,'SAm Capacity Data'!$A8)+SUMIFS(SAm!$T$3:$T$79,SAm!$F$3:$F$79,'SAm Capacity Data'!AF$22,SAm!$U$3:$U$79,'SAm Capacity Data'!$A8) -> 0
A9: Total Capacity | B9: =SUM(B3:B8) -> 0 | C9: =SUM(C3:C8) -> 0 | D9: =SUM(D3:D8) -> 0 | E9: =SUM(E3:E8) -> 0 | F9: =SUM(F3:F8) -> 0 | G9: =SUM(G3:G8) -> 117.654 | H9: =SUM(H3:H8) -> 49.5 | I9: =SUM(I3:I8) -> 91.5 | ... AF9: =SUM(AF3:AF8) -> 0
A11: South American Cumulative Probability Adjusted SAF Capacity
A12: (mil gal/yr) | B12: =B2 -> < 2021 | C12: =C2 -> 2021 | D12: =D2 -> 2022 | E12: =E2 -> 2023 | F12: =F2 -> 2024 | G12: =G2 -> 2025 | H12: =H2 -> 2026 | I12: =I2 -> 2027 | ... AF12: =AF2 -> 2050
A13: HEFA | B13: =B3 -> 0 | C13: =B13+C3 -> 0 | D13: =C13+D3 -> 0 | E13: =D13+E3 -> 0 | F13: =E13+F3 -> 0 | G13: =F13+G3 -> 117.6 | H13: =G13+H3 -> 167.1 | I13: =H13+I3 -> 258.6 | J13: =I13+J3 -> 326.052 | ... AF13: =AE13+AF3 -> 397.4115
A14: ATJ | B14: =B4 -> 0 | C14: =B14+C4 -> 0 | D14: =C14+D4 -> 0 | E14: =D14+E4 -> 0 | F14: =E14+F4 -> 0 | G14: =F14+G4 -> 0 | H14: =G14+H4 -> 0 | I14: =H14+I4 -> 0 | J14: =I14+J4 -> 0 | ... AF14: =AE14+AF4 -> 15.615
A15: FT | B15: =B5 -> 0 | C15: =B15+C5 -> 0 | D15: =C15+D5 -> 0 | E15: =D15+E5 -> 0 | F15: =E15+F5 -> 0 | G15: =F15+G5 -> 0.054 | H15: =G15+H5 -> 0.054 | I15: =H15+I5 -> 0.054 | J15: =I15+J5 -> 0.054 | ... AF15: =AE15+AF5 -> 0.054
A16: PTL | B16: =B6 -> 0 | C16: =B16+C6 -> 0 | D16: =C16+D6 -> 0 | E16: =D16+E6 -> 0 | F16: =E16+F6 -> 0 | G16: =F16+G6 -> 0 | H16: =G16+H6 -> 0 | I16: =H16+I6 -> 0 | J16: =I16+J6 -> 0 | ... AF16: =AE16+AF6 -> 63.127975
A17: Pyrolysis | B17: =B7 -> 0 | C17: =B17+C7 -> 0 | D17: =C17+D7 -> 0 | E17: =D17+E7 -> 0 | F17: =E17+F7 -> 0 | G17: =F17+G7 -> 0 | H17: =G17+H7 -> 0 | I17: =H17+I7 -> 0 | J17: =I17+J7 -> 0 | ... AF17: =AE17+AF7 -> 0
A18: Co-Processing | B18: =B8 -> 0 | C18: =B18+C8 -> 0 | D18: =C18+D8 -> 0 | E18: =D18+E8 -> 0 | F18: =E18+F8 -> 0 | G18: =F18+G8 -> 0 | H18: =G18+H8 -> 0 | I18: =H18+I8 -> 0 | J18: =I18+J8 -> 4.1391 | ... AF18: =AE18+AF8 -> 4.1391
A19: Total Capacity | B19: =SUM(B13:B18) -> 0 | C19: =SUM(C13:C18) -> 0 | D19: =SUM(D13:D18) -> 0 | E19: =SUM(E13:E18) -> 0 | F19: =SUM(F13:F18) -> 0 | G19: =SUM(G13:G18) -> 117.654 | H19: =SUM(H13:H18) -> 167.154 | I19: =SUM(I13:I18) -> 258.654 | ... AF19: =SUM(AF13:AF18) -> 480.34757
A21: South American Announced SAF Capacity
A22: (mil gal/yr) | B22: =B2 -> < 2021 | C22: =C2 -> 2021 | D22: =D2 -> 2022 | E22: =E2 -> 2023 | F22: =F2 -> 2024 | G22: =G2 -> 2025 | H22: =H2 -> 2026 | I22: =I2 -> 2027 | ... AF22: =AF2 -> 2050
A23: HEFA | B23: =SUMIFS(SAm!$N$3:$N$79,SAm!$F$3:$F$79,"<"&'SAm Capacity Data'!C$22,SAm!$U$3:$U$79,'SAm Capacity Data'!$A23)+SUMIFS(SAm!$P$3:$P$79,SAm!$F$3:$F$79,"<"&'SAm Capacity Data'!C$22,SAm!$U$3:$U$79,'SAm Capacity Data'!$A23) -> 0 | C23: =SUMIFS(SAm!$N$3:$N$79,SAm!$F$3:$F$79,'SAm Capacity Data'!C$22,SAm!$U$3:$U$79,'SAm Capacity Data'!$A23)+SUMIFS(SAm!$P$3:$P$79,SAm!$F$3:$F$79,'SAm Capacity Data'!C$22,SAm!$U$3:$U$79,'SAm Capacity Data'!$A23) -> 0 | D23: =SUMIFS(SAm!$N$3:$N$79,SAm!$F$3:$F$79,'SAm Capacity Data'!D$22,SAm!$U$3:$U$79,'SAm Capacity Data'!$A23)+SUMIFS(SAm!$P$3:$P$79,SAm!$F$3:$F$79,'SAm Capacity Data'!D$22,SAm!$U$3:$U$79,'SAm Capacity Data'!$A23) -> 0 | E23: =SUMIFS(SAm!$N$3:$N$79,SAm!$F$3:$F$79,'SAm Capacity Data'!E$22,SAm!$U$3:$U$79,'SAm Capacity Data'!$A23)+SUMIFS(SAm!$P$3:$P$79,SAm!$F$3:$F$79,'SAm Capacity Data'!E$22,SAm!$U$3:$U$79,'SAm Capacity Data'!$A23) -> 0 | F23: =SUMIFS(SAm!$N$3:$N$79,SAm!$F$3:$F$79,'SAm Capacity Data'!F$22,SAm!$U$3:$U$79,'SAm Capacity Data'!$A23)+SUMIFS(SAm!$P$3:$P$79,SAm!$F$3:$F$79,'SAm Capacity Data'!F$22,SAm!$U$3:$U$79,'SAm Capacity Data'!$A23) -> 0 | G23: =SUMIFS(SAm!$N$3:$N$79,SAm!$F$3:$F$79,'SAm Capacity Data'!G$22,SAm!$U$3:$U$79,'SAm Capacity Data'!$A23)+SUMIFS(SAm!$P$3:$P$79,SAm!$F$3:$F$79,'SAm Capacity Data'!G$22,SAm!$U$3:$U$79,'SAm Capacity Data'!$A23) -> 147 | H23: =SUMIFS(SAm!$N$3:$N$79,SAm!$F$3:$F$79,'SAm Capacity Data'!H$22,SAm!$U$3:$U$79,'SAm Capacity Data'!$A23)+SUMIFS(SAm!$P$3:$P$79,SAm!$F$3:$F$79,'SAm Capacity Data'!H$22,SAm!$U$3:$U$79,'SAm Capacity Data'!$A23) -> 66 | I23: =SUMIFS(SAm!$N$3:$N$79,SAm!$F$3:$F$79,'SAm Capacity Data'!I$22,SAm!$U$3:$U$79,'SAm Capacity Data'!$A23)+SUMIFS(SAm!$P$3:$P$79,SAm!$F$3:$F$79,'SAm Capacity Data'!I$22,SAm!$U$3:$U$79,'SAm Capacity Data'!$A23) -> 132 | J23: =SUMIFS(SAm!$N$3:$N$79,SAm!$F$3:$F$79,'SAm Capacity Data'!J$22,SAm!$U$3:$U$79,'SAm Capacity Data'!$A23)+SUMIFS(SAm!$P$3:$P$79,SAm!$F$3:$F$79,'SAm Capacity Data'!J$22,SAm!$U$3:$U$79,'SAm Capacity Data'!$A23) -> 122.64 | ... AF23: =SUMIFS(SAm!$N$3:$N$79,SAm!$F$3:$F$79,'SAm Capacity Data'!AF$22,SAm!$U$3:$U$79,'SAm Capacity Data'!$A23)+SUMIFS(SAm!$P$3:$P$79,SAm!$F$3:$F$79,'SAm Capacity Data'!AF$22,SAm!$U$3:$U$79,'SAm Capacity Data'!$A23) -> 0
A24: ATJ | B24: =SUMIFS(SAm!$N$3:$N$79,SAm!$F$3:$F$79,"<"&'SAm Capacity Data'!C$22,SAm!$U$3:$U$79,'SAm Capacity Data'!$A24)+SUMIFS(SAm!$P$3:$P$79,SAm!$F$3:$F$79,"<"&'SAm Capacity Data'!C$22,SAm!$U$3:$U$79,'SAm Capacity Data'!$A24) -> 0 | C24: =SUMIFS(SAm!$N$3:$N$79,SAm!$F$3:$F$79,'SAm Capacity Data'!C$22,SAm!$U$3:$U$79,'SAm Capacity Data'!$A24)+SUMIFS(SAm!$P$3:$P$79,SAm!$F$3:$F$79,'SAm Capacity Data'!C$22,SAm!$U$3:$U$79,'SAm Capacity Data'!$A24) -> 0 | D24: =SUMIFS(SAm!$N$3:$N$79,SAm!$F$3:$F$79,'SAm Capacity Data'!D$22,SAm!$U$3:$U$79,'SAm Capacity Data'!$A24)+SUMIFS(SAm!$P$3:$P$79,SAm!$F$3:$F$79,'SAm Capacity Data'!D$22,SAm!$U$3:$U$79,'SAm Capacity Data'!$A24) -> 0 | E24: =SUMIFS(SAm!$N$3:$N$79,SAm!$F$3:$F$79,'SAm Capacity Data'!E$22,SAm!$U$3:$U$79,'SAm Capacity Data'!$A24)+SUMIFS(SAm!$P$3:$P$79,SAm!$F$3:$F$79,'SAm Capacity Data'!E$22,SAm!$U$3:$U$79,'SAm Capacity Data'!$A24) -> 0 | F24: =SUMIFS(SAm!$N$3:$N$79,SAm!$F$3:$F$79,'SAm Capacity Data'!F$22,SAm!$U$3:$U$79,'SAm Capacity Data'!$A24)+SUMIFS(SAm!$P$3:$P$79,SAm!$F$3:$F$79,'SAm Capacity Data'!F$22,SAm!$U$3:$U$79,'SAm Capacity Data'!$A24) -> 0 | G24: =SUMIFS(SAm!$N$3:$N$79,SAm!$F$3:$F$79,'SAm Capacity Data'!G$22,SAm!$U$3:$U$79,'SAm Capacity Data'!$A24)+SUMIFS(SAm!$P$3:$P$79,SAm!$F$3:$F$79,'SAm Capacity Data'!G$22,SAm!$U$3:$U$79,'SAm Capacity Data'!$A24) -> 0 | H24: =SUMIFS(SAm!$N$3:$N$79,SAm!$F$3:$F$79,'SAm Capacity Data'!H$22,SAm!$U$3:$U$79,'SAm Capacity Data'!$A24)+SUMIFS(SAm!$P$3:$P$79,SAm!$F$3:$F$79,'SAm Capacity Data'!H$22,SAm!$U$3:$U$79,'SAm Capacity Data'!$A24) -> 0 | I24: =SUMIFS(SAm!$N$3:$N$79,SAm!$F$3:$F$79,'SAm Capacity Data'!I$22,SAm!$U$3:$U$79,'SAm Capacity Data'!$A24)+SUMIFS(SAm!$P$3:$P$79,SAm!$F$3:$F$79,'SAm Capacity Data'!I$22,SAm!$U$3:$U$79,'SAm Capacity Data'!$A24) -> 0 | J24: =SUMIFS(SAm!$N$3:$N$79,SAm!$F$3:$F$79,'SAm Capacity Data'!J$22,SAm!$U$3:$U$79,'SAm Capacity Data'!$A24)+SUMIFS(SAm!$P$3:$P$79,SAm!$F$3:$F$79,'SAm Capacity Data'!J$22,SAm!$U$3:$U$79,'SAm Capacity Data'!$A24) -> 0 | ... AF24: =SUMIFS(SAm!$N$3:$N$79,SAm!$F$3:$F$79,'SAm Capacity Data'!AF$22,SAm!$U$3:$U$79,'SAm Capacity Data'!$A24)+SUMIFS(SAm!$P$3:$P$79,SAm!$F$3:$F$79,'SAm Capacity Data'!AF$22,SAm!$U$3:$U$79,'SAm Capacity Data'!$A24) -> 0
A25: FT | B25: =SUMIFS(SAm!$N$3:$N$79,SAm!$F$3:$F$79,"<"&'SAm Capacity Data'!C$22,SAm!$U$3:$U$79,'SAm Capacity Data'!$A25)+SUMIFS(SAm!$P$3:$P$79,SAm!$F$3:$F$79,"<"&'SAm Capacity Data'!C$22,SAm!$U$3:$U$79,'SAm Capacity Data'!$A25) -> 0 | C25: =SUMIFS(SAm!$N$3:$N$79,SAm!$F$3:$F$79,'SAm Capacity Data'!C$22,SAm!$U$3:$U$79,'SAm Capacity Data'!$A25)+SUMIFS(SAm!$P$3:$P$79,SAm!$F$3:$F$79,'SAm Capacity Data'!C$22,SAm!$U$3:$U$79,'SAm Capacity Data'!$A25) -> 0 | D25: =SUMIFS(SAm!$N$3:$N$79,SAm!$F$3:$F$79,'SAm Capacity Data'!D$22,SAm!$U$3:$U$79,'SAm Capacity Data'!$A25)+SUMIFS(SAm!$P$3:$P$79,SAm!$F$3:$F$79,'SAm Capacity Data'!D$22,SAm!$U$3:$U$79,'SAm Capacity Data'!$A25) -> 0 | E25: =SUMIFS(SAm!$N$3:$N$79,SAm!$F$3:$F$79,'SAm Capacity Data'!E$22,SAm!$U$3:$U$79,'SAm Capacity Data'!$A25)+SUMIFS(SAm!$P$3:$P$79,SAm!$F$3:$F$79,'SAm Capacity Data'!E$22,SAm!$U$3:$U$79,'SAm Capacity Data'!$A25) -> 0 | F25: =SUMIFS(SAm!$N$3:$N$79,SAm!$F$3:$F$79,'SAm Capacity Data'!F$22,SAm!$U$3:$U$79,'SAm Capacity Data'!$A25)+SUMIFS(SAm!$P$3:$P$79,SAm!$F$3:$F$79,'SAm Capacity Data'!F$22,SAm!$U$3:$U$79,'SAm Capacity Data'!$A25) -> 0 | G25: =SUMIFS(SAm!$N$3:$N$79,SAm!$F$3:$F$79,'SAm Capacity Data'!G$22,SAm!$U$3:$U$79,'SAm Capacity Data'!$A25)+SUMIFS(SAm!$P$3:$P$79,SAm!$F$3:$F$79,'SAm Capacity Data'!G$22,SAm!$U$3:$U$79,'SAm Capacity Data'!$A25) -> 0.072 | H25: =SUMIFS(SAm!$N$3:$N$79,SAm!$F$3:$F$79,'SAm Capacity Data'!H$22,SAm!$U$3:$U$79,'SAm Capacity Data'!$A25)+SUMIFS(SAm!$P$3:$P$79,SAm!$F$3:$F$79,'SAm Capacity Data'!H$22,SAm!$U$3:$U$79,'SAm Capacity Data'!$A25) -> 0 | I25: =SUMIFS(SAm!$N$3:$N$79,SAm!$F$3:$F$79,'SAm Capacity Data'!I$22,SAm!$U$3:$U$79,'SAm Capacity Data'!$A25)+SUMIFS(SAm!$P$3:$P$79,SAm!$F$3:$F$79,'SAm Capacity Data'!I$22,SAm!$U$3:$U$79,'SAm Capacity Data'!$A25) -> 0 | J25: =SUMIFS(SAm!$N$3:$N$79,SAm!$F$3:$F$79,'SAm Capacity Data'!J$22,SAm!$U$3:$U$79,'SAm Capacity Data'!$A25)+SUMIFS(SAm!$P$3:$P$79,SAm!$F$3:$F$79,'SAm Capacity Data'!J$22,SAm!$U$3:$U$79,'SAm Capacity Data'!$A25) -> 0 | ... AF25: =SUMIFS(SAm!$N$3:$N$79,SAm!$F$3:$F$79,'SAm Capacity Data'!AF$22,SAm!$U$3:$U$79,'SAm Capacity Data'!$A25)+SUMIFS(SAm!$P$3:$P$79,SAm!$F$3:$F$79,'SAm Capacity Data'!AF$22,SAm!$U$3:$U$79,'SAm Capacity Data'!$A25) -> 0
A26: PTL | B26: =SUMIFS(SAm!$N$3:$N$79,SAm!$F$3:$F$79,"<"&'SAm Capacity Data'!C$22,SAm!$U$3:$U$79,'SAm Capacity Data'!$A26)+SUMIFS(SAm!$P$3:$P$79,SAm!$F$3:$F$79,"<"&'SAm Capacity Data'!C$22,SAm!$U$3:$U$79,'SAm Capacity Data'!$A26) -> 0 | C26: =SUMIFS(SAm!$N$3:$N$79,SAm!$F$3:$F$79,'SAm Capacity Data'!C$22,SAm!$U$3:$U$79,'SAm Capacity Data'!$A26)+SUMIFS(SAm!$P$3:$P$79,SAm!$F$3:$F$79,'SAm Capacity Data'!C$22,SAm!$U$3:$U$79,'SAm Capacity Data'!$A26) -> 0 | D26: =SUMIFS(SAm!$N$3:$N$79,SAm!$F$3:$F$79,'SAm Capacity Data'!D$22,SAm!$U$3:$U$79,'SAm Capacity Data'!$A26)+SUMIFS(SAm!$P$3:$P$79,SAm!$F$3:$F$79,'SAm Capacity Data'!D$22,SAm!$U$3:$U$79,'SAm Capacity Data'!$A26) -> 0 | E26: =SUMIFS(SAm!$N$3:$N$79,SAm!$F$3:$F$79,'SAm Capacity Data'!E$22,SAm!$U$3:$U$79,'SAm Capacity Data'!$A26)+SUMIFS(SAm!$P$3:$P$79,SAm!$F$3:$F$79,'SAm Capacity Data'!E$22,SAm!$U$3:$U$79,'SAm Capacity Data'!$A26) -> 0 | F26: =SUMIFS(SAm!$N$3:$N$79,SAm!$F$3:$F$79,'SAm Capacity Data'!F$22,SAm!$U$3:$U$79,'SAm Capacity Data'!$A26)+SUMIFS(SAm!$P$3:$P$79,SAm!$F$3:$F$79,'SAm Capacity Data'!F$22,SAm!$U$3:$U$79,'SAm Capacity Data'!$A26) -> 0 | G26: =SUMIFS(SAm!$N$3:$N$79,SAm!$F$3:$F$79,'SAm Capacity Data'!G$22,SAm!$U$3:$U$79,'SAm Capacity Data'!$A26)+SUMIFS(SAm!$P$3:$P$79,SAm!$F$3:$F$79,'SAm Capacity Data'!G$22,SAm!$U$3:$U$79,'SAm Capacity Data'!$A26) -> 0 | H26: =SUMIFS(SAm!$N$3:$N$79,SAm!$F$3:$F$79,'SAm Capacity Data'!H$22,SAm!$U$3:$U$79,'SAm Capacity Data'!$A26)+SUMIFS(SAm!$P$3:$P$79,SAm!$F$3:$F$79,'SAm Capacity Data'!H$22,SAm!$U$3:$U$79,'SAm Capacity Data'!$A26) -> 0 | I26: =SUMIFS(SAm!$N$3:$N$79,SAm!$F$3:$F$79,'SAm Capacity Data'!I$22,SAm!$U$3:$U$79,'SAm Capacity Data'!$A26)+SUMIFS(SAm!$P$3:$P$79,SAm!$F$3:$F$79,'SAm Capacity Data'!I$22,SAm!$U$3:$U$79,'SAm Capacity Data'!$A26) -> 0 | J26: =SUMIFS(SAm!$N$3:$N$79,SAm!$F$3:$F$79,'SAm Capacity Data'!J$22,SAm!$U$3:$U$79,'SAm Capacity Data'!$A26)+SUMIFS(SAm!$P$3:$P$79,SAm!$F$3:$F$79,'SAm Capacity Data'!J$22,SAm!$U$3:$U$79,'SAm Capacity Data'!$A26) -> 0 | ... AF26: =SUMIFS(SAm!$N$3:$N$79,SAm!$F$3:$F$79,'SAm Capacity Data'!AF$22,SAm!$U$3:$U$79,'SAm Capacity Data'!$A26)+SUMIFS(SAm!$P$3:$P$79,SAm!$F$3:$F$79,'SAm Capacity Data'!AF$22,SAm!$U$3:$U$79,'SAm Capacity Data'!$A26) -> 0
A27: Pyrolysis | B27: =SUMIFS(SAm!$N$3:$N$79,SAm!$F$3:$F$79,"<"&'SAm Capacity Data'!C$22,SAm!$U$3:$U$79,'SAm Capacity Data'!$A27)+SUMIFS(SAm!$P$3:$P$79,SAm!$F$3:$F$79,"<"&'SAm Capacity Data'!C$22,SAm!$U$3:$U$79,'SAm Capacity Data'!$A27) -> 0 | C27: =SUMIFS(SAm!$N$3:$N$79,SAm!$F$3:$F$79,'SAm Capacity Data'!C$22,SAm!$U$3:$U$79,'SAm Capacity Data'!$A27)+SUMIFS(SAm!$P$3:$P$79,SAm!$F$3:$F$79,'SAm Capacity Data'!C$22,SAm!$U$3:$U$79,'SAm Capacity Data'!$A27) -> 0 | D27: =SUMIFS(SAm!$N$3:$N$79,SAm!$F$3:$F$79,'SAm Capacity Data'!D$22,SAm!$U$3:$U$79,'SAm Capacity Data'!$A27)+SUMIFS(SAm!$P$3:$P$79,SAm!$F$3:$F$79,'SAm Capacity Data'!D$22,SAm!$U$3:$U$79,'SAm Capacity Data'!$A27) -> 0 | E27: =SUMIFS(SAm!$N$3:$N$79,SAm!$F$3:$F$79,'SAm Capacity Data'!E$22,SAm!$U$3:$U$79,'SAm Capacity Data'!$A27)+SUMIFS(SAm!$P$3:$P$79,SAm!$F$3:$F$79,'SAm Capacity Data'!E$22,SAm!$U$3:$U$79,'SAm Capacity Data'!$A27) -> 0 | F27: =SUMIFS(SAm!$N$3:$N$79,SAm!$F$3:$F$79,'SAm Capacity Data'!F$22,SAm!$U$3:$U$79,'SAm Capacity Data'!$A27)+SUMIFS(SAm!$P$3:$P$79,SAm!$F$3:$F$79,'SAm Capacity Data'!F$22,SAm!$U$3:$U$79,'SAm Capacity Data'!$A27) -> 0 | G27: =SUMIFS(SAm!$N$3:$N$79,SAm!$F$3:$F$79,'SAm Capacity Data'!G$22,SAm!$U$3:$U$79,'SAm Capacity Data'!$A27)+SUMIFS(SAm!$P$3:$P$79,SAm!$F$3:$F$79,'SAm Capacity Data'!G$22,SAm!$U$3:$U$79,'SAm Capacity Data'!$A27) -> 0 | H27: =SUMIFS(SAm!$N$3:$N$79,SAm!$F$3:$F$79,'SAm Capacity Data'!H$22,SAm!$U$3:$U$79,'SAm Capacity Data'!$A27)+SUMIFS(SAm!$P$3:$P$79,SAm!$F$3:$F$79,'SAm Capacity Data'!H$22,SAm!$U$3:$U$79,'SAm Capacity Data'!$A27) -> 0 | I27: =SUMIFS(SAm!$N$3:$N$79,SAm!$F$3:$F$79,'SAm Capacity Data'!I$22,SAm!$U$3:$U$79,'SAm Capacity Data'!$A27)+SUMIFS(SAm!$P$3:$P$79,SAm!$F$3:$F$79,'SAm Capacity Data'!I$22,SAm!$U$3:$U$79,'SAm Capacity Data'!$A27) -> 0 | J27: =SUMIFS(SAm!$N$3:$N$79,SAm!$F$3:$F$79,'SAm Capacity Data'!J$22,SAm!$U$3:$U$79,'SAm Capacity Data'!$A27)+SUMIFS(SAm!$P$3:$P$79,SAm!$F$3:$F$79,'SAm Capacity Data'!J$22,SAm!$U$3:$U$79,'SAm Capacity Data'!$A27) -> 0 | ... AF27: =SUMIFS(SAm!$N$3:$N$79,SAm!$F$3:$F$79,'SAm Capacity Data'!AF$22,SAm!$U$3:$U$79,'SAm Capacity Data'!$A27)+SUMIFS(SAm!$P$3:$P$79,SAm!$F$3:$F$79,'SAm Capacity Data'!AF$22,SAm!$U$3:$U$79,'SAm Capacity Data'!$A27) -> 0
A28: Co-Processing | B28: =SUMIFS(SAm!$N$3:$N$79,SAm!$F$3:$F$79,"<"&'SAm Capacity Data'!C$22,SAm!$U$3:$U$79,'SAm Capacity Data'!$A28)+SUMIFS(SAm!$P$3:$P$79,SAm!$F$3:$F$79,"<"&'SAm Capacity Data'!C$22,SAm!$U$3:$U$79,'SAm Capacity Data'!$A28) -> 0 | C28: =SUMIFS(SAm!$N$3:$N$79,SAm!$F$3:$F$79,'SAm Capacity Data'!C$22,SAm!$U$3:$U$79,'SAm Capacity Data'!$A28)+SUMIFS(SAm!$P$3:$P$79,SAm!$F$3:$F$79,'SAm Capacity Data'!C$22,SAm!$U$3:$U$79,'SAm Capacity Data'!$A28) -> 0 | D28: =SUMIFS(SAm!$N$3:$N$79,SAm!$F$3:$F$79,'SAm Capacity Data'!D$22,SAm!$U$3:$U$79,'SAm Capacity Data'!$A28)+SUMIFS(SAm!$P$3:$P$79,SAm!$F$3:$F$79,'SAm Capacity Data'!D$22,SAm!$U$3:$U$79,'SAm Capacity Data'!$A28) -> 0 | E28: =SUMIFS(SAm!$N$3:$N$79,SAm!$F$3:$F$79,'SAm Capacity Data'!E$22,SAm!$U$3:$U$79,'SAm Capacity Data'!$A28)+SUMIFS(SAm!$P$3:$P$79,SAm!$F$3:$F$79,'SAm Capacity Data'!E$22,SAm!$U$3:$U$79,'SAm Capacity Data'!$A28) -> 0 | F28: =SUMIFS(SAm!$N$3:$N$79,SAm!$F$3:$F$79,'SAm Capacity Data'!F$22,SAm!$U$3:$U$79,'SAm Capacity Data'!$A28)+SUMIFS(SAm!$P$3:$P$79,SAm!$F$3:$F$79,'SAm Capacity Data'!F$22,SAm!$U$3:$U$79,'SAm Capacity Data'!$A28) -> 0 | G28: =SUMIFS(SAm!$N$3:$N$79,SAm!$F$3:$F$79,'SAm Capacity Data'!G$22,SAm!$U$3:$U$79,'SAm Capacity Data'!$A28)+SUMIFS(SAm!$P$3:$P$79,SAm!$F$3:$F$79,'SAm Capacity Data'!G$22,SAm!$U$3:$U$79,'SAm Capacity Data'!$A28) -> 0 | H28: =SUMIFS(SAm!$N$3:$N$79,SAm!$F$3:$F$79,'SAm Capacity Data'!H$22,SAm!$U$3:$U$79,'SAm Capacity Data'!$A28)+SUMIFS(SAm!$P$3:$P$79,SAm!$F$3:$F$79,'SAm Capacity Data'!H$22,SAm!$U$3:$U$79,'SAm Capacity Data'!$A28) -> 0 | I28: =SUMIFS(SAm!$N$3:$N$79,SAm!$F$3:$F$79,'SAm Capacity Data'!I$22,SAm!$U$3:$U$79,'SAm Capacity Data'!$A28)+SUMIFS(SAm!$P$3:$P$79,SAm!$F$3:$F$79,'SAm Capacity Data'!I$22,SAm!$U$3:$U$79,'SAm Capacity Data'!$A28) -> 0 | J28: =SUMIFS(SAm!$N$3:$N$79,SAm!$F$3:$F$79,'SAm Capacity Data'!J$22,SAm!$U$3:$U$79,'SAm Capacity Data'!$A28)+SUMIFS(SAm!$P$3:$P$79,SAm!$F$3:$F$79,'SAm Capacity Data'!J$22,SAm!$U$3:$U$79,'SAm Capacity Data'!$A28) -> 6.8985 | ... AF28: =SUMIFS(SAm!$N$3:$N$79,SAm!$F$3:$F$79,'SAm Capacity Data'!AF$22,SAm!$U$3:$U$79,'SAm Capacity Data'!$A28)+SUMIFS(SAm!$P$3:$P$79,SAm!$F$3:$F$79,'SAm Capacity Data'!AF$22,SAm!$U$3:$U$79,'SAm Capacity Data'!$A28) -> 0
A29: Total Capacity | B29: =SUM(B23:B28) -> 0 | C29: =B29+SUM(C23:C28) -> 0 | D29: =C29+SUM(D23:D28) -> 0 | E29: =D29+SUM(E23:E28) -> 0 | F29: =E29+SUM(F23:F28) -> 0 | G29: =F29+SUM(G23:G28) -> 147.072 | H29: =G29+SUM(H23:H28) -> 213.072 | I29: =H29+SUM(I23:I28) -> 345.072 | J29: =I29+SUM(J23:J28) -> 474.6105 | ... AF29: =AE29+SUM(AF23:AF28) -> 890.905
B30: =B19/B29 -> #DIV/0! | C30: =C19/C29 -> #DIV/0! | D30: =D19/D29 -> #DIV/0! | E30: =E19/E29 -> #DIV/0! | F30: =F19/F29 -> #DIV/0! | G30: =G19/G29 -> 0.79997552 | H30: =H19/H29 -> 0.78449538 | I30: =I19/I29 -> 0.74956531 | ... AF30: =AF19/AF29 -> 0.53916812
A31: South American Cumulative SAF Capacity by Technology
A32: (mil gal/yr) | B32: =B22 -> < 2021 | C32: =C22 -> 2021 | D32: =D22 -> 2022 | E32: =E22 -> 2023 | F32: =F22 -> 2024 | G32: =G22 -> 2025 | H32: =H22 -> 2026 | I32: =I22 -> 2027 | ... AF32: =AF22 -> 2050
A33: HEFA Cumulative | B33: =B23 -> 0 | C33: =B33+C23 -> 0 | D33: =C33+D23 -> 0 | E33: =D33+E23 -> 0 | F33: =E33+F23 -> 0 | G33: =F33+G23 -> 147 | H33: =G33+H23 -> 213 | I33: =H33+I23 -> 345 | J33: =I33+J23 -> 467.64 | ... AF33: =AE33+AF23 -> 622.47 | AH33: =L33/$L$39 -> 0.6996478
A34: ATJ Cumulative | B34: =B24 -> 0 | C34: =B34+C24 -> 0 | D34: =C34+D24 -> 0 | E34: =D34+E24 -> 0 | F34: =E34+F24 -> 0 | G34: =F34+G24 -> 0 | H34: =G34+H24 -> 0 | I34: =H34+I24 -> 0 | J34: =I34+J24 -> 0 | ... AF34: =AE34+AF24 -> 52.05 | AH34: =L34/$L$39 -> 0.058503491
