Workbook
Name \p: #REF!
Name \p: #REF!
Name \s: #REF!
Name \s: #REF!
Name _J: #REF!
Name _J: #REF!
Name _P: #REF!
Name _P: #REF!
Name _S: #REF!
Name Domestic_chart6: #REF!
Name Domestic_chart6: #REF!
Name Forecast_Model_Output: #REF!
Name Forecast_Model_Output: #REF!
Name LATECON: #REF!
Name model_output: #REF!
Name Print_Area_MI: #REF!
Name Print_Titles_MI: #REF!
Name ss: #REF!

Sheet Small Refinery Exemptions
A1: SMALL REFINERY EXEMPTIONS | B1: 2010 | C1: 2011 | D1: 2012 | E1: 2013 | F1: 2014 | G1: 2015 | H1: 2016 | I1: 2017 | J1: 2018 | K1: 2019 | L1: 2020 | M1: 2021 | N1: 2022 | O1: 2023 | P1: 2024 | Q1: 2025 | R1: 2026 | S1: 2027 | T1: 2028 | U1: 2029 | V1: 2030 | W1: 2031 | X1: 2032 | Y1: 2033 | Z1: 2034 | AA1: 2035 | AB1: 2036 | AC1: 2037 | AD1: 2038 | AE1: 2039 | AF1: 2040 | AG1: 2041 | AH1: 2042 | AI1: 2043 | AJ1: 2044 | AK1: 2045 | AL1: 2046 | AM1: 2047 | AN1: 2048 | AO1: 2049 | AP1: 2050
A2: Petitions Forecast | C2: =C10 -> 42 | D2: =D10 -> 41 | E2: =E10 -> 30 | F2: =F10 -> 28 | G2: =G10 -> 28 | H2: =H10 -> 29 | I2: =I10 -> 37 | J2: =J10 -> 44 | ... P2: =P10 -> 30 | Q2: =FORECAST(P10,D8:O8,D10:O10)*P2+15 -> 30.372759 | R2: =FORECAST(Q10,E8:P8,E10:P10)*Q2+15 -> 30.513042 | S2: =FORECAST(R10,F8:Q8,F10:Q10)*R2+15 -> 30.530562 | T2: =FORECAST(S10,G8:R8,G10:R10)*S2+14 -> 29.684779 | U2: =FORECAST(T10,H8:S8,H10:S10)*T2+14 -> 29.509777 | V2: =FORECAST(U10,I8:T8,I10:T10)*U2+14 -> 29.740363 | W2: =FORECAST(V10,J8:U8,J10:U10)*V2+13 -> 29.080415 | X2: =FORECAST(W10,K8:V8,K10:V10)*W2+13 -> 28.762714 | Y2: =FORECAST(X10,L8:W8,L10:W10)*X2+13 -> 28.556122 | Z2: =FORECAST(Y10,M8:X8,M10:X10)*Y2+13 -> 28.337775 | AA2: =FORECAST(Z10,N8:Y8,N10:Y10)*Z2+13 -> 28.205309 | AB2: =FORECAST(AA10,O8:Z8,O10:Z10)*AA2+13 -> 28.104347 | AC2: =FORECAST(AB10,P8:AA8,P10:AA10)*AB2+13 -> 28.03142 | AD2: =FORECAST(AC10,Q8:AB8,Q10:AB10)*AC2+13 -> 27.911495 | ... AH2: =FORECAST(AG10,U8:AF8,U10:AF10)*AG2+13 -> 25.12396 | AI2: =FORECAST(AH10,V8:AG8,V10:AG10)*AH2+14 -> 25.873369 | AJ2: =FORECAST(AI10,W8:AH8,W10:AH10)*AI2+14 -> 26.639495 | AK2: =FORECAST(AJ10,X8:AI8,X10:AI10)*AJ2+14 -> 27.231241 | AL2: =FORECAST(AK10,Y8:AJ8,Y10:AJ10)*AK2+14 -> 27.639115 | AM2: =FORECAST(AL10,Z8:AK8,Z10:AK10)*AL2+14 -> 27.846349 | AN2: =FORECAST(AM10,AA8:AL8,AA10:AL10)*AM2+15 -> 28.822394 | AO2: =FORECAST(AN10,AB8:AM8,AB10:AM10)*AN2+14 -> 28.175758 | AP2: =FORECAST(AO10,AC8:AN8,AC10:AN10)*AO2+15 -> 28.601145
A3: Full Grants Forecast | C3: =C11 -> 24 | D3: =D11 -> 23 | E3: =E11 -> 8 | F3: =F11 -> 8 | G3: =G11 -> 7 | H3: =H11 -> 19 | I3: =I11 -> 35 | J3: =J11 -> 29 | ... N3: =N11 -> 6 | O3: =O2-O4-O6-O7 -> 21 | P3: =P2-P4-P6-P7 -> 18.990765 | Q3: =Q2-Q4-Q6-Q7 -> 14.702491 | R3: =R2-R4-R6-R7 -> 15.997708 | S3: =S2-S4-S6-S7 -> 17.451114 | T3: =T2-T4-T6-T7 -> 14.197675 | U3: =U2-U4-U6-U7 -> 14.948533 | V3: =V2-V4-V6-V7 -> 14.963373 | ... AP3: =AP2-AP4-AP6-AP7 -> 11.336916 | BH3: How to calculate the implied ethanol percent
A4: Partial Grants Forecast | E4: 0 | F4: 0 | G4: 0 | H4: 0 | I4: 0 | J4: 0 | K4: 0 | L4: 0 | M4: 0 | N4: 0 | O4: 0 | P4: 0 | Q4: =FORECAST(Q2,G12:P12,G10:P10) -> 7.9925849 | R4: =FORECAST(R2,H12:Q12,H10:Q10) -> 7.6611531 | S4: =FORECAST(S2,I12:R12,I10:R10) -> 7.6473052 | T4: =FORECAST(T2,J12:S12,J10:S10) -> 7.7224052 | U4: =FORECAST(U2,K12:T12,K10:T10) -> 7.8289885 | V4: =FORECAST(V2,L11:U11,L2:U2) -> 8.2811606 | W4: =FORECAST(W2,M11:V11,M2:V2) -> 9.2552208 | X4: =FORECAST(X2,N11:W11,N2:W2) -> 8.9816048 | Y4: =FORECAST(Y2,O11:X11,O2:X2) -> 9.8979427 | Z4: =FORECAST(Z2,P11:Y11,P2:Y2) -> 15.902254 | AA4: =FORECAST(AA2,Q11:Z11,Q2:Z2) -> 12.843579 | AB4: =FORECAST(AB2,R11:AA11,R2:AA2) -> 10.832121 | AC4: =FORECAST(AC2,S11:AB11,S2:AB2) -> 8.7294839 | ... AP4: =FORECAST(AP2,AF11:AO11,AF2:AO2) -> 10.45655 | BG4: Total | BH4: =P21*P28 -> 2692500000
A5: Average Partial Grant Percentage | C5: 0.5 | D5: 0.5 | E5: 0.5 | F5: 0.5 | G5: 0.5 | H5: 0.5 | I5: 0.5 | J5: 0.5 | K5: 0.5 | L5: 0.5 | M5: 0.5 | N5: 0.5 | O5: 0.5 | P5: 0.5 | Q5: 0.5 | R5: 0.5 | S5: 0.5 | T5: 0.5 | U5: 0.5 | V5: 0.5 | W5: 0.5 | X5: 0.5 | Y5: 0.5 | Z5: 0.5 | AA5: 0.5 | AB5: 0.5 | AC5: 0.5 | AD5: 0.5 | AE5: 0.5 | AF5: 0.5 | AG5: 0.5 | AH5: 0.5 | AI5: 0.5 | AJ5: 0.5 | AK5: 0.5 | AL5: 0.5 | AM5: 0.5 | AN5: 0.5 | AO5: 0.5 | AP5: 0.5 | BI5: Calculation for SRE impact per fuel code
A6: Pending Forecast | C6: =C15 -> 0 | D6: =D15 -> 0 | E6: =E15 -> 0 | F6: =F15 -> 0 | G6: =G15 -> 0 | H6: =H15 -> 0 | I6: =I15 -> 0 | J6: =J15 -> 0 | ... O6: =O15 -> 0 | P6: =FORECAST(P10,C6:O6,C10:O10) -> 0.21096681 | Q6: 0 | R6: 0 | S6: 0 | T6: 0 | U6: 0 | V6: 0 | W6: 0 | X6: 0 | Y6: 0 | Z6: 0 | AA6: 0 | AB6: 0 | AC6: 0 | AD6: 0 | AE6: 0 | AF6: 0 | AG6: 0 | AH6: 0 | AI6: 0 | AJ6: 0 | AK6: 0 | AL6: 0 | AM6: 0 | AN6: 0 | AO6: 0 | AP6: 0
A7: Denials/Withdrawn Forecast | C7: =C13+C14 -> 18 | D7: =D13+D14 -> 18 | E7: =E13+E14 -> 22 | F7: =F13+F14 -> 20 | G7: =G13+G14 -> 21 | H7: =H13+H14 -> 10 | I7: =I13+I14 -> 2 | J7: =J13+J14 -> 12 | ... O7: =O13+O14 -> 5 | P7: =FORECAST(P2,C7:O7,C10:O10) -> 10.798268 | Q7: =FORECAST(Q2,D13:P13,D10:P10) -> 7.6776829 | R7: =FORECAST(R2,E13:Q13,E10:Q10) -> 6.8541813 | S7: =FORECAST(S2,F13:R13,F10:R10) -> 5.432143 | T7: =FORECAST(T2,G7:S7,G10:S10) -> 7.7646988 | U7: =FORECAST(U2,H7:T7,H10:T10) -> 6.7322559 | V7: =FORECAST(V2,I7:U7,I10:U10) -> 6.4958299 | W7: =FORECAST(W2,J7:V7,J10:V10) -> 6.838981 | X7: =FORECAST(X2,K7:W7,K10:W10) -> 6.4454096 | Y7: =FORECAST(Y2,L7:X7,L10:X10) -> 6.5914834 | Z7: =FORECAST(Z2,M7:Y7,M10:Y10) -> 6.4641895 | AA7: =FORECAST(AA2,N7:Z7,N10:Z10) -> 6.7104641 | ... AP7: =FORECAST(AP2,AC7:AO7,AC10:AO10) -> 6.807679
A8: Portion of Applications Approved | C8: =AVERAGE(B3:$C3)/AVERAGE(B2:$C2) -> 0.57142857 | D8: =AVERAGE($C3:C3)/AVERAGE($C2:C2) -> 0.57142857 | E8: =AVERAGE($C3:D3)/AVERAGE($C2:D2) -> 0.56626506 | F8: =AVERAGE($C3:E3)/AVERAGE($C2:E2) -> 0.48672566 | G8: =AVERAGE($C3:F3)/AVERAGE($C2:F2) -> 0.44680851 | H8: =AVERAGE($C3:G3)/AVERAGE($C2:G2) -> 0.41420118 | I8: =AVERAGE($C3:H3)/AVERAGE($C2:H2) -> 0.44949495 | J8: =AVERAGE($C3:I3)/AVERAGE($C2:I2) -> 0.52765957 | K8: =AVERAGE($C3:J3)/AVERAGE($C2:J2) -> 0.5483871 | ... AP8: =AVERAGE($C3:AO3)/AVERAGE($C2:AO2) -> 0.46354351 | BG8: Adv X Total above | BH8: =P27*BH4 -> 1.0204575e+08
A9: DOE Recommendations | C9: =C1 -> 2011 | D9: =D1 -> 2012 | E9: =E1 -> 2013 | F9: =F1 -> 2014 | G9: =G1 -> 2015 | H9: =H1 -> 2016 | I9: =I1 -> 2017 | J9: =J1 -> 2018 | ... AP9: =AP1 -> 2050 | BG9: Renewable Fuel X Total above | BH9: =P28*BH4 -> 336562500
A10: Petitions Received | C10: 42 | D10: 41 | E10: 30 | F10: 28 | G10: 28 | H10: 29 | I10: 37 | J10: 44 | K10: 34 | L10: 32 | M10: 26 | N10: 24 | O10: 26 | P10: 30 | Q10: 11 | R10: =R2 -> 30.513042 | S10: =S2 -> 30.530562 | T10: =T2 -> 29.684779 | U10: =U2 -> 29.509777 | V10: =V2 -> 29.740363 | W10: =W2 -> 29.080415 | X10: =X2 -> 28.762714 | Y10: =Y2 -> 28.556122 | ... AP10: =AP2 -> 28.601145 | BG10: Subtract Advanced Percentage Product from the Total Percentage Product | BH10: =BH9-BH8 -> 234516750
A11: Grants Issued | C11: 24 | D11: 23 | E11: 8 | F11: 8 | G11: 7 | H11: 19 | I11: 35 | J11: 29 | K11: 25 | L11: 7 | M11: 15 | N11: 6 | O11: 6 | P11: 4 | Q11: 0 | R11: 0 | S11: =S3 -> 17.451114 | T11: =T3 -> 14.197675 | U11: =U3 -> 14.948533 | V11: =V3 -> 14.963373 | W11: =W3 -> 12.986213 | X11: =X3 -> 13.335699 | Y11: =Y3 -> 12.066696 | Z11: =Z3 -> 5.9713316 | ... AP11: =AP3 -> 11.336916 | AQ11: Divide the Difference between Advanced Percentage Total from the Total Percentage Total - this is the implied ethanol Percentage Standard | BH11: =BH10/BH4 -> 0.0871 | BI11: =BH11*100 -> 8.71 | BJ11: =BI11-0.14 -> 8.57
A12: Partial Grants Issued | C12: 0 | D12: 0 | E12: 0 | F12: 0 | G12: 0 | H12: 0 | I12: 0 | J12: 3 | K12: 4 | L12: 17 | M12: 6 | N12: 14 | O12: 15 | P12: 18 | Q12: 0 | R12: 0 | S12: 0 | T12: 0 | U12: 0 | V12: 0 | W12: 0 | X12: 0 | Y12: 0 | Z12: 0 | AA12: 0 | AB12: 0 | AC12: 0 | AD12: 0 | AE12: 0 | AF12: 0 | AG12: 0 | AH12: 0 | AI12: 0 | AJ12: 0 | AK12: 0 | AL12: 0 | AM12: 0 | AN12: 0 | AO12: 0 | AP12: 0
A13: Denials Issued | C13: 13 | D13: 13 | E13: 18 | F13: 16 | G13: 17 | H13: 8 | I13: 1 | J13: 7 | K13: 1 | L13: 6 | M13: 1 | N13: 3 | O13: 4 | P13: 5 | Q13: 0 | R13: 0 | S13: =S7 -> 5.432143 | T13: =T7 -> 7.7646988 | U13: =U7 -> 6.7322559 | V13: =V7 -> 6.4958299 | W13: =W7 -> 6.838981 | X13: =X7 -> 6.4454096 | Y13: =Y7 -> 6.5914834 | Z13: =Z7 -> 6.4641895 | ... AP13: =AP7 -> 6.807679
A14: Ineligible or Withdrawn | C14: 5 | D14: 5 | E14: 4 | F14: 4 | G14: 4 | H14: 2 | I14: 1 | J14: 5 | K14: 4 | L14: 2 | M14: 2 | N14: 1 | O14: 1 | P14: 3 | Q14: 0 | R14: 0 | S14: =S10-S11-S13-S15 -> 7.6473052 | T14: =T10-T11-T13-T15 -> 7.7224052 | U14: =U10-U11-U13-U15 -> 7.8289885 | V14: =V10-V11-V13-V15 -> 8.2811606 | W14: =W10-W11-W13-W15 -> 9.2552208 | X14: =X10-X11-X13-X15 -> 8.9816048 | Y14: =Y10-Y11-Y13-Y15 -> 9.8979427 | Z14: =Z10-Z11-Z13-Z15 -> 15.902254 | ... AP14: =AP10-AP11-AP13-AP15 -> 10.45655 | BH14: 17050000000
A15: Pending | C15: 0 | D15: 0 | E15: 0 | F15: 0 | G15: 0 | H15: 0 | I15: 0 | J15: 0 | K15: 0 | L15: 0 | M15: 2 | N15: 0 | O15: 0 | P15: 0 | Q15: 11 | R15: 0 | S15: =S6 -> 0 | T15: =T6 -> 0 | U15: =U6 -> 0 | V15: =V6 -> 0 | W15: =W6 -> 0 | X15: =X6 -> 0 | Y15: =Y6 -> 0 | Z15: =Z6 -> 0 | ... AP15: =AP6 -> 0 | BH15: =BH14*K25 -> 39215000
BG16: =11+15+57+34.5+7.5+26.5+22.3+50+75+15+20+40.7+74.5+18 -> 467 | BH16: =BH14*K26 -> 294965000 | BI16: =BH16/1.5 -> 1.9664333e+08
A17: Renewable Volume Obligations | BG17: =BG16/14 -> 33.357143 | BH17: =BH14*K27 -> 462055000 | BI17: =BH17/'RVO Forecast'!K6 -> 2.9533206e+08
A18: Cellulosic Biofuel | C18: ='RVO Forecast'!B14 -> 0 | D18: ='RVO Forecast'!C14 -> 0 | E18: ='RVO Forecast'!D14 -> 800000 | F18: ='RVO Forecast'!E14 -> 33000000 | G18: ='RVO Forecast'!F14 -> 123000000 | H18: ='RVO Forecast'!G14 -> 230000000 | I18: ='RVO Forecast'!H14 -> 311000000 | J18: ='RVO Forecast'!I14 -> 288000000 | ... AP18: ='RVO Forecast'!AO14 -> 15250000000 | BG18: =BG17*7 -> 233.5 | BH18: =BH14*K28 -> 1870385000
A19: Biomass-Based Diesel | C19: ='RVO Forecast'!B10 -> 800000000 | D19: ='RVO Forecast'!C10 -> 1000000000 | E19: ='RVO Forecast'!D10 -> 1280000000 | F19: ='RVO Forecast'!E10 -> 1630000000 | G19: ='RVO Forecast'!F10 -> 1730000000 | H19: ='RVO Forecast'!G10 -> 1900000000 | I19: ='RVO Forecast'!H10 -> 2000000000 | J19: ='RVO Forecast'!I10 -> 2100000000 | ... R19: ='RVO Forecast'!Q10 -> 7120000000 | S19: 2430000007 | T19: 2430000008 | U19: 2430000009 | V19: 2430000010 | W19: 2430000011 | X19: 2430000012 | Y19: 2430000013 | Z19: 2430000014 | AA19: 2430000015 | AB19: 2430000016 | AC19: 2430000017 | AD19: 2430000018 | AE19: 2430000019 | AF19: 2430000020 | AG19: 2430000021 | AH19: 2430000022 | AI19: 2430000023 | AJ19: 2430000024 | AK19: 2430000025 | AL19: 2430000026 | AM19: 2430000027 | AN19: 2430000028 | AO19: 2430000029 | AP19: 2430000030 | BH19: =BH14*K29 -> 1408330000
A20: Advanced Biofuel | C20: ='RVO Forecast'!B18 -> 1350000000 | D20: ='RVO Forecast'!C18 -> 2000000000 | E20: ='RVO Forecast'!D18 -> 2670000000 | F20: ='RVO Forecast'!E18 -> 2670000000 | G20: ='RVO Forecast'!F18 -> 2880000000 | H20: ='RVO Forecast'!G18 -> 3610000000 | I20: ='RVO Forecast'!H18 -> 4280000000 | J20: ='RVO Forecast'!I18 -> 4290000000 | ... AP20: ='RVO Forecast'!AO18 -> 3.37e+10
A21: Renewable Fuel | E21: ='RVO Forecast'!D8 -> 16550000000 | F21: ='RVO Forecast'!E8 -> 16280000000 | G21: ='RVO Forecast'!F8 -> 16930000000 | H21: ='RVO Forecast'!G8 -> 18110000000 | I21: ='RVO Forecast'!H8 -> 19280000000 | J21: ='RVO Forecast'!I8 -> 19290000000 | K21: ='RVO Forecast'!J8 -> 19920000000 | L21: ='RVO Forecast'!K8 -> 1.713e+10 | ... AP21: ='RVO Forecast'!AO8 -> 48700000000
A22: Implied Ethanol | E22: =E21-E20 -> 13880000000 | F22: =F21-F20 -> 13610000000 | G22: =G21-G20 -> 14050000000 | H22: =H21-H20 -> 14500000000 | I22: 15000000000 | J22: 15000000000 | K22: =K21-K20 -> 15000000000 | L22: =L21-L20 -> 1.25e+10 | M22: =M21-M20 -> 13790000000 | N22: =N21-N20 -> 15000000000 | O22: =O21-O20 -> 15000000000 | P22: =P21-P20 -> 15000000000 | Q22: =Q21-Q20 -> 15000000000 | R22: =R21-R20 -> 15000000000 | ... AP22: =AP21-AP20 -> 1.5e+10
A24: EPA Final Percent Standards
A25: Cellulosic Biofuel | E25: 4e-05 | F25: 0.00019 | G25: 0.00069 | H25: 0.00128 | I25: 0.00173 | J25: 0.00159 | K25: 0.0023 | L25: 0.0029 | M25: 0.0033 | N25: 0.0035 | O25: 0.0048 | P25: 0.0063 | Q25: 0.0081 | R25: =FORECAST(R18,$F25:$J25,$F18:$J18) -> 0.0071800511 | S25: =FORECAST(S18,$F25:$J25,$F18:$J18) -> 0.0075110058 | T25: =FORECAST(T18,$F25:$J25,$F18:$J18) -> 0.0077316423 | U25: =FORECAST(U18,$F25:$J25,$F18:$J18) -> 0.01793608 | V25: =FORECAST(V18,$F25:$J25,$F18:$J18) -> 0.019315058 | W25: =FORECAST(W18,$F25:$J25,$F18:$J18) -> 0.020694036 | X25: =FORECAST(X18,$F25:$J25,$F18:$J18) -> 0.022073014 | Y25: =FORECAST(Y18,$F25:$J25,$F18:$J18) -> 0.023451992 | ... AP25: =FORECAST(AP18,$F25:$J25,$F18:$J18) -> 0.084127026
A26: Biomass-Based Diesel | E26: 0.0113 | F26: 0.0141 | G26: 0.0149 | H26: 0.0159 | I26: 0.0167 | J26: 0.0174 | K26: 0.0173 | L26: 0.021 | M26: 0.0216 | N26: 0.0233 | O26: 0.0258 | P26: 0.0282 | Q26: 0.0315 | R26: =FORECAST(R19,$F26:$J26,$F19:$J19) -> 0.052068975 | S26: =FORECAST(S19,$F26:$J26,$F19:$J19) -> 0.019656343 | T26: =FORECAST(T19,$F26:$J26,$F19:$J19) -> 0.019656343 | U26: =FORECAST(U19,$F26:$J26,$F19:$J19) -> 0.019656343 | V26: =FORECAST(V19,$F26:$J26,$F19:$J19) -> 0.019656343 | W26: =FORECAST(W19,$F26:$J26,$F19:$J19) -> 0.019656343 | X26: =FORECAST(X19,$F26:$J26,$F19:$J19) -> 0.019656343 | Y26: =FORECAST(Y19,$F26:$J26,$F19:$J19) -> 0.019656343 | ... AP26: =FORECAST(AP19,$F26:$J26,$F19:$J19) -> 0.019656343
A27: Advanced Biofuel | E27: 0.0162 | F27: 0.0151 | G27: 0.0162 | H27: 0.0201 | I27: 0.0238 | J27: 0.0237 | K27: 0.0271 | L27: 0.0293 | M27: 0.03 | N27: 0.0316 | O27: 0.0339 | P27: 0.0379 | Q27: 0.0431 | R27: =FORECAST(R20,$F27:$J27,$F20:$J20) -> 0.049130995 | S27: =FORECAST(S20,$F27:$J27,$F20:$J20) -> 0.051490228 | T27: =FORECAST(T20,$F27:$J27,$F20:$J20) -> 0.055726122 | U27: =FORECAST(U20,$F27:$J27,$F20:$J20) -> 0.062428487 | V27: =FORECAST(V20,$F27:$J27,$F20:$J20) -> 0.068326568 | W27: =FORECAST(W20,$F27:$J27,$F20:$J20) -> 0.074224649 | X27: =FORECAST(X20,$F27:$J27,$F20:$J20) -> 0.080122729 | Y27: =FORECAST(Y20,$F27:$J27,$F20:$J20) -> 0.08602081 | ... AP27: =FORECAST(AP20,$F27:$J27,$F20:$J20) -> 0.18146248 | BH27: 318054000
A28: Renewable Fuel | E28: 0.0974 | F28: 0.0919 | G28: 0.0952 | H28: 0.101 | I28: 0.107 | J28: 0.1067 | K28: 0.1097 | L28: 0.1009 | M28: 0.1119 | N28: 0.1159 | O28: 0.1196 | P28: 0.125 | Q28: 0.1313 | R28: =FORECAST(R21,$F28:$J28,$F21:$J21) -> 0.13036076 | S28: =FORECAST(S21,$F28:$J28,$F21:$J21) -> 0.13254553 | T28: =FORECAST(T21,$F28:$J28,$F21:$J21) -> 0.13646817 | U28: =FORECAST(U21,$F28:$J28,$F21:$J21) -> 0.14267488 | V28: =FORECAST(V21,$F28:$J28,$F21:$J21) -> 0.14813679 | W28: =FORECAST(W21,$F28:$J28,$F21:$J21) -> 0.15359869 | X28: =FORECAST(X21,$F28:$J28,$F21:$J21) -> 0.1590606 | Y28: =FORECAST(Y21,$F28:$J28,$F21:$J21) -> 0.16452251 | ... AP28: =FORECAST(AP21,$F28:$J28,$F21:$J21) -> 0.25290609 | BH28: =BH27/J36 -> 0.78642923
A29: Implied Ethanol | E29: =E28-E27 -> 0.0812 | F29: =F28-F27 -> 0.0768 | G29: =G28-G27 -> 0.079 | H29: 0.0809 | I29: 0.0832 | J29: 0.083 | K29: 0.0826 | L29: 0.0789 | M29: 0.0819 | N29: 0.0829 | O29: 0.0857 | P29: 0.0871 | Q29: 0.0882 | R29: =FORECAST(R22,$F29:$J29,$F22:$J22) -> 0.083125786 | S29: =FORECAST(S22,$F29:$J29,$F22:$J22) -> 0.083125786 | T29: =FORECAST(T22,$F29:$J29,$F22:$J22) -> 0.083125786 | U29: =FORECAST(U22,$F29:$J29,$F22:$J22) -> 0.083125786 | V29: =FORECAST(V22,$F29:$J29,$F22:$J22) -> 0.083125786 | W29: =FORECAST(W22,$F29:$J29,$F22:$J22) -> 0.083125786 | X29: =FORECAST(X22,$F29:$J29,$F22:$J22) -> 0.083125786 | Y29: =FORECAST(Y22,$F29:$J29,$F22:$J22) -> 0.083125786 | ... AP29: =FORECAST(AP22,$F29:$J29,$F22:$J22) -> 0.083125786
A30: Supplemental Standard | N30: 0.0014 | O30: 0.0014
A31: Estimated Total Exemptions of Fossil Fuel from Blending | E31: 1980000000 | F31: 2300000000 | G31: 3070000000 | H31: 7820000000 | I31: 17050000000 | J31: 13620000000 | K31: 13300000000 | L31: 7140000000 | M31: 8090000000 | N31: 6450000000 | O31: 5600000000 | P31: 5820000000 | Q31: =MROUND(AVERAGE(L32:P32)*Q3,10000000) -> 6670000000 | R31: =MROUND($I$32*R3,10000000) -> 7790000000 | S31: =MROUND($I$32*S3,10000000) -> 8500000000 | T31: =MROUND($I$32*T3,10000000) -> 6920000000 | U31: =MROUND($I$32*U3,10000000) -> 7280000000 | V31: =MROUND($I$32*V3,10000000) -> 7290000000 | W31: =MROUND($I$32*W3,10000000) -> 6330000000 | X31: =MROUND($I$32*X3,10000000) -> 6500000000 | Y31: =MROUND($I$32*Y3,10000000) -> 5880000000 | ... AP31: =MROUND($I$32*AP3,10000000) -> 5520000000 | BH31: 14858000000 | BI31: =J31-BH31 -> -1238000000 | BJ31: 19031000000 | BK31: =K31-BJ31 -> -5731000000
A32: Volume per Exemption | E32: =IF(E10=0,0,E31/(E11+(E12*E5))) -> 247500000 | F32: =IF(F10=0,0,F31/(F11+(F12*F5))) -> 287500000 | G32: =IF(G10=0,0,G31/(G11+(G12*G5))) -> 4.3857143e+08 | H32: =IF(H10=0,0,H31/(H11+(H12*H5))) -> 4.1157895e+08 | I32: =IF(I10=0,0,I31/(I11+(I12*I5))) -> 4.8714286e+08 | J32: =IF(J10=0,0,J31/(J11+(J12*J5))) -> 4.4655738e+08 | K32: =IF(K10=0,0,K31/(K11+(K12*K5))) -> 4.9259259e+08 | L32: =IF(L10=0,0,L31/(L11+(L12*L5))) -> 4.6064516e+08 | ... P32: =IF(P10=0,0,P31/(P11+(P12*P5))) -> 4.4769231e+08 | Q32: =IF(Q3=0,0,Q31/(Q3+(Q4*Q5))) -> 3.5670769e+08 | R32: =IF(R3=0,0,R31/(R3+(R4*R5))) -> 3.9287313e+08 | S32: =IF(S3=0,0,S31/(S3+(S4*S5))) -> 3.9953434e+08 | T32: =IF(T3=0,0,T31/(T3+(T4*T5))) -> 3.8319104e+08 | U32: =IF(U3=0,0,U31/(U3+(U4*U5))) -> 3.8594017e+08 | V32: =AVERAGE($E32:$I32) -> 3.7445865e+08 | W32: =AVERAGE($E32:$I32) -> 3.7445865e+08 | X32: =AVERAGE($E32:$I32) -> 3.7445865e+08 | Y32: =AVERAGE($E32:$I32) -> 3.7445865e+08 | Z32: =AVERAGE($E32:$I32) -> 3.7445865e+08 | AA32: =AVERAGE($E32:$I32) -> 3.7445865e+08 | AB32: =AVERAGE($E32:$I32) -> 3.7445865e+08 | AC32: =AVERAGE($E32:$I32) -> 3.7445865e+08 | ... AP32: =AVERAGE($E32:$I32) -> 3.7445865e+08
A33: Gallons Exempt by Fuel Type
A34: Cellulosic Biofuel | D34: =SUM(E34:I34) -> 42140600 | E34: =E$31*E25 -> 79200 | F34: =F$31*F25 -> 437000 | G34: =G$31*G25 -> 2118300 | H34: =H$31*H25 -> 10009600 | I34: =I$31*I25 -> 29496500 | J34: =(J$31*J25)+5933900 -> 27589700 | K34: =(K$31*K25) -> 30590000 | L34: =L$31*L25 -> 20706000 | M34: =M$31*M25 -> 26697000 | N34: =N$31*N25 -> 22575000 | O34: =O$31*O25 -> 26880000 | P34: =P$31*P25 -> 36666000 | Q34: =Q$31*Q25 -> 54027000 | R34: =R$31*R25 -> 55932598 | S34: =S$31*S25 -> 63843550 | ... AP34: =AP$31*AP25 -> 4.6438118e+08 | BH34: 27271700 | BI34: =J34-BH34 -> 318000 | BJ34: 42402800 | BK34: =K34-BJ34 -> -11812800
A35: Biomass-Based Diesel | C35: =D35/5/12 -> 5662444.4 | D35: =SUM(E35:I35) -> 3.3974667e+08 | E35: =E$31*E26/1.5 -> 14916000 | F35: =F$31*F26/1.5 -> 21620000 | G35: =G$31*G26/1.5 -> 30495333 | H35: =H$31*H26/1.5 -> 82892000 | I35: =I$31*I26/1.5 -> 1.8982333e+08 | J35: =(J$31*J26/1.5)+38187333 -> 1.9617933e+08 | K35: =(K$31*K26/1/'RVO Forecast'!J$6) -> 1.4702954e+08 | L35: =L$31*L26/1.5 -> 99960000 | M35: =M$31*M26/1.5 -> 116496000 | N35: =N$31*N26/1.5 -> 100190000 | O35: =O$31*O26/1.5 -> 96320000 | P35: =P$31*P26/1.5 -> 109416000 | Q35: =Q$31*Q26/1.5 -> 140070000 | R35: =R$31*R26/1.5 -> 2.7041154e+08 | S35: =S$31*S26/1.5 -> 1.1138594e+08 | ... AP35: =AP$31*AP26/1.5 -> 72335343 | BH35: 1.9385933e+08 | BI35: =J35-BH35 -> 2320000 | BJ35: 2.0497609e+08 | BK35: =K35-BJ35 -> -57946558
A36: Advanced Biofuel | D36: =SUM(E36:I36) -> 4.3991591e+08 | E36: =E$31*E27/1/'RVO Forecast'!D$6 -> 20802597 | F36: =F$31*F27/1/'RVO Forecast'!E$6 -> 22415614 | G36: =G$31*G27/1/'RVO Forecast'!F$6 -> 32111327 | H36: =H$31*H27/1/'RVO Forecast'!G$6 -> 1.0201374e+08 | I36: =I$31*I27/1/'RVO Forecast'!H$6 -> 2.6257263e+08 | J36: =(J$31*J27)+81634000 -> 404428000 | K36: =(K$31*K27/1/'RVO Forecast'!J$6) -> 2.3031794e+08 | L36: =L$31*L27/1/'RVO Forecast'!K$6 -> 1.3371581e+08 | M36: =M$31*M27/1/'RVO Forecast'!L$6 -> 1.5345942e+08 | N36: =N$31*N27/1/'RVO Forecast'!M$6 -> 1.2730032e+08 | O36: =O$31*O27/1/'RVO Forecast'!N$6 -> 1.1760341e+08 | P36: =P$31*P27/1/'RVO Forecast'!O$6 -> 1.3562121e+08 | Q36: =Q$31*Q27/1/'RVO Forecast'!P$6 -> 1.7662031e+08 | R36: =R$31*R27/1/'RVO Forecast'!Q$6 -> 2.3478025e+08 | S36: =S$31*S27/1/'RVO Forecast'!R$6 -> 2.679046e+08 | ... AP36: =AP$31*AP27/1/'RVO Forecast'!AO$6 -> 5.9214765e+08 | BH36: 399688000 | BI36: =J36-BH36 -> 4740000 | BJ36: 3.2108972e+08 | BK36: =K36-BJ36 -> -90771776
A37: Renewable Fuel | E37: =E$31*E28 -> 192852000 | F37: =F$31*F28 -> 211370000 | G37: =G$31*G28 -> 292264000 | H37: =H$31*H28 -> 789820000 | I37: =I$31*I28 -> 1824350000 | J37: =(J$31*J28)+367010000 -> 1820264000 | K37: =(K$31*K28) -> 1459010000 | L37: =L$31*L28 -> 720426000 | M37: =M$31*M28 -> 905271000 | N37: =N$31*N28 -> 747555000 | O37: =O$31*O28 -> 669760000 | P37: =P$31*P28 -> 727500000 | Q37: =Q$31*Q28 -> 875771000 | R37: =R$31*R28 -> 1.0155104e+09 | S37: =S$31*S28 -> 1.126637e+09 | ... AP37: =AP$31*AP28 -> 1.3960416e+09 | BH37: 1798924000 | BI37: =J37-BH37 -> 21340000 | BJ37: 2022429200 | BK37: =K37-BJ37 -> -563419200
A38: Implied Ethanol | E38: =E$31*E29 -> 160776000 | F38: =F$31*F29 -> 1.7664e+08 | G38: =G$31*G29 -> 2.4253e+08 | H38: =H$31*H29 -> 632638000 | I38: =I$31*I29 -> 1418560000 | J38: =(J$31*J29)+285376000 -> 1415836000 | K38: =(K$31*K29) -> 1098580000 | L38: =L$31*L29 -> 563346000 | M38: =M$31*M29 -> 662571000 | N38: =N$31*N29 -> 534705000 | O38: =O$31*O29 -> 479920000 | P38: =P$31*P29 -> 506922000 | Q38: =Q$31*Q29 -> 588294000 | R38: =R$31*R29 -> 6.4754988e+08 | S38: =S$31*S29 -> 7.0656918e+08 | ... AP38: =AP$31*AP29 -> 4.5885434e+08 | BH38: 1399236000 | BI38: =J38-BH38 -> 16600000 | BJ38: 1.5228136e+09 | BK38: =K38-BJ38 -> -4.242336e+08
J39: =J38/3 -> 4.7194533e+08 | BI39: =BI38/3 -> 5533333.3
A40: RINs Exempt
A41: Cellulosic Biofuel | E41: =E34 -> 79200 | F41: =F34 -> 437000 | G41: =G34 -> 2118300 | H41: =H34 -> 10009600 | I41: =I34 -> 29496500 | J41: =J34 -> 27589700 | K41: =K34 -> 30590000 | L41: =L34 -> 20706000 | ... AP41: =AP34 -> 4.6438118e+08 | BH41: 27271700 | BI41: =J41-BH41 -> 318000 | BJ41: 42402800 | BK41: =K41-BJ41 -> -11812800
A42: Biomass-Based Diesel | E42: =E35*'RVO Forecast'!D$6 -> 22999322 | F42: =F35*'RVO Forecast'!E$6 -> 33497303 | G42: =G35*'RVO Forecast'!F$6 -> 47231151 | H42: =H35*'RVO Forecast'!G$6 -> 1.2771936e+08 | I42: =I35*'RVO Forecast'!H$6 -> 2.933604e+08 | J42: =J35*'RVO Forecast'!I$6 -> 3.0339361e+08 | K42: =K35*'RVO Forecast'!J$6 -> 2.3009e+08 | L42: =L35*'RVO Forecast'!K$6 -> 1.5639012e+08 | ... AP42: =AP35*'RVO Forecast'!AO$6 -> 1.2236197e+08 | BH42: 3.0009425e+08 | BI42: =J42-BH42 -> 3299367 | BJ42: 318942800 | BK42: =K42-BJ42 -> -88852800
A43: Advanced Biofuel | E43: =E36*'RVO Forecast'!D$6 -> 32076000 | F43: =F36*'RVO Forecast'!E$6 -> 34730000 | G43: =G36*'RVO Forecast'!F$6 -> 49734000 | H43: =H36*'RVO Forecast'!G$6 -> 157182000 | I43: =I36*'RVO Forecast'!H$6 -> 405790000 | J43: =J36*'RVO Forecast'!I$6 -> 6.2545259e+08 | K43: =K36*'RVO Forecast'!J$6 -> 360430000 | L43: =L36*'RVO Forecast'!K$6 -> 209202000 | ... AP43: =AP36*'RVO Forecast'!AO$6 -> 1.0016729e+09 | BH43: 6.1871702e+08 | BI43: =J43-BH43 -> 6735570 | BJ43: 499615600 | BK43: =K43-BJ43 -> -139185600
A44: Renewable Fuel | E44: =E45+E43 -> 192852000 | F44: =F45+F43 -> 2.1137e+08 | G44: =G45+G43 -> 2.92264e+08 | H44: =H45+H43 -> 789820000 | I44: =I45+I43 -> 1824350000 | J44: =J45+J43 -> 2.0412886e+09 | K44: =K45+K43 -> 1459010000 | L44: =L45+L43 -> 772548000 | ... AP44: =AP45+AP43 -> 1.4605272e+09 | BH44: 2017953024 | BI44: =J44-BH44 -> 23335570 | BJ44: 2.0224292e+09 | BK44: =K44-BJ44 -> -5.634192e+08
A45: Implied Ethanol | E45: =E38 -> 160776000 | F45: =F38 -> 1.7664e+08 | G45: =G38 -> 2.4253e+08 | H45: =H38 -> 632638000 | I45: =I38 -> 1418560000 | J45: =J38 -> 1415836000 | K45: =K38 -> 1098580000 | L45: =L38 -> 563346000 | ... AP45: =AP38 -> 4.5885434e+08 | BH45: 1399236000 | BI45: =J45-BH45 -> 16600000 | BJ45: 1.5228136e+09 | BK45: =K45-BJ45 -> -4.242336e+08
A47: RINs Exempt by Fuel Code
A48: D3 | E48: ='Small Refinery Exemptions'!E41*('[1]D3 RIN Forecast'!E$15/('[1]D3 RIN Forecast'!E$15+'[1]D7 RIN Forecast'!E$13)) -> 40904.475 | F48: ='Small Refinery Exemptions'!F41*('[1]D3 RIN Forecast'!F$15/('[1]D3 RIN Forecast'!F$15+'[1]D7 RIN Forecast'!F$13)) -> 436224.52 | G48: ='Small Refinery Exemptions'!G41*('[1]D3 RIN Forecast'!G$15/('[1]D3 RIN Forecast'!G$15+'[1]D7 RIN Forecast'!G$13)) -> 2114202.1 | H48: ='Small Refinery Exemptions'!H41*('[1]D3 RIN Forecast'!H$15/('[1]D3 RIN Forecast'!H$15+'[1]D7 RIN Forecast'!H$13)) -> 9981867.9 | I48: ='Small Refinery Exemptions'!I41*('[1]D3 RIN Forecast'!I$15/('[1]D3 RIN Forecast'!I$15+'[1]D7 RIN Forecast'!I$13)) -> 29292676 | J48: ='Small Refinery Exemptions'!J41*('[1]D3 RIN Forecast'!J$15/('[1]D3 RIN Forecast'!J$15+'[1]D7 RIN Forecast'!J$13)) -> 27374867 | K48: ='Small Refinery Exemptions'!K41*('[1]D3 RIN Forecast'!K$15/('[1]D3 RIN Forecast'!K$15+'[1]D7 RIN Forecast'!K$13)) -> 30493103 | L48: ='Small Refinery Exemptions'!L41*('[1]D3 RIN Forecast'!L$15/('[1]D3 RIN Forecast'!L$15+'[1]D7 RIN Forecast'!L$13)) -> 20703713 | ... O48: ='Small Refinery Exemptions'!O41*('[1]D3 RIN Forecast'!O$15/('[1]D3 RIN Forecast'!O$15+'[1]D7 RIN Forecast'!O$13)) -> 26872039 | P48: ='Small Refinery Exemptions'!P41*('[1]D3 RIN Forecast'!P$15/('[1]D3 RIN Forecast'!P$15+'[1]D7 RIN Forecast'!AE$13)) -> 36666000 | Q48: ='Small Refinery Exemptions'!Q41*('[1]D3 RIN Forecast'!Q$15/('[1]D3 RIN Forecast'!Q$15+'[1]D7 RIN Forecast'!AF$13)) -> 54027000 | R48: ='Small Refinery Exemptions'!R41*('[1]D3 RIN Forecast'!R$15/('[1]D3 RIN Forecast'!R$15+'[1]D7 RIN Forecast'!AG$13)) -> 55932598 | S48: ='Small Refinery Exemptions'!S41*('[1]D3 RIN Forecast'!S$15/('[1]D3 RIN Forecast'!S$15+'[1]D7 RIN Forecast'!AH$13)) -> 63843550 | T48: ='Small Refinery Exemptions'!T41*('[1]D3 RIN Forecast'!T$15/('[1]D3 RIN Forecast'!T$15+'[1]D7 RIN Forecast'!AI$13)) -> 53502965 | U48: ='Small Refinery Exemptions'!U41*('[1]D3 RIN Forecast'!U$15/('[1]D3 RIN Forecast'!U$15+'[1]D7 RIN Forecast'!AJ$13)) -> 1.3057466e+08 | V48: ='Small Refinery Exemptions'!V41*('[1]D3 RIN Forecast'!V$15/('[1]D3 RIN Forecast'!V$15+'[1]D7 RIN Forecast'!AK$13)) -> 1.4080677e+08 | W48: ='Small Refinery Exemptions'!W41*('[1]D3 RIN Forecast'!W$15/('[1]D3 RIN Forecast'!W$15+'[1]D7 RIN Forecast'!AL$13)) -> 1.3099325e+08 | ... AP48: ='Small Refinery Exemptions'!AP41*('[1]D3 RIN Forecast'!AP$15/('[1]D3 RIN Forecast'!AP$15+'[1]D7 RIN Forecast'!BE$13)) -> #DIV/0! | BH48: 27059343 | BI48: =J48-BH48 -> 315523.9 | BJ48: 42008812 | BK48: =K48-BJ48 -> -11515709
A49: D4 | E49: =E42-E52 -> 22961026 | F49: =F42-F52 -> 33496527 | G49: =G42-G52 -> 47227053 | H49: =H42-H52 -> 1.2769163e+08 | I49: =I42-I52 -> 2.9315657e+08 | J49: =J42-J52 -> 3.0317878e+08 | K49: =K42-K52 -> 2.299931e+08 | L49: =L42-L52 -> 1.5638784e+08 | ... AP49: =AP42-AP52 -> #DIV/0! | BH49: 2.9988189e+08 | BI49: =J49-BH49 -> 3296890.9 | BJ49: 3.1854881e+08 | BK49: =K49-BJ49 -> -88555709
A50: D5 | E50: =E43-E49-E48-E52 -> 9035773.8 | F50: =F43-F49-F48-F52 -> 796472.5 | G50: =G43-G49-G48-G52 -> 388647.34 | H50: =H43-H49-H48-H52 -> 19480768 | I50: =I43-I49-I48-I52 -> 83136929 | J50: =J43-J49-J48-J52 -> 2.9468411e+08 | K50: =K43-K49-K48-K52 -> 99846897 | L50: =L43-L49-L48-L52 -> 32108164 | ... AP50: =AP43-AP49-AP48-AP52 -> #DIV/0! | BG50: =395/20940 -> 0.018863419 | BH50: 2.9156343e+08 | BI50: =J50-BH50 -> 3120679.1 | BJ50: 1.3866399e+08 | BK50: =K50-BJ50 -> -38817091
A51: D6 | E51: =E38 -> 160776000 | F51: =F38 -> 1.7664e+08 | G51: =G38 -> 2.4253e+08 | H51: =H38 -> 632638000 | I51: =I38 -> 1418560000 | J51: =J38 -> 1415836000 | K51: =K38 -> 1098580000 | L51: =L38 -> 563346000 | ... AP51: =AP38 -> 4.5885434e+08 | BG51: =826/21540 -> 0.038347261 | BH51: 1399236000 | BI51: =J51-BH51 -> 16600000 | BJ51: 1.5228136e+09 | BK51: =K51-BJ51 -> -4.242336e+08
A52: D7 | E52: =E41-E48 -> 38295.525 | F52: =F41-F48 -> 775.47545 | G52: =G41-G48 -> 4097.9341 | H52: =H41-H48 -> 27732.116 | I52: =I41-I48 -> 203824.16 | J52: =J41-J48 -> 214833.34 | K52: =K41-K48 -> 96896.826 | L52: =L41-L48 -> 2287.4787 | ... AP52: =AP41-AP48 -> #DIV/0! | BG52: =1116/22330 -> 0.049977609 | BH52: 212357.24 | BI52: =J52-BH52 -> 2476.1029 | BJ52: 393987.69 | BK52: =K52-BJ52 -> -297090.86
H53: =SUM(H48:H52) -> 789820000 | I53: =SUM(I48:I52) -> 1824350000 | J53: =SUM(J48:J52) -> 2.0412886e+09
A54: Gallons Exempt by Fuel Code
A55: D3 | E55: =E48 -> 40904.475 | F55: =F48 -> 436224.52 | G55: =G48 -> 2114202.1 | H55: =H48 -> 9981867.9 | I55: =I48 -> 29292676 | J55: =J48 -> 27374867 | K55: =K48 -> 30493103 | L55: =L48 -> 20703713 | ... AP55: =AP48 -> #DIV/0!
A56: D4 | E56: =E49/'RVO Forecast'!D$6 -> 14891164 | F56: =F49/'RVO Forecast'!E$6 -> 21619499 | G56: =G49/'RVO Forecast'!F$6 -> 30492687 | H56: =H49/'RVO Forecast'!G$6 -> 82874001 | I56: =I49/'RVO Forecast'!H$6 -> 1.8969145e+08 | J56: =J49/'RVO Forecast'!I$6 -> 1.9604042e+08 | K56: =K49/'RVO Forecast'!J$6 -> 1.4696762e+08 | L56: =L49/'RVO Forecast'!K$6 -> 99958538 | ... AP56: =AP49/'RVO Forecast'!AO$6 -> #DIV/0!
A57: D5 | E57: =E50 -> 9035773.8 | F57: =F50/'RVO Forecast'!E6 -> 514063.34 | G57: =G50/'RVO Forecast'!F6 -> 250934.6 | H57: =H50/'RVO Forecast'!G6 -> 12643344 | I57: =I50/'RVO Forecast'!H6 -> 53795022 | J57: =J50/'RVO Forecast'!I6 -> 1.9054763e+08 | K57: =K50/'RVO Forecast'!J6 -> 63803046 | L57: =L50/'RVO Forecast'!K6 -> 20522601 | M57: =M50/'RVO Forecast'!L6 -> 20090235 | ... AP57: =AP50/'RVO Forecast'!AO6 -> #DIV/0!
A58: D6 | E58: =E51 -> 160776000 | F58: =F51 -> 1.7664e+08 | G58: =G51 -> 2.4253e+08 | H58: =H51 -> 632638000 | I58: =I51 -> 1418560000 | J58: =J51 -> 1415836000 | K58: =K51 -> 1098580000 | L58: =L51 -> 563346000 | ... AP58: =AP51 -> 4.5885434e+08
A59: D7 | E59: =E52 -> 38295.525 | F59: =F52 -> 775.47545 | G59: =G52 -> 4097.9341 | H59: =H52 -> 27732.116 | I59: =I52 -> 203824.16 | J59: =J52 -> 214833.34 | K59: =K52 -> 96896.826 | L59: =L52 -> 2287.4787 | ... AP59: =AP52 -> #DIV/0!
A61: DOE Recommended RINs | G61: 290000000 | H61: 440000000 | I61: 1020000000 | J61: 840000000
A63: 2016 - 2018 Percentage Standards
A64: Cellulosic Biofuel | B64: 0.31 | L64: =B64/100*L$31 -> 22134000
A65: Biomass-Based Diesel | B65: 2.08 | L65: =B65/100*L$31 -> 148512000
A66: Advanced Biofuel | B66: 2.88 | L66: =B66/100*L$31/1/'RVO Forecast'!K6 -> 1.3143397e+08 | BH66: =B66/100*'RVO Forecast'!K$8 -> 4.93344e+08
A67: Renewable Fuel | B67: 11.46 | L67: =B67/100*L$31 -> 818244000 | BH67: =B67/100*'RVO Forecast'!K$8 -> 1963098000
A68: Implied Ethanol | B68: =BH68*100 -> 8.58 | L68: =B68/100*L$31 -> 6.12612e+08 | BH68: =(BH67-BH66)/'RVO Forecast'!K$8 -> 0.0858
A70: 2015 - 2017 Percentage Standards
A71: Cellulosic Biofuel | B71: 0.31
A72: Biomass-Based Diesel | B72: 2.06
A73: Advanced Biofuel | B73: 2.85 | BH73: =B73/100*'RVO Forecast'!K$8 -> 4.88205e+08
A74: Renewable Fuel | B74: 11.35 | BH74: =B74/100*'RVO Forecast'!K$8 -> 1.944255e+09
A75: Implied Ethanol | B75: =BH75*100 -> 8.5 | BH75: =(BH74-BH73)/'RVO Forecast'!K$8 -> 0.085

Sheet Final % Std
A1: Step 1. - Gather the following data
C2: ='RVO Forecast'!B1 -> 2011 | D2: ='RVO Forecast'!C1 -> 2012 | E2: ='RVO Forecast'!D1 -> 2013 | F2: ='RVO Forecast'!E1 -> 2014 | G2: ='RVO Forecast'!F1 -> 2015 | H2: ='RVO Forecast'!G1 -> 2016 | I2: ='RVO Forecast'!H1 -> 2017 | J2: ='RVO Forecast'!I1 -> 2018 | ... R2: ='RVO Forecast'!Q1 -> 2026
B3: Total RVO | C3: ='RVO Forecast'!B8 -> 13950000000 | D3: ='RVO Forecast'!C8 -> 15200000000 | E3: ='RVO Forecast'!D8 -> 16550000000 | F3: ='RVO Forecast'!E8 -> 16280000000 | G3: ='RVO Forecast'!F8 -> 16930000000 | H3: ='RVO Forecast'!G8 -> 18110000000 | I3: ='RVO Forecast'!H8 -> 19280000000 | J3: ='RVO Forecast'!I8 -> 19290000000 | ... R3: ='RVO Forecast'!Q8 -> 24020000000
B4: Advanced RVO | C4: 1350000000 | D4: 2000000000 | E4: 2750000000 | F4: 2670000000 | G4: 2880000000 | H4: 3610000000 | I4: 4280000000 | J4: ='[2]10 Year RFS Curves (2020)'!C$20*1000000000 -> 4290000000 | K4: ='[2]10 Year RFS Curves (2020)'!D$20*1000000000 -> 4920000000 | L4: ='[2]10 Year RFS Curves (2020)'!E$20*1000000000 -> 4630000000 | M4: ='[2]10 Year RFS Curves (2020)'!F$20*1000000000 -> 5050000000 | N4: ='[2]10 Year RFS Curves (2020)'!G$20*1000000000 -> 5630000000 | O4: ='[2]10 Year RFS Curves (2020)'!H$20*1000000000 -> 5940000000 | P4: ='[2]10 Year RFS Curves (2020)'!I$20*1000000000 -> 6540000000 | Q4: ='[2]10 Year RFS Curves (2020)'!J$20*1000000000 -> 7330000000 | R4: ='[2]10 Year RFS Curves (2020)'!K$20*1000000000 -> 9020000000
B5: BBD RVO | C5: ='RVO Forecast'!B10 -> 800000000 | D5: ='RVO Forecast'!C10 -> 1000000000 | E5: ='RVO Forecast'!D10 -> 1280000000 | F5: ='RVO Forecast'!E10 -> 1630000000 | G5: ='RVO Forecast'!F10 -> 1730000000 | H5: ='RVO Forecast'!G10 -> 1900000000 | I5: ='RVO Forecast'!H10 -> 2000000000 | J5: ='RVO Forecast'!I10 -> 2100000000 | ... R5: ='RVO Forecast'!Q10 -> 7120000000
B6: Cellulosic RVO | C6: ='RVO Forecast'!B14 -> 0 | D6: ='RVO Forecast'!C14 -> 0 | E6: ='RVO Forecast'!D14 -> 800000 | F6: ='RVO Forecast'!E14 -> 33000000 | G6: ='RVO Forecast'!F14 -> 123000000 | H6: ='RVO Forecast'!G14 -> 230000000 | I6: ='RVO Forecast'!H14 -> 311000000 | J6: ='RVO Forecast'!I14 -> 288000000 | ... R6: ='RVO Forecast'!Q14 -> 1300000000
B7: Implied Ethanol RVO | C7: =C3-C4-C5-C6 -> 11800000000 | D7: =D3-D4-D5-D6 -> 12200000000 | E7: =E3-E4-E5-E6 -> 12519200000 | F7: =F3-F4-F5-F6 -> 11947000000 | G7: =G3-G4-G5-G6 -> 12197000000 | H7: =H3-H4-H5-H6 -> 12370000000 | I7: =I3-I4-I5-I6 -> 12689000000 | J7: =J3-J4-J5-J6 -> 12612000000 | ... R7: =R3-R4-R5-R6 -> 6580000000
B8: Supplemental RVO | C8: 0 | D8: 0 | E8: 0 | F8: 0 | G8: 0 | H8: 0 | I8: 0 | J8: 0 | K8: 0 | L8: 0 | M8: 0 | N8: 250000000 | O8: 0 | P8: 0 | Q8: 0 | R8: 0
B9: Gasoline Demand | C9: =C14 -> 138000000000 | D9: =D14 -> 139000000000 | E9: =E14 -> 137000000000 | F9: =F14 -> 135000000000 | G9: =G14 -> 134000000000 | H9: =H14 -> 135000000000 | I9: =I14 -> 136000000000 | J9: =J14 -> 137000000000 | ... R9: =R14 -> 0
B10: Ethanol Supply | C10: ='[1]Monthly Gallon Summary'!C$304 -> 13802805925 | D10: ='[1]Monthly Gallon Summary'!D$304 -> 13590204834 | E10: ='[1]Monthly Gallon Summary'!E$304 -> 13557221593 | F10: ='[1]Monthly Gallon Summary'!F$304 -> 14145535990 | G10: ='[1]Monthly Gallon Summary'!G$304 -> 14649144465 | H10: ='[1]Monthly Gallon Summary'!H$304 -> 14978434370 | I10: ='[1]Monthly Gallon Summary'!I$304 -> 15214237066 | J10: ='[1]Monthly Gallon Summary'!J$304 -> 15381973558 | ... R10: ='[1]Monthly Gallon Summary'!R$304 -> 1.5472585e+10
B11: Gasoline Exemptions | C11: ='Small Refinery Exemptions'!C38 -> 0 | D11: ='Small Refinery Exemptions'!D38 -> 0 | E11: ='Small Refinery Exemptions'!E38 -> 160776000 | F11: ='Small Refinery Exemptions'!F38 -> 1.7664e+08 | G11: ='Small Refinery Exemptions'!G38 -> 2.4253e+08 | H11: ='Small Refinery Exemptions'!H38 -> 632638000 | I11: ='Small Refinery Exemptions'!I38 -> 1418560000 | J11: ='Small Refinery Exemptions'!J38 -> 1415836000 | ... R11: ='Small Refinery Exemptions'!R38 -> 6.4754988e+08
B12: Net Renewable Gasoline Demand | C12: =C10-C11 -> 13802805925 | D12: =D10-D11 -> 13590204834 | E12: =E10-E11 -> 13396445593 | F12: =F10-F11 -> 13968895990 | G12: =G10-G11 -> 14406614465 | H12: =H10-H11 -> 14345796370 | I12: =I10-I11 -> 13795677066 | J12: =J10-J11 -> 13966137558 | ... R12: =R10-R11 -> 1.4825035e+10
B13: Gasoline Classic Demand | C13: =C9-C12 -> 124197194075 | D13: =D9-D12 -> 125409795166 | E13: =E9-E12 -> 123603554407 | F13: =F9-F12 -> 121031104010 | G13: =G9-G12 -> 119593385535 | H13: =H9-H12 -> 120654203630 | I13: =I9-I12 -> 122204322934 | J13: =J9-J12 -> 123033862442 | ... R13: =R9-R12 -> -1.4825035e+10
B14: EPA Gasoline Demand | C14: 138000000000 | D14: 139000000000 | E14: 137000000000 | F14: 135000000000 | G14: 134000000000 | H14: 135000000000 | I14: 136000000000 | J14: 137000000000 | K14: 137000000000 | L14: 125000000000 | M14: 130000000000 | N14: 135000000000 | O14: 140000000000 | P14: 141000000000 | Q14: 142000000000
B15: EPA Diesel Demand | C15: 50000000000 | D15: 51000000000 | E15: 52000000000 | F15: 53000000000 | G15: 54000000000 | H15: 54000000000 | I15: 55000000000 | J15: 55000000000 | K15: 55000000000 | L15: 60000000000 | M15: 52000000000 | N15: 54000000000 | O15: 56000000000 | P15: 57000000000 | Q15: 58000000000
B17: Demand
B18: Diesel Demand | C18: =C15 -> 50000000000 | D18: =D15 -> 51000000000 | E18: =E15 -> 52000000000 | F18: =F15 -> 53000000000 | G18: =G15 -> 54000000000 | H18: =H15 -> 54000000000 | I18: =I15 -> 55000000000 | J18: =J15 -> 55000000000 | ... Q18: =Q15 -> 58000000000 | R18: =FORECAST(R2,C18:Q18,C2:Q2) -> 5.7885714e+10
B19: Biomass-Based Diesel Supply | C19: ='[1]Monthly Gallon Summary'!C$176 -> 1143591192 | D19: ='[1]Monthly Gallon Summary'!D$176 -> 1159850473 | E19: ='[1]Monthly Gallon Summary'!E$176 -> 1987866219 | F19: ='[1]Monthly Gallon Summary'!F$176 -> 1976615894 | G19: ='[1]Monthly Gallon Summary'!G$176 -> 2103082154 | H19: ='[1]Monthly Gallon Summary'!H$176 -> 2898448908 | I19: ='[1]Monthly Gallon Summary'!I$176 -> 2652888204 | J19: ='[1]Monthly Gallon Summary'!J$176 -> 2645925155 | ... R19: ='[1]Monthly Gallon Summary'!R$176 -> 4.6151765e+09
B20: Diesel Exemptions | C20: ='Small Refinery Exemptions'!C35 -> 5662444.4 | D20: ='Small Refinery Exemptions'!D35 -> 3.3974667e+08 | E20: ='Small Refinery Exemptions'!E35 -> 14916000 | F20: ='Small Refinery Exemptions'!F35 -> 21620000 | G20: ='Small Refinery Exemptions'!G35 -> 30495333 | H20: ='Small Refinery Exemptions'!H35 -> 82892000 | I20: ='Small Refinery Exemptions'!I35 -> 1.8982333e+08 | J20: ='Small Refinery Exemptions'!J35 -> 1.9617933e+08 | ... R20: ='Small Refinery Exemptions'!R35 -> 2.7041154e+08
B21: Net Biomass-Based Diesel Demand | C21: =C19-C20 -> 1.1379287e+09 | D21: =D19-D20 -> 8.2010381e+08 | E21: =E19-E20 -> 1972950219 | F21: =F19-F20 -> 1954995894 | G21: =G19-G20 -> 2.0725868e+09 | H21: =H19-H20 -> 2815556908 | I21: =I19-I20 -> 2.4630649e+09 | J21: =J19-J20 -> 2449745822 | ... R21: =R19-R20 -> 4.344765e+09
B22: Diesel Classic Demand | C22: =C18-C21 -> 4.8862071e+10 | D22: =D18-D21 -> 5.0179896e+10 | E22: =E18-E21 -> 50027049781 | F22: =F18-F21 -> 51045004106 | G22: =G18-G21 -> 5.1927413e+10 | H22: =H18-H21 -> 51184443092 | I22: =I18-I21 -> 5.2536935e+10 | J22: =J18-J21 -> 52550254178 | ... R22: =R18-R21 -> 5.3540949e+10
B24: Total Fuel Demand for Calculation | C24: =C22+C13 -> 1.7305927e+11 | D24: =D22+D13 -> 1.7558969e+11 | E24: =E22+E13 -> 173630604188 | F24: =F22+F13 -> 172076108116 | G24: =G22+G13 -> 1.715208e+11 | H24: =H22+H13 -> 171838646722 | I24: =I22+I13 -> 1.7474126e+11 | J24: =J22+J13 -> 175584116620 | ... R24: =R22+R13 -> 3.8715914e+10
B25: EPA Demand for Calculation | I25: =I3/I24 -> 0.11033456 | J25: =J3/J24 -> 0.10986187 | K25: =K3/K24 -> 0.11378114 | L25: =L3/L24 -> 0.10130673 | M25: =M3/M24 -> 0.11432716 | N25: =N3/N24 -> 0.12086121 | O25: =O3/O24 -> 0.11897185 | P25: =P3/P24 -> 0.12158228 | ... R25: =R3/R24 -> 0.6204167
B26: Mandates
B27: Cellulosic | C27: =C6 -> 0 | D27: =D6 -> 0 | E27: =E6 -> 800000 | F27: =F6 -> 33000000 | G27: =G6 -> 123000000 | H27: =H6 -> 230000000 | I27: =I6 -> 311000000 | J27: =J6 -> 288000000 | ... R27: =R6 -> 1300000000
B28: Biomass-Based Diesel | C28: =C5 -> 800000000 | D28: =D5 -> 1000000000 | E28: =E5 -> 1280000000 | F28: =F5 -> 1630000000 | G28: =G5 -> 1730000000 | H28: =H5 -> 1900000000 | I28: =I5 -> 2000000000 | J28: =J5 -> 2100000000 | ... R28: =R5 -> 7120000000
B29: Advanced | C29: =C4 -> 1350000000 | D29: =D4 -> 2000000000 | E29: =E4 -> 2750000000 | F29: =F4 -> 2670000000 | G29: =G4 -> 2880000000 | H29: =H4 -> 3610000000 | I29: =I4 -> 4280000000 | J29: =J4 -> 4290000000 | ... R29: =R4 -> 9020000000
B30: Total | C30: =C3 -> 13950000000 | D30: =D3 -> 15200000000 | E30: =E3 -> 16550000000 | F30: =F3 -> 16280000000 | G30: =G3 -> 16930000000 | H30: =H3 -> 18110000000 | I30: =I3 -> 19280000000 | J30: =J3 -> 19290000000 | ... R30: =R3 -> 24020000000
B31: Ethanol | C31: ='RVO Forecast'!B49 -> 12600000000 | D31: ='RVO Forecast'!C49 -> 13200000000 | E31: ='RVO Forecast'!D49 -> 13880000000 | F31: ='RVO Forecast'!E49 -> 13610000000 | G31: ='RVO Forecast'!F49 -> 14050000000 | H31: ='RVO Forecast'!G49 -> 14500000000 | I31: ='RVO Forecast'!H49 -> 15000000000 | J31: ='RVO Forecast'!I49 -> 15000000000 | ... R31: ='RVO Forecast'!Q49 -> 1.5e+10
B32: Supplemental | C32: =C8 -> 0 | D32: =D8 -> 0 | E32: =E8 -> 0 | F32: =F8 -> 0 | G32: =G8 -> 0 | H32: =H8 -> 0 | I32: =I8 -> 0 | J32: =J8 -> 0 | ... R32: =R8 -> 0
B34: Percentage Standards
B35: Cellulosic | C35: =C27/C24 -> 0 | D35: =D27/D24 -> 0 | E35: =E27/E24 -> 4.6074827e-06 | F35: =F27/F24 -> 0.00019177561 | G35: =G27/G24 -> 0.0007171142 | H35: =H27/H24 -> 0.0013384649 | I35: =I27/I24 -> 0.0017797743 | J35: =J27/J24 -> 0.0016402395 | ... R35: =R27/R24 -> 0.033577923
B36: BBD | C36: =C28/C24 -> 0.0046226938 | D36: =D28/D24 -> 0.0056950952 | E36: =E28/E24 -> 0.0073719723 | F36: =F28/F24 -> 0.0094725527 | G36: =G28/G24 -> 0.01008624 | H36: =H28/H24 -> 0.011056884 | I36: =I28/I24 -> 0.011445494 | J36: =J28/J24 -> 0.01196008 | ... R36: =R28/R24 -> 0.1839037
B37: Advanced | C37: =C29/C24 -> 0.0078007959 | D37: =D29/D24 -> 0.01139019 | E37: =E29/E24 -> 0.015838222 | F37: =F29/F24 -> 0.01551639 | G37: =G29/G24 -> 0.016790967 | H37: =H29/H24 -> 0.02100808 | I37: =I29/I24 -> 0.024493357 | J37: =J29/J24 -> 0.024432734 | ... R37: =R29/R24 -> 0.23297913
B38: Ethanol | C38: =C31/C24-SUM(C35:C37) -> 0.060383938 | D38: =D31/D24-SUM(D35:D37) -> 0.058089971 | E38: =E31/E24-SUM(E35:E37) -> 0.056725023 | F38: =F31/F24-SUM(F35:F37) -> 0.053912191 | G38: =G31/G24-SUM(G35:G37) -> 0.054319943 | H38: =H31/H24-SUM(H35:H37) -> 0.050978055 | I38: =I31/I24-SUM(I35:I37) -> 0.048122579 | J38: =J31/J24-SUM(J35:J37) -> 0.047396087 | ... R38: =R31/R24-SUM(R35:R37) -> -0.063023179
B39: Supplemental - if applicable | C39: #N/A | D39: #N/A | E39: #N/A | F39: #N/A | G39: #N/A | H39: #N/A | I39: #N/A | J39: #N/A | K39: #N/A | L39: #N/A | M39: #N/A | N39: #N/A | O39: #N/A | P39: #N/A | Q39: #N/A | R39: #N/A
B40: Total | C40: =C30/C24 -> 0.080608224 | D40: =D30/D24 -> 0.086565446 | E40: =E30/E24 -> 0.095317298 | F40: =F30/F24 -> 0.094609299 | G40: =G30/G24 -> 0.098705231 | H40: =H30/H24 -> 0.10538956 | I40: =I30/I24 -> 0.11033456 | J40: =J30/J24 -> 0.10986187 | ... R40: =R30/R24 -> 0.6204167
A42: Step 2. Find or Estimate/Predict the EPA Final Percent Standards
C43: =C2 -> 2011 | D43: =D2 -> 2012 | E43: =E2 -> 2013 | F43: =F2 -> 2014 | G43: =G2 -> 2015 | H43: =H2 -> 2016 | I43: =I2 -> 2017 | J43: =J2 -> 2018 | ... Q43: =Q2 -> 2025
B44: Cellulosic | L44: ='Small Refinery Exemptions'!L25 -> 0.0029 | M44: ='Small Refinery Exemptions'!M25 -> 0.0033 | N44: ='Small Refinery Exemptions'!N25 -> 0.0035 | O44: 0.0048 | P44: 0.0063 | Q44: 0.0081
B45: BBD | L45: ='Small Refinery Exemptions'!L26 -> 0.021 | M45: ='Small Refinery Exemptions'!M26 -> 0.0216 | N45: ='Small Refinery Exemptions'!N26 -> 0.0233 | O45: 0.0258 | P45: 0.0282 | Q45: 0.0315
B46: Advanced | L46: ='Small Refinery Exemptions'!L27 -> 0.0293 | M46: ='Small Refinery Exemptions'!M27 -> 0.03 | N46: ='Small Refinery Exemptions'!N27 -> 0.0316 | O46: 0.0339 | P46: 0.0379 | Q46: 0.0431
B47: Total | L47: ='Small Refinery Exemptions'!L28 -> 0.1009 | M47: ='Small Refinery Exemptions'!M28 -> 0.1119 | N47: ='Small Refinery Exemptions'!N28 -> 0.1159 | O47: 0.1196 | P47: 0.125 | Q47: 0.1313
B48: Supplemental - if applicable | Q48: n/a
A50: Step 3. Multiply the Total RVO by the "Total" Percent Standard
B51: Total RVO X Total Percent | C51: =C47*C3 -> 0 | D51: =D47*D3 -> 0 | E51: =E47*E3 -> 0 | F51: =F47*F3 -> 0 | G51: =G47*G3 -> 0 | H51: =H47*H3 -> 0 | I51: =I47*I3 -> 0 | J51: =J47*J3 -> 0 | ... Q51: =Q47*Q3 -> 2931929000
A53: Step 4. Multiply the Advanced RVO by the Product of the Previous Step
B54: Advanced RVO X Advanced Percent | C54: =C4*C46 -> 0 | D54: =D4*D46 -> 0 | E54: =E4*E46 -> 0 | F54: =F4*F46 -> 0 | G54: =G4*G46 -> 0 | H54: =H4*H46 -> 0 | I54: =I4*I46 -> 0 | J54: =J4*J46 -> 0 | ... Q54: =Q4*Q46 -> 315923000
A56: Step 5. Multiply the Total Percentage by the Product of Step 3
B57: Total Percent X Product in Step 2 | C57: =C47*C51 -> 0 | D57: =D47*D51 -> 0 | E57: =E47*E51 -> 0 | F57: =F47*F51 -> 0 | G57: =G47*G51 -> 0 | H57: =H47*H51 -> 0 | I57: =I47*I51 -> 0 | J57: =J47*J51 -> 0 | ... Q57: =Q47*Q51 -> 3.8496228e+08
A59: Step 6. Subtract the Product of Step 4 from the Product of Step 5
B60: Total Percentage Volume - Advanced Percentage Volume | C60: =C57-C54 -> 0 | D60: =D57-D54 -> 0 | E60: =E57-E54 -> 0 | F60: =F57-F54 -> 0 | G60: =G57-G54 -> 0 | H60: =H57-H54 -> 0 | I60: =I57-I54 -> 0 | J60: =J57-J54 -> 0 | ... Q60: =Q57-Q54 -> 69039278
A62: Step 7. Divide the Remaining Total Percentage Volume by the Total Renewable Fuel Volume
B63: Result of Step 6 / Total Percentage Volume | C63: =C60/C51 -> #DIV/0! | D63: =D60/D51 -> #DIV/0! | E63: =E60/E51 -> #DIV/0! | F63: =F60/F51 -> #DIV/0! | G63: =G60/G51 -> #DIV/0! | H63: =H60/H51 -> #DIV/0! | I63: =I60/I51 -> #DIV/0! | J63: =J60/J51 -> #DIV/0! | ... Q63: =Q60/Q51 -> 0.023547391
B64: This is the implied ethanol total percentage standard

Sheet RFS % Std Formula
E1: Pandemic Effect | F1: Billions of Gallons
A2: 2020 | D2: Billions of Gallons | E2: Final RFS for 2020 and BBD 2021 | F2: Final RFS for 2020 and BBD 2021 | G2: Proposed values from July NPR | H2: Proposed Based on 2016-2018 est | I2: Proposed Based on 2015-2017 est
A3: Term | B3: Description | D3: Steo 2021 @6/3/21
A4: RFVcb | B4: Required Cellulosic Volume | D4: 0.59 | F4: 0.59 | G4: 0.54 | H4: 0.54 | I4: 0.54
A5: RFVbbd | B5: Required BBD Volume x 1.5 | D5: =2.43*1.5 -> 3.645 | F5: =2.43*1.5 -> 3.645 | G5: =2.43*1.5 -> 3.645 | H5: =2.43*1.5 -> 3.645 | I5: =2.43*1.5 -> 3.645
A6: RFVab | B6: Required Advanced Bio Volume | D6: 5.09 | F6: 5.09 | G6: 5.04 | H6: 5.04 | I6: 5.04 | J6: =+F5+F4 -> 4.235
A7: RFVrf | B7: Required Volume of renewable fuel | D7: 19.92 | F7: 20.09 | G7: 20.04 | H7: 20.04 | I7: 20.04 | J7: =+F6-J6 -> 0.855
A8: G | B8: Projected volume of gasoline | D8: =8.74*42*365/1000 -> 133.9842 | E8: =+G85 -> 122.467 | F8: 142.68 | G8: 143.49 | H8: 142.49 | I8: 142.49
A9: D | B9: Projected volume of diesel | D9: =3.8*42*365/1000 -> 58.254 | E9: =+I85 -> 53.22625 | F9: 55.3 | G9: 57.06 | H9: 56.77 | I9: 56.77
A10: RG | B10: Projected volume of renewables in gas | C10: =+D8*0.1 -> 13.39842 | D10: =0.898*42*365/1000 -> 13.76634 | E10: 14.42 | F10: 14.42 | G10: 14.62 | H10: 14.58 | I10: 14.58
A11: RD | B11: Projected volume of renewables in diesel | D11: =0.145*42*365/1000 -> 2.22285 | E11: 2.48 | F11: 2.48 | G11: 2.48 | H11: 2.48 | I11: 2.48
A12: GS | B12: Projected volume of gasoline for opt-in areas | D12: 0 | E12: 0 | F12: 0 | G12: 0 | H12: 0 | I12: 0
A13: RGS | B13: Projected volume of renewables in gasoline for opt-in areas | D13: 0 | E13: 0 | F13: 0 | G13: 0 | H13: 0 | I13: 0
A14: DS | B14: Projected volume of diesel for opt-in areas | D14: 0 | E14: 0 | F14: 0 | G14: 0 | H14: 0 | I14: 0
A15: RDS | B15: Projected volume of renewablse in diesel for opt-in areas | D15: 0 | E15: 0 | F15: 0 | G15: 0 | H15: 0 | I15: 0
A16: GE | B16: Projected volume of exempt gasoline | D16: 4.17 | E16: 4.24 | F16: 4.24 | G16: 0 | H16: 4.24 | I16: 3.23
A17: DE | B17: Projected volum of exempt diesel | D17: 3.02 | E17: 3.02 | F17: 3.02 | G17: 0 | H17: 3.02 | I17: 2.42
B19: Estimated from SRE page Column E, 362 | D19: 2019 final rule
A20: Numerator | B20: =+A7 -> RFVrf | D20: 19.92 | F20: =+F7 -> 20.09 | G20: =+G7 -> 20.04 | H20: =+H7 -> 20.04 | I20: =+I7 -> 20.04
A22: Denominator | B22: (G-RG) | D22: =+D8-D10 -> 120.21786 | E22: =+E8-E10 -> 108.047 | F22: =+F8-F10 -> 128.26 | G22: =+G8-G10 -> 128.87 | H22: =+H8-H10 -> 127.91 | I22: =+I8-I10 -> 127.91
B23: GS-RGS | D23: =+D12-D13 -> 0 | E23: =+E12-E13 -> 0 | F23: =+F12-F13 -> 0 | G23: =+G12-G13 -> 0 | H23: =+H12-H13 -> 0 | I23: =+I12-I13 -> 0
B24: GE | D24: =+D16 -> 4.17 | E24: =+E16 -> 4.24 | F24: =+F16 -> 4.24 | G24: =+G16 -> 0 | H24: =+H16 -> 4.24 | I24: =+I16 -> 3.23
B25: D-RD | D25: =+D9-D11 -> 56.03115 | E25: =+E9-E11 -> 50.74625 | F25: =+F9-F11 -> 52.82 | G25: =+G9-G11 -> 54.58 | H25: =+H9-H11 -> 54.29 | I25: =+I9-I11 -> 54.29
B26: DS-RDS | D26: =+D14-D15 -> 0 | E26: =+E14-E15 -> 0 | F26: =+F14-F15 -> 0 | G26: =+G14-G15 -> 0 | H26: =+H14-H15 -> 0 | I26: =+I14-I15 -> 0
B27: DE | D27: =+D17 -> 3.02 | E27: =+E17 -> 3.02 | F27: =+F17 -> 3.02 | G27: =+G17 -> 0 | H27: =+H17 -> 3.02 | I27: =+I17 -> 2.42
A29: Denominator | D29: =D22+D23-D24+D25+D26-D27 -> 169.05901 | E29: =E22+E23-E24+E25+E26-E27 -> 151.53325 | F29: =F22+F23-F24+F25+F26-F27 -> 173.82 | G29: =G22+G23-G24+G25+G26-G27 -> 183.45 | H29: =H22+H23-H24+H25+H26-H27 -> 174.94 | I29: =I22+I23-I24+I25+I26-I27 -> 176.55
D30: =+D20/D29 -> 0.11782868 | F30: =+F20/F29 -> 0.11557933 | G30: =+G20/G29 -> 0.10923957 | H30: =+H20/H29 -> 0.11455356 | I30: =+I20/I29 -> 0.11350892
A31: Outcome N/D | B31: Percentage Standard
B32: Celluloic percentage Standard | D32: =+D4/D29 -> 0.0034899057 | E32: 0.003394316 | F32: =+F4/F29 -> 0.003394316 | G32: =+G4/G29 -> 0.0029435814 | H32: =+H4/H29 -> 0.0030867726 | I32: =+I4/I29 -> 0.0030586236
B33: BBD percentage Standard | D33: =+D5/D29 -> 0.021560519 | E33: 0.020969969 | F33: =+F5/F29 -> 0.020969969 | G33: =+G5/G29 -> 0.019869174 | H33: =+H5/H29 -> 0.020835715 | I33: =+I5/I29 -> 0.020645709
B34: Advanced percentage standard | D34: =+D6/D29 -> 0.03010783 | E34: 0.029283166 | F34: =+F6/F29 -> 0.029283166 | G34: =+G6/G29 -> 0.027473426 | H34: =+H6/H29 -> 0.028809878 | I34: =+I6/I29 -> 0.028547154
B35: Renewable Fuel | D35: 0.113 | E35: 0.11557933 | F35: =+F30 -> 0.11557933 | G35: =+G30 -> 0.10923957 | H35: =+H30 -> 0.11455356 | I35: =+I30 -> 0.11350892
B36: Implied Ethanol | D36: =+D10/D29 -> 0.0814292 | E36: 0.082959383 | F36: =+F10/F29 -> 0.082959383 | G36: =+G10/G29 -> 0.07969474 | H36: =+H10/H29 -> 0.08334286 | I36: =+I10/I29 -> 0.082582838
B38: Volumes for Use in Determining Proposed 2020 Standard | D38: 2021 Guess | E38: Post Pandemic | F38: Original Mandate
B39: (Billion Gallons)
B40: Celluloic percentage Standard | D40: =+D32*D29 -> 0.59 | E40: =+E32*E29 -> 0.51435173 | F40: =+F32*F29 -> 0.59 | G40: =+G32*G29 -> 0.54 | H40: =+H32*H29 -> 0.54 | I40: =+I32*I29 -> 0.54
B41: BBD percentage Standard | D41: =+D33*D29/1.5 -> 2.43 | E41: =+E33*E29/1.5 -> 2.1184317 | F41: =+F33*F29/1.5 -> 2.43 | G41: =+G33*G29/1.5 -> 2.43 | H41: =+H33*H29/1.5 -> 2.43 | I41: =+I33*I29/1.5 -> 2.43
B42: Advanced percentage standard | D42: =+D34*D29 -> 5.09 | E42: =+E34*E29 -> 4.4373734 | F42: =+F34*F29 -> 5.09 | G42: =+G34*G29 -> 5.04 | H42: =+H34*H29 -> 5.04 | I42: =+I34*I29 -> 5.04
B43: Renewable Fuel | D43: =+D35*D29 -> 19.103668 | E43: =+E35*E29 -> 17.514112 | F43: =+F35*F29 -> 20.09 | G43: =+G35*G29 -> 20.04 | H43: =+H35*H29 -> 20.04 | I43: =+I35*I29 -> 20.04
B44: Implied Ethanol | D44: =+D43-D42 -> 14.013668 | E44: =+E43-E42 -> 13.076739 | F44: =+F43-F42 -> 15 | G44: =+G43-G42 -> 15 | H44: =+H43-H42 -> 15 | I44: =+I43-I42 -> 15
B46: Effect of EPA Proposal to Add-in 770 million gallons | H46: 0.77 | I46: 0.58
B47: Celluloic percentage Standard | H47: =+H32*H$46 -> 0.0023768149 | I47: =+I32*I$46 -> 0.0017740017
B48: BBD percentage Standard | H48: =+H33*H$46 -> 0.016043501 | I48: =+I33*I$46 -> 0.011974511
B49: Advanced percentage standard | H49: =+H34*H$46 -> 0.022183606 | I49: =+I34*I$46 -> 0.016557349
B50: Renewable Fuel | H50: =+H35*H$46 -> 0.088206242 | I50: =+I35*I$46 -> 0.065835174
B51: Implied Ethanol | H51: =+H36*H$46 -> 0.064174003 | I51: =+I36*I$46 -> 0.047898046
N52: EPA Use
B53: Effect of EPA Proposal had they added in Actual SRE avg | H53: 1.347 | I53: 0.967 | N53: RINs | O53: Gallons | Q53: gas | R53: diesel
B54: Celluloic percentage Standard | H54: =+H32*H$53 -> 0.0041578827 | I54: =+I32*I$53 -> 0.002957689 | K54: 2016-2018 average | M54: =(440+1020+840)/3 -> 766.66667 | N54: 770 | Q54: =2450+5650+4620 -> 12720 | R54: =1930+3870+3270 -> 9070 | S54: =+Q54+R54 -> 21790 | T54: =+S54/3 -> 7263.3333
B55: BBD percentage Standard | H55: =+H33*H$53 -> 0.028065708 | I55: =+I33*I$53 -> 0.019964401 | K55: 2015-2017 average | M55: =(290+440+1020)/3 -> 583.33333 | N55: 580 | Q55: =1590+2450+5650 -> 9690 | R55: =1450+1930+3870 -> 7250 | S55: =+Q55+R55 -> 16940 | T55: =+S55/3 -> 5646.6667
B56: Advanced percentage standard | H56: =+H34*H$53 -> 0.038806905 | I56: =+I34*I$53 -> 0.027605098
B57: Renewable Fuel | H57: =+H35*H$53 -> 0.15430365 | I57: =+I35*I$53 -> 0.10976313
B58: Implied Ethanol | H58: =+H36*H$53 -> 0.11226283 | I58: =+I36*I$53 -> 0.079857604
B60: first decimal point = 100 million
B61: Second decimal point =10 million
B62: Third decimal point = 1 million
B63: Fourth decimal point = 100 thousand | H63: 770000000 | Q63: =1430+1820+790 -> 4040
H64: =+H63*H33 -> 16043501 | Q64: =+Q63/3 -> 1346.6667
M67: RINs | N67: Gallons
K68: 2016-2018 average | M68: =(790+1820+1430)/3 -> 1346.6667 | N68: =(7840+17050+13420)/3 -> 12770
K69: 2015-2017 average | M69: =(290+790+1820)/3 -> 966.66667 | N69: =(3070+7840+17050)/3 -> 9320
F70: Effect on Gasoline and Diesel Consumption due to Carona Virus
F71: Gasoline | H71: Diesel
F72: 142.68 | G72: 142.68 | H72: =+F9 -> 55.3 | I72: =+H72 -> 55.3
E73: Jan | F73: =+F72/12 -> 11.89 | G73: =+F73 -> 11.89 | H73: =+H72/12 -> 4.6083333 | I73: =+H73 -> 4.6083333
E74: Feb | F74: 11.89 | G74: =+F74 -> 11.89 | H74: =+H73 -> 4.6083333 | I74: =+H74 -> 4.6083333
B75: Down 10% | E75: Mar | F75: 11.89 | G75: =+F75*0.9 -> 10.701 | H75: =+H74 -> 4.6083333 | I75: =+H75 -> 4.6083333 | J75: 0
B76: Down 35% | E76: Apr | F76: 11.89 | G76: =+F76*0.65 -> 7.7285 | H76: =+H75 -> 4.6083333 | I76: =+H76*0.95 -> 4.3779167 | J76: -0.05
B77: Down 40% | E77: May | F77: 11.89 | G77: =+F77*0.6 -> 7.134 | H77: =+H76 -> 4.6083333 | I77: =+H77*0.95 -> 4.3779167 | J77: -0.05
B78: Down 35% | E78: Jun | F78: 11.89 | G78: =+F78*0.65 -> 7.7285 | H78: =+H77 -> 4.6083333 | I78: =+H78*0.95 -> 4.3779167 | J78: -0.05
B79: Down 30% | E79: Jul | F79: 11.89 | G79: =+F79*0.7 -> 8.323 | H79: =+H78 -> 4.6083333 | I79: =+H79*0.85 -> 3.9170833 | J79: -0.15
B80: Down 20% | E80: Aug | F80: 11.89 | G80: =+F80*0.8 -> 9.512 | H80: =+H79 -> 4.6083333 | I80: =+H80*0.9 -> 4.1475 | J80: -0.1
E81: Sep | F81: 11.89 | G81: =+F81 -> 11.89 | H81: =+H80 -> 4.6083333 | I81: =+H81*0.95 -> 4.3779167 | J81: -0.05
E82: Oct | F82: 11.89 | G82: =+F82 -> 11.89 | H82: =+H81 -> 4.6083333 | I82: =+H82 -> 4.6083333
E83: Nov | F83: 11.89 | G83: =+F83 -> 11.89 | H83: =+H82 -> 4.6083333 | I83: =+H83 -> 4.6083333
E84: Dec | F84: 11.89 | G84: =+F84 -> 11.89 | H84: =+H83 -> 4.6083333 | I84: =+H84 -> 4.6083333
F85: =SUM(F73:F84) -> 142.68 | G85: =SUM(G73:G84) -> 122.467 | H85: =SUM(H73:H84) -> 55.3 | I85: =SUM(I73:I84) -> 53.22625
F86: Original EIA Est | G86: Revised | H86: Original EIA Est | I86: Revised
F88: Yearly Decline | G88: =+G85/F85-1 -> -0.14166667 | I88: =+I85/H85-1 -> -0.0375
E92: Final RFS for 2020 and BBD 2021 (Pandemic) | F92: Final RFS for 2020 and BBD 2021
B94: Volumes for Use in Determining Proposed 2020 Standard | E94: Post Pandemic | F94: Original Mandate
B95: (Billion Gallons)
B96: Celluloic percentage Standard | E96: =+E40 -> 0.51435173 | F96: =+F40 -> 0.59
B97: BBD percentage Standard | E97: =+E41 -> 2.1184317 | F97: =+F41 -> 2.43
B98: Advanced percentage standard | E98: =+E42 -> 4.4373734 | F98: =+F42 -> 5.09
B99: Renewable Fuel | E99: =+E43 -> 17.514112 | F99: =+F43 -> 20.09 | H99: Gallons for BBD | I99: Post Pandemic | J99: Original Mandate
B100: Implied Ethanol | E100: =+E44 -> 13.076739 | F100: =+F44 -> 15 | H100: Mandate | I100: =+E41 -> 2.1184317 | J100: =+F41 -> 2.43
H101: Unspecified D5 | I101: 0.43 | J101: 0.4 | L101: 2019
B102: BBD percentage Standard in Ethanol Equivalent Gallons | E102: =+E97*1.55 -> 3.2835691 | F102: =+F97*1.55 -> 3.7665 | H102: BBD in D5 already | I102: 0.04 | J102: 0.04 | L102: 0.034
B104: Calculating Potential D4 Gallons Needed to Fulfill D5 Mandate | H104: Total | I104: =+I102+I101+I100 -> 2.5884317 | J104: =+J102+J101+J100 -> 2.87
B105: Advanced Mandate | E105: =+E98 -> 4.4373734 | F105: =+F98 -> 5.09
B106: Biomass-based diesel Mandate | E106: =+E102 -> 3.2835691 | F106: =+F102 -> 3.7665
B107: Cellulosic Mandate | E107: =+E96 -> 0.51435173 | F107: =+F96 -> 0.59
B108: Unspecified D5 - (1-2-3) | E108: =+E105-E106-E107 -> 0.63945253 | F108: =+F105-F106-F107 -> 0.7335
B110: Expected D5 2020 production | E110: 0.21 | F110: 0.33
B111: Potential balance to be filled by D4 | E111: =+E108-E110 -> 0.42945253 | F111: =+F108-F110 -> 0.4035
B114: Expected D5 2020 Production
B115: 1 | E115: Non Cell Eth Imports expected to be at least 100 million gallons lower due to pandemic
B116: 2 | E116: RD production expected to be 10 million gallons higher
B117: 3 | E117: 2019 D5 was about 282 million gallons
...

Sheet Mandate Levels and Rules
U1: Proposed due by June 1 | W1: https://iowarfa.org/2015/04/epa-reaches-agreement-on-rfs-deadlines/
R2: Mandated | S2: final rule by
S3: Nov 30 each year
R4: Renewable Fuel Standards - Final and Proposed rule's
R5: Final Rule | S5: Publish date | U5: Proposed Rule
R6: 2011 | S6: 40521 | U6: 2011 | V6: 40379
R7: 2012 | S7: 40917 | U7: 2012 | V7: 40725
R8: 2013 | S8: 41501 | U8: 2013 | V8: 41312
R9: 2014 | S9: 42352 | U9: 2014 | V9: 42165 | Z9: https://www.ecfr.gov/cgi-bin/text-idx?SID=0230338f5cea609814d2898c4b6d3b50&mc=true&node=pt40.19.80&rgn=div5
R10: 2015 | S10: 42352 | U10: 2015 | V10: 42165 | Z10: §80.1405 What are the Renewable Fuel Standards?
R11: 2016 | S11: 42352 | U11: 2016 | V11: 42165 | Z11: (b) EPA will calculate the value of the annual standards and publish these values in the Federal Register by November 30 of the year preceding the compliance period.
R12: 2017 | S12: 42716 | U12: 2017 | V12: 42508 | AA12: Under section 211 of the Clean Air Act, the Environmental Protection Agency (EPA) is required to set renewable fuel percentage standards every year.
R13: 2018 | S13: 43081 | U13: 2018 | V13: 42937
R14: 2019 | S14: 43445 | U14: 2019 | V14: 43291
R15: 2020 | S15: 43867 | U15: 2020 | V15: 43675
R16: 2021 | S16: MIA | U16: 2021 | V16: MIA
Y18: Hyperlink to regulations - | AA18: Renewable Fuels Program Government Regulations
L20: EPA proposes to extend 2019, 2020 RFS deadlines | Y20: Consent Decree | AA20: https://www.epa.gov/sites/production/files/2015-08/documents/consent-decree-proposed-2015-04-10.pdf
Y21: EPA OBLIGATIONS
AH22: RFS Waiver Provisions
Y23: 3. EPA shall sign by June1, 2015, and submit to the Office of the Federal Registeras expeditiously as reasonably possible and in any event no later than ten (10) business days after such signature for publication in the Federal Register, a notice of proposed rulemaking to determine in accordance with 42 U.S.C. § 7545(o)(3)(B) the renewable fuel obligations for calendar year 2015. Following its submission, EPA shall not take any action to delay or otherwise interfere with immediate publication of the notice in the Federal Register. | AH23: 3 separate waivers, a general waiver, a cellulosic waiver, and a biomass-based diesel waiver.
AG24: 1 | AH24: General Waiver
AI25: The RFS statute gives the EPA Administrator the authority to waive the RFS requirements, in whole or in part, “by reducing the national quantity of renewable fuel required” if
AI27: 1. implementation of the requirement would severely harm the economy or environment of a state, a region, or the United States, or
AI28: 2. domestic renewable fuel supply is inadequate to meet the mandate.
R30: The EPA has never been very good at meeting its timeline, although the current administration is striving to keep deadlines, at least for the final rule. • Proposed rulings are supposedly due by June 1 • Final Rule by 11/30 • Proposed and Final rules will be for 2021 volumes for everything but biodiesel, which will be for 2022. | AG30: 2 | AH30: Cellulosic Biofuel Waiver
AI31: The RFS statute obligates the EPA Administrator to reduce the cellulosic biofuel mandate when the projected production capacity for a given year is less than the volume required in the statute. The law does not require the EPA Administrator to consult with the Secretary of Agriculture or the Secretary of Energy when issuing a cellulosic biofuel waiver, or to give public notice and opportunity for comment. However, the Administrator must use the projected volume estimate from the U.S. Energy Information Administration provided under the applicable percentages section of the statute. In prior waiver determinations, EPA has provided opportunity for public comment. The Administrator must set the new required amount at the “projected available volume during that calendar year” by November 30 of the preceding year. Should the Administrator reduce the cellulosic biofuel volume, the Administrator also may reduce the volumes of advanced biofuel and total renewable fuel by the same or lesser volume. When the Administrator issues a cellulosic biofuel waiver, the Administrator must offer cellulosic biofuel waiver credits for obligated parties to purchase for that compliance year in lieu of using actual cellulosic biofuel.
Y32: 4. EPA shall sign by November 30, 2015, and submit to the Office of the Federal Register as expeditiously as reasonably possible and in any event no later than ten (10) business days after such signature for publication in the Federal Register, a final rule or rules determining in accordance with 42 U.S.C. § 7545(o)(3)(B) the renewable fuel obligations for calendar years 2014 and 2015. Following its submission, EPA shall not take any action to delay or otherwise interfere with immediate publication of the final rule or rules in the Federal Register.
B39: https://www.epa.gov/renewable-fuel-standard-program/overview-renewable-fuel-standard
C40: Original RFS Statutory Mandates | J40: Actual RFS Mandates | R40: Original RFS Statutory Mandates (Billions of Gallons) | Y40: Actual RFS Mandates | AA40: (Billion Gallons)
T41: Advanced-Non Specified
C42: Cellulosic | D42: BBD* | E42: Advanced | F42: Ethanol | G42: total | J42: Cellulosic | K42: BBD | L42: Advanced | M42: Ethanol | N42: total | R42: Cellulosic | S42: BBD* | U42: Ethanol | V42: total | Y42: Cellulosic | Z42: BBD | AA42: Advanced-Non Specified | AB42: Ethanol | AC42: total | AD42: % of Statute
B43: 2006 | C43: NA | D43: NA | E43: NA | I43: 2006 | Q43: 2006 | R43: NA | S43: NA | T43: NA | V43: 4 | X43: 2006
B44: 2007 | C44: NA | D44: NA | E44: NA | I44: 2007 | Q44: 2007 | R44: NA | S44: NA | T44: NA | V44: 4.7 | X44: 2007
B45: 2008 | C45: NA | D45: NA | E45: NA | I45: 2008 | Q45: 2008 | R45: NA | S45: NA | T45: NA | V45: 9 | X45: 2008 | AG45: 3 | AH45: Biomass-Based Diesel Waiver
B46: 2009 | C46: NA | D46: 0.5 | E46: 0.6 | F46: 10.5 | G46: 11.1 | I46: 2009 | Q46: 2009 | R46: NA | S46: 0.5 | T46: =+E46-S46 -> 0.1 | U46: 10.5 | V46: 11.1 | X46: 2009 | AI46: The RFS statutory provisions give the EPA Administrator authority to reduce the amount of biomass-based diesel required for up to 60 days if the Administrator determines that there are significant market circumstances (including feedstock disruptions) “that would make the price of biomass-based diesel fuel increase significantly.”17 If these market circumstances continue past the initial 60-day period, the Administrator may issue another waiver for an additional 60 days. The Administrator is to consult with the Secretaries of Energy and Agriculture prior to issuing such a waiver. If the Administrator issues a biomass-based diesel waiver, the Administrator also may reduce the volumes of advanced biofuel and renewable fuel by the same or lesser volume. As of July 2020, EPA has not used the biomass-based diesel waiver authority.
B47: 2010 | C47: 0.1 | D47: 0.65 | E47: 0.95 | F47: 12 | G47: 12.95 | I47: 2010 | Q47: 2010 | R47: 0.1 | S47: 0.65 | T47: =+E47-S47-R47 -> 0.2 | U47: 12 | V47: 12.95 | X47: 2010
B48: 2011 | C48: 0.25 | D48: 0.8 | E48: 1.35 | F48: 12.6 | G48: 13.95 | I48: 2011 | Q48: 2011 | R48: 0.25 | S48: 0.8 | T48: =+E48-S48-R48 -> 0.3 | U48: 12.6 | V48: 13.95 | X48: 2011 | AE48: Reset Provision Allowed 2016 or later
B49: 2012 | C49: 0.5 | D49: 1 | E49: 2 | F49: 13.2 | G49: 15.2 | I49: 2012 | Q49: 2012 | R49: 0.5 | S49: 1 | T49: =+E49-S49-R49 -> 0.5 | U49: 13.2 | V49: 15.2 | X49: 2012 | AG49: Final Mandate @20% of Statute
B50: 2013 | C50: 1 | D50: 1 | E50: 2.75 | F50: 13.8 | G50: 16.55 | I50: 2013 | J50: 0.006 | K50: 1.28 | L50: 2.75 | M50: =+N50-L50 -> 13.8 | N50: 16.55 | P50: =+M50+L50 -> 16.55 | Q50: 2013 | R50: 1 | S50: 1 | T50: =+E50-S50-R50 -> 0.75 | U50: 13.8 | V50: 16.55 | X50: 2013 | Y50: 0.006 | Z50: 1.28 | AA50: =+L50-Z50-Y50 -> 1.464 | AB50: =+AC50-L50 -> 13.8 | AC50: 16.55 | AE50: Year | AF50: 20% of Stat
B51: 2014 | C51: 1.75 | D51: 1 | E51: 3.75 | F51: 14.4 | G51: 18.15 | I51: 2014 | J51: 0.033 | K51: 1.63 | L51: 2.67 | M51: =+N51-L51 -> 13.61 | N51: 16.28 | P51: =+M51+L51 -> 16.28 | Q51: 2014 | R51: 1.75 | S51: 1 | T51: =+E51-S51-R51 -> 1 | U51: 14.4 | V51: 18.15 | X51: 2014 | Y51: 0.033 | Z51: 1.63 | AA51: =+L51-Z51-Y51 -> 1.007 | AB51: 13.61 | AC51: 16.28 | AD51: =+AC51/V51 -> 0.8969697
B52: 2015 | C52: 3 | D52: 1 | E52: 5.5 | F52: 15 | G52: 20.5 | I52: 2015 | J52: 0.123 | K52: 1.73 | L52: 2.88 | M52: =+N52-L52 -> 14.05 | N52: 16.93 | P52: =+M52+L52 -> 16.93 | Q52: 2015 | R52: 3 | S52: 1 | T52: =+E52-S52-R52 -> 1.5 | U52: 15 | V52: 20.5 | X52: 2015 | Y52: 0.123 | Z52: 1.73 | AA52: =+L52-Z52-Y52 -> 1.027 | AB52: 14.05 | AC52: 16.93 | AD52: =+AC52/V52 -> 0.82585366
B53: 2016 | C53: 4.25 | D53: 1 | E53: 7.25 | F53: 15 | G53: 22.25 | I53: 2016 | J53: 0.23 | K53: 1.9 | L53: 3.61 | M53: =+N53-L53 -> 14.5 | N53: 18.11 | P53: =+M53+L53 -> 18.11 | Q53: 2016 | R53: 4.25 | S53: 1 | T53: =+E53-S53-R53 -> 2 | U53: 15 | V53: 22.25 | W53: =+V53*0.8 -> 17.8 | X53: 2016 | Y53: 0.23 | Z53: 1.9 | AA53: =+L53-Z53-Y53 -> 1.48 | AB53: 14.5 | AC53: 18.11 | AD53: =+AC53/V53 -> 0.81393258 | AE53: 2016 | AF53: =+V53*0.2 -> 4.45 | AG53: =+V53-AF53 -> 17.8
B54: 2017 | C54: 5.5 | D54: 1 | E54: 9 | F54: 15 | G54: 24 | I54: 2017 | J54: 0.311 | K54: 2 | L54: 4.28 | M54: =+N54-L54 -> 15 | N54: 19.28 | P54: =+M54+L54 -> 19.28 | Q54: 2017 | R54: 5.5 | S54: 1 | T54: =+E54-S54-R54 -> 2.5 | U54: 15 | V54: 24 | W54: =+V54*0.8 -> 19.2 | X54: 2017 | Y54: 0.311 | Z54: 2 | AA54: =+L54-Z54-Y54 -> 1.969 | AB54: 15 | AC54: 19.28 | AD54: =+AC54/V54 -> 0.80333333 | AE54: 2017 | AF54: =+V54*0.2 -> 4.8 | AG54: =+V54-AF54 -> 19.2
B55: 2018 | C55: 7 | D55: 1 | E55: 11 | F55: 15 | G55: 26 | I55: 2018 | J55: 0.288 | K55: 2.1 | L55: 4.29 | M55: =+N55-L55 -> 15 | N55: 19.29 | P55: =+M55+L55 -> 19.29 | Q55: 2018 | R55: 7 | S55: 1 | T55: =+E55-S55-R55 -> 3 | U55: 15 | V55: 26 | W55: =+V55*0.8 -> 20.8 | X55: 2018 | Y55: 0.288 | Z55: 2.1 | AA55: =+L55-Z55-Y55 -> 1.902 | AB55: 15 | AC55: 19.29 | AD55: =+AC55/V55 -> 0.74192308 | AE55: 2018 | AF55: =+V55*0.2 -> 5.2 | AG55: =+V55-AF55 -> 20.8 | AH55: Reset Provision - Modification of Applicable Volumes
B56: 2019 | C56: 8.5 | D56: 1 | E56: 13 | F56: 15 | G56: 28 | I56: 2019 | J56: 0.418 | K56: 2.1 | L56: 4.92 | M56: =+N56-L56 -> 15 | N56: 19.92 | P56: =+M56+L56 -> 19.92 | Q56: 2019 | R56: 8.5 | S56: 1 | T56: =+E56-S56-R56 -> 3.5 | U56: 15 | V56: 28 | W56: =+V56*0.8 -> 22.4 | X56: 2019 | Y56: 0.418 | Z56: 2.1 | AA56: =+L56-Z56-Y56 -> 2.402 | AB56: 15 | AC56: 19.92 | AD56: =+AC56/V56 -> 0.71142857 | AE56: 2019 | AF56: =+V56*0.2 -> 5.6 | AG56: =+V56-AF56 -> 22.4 | AI56: This provision requires that the EPA Administrator modify the applicable volumes of the RFS in future years starting in 2016 if certain conditions are met. Specifically, it provides that, starting in 2016, the EPA Administrator shall modify the applicable volumes of the RFS for subsequent years if the Administrator waives the renewable fuel mandate, the advanced biofuel mandate, the cellulosic biofuel mandate, or the biomass-based diesel mandate by at least 20% for two consecutive years or by at least 50% for a single year. This reset section does not state what the modified amount must be. Rather, it requires that the Administrator determine the applicable volumes—in coordination with the Secretaries of Energy and Agriculture—based on a review of program implementation thus far and an analysis of certain factors (e.g., the impact of the production and use of renewable fuels on the environment).
B57: 2020 | C57: 10.5 | D57: 1 | E57: 15 | F57: 15 | G57: 30 | I57: 2020 | J57: 0.59 | K57: 2.43 | L57: 5.09 | M57: =+N57-L57 -> 15 | N57: 20.09 | P57: =+M57+L57 -> 20.09 | Q57: 2020 | R57: 10.5 | S57: 1 | T57: =+E57-S57-R57 -> 3.5 | U57: 15 | V57: 30 | W57: =+V57*0.8 -> 24 | X57: 2020 | Y57: 0.59 | Z57: 2.43 | AA57: =+L57-Z57-Y57 -> 2.07 | AB57: 15 | AC57: 20.09 | AD57: =+AC57/V57 -> 0.66966667 | AE57: 2020 | AF57: =+V57*0.2 -> 6 | AG57: =+V57-AF57 -> 24
B58: 2021 | C58: 13.5 | D58: 1 | E58: 18 | F58: 15 | G58: 33 | I58: 2021 | J58: 0.83 | K58: 2.43 | Q58: 2021 | R58: 13.5 | S58: 1 | T58: =+E58-S58-R58 -> 3.5 | U58: 15 | V58: 33 | W58: =+V58*0.8 -> 26.4 | X58: 2021 | Z58: 2.43 | AE58: 2021
B59: 2022 | C59: 16 | D59: 1 | E59: 21 | F59: 15 | G59: 36 | I59: 2022 | Q59: 2022 | R59: 16 | S59: 1 | T59: =+E59-S59-R59 -> 4 | U59: 15 | V59: 36 | W59: =+V59*0.8 -> 28.8 | X59: 2022 | AE59: 2022
I60: =+I94 -> Speculation
C61: *statute sets 1 billion gallons minimum, but EPA may raise requirement | I61: =+I95 -> EPA can reduce cellulosic by difference between statute and EIA estimated use for the year. | R61: *statute sets 1 billion gallons minimum, but EPA may raise requirement
AF62: *Total waived exceeded 20% in 2018, 2019, and 2020
K63: Cellulosic - Statute vs Actual (billion gallons)
J64: Statute | K64: Actual | L64: Difference | M64: % of Statute
I65: 2016 | J65: =+C53 -> 4.25 | K65: =+J53 -> 0.23 | L65: =+K65-J65 -> -4.02 | M65: =+K65/J65 -> 0.054117647 | O65: =+K66/K65 -> 1.3521739 | AH65: * | AI65: Since 2010, EPA has regularly used Cellulosic Biofuel Authority to lower both advanced and total
I66: 2017 | J66: =+C54 -> 5.5 | K66: =+J54 -> 0.311 | L66: =+K66-J66 -> -5.189 | M66: =+K66/J66 -> 0.056545455 | O66: =+K67/K66 -> 0.92604502 | P66: =+K65*O65 -> 0.311 | AI66: renewable fuel volume. In December 2019, EPA used it to reduce the applicable total renewable fuel, advanced biofuel, and cellulosic biofuel volume requirements for 2020. A biomass-based diesel waiver has not been used.
I67: 2018 | J67: =+C55 -> 7 | K67: =+J55 -> 0.288 | L67: =+K67-J67 -> -6.712 | M67: =+K67/J67 -> 0.041142857 | O67: =+K68/K67 -> 1.4513889 | P67: =+K66*O66 -> 0.288
I68: 2019 | J68: =+C56 -> 8.5 | K68: =+J56 -> 0.418 | L68: =+K68-J68 -> -8.082 | M68: =+K68/J68 -> 0.049176471 | O68: =+K69/K68 -> 1.4114833 | P68: =+K67*O67 -> 0.418
I69: 2020 | J69: =+C57 -> 10.5 | K69: =+J57 -> 0.59 | L69: =+K69-J69 -> -9.91 | M69: =+K69/J69 -> 0.056190476 | O69: =+K70/K69 -> 1.4114833 | P69: =+K68*O68 -> 0.59 | AI69: EPA has exercised the general waoiver authority once to reduce total renewable fuel volumes for the combined 201, 2015, and 2016 years. The ruling was vacated by the US Courd of Appeals after it was concluded EPA had incorrectly interpreted the general waiver provision.
I70: 2021 | J70: =+C58 -> 13.5 | K70: =+P70 -> 0.83277512 | L70: =+K70-J70 -> -12.667225 | O70: My EIA Est.. | P70: =+P69*O68 -> 0.83277512
I71: 2022 | J71: =+C59 -> 16 | K71: =+J59 -> 0
K73: Advanced - Statute vs Actual (billion gallons)
J74: Statute | K74: Actual | L74: Difference | M74: % of Statute
I75: 2016 | J75: =+E53 -> 7.25 | K75: =+L53 -> 3.61 | L75: =+K75-J75 -> -3.64 | M75: =+K75/J75 -> 0.49793103
I76: 2017 | J76: =+E54 -> 9 | K76: =+L54 -> 4.28 | L76: =+K76-J76 -> -4.72 | M76: =+K76/J76 -> 0.47555556
I77: 2018 | J77: =+E55 -> 11 | K77: =+L55 -> 4.29 | L77: =+K77-J77 -> -6.71 | M77: =+K77/J77 -> 0.39
I78: 2019 | J78: =+E56 -> 13 | K78: =+L56 -> 4.92 | L78: =+K78-J78 -> -8.08 | M78: =+K78/J78 -> 0.37846154
I79: 2020 | J79: =+E57 -> 15 | K79: =+L57 -> 5.09 | L79: =+K79-J79 -> -9.91 | M79: =+K79/J79 -> 0.33933333
I80: 2021 | J80: =+E58 -> 18 | K80: =+J80+L70 -> 5.3327751 | L80: =+K80-J80 -> -12.667225 | M80: =+K80/J80 -> 0.29626528
I81: 2022 | J81: =+E59 -> 21 | K81: =+L59 -> 0
K83: Total Renewable Fuel - Statute vs Actual (billion gallons)
J84: Statute | K84: Actual | L84: Difference | M84: % of Statute
I85: 2016 | J85: =+G53 -> 22.25 | K85: =+N53 -> 18.11 | L85: =+K85-J85 -> -4.14 | M85: =+K85/J85 -> 0.81393258
I86: 2017 | J86: =+G54 -> 24 | K86: =+N54 -> 19.28 | L86: =+K86-J86 -> -4.72 | M86: =+K86/J86 -> 0.80333333
I87: 2018 | J87: =+G55 -> 26 | K87: =+N55 -> 19.29 | L87: =+K87-J87 -> -6.71 | M87: =+K87/J87 -> 0.74192308
I88: 2019 | J88: =+G56 -> 28 | K88: =+N56 -> 19.92 | L88: =+K88-J88 -> -8.08 | M88: =+K88/J88 -> 0.71142857
I89: 2020 | J89: =+G57 -> 30 | K89: =+N57 -> 20.09 | L89: =+K89-J89 -> -9.91 | M89: =+K89/J89 -> 0.66966667
I90: 2021 | J90: =+G58 -> 33 | K90: =+J90+L70 -> 20.332775 | L90: =+K90-J90 -> -12.667225 | M90: =+K90/J90 -> 0.6161447
I91: 2022 | J91: =+G59 -> 36 | K91: =+N59 -> 0 | L91: =+K91-J91 -> -36
I94: Speculation
I95: EPA can reduce cellulosic by difference between statute and EIA estimated use for the year.

Sheet RVO Table
B2: EPA Renewable Volume Obligations | H2: Clean Fuels Alliance America, American Farm Bureau Federation, American Soybean Association, National Oilseed Processors Association, North American Renderers Association, and U.S. Canola Association sent a letter to EPA Administrator
C3: 2019 | D3: 2023 | E3: 2024 | F3: 2025 | H3: 2026 Recommendation 3/17/25
B4: Cellulosic Biofuel | C4: ='RVO Forecast'!J14/1000000000 -> 0.418 | D4: 0.72 | E4: 1.42 | F4: 2.13
B5: Biomass-Based Diesel | C5: ='RVO Forecast'!J10/1000000000 -> 2.1 | D5: 2.82 | E5: 2.89 | F5: 2.95 | H5: 5.25 | I5: =H5/F5-1 -> 0.77966102
B6: Advanced Biofuel | C6: ='RVO Forecast'!J18/1000000000 -> 4.92 | D6: 5.82 | E6: 6.62 | F6: 7.43 | H6: =F6*(1+I5) -> 13.222881
B7: Implied Ethanol | C7: ='RVO Forecast'!J49/1000000000 -> 15 | D7: 15 | E7: 15.25 | F7: 15.25
B8: Renewable Fuel | C8: ='RVO Forecast'!J8/1000000000 -> 19.92 | D8: 20.82 | E8: 21.87 | F8: 22.68
B9: Supplemental Standard | C9: N/A | D9: 0.25 | E9: N/A | F9: N/A
B11: (billion gallons) - all values are ethanol-equivalent on an energy content basis,
B12: except for biomass-based diesel which is biodiesel equivalent

Sheet RVO Forecast
A1: =O3*0.025 -> 89098112 | B1: 2011 | C1: 2012 | D1: 2013 | E1: 2014 | F1: 2015 | G1: 2016 | H1: 2017 | I1: 2018 | J1: 2019 | K1: 2020 | L1: 2021 | M1: 2022 | N1: 2023 | O1: 2024 | P1: 2025 | Q1: 2026 | R1: 2027 | S1: 2028 | T1: 2029 | U1: 2030 | V1: 2031 | W1: 2032 | X1: 2033 | Y1: 2034 | Z1: 2035 | AA1: 2036 | AB1: 2037 | AC1: 2038 | AD1: 2039 | AE1: 2040 | AF1: 2041 | AG1: 2042 | AH1: 2043 | AI1: 2044 | AJ1: 2045 | AK1: 2046 | AL1: 2047 | AM1: 2048 | AN1: 2049 | AO1: 2050 | AP1: 2051
A2: Biodiesel Production | B2: ='[1]D4 Gallon Forecast'!C$65+'[1]D6 Gallon Forecast'!C$61 -> 1081549902 | C2: ='[1]D4 Gallon Forecast'!D$65+'[1]D6 Gallon Forecast'!D$61 -> 1057176449 | D2: ='[1]D4 Gallon Forecast'!E$65+'[1]D6 Gallon Forecast'!E$61 -> 1571180819 | E2: ='[1]D4 Gallon Forecast'!F$65+'[1]D6 Gallon Forecast'!F$61 -> 1488723198 | F2: ='[1]D4 Gallon Forecast'!G$65+'[1]D6 Gallon Forecast'!G$61 -> 1589937580 | G2: ='[1]D4 Gallon Forecast'!H$65+'[1]D6 Gallon Forecast'!H$61 -> 2307275437 | H2: ='[1]D4 Gallon Forecast'!I$65+'[1]D6 Gallon Forecast'!I$61 -> 2050164384 | I2: ='[1]D4 Gallon Forecast'!J$65+'[1]D6 Gallon Forecast'!J$61 -> 2030594071 | ... O2: ='[1]D4 Gallon Forecast'!P$65+'[1]D6 Gallon Forecast'!P$61 -> 2073990064 | P2: ='[2]10 Year RFS Curves (2020)'!J$45*1000000000 -> 1.580916e+09 | Q2: ='[2]10 Year RFS Curves (2020)'!K$45*1000000000 -> 1.4562889e+09 | R2: ='[2]10 Year RFS Curves (2020)'!L$45*1000000000 -> 1.4741038e+09 | S2: ='[2]10 Year RFS Curves (2020)'!M$45*1000000000 -> 1.1900368e+09 | T2: ='[2]10 Year RFS Curves (2020)'!N$45*1000000000 -> 1.3937372e+09 | U2: ='[2]10 Year RFS Curves (2020)'!O$45*1000000000 -> 1.4315568e+09 | V2: ='[2]10 Year RFS Curves (2020)'!P$45*1000000000 -> 1.4364393e+09 | W2: ='[2]10 Year RFS Curves (2020)'!Q$45*1000000000 -> 1.4914822e+09 | ... AP2: ='[2]10 Year RFS Curves (2020)'!AJ$45*1000000000 -> 3.1455437e+08
A3: Renewable Diesel | B3: ='[1]D4 Gallon Forecast'!C$129+'[1]D5 Gallon Forecast'!C$116+'[1]D6 Gallon Forecast'!C$205 -> 62041290 | C3: ='[1]D4 Gallon Forecast'!D$129+'[1]D5 Gallon Forecast'!D$116+'[1]D6 Gallon Forecast'!D$205 -> 102674024 | D3: ='[1]D4 Gallon Forecast'!E$129+'[1]D5 Gallon Forecast'!E$116+'[1]D6 Gallon Forecast'!E$205 -> 416685400 | E3: ='[1]D4 Gallon Forecast'!F$129+'[1]D5 Gallon Forecast'!F$116+'[1]D6 Gallon Forecast'!F$205 -> 487892696 | F3: ='[1]D4 Gallon Forecast'!G$129+'[1]D5 Gallon Forecast'!G$116+'[1]D6 Gallon Forecast'!G$205 -> 513144574 | G3: ='[1]D4 Gallon Forecast'!H$129+'[1]D5 Gallon Forecast'!H$116+'[1]D6 Gallon Forecast'!H$205 -> 591173471 | H3: ='[1]D4 Gallon Forecast'!I$129+'[1]D5 Gallon Forecast'!I$116+'[1]D6 Gallon Forecast'!I$205 -> 602723820 | I3: ='[1]D4 Gallon Forecast'!J$129+'[1]D5 Gallon Forecast'!J$116+'[1]D6 Gallon Forecast'!J$205 -> 615331084 | ... O3: ='[1]D4 Gallon Forecast'!P$129+'[1]D5 Gallon Forecast'!P$116+'[1]D6 Gallon Forecast'!P$205 -> 3563924491 | P3: ='[2]10 Year RFS Curves (2020)'!J$46*1000000000 -> 2.7895966e+09 | Q3: ='[2]10 Year RFS Curves (2020)'!K$46*1000000000 -> 2.7143447e+09 | R3: ='[2]10 Year RFS Curves (2020)'!L$46*1000000000 -> 2.9704608e+09 | S3: ='[2]10 Year RFS Curves (2020)'!M$46*1000000000 -> 3.0164948e+09 | T3: ='[2]10 Year RFS Curves (2020)'!N$46*1000000000 -> 3.0319186e+09 | U3: ='[2]10 Year RFS Curves (2020)'!O$46*1000000000 -> 3.1796222e+09 | V3: ='[2]10 Year RFS Curves (2020)'!P$46*1000000000 -> 3.4578266e+09 | W3: ='[2]10 Year RFS Curves (2020)'!Q$46*1000000000 -> 4.1105962e+09 | ... AP3: ='[2]10 Year RFS Curves (2020)'!AJ$46*1000000000 -> 7.2358166e+09
A4: Co-Processing | B4: ='[1]D5 Gallon Forecast'!C$9 -> 4536038 | C4: ='[1]D5 Gallon Forecast'!D$9 -> 10038332 | D4: ='[1]D5 Gallon Forecast'!E$9 -> 41266830 | E4: ='[1]D5 Gallon Forecast'!F$9 -> 8604718 | F4: ='[1]D5 Gallon Forecast'!G$9 -> 4979775 | G4: ='[1]D5 Gallon Forecast'!H$9 -> 4666016 | H4: ='[1]D5 Gallon Forecast'!I$9 -> 5147237 | I4: ='[1]D5 Gallon Forecast'!J$9 -> 23607885 | ... O4: ='[1]D5 Gallon Forecast'!P$9 -> 67136623 | P4: ='[2]10 Year RFS Curves (2020)'!J$47*1000000000 -> 61713906 | Q4: ='[2]10 Year RFS Curves (2020)'!K$47*1000000000 -> 74644480 | R4: ='[2]10 Year RFS Curves (2020)'!L$47*1000000000 -> 90174703 | S4: ='[2]10 Year RFS Curves (2020)'!M$47*1000000000 -> 94265461 | T4: ='[2]10 Year RFS Curves (2020)'!N$47*1000000000 -> 1.0106395e+08 | U4: ='[2]10 Year RFS Curves (2020)'!O$47*1000000000 -> 1.0810716e+08 | V4: ='[2]10 Year RFS Curves (2020)'!P$47*1000000000 -> 1.1237937e+08 | W4: ='[2]10 Year RFS Curves (2020)'!Q$47*1000000000 -> 1.2742848e+08 | ... AP4: ='[2]10 Year RFS Curves (2020)'!AJ$47*1000000000 -> 2.5478227e+08
A5: Total | B5: =SUM(B2:B4) -> 1148127230 | C5: =SUM(C2:C4) -> 1169888805 | D5: =SUM(D2:D4) -> 2029133049 | E5: =SUM(E2:E4) -> 1985220612 | F5: =SUM(F2:F4) -> 2108061929 | G5: =SUM(G2:G4) -> 2903114924 | H5: =SUM(H2:H4) -> 2658035441 | I5: =SUM(I2:I4) -> 2669533040 | ... AP5: =SUM(AP2:AP4) -> 7.8051532e+09
A6: RIN Adjustment | B6: =((B2*1.5)+(B3*1.7))/(B2+B3) -> 1.5108503 | C6: =((C2*1.5)+(C3*1.7))/(C2+C3) -> 1.5177047 | D6: =((D2*1.5)+(D3*1.7))/(D2+D3) -> 1.5419229 | E6: =((E2*1.5)+(E3*1.7))/(E2+E3) -> 1.5493665 | F6: =((F2*1.5)+(F3*1.7))/(F2+F3) -> 1.5487993 | G6: =((G2*1.5)+(G3*1.7))/(G2+G3) -> 1.5407924 | H6: =((H2*1.5)+(H3*1.7))/(H2+H3) -> 1.5454391 | I6: =((I2*1.5)+(I3*1.7))/(I2+I3) -> 1.5465116 | ... AP6: =((AP2*1.5)+(AP3*1.7))/(AP2+AP3) -> 1.6916678
A8: Renewable Fuel Mandate | B8: 13950000000 | C8: 15200000000 | D8: 16550000000 | E8: 16280000000 | F8: 16930000000 | G8: 18110000000 | H8: 19280000000 | I8: ='[2]10 Year RFS Curves (2020)'!C$18*1000000000 -> 19290000000 | J8: ='[2]10 Year RFS Curves (2020)'!D$18*1000000000 -> 19920000000 | K8: ='[2]10 Year RFS Curves (2020)'!E$18*1000000000 -> 1.713e+10 | L8: ='[2]10 Year RFS Curves (2020)'!F$18*1000000000 -> 18840000000 | M8: ='[2]10 Year RFS Curves (2020)'!G$18*1000000000 -> 20630000000 | N8: ='[2]10 Year RFS Curves (2020)'!H$18*1000000000 -> 20940000000 | O8: ='[2]10 Year RFS Curves (2020)'!I$18*1000000000 -> 21540000000 | P8: ='[2]10 Year RFS Curves (2020)'!J$18*1000000000 -> 22330000000 | ... AP8: ='[2]10 Year RFS Curves (2020)'!AJ$18*1000000000 -> 49700000000
A10: D4 Mandate | B10: 800000000 | C10: 1000000000 | D10: 1280000000 | E10: 1630000000 | F10: 1730000000 | G10: 1900000000 | H10: 2000000000 | I10: 2100000000 | J10: ='[2]10 Year RFS Curves (2020)'!D$13*1000000000 -> 2100000000 | K10: ='[2]10 Year RFS Curves (2020)'!E$13*1000000000 -> 2430000000 | L10: ='[2]10 Year RFS Curves (2020)'!F$13*1000000000 -> 2430000000 | M10: ='[2]10 Year RFS Curves (2020)'!G$13*1000000000 -> 2760000000 | N10: ='[2]10 Year RFS Curves (2020)'!H$13*1000000000 -> 2820000000 | O10: ='[2]10 Year RFS Curves (2020)'!I$13*1000000000 -> 3040000000 | P10: ='[2]10 Year RFS Curves (2020)'!J$13*1000000000 -> 3500000000 | Q10: ='[2]10 Year RFS Curves (2020)'!K$13*1000000000 -> 7120000000 | ... AP10: ='[2]10 Year RFS Curves (2020)'!AJ$13*1000000000 -> 12900000000
A11: Small Refinery Exemptions | E11: ='Small Refinery Exemptions'!E42 -> 22999322 | F11: ='Small Refinery Exemptions'!F42 -> 33497303 | G11: ='Small Refinery Exemptions'!G42 -> 47231151 | H11: ='Small Refinery Exemptions'!H42 -> 1.2771936e+08 | I11: ='Small Refinery Exemptions'!I42 -> 2.933604e+08 | J11: ='Small Refinery Exemptions'!J42 -> 3.0339361e+08 | K11: ='Small Refinery Exemptions'!K42 -> 2.3009e+08 | L11: ='Small Refinery Exemptions'!L42 -> 1.5639012e+08 | ... AP11: ='Small Refinery Exemptions'!AP42 -> 1.2236197e+08
A12: D4 Mandate after Exemptions | B12: =B10-B11 -> 800000000 | C12: =C10-C11 -> 1000000000 | D12: =D10-D11 -> 1280000000 | E12: =E10-E11 -> 1.6070007e+09 | F12: =F10-F11 -> 1.6965027e+09 | G12: =G10-G11 -> 1.8527688e+09 | H12: =H10-H11 -> 1.8722806e+09 | I12: =I10-I11 -> 1.8066396e+09 | ... AP12: =AP10-AP11 -> 1.2777638e+10
A14: D3 Mandate | B14: 0 | C14: 0 | D14: 800000 | E14: 33000000 | F14: 123000000 | G14: 230000000 | H14: 311000000 | I14: 288000000 | J14: ='[2]10 Year RFS Curves (2020)'!D$17*1000000000 -> 418000000 | K14: ='[2]10 Year RFS Curves (2020)'!E$17*1000000000 -> 510000000 | L14: ='[2]10 Year RFS Curves (2020)'!F$17*1000000000 -> 560000000 | M14: ='[2]10 Year RFS Curves (2020)'!G$17*1000000000 -> 630000000 | N14: ='[2]10 Year RFS Curves (2020)'!H$17*1000000000 -> 840000000 | O14: ='[2]10 Year RFS Curves (2020)'!I$17*1000000000 -> 1090000000 | P14: ='[2]10 Year RFS Curves (2020)'!J$17*1000000000 -> 1380000000 | Q14: ='[2]10 Year RFS Curves (2020)'!K$17*1000000000 -> 1300000000 | ... AP14: ='[2]10 Year RFS Curves (2020)'!AJ$17*1000000000 -> 16250000000
A15: Small Refinery Exemptions | E15: ='Small Refinery Exemptions'!E41 -> 79200 | F15: ='Small Refinery Exemptions'!F41 -> 437000 | G15: ='Small Refinery Exemptions'!G41 -> 2118300 | H15: ='Small Refinery Exemptions'!H41 -> 10009600 | I15: ='Small Refinery Exemptions'!I41 -> 29496500 | J15: ='Small Refinery Exemptions'!J41 -> 27589700 | K15: ='Small Refinery Exemptions'!K41 -> 30590000 | L15: ='Small Refinery Exemptions'!L41 -> 20706000 | ... AP15: ='Small Refinery Exemptions'!AP41 -> 4.6438118e+08
A16: D3 Mandate after Exemptions | B16: =B14-B15 -> 0 | C16: =C14-C15 -> 0 | D16: =D14-D15 -> 800000 | E16: =E14-E15 -> 32920800 | F16: =F14-F15 -> 122563000 | G16: =G14-G15 -> 227881700 | H16: =H14-H15 -> 300990400 | I16: =I14-I15 -> 258503500 | ... AP16: =AP14-AP15 -> 1.5785619e+10
A18: D5 Mandate (ethanol equivalent gallons) | B18: 1350000000 | C18: 2000000000 | D18: 2670000000 | E18: 2670000000 | F18: 2880000000 | G18: 3610000000 | H18: 4280000000 | I18: 4290000000 | J18: =SUM('[2]10 Year RFS Curves (2020)'!D$13+'[2]10 Year RFS Curves (2020)'!D$15+'[2]10 Year RFS Curves (2020)'!D$17)*1000000000 -> 4920000000 | K18: =SUM('[2]10 Year RFS Curves (2020)'!E$13+'[2]10 Year RFS Curves (2020)'!E$15+'[2]10 Year RFS Curves (2020)'!E$17)*1000000000 -> 4630000000 | L18: =SUM('[2]10 Year RFS Curves (2020)'!F$13+'[2]10 Year RFS Curves (2020)'!F$15+'[2]10 Year RFS Curves (2020)'!F$17)*1000000000 -> 5.05e+09 | M18: =SUM('[2]10 Year RFS Curves (2020)'!G$13+'[2]10 Year RFS Curves (2020)'!G$15+'[2]10 Year RFS Curves (2020)'!G$17)*1000000000 -> 5630000000 | N18: =SUM('[2]10 Year RFS Curves (2020)'!H$13+'[2]10 Year RFS Curves (2020)'!H$15+'[2]10 Year RFS Curves (2020)'!H$17)*1000000000 -> 5940000000 | O18: =SUM('[2]10 Year RFS Curves (2020)'!I$13+'[2]10 Year RFS Curves (2020)'!I$15+'[2]10 Year RFS Curves (2020)'!I$17)*1000000000 -> 6540000000 | P18: =SUM('[2]10 Year RFS Curves (2020)'!J$13+'[2]10 Year RFS Curves (2020)'!J$15+'[2]10 Year RFS Curves (2020)'!J$17)*1000000000 -> 7330000000 | Q18: =SUM('[2]10 Year RFS Curves (2020)'!K$13+'[2]10 Year RFS Curves (2020)'!K$15+'[2]10 Year RFS Curves (2020)'!K$17)*1000000000 -> 9020000000 | ... AP18: =SUM('[2]10 Year RFS Curves (2020)'!AJ$13+'[2]10 Year RFS Curves (2020)'!AJ$15+'[2]10 Year RFS Curves (2020)'!AJ$17)*1000000000 -> 34700000000
A19: Small Refinery Exemptions | E19: ='Small Refinery Exemptions'!E43 -> 32076000 | F19: ='Small Refinery Exemptions'!F43 -> 34730000 | G19: ='Small Refinery Exemptions'!G43 -> 49734000 | H19: ='Small Refinery Exemptions'!H43 -> 157182000 | I19: ='Small Refinery Exemptions'!I43 -> 405790000 | J19: ='Small Refinery Exemptions'!J43 -> 6.2545259e+08 | K19: ='Small Refinery Exemptions'!K43 -> 360430000 | L19: ='Small Refinery Exemptions'!L43 -> 209202000 | ... AP19: ='Small Refinery Exemptions'!AP43 -> 1.0016729e+09
A20: D5 Mandate after Exemptions | B20: =B18-B19 -> 1350000000 | C20: =C18-C19 -> 2000000000 | D20: =D18-D19 -> 2670000000 | E20: =E18-E19 -> 2637924000 | F20: =F18-F19 -> 2845270000 | G20: =G18-G19 -> 3560266000 | H20: =H18-H19 -> 4122818000 | I20: =I18-I19 -> 3884210000 | ... AP20: =AP18-AP19 -> 3.3698327e+10
A22: Unspecified D5 Pre-Exemptions | B22: =B18-B14-(B10*B6) -> 1.4131979e+08 | C22: =C18-C14-(C10*C6) -> 4.822953e+08 | D22: =D18-D14-(D10*D6) -> 6.9553871e+08 | E22: =E18-E14-(E10*E6) -> 1.1153266e+08 | F22: =F18-F14-(F10*F6) -> 77577229 | G22: =G18-G14-(G10*G6) -> 4.5249444e+08 | H22: =H18-H14-(H10*H6) -> 8.7812187e+08 | I22: =I18-I14-(I10*I6) -> 7.5432564e+08 | J22: =J18-J14-(J10*J6) -> 1.2156603e+09 | K22: ='[2]10 Year RFS Curves (2020)'!E$15*1000000000 -> 1690000000 | L22: ='[2]10 Year RFS Curves (2020)'!F$15*1000000000 -> 2060000000 | M22: ='[2]10 Year RFS Curves (2020)'!G$15*1000000000 -> 2240000000 | N22: ='[2]10 Year RFS Curves (2020)'!H$15*1000000000 -> 2.28e+09 | O22: ='[2]10 Year RFS Curves (2020)'!I$15*1000000000 -> 2410000000 | P22: ='[2]10 Year RFS Curves (2020)'!J$15*1000000000 -> 2450000000 | Q22: ='[2]10 Year RFS Curves (2020)'!K$15*1000000000 -> 6e+08 | R22: ='[2]10 Year RFS Curves (2020)'!L$15*1000000000 -> 6e+08 | ... AP22: ='[2]10 Year RFS Curves (2020)'!AJ$15*1000000000 -> 5.55e+09
A23: Unspecified D5 after Exemptions | B23: =B22-(B19+B15+(B11*B6)) -> 1.4131979e+08 | C23: =C22-(C19+C15+(C11*C6)) -> 4.822953e+08 | D23: =D22-(D19+D15+(D11*D6)) -> 6.9553871e+08 | E23: =E22-(E19+E15+(E11*E6)) -> 43743084 | F23: =F22-(F19+F15+(F11*F6)) -> -9470369.8 | G23: =G22-(G19+G15+(G11*G6)) -> 3.2786874e+08 | H23: =H22-(H19+H15+(H11*H6)) -> 5.1354777e+08 | I23: =I22-(I19+I15+(I11*I6)) -> -1.3464612e+08 | ... AP23: =AP22-(AP19+AP15+(AP11*AP6)) -> 3.8769501e+09
A25: D5 Production | B25: ='[1]D5 Gallon Forecast'!C$28 -> 215755059 | C25: ='[1]D5 Gallon Forecast'!D$28 -> 618671889 | D25: ='[1]D5 Gallon Forecast'!E$28 -> 527775069 | E25: ='[1]D5 Gallon Forecast'!F$28 -> 131427352 | F25: ='[1]D5 Gallon Forecast'!G$28 -> 135291787 | G25: ='[1]D5 Gallon Forecast'!H$28 -> 85201935 | H25: ='[1]D5 Gallon Forecast'!I$28 -> 128800020 | I25: ='[1]D5 Gallon Forecast'!J$28 -> 150976112 | ... O25: ='[1]D5 Gallon Forecast'!P$28 -> 164671255 | P25: ='[1]D5 Gallon Forecast'!$BB$28 -> 187865954 | Q25: ='[1]D5 Gallon Forecast'!$BD$28 -> 213000000 | R25: ='[1]D5 Gallon Forecast'!$BF$28 -> 234750000 | S25: ='[1]D5 Gallon Forecast'!$BH$28 -> 246750000 | T25: ='[1]D5 Gallon Forecast'!$BJ$28 -> 260000000 | U25: ='[1]D5 Gallon Forecast'!$BL$28 -> 280000000 | V25: ='[1]D5 Gallon Forecast'!$BN$28 -> 300000000 | W25: ='[1]D5 Gallon Forecast'!BP$28 -> 310000000 | X25: ='[1]D5 Gallon Forecast'!BR$28 -> 325000000 | Y25: ='[1]D5 Gallon Forecast'!BT$28 -> 340000000 | Z25: ='[1]D5 Gallon Forecast'!BV$28 -> 360500000 | AA25: ='[1]D5 Gallon Forecast'!BX$28 -> 380000000 | AB25: ='[1]D5 Gallon Forecast'!BZ$28 -> 400000000 | AC25: ='[1]D5 Gallon Forecast'!CB$28 -> 425000000 | AD25: ='[1]D5 Gallon Forecast'!CD$28 -> 450000000 | AE25: ='[1]D5 Gallon Forecast'!CF$28 -> 475000000 | AF25: ='[1]D5 Gallon Forecast'!CH$28 -> 495000000 | AG25: ='[1]D5 Gallon Forecast'!CJ$28 -> 525000000 | AH25: ='[1]D5 Gallon Forecast'!CL$28 -> 550000000 | AI25: ='[1]D5 Gallon Forecast'!CN$28 -> 575000000 | AJ25: ='[1]D5 Gallon Forecast'!CP$28 -> 600000000 | AK25: ='[1]D5 Gallon Forecast'!CR$28 -> 650000000 | AL25: ='[1]D5 Gallon Forecast'!CT$28 -> 700000000 | AM25: ='[1]D5 Gallon Forecast'!CV$28 -> 800000000 | AN25: ='[1]D5 Gallon Forecast'!CX$28 -> 900000000 | AO25: ='[1]D5 Gallon Forecast'!CZ$28 -> 1000000000 | AP25: ='[1]D5 Gallon Forecast'!DA$28 -> -771793777
A26: Brazilian Ethanol Imports | B26: ='[1]D6 Gallon Forecast'!C$141+'[1]D5 Gallon Forecast'!C$100 -> 175630079 | C26: ='[1]D6 Gallon Forecast'!D$141+'[1]D5 Gallon Forecast'!D$100 -> 575793102 | D26: ='[1]D6 Gallon Forecast'!E$141+'[1]D5 Gallon Forecast'!E$100 -> 435313268 | E26: ='[1]D6 Gallon Forecast'!F$141+'[1]D5 Gallon Forecast'!F$100 -> 65662085 | F26: ='[1]D6 Gallon Forecast'!G$141+'[1]D5 Gallon Forecast'!G$100 -> 95962295 | G26: ='[1]D6 Gallon Forecast'!H$141+'[1]D5 Gallon Forecast'!H$100 -> 46143019 | H26: ='[1]D6 Gallon Forecast'!I$141+'[1]D5 Gallon Forecast'!I$100 -> 86237058 | I26: ='[1]D6 Gallon Forecast'!J$141+'[1]D5 Gallon Forecast'!J$100 -> 90407091 | ... AP26: ='[1]D6 Gallon Forecast'!AQ$141+'[1]D5 Gallon Forecast'!AQ$100 -> 12500010
A27: Unspecified D5 After Exemptions after D5 Production and Ethanol Imports | B27: =IF(B23<SUM(B25:B26),0,B23-B25-B26) -> 0 | C27: =IF(C23<SUM(C25:C26),0,C23-C25-C26) -> 0 | D27: =IF(D23<SUM(D25:D26),0,D23-D25-D26) -> 0 | E27: =IF(E23<SUM(E25:E26),0,E23-E25-E26) -> 0 | F27: =IF(F23<SUM(F25:F26),0,F23-F25-F26) -> 0 | G27: =IF(G23<SUM(G25:G26),0,G23-G25-G26) -> 1.9652378e+08 | H27: =IF(H23<SUM(H25:H26),0,H23-H25-H26) -> 2.9851069e+08 | I27: =IF(I23<SUM(I25:I26),0,I23-I25-I26) -> 0 | ... AP27: =IF(AP23<SUM(AP25:AP26),0,AP23-AP25-AP26) -> 4.6362439e+09
A28: Converted Back to Biodiesel Gallons | B28: =B27/B6 -> 0 | C28: =C27/C6 -> 0 | D28: =D27/D6 -> 0 | E28: =E27/E6 -> 0 | F28: =F27/F6 -> 0 | G28: =G27/G6 -> 1.2754722e+08 | H28: =H27/H6 -> 1.9315591e+08 | I28: =I27/I6 -> 0 | ... AP28: =AP27/AP6 -> 2.7406349e+09
A30: Unspecified math result (row 22) | K30: =K$18-K$14-(K$10*K$6) -> 3.1819929e+08 | L30: =L$18-L$14-(L$10*L$6) -> 6.4689292e+08 | M30: =M$18-M$14-(M$10*M$6) -> 5.8097572e+08 | N30: =N$18-N$14-(N$10*N$6) -> 5.4784611e+08 | O30: =O$18-O$14-(O$10*O$6) -> 5.0566177e+08 | P30: =P$18-P$14-(P$10*P$6) -> 2.5320628e+08 | Q30: =Q$18-Q$14-(Q$10*Q$6) -> -3.8867721e+09 | R30: =R$18-R$14-(R$10*R$6) -> -4.1525034e+09 | ... AP30: =AP$18-AP$14-(AP$10*AP$6) -> -3.3725152e+09
A31: Ethanol Production | K31: ='[1]D6 Gallon Forecast'!L$7 -> 12845194670 | L31: ='[1]D6 Gallon Forecast'!M$7 -> 14110176420 | M31: ='[1]D6 Gallon Forecast'!N$7 -> 14409400981 | N31: ='[1]D6 Gallon Forecast'!O$7 -> 14666291777 | O31: ='[1]D6 Gallon Forecast'!P$7 -> 14853081800 | P31: ='[1]D6 Gallon Forecast'!Q$7 -> 1.4581439e+10 | Q31: ='[1]D6 Gallon Forecast'!R$7 -> 1.4655294e+10 | R31: ='[1]D6 Gallon Forecast'!S$7 -> 1.4687015e+10 | ... V31: ='[1]D6 Gallon Forecast'!W$7 -> 1.5203857e+10 | W31: =W22-W30 -> 5.6590847e+09 | X31: =X22-X30 -> 5.9357356e+09 | Y31: =Y22-Y30 -> 5.9114575e+09 | Z31: =Z22-Z30 -> 6.0042795e+09 | AA31: =AA22-AA30 -> 6.1699101e+09 | AB31: =AB22-AB30 -> 6.3335522e+09 | AC31: =AC22-AC30 -> 6.4272679e+09 | AD31: =AD22-AD30 -> 5.311249e+09 | ... AP31: =AP22-AP30 -> 8.9225152e+09
A32: Ethanol Mandate | K32: ='[2]10 Year RFS Curves (2020)'!E$16*1000000000+250000000 -> 12750000000 | L32: ='[2]10 Year RFS Curves (2020)'!F$16*1000000000+250000000 -> 14040000000 | M32: ='[2]10 Year RFS Curves (2020)'!G$16*1000000000+250000000 -> 1.525e+10 | N32: ='[2]10 Year RFS Curves (2020)'!H$16*1000000000+250000000 -> 15500000000 | O32: ='[2]10 Year RFS Curves (2020)'!I$16*1000000000+250000000 -> 15250000000 | P32: ='[2]10 Year RFS Curves (2020)'!J$16*1000000000 -> 15000000000 | Q32: ='[2]10 Year RFS Curves (2020)'!K$16*1000000000 -> 1.5e+10 | R32: ='[2]10 Year RFS Curves (2020)'!L$16*1000000000 -> 15000000000 | S32: ='[2]10 Year RFS Curves (2020)'!M$16*1000000000 -> 1.5e+10 | T32: ='[2]10 Year RFS Curves (2020)'!N$16*1000000000 -> 15000000000 | U32: ='[2]10 Year RFS Curves (2020)'!O$16*1000000000 -> 15000000000 | V32: ='[2]10 Year RFS Curves (2020)'!P$16*1000000000 -> 15000000000 | W32: =W$20-W$16-(W$12*W$6) -> -3.7237355e+09 | X32: =X$20-X$16-(X$12*X$6) -> -3.4302832e+09 | Y32: =Y$20-Y$16-(Y$12*Y$6) -> -2.6684243e+09 | Z32: =Z$20-Z$16-(Z$12*Z$6) -> -1.9455459e+09 | AA32: =AA$20-AA$16-(AA$12*AA$6) -> -1.4197138e+09 | AB32: =AB$20-AB$16-(AB$12*AB$6) -> -8.8373951e+08 | AC32: =AC$20-AC$16-(AC$12*AC$6) -> -2.8918557e+08 | AD32: =AD$20-AD$16-(AD$12*AD$6) -> 3.3556151e+09 | ... AP32: =AP$20-AP$16-(AP$12*AP$6) -> -3.7028111e+09
A33: Ethanol Gap | K33: =K32-K31 -> -95194670 | L33: =L32-L31 -> -70176420 | M33: =M32-M31 -> 8.4059902e+08 | N33: =N32-N31 -> 833708223 | O33: =O32-O31 -> 396918200 | P33: =P32-P31 -> 4.1856123e+08 | Q33: =Q32-Q31 -> 3.4470611e+08 | R33: =R32-R31 -> 3.1298522e+08 | ... V33: =V32-V31 -> -2.0385693e+08 | W33: =W23-W32 -> 4.9487022e+09 | X33: =X23-X32 -> 5.1832354e+09 | Y33: =Y23-Y32 -> 5.2137865e+09 | Z33: =Z23-Z32 -> 5.6518444e+09 | AA33: =AA23-AA32 -> 5.6458986e+09 | AB33: =AB23-AB32 -> 5.6864048e+09 | AC33: =AC23-AC32 -> 5.6423225e+09 | AD33: =AD23-AD32 -> 4.5214191e+09 | ... AP33: =AP23-AP32 -> 7.5797612e+09
A34: Additional D4 Production adjusted to biomass-based diesel gallons | K34: =K33/K6 -> -60845653 | L34: =L33/L6 -> -44372612 | M34: =M33/M6 -> 5.2501483e+08 | N34: =N33/N6 -> 5.1647138e+08 | O34: =O33/O6 -> 2.4404304e+08 | P34: =P33/P6 -> 2.5715593e+08 | Q34: =Q33/Q6 -> 2.1145479e+08 | R34: =R33/R6 -> 1.9158445e+08 | ... Z34: =Z33/Z6 -> 3.4198903e+09
A35: Total Potential Biomass-Based Diesel Production | K35: =K12+K30+K34 -> 2.4572636e+09 | L35: =L12+L30+L34 -> 2.8761302e+09 | M35: =M12+M30+M34 -> 3.6817491e+09 | N35: =N12+N30+N34 -> 3.7239037e+09 | O35: =O12+O30+O34 -> 3.6342213e+09 | P35: =P12+P30+P34 -> 3.8324051e+09 | Q35: =Q12+Q30+Q34 -> 3.216697e+09 | R35: =R12+R30+R34 -> 3.0982657e+09 | ... Z35: =Z12+Z30+Z34 -> 1.0702706e+10
A36: Predicted Biomass-Based Diesel Production | K36: =SUM(K5) -> 3053952222 | L36: =SUM(L5) -> 3291964808 | M36: =SUM(M5) -> 3838259872 | N36: =SUM(N5) -> 5164203423 | O36: =SUM(O5) -> 5705051178 | P36: =SUM(P5) -> 4.4322265e+09 | Q36: =SUM(Q5) -> 4.2452781e+09 | R36: =SUM(R5) -> 4.5347393e+09 | ... Z36: =SUM(Z5) -> 5.6489183e+09
A37: Production needed beyond BBD production | K37: =K35-K36 -> -5.9668859e+08 | L37: =L35-L36 -> -4.1583463e+08 | M37: =M35-M36 -> -1.5651072e+08 | N37: =N35-N36 -> -1.4402997e+09 | O37: =O35-O36 -> -2.0708299e+09 | P37: =P35-P36 -> -5.9982145e+08 | Q37: =Q35-Q36 -> -1.0285811e+09 | R37: =R35-R36 -> -1.4364736e+09 | ... Z37: =Z35-Z36 -> 5.0537874e+09
A39: Additional D4 production after exemptions and ethanol imports | B39: =IF(B43-B25<0,0,B43-B25) -> 0 | C39: =IF(C43-C25<0,0,C43-C25) -> 0 | D39: =IF(D43-D25<0,0,D43-D25) -> 0 | E39: =IF(E43-E25<0,0,E43-E25) -> 0 | F39: =IF(F43-F25<0,0,F43-F25) -> 0 | G39: =IF(G43-G25<0,0,G43-G25) -> 1.6337958e+08 | H39: =IF(H43-H25<0,0,H43-H25) -> 2.4823885e+08 | I39: =IF(I43-I25<0,0,I43-I25) -> 0 | ... AP39: =IF(AP43-AP25<0,0,AP43-AP25) -> 3.0561962e+09
A40: D4 Production with UAB after ethanol imports and D5 production | B40: =B39+B12 -> 800000000 | C40: =C39+C12 -> 1000000000 | D40: =D39+D12 -> 1280000000 | E40: =E39+E12 -> 1.6070007e+09 | F40: =F39+F12 -> 1.6965027e+09 | G40: =G39+G12 -> 2.0161484e+09 | H40: =H39+H12 -> 2.1205195e+09 | I40: =I39+I12 -> 1.8066396e+09 | ... AP40: =AP39+AP12 -> 1.5833834e+10
A42: Unspecified D5 after Exemptions and Ethanol Imports | B42: =IF(B23-B26<0,0,B23-B26) -> 0 | C42: =IF(C23-C26<0,0,C23-C26) -> 0 | D42: =IF(D23-D26<0,0,D23-D26) -> 2.6022544e+08 | E42: =IF(E23-E26<0,0,E23-E26) -> 0 | F42: =IF(F23-F26<0,0,F23-F26) -> 0 | G42: =IF(G23-G26<0,0,G23-G26) -> 2.8172572e+08 | H42: =IF(H23-H26<0,0,H23-H26) -> 4.2731071e+08 | I42: =IF(I23-I26<0,0,I23-I26) -> 0 | ... AP42: =IF(AP23-AP26<0,0,AP23-AP26) -> 3.8644501e+09
A43: Unspecified D5 after Ethanol Imports Adjusted to Biodiesel Gallons | B43: =B42*1.5/1.7 -> 0 | C43: =C42*1.5/1.7 -> 0 | D43: =D42*1.5/1.7 -> 2.2961069e+08 | E43: =E42*1.5/1.7 -> 0 | F43: =F42*1.5/1.7 -> 0 | G43: =G42*1.5/1.7 -> 2.4858152e+08 | H43: =H42*1.5/1.7 -> 3.7703887e+08 | I43: =I42*1.5/1.7 -> 0 | ... K43: =K42*1.5/1.7 -> 6.5454146e+08 | L43: =L42/L6 -> 9.5465746e+08 | M43: =M42/M6 -> 9.8742698e+08 | N43: =N42/N6 -> 1.090898e+09 | O43: =O42/O6 -> 1.184161e+09 | P43: =P42/P6 -> 1.1604749e+09 | Q43: =Q42/Q6 -> 0 | R43: =R42/R6 -> 0 | S43: =S42/S6 -> 1.7459965e+08 | ... AP43: =AP42/AP6 -> 2.2844024e+09
A49: D6 Mandate | B49: =B8-B18 -> 12600000000 | C49: =C8-C18 -> 13200000000 | D49: =D8-D18 -> 13880000000 | E49: =E8-E18 -> 13610000000 | F49: =F8-F18 -> 14050000000 | G49: =G8-G18 -> 14500000000 | H49: =H8-H18 -> 15000000000 | I49: =I8-I18 -> 15000000000 | ... K49: =K8-K18 -> 1.25e+10 | L49: ='[2]10 Year RFS Curves (2020)'!F$16*1000000000 -> 13790000000 | M49: ='[2]10 Year RFS Curves (2020)'!G$16*1000000000 -> 1.5e+10 | N49: ='[2]10 Year RFS Curves (2020)'!H$16*1000000000 -> 15250000000 | O49: ='[2]10 Year RFS Curves (2020)'!I$16*1000000000 -> 15000000000 | P49: ='[2]10 Year RFS Curves (2020)'!J$16*1000000000 -> 15000000000 | Q49: ='[2]10 Year RFS Curves (2020)'!K$16*1000000000 -> 1.5e+10 | R49: ='[2]10 Year RFS Curves (2020)'!L$16*1000000000 -> 15000000000 | S49: ='[2]10 Year RFS Curves (2020)'!M$16*1000000000 -> 1.5e+10 | ... AP49: ='[2]10 Year RFS Curves (2020)'!AJ$16*1000000000 -> 15000000000
A50: Small Refinery Exemptions | E50: ='Small Refinery Exemptions'!E38 -> 160776000 | F50: ='Small Refinery Exemptions'!F38 -> 1.7664e+08 | G50: ='Small Refinery Exemptions'!G38 -> 2.4253e+08 | H50: ='Small Refinery Exemptions'!H38 -> 632638000 | I50: ='Small Refinery Exemptions'!I38 -> 1418560000 | J50: ='Small Refinery Exemptions'!J38 -> 1415836000 | K50: ='Small Refinery Exemptions'!K38 -> 1098580000 | L50: ='Small Refinery Exemptions'!L38 -> 563346000 | ... AG50: ='Small Refinery Exemptions'!AG38 -> 3.5079082e+08 | AH50: ='Small Refinery Exemptions'!AP38 -> 4.5885434e+08 | AI50: ='Small Refinery Exemptions'!AQ38 -> 0 | AJ50: ='Small Refinery Exemptions'!AR38 -> 0 | AK50: ='Small Refinery Exemptions'!AS38 -> 0 | AL50: ='Small Refinery Exemptions'!AT38 -> 0 | AM50: ='Small Refinery Exemptions'!AU38 -> 0 | AN50: ='Small Refinery Exemptions'!AV38 -> 0 | AO50: ='Small Refinery Exemptions'!AW38 -> 0 | AP50: ='Small Refinery Exemptions'!AX38 -> 0
A51: D6 Mandate after Exemptions | B51: =B49-B50 -> 12600000000 | C51: =C49-C50 -> 13200000000 | D51: =D49-D50 -> 13880000000 | E51: =E49-E50 -> 13449224000 | F51: =F49-F50 -> 13873360000 | G51: =G49-G50 -> 14257470000 | H51: =H49-H50 -> 14367362000 | I51: =I49-I50 -> 13581440000 | ... AP51: =AP49-AP50 -> 15000000000
A53: D7 Mandate | D53: =D18-(D10*D6)-D14 -> 6.9553871e+08 | E53: =E18-(E10*E6)-E14 -> 1.1153266e+08 | F53: =F18-(F10*F6)-F14 -> 77577229 | G53: =G18-(G10*G6)-G14 -> 4.5249444e+08 | H53: =H18-(H10*H6)-H14 -> 8.7812187e+08 | I53: =I18-(I10*I6)-I14 -> 7.5432564e+08 | J53: =J18-(J10*J6)-J14 -> 1.2156603e+09 | K53: =K18-(K10*K6)-K14 -> 3.1819929e+08 | ... X53: =X18-(X10*X6)-X14 -> -3.2857356e+09
A54: Small Refinery Exemptions | D54: ='Small Refinery Exemptions'!E52 -> 38295.525 | E54: ='Small Refinery Exemptions'!F52 -> 775.47545 | F54: ='Small Refinery Exemptions'!G52 -> 4097.9341 | G54: ='Small Refinery Exemptions'!H52 -> 27732.116 | H54: ='Small Refinery Exemptions'!I52 -> 203824.16 | I54: ='Small Refinery Exemptions'!J52 -> 214833.34 | J54: ='Small Refinery Exemptions'!K52 -> 96896.826 | K54: ='Small Refinery Exemptions'!L52 -> 2287.4787 | ... X54: ='Small Refinery Exemptions'!Y52 -> 0.10158888
A55: D7 Mandate after Exemptions | D55: =D53-D54 -> 6.9550042e+08 | E55: =E53-E54 -> 1.1153189e+08 | F55: =F53-F54 -> 77573131 | G55: =G53-G54 -> 4.524667e+08 | H55: =H53-H54 -> 8.7791804e+08 | I55: =I53-I54 -> 7.541108e+08 | J55: =J53-J54 -> 1.2155634e+09 | K55: =K53-K54 -> 3.18197e+08 | ... X55: =X53-X54 -> -3.2857356e+09
A58: STEO Gasoline Consumption | M58: =8.76*42*365/1000 -> 134.2908 | N58: =8.74*365*42/1000 -> 133.9842
M59: =M58*'Small Refinery Exemptions'!N29 -> 11.132707 | N59: =N58*'Small Refinery Exemptions'!O29 -> 11.482446
N62: =N2*1.5 -> 3275240976 | O62: =O2*1.5 -> 3110985096
N63: =SUM(N3:N4)*1.7 -> 5.067206e+09 | O63: =SUM(O3:O4)*1.7 -> 6.1728039e+09
N64: =SUM(N62:N63) -> 8.342447e+09 | O64: =SUM(O62:O63) -> 9.283789e+09
N66: =N5*1.6 -> 8.2627255e+09 | O66: =O5*1.6 -> 9.1280819e+09
A72: Co-Processing
A73: Unspecified D5
A75: D5 Balance for D4 before Exemptions | B75: =IF(B22-B25<0,0,B22-B25) -> 0 | C75: =IF(C22-C25<0,0,C22-C25) -> 0 | D75: =IF(D22-D25<0,0,D22-D25) -> 1.6776364e+08 | E75: =IF(E22-E25<0,0,E22-E25) -> 0 | F75: =IF(F22-F25<0,0,F22-F25) -> 0 | G75: =IF(G22-G25<0,0,G22-G25) -> 3.672925e+08 | H75: =IF(H22-H25<0,0,H22-H25) -> 7.4932185e+08 | I75: =IF(I22-I25<0,0,I22-I25) -> 6.0334952e+08 | ... O75: =IF(O22-O25<0,0,O22-O25) -> 2245328745
A77: Amount for D4 | B77: =IF(B75<0,0,B75/1.54) -> 0 | C77: =IF(C75<0,0,C75/1.54) -> 0 | D77: =IF(D75<0,0,D75/1.54) -> 1.0893743e+08 | E77: =IF(E75<0,0,E75/1.54) -> 0 | F77: =IF(F75<0,0,F75/1.54) -> 0 | G77: =IF(G75<0,0,G75/1.54) -> 2.3850162e+08 | H77: =IF(H75<0,0,H75/1.54) -> 4.8657263e+08 | I77: =IF(I75<0,0,I75/1.54) -> 3.9178541e+08 | J77: =IF(J75<0,0,J75/1.54) -> 6.0454109e+08 | K77: =IF(K75<0,0,K75/K6) -> 8.9638943e+08 | L77: =IF(L75<0,0,L75/L6) -> 1.1899659e+09 | M77: =IF(M75<0,0,M75/M6) -> 1.2389027e+09 | N77: =IF(N75<0,0,N75/N6) -> 1.2981985e+09 | O77: =IF(O75<0,0,O75/O6) -> 1.3805284e+09
A78: Portion of D5 Production Falling to D4 after Exemptions | B78: =IF(B39>0,B39/1.54,0) -> 0 | C78: =IF(C39>0,C39/1.54,0) -> 0 | D78: =IF(D39>0,D39/1.54,0) -> 0 | E78: =IF(E39>0,E39/1.54,0) -> 0 | F78: =IF(F39>0,F39/1.54,0) -> 0 | G78: =IF(G39>0,G39/1.54,0) -> 1.0609064e+08 | H78: =IF(H39>0,H39/1.54,0) -> 1.6119406e+08 | I78: =IF(I39>0,I39/1.54,0) -> 0 | J78: =IF(J39>0,J39/1.54,0) -> 0 | K78: =IF(K39>0,K39/K6,0) -> 2.3455457e+08 | L78: =IF(L39>0,L39/L6,0) -> 4.910568e+08 | M78: =IF(M39>0,M39/M6,0) -> 4.565803e+08 | N78: =IF(N39>0,N39/N6,0) -> 5.6156526e+08 | O78: =IF(O39>0,O39/O6,0) -> 6.2682782e+08
A79: D4 Mandate + D5 | B79: =B10+B77 -> 800000000 | C79: =C10+C77 -> 1000000000 | D79: =D10+D77 -> 1.3889374e+09 | E79: =E10+E77 -> 1630000000 | F79: =F10+F77 -> 1730000000 | G79: =G10+G77 -> 2.1385016e+09 | H79: =H10+H77 -> 2.4865726e+09 | I79: =I10+I77 -> 2.4917854e+09 | ... O79: =O10+O77 -> 4.4205284e+09
A80: D4 Mandate + D5 After Exemptions | B80: =B12+B78 -> 800000000 | C80: =C12+C78 -> 1000000000 | D80: =D12+D78 -> 1280000000 | E80: =E12+E78 -> 1.6070007e+09 | F80: =F12+F78 -> 1.6965027e+09 | G80: =G12+G78 -> 1.9588595e+09 | H80: =H12+H78 -> 2.0334747e+09 | I80: =I12+I78 -> 1.8066396e+09 | ... O80: =O12+O78 -> 3.5113443e+09
A82: Actual D4 Consumption | B82: =B5 -> 1148127230 | C82: =C5 -> 1169888805 | D82: =D5 -> 2029133049 | E82: =E5 -> 1985220612 | F82: =F5 -> 2108061929 | G82: =G5 -> 2903114924 | H82: =H5 -> 2658035441 | I82: =I5 -> 2669533040 | ... O82: =O5 -> 5705051178
A83: Projection - Actual | B83: =B82-B80 -> 348127230 | C83: =C82-C80 -> 169888805 | D83: =D82-D80 -> 749133049 | E83: =E82-E80 -> 3.7821993e+08 | F83: =F82-F80 -> 4.1155923e+08 | G83: =G82-G80 -> 9.4425544e+08 | H83: =H82-H80 -> 6.2456075e+08 | I83: =I82-I80 -> 8.6289344e+08 | ... O83: =O82-O80 -> 2.1937069e+09
A84: Actual California Biodiesel Production | B84: 19975945 | C84: 59901129 | D84: 66798096 | E84: 126450435 | F84: 163348743 | G84: 170005865 | H84: 200000000 | I84: 275000000 | J84: 350000000 | K84: 350000000 | L84: 350000000 | M84: 350000000 | N84: 350000000 | O84: 350000000
A85: Actual California Renewable Diesel Production | B85: 8814907 | C85: 116939022 | D85: 112844869 | E85: 165157935 | F85: 257671157 | G85: 335464394 | H85: 450000000 | I85: 570000000 | J85: 650000000 | K85: 650000000 | L85: 650000000 | M85: 650000000 | N85: 650000000 | O85: 650000000
A86: Estimated California Co-Processing
A87: Total California D4 | B87: =B85+B84 -> 28790852 | C87: =C85+C84 -> 176840151 | D87: =D85+D84 -> 179642965 | E87: =E85+E84 -> 291608370 | F87: =F85+F84 -> 421019900 | G87: =G85+G84 -> 505470259 | H87: =H85+H84 -> 650000000 | I87: =I85+I84 -> 845000000 | ... O87: =O85+O84 -> 1000000000
A88: Renewable Diesel Projection

Sheet RIN Balance Sheet
B1: 2010 | C1: 2011 | D1: 2012 | E1: 2013 | F1: 2014 | G1: 2015 | H1: 2016 | I1: 2017 | J1: 2018 | K1: 2019 | L1: 2020 | M1: 2021 | N1: 2022 | O1: 2023 | P1: 2024 | Q1: 2025 | R1: 2026
A2: RIN BANK BEGINNING BALANCE | B2: 0 | C2: =B26 -> 2812465761 | D2: =C26 -> 4551975041 | E2: =D31 -> 2471227385 | F2: =E31 -> 1583274541 | G2: =F31 -> 1694877229 | H2: =G31 -> 1648646780 | I2: =H31 -> 2476536173 | J2: =I31 -> 3055845408 | K2: =J31 -> 2618280949 | L2: =K31 -> 1217208431 | ... R2: =Q31 -> -5.1639801e+08
A4: RIN GENERATION | B4: =SUM(B5:B9) -> 7147975929 | C4: =SUM(C5:C9) -> 15535487739 | D4: =SUM(D5:D9) -> 15352270097 | E4: =SUM(E5:E9) -> 16649629221 | F4: =SUM(F5:F9) -> 17245997350 | G4: =SUM(G5:G9) -> 17931107377 | H4: =SUM(H5:H9) -> 19475036022 | I4: =SUM(I5:I9) -> 19354130885 | ... R4: =SUM(R5:R9) -> 2.3944824e+10
A5: D3 | B5: ='[1]D3 RIN Forecast'!B$15 -> 0 | C5: ='[1]D3 RIN Forecast'!C$15 -> 0 | D5: ='[1]D3 RIN Forecast'!D$15 -> 20069 | E5: ='[1]D3 RIN Forecast'!E$15 -> 422740 | F5: ='[1]D3 RIN Forecast'!F$15 -> 33360560 | G5: ='[1]D3 RIN Forecast'!G$15 -> 142040241 | H5: ='[1]D3 RIN Forecast'!H$15 -> 192361795 | I5: ='[1]D3 RIN Forecast'!I$15 -> 250624473 | ... R5: ='[1]D3 RIN Forecast'!R$15 -> 7.7255883e+08
A6: D4 | B6: ='[1]D4 RIN Forecast'!B$27 -> 323276448 | C6: ='[1]D4 RIN Forecast'!C$27 -> 1691614024 | D6: ='[1]D4 RIN Forecast'!D$27 -> 1737333997 | E6: ='[1]D4 RIN Forecast'!E$27 -> 2740474431 | F6: ='[1]D4 RIN Forecast'!F$27 -> 2709972461 | G6: ='[1]D4 RIN Forecast'!G$27 -> 2795798365 | H6: ='[1]D4 RIN Forecast'!H$27 -> 4008319745 | I6: ='[1]D4 RIN Forecast'!I$27 -> 3848913464 | ... R6: ='[1]D4 RIN Forecast'!R$27 -> 8.1904747e+09
A7: D5 | B7: ='[1]D5 RIN Forecast'!B$28 -> 28611632 | C7: ='[1]D5 RIN Forecast'!C$28 -> 228558018 | D7: ='[1]D5 RIN Forecast'!D$28 -> 627072689 | E7: ='[1]D5 RIN Forecast'!E$28 -> 557824688 | F7: ='[1]D5 RIN Forecast'!F$28 -> 143540533 | G7: ='[1]D5 RIN Forecast'!G$28 -> 147091443 | H7: ='[1]D5 RIN Forecast'!H$28 -> 98103017 | I7: ='[1]D5 RIN Forecast'!I$28 -> 143646572 | ... R7: ='[1]D5 RIN Forecast'!R$28 -> 3.093207e+08
A8: D6 | B8: ='[1]D6 RIN Forecast'!B$23 -> 6796087849 | C8: ='[1]D6 RIN Forecast'!C$23 -> 13615315697 | D8: ='[1]D6 RIN Forecast'!D$23 -> 12987841601 | E8: ='[1]D6 RIN Forecast'!E$23 -> 13350511585 | F8: ='[1]D6 RIN Forecast'!F$23 -> 14359064491 | G8: ='[1]D6 RIN Forecast'!G$23 -> 14845902013 | H8: ='[1]D6 RIN Forecast'!H$23 -> 15175717036 | I8: ='[1]D6 RIN Forecast'!I$23 -> 15109202482 | ... R8: ='[1]D6 RIN Forecast'!R$23 -> 1.4672199e+10
A9: D7 | B9: ='[1]D7 RIN Forecast'!B$13 -> 0 | C9: ='[1]D7 RIN Forecast'!C$13 -> 0 | D9: ='[1]D7 RIN Forecast'!D$13 -> 1741 | E9: ='[1]D7 RIN Forecast'!E$13 -> 395777 | F9: ='[1]D7 RIN Forecast'!F$13 -> 59305 | G9: ='[1]D7 RIN Forecast'!G$13 -> 275315 | H9: ='[1]D7 RIN Forecast'!H$13 -> 534429 | I9: ='[1]D7 RIN Forecast'!I$13 -> 1743894 | ... R9: ='[1]D7 RIN Forecast'!R$13 -> 271355.96
A10: Small Refinery Exemptions | C10: ='Small Refinery Exemptions'!B44 -> 0 | D10: ='Small Refinery Exemptions'!C44 -> 0 | E10: ='Small Refinery Exemptions'!D44 -> 0 | F10: ='Small Refinery Exemptions'!E44 -> 192852000 | G10: ='Small Refinery Exemptions'!F44 -> 2.1137e+08 | H10: ='Small Refinery Exemptions'!G44 -> 2.92264e+08 | I10: ='Small Refinery Exemptions'!H44 -> 789820000 | J10: ='Small Refinery Exemptions'!I44 -> 1824350000 | ... R10: ='Small Refinery Exemptions'!Q44 -> 875771000
A11: Errors | B11: ='RIN Retirements'!B25 -> 25113475 | C11: ='RIN Retirements'!C25 -> 78473364 | D11: ='RIN Retirements'!D25 -> 45611665 | E11: ='RIN Retirements'!E25 -> 40623544 | F11: ='RIN Retirements'!F25 -> 21899568 | G11: ='RIN Retirements'!G25 -> 9513432 | H11: ='RIN Retirements'!H25 -> 27233554 | I11: ='RIN Retirements'!I25 -> 38658277 | ... R11: ='RIN Retirements'!R25 -> 0
A12: Others | B12: ='RIN Retirements'!B47 -> 99069268 | C12: ='RIN Retirements'!C47 -> 390181518 | D12: ='RIN Retirements'!D47 -> 90759633 | E12: ='RIN Retirements'!E47 -> 176478026 | F12: ='RIN Retirements'!F47 -> 373012020 | G12: ='RIN Retirements'!G47 -> 240715075 | H12: ='RIN Retirements'!H47 -> 327881218 | I12: ='RIN Retirements'!I47 -> 420188084 | ... N12: ='RIN Retirements'!N47 -> 266712690 | O12: ='RIN Retirements'!R47 -> 0 | P12: ='RIN Retirements'!S47 -> 0 | Q12: ='RIN Retirements'!T47 -> 0 | R12: ='RIN Retirements'!U47 -> 0
A13: NET RIN GENERATION | B13: =B4-B10-B11-B12 -> 7023793186 | C13: =C4-C10-C11-C12 -> 15066832857 | D13: =D4-D10-D11-D12 -> 15215898799 | E13: =E4-E10-E11-E12 -> 16432527651 | F13: =F4-F10-F11-F12 -> 16658233762 | G13: =G4-G10-G11-G12 -> 17469508870 | H13: =H4-H10-H11-H12 -> 18827657250 | I13: =I4-I10-I11-I12 -> 18105464524 | ... R13: =R4-R10-R11-R12 -> 2.3069053e+10
A15: RIN RETIREMENT | B15: =SUM(B16:B20) -> 4211327425 | C15: =SUM(C16:C20) -> 13327323577 | D15: =SUM(D16:D20) -> 16296553703 | E15: =SUM(E16:E20) -> 17311269123 | F15: =SUM(F16:F20) -> 16660418629 | G15: =SUM(G16:G20) -> 17838472400 | H15: =SUM(H16:H20) -> 17888987566 | I15: =SUM(I16:I20) -> 18152769160 | ... R15: =SUM(R16:R20) -> 2.3633519e+10
A16: D3 | B16: ='RIN Retirements'!B4 -> 0 | C16: ='RIN Retirements'!C4 -> 0 | D16: ='RIN Retirements'!D4 -> 0 | E16: ='RIN Retirements'!E4 -> 293023 | F16: ='RIN Retirements'!F4 -> 21143070 | G16: ='RIN Retirements'!G4 -> 112841471 | H16: ='RIN Retirements'!H4 -> 189349748 | I16: ='RIN Retirements'!I4 -> 259889372 | ... L16: ='RIN Retirements'!L4 -> 503825187 | M16: =M5*(SUM(H16:L16)/SUM(H5:L5)) -> 5.5901454e+08 | N16: =N5*(SUM(I16:M16)/SUM(I5:M5)) -> 6.5750702e+08 | O16: =O5*(SUM(J16:N16)/SUM(J5:N5)) -> 6.8869921e+08 | P16: =P5*(SUM(K16:O16)/SUM(K5:O5)) -> 9.0777219e+08 | Q16: =Q5*(SUM(L16:P16)/SUM(L5:P5)) -> 6.3306676e+08 | R16: =R5*(SUM(M16:Q16)/SUM(M5:Q5)) -> 7.5949767e+08
A17: D4 | B17: ='RIN Retirements'!B8 -> 222710547 | C17: ='RIN Retirements'!C8 -> 1319863392 | D17: ='RIN Retirements'!D8 -> 1679016522 | E17: ='RIN Retirements'!E8 -> 2379043691 | F17: ='RIN Retirements'!F8 -> 2720901529 | G17: ='RIN Retirements'!G8 -> 2876836117 | H17: ='RIN Retirements'!H8 -> 3281819764 | I17: ='RIN Retirements'!I8 -> 3844871513 | ... L17: ='RIN Retirements'!L8 -> 4288533419 | M17: =M6*(SUM(H17:L17)/SUM(H6:L6)) -> 4.7400204e+09 | N17: =N6*(SUM(I17:M17)/SUM(I6:M6)) -> 5.796855e+09 | O17: =O6*(SUM(J17:N17)/SUM(J6:N6)) -> 7.9826367e+09 | P17: =P6*(SUM(K17:O17)/SUM(K6:O6)) -> 9.1631112e+09 | Q17: =Q6*(SUM(L17:P17)/SUM(L6:P6)) -> 7.728135e+09 | R17: =R6*(SUM(M17:Q17)/SUM(M6:Q6)) -> 8.1504821e+09
A18: D5 | B18: ='RIN Retirements'!B12 -> 24808442 | C18: ='RIN Retirements'!C12 -> 173316504 | D18: ='RIN Retirements'!D12 -> 481271750 | E18: ='RIN Retirements'!E12 -> 673610540 | F18: ='RIN Retirements'!F12 -> 130729680 | G18: ='RIN Retirements'!G12 -> 101203401 | H18: ='RIN Retirements'!H12 -> 181556905 | I18: ='RIN Retirements'!I12 -> 150031625 | ... L18: ='RIN Retirements'!L12 -> 332236392 | M18: =M7*(SUM(H18:L18)/SUM(H7:L7)) -> 2.5322338e+08 | N18: =N7*(SUM(I18:M18)/SUM(I7:M7)) -> 3.4986132e+08 | O18: =O7*(SUM(J18:N18)/SUM(J7:N7)) -> 2.6775537e+08 | P18: =P7*(SUM(K18:O18)/SUM(K7:O7)) -> 2.4928444e+08 | Q18: =Q7*(SUM(L18:P18)/SUM(L7:P7)) -> 2.8047891e+08 | R18: =R7*(SUM(M18:Q18)/SUM(M7:Q7)) -> 3.1935997e+08
A19: D6 | B19: ='RIN Retirements'!B16 -> 3963808436 | C19: ='RIN Retirements'!C16 -> 11834143681 | D19: ='RIN Retirements'!D16 -> 14136265431 | E19: ='RIN Retirements'!E16 -> 14257997232 | F19: ='RIN Retirements'!F16 -> 13787538096 | G19: ='RIN Retirements'!G16 -> 14747491411 | H19: ='RIN Retirements'!H16 -> 14235690161 | I19: ='RIN Retirements'!I16 -> 13896400123 | ... L19: ='RIN Retirements'!L16 -> 12720304774 | M19: =M8*(SUM(H19:L19)/SUM(H8:L8)) -> 1.3836124e+10 | N19: =N8*(SUM(I19:M19)/SUM(I8:M8)) -> 1.421059e+10 | O19: =O8*(SUM(J19:N19)/SUM(J8:N8)) -> 1.4635639e+10 | P19: =P8*(SUM(K19:O19)/SUM(K8:O8)) -> 1.47393e+10 | Q19: =Q8*(SUM(L19:P19)/SUM(L8:P8)) -> 1.4327607e+10 | R19: =R8*(SUM(M19:Q19)/SUM(M8:Q8)) -> 1.4403896e+10
A20: D7 | B20: ='RIN Retirements'!B20 -> 0 | C20: ='RIN Retirements'!C20 -> 0 | D20: ='RIN Retirements'!D20 -> 0 | E20: ='RIN Retirements'!E20 -> 324637 | F20: ='RIN Retirements'!F20 -> 106254 | G20: ='RIN Retirements'!G20 -> 100000 | H20: ='RIN Retirements'!H20 -> 570988 | I20: ='RIN Retirements'!I20 -> 1576527 | ... L20: ='RIN Retirements'!L20 -> 55892 | M20: =M9*(SUM(H20:L20)/SUM(H9:L9)) -> 237286.44 | N20: =N9*(SUM(I20:M20)/SUM(I9:M9)) -> 224197.93 | O20: =O9*(SUM(J20:N20)/SUM(J9:N9)) -> 201677.37 | P20: =P9*(SUM(K20:O20)/SUM(K9:O9)) -> 295402.22 | Q20: =Q9*(SUM(L20:P20)/SUM(L9:P9)) -> 226272.78 | R20: =R9*(SUM(M20:Q20)/SUM(M9:Q9)) -> 282460.99
A22: RIN SURPLUS | B22: =B13-B15 -> 2812465761 | C22: =C13-C15 -> 1739509280 | D22: =D13-D15 -> -1080654904 | E22: =E13-E15 -> -878741472 | F22: =F4-F15 -> 585578721 | G22: =G4-G15 -> 92634977 | H22: =H4-H15 -> 1586048456 | I22: =I4-I15 -> 1201361725 | J22: =J4-J15 -> 184488031 | K22: =K4-K15 -> -779020028 | L22: =L4-L15 -> 473291524 | M22: =M4-M15 -> 5.4518662e+08 | ... R22: =R4-R15 -> 3.1130555e+08
A23: TOTAL AVAILABLE - UNLOCKED | B23: =B63 -> 429461188 | C23: =C63 -> 495110209 | D23: =D63 -> 15877110 | E23: =E63 -> 6467532 | F23: =F63 -> 19770934 | G23: =G63 -> 17950875 | H23: =H63 -> 26230734 | I23: =I63 -> 186336344 | ... L23: =L63 -> 2000064861 | M23: =(SUM(H23:L23)/SUM(H$22:L$22))*M$22 -> 4.5790871e+08 | N23: =(SUM(I23:M23)/SUM(I$22:M$22))*N$22 -> 5.3540128e+08 | O23: =(SUM(J23:N23)/SUM(J$22:N$22))*O$22 -> 6.1221504e+08 | P23: =(SUM(K23:O23)/SUM(K$22:O$22))*P$22 -> 7.7859312e+08 | Q23: =(SUM(L23:P23)/SUM(L$22:P$22))*Q$22 -> 9.2480532e+08 | R23: =(SUM(M23:Q23)/SUM(M$22:Q$22))*R$22 -> 6.7528176e+08
A24: TOTAL AVAILABLE - LOCKED | B24: 0 | C24: 0 | D24: 0 | E24: 0 | F24: 0 | G24: =G68 -> 2272248 | H24: =H68 -> 2423397 | I24: =I68 -> 983275 | J24: =J68 -> 767169 | K24: =K68 -> 2943662 | L24: =L68 -> 6191196 | M24: =(SUM(H24:L24)/SUM(H$22:L$22))*M$22 -> 2721403.9 | N24: =(SUM(I24:M24)/SUM(I$22:M$22))*N$22 -> 2727434.7 | O24: =(SUM(J24:N24)/SUM(J$22:N$22))*O$22 -> 3111837.5 | P24: =(SUM(K24:O24)/SUM(K$22:O$22))*P$22 -> 3806692 | Q24: =(SUM(L24:P24)/SUM(L$22:P$22))*Q$22 -> 3914767.9 | R24: =(SUM(M24:Q24)/SUM(M$22:Q$22))*R$22 -> 3322841.8
A26: RIN BANK ENDING BALANCE | B26: =B2+B22 -> 2812465761 | C26: =C2+C22 -> 4551975041 | D26: =D2+D22 -> 3471320137 | E26: =E2+E22 -> 1592485913 | F26: =F2+F22 -> 2168853262 | G26: =G2+G22 -> 1787512206 | H26: =H2+H22 -> 3234695236 | I26: =I2+I22 -> 3677897898 | ... L26: =L2+L22 -> 1690499955 | M26: =M2+M4-M15 -> 1.6136341e+09 | N26: =N2+N4-N15 -> 1.317371e+09 | O26: =O2+O4-O15 -> 8.4730055e+08 | P26: =P2+P4-P15 -> 3.7953965e+08 | Q26: =Q2+Q4-Q15 -> 1.0565448e+08 | R26: =R2+R4-R15 -> -2.0509246e+08
A28: RIN CARRYOVER | B28: ='RIN Carryover'!B37 -> 0 | C28: ='RIN Carryover'!C37 -> 0 | D28: ='RIN Carryover'!D37 -> 2.4685152e+09 | E28: ='RIN Carryover'!E37 -> 1.5785184e+09 | F28: ='RIN Carryover'!F37 -> 1.6852951e+09 | G28: ='RIN Carryover'!G37 -> 1.6445841e+09 | H28: ='RIN Carryover'!H37 -> 2.4460268e+09 | I28: ='RIN Carryover'!I37 -> 2.5331158e+09 | ... R28: ='RIN Carryover'!R37 -> 0
A30: RIN Bank Estimates - EPA | D30: 2666000000 | E30: 1740000000 | F30: 1740000000 | G30: 1740000000 | H30: 1540000000 | I30: 2220000000 | J30: 3480000000 | K30: 1830000000
A31: Actual RIN Bank - EPA | D31: 2471227385 | E31: 1583274541 | F31: 1694877229 | G31: 1648646780 | H31: 2476536173 | I31: 3055845408 | J31: =I31+J26-I26 -> 2618280949 | K31: =J31+K26-J26 -> 1217208431 | L31: =K31+L26-K26 -> 1068447465 | M31: =L31+M26-L26 -> 9.915816e+08 | N31: =M31+N26-M26 -> 6.9531855e+08 | O31: =N31+O26-N26 -> 2.2524806e+08 | P31: =O31+P26-O26 -> -2.4251284e+08 | Q31: =P31+Q26-P26 -> -5.1639801e+08 | R31: =Q31+R26-Q26 -> -8.2714495e+08
E32: =E31-D31 -> -887952844 | F32: =F31-E31 -> 111602688 | G32: =G31-F31 -> -46230449 | H32: =H31-G31 -> 827889393 | I32: =I31-H31 -> 579309235
A38: RR CHECK
A39: D3 | B39: ='RIN Retirements'!B4+'RIN Retirements'!B26+'RIN Retirements'!B48 -> 0 | C39: ='RIN Retirements'!C4+'RIN Retirements'!C26+'RIN Retirements'!C48 -> 0 | D39: ='RIN Retirements'!D4+'RIN Retirements'!D26+'RIN Retirements'!D48 -> 0 | E39: ='RIN Retirements'!E4+'RIN Retirements'!E26+'RIN Retirements'!E48 -> 293023 | F39: ='RIN Retirements'!F4+'RIN Retirements'!F26+'RIN Retirements'!F48 -> 21519986 | G39: ='RIN Retirements'!G4+'RIN Retirements'!G26+'RIN Retirements'!G48 -> 115477446 | H39: ='RIN Retirements'!H4+'RIN Retirements'!H26+'RIN Retirements'!H48 -> 191720986 | I39: ='RIN Retirements'!I4+'RIN Retirements'!I26+'RIN Retirements'!I48 -> 261797839
A40: D4 | B40: ='RIN Retirements'!B8+'RIN Retirements'!B30+'RIN Retirements'!B60 -> 259756976 | C40: ='RIN Retirements'!C8+'RIN Retirements'!C30+'RIN Retirements'!C60 -> 1432202935 | D40: ='RIN Retirements'!D8+'RIN Retirements'!D30+'RIN Retirements'!D60 -> 1769859990 | E40: ='RIN Retirements'!E8+'RIN Retirements'!E30+'RIN Retirements'!E60 -> 2480660350 | F40: ='RIN Retirements'!F8+'RIN Retirements'!F30+'RIN Retirements'!F60 -> 2819782159 | G40: ='RIN Retirements'!G8+'RIN Retirements'!G30+'RIN Retirements'!G60 -> 2922121132 | H40: ='RIN Retirements'!H8+'RIN Retirements'!H30+'RIN Retirements'!H60 -> 3403016563 | I40: ='RIN Retirements'!I8+'RIN Retirements'!I30+'RIN Retirements'!I60 -> 3956397046
A41: D5 | B41: ='RIN Retirements'!B12+'RIN Retirements'!B34+'RIN Retirements'!B72 -> 24975098 | C41: ='RIN Retirements'!C12+'RIN Retirements'!C34+'RIN Retirements'!C72 -> 178626333 | D41: ='RIN Retirements'!D12+'RIN Retirements'!D34+'RIN Retirements'!D72 -> 511193254 | E41: ='RIN Retirements'!E12+'RIN Retirements'!E34+'RIN Retirements'!E72 -> 680029914 | F41: ='RIN Retirements'!F12+'RIN Retirements'!F34+'RIN Retirements'!F72 -> 130950106 | G41: ='RIN Retirements'!G12+'RIN Retirements'!G34+'RIN Retirements'!G72 -> 101481528 | H41: ='RIN Retirements'!H12+'RIN Retirements'!H34+'RIN Retirements'!H72 -> 181704946 | I41: ='RIN Retirements'!I12+'RIN Retirements'!I34+'RIN Retirements'!I72 -> 150152677
A42: D6 | B42: ='RIN Retirements'!B16+'RIN Retirements'!B38+'RIN Retirements'!B84 -> 4050778094 | C42: ='RIN Retirements'!C16+'RIN Retirements'!C38+'RIN Retirements'!C84 -> 12185149191 | D42: ='RIN Retirements'!D16+'RIN Retirements'!D38+'RIN Retirements'!D84 -> 14151871757 | E42: ='RIN Retirements'!E16+'RIN Retirements'!E38+'RIN Retirements'!E84 -> 14367054437 | F42: ='RIN Retirements'!F16+'RIN Retirements'!F38+'RIN Retirements'!F84 -> 14082966715 | G42: ='RIN Retirements'!G16+'RIN Retirements'!G38+'RIN Retirements'!G84 -> 14949493271 | H42: ='RIN Retirements'!H16+'RIN Retirements'!H38+'RIN Retirements'!H84 -> 14467035414 | I42: ='RIN Retirements'!I16+'RIN Retirements'!I38+'RIN Retirements'!I84 -> 14241615830
A43: D7 | B43: ='RIN Retirements'!B20+'RIN Retirements'!B42+'RIN Retirements'!B96 -> 0 | C43: ='RIN Retirements'!C20+'RIN Retirements'!C42+'RIN Retirements'!C96 -> 0 | D43: ='RIN Retirements'!D20+'RIN Retirements'!D42+'RIN Retirements'!D96 -> 0 | E43: ='RIN Retirements'!E20+'RIN Retirements'!E42+'RIN Retirements'!E96 -> 332969 | F43: ='RIN Retirements'!F20+'RIN Retirements'!F42+'RIN Retirements'!F96 -> 111251 | G43: ='RIN Retirements'!G20+'RIN Retirements'!G42+'RIN Retirements'!G96 -> 127530 | H43: ='RIN Retirements'!H20+'RIN Retirements'!H42+'RIN Retirements'!H96 -> 624429 | I43: ='RIN Retirements'!I20+'RIN Retirements'!I42+'RIN Retirements'!I96 -> 1652129
A46: D3 | B46: =B39-B16 -> 0 | C46: =C39-C16 -> 0 | D46: =D39-D16 -> 0 | E46: =E39-E16 -> 0 | F46: =F39-F16 -> 376916 | G46: =G39-G16 -> 2635975 | H46: =H39-H16 -> 2371238 | I46: =I39-I16 -> 1908467
A47: D4 | B47: =B40-B17 -> 37046429 | C47: =C40-C17 -> 112339543 | D47: =D40-D17 -> 90843468 | E47: =E40-E17 -> 101616659 | F47: =F40-F17 -> 98880630 | G47: =G40-G17 -> 45285015 | H47: =H40-H17 -> 121196799 | I47: =I40-I17 -> 111525533
A48: D5 | B48: =B41-B18 -> 166656 | C48: =C41-C18 -> 5309829 | D48: =D41-D18 -> 29921504 | E48: =E41-E18 -> 6419374 | F48: =F41-F18 -> 220426 | G48: =G41-G18 -> 278127 | H48: =H41-H18 -> 148041 | I48: =I41-I18 -> 121052
A49: D6 | B49: =B42-B19 -> 86969658 | C49: =C42-C19 -> 351005510 | D49: =D42-D19 -> 15606326 | E49: =E42-E19 -> 109057205 | F49: =F42-F19 -> 295428619 | G49: =G42-G19 -> 202001860 | H49: =H42-H19 -> 231345253 | I49: =I42-I19 -> 345215707
A50: D7 | B50: =B43-B20 -> 0 | C50: =C43-C20 -> 0 | D50: =D43-D20 -> 0 | E50: =E43-E20 -> 8332 | F50: =F43-F20 -> 4997 | G50: =G43-G20 -> 27530 | H50: =H43-H20 -> 53441 | I50: =I43-I20 -> 75602
A53: RIN RETIREMENT
A54: D3 | B54: ='D3 RIN Balance Sheet'!B9 -> 0 | C54: ='D3 RIN Balance Sheet'!C9 -> 0 | D54: ='D3 RIN Balance Sheet'!D9 -> 0 | E54: ='D3 RIN Balance Sheet'!E9 -> 293023 | F54: ='D3 RIN Balance Sheet'!F9 -> 21143070 | G54: ='D3 RIN Balance Sheet'!G9 -> 112841471 | H54: ='D3 RIN Balance Sheet'!H9 -> 189349748 | I54: ='D3 RIN Balance Sheet'!I9 -> 259889372 | ... K54: ='D3 RIN Balance Sheet'!K9 -> 410620831
A55: D4
A56: D5
A57: D6
A58: D7
A60: All RINs
A61: Assigned | B61: 44980687 | C61: 20140537 | D61: 5979336 | E61: 3759050 | F61: 10761337 | G61: 2824332 | H61: 5499196 | I61: 8409310 | J61: 7773394 | K61: 2407946 | L61: 13405207 | M61: 135138639 | N61: 1893131812
A62: Separated | B62: 384480501 | C62: 474969672 | D62: 9897774 | E62: 2708482 | F62: 9009597 | G62: 15126543 | H62: 20731538 | I62: 177927034 | J62: 5216120 | K62: 11318168 | L62: 1986659654 | M62: 18328523040 | N62: 16214603505
A63: Total Available | B63: =SUM(B61:B62) -> 429461188 | C63: =SUM(C61:C62) -> 495110209 | D63: =SUM(D61:D62) -> 15877110 | E63: =SUM(E61:E62) -> 6467532 | F63: =SUM(F61:F62) -> 19770934 | G63: =SUM(G61:G62) -> 17950875 | H63: =SUM(H61:H62) -> 26230734 | I63: =SUM(I61:I62) -> 186336344 | ... N63: =SUM(N61:N62) -> 18107735317
A65: All RINs
A66: Assigned | B66: 0 | C66: 0 | D66: 0 | E66: 0 | F66: 0 | G66: 523045 | H66: 830276 | I66: 34283 | J66: 10907 | K66: 20777 | L66: 129460 | M66: 3176174 | N66: 27099284
A67: Separated | B67: 0 | C67: 0 | D67: 0 | E67: 0 | F67: 0 | G67: 1749203 | H67: 1593121 | I67: 948992 | J67: 756262 | K67: 2922885 | L67: 6061736 | M67: 251550511 | N67: 66960171
A68: Total Locked | B68: =SUM(B66:B67) -> 0 | C68: =SUM(C66:C67) -> 0 | D68: =SUM(D66:D67) -> 0 | E68: =SUM(E66:E67) -> 0 | F68: =SUM(F66:F67) -> 0 | G68: =SUM(G66:G67) -> 2272248 | H68: =SUM(H66:H67) -> 2423397 | I68: =SUM(I66:I67) -> 983275 | ... N68: =SUM(N66:N67) -> 94059455
A70: All RINs
A71: Assigned | B71: 16837332 | C71: 47904708 | D71: 86126098 | E71: 186354778 | F71: 366826491 | G71: 230033675 | H71: 266061669 | I71: 295396336 | J71: 252758810 | K71: 289966450 | L71: 293361060 | M71: 209345702 | N71: 190974775
A72: Separated | B72: 6701677409 | C72: 14992472822 | D72: 15250266889 | E72: 16456806911 | F72: 16859399925 | G72: 17680850579 | H72: 19181480293 | I72: 19097108389 | J72: 19299621377 | K72: 19505972064 | L72: 16018639455 | M72: 1006703844 | N72: 982142664
A73: Total Retired | B73: =B72+B71 -> 6718514741 | C73: =C72+C71 -> 15040377530 | D73: =D72+D71 -> 15336392987 | E73: =E72+E71 -> 16643161689 | F73: =F72+F71 -> 17226226416 | G73: =G72+G71 -> 17910884254 | H73: =H72+H71 -> 19447541962 | I73: =I72+I71 -> 19392504725 | ... N73: =N72+N71 -> 1173117439
A77: Generation | B77: 7147975929 | C77: 15535487739 | D77: 15352270097 | E77: 16649629221 | F77: 17245997350 | G77: 17931107377 | H77: 19476196093 | I77: 19579824344 | J77: 19566136870 | K77: 19812608290 | L77: 18318256572 | M77: 19934437910 | N77: 19374912211
A78: Retired | B78: =B73 -> 6718514741 | C78: =C73 -> 15040377530 | D78: =D73 -> 15336392987 | E78: =E73 -> 16643161689 | F78: =F73 -> 17226226416 | G78: =G73 -> 17910884254 | H78: =H73 -> 19447541962 | I78: =I73 -> 19392504725 | ... N78: =N73 -> 1173117439
A79: Available | B79: =B77-B78 -> 429461188 | C79: =C77-C78 -> 495110209 | D79: =D77-D78 -> 15877110 | E79: =E77-E78 -> 6467532 | F79: =F77-F78 -> 19770934 | G79: =G77-G78 -> 20223123 | H79: =H77-H78 -> 28654131 | I79: =I77-I78 -> 187319619 | ... N79: =N77-N78 -> 18201794772
A86: Unadjusted RIN Bank | D86: 2471227385 | E86: 1583274541 | F86: 1694877229 | G86: 1648646780 | H86: 2476536173 | I86: 3055845408 | J86: 2618273207 | K86: 1217200689 | L86: 2945654913 | M86: 3.2458212e+09 | N86: 3.429482e+09 | O86: 3.5575048e+09 | P86: 3.8405711e+09 | Q86: 4.5131189e+09 | R86: 4.9980058e+09
A87: Adjusted RIN Bank | O87: 3.5734839e+09 | P87: 3.8787585e+09 | Q87: 4.58846e+09 | R87: 5.0615722e+09

Sheet RIN Carryover
B1: 2010 | C1: 2011 | D1: 2012 | E1: 2013 | F1: 2014 | G1: 2015 | H1: 2016 | I1: 2017 | J1: 2018 | K1: 2019 | L1: 2020 | M1: 2021 | N1: 2022 | O1: 2023 | P1: 2024
A2: CARRYOVER RINS BY FUEL CODE
A3: D3 | B3: ='D3 RIN Balance Sheet'!B12 -> 0 | C3: ='D3 RIN Balance Sheet'!C12 -> 0 | D3: ='D3 RIN Balance Sheet'!D12 -> 20069 | E3: ='D3 RIN Balance Sheet'!E12 -> 129717 | F3: ='D3 RIN Balance Sheet'!F12 -> 11799670 | G3: ='D3 RIN Balance Sheet'!G12 -> 26126570 | H3: ='D3 RIN Balance Sheet'!H12 -> -1473393.1 | I3: ='D3 RIN Balance Sheet'!I12 -> -21155234 | ... P3: ='D3 RIN Balance Sheet'!P12 -> 8.9306813e+08
A4: D4 | B4: ='D4 RIN Balance Sheet'!B12 -> 63519472 | C4: ='D4 RIN Balance Sheet'!C12 -> 259411089 | D4: ='D4 RIN Balance Sheet'!D12 -> -32525993 | E4: ='D4 RIN Balance Sheet'!E12 -> 259814081 | F4: ='D4 RIN Balance Sheet'!F12 -> -1.3277072e+08 | G4: ='D4 RIN Balance Sheet'!G12 -> -1.5981929e+08 | H4: ='D4 RIN Balance Sheet'!H12 -> 5.5807613e+08 | I4: ='D4 RIN Balance Sheet'!I12 -> -2.3517521e+08 | ... P4: ='D4 RIN Balance Sheet'!P12 -> 8.0125837e+09
A5: D5 | B5: ='D5 RIN Balance Sheet'!B12 -> 3636534 | C5: ='D5 RIN Balance Sheet'!C12 -> 49931685 | D5: ='D5 RIN Balance Sheet'!D12 -> 115879435 | E5: ='D5 RIN Balance Sheet'!E12 -> -122205226 | F5: ='D5 RIN Balance Sheet'!F12 -> 3554653.2 | G5: ='D5 RIN Balance Sheet'!G12 -> 44813442 | H5: ='D5 RIN Balance Sheet'!H12 -> -83990576 | I5: ='D5 RIN Balance Sheet'!I12 -> -25986873 | ... P5: ='D5 RIN Balance Sheet'!P12 -> 1.8733665e+08
A6: D6 | B6: ='D6 RIN Balance Sheet'!B12 -> 2745309755 | C6: ='D6 RIN Balance Sheet'!C12 -> 11944446795 | D6: ='D6 RIN Balance Sheet'!D12 -> 11293218753 | E6: ='D6 RIN Balance Sheet'!E12 -> 10862410689 | F6: ='D6 RIN Balance Sheet'!F12 -> 11181958343 | G6: ='D6 RIN Balance Sheet'!G12 -> 11590424036 | H6: ='D6 RIN Balance Sheet'!H12 -> 11420022019 | I6: ='D6 RIN Balance Sheet'!I12 -> 10286477262 | ... P6: ='D6 RIN Balance Sheet'!P12 -> 13420548303
A7: D7 | B7: ='D7 RIN Balance Sheet'!B12 -> 0 | C7: ='D7 RIN Balance Sheet'!C12 -> 0 | D7: ='D7 RIN Balance Sheet'!D12 -> 1741 | E7: ='D7 RIN Balance Sheet'!E12 -> 62808 | F7: ='D7 RIN Balance Sheet'!F12 -> -90241.525 | G7: ='D7 RIN Balance Sheet'!G12 -> 147009.52 | H7: ='D7 RIN Balance Sheet'!H12 -> -94097.934 | I7: ='D7 RIN Balance Sheet'!I12 -> 64032.884 | ... P7: ='D7 RIN Balance Sheet'!P12 -> 196127.62
A9: CARRYOVER RINS BY MANDATE GROUP
A10: Cellulosic Biofuel | D10: 21810 | E10: 194266 | F10: 11971137 | G10: 38672858 | H10: 38793644 | I10: 21404526 | J10: ='D3 RIN Balance Sheet'!J12+'D7 RIN Balance Sheet'!J12 -> -2940256 | K10: ='D3 RIN Balance Sheet'!K12+'D7 RIN Balance Sheet'!K12 -> -33093098 | L10: ='D3 RIN Balance Sheet'!L12+'D7 RIN Balance Sheet'!L12 -> -29528706 | M10: ='D3 RIN Balance Sheet'!M12+'D7 RIN Balance Sheet'!M12 -> -20180604 | N10: ='D3 RIN Balance Sheet'!N12+'D7 RIN Balance Sheet'!N12 -> -23821905 | O10: ='D3 RIN Balance Sheet'!O12+'D7 RIN Balance Sheet'!O12 -> -56064382 | P10: ='D3 RIN Balance Sheet'!P12+'D7 RIN Balance Sheet'!P12 -> 893264260
A11: Biomass-Based Diesel | D11: 264535851 | E11: 521898462 | F11: 409981084 | G11: 272409710 | H11: 872426739 | I11: 715063109 | J11: ='D4 RIN Balance Sheet'!J12+'D7 RIN Balance Sheet'!J12 -> -4.2988793e+08 | K11: ='D4 RIN Balance Sheet'!K12+'D7 RIN Balance Sheet'!K12 -> -7.4845856e+08 | L11: ='D4 RIN Balance Sheet'!L12+'D7 RIN Balance Sheet'!L12 -> -2.1653521e+08 | M11: ='D4 RIN Balance Sheet'!M12+'D7 RIN Balance Sheet'!M12 -> -1.5117633e+08 | N11: ='D4 RIN Balance Sheet'!N12+'D7 RIN Balance Sheet'!N12 -> -1.6905103e+08 | O11: ='D4 RIN Balance Sheet'!O12+'D7 RIN Balance Sheet'!O12 -> 5.5619931e+08 | P11: ='D4 RIN Balance Sheet'!P12+'D7 RIN Balance Sheet'!P12 -> 8.0127799e+09
A12: Advanced Biofuel | D12: 431258854 | E12: 565118145 | F12: 477339429 | G12: 411137437 | H12: 926167271 | I12: 739925183 | J12: ='D3 RIN Balance Sheet'!J12+'D4 RIN Balance Sheet'!J12+'D5 RIN Balance Sheet'!J12+'D7 RIN Balance Sheet'!J12 -> -5.1055202e+08 | K12: ='D3 RIN Balance Sheet'!K12+'D4 RIN Balance Sheet'!K12+'D5 RIN Balance Sheet'!K12+'D7 RIN Balance Sheet'!K12 -> -1.087804e+09 | L12: ='D3 RIN Balance Sheet'!L12+'D4 RIN Balance Sheet'!L12+'D5 RIN Balance Sheet'!L12+'D7 RIN Balance Sheet'!L12 -> -3.4306122e+08 | M12: ='D3 RIN Balance Sheet'!M12+'D4 RIN Balance Sheet'!M12+'D5 RIN Balance Sheet'!M12+'D7 RIN Balance Sheet'!M12 -> -2.0315728e+08 | N12: ='D3 RIN Balance Sheet'!N12+'D4 RIN Balance Sheet'!N12+'D5 RIN Balance Sheet'!N12+'D7 RIN Balance Sheet'!N12 -> -2.2207628e+08 | O12: ='D3 RIN Balance Sheet'!O12+'D4 RIN Balance Sheet'!O12+'D5 RIN Balance Sheet'!O12+'D7 RIN Balance Sheet'!O12 -> 4.8942806e+08 | P12: ='D3 RIN Balance Sheet'!P12+'D4 RIN Balance Sheet'!P12+'D5 RIN Balance Sheet'!P12+'D7 RIN Balance Sheet'!P12 -> 9093184651
A13: Total Renewable Fuel | D13: 2546748740 | E13: 1652130158 | F13: 1836329759 | G13: 1655725924 | H13: 2870934029 | I13: 3270005871 | J13: ='D3 RIN Balance Sheet'!J12+'D4 RIN Balance Sheet'!J12+'D5 RIN Balance Sheet'!J12+'D6 RIN Balance Sheet'!J12+'D7 RIN Balance Sheet'!J12 -> 9.0692501e+09 | K13: ='D3 RIN Balance Sheet'!K12+'D4 RIN Balance Sheet'!K12+'D5 RIN Balance Sheet'!K12+'D6 RIN Balance Sheet'!K12+'D7 RIN Balance Sheet'!K12 -> 7.6487637e+09 | L13: ='D3 RIN Balance Sheet'!L12+'D4 RIN Balance Sheet'!L12+'D5 RIN Balance Sheet'!L12+'D6 RIN Balance Sheet'!L12+'D7 RIN Balance Sheet'!L12 -> 7101371584 | M13: ='D3 RIN Balance Sheet'!M12+'D4 RIN Balance Sheet'!M12+'D5 RIN Balance Sheet'!M12+'D6 RIN Balance Sheet'!M12+'D7 RIN Balance Sheet'!M12 -> 8527268895 | N13: ='D3 RIN Balance Sheet'!N12+'D4 RIN Balance Sheet'!N12+'D5 RIN Balance Sheet'!N12+'D6 RIN Balance Sheet'!N12+'D7 RIN Balance Sheet'!N12 -> 7870327692 | O13: ='D3 RIN Balance Sheet'!O12+'D4 RIN Balance Sheet'!O12+'D5 RIN Balance Sheet'!O12+'D6 RIN Balance Sheet'!O12+'D7 RIN Balance Sheet'!O12 -> 7518335807 | P13: ='D3 RIN Balance Sheet'!P12+'D4 RIN Balance Sheet'!P12+'D5 RIN Balance Sheet'!P12+'D6 RIN Balance Sheet'!P12+'D7 RIN Balance Sheet'!P12 -> 22513732954
A15: COMPLIANCE DEFICITS (gallons)
A16: Cellulosic Biofuel | D16: 0 | E16: 31 | F16: 7615 | G16: 22823 | H16: 4454758 | I16: 19976793 | J16: 2964921 | L16: =FORECAST(L10,$D16:$I16,$D$10:$I$10) -> -539233.77 | M16: =FORECAST(M10,$D16:$I16,$D$10:$I$10) -> 359069.33 | N16: =FORECAST(N10,$D16:$I16,$D$10:$I$10) -> 9159.587 | O16: =FORECAST(O10,$D16:$I16,$D$10:$I$10) -> -3089171.7 | P16: =FORECAST(P10,$D16:$I16,$D$10:$I$10) -> 88136284
A17: Biomass-Based Diesel | B17: 227120812 | C17: 45802515 | D17: 28488338 | E17: 23535850 | F17: 20276804 | G17: 5555088 | H17: 40944372 | I17: 75247335 | J17: 19737837 | L17: =FORECAST(L11,$D17:$I17,$D$11:$I$11) -> -16806921 | M17: =FORECAST(M11,$D17:$I17,$D$11:$I$11) -> -12381821 | N17: =FORECAST(N11,$D17:$I17,$D$11:$I$11) -> -13592022 | O17: =FORECAST(O11,$D17:$I17,$D$11:$I$11) -> 35510787 | P17: =FORECAST(P11,$D17:$I17,$D$11:$I$11) -> 5.4035585e+08
A18: Advanced Biofuel | B18: 229693190 | C18: 37394607 | D18: 19405830 | E18: 26605634 | F18: 21654525 | G18: 4897514 | H18: 66462857 | I18: 137768294 | J18: 28987972 | L18: =FORECAST(L12,$D18:$I18,$D$12:$I$12) -> -1.1470413e+08 | M18: =FORECAST(M12,$D18:$I18,$D$12:$I$12) -> -90635226 | N18: =FORECAST(N12,$D18:$I18,$D$12:$I$12) -> -93890028 | O18: =FORECAST(O12,$D18:$I18,$D$12:$I$12) -> 28516304 | P18: =FORECAST(P12,$D18:$I18,$D$12:$I$12) -> 1.508696e+09
A19: Total Renewable Fuel | B19: 163353609 | C19: 68763484 | D19: 75236441 | E19: 68855617 | F19: 141478021 | G19: 10419624 | H19: 390514451 | I19: 681328963 | J19: 124917352 | L19: =FORECAST(L13,$D19:$I19,$D$13:$I$13) -> 1.7979281e+09 | M19: =FORECAST(M13,$D19:$I19,$D$13:$I$13) -> 2.2646855e+09 | N19: =FORECAST(N13,$D19:$I19,$D$13:$I$13) -> 2.0496404e+09 | O19: =FORECAST(O13,$D19:$I19,$D$13:$I$13) -> 1.9344184e+09 | P19: =FORECAST(P13,$D19:$I19,$D$13:$I$13) -> 6.8430552e+09
D20: =D19/D13 -> 0.029542153 | E20: =E19/E13 -> 0.041676872 | F20: =F19/F13 -> 0.077043908 | G20: =G19/G13 -> 0.006293085 | H20: =H19/H13 -> 0.13602348 | I20: =I19/I13 -> 0.20835711
A21: NET CARRYOVER RINS
A22: Cellulosic Biofuel | D22: =D10-(D16*D46) -> 21810 | E22: =E10-(E16*E46) -> 194216.69 | F22: =F10-(F16*F46) -> 11963518 | G22: =G10-(G16*G46) -> 38650035 | H22: =H10-(H16*H46) -> 34338886 | I22: =I10-(I16*I46) -> 1427718 | J22: =J10-(J16*J46) -> -5905220.7 | K22: =K10-(K16*K46) -> -33093098 | L22: =L10-L16 -> -28989472 | M22: =M10-M16 -> -20539673 | N22: =N10-N16 -> -23831065 | O22: =O10-O16 -> -52975210 | P22: =P10-P16 -> 8.0512798e+08
A23: Biomass-Based Diesel | D23: =D11-(D17*D47) -> 2.2179377e+08 | E23: =E11-(E17*E47) -> 4.859512e+08 | F23: =F11-(F17*F47) -> 3.7882084e+08 | G23: =G11-(G17*G47) -> 2.6389129e+08 | H23: =H11-(H17*H47) -> 8.0972335e+08 | I23: =I11-(I17*I47) -> 5.9949012e+08 | J23: =J11-(J17*J47) -> -4.6017682e+08 | K23: =K11-(K17*K47) -> -7.4845856e+08 | L23: =L11-L17 -> -1.9972829e+08 | M23: =M11-M17 -> -1.387945e+08 | N23: =N11-N17 -> -1.55459e+08 | O23: =O11-O17 -> 5.2068852e+08 | P23: =P11-P17 -> 7.472424e+09
A24: Advanced Biofuel | D24: =D12-(D18*D48) -> 4.05433e+08 | E24: =E12-(E18*E48) -> 5.2733084e+08 | F24: =F12-(F18*F48) -> 4.4491965e+08 | G24: =G12-(G18*G48) -> 4.039454e+08 | H24: =H12-(H18*H48) -> 8.2748632e+08 | I24: =I12-(I18*I48) -> 5.3740529e+08 | J24: =J12-(J18*J48) -> -5.5288072e+08 | K24: =K12-(K18*K48) -> -1.087804e+09 | L24: =L12-L18 -> -2.283571e+08 | M24: =M12-M18 -> -1.1252205e+08 | N24: =N12-N18 -> -1.2818625e+08 | O24: =O12-O18 -> 4.6091175e+08 | P24: =P12-P18 -> 7.5844886e+09
A25: Total Renewable Fuel | D25: =D13-(D19*D49) -> 2.4685152e+09 | E25: =E13-(E19*E49) -> 1.5785184e+09 | F25: =F13-(F19*F49) -> 1.6852951e+09 | G25: =G13-(G19*G49) -> 1.6445841e+09 | H25: =H13-(H19*H49) -> 2.4460268e+09 | I25: =I13-(I19*I49) -> 2.5331158e+09 | J25: =J13-(J19*J49) -> 8.9343114e+09 | K25: =K13-(K19*K49) -> 7.6487637e+09 | L25: =L13-L19 -> 5.3034435e+09 | M25: =M13-M19 -> 6.2625834e+09 | N25: =N13-N19 -> 5.8206873e+09 | O25: =O13-O19 -> 5.5839174e+09 | P25: =P13-P19 -> 1.5670678e+10
A27: CARRYOVER LIMIT
A28: Cellulosic Biofuel | B28: ='RVO Forecast'!B14*0.2 -> 0 | C28: ='RVO Forecast'!C14*0.2 -> 0 | D28: ='RVO Forecast'!D14*0.2 -> 160000 | E28: ='RVO Forecast'!E14*0.2 -> 6600000 | F28: ='RVO Forecast'!F14*0.2 -> 24600000 | G28: ='RVO Forecast'!G14*0.2 -> 46000000 | H28: ='RVO Forecast'!H14*0.2 -> 62200000 | I28: ='RVO Forecast'!I14*0.2 -> 57600000 | ... P28: ='RVO Forecast'!P14*0.2 -> 276000000
A29: Biomass-Based Diesel | I29: =3150000000*0.2 -> 630000000 | J29: =3150000000*0.2 -> 630000000 | K29: =3150000000*0.2 -> 630000000 | L29: =3150000000*0.2 -> 630000000 | M29: =3150000000*0.2 -> 630000000 | N29: =3150000000*0.2 -> 630000000 | O29: =3150000000*0.2 -> 630000000 | P29: =3150000000*0.2 -> 630000000
A30: Advanced Biofuel | B30: ='RVO Forecast'!B18*0.2 -> 270000000 | C30: ='RVO Forecast'!C18*0.2 -> 400000000 | D30: ='RVO Forecast'!D18*0.2 -> 534000000 | E30: ='RVO Forecast'!E18*0.2 -> 534000000 | F30: ='RVO Forecast'!F18*0.2 -> 576000000 | G30: ='RVO Forecast'!G18*0.2 -> 722000000 | H30: ='RVO Forecast'!H18*0.2 -> 856000000 | I30: ='RVO Forecast'!I18*0.2 -> 858000000 | ... P30: ='RVO Forecast'!P18*0.2 -> 1466000000
A31: Total Renewable Fuel | B31: ='RVO Forecast'!B8*0.2 -> 2790000000 | C31: ='RVO Forecast'!C8*0.2 -> 3040000000 | D31: ='RVO Forecast'!D8*0.2 -> 3310000000 | E31: ='RVO Forecast'!E8*0.2 -> 3256000000 | F31: ='RVO Forecast'!F8*0.2 -> 3386000000 | G31: ='RVO Forecast'!G8*0.2 -> 3622000000 | H31: ='RVO Forecast'!H8*0.2 -> 3856000000 | I31: ='RVO Forecast'!I8*0.2 -> 3858000000 | ... K31: ='RVO Forecast'!K8*0.2 -> 3426000000 | L31: ='RVO Forecast'!L49*0.2 -> 2758000000 | M31: ='RVO Forecast'!M49*0.2 -> 3000000000 | N31: ='RVO Forecast'!N49*0.2 -> 3050000000 | O31: ='RVO Forecast'!O49*0.2 -> 3000000000 | P31: ='RVO Forecast'!P49*0.2 -> 3000000000
A33: AVAILABLE RINS
A34: Cellulosic Biofuel | B34: =IF(B22<B28,B22,B28) -> 0 | C34: =IF(C22<C28,C22,C28) -> 0 | D34: =IF(D22<D28,D22,D28) -> 21810 | E34: =IF(E22<E28,E22,E28) -> 194216.69 | F34: =IF(F22<F28,F22,F28) -> 11963518 | G34: =IF(G22<G28,G22,G28) -> 38650035 | H34: =IF(H22<H28,H22,H28) -> 34338886 | I34: =IF(I22<I28,I22,I28) -> 1427718 | ... P34: =IF(P22<P28,P22,P28) -> 276000000
A35: Biomass-Based Diesel | B35: =B23 -> 0 | C35: =C23 -> 0 | D35: =D23 -> 2.2179377e+08 | E35: =E23 -> 4.859512e+08 | F35: =F23 -> 3.7882084e+08 | G35: =G23 -> 2.6389129e+08 | H35: =H23 -> 8.0972335e+08 | I35: =I23 -> 5.9949012e+08 | ... P35: =P23 -> 7.472424e+09
A36: Advanced Biofuel | B36: =IF(B24<B30,B24,B30) -> 0 | C36: =IF(C24<C30,C24,C30) -> 0 | D36: =IF(D24<D30,D24,D30) -> 4.05433e+08 | E36: =IF(E24<E30,E24,E30) -> 5.2733084e+08 | F36: =IF(F24<F30,F24,F30) -> 4.4491965e+08 | G36: =IF(G24<G30,G24,G30) -> 4.039454e+08 | H36: =IF(H24<H30,H24,H30) -> 8.2748632e+08 | I36: =IF(I24<I30,I24,I30) -> 5.3740529e+08 | ... P36: =IF(P24<P30,P24,P30) -> 1466000000
A37: Total Renewable Fuel | B37: =IF(B25<B31,B25,B31) -> 0 | C37: =IF(C25<C31,C25,C31) -> 0 | D37: =IF(D25<D31,D25,D31) -> 2.4685152e+09 | E37: =IF(E25<E31,E25,E31) -> 1.5785184e+09 | F37: =IF(F25<F31,F25,F31) -> 1.6852951e+09 | G37: =IF(G25<G31,G25,G31) -> 1.6445841e+09 | H37: =IF(H25<H31,H25,H31) -> 2.4460268e+09 | I37: =IF(I25<I31,I25,I31) -> 2.5331158e+09 | ... P37: =IF(P25<P31,P25,P31) -> 3000000000
D38: 2471227385 | E38: 1583274541 | F38: 1694877229 | G38: 1648646780 | H38: 2476536173 | I38: 3055845408
A40: Cellulosic Biofuel | B40: D3 + D7
A41: Biomass-Based Diesel | B41: D4 + D7
A42: Advanced Biofuel | B42: D3 + D4 + D5 + D7
A43: Total Renewable Fuel | B43: All D Codes
A46: Cellulosic | C46: #DIV/0! | D46: 1.0339923 | E46: 1.5905054 | F46: 1.00055 | G46: 1 | H46: 1 | I46: 1.0000007 | J46: 1.0000147 | K46: 1.0000131 | L46: 1.0000089 | M46: #DIV/0! | N46: #DIV/0! | O46: 0.099850326 | P46: 0
A47: Biomass-Based Diesel | C47: 1.5067384 | D47: 1.500336 | E47: 1.5273406 | F47: 1.5367434 | G47: 1.5334453 | H47: 1.5314288 | I47: 1.535908 | J47: 1.5345595 | K47: 1.71653 | L47: 1.7353863 | M47: #DIV/0! | N47: #DIV/0! | O47: 1.3648756 | P47: 1.2932701
A48: Advanced Biofuel | C48: 1.4346191 | D48: 1.3308295 | E48: 1.4202745 | F48: 1.4971366 | G48: 1.4685072 | H48: 1.4847534 | I48: 1.4700036 | J48: 1.4602158 | K48: 1.5739223 | L48: 1.5900253 | M48: #DIV/0! | N48: #DIV/0! | O48: 1.13361 | P48: 1.9060203
A49: Total Renewable Fuel | C49: 1.039046 | D49: 1.0398361 | E49: 1.0690745 | F49: 1.0675489 | G49: 1.0693129 | H49: 1.0880705 | I49: 1.0815481 | J49: 1.0802239 | K49: 1.1086547 | L49: 1.1216826 | M49: #DIV/0! | N49: #DIV/0! | O49: 0.21557423 | P49: 0.91074441

Sheet D3 RIN Balance Sheet
B1: 2010 | C1: 2011 | D1: 2012 | E1: 2013 | F1: 2014 | G1: 2015 | H1: 2016 | I1: 2017 | J1: 2018 | K1: 2019 | L1: 2020 | M1: 2021 | N1: 2022 | O1: 2023 | P1: 2024
A3: RIN GENERATION | B3: ='[1]D3 RIN Forecast'!B$15 -> 0 | C3: ='[1]D3 RIN Forecast'!C$15 -> 0 | D3: ='[1]D3 RIN Forecast'!D$15 -> 20069 | E3: ='[1]D3 RIN Forecast'!E$15 -> 422740 | F3: ='[1]D3 RIN Forecast'!F$15 -> 33360560 | G3: ='[1]D3 RIN Forecast'!G$15 -> 142040241 | H3: ='[1]D3 RIN Forecast'!H$15 -> 192361795 | I3: ='[1]D3 RIN Forecast'!I$15 -> 250624473 | ... P3: ='[1]D3 RIN Forecast'!P$15 -> 921163090
A4: Small Refinery Exemptions | B4: 0 | C4: ='Small Refinery Exemptions'!B48 -> 0 | D4: ='Small Refinery Exemptions'!C48 -> 0 | E4: ='Small Refinery Exemptions'!D48 -> 0 | F4: ='Small Refinery Exemptions'!E48 -> 40904.475 | G4: ='Small Refinery Exemptions'!F48 -> 436224.52 | H4: ='Small Refinery Exemptions'!G48 -> 2114202.1 | I4: ='Small Refinery Exemptions'!H48 -> 9981867.9 | J4: ='Small Refinery Exemptions'!I48 -> 29292676 | ... P4: ='Small Refinery Exemptions'!O48 -> 26872039
A5: Errors | B5: ='RIN Retirements'!B26 -> 0 | C5: ='RIN Retirements'!C26 -> 0 | D5: ='RIN Retirements'!D26 -> 0 | E5: ='RIN Retirements'!E26 -> 0 | F5: ='RIN Retirements'!F26 -> 342326 | G5: ='RIN Retirements'!G26 -> 2024139 | H5: ='RIN Retirements'!H26 -> 2061978 | I5: ='RIN Retirements'!I26 -> 45292 | ... P5: ='RIN Retirements'!P26 -> 1130290
A6: Others | B6: ='RIN Retirements'!B48 -> 0 | C6: ='RIN Retirements'!C48 -> 0 | D6: ='RIN Retirements'!D48 -> 0 | E6: ='RIN Retirements'!E48 -> 0 | F6: ='RIN Retirements'!F48 -> 34590 | G6: ='RIN Retirements'!G48 -> 611836 | H6: ='RIN Retirements'!H48 -> 309260 | I6: ='RIN Retirements'!I48 -> 1863175 | ... P6: ='RIN Retirements'!P48 -> 24650
A7: NET RIN GENERATION | B7: =B3-SUM(B4:B6) -> 0 | C7: =C3-SUM(C4:C6) -> 0 | D7: =D3-SUM(D4:D6) -> 20069 | E7: =E3-SUM(E5:E6) -> 422740 | F7: =F3-SUM(F4:F6) -> 32942740 | G7: =G3-SUM(G4:G6) -> 1.3896804e+08 | H7: =H3-SUM(H4:H6) -> 1.8787635e+08 | I7: =I3-SUM(I4:I6) -> 2.3873414e+08 | J7: =J3-SUM(J4:J6) -> 2.8044743e+08 | K7: =K3-SUM(K4:K6) -> 3.7838871e+08 | L7: =L3-SUM(L4:L6) -> 4.7439338e+08 | M7: =M3-SUM(M4:M6) -> 5.4231607e+08 | ... P7: =P3-SUM(P4:P6) -> 8.9313611e+08
A9: RIN RETIREMENT | B9: ='RIN Retirements'!B4 -> 0 | C9: ='RIN Retirements'!C4 -> 0 | D9: ='RIN Retirements'!D4 -> 0 | E9: ='RIN Retirements'!E4 -> 293023 | F9: ='RIN Retirements'!F4 -> 21143070 | G9: ='RIN Retirements'!G4 -> 112841471 | H9: ='RIN Retirements'!H4 -> 189349748 | I9: ='RIN Retirements'!I4 -> 259889372 | ... P9: ='RIN Retirements'!P4 -> 67979
A10: Settlements
A12: RIN SURPLUS | B12: =B7-B9 -> 0 | C12: =C7-C9 -> 0 | D12: =D7-D9 -> 20069 | E12: =E7-E9 -> 129717 | F12: =F7-F9 -> 11799670 | G12: =G7-G9 -> 26126570 | H12: =H7-H9 -> -1473393.1 | I12: =I7-I9 -> -21155234 | ... P12: =P7-P9 -> 8.9306813e+08
A13: RIN SURPLUS ex SREs | B13: =B12+B4 -> 0 | C13: =C12+C4 -> 0 | D13: =D12+D4 -> 20069 | E13: =E12+E4 -> 129717 | F13: =F12+F4 -> 11840574 | G13: =G12+G4 -> 26562795 | H13: =H12+H4 -> 640809 | I13: =I12+I4 -> -11173366 | ... P13: =P12+P4 -> 919940171
A15: RIN SURPLUS
A16: TOTAL AVAILABLE - UNLOCKED
A17: TOTAL AVAILABLE - LOCKED
A19: RIN BANK ENDING BALANCE

Sheet D4 RIN Balance Sheet
B1: 2010 | C1: 2011 | D1: 2012 | E1: 2013 | F1: 2014 | G1: 2015 | H1: 2016 | I1: 2017 | J1: 2018 | K1: 2019 | L1: 2020 | M1: 2021 | N1: 2022 | O1: 2023 | P1: 2024
A3: RIN GENERATION | B3: ='[1]D4 RIN Forecast'!B$27 -> 323276448 | C3: ='[1]D4 RIN Forecast'!C$27 -> 1691614024 | D3: ='[1]D4 RIN Forecast'!D$27 -> 1737333997 | E3: ='[1]D4 RIN Forecast'!E$27 -> 2740474431 | F3: ='[1]D4 RIN Forecast'!F$27 -> 2709972461 | G3: ='[1]D4 RIN Forecast'!G$27 -> 2795798365 | H3: ='[1]D4 RIN Forecast'!H$27 -> 4008319745 | I3: ='[1]D4 RIN Forecast'!I$27 -> 3848913464 | ... P3: ='[1]D4 RIN Forecast'!P$27 -> 9158971248
A4: Small Refinery Exemptions | C4: ='Small Refinery Exemptions'!B49 -> 0 | D4: ='Small Refinery Exemptions'!C49 -> 0 | E4: ='Small Refinery Exemptions'!D49 -> 0 | F4: ='Small Refinery Exemptions'!E49 -> 22961026 | G4: ='Small Refinery Exemptions'!F49 -> 33496527 | H4: ='Small Refinery Exemptions'!G49 -> 47227053 | I4: ='Small Refinery Exemptions'!H49 -> 1.2769163e+08 | J4: ='Small Refinery Exemptions'!I49 -> 2.9315657e+08 | ... P4: ='Small Refinery Exemptions'!O49 -> 1.5547554e+08
A5: Errors | B5: ='RIN Retirements'!B30 -> 13812123 | C5: ='RIN Retirements'!C30 -> 46787035 | D5: ='RIN Retirements'!D30 -> 8948629 | E5: ='RIN Retirements'!E30 -> 9467178 | F5: ='RIN Retirements'!F30 -> 7016765 | G5: ='RIN Retirements'!G30 -> 2880290 | H5: ='RIN Retirements'!H30 -> 6188858 | I5: ='RIN Retirements'!I30 -> 19001829 | ... P5: ='RIN Retirements'!P30 -> 2139574
A6: Others | B6: ='RIN Retirements'!B60 -> 23234306 | C6: ='RIN Retirements'!C60 -> 65552508 | D6: ='RIN Retirements'!D60 -> 81894839 | E6: ='RIN Retirements'!E60 -> 92149481 | F6: ='RIN Retirements'!F60 -> 91863865 | G6: ='RIN Retirements'!G60 -> 42404725 | H6: ='RIN Retirements'!H60 -> 115007941 | I6: ='RIN Retirements'!I60 -> 92523704 | ... P6: ='RIN Retirements'!P60 -> 16273483
A7: NET RIN GENERATION | B7: =B3-SUM(B4:B6) -> 286230019 | C7: =C3-SUM(C4:C6) -> 1579274481 | D7: =D3-SUM(D4:D6) -> 1646490529 | E7: =E3-SUM(E4:E6) -> 2638857772 | F7: =F3-SUM(F4:F6) -> 2.5881308e+09 | G7: =G3-SUM(G4:G6) -> 2.7170168e+09 | H7: =H3-SUM(H4:H6) -> 3.8398959e+09 | I7: =I3-SUM(I4:I6) -> 3.6096963e+09 | ... P7: =P3-SUM(P4:P6) -> 8.9850827e+09
A9: RIN RETIREMENT | B9: ='RIN Retirements'!B8 -> 222710547 | C9: ='RIN Retirements'!C8 -> 1319863392 | D9: ='RIN Retirements'!D8 -> 1679016522 | E9: ='RIN Retirements'!E8 -> 2379043691 | F9: ='RIN Retirements'!F8 -> 2720901529 | G9: ='RIN Retirements'!G8 -> 2876836117 | H9: ='RIN Retirements'!H8 -> 3281819764 | I9: ='RIN Retirements'!I8 -> 3844871513 | ... P9: ='RIN Retirements'!P8 -> 972498916
A10: Settlements
A12: RIN SURPLUS | B12: =B7-B9 -> 63519472 | C12: =C7-C9 -> 259411089 | D12: =D7-D9 -> -32525993 | E12: =E7-E9 -> 259814081 | F12: =F7-F9 -> -1.3277072e+08 | G12: =G7-G9 -> -1.5981929e+08 | H12: =H7-H9 -> 5.5807613e+08 | I12: =I7-I9 -> -2.3517521e+08 | ... P12: =P7-P9 -> 8.0125837e+09
A15: RIN SURPLUS
A16: TOTAL AVAILABLE - UNLOCKED
A17: TOTAL AVAILABLE - LOCKED
A19: RIN BANK ENDING BALANCE

Sheet D5 RIN Balance Sheet
B1: 2010 | C1: 2011 | D1: 2012 | E1: 2013 | F1: 2014 | G1: 2015 | H1: 2016 | I1: 2017 | J1: 2018 | K1: 2019 | L1: 2020 | M1: 2021 | N1: 2022 | O1: 2023 | P1: 2024
A3: RIN GENERATION | B3: ='[1]D5 RIN Forecast'!B$28 -> 28611632 | C3: ='[1]D5 RIN Forecast'!C$28 -> 228558018 | D3: ='[1]D5 RIN Forecast'!D$28 -> 627072689 | E3: ='[1]D5 RIN Forecast'!E$28 -> 557824688 | F3: ='[1]D5 RIN Forecast'!F$28 -> 143540533 | G3: ='[1]D5 RIN Forecast'!G$28 -> 147091443 | H3: ='[1]D5 RIN Forecast'!H$28 -> 98103017 | I3: ='[1]D5 RIN Forecast'!I$28 -> 143646572 | ... P3: ='[1]D5 RIN Forecast'!P$28 -> 243155929
A4: Small Refinery Exemptions | C4: ='Small Refinery Exemptions'!B50 -> 0 | D4: ='Small Refinery Exemptions'!C50 -> 0 | E4: ='Small Refinery Exemptions'!D50 -> 0 | F4: ='Small Refinery Exemptions'!E50 -> 9035773.8 | G4: ='Small Refinery Exemptions'!F50 -> 796472.5 | H4: ='Small Refinery Exemptions'!G50 -> 388647.34 | I4: ='Small Refinery Exemptions'!H50 -> 19480768 | J4: ='Small Refinery Exemptions'!I50 -> 83136929 | ... P4: ='Small Refinery Exemptions'!O50 -> 7484463.8
A5: Errors | B5: ='RIN Retirements'!B34 -> 65268 | C5: ='RIN Retirements'!C34 -> 3600279 | D5: ='RIN Retirements'!D34 -> 29709496 | E5: ='RIN Retirements'!E34 -> 6246169 | F5: ='RIN Retirements'!F34 -> 124707 | G5: ='RIN Retirements'!G34 -> 262346 | H5: ='RIN Retirements'!H34 -> 132964 | I5: ='RIN Retirements'!I34 -> 92528 | ... P5: ='RIN Retirements'!P34 -> 2103
A6: Others | B6: ='RIN Retirements'!B72 -> 101388 | C6: ='RIN Retirements'!C72 -> 1709550 | D6: ='RIN Retirements'!D72 -> 212008 | E6: ='RIN Retirements'!E72 -> 173205 | F6: ='RIN Retirements'!F72 -> 95719 | G6: ='RIN Retirements'!G72 -> 15781 | H6: ='RIN Retirements'!H72 -> 15077 | I6: ='RIN Retirements'!I72 -> 28524 | ... P6: ='RIN Retirements'!P72 -> 2369109
A7: NET RIN GENERATION | B7: =B3-SUM(B4:B6) -> 28444976 | C7: =C3-SUM(C4:C6) -> 223248189 | D7: =D3-SUM(D4:D6) -> 597151185 | E7: =E3-SUM(E4:E6) -> 551405314 | F7: =F3-SUM(F4:F6) -> 1.3428433e+08 | G7: =G3-SUM(G4:G6) -> 1.4601684e+08 | H7: =H3-SUM(H4:H6) -> 97566329 | I7: =I3-SUM(I4:I6) -> 1.2404475e+08 | ... P7: =P3-SUM(P4:P6) -> 2.3330025e+08
A9: RIN RETIREMENT | B9: ='RIN Retirements'!B12 -> 24808442 | C9: ='RIN Retirements'!C12 -> 173316504 | D9: ='RIN Retirements'!D12 -> 481271750 | E9: ='RIN Retirements'!E12 -> 673610540 | F9: ='RIN Retirements'!F12 -> 130729680 | G9: ='RIN Retirements'!G12 -> 101203401 | H9: ='RIN Retirements'!H12 -> 181556905 | I9: ='RIN Retirements'!I12 -> 150031625 | ... P9: ='RIN Retirements'!P12 -> 45963601
A10: Settlements
A12: RIN SURPLUS | B12: =B7-B9 -> 3636534 | C12: =C7-C9 -> 49931685 | D12: =D7-D9 -> 115879435 | E12: =E7-E9 -> -122205226 | F12: =F7-F9 -> 3554653.2 | G12: =G7-G9 -> 44813442 | H12: =H7-H9 -> -83990576 | I12: =I7-I9 -> -25986873 | ... P12: =P7-P9 -> 1.8733665e+08
A15: RIN SURPLUS
A16: TOTAL AVAILABLE - UNLOCKED
A17: TOTAL AVAILABLE - LOCKED
A19: RIN BANK ENDING BALANCE

Sheet D6 RIN Balance Sheet
B1: 2010 | C1: 2011 | D1: 2012 | E1: 2013 | F1: 2014 | G1: 2015 | H1: 2016 | I1: 2017 | J1: 2018 | K1: 2019 | L1: 2020 | M1: 2021 | N1: 2022 | O1: 2023 | P1: 2024
A3: RIN GENERATION | B3: ='[1]D6 RIN Forecast'!B$23 -> 6796087849 | C3: ='[1]D6 RIN Forecast'!C$23 -> 13615315697 | D3: ='[1]D6 RIN Forecast'!D$23 -> 12987841601 | E3: ='[1]D6 RIN Forecast'!E$23 -> 13350511585 | F3: ='[1]D6 RIN Forecast'!F$23 -> 14359064491 | G3: ='[1]D6 RIN Forecast'!G$23 -> 14845902013 | H3: ='[1]D6 RIN Forecast'!H$23 -> 15175717036 | I3: ='[1]D6 RIN Forecast'!I$23 -> 15109202482 | ... P3: ='[1]D6 RIN Forecast'!P$23 -> 14890536490
A4: Small Refinery Exemptions | C4: ='Small Refinery Exemptions'!B51 -> 0 | D4: ='Small Refinery Exemptions'!C51 -> 0 | E4: ='Small Refinery Exemptions'!D51 -> 0 | F4: ='Small Refinery Exemptions'!E51 -> 160776000 | G4: ='Small Refinery Exemptions'!F51 -> 1.7664e+08 | H4: ='Small Refinery Exemptions'!G51 -> 2.4253e+08 | I4: ='Small Refinery Exemptions'!H51 -> 632638000 | J4: ='Small Refinery Exemptions'!I51 -> 1418560000 | ... P4: ='Small Refinery Exemptions'!O51 -> 479920000
A5: Errors | B5: ='RIN Retirements'!B38 -> 11236084 | C5: ='RIN Retirements'!C38 -> 28086050 | D5: ='RIN Retirements'!D38 -> 6953540 | E5: ='RIN Retirements'!E38 -> 24901865 | F5: ='RIN Retirements'!F38 -> 14410773 | G5: ='RIN Retirements'!G38 -> 4319127 | H5: ='RIN Retirements'!H38 -> 18796313 | I5: ='RIN Retirements'!I38 -> 19443026 | ... P5: ='RIN Retirements'!P38 -> 17141957
A6: Others | B6: ='RIN Retirements'!B84 -> 75733574 | C6: ='RIN Retirements'!C84 -> 322919460 | D6: ='RIN Retirements'!D84 -> 8652786 | E6: ='RIN Retirements'!E84 -> 84155340 | F6: ='RIN Retirements'!F84 -> 281017846 | G6: ='RIN Retirements'!G84 -> 197682733 | H6: ='RIN Retirements'!H84 -> 212548940 | I6: ='RIN Retirements'!I84 -> 325772681 | ... P6: ='RIN Retirements'!P84 -> 427314
A7: NET RIN GENERATION | B7: =B3-SUM(B4:B6) -> 6709118191 | C7: =C3-SUM(C4:C6) -> 13264310187 | D7: =D3-SUM(D4:D6) -> 12972235275 | E7: =E3-SUM(E4:E6) -> 13241454380 | F7: =F3-SUM(F4:F6) -> 13902859872 | G7: =G3-SUM(G4:G6) -> 14467260153 | H7: =H3-SUM(H4:H6) -> 14701841783 | I7: =I3-SUM(I4:I6) -> 14131348775 | ... P7: =P3-SUM(P4:P6) -> 14393047219
A9: RIN RETIREMENT | B9: ='RIN Retirements'!B16 -> 3963808436 | C9: ='RIN Retirements'!C8 -> 1319863392 | D9: ='RIN Retirements'!D8 -> 1679016522 | E9: ='RIN Retirements'!E8 -> 2379043691 | F9: ='RIN Retirements'!F8 -> 2720901529 | G9: ='RIN Retirements'!G8 -> 2876836117 | H9: ='RIN Retirements'!H8 -> 3281819764 | I9: ='RIN Retirements'!I8 -> 3844871513 | J9: ='RIN Retirements'!J8 -> 3930837317 | ... P9: ='RIN Retirements'!P8 -> 972498916
A10: Settlements
A12: RIN SURPLUS | B12: =B7-B9 -> 2745309755 | C12: =C7-C9 -> 11944446795 | D12: =D7-D9 -> 11293218753 | E12: =E7-E9 -> 10862410689 | F12: =F7-F9 -> 11181958343 | G12: =G7-G9 -> 11590424036 | H12: =H7-H9 -> 11420022019 | I12: =I7-I9 -> 10286477262 | ... P12: =P7-P9 -> 13420548303
A15: RIN SURPLUS
A16: TOTAL AVAILABLE - UNLOCKED
A17: TOTAL AVAILABLE - LOCKED
A19: RIN BANK ENDING BALANCE

Sheet D7 RIN Balance Sheet
B1: 2010 | C1: 2011 | D1: 2012 | E1: 2013 | F1: 2014 | G1: 2015 | H1: 2016 | I1: 2017 | J1: 2018 | K1: 2019 | L1: 2020 | M1: 2021 | N1: 2022 | O1: 2023 | P1: 2024
A3: RIN GENERATION | B3: ='[1]D7 RIN Forecast'!B$13 -> 0 | C3: ='[1]D7 RIN Forecast'!C$13 -> 0 | D3: ='[1]D7 RIN Forecast'!D$13 -> 1741 | E3: ='[1]D7 RIN Forecast'!E$13 -> 395777 | F3: ='[1]D7 RIN Forecast'!F$13 -> 59305 | G3: ='[1]D7 RIN Forecast'!G$13 -> 275315 | H3: ='[1]D7 RIN Forecast'!H$13 -> 534429 | I3: ='[1]D7 RIN Forecast'!I$13 -> 1743894 | ... P3: ='[1]D7 RIN Forecast'!P$13 -> 227964
A4: Small Refinery Exemptions | C4: ='Small Refinery Exemptions'!B52 -> 0 | D4: ='Small Refinery Exemptions'!C52 -> 0 | E4: ='Small Refinery Exemptions'!D52 -> 0 | F4: ='Small Refinery Exemptions'!E52 -> 38295.525 | G4: ='Small Refinery Exemptions'!F52 -> 775.47545 | H4: ='Small Refinery Exemptions'!G52 -> 4097.9341 | I4: ='Small Refinery Exemptions'!H52 -> 27732.116 | J4: ='Small Refinery Exemptions'!I52 -> 203824.16 | ... P4: ='Small Refinery Exemptions'!O52 -> 7961.3762
A5: Errors | B5: ='RIN Retirements'!B42 -> 0 | C5: ='RIN Retirements'!C42 -> 0 | D5: ='RIN Retirements'!D42 -> 0 | E5: ='RIN Retirements'!E42 -> 8332 | F5: ='RIN Retirements'!F42 -> 4997 | G5: ='RIN Retirements'!G42 -> 27530 | H5: ='RIN Retirements'!H42 -> 53441 | I5: ='RIN Retirements'!I42 -> 75602 | ... P5: ='RIN Retirements'!P42 -> 23875
A6: Others | B6: ='RIN Retirements'!B96 -> 0 | C6: ='RIN Retirements'!C96 -> 0 | D6: ='RIN Retirements'!D96 -> 0 | E6: ='RIN Retirements'!E96 -> 0 | F6: ='RIN Retirements'!F96 -> 0 | G6: ='RIN Retirements'!G96 -> 0 | H6: ='RIN Retirements'!H96 -> 0 | I6: ='RIN Retirements'!I96 -> 0 | ... P6: ='RIN Retirements'!P96 -> 0
A7: NET RIN GENERATION | B7: =B3-SUM(B4:B6) -> 0 | C7: =C3-SUM(C4:C6) -> 0 | D7: =D3-SUM(D4:D6) -> 1741 | E7: =E3-SUM(E4:E6) -> 387445 | F7: =F3-SUM(F4:F6) -> 16012.475 | G7: =G3-SUM(G4:G6) -> 247009.52 | H7: =H3-SUM(H4:H6) -> 476890.07 | I7: =I3-SUM(I4:I6) -> 1640559.9 | ... P7: =P3-SUM(P4:P6) -> 196127.62
A9: RIN RETIREMENT | B9: ='RIN Retirements'!B20 -> 0 | C9: ='RIN Retirements'!C20 -> 0 | D9: ='RIN Retirements'!D20 -> 0 | E9: ='RIN Retirements'!E20 -> 324637 | F9: ='RIN Retirements'!F20 -> 106254 | G9: ='RIN Retirements'!G20 -> 100000 | H9: ='RIN Retirements'!H20 -> 570988 | I9: ='RIN Retirements'!I20 -> 1576527 | ... P9: ='RIN Retirements'!P20 -> 0
A10: Settlements
A12: RIN SURPLUS | B12: =B7-B9 -> 0 | C12: =C7-C9 -> 0 | D12: =D7-D9 -> 1741 | E12: =E7-E9 -> 62808 | F12: =F7-F9 -> -90241.525 | G12: =G7-G9 -> 147009.52 | H12: =H7-H9 -> -94097.934 | I12: =I7-I9 -> 64032.884 | ... P12: =P7-P9 -> 196127.62
A13: RIN SURPLUS ex SREs | B13: =B12+B4 -> 0 | C13: =C12+C4 -> 0 | D13: =D12+D4 -> 1741 | E13: =E12+E4 -> 62808 | F13: =F12+F4 -> -51946 | G13: =G12+G4 -> 147785 | H13: =H12+H4 -> -90000 | I13: =I12+I4 -> 91765 | ... P13: =P12+P4 -> 204089
A15: RIN SURPLUS
A16: TOTAL AVAILABLE - UNLOCKED
A17: TOTAL AVAILABLE - LOCKED
A19: RIN BANK ENDING BALANCE

Sheet RIN Retirements
S1: RIN RETIREMENTS FOR ANNUAL COMPLIANCE CURRENT RIN YEAR | AJ1: RIN RETIREMENTS FOR ANNUAL COMPLIANCE PRIOR RIN YEAR - (RIN Generation Year)
B2: 2010 | C2: 2011 | D2: 2012 | E2: 2013 | F2: 2014 | G2: 2015 | H2: 2016 | I2: 2017 | J2: 2018 | K2: 2019 | L2: 2020 | M2: 2021 | N2: 2022 | O2: 2023 | P2: 2024 | S2: 2010 | T2: 2011 | U2: 2012 | V2: 2013 | W2: 2014 | X2: 2015 | Y2: 2016 | Z2: 2017 | AA2: 2018 | AB2: 2019 | AC2: 2020 | AD2: 2021 | AE2: 2022 | AF2: 2023 | AG2: 2024 | AJ2: 2010 | AK2: 2011 | AL2: 2012 | AM2: 2013 | AN2: 2014 | AO2: 2015 | AP2: 2016 | AQ2: 2017 | AR2: 2018 | AS2: 2019 | AT2: 2020 | AU2: 2021 | AV2: 2022 | AW2: 2023 | AX2: 2024
A3: RIN Retirements - Annual Compliance | B3: =B4+B8+B12+B16+B20 -> 4211327425 | C3: =C4+C8+C12+C16+C20 -> 13327323577 | D3: =D4+D8+D12+D16+D20 -> 16296553703 | E3: =E4+E8+E12+E16+E20 -> 17311269123 | F3: =F4+F8+F12+F16+F20 -> 16660418629 | G3: =G4+G8+G12+G16+G20 -> 17838472400 | H3: =H4+H8+H12+H16+H20 -> 17888987566 | I3: =I4+I8+I12+I16+I20 -> 18152769160 | ... P3: =P4+P8+P12+P16+P20 -> 1524914437
A4: D3 | B4: =SUM(B5:B7) -> 0 | C4: =SUM(C5:C7) -> 0 | D4: =SUM(D5:D7) -> 0 | E4: =SUM(E5:E7) -> 293023 | F4: =SUM(F5:F7) -> 21143070 | G4: =SUM(G5:G7) -> 112841471 | H4: =SUM(H5:H7) -> 189349748 | I4: =SUM(I5:I7) -> 259889372 | ... P4: =SUM(P5:P7) -> 67979
A5: Importers | B5: =S5 -> 0 | C5: =T5+AJ5 -> 0 | D5: =U5+AK5 -> 0 | E5: =V5+AL5 -> 495 | F5: =W5+AM5 -> 238252 | G5: =X5+AN5 -> 3135237 | H5: =Y5+AO5 -> 5286096 | I5: =Z5+AP5 -> 8277468 | J5: =AA5+AQ5 -> 7454889 | K5: =AB5+AR5 -> 12842945 | L5: =L118 -> 17089332 | M5: =M118 -> 21715482 | N5: =N118 -> 26492184 | O5: =O118 -> 52025191 | P5: =P118 -> 0 | S5: 0 | T5: 0 | U5: 0 | V5: 495 | W5: 238252 | X5: 2882222 | Y5: 4483095 | Z5: 6548283 | AA5: 6312039 | AB5: 10967242 | AC5: =FORECAST(L5,T5:AB5,C5:K5) -> 14349698 | AD5: =FORECAST(M5,U5:AC5,D5:L5) -> 18222452 | AE5: =FORECAST(N5,V5:AD5,E5:M5) -> 22217325 | AF5: =FORECAST(O5,W5:AE5,F5:N5) -> 43569528 | AG5: =FORECAST(P5,X5:AF5,G5:O5) -> 53278.155 | AJ5: 0 | AK5: 0 | AL5: 0 | AM5: 0 | AN5: 253015 | AO5: 803001 | AP5: 1729185 | AQ5: 1142850 | AR5: 1875703 | AS5: 0 | AT5: =L5-AC5 -> 2739633.9 | AU5: =M5-AD5 -> 3493030.1 | AV5: =N5-AH5 -> 26492184 | AW5: =O5-AI5 -> 52025191 | AX5: =P5-AJ5 -> 0
A6: Refiners | B6: =S6 -> 0 | C6: =T6+AJ6 -> 0 | D6: =U6+AK6 -> 0 | E6: =V6+AL6 -> 272459 | F6: =W6+AM6 -> 20904818 | G6: =X6+AN6 -> 109706234 | H6: =Y6+AO6 -> 184063652 | I6: =Z6+AP6 -> 251611904 | J6: =AA6+AQ6 -> 276485268 | K6: =AB6+AR6 -> 397777886 | L6: =L119 -> 486735855 | M6: =M119 -> 540778908 | N6: =N119 -> 633553647 | O6: =O119 -> 683771313 | P6: =P119 -> 0 | S6: 0 | T6: 0 | U6: 0 | V6: 272459 | W6: 20783114 | X6: 97996971 | Y6: 146733203 | Z6: 215199204 | AA6: 252851555 | AB6: 348721226 | AC6: =FORECAST(L6,T6:AB6,C6:K6) -> 4.2576242e+08 | AD6: =FORECAST(M6,U6:AC6,D6:L6) -> 4.73153e+08 | AE6: =FORECAST(N6,V6:AD6,E6:M6) -> 5.5453496e+08 | AF6: =FORECAST(O6,W6:AE6,F6:N6) -> 5.9872376e+08 | AG6: =FORECAST(P6,X6:AF6,G6:O6) -> -3005529.1 | AJ6: 0 | AK6: 0 | AL6: 0 | AM6: 121704 | AN6: 11709263 | AO6: 37330449 | AP6: 36412700 | AQ6: 23633713 | AR6: 49056660 | AS6: 0 | AT6: =L6-AC6 -> 60973430 | AU6: =M6-AD6 -> 67625911 | AV6: =N6-AH6 -> 633553647 | AW6: =O6-AI6 -> 683771313 | AX6: =P6-AJ6 -> 0
A7: Exporters | B7: =S7 -> 0 | C7: =T7+AJ7 -> 0 | D7: =U7+AK7 -> 0 | E7: =V7+AL7 -> 20069 | F7: =W7+AM7 -> 0 | G7: =X7+AN7 -> 0 | H7: =Y7+AO7 -> 0 | I7: =Z7+AP7 -> 0 | J7: =AA7+AQ7 -> 0 | K7: =AB7+AR7 -> 0 | L7: =L120 -> 0 | M7: =M120 -> 0 | N7: =N120 -> 0 | O7: =O120 -> 0 | P7: =P120 -> 67979 | S7: 0 | T7: 0 | U7: 0 | V7: 20069 | W7: 0 | X7: 0 | Y7: 0 | Z7: 0 | AA7: 0 | AB7: 0 | AC7: =FORECAST(L7,T7:AB7,C7:K7) -> 0 | AD7: =FORECAST(M7,U7:AC7,D7:L7) -> 0 | AE7: =FORECAST(N7,V7:AD7,E7:M7) -> 0 | AF7: =FORECAST(O7,W7:AE7,F7:N7) -> #DIV/0! | AG7: =FORECAST(P7,X7:AF7,G7:O7) -> #DIV/0! | AJ7: 0 | AK7: 0 | AL7: 0 | AM7: 0 | AN7: 0 | AO7: 0 | AP7: 0 | AQ7: 0 | AR7: 0 | AS7: 0 | AT7: 0 | AU7: 0 | AV7: 0 | AW7: 1 | AX7: 2
A8: D4 | B8: =SUM(B9:B11) -> 222710547 | C8: =SUM(C9:C11) -> 1319863392 | D8: =SUM(D9:D11) -> 1679016522 | E8: =SUM(E9:E11) -> 2379043691 | F8: =SUM(F9:F11) -> 2720901529 | G8: =SUM(G9:G11) -> 2876836117 | H8: =SUM(H9:H11) -> 3281819764 | I8: =SUM(I9:I11) -> 3844871513 | ... P8: =SUM(P9:P11) -> 972498916
A9: Importers | B9: =S9 -> 32383105 | C9: =T9+AJ9 -> 171114795 | D9: =U9+AK9 -> 53892018 | E9: =V9+AL9 -> 80408313 | F9: =W9+AM9 -> 81558056 | G9: =X9+AN9 -> 83871867 | H9: =Y9+AO9 -> 88692597 | I9: =Z9+AP9 -> 98079176 | J9: =AA9+AQ9 -> 105103871 | K9: =AB9+AR9 -> 127324436 | L9: =L132 -> 140255096 | M9: =M132 -> 171819690 | N9: =N132 -> 151152543 | O9: =O132 -> 265471820 | P9: =P132 -> 0 | S9: 32383105 | T9: 163711920 | U9: 44915835 | V9: 76681584 | W9: 65187113 | X9: 70987813 | Y9: 81759422 | Z9: 81894445 | AA9: 86953447 | AB9: 107935547 | AC9: =FORECAST(L9,T9:AB9,C9:K9) -> 1.2727996e+08 | AD9: =FORECAST(M9,U9:AC9,D9:L9) -> 1.5109006e+08 | AE9: =FORECAST(N9,V9:AD9,E9:M9) -> 1.3248083e+08 | AF9: =FORECAST(O9,W9:AE9,F9:N9) -> 2.3854419e+08 | AG9: =FORECAST(P9,X9:AF9,G9:O9) -> -5842598.3 | AJ9: 7402875 | AK9: 8976183 | AL9: 3726729 | AM9: 16370943 | AN9: 12884054 | AO9: 6933175 | AP9: 16184731 | AQ9: 18150424 | AR9: 19388889 | AS9: 0 | AT9: =M9-AC9 -> 44539729 | AU9: =N9-AD9 -> 62484.803 | AV9: =O9-AE9 -> 1.3299099e+08 | AW9: =P9-AF9 -> -2.3854419e+08 | AX9: =Q9-AG9 -> 5842598.3
A10: Refiners | B10: =S10 -> 161731886 | C10: =T10+AJ10 -> 1077109606 | D10: =U10+AK10 -> 1522793789 | E10: =V10+AL10 -> 2173913248 | F10: =W10+AM10 -> 2505502955 | G10: =X10+AN10 -> 2649612677 | H10: =Y10+AO10 -> 2991142826 | I10: =Z10+AP10 -> 3489986121 | J10: =AA10+AQ10 -> 3580700481 | K10: =AB10+AR10 -> 3966402350 | L10: =L133 -> 3636525700 | M10: =M133 -> 4088344997 | N10: =N133 -> 4758591693 | O10: =O133 -> 5928584065 | P10: =P133 -> 0 | S10: 161731886 | T10: 1027143577 | U10: 1253832732 | V10: 1929434761 | W10: 2026671104 | X10: 2277225641 | Y10: 2732337783 | Z10: 2685834276 | AA10: 2883849971 | AB10: 3403384067 | AC10: =FORECAST(L10,T10:AB10,C10:K10) -> 3.0185577e+09 | AD10: =FORECAST(M10,U10:AC10,D10:L10) -> 3.3873239e+09 | AE10: =FORECAST(N10,V10:AD10,E10:M10) -> 3.8860566e+09 | AF10: =FORECAST(O10,W10:AE10,F10:N10) -> 4.8192412e+09 | AG10: =FORECAST(P10,X10:AF10,G10:O10) -> 2.340658e+08 | AJ10: 49966029 | AK10: 268961057 | AL10: 244478487 | AM10: 478831851 | AN10: 372387036 | AO10: 258805043 | AP10: 804151845 | AQ10: 696850510 | AR10: 563018283 | AS10: 0 | AT10: =M10-AC10 -> 1.0697873e+09 | AU10: =N10-AD10 -> 1.3712678e+09 | AV10: =O10-AE10 -> 2.0425275e+09 | AW10: =P10-AF10 -> -4.8192412e+09 | AX10: =Q10-AG10 -> -2.340658e+08
A11: Exporters | B11: =S11 -> 28595556 | C11: =T11+AJ11 -> 71638991 | D11: =U11+AK11 -> 102330715 | E11: =V11+AL11 -> 124722130 | F11: =W11+AM11 -> 133840518 | G11: =X11+AN11 -> 143351573 | H11: =Y11+AO11 -> 201984341 | I11: =Z11+AP11 -> 256806216 | J11: =AA11+AQ11 -> 245032965 | K11: =AB11+AR11 -> 371706098 | L11: =L134 -> 511752623 | M11: =M134 -> 545711955 | N11: =N134 -> 728710359 | O11: =O134 -> 923272025 | P11: =P134 -> 972498916 | S11: 28595556 | T11: 68243730 | U11: 83207852 | V11: 110907514 | W11: 109261389 | X11: 130139080 | Y11: 201783657 | Z11: 213454481 | AA11: 213315988 | AB11: 339822095 | AC11: =FORECAST(L11,T11:AB11,C11:K11) -> 4.6114678e+08 | AD11: =FORECAST(M11,U11:AC11,D11:L11) -> 4.9345438e+08 | AE11: =FORECAST(N11,V11:AD11,E11:M11) -> 6.5938741e+08 | AF11: =FORECAST(O11,W11:AE11,F11:N11) -> 8.3673168e+08 | AG11: =FORECAST(P11,X11:AF11,G11:O11) -> 8.8001172e+08 | AJ11: 3395261 | AK11: 19122863 | AL11: 13814616 | AM11: 24579129 | AN11: 13212493 | AO11: 200684 | AP11: 43351735 | AQ11: 31716977 | AR11: 31884003 | AS11: 0 | AT11: =M11-AC11 -> 84565173 | AU11: =N11-AD11 -> 2.3525598e+08 | AV11: =O11-AE11 -> 2.6388461e+08 | AW11: =P11-AF11 -> 1.3576723e+08 | AX11: =Q11-AG11 -> -8.8001172e+08
A12: D5 | B12: =SUM(B13:B15) -> 24808442 | C12: =SUM(C13:C15) -> 173316504 | D12: =SUM(D13:D15) -> 481271750 | E12: =SUM(E13:E15) -> 673610540 | F12: =SUM(F13:F15) -> 130729680 | G12: =SUM(G13:G15) -> 101203401 | H12: =SUM(H13:H15) -> 181556905 | I12: =SUM(I13:I15) -> 150031625 | ... P12: =SUM(P13:P15) -> 45963601
A13: Importers | B13: =S13 -> 1087451 | C13: =T13+AJ13 -> 18260067 | D13: =U13+AK13 -> 16505748 | E13: =V13+AL13 -> 29857162 | F13: =W13+AM13 -> 4823149 | G13: =X13+AN13 -> 2647394 | H13: =Y13+AO13 -> 6810726 | I13: =Z13+AP13 -> 9316999 | J13: =AA13+AQ13 -> 2525884 | K13: =AB13+AR13 -> 1887839 | L13: =L152 -> 7723718 | M13: =M152 -> 7841263 | N13: =N152 -> 6903859 | O13: =O152 -> 9358170 | P13: =P152 -> 0 | S13: 1087451 | T13: 17349808 | U13: 14807585 | V13: 21692645 | W13: 3638250 | X13: 2056285 | Y13: 941133 | Z13: 9294686 | AA13: 2425370 | AB13: 1712520 | AC13: =FORECAST(L13,T13:AB13,C13:K13) -> 6159226 | AD13: =FORECAST(M13,U13:AC13,D13:L13) -> 5995734.6 | AE13: =FORECAST(N13,V13:AD13,E13:M13) -> 5075584.7 | AF13: =FORECAST(O13,W13:AE13,F13:N13) -> 7050049.7 | AG13: =FORECAST(P13,X13:AF13,G13:O13) -> -225833.04 | AJ13: 910259 | AK13: 1698163 | AL13: 8164517 | AM13: 1184899 | AN13: 591109 | AO13: 5869593 | AP13: 22313 | AQ13: 100514 | AR13: 175319 | AS13: 0 | AT13: =L13-AC13 -> 1564492 | AU13: =M13-AD13 -> 1845528.4 | AV13: =N13-AH13 -> 6903859 | AW13: =O13-AI13 -> 9358170 | AX13: =P13-AJ13 -> -910259
A14: Refiners | B14: =S14 -> 23720991 | C14: =T14+AJ14 -> 155056437 | D14: =U14+AK14 -> 464282276 | E14: =V14+AL14 -> 640465437 | F14: =W14+AM14 -> 125893314 | G14: =X14+AN14 -> 98556007 | H14: =Y14+AO14 -> 174746179 | I14: =Z14+AP14 -> 140704373 | J14: =AA14+AQ14 -> 169655633 | K14: =AB14+AR14 -> 329931071 | L14: =L153 -> 324512674 | M14: =M153 -> 224221540 | N14: =N153 -> 298932895 | O14: =O153 -> 174238256 | P14: =P153 -> 0 | S14: 23720991 | T14: 152386595 | U14: 415178490 | V14: 484181290 | W14: 84285790 | X14: 44554377 | Y14: 82066955 | Z14: 125802068 | AA14: 160130110 | AB14: 314525219 | AC14: =FORECAST(L14,T14:AB14,C14:K14) -> 2.6418238e+08 | AD14: =FORECAST(M14,U14:AC14,D14:L14) -> 1.7732145e+08 | AE14: =FORECAST(N14,V14:AD14,E14:M14) -> 2.3438226e+08 | AF14: =FORECAST(O14,W14:AE14,F14:N14) -> 1.304192e+08 | AG14: =FORECAST(P14,X14:AF14,G14:O14) -> -41414393 | AJ14: 2669842 | AK14: 49103786 | AL14: 156284147 | AM14: 41607524 | AN14: 54001630 | AO14: 92679224 | AP14: 14902305 | AQ14: 9525523 | AR14: 15405852 | AS14: 0 | AT14: =L14-AC14 -> 60330290 | AU14: =M14-AD14 -> 46900087 | AV14: =N14-AH14 -> 298932895 | AW14: =O14-AI14 -> 174238256 | AX14: =P14-AJ14 -> -2669842
A15: Exporters | B15: =S15 -> 0 | C15: =T15+AJ15 -> 0 | D15: =U15+AK15 -> 483726 | E15: =V15+AL15 -> 3287941 | F15: =W15+AM15 -> 13217 | G15: =X15+AN15 -> 0 | H15: =Y15+AO15 -> 0 | I15: =Z15+AP15 -> 10253 | J15: =AA15+AQ15 -> 58659 | K15: =AB15+AR15 -> 0 | L15: =L154 -> 0 | M15: =M154 -> 487164 | N15: =N154 -> 21714860 | O15: =O154 -> 65752652 | P15: =P154 -> 45963601 | S15: 0 | T15: 0 | U15: 462176 | V15: 2441413 | W15: 0 | X15: 0 | Y15: 0 | Z15: 0 | AA15: 58659 | AB15: 0 | AC15: 0 | AD15: 0 | AE15: 0 | AF15: 1 | AG15: 2 | AJ15: 0 | AK15: 21550 | AL15: 846528 | AM15: 13217 | AN15: 0 | AO15: 0 | AP15: 10253 | AQ15: 0 | AR15: 0 | AS15: =K15-AB15 -> 0 | AT15: =L15-AC15 -> 0 | AU15: =M15-AD15 -> 487164 | AV15: =N15-AH15 -> 21714860 | AW15: =O15-AI15 -> 65752652 | AX15: =P15-AJ15 -> 45963601
A16: D6 | B16: =SUM(B17:B19) -> 3963808436 | C16: =SUM(C17:C19) -> 11834143681 | D16: =SUM(D17:D19) -> 14136265431 | E16: =SUM(E17:E19) -> 14257997232 | F16: =SUM(F17:F19) -> 13787538096 | G16: =SUM(G17:G19) -> 14747491411 | H16: =SUM(H17:H19) -> 14235690161 | I16: =SUM(I17:I19) -> 13896400123 | ... P16: =SUM(P17:P19) -> 506383941
A17: Importers | B17: =S17 -> 397571032 | C17: =T17+AJ17 -> 1535468889 | D17: =U17+AK17 -> 574440713 | E17: =V17+AL17 -> 468866908 | F17: =W17+AM17 -> 414596388 | G17: =X17+AN17 -> 448357500 | H17: =Y17+AO17 -> 405140958 | I17: =Z17+AP17 -> 404596790 | J17: =AA17+AQ17 -> 402826202 | K17: =AB17+AR17 -> 479447552 | L17: =L170 -> 429957750 | M17: =M170 -> 566850198 | N17: =N170 -> 425114231 | O17: =O170 -> 340053222 | P17: =P170 -> 0 | S17: 397571032 | T17: 1214365626 | U17: 464506905 | V17: 426802089 | W17: 383806261 | X17: 379542689 | Y17: 343730464 | Z17: 353848462 | AA17: 327624295 | AB17: 398975202 | AC17: =FORECAST(L17,T17:AB17,C17:K17) -> 3.698925e+08 | AD17: =FORECAST(M17,U17:AC17,D17:L17) -> 4.6741719e+08 | AE17: =FORECAST(N17,V17:AD17,E17:M17) -> 3.6724098e+08 | AF17: =FORECAST(O17,W17:AE17,F17:N17) -> 3.0351514e+08 | AG17: =FORECAST(P17,X17:AF17,G17:O17) -> 48546272 | AJ17: 321103263 | AK17: 109933808 | AL17: 42064819 | AM17: 30790127 | AN17: 68814811 | AO17: 61410494 | AP17: 50748328 | AQ17: 75201907 | AR17: 80472350 | AS17: 0 | AT17: =L17-AC17 -> 60065249 | AU17: =M17-AD17 -> 99433003 | AV17: =N17-AH17 -> 425114231 | AW17: =O17-AI17 -> 340053222 | AX17: =P17-AJ17 -> -321103263
A18: Refiners | B18: =S18 -> 3390488902 | C18: =T18+AJ18 -> 9690140747 | D18: =U18+AK18 -> 13140456554 | E18: =V18+AL18 -> 13488274973 | F18: =W18+AM18 -> 12981779798 | G18: =X18+AN18 -> 13899324992 | H18: =Y18+AO18 -> 13409952319 | I18: =Z18+AP18 -> 13142434526 | J18: =AA18+AQ18 -> 14088890736 | K18: =AB18+AR18 -> 14536356355 | L18: =L171 -> 11978833783 | M18: =M171 -> 13211539487 | N18: =N171 -> 13590347309 | O18: =O171 -> 13416040218 | P18: =P171 -> 0 | S18: 3390488902 | T18: 7769788969 | U18: 10080436228 | V18: 11450141829 | W18: 11940537686 | X18: 12626678939 | Y18: 12255314786 | Z18: 11290100563 | AA18: 11398289693 | AB18: 11818488736 | AC18: =FORECAST(L18,T18:AB18,C18:K18) -> 1.0106584e+10 | AD18: =FORECAST(M18,U18:AC18,D18:L18) -> 1.1302104e+10 | AE18: =FORECAST(N18,V18:AD18,E18:M18) -> 1.1687358e+10 | AF18: =FORECAST(O18,W18:AE18,F18:N18) -> 1.159611e+10 | AG18: =FORECAST(P18,X18:AF18,G18:O18) -> 1.9973721e+09 | AJ18: 1920351778 | AK18: 3060020326 | AL18: 2038133144 | AM18: 1041242112 | AN18: 1272646053 | AO18: 1154637533 | AP18: 1852333963 | AQ18: 2690601043 | AR18: 2717867619 | AS18: 0 | AT18: =L18-AC18 -> 1.8722501e+09 | AU18: =M18-AD18 -> 1.9094351e+09 | AV18: =N18-AH18 -> 13590347309 | AW18: =O18-AI18 -> 13416040218 | AX18: =P18-AJ18 -> -1920351778
A19: Exporters | B19: =S19 -> 175748502 | C19: =T19+AJ19 -> 608534045 | D19: =U19+AK19 -> 421368164 | E19: =V19+AL19 -> 300855351 | F19: =W19+AM19 -> 391161910 | G19: =X19+AN19 -> 399808919 | H19: =Y19+AO19 -> 420596884 | I19: =Z19+AP19 -> 349368807 | J19: =AA19+AQ19 -> 451218339 | K19: =AB19+AR19 -> 365988095 | L19: =L172 -> 311513241 | M19: =M172 -> 313025795 | N19: =N172 -> 373660194 | O19: =O172 -> 465909527 | P19: =P172 -> 506383941 | S19: 175748502 | T19: 531328779 | U19: 311802256 | V19: 277498449 | W19: 380301595 | X19: 389749558 | Y19: 400613908 | Z19: 327034369 | AA19: 375071281 | AB19: 305067041 | AC19: =FORECAST(L19,T19:AB19,C19:K19) -> 2.8655258e+08 | AD19: =FORECAST(M19,U19:AC19,D19:L19) -> 2.9306656e+08 | AE19: =FORECAST(N19,V19:AD19,E19:M19) -> 3.4275307e+08 | AF19: =FORECAST(O19,W19:AE19,F19:N19) -> 4.1896102e+08 | AG19: =FORECAST(P19,X19:AF19,G19:O19) -> 4.4879077e+08 | AJ19: 77205266 | AK19: 109565908 | AL19: 23356902 | AM19: 10860315 | AN19: 10059361 | AO19: 19982976 | AP19: 22334438 | AQ19: 76147058 | AR19: 60921054 | AS19: 0 | AT19: =L19-AC19 -> 24960662 | AU19: =M19-AD19 -> 19959239 | AV19: =N19-AH19 -> 373660194 | AW19: =O19-AI19 -> 465909527 | AX19: =P19-AJ19 -> 429178675
A20: D7 | B20: =SUM(B21:B23) -> 0 | C20: =SUM(C21:C23) -> 0 | D20: =SUM(D21:D23) -> 0 | E20: =SUM(E21:E23) -> 324637 | F20: =SUM(F21:F23) -> 106254 | G20: =SUM(G21:G23) -> 100000 | H20: =SUM(H21:H23) -> 570988 | I20: =SUM(I21:I23) -> 1576527 | ... P20: =SUM(P21:P23) -> 0
A21: Importers | B21: =S21 -> 0 | C21: =T21+AJ21 -> 0 | D21: =U21+AK21 -> 0 | E21: =V21+AL21 -> 123 | F21: =W21+AM21 -> 7553 | G21: =X21+AN21 -> 0 | H21: =Y21+AO21 -> 0 | I21: =Z21+AP21 -> 59519 | J21: =AA21+AQ21 -> 121780 | K21: =AB21+AR21 -> 212693 | L21: =L190 -> 0 | M21: =M190 -> 0 | N21: =N190 -> 0 | O21: =O190 -> 0 | P21: =P190 -> 0 | S21: 0 | T21: 0 | U21: 0 | V21: 0 | W21: 0 | X21: 0 | Y21: 0 | Z21: 59519 | AA21: 121299 | AB21: 177337 | AC21: =FORECAST(L21,T21:AB21,C21:K21)-1660.4 -> -939.96997 | AD21: =FORECAST(M21,U21:AC21,D21:L21)-1660.4 -> -1085.3418 | AE21: =FORECAST(N21,V21:AD21,E21:M21)-1660.4 -> -1253.1962 | AF21: =FORECAST(O21,W21:AE21,F21:N21)-1660.4 -> -1430.3371 | AG21: =FORECAST(P21,X21:AF21,G21:O21)-1660.4 -> -685.68941 | AJ21: 0 | AK21: 0 | AL21: 123 | AM21: 7553 | AN21: 0 | AO21: 0 | AP21: 0 | AQ21: 481 | AR21: 35356 | AS21: =K21-AB21 -> 35356 | AT21: =L21-AC21 -> 939.96997 | AU21: =M21-AD21 -> 1085.3418 | AV21: =N21-AH21 -> 0 | AW21: =O21-AI21 -> 0 | AX21: =P21-AJ21 -> 0
A22: Refiners | B22: =S22 -> 0 | C22: =T22+AJ22 -> 0 | D22: =U22+AK22 -> 0 | E22: =V22+AL22 -> 324514 | F22: =W22+AM22 -> 98701 | G22: =X22+AN22 -> 100000 | H22: =Y22+AO22 -> 570988 | I22: =Z22+AP22 -> 1517008 | J22: =AA22+AQ22 -> 1568028 | K22: =AB22+AR22 -> 1743294 | L22: =L191 -> 55892 | M22: =M191 -> 247518 | N22: =N191 -> 236352 | O22: =O191 -> 208643 | P22: =P191 -> 0 | S22: 0 | T22: 0 | U22: 0 | V22: 322896 | W22: 45449 | X22: 100000 | Y22: 480988 | Z22: 1517008 | AA22: 1568028 | AB22: 1033128 | AC22: =FORECAST(L22,T22:AB22,C22:K22) -> 62226.871 | AD22: =FORECAST(M22,U22:AC22,D22:L22) -> 224370.74 | AE22: =FORECAST(N22,V22:AD22,E22:M22) -> 218737.12 | AF22: =FORECAST(O22,W22:AE22,F22:N22) -> 191068.26 | AG22: =FORECAST(P22,X22:AF22,G22:O22) -> 29906.747 | AJ22: 0 | AK22: 0 | AL22: 1618 | AM22: 53252 | AN22: 0 | AO22: 90000 | AP22: 0 | AQ22: 0 | AR22: 710166 | AS22: =K22-AB22 -> 710166 | AT22: =L22-AC22 -> -6334.8713 | AU22: =M22-AD22 -> 23147.258 | AV22: =N22-AH22 -> 236352 | AW22: =O22-AI22 -> 208643 | AX22: =P22-AJ22 -> 0
A23: Exporters | B23: =S23 -> 0 | C23: =T23+AJ23 -> 0 | D23: =U23+AK23 -> 0 | E23: =V23+AL23 -> 0 | F23: =W23+AM23 -> 0 | G23: =X23+AN23 -> 0 | H23: =Y23+AO23 -> 0 | I23: =Z23+AP23 -> 0 | J23: =AA23+AQ23 -> 0 | K23: =AB23+AR23 -> 0 | L23: =L192 -> 0 | M23: =M192 -> 0 | N23: =N192 -> 0 | O23: =O192 -> 0 | P23: =P192 -> 0 | S23: 0 | T23: 0 | U23: 0 | V23: 0 | W23: 0 | X23: 0 | Y23: 0 | Z23: 0 | AA23: 0 | AB23: 0 | AC23: 0 | AD23: 0 | AE23: 0 | AF23: 1 | AG23: 2 | AJ23: 0 | AK23: 0 | AL23: 0 | AM23: 0 | AN23: 0 | AO23: 0 | AP23: 0 | AQ23: 0 | AR23: 0 | AS23: =K23-AB23 -> 0 | AT23: =L23-AC23 -> 0 | AU23: =M23-AD23 -> 0 | AV23: =N23-AH23 -> 0 | AW23: =O23-AI23 -> 0 | AX23: =P23-AJ23 -> 0
S24: Data from RIN Retirements for Annual Compliance Table - EPA Site
A25: RIN Retirements - Errors | B25: =B26+B30+B34+B38+B42 -> 25113475 | C25: =C26+C30+C34+C38+C42 -> 78473364 | D25: =D26+D30+D34+D38+D42 -> 45611665 | E25: =E26+E30+E34+E38+E42 -> 40623544 | F25: =F26+F30+F34+F38+F42 -> 21899568 | G25: =G26+G30+G34+G38+G42 -> 9513432 | H25: =H26+H30+H34+H38+H42 -> 27233554 | I25: =I26+I30+I34+I38+I42 -> 38658277 | ... P25: =P26+P30+P34+P38+P42 -> 20437799
A26: D3 | B26: =SUM(B27:B29) -> 0 | C26: =SUM(C27:C29) -> 0 | D26: =SUM(D27:D29) -> 0 | E26: =SUM(E27:E29) -> 0 | F26: =SUM(F27:F29) -> 342326 | G26: =SUM(G27:G29) -> 2024139 | H26: =SUM(H27:H29) -> 2061978 | I26: =SUM(I27:I29) -> 45292 | ... P26: =SUM(P27:P29) -> 1130290
A27: Import Volume Correction
A28: Invalid RIN | F28: 342326 | G28: 2024139 | H28: 2058045 | I28: 40073 | J28: 9969 | K28: 1273394 | L28: =L123 -> 713562 | M28: =M123 -> 5205881 | N28: =N123 -> 5286255 | O28: =O123 -> 1587010 | P28: =P123 -> 1130290
A29: Volume Error Correction | H29: 3933 | I29: 5219 | K29: 58206 | L29: =L127 -> 0 | M29: =M127 -> 0 | N29: =N127 -> 0 | O29: =O127 -> 0 | P29: =P127 -> 0
A30: D4 | B30: =SUM(B31:B33) -> 13812123 | C30: =SUM(C31:C33) -> 46787035 | D30: =SUM(D31:D33) -> 8948629 | E30: =SUM(E31:E33) -> 9467178 | F30: =SUM(F31:F33) -> 7016765 | G30: =SUM(G31:G33) -> 2880290 | H30: =SUM(H31:H33) -> 6188858 | I30: =SUM(I31:I33) -> 19001829 | ... P30: =SUM(P31:P33) -> 2139574
A31: Import Volume Correction | C31: 6851 | D31: 6699 | E31: 4433491 | G31: 10416 | J31: 84383
A32: Invalid RIN | B32: 13041810 | C32: 42804235 | D32: 7615391 | E32: 4100053 | F32: 6833365 | G32: 2604233 | H32: 5779755 | I32: 16804657 | J32: 15987077 | K32: 5858912 | L32: =L140 -> 31443904 | M32: =M140 -> 3721781 | N32: =N140 -> 7845498 | O32: =O140 -> 2708205 | P32: =P140 -> 2138105
A33: Volume Error Correction | B33: 770313 | C33: 3975949 | D33: 1326539 | E33: 933634 | F33: 183400 | G33: 265641 | H33: 409103 | I33: 2197172 | J33: 1698471 | K33: 628529 | L33: =L147 -> 21497 | M33: =M147 -> 329637 | N33: =N147 -> 3817 | O33: =O147 -> 30331 | P33: =P147 -> 1469
A34: D5 | B34: =SUM(B35:B37) -> 65268 | C34: =SUM(C35:C37) -> 3600279 | D34: =SUM(D35:D37) -> 29709496 | E34: =SUM(E35:E37) -> 6246169 | F34: =SUM(F35:F37) -> 124707 | G34: =SUM(G35:G37) -> 262346 | H34: =SUM(H35:H37) -> 132964 | I34: =SUM(I35:I37) -> 92528 | ... P34: =SUM(P35:P37) -> 2103
A35: Import Volume Correction | C35: 64425 | D35: 99695
A36: Invalid RIN | B36: 57876 | C36: 3535076 | D36: 29595838 | E36: 6222513 | F36: 124706 | G36: 262345 | H36: 124278 | I36: 84468 | J36: 856210 | K36: 196881 | L36: =L159 -> 15024 | M36: =M159 -> 824414 | N36: =N159 -> 6928395 | O36: =O159 -> 2408108 | P36: =P159 -> 0
A37: Volume Error Correction | B37: 7392 | C37: 778 | D37: 13963 | E37: 23656 | F37: 1 | G37: 1 | H37: 8686 | I37: 8060 | J37: 40170 | K37: 15900 | L37: =L165 -> 0 | M37: =M165 -> 41338 | N37: =N165 -> 80757 | O37: =O165 -> 25248 | P37: =P165 -> 2103
A38: D6 | B38: =SUM(B39:B41) -> 11236084 | C38: =SUM(C39:C41) -> 28086050 | D38: =SUM(D39:D41) -> 6953540 | E38: =SUM(E39:E41) -> 24901865 | F38: =SUM(F39:F41) -> 14410773 | G38: =SUM(G39:G41) -> 4319127 | H38: =SUM(H39:H41) -> 18796313 | I38: =SUM(I39:I41) -> 19443026 | ... P38: =SUM(P39:P41) -> 17141957
A39: Import Volume Correction | C39: 70663
A40: Invalid RIN | B40: 5364514 | C40: 20308085 | D40: 5317705 | E40: 21718069 | F40: 11513723 | G40: 3317742 | H40: 14371253 | I40: 14549117 | J40: 5821702 | K40: 4310506 | L40: =L178 -> 2196957 | M40: =M178 -> 11417351 | N40: =N178 -> 12865767 | O40: =O178 -> 6459246 | P40: =P178 -> 15966104
A41: Volume Error Correction | B41: 5871570 | C41: 7707302 | D41: 1635835 | E41: 3183796 | F41: 2897050 | G41: 1001385 | H41: 4425060 | I41: 4893909 | J41: 3482159 | K41: 6087150 | L41: =L185 -> 3493966 | M41: =M185 -> 3728791 | N41: =N185 -> 762235 | O41: =O185 -> 1842201 | P41: =P185 -> 1175853
A42: D7 | B42: =SUM(B43:B45) -> 0 | C42: =SUM(C43:C45) -> 0 | D42: =SUM(D43:D45) -> 0 | E42: =SUM(E43:E45) -> 8332 | F42: =SUM(F43:F45) -> 4997 | G42: =SUM(G43:G45) -> 27530 | H42: =SUM(H43:H45) -> 53441 | I42: =SUM(I43:I45) -> 75602 | ... P42: =SUM(P43:P45) -> 23875
A43: Import Volume Correction
A44: Invalid RIN | E44: 8332 | F44: 4997 | G44: 27530 | H44: 53441 | I44: 75602 | P44: =P194 -> 23875
A45: Volume Error Correction
A47: RIN Retirements - Other | B47: =B48+B60+B72+B84+B96 -> 99069268 | C47: =C48+C60+C72+C84+C96 -> 390181518 | D47: =D48+D60+D72+D84+D96 -> 90759633 | E47: =E48+E60+E72+E84+E96 -> 176478026 | F47: =F48+F60+F72+F84+F96 -> 373012020 | G47: =G48+G60+G72+G84+G96 -> 240715075 | H47: =H48+H60+H72+H84+H96 -> 327881218 | I47: =I48+I60+I72+I84+I96 -> 420188084 | ... P47: =P48+P60+P72+P84+P96 -> 19094556
A48: D3 | B48: =SUM(B49:B59) -> 0 | C48: =SUM(C49:C59) -> 0 | D48: =SUM(D49:D59) -> 0 | E48: =SUM(E49:E59) -> 0 | F48: =SUM(F49:F59) -> 34590 | G48: =SUM(G49:G59) -> 611836 | H48: =SUM(H49:H59) -> 309260 | I48: =SUM(I49:I59) -> 1863175 | ... P48: =SUM(P49:P59) -> 24650
A49: Reported Spill
A50: Contaminated or Spoiled Fuel
A51: Renewable Fuel Used in an Ocean Going Vessel
A52: Enforcement Obligation | H52: 0 | L52: =L122 -> 79474 | M52: =M122 -> 0 | N52: =N122 -> 2907 | O52: =O122 -> 219156 | P52: =P122 -> 0
A53: RF Used or Designated in Application Not Transportation Fuel, Heating Oil, or Jet Fuel | F53: 27943 | I53: 844
A54: Feedstock using renewable fuel with RINs
A55: Remedial Action - Retirement Pursuant 80.1431§(c) | F55: 6647 | G55: 100100 | H55: 309260 | I55: 1102074 | J55: 251839 | K55: 270776 | L55: =L125 -> 192694 | M55: =M125 -> 188487 | N55: =N125 -> 184174 | O55: =O125 -> 118471 | P55: =P125 -> 24650
A56: Remedial Action - Retire for Compliance | G56: 511736 | I56: 758869 | J56: 2340756 | K56: 6756856 | L56: =L124 -> 0 | M56: =M124 -> 0 | N56: =N124 -> 224485 | O56: =O124 -> 1100 | P56: =P124 -> 0
A57: Remediation of Invalid RIN Use for Compliance
A58: Voluntary RIN Retirement | I58: 1388 | J58: 5530
A59: Delayed RIN Retire per 40CFR 80.1426§(g)(3) only
A60: D4 | B60: =SUM(B61:B71) -> 23234306 | C60: =SUM(C61:C71) -> 65552508 | D60: =SUM(D61:D71) -> 81894839 | E60: =SUM(E61:E71) -> 92149481 | F60: =SUM(F61:F71) -> 91863865 | G60: =SUM(G61:G71) -> 42404725 | H60: =SUM(H61:H71) -> 115007941 | I60: =SUM(I61:I71) -> 92523704 | ... P60: =SUM(P61:P71) -> 16273483
A61: Reported Spill | B61: 76007 | C61: 8 | D61: 525 | E61: 46970 | F61: 50080 | G61: 1144 | H61: 109217 | I61: 9673 | J61: 113 | K61: 329553 | L61: =L146 -> 15482 | M61: =M146 -> 6277 | N61: =N146 -> 23837 | O61: =O146 -> 286 | P61: =P146 -> 0
A62: Contaminated or Spoiled Fuel | B62: 77147 | C62: =C136 -> 65977 | D62: 108545 | E62: 172124 | F62: 915386 | G62: 63042 | H62: 1016216 | I62: 2137671 | J62: 185482 | K62: 344209 | L62: =L136 -> 168622 | M62: =M136 -> 170062 | N62: =N136 -> 4023453 | O62: =O136 -> 2330849 | P62: =P136 -> 1769955
A63: Renewable Fuel Used in an Ocean Going Vessel | C63: 9000 | E63: 8946 | L63: =L144 -> 0 | M63: =M144 -> 46179 | N63: =N144 -> 40001 | O63: =O144 -> 7134963 | P63: =P144 -> 4105711
A64: Enforcement Obligation | B64: 6919575 | C64: 582000 | E64: 7278935 | F64: 2184121 | G64: 9725 | H64: 65009875 | I64: 36004670 | L64: =L137 -> 16254262 | M64: =M137 -> 37458 | N64: =N137 -> 1422 | O64: =O137 -> 0 | P64: =P137 -> 0
A65: RF Used or Designated in Application Not Transportation Fuel, Heating Oil, or Jet Fuel | B65: 3718775 | C65: 7502825 | D65: 40791273 | E65: 79744083 | F65: 81303420 | G65: 29940361 | H65: 36556846 | I65: 10202154 | J65: 46467227 | K65: 65921401 | L65: =L145 -> 135046367 | M65: =M145 -> 47838602 | N65: =N145 -> 91500674 | O65: =O145 -> 67740162 | P65: =P145 -> 7377346
A66: Feedstock using renewable fuel with RINs | K66: 3187664 | L66: =L138 -> 3334888 | M66: =M138 -> 8179164 | N66: =N138 -> 24699518 | O66: =O138 -> 37669250 | P66: =P138 -> 3012885
A67: Remedial Action - Retirement Pursuant 80.1431§(c) | C67: 221020 | D67: 399291 | E67: 515262 | F67: 1524529 | G67: 309110 | H67: 315586 | I67: 934998 | J67: 2923637 | K67: 3823605 | L67: =L142 -> 859850 | M67: =M142 -> 638669 | N67: =N142 -> 4222936 | O67: =O142 -> 1189847 | P67: =P142 -> 7586
A68: Remedial Action - Retire for Compliance | B68: 2902905 | C68: 15130519 | D68: 53466 | E68: 173330 | F68: 1372052 | G68: 6840 | H68: 322184 | I68: 43234538 | J68: 12294997 | K68: 45343619 | L68: =L141 -> 994757 | M68: =M141 -> 940083 | N68: =N141 -> 567425 | O68: =O141 -> 0 | P68: =P141 -> 0
A69: Remediation of Invalid RIN Use for Compliance | B69: 9539897 | C69: 42041159 | D69: 40541739 | E69: 4209831 | F69: 4514277 | G69: 12029294 | H69: 11664669 | L69: =L143 -> 4305 | M69: =M143 -> 0 | N69: =N143 -> 0 | O69: =O143 -> 12000000 | P69: =P143 -> 0
A70: Voluntary RIN Retirement | G70: 45209 | H70: 13348 | J70: 25370 | K70: 155435 | L70: =L148 -> 0 | M70: =M148 -> 0 | N70: =N148 -> 0 | O70: =O148 -> 0 | P70: =P148 -> 0
A71: Delayed RIN Retire per 40CFR 80.1426§(g)(3) only
A72: D5 | B72: =SUM(B73:B83) -> 101388 | C72: =SUM(C73:C83) -> 1709550 | D72: =SUM(D73:D83) -> 212008 | E72: =SUM(E73:E83) -> 173205 | F72: =SUM(F73:F83) -> 95719 | G72: =SUM(G73:G83) -> 15781 | H72: =SUM(H73:H83) -> 15077 | I72: =SUM(I73:I83) -> 28524 | ... P72: =SUM(P73:P83) -> 2369109
A73: Reported Spill | D73: 11 | L73: =L164 -> 0 | M73: =M164 -> 0 | N73: =N164 -> 0 | O73: =O164 -> 0 | P73: =P164 -> 0
A74: Contaminated or Spoiled Fuel | K74: 137114 | L74: =L156 -> 4382 | M74: =M156 -> 36820 | N74: =N156 -> 188045 | O74: =O156 -> 187804 | P74: =P156 -> 131521
A75: Renewable Fuel Used in an Ocean Going Vessel
A76: Enforcement Obligation | H76: 0 | I76: 5 | L76: =L157 -> 0 | M76: =M157 -> 0 | N76: =N157 -> 0 | O76: =O157 -> 0 | P76: =P157 -> 0
A77: RF Used or Designated in Application Not Transportation Fuel, Heating Oil, or Jet Fuel | C77: 47792 | D77: 112018 | F77: 93978 | K77: 477 | L77: =L163 -> 0 | M77: =M163 -> 0 | N77: =N163 -> 943395 | O77: =O163 -> 532728 | P77: =P163 -> 2234646
A78: Feedstock using renewable fuel with RINs
A79: Remedial Action - Retirement Pursuant 80.1431§(c) | C79: 25792 | D79: 55633 | E79: 75065 | F79: 1741 | G79: 15781 | H79: 15077 | I79: 991 | J79: 2210 | K79: 29817 | L79: =L161 -> 228092 | M79: =M161 -> 105420 | N79: =N161 -> 529264 | O79: =O161 -> 317646 | P79: =P161 -> 2942
A80: Remedial Action - Retire for Compliance | B80: 101388 | C80: 1635966 | D80: 17627 | I80: 27528 | J80: 168452 | K80: 2573638 | L80: =L160 -> 0 | M80: =M160 -> 8612 | N80: =N160 -> 0 | O80: =O160 -> 0 | P80: =P160 -> 0
A81: Remediation of Invalid RIN Use for Compliance | D81: 26719 | E81: 98140 | J81: 7798 | L81: =L162 -> 0 | M81: =M162 -> 0 | N81: =N162 -> 0 | O81: =O162 -> 0 | P81: =P162 -> 0
A82: Voluntary RIN Retirement | J82: 24233 | L82: =L166 -> 0 | M82: =M166 -> 0 | N82: =N166 -> 3983943 | O82: =O166 -> 0 | P82: =P166 -> 0
A83: Delayed RIN Retire per 40CFR 80.1426§(g)(3) only
A84: D6 | B84: =SUM(B85:B95) -> 75733574 | C84: =SUM(C85:C95) -> 322919460 | D84: =SUM(D85:D95) -> 8652786 | E84: =SUM(E85:E95) -> 84155340 | F84: =SUM(F85:F95) -> 281017846 | G84: =SUM(G85:G95) -> 197682733 | H84: =SUM(H85:H95) -> 212548940 | I84: =SUM(I85:I95) -> 325772681 | ... P84: =SUM(P85:P95) -> 427314
A85: Reported Spill | C85: 78800 | D85: 98707 | E85: 92960 | F85: 104154 | G85: 20327 | H85: 367501 | I85: 18310 | J85: 63489 | K85: 719305 | L85: =L184 -> 118151 | M85: =M184 -> 15723 | N85: =N184 -> 5502 | O85: =O184 -> 109459 | P85: =P184 -> 155
A86: Contaminated or Spoiled Fuel | B86: 353963 | C86: 3466919 | D86: 374636 | E86: 629265 | F86: 142152 | G86: 618142 | H86: 246788 | I86: 143454 | J86: 91608 | K86: 67264 | L86: =L174 -> 1546164 | M86: =M174 -> 80910 | N86: =N174 -> 39852 | O86: =O174 -> 497103 | P86: =P174 -> 60672
A87: Renewable Fuel Used in an Ocean Going Vessel | B87: 1048792 | C87: 4195168 | D87: 4827457 | E87: 171191 | H87: 3000 | L87: =L182 -> 0 | M87: =M182 -> 0 | N87: =N182 -> 0 | O87: =O182 -> 0 | P87: =P182 -> 0
A88: Enforcement Obligation | B88: 50061329 | C88: 235287 | D88: 0 | H88: 0 | K88: 971019 | L88: =L176 -> 4886308 | M88: =M176 -> 621738 | N88: =N176 -> 0 | O88: =O176 -> 0 | P88: =P176 -> 0
A89: RF Used or Designated in Application Not Transportation Fuel, Heating Oil, or Jet Fuel | B89: 536185 | C89: 1950301 | D89: 1232868 | E89: 78269346 | F89: 254064945 | G89: 194354946 | H89: 206263834 | I89: 241551304 | J89: 181771952 | K89: 199239469 | L89: =L183 -> 130741895 | M89: =M183 -> 135074726 | N89: =N183 -> 127616314 | O89: =O183 -> 101241955 | P89: =P183 -> 34733
A90: Feedstock using renewable fuel with RINs
A91: Remedial Action - Retirement Pursuant 80.1431§(c) | C91: 638322 | D91: 1654270 | E91: 4123424 | F91: 11907196 | G91: 2188598 | H91: 2947396 | I91: 2071283 | J91: 2384504 | K91: 8507450 | L91: =L180 -> 10213899 | M91: =M180 -> 7400179 | N91: =N180 -> 4800391 | O91: =O180 -> 3666099 | P91: =P180 -> 331754
A92: Remedial Action - Retire for Compliance | B92: 13849616 | C92: 296819853 | D92: 464398 | E92: 868794 | F92: 14428150 | G92: 17602 | H92: 2713830 | I92: 79874230 | J92: 25957741 | K92: 90472518 | L92: =L179 -> 2106793 | M92: =M179 -> 87698 | N92: =N179 -> 2996345 | O92: =O179 -> 1018 | P92: =P179 -> 0
A93: Remediation of Invalid RIN Use for Compliance | B93: 3831349 | C93: 15534810 | D93: 450 | E93: 360 | F93: 371249 | G93: 422068 | H93: 6591 | I93: 2114100 | L93: =L181 -> 0 | M93: =M181 -> 198545 | N93: =N181 -> 118807 | O93: =O181 -> 24895 | P93: =P181 -> 0
A94: Voluntary RIN Retirement | G94: 61050 | J94: 33695 | L94: =L186 -> 0 | M94: =M186 -> 0 | N94: =N186 -> 0 | O94: =O186 -> 0 | P94: =P186 -> 0
A95: Delayed RIN Retire per 40CFR 80.1426§(g)(3) only | B95: 6052340
A96: D7 | B96: =SUM(B97:B107) -> 0 | C96: =SUM(C97:C107) -> 0 | D96: =SUM(D97:D107) -> 0 | E96: =SUM(E97:E107) -> 0 | F96: =SUM(F97:F107) -> 0 | G96: =SUM(G97:G107) -> 0 | H96: =SUM(H97:H107) -> 0 | I96: =SUM(I97:I107) -> 0 | ... P96: =SUM(P97:P107) -> 0
A97: Reported Spill
A98: Contaminated or Spoiled Fuel
A99: Renewable Fuel Used in an Ocean Going Vessel
A100: Enforcement Obligation
A101: RF Used or Designated in Application Not Transportation Fuel, Heating Oil, or Jet Fuel
...

Sheet RIN Assignments-Separations
B1: 2010 | C1: 2011 | D1: 2012 | E1: 2013 | F1: 2014 | G1: 2015 | H1: 2016 | I1: 2017 | J1: 2018 | K1: 2019 | L1: 2020 | M1: 2021 | N1: 2022 | O1: 2023 | P1: 2024
A2: D3
A3: Assigned | B3: 0 | C3: 0 | D3: 0 | E3: 0 | F3: 29116 | G3: 1371351 | H3: 1153780 | I3: 714288 | J3: 223639 | K3: 462387 | L3: 218820 | M3: 4209158 | N3: 51661 | O3: 58012 | P3: 73989
A4: Separated | B4: 0 | C4: 0 | D4: 0 | E4: 414727 | F4: 33331444 | G4: 140277267 | H4: 190556256 | I4: 249517862 | J4: 312480412 | K4: 413514128 | L4: 505612582 | M4: 564173620 | N4: 668430036 | O4: 743864251 | P4: 1148930
A5: Total | B5: =SUM(B3:B4) -> 0 | C5: =SUM(C3:C4) -> 0 | D5: =SUM(D3:D4) -> 0 | E5: =SUM(E3:E4) -> 414727 | F5: =SUM(F3:F4) -> 33360560 | G5: =SUM(G3:G4) -> 141648618 | H5: =SUM(H3:H4) -> 191710036 | I5: =SUM(I3:I4) -> 250232150 | ... P5: =SUM(P3:P4) -> 1222919
A6: D4
A7: Assigned | B7: 6534849 | C7: 13466161 | D7: 44718017 | E7: 80310387 | F7: 87650801 | G7: 29584233 | H7: 38319251 | I7: 31109297 | J7: 59786798 | K7: 74768737 | L7: 147522077 | M7: 59202779 | N7: 123414303 | O7: 107780173 | P7: 7904600
A8: Separated | B8: 313986292 | C8: 1655032712 | D8: 1690101702 | E8: 2658112054 | F8: 2610833018 | G8: 2759891109 | H8: 3962422137 | I8: 3823898680 | J8: 3818607045 | K8: 4069596750 | L8: 4341046992 | M8: 4808892366 | N8: 5662556844 | O8: 7227513671 | P8: 983007373
A9: Total | B9: =SUM(B7:B8) -> 320521141 | C9: =SUM(C7:C8) -> 1668498873 | D9: =SUM(D7:D8) -> 1734819719 | E9: =SUM(E7:E8) -> 2738422441 | F9: =SUM(F7:F8) -> 2698483819 | G9: =SUM(G7:G8) -> 2789475342 | H9: =SUM(H7:H8) -> 4000741388 | I9: =SUM(I7:I8) -> 3855007977 | ... P9: =SUM(P7:P8) -> 990911973
A10: D5
A11: Assigned | B11: 57876 | C11: 3600644 | D11: 27007251 | E11: 2331140 | F11: 92250 | G11: 27297 | H11: 127612 | I11: 89611 | J11: 639062 | K11: 147905 | L11: 0 | M11: 86016 | N11: 1096278 | O11: 1462 | P11: 1
A12: Separated | B12: 28497323 | C12: 222269087 | D12: 598657696 | E12: 555209222 | F12: 142644955 | G12: 145410309 | H12: 97963388 | I12: 144823143 | J12: 178655321 | K12: 322083460 | L12: 335235403 | M12: 233480555 | N12: 339154135 | O12: 252863328 | P12: 48334812
A13: Total | B13: =SUM(B11:B12) -> 28555199 | C13: =SUM(C11:C12) -> 225869731 | D13: =SUM(D11:D12) -> 625664947 | E13: =SUM(E11:E12) -> 557540362 | F13: =SUM(F11:F12) -> 142737205 | G13: =SUM(G11:G12) -> 145437606 | H13: =SUM(H11:H12) -> 98091000 | I13: =SUM(I11:I12) -> 144912754 | ... P13: =SUM(P11:P12) -> 48334813
A14: D6
A15: Assigned | B15: 10244607 | C15: 30837903 | D15: 14400830 | E15: 103713251 | F15: 279049327 | G15: 198965192 | H15: 226370183 | I15: 263361866 | J15: 192109311 | K15: 214587421 | L15: 145632840 | M15: 154212005 | N15: 140334185 | O15: 113310182 | P15: 12719065
A16: Separated | B16: 6359193794 | C16: 13115171023 | D16: 12961505750 | E16: 13242678875 | F16: 14072545059 | G16: 14635038857 | H16: 14929996824 | I16: 14951701058 | J16: 14987755104 | K16: 14700802843 | L16: 12837626504 | M16: 14099294297 | N16: 14398702001 | O16: 14358499964 | P16: 511234147
A17: Total | B17: =SUM(B15:B16) -> 6369438401 | C17: =SUM(C15:C16) -> 13146008926 | D17: =SUM(D15:D16) -> 12975906580 | E17: =SUM(E15:E16) -> 13346392126 | F17: =SUM(F15:F16) -> 14351594386 | G17: =SUM(G15:G16) -> 14834004049 | H17: =SUM(H15:H16) -> 15156367007 | I17: =SUM(I15:I16) -> 15215062924 | ... P17: =SUM(P15:P16) -> 523953212
A18: D7
A19: Assigned | B19: 0 | C19: 0 | D19: 0 | E19: 0 | F19: 4997 | G19: 10157 | H19: 12758 | I19: 75602 | J19: 0 | K19: 0 | L19: 0 | M19: 0 | N19: 0 | O19: 0 | P19: 0
A20: Separated | B20: 0 | C20: 0 | D20: 1741 | E20: 392033 | F20: 45449 | G20: 207373 | H20: 521671 | I20: 1667833 | J20: 2440000 | K20: 1315941 | L20: 55892 | M20: 247518 | N20: 236352 | O20: 208643 | P20: 23875
A21: Total | B21: =SUM(B19:B20) -> 0 | C21: =SUM(C19:C20) -> 0 | D21: =SUM(D19:D20) -> 1741 | E21: =SUM(E19:E20) -> 392033 | F21: =SUM(F19:F20) -> 50446 | G21: =SUM(G19:G20) -> 217530 | H21: =SUM(H19:H20) -> 534429 | I21: =SUM(I19:I20) -> 1743435 | ... P21: =SUM(P19:P20) -> 23875
A24: Check versus Retirement Data
A25: D3 | B25: =B5-B29 -> 0 | C25: =C5-C29 -> 0 | D25: =D5-D29 -> 0 | E25: =E5-E29 -> 121704 | F25: =F5-F29 -> 11840574 | G25: =G5-G29 -> 26171172 | H25: =H5-H29 -> -10950 | I25: =I5-I29 -> -11565689 | ... P25: =P5-P29 -> 0
A26: Errors | B26: ='RIN Retirements'!B26 -> 0 | C26: ='RIN Retirements'!C26 -> 0 | D26: ='RIN Retirements'!D26 -> 0 | E26: ='RIN Retirements'!E26 -> 0 | F26: ='RIN Retirements'!F26 -> 342326 | G26: ='RIN Retirements'!G26 -> 2024139 | H26: ='RIN Retirements'!H26 -> 2061978 | I26: ='RIN Retirements'!I26 -> 45292 | ... P26: ='RIN Retirements'!P26 -> 1130290
A27: Other Reasons | B27: ='RIN Retirements'!B48 -> 0 | C27: ='RIN Retirements'!C48 -> 0 | D27: ='RIN Retirements'!D48 -> 0 | E27: ='RIN Retirements'!E48 -> 0 | F27: ='RIN Retirements'!F48 -> 34590 | G27: ='RIN Retirements'!G48 -> 611836 | H27: ='RIN Retirements'!H48 -> 309260 | I27: ='RIN Retirements'!I48 -> 1863175 | ... P27: ='RIN Retirements'!P48 -> 24650
A28: Compliance | B28: ='RIN Retirements'!B4 -> 0 | C28: ='RIN Retirements'!C4 -> 0 | D28: ='RIN Retirements'!D4 -> 0 | E28: ='RIN Retirements'!E4 -> 293023 | F28: ='RIN Retirements'!F4 -> 21143070 | G28: ='RIN Retirements'!G4 -> 112841471 | H28: ='RIN Retirements'!H4 -> 189349748 | I28: ='RIN Retirements'!I4 -> 259889372 | ... P28: ='RIN Retirements'!P4 -> 67979
A29: Total | B29: =SUM(B26:B28) -> 0 | C29: =SUM(C26:C28) -> 0 | D29: =SUM(D26:D28) -> 0 | E29: =SUM(E26:E28) -> 293023 | F29: =SUM(F26:F28) -> 21519986 | G29: =SUM(G26:G28) -> 115477446 | H29: =SUM(H26:H28) -> 191720986 | I29: =SUM(I26:I28) -> 261797839 | ... P29: =SUM(P26:P28) -> 1222919
A30: D4 | B30: =B9-B34 -> 60764165 | C30: =C9-C34 -> 236295938 | D30: =D9-D34 -> -35040271 | E30: =E9-E34 -> 257762091 | F30: =F9-F34 -> -121298340 | G30: =G9-G34 -> -132645790 | H30: =H9-H34 -> 597724825 | I30: =I9-I34 -> -101389069 | ... P30: =P9-P34 -> 0
A31: Errors | B31: ='RIN Retirements'!B30 -> 13812123 | C31: ='RIN Retirements'!C30 -> 46787035 | D31: ='RIN Retirements'!D30 -> 8948629 | E31: ='RIN Retirements'!E30 -> 9467178 | F31: ='RIN Retirements'!F30 -> 7016765 | G31: ='RIN Retirements'!G30 -> 2880290 | H31: ='RIN Retirements'!H30 -> 6188858 | I31: ='RIN Retirements'!I30 -> 19001829 | ... P31: ='RIN Retirements'!P30 -> 2139574
A32: Other Reasons | B32: ='RIN Retirements'!B60 -> 23234306 | C32: ='RIN Retirements'!C60 -> 65552508 | D32: ='RIN Retirements'!D60 -> 81894839 | E32: ='RIN Retirements'!E60 -> 92149481 | F32: ='RIN Retirements'!F60 -> 91863865 | G32: ='RIN Retirements'!G60 -> 42404725 | H32: ='RIN Retirements'!H60 -> 115007941 | I32: ='RIN Retirements'!I60 -> 92523704 | ... P32: ='RIN Retirements'!P60 -> 16273483
A33: Compliance | B33: ='RIN Retirements'!B8 -> 222710547 | C33: ='RIN Retirements'!C8 -> 1319863392 | D33: ='RIN Retirements'!D8 -> 1679016522 | E33: ='RIN Retirements'!E8 -> 2379043691 | F33: ='RIN Retirements'!F8 -> 2720901529 | G33: ='RIN Retirements'!G8 -> 2876836117 | H33: ='RIN Retirements'!H8 -> 3281819764 | I33: ='RIN Retirements'!I8 -> 3844871513 | ... P33: ='RIN Retirements'!P8 -> 972498916
A34: Total | B34: =SUM(B31:B33) -> 259756976 | C34: =SUM(C31:C33) -> 1432202935 | D34: =SUM(D31:D33) -> 1769859990 | E34: =SUM(E31:E33) -> 2480660350 | F34: =SUM(F31:F33) -> 2819782159 | G34: =SUM(G31:G33) -> 2922121132 | H34: =SUM(H31:H33) -> 3403016563 | I34: =SUM(I31:I33) -> 3956397046 | ... P34: =SUM(P31:P33) -> 990911973
A35: D5 | B35: =B13-B39 -> 3580101 | C35: =C13-C39 -> 47243398 | D35: =D13-D39 -> 114471693 | E35: =E13-E39 -> -122489552 | F35: =F13-F39 -> 11787099 | G35: =G13-G39 -> 43956078 | H35: =H13-H39 -> -83613946 | I35: =I13-I39 -> -5239923 | ... P35: =P13-P39 -> 0
A36: Errors | B36: ='RIN Retirements'!B34 -> 65268 | C36: ='RIN Retirements'!C34 -> 3600279 | D36: ='RIN Retirements'!D34 -> 29709496 | E36: ='RIN Retirements'!E34 -> 6246169 | F36: ='RIN Retirements'!F34 -> 124707 | G36: ='RIN Retirements'!G34 -> 262346 | H36: ='RIN Retirements'!H34 -> 132964 | I36: ='RIN Retirements'!I34 -> 92528 | ... P36: ='RIN Retirements'!P34 -> 2103
A37: Other Reasons | B37: ='RIN Retirements'!B72 -> 101388 | C37: ='RIN Retirements'!C72 -> 1709550 | D37: ='RIN Retirements'!D72 -> 212008 | E37: ='RIN Retirements'!E72 -> 173205 | F37: ='RIN Retirements'!F72 -> 95719 | G37: ='RIN Retirements'!G72 -> 15781 | H37: ='RIN Retirements'!H72 -> 15077 | I37: ='RIN Retirements'!I72 -> 28524 | ... P37: ='RIN Retirements'!P72 -> 2369109
A38: Compliance | B38: ='RIN Retirements'!B12 -> 24808442 | C38: ='RIN Retirements'!C12 -> 173316504 | D38: ='RIN Retirements'!D12 -> 481271750 | E38: ='RIN Retirements'!E12 -> 673610540 | F38: ='RIN Retirements'!F12 -> 130729680 | G38: ='RIN Retirements'!G12 -> 101203401 | H38: ='RIN Retirements'!H12 -> 181556905 | I38: ='RIN Retirements'!I12 -> 150031625 | ... P38: ='RIN Retirements'!P12 -> 45963601
A39: Total | B39: =SUM(B36:B38) -> 24975098 | C39: =SUM(C36:C38) -> 178626333 | D39: =SUM(D36:D38) -> 511193254 | E39: =SUM(E36:E38) -> 680029914 | F39: =SUM(F36:F38) -> 130950106 | G39: =SUM(G36:G38) -> 101481528 | H39: =SUM(H36:H38) -> 181704946 | I39: =SUM(I36:I38) -> 150152677 | ... P39: =SUM(P36:P38) -> 48334813
A40: D6 | B40: =B17-B44 -> 2318660307 | C40: =C17-C44 -> 960859735 | D40: =D17-D44 -> -1175965177 | E40: =E17-E44 -> -1020662311 | F40: =F17-F44 -> 268627671 | G40: =G17-G44 -> -115489222 | H40: =H17-H44 -> 689331593 | I40: =I17-I44 -> 973447094 | ... P40: =P17-P44 -> 0
A41: Errors | B41: ='RIN Retirements'!B38 -> 11236084 | C41: ='RIN Retirements'!C38 -> 28086050 | D41: ='RIN Retirements'!D38 -> 6953540 | E41: ='RIN Retirements'!E38 -> 24901865 | F41: ='RIN Retirements'!F38 -> 14410773 | G41: ='RIN Retirements'!G38 -> 4319127 | H41: ='RIN Retirements'!H38 -> 18796313 | I41: ='RIN Retirements'!I38 -> 19443026 | ... P41: ='RIN Retirements'!P38 -> 17141957
A42: Other Reasons | B42: ='RIN Retirements'!B84 -> 75733574 | C42: ='RIN Retirements'!C84 -> 322919460 | D42: ='RIN Retirements'!D84 -> 8652786 | E42: ='RIN Retirements'!E84 -> 84155340 | F42: ='RIN Retirements'!F84 -> 281017846 | G42: ='RIN Retirements'!G84 -> 197682733 | H42: ='RIN Retirements'!H84 -> 212548940 | I42: ='RIN Retirements'!I84 -> 325772681 | ... P42: ='RIN Retirements'!P84 -> 427314
A43: Compliance | B43: ='RIN Retirements'!B16 -> 3963808436 | C43: ='RIN Retirements'!C16 -> 11834143681 | D43: ='RIN Retirements'!D16 -> 14136265431 | E43: ='RIN Retirements'!E16 -> 14257997232 | F43: ='RIN Retirements'!F16 -> 13787538096 | G43: ='RIN Retirements'!G16 -> 14747491411 | H43: ='RIN Retirements'!H16 -> 14235690161 | I43: ='RIN Retirements'!I16 -> 13896400123 | ... P43: ='RIN Retirements'!P16 -> 506383941
A44: Total | B44: =SUM(B41:B43) -> 4050778094 | C44: =SUM(C41:C43) -> 12185149191 | D44: =SUM(D41:D43) -> 14151871757 | E44: =SUM(E41:E43) -> 14367054437 | F44: =SUM(F41:F43) -> 14082966715 | G44: =SUM(G41:G43) -> 14949493271 | H44: =SUM(H41:H43) -> 14467035414 | I44: =SUM(I41:I43) -> 14241615830 | ... P44: =SUM(P41:P43) -> 523953212
A45: D7 | B45: =B21-B49 -> 0 | C45: =C21-C49 -> 0 | D45: =D21-D49 -> 1741 | E45: =E21-E49 -> 59064 | F45: =F21-F49 -> -60805 | G45: =G21-G49 -> 90000 | H45: =H21-H49 -> -90000 | I45: =I21-I49 -> 91306 | ... P45: =P21-P49 -> 0
A46: Errors | B46: ='RIN Retirements'!B42 -> 0 | C46: ='RIN Retirements'!C42 -> 0 | D46: ='RIN Retirements'!D42 -> 0 | E46: ='RIN Retirements'!E42 -> 8332 | F46: ='RIN Retirements'!F42 -> 4997 | G46: ='RIN Retirements'!G42 -> 27530 | H46: ='RIN Retirements'!H42 -> 53441 | I46: ='RIN Retirements'!I42 -> 75602 | ... P46: ='RIN Retirements'!P42 -> 23875
A47: Other Reasons | B47: ='RIN Retirements'!B96 -> 0 | C47: ='RIN Retirements'!C96 -> 0 | D47: ='RIN Retirements'!D96 -> 0 | E47: ='RIN Retirements'!E96 -> 0 | F47: ='RIN Retirements'!F96 -> 0 | G47: ='RIN Retirements'!G96 -> 0 | H47: ='RIN Retirements'!H96 -> 0 | I47: ='RIN Retirements'!I96 -> 0 | ... P47: ='RIN Retirements'!P96 -> 0
