Workbook

Sheet BioD Profit per Gallon
A1: Profit per gallon ==> | B1: SBO | C1: Canola Oil | D1: BFT | E1: CWG | F1: DCO | G1: Poultry Fat | H1: UCO | I1: Yellow Grease | L1: Profit per pound ==> | M1: SBO | N1: Canola Oil | O1: BFT | P1: CWG | Q1: DCO | R1: Poultry Fat | S1: UCO | T1: Yellow Grease | V1: BFT | W1: CWG | X1: DCO | Y1: Poultry Fat | Z1: UCO | AA1: Yellow Grease
A2: ='Soybean Oil'!A2 -> 43469 | B2: ='Soybean Oil'!W2 -> 52.775 | C2: ='Canola Oil'!M2 -> 16.81 | D2: =BFT!W2 -> 88.305 | E2: =CWG!W2 -> 124.31396 | F2: =DCO!W2 -> 82.834 | G2: ='Poultry Fat'!W2 -> 73.2065 | H2: =UCO!W2 -> 120.05 | I2: ='Yellow Grease'!W2 -> 138.575 | K2: =I2-C2 -> 121.765 | M2: =B2/'Feedstock Conversions'!$B$17 -> 7.0366667 | N2: =C2/'Feedstock Conversions'!$B$13 -> 2.2563758 | O2: =D2/'Feedstock Conversions'!$B$20 -> 11.394194 | P2: =E2/'Feedstock Conversions'!$B$21 -> 15.820051 | Q2: =F2/'Feedstock Conversions'!$B$14 -> 10.101707 | R2: =G2/'Feedstock Conversions'!$B$19 -> 9.8263758 | S2: =I2/'Feedstock Conversions'!$B$24 -> 16.497024 | T2: =I2/'Feedstock Conversions'!$B$23 -> 16.837789
A3: ='Soybean Oil'!A3 -> 43476 | B3: ='Soybean Oil'!W3 -> 49.815 | C3: ='Canola Oil'!M3 -> 13.8614 | D3: =BFT!W3 -> 87.055 | E3: =CWG!W3 -> 118.34916 | F3: =DCO!W3 -> 81.174 | G3: ='Poultry Fat'!W3 -> 71.9565 | H3: =UCO!W3 -> 118.38 | I3: ='Yellow Grease'!W3 -> 136.0905 | K3: =I3-C3 -> 122.2291 | M3: =B3/'Feedstock Conversions'!$B$17 -> 6.642 | N3: =C3/'Feedstock Conversions'!$B$13 -> 1.8605906 | O3: =D3/'Feedstock Conversions'!$B$20 -> 11.232903 | P3: =E3/'Feedstock Conversions'!$B$21 -> 15.060977 | Q3: =F3/'Feedstock Conversions'!$B$14 -> 9.8992683 | R3: =G3/'Feedstock Conversions'!$B$19 -> 9.6585906 | S3: =I3/'Feedstock Conversions'!$B$24 -> 16.20125 | T3: =I3/'Feedstock Conversions'!$B$23 -> 16.535905
A4: ='Soybean Oil'!A4 -> 43483 | B4: ='Soybean Oil'!W4 -> 51 | C4: ='Canola Oil'!M4 -> 13.1015 | D4: =BFT!W4 -> 87.055 | E4: =CWG!W4 -> 115.59886 | F4: =DCO!W4 -> 81.994 | G4: ='Poultry Fat'!W4 -> 70.4665 | H4: =UCO!W4 -> 116.7 | I4: ='Yellow Grease'!W4 -> 131.1525 | K4: =I4-C4 -> 118.051 | M4: =B4/'Feedstock Conversions'!$B$17 -> 6.8 | N4: =C4/'Feedstock Conversions'!$B$13 -> 1.7585906 | O4: =D4/'Feedstock Conversions'!$B$20 -> 11.232903 | P4: =E4/'Feedstock Conversions'!$B$21 -> 14.710977 | Q4: =F4/'Feedstock Conversions'!$B$14 -> 9.9992683 | R4: =G4/'Feedstock Conversions'!$B$19 -> 9.4585906 | S4: =I4/'Feedstock Conversions'!$B$24 -> 15.613393 | T4: =I4/'Feedstock Conversions'!$B$23 -> 15.935905
A5: ='Soybean Oil'!A5 -> 43490 | B5: ='Soybean Oil'!W5 -> 45.1875 | C5: ='Canola Oil'!M5 -> 20.81225 | D5: =BFT!W5 -> 87.055 | E5: =CWG!W5 -> 113.24146 | F5: =DCO!W5 -> 83.634 | G5: ='Poultry Fat'!W5 -> 70.094 | H5: =UCO!W5 -> 113.55 | I5: ='Yellow Grease'!W5 -> 128.06625 | K5: =I5-C5 -> 107.254 | M5: =B5/'Feedstock Conversions'!$B$17 -> 6.025 | N5: =C5/'Feedstock Conversions'!$B$13 -> 2.7935906 | O5: =D5/'Feedstock Conversions'!$B$20 -> 11.232903 | P5: =E5/'Feedstock Conversions'!$B$21 -> 14.410977 | Q5: =F5/'Feedstock Conversions'!$B$14 -> 10.199268 | R5: =G5/'Feedstock Conversions'!$B$19 -> 9.4085906 | S5: =I5/'Feedstock Conversions'!$B$24 -> 15.245982 | T5: =I5/'Feedstock Conversions'!$B$23 -> 15.560905
A6: ='Soybean Oil'!A6 -> 43497 | B6: ='Soybean Oil'!W6 -> 40.065 | C6: ='Canola Oil'!M6 -> 15.7239 | D6: =BFT!W6 -> 87.055 | E6: =CWG!W6 -> 114.42016 | F6: =DCO!W6 -> 82.814 | G6: ='Poultry Fat'!W6 -> 70.094 | H6: =UCO!W6 -> 109.98 | I6: ='Yellow Grease'!W6 -> 127.0375 | K6: =I6-C6 -> 111.3136 | M6: =B6/'Feedstock Conversions'!$B$17 -> 5.342 | N6: =C6/'Feedstock Conversions'!$B$13 -> 2.1105906 | O6: =D6/'Feedstock Conversions'!$B$20 -> 11.232903 | P6: =E6/'Feedstock Conversions'!$B$21 -> 14.560977 | Q6: =F6/'Feedstock Conversions'!$B$14 -> 10.099268 | R6: =G6/'Feedstock Conversions'!$B$19 -> 9.4085906 | S6: =I6/'Feedstock Conversions'!$B$24 -> 15.123512 | T6: =I6/'Feedstock Conversions'!$B$23 -> 15.435905
A7: ='Soybean Oil'!A7 -> 43504 | B7: ='Soybean Oil'!W7 -> 39.265 | C7: ='Canola Oil'!M7 -> 13.1459 | D7: =BFT!W7 -> 87.755 | E7: =CWG!W7 -> 115.90596 | F7: =DCO!W7 -> 82.284 | G7: ='Poultry Fat'!W7 -> 70.794 | H7: =UCO!W7 -> 109 | I7: ='Yellow Grease'!W7 -> 127.7375 | K7: =I7-C7 -> 114.5916 | M7: =B7/'Feedstock Conversions'!$B$17 -> 5.2353333 | N7: =C7/'Feedstock Conversions'!$B$13 -> 1.7645503 | O7: =D7/'Feedstock Conversions'!$B$20 -> 11.323226 | P7: =E7/'Feedstock Conversions'!$B$21 -> 14.750059 | Q7: =F7/'Feedstock Conversions'!$B$14 -> 10.034634 | R7: =G7/'Feedstock Conversions'!$B$19 -> 9.5025503 | S7: =I7/'Feedstock Conversions'!$B$24 -> 15.206845 | T7: =I7/'Feedstock Conversions'!$B$23 -> 15.52096
A8: ='Soybean Oil'!A8 -> 43511 | B8: ='Soybean Oil'!W8 -> 48.5 | C8: ='Canola Oil'!M8 -> 21.154 | D8: =BFT!W8 -> 91.755 | E8: =CWG!W8 -> 120.29886 | F8: =DCO!W8 -> 89.564 | G8: ='Poultry Fat'!W8 -> 74.794 | H8: =UCO!W8 -> 113 | I8: ='Yellow Grease'!W8 -> 131.7375 | K8: =I8-C8 -> 110.5835 | M8: =B8/'Feedstock Conversions'!$B$17 -> 6.4666667 | N8: =C8/'Feedstock Conversions'!$B$13 -> 2.8394631 | O8: =D8/'Feedstock Conversions'!$B$20 -> 11.839355 | P8: =E8/'Feedstock Conversions'!$B$21 -> 15.309094 | Q8: =F8/'Feedstock Conversions'!$B$14 -> 10.922439 | R8: =G8/'Feedstock Conversions'!$B$19 -> 10.039463 | S8: =I8/'Feedstock Conversions'!$B$24 -> 15.683036 | T8: =I8/'Feedstock Conversions'!$B$23 -> 16.006987
A9: ='Soybean Oil'!A9 -> 43518 | B9: ='Soybean Oil'!W9 -> 50.0875 | C9: ='Canola Oil'!M9 -> 21.24625 | D9: =BFT!W9 -> 92.555 | E9: =CWG!W9 -> 123.40675 | F9: =DCO!W9 -> 95.284 | G9: ='Poultry Fat'!W9 -> 75.594 | H9: =UCO!W9 -> 113.8 | I9: ='Yellow Grease'!W9 -> 132.5375 | K9: =I9-C9 -> 111.29125 | M9: =B9/'Feedstock Conversions'!$B$17 -> 6.6783333 | N9: =C9/'Feedstock Conversions'!$B$13 -> 2.8518456 | O9: =D9/'Feedstock Conversions'!$B$20 -> 11.942581 | P9: =E9/'Feedstock Conversions'!$B$21 -> 15.704601 | Q9: =F9/'Feedstock Conversions'!$B$14 -> 11.62 | R9: =G9/'Feedstock Conversions'!$B$19 -> 10.146846 | S9: =I9/'Feedstock Conversions'!$B$24 -> 15.778274 | T9: =I9/'Feedstock Conversions'!$B$23 -> 16.104192
A10: ='Soybean Oil'!A10 -> 43525 | B10: ='Soybean Oil'!W10 -> 50.725 | C10: ='Canola Oil'!M10 -> 29.3295 | D10: =BFT!W10 -> 92.555 | E10: =CWG!W10 -> 124.24206 | F10: =DCO!W10 -> 96.309 | G10: ='Poultry Fat'!W10 -> 75.594 | H10: =UCO!W10 -> 113.8 | I10: ='Yellow Grease'!W10 -> 127.188 | K10: =I10-C10 -> 97.8585 | M10: =B10/'Feedstock Conversions'!$B$17 -> 6.7633333 | N10: =C10/'Feedstock Conversions'!$B$13 -> 3.9368456 | O10: =D10/'Feedstock Conversions'!$B$20 -> 11.942581 | P10: =E10/'Feedstock Conversions'!$B$21 -> 15.810901 | Q10: =F10/'Feedstock Conversions'!$B$14 -> 11.745 | R10: =G10/'Feedstock Conversions'!$B$19 -> 10.146846 | S10: =I10/'Feedstock Conversions'!$B$24 -> 15.141429 | T10: =I10/'Feedstock Conversions'!$B$23 -> 15.454192
A11: ='Soybean Oil'!A11 -> 43532 | B11: ='Soybean Oil'!W11 -> 53.2 | C11: ='Canola Oil'!M11 -> 31.192 | D11: =BFT!W11 -> 92.555 | E11: =CWG!W11 -> 127.77816 | F11: =DCO!W11 -> 97.949 | G11: ='Poultry Fat'!W11 -> 75.594 | H11: =UCO!W11 -> 112.12 | I11: ='Yellow Grease'!W11 -> 130.48 | K11: =I11-C11 -> 99.288 | M11: =B11/'Feedstock Conversions'!$B$17 -> 7.0933333 | N11: =C11/'Feedstock Conversions'!$B$13 -> 4.1868456 | O11: =D11/'Feedstock Conversions'!$B$20 -> 11.942581 | P11: =E11/'Feedstock Conversions'!$B$21 -> 16.260901 | Q11: =F11/'Feedstock Conversions'!$B$14 -> 11.945 | R11: =G11/'Feedstock Conversions'!$B$19 -> 10.146846 | S11: =I11/'Feedstock Conversions'!$B$24 -> 15.533333 | T11: =I11/'Feedstock Conversions'!$B$23 -> 15.854192
A12: ='Soybean Oil'!A12 -> 43539 | B12: ='Soybean Oil'!W12 -> 54.31 | C12: ='Canola Oil'!M12 -> 29.1656 | D12: =BFT!W12 -> 92.555 | E12: =CWG!W12 -> 132.88586 | F12: =DCO!W12 -> 97.334 | G12: ='Poultry Fat'!W12 -> 75.594 | H12: =UCO!W12 -> 111.7 | I12: ='Yellow Grease'!W12 -> 130.48 | K12: =I12-C12 -> 101.3144 | M12: =B12/'Feedstock Conversions'!$B$17 -> 7.2413333 | N12: =C12/'Feedstock Conversions'!$B$13 -> 3.9148456 | O12: =D12/'Feedstock Conversions'!$B$20 -> 11.942581 | P12: =E12/'Feedstock Conversions'!$B$21 -> 16.910901 | Q12: =F12/'Feedstock Conversions'!$B$14 -> 11.87 | R12: =G12/'Feedstock Conversions'!$B$19 -> 10.146846 | S12: =I12/'Feedstock Conversions'!$B$24 -> 15.533333 | T12: =I12/'Feedstock Conversions'!$B$23 -> 15.854192
A13: ='Soybean Oil'!A13 -> 43546 | B13: ='Soybean Oil'!W13 -> 58.585 | C13: ='Canola Oil'!M13 -> 32.6671 | D13: =BFT!W13 -> 92.555 | E13: =CWG!W13 -> 136.02906 | F13: =DCO!W13 -> 97.334 | G13: ='Poultry Fat'!W13 -> 75.594 | H13: =UCO!W13 -> 111.7 | I13: ='Yellow Grease'!W13 -> 130.48 | K13: =I13-C13 -> 97.8129 | M13: =B13/'Feedstock Conversions'!$B$17 -> 7.8113333 | N13: =C13/'Feedstock Conversions'!$B$13 -> 4.3848456 | O13: =D13/'Feedstock Conversions'!$B$20 -> 11.942581 | P13: =E13/'Feedstock Conversions'!$B$21 -> 17.310901 | Q13: =F13/'Feedstock Conversions'!$B$14 -> 11.87 | R13: =G13/'Feedstock Conversions'!$B$19 -> 10.146846 | S13: =I13/'Feedstock Conversions'!$B$24 -> 15.533333 | T13: =I13/'Feedstock Conversions'!$B$23 -> 15.854192
... A221: ='Soybean Oil'!A221 -> 45002 | B221: ='Soybean Oil'!W221 -> 89.276719 | C221: ='Canola Oil'!M221 -> 101.4757 | D221: =BFT!W221 -> 176.20694 | E221: =CWG!W221 -> 213.03244 | F221: =DCO!W221 -> 167.19735 | G221: ='Poultry Fat'!W221 -> 138.09167 | H221: =UCO!W221 -> 251.12 | I221: ='Yellow Grease'!W221 -> 282.756 | K221: =I221-C221 -> 181.2803 | M221: =B221/'Feedstock Conversions'!$B$17 -> 11.903563 | N221: =C221/'Feedstock Conversions'!$B$13 -> 13.620899 | O221: =D221/'Feedstock Conversions'!$B$20 -> 22.73638 | P221: =E221/'Feedstock Conversions'!$B$21 -> 27.110262 | Q221: =F221/'Feedstock Conversions'!$B$14 -> 20.38992 | R221: =G221/'Feedstock Conversions'!$B$19 -> 18.535795 | S221: =I221/'Feedstock Conversions'!$B$24 -> 33.661429 | T221: =I221/'Feedstock Conversions'!$B$23 -> 34.356744
A222: ='Soybean Oil'!A222 -> 45009 | B222: ='Soybean Oil'!W222 -> 88.541719 | C222: ='Canola Oil'!M222 -> 106.2531 | D222: =BFT!W222 -> 171.95694 | E222: =CWG!W222 -> 213.60524 | F222: =DCO!W222 -> 169.54735 | G222: ='Poultry Fat'!W222 -> 129.35105 | H222: =UCO!W222 -> 274.4 | I222: ='Yellow Grease'!W222 -> 281.455 | K222: =I222-C222 -> 175.2019 | M222: =B222/'Feedstock Conversions'!$B$17 -> 11.805563 | N222: =C222/'Feedstock Conversions'!$B$13 -> 14.262161 | O222: =D222/'Feedstock Conversions'!$B$20 -> 22.187993 | P222: =E222/'Feedstock Conversions'!$B$21 -> 27.183156 | Q222: =F222/'Feedstock Conversions'!$B$14 -> 20.676506 | R222: =G222/'Feedstock Conversions'!$B$19 -> 17.362557 | S222: =I222/'Feedstock Conversions'!$B$24 -> 33.506548 | T222: =I222/'Feedstock Conversions'!$B$23 -> 34.198663 | V222: =D236/D223-1 -> -0.72185673 | W222: =E236/E223-1 -> -0.50680734 | X222: =F236/F223-1 -> -0.80323066 | Y222: =G236/G223-1 -> -0.24088938 | Z222: =H236/H223-1 -> -0.51216216 | AA222: =I236/I223-1 -> -0.23290852
A223: ='Soybean Oil'!A223 -> 45016 | B223: ='Soybean Oil'!W223 -> 73.746719 | C223: ='Canola Oil'!M223 -> 98.2084 | D223: =BFT!W223 -> 180.23194 | E223: =CWG!W223 -> 214.24904 | F223: =DCO!W223 -> 178.76735 | G223: ='Poultry Fat'!W223 -> 131.12917 | H223: =UCO!W223 -> 266.4 | I223: ='Yellow Grease'!W223 -> 273.455 | K223: =I223-C223 -> 175.2466 | M223: =B223/'Feedstock Conversions'!$B$17 -> 9.8328959 | N223: =C223/'Feedstock Conversions'!$B$13 -> 13.182336 | O223: =D223/'Feedstock Conversions'!$B$20 -> 23.255735 | P223: =E223/'Feedstock Conversions'!$B$21 -> 27.265085 | Q223: =F223/'Feedstock Conversions'!$B$14 -> 21.800896 | R223: =G223/'Feedstock Conversions'!$B$19 -> 17.601231 | S223: =I223/'Feedstock Conversions'!$B$24 -> 32.554167 | T223: =I223/'Feedstock Conversions'!$B$23 -> 33.22661
A224: ='Soybean Oil'!A224 -> 45023 | B224: ='Soybean Oil'!W224 -> 66.275091 | C224: ='Canola Oil'!M224 -> 91.933375 | D224: =BFT!W224 -> 180.1053 | E224: =CWG!W224 -> 208.441 | F224: =DCO!W224 -> 155.95093 | G224: ='Poultry Fat'!W224 -> 129.37592 | H224: =UCO!W224 -> 265.15 | I224: ='Yellow Grease'!W224 -> 272.205 | K224: =I224-C224 -> 180.27163 | M224: =B224/'Feedstock Conversions'!$B$17 -> 8.8366788 | N224: =C224/'Feedstock Conversions'!$B$13 -> 12.34005 | O224: =D224/'Feedstock Conversions'!$B$20 -> 23.239394 | P224: =E224/'Feedstock Conversions'!$B$21 -> 26.525961 | Q224: =F224/'Feedstock Conversions'!$B$14 -> 19.018406 | R224: =G224/'Feedstock Conversions'!$B$19 -> 17.365896 | S224: =I224/'Feedstock Conversions'!$B$24 -> 32.405357 | T224: =I224/'Feedstock Conversions'!$B$23 -> 33.074727
A225: ='Soybean Oil'!A225 -> 45030 | B225: ='Soybean Oil'!W225 -> 68.093841 | C225: ='Canola Oil'!M225 -> 95.5575 | D225: =BFT!W225 -> 173.3553 | E225: =CWG!W225 -> 192.45785 | F225: =DCO!W225 -> 124.39593 | G225: ='Poultry Fat'!W225 -> 127.56155 | H225: =UCO!W225 -> 253.36 | I225: ='Yellow Grease'!W225 -> 265.455 | K225: =I225-C225 -> 169.8975 | M225: =B225/'Feedstock Conversions'!$B$17 -> 9.0791788 | N225: =C225/'Feedstock Conversions'!$B$13 -> 12.82651 | O225: =D225/'Feedstock Conversions'!$B$20 -> 22.368426 | P225: =E225/'Feedstock Conversions'!$B$21 -> 24.491964 | Q225: =F225/'Feedstock Conversions'!$B$14 -> 15.170236 | R225: =G225/'Feedstock Conversions'!$B$19 -> 17.122356 | S225: =I225/'Feedstock Conversions'!$B$24 -> 31.601786 | T225: =I225/'Feedstock Conversions'!$B$23 -> 32.254557
A226: ='Soybean Oil'!A226 -> 45037 | B226: ='Soybean Oil'!W226 -> 63.048841 | C226: ='Canola Oil'!M226 -> 83.0828 | D226: =BFT!W226 -> 155.8553 | E226: =CWG!W226 -> 178.67085 | F226: =DCO!W226 -> 115.01593 | G226: ='Poultry Fat'!W226 -> 128.54155 | H226: =UCO!W226 -> 245.48 | I226: ='Yellow Grease'!W226 -> 263.455 | K226: =I226-C226 -> 180.3722 | M226: =B226/'Feedstock Conversions'!$B$17 -> 8.4065121 | N226: =C226/'Feedstock Conversions'!$B$13 -> 11.152054 | O226: =D226/'Feedstock Conversions'!$B$20 -> 20.110362 | P226: =E226/'Feedstock Conversions'!$B$21 -> 22.737446 | Q226: =F226/'Feedstock Conversions'!$B$14 -> 14.026333 | R226: =G226/'Feedstock Conversions'!$B$19 -> 17.253899 | S226: =I226/'Feedstock Conversions'!$B$24 -> 31.36369 | T226: =I226/'Feedstock Conversions'!$B$23 -> 32.011543
A227: ='Soybean Oil'!A227 -> 45044 | B227: ='Soybean Oil'!W227 -> 76.983841 | C227: ='Canola Oil'!M227 -> 95.0024 | D227: =BFT!W227 -> 122.8303 | E227: =CWG!W227 -> 164.56315 | F227: =DCO!W227 -> 102.73593 | G227: ='Poultry Fat'!W227 -> 119.54155 | H227: =UCO!W227 -> 235.64 | I227: ='Yellow Grease'!W227 -> 254.455 | K227: =I227-C227 -> 159.4526 | M227: =B227/'Feedstock Conversions'!$B$17 -> 10.264512 | N227: =C227/'Feedstock Conversions'!$B$13 -> 12.752 | O227: =D227/'Feedstock Conversions'!$B$20 -> 15.849071 | P227: =E227/'Feedstock Conversions'!$B$21 -> 20.942117 | Q227: =F227/'Feedstock Conversions'!$B$14 -> 12.528772 | R227: =G227/'Feedstock Conversions'!$B$19 -> 16.045845 | S227: =I227/'Feedstock Conversions'!$B$24 -> 30.292262 | T227: =I227/'Feedstock Conversions'!$B$23 -> 30.917983
A228: ='Soybean Oil'!A228 -> 45051 | B228: ='Soybean Oil'!W228 -> 62.268841 | C228: ='Canola Oil'!M228 -> 82.5805 | D228: =BFT!W228 -> 113.7303 | E228: =CWG!W228 -> 149.52645 | F228: =DCO!W228 -> 94.275933 | G228: ='Poultry Fat'!W228 -> 113.54155 | H228: =UCO!W228 -> 216.2 | I228: ='Yellow Grease'!W228 -> 243.517 | K228: =I228-C228 -> 160.9365 | M228: =B228/'Feedstock Conversions'!$B$17 -> 8.3025121 | N228: =C228/'Feedstock Conversions'!$B$13 -> 11.084631 | O228: =D228/'Feedstock Conversions'!$B$20 -> 14.674878 | P228: =E228/'Feedstock Conversions'!$B$21 -> 19.028564 | Q228: =F228/'Feedstock Conversions'!$B$14 -> 11.497065 | R228: =G228/'Feedstock Conversions'!$B$19 -> 15.240476 | S228: =I228/'Feedstock Conversions'!$B$24 -> 28.990119 | T228: =I228/'Feedstock Conversions'!$B$23 -> 29.588943
A229: ='Soybean Oil'!A229 -> 45058 | B229: ='Soybean Oil'!W229 -> 64.178841 | C229: ='Canola Oil'!M229 -> 91.2041 | D229: =BFT!W229 -> 115.3803 | E229: =CWG!W229 -> 140.15365 | F229: =DCO!W229 -> 84.355933 | G229: ='Poultry Fat'!W229 -> 116.74155 | H229: =UCO!W229 -> 211 | I229: ='Yellow Grease'!W229 -> 243.425 | K229: =I229-C229 -> 152.2209 | M229: =B229/'Feedstock Conversions'!$B$17 -> 8.5571788 | N229: =C229/'Feedstock Conversions'!$B$13 -> 12.242161 | O229: =D229/'Feedstock Conversions'!$B$20 -> 14.887781 | P229: =E229/'Feedstock Conversions'!$B$21 -> 17.835792 | Q229: =F229/'Feedstock Conversions'!$B$14 -> 10.287309 | R229: =G229/'Feedstock Conversions'!$B$19 -> 15.670007 | S229: =I229/'Feedstock Conversions'!$B$24 -> 28.979167 | T229: =I229/'Feedstock Conversions'!$B$23 -> 29.577764
A230: ='Soybean Oil'!A230 -> 45065 | B230: ='Soybean Oil'!W230 -> 102.42884 | C230: ='Canola Oil'!M230 -> 121.7811 | D230: =BFT!W230 -> 117.8553 | E230: =CWG!W230 -> 142.59625 | F230: =DCO!W230 -> 92.435933 | G230: ='Poultry Fat'!W230 -> 121.54155 | H230: =UCO!W230 -> 215.8 | I230: ='Yellow Grease'!W230 -> 248.225 | K230: =I230-C230 -> 126.4439 | M230: =B230/'Feedstock Conversions'!$B$17 -> 13.657179 | N230: =C230/'Feedstock Conversions'!$B$13 -> 16.346456 | O230: =D230/'Feedstock Conversions'!$B$20 -> 15.207136 | P230: =E230/'Feedstock Conversions'!$B$21 -> 18.146634 | Q230: =F230/'Feedstock Conversions'!$B$14 -> 11.272675 | R230: =G230/'Feedstock Conversions'!$B$19 -> 16.314302 | S230: =I230/'Feedstock Conversions'!$B$24 -> 29.550595 | T230: =I230/'Feedstock Conversions'!$B$23 -> 30.160996
A231: ='Soybean Oil'!A231 -> 45072 | B231: ='Soybean Oil'!W231 -> 90.038841 | C231: ='Canola Oil'!M231 -> 114.6887 | D231: =BFT!W231 -> 117.8553 | E231: =CWG!W231 -> 142.59625 | F231: =DCO!W231 -> 102.27593 | G231: ='Poultry Fat'!W231 -> 121.54155 | H231: =UCO!W231 -> 215.8 | I231: ='Yellow Grease'!W231 -> 248.225 | K231: =I231-C231 -> 133.5363 | M231: =B231/'Feedstock Conversions'!$B$17 -> 12.005179 | N231: =C231/'Feedstock Conversions'!$B$13 -> 15.394456 | O231: =D231/'Feedstock Conversions'!$B$20 -> 15.207136 | P231: =E231/'Feedstock Conversions'!$B$21 -> 18.146634 | Q231: =F231/'Feedstock Conversions'!$B$14 -> 12.472675 | R231: =G231/'Feedstock Conversions'!$B$19 -> 16.314302 | S231: =I231/'Feedstock Conversions'!$B$24 -> 29.550595 | T231: =I231/'Feedstock Conversions'!$B$23 -> 30.160996
A232: 45079 | B232: ='Soybean Oil'!W232 -> 79.043841 | C232: ='Canola Oil'!M232 -> 111.897 | D232: =BFT!W232 -> 108.1053 | E232: =CWG!W232 -> 135.793 | F232: =DCO!W232 -> 92.525933 | G232: ='Poultry Fat'!W232 -> 111.79155 | H232: =UCO!W232 -> 206.05 | I232: ='Yellow Grease'!W232 -> 238.475 | K232: =I232-C232 -> 126.578 | M232: =B232/'Feedstock Conversions'!$B$17 -> 10.539179 | N232: =C232/'Feedstock Conversions'!$B$13 -> 15.019732 | O232: =D232/'Feedstock Conversions'!$B$20 -> 13.949071 | P232: =E232/'Feedstock Conversions'!$B$21 -> 17.280861 | Q232: =F232/'Feedstock Conversions'!$B$14 -> 11.28365 | R232: =G232/'Feedstock Conversions'!$B$19 -> 15.005577 | S232: =I232/'Feedstock Conversions'!$B$24 -> 28.389881 | T232: =I232/'Feedstock Conversions'!$B$23 -> 28.976306
A233: 45086 | B233: ='Soybean Oil'!W233 -> 40.733841 | C233: ='Canola Oil'!M233 -> 61.1424 | D233: =BFT!W233 -> 106.7303 | E233: =CWG!W233 -> 128.38205 | F233: =DCO!W233 -> 77.435933 | G233: ='Poultry Fat'!W233 -> 106.54155 | H233: =UCO!W233 -> 200.8 | I233: ='Yellow Grease'!W233 -> 233.225 | K233: =I233-C233 -> 172.0826 | M233: =B233/'Feedstock Conversions'!$B$17 -> 5.4311788 | N233: =C233/'Feedstock Conversions'!$B$13 -> 8.2070336 | O233: =D233/'Feedstock Conversions'!$B$20 -> 13.771652 | P233: =E233/'Feedstock Conversions'!$B$21 -> 16.337752 | Q233: =F233/'Feedstock Conversions'!$B$14 -> 9.4434064 | R233: =G233/'Feedstock Conversions'!$B$19 -> 14.300879 | S233: =I233/'Feedstock Conversions'!$B$24 -> 27.764881 | T233: =I233/'Feedstock Conversions'!$B$23 -> 28.338396
A234: 45093 | B234: ='Soybean Oil'!W234 -> -9.891159 | C234: ='Canola Oil'!M234 -> 13.0699 | D234: =BFT!W234 -> 85.130302 | E234: =CWG!W234 -> 117.13115 | F234: =DCO!W234 -> 46.965933 | G234: ='Poultry Fat'!W234 -> 103.54155 | H234: =UCO!W234 -> 157.48 | I234: ='Yellow Grease'!W234 -> 223.641 | K234: =I234-C234 -> 210.5711 | M234: =B234/'Feedstock Conversions'!$B$17 -> -1.3188212 | N234: =C234/'Feedstock Conversions'!$B$13 -> 1.754349 | O234: =D234/'Feedstock Conversions'!$B$20 -> 10.984555 | P234: =E234/'Feedstock Conversions'!$B$21 -> 14.905975 | Q234: =F234/'Feedstock Conversions'!$B$14 -> 5.7275528 | R234: =G234/'Feedstock Conversions'!$B$19 -> 13.898194 | S234: =I234/'Feedstock Conversions'!$B$24 -> 26.623929 | T234: =I234/'Feedstock Conversions'!$B$23 -> 27.173876
A235: 45100 | B235: ='Soybean Oil'!W235 -> -12.568659 | C235: ='Canola Oil'!M235 -> -2.906625 | D235: =BFT!W235 -> 72.730302 | E235: =CWG!W235 -> 116.73825 | F235: =DCO!W235 -> 38.150933 | G235: ='Poultry Fat'!W235 -> 103.54155 | H235: =UCO!W235 -> 122.2 | I235: ='Yellow Grease'!W235 -> 213.765 | K235: =I235-C235 -> 216.67163 | M235: =B235/'Feedstock Conversions'!$B$17 -> -1.6758212 | N235: =C235/'Feedstock Conversions'!$B$13 -> -0.39015101 | O235: =D235/'Feedstock Conversions'!$B$20 -> 9.3845551 | P235: =E235/'Feedstock Conversions'!$B$21 -> 14.855975 | Q235: =F235/'Feedstock Conversions'!$B$14 -> 4.6525528 | R235: =G235/'Feedstock Conversions'!$B$19 -> 13.898194 | S235: =I235/'Feedstock Conversions'!$B$24 -> 25.448214 | T235: =I235/'Feedstock Conversions'!$B$23 -> 25.973876
A236: 45107 | B236: ='Soybean Oil'!W236 -> -46.936159 | C236: ='Canola Oil'!M236 -> -35.6748 | D236: =BFT!W236 -> 50.130302 | E236: =CWG!W236 -> 105.66605 | F236: =DCO!W236 -> 35.175933 | G236: ='Poultry Fat'!W236 -> 99.541549 | H236: =UCO!W236 -> 129.96 | I236: ='Yellow Grease'!W236 -> 209.765 | K236: =I236-C236 -> 245.4398 | M236: =B236/'Feedstock Conversions'!$B$17 -> -6.2581545 | N236: =C236/'Feedstock Conversions'!$B$13 -> -4.7885638 | O236: =D236/'Feedstock Conversions'!$B$20 -> 6.4684261 | P236: =E236/'Feedstock Conversions'!$B$21 -> 13.44694 | Q236: =F236/'Feedstock Conversions'!$B$14 -> 4.2897479 | R236: =G236/'Feedstock Conversions'!$B$19 -> 13.361282 | S236: =I236/'Feedstock Conversions'!$B$24 -> 24.972024 | T236: =I236/'Feedstock Conversions'!$B$23 -> 25.487849
A237: 45114 | B237: ='Soybean Oil'!W237 -> -67.874909 | C237: ='Canola Oil'!M237 -> -56.490625 | D237: =BFT!W237 -> 39.105302 | E237: =CWG!W237 -> 94.522254 | F237: =DCO!W237 -> 16.275933 | G237: ='Poultry Fat'!W237 -> 97.041549 | H237: =UCO!W237 -> 145.1 | I237: ='Yellow Grease'!W237 -> 207.265 | K237: =I237-C237 -> 263.75563 | M237: =B237/'Feedstock Conversions'!$B$17 -> -9.0499879 | N237: =C237/'Feedstock Conversions'!$B$13 -> -7.5826342 | O237: =D237/'Feedstock Conversions'!$B$20 -> 5.0458455 | P237: =E237/'Feedstock Conversions'!$B$21 -> 12.028793 | Q237: =F237/'Feedstock Conversions'!$B$14 -> 1.9848699 | R237: =G237/'Feedstock Conversions'!$B$19 -> 13.025711 | S237: =I237/'Feedstock Conversions'!$B$24 -> 24.674405 | T237: =I237/'Feedstock Conversions'!$B$23 -> 25.184083
A238: =A237+7 -> 45121 | B238: ='Soybean Oil'!W238 -> -78.716159 | C238: ='Canola Oil'!M238 -> -64.2596 | D238: =BFT!W238 -> 30.480302 | E238: =CWG!W238 -> 77.091454 | F238: =DCO!W238 -> -21.314067 | G238: ='Poultry Fat'!W238 -> 94.081549 | H238: =UCO!W238 -> 144.74 | I238: ='Yellow Grease'!W238 -> 202.035 | K238: =I238-C238 -> 266.2946 | M238: =B238/'Feedstock Conversions'!$B$17 -> -10.495488 | N238: =C238/'Feedstock Conversions'!$B$13 -> -8.6254497 | O238: =D238/'Feedstock Conversions'!$B$20 -> 3.9329422 | P238: =E238/'Feedstock Conversions'!$B$21 -> 9.8105693 | Q238: =F238/'Feedstock Conversions'!$B$14 -> -2.5992765 | R238: =G238/'Feedstock Conversions'!$B$19 -> 12.628396 | S238: =I238/'Feedstock Conversions'!$B$24 -> 24.051786 | T238: =I238/'Feedstock Conversions'!$B$23 -> 24.548603
A239: =A238+7 -> 45128 | B239: ='Soybean Oil'!W239 -> -88.756159 | C239: ='Canola Oil'!M239 -> -73.481 | D239: =BFT!W239 -> 19.080302 | E239: =CWG!W239 -> 62.375454 | F239: =DCO!W239 -> -28.924067 | G239: ='Poultry Fat'!W239 -> 87.631549 | H239: =UCO!W239 -> 137.34 | I239: ='Yellow Grease'!W239 -> 190.69 | K239: =I239-C239 -> 264.171 | M239: =B239/'Feedstock Conversions'!$B$17 -> -11.834155 | N239: =C239/'Feedstock Conversions'!$B$13 -> -9.8632215 | O239: =D239/'Feedstock Conversions'!$B$20 -> 2.4619745 | P239: =E239/'Feedstock Conversions'!$B$21 -> 7.9378282 | Q239: =F239/'Feedstock Conversions'!$B$14 -> -3.5273253 | R239: =G239/'Feedstock Conversions'!$B$19 -> 11.762624 | S239: =I239/'Feedstock Conversions'!$B$24 -> 22.70119 | T239: =I239/'Feedstock Conversions'!$B$23 -> 23.170109
A240: =A239+7 -> 45135 | B240: ='Soybean Oil'!W240 -> -61.951159 | C240: ='Canola Oil'!M240 -> -46.4847 | D240: =BFT!W240 -> 71.480302 | E240: =CWG!W240 -> 105.69555 | F240: =DCO!W240 -> 24.115933 | G240: ='Poultry Fat'!W240 -> 141.64155 | H240: =UCO!W240 -> 187.8 | I240: ='Yellow Grease'!W240 -> 246.19 | K240: =I240-C240 -> 292.6747 | M240: =B240/'Feedstock Conversions'!$B$17 -> -8.2601545 | N240: =C240/'Feedstock Conversions'!$B$13 -> -6.239557 | O240: =D240/'Feedstock Conversions'!$B$20 -> 9.2232648 | P240: =E240/'Feedstock Conversions'!$B$21 -> 13.450694 | Q240: =F240/'Feedstock Conversions'!$B$14 -> 2.9409674 | R240: =G240/'Feedstock Conversions'!$B$19 -> 19.012288 | S240: =I240/'Feedstock Conversions'!$B$24 -> 29.308333 | T240: =I240/'Feedstock Conversions'!$B$23 -> 29.91373
A241: =A240+7 -> 45142 | B241: ='Soybean Oil'!W241 -> 30.503841 | C241: ='Canola Oil'!M241 -> 30.7006 | D241: =BFT!W241 -> 108.4803 | E241: =CWG!W241 -> 132.08725 | F241: =DCO!W241 -> 62.755933 | G241: ='Poultry Fat'!W241 -> 178.64155 | H241: =UCO!W241 -> 224.8 | I241: ='Yellow Grease'!W241 -> 283.19 | K241: =I241-C241 -> 252.4894 | M241: =B241/'Feedstock Conversions'!$B$17 -> 4.0671788 | N241: =C241/'Feedstock Conversions'!$B$13 -> 4.1208859 | O241: =D241/'Feedstock Conversions'!$B$20 -> 13.997458 | P241: =E241/'Feedstock Conversions'!$B$21 -> 16.809271 | Q241: =F241/'Feedstock Conversions'!$B$14 -> 7.6531625 | R241: =G241/'Feedstock Conversions'!$B$19 -> 23.978731 | S241: =I241/'Feedstock Conversions'!$B$24 -> 33.713095 | T241: =I241/'Feedstock Conversions'!$B$23 -> 34.409478
A242: =A241+7 -> 45149 | B242: ='Soybean Oil'!W242 -> 40.973841 | C242: ='Canola Oil'!M242 -> 53.7858 | D242: =BFT!W242 -> 105.2803 | E242: =CWG!W242 -> 131.15825 | F242: =DCO!W242 -> 69.035933 | G242: ='Poultry Fat'!W242 -> 181.64155 | H242: =UCO!W242 -> 227.8 | I242: ='Yellow Grease'!W242 -> 286.19 | K242: =I242-C242 -> 232.4042 | M242: =B242/'Feedstock Conversions'!$B$17 -> 5.4631788 | N242: =C242/'Feedstock Conversions'!$B$13 -> 7.2195705 | O242: =D242/'Feedstock Conversions'!$B$20 -> 13.584555 | P242: =E242/'Feedstock Conversions'!$B$21 -> 16.691048 | Q242: =F242/'Feedstock Conversions'!$B$14 -> 8.4190162 | R242: =G242/'Feedstock Conversions'!$B$19 -> 24.381416 | S242: =I242/'Feedstock Conversions'!$B$24 -> 34.070238 | T242: =I242/'Feedstock Conversions'!$B$23 -> 34.773998
A243: =A242+7 -> 45156 | B243: ='Soybean Oil'!W243 -> 11.563841 | C243: ='Canola Oil'!M243 -> 18.1327 | D243: =BFT!W243 -> 83.080302 | E243: =CWG!W243 -> 109.65765 | F243: =DCO!W243 -> 51.395933 | G243: ='Poultry Fat'!W243 -> 165.64155 | H243: =UCO!W243 -> 211.8 | I243: ='Yellow Grease'!W243 -> 270.19 | K243: =I243-C243 -> 252.0573 | M243: =B243/'Feedstock Conversions'!$B$17 -> 1.5418455 | N243: =C243/'Feedstock Conversions'!$B$13 -> 2.4339195 | O243: =D243/'Feedstock Conversions'!$B$20 -> 10.720039 | P243: =E243/'Feedstock Conversions'!$B$21 -> 13.954906 | Q243: =F243/'Feedstock Conversions'!$B$14 -> 6.2677967 | R243: =G243/'Feedstock Conversions'!$B$19 -> 22.233765 | S243: =I243/'Feedstock Conversions'!$B$24 -> 32.165476 | T243: =I243/'Feedstock Conversions'!$B$23 -> 32.829891
A244: =A243+7 -> 45163 | B244: ='Soybean Oil'!W244 -> 1.663841 | C244: ='Canola Oil'!M244 -> 13.8062 | D244: =BFT!W244 -> 67.980302 | E244: =CWG!W244 -> 95.300254 | F244: =DCO!W244 -> 38.575933 | G244: ='Poultry Fat'!W244 -> 153.64155 | H244: =UCO!W244 -> 199.8 | I244: ='Yellow Grease'!W244 -> 258.19 | K244: =I244-C244 -> 244.3838 | M244: =B244/'Feedstock Conversions'!$B$17 -> 0.22184546 | N244: =C244/'Feedstock Conversions'!$B$13 -> 1.8531812 | O244: =D244/'Feedstock Conversions'!$B$20 -> 8.7716519 | P244: =E244/'Feedstock Conversions'!$B$21 -> 12.1278 | Q244: =F244/'Feedstock Conversions'!$B$14 -> 4.7043821 | R244: =G244/'Feedstock Conversions'!$B$19 -> 20.623027 | S244: =I244/'Feedstock Conversions'!$B$24 -> 30.736905 | T244: =I244/'Feedstock Conversions'!$B$23 -> 31.37181
A245: =A244+7 -> 45170 | B245: ='Soybean Oil'!W245 -> 6.688841 | C245: ='Canola Oil'!M245 -> 20.2877 | D245: =BFT!W245 -> 67.980302 | E245: =CWG!W245 -> 93.728654 | F245: =DCO!W245 -> 47.595933 | G245: ='Poultry Fat'!W245 -> 153.64155 | H245: =UCO!W245 -> 199.8 | I245: ='Yellow Grease'!W245 -> 258.19 | K245: =I245-C245 -> 237.9023 | M245: =B245/'Feedstock Conversions'!$B$17 -> 0.89184546 | N245: =C245/'Feedstock Conversions'!$B$13 -> 2.7231812 | O245: =D245/'Feedstock Conversions'!$B$20 -> 8.7716519 | P245: =E245/'Feedstock Conversions'!$B$21 -> 11.9278 | Q245: =F245/'Feedstock Conversions'!$B$14 -> 5.8043821 | R245: =G245/'Feedstock Conversions'!$B$19 -> 20.623027 | S245: =I245/'Feedstock Conversions'!$B$24 -> 30.736905 | T245: =I245/'Feedstock Conversions'!$B$23 -> 31.37181
A246: =A245+7 -> 45177 | B246: ='Soybean Oil'!W246 -> 29.237591 | C246: ='Canola Oil'!M246 -> 44.176125 | D246: =BFT!W246 -> 67.980302 | E246: =CWG!W246 -> 88.424504 | F246: =DCO!W246 -> 54.975933 | G246: ='Poultry Fat'!W246 -> 153.64155 | H246: =UCO!W246 -> 199.8 | I246: ='Yellow Grease'!W246 -> 258.19 | K246: =I246-C246 -> 214.01387 | M246: =B246/'Feedstock Conversions'!$B$17 -> 3.8983455 | N246: =C246/'Feedstock Conversions'!$B$13 -> 5.9296812 | O246: =D246/'Feedstock Conversions'!$B$20 -> 8.7716519 | P246: =E246/'Feedstock Conversions'!$B$21 -> 11.2528 | Q246: =F246/'Feedstock Conversions'!$B$14 -> 6.7043821 | R246: =G246/'Feedstock Conversions'!$B$19 -> 20.623027 | S246: =I246/'Feedstock Conversions'!$B$24 -> 30.736905 | T246: =I246/'Feedstock Conversions'!$B$23 -> 31.37181
A247: =A246+7 -> 45184 | B247: ='Soybean Oil'!W247 -> 37.638841 | C247: ='Canola Oil'!M247 -> 56.2597 | D247: =BFT!W247 -> 67.655302 | E247: =CWG!W247 -> 86.299054 | F247: =DCO!W247 -> 54.515933 | G247: ='Poultry Fat'!W247 -> 155.64155 | H247: =UCO!W247 -> 192.56 | I247: ='Yellow Grease'!W247 -> 253.606 | K247: =I247-C247 -> 197.3463 | M247: =B247/'Feedstock Conversions'!$B$17 -> 5.0185121 | N247: =C247/'Feedstock Conversions'!$B$13 -> 7.5516376 | O247: =D247/'Feedstock Conversions'!$B$20 -> 8.7297164 | P247: =E247/'Feedstock Conversions'!$B$21 -> 10.982318 | Q247: =F247/'Feedstock Conversions'!$B$14 -> 6.6482845 | R247: =G247/'Feedstock Conversions'!$B$19 -> 20.891483 | S247: =I247/'Feedstock Conversions'!$B$24 -> 30.19119 | T247: =I247/'Feedstock Conversions'!$B$23 -> 30.814824
A248: =A247+7 -> 45191 | B248: ='Soybean Oil'!W248 -> 49.473841 | C248: ='Canola Oil'!M248 -> 64.1963 | D248: =BFT!W248 -> 63.105302 | E248: =CWG!W248 -> 77.798454 | F248: =DCO!W248 -> 49.875933 | G248: ='Poultry Fat'!W248 -> 152.64155 | H248: =UCO!W248 -> 182 | I248: ='Yellow Grease'!W248 -> 235.792 | K248: =I248-C248 -> 171.5957 | M248: =B248/'Feedstock Conversions'!$B$17 -> 6.5965121 | N248: =C248/'Feedstock Conversions'!$B$13 -> 8.616953 | O248: =D248/'Feedstock Conversions'!$B$20 -> 8.1426197 | P248: =E248/'Feedstock Conversions'!$B$21 -> 9.9005413 | Q248: =F248/'Feedstock Conversions'!$B$14 -> 6.0824308 | R248: =G248/'Feedstock Conversions'!$B$19 -> 20.488798 | S248: =I248/'Feedstock Conversions'!$B$24 -> 28.070476 | T248: =I248/'Feedstock Conversions'!$B$23 -> 28.650304
A249: =A248+7 -> 45198 | B249: ='Soybean Oil'!W249 -> 56.558841 | C249: ='Canola Oil'!M249 -> 64.4969 | D249: =BFT!W249 -> 58.730302 | E249: =CWG!W249 -> 88.908554 | F249: =DCO!W249 -> 46.585933 | G249: ='Poultry Fat'!W249 -> 136.64155 | H249: =UCO!W249 -> 166 | I249: ='Yellow Grease'!W249 -> 216.5 | K249: =I249-C249 -> 152.0031 | M249: =B249/'Feedstock Conversions'!$B$17 -> 7.5411788 | N249: =C249/'Feedstock Conversions'!$B$13 -> 8.657302 | O249: =D249/'Feedstock Conversions'!$B$20 -> 7.5781035 | P249: =E249/'Feedstock Conversions'!$B$21 -> 11.3144 | Q249: =F249/'Feedstock Conversions'!$B$14 -> 5.6812113 | R249: =G249/'Feedstock Conversions'!$B$19 -> 18.341147 | S249: =I249/'Feedstock Conversions'!$B$24 -> 25.77381 | T249: =I249/'Feedstock Conversions'!$B$23 -> 26.306197
... A262: =A261+7 -> 45289 | B262: ='Soybean Oil'!W262 -> 62.909022 | C262: ='Canola Oil'!M262 -> 68.483125 | D262: =BFT!W262 -> 160.92036 | E262: =CWG!W262 -> 228.37646 | F262: =DCO!W262 -> 112.47703 | G262: ='Poultry Fat'!W262 -> 145.64925 | H262: =UCO!W262 -> 238.05 | I262: ='Yellow Grease'!W262 -> 260.545 | K262: =I262-C262 -> 192.06187 | M262: =B262/'Feedstock Conversions'!$B$17 -> 8.3878695 | N262: =C262/'Feedstock Conversions'!$B$13 -> 9.1923658 | O262: =D262/'Feedstock Conversions'!$B$20 -> 20.763918 | P262: =E262/'Feedstock Conversions'!$B$21 -> 29.062925 | Q262: =F262/'Feedstock Conversions'!$B$14 -> 13.716711 | R262: =G262/'Feedstock Conversions'!$B$19 -> 19.550235 | S262: =I262/'Feedstock Conversions'!$B$24 -> 31.017262 | T262: =I262/'Feedstock Conversions'!$B$23 -> 31.657959
A263: =A262+7 -> 45296 | B263: ='Soybean Oil'!W263 -> 64.603149 | C263: ='Canola Oil'!M263 -> 74.62725 | D263: =BFT!W263 -> 161.647 | E263: =CWG!W263 -> 234.0419 | F263: =DCO!W263 -> 98.968443 | G263: ='Poultry Fat'!W263 -> 148.16188 | H263: =UCO!W263 -> 248.35 | I263: ='Yellow Grease'!W263 -> 259.295 | J263: =B263*0.55+I263*0.1+F263*0.1+D263*0.05+C263*0.11+((E263*0.33+G263*0.33+H263*0.33)*0.09) -> 106.37687 | K263: =I263-C263 -> 184.66775 | M263: =B263/'Feedstock Conversions'!$B$17 -> 8.6137533 | N263: =C263/'Feedstock Conversions'!$B$13 -> 10.017081 | O263: =D263/'Feedstock Conversions'!$B$20 -> 20.857678 | P263: =E263/'Feedstock Conversions'!$B$21 -> 29.783902 | Q263: =F263/'Feedstock Conversions'!$B$14 -> 12.069322 | R263: =G263/'Feedstock Conversions'!$B$19 -> 19.8875 | S263: =I263/'Feedstock Conversions'!$B$24 -> 30.868452 | T263: =I263/'Feedstock Conversions'!$B$23 -> 31.506075 | U263: =M263*0.55+T263*0.1+Q263*0.1+O263*0.05+N263*0.11+((P263*0.33+R263*0.33+S263*0.33)*0.09) -> 13.631901
A264: =A263+7 -> 45303 | B264: ='Soybean Oil'!W264 -> 61.220649 | C264: ='Canola Oil'!M264 -> 69.3448 | D264: =BFT!W264 -> 161.947 | E264: =CWG!W264 -> 226.02415 | F264: =DCO!W264 -> 111.28844 | G264: ='Poultry Fat'!W264 -> 146.98438 | H264: =UCO!W264 -> 250.9 | I264: ='Yellow Grease'!W264 -> 267.578 | J264: =B264*0.55+I264*0.1+F264*0.1+D264*0.05+C264*0.11+((E264*0.33+G264*0.33+H264*0.33)*0.09) -> 105.81336 | K264: =I264-C264 -> 198.2332 | M264: =B264/'Feedstock Conversions'!$B$17 -> 8.1627533 | N264: =C264/'Feedstock Conversions'!$B$13 -> 9.3080268 | O264: =D264/'Feedstock Conversions'!$B$20 -> 20.896388 | P264: =E264/'Feedstock Conversions'!$B$21 -> 28.763572 | Q264: =F264/'Feedstock Conversions'!$B$14 -> 13.571761 | R264: =G264/'Feedstock Conversions'!$B$19 -> 19.729447 | S264: =I264/'Feedstock Conversions'!$B$24 -> 31.854524 | T264: =I264/'Feedstock Conversions'!$B$23 -> 32.512515 | U264: =M264*0.55+T264*0.1+Q264*0.1+O264*0.05+N264*0.11+((P264*0.33+R264*0.33+S264*0.33)*0.09) -> 13.552966
A265: =A264+7 -> 45310 | B265: ='Soybean Oil'!W265 -> 63.121899 | C265: ='Canola Oil'!M265 -> 70.262125 | D265: =BFT!W265 -> 162.147 | E265: =CWG!W265 -> 220.02415 | F265: =DCO!W265 -> 108.56844 | G265: ='Poultry Fat'!W265 -> 142.47438 | H265: =UCO!W265 -> 244.9 | I265: ='Yellow Grease'!W265 -> 273.1 | J265: =B265*0.55+I265*0.1+F265*0.1+D265*0.05+C265*0.11+((E265*0.33+G265*0.33+H265*0.33)*0.09) -> 106.75981 | K265: =I265-C265 -> 202.83788 | M265: =B265/'Feedstock Conversions'!$B$17 -> 8.4162533 | N265: =C265/'Feedstock Conversions'!$B$13 -> 9.4311577 | O265: =D265/'Feedstock Conversions'!$B$20 -> 20.922194 | P265: =E265/'Feedstock Conversions'!$B$21 -> 28.000019 | Q265: =F265/'Feedstock Conversions'!$B$14 -> 13.240054 | R265: =G265/'Feedstock Conversions'!$B$19 -> 19.124078 | S265: =I265/'Feedstock Conversions'!$B$24 -> 32.511905 | T265: =I265/'Feedstock Conversions'!$B$23 -> 33.183475 | U265: =M265*0.55+T265*0.1+Q265*0.1+O265*0.05+N265*0.11+((P265*0.33+R265*0.33+S265*0.33)*0.09) -> 13.720019
A266: =A265+7 -> 45317 | B266: ='Soybean Oil'!W266 -> 56.090649 | C266: ='Canola Oil'!M266 -> 63.7965 | D266: =BFT!W266 -> 156.147 | E266: =CWG!W266 -> 214.02415 | F266: =DCO!W266 -> 102.56844 | G266: ='Poultry Fat'!W266 -> 136.47438 | H266: =UCO!W266 -> 238.9 | I266: ='Yellow Grease'!W266 -> 267.1 | J266: =B266*0.55+I266*0.1+F266*0.1+D266*0.05+C266*0.11+((E266*0.33+G266*0.33+H266*0.33)*0.09) -> 100.1468 | K266: =I266-C266 -> 203.3035 | M266: =B266/'Feedstock Conversions'!$B$17 -> 7.4787533 | N266: =C266/'Feedstock Conversions'!$B$13 -> 8.5632886 | O266: =D266/'Feedstock Conversions'!$B$20 -> 20.148001 | P266: =E266/'Feedstock Conversions'!$B$21 -> 27.236466 | Q266: =F266/'Feedstock Conversions'!$B$14 -> 12.508347 | R266: =G266/'Feedstock Conversions'!$B$19 -> 18.318709 | S266: =I266/'Feedstock Conversions'!$B$24 -> 31.797619 | T266: =I266/'Feedstock Conversions'!$B$23 -> 32.454435 | U266: =M266*0.55+T266*0.1+Q266*0.1+O266*0.05+N266*0.11+((P266*0.33+R266*0.33+S266*0.33)*0.09) -> 12.856332
A267: =A266+7 -> 45324 | B267: ='Soybean Oil'!W267 -> 66.340649 | C267: ='Canola Oil'!M267 -> 79.539 | D267: =BFT!W267 -> 161.447 | E267: =CWG!W267 -> 211.59575 | F267: =DCO!W267 -> 101.02844 | G267: ='Poultry Fat'!W267 -> 132.47438 | H267: =UCO!W267 -> 234.9 | I267: ='Yellow Grease'!W267 -> 263.1 | J267: =B267*0.55+I267*0.1+F267*0.1+D267*0.05+C267*0.11+((E267*0.33+G267*0.33+H267*0.33)*0.09) -> 106.91725 | K267: =I267-C267 -> 183.561 | M267: =B267/'Feedstock Conversions'!$B$17 -> 8.8454199 | N267: =C267/'Feedstock Conversions'!$B$13 -> 10.676376 | O267: =D267/'Feedstock Conversions'!$B$20 -> 20.831872 | P267: =E267/'Feedstock Conversions'!$B$21 -> 26.927431 | Q267: =F267/'Feedstock Conversions'!$B$14 -> 12.320542 | R267: =G267/'Feedstock Conversions'!$B$19 -> 17.781796 | S267: =I267/'Feedstock Conversions'!$B$24 -> 31.321429 | T267: =I267/'Feedstock Conversions'!$B$23 -> 31.968408 | U267: =M267*0.55+T267*0.1+Q267*0.1+O267*0.05+N267*0.11+((P267*0.33+R267*0.33+S267*0.33)*0.09) -> 13.767981
A268: =A267+7 -> 45331 | B268: ='Soybean Oil'!W268 -> 59.470649 | C268: ='Canola Oil'!M268 -> 70.0873 | D268: =BFT!W268 -> 159.222 | E268: =CWG!W268 -> 205.05965 | F268: =DCO!W268 -> 99.668443 | G268: ='Poultry Fat'!W268 -> 129.47438 | H268: =UCO!W268 -> 231.9 | I268: ='Yellow Grease'!W268 -> 260.1 | J268: =B268*0.55+I268*0.1+F268*0.1+D268*0.05+C268*0.11+((E268*0.33+G268*0.33+H268*0.33)*0.09) -> 101.1795 | K268: =I268-C268 -> 190.0127 | M268: =B268/'Feedstock Conversions'!$B$17 -> 7.9294199 | N268: =C268/'Feedstock Conversions'!$B$13 -> 9.4076913 | O268: =D268/'Feedstock Conversions'!$B$20 -> 20.544775 | P268: =E268/'Feedstock Conversions'!$B$21 -> 26.095654 | Q268: =F268/'Feedstock Conversions'!$B$14 -> 12.154688 | R268: =G268/'Feedstock Conversions'!$B$19 -> 17.379111 | S268: =I268/'Feedstock Conversions'!$B$24 -> 30.964286 | T268: =I268/'Feedstock Conversions'!$B$23 -> 31.603888 | U268: =M268*0.55+T268*0.1+Q268*0.1+O268*0.05+N268*0.11+((P268*0.33+R268*0.33+S268*0.33)*0.09) -> 13.009963
A269: =A268+7 -> 45338 | B269: ='Soybean Oil'!W269 -> 60.980649 | C269: ='Canola Oil'!M269 -> 68.9464 | D269: =BFT!W269 -> 141.822 | E269: =CWG!W269 -> 199.27385 | F269: =DCO!W269 -> 94.668443 | G269: ='Poultry Fat'!W269 -> 124.47438 | H269: =UCO!W269 -> 226.9 | I269: ='Yellow Grease'!W269 -> 255.1 | J269: =B269*0.55+I269*0.1+F269*0.1+D269*0.05+C269*0.11+((E269*0.33+G269*0.33+H269*0.33)*0.09) -> 99.545658 | K269: =I269-C269 -> 186.1536 | M269: =B269/'Feedstock Conversions'!$B$17 -> 8.1307533 | N269: =C269/'Feedstock Conversions'!$B$13 -> 9.2545503 | O269: =D269/'Feedstock Conversions'!$B$20 -> 18.299613 | P269: =E269/'Feedstock Conversions'!$B$21 -> 25.35936 | Q269: =F269/'Feedstock Conversions'!$B$14 -> 11.544932 | R269: =G269/'Feedstock Conversions'!$B$19 -> 16.70797 | S269: =I269/'Feedstock Conversions'!$B$24 -> 30.369048 | T269: =I269/'Feedstock Conversions'!$B$23 -> 30.996355 | U269: =M269*0.55+T269*0.1+Q269*0.1+O269*0.05+N269*0.11+((P269*0.33+R269*0.33+S269*0.33)*0.09) -> 12.810385
A270: =A269+7 -> 45345 | B270: ='Soybean Oil'!W270 -> 50.621899 | C270: ='Canola Oil'!M270 -> 61.299625 | D270: =BFT!W270 -> 121.522 | E270: =CWG!W270 -> 171.54115 | F270: =DCO!W270 -> 85.368443 | G270: ='Poultry Fat'!W270 -> 101.84938 | H270: =UCO!W270 -> 204.275 | I270: ='Yellow Grease'!W270 -> 232.475 | J270: =B270*0.55+I270*0.1+F270*0.1+D270*0.05+C270*0.11+((E270*0.33+G270*0.33+H270*0.33)*0.09) -> 86.632114 | K270: =I270-C270 -> 171.17538 | M270: =B270/'Feedstock Conversions'!$B$17 -> 6.7495866 | N270: =C270/'Feedstock Conversions'!$B$13 -> 8.2281376 | O270: =D270/'Feedstock Conversions'!$B$20 -> 15.680259 | P270: =E270/'Feedstock Conversions'!$B$21 -> 21.830129 | Q270: =F270/'Feedstock Conversions'!$B$14 -> 10.410786 | R270: =G270/'Feedstock Conversions'!$B$19 -> 13.671058 | S270: =I270/'Feedstock Conversions'!$B$24 -> 27.675595 | T270: =I270/'Feedstock Conversions'!$B$23 -> 28.247266 | U270: =M270*0.55+T270*0.1+Q270*0.1+O270*0.05+N270*0.11+((P270*0.33+R270*0.33+S270*0.33)*0.09) -> 11.143536
A271: =A270+7 -> 45352 | B271: ='Soybean Oil'!W271 -> 43.630649 | C271: ='Canola Oil'!M271 -> 91.279605 | D271: =BFT!W271 -> 116.147 | E271: =CWG!W271 -> 166.16615 | F271: =DCO!W271 -> 89.628443 | G271: ='Poultry Fat'!W271 -> 96.474378 | H271: =UCO!W271 -> 202.68 | I271: ='Yellow Grease'!W271 -> 227.1 | J271: =B271*0.55+I271*0.1+F271*0.1+D271*0.05+C271*0.11+((E271*0.33+G271*0.33+H271*0.33)*0.09) -> 85.337828 | K271: =I271-C271 -> 135.82039 | M271: =B271/'Feedstock Conversions'!$B$17 -> 5.8174199 | N271: =C271/'Feedstock Conversions'!$B$13 -> 12.252296 | O271: =D271/'Feedstock Conversions'!$B$20 -> 14.98671 | P271: =E271/'Feedstock Conversions'!$B$21 -> 21.146112 | Q271: =F271/'Feedstock Conversions'!$B$14 -> 10.930298 | R271: =G271/'Feedstock Conversions'!$B$19 -> 12.949581 | S271: =I271/'Feedstock Conversions'!$B$24 -> 27.035714 | T271: =I271/'Feedstock Conversions'!$B$23 -> 27.594168 | U271: =M271*0.55+T271*0.1+Q271*0.1+O271*0.05+N271*0.11+((P271*0.33+R271*0.33+S271*0.33)*0.09) -> 10.964718
A272: =A271+7 -> 45359 | B272: ='Soybean Oil'!W272 -> 40.490649 | C272: ='Canola Oil'!M272 -> 87.308242 | D272: =BFT!W272 -> 111.147 | E272: =CWG!W272 -> 158.02295 | F272: =DCO!W272 -> 86.268443 | G272: ='Poultry Fat'!W272 -> 91.474378 | H272: =UCO!W272 -> 200.2 | I272: ='Yellow Grease'!W272 -> 222.1 | J272: =B272*0.55+I272*0.1+F272*0.1+D272*0.05+C272*0.11+((E272*0.33+G272*0.33+H272*0.33)*0.09) -> 81.623969 | K272: =I272-C272 -> 134.79176 | M272: =B272/'Feedstock Conversions'!$B$17 -> 5.3987533 | N272: =C272/'Feedstock Conversions'!$B$13 -> 11.719227 | O272: =D272/'Feedstock Conversions'!$B$20 -> 14.341549 | P272: =E272/'Feedstock Conversions'!$B$21 -> 20.109818 | Q272: =F272/'Feedstock Conversions'!$B$14 -> 10.520542 | R272: =G272/'Feedstock Conversions'!$B$19 -> 12.27844 | S272: =I272/'Feedstock Conversions'!$B$24 -> 26.440476 | T272: =I272/'Feedstock Conversions'!$B$23 -> 26.986634 | U272: =M272*0.55+T272*0.1+Q272*0.1+O272*0.05+N272*0.11+((P272*0.33+R272*0.33+S272*0.33)*0.09) -> 10.473438
A273: =A272+7 -> 45366 | B273: ='Soybean Oil'!W273 -> 23.305649 | C273: ='Canola Oil'!M273 -> 66.781531 | D273: =BFT!W273 -> 100.947 | E273: =CWG!W273 -> 147.73655 | F273: =DCO!W273 -> 73.043443 | G273: ='Poultry Fat'!W273 -> 87.474378 | H273: =UCO!W273 -> 196.2 | I273: ='Yellow Grease'!W273 -> 218.1 | J273: =B273*0.55+I273*0.1+F273*0.1+D273*0.05+C273*0.11+((E273*0.33+G273*0.33+H273*0.33)*0.09) -> 67.138675 | K273: =I273-C273 -> 151.31847 | M273: =B273/'Feedstock Conversions'!$B$17 -> 3.1074199 | N273: =C273/'Feedstock Conversions'!$B$13 -> 8.9639639 | O273: =D273/'Feedstock Conversions'!$B$20 -> 13.02542 | P273: =E273/'Feedstock Conversions'!$B$21 -> 18.800783 | Q273: =F273/'Feedstock Conversions'!$B$14 -> 8.907737 | R273: =G273/'Feedstock Conversions'!$B$19 -> 11.741527 | S273: =I273/'Feedstock Conversions'!$B$24 -> 25.964286 | T273: =I273/'Feedstock Conversions'!$B$23 -> 26.500608 | U273: =M273*0.55+T273*0.1+Q273*0.1+O273*0.05+N273*0.11+((P273*0.33+R273*0.33+S273*0.33)*0.09) -> 8.5654683
A274: =A273+7 -> 45373 | B274: ='Soybean Oil'!W274 -> 23.785649 | C274: ='Canola Oil'!M274 -> 61.467947 | D274: =BFT!W274 -> 99.397004 | E274: =CWG!W274 -> 137.91405 | F274: =DCO!W274 -> 66.893443 | G274: ='Poultry Fat'!W274 -> 87.474378 | H274: =UCO!W274 -> 196.2 | I274: ='Yellow Grease'!W274 -> 218.1 | J274: =B274*0.55+I274*0.1+F274*0.1+D274*0.05+C274*0.11+((E274*0.33+G274*0.33+H274*0.33)*0.09) -> 65.833952 | K274: =I274-C274 -> 156.63205 | M274: =B274/'Feedstock Conversions'!$B$17 -> 3.1714199 | N274: =C274/'Feedstock Conversions'!$B$13 -> 8.2507311 | O274: =D274/'Feedstock Conversions'!$B$20 -> 12.82542 | P274: =E274/'Feedstock Conversions'!$B$21 -> 17.550783 | Q274: =F274/'Feedstock Conversions'!$B$14 -> 8.157737 | R274: =G274/'Feedstock Conversions'!$B$19 -> 11.741527 | S274: =I274/'Feedstock Conversions'!$B$24 -> 25.964286 | T274: =I274/'Feedstock Conversions'!$B$23 -> 26.500608 | U274: =M274*0.55+T274*0.1+Q274*0.1+O274*0.05+N274*0.11+((P274*0.33+R274*0.33+S274*0.33)*0.09) -> 8.4000877
... A308: =A307+7 -> 45611 | B308: ='Soybean Oil'!W308 -> 68.179927 | C308: ='Canola Oil'!M308 -> 92.615814 | D308: =BFT!W308 -> 113.76176 | E308: =CWG!W308 -> 106.24491 | F308: =DCO!W308 -> 59.464054 | G308: ='Poultry Fat'!W308 -> 113.19356 | H308: =UCO!W308 -> 113.56 | I308: ='Yellow Grease'!W308 -> 163.03 | J308: =B308*0.55+I308*0.1+F308*0.1+D308*0.05+C308*0.11+((E308*0.33+G308*0.33+H308*0.33)*0.09) -> 85.514247 | K308: =I308-C308 -> 70.414186 | M308: =B308/'Feedstock Conversions'!$B$17 -> 9.090657 | N308: =C308/'Feedstock Conversions'!$B$13 -> 12.431653 | O308: =D308/'Feedstock Conversions'!$B$20 -> 14.678937 | P308: =E308/'Feedstock Conversions'!$B$21 -> 13.520604 | Q308: =F308/'Feedstock Conversions'!$B$14 -> 7.2517139 | R308: =G308/'Feedstock Conversions'!$B$19 -> 15.193767 | S308: =I308/'Feedstock Conversions'!$B$24 -> 19.408333 | T308: =I308/'Feedstock Conversions'!$B$23 -> 19.809235 | U308: =M308*0.55+T308*0.1+Q308*0.1+O308*0.05+N308*0.11+((P308*0.33+R308*0.33+S308*0.33)*0.09) -> 11.236629
A309: =A308+7 -> 45618 | B309: ='Soybean Oil'!W309 -> 89.369927 | C309: ='Canola Oil'!M309 -> 110.13846 | D309: =BFT!W309 -> 118.06176 | E309: =CWG!W309 -> 112.11651 | F309: =DCO!W309 -> 69.914054 | G309: ='Poultry Fat'!W309 -> 117.49356 | H309: =UCO!W309 -> 109.04 | I309: ='Yellow Grease'!W309 -> 167.33 | J309: =B309*0.55+I309*0.1+F309*0.1+D309*0.05+C309*0.11+((E309*0.33+G309*0.33+H309*0.33)*0.09) -> 100.95409 | K309: =I309-C309 -> 57.191545 | M309: =B309/'Feedstock Conversions'!$B$17 -> 11.91599 | N309: =C309/'Feedstock Conversions'!$B$13 -> 14.783685 | O309: =D309/'Feedstock Conversions'!$B$20 -> 15.233775 | P309: =E309/'Feedstock Conversions'!$B$21 -> 14.267817 | Q309: =F309/'Feedstock Conversions'!$B$14 -> 8.5261041 | R309: =G309/'Feedstock Conversions'!$B$19 -> 15.770948 | S309: =I309/'Feedstock Conversions'!$B$24 -> 19.920238 | T309: =I309/'Feedstock Conversions'!$B$23 -> 20.331713 | U309: =M309*0.55+T309*0.1+Q309*0.1+O309*0.05+N309*0.11+((P309*0.33+R309*0.33+S309*0.33)*0.09) -> 13.311253 | AB309: Includes RIN, LCFS and BTC - does not subtract out fixed costs (45cpg)
A310: =A309+7 -> 45625 | B310: ='Soybean Oil'!W310 -> 108.46743 | C310: ='Canola Oil'!M310 -> 125.00847 | D310: =BFT!W310 -> 108.63676 | E310: =CWG!W310 -> 117.06681 | F310: =DCO!W310 -> 84.414054 | G310: ='Poultry Fat'!W310 -> 119.69356 | H310: =UCO!W310 -> 106.2 | I310: ='Yellow Grease'!W310 -> 169.53 | J310: =B310*0.55+I310*0.1+F310*0.1+D310*0.05+C310*0.11+((E310*0.33+G310*0.33+H310*0.33)*0.09) -> 114.42018 | K310: =I310-C310 -> 44.521528 | M310: =B310/'Feedstock Conversions'!$B$17 -> 14.462324 | N310: =C310/'Feedstock Conversions'!$B$13 -> 16.779661 | O310: =D310/'Feedstock Conversions'!$B$20 -> 14.017646 | P310: =E310/'Feedstock Conversions'!$B$21 -> 14.897787 | Q310: =F310/'Feedstock Conversions'!$B$14 -> 10.294397 | R310: =G310/'Feedstock Conversions'!$B$19 -> 16.06625 | S310: =I310/'Feedstock Conversions'!$B$24 -> 20.182143 | T310: =I310/'Feedstock Conversions'!$B$23 -> 20.599028 | U310: =M310*0.55+T310*0.1+Q310*0.1+O310*0.05+N310*0.11+((P310*0.33+R310*0.33+S310*0.33)*0.09) -> 15.109307 | AB310: Includes RIN, LCFS and BTC - does not subtract out fixed costs (45cpg)
A311: =A310+7 -> 45632 | B311: ='Soybean Oil'!W311 -> 110.07993 | C311: ='Canola Oil'!M311 -> 120.90951 | D311: =BFT!W311 -> 108.63676 | E311: =CWG!W311 -> 117.45971 | F311: =DCO!W311 -> 94.254054 | G311: ='Poultry Fat'!W311 -> 119.69356 | H311: =UCO!W311 -> 106.2 | I311: ='Yellow Grease'!W311 -> 169.53 | J311: =B311*0.55+I311*0.1+F311*0.1+D311*0.05+C311*0.11+((E311*0.33+G311*0.33+H311*0.33)*0.09) -> 115.85184 | K311: =I311-C311 -> 48.620488 | M311: =B311/'Feedstock Conversions'!$B$17 -> 14.677324 | N311: =C311/'Feedstock Conversions'!$B$13 -> 16.229465 | O311: =D311/'Feedstock Conversions'!$B$20 -> 14.017646 | P311: =E311/'Feedstock Conversions'!$B$21 -> 14.947787 | Q311: =F311/'Feedstock Conversions'!$B$14 -> 11.494397 | R311: =G311/'Feedstock Conversions'!$B$19 -> 16.06625 | S311: =I311/'Feedstock Conversions'!$B$24 -> 20.182143 | T311: =I311/'Feedstock Conversions'!$B$23 -> 20.599028 | U311: =M311*0.55+T311*0.1+Q311*0.1+O311*0.05+N311*0.11+((P311*0.33+R311*0.33+S311*0.33)*0.09) -> 15.28852 | AB311: Includes RIN, LCFS and BTC - does not subtract out fixed costs (45cpg)
A312: =A311+7 -> 45639 | B312: ='Soybean Oil'!W312 -> 115.32993 | C312: ='Canola Oil'!M312 -> 120.2525 | D312: =BFT!W312 -> 108.63676 | E312: =CWG!W312 -> 124.53191 | F312: =DCO!W312 -> 91.138054 | G312: ='Poultry Fat'!W312 -> 119.69356 | H312: =UCO!W312 -> 106.2 | I312: ='Yellow Grease'!W312 -> 169.53 | J312: =B312*0.55+I312*0.1+F312*0.1+D312*0.05+C312*0.11+((E312*0.33+G312*0.33+H312*0.33)*0.09) -> 118.56551 | K312: =I312-C312 -> 49.277503 | M312: =B312/'Feedstock Conversions'!$B$17 -> 15.377324 | N312: =C312/'Feedstock Conversions'!$B$13 -> 16.141275 | O312: =D312/'Feedstock Conversions'!$B$20 -> 14.017646 | P312: =E312/'Feedstock Conversions'!$B$21 -> 15.847787 | Q312: =F312/'Feedstock Conversions'!$B$14 -> 11.114397 | R312: =G312/'Feedstock Conversions'!$B$19 -> 16.06625 | S312: =I312/'Feedstock Conversions'!$B$24 -> 20.182143 | T312: =I312/'Feedstock Conversions'!$B$23 -> 20.599028 | U312: =M312*0.55+T312*0.1+Q312*0.1+O312*0.05+N312*0.11+((P312*0.33+R312*0.33+S312*0.33)*0.09) -> 15.65255 | AB312: Includes RIN, LCFS and BTC - does not subtract out fixed costs (45cpg)
A313: =A312+7 -> 45646 | B313: ='Soybean Oil'!W313 -> 127.40493 | C313: ='Canola Oil'!M313 -> 120.05779 | D313: =BFT!W313 -> 108.41176 | E313: =CWG!W313 -> 140.51301 | F313: =DCO!W313 -> 94.434054 | G313: ='Poultry Fat'!W313 -> 112.49356 | H313: =UCO!W313 -> 101.94 | I313: ='Yellow Grease'!W313 -> 162.33 | J313: =B313*0.55+I313*0.1+F313*0.1+D313*0.05+C313*0.11+((E313*0.33+G313*0.33+H313*0.33)*0.09) -> 124.91797 | K313: =I313-C313 -> 42.272209 | M313: =B313/'Feedstock Conversions'!$B$17 -> 16.987324 | N313: =C313/'Feedstock Conversions'!$B$13 -> 16.11514 | O313: =D313/'Feedstock Conversions'!$B$20 -> 13.988614 | P313: =E313/'Feedstock Conversions'!$B$21 -> 17.881523 | Q313: =F313/'Feedstock Conversions'!$B$14 -> 11.516348 | R313: =G313/'Feedstock Conversions'!$B$19 -> 15.099807 | S313: =I313/'Feedstock Conversions'!$B$24 -> 19.325 | T313: =I313/'Feedstock Conversions'!$B$23 -> 19.72418 | U313: =M313*0.55+T313*0.1+Q313*0.1+O313*0.05+N313*0.11+((P313*0.33+R313*0.33+S313*0.33)*0.09) -> 16.492675 | AB313: Includes RIN, LCFS and BTC - does not subtract out fixed costs (45cpg)
A314: =A313+7 -> 45653 | B314: ='Soybean Oil'!W314 -> 122.52993 | C314: ='Canola Oil'!M314 -> 120.0578 | D314: =BFT!W314 -> 102.26176 | E314: =CWG!W314 -> 143.22877 | F314: =DCO!W314 -> 86.914054 | G314: ='Poultry Fat'!W314 -> 101.69356 | H314: =UCO!W314 -> 102.9 | I314: ='Yellow Grease'!W314 -> 151.53 | J314: =B314*0.55+I314*0.1+F314*0.1+D314*0.05+C314*0.11+((E314*0.33+G314*0.33+H314*0.33)*0.09) -> 119.88563 | K314: =I314-C314 -> 31.472201 | M314: =B314/'Feedstock Conversions'!$B$17 -> 16.337324 | N314: =C314/'Feedstock Conversions'!$B$13 -> 16.115141 | O314: =D314/'Feedstock Conversions'!$B$20 -> 13.195066 | P314: =E314/'Feedstock Conversions'!$B$21 -> 18.227128 | Q314: =F314/'Feedstock Conversions'!$B$14 -> 10.599275 | R314: =G314/'Feedstock Conversions'!$B$19 -> 13.650142 | S314: =I314/'Feedstock Conversions'!$B$24 -> 18.039286 | T314: =I314/'Feedstock Conversions'!$B$23 -> 18.411908 | U314: =M314*0.55+T314*0.1+Q314*0.1+O314*0.05+N314*0.11+((P314*0.33+R314*0.33+S314*0.33)*0.09) -> 15.801587 | AB314: Includes RIN, LCFS and BTC - does not subtract out fixed costs (45cpg)
A315: =A314+7 -> 45660 | B315: ='Soybean Oil'!W315 -> 115.59457 | C315: ='Canola Oil'!M315 -> 20.544454 | D315: =BFT!W315 -> 102.14772 | E315: =CWG!W315 -> 149.35801 | F315: =DCO!W315 -> 86.914054 | G315: ='Poultry Fat'!W315 -> 103.55606 | H315: =UCO!W315 -> 102.9 | I315: ='Yellow Grease'!W315 -> 151.53 | J315: =B315*0.55+I315*0.1+F315*0.1+D315*0.05+C315*0.11+((E315*0.33+G315*0.33+H315*0.33)*0.09) -> 105.35637 | K315: =I315-C315 -> 130.98555 | M315: =B315/'Feedstock Conversions'!$B$17 -> 15.412609 | N315: =C315/'Feedstock Conversions'!$B$13 -> 2.7576448 | O315: =D315/'Feedstock Conversions'!$B$20 -> 13.180351 | P315: =E315/'Feedstock Conversions'!$B$21 -> 19.007128 | Q315: =F315/'Feedstock Conversions'!$B$14 -> 10.599275 | R315: =G315/'Feedstock Conversions'!$B$19 -> 13.900142 | S315: =I315/'Feedstock Conversions'!$B$24 -> 18.039286 | T315: =I315/'Feedstock Conversions'!$B$23 -> 18.411908 | U315: =M315*0.55+T315*0.1+Q315*0.1+O315*0.05+N315*0.11+((P315*0.33+R315*0.33+S315*0.33)*0.09) -> 13.853524
A316: =A315+7 -> 45667 | B316: ='Soybean Oil'!W316 -> 69.079569 | C316: ='Canola Oil'!M316 -> 19.254979 | D316: =BFT!W316 -> 56.647721 | E316: =CWG!W316 -> 135.53987 | F316: =DCO!W316 -> 56.793395 | G316: ='Poultry Fat'!W316 -> 75.308938 | H316: =UCO!W316 -> 67.86 | I316: ='Yellow Grease'!W316 -> 121.53 | J316: =B316*0.55+I316*0.1+F316*0.1+D316*0.05+C316*0.11+((E316*0.33+G316*0.33+H316*0.33)*0.09) -> 69.054188 | K316: =I316-C316 -> 102.27502 | M316: =B316/'Feedstock Conversions'!$B$17 -> 9.2106092 | N316: =C316/'Feedstock Conversions'!$B$13 -> 2.5845609 | O316: =D316/'Feedstock Conversions'!$B$20 -> 7.3093834 | P316: =E316/'Feedstock Conversions'!$B$21 -> 17.248648 | Q316: =F316/'Feedstock Conversions'!$B$14 -> 6.9260238 | R316: =G316/'Feedstock Conversions'!$B$19 -> 10.108582 | S316: =I316/'Feedstock Conversions'!$B$24 -> 14.467857 | T316: =I316/'Feedstock Conversions'!$B$23 -> 14.766707 | U316: =M316*0.55+T316*0.1+Q316*0.1+O316*0.05+N316*0.11+((P316*0.33+R316*0.33+S316*0.33)*0.09) -> 9.1270841
A317: =A316+7 -> 45674 | B317: ='Soybean Oil'!W317 -> 18.319569 | C317: ='Canola Oil'!M317 -> 19.157655 | D317: =BFT!W317 -> 25.072721 | E317: =CWG!W317 -> 102.89328 | F317: =DCO!W317 -> 13.743395 | G317: ='Poultry Fat'!W317 -> 50.708938 | H317: =UCO!W317 -> 39.9 | I317: ='Yellow Grease'!W317 -> 96.93 | J317: =B317*0.55+I317*0.1+F317*0.1+D317*0.05+C317*0.11+((E317*0.33+G317*0.33+H317*0.33)*0.09) -> 30.251097 | K317: =I317-C317 -> 77.772345 | M317: =B317/'Feedstock Conversions'!$B$17 -> 2.4426092 | N317: =C317/'Feedstock Conversions'!$B$13 -> 2.5714973 | O317: =D317/'Feedstock Conversions'!$B$20 -> 3.2351898 | P317: =E317/'Feedstock Conversions'!$B$21 -> 13.09408 | Q317: =F317/'Feedstock Conversions'!$B$14 -> 1.6760238 | R317: =G317/'Feedstock Conversions'!$B$19 -> 6.8065689 | S317: =I317/'Feedstock Conversions'!$B$24 -> 11.539286 | T317: =I317/'Feedstock Conversions'!$B$23 -> 11.777643 | U317: =M317*0.55+T317*0.1+Q317*0.1+O317*0.05+N317*0.11+((P317*0.33+R317*0.33+S317*0.33)*0.09) -> 4.067192
A318: =A317+7 -> 45681 | B318: ='Soybean Oil'!W318 -> 38.500819 | C318: ='Canola Oil'!M318 -> 17.046989 | D318: =BFT!W318 -> 18.522721 | E318: =CWG!W318 -> 84.471933 | F318: =DCO!W318 -> 15.043395 | G318: ='Poultry Fat'!W318 -> 64.308938 | H318: =UCO!W318 -> 53.5 | I318: ='Yellow Grease'!W318 -> 110.53 | J318: =B318*0.55+I318*0.1+F318*0.1+D318*0.05+C318*0.11+((E318*0.33+G318*0.33+H318*0.33)*0.09) -> 42.541837 | K318: =I318-C318 -> 93.483011 | M318: =B318/'Feedstock Conversions'!$B$17 -> 5.1334425 | N318: =C318/'Feedstock Conversions'!$B$13 -> 2.2881865 | O318: =D318/'Feedstock Conversions'!$B$20 -> 2.3900285 | P318: =E318/'Feedstock Conversions'!$B$21 -> 10.749801 | Q318: =F318/'Feedstock Conversions'!$B$14 -> 1.8345604 | R318: =G318/'Feedstock Conversions'!$B$19 -> 8.6320723 | S318: =I318/'Feedstock Conversions'!$B$24 -> 13.158333 | T318: =I318/'Feedstock Conversions'!$B$23 -> 13.430134 | U318: =M318*0.55+T318*0.1+Q318*0.1+O318*0.05+N318*0.11+((P318*0.33+R318*0.33+S318*0.33)*0.09) -> 5.6875089
A319: =A318+7 -> 45688 | B319: ='Soybean Oil'!W319 -> 37.959569 | C319: ='Canola Oil'!M319 -> 17.868121 | D319: =BFT!W319 -> 5.1727212 | E319: =CWG!W319 -> 66.102683 | F319: =DCO!W319 -> 2.8833953 | G319: ='Poultry Fat'!W319 -> 58.708938 | H319: =UCO!W319 -> 47.9 | I319: ='Yellow Grease'!W319 -> 104.93 | J319: =B319*0.55+I319*0.1+F319*0.1+D319*0.05+C319*0.11+((E319*0.33+G319*0.33+H319*0.33)*0.09) -> 39.012767 | K319: =I319-C319 -> 87.061879 | M319: =B319/'Feedstock Conversions'!$B$17 -> 5.0612758 | N319: =C319/'Feedstock Conversions'!$B$13 -> 2.3984055 | O319: =D319/'Feedstock Conversions'!$B$20 -> 0.66744789 | P319: =E319/'Feedstock Conversions'!$B$21 -> 8.4121511 | Q319: =F319/'Feedstock Conversions'!$B$14 -> 0.35163357 | R319: =G319/'Feedstock Conversions'!$B$19 -> 7.8803944 | S319: =I319/'Feedstock Conversions'!$B$24 -> 12.491667 | T319: =I319/'Feedstock Conversions'!$B$23 -> 12.749696 | U319: =M319*0.55+T319*0.1+Q319*0.1+O319*0.05+N319*0.11+((P319*0.33+R319*0.33+S319*0.33)*0.09) -> 5.2459228
A320: =A319+7 -> 45695 | B320: ='Soybean Oil'!W320 -> 28.359569 | C320: ='Canola Oil'!M320 -> 18.841329 | D320: =BFT!W320 -> -12.627279 | E320: =CWG!W320 -> 54.416283 | F320: =DCO!W320 -> -12.356605 | G320: ='Poultry Fat'!W320 -> 48.838938 | H320: =UCO!W320 -> 42.5 | I320: ='Yellow Grease'!W320 -> 99.53 | J320: =B320*0.55+I320*0.1+F320*0.1+D320*0.05+C320*0.11+((E320*0.33+G320*0.33+H320*0.33)*0.09) -> 30.085215 | K320: =I320-C320 -> 80.688671 | M320: =B320/'Feedstock Conversions'!$B$17 -> 3.7812758 | N320: =C320/'Feedstock Conversions'!$B$13 -> 2.5290375 | O320: =D320/'Feedstock Conversions'!$B$20 -> -1.6293263 | P320: =E320/'Feedstock Conversions'!$B$21 -> 6.9249533 | Q320: =F320/'Feedstock Conversions'!$B$14 -> -1.506903 | R320: =G320/'Feedstock Conversions'!$B$19 -> 6.5555622 | S320: =I320/'Feedstock Conversions'!$B$24 -> 11.84881 | T320: =I320/'Feedstock Conversions'!$B$23 -> 12.09356 | U320: =M320*0.55+T320*0.1+Q320*0.1+O320*0.05+N320*0.11+((P320*0.33+R320*0.33+S320*0.33)*0.09) -> 4.0873762
A321: =A320+7 -> 45702 | B321: ='Soybean Oil'!W321 -> 30.284569 | C321: ='Canola Oil'!M321 -> 18.525043 | D321: =BFT!W321 -> -5.0272788 | E321: =CWG!W321 -> 52.543483 | F321: =DCO!W321 -> -9.8566047 | G321: ='Poultry Fat'!W321 -> 56.558938 | H321: =UCO!W321 -> 53.2 | I321: ='Yellow Grease'!W321 -> 110.23 | J321: =B321*0.55+I321*0.1+F321*0.1+D321*0.05+C321*0.11+((E321*0.33+G321*0.33+H321*0.33)*0.09) -> 33.300625 | K321: =I321-C321 -> 91.704957 | M321: =B321/'Feedstock Conversions'!$B$17 -> 4.0379425 | N321: =C321/'Feedstock Conversions'!$B$13 -> 2.486583 | O321: =D321/'Feedstock Conversions'!$B$20 -> -0.64868114 | P321: =E321/'Feedstock Conversions'!$B$21 -> 6.6866229 | Q321: =F321/'Feedstock Conversions'!$B$14 -> -1.202025 | R321: =G321/'Feedstock Conversions'!$B$19 -> 7.5918038 | S321: =I321/'Feedstock Conversions'!$B$24 -> 13.122619 | T321: =I321/'Feedstock Conversions'!$B$23 -> 13.393682 | U321: =M321*0.55+T321*0.1+Q321*0.1+O321*0.05+N321*0.11+((P321*0.33+R321*0.33+S321*0.33)*0.09) -> 4.4949352
A322: =A321+7 -> 45709 | B322: ='Soybean Oil'!W322 -> 28.713319 | C322: ='Canola Oil'!M322 -> 16.286668 | D322: =BFT!W322 -> -11.758529 | E322: =CWG!W322 -> 39.421558 | F322: =DCO!W322 -> -30.264605 | G322: ='Poultry Fat'!W322 -> 64.358938 | H322: =UCO!W322 -> 61 | I322: ='Yellow Grease'!W322 -> 118.03 | J322: =B322*0.55+I322*0.1+F322*0.1+D322*0.05+C322*0.11+((E322*0.33+G322*0.33+H322*0.33)*0.09) -> 30.666453 | K322: =I322-C322 -> 101.74333 | M322: =B322/'Feedstock Conversions'!$B$17 -> 3.8284425 | N322: =C322/'Feedstock Conversions'!$B$13 -> 2.1861299 | O322: =D322/'Feedstock Conversions'!$B$20 -> -1.5172295 | P322: =E322/'Feedstock Conversions'!$B$21 -> 5.0167419 | Q322: =F322/'Feedstock Conversions'!$B$14 -> -3.6908055 | R322: =G322/'Feedstock Conversions'!$B$19 -> 8.6387837 | S322: =I322/'Feedstock Conversions'!$B$24 -> 14.05119 | T322: =I322/'Feedstock Conversions'!$B$23 -> 14.341434 | U322: =M322*0.55+T322*0.1+Q322*0.1+O322*0.05+N322*0.11+((P322*0.33+R322*0.33+S322*0.33)*0.09) -> 4.1582085
A323: =A322+7 -> 45716 | B323: ='Soybean Oil'!W323 -> 29.384569 | C323: ='Canola Oil'!M323 -> 12.856104 | D323: =BFT!W323 -> -31.602279 | E323: =CWG!W323 -> 22.162383 | F323: =DCO!W323 -> -45.756605 | G323: ='Poultry Fat'!W323 -> 49.358938 | H323: =UCO!W323 -> 46 | I323: ='Yellow Grease'!W323 -> 103.03 | J323: =B323*0.55+I323*0.1+F323*0.1+D323*0.05+C323*0.11+((E323*0.33+G323*0.33+H323*0.33)*0.09) -> 25.213293 | K323: =I323-C323 -> 90.173896 | M323: =B323/'Feedstock Conversions'!$B$17 -> 3.9179425 | N323: =C323/'Feedstock Conversions'!$B$13 -> 1.7256516 | O323: =D323/'Feedstock Conversions'!$B$20 -> -4.0777134 | P323: =E323/'Feedstock Conversions'!$B$21 -> 2.8203592 | Q323: =F323/'Feedstock Conversions'!$B$14 -> -5.5800737 | R323: =G323/'Feedstock Conversions'!$B$19 -> 6.6253609 | S323: =I323/'Feedstock Conversions'!$B$24 -> 12.265476 | T323: =I323/'Feedstock Conversions'!$B$23 -> 12.518834 | U323: =M323*0.55+T323*0.1+Q323*0.1+O323*0.05+N323*0.11+((P323*0.33+R323*0.33+S323*0.33)*0.09) -> 3.4795029
A324: =A323+7 -> 45723 | B324: ='Soybean Oil'!W324 -> 16.104569 | C324: ='Canola Oil'!M324 -> 10.374416 | D324: =BFT!W324 -> -45.102279 | E324: =CWG!W324 -> -5.266017 | F324: =DCO!W324 -> -51.796605 | G324: ='Poultry Fat'!W324 -> 20.358938 | H324: =UCO!W324 -> 20.36 | I324: ='Yellow Grease'!W324 -> 74.03 | J324: =B324*0.55+I324*0.1+F324*0.1+D324*0.05+C324*0.11+((E324*0.33+G324*0.33+H324*0.33)*0.09) -> 11.019876 | K324: =I324-C324 -> 63.655584 | M324: =B324/'Feedstock Conversions'!$B$17 -> 2.1472758 | N324: =C324/'Feedstock Conversions'!$B$13 -> 1.3925391 | O324: =D324/'Feedstock Conversions'!$B$20 -> -5.8196489 | P324: =E324/'Feedstock Conversions'!$B$21 -> -0.67014724 | Q324: =F324/'Feedstock Conversions'!$B$14 -> -6.3166591 | R324: =G324/'Feedstock Conversions'!$B$19 -> 2.7327434 | S324: =I324/'Feedstock Conversions'!$B$24 -> 8.8130952 | T324: =I324/'Feedstock Conversions'!$B$23 -> 8.9951397 | U324: =M324*0.55+T324*0.1+Q324*0.1+O324*0.05+N324*0.11+((P324*0.33+R324*0.33+S324*0.33)*0.09) -> 1.6340547
A325: =A324+7 -> 45730 | B325: ='Soybean Oil'!W325 -> 17.234569 | C325: ='Canola Oil'!M325 -> 10.569055 | D325: =BFT!W325 -> -41.927279 | E325: =CWG!W325 -> -12.908617 | F325: =DCO!W325 -> -48.676605 | G325: ='Poultry Fat'!W325 -> 10.358938 | H325: =UCO!W325 -> 15.4 | I325: ='Yellow Grease'!W325 -> 64.03 | J325: =B325*0.55+I325*0.1+F325*0.1+D325*0.05+C325*0.11+((E325*0.33+G325*0.33+H325*0.33)*0.09) -> 10.462239 | K325: =I325-C325 -> 53.460945 | M325: =B325/'Feedstock Conversions'!$B$17 -> 2.2979425 | N325: =C325/'Feedstock Conversions'!$B$13 -> 1.4186651 | O325: =D325/'Feedstock Conversions'!$B$20 -> -5.4099715 | P325: =E325/'Feedstock Conversions'!$B$21 -> -1.6427357 | Q325: =F325/'Feedstock Conversions'!$B$14 -> -5.9361713 | R325: =G325/'Feedstock Conversions'!$B$19 -> 1.3904615 | S325: =I325/'Feedstock Conversions'!$B$24 -> 7.622619 | T325: =I325/'Feedstock Conversions'!$B$23 -> 7.7800729 | U325: =M325*0.55+T325*0.1+Q325*0.1+O325*0.05+N325*0.11+((P325*0.33+R325*0.33+S325*0.33)*0.09) -> 1.5527124
A326: =A325+7 -> 45737 | B326: ='Soybean Oil'!W326 -> 22.964569 | C326: ='Canola Oil'!M326 -> 12.12619 | D326: =BFT!W326 -> -17.777279 | E326: =CWG!W326 -> 13.007383 | F326: =DCO!W326 -> -31.096605 | G326: ='Poultry Fat'!W326 -> 11.618938 | H326: =UCO!W326 -> 25.6 | I326: ='Yellow Grease'!W326 -> 74.23 | J326: =B326*0.55+I326*0.1+F326*0.1+D326*0.05+C326*0.11+((E326*0.33+G326*0.33+H326*0.33)*0.09) -> 18.880591 | K326: =I326-C326 -> 62.10381 | M326: =B326/'Feedstock Conversions'!$B$17 -> 3.0619425 | N326: =C326/'Feedstock Conversions'!$B$13 -> 1.6276765 | O326: =D326/'Feedstock Conversions'!$B$20 -> -2.2938424 | P326: =E326/'Feedstock Conversions'!$B$21 -> 1.6553045 | Q326: =F326/'Feedstock Conversions'!$B$14 -> -3.7922689 | R326: =G326/'Feedstock Conversions'!$B$19 -> 1.559589 | S326: =I326/'Feedstock Conversions'!$B$24 -> 8.8369048 | T326: =I326/'Feedstock Conversions'!$B$23 -> 9.0194411 | U326: =M326*0.55+T326*0.1+Q326*0.1+O326*0.05+N326*0.11+((P326*0.33+R326*0.33+S326*0.33)*0.09) -> 2.6290763
... A330: =A329+7 -> 45765 | B330: ='Soybean Oil'!W330 -> 18.769569 | C330: ='Canola Oil'!M330 -> 11.217863 | D330: =BFT!W330 -> 1.2727212 | E330: =CWG!W330 -> 22.696683 | F330: =DCO!W330 -> -34.989938 | G330: ='Poultry Fat'!W330 -> 42.992272 | H330: =UCO!W330 -> 59.5 | I330: ='Yellow Grease'!W330 -> 116.53 | J330: =B330*0.55+I330*0.1+F330*0.1+D330*0.05+C330*0.11+((E330*0.33+G330*0.33+H330*0.33)*0.09) -> 23.492982 | K330: =I330-C330 -> 105.31214 | M330: =B330/'Feedstock Conversions'!$B$17 -> 2.5026092 | N330: =C330/'Feedstock Conversions'!$B$13 -> 1.5057535 | O330: =D330/'Feedstock Conversions'!$B$20 -> 0.16422209 | P330: =E330/'Feedstock Conversions'!$B$21 -> 2.8883536 | Q330: =F330/'Feedstock Conversions'!$B$14 -> -4.2670656 | R330: =G330/'Feedstock Conversions'!$B$19 -> 5.7707747 | S330: =I330/'Feedstock Conversions'!$B$24 -> 13.872619 | T330: =I330/'Feedstock Conversions'!$B$23 -> 14.159174 | U330: =M330*0.55+T330*0.1+Q330*0.1+O330*0.05+N330*0.11+((P330*0.33+R330*0.33+S330*0.33)*0.09) -> 3.2086827

Sheet RD Profit per Gallon
A1: Profit per pound ==> | B1: SBO | C1: Canola Oil | D1: BFT | E1: CWG | F1: DCO | G1: Poultry Fat | H1: UCO | I1: Yellow Grease | K1: Profit per gallon ====> | L1: SBO | M1: Canola Oil | N1: BFT | O1: CWG | P1: DCO | Q1: Poultry Fat | R1: UCO | S1: Yellow Grease | U1: ---> SBO | V1: BFT | W1: CWG | X1: DCO | Y1: Poultry Fat | Z1: UCO | AA1: Yellow Grease | AC1: Yes - substitute the feedstock | AD1: No - do not sustitute the feedstock
A2: 43637 | B2: ='Soybean Oil'!X26/'Feedstock Conversions'!B$5 -> 26.805607 | D2: =BFT!X26/'Feedstock Conversions'!B$7 -> 23.575993 | E2: =CWG!X26/'Feedstock Conversions'!B$9 -> 24.775072 | F2: =DCO!X26/'Feedstock Conversions'!B$8 -> 22.095567 | G2: ='Poultry Fat'!X26/'Feedstock Conversions'!B$10 -> 25.706113 | H2: =UCO!X26/'Feedstock Conversions'!B$4 -> 44.833523 | I2: ='Yellow Grease'!X26/'Feedstock Conversions'!B$3 -> 43.653093 | L2: ='Soybean Oil'!X26 -> 201.04206 | M2: ='Canola Oil'!N26 -> 210.00862 | N2: =BFT!X26 -> 221.14282 | O2: =CWG!X26 -> 232.2663 | P2: =DCO!X26 -> 203.27921 | Q2: ='Poultry Fat'!X26 -> 208.76363 | R2: =UCO!X26 -> 359.11652 | S2: ='Yellow Grease'!X26 -> 371.05129 | V2: =IF($L2-N2>$B2-D2,"YES","NO") -> NO | W2: =IF($L2-O2>$B2-E2,"YES","NO") -> NO | X2: =IF($L2-P2>$B2-F2,"YES","NO") -> NO | Y2: =IF($L2-Q2>$B2-G2,"YES","NO") -> NO | Z2: =IF($L2-R2>$B2-H2,"YES","NO") -> NO | AA2: =IF($L2-S2>$B2-I2,"YES","NO") -> NO
A3: 43644 | B3: ='Soybean Oil'!X27/'Feedstock Conversions'!B$5 -> 26.944437 | D3: =BFT!X27/'Feedstock Conversions'!B$7 -> 23.461167 | E3: =CWG!X27/'Feedstock Conversions'!B$9 -> 24.225087 | F3: =DCO!X27/'Feedstock Conversions'!B$8 -> 21.845969 | G3: ='Poultry Fat'!X27/'Feedstock Conversions'!B$10 -> 25.426521 | H3: =UCO!X27/'Feedstock Conversions'!B$4 -> 44.715829 | I3: ='Yellow Grease'!X27/'Feedstock Conversions'!B$3 -> 43.547515 | L3: ='Soybean Oil'!X27 -> 202.08328 | M3: ='Canola Oil'!N27 -> 211.21394 | N3: =BFT!X27 -> 220.06575 | O3: =CWG!X27 -> 227.11019 | P3: =DCO!X27 -> 200.98292 | Q3: ='Poultry Fat'!X27 -> 206.49301 | R3: =UCO!X27 -> 358.17379 | S3: ='Yellow Grease'!X27 -> 370.15388 | V3: =IF($L3-N3>$B3-D3,"YES","NO") -> NO | W3: =IF($L3-O3>$B3-E3,"YES","NO") -> NO | X3: =IF($L3-P3>$B3-F3,"YES","NO") -> NO | Y3: =IF($L3-Q3>$B3-G3,"YES","NO") -> NO | Z3: =IF($L3-R3>$B3-H3,"YES","NO") -> NO | AA3: =IF($L3-S3>$B3-I3,"YES","NO") -> NO
A4: 43651 | B4: ='Soybean Oil'!X28/'Feedstock Conversions'!B$5 -> 26.52209 | D4: =BFT!X28/'Feedstock Conversions'!B$7 -> 23.099549 | E4: =CWG!X28/'Feedstock Conversions'!B$9 -> 23.316935 | F4: =DCO!X28/'Feedstock Conversions'!B$8 -> 21.427858 | G4: ='Poultry Fat'!X28/'Feedstock Conversions'!B$10 -> 24.959543 | H4: =UCO!X28/'Feedstock Conversions'!B$4 -> 44.276076 | I4: ='Yellow Grease'!X28/'Feedstock Conversions'!B$3 -> 43.144367 | L4: ='Soybean Oil'!X28 -> 198.91568 | M4: ='Canola Oil'!N28 -> 207.9322 | N4: =BFT!X28 -> 216.67377 | O4: =CWG!X28 -> 218.59627 | P4: =DCO!X28 -> 197.1363 | Q4: ='Poultry Fat'!X28 -> 202.70061 | R4: =UCO!X28 -> 354.65137 | S4: ='Yellow Grease'!X28 -> 366.72712 | V4: =IF($L4-N4>$B4-D4,"YES","NO") -> NO | W4: =IF($L4-O4>$B4-E4,"YES","NO") -> NO | X4: =IF($L4-P4>$B4-F4,"YES","NO") -> NO | Y4: =IF($L4-Q4>$B4-G4,"YES","NO") -> NO | Z4: =IF($L4-R4>$B4-H4,"YES","NO") -> NO | AA4: =IF($L4-S4>$B4-I4,"YES","NO") -> NO
A5: 43658 | B5: ='Soybean Oil'!X29/'Feedstock Conversions'!B$5 -> 26.515267 | D5: =BFT!X29/'Feedstock Conversions'!B$7 -> 22.769587 | E5: =CWG!X29/'Feedstock Conversions'!B$9 -> 23.390773 | F5: =DCO!X29/'Feedstock Conversions'!B$8 -> 21.582574 | G5: ='Poultry Fat'!X29/'Feedstock Conversions'!B$10 -> 25.141487 | H5: =UCO!X29/'Feedstock Conversions'!B$4 -> 44.569156 | I5: ='Yellow Grease'!X29/'Feedstock Conversions'!B$3 -> 43.431807 | L5: ='Soybean Oil'!X29 -> 198.8645 | M5: ='Canola Oil'!N29 -> 211.09411 | N5: =BFT!X29 -> 213.57873 | O5: =CWG!X29 -> 219.2885 | P5: =DCO!X29 -> 198.55968 | Q5: ='Poultry Fat'!X29 -> 204.17821 | R5: =UCO!X29 -> 356.99894 | S5: ='Yellow Grease'!X29 -> 369.17036 | V5: =IF($L5-N5>$B5-D5,"YES","NO") -> NO | W5: =IF($L5-O5>$B5-E5,"YES","NO") -> NO | X5: =IF($L5-P5>$B5-F5,"YES","NO") -> NO | Y5: =IF($L5-Q5>$B5-G5,"YES","NO") -> NO | Z5: =IF($L5-R5>$B5-H5,"YES","NO") -> NO | AA5: =IF($L5-S5>$B5-I5,"YES","NO") -> NO
A6: 43665 | B6: ='Soybean Oil'!X30/'Feedstock Conversions'!B$5 -> 26.272854 | D6: =BFT!X30/'Feedstock Conversions'!B$7 -> 21.582641 | E6: =CWG!X30/'Feedstock Conversions'!B$9 -> 22.487966 | F6: =DCO!X30/'Feedstock Conversions'!B$8 -> 21.156328 | G6: ='Poultry Fat'!X30/'Feedstock Conversions'!B$10 -> 24.663537 | H6: =UCO!X30/'Feedstock Conversions'!B$4 -> 44.259221 | I6: ='Yellow Grease'!X30/'Feedstock Conversions'!B$3 -> 43.148032 | L6: ='Soybean Oil'!X30 -> 197.0464 | M6: ='Canola Oil'!N30 -> 210.17655 | N6: =BFT!X30 -> 202.44517 | O6: =CWG!X30 -> 210.82468 | P6: =DCO!X30 -> 194.63822 | Q6: ='Poultry Fat'!X30 -> 200.2967 | R6: =UCO!X30 -> 354.51636 | S6: ='Yellow Grease'!X30 -> 366.75827 | V6: =IF($L6-N6>$B6-D6,"YES","NO") -> NO | W6: =IF($L6-O6>$B6-E6,"YES","NO") -> NO | X6: =IF($L6-P6>$B6-F6,"YES","NO") -> NO | Y6: =IF($L6-Q6>$B6-G6,"YES","NO") -> NO | Z6: =IF($L6-R6>$B6-H6,"YES","NO") -> NO | AA6: =IF($L6-S6>$B6-I6,"YES","NO") -> NO
A7: 43672 | B7: ='Soybean Oil'!X31/'Feedstock Conversions'!B$5 -> 27.342186 | D7: =BFT!X31/'Feedstock Conversions'!B$7 -> 21.991073 | E7: =CWG!X31/'Feedstock Conversions'!B$9 -> 22.767533 | F7: =DCO!X31/'Feedstock Conversions'!B$8 -> 21.53509 | G7: ='Poultry Fat'!X31/'Feedstock Conversions'!B$10 -> 25.086114 | H7: =UCO!X31/'Feedstock Conversions'!B$4 -> 45.054345 | I7: ='Yellow Grease'!X31/'Feedstock Conversions'!B$3 -> 43.88636 | L7: ='Soybean Oil'!X31 -> 205.06639 | M7: ='Canola Oil'!N31 -> 215.59015 | N7: =BFT!X31 -> 206.27627 | O7: =CWG!X31 -> 213.44562 | P7: =DCO!X31 -> 198.12282 | Q7: ='Poultry Fat'!X31 -> 203.72851 | R7: =UCO!X31 -> 360.8853 | S7: ='Yellow Grease'!X31 -> 373.03406 | V7: =IF($L7-N7>$B7-D7,"YES","NO") -> NO | W7: =IF($L7-O7>$B7-E7,"YES","NO") -> NO | X7: =IF($L7-P7>$B7-F7,"YES","NO") -> YES | Y7: =IF($L7-Q7>$B7-G7,"YES","NO") -> NO | Z7: =IF($L7-R7>$B7-H7,"YES","NO") -> NO | AA7: =IF($L7-S7>$B7-I7,"YES","NO") -> NO
A8: 43679 | B8: ='Soybean Oil'!X32/'Feedstock Conversions'!B$5 -> 27.916456 | D8: =BFT!X32/'Feedstock Conversions'!B$7 -> 22.026962 | E8: =CWG!X32/'Feedstock Conversions'!B$9 -> 22.432368 | F8: =DCO!X32/'Feedstock Conversions'!B$8 -> 21.572493 | G8: ='Poultry Fat'!X32/'Feedstock Conversions'!B$10 -> 25.127257 | H8: =UCO!X32/'Feedstock Conversions'!B$4 -> 45.08985 | I8: ='Yellow Grease'!X32/'Feedstock Conversions'!B$3 -> 43.917745 | L8: ='Soybean Oil'!X32 -> 209.37342 | M8: ='Canola Oil'!N32 -> 212.52937 | N8: =BFT!X32 -> 206.61291 | O8: =CWG!X32 -> 210.30345 | P8: =DCO!X32 -> 198.46694 | Q8: ='Poultry Fat'!X32 -> 204.06264 | R8: =UCO!X32 -> 361.1697 | S8: ='Yellow Grease'!X32 -> 373.30084 | V8: =IF($L8-N8>$B8-D8,"YES","NO") -> NO | W8: =IF($L8-O8>$B8-E8,"YES","NO") -> NO | X8: =IF($L8-P8>$B8-F8,"YES","NO") -> YES | Y8: =IF($L8-Q8>$B8-G8,"YES","NO") -> YES | Z8: =IF($L8-R8>$B8-H8,"YES","NO") -> NO | AA8: =IF($L8-S8>$B8-I8,"YES","NO") -> NO
A9: 43686 | B9: ='Soybean Oil'!X33/'Feedstock Conversions'!B$5 -> 26.657429 | D9: =BFT!X33/'Feedstock Conversions'!B$7 -> 21.242084 | E9: =CWG!X33/'Feedstock Conversions'!B$9 -> 21.648754 | F9: =DCO!X33/'Feedstock Conversions'!B$8 -> 20.772607 | G9: ='Poultry Fat'!X33/'Feedstock Conversions'!B$10 -> 24.220585 | H9: =UCO!X33/'Feedstock Conversions'!B$4 -> 44.167934 | I9: ='Yellow Grease'!X33/'Feedstock Conversions'!B$3 -> 43.048087 | L9: ='Soybean Oil'!X33 -> 199.93072 | M9: ='Canola Oil'!N33 -> 203.08325 | N9: =BFT!X33 -> 199.25075 | O9: =CWG!X33 -> 202.95707 | P9: =DCO!X33 -> 191.10799 | Q9: ='Poultry Fat'!X33 -> 196.69941 | R9: =UCO!X33 -> 353.78515 | S9: ='Yellow Grease'!X33 -> 365.90874 | V9: =IF($L9-N9>$B9-D9,"YES","NO") -> NO | W9: =IF($L9-O9>$B9-E9,"YES","NO") -> NO | X9: =IF($L9-P9>$B9-F9,"YES","NO") -> YES | Y9: =IF($L9-Q9>$B9-G9,"YES","NO") -> YES | Z9: =IF($L9-R9>$B9-H9,"YES","NO") -> NO | AA9: =IF($L9-S9>$B9-I9,"YES","NO") -> NO
A10: 43693 | B10: ='Soybean Oil'!X34/'Feedstock Conversions'!B$5 -> 24.874672 | D10: =BFT!X34/'Feedstock Conversions'!B$7 -> 20.57785 | E10: =CWG!X34/'Feedstock Conversions'!B$9 -> 21.989776 | F10: =DCO!X34/'Feedstock Conversions'!B$8 -> 19.770451 | G10: ='Poultry Fat'!X34/'Feedstock Conversions'!B$10 -> 23.083543 | H10: =UCO!X34/'Feedstock Conversions'!B$4 -> 42.780774 | I10: ='Yellow Grease'!X34/'Feedstock Conversions'!B$3 -> 42.303343 | L10: ='Soybean Oil'!X34 -> 186.56004 | M10: ='Canola Oil'!N34 -> 187.76554 | N10: =BFT!X34 -> 193.02024 | O10: =CWG!X34 -> 206.15415 | P10: =DCO!X34 -> 181.88815 | Q10: ='Poultry Fat'!X34 -> 187.4653 | R10: =UCO!X34 -> 342.674 | S10: ='Yellow Grease'!X34 -> 359.57841 | V10: =IF($L10-N10>$B10-D10,"YES","NO") -> NO | W10: =IF($L10-O10>$B10-E10,"YES","NO") -> NO | X10: =IF($L10-P10>$B10-F10,"YES","NO") -> NO | Y10: =IF($L10-Q10>$B10-G10,"YES","NO") -> NO | Z10: =IF($L10-R10>$B10-H10,"YES","NO") -> NO | AA10: =IF($L10-S10>$B10-I10,"YES","NO") -> NO
A11: 43700 | B11: ='Soybean Oil'!X35/'Feedstock Conversions'!B$5 -> 26.22606 | D11: =BFT!X35/'Feedstock Conversions'!B$7 -> 21.482884 | E11: =CWG!X35/'Feedstock Conversions'!B$9 -> 24.42117 | F11: =DCO!X35/'Feedstock Conversions'!B$8 -> 20.47081 | G11: ='Poultry Fat'!X35/'Feedstock Conversions'!B$10 -> 23.884493 | H11: =UCO!X35/'Feedstock Conversions'!B$4 -> 43.730668 | I11: ='Yellow Grease'!X35/'Feedstock Conversions'!B$3 -> 43.652566 | L11: ='Soybean Oil'!X35 -> 196.69545 | M11: ='Canola Oil'!N35 -> 200.22378 | N11: =BFT!X35 -> 201.50945 | O11: =CWG!X35 -> 228.94847 | P11: =DCO!X35 -> 188.33145 | Q11: ='Poultry Fat'!X35 -> 193.96995 | R11: =UCO!X35 -> 350.28265 | S11: ='Yellow Grease'!X35 -> 371.04681 | V11: =IF($L11-N11>$B11-D11,"YES","NO") -> NO | W11: =IF($L11-O11>$B11-E11,"YES","NO") -> NO | X11: =IF($L11-P11>$B11-F11,"YES","NO") -> YES | Y11: =IF($L11-Q11>$B11-G11,"YES","NO") -> YES | Z11: =IF($L11-R11>$B11-H11,"YES","NO") -> NO | AA11: =IF($L11-S11>$B11-I11,"YES","NO") -> NO
A12: 43707 | B12: ='Soybean Oil'!X36/'Feedstock Conversions'!B$5 -> 27.147016 | D12: =BFT!X36/'Feedstock Conversions'!B$7 -> 22.735725 | E12: =CWG!X36/'Feedstock Conversions'!B$9 -> 25.731248 | F12: =DCO!X36/'Feedstock Conversions'!B$8 -> 20.805101 | G12: ='Poultry Fat'!X36/'Feedstock Conversions'!B$10 -> 24.268814 | H12: =UCO!X36/'Feedstock Conversions'!B$4 -> 44.173675 | I12: ='Yellow Grease'!X36/'Feedstock Conversions'!B$3 -> 44.279513 | L12: ='Soybean Oil'!X36 -> 203.60262 | M12: ='Canola Oil'!N36 -> 205.08617 | N12: =BFT!X36 -> 213.2611 | O12: =CWG!X36 -> 241.23045 | P12: =DCO!X36 -> 191.40693 | Q12: ='Poultry Fat'!X36 -> 197.09108 | R12: =UCO!X36 -> 353.83113 | S12: ='Yellow Grease'!X36 -> 376.37586 | V12: =IF($L12-N12>$B12-D12,"YES","NO") -> NO | W12: =IF($L12-O12>$B12-E12,"YES","NO") -> NO | X12: =IF($L12-P12>$B12-F12,"YES","NO") -> YES | Y12: =IF($L12-Q12>$B12-G12,"YES","NO") -> YES | Z12: =IF($L12-R12>$B12-H12,"YES","NO") -> NO | AA12: =IF($L12-S12>$B12-I12,"YES","NO") -> NO
A13: 43714 | B13: ='Soybean Oil'!X37/'Feedstock Conversions'!B$5 -> 27.218268 | D13: =BFT!X37/'Feedstock Conversions'!B$7 -> 24.623949 | E13: =CWG!X37/'Feedstock Conversions'!B$9 -> 26.424674 | F13: =DCO!X37/'Feedstock Conversions'!B$8 -> 21.067399 | G13: ='Poultry Fat'!X37/'Feedstock Conversions'!B$10 -> 24.564376 | H13: =UCO!X37/'Feedstock Conversions'!B$4 -> 44.502809 | I13: ='Yellow Grease'!X37/'Feedstock Conversions'!B$3 -> 44.587007 | L13: ='Soybean Oil'!X37 -> 204.13701 | M13: ='Canola Oil'!N37 -> 205.03186 | N13: =BFT!X37 -> 230.97264 | O13: =CWG!X37 -> 247.73131 | P13: =DCO!X37 -> 193.82007 | Q13: ='Poultry Fat'!X37 -> 199.49139 | R13: =UCO!X37 -> 356.4675 | S13: ='Yellow Grease'!X37 -> 378.98956 | V13: =IF($L13-N13>$B13-D13,"YES","NO") -> NO | W13: =IF($L13-O13>$B13-E13,"YES","NO") -> NO | X13: =IF($L13-P13>$B13-F13,"YES","NO") -> YES | Y13: =IF($L13-Q13>$B13-G13,"YES","NO") -> YES | Z13: =IF($L13-R13>$B13-H13,"YES","NO") -> NO | AA13: =IF($L13-S13>$B13-I13,"YES","NO") -> NO
... A130: 44533 | B130: ='Soybean Oil'!X154/'Feedstock Conversions'!B$5 -> 2.0000931 | D130: =BFT!X154/'Feedstock Conversions'!B$7 -> 7.8228845 | E130: =CWG!X154/'Feedstock Conversions'!B$9 -> 19.695649 | F130: =DCO!X154/'Feedstock Conversions'!B$8 -> 3.0108786 | G130: ='Poultry Fat'!X154/'Feedstock Conversions'!B$10 -> 3.9164643 | H130: =UCO!X154/'Feedstock Conversions'!B$4 -> 26.451003 | I130: ='Yellow Grease'!X154/'Feedstock Conversions'!B$3 -> 28.329282 | L130: ='Soybean Oil'!X154 -> 15.000698 | M130: ='Canola Oil'!N154 -> -33.509323 | N130: =BFT!X154 -> 73.378657 | O130: =CWG!X154 -> 184.64671 | P130: =DCO!X154 -> 27.700083 | Q130: ='Poultry Fat'!X154 -> 31.806259 | R130: =UCO!X154 -> 211.87253 | S130: ='Yellow Grease'!X154 -> 240.7989 | V130: =IF($L130-N130>$B130-D130,"YES","NO") -> NO | W130: =IF($L130-O130>$B130-E130,"YES","NO") -> NO | X130: =IF($L130-P130>$B130-F130,"YES","NO") -> NO | Y130: =IF($L130-Q130>$B130-G130,"YES","NO") -> NO | Z130: =IF($L130-R130>$B130-H130,"YES","NO") -> NO | AA130: =IF($L130-S130>$B130-I130,"YES","NO") -> NO
A131: 44540 | B131: ='Soybean Oil'!X155/'Feedstock Conversions'!B$5 -> 4.1303166 | C131: =M131/'Feedstock Conversions'!$B$6 -> -2.1878044 | D131: =BFT!X155/'Feedstock Conversions'!B$7 -> 10.949621 | E131: =CWG!X155/'Feedstock Conversions'!B$9 -> 22.948343 | F131: =DCO!X155/'Feedstock Conversions'!B$8 -> 5.5250851 | G131: ='Poultry Fat'!X155/'Feedstock Conversions'!B$10 -> 6.7959349 | H131: =UCO!X155/'Feedstock Conversions'!B$4 -> 26.704722 | I131: ='Yellow Grease'!X155/'Feedstock Conversions'!B$3 -> 31.423095 | L131: ='Soybean Oil'!X155 -> 30.977374 | M131: ='Canola Oil'!N155 -> -16.517923 | N131: =BFT!X155 -> 102.70744 | O131: =CWG!X155 -> 215.14072 | P131: =DCO!X155 -> 50.830783 | Q131: ='Poultry Fat'!X155 -> 55.19092 | R131: =UCO!X155 -> 213.90483 | S131: ='Yellow Grease'!X155 -> 267.09631 | V131: =IF($L131-N131>$B131-D131,"YES","NO") -> NO | W131: =IF($L131-O131>$B131-E131,"YES","NO") -> NO | X131: =IF($L131-P131>$B131-F131,"YES","NO") -> NO | Y131: =IF($L131-Q131>$B131-G131,"YES","NO") -> NO | Z131: =IF($L131-R131>$B131-H131,"YES","NO") -> NO | AA131: =IF($L131-S131>$B131-I131,"YES","NO") -> NO
A132: 44547 | B132: ='Soybean Oil'!X156/'Feedstock Conversions'!B$5 -> 4.7975569 | C132: =M132/'Feedstock Conversions'!$B$6 -> -1.6070549 | D132: =BFT!X156/'Feedstock Conversions'!B$7 -> 10.699376 | E132: =CWG!X156/'Feedstock Conversions'!B$9 -> 22.62057 | F132: =DCO!X156/'Feedstock Conversions'!B$8 -> 5.0347088 | G132: ='Poultry Fat'!X156/'Feedstock Conversions'!B$10 -> 6.2253073 | H132: =UCO!X156/'Feedstock Conversions'!B$4 -> 24.7263 | I132: ='Yellow Grease'!X156/'Feedstock Conversions'!B$3 -> 29.721722 | L132: ='Soybean Oil'!X156 -> 35.981677 | M132: ='Canola Oil'!N156 -> -12.133265 | N132: =BFT!X156 -> 100.36014 | O132: =CWG!X156 -> 212.06784 | P132: =DCO!X156 -> 46.319321 | Q132: ='Poultry Fat'!X156 -> 50.556758 | R132: =UCO!X156 -> 198.05766 | S132: ='Yellow Grease'!X156 -> 252.63464 | V132: =IF($L132-N132>$B132-D132,"YES","NO") -> NO | W132: =IF($L132-O132>$B132-E132,"YES","NO") -> NO | X132: =IF($L132-P132>$B132-F132,"YES","NO") -> NO | Y132: =IF($L132-Q132>$B132-G132,"YES","NO") -> NO | Z132: =IF($L132-R132>$B132-H132,"YES","NO") -> NO | AA132: =IF($L132-S132>$B132-I132,"YES","NO") -> NO
A133: 44554 | B133: ='Soybean Oil'!X157/'Feedstock Conversions'!B$5 -> 5.8534424 | C133: =M133/'Feedstock Conversions'!$B$6 -> -0.58813457 | D133: =BFT!X157/'Feedstock Conversions'!B$7 -> 11.79683 | E133: =CWG!X157/'Feedstock Conversions'!B$9 -> 24.069 | F133: =DCO!X157/'Feedstock Conversions'!B$8 -> 6.6566302 | G133: ='Poultry Fat'!X157/'Feedstock Conversions'!B$10 -> 8.0547826 | H133: =UCO!X157/'Feedstock Conversions'!B$4 -> 26.416564 | I133: ='Yellow Grease'!X157/'Feedstock Conversions'!B$3 -> 31.308425 | L133: ='Soybean Oil'!X157 -> 43.900818 | M133: ='Canola Oil'!N157 -> -4.440416 | N133: =BFT!X157 -> 110.65426 | O133: =CWG!X157 -> 225.64688 | P133: =DCO!X157 -> 61.240998 | Q133: ='Poultry Fat'!X157 -> 65.414232 | R133: =UCO!X157 -> 211.59667 | S133: ='Yellow Grease'!X157 -> 266.12161 | V133: =IF($L133-N133>$B133-D133,"YES","NO") -> NO | W133: =IF($L133-O133>$B133-E133,"YES","NO") -> NO | X133: =IF($L133-P133>$B133-F133,"YES","NO") -> NO | Y133: =IF($L133-Q133>$B133-G133,"YES","NO") -> NO | Z133: =IF($L133-R133>$B133-H133,"YES","NO") -> NO | AA133: =IF($L133-S133>$B133-I133,"YES","NO") -> NO
A134: 44561 | B134: ='Soybean Oil'!X158/'Feedstock Conversions'!B$5 -> 6.0151168 | C134: =M134/'Feedstock Conversions'!$B$6 -> -1.0018858 | D134: =BFT!X158/'Feedstock Conversions'!B$7 -> 12.114928 | E134: =CWG!X158/'Feedstock Conversions'!B$9 -> 25.489728 | F134: =DCO!X158/'Feedstock Conversions'!B$8 -> 8.1231751 | G134: ='Poultry Fat'!X158/'Feedstock Conversions'!B$10 -> 9.7233933 | H134: =UCO!X158/'Feedstock Conversions'!B$4 -> 28.51992 | I134: ='Yellow Grease'!X158/'Feedstock Conversions'!B$3 -> 33.324364 | L134: ='Soybean Oil'!X158 -> 45.113376 | M134: ='Canola Oil'!N158 -> -7.5642377 | N134: =BFT!X158 -> 113.63803 | O134: =CWG!X158 -> 238.9662 | P134: =DCO!X158 -> 74.733211 | Q134: ='Poultry Fat'!X158 -> 78.965298 | R134: =UCO!X158 -> 228.44456 | S134: ='Yellow Grease'!X158 -> 283.25709 | V134: =IF($L134-N134>$B134-D134,"YES","NO") -> NO | W134: =IF($L134-O134>$B134-E134,"YES","NO") -> NO | X134: =IF($L134-P134>$B134-F134,"YES","NO") -> NO | Y134: =IF($L134-Q134>$B134-G134,"YES","NO") -> NO | Z134: =IF($L134-R134>$B134-H134,"YES","NO") -> NO | AA134: =IF($L134-S134>$B134-I134,"YES","NO") -> NO
A135: 44568 | B135: ='Soybean Oil'!X159/'Feedstock Conversions'!B$5 -> 7.3913683 | C135: =M135/'Feedstock Conversions'!$B$6 -> -0.7310722 | D135: =BFT!X159/'Feedstock Conversions'!B$7 -> 9.4937203 | E135: =CWG!X159/'Feedstock Conversions'!B$9 -> 24.94157 | F135: =DCO!X159/'Feedstock Conversions'!B$8 -> 9.9509979 | G135: ='Poultry Fat'!X159/'Feedstock Conversions'!B$10 -> 11.802768 | H135: =UCO!X159/'Feedstock Conversions'!B$4 -> 30.672281 | I135: ='Yellow Grease'!X159/'Feedstock Conversions'!B$3 -> 35.367382 | L135: ='Soybean Oil'!X159 -> 55.435262 | M135: ='Canola Oil'!N159 -> -5.5195951 | N135: =BFT!X159 -> 89.051097 | O135: =CWG!X159 -> 233.82722 | P135: =DCO!X159 -> 91.549181 | Q135: ='Poultry Fat'!X159 -> 95.852248 | R135: =UCO!X159 -> 245.68497 | S135: ='Yellow Grease'!X159 -> 300.62275 | V135: =IF($L135-N135>$B135-D135,"YES","NO") -> NO | W135: =IF($L135-O135>$B135-E135,"YES","NO") -> NO | X135: =IF($L135-P135>$B135-F135,"YES","NO") -> NO | Y135: =IF($L135-Q135>$B135-G135,"YES","NO") -> NO | Z135: =IF($L135-R135>$B135-H135,"YES","NO") -> NO | AA135: =IF($L135-S135>$B135-I135,"YES","NO") -> NO
A136: 44575 | B136: ='Soybean Oil'!X160/'Feedstock Conversions'!B$5 -> 10.872067 | C136: =M136/'Feedstock Conversions'!$B$6 -> 1.2428979 | D136: =BFT!X160/'Feedstock Conversions'!B$7 -> 6.4958676 | E136: =CWG!X160/'Feedstock Conversions'!B$9 -> 20.641312 | F136: =DCO!X160/'Feedstock Conversions'!B$8 -> 11.787708 | G136: ='Poultry Fat'!X160/'Feedstock Conversions'!B$10 -> 13.884525 | H136: =UCO!X160/'Feedstock Conversions'!B$4 -> 31.588251 | I136: ='Yellow Grease'!X160/'Feedstock Conversions'!B$3 -> 36.46315 | L136: ='Soybean Oil'!X160 -> 81.540501 | M136: ='Canola Oil'!N160 -> 9.3838791 | N136: =BFT!X160 -> 60.931238 | O136: =CWG!X160 -> 193.5123 | P136: =DCO!X160 -> 108.44691 | Q136: ='Poultry Fat'!X160 -> 112.75854 | R136: =UCO!X160 -> 253.02189 | S136: ='Yellow Grease'!X160 -> 309.93678 | V136: =IF($L136-N136>$B136-D136,"YES","NO") -> YES | W136: =IF($L136-O136>$B136-E136,"YES","NO") -> NO | X136: =IF($L136-P136>$B136-F136,"YES","NO") -> NO | Y136: =IF($L136-Q136>$B136-G136,"YES","NO") -> NO | Z136: =IF($L136-R136>$B136-H136,"YES","NO") -> NO | AA136: =IF($L136-S136>$B136-I136,"YES","NO") -> NO
A137: 44582 | B137: ='Soybean Oil'!X161/'Feedstock Conversions'!B$5 -> 7.9486907 | C137: =M137/'Feedstock Conversions'!$B$6 -> -1.8720013 | D137: =BFT!X161/'Feedstock Conversions'!B$7 -> 1.4271917 | E137: =CWG!X161/'Feedstock Conversions'!B$9 -> 13.982119 | F137: =DCO!X161/'Feedstock Conversions'!B$8 -> 10.77529 | G137: ='Poultry Fat'!X161/'Feedstock Conversions'!B$10 -> 12.730676 | H137: =UCO!X161/'Feedstock Conversions'!B$4 -> 30.113627 | I137: ='Yellow Grease'!X161/'Feedstock Conversions'!B$3 -> 34.513805 | L137: ='Soybean Oil'!X161 -> 59.61518 | M137: ='Canola Oil'!N161 -> -14.133609 | N137: =BFT!X161 -> 13.387058 | O137: =CWG!X161 -> 131.08236 | P137: =DCO!X161 -> 99.132667 | Q137: ='Poultry Fat'!X161 -> 103.38794 | R137: =UCO!X161 -> 241.21015 | S137: ='Yellow Grease'!X161 -> 293.36735 | V137: =IF($L137-N137>$B137-D137,"YES","NO") -> YES | W137: =IF($L137-O137>$B137-E137,"YES","NO") -> NO | X137: =IF($L137-P137>$B137-F137,"YES","NO") -> NO | Y137: =IF($L137-Q137>$B137-G137,"YES","NO") -> NO | Z137: =IF($L137-R137>$B137-H137,"YES","NO") -> NO | AA137: =IF($L137-S137>$B137-I137,"YES","NO") -> NO
A138: 44589 | B138: ='Soybean Oil'!X162/'Feedstock Conversions'!B$5 -> 9.0578918 | C138: =M138/'Feedstock Conversions'!$B$6 -> -0.89969921 | D138: =BFT!X162/'Feedstock Conversions'!B$7 -> 3.8813392 | E138: =CWG!X162/'Feedstock Conversions'!B$9 -> 11.646462 | F138: =DCO!X162/'Feedstock Conversions'!B$8 -> 11.084987 | G138: ='Poultry Fat'!X162/'Feedstock Conversions'!B$10 -> 13.082655 | H138: =UCO!X162/'Feedstock Conversions'!B$4 -> 32.316769 | I138: ='Yellow Grease'!X162/'Feedstock Conversions'!B$3 -> 36.461132 | L138: ='Soybean Oil'!X162 -> 67.934189 | M138: ='Canola Oil'!N162 -> -6.7927291 | N138: =BFT!X162 -> 36.406961 | O138: =CWG!X162 -> 109.18558 | P138: =DCO!X162 -> 101.98188 | Q138: ='Poultry Fat'!X162 -> 106.24642 | R138: =UCO!X162 -> 258.85732 | S138: ='Yellow Grease'!X162 -> 309.91963 | V138: =IF($L138-N138>$B138-D138,"YES","NO") -> YES | W138: =IF($L138-O138>$B138-E138,"YES","NO") -> NO | X138: =IF($L138-P138>$B138-F138,"YES","NO") -> NO | Y138: =IF($L138-Q138>$B138-G138,"YES","NO") -> NO | Z138: =IF($L138-R138>$B138-H138,"YES","NO") -> NO | AA138: =IF($L138-S138>$B138-I138,"YES","NO") -> NO
A139: 44596 | B139: ='Soybean Oil'!X163/'Feedstock Conversions'!B$5 -> 8.9732609 | C139: =M139/'Feedstock Conversions'!$B$6 -> -1.8084902 | D139: =BFT!X163/'Feedstock Conversions'!B$7 -> 4.2092389 | E139: =CWG!X163/'Feedstock Conversions'!B$9 -> 9.4914808 | F139: =DCO!X163/'Feedstock Conversions'!B$8 -> 9.8334412 | G139: ='Poultry Fat'!X163/'Feedstock Conversions'!B$10 -> 11.643945 | H139: =UCO!X163/'Feedstock Conversions'!B$4 -> 32.999732 | I139: ='Yellow Grease'!X163/'Feedstock Conversions'!B$3 -> 36.84448 | L139: ='Soybean Oil'!X163 -> 67.299457 | M139: ='Canola Oil'!N163 -> -13.654101 | N139: =BFT!X163 -> 39.482661 | O139: =CWG!X163 -> 88.982632 | P139: =DCO!X163 -> 90.467659 | Q139: ='Poultry Fat'!X163 -> 94.562421 | R139: =UCO!X163 -> 264.32786 | S139: ='Yellow Grease'!X163 -> 313.17808 | V139: =IF($L139-N139>$B139-D139,"YES","NO") -> YES | W139: =IF($L139-O139>$B139-E139,"YES","NO") -> NO | X139: =IF($L139-P139>$B139-F139,"YES","NO") -> NO | Y139: =IF($L139-Q139>$B139-G139,"YES","NO") -> NO | Z139: =IF($L139-R139>$B139-H139,"YES","NO") -> NO | AA139: =IF($L139-S139>$B139-I139,"YES","NO") -> NO
A140: 44603 | B140: ='Soybean Oil'!X164/'Feedstock Conversions'!B$5 -> 10.435038 | C140: =M140/'Feedstock Conversions'!$B$6 -> -1.1403471 | D140: =BFT!X164/'Feedstock Conversions'!B$7 -> 4.1997519 | E140: =CWG!X164/'Feedstock Conversions'!B$9 -> 7.7554168 | F140: =DCO!X164/'Feedstock Conversions'!B$8 -> 8.4867959 | G140: ='Poultry Fat'!X164/'Feedstock Conversions'!B$10 -> 10.11103 | H140: =UCO!X164/'Feedstock Conversions'!B$4 -> 31.156729 | I140: ='Yellow Grease'!X164/'Feedstock Conversions'!B$3 -> 33.258811 | L140: ='Soybean Oil'!X164 -> 78.262787 | M140: ='Canola Oil'!N164 -> -8.6096205 | N140: =BFT!X164 -> 39.393672 | O140: =CWG!X164 -> 72.707033 | P140: =DCO!X164 -> 78.078522 | Q140: ='Poultry Fat'!X164 -> 82.113361 | R140: =UCO!X164 -> 249.5654 | S140: ='Yellow Grease'!X164 -> 282.69989 | V140: =IF($L140-N140>$B140-D140,"YES","NO") -> YES | W140: =IF($L140-O140>$B140-E140,"YES","NO") -> YES | X140: =IF($L140-P140>$B140-F140,"YES","NO") -> NO | Y140: =IF($L140-Q140>$B140-G140,"YES","NO") -> NO | Z140: =IF($L140-R140>$B140-H140,"YES","NO") -> NO | AA140: =IF($L140-S140>$B140-I140,"YES","NO") -> NO
A141: 44610 | B141: ='Soybean Oil'!X165/'Feedstock Conversions'!B$5 -> 10.635588 | C141: =M141/'Feedstock Conversions'!$B$6 -> -1.4916546 | D141: =BFT!X165/'Feedstock Conversions'!B$7 -> 5.6690463 | E141: =CWG!X165/'Feedstock Conversions'!B$9 -> 10.212717 | F141: =DCO!X165/'Feedstock Conversions'!B$8 -> 9.431902 | G141: ='Poultry Fat'!X165/'Feedstock Conversions'!B$10 -> 11.177821 | H141: =UCO!X165/'Feedstock Conversions'!B$4 -> 32.593344 | I141: ='Yellow Grease'!X165/'Feedstock Conversions'!B$3 -> 34.606093 | L141: ='Soybean Oil'!X165 -> 79.766912 | M141: ='Canola Oil'!N165 -> -11.261993 | N141: =BFT!X165 -> 53.175655 | O141: =CWG!X165 -> 95.744219 | P141: =DCO!X165 -> 86.773498 | Q141: ='Poultry Fat'!X165 -> 90.776949 | R141: =UCO!X165 -> 261.07268 | S141: ='Yellow Grease'!X165 -> 294.15179 | V141: =IF($L141-N141>$B141-D141,"YES","NO") -> YES | W141: =IF($L141-O141>$B141-E141,"YES","NO") -> NO | X141: =IF($L141-P141>$B141-F141,"YES","NO") -> NO | Y141: =IF($L141-Q141>$B141-G141,"YES","NO") -> NO | Z141: =IF($L141-R141>$B141-H141,"YES","NO") -> NO | AA141: =IF($L141-S141>$B141-I141,"YES","NO") -> NO
A142: 44617 | B142: ='Soybean Oil'!X166/'Feedstock Conversions'!B$5 -> 9.5342761 | C142: =M142/'Feedstock Conversions'!$B$6 -> -2.8550984 | D142: =BFT!X166/'Feedstock Conversions'!B$7 -> 7.100283 | E142: =CWG!X166/'Feedstock Conversions'!B$9 -> 11.099056 | F142: =DCO!X166/'Feedstock Conversions'!B$8 -> 11.214981 | G142: ='Poultry Fat'!X166/'Feedstock Conversions'!B$10 -> 13.19847 | H142: =UCO!X166/'Feedstock Conversions'!B$4 -> 34.145273 | I142: ='Yellow Grease'!X166/'Feedstock Conversions'!B$3 -> 35.401507 | L142: ='Soybean Oil'!X166 -> 71.507071 | M142: ='Canola Oil'!N166 -> -21.555993 | N142: =BFT!X166 -> 66.600655 | O142: =CWG!X166 -> 104.05365 | P142: =DCO!X166 -> 103.17782 | Q142: ='Poultry Fat'!X166 -> 107.18698 | R142: =UCO!X166 -> 273.50363 | S142: ='Yellow Grease'!X166 -> 300.91281 | V142: =IF($L142-N142>$B142-D142,"YES","NO") -> YES | W142: =IF($L142-O142>$B142-E142,"YES","NO") -> NO | X142: =IF($L142-P142>$B142-F142,"YES","NO") -> NO | Y142: =IF($L142-Q142>$B142-G142,"YES","NO") -> NO | Z142: =IF($L142-R142>$B142-H142,"YES","NO") -> NO | AA142: =IF($L142-S142>$B142-I142,"YES","NO") -> NO
... A190: 44953 | B190: ='Soybean Oil'!X214/'Feedstock Conversions'!B$5 -> 20.625576 | C190: =M190/'Feedstock Conversions'!$B$6 -> 20.806799 | D190: =BFT!X214/'Feedstock Conversions'!B$7 -> 8.8280443 | E190: =CWG!X214/'Feedstock Conversions'!B$9 -> 14.664414 | F190: =DCO!X214/'Feedstock Conversions'!B$8 -> 1.487945 | G190: ='Poultry Fat'!X214/'Feedstock Conversions'!B$10 -> 1.9069667 | H190: =UCO!X214/'Feedstock Conversions'!B$4 -> 32.559762 | I190: ='Yellow Grease'!X214/'Feedstock Conversions'!B$3 -> 38.395382 | L190: ='Soybean Oil'!X214 -> 154.69182 | M190: ='Canola Oil'!N214 -> 157.09133 | N190: =BFT!X214 -> 82.807055 | O190: =CWG!X214 -> 137.47889 | P190: =DCO!X214 -> 13.689094 | Q190: ='Poultry Fat'!X214 -> 15.486795 | R190: =UCO!X214 -> 260.80369 | S190: ='Yellow Grease'!X214 -> 326.36074 | V190: =IF($L190-N190>$B190-D190,"YES","NO") -> YES | W190: =IF($L190-O190>$B190-E190,"YES","NO") -> YES | X190: =IF($L190-P190>$B190-F190,"YES","NO") -> YES | Y190: =IF($L190-Q190>$B190-G190,"YES","NO") -> YES | Z190: =IF($L190-R190>$B190-H190,"YES","NO") -> NO | AA190: =IF($L190-S190>$B190-I190,"YES","NO") -> NO
A191: ='Soybean Oil'!A215 -> 44960 | B191: ='Soybean Oil'!X215/'Feedstock Conversions'!B$5 -> 14.891412 | C191: =M191/'Feedstock Conversions'!$B$6 -> 15.337619 | D191: =BFT!X215/'Feedstock Conversions'!B$7 -> 5.9038194 | E191: =CWG!X215/'Feedstock Conversions'!B$9 -> 11.655167 | F191: =DCO!X215/'Feedstock Conversions'!B$8 -> -1.1646772 | G191: ='Poultry Fat'!X215/'Feedstock Conversions'!B$10 -> -1.1034817 | H191: =UCO!X215/'Feedstock Conversions'!B$4 -> 27.232846 | I191: ='Yellow Grease'!X215/'Feedstock Conversions'!B$3 -> 33.366365 | J191: =I191-F191 -> 34.531042 | L191: ='Soybean Oil'!X215 -> 111.68559 | M191: ='Canola Oil'!N215 -> 115.79902 | N191: =BFT!X215 -> 55.377826 | O191: =CWG!X215 -> 109.26719 | P191: =DCO!X215 -> -10.71503 | Q191: ='Poultry Fat'!X215 -> -8.961559 | R191: =UCO!X215 -> 218.13509 | S191: ='Yellow Grease'!X215 -> 283.6141 | V191: =IF($L191-N191>$B191-D191,"YES","NO") -> YES | W191: =IF($L191-O191>$B191-E191,"YES","NO") -> NO | X191: =IF($L191-P191>$B191-F191,"YES","NO") -> YES | Y191: =IF($L191-Q191>$B191-G191,"YES","NO") -> YES | Z191: =IF($L191-R191>$B191-H191,"YES","NO") -> NO | AA191: =IF($L191-S191>$B191-I191,"YES","NO") -> NO
A192: ='Soybean Oil'!A216 -> 44967 | B192: ='Soybean Oil'!X216/'Feedstock Conversions'!B$5 -> 16.688645 | C192: =M192/'Feedstock Conversions'!$B$6 -> 18.874436 | D192: =BFT!X216/'Feedstock Conversions'!B$7 -> 10.855424 | E192: =CWG!X216/'Feedstock Conversions'!B$9 -> 15.117405 | F192: =DCO!X216/'Feedstock Conversions'!B$8 -> 0.74470788 | G192: ='Poultry Fat'!X216/'Feedstock Conversions'!B$10 -> 1.0562123 | H192: =UCO!X216/'Feedstock Conversions'!B$4 -> 30.158469 | I192: ='Yellow Grease'!X216/'Feedstock Conversions'!B$3 -> 33.290649 | J192: =I192-F192 -> 32.545941 | L192: ='Soybean Oil'!X216 -> 125.16483 | M192: ='Canola Oil'!N216 -> 142.50199 | N192: =BFT!X216 -> 101.82388 | O192: =CWG!X216 -> 141.72567 | P192: =DCO!X216 -> 6.8513125 | Q192: ='Poultry Fat'!X216 -> 8.5776758 | R192: =UCO!X216 -> 241.56934 | S192: ='Yellow Grease'!X216 -> 282.97052 | V192: =IF($L192-N192>$B192-D192,"YES","NO") -> YES | W192: =IF($L192-O192>$B192-E192,"YES","NO") -> NO | X192: =IF($L192-P192>$B192-F192,"YES","NO") -> YES | Y192: =IF($L192-Q192>$B192-G192,"YES","NO") -> YES | Z192: =IF($L192-R192>$B192-H192,"YES","NO") -> NO | AA192: =IF($L192-S192>$B192-I192,"YES","NO") -> NO
A193: ='Soybean Oil'!A217 -> 44974 | B193: ='Soybean Oil'!X217/'Feedstock Conversions'!B$5 -> 17.250979 | C193: =M193/'Feedstock Conversions'!$B$6 -> 19.380712 | D193: =BFT!X217/'Feedstock Conversions'!B$7 -> 15.148279 | E193: =CWG!X217/'Feedstock Conversions'!B$9 -> 17.675501 | F193: =DCO!X217/'Feedstock Conversions'!B$8 -> 2.2864149 | G193: ='Poultry Fat'!X217/'Feedstock Conversions'!B$10 -> 2.813791 | H193: =UCO!X217/'Feedstock Conversions'!B$4 -> 35.896944 | I193: ='Yellow Grease'!X217/'Feedstock Conversions'!B$3 -> 35.770624 | J193: =I193-F193 -> 33.484209 | L193: ='Soybean Oil'!X217 -> 129.38234 | M193: ='Canola Oil'!N217 -> 146.32437 | N193: =BFT!X217 -> 142.09086 | O193: =CWG!X217 -> 165.70782 | P193: =DCO!X217 -> 21.035017 | Q193: ='Poultry Fat'!X217 -> 22.851266 | R193: =UCO!X217 -> 287.53452 | S193: ='Yellow Grease'!X217 -> 304.0503 | V193: =IF($L193-N193>$B193-D193,"YES","NO") -> NO | W193: =IF($L193-O193>$B193-E193,"YES","NO") -> NO | X193: =IF($L193-P193>$B193-F193,"YES","NO") -> YES | Y193: =IF($L193-Q193>$B193-G193,"YES","NO") -> YES | Z193: =IF($L193-R193>$B193-H193,"YES","NO") -> NO | AA193: =IF($L193-S193>$B193-I193,"YES","NO") -> NO
A194: ='Soybean Oil'!A218 -> 44981 | B194: ='Soybean Oil'!X218/'Feedstock Conversions'!B$5 -> 15.011419 | C194: =M194/'Feedstock Conversions'!$B$6 -> 17.292784 | D194: =BFT!X218/'Feedstock Conversions'!B$7 -> 14.492677 | E194: =CWG!X218/'Feedstock Conversions'!B$9 -> 18.630542 | F194: =DCO!X218/'Feedstock Conversions'!B$8 -> 2.0380094 | G194: ='Poultry Fat'!X218/'Feedstock Conversions'!B$10 -> 2.5525024 | H194: =UCO!X218/'Feedstock Conversions'!B$4 -> 40.458588 | I194: ='Yellow Grease'!X218/'Feedstock Conversions'!B$3 -> 38.950597 | J194: =I194-F194 -> 36.912588 | L194: ='Soybean Oil'!X218 -> 112.58564 | M194: ='Canola Oil'!N218 -> 130.56052 | N194: =BFT!X218 -> 135.94131 | O194: =CWG!X218 -> 174.66133 | P194: =DCO!X218 -> 18.749687 | Q194: ='Poultry Fat'!X218 -> 20.729298 | R194: =UCO!X218 -> 324.07329 | S194: ='Yellow Grease'!X218 -> 331.08007 | V194: =IF($L194-N194>$B194-D194,"YES","NO") -> NO | W194: =IF($L194-O194>$B194-E194,"YES","NO") -> NO | X194: =IF($L194-P194>$B194-F194,"YES","NO") -> YES | Y194: =IF($L194-Q194>$B194-G194,"YES","NO") -> YES | Z194: =IF($L194-R194>$B194-H194,"YES","NO") -> NO | AA194: =IF($L194-S194>$B194-I194,"YES","NO") -> NO
A195: ='Soybean Oil'!A219 -> 44988 | B195: ='Soybean Oil'!X219/'Feedstock Conversions'!B$5 -> 16.335223 | C195: =M195/'Feedstock Conversions'!$B$6 -> 18.204974 | D195: =BFT!X219/'Feedstock Conversions'!B$7 -> 15.120143 | E195: =CWG!X219/'Feedstock Conversions'!B$9 -> 19.321171 | F195: =DCO!X219/'Feedstock Conversions'!B$8 -> 3.9843452 | G195: ='Poultry Fat'!X219/'Feedstock Conversions'!B$10 -> 4.7453594 | H195: =UCO!X219/'Feedstock Conversions'!B$4 -> 42.687132 | I195: ='Yellow Grease'!X219/'Feedstock Conversions'!B$3 -> 40.821119 | J195: =I195-F195 -> 36.836774 | L195: ='Soybean Oil'!X219 -> 122.51417 | M195: ='Canola Oil'!N219 -> 137.44756 | N195: =BFT!X219 -> 141.82694 | O195: =CWG!X219 -> 181.13598 | P195: =DCO!X219 -> 36.655976 | Q195: ='Poultry Fat'!X219 -> 38.537855 | R195: =UCO!X219 -> 341.92393 | S195: ='Yellow Grease'!X219 -> 346.97951 | V195: =IF($L195-N195>$B195-D195,"YES","NO") -> NO | W195: =IF($L195-O195>$B195-E195,"YES","NO") -> NO | X195: =IF($L195-P195>$B195-F195,"YES","NO") -> YES | Y195: =IF($L195-Q195>$B195-G195,"YES","NO") -> YES | Z195: =IF($L195-R195>$B195-H195,"YES","NO") -> NO | AA195: =IF($L195-S195>$B195-I195,"YES","NO") -> NO
A196: ='Soybean Oil'!A220 -> 44995 | B196: ='Soybean Oil'!X220/'Feedstock Conversions'!B$5 -> 16.39991 | C196: =M196/'Feedstock Conversions'!$B$6 -> 18.107194 | D196: =BFT!X220/'Feedstock Conversions'!B$7 -> 13.16397 | E196: =CWG!X220/'Feedstock Conversions'!B$9 -> 18.16171 | F196: =DCO!X220/'Feedstock Conversions'!B$8 -> 5.0329129 | G196: ='Poultry Fat'!X220/'Feedstock Conversions'!B$10 -> 5.9339238 | H196: =UCO!X220/'Feedstock Conversions'!B$4 -> 40.40011 | I196: ='Yellow Grease'!X220/'Feedstock Conversions'!B$3 -> 39.917121 | J196: =I196-F196 -> 34.884208 | L196: ='Soybean Oil'!X220 -> 122.99933 | M196: ='Canola Oil'!N220 -> 136.70931 | N196: =BFT!X220 -> 123.47804 | O196: =CWG!X220 -> 170.26603 | P196: =DCO!X220 -> 46.302799 | Q196: ='Poultry Fat'!X220 -> 48.190384 | R196: =UCO!X220 -> 323.60488 | S196: ='Yellow Grease'!X220 -> 339.29553 | V196: =IF($L196-N196>$B196-D196,"YES","NO") -> NO | W196: =IF($L196-O196>$B196-E196,"YES","NO") -> NO | X196: =IF($L196-P196>$B196-F196,"YES","NO") -> YES | Y196: =IF($L196-Q196>$B196-G196,"YES","NO") -> YES | Z196: =IF($L196-R196>$B196-H196,"YES","NO") -> NO | AA196: =IF($L196-S196>$B196-I196,"YES","NO") -> NO
A197: ='Soybean Oil'!A221 -> 45002 | B197: ='Soybean Oil'!X221/'Feedstock Conversions'!B$5 -> 15.992366 | C197: =M197/'Feedstock Conversions'!$B$6 -> 18.439998 | D197: =BFT!X221/'Feedstock Conversions'!B$7 -> 14.243503 | E197: =CWG!X221/'Feedstock Conversions'!B$9 -> 18.992241 | F197: =DCO!X221/'Feedstock Conversions'!B$8 -> 5.6942373 | G197: ='Poultry Fat'!X221/'Feedstock Conversions'!B$10 -> 6.6982086 | H197: =UCO!X221/'Feedstock Conversions'!B$4 -> 41.616825 | I197: ='Yellow Grease'!X221/'Feedstock Conversions'!B$3 -> 39.900579 | J197: =I197-F197 -> 34.206342 | L197: ='Soybean Oil'!X221 -> 119.94275 | M197: ='Canola Oil'!N221 -> 139.22199 | N197: =BFT!X221 -> 133.60406 | O197: =CWG!X221 -> 178.05226 | P197: =DCO!X221 -> 52.386983 | Q197: ='Poultry Fat'!X221 -> 54.397269 | R197: =UCO!X221 -> 333.35076 | S197: ='Yellow Grease'!X221 -> 339.15492 | V197: =IF($L197-N197>$B197-D197,"YES","NO") -> NO | W197: =IF($L197-O197>$B197-E197,"YES","NO") -> NO | X197: =IF($L197-P197>$B197-F197,"YES","NO") -> YES | Y197: =IF($L197-Q197>$B197-G197,"YES","NO") -> YES | Z197: =IF($L197-R197>$B197-H197,"YES","NO") -> NO | AA197: =IF($L197-S197>$B197-I197,"YES","NO") -> NO
A198: ='Soybean Oil'!A222 -> 45009 | B198: ='Soybean Oil'!X222/'Feedstock Conversions'!B$5 -> 17.364255 | C198: =M198/'Feedstock Conversions'!$B$6 -> 20.518944 | D198: =BFT!X222/'Feedstock Conversions'!B$7 -> 15.102566 | E198: =CWG!X222/'Feedstock Conversions'!B$9 -> 20.463009 | F198: =DCO!X222/'Feedstock Conversions'!B$8 -> 6.8573277 | G198: ='Poultry Fat'!X222/'Feedstock Conversions'!B$10 -> 8.0121172 | H198: =UCO!X222/'Feedstock Conversions'!B$4 -> 45.632214 | I198: ='Yellow Grease'!X222/'Feedstock Conversions'!B$3 -> 41.020391 | J198: =I198-F198 -> 34.163064 | L198: ='Soybean Oil'!X222 -> 130.23191 | M198: ='Canola Oil'!N222 -> 154.91803 | N198: =BFT!X222 -> 141.66207 | O198: =CWG!X222 -> 191.84071 | P198: =DCO!X222 -> 63.087415 | Q198: ='Poultry Fat'!X222 -> 65.067739 | R198: =UCO!X222 -> 365.51404 | S198: ='Yellow Grease'!X222 -> 348.67333 | V198: =IF($L198-N198>$B198-D198,"YES","NO") -> NO | W198: =IF($L198-O198>$B198-E198,"YES","NO") -> NO | X198: =IF($L198-P198>$B198-F198,"YES","NO") -> YES | Y198: =IF($L198-Q198>$B198-G198,"YES","NO") -> YES | Z198: =IF($L198-R198>$B198-H198,"YES","NO") -> NO | AA198: =IF($L198-S198>$B198-I198,"YES","NO") -> NO
A199: ='Soybean Oil'!A223 -> 45016 | B199: ='Soybean Oil'!X223/'Feedstock Conversions'!B$5 -> 16.118213 | C199: =M199/'Feedstock Conversions'!$B$6 -> 20.169908 | D199: =BFT!X223/'Feedstock Conversions'!B$7 -> 16.916618 | E199: =CWG!X223/'Feedstock Conversions'!B$9 -> 21.281397 | F199: =DCO!X223/'Feedstock Conversions'!B$8 -> 7.4362793 | G199: ='Poultry Fat'!X223/'Feedstock Conversions'!B$10 -> 8.6665725 | H199: =UCO!X223/'Feedstock Conversions'!B$4 -> 45.289905 | I199: ='Yellow Grease'!X223/'Feedstock Conversions'!B$3 -> 40.695446 | J199: =I199-F199 -> 33.259167 | L199: ='Soybean Oil'!X223 -> 120.8866 | M199: ='Canola Oil'!N223 -> 152.28281 | N199: =BFT!X223 -> 158.67788 | O199: =CWG!X223 -> 199.5131 | P199: =DCO!X223 -> 68.41377 | Q199: ='Poultry Fat'!X223 -> 70.38268 | R199: =UCO!X223 -> 362.77214 | S199: ='Yellow Grease'!X223 -> 345.91129 | V199: =IF($L199-N199>$B199-D199,"YES","NO") -> NO | W199: =IF($L199-O199>$B199-E199,"YES","NO") -> NO | X199: =IF($L199-P199>$B199-F199,"YES","NO") -> YES | Y199: =IF($L199-Q199>$B199-G199,"YES","NO") -> YES | Z199: =IF($L199-R199>$B199-H199,"YES","NO") -> NO | AA199: =IF($L199-S199>$B199-I199,"YES","NO") -> NO
A200: ='Soybean Oil'!A224 -> 45023 | B200: ='Soybean Oil'!X224/'Feedstock Conversions'!B$5 -> 15.27284 | C200: =M200/'Feedstock Conversions'!$B$6 -> 19.531887 | D200: =BFT!X224/'Feedstock Conversions'!B$7 -> 17.163144 | E200: =CWG!X224/'Feedstock Conversions'!B$9 -> 20.766512 | F200: =DCO!X224/'Feedstock Conversions'!B$8 -> 7.6681669 | G200: ='Poultry Fat'!X224/'Feedstock Conversions'!B$10 -> 8.9406839 | H200: =UCO!X224/'Feedstock Conversions'!B$4 -> 45.469419 | I200: ='Yellow Grease'!X224/'Feedstock Conversions'!B$3 -> 40.883863 | J200: =I200-F200 -> 33.215696 | L200: ='Soybean Oil'!X224 -> 114.5463 | M200: ='Canola Oil'!N224 -> 147.46574 | N200: =BFT!X224 -> 160.99029 | O200: =CWG!X224 -> 194.68605 | P200: =DCO!X224 -> 70.547136 | Q200: ='Poultry Fat'!X224 -> 72.608784 | R200: =UCO!X224 -> 364.21005 | S200: ='Yellow Grease'!X224 -> 347.51284 | V200: =IF($L200-N200>$B200-D200,"YES","NO") -> NO | W200: =IF($L200-O200>$B200-E200,"YES","NO") -> NO | X200: =IF($L200-P200>$B200-F200,"YES","NO") -> YES | Y200: =IF($L200-Q200>$B200-G200,"YES","NO") -> YES | Z200: =IF($L200-R200>$B200-H200,"YES","NO") -> NO | AA200: =IF($L200-S200>$B200-I200,"YES","NO") -> NO
A201: ='Soybean Oil'!A225 -> 45030 | B201: ='Soybean Oil'!X225/'Feedstock Conversions'!B$5 -> 16.52727 | C201: =M201/'Feedstock Conversions'!$B$6 -> 21.071042 | D201: =BFT!X225/'Feedstock Conversions'!B$7 -> 17.394983 | E201: =CWG!X225/'Feedstock Conversions'!B$9 -> 19.778036 | F201: =DCO!X225/'Feedstock Conversions'!B$8 -> 8.6288361 | G201: ='Poultry Fat'!X225/'Feedstock Conversions'!B$10 -> 10.043201 | H201: =UCO!X225/'Feedstock Conversions'!B$4 -> 45.216386 | I201: ='Yellow Grease'!X225/'Feedstock Conversions'!B$3 -> 41.234818 | J201: =I201-F201 -> 32.605982 | L201: ='Soybean Oil'!X225 -> 123.95452 | M201: ='Canola Oil'!N225 -> 159.08637 | N201: =BFT!X225 -> 163.16494 | O201: =CWG!X225 -> 185.41908 | P201: =DCO!X225 -> 79.385292 | Q201: ='Poultry Fat'!X225 -> 81.562507 | R201: =UCO!X225 -> 362.18325 | S201: ='Yellow Grease'!X225 -> 350.49596 | V201: =IF($L201-N201>$B201-D201,"YES","NO") -> NO | W201: =IF($L201-O201>$B201-E201,"YES","NO") -> NO | X201: =IF($L201-P201>$B201-F201,"YES","NO") -> YES | Y201: =IF($L201-Q201>$B201-G201,"YES","NO") -> YES | Z201: =IF($L201-R201>$B201-H201,"YES","NO") -> NO | AA201: =IF($L201-S201>$B201-I201,"YES","NO") -> NO
A202: ='Soybean Oil'!A226 -> 45037 | B202: ='Soybean Oil'!X226/'Feedstock Conversions'!B$5 -> 15.156791 | C202: =M202/'Feedstock Conversions'!$B$6 -> 18.81609 | D202: =BFT!X226/'Feedstock Conversions'!B$7 -> 14.862808 | E202: =CWG!X226/'Feedstock Conversions'!B$9 -> 17.669283 | F202: =DCO!X226/'Feedstock Conversions'!B$8 -> 8.2878541 | G202: ='Poultry Fat'!X226/'Feedstock Conversions'!B$10 -> 9.6808148 | H202: =UCO!X226/'Feedstock Conversions'!B$4 -> 44.019911 | I202: ='Yellow Grease'!X226/'Feedstock Conversions'!B$3 -> 40.807244 | J202: =I202-F202 -> 32.51939 | L202: ='Soybean Oil'!X226 -> 113.67593 | M202: ='Canola Oil'!N226 -> 142.06148 | N202: =BFT!X226 -> 139.41314 | O202: =CWG!X226 -> 165.64953 | P202: =DCO!X226 -> 76.248257 | Q202: ='Poultry Fat'!X226 -> 78.61951 | R202: =UCO!X226 -> 352.59949 | S202: ='Yellow Grease'!X226 -> 346.86158 | V202: =IF($L202-N202>$B202-D202,"YES","NO") -> NO | W202: =IF($L202-O202>$B202-E202,"YES","NO") -> NO | X202: =IF($L202-P202>$B202-F202,"YES","NO") -> YES | Y202: =IF($L202-Q202>$B202-G202,"YES","NO") -> YES | Z202: =IF($L202-R202>$B202-H202,"YES","NO") -> NO | AA202: =IF($L202-S202>$B202-I202,"YES","NO") -> NO
... A208: ='Soybean Oil'!A232 -> 45079 | B208: ='Soybean Oil'!X232/'Feedstock Conversions'!B$5 -> 13.345526 | C208: =M208/'Feedstock Conversions'!$B$6 -> 18.740018 | D208: =BFT!X232/'Feedstock Conversions'!B$7 -> 5.9904091 | E208: =CWG!X232/'Feedstock Conversions'!B$9 -> 9.4479673 | F208: =DCO!X232/'Feedstock Conversions'!B$8 -> 5.1363664 | G208: ='Poultry Fat'!X232/'Feedstock Conversions'!B$10 -> 6.1173526 | H208: =UCO!X232/'Feedstock Conversions'!B$4 -> 35.649563 | I208: ='Yellow Grease'!X232/'Feedstock Conversions'!B$3 -> 34.475029 | J208: =I208-F208 -> 29.338663 | L208: ='Soybean Oil'!X232 -> 100.09144 | M208: ='Canola Oil'!N232 -> 141.48714 | N208: =BFT!X232 -> 56.190037 | O208: =CWG!X232 -> 88.574694 | P208: =DCO!X232 -> 47.254571 | Q208: ='Poultry Fat'!X232 -> 49.68004 | R208: =UCO!X232 -> 285.553 | S208: ='Yellow Grease'!X232 -> 293.03775 | V208: =IF($L208-N208>$B208-D208,"YES","NO") -> YES | W208: =IF($L208-O208>$B208-E208,"YES","NO") -> YES | X208: =IF($L208-P208>$B208-F208,"YES","NO") -> YES | Y208: =IF($L208-Q208>$B208-G208,"YES","NO") -> YES | Z208: =IF($L208-R208>$B208-H208,"YES","NO") -> NO | AA208: =IF($L208-S208>$B208-I208,"YES","NO") -> NO
A209: 45086 | B209: ='Soybean Oil'!X233/'Feedstock Conversions'!B$5 -> 9.3645567 | C209: =M209/'Feedstock Conversions'!$B$6 -> 13.099185 | D209: =BFT!X233/'Feedstock Conversions'!B$7 -> 6.731684 | E209: =CWG!X233/'Feedstock Conversions'!B$9 -> 9.4463472 | F209: =DCO!X233/'Feedstock Conversions'!B$8 -> 5.9596305 | G209: ='Poultry Fat'!X233/'Feedstock Conversions'!B$10 -> 7.039967 | H209: =UCO!X233/'Feedstock Conversions'!B$4 -> 35.878993 | I209: ='Yellow Grease'!X233/'Feedstock Conversions'!B$3 -> 34.674352 | J209: =I209-F209 -> 28.714721 | L209: ='Soybean Oil'!X233 -> 70.234175 | M209: ='Canola Oil'!N233 -> 98.898846 | N209: =BFT!X233 -> 63.143196 | O209: =CWG!X233 -> 88.559505 | P209: =DCO!X233 -> 54.8286 | Q209: ='Poultry Fat'!X233 -> 57.172745 | R209: =UCO!X233 -> 287.39074 | S209: ='Yellow Grease'!X233 -> 294.73199 | V209: =IF($L209-N209>$B209-D209,"YES","NO") -> YES | W209: =IF($L209-O209>$B209-E209,"YES","NO") -> NO | X209: =IF($L209-P209>$B209-F209,"YES","NO") -> YES | Y209: =IF($L209-Q209>$B209-G209,"YES","NO") -> YES | Z209: =IF($L209-R209>$B209-H209,"YES","NO") -> NO | AA209: =IF($L209-S209>$B209-I209,"YES","NO") -> NO
A210: =A209+7 -> 45093 | B210: ='Soybean Oil'!X234/'Feedstock Conversions'!B$5 -> 4.3633135 | C210: =M210/'Feedstock Conversions'!$B$6 -> 8.4804567 | D210: =BFT!X234/'Feedstock Conversions'!B$7 -> 5.4399889 | E210: =CWG!X234/'Feedstock Conversions'!B$9 -> 9.4957064 | F210: =DCO!X234/'Feedstock Conversions'!B$8 -> 7.4137333 | G210: ='Poultry Fat'!X234/'Feedstock Conversions'!B$10 -> 8.6902225 | H210: =UCO!X234/'Feedstock Conversions'!B$4 -> 32.392699 | I210: ='Yellow Grease'!X234/'Feedstock Conversions'!B$3 -> 35.117361 | J210: =I210-F210 -> 27.703628 | L210: ='Soybean Oil'!X234 -> 32.724851 | M210: ='Canola Oil'!N234 -> 64.027448 | N210: =BFT!X234 -> 51.027096 | O210: =CWG!X234 -> 89.022248 | P210: =DCO!X234 -> 68.206346 | Q210: ='Poultry Fat'!X234 -> 70.574745 | R210: =UCO!X234 -> 259.46552 | S210: ='Yellow Grease'!X234 -> 298.49757 | V210: =IF($L210-N210>$B210-D210,"YES","NO") -> NO | W210: =IF($L210-O210>$B210-E210,"YES","NO") -> NO | X210: =IF($L210-P210>$B210-F210,"YES","NO") -> NO | Y210: =IF($L210-Q210>$B210-G210,"YES","NO") -> NO | Z210: =IF($L210-R210>$B210-H210,"YES","NO") -> NO | AA210: =IF($L210-S210>$B210-I210,"YES","NO") -> NO
A211: =A210+7 -> 45100 | B211: ='Soybean Oil'!X235/'Feedstock Conversions'!B$5 -> 2.8618771 | C211: =M211/'Feedstock Conversions'!$B$6 -> 5.1517951 | D211: =BFT!X235/'Feedstock Conversions'!B$7 -> 2.7250313 | E211: =CWG!X235/'Feedstock Conversions'!B$9 -> 8.3939666 | F211: =DCO!X235/'Feedstock Conversions'!B$8 -> 6.290165 | G211: ='Poultry Fat'!X235/'Feedstock Conversions'!B$10 -> 7.3974131 | H211: =UCO!X235/'Feedstock Conversions'!B$4 -> 26.781053 | I211: ='Yellow Grease'!X235/'Feedstock Conversions'!B$3 -> 32.553403 | J211: =I211-F211 -> 26.263238 | L211: ='Soybean Oil'!X235 -> 21.464078 | M211: ='Canola Oil'!N235 -> 38.896053 | N211: =BFT!X235 -> 25.560794 | O211: =CWG!X235 -> 78.693436 | P211: =DCO!X235 -> 57.869518 | Q211: ='Poultry Fat'!X235 -> 60.075625 | R211: =UCO!X235 -> 214.51624 | S211: ='Yellow Grease'!X235 -> 276.70392 | V211: =IF($L211-N211>$B211-D211,"YES","NO") -> NO | W211: =IF($L211-O211>$B211-E211,"YES","NO") -> NO | X211: =IF($L211-P211>$B211-F211,"YES","NO") -> NO | Y211: =IF($L211-Q211>$B211-G211,"YES","NO") -> NO | Z211: =IF($L211-R211>$B211-H211,"YES","NO") -> NO | AA211: =IF($L211-S211>$B211-I211,"YES","NO") -> NO
A212: =A211+7 -> 45107 | B212: ='Soybean Oil'!X236/'Feedstock Conversions'!B$5 -> -0.64632273 | C212: =M212/'Feedstock Conversions'!$B$6 -> 1.8744998 | D212: =BFT!X236/'Feedstock Conversions'!B$7 -> 0.74645757 | E212: =CWG!X236/'Feedstock Conversions'!B$9 -> 7.9191237 | F212: =DCO!X236/'Feedstock Conversions'!B$8 -> 7.1553446 | G212: ='Poultry Fat'!X236/'Feedstock Conversions'!B$10 -> 8.376427 | H212: =UCO!X236/'Feedstock Conversions'!B$4 -> 28.668735 | I212: ='Yellow Grease'!X236/'Feedstock Conversions'!B$3 -> 33.01112 | J212: =I212-F212 -> 25.855775 | L212: ='Soybean Oil'!X236 -> -4.8474205 | M212: ='Canola Oil'!N236 -> 14.152473 | N212: =BFT!X236 -> 7.001772 | O212: =CWG!X236 -> 74.241785 | P212: =DCO!X236 -> 65.82917 | Q212: ='Poultry Fat'!X236 -> 68.02636 | R212: =UCO!X236 -> 229.63657 | S212: ='Yellow Grease'!X236 -> 280.59452 | V212: =IF($L212-N212>$B212-D212,"YES","NO") -> NO | W212: =IF($L212-O212>$B212-E212,"YES","NO") -> NO | X212: =IF($L212-P212>$B212-F212,"YES","NO") -> NO | Y212: =IF($L212-Q212>$B212-G212,"YES","NO") -> NO | Z212: =IF($L212-R212>$B212-H212,"YES","NO") -> NO | AA212: =IF($L212-S212>$B212-I212,"YES","NO") -> NO
A213: =A212+7 -> 45114 | B213: ='Soybean Oil'!X237/'Feedstock Conversions'!B$5 -> 1.3089963 | C213: =M213/'Feedstock Conversions'!$B$6 -> 2.2537628 | D213: =BFT!X237/'Feedstock Conversions'!B$7 -> 1.8432937 | E213: =CWG!X237/'Feedstock Conversions'!B$9 -> 9.0451809 | F213: =DCO!X237/'Feedstock Conversions'!B$8 -> 9.6727053 | G213: ='Poultry Fat'!X237/'Feedstock Conversions'!B$10 -> 11.219415 | H213: =UCO!X237/'Feedstock Conversions'!B$4 -> 33.294721 | I213: ='Yellow Grease'!X237/'Feedstock Conversions'!B$3 -> 35.376681 | J213: =I213-F213 -> 25.703976 | L213: ='Soybean Oil'!X237 -> 9.8174723 | M213: ='Canola Oil'!N237 -> 17.015909 | N213: =BFT!X237 -> 17.290095 | O213: =CWG!X237 -> 84.798571 | P213: =DCO!X237 -> 88.988889 | Q213: ='Poultry Fat'!X237 -> 91.114741 | R213: =UCO!X237 -> 266.69072 | S213: ='Yellow Grease'!X237 -> 300.70179 | V213: =IF($L213-N213>$B213-D213,"YES","NO") -> NO | W213: =IF($L213-O213>$B213-E213,"YES","NO") -> NO | X213: =IF($L213-P213>$B213-F213,"YES","NO") -> NO | Y213: =IF($L213-Q213>$B213-G213,"YES","NO") -> NO | Z213: =IF($L213-R213>$B213-H213,"YES","NO") -> NO | AA213: =IF($L213-S213>$B213-I213,"YES","NO") -> NO
A214: =A213+7 -> 45121 | B214: ='Soybean Oil'!X238/'Feedstock Conversions'!B$5 -> -0.5365037 | C214: =M214/'Feedstock Conversions'!$B$6 -> 2.3422369 | D214: =BFT!X238/'Feedstock Conversions'!B$7 -> 1.5051694 | E214: =CWG!X238/'Feedstock Conversions'!B$9 -> 7.6340427 | F214: =DCO!X238/'Feedstock Conversions'!B$8 -> 10.536682 | G214: ='Poultry Fat'!X238/'Feedstock Conversions'!B$10 -> 12.189907 | H214: =UCO!X238/'Feedstock Conversions'!B$4 -> 34.211526 | I214: ='Yellow Grease'!X238/'Feedstock Conversions'!B$3 -> 35.603656 | J214: =I214-F214 -> 25.066974 | L214: ='Soybean Oil'!X238 -> -4.0237777 | M214: ='Canola Oil'!N238 -> 17.683889 | N214: =BFT!X238 -> 14.118489 | O214: =CWG!X238 -> 71.56915 | P214: =DCO!X238 -> 96.937474 | Q214: ='Poultry Fat'!X238 -> 98.99627 | R214: =UCO!X238 -> 274.03432 | S214: ='Yellow Grease'!X238 -> 302.63108 | V214: =IF($L214-N214>$B214-D214,"YES","NO") -> NO | W214: =IF($L214-O214>$B214-E214,"YES","NO") -> NO | X214: =IF($L214-P214>$B214-F214,"YES","NO") -> NO | Y214: =IF($L214-Q214>$B214-G214,"YES","NO") -> NO | Z214: =IF($L214-R214>$B214-H214,"YES","NO") -> NO | AA214: =IF($L214-S214>$B214-I214,"YES","NO") -> NO
A215: =A214+7 -> 45128 | B215: ='Soybean Oil'!X239/'Feedstock Conversions'!B$5 -> -1.5190908 | C215: =M215/'Feedstock Conversions'!$B$6 -> 1.4845643 | D215: =BFT!X239/'Feedstock Conversions'!B$7 -> 0.32285098 | E215: =CWG!X239/'Feedstock Conversions'!B$9 -> 6.0435322 | F215: =DCO!X239/'Feedstock Conversions'!B$8 -> 10.852099 | G215: ='Poultry Fat'!X239/'Feedstock Conversions'!B$10 -> 12.54986 | H215: =UCO!X239/'Feedstock Conversions'!B$4 -> 33.714623 | I215: ='Yellow Grease'!X239/'Feedstock Conversions'!B$3 -> 34.582194 | J215: =I215-F215 -> 23.730095 | L215: ='Soybean Oil'!X239 -> -11.393181 | M215: ='Canola Oil'!N239 -> 11.208461 | N215: =BFT!X239 -> 3.0283422 | O215: =CWG!X239 -> 56.658114 | P215: =DCO!X239 -> 99.839309 | Q215: ='Poultry Fat'!X239 -> 101.91951 | R215: =UCO!X239 -> 270.05413 | S215: ='Yellow Grease'!X239 -> 293.94865 | V215: =IF($L215-N215>$B215-D215,"YES","NO") -> NO | W215: =IF($L215-O215>$B215-E215,"YES","NO") -> NO | X215: =IF($L215-P215>$B215-F215,"YES","NO") -> NO | Y215: =IF($L215-Q215>$B215-G215,"YES","NO") -> NO | Z215: =IF($L215-R215>$B215-H215,"YES","NO") -> NO | AA215: =IF($L215-S215>$B215-I215,"YES","NO") -> NO
A216: =A215+7 -> 45135 | B216: ='Soybean Oil'!X240/'Feedstock Conversions'!B$5 -> -0.95969387 | C216: =M216/'Feedstock Conversions'!$B$6 -> 2.0735812 | D216: =BFT!X240/'Feedstock Conversions'!B$7 -> 3.4503864 | E216: =CWG!X240/'Feedstock Conversions'!B$9 -> 8.0162171 | F216: =DCO!X240/'Feedstock Conversions'!B$8 -> 8.4146496 | G216: ='Poultry Fat'!X240/'Feedstock Conversions'!B$10 -> 9.7907231 | H216: =UCO!X240/'Feedstock Conversions'!B$4 -> 37.256676 | I216: ='Yellow Grease'!X240/'Feedstock Conversions'!B$3 -> 38.489024 | J216: =I216-F216 -> 30.074374 | L216: ='Soybean Oil'!X240 -> -7.1977041 | M216: ='Canola Oil'!N240 -> 15.655538 | N216: =BFT!X240 -> 32.364625 | O216: =CWG!X240 -> 75.152035 | P216: =DCO!X240 -> 77.414776 | Q216: ='Poultry Fat'!X240 -> 79.512094 | R216: =UCO!X240 -> 298.42598 | S216: ='Yellow Grease'!X240 -> 327.1567 | V216: =IF($L216-N216>$B216-D216,"YES","NO") -> NO | W216: =IF($L216-O216>$B216-E216,"YES","NO") -> NO | X216: =IF($L216-P216>$B216-F216,"YES","NO") -> NO | Y216: =IF($L216-Q216>$B216-G216,"YES","NO") -> NO | Z216: =IF($L216-R216>$B216-H216,"YES","NO") -> NO | AA216: =IF($L216-S216>$B216-I216,"YES","NO") -> NO
A217: =A216+7 -> 45142 | B217: ='Soybean Oil'!X241/'Feedstock Conversions'!B$5 -> 6.5791743 | C217: =M217/'Feedstock Conversions'!$B$6 -> 7.5653377 | D217: =BFT!X241/'Feedstock Conversions'!B$7 -> 3.6329978 | E217: =CWG!X241/'Feedstock Conversions'!B$9 -> 6.8276083 | F217: =DCO!X241/'Feedstock Conversions'!B$8 -> 4.5746837 | G217: ='Poultry Fat'!X241/'Feedstock Conversions'!B$10 -> 5.4473238 | H217: =UCO!X241/'Feedstock Conversions'!B$4 -> 37.505928 | I217: ='Yellow Grease'!X241/'Feedstock Conversions'!B$3 -> 38.735162 | J217: =I217-F217 -> 34.160478 | L217: ='Soybean Oil'!X241 -> 49.343807 | M217: ='Canola Oil'!N241 -> 57.1183 | N217: =BFT!X241 -> 34.077519 | O217: =CWG!X241 -> 64.008828 | P217: =DCO!X241 -> 42.08709 | Q217: ='Poultry Fat'!X241 -> 44.238624 | R217: =UCO!X241 -> 300.42248 | S217: ='Yellow Grease'!X241 -> 329.24887 | V217: =IF($L217-N217>$B217-D217,"YES","NO") -> YES | W217: =IF($L217-O217>$B217-E217,"YES","NO") -> NO | X217: =IF($L217-P217>$B217-F217,"YES","NO") -> YES | Y217: =IF($L217-Q217>$B217-G217,"YES","NO") -> YES | Z217: =IF($L217-R217>$B217-H217,"YES","NO") -> NO | AA217: =IF($L217-S217>$B217-I217,"YES","NO") -> NO
A218: =A217+7 -> 45149 | B218: ='Soybean Oil'!X242/'Feedstock Conversions'!B$5 -> 10.059556 | C218: =M218/'Feedstock Conversions'!$B$6 -> 12.741479 | D218: =BFT!X242/'Feedstock Conversions'!B$7 -> 4.9459716 | E218: =CWG!X242/'Feedstock Conversions'!B$9 -> 8.4013179 | F218: =DCO!X242/'Feedstock Conversions'!B$8 -> 6.3945539 | G218: ='Poultry Fat'!X242/'Feedstock Conversions'!B$10 -> 7.5215985 | H218: =UCO!X242/'Feedstock Conversions'!B$4 -> 40.047385 | I218: ='Yellow Grease'!X242/'Feedstock Conversions'!B$3 -> 41.151436 | J218: =I218-F218 -> 34.756882 | L218: ='Soybean Oil'!X242 -> 75.44667 | M218: ='Canola Oil'!N242 -> 96.198165 | N218: =BFT!X242 -> 46.393213 | O218: =CWG!X242 -> 78.762356 | P218: =DCO!X242 -> 58.829896 | Q218: ='Poultry Fat'!X242 -> 61.084155 | R218: =UCO!X242 -> 320.77955 | S218: ='Yellow Grease'!X242 -> 349.7872 | V218: =IF($L218-N218>$B218-D218,"YES","NO") -> YES | W218: =IF($L218-O218>$B218-E218,"YES","NO") -> NO | X218: =IF($L218-P218>$B218-F218,"YES","NO") -> YES | Y218: =IF($L218-Q218>$B218-G218,"YES","NO") -> YES | Z218: =IF($L218-R218>$B218-H218,"YES","NO") -> NO | AA218: =IF($L218-S218>$B218-I218,"YES","NO") -> NO
A219: =A218+7 -> 45156 | B219: ='Soybean Oil'!X243/'Feedstock Conversions'!B$5 -> 9.1929477 | C219: =M219/'Feedstock Conversions'!$B$6 -> 11.06103 | D219: =BFT!X243/'Feedstock Conversions'!B$7 -> 4.9020226 | E219: =CWG!X243/'Feedstock Conversions'!B$9 -> 8.4516014 | F219: =DCO!X243/'Feedstock Conversions'!B$8 -> 8.9032508 | G219: ='Poultry Fat'!X243/'Feedstock Conversions'!B$10 -> 10.365489 | H219: =UCO!X243/'Feedstock Conversions'!B$4 -> 40.942997 | I219: ='Yellow Grease'!X243/'Feedstock Conversions'!B$3 -> 41.998677 | J219: =I219-F219 -> 33.095426 | L219: ='Soybean Oil'!X243 -> 68.947108 | M219: ='Canola Oil'!N243 -> 83.510777 | N219: =BFT!X243 -> 45.980972 | O219: =CWG!X243 -> 79.233763 | P219: =DCO!X243 -> 81.909908 | Q219: ='Poultry Fat'!X243 -> 84.179861 | R219: =UCO!X243 -> 327.95341 | S219: ='Yellow Grease'!X243 -> 356.98875 | V219: =IF($L219-N219>$B219-D219,"YES","NO") -> YES | W219: =IF($L219-O219>$B219-E219,"YES","NO") -> NO | X219: =IF($L219-P219>$B219-F219,"YES","NO") -> NO | Y219: =IF($L219-Q219>$B219-G219,"YES","NO") -> NO | Z219: =IF($L219-R219>$B219-H219,"YES","NO") -> NO | AA219: =IF($L219-S219>$B219-I219,"YES","NO") -> NO
A220: =A219+7 -> 45163 | B220: ='Soybean Oil'!X244/'Feedstock Conversions'!B$5 -> 8.5007833 | C220: =M220/'Feedstock Conversions'!$B$6 -> 11.091029 | D220: =BFT!X244/'Feedstock Conversions'!B$7 -> 3.6702284 | E220: =CWG!X244/'Feedstock Conversions'!B$9 -> 7.3367542 | F220: =DCO!X244/'Feedstock Conversions'!B$8 -> 9.3631286 | G220: ='Poultry Fat'!X244/'Feedstock Conversions'!B$10 -> 10.881011 | H220: =UCO!X244/'Feedstock Conversions'!B$4 -> 39.940051 | I220: ='Yellow Grease'!X244/'Feedstock Conversions'!B$3 -> 41.044366 | J220: =I220-F220 -> 31.681237 | L220: ='Soybean Oil'!X244 -> 63.755875 | M220: ='Canola Oil'!N244 -> 83.737269 | N220: =BFT!X244 -> 34.426743 | O220: =CWG!X244 -> 68.78207 | P220: =DCO!X244 -> 86.140783 | Q220: ='Poultry Fat'!X244 -> 88.366508 | R220: =UCO!X244 -> 319.91981 | S220: ='Yellow Grease'!X244 -> 348.87711 | V220: =IF($L220-N220>$B220-D220,"YES","NO") -> YES | W220: =IF($L220-O220>$B220-E220,"YES","NO") -> NO | X220: =IF($L220-P220>$B220-F220,"YES","NO") -> NO | Y220: =IF($L220-Q220>$B220-G220,"YES","NO") -> NO | Z220: =IF($L220-R220>$B220-H220,"YES","NO") -> NO | AA220: =IF($L220-S220>$B220-I220,"YES","NO") -> NO
A221: =A220+7 -> 45170 | B221: ='Soybean Oil'!X245/'Feedstock Conversions'!B$5 -> 10.614762 | C221: =M221/'Feedstock Conversions'!$B$6 -> 13.38126 | D221: =BFT!X245/'Feedstock Conversions'!B$7 -> 4.8177664 | E221: =CWG!X245/'Feedstock Conversions'!B$9 -> 8.2871481 | F221: =DCO!X245/'Feedstock Conversions'!B$8 -> 10.533583 | G221: ='Poultry Fat'!X245/'Feedstock Conversions'!B$10 -> 12.206248 | H221: =UCO!X245/'Feedstock Conversions'!B$4 -> 41.280133 | I221: ='Yellow Grease'!X245/'Feedstock Conversions'!B$3 -> 42.306011 | J221: =I221-F221 -> 31.772428 | L221: ='Soybean Oil'!X245 -> 79.610716 | M221: ='Canola Oil'!N245 -> 101.02851 | N221: =BFT!X245 -> 45.190649 | O221: =CWG!X245 -> 77.692013 | P221: =DCO!X245 -> 96.908961 | Q221: ='Poultry Fat'!X245 -> 99.128978 | R221: =UCO!X245 -> 330.65386 | S221: ='Yellow Grease'!X245 -> 359.60109 | V221: =IF($L221-N221>$B221-D221,"YES","NO") -> YES | W221: =IF($L221-O221>$B221-E221,"YES","NO") -> NO | X221: =IF($L221-P221>$B221-F221,"YES","NO") -> NO | Y221: =IF($L221-Q221>$B221-G221,"YES","NO") -> NO | Z221: =IF($L221-R221>$B221-H221,"YES","NO") -> NO | AA221: =IF($L221-S221>$B221-I221,"YES","NO") -> NO
... A238: =A237+7 -> 45289 | B238: ='Soybean Oil'!X262/'Feedstock Conversions'!B$5 -> 8.8374004 | C238: =M238/'Feedstock Conversions'!$B$6 -> 10.420672 | D238: =BFT!X262/'Feedstock Conversions'!B$7 -> 11.484889 | E238: =CWG!X262/'Feedstock Conversions'!B$9 -> 20.005303 | F238: =DCO!X262/'Feedstock Conversions'!B$8 -> 2.6411433 | G238: ='Poultry Fat'!X262/'Feedstock Conversions'!B$10 -> 3.2304874 | H238: =UCO!X262/'Feedstock Conversions'!B$4 -> 35.926958 | I238: ='Yellow Grease'!X262/'Feedstock Conversions'!B$3 -> 34.211463 | J238: =I238-F238 -> 31.57032 | L238: ='Soybean Oil'!X262 -> 66.280503 | M238: ='Canola Oil'!N262 -> 78.676074 | N238: =BFT!X262 -> 107.72826 | O238: =CWG!X262 -> 187.54972 | P238: =DCO!X262 -> 24.298518 | Q238: ='Poultry Fat'!X262 -> 26.235326 | R238: =UCO!X262 -> 287.77493 | S238: ='Yellow Grease'!X262 -> 290.79744 | V238: =IF($L238-N238>$B238-D238,"YES","NO") -> NO | W238: =IF($L238-O238>$B238-E238,"YES","NO") -> NO | X238: =IF($L238-P238>$B238-F238,"YES","NO") -> YES | Y238: =IF($L238-Q238>$B238-G238,"YES","NO") -> YES | Z238: =IF($L238-R238>$B238-H238,"YES","NO") -> NO | AA238: =IF($L238-S238>$B238-I238,"YES","NO") -> NO
A239: =A238+7 -> 45296 | B239: ='Soybean Oil'!X263/'Feedstock Conversions'!B$5 -> 10.166511 | C239: =M239/'Feedstock Conversions'!$B$6 -> 12.317073 | D239: =BFT!X263/'Feedstock Conversions'!B$7 -> 12.453642 | E239: =CWG!X263/'Feedstock Conversions'!B$9 -> 21.610656 | F239: =DCO!X263/'Feedstock Conversions'!B$8 -> 3.5070006 | G239: ='Poultry Fat'!X263/'Feedstock Conversions'!B$10 -> 4.2078534 | H239: =UCO!X263/'Feedstock Conversions'!B$4 -> 38.119094 | I239: ='Yellow Grease'!X263/'Feedstock Conversions'!B$3 -> 34.97557 | J239: =I239-F239 -> 31.46857 | L239: ='Soybean Oil'!X263 -> 76.248836 | M239: ='Canola Oil'!N263 -> 92.993904 | N239: =BFT!X263 -> 116.81516 | O239: =CWG!X263 -> 202.5999 | P239: =DCO!X263 -> 32.264405 | Q239: ='Poultry Fat'!X263 -> 34.172679 | R239: =UCO!X263 -> 305.33394 | S239: ='Yellow Grease'!X263 -> 297.29235 | T239: =N239*0.44+R239*0.15+P239*0.12+L239*0.15+((S239*0.25+Q239*0.25+O239*0.25+M239*0.25)*0.14) -> 134.45488 | V239: =IF($L239-N239>$B239-D239,"YES","NO") -> NO | W239: =IF($L239-O239>$B239-E239,"YES","NO") -> NO | X239: =IF($L239-P239>$B239-F239,"YES","NO") -> YES | Y239: =IF($L239-Q239>$B239-G239,"YES","NO") -> YES | Z239: =IF($L239-R239>$B239-H239,"YES","NO") -> NO | AA239: =IF($L239-S239>$B239-I239,"YES","NO") -> NO
A240: =A239+7 -> 45303 | B240: ='Soybean Oil'!X264/'Feedstock Conversions'!B$5 -> 8.1012868 | C240: =M240/'Feedstock Conversions'!$B$6 -> 10.027521 | D240: =BFT!X264/'Feedstock Conversions'!B$7 -> 11.439488 | E240: =CWG!X264/'Feedstock Conversions'!B$9 -> 19.508821 | F240: =DCO!X264/'Feedstock Conversions'!B$8 -> 2.2254072 | G240: ='Poultry Fat'!X264/'Feedstock Conversions'!B$10 -> 2.7596118 | H240: =UCO!X264/'Feedstock Conversions'!B$4 -> 36.92034 | I240: ='Yellow Grease'!X264/'Feedstock Conversions'!B$3 -> 34.656258 | J240: =I240-F240 -> 32.430851 | L240: ='Soybean Oil'!X264 -> 60.759651 | M240: ='Canola Oil'!N264 -> 75.707782 | N240: =BFT!X264 -> 107.3024 | O240: =CWG!X264 -> 182.8952 | P240: =DCO!X264 -> 20.473746 | Q240: ='Poultry Fat'!X264 -> 22.411268 | R240: =UCO!X264 -> 295.73192 | S240: ='Yellow Grease'!X264 -> 294.57819 | T240: =N240*0.44+R240*0.15+P240*0.12+L240*0.15+((S240*0.25+Q240*0.25+O240*0.25+M240*0.25)*0.14) -> 123.28938 | V240: =IF($L240-N240>$B240-D240,"YES","NO") -> NO | W240: =IF($L240-O240>$B240-E240,"YES","NO") -> NO | X240: =IF($L240-P240>$B240-F240,"YES","NO") -> YES | Y240: =IF($L240-Q240>$B240-G240,"YES","NO") -> YES | Z240: =IF($L240-R240>$B240-H240,"YES","NO") -> NO | AA240: =IF($L240-S240>$B240-I240,"YES","NO") -> NO
A241: =A240+7 -> 45310 | B241: ='Soybean Oil'!X265/'Feedstock Conversions'!B$5 -> 7.8761273 | C241: =M241/'Feedstock Conversions'!$B$6 -> 9.5904194 | D241: =BFT!X265/'Feedstock Conversions'!B$7 -> 10.997661 | E241: =CWG!X265/'Feedstock Conversions'!B$9 -> 18.336384 | F241: =DCO!X265/'Feedstock Conversions'!B$8 -> 1.6259521 | G241: ='Poultry Fat'!X265/'Feedstock Conversions'!B$10 -> 2.0585857 | H241: =UCO!X265/'Feedstock Conversions'!B$4 -> 35.349761 | I241: ='Yellow Grease'!X265/'Feedstock Conversions'!B$3 -> 34.539233 | J241: =I241-F241 -> 32.913281 | L241: ='Soybean Oil'!X265 -> 59.070955 | M241: ='Canola Oil'!N265 -> 72.407666 | N241: =BFT!X265 -> 103.15806 | O241: =CWG!X265 -> 171.9036 | P241: =DCO!X265 -> 14.958759 | Q241: ='Poultry Fat'!X265 -> 16.718118 | R241: =UCO!X265 -> 283.15158 | S241: ='Yellow Grease'!X265 -> 293.58348 | T241: =N241*0.44+R241*0.15+P241*0.12+L241*0.15+((S241*0.25+Q241*0.25+O241*0.25+M241*0.25)*0.14) -> 117.92943 | V241: =IF($L241-N241>$B241-D241,"YES","NO") -> NO | W241: =IF($L241-O241>$B241-E241,"YES","NO") -> NO | X241: =IF($L241-P241>$B241-F241,"YES","NO") -> YES | Y241: =IF($L241-Q241>$B241-G241,"YES","NO") -> YES | Z241: =IF($L241-R241>$B241-H241,"YES","NO") -> NO | AA241: =IF($L241-S241>$B241-I241,"YES","NO") -> NO
A242: =A241+7 -> 45317 | B242: ='Soybean Oil'!X266/'Feedstock Conversions'!B$5 -> 5.1995491 | C242: =M242/'Feedstock Conversions'!$B$6 -> 6.9551516 | D242: =BFT!X266/'Feedstock Conversions'!B$7 -> 8.831945 | E242: =CWG!X266/'Feedstock Conversions'!B$9 -> 16.21278 | F242: =DCO!X266/'Feedstock Conversions'!B$8 -> 0.078990055 | G242: ='Poultry Fat'!X266/'Feedstock Conversions'!B$10 -> 0.29257219 | H242: =UCO!X266/'Feedstock Conversions'!B$4 -> 32.741765 | I242: ='Yellow Grease'!X266/'Feedstock Conversions'!B$3 -> 32.058738 | J242: =I242-F242 -> 31.979748 | L242: ='Soybean Oil'!X266 -> 38.996618 | M242: ='Canola Oil'!N266 -> 52.511395 | N242: =BFT!X266 -> 82.843644 | O242: =CWG!X266 -> 151.99481 | P242: =DCO!X266 -> 0.7267085 | Q242: ='Poultry Fat'!X266 -> 2.3760275 | R242: =UCO!X266 -> 262.26154 | S242: ='Yellow Grease'!X266 -> 272.49927 | T242: =N242*0.44+R242*0.15+P242*0.12+L242*0.15+((S242*0.25+Q242*0.25+O242*0.25+M242*0.25)*0.14) -> 98.505484 | V242: =IF($L242-N242>$B242-D242,"YES","NO") -> NO | W242: =IF($L242-O242>$B242-E242,"YES","NO") -> NO | X242: =IF($L242-P242>$B242-F242,"YES","NO") -> YES | Y242: =IF($L242-Q242>$B242-G242,"YES","NO") -> YES | Z242: =IF($L242-R242>$B242-H242,"YES","NO") -> NO | AA242: =IF($L242-S242>$B242-I242,"YES","NO") -> NO
A243: =A242+7 -> 45324 | B243: ='Soybean Oil'!X267/'Feedstock Conversions'!B$5 -> 4.3849142 | C243: =M243/'Feedstock Conversions'!$B$6 -> 6.8773885 | D243: =BFT!X267/'Feedstock Conversions'!B$7 -> 7.8719387 | E243: =CWG!X267/'Feedstock Conversions'!B$9 -> 14.248256 | F243: =DCO!X267/'Feedstock Conversions'!B$8 -> -1.6891911 | G243: ='Poultry Fat'!X267/'Feedstock Conversions'!B$10 -> -1.7094438 | H243: =UCO!X267/'Feedstock Conversions'!B$4 -> 30.21791 | I243: ='Yellow Grease'!X267/'Feedstock Conversions'!B$3 -> 29.682153 | J243: =I243-F243 -> 31.371344 | L243: ='Soybean Oil'!X267 -> 32.886857 | M243: ='Canola Oil'!N267 -> 51.924283 | N243: =BFT!X267 -> 73.838785 | O243: =CWG!X267 -> 133.5774 | P243: =DCO!X267 -> -15.540558 | Q243: ='Poultry Fat'!X267 -> -13.882678 | R243: =UCO!X267 -> 242.04546 | S243: ='Yellow Grease'!X267 -> 252.2983 | T243: =N243*0.44+R243*0.15+P243*0.12+L243*0.15+((S243*0.25+Q243*0.25+O243*0.25+M243*0.25)*0.14) -> 86.701152 | V243: =IF($L243-N243>$B243-D243,"YES","NO") -> NO | W243: =IF($L243-O243>$B243-E243,"YES","NO") -> NO | X243: =IF($L243-P243>$B243-F243,"YES","NO") -> YES | Y243: =IF($L243-Q243>$B243-G243,"YES","NO") -> YES | Z243: =IF($L243-R243>$B243-H243,"YES","NO") -> NO | AA243: =IF($L243-S243>$B243-I243,"YES","NO") -> NO
A244: =A243+7 -> 45331 | B244: ='Soybean Oil'!X268/'Feedstock Conversions'!B$5 -> 8.4204596 | C244: =M244/'Feedstock Conversions'!$B$6 -> 10.570884 | D244: =BFT!X268/'Feedstock Conversions'!B$7 -> 11.681527 | E244: =CWG!X268/'Feedstock Conversions'!B$9 -> 17.487384 | F244: =DCO!X268/'Feedstock Conversions'!B$8 -> 2.4144204 | G244: ='Poultry Fat'!X268/'Feedstock Conversions'!B$10 -> 2.9463275 | H244: =UCO!X268/'Feedstock Conversions'!B$4 -> 34.599244 | I244: ='Yellow Grease'!X268/'Feedstock Conversions'!B$3 -> 33.822762 | J244: =I244-F244 -> 31.408342 | L244: ='Soybean Oil'!X268 -> 63.153447 | M244: ='Canola Oil'!N268 -> 79.810175 | N244: =BFT!X268 -> 109.57273 | O244: =CWG!X268 -> 163.94422 | P244: =DCO!X268 -> 22.212667 | Q244: ='Poultry Fat'!X268 -> 23.927617 | R244: =UCO!X268 -> 277.13994 | S244: ='Yellow Grease'!X268 -> 287.49348 | T244: =N244*0.44+R244*0.15+P244*0.12+L244*0.15+((S244*0.25+Q244*0.25+O244*0.25+M244*0.25)*0.14) -> 121.35267 | V244: =IF($L244-N244>$B244-D244,"YES","NO") -> NO | W244: =IF($L244-O244>$B244-E244,"YES","NO") -> NO | X244: =IF($L244-P244>$B244-F244,"YES","NO") -> YES | Y244: =IF($L244-Q244>$B244-G244,"YES","NO") -> YES | Z244: =IF($L244-R244>$B244-H244,"YES","NO") -> NO | AA244: =IF($L244-S244>$B244-I244,"YES","NO") -> NO
A245: =A244+7 -> 45338 | B245: ='Soybean Oil'!X269/'Feedstock Conversions'!B$5 -> 5.1495505 | C245: =M245/'Feedstock Conversions'!$B$6 -> 7.0237693 | D245: =BFT!X269/'Feedstock Conversions'!B$7 -> 6.9127515 | E245: =CWG!X269/'Feedstock Conversions'!B$9 -> 14.172039 | F245: =DCO!X269/'Feedstock Conversions'!B$8 -> -0.2821611 | G245: ='Poultry Fat'!X269/'Feedstock Conversions'!B$10 -> -0.094419076 | H245: =UCO!X269/'Feedstock Conversions'!B$4 -> 30.963035 | I245: ='Yellow Grease'!X269/'Feedstock Conversions'!B$3 -> 30.419864 | J245: =I245-F245 -> 30.702025 | L245: ='Soybean Oil'!X269 -> 38.621629 | M245: ='Canola Oil'!N269 -> 53.029458 | N245: =BFT!X269 -> 64.841609 | O245: =CWG!X269 -> 132.86286 | P245: =DCO!X269 -> -2.5958821 | Q245: ='Poultry Fat'!X269 -> -0.76679305 | R245: =UCO!X269 -> 248.01391 | S245: ='Yellow Grease'!X269 -> 258.56884 | T245: =N245*0.44+R245*0.15+P245*0.12+L245*0.15+((S245*0.25+Q245*0.25+O245*0.25+M245*0.25)*0.14) -> 86.743436 | V245: =IF($L245-N245>$B245-D245,"YES","NO") -> NO | W245: =IF($L245-O245>$B245-E245,"YES","NO") -> NO | X245: =IF($L245-P245>$B245-F245,"YES","NO") -> YES | Y245: =IF($L245-Q245>$B245-G245,"YES","NO") -> YES | Z245: =IF($L245-R245>$B245-H245,"YES","NO") -> NO | AA245: =IF($L245-S245>$B245-I245,"YES","NO") -> NO
A246: =A245+7 -> 45345 | B246: ='Soybean Oil'!X270/'Feedstock Conversions'!B$5 -> 4.6026403 | C246: =M246/'Feedstock Conversions'!$B$6 -> 6.8300323 | D246: =BFT!X270/'Feedstock Conversions'!B$7 -> 5.4422727 | E246: =CWG!X270/'Feedstock Conversions'!B$9 -> 11.75875 | F246: =DCO!X270/'Feedstock Conversions'!B$8 -> 0.37364253 | G246: ='Poultry Fat'!X270/'Feedstock Conversions'!B$10 -> 0.64595553 | H246: =UCO!X270/'Feedstock Conversions'!B$4 -> 28.876229 | I246: ='Yellow Grease'!X270/'Feedstock Conversions'!B$3 -> 28.449062 | J246: =I246-F246 -> 28.07542 | L246: ='Soybean Oil'!X270 -> 34.519802 | M246: ='Canola Oil'!N270 -> 51.566744 | N246: =BFT!X270 -> 51.048518 | O246: =CWG!X270 -> 110.23828 | P246: =DCO!X270 -> 3.4375113 | Q246: ='Poultry Fat'!X270 -> 5.2459125 | R246: =UCO!X270 -> 231.2986 | S246: ='Yellow Grease'!X270 -> 241.81703 | T246: =N246*0.44+R246*0.15+P246*0.12+L246*0.15+((S246*0.25+Q246*0.25+O246*0.25+M246*0.25)*0.14) -> 77.056988 | V246: =IF($L246-N246>$B246-D246,"YES","NO") -> NO | W246: =IF($L246-O246>$B246-E246,"YES","NO") -> NO | X246: =IF($L246-P246>$B246-F246,"YES","NO") -> YES | Y246: =IF($L246-Q246>$B246-G246,"YES","NO") -> YES | Z246: =IF($L246-R246>$B246-H246,"YES","NO") -> NO | AA246: =IF($L246-S246>$B246-I246,"YES","NO") -> NO
A247: =A246+7 -> 45352 | B247: ='Soybean Oil'!X271/'Feedstock Conversions'!B$5 -> 6.1144292 | C247: =M247/'Feedstock Conversions'!$B$6 -> 8.4435165 | D247: =BFT!X271/'Feedstock Conversions'!B$7 -> 6.9191418 | E247: =CWG!X271/'Feedstock Conversions'!B$9 -> 13.205833 | F247: =DCO!X271/'Feedstock Conversions'!B$8 -> 2.4573199 | G247: ='Poultry Fat'!X271/'Feedstock Conversions'!B$10 -> 3.0160078 | H247: =UCO!X271/'Feedstock Conversions'!B$4 -> 31.106478 | I247: ='Yellow Grease'!X271/'Feedstock Conversions'!B$3 -> 30.142827 | J247: =I247-F247 -> 27.685507 | L247: ='Soybean Oil'!X271 -> 45.858219 | M247: ='Canola Oil'!N271 -> 63.748549 | N247: =BFT!X271 -> 64.90155 | O247: =CWG!X271 -> 123.80468 | P247: =DCO!X271 -> 22.607343 | Q247: ='Poultry Fat'!X271 -> 24.493502 | R247: =UCO!X271 -> 249.16289 | S247: ='Yellow Grease'!X271 -> 256.21403 | T247: =N247*0.44+R247*0.15+P247*0.12+L247*0.15+((S247*0.25+Q247*0.25+O247*0.25+M247*0.25)*0.14) -> 91.911856 | V247: =IF($L247-N247>$B247-D247,"YES","NO") -> NO | W247: =IF($L247-O247>$B247-E247,"YES","NO") -> NO | X247: =IF($L247-P247>$B247-F247,"YES","NO") -> YES | Y247: =IF($L247-Q247>$B247-G247,"YES","NO") -> YES | Z247: =IF($L247-R247>$B247-H247,"YES","NO") -> NO | AA247: =IF($L247-S247>$B247-I247,"YES","NO") -> NO
A248: =A247+7 -> 45359 | B248: ='Soybean Oil'!X272/'Feedstock Conversions'!B$5 -> 7.2465936 | C248: =M248/'Feedstock Conversions'!$B$6 -> 8.9951202 | D248: =BFT!X272/'Feedstock Conversions'!B$7 -> 7.6805735 | E248: =CWG!X272/'Feedstock Conversions'!B$9 -> 13.55028 | F248: =DCO!X272/'Feedstock Conversions'!B$8 -> 3.7735291 | G248: ='Poultry Fat'!X272/'Feedstock Conversions'!B$10 -> 4.5125112 | H248: =UCO!X272/'Feedstock Conversions'!B$4 -> 32.327027 | I248: ='Yellow Grease'!X272/'Feedstock Conversions'!B$3 -> 31.01949 | J248: =I248-F248 -> 27.245961 | L248: ='Soybean Oil'!X272 -> 54.349452 | M248: ='Canola Oil'!N272 -> 67.913158 | N248: =BFT!X272 -> 72.04378 | O248: =CWG!X272 -> 127.03388 | P248: =DCO!X272 -> 34.716468 | Q248: ='Poultry Fat'!X272 -> 36.646856 | R248: =UCO!X272 -> 258.93949 | S248: ='Yellow Grease'!X272 -> 263.66567 | T248: =N248*0.44+R248*0.15+P248*0.12+L248*0.15+((S248*0.25+Q248*0.25+O248*0.25+M248*0.25)*0.14) -> 100.19266 | V248: =IF($L248-N248>$B248-D248,"YES","NO") -> NO | W248: =IF($L248-O248>$B248-E248,"YES","NO") -> NO | X248: =IF($L248-P248>$B248-F248,"YES","NO") -> YES | Y248: =IF($L248-Q248>$B248-G248,"YES","NO") -> YES | Z248: =IF($L248-R248>$B248-H248,"YES","NO") -> NO | AA248: =IF($L248-S248>$B248-I248,"YES","NO") -> NO
A249: =A248+7 -> 45366 | B249: ='Soybean Oil'!X273/'Feedstock Conversions'!B$5 -> 7.8913716 | C249: =M249/'Feedstock Conversions'!$B$6 -> 8.8718435 | D249: =BFT!X273/'Feedstock Conversions'!B$7 -> 8.8386753 | E249: =CWG!X273/'Feedstock Conversions'!B$9 -> 14.697645 | F249: =DCO!X273/'Feedstock Conversions'!B$8 -> 6.2022865 | G249: ='Poultry Fat'!X273/'Feedstock Conversions'!B$10 -> 7.2675994 | H249: =UCO!X273/'Feedstock Conversions'!B$4 -> 34.639603 | I249: ='Yellow Grease'!X273/'Feedstock Conversions'!B$3 -> 33.204972 | J249: =I249-F249 -> 27.002686 | L249: ='Soybean Oil'!X273 -> 59.185287 | M249: ='Canola Oil'!N273 -> 66.982418 | N249: =BFT!X273 -> 82.906774 | O249: =CWG!X273 -> 137.79043 | P249: =DCO!X273 -> 57.061036 | Q249: ='Poultry Fat'!X273 -> 59.021386 | R249: =UCO!X273 -> 277.46322 | S249: ='Yellow Grease'!X273 -> 282.24226 | T249: =N249*0.44+R249*0.15+P249*0.12+L249*0.15+((S249*0.25+Q249*0.25+O249*0.25+M249*0.25)*0.14) -> 112.93486 | V249: =IF($L249-N249>$B249-D249,"YES","NO") -> NO | W249: =IF($L249-O249>$B249-E249,"YES","NO") -> NO | X249: =IF($L249-P249>$B249-F249,"YES","NO") -> YES | Y249: =IF($L249-Q249>$B249-G249,"YES","NO") -> NO | Z249: =IF($L249-R249>$B249-H249,"YES","NO") -> NO | AA249: =IF($L249-S249>$B249-I249,"YES","NO") -> NO
A250: =A249+7 -> 45373 | B250: ='Soybean Oil'!X274/'Feedstock Conversions'!B$5 -> 9.2937095 | C250: =M250/'Feedstock Conversions'!$B$6 -> 9.8778413 | D250: =BFT!X274/'Feedstock Conversions'!B$7 -> 9.5998203 | E250: =CWG!X274/'Feedstock Conversions'!B$9 -> 14.444084 | F250: =DCO!X274/'Feedstock Conversions'!B$8 -> 7.1894333 | G250: ='Poultry Fat'!X274/'Feedstock Conversions'!B$10 -> 8.3749886 | H250: =UCO!X274/'Feedstock Conversions'!B$4 -> 35.707368 | I250: ='Yellow Grease'!X274/'Feedstock Conversions'!B$3 -> 34.192821 | J250: =I250-F250 -> 27.003388 | L250: ='Soybean Oil'!X274 -> 69.702822 | M250: ='Canola Oil'!N274 -> 74.577702 | N250: =BFT!X274 -> 90.046315 | O250: =CWG!X274 -> 135.41329 | P250: =DCO!X274 -> 66.142787 | Q250: ='Poultry Fat'!X274 -> 68.014678 | R250: =UCO!X274 -> 286.01602 | S250: ='Yellow Grease'!X274 -> 290.63898 | T250: =N250*0.44+R250*0.15+P250*0.12+L250*0.15+((S250*0.25+Q250*0.25+O250*0.25+M250*0.25)*0.14) -> 120.8179 | V250: =IF($L250-N250>$B250-D250,"YES","NO") -> NO | W250: =IF($L250-O250>$B250-E250,"YES","NO") -> NO | X250: =IF($L250-P250>$B250-F250,"YES","NO") -> YES | Y250: =IF($L250-Q250>$B250-G250,"YES","NO") -> YES | Z250: =IF($L250-R250>$B250-H250,"YES","NO") -> NO | AA250: =IF($L250-S250>$B250-I250,"YES","NO") -> NO
... A306: =A305+7 -> 45765 | B306: ='Soybean Oil'!X330/'Feedstock Conversions'!B$5 -> 6.0676308 | C306: =M306/'Feedstock Conversions'!$B$6 -> 7.1932368 | D306: =BFT!X330/'Feedstock Conversions'!B$7 -> -0.71128346 | E306: =CWG!X330/'Feedstock Conversions'!B$9 -> -4.1238518 | F306: =DCO!X330/'Feedstock Conversions'!B$8 -> 10.061813 | G306: ='Poultry Fat'!X330/'Feedstock Conversions'!B$10 -> 5.3217661 | H306: =UCO!X330/'Feedstock Conversions'!B$4 -> 21.284232 | I306: ='Yellow Grease'!X330/'Feedstock Conversions'!B$3 -> 22.393954 | J306: =I306-F306 -> 12.332141 | L306: ='Soybean Oil'!X330 -> 45.507231 | M306: ='Canola Oil'!N330 -> 54.308938 | N306: =BFT!X330 -> -6.6718388 | O306: =CWG!X330 -> -38.661111 | P306: =DCO!X330 -> 92.568679 | Q306: ='Poultry Fat'!X330 -> 43.218949 | R306: =UCO!X330 -> 170.4867 | S306: ='Yellow Grease'!X330 -> 190.34861 | T306: =N306*0.44+R306*0.15+P306*0.12+L306*0.15+((S306*0.25+Q306*0.25+O306*0.25+M306*0.25)*0.14) -> 49.29426 | V306: =IF($L306-N306>$B306-D306,"YES","NO") -> YES | W306: =IF($L306-O306>$B306-E306,"YES","NO") -> YES | X306: =IF($L306-P306>$B306-F306,"YES","NO") -> NO | Y306: =IF($L306-Q306>$B306-G306,"YES","NO") -> YES | Z306: =IF($L306-R306>$B306-H306,"YES","NO") -> NO | AA306: =IF($L306-S306>$B306-I306,"YES","NO") -> NO

Sheet Soybean Oil
B1: RBD Soybean Oil (Central Illinois) | C1: RBD Soybean Oil (West Coast) | E1: RBD Soybean Oil - BioD | F1: RBD Soybean Oil - RD | H1: Biodiesel w/o Credits | I1: BioD LCFS Credit Value | J1: Biodiesel D4 RIN Credit Value | K1: BTC/45Z Credit Value | L1: Total Revenue | M1: Revenue per Pound | O1: Renewable Diesel | P1: RD LCFS Credit Value | Q1: Renewable Diesel D4 RIN Credit Value | R1: BTC Credit Value | S1: Cap and Trade Credit Value | T1: Total Revenue | U1: Revenue per Pound | W1: Soybean Oil BioD Profit | X1: Soybean Oil RD Profit | AA1: BioD LCFS CI Scores | AB1: RD LCFS CI Scores | AE1: RBD SBO - Gulf | AF1: RBD SBO - Southern Plains | AG1: RBD - SBO Mountain West | AH1: RBD - SBO Eastern Corn Belt | AI1: RBD - SBO Western Corn Belt | AJ1: RBD - SBO Southeast | AK1: RBD - Canadian Refinery | AM1: Gulf BioD Profit | AN1: Southern Plains BioD Profit | AO1: Mountain West BioD Profit | AP1: Eastern Corn Belt BioD Profit | AQ1: Western Corn Belt BioD Profit | AR1: Southeast BioD Profit | AS1: Canadian BioD Profit | AU1: Gulf RD Profit | AV1: Southern Plains RD Profit | AW1: Mountain West RD Profit | AX1: Eastern Corn Belt RD Profit | AY1: Western Corn Belt RD Profit | AZ1: Southeast RD Profit | BA1: Canadian RD Profit | BH1: Week | BI1: Year | BJ1: Month | BM1: Northeast BioD Profit | BN1: Southeast BioD Profit | BO1: Upper Midwest BioD Profit | BP1: Lower Midwest BioD Profit | BQ1: South Central BioD Profit | BR1: Rocky Mountain BioD Profit | BS1: California over max in other regions
A2: 43469 | B2: 31.75 | C2: =B2+'Rail Costs'!B2 -> 36.13 | E2: =C2*'Feedstock Conversions'!B$17 -> 270.975 | H2: ='Fuel Values'!B2-'Soybean Oil'!I2-'Soybean Oil'!J2-'Soybean Oil'!K2 -> 38.450002 | I2: =('LCFS Values'!$E$2-'Soybean Oil'!$AA$4)/1000000*'LCFS Values'!B2*'LCFS Values'!$G$2*100 -> 99.424998 | J2: ='RIN Values'!C2 -> 85.875 | K2: ='Fixed Credits Value'!B2 -> 100 | L2: =H2+I2+J2+K2 -> 323.75 | M2: =L2/'Feedstock Conversions'!B$17 -> 43.166667 | W2: =L2-E2 -> 52.775 | Z2: Low | AA2: =MIN(AA10:AA105) -> 49.16 | AB2: =MIN(AB10:AB105) -> 51.74 | AD2: 43469 | AE2: =B2+'Rail Costs'!K2 -> 32.845 | AF2: =$B2+'Rail Costs'!L2 -> 33.94 | AG2: =$B2+'Rail Costs'!M2 -> 35.035 | AH2: =$B2+'Rail Costs'!N2 -> 32.188 | AI2: =$B2+'Rail Costs'!O2 -> 32.407 | AJ2: =$B2+'Rail Costs'!P2 -> 33.064 | AK2: =(AVERAGEIFS([1]Spreads!$B$23:$B$1056,[1]Spreads!$Y$23:$Y$1056,BH2,[1]Spreads!$X$23:$X$1056,BI2)*1.03)+('Rail Costs'!X2*100/2204.622) -> #VALUE! | AM2: ='Soybean Oil'!$L2-('Soybean Oil'!AE2*'Feedstock Conversions'!$B$17)-'Rail Costs'!Q2 -> 73.703525 | AN2: ='Soybean Oil'!$L2-('Soybean Oil'!AF2*'Feedstock Conversions'!$B$17)-'Rail Costs'!R2 -> 65.899313 | AO2: ='Soybean Oil'!$L2-('Soybean Oil'!AG2*'Feedstock Conversions'!$B$17)-'Rail Costs'!S2 -> 57.856079 | AP2: ='Soybean Oil'!$L2-('Soybean Oil'!AH2*'Feedstock Conversions'!$B$17)-'Rail Costs'!T2 -> 78.807642 | AQ2: ='Soybean Oil'!$L2-('Soybean Oil'!AI2*'Feedstock Conversions'!$B$17)-'Rail Costs'!U2 -> 77.31218 | AR2: ='Soybean Oil'!$L2-('Soybean Oil'!AJ2*'Feedstock Conversions'!$B$17)-'Rail Costs'!V2 -> 71.531171 | AS2: ='Soybean Oil'!$L2-('Soybean Oil'!AK2*'Feedstock Conversions'!$B$17)-'Rail Costs'!Y2 -> #VALUE! | BH2: =WEEKNUM(A2) -> 1 | BI2: =YEAR(A2) -> 2019 | BJ2: =MONTH(A2) -> 1 | BM2: ='Fuel Values'!G2-($E2) -> 1.4 | BN2: ='Fuel Values'!H2-($AJ2*'Feedstock Conversions'!$B$17) -> 8.52 | BO2: ='Fuel Values'!I2-($AI2*'Feedstock Conversions'!$B$17) -> 31.5725 | BP2: ='Fuel Values'!J2-($AH2*'Feedstock Conversions'!$B$17) -> 28.715 | BQ2: ='Fuel Values'!K2-($AF2*'Feedstock Conversions'!$B$17) -> -0.05 | BR2: ='Fuel Values'!L2-($AG2*'Feedstock Conversions'!$B$17) -> 17.2375
A3: 43476 | B3: 31.978 | C3: =B3+'Rail Costs'!B3 -> 36.358 | E3: =C3*'Feedstock Conversions'!B$17 -> 272.685 | H3: ='Fuel Values'!B3-'Soybean Oil'!I3-'Soybean Oil'!J3-'Soybean Oil'!K3 -> 46.170824 | I3: =('LCFS Values'!$E$2-'Soybean Oil'!$AA$4)/1000000*'LCFS Values'!B3*'LCFS Values'!$G$2*100 -> 97.204176 | J3: ='RIN Values'!C3 -> 79.125 | K3: ='Fixed Credits Value'!B3 -> 100 | L3: =H3+I3+J3+K3 -> 322.5 | M3: =L3/'Feedstock Conversions'!B$17 -> 43 | W3: =L3-E3 -> 49.815 | Z3: High | AA3: =MAX(AA10:AA105) -> 66.85 | AB3: =MAX(AB10:AB105) -> 80.81 | AD3: 43476 | AE3: =B3+'Rail Costs'!K3 -> 33.073 | AF3: =$B3+'Rail Costs'!L3 -> 34.168 | AG3: =$B3+'Rail Costs'!M3 -> 35.263 | AH3: =$B3+'Rail Costs'!N3 -> 32.416 | AI3: =$B3+'Rail Costs'!O3 -> 32.635 | AJ3: =$B3+'Rail Costs'!P3 -> 33.292 | AK3: =(AVERAGEIFS([1]Spreads!$B$23:$B$1056,[1]Spreads!$Y$23:$Y$1056,BH3,[1]Spreads!$X$23:$X$1056,BI3)*1.03)+('Rail Costs'!X3*100/2204.622) -> #VALUE! | AM3: ='Soybean Oil'!$L3-('Soybean Oil'!AE3*'Feedstock Conversions'!$B$17)-'Rail Costs'!Q3 -> 70.743525 | AN3: ='Soybean Oil'!$L3-('Soybean Oil'!AF3*'Feedstock Conversions'!$B$17)-'Rail Costs'!R3 -> 62.939313 | AO3: ='Soybean Oil'!$L3-('Soybean Oil'!AG3*'Feedstock Conversions'!$B$17)-'Rail Costs'!S3 -> 54.896079 | AP3: ='Soybean Oil'!$L3-('Soybean Oil'!AH3*'Feedstock Conversions'!$B$17)-'Rail Costs'!T3 -> 75.847642 | AQ3: ='Soybean Oil'!$L3-('Soybean Oil'!AI3*'Feedstock Conversions'!$B$17)-'Rail Costs'!U3 -> 74.35218 | AR3: ='Soybean Oil'!$L3-('Soybean Oil'!AJ3*'Feedstock Conversions'!$B$17)-'Rail Costs'!V3 -> 68.571171 | AS3: ='Soybean Oil'!$L3-('Soybean Oil'!AK3*'Feedstock Conversions'!$B$17)-'Rail Costs'!Y3 -> #VALUE! | BH3: =WEEKNUM(A3) -> 2 | BI3: =YEAR(A3) -> 2019 | BJ3: =MONTH(A3) -> 1 | BM3: ='Fuel Values'!G3-(E3) -> 8.215 | BN3: ='Fuel Values'!H3-($AJ3*'Feedstock Conversions'!$B$5) -> 19.71 | BO3: ='Fuel Values'!I3-($AI3*'Feedstock Conversions'!$B$17) -> 32.8375 | BP3: ='Fuel Values'!J3-($AH3*'Feedstock Conversions'!$B$17) -> 30.28 | BQ3: ='Fuel Values'!K3-($AF3*'Feedstock Conversions'!$B$17) -> 6.94 | BR3: ='Fuel Values'!L3-($AG3*'Feedstock Conversions'!$B$17) -> 17.8275 | BS3: =W3-MAX(BM3:BR3) -> 16.9775
A4: 43483 | B4: 31.82 | C4: =B4+'Rail Costs'!B4 -> 36.2 | E4: =C4*'Feedstock Conversions'!B$17 -> 271.5 | H4: ='Fuel Values'!B4-'Soybean Oil'!I4-'Soybean Oil'!J4-'Soybean Oil'!K4 -> 50.339821 | I4: =('LCFS Values'!$E$2-'Soybean Oil'!$AA$4)/1000000*'LCFS Values'!B4*'LCFS Values'!$G$2*100 -> 97.460179 | J4: ='RIN Values'!C4 -> 74.7 | K4: ='Fixed Credits Value'!B4 -> 100 | L4: =H4+I4+J4+K4 -> 322.5 | M4: =L4/'Feedstock Conversions'!B$17 -> 43 | W4: =L4-E4 -> 51 | Z4: Average | AA4: =AVERAGE(AA10:AA105) -> 56.094211 | AB4: =AVERAGE(AB10:AB105) -> 60.604444 | AD4: 43483 | AE4: =B4+'Rail Costs'!K4 -> 32.915 | AF4: =$B4+'Rail Costs'!L4 -> 34.01 | AG4: =$B4+'Rail Costs'!M4 -> 35.105 | AH4: =$B4+'Rail Costs'!N4 -> 32.258 | AI4: =$B4+'Rail Costs'!O4 -> 32.477 | AJ4: =$B4+'Rail Costs'!P4 -> 33.134 | AK4: =(AVERAGEIFS([1]Spreads!$B$23:$B$1056,[1]Spreads!$Y$23:$Y$1056,BH4,[1]Spreads!$X$23:$X$1056,BI4)*1.03)+('Rail Costs'!X4*100/2204.622) -> #VALUE! | AM4: ='Soybean Oil'!$L4-('Soybean Oil'!AE4*'Feedstock Conversions'!$B$17)-'Rail Costs'!Q4 -> 71.928525 | AN4: ='Soybean Oil'!$L4-('Soybean Oil'!AF4*'Feedstock Conversions'!$B$17)-'Rail Costs'!R4 -> 64.124313 | AO4: ='Soybean Oil'!$L4-('Soybean Oil'!AG4*'Feedstock Conversions'!$B$17)-'Rail Costs'!S4 -> 56.081079 | AP4: ='Soybean Oil'!$L4-('Soybean Oil'!AH4*'Feedstock Conversions'!$B$17)-'Rail Costs'!T4 -> 77.032642 | AQ4: ='Soybean Oil'!$L4-('Soybean Oil'!AI4*'Feedstock Conversions'!$B$17)-'Rail Costs'!U4 -> 75.53718 | AR4: ='Soybean Oil'!$L4-('Soybean Oil'!AJ4*'Feedstock Conversions'!$B$17)-'Rail Costs'!V4 -> 69.756171 | AS4: ='Soybean Oil'!$L4-('Soybean Oil'!AK4*'Feedstock Conversions'!$B$17)-'Rail Costs'!Y4 -> #VALUE! | BH4: =WEEKNUM(A4) -> 3 | BI4: =YEAR(A4) -> 2019 | BJ4: =MONTH(A4) -> 1 | BM4: ='Fuel Values'!G4-(E4) -> 16 | BN4: ='Fuel Values'!H4-($AJ4*'Feedstock Conversions'!$B$5) -> 29.495 | BO4: ='Fuel Values'!I4-($AI4*'Feedstock Conversions'!$B$17) -> 36.4225 | BP4: ='Fuel Values'!J4-($AH4*'Feedstock Conversions'!$B$17) -> 34.065 | BQ4: ='Fuel Values'!K4-($AF4*'Feedstock Conversions'!$B$17) -> 16.925 | BR4: ='Fuel Values'!L4-($AG4*'Feedstock Conversions'!$B$17) -> 21.2125 | BS4: =W4-MAX(BM4:BR4) -> 14.5775
A5: 43490 | B5: 32.595 | C5: =B5+'Rail Costs'!B5 -> 36.975 | E5: =C5*'Feedstock Conversions'!B$17 -> 277.3125 | H5: ='Fuel Values'!B5-'Soybean Oil'!I5-'Soybean Oil'!J5-'Soybean Oil'!K5 -> 43.966565 | I5: =('LCFS Values'!$E$2-'Soybean Oil'!$AA$4)/1000000*'LCFS Values'!B5*'LCFS Values'!$G$2*100 -> 98.048985 | J5: ='RIN Values'!C5 -> 80.48445 | K5: ='Fixed Credits Value'!B5 -> 100 | L5: =H5+I5+J5+K5 -> 322.5 | M5: =L5/'Feedstock Conversions'!B$17 -> 43 | W5: =L5-E5 -> 45.1875 | AD5: 43490 | AE5: =B5+'Rail Costs'!K5 -> 33.69 | AF5: =$B5+'Rail Costs'!L5 -> 34.785 | AG5: =$B5+'Rail Costs'!M5 -> 35.88 | AH5: =$B5+'Rail Costs'!N5 -> 33.033 | AI5: =$B5+'Rail Costs'!O5 -> 33.252 | AJ5: =$B5+'Rail Costs'!P5 -> 33.909 | AK5: =(AVERAGEIFS([1]Spreads!$B$23:$B$1056,[1]Spreads!$Y$23:$Y$1056,BH5,[1]Spreads!$X$23:$X$1056,BI5)*1.03)+('Rail Costs'!X5*100/2204.622) -> #VALUE! | AM5: ='Soybean Oil'!$L5-('Soybean Oil'!AE5*'Feedstock Conversions'!$B$17)-'Rail Costs'!Q5 -> 66.116025 | AN5: ='Soybean Oil'!$L5-('Soybean Oil'!AF5*'Feedstock Conversions'!$B$17)-'Rail Costs'!R5 -> 58.311813 | AO5: ='Soybean Oil'!$L5-('Soybean Oil'!AG5*'Feedstock Conversions'!$B$17)-'Rail Costs'!S5 -> 50.268579 | AP5: ='Soybean Oil'!$L5-('Soybean Oil'!AH5*'Feedstock Conversions'!$B$17)-'Rail Costs'!T5 -> 71.220142 | AQ5: ='Soybean Oil'!$L5-('Soybean Oil'!AI5*'Feedstock Conversions'!$B$17)-'Rail Costs'!U5 -> 69.72468 | AR5: ='Soybean Oil'!$L5-('Soybean Oil'!AJ5*'Feedstock Conversions'!$B$17)-'Rail Costs'!V5 -> 63.943671 | AS5: ='Soybean Oil'!$L5-('Soybean Oil'!AK5*'Feedstock Conversions'!$B$17)-'Rail Costs'!Y5 -> #VALUE! | BH5: =WEEKNUM(A5) -> 4 | BI5: =YEAR(A5) -> 2019 | BJ5: =MONTH(A5) -> 1 | BM5: ='Fuel Values'!G5-(E5) -> 8.3125 | BN5: ='Fuel Values'!H5-($AJ5*'Feedstock Conversions'!$B$5) -> 20.6825 | BO5: ='Fuel Values'!I5-($AI5*'Feedstock Conversions'!$B$17) -> 28.735 | BP5: ='Fuel Values'!J5-($AH5*'Feedstock Conversions'!$B$17) -> 27.8775 | BQ5: ='Fuel Values'!K5-($AF5*'Feedstock Conversions'!$B$17) -> 13.1125 | BR5: ='Fuel Values'!L5-($AG5*'Feedstock Conversions'!$B$17) -> 14.275 | BS5: =W5-MAX(BM5:BR5) -> 16.4525
A6: 43497 | B6: 33.278 | C6: =B6+'Rail Costs'!B6 -> 37.658 | E6: =C6*'Feedstock Conversions'!B$17 -> 282.435 | H6: ='Fuel Values'!B6-'Soybean Oil'!I6-'Soybean Oil'!J6-'Soybean Oil'!K6 -> 39.948209 | I6: =('LCFS Values'!$E$2-'Soybean Oil'!$AA$4)/1000000*'LCFS Values'!B6*'LCFS Values'!$G$2*100 -> 98.701791 | J6: ='RIN Values'!C6 -> 83.85 | K6: ='Fixed Credits Value'!B6 -> 100 | L6: =H6+I6+J6+K6 -> 322.5 | M6: =L6/'Feedstock Conversions'!B$17 -> 43 | W6: =L6-E6 -> 40.065 | AD6: 43497 | AE6: =B6+'Rail Costs'!K6 -> 34.373 | AF6: =$B6+'Rail Costs'!L6 -> 35.468 | AG6: =$B6+'Rail Costs'!M6 -> 36.563 | AH6: =$B6+'Rail Costs'!N6 -> 33.716 | AI6: =$B6+'Rail Costs'!O6 -> 33.935 | AJ6: =$B6+'Rail Costs'!P6 -> 34.592 | AK6: =(AVERAGEIFS([1]Spreads!$B$23:$B$1056,[1]Spreads!$Y$23:$Y$1056,BH6,[1]Spreads!$X$23:$X$1056,BI6)*1.03)+('Rail Costs'!X6*100/2204.622) -> #VALUE! | AM6: ='Soybean Oil'!$L6-('Soybean Oil'!AE6*'Feedstock Conversions'!$B$17)-'Rail Costs'!Q6 -> 60.993525 | AN6: ='Soybean Oil'!$L6-('Soybean Oil'!AF6*'Feedstock Conversions'!$B$17)-'Rail Costs'!R6 -> 53.189313 | AO6: ='Soybean Oil'!$L6-('Soybean Oil'!AG6*'Feedstock Conversions'!$B$17)-'Rail Costs'!S6 -> 45.146079 | AP6: ='Soybean Oil'!$L6-('Soybean Oil'!AH6*'Feedstock Conversions'!$B$17)-'Rail Costs'!T6 -> 66.097642 | AQ6: ='Soybean Oil'!$L6-('Soybean Oil'!AI6*'Feedstock Conversions'!$B$17)-'Rail Costs'!U6 -> 64.60218 | AR6: ='Soybean Oil'!$L6-('Soybean Oil'!AJ6*'Feedstock Conversions'!$B$17)-'Rail Costs'!V6 -> 58.821171 | AS6: ='Soybean Oil'!$L6-('Soybean Oil'!AK6*'Feedstock Conversions'!$B$17)-'Rail Costs'!Y6 -> #VALUE! | BH6: =WEEKNUM(A6) -> 5 | BI6: =YEAR(A6) -> 2019 | BJ6: =MONTH(A6) -> 2 | BM6: ='Fuel Values'!G6-(E6) -> 4.965 | BN6: ='Fuel Values'!H6-($AJ6*'Feedstock Conversions'!$B$5) -> 16.36 | BO6: ='Fuel Values'!I6-($AI6*'Feedstock Conversions'!$B$17) -> 25.9875 | BP6: ='Fuel Values'!J6-($AH6*'Feedstock Conversions'!$B$17) -> 23.53 | BQ6: ='Fuel Values'!K6-($AF6*'Feedstock Conversions'!$B$17) -> 10.39 | BR6: ='Fuel Values'!L6-($AG6*'Feedstock Conversions'!$B$17) -> 9.9775 | BS6: =W6-MAX(BM6:BR6) -> 14.0775
A7: 43504 | B7: 33.478 | C7: =B7+'Rail Costs'!B7 -> 37.858 | E7: =C7*'Feedstock Conversions'!B$17 -> 283.935 | H7: ='Fuel Values'!B7-'Soybean Oil'!I7-'Soybean Oil'!J7-'Soybean Oil'!K7 -> 38.616201 | I7: =('LCFS Values'!$E$2-'Soybean Oil'!$AA$4)/1000000*'LCFS Values'!B7*'LCFS Values'!$G$2*100 -> 99.533799 | J7: ='RIN Values'!C7 -> 85.05 | K7: ='Fixed Credits Value'!B7 -> 100 | L7: =H7+I7+J7+K7 -> 323.2 | M7: =L7/'Feedstock Conversions'!B$17 -> 43.093333 | W7: =L7-E7 -> 39.265 | AD7: 43504 | AE7: =B7+'Rail Costs'!K7 -> 34.573 | AF7: =$B7+'Rail Costs'!L7 -> 35.668 | AG7: =$B7+'Rail Costs'!M7 -> 36.763 | AH7: =$B7+'Rail Costs'!N7 -> 33.916 | AI7: =$B7+'Rail Costs'!O7 -> 34.135 | AJ7: =$B7+'Rail Costs'!P7 -> 34.792 | AK7: =(AVERAGEIFS([1]Spreads!$B$23:$B$1056,[1]Spreads!$Y$23:$Y$1056,BH7,[1]Spreads!$X$23:$X$1056,BI7)*1.03)+('Rail Costs'!X7*100/2204.622) -> #VALUE! | AM7: ='Soybean Oil'!$L7-('Soybean Oil'!AE7*'Feedstock Conversions'!$B$17)-'Rail Costs'!Q7 -> 60.193525 | AN7: ='Soybean Oil'!$L7-('Soybean Oil'!AF7*'Feedstock Conversions'!$B$17)-'Rail Costs'!R7 -> 52.389313 | AO7: ='Soybean Oil'!$L7-('Soybean Oil'!AG7*'Feedstock Conversions'!$B$17)-'Rail Costs'!S7 -> 44.346079 | AP7: ='Soybean Oil'!$L7-('Soybean Oil'!AH7*'Feedstock Conversions'!$B$17)-'Rail Costs'!T7 -> 65.297642 | AQ7: ='Soybean Oil'!$L7-('Soybean Oil'!AI7*'Feedstock Conversions'!$B$17)-'Rail Costs'!U7 -> 63.80218 | AR7: ='Soybean Oil'!$L7-('Soybean Oil'!AJ7*'Feedstock Conversions'!$B$17)-'Rail Costs'!V7 -> 58.021171 | AS7: ='Soybean Oil'!$L7-('Soybean Oil'!AK7*'Feedstock Conversions'!$B$17)-'Rail Costs'!Y7 -> #VALUE! | BH7: =WEEKNUM(A7) -> 6 | BI7: =YEAR(A7) -> 2019 | BJ7: =MONTH(A7) -> 2 | BM7: ='Fuel Values'!G7-(E7) -> 5.065 | BN7: ='Fuel Values'!H7-($AJ7*'Feedstock Conversions'!$B$5) -> 16.06 | BO7: ='Fuel Values'!I7-($AI7*'Feedstock Conversions'!$B$17) -> 26.8875 | BP7: ='Fuel Values'!J7-($AH7*'Feedstock Conversions'!$B$17) -> 23.13 | BQ7: ='Fuel Values'!K7-($AF7*'Feedstock Conversions'!$B$17) -> 10.49 | BR7: ='Fuel Values'!L7-($AG7*'Feedstock Conversions'!$B$17) -> 9.9775 | BS7: =W7-MAX(BM7:BR7) -> 12.3775
A8: 43511 | B8: 32.78 | C8: =B8+'Rail Costs'!B8 -> 37.16 | E8: =C8*'Feedstock Conversions'!B$17 -> 278.7 | H8: ='Fuel Values'!B8-'Soybean Oil'!I8-'Soybean Oil'!J8-'Soybean Oil'!K8 -> 43.893391 | I8: =('LCFS Values'!$E$2-'Soybean Oil'!$AA$4)/1000000*'LCFS Values'!B8*'LCFS Values'!$G$2*100 -> 100.50661 | J8: ='RIN Values'!C8 -> 82.8 | K8: ='Fixed Credits Value'!B8 -> 100 | L8: =H8+I8+J8+K8 -> 327.2 | M8: =L8/'Feedstock Conversions'!B$17 -> 43.626667 | W8: =L8-E8 -> 48.5 | AA8: Current CI Certifications | AD8: 43511 | AE8: =B8+'Rail Costs'!K8 -> 33.875 | AF8: =$B8+'Rail Costs'!L8 -> 34.97 | AG8: =$B8+'Rail Costs'!M8 -> 36.065 | AH8: =$B8+'Rail Costs'!N8 -> 33.218 | AI8: =$B8+'Rail Costs'!O8 -> 33.437 | AJ8: =$B8+'Rail Costs'!P8 -> 34.094 | AK8: =(AVERAGEIFS([1]Spreads!$B$23:$B$1056,[1]Spreads!$Y$23:$Y$1056,BH8,[1]Spreads!$X$23:$X$1056,BI8)*1.03)+('Rail Costs'!X8*100/2204.622) -> #VALUE! | AM8: ='Soybean Oil'!$L8-('Soybean Oil'!AE8*'Feedstock Conversions'!$B$17)-'Rail Costs'!Q8 -> 69.428525 | AN8: ='Soybean Oil'!$L8-('Soybean Oil'!AF8*'Feedstock Conversions'!$B$17)-'Rail Costs'!R8 -> 61.624313 | AO8: ='Soybean Oil'!$L8-('Soybean Oil'!AG8*'Feedstock Conversions'!$B$17)-'Rail Costs'!S8 -> 53.581079 | AP8: ='Soybean Oil'!$L8-('Soybean Oil'!AH8*'Feedstock Conversions'!$B$17)-'Rail Costs'!T8 -> 74.532642 | AQ8: ='Soybean Oil'!$L8-('Soybean Oil'!AI8*'Feedstock Conversions'!$B$17)-'Rail Costs'!U8 -> 73.03718 | AR8: ='Soybean Oil'!$L8-('Soybean Oil'!AJ8*'Feedstock Conversions'!$B$17)-'Rail Costs'!V8 -> 67.256171 | AS8: ='Soybean Oil'!$L8-('Soybean Oil'!AK8*'Feedstock Conversions'!$B$17)-'Rail Costs'!Y8 -> #VALUE! | BH8: =WEEKNUM(A8) -> 7 | BI8: =YEAR(A8) -> 2019 | BJ8: =MONTH(A8) -> 2 | BM8: ='Fuel Values'!G8-(E8) -> 9.7 | BN8: ='Fuel Values'!H8-($AJ8*'Feedstock Conversions'!$B$5) -> 21.895 | BO8: ='Fuel Values'!I8-($AI8*'Feedstock Conversions'!$B$17) -> 36.1225 | BP8: ='Fuel Values'!J8-($AH8*'Feedstock Conversions'!$B$17) -> 28.265 | BQ8: ='Fuel Values'!K8-($AF8*'Feedstock Conversions'!$B$17) -> 15.725 | BR8: ='Fuel Values'!L8-($AG8*'Feedstock Conversions'!$B$17) -> 18.9125 | BS8: =W8-MAX(BM8:BR8) -> 12.3775
A9: 43518 | B9: 32.675 | C9: =B9+'Rail Costs'!B9 -> 37.055 | E9: =C9*'Feedstock Conversions'!B$17 -> 277.9125 | H9: ='Fuel Values'!B9-'Soybean Oil'!I9-'Soybean Oil'!J9-'Soybean Oil'!K9 -> 44.853044 | I9: =('LCFS Values'!$E$2-'Soybean Oil'!$AA$4)/1000000*'LCFS Values'!B9*'LCFS Values'!$G$2*100 -> 100.22501 | J9: ='RIN Values'!C9 -> 82.92195 | K9: ='Fixed Credits Value'!B9 -> 100 | L9: =H9+I9+J9+K9 -> 328 | M9: =L9/'Feedstock Conversions'!B$17 -> 43.733333 | W9: =L9-E9 -> 50.0875 | AA9: BioD | AB9: RD | AC9: SAF | AD9: 43518 | AE9: =B9+'Rail Costs'!K9 -> 33.77 | AF9: =$B9+'Rail Costs'!L9 -> 34.865 | AG9: =$B9+'Rail Costs'!M9 -> 35.96 | AH9: =$B9+'Rail Costs'!N9 -> 33.113 | AI9: =$B9+'Rail Costs'!O9 -> 33.332 | AJ9: =$B9+'Rail Costs'!P9 -> 33.989 | AK9: =(AVERAGEIFS([1]Spreads!$B$23:$B$1056,[1]Spreads!$Y$23:$Y$1056,BH9,[1]Spreads!$X$23:$X$1056,BI9)*1.03)+('Rail Costs'!X9*100/2204.622) -> #VALUE! | AM9: ='Soybean Oil'!$L9-('Soybean Oil'!AE9*'Feedstock Conversions'!$B$17)-'Rail Costs'!Q9 -> 71.016025 | AN9: ='Soybean Oil'!$L9-('Soybean Oil'!AF9*'Feedstock Conversions'!$B$17)-'Rail Costs'!R9 -> 63.211813 | AO9: ='Soybean Oil'!$L9-('Soybean Oil'!AG9*'Feedstock Conversions'!$B$17)-'Rail Costs'!S9 -> 55.168579 | AP9: ='Soybean Oil'!$L9-('Soybean Oil'!AH9*'Feedstock Conversions'!$B$17)-'Rail Costs'!T9 -> 76.120142 | AQ9: ='Soybean Oil'!$L9-('Soybean Oil'!AI9*'Feedstock Conversions'!$B$17)-'Rail Costs'!U9 -> 74.62468 | AR9: ='Soybean Oil'!$L9-('Soybean Oil'!AJ9*'Feedstock Conversions'!$B$17)-'Rail Costs'!V9 -> 68.843671 | AS9: ='Soybean Oil'!$L9-('Soybean Oil'!AK9*'Feedstock Conversions'!$B$17)-'Rail Costs'!Y9 -> #VALUE! | BH9: =WEEKNUM(A9) -> 8 | BI9: =YEAR(A9) -> 2019 | BJ9: =MONTH(A9) -> 2 | BM9: ='Fuel Values'!G9-(E9) -> 13.8375 | BN9: ='Fuel Values'!H9-($AJ9*'Feedstock Conversions'!$B$5) -> 27.2075 | BO9: ='Fuel Values'!I9-($AI9*'Feedstock Conversions'!$B$17) -> 36.635 | BP9: ='Fuel Values'!J9-($AH9*'Feedstock Conversions'!$B$17) -> 29.9025 | BQ9: ='Fuel Values'!K9-($AF9*'Feedstock Conversions'!$B$17) -> 19.1375 | BR9: ='Fuel Values'!L9-($AG9*'Feedstock Conversions'!$B$17) -> 20.3 | BS9: =W9-MAX(BM9:BR9) -> 13.4525
A10: 43525 | B10: 32.59 | C10: =B10+'Rail Costs'!B10 -> 36.97 | E10: =C10*'Feedstock Conversions'!B$17 -> 277.275 | H10: ='Fuel Values'!B10-'Soybean Oil'!I10-'Soybean Oil'!J10-'Soybean Oil'!K10 -> 47.894591 | I10: =('LCFS Values'!$E$2-'Soybean Oil'!$AA$4)/1000000*'LCFS Values'!B10*'LCFS Values'!$G$2*100 -> 100.45541 | J10: ='RIN Values'!C10 -> 79.65 | K10: ='Fixed Credits Value'!B10 -> 100 | L10: =H10+I10+J10+K10 -> 328 | M10: =L10/'Feedstock Conversions'!B$17 -> 43.733333 | W10: =L10-E10 -> 50.725 | AA10: 56.03 | AB10: 56.57 | AD10: 43525 | AE10: =B10+'Rail Costs'!K10 -> 33.685 | AF10: =$B10+'Rail Costs'!L10 -> 34.78 | AG10: =$B10+'Rail Costs'!M10 -> 35.875 | AH10: =$B10+'Rail Costs'!N10 -> 33.028 | AI10: =$B10+'Rail Costs'!O10 -> 33.247 | AJ10: =$B10+'Rail Costs'!P10 -> 33.904 | AK10: =(AVERAGEIFS([1]Spreads!$B$23:$B$1056,[1]Spreads!$Y$23:$Y$1056,BH10,[1]Spreads!$X$23:$X$1056,BI10)*1.03)+('Rail Costs'!X10*100/2204.622) -> #VALUE! | AM10: ='Soybean Oil'!$L10-('Soybean Oil'!AE10*'Feedstock Conversions'!$B$17)-'Rail Costs'!Q10 -> 71.653525 | AN10: ='Soybean Oil'!$L10-('Soybean Oil'!AF10*'Feedstock Conversions'!$B$17)-'Rail Costs'!R10 -> 63.849313 | AO10: ='Soybean Oil'!$L10-('Soybean Oil'!AG10*'Feedstock Conversions'!$B$17)-'Rail Costs'!S10 -> 55.806079 | AP10: ='Soybean Oil'!$L10-('Soybean Oil'!AH10*'Feedstock Conversions'!$B$17)-'Rail Costs'!T10 -> 76.757642 | AQ10: ='Soybean Oil'!$L10-('Soybean Oil'!AI10*'Feedstock Conversions'!$B$17)-'Rail Costs'!U10 -> 75.26218 | AR10: ='Soybean Oil'!$L10-('Soybean Oil'!AJ10*'Feedstock Conversions'!$B$17)-'Rail Costs'!V10 -> 69.481171 | AS10: ='Soybean Oil'!$L10-('Soybean Oil'!AK10*'Feedstock Conversions'!$B$17)-'Rail Costs'!Y10 -> #VALUE! | BH10: =WEEKNUM(A10) -> 9 | BI10: =YEAR(A10) -> 2019 | BJ10: =MONTH(A10) -> 3 | BM10: ='Fuel Values'!G10-(E10) -> 15.725 | BN10: ='Fuel Values'!H10-($AJ10*'Feedstock Conversions'!$B$5) -> 29.22 | BO10: ='Fuel Values'!I10-($AI10*'Feedstock Conversions'!$B$17) -> 36.6475 | BP10: ='Fuel Values'!J10-($AH10*'Feedstock Conversions'!$B$17) -> 31.29 | BQ10: ='Fuel Values'!K10-($AF10*'Feedstock Conversions'!$B$17) -> 20.65 | BR10: ='Fuel Values'!L10-($AG10*'Feedstock Conversions'!$B$17) -> 20.9375 | BS10: =W10-MAX(BM10:BR10) -> 14.0775
A11: 43532 | B11: 32.26 | C11: =B11+'Rail Costs'!B11 -> 36.64 | E11: =C11*'Feedstock Conversions'!B$17 -> 274.8 | H11: ='Fuel Values'!B11-'Soybean Oil'!I11-'Soybean Oil'!J11-'Soybean Oil'!K11 -> 54.779796 | I11: =('LCFS Values'!$E$2-'Soybean Oil'!$AA$4)/1000000*'LCFS Values'!B11*'LCFS Values'!$G$2*100 -> 100.0202 | J11: ='RIN Values'!C11 -> 73.2 | K11: ='Fixed Credits Value'!B11 -> 100 | L11: =H11+I11+J11+K11 -> 328 | M11: =L11/'Feedstock Conversions'!B$17 -> 43.733333 | W11: =L11-E11 -> 53.2 | AA11: 52.45 | AB11: 58.34 | AD11: 43532 | AE11: =B11+'Rail Costs'!K11 -> 33.355 | AF11: =$B11+'Rail Costs'!L11 -> 34.45 | AG11: =$B11+'Rail Costs'!M11 -> 35.545 | AH11: =$B11+'Rail Costs'!N11 -> 32.698 | AI11: =$B11+'Rail Costs'!O11 -> 32.917 | AJ11: =$B11+'Rail Costs'!P11 -> 33.574 | AK11: =(AVERAGEIFS([1]Spreads!$B$23:$B$1056,[1]Spreads!$Y$23:$Y$1056,BH11,[1]Spreads!$X$23:$X$1056,BI11)*1.03)+('Rail Costs'!X11*100/2204.622) -> #VALUE! | AM11: ='Soybean Oil'!$L11-('Soybean Oil'!AE11*'Feedstock Conversions'!$B$17)-'Rail Costs'!Q11 -> 74.128525 | AN11: ='Soybean Oil'!$L11-('Soybean Oil'!AF11*'Feedstock Conversions'!$B$17)-'Rail Costs'!R11 -> 66.324313 | AO11: ='Soybean Oil'!$L11-('Soybean Oil'!AG11*'Feedstock Conversions'!$B$17)-'Rail Costs'!S11 -> 58.281079 | AP11: ='Soybean Oil'!$L11-('Soybean Oil'!AH11*'Feedstock Conversions'!$B$17)-'Rail Costs'!T11 -> 79.232642 | AQ11: ='Soybean Oil'!$L11-('Soybean Oil'!AI11*'Feedstock Conversions'!$B$17)-'Rail Costs'!U11 -> 77.73718 | AR11: ='Soybean Oil'!$L11-('Soybean Oil'!AJ11*'Feedstock Conversions'!$B$17)-'Rail Costs'!V11 -> 71.956171 | AS11: ='Soybean Oil'!$L11-('Soybean Oil'!AK11*'Feedstock Conversions'!$B$17)-'Rail Costs'!Y11 -> #VALUE! | BH11: =WEEKNUM(A11) -> 10 | BI11: =YEAR(A11) -> 2019 | BJ11: =MONTH(A11) -> 3 | BM11: ='Fuel Values'!G11-(E11) -> 13.4 | BN11: ='Fuel Values'!H11-($AJ11*'Feedstock Conversions'!$B$5) -> 27.195 | BO11: ='Fuel Values'!I11-($AI11*'Feedstock Conversions'!$B$17) -> 33.1225 | BP11: ='Fuel Values'!J11-($AH11*'Feedstock Conversions'!$B$17) -> 29.865 | BQ11: ='Fuel Values'!K11-($AF11*'Feedstock Conversions'!$B$17) -> 18.925 | BR11: ='Fuel Values'!L11-($AG11*'Feedstock Conversions'!$B$17) -> 18.9125 | BS11: =W11-MAX(BM11:BR11) -> 20.0775
A12: 43539 | B12: 32.112 | C12: =B12+'Rail Costs'!B12 -> 36.492 | E12: =C12*'Feedstock Conversions'!B$17 -> 273.69 | H12: ='Fuel Values'!B12-'Soybean Oil'!I12-'Soybean Oil'!J12-'Soybean Oil'!K12 -> 62.177395 | I12: =('LCFS Values'!$E$2-'Soybean Oil'!$AA$4)/1000000*'LCFS Values'!B12*'LCFS Values'!$G$2*100 -> 100.12261 | J12: ='RIN Values'!C12 -> 65.7 | K12: ='Fixed Credits Value'!B12 -> 100 | L12: =H12+I12+J12+K12 -> 328 | M12: =L12/'Feedstock Conversions'!B$17 -> 43.733333 | W12: =L12-E12 -> 54.31 | AA12: 50.85 | AB12: 53.86 | AD12: 43539 | AE12: =B12+'Rail Costs'!K12 -> 33.207 | AF12: =$B12+'Rail Costs'!L12 -> 34.302 | AG12: =$B12+'Rail Costs'!M12 -> 35.397 | AH12: =$B12+'Rail Costs'!N12 -> 32.55 | AI12: =$B12+'Rail Costs'!O12 -> 32.769 | AJ12: =$B12+'Rail Costs'!P12 -> 33.426 | AK12: =(AVERAGEIFS([1]Spreads!$B$23:$B$1056,[1]Spreads!$Y$23:$Y$1056,BH12,[1]Spreads!$X$23:$X$1056,BI12)*1.03)+('Rail Costs'!X12*100/2204.622) -> #VALUE! | AM12: ='Soybean Oil'!$L12-('Soybean Oil'!AE12*'Feedstock Conversions'!$B$17)-'Rail Costs'!Q12 -> 75.238525 | AN12: ='Soybean Oil'!$L12-('Soybean Oil'!AF12*'Feedstock Conversions'!$B$17)-'Rail Costs'!R12 -> 67.434313 | AO12: ='Soybean Oil'!$L12-('Soybean Oil'!AG12*'Feedstock Conversions'!$B$17)-'Rail Costs'!S12 -> 59.391079 | AP12: ='Soybean Oil'!$L12-('Soybean Oil'!AH12*'Feedstock Conversions'!$B$17)-'Rail Costs'!T12 -> 80.342642 | AQ12: ='Soybean Oil'!$L12-('Soybean Oil'!AI12*'Feedstock Conversions'!$B$17)-'Rail Costs'!U12 -> 78.84718 | AR12: ='Soybean Oil'!$L12-('Soybean Oil'!AJ12*'Feedstock Conversions'!$B$17)-'Rail Costs'!V12 -> 73.066171 | AS12: ='Soybean Oil'!$L12-('Soybean Oil'!AK12*'Feedstock Conversions'!$B$17)-'Rail Costs'!Y12 -> #VALUE! | BH12: =WEEKNUM(A12) -> 11 | BI12: =YEAR(A12) -> 2019 | BJ12: =MONTH(A12) -> 3 | BM12: ='Fuel Values'!G12-(E12) -> 9.71 | BN12: ='Fuel Values'!H12-($AJ12*'Feedstock Conversions'!$B$5) -> 24.905 | BO12: ='Fuel Values'!I12-($AI12*'Feedstock Conversions'!$B$17) -> 31.8325 | BP12: ='Fuel Values'!J12-($AH12*'Feedstock Conversions'!$B$17) -> 28.375 | BQ12: ='Fuel Values'!K12-($AF12*'Feedstock Conversions'!$B$17) -> 17.035 | BR12: ='Fuel Values'!L12-($AG12*'Feedstock Conversions'!$B$17) -> 18.0225 | BS12: =W12-MAX(BM12:BR12) -> 22.4775
A13: 43546 | B13: 31.542 | C13: =B13+'Rail Costs'!B13 -> 35.922 | E13: =C13*'Feedstock Conversions'!B$17 -> 269.415 | H13: ='Fuel Values'!B13-'Soybean Oil'!I13-'Soybean Oil'!J13-'Soybean Oil'!K13 -> 71.378595 | I13: =('LCFS Values'!$E$2-'Soybean Oil'!$AA$4)/1000000*'LCFS Values'!B13*'LCFS Values'!$G$2*100 -> 100.0714 | J13: ='RIN Values'!C13 -> 56.55 | K13: ='Fixed Credits Value'!B13 -> 100 | L13: =H13+I13+J13+K13 -> 328 | M13: =L13/'Feedstock Conversions'!B$17 -> 43.733333 | W13: =L13-E13 -> 58.585 | AA13: 49.16 | AB13: 64.24 | AD13: 43546 | AE13: =B13+'Rail Costs'!K13 -> 32.637 | AF13: =$B13+'Rail Costs'!L13 -> 33.732 | AG13: =$B13+'Rail Costs'!M13 -> 34.827 | AH13: =$B13+'Rail Costs'!N13 -> 31.98 | AI13: =$B13+'Rail Costs'!O13 -> 32.199 | AJ13: =$B13+'Rail Costs'!P13 -> 32.856 | AK13: =(AVERAGEIFS([1]Spreads!$B$23:$B$1056,[1]Spreads!$Y$23:$Y$1056,BH13,[1]Spreads!$X$23:$X$1056,BI13)*1.03)+('Rail Costs'!X13*100/2204.622) -> #VALUE! | AM13: ='Soybean Oil'!$L13-('Soybean Oil'!AE13*'Feedstock Conversions'!$B$17)-'Rail Costs'!Q13 -> 79.513525 | AN13: ='Soybean Oil'!$L13-('Soybean Oil'!AF13*'Feedstock Conversions'!$B$17)-'Rail Costs'!R13 -> 71.709313 | AO13: ='Soybean Oil'!$L13-('Soybean Oil'!AG13*'Feedstock Conversions'!$B$17)-'Rail Costs'!S13 -> 63.666079 | AP13: ='Soybean Oil'!$L13-('Soybean Oil'!AH13*'Feedstock Conversions'!$B$17)-'Rail Costs'!T13 -> 84.617642 | AQ13: ='Soybean Oil'!$L13-('Soybean Oil'!AI13*'Feedstock Conversions'!$B$17)-'Rail Costs'!U13 -> 83.12218 | AR13: ='Soybean Oil'!$L13-('Soybean Oil'!AJ13*'Feedstock Conversions'!$B$17)-'Rail Costs'!V13 -> 77.341171 | AS13: ='Soybean Oil'!$L13-('Soybean Oil'!AK13*'Feedstock Conversions'!$B$17)-'Rail Costs'!Y13 -> #VALUE! | BH13: =WEEKNUM(A13) -> 12 | BI13: =YEAR(A13) -> 2019 | BJ13: =MONTH(A13) -> 3 | BM13: ='Fuel Values'!G13-(E13) -> 11.585 | BN13: ='Fuel Values'!H13-($AJ13*'Feedstock Conversions'!$B$5) -> 25.58 | BO13: ='Fuel Values'!I13-($AI13*'Feedstock Conversions'!$B$17) -> 37.3075 | BP13: ='Fuel Values'!J13-($AH13*'Feedstock Conversions'!$B$17) -> 32.05 | BQ13: ='Fuel Values'!K13-($AF13*'Feedstock Conversions'!$B$17) -> 21.01 | BR13: ='Fuel Values'!L13-($AG13*'Feedstock Conversions'!$B$17) -> 22.5975 | BS13: =W13-MAX(BM13:BR13) -> 21.2775
A14: 43553 | B14: 31.056 | C14: =B14+'Rail Costs'!B14 -> 35.436 | E14: =C14*'Feedstock Conversions'!B$17 -> 265.77 | H14: ='Fuel Values'!B14-'Soybean Oil'!I14-'Soybean Oil'!J14-'Soybean Oil'!K14 -> 72.828806 | I14: =('LCFS Values'!$E$2-'Soybean Oil'!$AA$4)/1000000*'LCFS Values'!B14*'LCFS Values'!$G$2*100 -> 98.996194 | J14: ='RIN Values'!C14 -> 56.175 | K14: ='Fixed Credits Value'!B14 -> 100 | L14: =H14+I14+J14+K14 -> 328 | M14: =L14/'Feedstock Conversions'!B$17 -> 43.733333 | W14: =L14-E14 -> 62.23 | AA14: 51.11 | AB14: 57.64 | AD14: 43553 | AE14: =B14+'Rail Costs'!K14 -> 32.151 | AF14: =$B14+'Rail Costs'!L14 -> 33.246 | AG14: =$B14+'Rail Costs'!M14 -> 34.341 | AH14: =$B14+'Rail Costs'!N14 -> 31.494 | AI14: =$B14+'Rail Costs'!O14 -> 31.713 | AJ14: =$B14+'Rail Costs'!P14 -> 32.37 | AK14: =(AVERAGEIFS([1]Spreads!$B$23:$B$1056,[1]Spreads!$Y$23:$Y$1056,BH14,[1]Spreads!$X$23:$X$1056,BI14)*1.03)+('Rail Costs'!X14*100/2204.622) -> #VALUE! | AM14: ='Soybean Oil'!$L14-('Soybean Oil'!AE14*'Feedstock Conversions'!$B$17)-'Rail Costs'!Q14 -> 83.158525 | AN14: ='Soybean Oil'!$L14-('Soybean Oil'!AF14*'Feedstock Conversions'!$B$17)-'Rail Costs'!R14 -> 75.354313 | AO14: ='Soybean Oil'!$L14-('Soybean Oil'!AG14*'Feedstock Conversions'!$B$17)-'Rail Costs'!S14 -> 67.311079 | AP14: ='Soybean Oil'!$L14-('Soybean Oil'!AH14*'Feedstock Conversions'!$B$17)-'Rail Costs'!T14 -> 88.262642 | AQ14: ='Soybean Oil'!$L14-('Soybean Oil'!AI14*'Feedstock Conversions'!$B$17)-'Rail Costs'!U14 -> 86.76718 | AR14: ='Soybean Oil'!$L14-('Soybean Oil'!AJ14*'Feedstock Conversions'!$B$17)-'Rail Costs'!V14 -> 80.986171 | AS14: ='Soybean Oil'!$L14-('Soybean Oil'!AK14*'Feedstock Conversions'!$B$17)-'Rail Costs'!Y14 -> #VALUE! | BH14: =WEEKNUM(A14) -> 13 | BI14: =YEAR(A14) -> 2019 | BJ14: =MONTH(A14) -> 3 | BM14: ='Fuel Values'!G14-(E14) -> 15.23 | BN14: ='Fuel Values'!H14-($AJ14*'Feedstock Conversions'!$B$5) -> 27.225 | BO14: ='Fuel Values'!I14-($AI14*'Feedstock Conversions'!$B$17) -> 40.1525 | BP14: ='Fuel Values'!J14-($AH14*'Feedstock Conversions'!$B$17) -> 35.295 | BQ14: ='Fuel Values'!K14-($AF14*'Feedstock Conversions'!$B$17) -> 24.655 | BR14: ='Fuel Values'!L14-($AG14*'Feedstock Conversions'!$B$17) -> 25.4425 | BS14: =W14-MAX(BM14:BR14) -> 22.0775
A15: 43560 | B15: 31.426 | C15: =B15+'Rail Costs'!B15 -> 35.81581 | E15: =C15*'Feedstock Conversions'!B$17 -> 268.61857 | H15: ='Fuel Values'!B15-'Soybean Oil'!I15-'Soybean Oil'!J15-'Soybean Oil'!K15 -> 70.049426 | I15: =('LCFS Values'!$E$2-'Soybean Oil'!$AA$4)/1000000*'LCFS Values'!B15*'LCFS Values'!$G$2*100 -> 97.050574 | J15: ='RIN Values'!C15 -> 57.9 | K15: ='Fixed Credits Value'!B15 -> 100 | L15: =H15+I15+J15+K15 -> 325 | M15: =L15/'Feedstock Conversions'!B$17 -> 43.333333 | W15: =L15-E15 -> 56.381428 | AA15: 54.5 | AB15: 54.68 | AD15: 43560 | AE15: =B15+'Rail Costs'!K15 -> 32.523452 | AF15: =$B15+'Rail Costs'!L15 -> 33.620905 | AG15: =$B15+'Rail Costs'!M15 -> 34.718357 | AH15: =$B15+'Rail Costs'!N15 -> 31.864981 | AI15: =$B15+'Rail Costs'!O15 -> 32.084471 | AJ15: =$B15+'Rail Costs'!P15 -> 32.742943 | AK15: =(AVERAGEIFS([1]Spreads!$B$23:$B$1056,[1]Spreads!$Y$23:$Y$1056,BH15,[1]Spreads!$X$23:$X$1056,BI15)*1.03)+('Rail Costs'!X15*100/2204.622) -> #VALUE! | AM15: ='Soybean Oil'!$L15-('Soybean Oil'!AE15*'Feedstock Conversions'!$B$17)-'Rail Costs'!Q15 -> 77.356825 | AN15: ='Soybean Oil'!$L15-('Soybean Oil'!AF15*'Feedstock Conversions'!$B$17)-'Rail Costs'!R15 -> 69.535135 | AO15: ='Soybean Oil'!$L15-('Soybean Oil'!AG15*'Feedstock Conversions'!$B$17)-'Rail Costs'!S15 -> 61.473887 | AP15: ='Soybean Oil'!$L15-('Soybean Oil'!AH15*'Feedstock Conversions'!$B$17)-'Rail Costs'!T15 -> 82.472374 | AQ15: ='Soybean Oil'!$L15-('Soybean Oil'!AI15*'Feedstock Conversions'!$B$17)-'Rail Costs'!U15 -> 80.973563 | AR15: ='Soybean Oil'!$L15-('Soybean Oil'!AJ15*'Feedstock Conversions'!$B$17)-'Rail Costs'!V15 -> 75.179606 | AS15: ='Soybean Oil'!$L15-('Soybean Oil'!AK15*'Feedstock Conversions'!$B$17)-'Rail Costs'!Y15 -> #VALUE! | BH15: =WEEKNUM(A15) -> 14 | BI15: =YEAR(A15) -> 2019 | BJ15: =MONTH(A15) -> 4 | BM15: ='Fuel Values'!G15-(E15) -> 11.181428 | BN15: ='Fuel Values'!H15-($AJ15*'Feedstock Conversions'!$B$5) -> 22.627928 | BO15: ='Fuel Values'!I15-($AI15*'Feedstock Conversions'!$B$17) -> 36.466464 | BP15: ='Fuel Values'!J15-($AH15*'Feedstock Conversions'!$B$17) -> 30.712643 | BQ15: ='Fuel Values'!K15-($AF15*'Feedstock Conversions'!$B$17) -> 14.943214 | BR15: ='Fuel Values'!L15-($AG15*'Feedstock Conversions'!$B$17) -> 21.112321 | BS15: =W15-MAX(BM15:BR15) -> 19.914964
A16: 43567 | B16: 31.534 | C16: =B16+'Rail Costs'!B16 -> 35.92381 | E16: =C16*'Feedstock Conversions'!B$17 -> 269.42857 | H16: ='Fuel Values'!B16-'Soybean Oil'!I16-'Soybean Oil'!J16-'Soybean Oil'!K16 -> 73.410051 | I16: =('LCFS Values'!$E$2-'Soybean Oil'!$AA$4)/1000000*'LCFS Values'!B16*'LCFS Values'!$G$2*100 -> 94.464949 | J16: ='RIN Values'!C16 -> 55.125 | K16: ='Fixed Credits Value'!B16 -> 100 | L16: =H16+I16+J16+K16 -> 323 | M16: =L16/'Feedstock Conversions'!B$17 -> 43.066667 | W16: =L16-E16 -> 53.571428 | AA16: 52.22 | AB16: 60.13 | AD16: 43567 | AE16: =B16+'Rail Costs'!K16 -> 32.631452 | AF16: =$B16+'Rail Costs'!L16 -> 33.728905 | AG16: =$B16+'Rail Costs'!M16 -> 34.826357 | AH16: =$B16+'Rail Costs'!N16 -> 31.972981 | AI16: =$B16+'Rail Costs'!O16 -> 32.192471 | AJ16: =$B16+'Rail Costs'!P16 -> 32.850943 | AK16: =(AVERAGEIFS([1]Spreads!$B$23:$B$1056,[1]Spreads!$Y$23:$Y$1056,BH16,[1]Spreads!$X$23:$X$1056,BI16)*1.03)+('Rail Costs'!X16*100/2204.622) -> #VALUE! | AM16: ='Soybean Oil'!$L16-('Soybean Oil'!AE16*'Feedstock Conversions'!$B$17)-'Rail Costs'!Q16 -> 74.546825 | AN16: ='Soybean Oil'!$L16-('Soybean Oil'!AF16*'Feedstock Conversions'!$B$17)-'Rail Costs'!R16 -> 66.725135 | AO16: ='Soybean Oil'!$L16-('Soybean Oil'!AG16*'Feedstock Conversions'!$B$17)-'Rail Costs'!S16 -> 58.663887 | AP16: ='Soybean Oil'!$L16-('Soybean Oil'!AH16*'Feedstock Conversions'!$B$17)-'Rail Costs'!T16 -> 79.662374 | AQ16: ='Soybean Oil'!$L16-('Soybean Oil'!AI16*'Feedstock Conversions'!$B$17)-'Rail Costs'!U16 -> 78.163563 | AR16: ='Soybean Oil'!$L16-('Soybean Oil'!AJ16*'Feedstock Conversions'!$B$17)-'Rail Costs'!V16 -> 72.369606 | AS16: ='Soybean Oil'!$L16-('Soybean Oil'!AK16*'Feedstock Conversions'!$B$17)-'Rail Costs'!Y16 -> #VALUE! | BH16: =WEEKNUM(A16) -> 15 | BI16: =YEAR(A16) -> 2019 | BJ16: =MONTH(A16) -> 4 | BM16: ='Fuel Values'!G16-(E16) -> 10.771428 | BN16: ='Fuel Values'!H16-($AJ16*'Feedstock Conversions'!$B$5) -> 21.517928 | BO16: ='Fuel Values'!I16-($AI16*'Feedstock Conversions'!$B$17) -> 35.656464 | BP16: ='Fuel Values'!J16-($AH16*'Feedstock Conversions'!$B$17) -> 29.902643 | BQ16: ='Fuel Values'!K16-($AF16*'Feedstock Conversions'!$B$17) -> 11.333214 | BR16: ='Fuel Values'!L16-($AG16*'Feedstock Conversions'!$B$17) -> 19.302321 | BS16: =W16-MAX(BM16:BR16) -> 17.914964
A17: 43574 | B17: 31.2475 | C17: =B17+'Rail Costs'!B17 -> 35.63731 | E17: =C17*'Feedstock Conversions'!B$17 -> 267.27982 | H17: ='Fuel Values'!B17-'Soybean Oil'!I17-'Soybean Oil'!J17-'Soybean Oil'!K17 -> 75.490823 | I17: =('LCFS Values'!$E$2-'Soybean Oil'!$AA$4)/1000000*'LCFS Values'!B17*'LCFS Values'!$G$2*100 -> 92.352927 | J17: ='RIN Values'!C17 -> 54.65625 | K17: ='Fixed Credits Value'!B17 -> 100 | L17: =H17+I17+J17+K17 -> 322.5 | M17: =L17/'Feedstock Conversions'!B$17 -> 43 | W17: =L17-E17 -> 55.220178 | AA17: 59.53 | AB17: 58.16 | AD17: 43574 | AE17: =B17+'Rail Costs'!K17 -> 32.344952 | AF17: =$B17+'Rail Costs'!L17 -> 33.442405 | AG17: =$B17+'Rail Costs'!M17 -> 34.539857 | AH17: =$B17+'Rail Costs'!N17 -> 31.686481 | AI17: =$B17+'Rail Costs'!O17 -> 31.905971 | AJ17: =$B17+'Rail Costs'!P17 -> 32.564443 | AK17: =(AVERAGEIFS([1]Spreads!$B$23:$B$1056,[1]Spreads!$Y$23:$Y$1056,BH17,[1]Spreads!$X$23:$X$1056,BI17)*1.03)+('Rail Costs'!X17*100/2204.622) -> #VALUE! | AM17: ='Soybean Oil'!$L17-('Soybean Oil'!AE17*'Feedstock Conversions'!$B$17)-'Rail Costs'!Q17 -> 76.195575 | AN17: ='Soybean Oil'!$L17-('Soybean Oil'!AF17*'Feedstock Conversions'!$B$17)-'Rail Costs'!R17 -> 68.373885 | AO17: ='Soybean Oil'!$L17-('Soybean Oil'!AG17*'Feedstock Conversions'!$B$17)-'Rail Costs'!S17 -> 60.312637 | AP17: ='Soybean Oil'!$L17-('Soybean Oil'!AH17*'Feedstock Conversions'!$B$17)-'Rail Costs'!T17 -> 81.311124 | AQ17: ='Soybean Oil'!$L17-('Soybean Oil'!AI17*'Feedstock Conversions'!$B$17)-'Rail Costs'!U17 -> 79.812313 | AR17: ='Soybean Oil'!$L17-('Soybean Oil'!AJ17*'Feedstock Conversions'!$B$17)-'Rail Costs'!V17 -> 74.018356 | AS17: ='Soybean Oil'!$L17-('Soybean Oil'!AK17*'Feedstock Conversions'!$B$17)-'Rail Costs'!Y17 -> #VALUE! | BH17: =WEEKNUM(A17) -> 16 | BI17: =YEAR(A17) -> 2019 | BJ17: =MONTH(A17) -> 4 | BM17: ='Fuel Values'!G17-(E17) -> 12.220178 | BN17: ='Fuel Values'!H17-($AJ17*'Feedstock Conversions'!$B$5) -> 20.016678 | BO17: ='Fuel Values'!I17-($AI17*'Feedstock Conversions'!$B$17) -> 35.955214 | BP17: ='Fuel Values'!J17-($AH17*'Feedstock Conversions'!$B$17) -> 31.101393 | BQ17: ='Fuel Values'!K17-($AF17*'Feedstock Conversions'!$B$17) -> 12.181964 | BR17: ='Fuel Values'!L17-($AG17*'Feedstock Conversions'!$B$17) -> 19.951071 | BS17: =W17-MAX(BM17:BR17) -> 19.264964
A18: 43581 | B18: 30.356 | C18: =B18+'Rail Costs'!B18 -> 34.74581 | E18: =C18*'Feedstock Conversions'!B$17 -> 260.59357 | H18: ='Fuel Values'!B18-'Soybean Oil'!I18-'Soybean Oil'!J18-'Soybean Oil'!K18 -> 78.43244 | I18: =('LCFS Values'!$E$2-'Soybean Oil'!$AA$4)/1000000*'LCFS Values'!B18*'LCFS Values'!$G$2*100 -> 95.64256 | J18: ='RIN Values'!C18 -> 51.225 | K18: ='Fixed Credits Value'!B18 -> 100 | L18: =H18+I18+J18+K18 -> 325.3 | M18: =L18/'Feedstock Conversions'!B$17 -> 43.373333 | W18: =L18-E18 -> 64.706428 | AA18: 54.81 | AB18: 55.39 | AD18: 43581 | AE18: =B18+'Rail Costs'!K18 -> 31.453452 | AF18: =$B18+'Rail Costs'!L18 -> 32.550905 | AG18: =$B18+'Rail Costs'!M18 -> 33.648357 | AH18: =$B18+'Rail Costs'!N18 -> 30.794981 | AI18: =$B18+'Rail Costs'!O18 -> 31.014471 | AJ18: =$B18+'Rail Costs'!P18 -> 31.672943 | AK18: =(AVERAGEIFS([1]Spreads!$B$23:$B$1056,[1]Spreads!$Y$23:$Y$1056,BH18,[1]Spreads!$X$23:$X$1056,BI18)*1.03)+('Rail Costs'!X18*100/2204.622) -> #VALUE! | AM18: ='Soybean Oil'!$L18-('Soybean Oil'!AE18*'Feedstock Conversions'!$B$17)-'Rail Costs'!Q18 -> 85.681825 | AN18: ='Soybean Oil'!$L18-('Soybean Oil'!AF18*'Feedstock Conversions'!$B$17)-'Rail Costs'!R18 -> 77.860135 | AO18: ='Soybean Oil'!$L18-('Soybean Oil'!AG18*'Feedstock Conversions'!$B$17)-'Rail Costs'!S18 -> 69.798887 | AP18: ='Soybean Oil'!$L18-('Soybean Oil'!AH18*'Feedstock Conversions'!$B$17)-'Rail Costs'!T18 -> 90.797374 | AQ18: ='Soybean Oil'!$L18-('Soybean Oil'!AI18*'Feedstock Conversions'!$B$17)-'Rail Costs'!U18 -> 89.298563 | AR18: ='Soybean Oil'!$L18-('Soybean Oil'!AJ18*'Feedstock Conversions'!$B$17)-'Rail Costs'!V18 -> 83.504606 | AS18: ='Soybean Oil'!$L18-('Soybean Oil'!AK18*'Feedstock Conversions'!$B$17)-'Rail Costs'!Y18 -> #VALUE! | BH18: =WEEKNUM(A18) -> 17 | BI18: =YEAR(A18) -> 2019 | BJ18: =MONTH(A18) -> 4 | BM18: ='Fuel Values'!G18-(E18) -> 17.406428 | BN18: ='Fuel Values'!H18-($AJ18*'Feedstock Conversions'!$B$5) -> 28.452928 | BO18: ='Fuel Values'!I18-($AI18*'Feedstock Conversions'!$B$17) -> 42.191464 | BP18: ='Fuel Values'!J18-($AH18*'Feedstock Conversions'!$B$17) -> 37.837643 | BQ18: ='Fuel Values'!K18-($AF18*'Feedstock Conversions'!$B$17) -> 19.368214 | BR18: ='Fuel Values'!L18-($AG18*'Feedstock Conversions'!$B$17) -> 26.937321 | BS18: =W18-MAX(BM18:BR18) -> 22.514964
A19: 43588 | B19: 29.872 | C19: =B19+'Rail Costs'!B19 -> 34.26181 | E19: =C19*'Feedstock Conversions'!B$17 -> 256.96357 | H19: ='Fuel Values'!B19-'Soybean Oil'!I19-'Soybean Oil'!J19-'Soybean Oil'!K19 -> 79.528343 | I19: =('LCFS Values'!$E$2-'Soybean Oil'!$AA$4)/1000000*'LCFS Values'!B19*'LCFS Values'!$G$2*100 -> 95.284157 | J19: ='RIN Values'!C19 -> 52.6875 | K19: ='Fixed Credits Value'!B19 -> 100 | L19: =H19+I19+J19+K19 -> 327.5 | M19: =L19/'Feedstock Conversions'!B$17 -> 43.666667 | W19: =L19-E19 -> 70.536428 | AA19: 53.43 | AB19: 57.2 | AD19: 43588 | AE19: =B19+'Rail Costs'!K19 -> 30.969452 | AF19: =$B19+'Rail Costs'!L19 -> 32.066905 | AG19: =$B19+'Rail Costs'!M19 -> 33.164357 | AH19: =$B19+'Rail Costs'!N19 -> 30.310981 | AI19: =$B19+'Rail Costs'!O19 -> 30.530471 | AJ19: =$B19+'Rail Costs'!P19 -> 31.188943 | AK19: =(AVERAGEIFS([1]Spreads!$B$23:$B$1056,[1]Spreads!$Y$23:$Y$1056,BH19,[1]Spreads!$X$23:$X$1056,BI19)*1.03)+('Rail Costs'!X19*100/2204.622) -> #VALUE! | AM19: ='Soybean Oil'!$L19-('Soybean Oil'!AE19*'Feedstock Conversions'!$B$17)-'Rail Costs'!Q19 -> 91.511825 | AN19: ='Soybean Oil'!$L19-('Soybean Oil'!AF19*'Feedstock Conversions'!$B$17)-'Rail Costs'!R19 -> 83.690135 | AO19: ='Soybean Oil'!$L19-('Soybean Oil'!AG19*'Feedstock Conversions'!$B$17)-'Rail Costs'!S19 -> 75.628887 | AP19: ='Soybean Oil'!$L19-('Soybean Oil'!AH19*'Feedstock Conversions'!$B$17)-'Rail Costs'!T19 -> 96.627374 | AQ19: ='Soybean Oil'!$L19-('Soybean Oil'!AI19*'Feedstock Conversions'!$B$17)-'Rail Costs'!U19 -> 95.128563 | AR19: ='Soybean Oil'!$L19-('Soybean Oil'!AJ19*'Feedstock Conversions'!$B$17)-'Rail Costs'!V19 -> 89.334606 | AS19: ='Soybean Oil'!$L19-('Soybean Oil'!AK19*'Feedstock Conversions'!$B$17)-'Rail Costs'!Y19 -> #VALUE! | BH19: =WEEKNUM(A19) -> 18 | BI19: =YEAR(A19) -> 2019 | BJ19: =MONTH(A19) -> 5 | BM19: ='Fuel Values'!G19-(E19) -> 20.236428 | BN19: ='Fuel Values'!H19-($AJ19*'Feedstock Conversions'!$B$5) -> 35.482928 | BO19: ='Fuel Values'!I19-($AI19*'Feedstock Conversions'!$B$17) -> 46.621464 | BP19: ='Fuel Values'!J19-($AH19*'Feedstock Conversions'!$B$17) -> 42.067643 | BQ19: ='Fuel Values'!K19-($AF19*'Feedstock Conversions'!$B$17) -> 24.398214 | BR19: ='Fuel Values'!L19-($AG19*'Feedstock Conversions'!$B$17) -> 31.167321 | BS19: =W19-MAX(BM19:BR19) -> 23.914964
A20: 43595 | B20: 29.506 | C20: =B20+'Rail Costs'!B20 -> 33.89581 | E20: =C20*'Feedstock Conversions'!B$17 -> 254.21857 | H20: ='Fuel Values'!B20-'Soybean Oil'!I20-'Soybean Oil'!J20-'Soybean Oil'!K20 -> 82.736041 | I20: =('LCFS Values'!$E$2-'Soybean Oil'!$AA$4)/1000000*'LCFS Values'!B20*'LCFS Values'!$G$2*100 -> 95.488959 | J20: ='RIN Values'!C20 -> 49.275 | K20: ='Fixed Credits Value'!B20 -> 100 | L20: =H20+I20+J20+K20 -> 327.5 | M20: =L20/'Feedstock Conversions'!B$17 -> 43.666667 | W20: =L20-E20 -> 73.281428 | AA20: 56.2 | AB20: 80.81 | AD20: 43595 | AE20: =B20+'Rail Costs'!K20 -> 30.603452 | AF20: =$B20+'Rail Costs'!L20 -> 31.700905 | AG20: =$B20+'Rail Costs'!M20 -> 32.798357 | AH20: =$B20+'Rail Costs'!N20 -> 29.944981 | AI20: =$B20+'Rail Costs'!O20 -> 30.164471 | AJ20: =$B20+'Rail Costs'!P20 -> 30.822943 | AK20: =(AVERAGEIFS([1]Spreads!$B$23:$B$1056,[1]Spreads!$Y$23:$Y$1056,BH20,[1]Spreads!$X$23:$X$1056,BI20)*1.03)+('Rail Costs'!X20*100/2204.622) -> #VALUE! | AM20: ='Soybean Oil'!$L20-('Soybean Oil'!AE20*'Feedstock Conversions'!$B$17)-'Rail Costs'!Q20 -> 94.256825 | AN20: ='Soybean Oil'!$L20-('Soybean Oil'!AF20*'Feedstock Conversions'!$B$17)-'Rail Costs'!R20 -> 86.435135 | AO20: ='Soybean Oil'!$L20-('Soybean Oil'!AG20*'Feedstock Conversions'!$B$17)-'Rail Costs'!S20 -> 78.373887 | AP20: ='Soybean Oil'!$L20-('Soybean Oil'!AH20*'Feedstock Conversions'!$B$17)-'Rail Costs'!T20 -> 99.372374 | AQ20: ='Soybean Oil'!$L20-('Soybean Oil'!AI20*'Feedstock Conversions'!$B$17)-'Rail Costs'!U20 -> 97.873563 | AR20: ='Soybean Oil'!$L20-('Soybean Oil'!AJ20*'Feedstock Conversions'!$B$17)-'Rail Costs'!V20 -> 92.079606 | AS20: ='Soybean Oil'!$L20-('Soybean Oil'!AK20*'Feedstock Conversions'!$B$17)-'Rail Costs'!Y20 -> #VALUE! | BH20: =WEEKNUM(A20) -> 19 | BI20: =YEAR(A20) -> 2019 | BJ20: =MONTH(A20) -> 5 | BM20: ='Fuel Values'!G20-(E20) -> 17.981428 | BN20: ='Fuel Values'!H20-($AJ20*'Feedstock Conversions'!$B$5) -> 37.027928 | BO20: ='Fuel Values'!I20-($AI20*'Feedstock Conversions'!$B$17) -> 45.366464 | BP20: ='Fuel Values'!J20-($AH20*'Feedstock Conversions'!$B$17) -> 41.812643 | BQ20: ='Fuel Values'!K20-($AF20*'Feedstock Conversions'!$B$17) -> 24.443214 | BR20: ='Fuel Values'!L20-($AG20*'Feedstock Conversions'!$B$17) -> 31.512321 | BS20: =W20-MAX(BM20:BR20) -> 27.914964
A21: 43602 | B21: 29.808 | C21: =B21+'Rail Costs'!B21 -> 34.19781 | E21: =C21*'Feedstock Conversions'!B$17 -> 256.48357 | H21: ='Fuel Values'!B21-'Soybean Oil'!I21-'Soybean Oil'!J21-'Soybean Oil'!K21 -> 82.602638 | I21: =('LCFS Values'!$E$2-'Soybean Oil'!$AA$4)/1000000*'LCFS Values'!B21*'LCFS Values'!$G$2*100 -> 95.847362 | J21: ='RIN Values'!C21 -> 49.05 | K21: ='Fixed Credits Value'!B21 -> 100 | L21: =H21+I21+J21+K21 -> 327.5 | M21: =L21/'Feedstock Conversions'!B$17 -> 43.666667 | W21: =L21-E21 -> 71.016428 | AA21: 58.55 | AB21: 57.13 | AD21: 43602 | AE21: =B21+'Rail Costs'!K21 -> 30.905452 | AF21: =$B21+'Rail Costs'!L21 -> 32.002905 | AG21: =$B21+'Rail Costs'!M21 -> 33.100357 | AH21: =$B21+'Rail Costs'!N21 -> 30.246981 | AI21: =$B21+'Rail Costs'!O21 -> 30.466471 | AJ21: =$B21+'Rail Costs'!P21 -> 31.124943 | AK21: =(AVERAGEIFS([1]Spreads!$B$23:$B$1056,[1]Spreads!$Y$23:$Y$1056,BH21,[1]Spreads!$X$23:$X$1056,BI21)*1.03)+('Rail Costs'!X21*100/2204.622) -> #VALUE! | AM21: ='Soybean Oil'!$L21-('Soybean Oil'!AE21*'Feedstock Conversions'!$B$17)-'Rail Costs'!Q21 -> 91.991825 | AN21: ='Soybean Oil'!$L21-('Soybean Oil'!AF21*'Feedstock Conversions'!$B$17)-'Rail Costs'!R21 -> 84.170135 | AO21: ='Soybean Oil'!$L21-('Soybean Oil'!AG21*'Feedstock Conversions'!$B$17)-'Rail Costs'!S21 -> 76.108887 | AP21: ='Soybean Oil'!$L21-('Soybean Oil'!AH21*'Feedstock Conversions'!$B$17)-'Rail Costs'!T21 -> 97.107374 | AQ21: ='Soybean Oil'!$L21-('Soybean Oil'!AI21*'Feedstock Conversions'!$B$17)-'Rail Costs'!U21 -> 95.608563 | AR21: ='Soybean Oil'!$L21-('Soybean Oil'!AJ21*'Feedstock Conversions'!$B$17)-'Rail Costs'!V21 -> 89.814606 | AS21: ='Soybean Oil'!$L21-('Soybean Oil'!AK21*'Feedstock Conversions'!$B$17)-'Rail Costs'!Y21 -> #VALUE! | BH21: =WEEKNUM(A21) -> 20 | BI21: =YEAR(A21) -> 2019 | BJ21: =MONTH(A21) -> 5 | BM21: ='Fuel Values'!G21-(E21) -> 15.116428 | BN21: ='Fuel Values'!H21-($AJ21*'Feedstock Conversions'!$B$5) -> 36.762928 | BO21: ='Fuel Values'!I21-($AI21*'Feedstock Conversions'!$B$17) -> 42.101464 | BP21: ='Fuel Values'!J21-($AH21*'Feedstock Conversions'!$B$17) -> 40.347643 | BQ21: ='Fuel Values'!K21-($AF21*'Feedstock Conversions'!$B$17) -> 21.978214 | BR21: ='Fuel Values'!L21-($AG21*'Feedstock Conversions'!$B$17) -> 29.247321 | BS21: =W21-MAX(BM21:BR21) -> 28.914964
... A25: 43630 | B25: 31.058 | C25: =B25+'Rail Costs'!B25 -> 35.44781 | E25: =C25*'Feedstock Conversions'!B$17 -> 265.85857 | H25: ='Fuel Values'!B25-'Soybean Oil'!I25-'Soybean Oil'!J25-'Soybean Oil'!K25 -> 62.179617 | I25: =('LCFS Values'!$E$2-'Soybean Oil'!$AA$4)/1000000*'LCFS Values'!B25*'LCFS Values'!$G$2*100 -> 97.895383 | J25: ='RIN Values'!C25 -> 64.425 | K25: ='Fixed Credits Value'!B25 -> 100 | L25: =H25+I25+J25+K25 -> 324.5 | M25: =L25/'Feedstock Conversions'!B$17 -> 43.266667 | W25: =L25-E25 -> 58.641428 | AA25: 55.74 | AB25: 51.74 | AD25: 43630 | AE25: =B25+'Rail Costs'!K25 -> 32.155452 | AF25: =$B25+'Rail Costs'!L25 -> 33.252905 | AG25: =$B25+'Rail Costs'!M25 -> 34.350357 | AH25: =$B25+'Rail Costs'!N25 -> 31.496981 | AI25: =$B25+'Rail Costs'!O25 -> 31.716471 | AJ25: =$B25+'Rail Costs'!P25 -> 32.374943 | AK25: =(AVERAGEIFS([1]Spreads!$B$23:$B$1056,[1]Spreads!$Y$23:$Y$1056,BH25,[1]Spreads!$X$23:$X$1056,BI25)*1.03)+('Rail Costs'!X25*100/2204.622) -> #VALUE! | AM25: ='Soybean Oil'!$L25-('Soybean Oil'!AE25*'Feedstock Conversions'!$B$17)-'Rail Costs'!Q25 -> 79.616825 | AN25: ='Soybean Oil'!$L25-('Soybean Oil'!AF25*'Feedstock Conversions'!$B$17)-'Rail Costs'!R25 -> 71.795135 | AO25: ='Soybean Oil'!$L25-('Soybean Oil'!AG25*'Feedstock Conversions'!$B$17)-'Rail Costs'!S25 -> 63.733887 | AP25: ='Soybean Oil'!$L25-('Soybean Oil'!AH25*'Feedstock Conversions'!$B$17)-'Rail Costs'!T25 -> 84.732374 | AQ25: ='Soybean Oil'!$L25-('Soybean Oil'!AI25*'Feedstock Conversions'!$B$17)-'Rail Costs'!U25 -> 83.233563 | AR25: ='Soybean Oil'!$L25-('Soybean Oil'!AJ25*'Feedstock Conversions'!$B$17)-'Rail Costs'!V25 -> 77.439606 | AS25: ='Soybean Oil'!$L25-('Soybean Oil'!AK25*'Feedstock Conversions'!$B$17)-'Rail Costs'!Y25 -> #VALUE! | BH25: =WEEKNUM(A25) -> 24 | BI25: =YEAR(A25) -> 2019 | BJ25: =MONTH(A25) -> 6 | BM25: ='Fuel Values'!G25-(E25) -> 5.3414278 | BN25: ='Fuel Values'!H25-($AJ25*'Feedstock Conversions'!$B$5) -> 20.787928 | BO25: ='Fuel Values'!I25-($AI25*'Feedstock Conversions'!$B$17) -> 34.126464 | BP25: ='Fuel Values'!J25-($AH25*'Feedstock Conversions'!$B$17) -> 33.772643 | BQ25: ='Fuel Values'!K25-($AF25*'Feedstock Conversions'!$B$17) -> 5.7032139 | BR25: ='Fuel Values'!L25-($AG25*'Feedstock Conversions'!$B$17) -> 19.872321 | BS25: =W25-MAX(BM25:BR25) -> 24.514964
A26: 43637 | B26: 31.914 | C26: =B26+'Rail Costs'!B26 -> 36.30381 | E26: =C26*'Feedstock Conversions'!B$17 -> 272.27857 | F26: =C26*'Feedstock Conversions'!B$5 -> 272.27857 | H26: ='Fuel Values'!B26-'Soybean Oil'!I26-'Soybean Oil'!J26-'Soybean Oil'!K26 -> 60.692612 | I26: =('LCFS Values'!$E$2-'Soybean Oil'!$AA$4)/1000000*'LCFS Values'!B26*'LCFS Values'!$G$2*100 -> 98.407388 | J26: ='RIN Values'!C26 -> 70.2 | K26: ='Fixed Credits Value'!B26 -> 100 | L26: =H26+I26+J26+K26 -> 329.3 | M26: =L26/'Feedstock Conversions'!B$17 -> 43.906667 | O26: ='Fuel Values'!C26*100 -> 191.01 | P26: =('LCFS Values'!$E$2-'Soybean Oil'!$AB$4)/1000000*'LCFS Values'!B26*'LCFS Values'!$G$2*100 -> 86.750628 | Q26: ='RIN Values'!D26 -> 79.56 | R26: ='Fixed Credits Value'!B26 -> 100 | S26: ='Fixed Credits Value'!C26 -> 16 | T26: =O26+P26+Q26+R26+S26 -> 473.32063 | U26: =T26/7.5 -> 63.109417 | W26: =L26-E26 -> 57.021428 | X26: =T26-F26 -> 201.04206 | AA26: 57 | AB26: 69.78 | AD26: 43637 | AE26: =B26+'Rail Costs'!K26 -> 33.011452 | AF26: =$B26+'Rail Costs'!L26 -> 34.108905 | AG26: =$B26+'Rail Costs'!M26 -> 35.206357 | AH26: =$B26+'Rail Costs'!N26 -> 32.352981 | AI26: =$B26+'Rail Costs'!O26 -> 32.572471 | AJ26: =$B26+'Rail Costs'!P26 -> 33.230943 | AK26: =(AVERAGEIFS([1]Spreads!$B$23:$B$1056,[1]Spreads!$Y$23:$Y$1056,BH26,[1]Spreads!$X$23:$X$1056,BI26)*1.03)+('Rail Costs'!X26*100/2204.622) -> #VALUE! | AM26: ='Soybean Oil'!$L26-('Soybean Oil'!AE26*'Feedstock Conversions'!$B$17)-'Rail Costs'!Q26 -> 77.996825 | AN26: ='Soybean Oil'!$L26-('Soybean Oil'!AF26*'Feedstock Conversions'!$B$17)-'Rail Costs'!R26 -> 70.175135 | AO26: ='Soybean Oil'!$L26-('Soybean Oil'!AG26*'Feedstock Conversions'!$B$17)-'Rail Costs'!S26 -> 62.113887 | AP26: ='Soybean Oil'!$L26-('Soybean Oil'!AH26*'Feedstock Conversions'!$B$17)-'Rail Costs'!T26 -> 83.112374 | AQ26: ='Soybean Oil'!$L26-('Soybean Oil'!AI26*'Feedstock Conversions'!$B$17)-'Rail Costs'!U26 -> 81.613563 | AR26: ='Soybean Oil'!$L26-('Soybean Oil'!AJ26*'Feedstock Conversions'!$B$17)-'Rail Costs'!V26 -> 75.819606 | AS26: ='Soybean Oil'!$L26-('Soybean Oil'!AK26*'Feedstock Conversions'!$B$17)-'Rail Costs'!Y26 -> #VALUE! | AU26: =$T26-(AE26*'Feedstock Conversions'!$B$5)-'Rail Costs'!Q26 -> 222.01745 | AV26: =$T26-(AF26*'Feedstock Conversions'!$B$5)-'Rail Costs'!R26 -> 214.19576 | AW26: =$T26-(AG26*'Feedstock Conversions'!$B$5)-'Rail Costs'!S26 -> 206.13452 | AX26: =$T26-(AH26*'Feedstock Conversions'!$B$5)-'Rail Costs'!T26 -> 227.133 | AY26: =$T26-(AI26*'Feedstock Conversions'!$B$5)-'Rail Costs'!U26 -> 225.63419 | AZ26: =$T26-(AJ26*'Feedstock Conversions'!$B$5)-'Rail Costs'!V26 -> 219.84023 | BA26: =$T26-(AK26*'Feedstock Conversions'!$B$5)-'Rail Costs'!Y26 -> #VALUE! | BH26: =WEEKNUM(A26) -> 25 | BI26: =YEAR(A26) -> 2019 | BJ26: =MONTH(A26) -> 6 | BM26: ='Fuel Values'!G26-(E26) -> 3.7214278 | BN26: ='Fuel Values'!H26-($AJ26*'Feedstock Conversions'!$B$5) -> 18.867928 | BO26: ='Fuel Values'!I26-($AI26*'Feedstock Conversions'!$B$17) -> 30.706464 | BP26: ='Fuel Values'!J26-($AH26*'Feedstock Conversions'!$B$17) -> 28.852643 | BQ26: ='Fuel Values'!K26-($AF26*'Feedstock Conversions'!$B$17) -> 0.18321389 | BR26: ='Fuel Values'!L26-($AG26*'Feedstock Conversions'!$B$17) -> 15.252321 | BS26: =W26-MAX(BM26:BR26) -> 26.314964
A27: 43644 | B27: 31.592 | C27: =B27+'Rail Costs'!B27 -> 35.98181 | E27: =C27*'Feedstock Conversions'!B$17 -> 269.86357 | F27: =C27*'Feedstock Conversions'!B$5 -> 269.86357 | H27: ='Fuel Values'!B27-'Soybean Oil'!I27-'Soybean Oil'!J27-'Soybean Oil'!K27 -> 66.531807 | I27: =('LCFS Values'!$E$2-'Soybean Oil'!$AA$4)/1000000*'LCFS Values'!B27*'LCFS Values'!$G$2*100 -> 98.868193 | J27: ='RIN Values'!C27 -> 65.1 | K27: ='Fixed Credits Value'!B27 -> 100 | L27: =H27+I27+J27+K27 -> 330.5 | M27: =L27/'Feedstock Conversions'!B$17 -> 44.066667 | O27: ='Fuel Values'!C27*100 -> 195.01 | P27: =('LCFS Values'!$E$2-'Soybean Oil'!$AB$4)/1000000*'LCFS Values'!B27*'LCFS Values'!$G$2*100 -> 87.156849 | Q27: ='RIN Values'!D27 -> 73.78 | R27: ='Fixed Credits Value'!B27 -> 100 | S27: ='Fixed Credits Value'!C27 -> 16 | T27: =O27+P27+Q27+R27+S27 -> 471.94685 | U27: =T27/7.5 -> 62.926246 | W27: =L27-E27 -> 60.636428 | X27: =T27-F27 -> 202.08328 | AA27: 66.13 | AB27: 69.41 | AD27: 43644 | AE27: =B27+'Rail Costs'!K27 -> 32.689452 | AF27: =$B27+'Rail Costs'!L27 -> 33.786905 | AG27: =$B27+'Rail Costs'!M27 -> 34.884357 | AH27: =$B27+'Rail Costs'!N27 -> 32.030981 | AI27: =$B27+'Rail Costs'!O27 -> 32.250471 | AJ27: =$B27+'Rail Costs'!P27 -> 32.908943 | AK27: =(AVERAGEIFS([1]Spreads!$B$23:$B$1056,[1]Spreads!$Y$23:$Y$1056,BH27,[1]Spreads!$X$23:$X$1056,BI27)*1.03)+('Rail Costs'!X27*100/2204.622) -> #VALUE! | AM27: ='Soybean Oil'!$L27-('Soybean Oil'!AE27*'Feedstock Conversions'!$B$17)-'Rail Costs'!Q27 -> 81.611825 | AN27: ='Soybean Oil'!$L27-('Soybean Oil'!AF27*'Feedstock Conversions'!$B$17)-'Rail Costs'!R27 -> 73.790135 | AO27: ='Soybean Oil'!$L27-('Soybean Oil'!AG27*'Feedstock Conversions'!$B$17)-'Rail Costs'!S27 -> 65.728887 | AP27: ='Soybean Oil'!$L27-('Soybean Oil'!AH27*'Feedstock Conversions'!$B$17)-'Rail Costs'!T27 -> 86.727374 | AQ27: ='Soybean Oil'!$L27-('Soybean Oil'!AI27*'Feedstock Conversions'!$B$17)-'Rail Costs'!U27 -> 85.228563 | AR27: ='Soybean Oil'!$L27-('Soybean Oil'!AJ27*'Feedstock Conversions'!$B$17)-'Rail Costs'!V27 -> 79.434606 | AS27: ='Soybean Oil'!$L27-('Soybean Oil'!AK27*'Feedstock Conversions'!$B$17)-'Rail Costs'!Y27 -> #VALUE! | AU27: =$T27-(AE27*'Feedstock Conversions'!$B$5)-'Rail Costs'!Q27 -> 223.05867 | AV27: =$T27-(AF27*'Feedstock Conversions'!$B$5)-'Rail Costs'!R27 -> 215.23698 | AW27: =$T27-(AG27*'Feedstock Conversions'!$B$5)-'Rail Costs'!S27 -> 207.17574 | AX27: =$T27-(AH27*'Feedstock Conversions'!$B$5)-'Rail Costs'!T27 -> 228.17422 | AY27: =$T27-(AI27*'Feedstock Conversions'!$B$5)-'Rail Costs'!U27 -> 226.67541 | AZ27: =$T27-(AJ27*'Feedstock Conversions'!$B$5)-'Rail Costs'!V27 -> 220.88145 | BA27: =$T27-(AK27*'Feedstock Conversions'!$B$5)-'Rail Costs'!Y27 -> #VALUE! | BH27: =WEEKNUM(A27) -> 26 | BI27: =YEAR(A27) -> 2019 | BJ27: =MONTH(A27) -> 6 | BM27: ='Fuel Values'!G27-(E27) -> 10.136428 | BN27: ='Fuel Values'!H27-($AJ27*'Feedstock Conversions'!$B$5) -> 24.282928 | BO27: ='Fuel Values'!I27-($AI27*'Feedstock Conversions'!$B$17) -> 35.921464 | BP27: ='Fuel Values'!J27-($AH27*'Feedstock Conversions'!$B$17) -> 34.467643 | BQ27: ='Fuel Values'!K27-($AF27*'Feedstock Conversions'!$B$17) -> 8.3982139 | BR27: ='Fuel Values'!L27-($AG27*'Feedstock Conversions'!$B$17) -> 19.867321 | BS27: =W27-MAX(BM27:BR27) -> 24.714964
A28: 43651 | B28: 31.4675 | C28: =B28+'Rail Costs'!B28 -> 35.813166 | E28: =C28*'Feedstock Conversions'!B$17 -> 268.59875 | F28: =C28*'Feedstock Conversions'!B$5 -> 268.59875 | H28: ='Fuel Values'!B28-'Soybean Oil'!I28-'Soybean Oil'!J28-'Soybean Oil'!K28 -> 67.658997 | I28: =('LCFS Values'!$E$2-'Soybean Oil'!$AA$4)/1000000*'LCFS Values'!B28*'LCFS Values'!$G$2*100 -> 99.841003 | J28: ='RIN Values'!C28 -> 63 | K28: ='Fixed Credits Value'!B28 -> 100 | L28: =H28+I28+J28+K28 -> 330.5 | M28: =L28/'Feedstock Conversions'!B$17 -> 44.066667 | O28: ='Fuel Values'!C28*100 -> 192.1 | P28: =('LCFS Values'!$E$2-'Soybean Oil'!$AB$4)/1000000*'LCFS Values'!B28*'LCFS Values'!$G$2*100 -> 88.014425 | Q28: ='RIN Values'!D28 -> 71.4 | R28: ='Fixed Credits Value'!B28 -> 100 | S28: ='Fixed Credits Value'!C28 -> 16 | T28: =O28+P28+Q28+R28+S28 -> 467.51442 | U28: =T28/7.5 -> 62.335257 | W28: =L28-E28 -> 61.901253 | X28: =T28-F28 -> 198.91568 | AA28: 57.16 | AD28: 43651 | AE28: =B28+'Rail Costs'!K28 -> 32.553917 | AF28: =$B28+'Rail Costs'!L28 -> 33.640333 | AG28: =$B28+'Rail Costs'!M28 -> 34.72675 | AH28: =$B28+'Rail Costs'!N28 -> 31.902067 | AI28: =$B28+'Rail Costs'!O28 -> 32.11935 | AJ28: =$B28+'Rail Costs'!P28 -> 32.7712 | AK28: =(AVERAGEIFS([1]Spreads!$B$23:$B$1056,[1]Spreads!$Y$23:$Y$1056,BH28,[1]Spreads!$X$23:$X$1056,BI28)*1.03)+('Rail Costs'!X28*100/2204.622) -> #VALUE! | AM28: ='Soybean Oil'!$L28-('Soybean Oil'!AE28*'Feedstock Conversions'!$B$17)-'Rail Costs'!Q28 -> 82.665724 | AN28: ='Soybean Oil'!$L28-('Soybean Oil'!AF28*'Feedstock Conversions'!$B$17)-'Rail Costs'!R28 -> 74.922688 | AO28: ='Soybean Oil'!$L28-('Soybean Oil'!AG28*'Feedstock Conversions'!$B$17)-'Rail Costs'!S28 -> 66.942503 | AP28: ='Soybean Oil'!$L28-('Soybean Oil'!AH28*'Feedstock Conversions'!$B$17)-'Rail Costs'!T28 -> 87.729832 | AQ28: ='Soybean Oil'!$L28-('Soybean Oil'!AI28*'Feedstock Conversions'!$B$17)-'Rail Costs'!U28 -> 86.246092 | AR28: ='Soybean Oil'!$L28-('Soybean Oil'!AJ28*'Feedstock Conversions'!$B$17)-'Rail Costs'!V28 -> 80.510399 | AS28: ='Soybean Oil'!$L28-('Soybean Oil'!AK28*'Feedstock Conversions'!$B$17)-'Rail Costs'!Y28 -> #VALUE! | AU28: =$T28-(AE28*'Feedstock Conversions'!$B$5)-'Rail Costs'!Q28 -> 219.68015 | AV28: =$T28-(AF28*'Feedstock Conversions'!$B$5)-'Rail Costs'!R28 -> 211.93711 | AW28: =$T28-(AG28*'Feedstock Conversions'!$B$5)-'Rail Costs'!S28 -> 203.95693 | AX28: =$T28-(AH28*'Feedstock Conversions'!$B$5)-'Rail Costs'!T28 -> 224.74426 | AY28: =$T28-(AI28*'Feedstock Conversions'!$B$5)-'Rail Costs'!U28 -> 223.26052 | AZ28: =$T28-(AJ28*'Feedstock Conversions'!$B$5)-'Rail Costs'!V28 -> 217.52482 | BA28: =$T28-(AK28*'Feedstock Conversions'!$B$5)-'Rail Costs'!Y28 -> #VALUE! | BH28: =WEEKNUM(A28) -> 27 | BI28: =YEAR(A28) -> 2019 | BJ28: =MONTH(A28) -> 7 | BM28: ='Fuel Values'!G28-(E28) -> 14.401253 | BN28: ='Fuel Values'!H28-($AJ28*'Feedstock Conversions'!$B$5) -> 27.716001 | BO28: ='Fuel Values'!I28-($AI28*'Feedstock Conversions'!$B$17) -> 38.104875 | BP28: ='Fuel Values'!J28-($AH28*'Feedstock Conversions'!$B$17) -> 38.7345 | BQ28: ='Fuel Values'!K28-($AF28*'Feedstock Conversions'!$B$17) -> 19.697501 | BR28: ='Fuel Values'!L28-($AG28*'Feedstock Conversions'!$B$17) -> 22.549377 | BS28: =W28-MAX(BM28:BR28) -> 23.166753
