Workbook
Name Feedstock_Inputs: '[2]LCFS Breakout'!$A:$A
Name RIN_Value__P: 'LCFS Categorized'!$C$2

Sheet Controls
B1: Biodiesel CI | C1: Baseline - 2019 | D1: Energy Density for Biodiesel | E1: Energy Density for Renewable Diesel
A2: Corn Oil | B2: 35.51 | C2: 94.17 | D2: 126.13 | E2: 129.65 | F2: =+(C2-B2)*D2/1000000 -> 0.0073987858 | G2: 8.2
A3: Tallow | B3: 35.67 | C3: 94.17 | D3: 126.13 | E3: 129.65 | F3: =+(C3-B3)*D3/1000000 -> 0.007378605 | G3: 7.75
A4: Soybean Oil | B4: 54.13 | C4: 94.17 | D4: 126.13 | E4: 129.65 | F4: =+(C4-B4)*D4/1000000 -> 0.0050502452 | G4: 7.4
A5: Canola | B5: 53.76 | C5: 94.17 | D5: 126.13 | E5: 129.65 | F5: =+(C5-B5)*D5/1000000 -> 0.0050969133 | G5: 7.4
A6: UCO - North America | B6: 22.12 | C6: 94.17 | D6: 126.13 | E6: 129.65 | F6: =+(C6-B6)*D6/1000000 -> 0.0090876665 | G6: 8.01
A7: UCO - California | B7: 17.18 | C7: 94.17 | D7: 126.13 | E7: 129.65 | F7: =+(C7-B7)*D7/1000000 -> 0.0097107487 | G7: 8.01
A8: SBO / Tallow | B8: =AVERAGE(B3:B4) -> 44.9 | C8: 94.17 | D8: 126.13 | E8: 129.65 | F8: =AVERAGE(F3:F4) -> 0.0062144251 | H8: *
B11: 94.17 | C11: Static | F11: Result 1.3073509
B12: =B8 -> 44.9 | C12: SBO / Tallow
B13: =B11-B12 -> 49.27 | C13: Result
B14: =B13/1000000 -> 4.927e-05 | C14: Result 2
B15: =B14*H15 -> 0.009203636 | C15: Weekly Average Credit Value 4/22 ending 4/26 | G15: Ex: | H15: 186.8
A16: Credit Value | B16: =B15*134.47 -> 1.2376129 | C16: $/gal Diesel gallon equiv 134.47

Sheet Controls 2
A1: 2023 | B1: Biodiesel CI | F1: Baseline Diesel Energy Density Schedule
A2: Baseline Energy Density | B2: 87.89 | E2: 2019 | F2: 94.147
E3: 2020 | F3: 92.92
A4: Renewable Diesel Feedstock Mix | E4: 2021 | F4: 91.66
A5: Tallow | B5: ='[1]Yellow Grease'!$AB$4 -> 21.242813 | E5: 2022 | F5: 90.41
A6: UCO - California | B6: =[1]UCO!$AB$4 -> 24.987143 | E6: 2023 | F6: 89.15
A7: Corn Oil | B7: =[1]DCO!$AB$4 -> 37.676111 | E7: 2024 | F7: 87.89
A8: Energy Density for Renewable Diesel | B8: 129.65 | E8: 2025 | F8: 86.64
B9: =(B5*0.5)+(B6*0.25)+(B7*0.25) -> 26.28722 | E9: 2026 | F9: 85.38
E10: 2027 | F10: 84.13
A11: Biodiesel Feedstock Mix | E11: 2028 | F11: 82.87
A12: Soybean Oil | B12: 54.13 | E12: 2029 | F12: 81.62
A13: Yellow Grease | B13: 22.12 | E13: 2030 | F13: 80.36
A14: Energy Density for Biodiesel | B14: 126.13 | E14: 2031 | F14: 80.36
A15: Mixed CI Score | B15: =(B12*0.75)+(B13*0.25) -> 46.1275

Sheet Calculator
T2: Assumptions:
V3: Gal | W3: BBL | X3: MTs
B4: Renewable Diesel Econs | I4: Biodiesel dlvd CA Econs
O5: * Stacked Bar with Credit Values 33, 41, 44, 46 - $/gal | T5: Biodiesel | V5: 1 | W5: 42 gals | X5: 300 gals
B6: Week Selector | J6: Week Selector | O6: *
B7: 43609 | D7: =VLOOKUP(B7,'[2]LCFS Breakout'!$B$2:$S$29,4,) -> 0 | E7: * Pulling | J7: 43609 | L7: =VLOOKUP(J7,'[2]LCFS Breakout'!$B$2:$S$29,4,) -> 0 | M7: * Pulling
B9: FEEDSTOCKS | J9: FEEDSTOCKS
B10: Tallow | C10: Cents / LB | D10: =VLOOKUP(B7,'[2]LCFS Breakout'!$B$2:$S$24,9,) -> 95.197122 | E10: * Pulling | J10: Tallow | K10: Cents / LB | L10: =VLOOKUP(J7,'[2]LCFS Breakout'!$B$2:$S$24,9,) -> 95.197122 | M10: * Pulling
C11: $/lb | D11: =D10/100 -> 0.95197122 | E11: * | K11: $/lb | L11: =L10/100 -> 0.95197122 | M11: * | P11: Tech Tallow Dlvd Cali | Q11: $/lb | R11: 0.335 | T11: RD | V11: 1 | W11: 42 gals | X11: 340 gals
C12: $/MT | D12: =D11*2204.62 -> 2098.7348 | E12: * | K12: $/MT | L12: =L11*2204.62 -> 2098.7348 | M12: * | Q12: $/MT | R12: =R11*2204.62 -> 738.5477
T13: D4 RINs | V13: 1.5
B14: Soybean Oil | C14: Cents / LB | D14: =VLOOKUP(B7,'[2]LCFS Breakout'!$B$2:$S$29,11,) -> 96.076816 | E14: * Pulling | J14: Soybean Oil | K14: Cents / LB | L14: =VLOOKUP(J7,'[2]LCFS Breakout'!$B$2:$S$24,11,) -> 96.076816 | M14: * Pulling
C15: $/lb | D15: =D14/100 -> 0.96076816 | E15: * | K15: $/lb | L15: =L14/100 -> 0.96076816 | M15: * | P15: Soybean Oil | Q15: $/lb
C16: $/MT | D16: =SUM(D15*2204.6) -> 2118.1095 | E16: * | K16: $/MT | L16: =SUM(L15*2204.6) -> 2118.1095 | M16: * | Q16: $/MT
B17: Dlvd CA Rail Actual | D17: 0.35 | G17: Graph | H17: * Insert into the first chart as a new box | J17: Dlvd CA Rail Actual | L17: 0.35 | N17: Graph | P17: Dlvd CA Rail accrual
B19: Feedstock Ratio | J19: Feedstock Ratio
B20: =B14 -> Soybean Oil | D20: =D16*E20 -> 529.52737 | E20: 0.25 | G20: Graph | H20: * | J20: =J14 & " Cost at 50%" -> Soybean Oil Cost at 50% | L20: =L16*0.5 -> 1059.0547 | M20: * | N20: Graph
B21: =B10 -> Tallow | D21: =D12*E21 -> 1574.0511 | E21: 0.75 | G21: Graph | H21: * | J21: =J10 & " Cost at 50%" -> Tallow Cost at 50% | L21: =L12*0.5 -> 1049.3674 | M21: * | N21: Graph
C22: Total | D22: =SUM(D20:D21) -> 2103.5785 | E22: * | K22: Total | L22: =SUM(L20:L21) -> 2108.4221 | M22: *
B24: RD Yield (Feedstock in/Fuel out) | D24: 0.94 | E24: * Manual Static | J24: BD Yield (Feedstock in/Fuel out) | L24: 0.96 | M24: * Manual Static | P24: BD Yield (Feedstock in?Fuel out) | R24: 0.96
C25: Result | D25: =D22/D24 -> 2237.8494 | E25: * | K25: Result | L25: =L22/L24 -> 2196.2731 | M25: *
B27: SBO Cost Per MT | D27: =D20/D24 -> 563.32699 | J27: SBO Cost Per MT | L27: =L20/L24 -> 1103.182
B28: Tallow Cost Per MT | D28: =D21/D24 -> 1674.5224 | J28: Tallow Cost Per MT | L28: =L21/L24 -> 1093.091
B30: SBO Cost Per Gal | D30: =D27/340 -> 1.6568441 | G30: Graph | J30: SBO Cost Per Gal | L30: =L27/300 -> 3.6772734 | N30: Graph
B31: Tallow Cost Per Gal | D31: =D28/340 -> 4.925066 | G31: Graph | J31: Tallow Cost Per Gal | L31: =L28/300 -> 3.6436368 | N31: Graph
B33: Fxd/Variable Production | C33: $/MT | D33: =D77+(136/340) -> 0.72352941 | E33: * Manual Static | J33: Fxd/Variable Production | K33: $/MT | L33: =R33+L77 -> 0.65 | M33: * Manual Static | P33: Fx/Variable Prodcution | Q33: $/MT | R33: =105/300 -> 0.35
C34: $/Gal | D34: =D33/340 -> 0.0021280277 | G34: Graph | K34: $/Gal | L34: =L33/300 -> 0.0021666667 | N34: Graph
B36: RD Cost | C36: $/MT | D36: =D33+D25 -> 2238.573 | E36: * | J36: BD Cost | K36: $/MT | L36: =L33+L25 -> 2196.9231 | M36: * | P36: BD Cost | Q36: $/MT | R36: 900
C37: $/Gal | D37: =SUM(D36/340) -> 6.5840381 | E37: * | K37: $/Gal | L37: =SUM(L36/300) -> 7.3230769 | M37: * | Q37: $/Gal | R37: =SUM(R36/300) -> 3
P39: BTC | R39: 1
B40: BTC | C40: $/Gal | D40: 1 | E40: * Manual Static | G40: Graph | J40: BTC | K40: $/Gal | L40: 1 | M40: * Manual Static | N40: Graph
B41: $/gal Diesel gallon Equiv | D41: 129.65 | E41: * Manual Static | J41: $/gal Diesel gallon Equiv | L41: 126.13 | M41: * Manual Static
B42: LCFS Credit Price | C42: $/Gal | D42: =D7/100 -> 0 | E42: * Pulling | J42: LCFS Credit Price | K42: $/Gal | L42: =L7/100 -> 0 | M42: * Pulling | P42: LCFS Credit Price | Q42: $/Gal
B43: 2019 ULSD Baseline CI | C43: gCO2e/MJ | D43: 94.17 | E43: * Manual Static | J43: 2019 ULSD Baseline CI | K43: gCO2e/MJ | L43: 94.17 | M43: * Manual Static | P43: 2019 ULSD Baseline CI | Q43: gCO2e/MJ | R43: 94.36
P44: Energy Density | Q44: MJ/gal | R44: 126.13
B45: Biodiesel CI | D45: 44.9 | E45: * Static (Tallow and SBO CI Average) | J45: Biodiesel CI | L45: 44.9 | M45: * Static (Tallow and SBO CI Average) | P45: Tech Tallow CI Score | R45: 30.79
B46: (ULSD CI - Biodiesel CI) | D46: =D43-D45 -> 49.27 | E46: * | J46: (ULSD CI - Biodiesel CI) | L46: =L43-L45 -> 49.27 | M46: *
P47: LCFS Credit Price | Q47: $/MT | R47: 196
B48: Credit Value | C48: $/gal | D48: =((D46/1000000)*D7)*D41 -> 0 | E48: * | G48: Graph | J48: Credit Value | K48: $/gal | L48: =((L46/1000000)*L7)*L41 -> 0 | M48: * | N48: Graph | P48: Credit Value | Q48: $/gal | R48: =(R43-R45)*R44/1000000*R47 -> 1.5715445
P50: CA Cap n Trade
B51: CA Cap n Trade | D51: 0.3 | G51: Graph | J51: CA Cap n Trade | L51: 0.3 | N51: Graph
B52: D4 RIN | C52: $/RIN | D52: 0.33 | G52: Graph | J52: D4 RIN | K52: $/RIN | L52: 0.33 | N52: Graph | P52: D4 RIN | Q52: $/RIN
C53: $/gal | D53: =SUM(D52*1.55) -> 0.5115 | K53: $/gal | L53: =SUM(L52*1.55) -> 0.5115 | Q53: $/gal
B55: Loaded w/ Credits | C55: $/gal | D55: =D37+D40+D42+D51+D53 -> 8.3955381 | J55: Loaded w/ Credits | K55: $/gal | L55: =L37+L40+L42+L51+L53 -> 9.1345769 | P55: Loaded w/ Credits
E57: Producer | G57: Blender | I57: OP/RP | M57: Producer | N57: Blender | O57: OP/RP
B58: RD Basis | D58: 0 | G58: 1 | J58: BD Basis | L58: -1.2 | N58: 1
B60: D4 RIN | C60: $/RIN | D60: 0.36 | E60: 1 | J60: D4 RIN | K60: $/RIN | L60: 0.36 | M60: 1 | P60: *Stacked Bar, 2 columns 1 for producer and one for blender with each of the amounts each receives. Producer gets D4 Rin Value * 100% = value. Blender gets X…
C61: $/gal | D61: =D60*1.7 -> 0.612 | K61: $/gal | L61: =L60*1.5 -> 0.54
B63: BTC | C63: $/gal | E63: 1 | J63: BTC | M63: 0.5
B65: LCFS Credit Value | E65: 1 | J65: LCFS Credit Value | M65: 1
B67: CA Cap N Trade | J67: CA Cap n Trade
B69: NYMEX HO | C69: $/gal | D69: 1.99 | J69: NYMEX HO | K69: $/gal | L69: 1.99
B70: or CARB Diesel "mark" | J70: or CARB Diesel "mark"
C73: $/gal | D73: =D69+D58+D61+D48 -> 2.602 | K73: $/gal | L73: =L69+L58+L61+R48 -> 2.9015445
B75: RD Gross Margin | C75: $/gal | D75: =D73-D53 -> 2.0905 | J75: BD Gross Margin | K75: $/gal | L75: =L73-R53 -> 2.9015445
B77: RD Variable Cost | C77: $/MT | D77: =110/340 -> 0.32352941 | J77: BD Variable Cost | K77: $/MT | L77: =90/300 -> 0.3 | N77: Constant
C78: $/gal | D78: =D77/D49 -> #DIV/0! | K78: $/gal | L78: =L77/R49 -> #DIV/0!

Sheet Gross Margins Calculations
A1: Biodiesel | H1: GRAPH OUTPUT OF THIS COLUMN
B2: Price of Tallow (cents per pound) | C2: Price of Tallow in $/MT | D2: Yield | E2: Price of Tallow per MT of Biodiesel | F2: Price of Tallow per Gallon | G2: Feedstock Mix | H2: Cost of Tallow Feedstock
B3: 35 | C3: =B3/100*2204.622 -> 771.6177 | D3: 0.96 | E3: =C3/D3 -> 803.76844 | F3: =E3/300 -> 2.6792281 | G3: 0.5 | H3: =F3*G3 -> 1.3396141
B4: Price of Soybean Oil (cents per pound) | C4: Price of Soybean Oil in $/MT | D4: Yield | E4: price of Soybean Oil in MT of Biodiesel | F4: Price of Soybean Oil per Gallon | G4: Feedstock Mix | H4: Cost of Soybean Oil Feedstock
B5: 27 | C5: =B5/100*2204.622 -> 595.24794 | D5: 0.96 | E5: =C5/D5 -> 620.04994 | F5: =E5/300 -> 2.0668331 | G5: 0.5 | H5: =F5*G5 -> 1.0334166
B6: Fixed Cost per Metric Tonne | F6: =F5+F3 -> 4.7460612 | H6: Fixed Cost per Gallon
B7: 105 | F7: =H7+F6 -> 5.0960612 | H7: =B7/300 -> 0.35
B8: Variable Cost per MT | F8: =H9+F7 -> 5.3960612 | H8: Variable Cost per Gallon
B9: 90 | H9: =B9/300 -> 0.3
H10: Price of CARB
H11: 2.01
A12: Renewable Diesel
B13: Price of Tallow (cents per pound) | C13: Price of Tallow in $/MT | D13: Yield | E13: Price of Tallow per MT of Biodiesel | F13: Price of Tallow per Gallon | G13: Feedstock Mix | H13: Cost of Tallow Feedstock
B14: 35 | C14: =B14/100*2204.622 -> 771.6177 | D14: 0.94 | E14: =C14/D14 -> 820.86989 | F14: =E14/340 -> 2.4143232 | G14: 0.25 | H14: =F14*G14 -> 0.6035808
B15: Price of Soybean Oil (cents per pound) | C15: Price of Soybean Oil in $/MT | D15: Yield | E15: price of Soybean Oil in MT of Biodiesel | F15: Price of Soybean Oil per Gallon | G15: Feedstock Mix | H15: Cost of Soybean Oil Feedstock
B16: 27 | C16: =B16/100*2204.622 -> 595.24794 | D16: 0.94 | E16: =C16/D16 -> 633.24249 | F16: =E16/340 -> 1.8624779 | G16: 0.75 | H16: =G16*F16 -> 1.3968584
B17: Fixed Cost per Metric Tonne | H17: Fixed Cost per Gallon
B18: 136 | H18: =B18/340 -> 0.4
B19: Variable Cost per MT | H19: Variable Cost per Gallon
B20: 110 | H20: =B20/340 -> 0.32352941
H21: Price of CARB
H22: 2.01

Sheet LCFS Categorized
A1: Category | B1: Type | C1: Breakout | D1: 7/5/19 | E1: 7/12/19 | F1: 7/19/19 | G1: 7/26/19 | H1: 8/2/19 | I1: 8/9/10 | J1: 8/16/19 | K1: 8/23/19 | L1: 8/30/19 | M1: 9/6/19 | N1: 9/13/19 | O1: 9/20/19 | P1: 9/28/19 | Q1: 10/5/19 | R1: 10/12/19 | S1: 10/19/19 | T1: 10/26/19 | U1: 11/2/19 | V1: 11/9/19 | W1: 11/16/19 | X1: 11/23/19 | Y1: 11/30/19 | Z1: 12/7/19 | AA1: 12/14/19 | AB1: 12/21/19 | AC1: 12/28/19
A2: Producer | B2: Biodiesel | C2: BD Producer D4 RIN Value | D2: =HLOOKUP('LCFS Categorized'!$C2,'LCFS Table'!$A$2:$CT$356,28,) -> 0.6 | E2: =HLOOKUP('LCFS Categorized'!$C2,'LCFS Table'!$A$2:$CT$356,29,) -> 0.61125 | F2: =HLOOKUP('LCFS Categorized'!$C2,'LCFS Table'!$A$2:$CT$356,30,) -> 0.67425 | G2: =HLOOKUP('LCFS Categorized'!$C2,'LCFS Table'!$A$2:$CT$356,31,) -> 0.68475 | H2: =HLOOKUP('LCFS Categorized'!$C2,'LCFS Table'!$A$2:$CT$356,32,) -> 0.7005 | I2: =HLOOKUP('LCFS Categorized'!$C2,'LCFS Table'!$A$2:$CT$356,33,) -> 0.6345 | J2: =HLOOKUP('LCFS Categorized'!$C2,'LCFS Table'!$A$2:$CT$356,34,) -> 0.6855 | K2: =HLOOKUP('LCFS Categorized'!$C2,'LCFS Table'!$A$2:$CT$356,35,) -> 0.7125 | L2: =HLOOKUP('LCFS Categorized'!$C2,'LCFS Table'!$A$2:$CT$356,36,) -> 0.70875 | M2: =HLOOKUP('LCFS Categorized'!$C2,'LCFS Table'!$A$2:$CT$356,37,) -> 0.7095 | N2: =HLOOKUP('LCFS Categorized'!$C2,'LCFS Table'!$A$2:$CT$356,38,) -> 0.7785 | O2: =HLOOKUP('LCFS Categorized'!$C2,'LCFS Table'!$A$2:$CT$356,39,) -> 0.735375 | P2: =HLOOKUP('LCFS Categorized'!$C2,'LCFS Table'!$A$2:$CT$356,40,) -> 0.81675 | Q2: =HLOOKUP('LCFS Categorized'!$C2,'LCFS Table'!$A$2:$CT$356,41,) -> 0.822 | R2: =HLOOKUP('LCFS Categorized'!$C2,'LCFS Table'!$A$2:$CT$356,42,) -> 0.8445 | S2: =HLOOKUP('LCFS Categorized'!$C2,'LCFS Table'!$A$2:$CT$356,43,) -> 0.87 | T2: =HLOOKUP('LCFS Categorized'!$C2,'LCFS Table'!$A$2:$CT$356,44,) -> 0.89925 | U2: =HLOOKUP('LCFS Categorized'!$C2,'LCFS Table'!$A$2:$CT$356,45,) -> 0.9345 | V2: =HLOOKUP('LCFS Categorized'!$C2,'LCFS Table'!$A$2:$CT$356,46,) -> 0.942 | W2: =HLOOKUP('LCFS Categorized'!$C2,'LCFS Table'!$A$2:$CT$356,47,) -> 0.94575 | X2: =HLOOKUP('LCFS Categorized'!$C2,'LCFS Table'!$A$2:$CT$356,48,) -> 0.8800005 | Y2: =HLOOKUP('LCFS Categorized'!$C2,'LCFS Table'!$A$2:$CT$356,49,) -> 0.876 | Z2: =HLOOKUP('LCFS Categorized'!$C2,'LCFS Table'!$A$2:$CT$356,50,) -> 0.8565 | AA2: =HLOOKUP('LCFS Categorized'!$C2,'LCFS Table'!$A$2:$CT$356,51,) -> 0.68325 | AB2: =HLOOKUP('LCFS Categorized'!$C2,'LCFS Table'!$A$2:$CT$356,52,) -> 0.64875 | AC2: =HLOOKUP('LCFS Categorized'!$C2,'LCFS Table'!$A$2:$CT$356,53,) -> 0.62625
A3: Producer | B3: Biodiesel | C3: BD Producer BTC Value | D3: =HLOOKUP('LCFS Categorized'!$C3,'LCFS Table'!$A$2:$CT$356,28,) -> 1 | E3: =HLOOKUP('LCFS Categorized'!$C3,'LCFS Table'!$A$2:$CT$356,29,) -> 1 | F3: =HLOOKUP('LCFS Categorized'!$C3,'LCFS Table'!$A$2:$CT$356,30,) -> 1 | G3: =HLOOKUP('LCFS Categorized'!$C3,'LCFS Table'!$A$2:$CT$356,31,) -> 1 | H3: =HLOOKUP('LCFS Categorized'!$C3,'LCFS Table'!$A$2:$CT$356,32,) -> 1 | I3: =HLOOKUP('LCFS Categorized'!$C3,'LCFS Table'!$A$2:$CT$356,33,) -> 1 | J3: =HLOOKUP('LCFS Categorized'!$C3,'LCFS Table'!$A$2:$CT$356,34,) -> 1 | K3: =HLOOKUP('LCFS Categorized'!$C3,'LCFS Table'!$A$2:$CT$356,35,) -> 1 | L3: =HLOOKUP('LCFS Categorized'!$C3,'LCFS Table'!$A$2:$CT$356,36,) -> 1 | M3: =HLOOKUP('LCFS Categorized'!$C3,'LCFS Table'!$A$2:$CT$356,37,) -> 1 | N3: =HLOOKUP('LCFS Categorized'!$C3,'LCFS Table'!$A$2:$CT$356,38,) -> 1 | O3: =HLOOKUP('LCFS Categorized'!$C3,'LCFS Table'!$A$2:$CT$356,39,) -> 1 | P3: =HLOOKUP('LCFS Categorized'!$C3,'LCFS Table'!$A$2:$CT$356,40,) -> 1 | Q3: =HLOOKUP('LCFS Categorized'!$C3,'LCFS Table'!$A$2:$CT$356,41,) -> 1 | R3: =HLOOKUP('LCFS Categorized'!$C3,'LCFS Table'!$A$2:$CT$356,42,) -> 1 | S3: =HLOOKUP('LCFS Categorized'!$C3,'LCFS Table'!$A$2:$CT$356,43,) -> 1 | T3: =HLOOKUP('LCFS Categorized'!$C3,'LCFS Table'!$A$2:$CT$356,44,) -> 1 | U3: =HLOOKUP('LCFS Categorized'!$C3,'LCFS Table'!$A$2:$CT$356,45,) -> 1 | V3: =HLOOKUP('LCFS Categorized'!$C3,'LCFS Table'!$A$2:$CT$356,46,) -> 1 | W3: =HLOOKUP('LCFS Categorized'!$C3,'LCFS Table'!$A$2:$CT$356,47,) -> 1 | X3: =HLOOKUP('LCFS Categorized'!$C3,'LCFS Table'!$A$2:$CT$356,48,) -> 1 | Y3: =HLOOKUP('LCFS Categorized'!$C3,'LCFS Table'!$A$2:$CT$356,49,) -> 1 | Z3: =HLOOKUP('LCFS Categorized'!$C3,'LCFS Table'!$A$2:$CT$356,50,) -> 1 | AA3: =HLOOKUP('LCFS Categorized'!$C3,'LCFS Table'!$A$2:$CT$356,51,) -> 1 | AB3: =HLOOKUP('LCFS Categorized'!$C3,'LCFS Table'!$A$2:$CT$356,52,) -> 1 | AC3: =HLOOKUP('LCFS Categorized'!$C3,'LCFS Table'!$A$2:$CT$356,53,) -> 1
A4: Producer | B4: Biodiesel | C4: BD Producer LCFS Credit Value | D4: =HLOOKUP('LCFS Categorized'!$C4,'LCFS Table'!$A$2:$CT$356,28,) -> 1.1925641 | E4: =HLOOKUP('LCFS Categorized'!$C4,'LCFS Table'!$A$2:$CT$356,29,) -> 1.2010435 | F4: =HLOOKUP('LCFS Categorized'!$C4,'LCFS Table'!$A$2:$CT$356,30,) -> 1.1898386 | G4: =HLOOKUP('LCFS Categorized'!$C4,'LCFS Table'!$A$2:$CT$356,31,) -> 1.1877188 | H4: =HLOOKUP('LCFS Categorized'!$C4,'LCFS Table'!$A$2:$CT$356,32,) -> 1.1868103 | I4: =HLOOKUP('LCFS Categorized'!$C4,'LCFS Table'!$A$2:$CT$356,33,) -> 1.1837819 | J4: =HLOOKUP('LCFS Categorized'!$C4,'LCFS Table'!$A$2:$CT$356,34,) -> 1.1968038 | K4: =HLOOKUP('LCFS Categorized'!$C4,'LCFS Table'!$A$2:$CT$356,35,) -> 1.2064945 | L4: =HLOOKUP('LCFS Categorized'!$C4,'LCFS Table'!$A$2:$CT$356,36,) -> 1.203769 | M4: =HLOOKUP('LCFS Categorized'!$C4,'LCFS Table'!$A$2:$CT$356,37,) -> 1.2116427 | N4: =HLOOKUP('LCFS Categorized'!$C4,'LCFS Table'!$A$2:$CT$356,38,) -> 1.2119456 | O4: =HLOOKUP('LCFS Categorized'!$C4,'LCFS Table'!$A$2:$CT$356,39,) -> 1.2081601 | P4: =HLOOKUP('LCFS Categorized'!$C4,'LCFS Table'!$A$2:$CT$356,40,) -> 1.2077059 | Q4: =HLOOKUP('LCFS Categorized'!$C4,'LCFS Table'!$A$2:$CT$356,41,) -> 1.2167909 | R4: =HLOOKUP('LCFS Categorized'!$C4,'LCFS Table'!$A$2:$CT$356,42,) -> 1.2279958 | S4: =HLOOKUP('LCFS Categorized'!$C4,'LCFS Table'!$A$2:$CT$356,43,) -> 1.2361724 | T4: =HLOOKUP('LCFS Categorized'!$C4,'LCFS Table'!$A$2:$CT$356,44,) -> 1.2573708 | U4: =HLOOKUP('LCFS Categorized'!$C4,'LCFS Table'!$A$2:$CT$356,45,) -> 1.2561595 | V4: =HLOOKUP('LCFS Categorized'!$C4,'LCFS Table'!$A$2:$CT$356,46,) -> 1.2649417 | W4: =HLOOKUP('LCFS Categorized'!$C4,'LCFS Table'!$A$2:$CT$356,47,) -> 1.2597935 | X4: =HLOOKUP('LCFS Categorized'!$C4,'LCFS Table'!$A$2:$CT$356,48,) -> 1.2537368 | Y4: =HLOOKUP('LCFS Categorized'!$C4,'LCFS Table'!$A$2:$CT$356,49,) -> 1.2537368 | Z4: =HLOOKUP('LCFS Categorized'!$C4,'LCFS Table'!$A$2:$CT$356,50,) -> 1.2558566 | AA4: =HLOOKUP('LCFS Categorized'!$C4,'LCFS Table'!$A$2:$CT$356,51,) -> 1.2452574 | AB4: =HLOOKUP('LCFS Categorized'!$C4,'LCFS Table'!$A$2:$CT$356,52,) -> 1.2476801 | AC4: =HLOOKUP('LCFS Categorized'!$C4,'LCFS Table'!$A$2:$CT$356,53,) -> 1.2461659
A5: Producer | B5: Biodiesel | C5: BD Producer Cap N Trade Value | D5: =HLOOKUP('LCFS Categorized'!$C5,'LCFS Table'!$A$2:$CT$356,28,) -> 0 | E5: =HLOOKUP('LCFS Categorized'!$C5,'LCFS Table'!$A$2:$CT$356,29,) -> 0 | F5: =HLOOKUP('LCFS Categorized'!$C5,'LCFS Table'!$A$2:$CT$356,30,) -> 0 | G5: =HLOOKUP('LCFS Categorized'!$C5,'LCFS Table'!$A$2:$CT$356,31,) -> 0 | H5: =HLOOKUP('LCFS Categorized'!$C5,'LCFS Table'!$A$2:$CT$356,32,) -> 0 | I5: =HLOOKUP('LCFS Categorized'!$C5,'LCFS Table'!$A$2:$CT$356,33,) -> 0 | J5: =HLOOKUP('LCFS Categorized'!$C5,'LCFS Table'!$A$2:$CT$356,34,) -> 0 | K5: =HLOOKUP('LCFS Categorized'!$C5,'LCFS Table'!$A$2:$CT$356,35,) -> 0 | L5: =HLOOKUP('LCFS Categorized'!$C5,'LCFS Table'!$A$2:$CT$356,36,) -> 0 | M5: =HLOOKUP('LCFS Categorized'!$C5,'LCFS Table'!$A$2:$CT$356,37,) -> 0 | N5: =HLOOKUP('LCFS Categorized'!$C5,'LCFS Table'!$A$2:$CT$356,38,) -> 0 | O5: =HLOOKUP('LCFS Categorized'!$C5,'LCFS Table'!$A$2:$CT$356,39,) -> 0 | P5: =HLOOKUP('LCFS Categorized'!$C5,'LCFS Table'!$A$2:$CT$356,40,) -> 0 | Q5: =HLOOKUP('LCFS Categorized'!$C5,'LCFS Table'!$A$2:$CT$356,41,) -> 0 | R5: =HLOOKUP('LCFS Categorized'!$C5,'LCFS Table'!$A$2:$CT$356,42,) -> 0 | S5: =HLOOKUP('LCFS Categorized'!$C5,'LCFS Table'!$A$2:$CT$356,43,) -> 0 | T5: =HLOOKUP('LCFS Categorized'!$C5,'LCFS Table'!$A$2:$CT$356,44,) -> 0 | U5: =HLOOKUP('LCFS Categorized'!$C5,'LCFS Table'!$A$2:$CT$356,45,) -> 0 | V5: =HLOOKUP('LCFS Categorized'!$C5,'LCFS Table'!$A$2:$CT$356,46,) -> 0 | W5: =HLOOKUP('LCFS Categorized'!$C5,'LCFS Table'!$A$2:$CT$356,47,) -> 0 | X5: =HLOOKUP('LCFS Categorized'!$C5,'LCFS Table'!$A$2:$CT$356,48,) -> 0 | Y5: =HLOOKUP('LCFS Categorized'!$C5,'LCFS Table'!$A$2:$CT$356,49,) -> 0 | Z5: =HLOOKUP('LCFS Categorized'!$C5,'LCFS Table'!$A$2:$CT$356,50,) -> 0 | AA5: =HLOOKUP('LCFS Categorized'!$C5,'LCFS Table'!$A$2:$CT$356,51,) -> 0 | AB5: =HLOOKUP('LCFS Categorized'!$C5,'LCFS Table'!$A$2:$CT$356,52,) -> 0 | AC5: =HLOOKUP('LCFS Categorized'!$C5,'LCFS Table'!$A$2:$CT$356,53,) -> 0
A6: Blender | B6: Biodiesel | C6: BD Blender D4 RIN Value | D6: =HLOOKUP('LCFS Categorized'!$C6,'LCFS Table'!$A$2:$CT$356,28,) -> 0 | E6: =HLOOKUP('LCFS Categorized'!$C6,'LCFS Table'!$A$2:$CT$356,29,) -> 0 | F6: =HLOOKUP('LCFS Categorized'!$C6,'LCFS Table'!$A$2:$CT$356,30,) -> 0 | G6: =HLOOKUP('LCFS Categorized'!$C6,'LCFS Table'!$A$2:$CT$356,31,) -> 0 | H6: =HLOOKUP('LCFS Categorized'!$C6,'LCFS Table'!$A$2:$CT$356,32,) -> 0 | I6: =HLOOKUP('LCFS Categorized'!$C6,'LCFS Table'!$A$2:$CT$356,33,) -> 0 | J6: =HLOOKUP('LCFS Categorized'!$C6,'LCFS Table'!$A$2:$CT$356,34,) -> 0 | K6: =HLOOKUP('LCFS Categorized'!$C6,'LCFS Table'!$A$2:$CT$356,35,) -> 0 | L6: =HLOOKUP('LCFS Categorized'!$C6,'LCFS Table'!$A$2:$CT$356,36,) -> 0 | M6: =HLOOKUP('LCFS Categorized'!$C6,'LCFS Table'!$A$2:$CT$356,37,) -> 0 | N6: =HLOOKUP('LCFS Categorized'!$C6,'LCFS Table'!$A$2:$CT$356,38,) -> 0 | O6: =HLOOKUP('LCFS Categorized'!$C6,'LCFS Table'!$A$2:$CT$356,39,) -> 0 | P6: =HLOOKUP('LCFS Categorized'!$C6,'LCFS Table'!$A$2:$CT$356,40,) -> 0 | Q6: =HLOOKUP('LCFS Categorized'!$C6,'LCFS Table'!$A$2:$CT$356,41,) -> 0 | R6: =HLOOKUP('LCFS Categorized'!$C6,'LCFS Table'!$A$2:$CT$356,42,) -> 0 | S6: =HLOOKUP('LCFS Categorized'!$C6,'LCFS Table'!$A$2:$CT$356,43,) -> 0 | T6: =HLOOKUP('LCFS Categorized'!$C6,'LCFS Table'!$A$2:$CT$356,44,) -> 0 | U6: =HLOOKUP('LCFS Categorized'!$C6,'LCFS Table'!$A$2:$CT$356,45,) -> 0 | V6: =HLOOKUP('LCFS Categorized'!$C6,'LCFS Table'!$A$2:$CT$356,46,) -> 0 | W6: =HLOOKUP('LCFS Categorized'!$C6,'LCFS Table'!$A$2:$CT$356,47,) -> 0 | X6: =HLOOKUP('LCFS Categorized'!$C6,'LCFS Table'!$A$2:$CT$356,48,) -> 0 | Y6: =HLOOKUP('LCFS Categorized'!$C6,'LCFS Table'!$A$2:$CT$356,49,) -> 0 | Z6: =HLOOKUP('LCFS Categorized'!$C6,'LCFS Table'!$A$2:$CT$356,50,) -> 0 | AA6: =HLOOKUP('LCFS Categorized'!$C6,'LCFS Table'!$A$2:$CT$356,51,) -> 0 | AB6: =HLOOKUP('LCFS Categorized'!$C6,'LCFS Table'!$A$2:$CT$356,52,) -> 0 | AC6: =HLOOKUP('LCFS Categorized'!$C6,'LCFS Table'!$A$2:$CT$356,53,) -> 0
A7: Blender | B7: Biodiesel | C7: BD Blender BTC Value | D7: =HLOOKUP('LCFS Categorized'!$C7,'LCFS Table'!$A$2:$CT$356,28,) -> 0 | E7: =HLOOKUP('LCFS Categorized'!$C7,'LCFS Table'!$A$2:$CT$356,29,) -> 0 | F7: =HLOOKUP('LCFS Categorized'!$C7,'LCFS Table'!$A$2:$CT$356,30,) -> 0 | G7: =HLOOKUP('LCFS Categorized'!$C7,'LCFS Table'!$A$2:$CT$356,31,) -> 0 | H7: =HLOOKUP('LCFS Categorized'!$C7,'LCFS Table'!$A$2:$CT$356,32,) -> 0 | I7: =HLOOKUP('LCFS Categorized'!$C7,'LCFS Table'!$A$2:$CT$356,33,) -> 0 | J7: =HLOOKUP('LCFS Categorized'!$C7,'LCFS Table'!$A$2:$CT$356,34,) -> 0 | K7: =HLOOKUP('LCFS Categorized'!$C7,'LCFS Table'!$A$2:$CT$356,35,) -> 0 | L7: =HLOOKUP('LCFS Categorized'!$C7,'LCFS Table'!$A$2:$CT$356,36,) -> 0 | M7: =HLOOKUP('LCFS Categorized'!$C7,'LCFS Table'!$A$2:$CT$356,37,) -> 0 | N7: =HLOOKUP('LCFS Categorized'!$C7,'LCFS Table'!$A$2:$CT$356,38,) -> 0 | O7: =HLOOKUP('LCFS Categorized'!$C7,'LCFS Table'!$A$2:$CT$356,39,) -> 0 | P7: =HLOOKUP('LCFS Categorized'!$C7,'LCFS Table'!$A$2:$CT$356,40,) -> 0 | Q7: =HLOOKUP('LCFS Categorized'!$C7,'LCFS Table'!$A$2:$CT$356,41,) -> 0 | R7: =HLOOKUP('LCFS Categorized'!$C7,'LCFS Table'!$A$2:$CT$356,42,) -> 0 | S7: =HLOOKUP('LCFS Categorized'!$C7,'LCFS Table'!$A$2:$CT$356,43,) -> 0 | T7: =HLOOKUP('LCFS Categorized'!$C7,'LCFS Table'!$A$2:$CT$356,44,) -> 0 | U7: =HLOOKUP('LCFS Categorized'!$C7,'LCFS Table'!$A$2:$CT$356,45,) -> 0 | V7: =HLOOKUP('LCFS Categorized'!$C7,'LCFS Table'!$A$2:$CT$356,46,) -> 0 | W7: =HLOOKUP('LCFS Categorized'!$C7,'LCFS Table'!$A$2:$CT$356,47,) -> 0 | X7: =HLOOKUP('LCFS Categorized'!$C7,'LCFS Table'!$A$2:$CT$356,48,) -> 0 | Y7: =HLOOKUP('LCFS Categorized'!$C7,'LCFS Table'!$A$2:$CT$356,49,) -> 0 | Z7: =HLOOKUP('LCFS Categorized'!$C7,'LCFS Table'!$A$2:$CT$356,50,) -> 0 | AA7: =HLOOKUP('LCFS Categorized'!$C7,'LCFS Table'!$A$2:$CT$356,51,) -> 0 | AB7: =HLOOKUP('LCFS Categorized'!$C7,'LCFS Table'!$A$2:$CT$356,52,) -> 0 | AC7: =HLOOKUP('LCFS Categorized'!$C7,'LCFS Table'!$A$2:$CT$356,53,) -> 0
A8: Blender | B8: Biodiesel | C8: BD Blender LCFS Credit Value | D8: =HLOOKUP('LCFS Categorized'!$C8,'LCFS Table'!$A$2:$CT$356,28,) -> 0 | E8: =HLOOKUP('LCFS Categorized'!$C8,'LCFS Table'!$A$2:$CT$356,29,) -> 0 | F8: =HLOOKUP('LCFS Categorized'!$C8,'LCFS Table'!$A$2:$CT$356,30,) -> 0 | G8: =HLOOKUP('LCFS Categorized'!$C8,'LCFS Table'!$A$2:$CT$356,31,) -> 0 | H8: =HLOOKUP('LCFS Categorized'!$C8,'LCFS Table'!$A$2:$CT$356,32,) -> 0 | I8: =HLOOKUP('LCFS Categorized'!$C8,'LCFS Table'!$A$2:$CT$356,33,) -> 0 | J8: =HLOOKUP('LCFS Categorized'!$C8,'LCFS Table'!$A$2:$CT$356,34,) -> 0 | K8: =HLOOKUP('LCFS Categorized'!$C8,'LCFS Table'!$A$2:$CT$356,35,) -> 0 | L8: =HLOOKUP('LCFS Categorized'!$C8,'LCFS Table'!$A$2:$CT$356,36,) -> 0 | M8: =HLOOKUP('LCFS Categorized'!$C8,'LCFS Table'!$A$2:$CT$356,37,) -> 0 | N8: =HLOOKUP('LCFS Categorized'!$C8,'LCFS Table'!$A$2:$CT$356,38,) -> 0 | O8: =HLOOKUP('LCFS Categorized'!$C8,'LCFS Table'!$A$2:$CT$356,39,) -> 0 | P8: =HLOOKUP('LCFS Categorized'!$C8,'LCFS Table'!$A$2:$CT$356,40,) -> 0 | Q8: =HLOOKUP('LCFS Categorized'!$C8,'LCFS Table'!$A$2:$CT$356,41,) -> 0 | R8: =HLOOKUP('LCFS Categorized'!$C8,'LCFS Table'!$A$2:$CT$356,42,) -> 0 | S8: =HLOOKUP('LCFS Categorized'!$C8,'LCFS Table'!$A$2:$CT$356,43,) -> 0 | T8: =HLOOKUP('LCFS Categorized'!$C8,'LCFS Table'!$A$2:$CT$356,44,) -> 0 | U8: =HLOOKUP('LCFS Categorized'!$C8,'LCFS Table'!$A$2:$CT$356,45,) -> 0 | V8: =HLOOKUP('LCFS Categorized'!$C8,'LCFS Table'!$A$2:$CT$356,46,) -> 0 | W8: =HLOOKUP('LCFS Categorized'!$C8,'LCFS Table'!$A$2:$CT$356,47,) -> 0 | X8: =HLOOKUP('LCFS Categorized'!$C8,'LCFS Table'!$A$2:$CT$356,48,) -> 0 | Y8: =HLOOKUP('LCFS Categorized'!$C8,'LCFS Table'!$A$2:$CT$356,49,) -> 0 | Z8: =HLOOKUP('LCFS Categorized'!$C8,'LCFS Table'!$A$2:$CT$356,50,) -> 0 | AA8: =HLOOKUP('LCFS Categorized'!$C8,'LCFS Table'!$A$2:$CT$356,51,) -> 0 | AB8: =HLOOKUP('LCFS Categorized'!$C8,'LCFS Table'!$A$2:$CT$356,52,) -> 0 | AC8: =HLOOKUP('LCFS Categorized'!$C8,'LCFS Table'!$A$2:$CT$356,53,) -> 0
A9: Blender | B9: Biodiesel | C9: BD Blender Cap N Trade Value | D9: =HLOOKUP('LCFS Categorized'!$C9,'LCFS Table'!$A$2:$CT$356,28,) -> 0 | E9: =HLOOKUP('LCFS Categorized'!$C9,'LCFS Table'!$A$2:$CT$356,29,) -> 0 | F9: =HLOOKUP('LCFS Categorized'!$C9,'LCFS Table'!$A$2:$CT$356,30,) -> 0 | G9: =HLOOKUP('LCFS Categorized'!$C9,'LCFS Table'!$A$2:$CT$356,31,) -> 0 | H9: =HLOOKUP('LCFS Categorized'!$C9,'LCFS Table'!$A$2:$CT$356,32,) -> 0 | I9: =HLOOKUP('LCFS Categorized'!$C9,'LCFS Table'!$A$2:$CT$356,33,) -> 0 | J9: =HLOOKUP('LCFS Categorized'!$C9,'LCFS Table'!$A$2:$CT$356,34,) -> 0 | K9: =HLOOKUP('LCFS Categorized'!$C9,'LCFS Table'!$A$2:$CT$356,35,) -> 0 | L9: =HLOOKUP('LCFS Categorized'!$C9,'LCFS Table'!$A$2:$CT$356,36,) -> 0 | M9: =HLOOKUP('LCFS Categorized'!$C9,'LCFS Table'!$A$2:$CT$356,37,) -> 0 | N9: =HLOOKUP('LCFS Categorized'!$C9,'LCFS Table'!$A$2:$CT$356,38,) -> 0 | O9: =HLOOKUP('LCFS Categorized'!$C9,'LCFS Table'!$A$2:$CT$356,39,) -> 0 | P9: =HLOOKUP('LCFS Categorized'!$C9,'LCFS Table'!$A$2:$CT$356,40,) -> 0 | Q9: =HLOOKUP('LCFS Categorized'!$C9,'LCFS Table'!$A$2:$CT$356,41,) -> 0 | R9: =HLOOKUP('LCFS Categorized'!$C9,'LCFS Table'!$A$2:$CT$356,42,) -> 0 | S9: =HLOOKUP('LCFS Categorized'!$C9,'LCFS Table'!$A$2:$CT$356,43,) -> 0 | T9: =HLOOKUP('LCFS Categorized'!$C9,'LCFS Table'!$A$2:$CT$356,44,) -> 0 | U9: =HLOOKUP('LCFS Categorized'!$C9,'LCFS Table'!$A$2:$CT$356,45,) -> 0 | V9: =HLOOKUP('LCFS Categorized'!$C9,'LCFS Table'!$A$2:$CT$356,46,) -> 0 | W9: =HLOOKUP('LCFS Categorized'!$C9,'LCFS Table'!$A$2:$CT$356,47,) -> 0 | X9: =HLOOKUP('LCFS Categorized'!$C9,'LCFS Table'!$A$2:$CT$356,48,) -> 0 | Y9: =HLOOKUP('LCFS Categorized'!$C9,'LCFS Table'!$A$2:$CT$356,49,) -> 0 | Z9: =HLOOKUP('LCFS Categorized'!$C9,'LCFS Table'!$A$2:$CT$356,50,) -> 0 | AA9: =HLOOKUP('LCFS Categorized'!$C9,'LCFS Table'!$A$2:$CT$356,51,) -> 0 | AB9: =HLOOKUP('LCFS Categorized'!$C9,'LCFS Table'!$A$2:$CT$356,52,) -> 0 | AC9: =HLOOKUP('LCFS Categorized'!$C9,'LCFS Table'!$A$2:$CT$356,53,) -> 0
A10: Producer | B10: Renewable Diesel | C10: RD Producer D4 RIN Value | D10: =HLOOKUP('LCFS Categorized'!$C10,'LCFS Table'!$A$2:$CT$356,28,) -> 0.68 | E10: =HLOOKUP('LCFS Categorized'!$C10,'LCFS Table'!$A$2:$CT$356,29,) -> 0.69275 | F10: =HLOOKUP('LCFS Categorized'!$C10,'LCFS Table'!$A$2:$CT$356,30,) -> 0.76415 | G10: =HLOOKUP('LCFS Categorized'!$C10,'LCFS Table'!$A$2:$CT$356,31,) -> 0.77605 | H10: =HLOOKUP('LCFS Categorized'!$C10,'LCFS Table'!$A$2:$CT$356,32,) -> 0.7939 | I10: =HLOOKUP('LCFS Categorized'!$C10,'LCFS Table'!$A$2:$CT$356,33,) -> 0.7191 | J10: =HLOOKUP('LCFS Categorized'!$C10,'LCFS Table'!$A$2:$CT$356,34,) -> 0.7769 | K10: =HLOOKUP('LCFS Categorized'!$C10,'LCFS Table'!$A$2:$CT$356,35,) -> 0.8075 | L10: =HLOOKUP('LCFS Categorized'!$C10,'LCFS Table'!$A$2:$CT$356,36,) -> 0.80325 | M10: =HLOOKUP('LCFS Categorized'!$C10,'LCFS Table'!$A$2:$CT$356,37,) -> 0.8041 | N10: =HLOOKUP('LCFS Categorized'!$C10,'LCFS Table'!$A$2:$CT$356,38,) -> 0.8823 | O10: =HLOOKUP('LCFS Categorized'!$C10,'LCFS Table'!$A$2:$CT$356,39,) -> 0.833425 | P10: =HLOOKUP('LCFS Categorized'!$C10,'LCFS Table'!$A$2:$CT$356,40,) -> 0.92565 | Q10: =HLOOKUP('LCFS Categorized'!$C10,'LCFS Table'!$A$2:$CT$356,41,) -> 0.9316 | R10: =HLOOKUP('LCFS Categorized'!$C10,'LCFS Table'!$A$2:$CT$356,42,) -> 0.9571 | S10: =HLOOKUP('LCFS Categorized'!$C10,'LCFS Table'!$A$2:$CT$356,43,) -> 0.986 | T10: =HLOOKUP('LCFS Categorized'!$C10,'LCFS Table'!$A$2:$CT$356,44,) -> 1.01915 | U10: =HLOOKUP('LCFS Categorized'!$C10,'LCFS Table'!$A$2:$CT$356,45,) -> 1.0591 | V10: =HLOOKUP('LCFS Categorized'!$C10,'LCFS Table'!$A$2:$CT$356,46,) -> 1.0676 | W10: =HLOOKUP('LCFS Categorized'!$C10,'LCFS Table'!$A$2:$CT$356,47,) -> 1.07185 | X10: =HLOOKUP('LCFS Categorized'!$C10,'LCFS Table'!$A$2:$CT$356,48,) -> 0.9973339 | Y10: =HLOOKUP('LCFS Categorized'!$C10,'LCFS Table'!$A$2:$CT$356,49,) -> 0.9928 | Z10: =HLOOKUP('LCFS Categorized'!$C10,'LCFS Table'!$A$2:$CT$356,50,) -> 0.9707 | AA10: =HLOOKUP('LCFS Categorized'!$C10,'LCFS Table'!$A$2:$CT$356,51,) -> 0.77435 | AB10: =HLOOKUP('LCFS Categorized'!$C10,'LCFS Table'!$A$2:$CT$356,52,) -> 0.73525 | AC10: =HLOOKUP('LCFS Categorized'!$C10,'LCFS Table'!$A$2:$CT$356,53,) -> 0.70975
A11: Producer | B11: Renewable Diesel | C11: RD Producer BTC Value | D11: =HLOOKUP('LCFS Categorized'!$C11,'LCFS Table'!$A$2:$CT$356,28,) -> 1 | E11: =HLOOKUP('LCFS Categorized'!$C11,'LCFS Table'!$A$2:$CT$356,29,) -> 1 | F11: =HLOOKUP('LCFS Categorized'!$C11,'LCFS Table'!$A$2:$CT$356,30,) -> 1 | G11: =HLOOKUP('LCFS Categorized'!$C11,'LCFS Table'!$A$2:$CT$356,31,) -> 1 | H11: =HLOOKUP('LCFS Categorized'!$C11,'LCFS Table'!$A$2:$CT$356,32,) -> 1 | I11: =HLOOKUP('LCFS Categorized'!$C11,'LCFS Table'!$A$2:$CT$356,33,) -> 1 | J11: =HLOOKUP('LCFS Categorized'!$C11,'LCFS Table'!$A$2:$CT$356,34,) -> 1 | K11: =HLOOKUP('LCFS Categorized'!$C11,'LCFS Table'!$A$2:$CT$356,35,) -> 1 | L11: =HLOOKUP('LCFS Categorized'!$C11,'LCFS Table'!$A$2:$CT$356,36,) -> 1 | M11: =HLOOKUP('LCFS Categorized'!$C11,'LCFS Table'!$A$2:$CT$356,37,) -> 1 | N11: =HLOOKUP('LCFS Categorized'!$C11,'LCFS Table'!$A$2:$CT$356,38,) -> 1 | O11: =HLOOKUP('LCFS Categorized'!$C11,'LCFS Table'!$A$2:$CT$356,39,) -> 1 | P11: =HLOOKUP('LCFS Categorized'!$C11,'LCFS Table'!$A$2:$CT$356,40,) -> 1 | Q11: =HLOOKUP('LCFS Categorized'!$C11,'LCFS Table'!$A$2:$CT$356,41,) -> 1 | R11: =HLOOKUP('LCFS Categorized'!$C11,'LCFS Table'!$A$2:$CT$356,42,) -> 1 | S11: =HLOOKUP('LCFS Categorized'!$C11,'LCFS Table'!$A$2:$CT$356,43,) -> 1 | T11: =HLOOKUP('LCFS Categorized'!$C11,'LCFS Table'!$A$2:$CT$356,44,) -> 1 | U11: =HLOOKUP('LCFS Categorized'!$C11,'LCFS Table'!$A$2:$CT$356,45,) -> 1 | V11: =HLOOKUP('LCFS Categorized'!$C11,'LCFS Table'!$A$2:$CT$356,46,) -> 1 | W11: =HLOOKUP('LCFS Categorized'!$C11,'LCFS Table'!$A$2:$CT$356,47,) -> 1 | X11: =HLOOKUP('LCFS Categorized'!$C11,'LCFS Table'!$A$2:$CT$356,48,) -> 1 | Y11: =HLOOKUP('LCFS Categorized'!$C11,'LCFS Table'!$A$2:$CT$356,49,) -> 1 | Z11: =HLOOKUP('LCFS Categorized'!$C11,'LCFS Table'!$A$2:$CT$356,50,) -> 1 | AA11: =HLOOKUP('LCFS Categorized'!$C11,'LCFS Table'!$A$2:$CT$356,51,) -> 1 | AB11: =HLOOKUP('LCFS Categorized'!$C11,'LCFS Table'!$A$2:$CT$356,52,) -> 1 | AC11: =HLOOKUP('LCFS Categorized'!$C11,'LCFS Table'!$A$2:$CT$356,53,) -> 1
A12: Producer | B12: Renewable Diesel | C12: RD Producer LCFS Credit Value | D12: =HLOOKUP('LCFS Categorized'!$C12,'LCFS Table'!$A$2:$CT$356,28,) -> 1.7323302 | E12: =HLOOKUP('LCFS Categorized'!$C12,'LCFS Table'!$A$2:$CT$356,29,) -> 1.7446475 | F12: =HLOOKUP('LCFS Categorized'!$C12,'LCFS Table'!$A$2:$CT$356,30,) -> 1.7283711 | G12: =HLOOKUP('LCFS Categorized'!$C12,'LCFS Table'!$A$2:$CT$356,31,) -> 1.7252918 | H12: =HLOOKUP('LCFS Categorized'!$C12,'LCFS Table'!$A$2:$CT$356,32,) -> 1.7239721 | I12: =HLOOKUP('LCFS Categorized'!$C12,'LCFS Table'!$A$2:$CT$356,33,) -> 1.7195731 | J12: =HLOOKUP('LCFS Categorized'!$C12,'LCFS Table'!$A$2:$CT$356,34,) -> 1.7384889 | K12: =HLOOKUP('LCFS Categorized'!$C12,'LCFS Table'!$A$2:$CT$356,35,) -> 1.7525657 | L12: =HLOOKUP('LCFS Categorized'!$C12,'LCFS Table'!$A$2:$CT$356,36,) -> 1.7486066 | M12: =HLOOKUP('LCFS Categorized'!$C12,'LCFS Table'!$A$2:$CT$356,37,) -> 1.760044 | N12: =HLOOKUP('LCFS Categorized'!$C12,'LCFS Table'!$A$2:$CT$356,38,) -> 1.7604839 | O12: =HLOOKUP('LCFS Categorized'!$C12,'LCFS Table'!$A$2:$CT$356,39,) -> 1.7549851 | P12: =HLOOKUP('LCFS Categorized'!$C12,'LCFS Table'!$A$2:$CT$356,40,) -> 1.7543253 | Q12: =HLOOKUP('LCFS Categorized'!$C12,'LCFS Table'!$A$2:$CT$356,41,) -> 1.7675223 | R12: =HLOOKUP('LCFS Categorized'!$C12,'LCFS Table'!$A$2:$CT$356,42,) -> 1.7837987 | S12: =HLOOKUP('LCFS Categorized'!$C12,'LCFS Table'!$A$2:$CT$356,43,) -> 1.795676 | T12: =HLOOKUP('LCFS Categorized'!$C12,'LCFS Table'!$A$2:$CT$356,44,) -> 1.8264691 | U12: =HLOOKUP('LCFS Categorized'!$C12,'LCFS Table'!$A$2:$CT$356,45,) -> 1.8247095 | V12: =HLOOKUP('LCFS Categorized'!$C12,'LCFS Table'!$A$2:$CT$356,46,) -> 1.8374666 | W12: =HLOOKUP('LCFS Categorized'!$C12,'LCFS Table'!$A$2:$CT$356,47,) -> 1.8299883 | X12: =HLOOKUP('LCFS Categorized'!$C12,'LCFS Table'!$A$2:$CT$356,48,) -> 1.8211902 | Y12: =HLOOKUP('LCFS Categorized'!$C12,'LCFS Table'!$A$2:$CT$356,49,) -> 1.8211902 | Z12: =HLOOKUP('LCFS Categorized'!$C12,'LCFS Table'!$A$2:$CT$356,50,) -> 1.8242696 | AA12: =HLOOKUP('LCFS Categorized'!$C12,'LCFS Table'!$A$2:$CT$356,51,) -> 1.808873 | AB12: =HLOOKUP('LCFS Categorized'!$C12,'LCFS Table'!$A$2:$CT$356,52,) -> 1.8123922 | AC12: =HLOOKUP('LCFS Categorized'!$C12,'LCFS Table'!$A$2:$CT$356,53,) -> 1.8101927
A13: Producer | B13: Renewable Diesel | C13: RD Producer Cap N Trade Value | D13: =HLOOKUP('LCFS Categorized'!$C13,'LCFS Table'!$A$2:$CT$356,28,) -> 0 | E13: =HLOOKUP('LCFS Categorized'!$C13,'LCFS Table'!$A$2:$CT$356,29,) -> 0 | F13: =HLOOKUP('LCFS Categorized'!$C13,'LCFS Table'!$A$2:$CT$356,30,) -> 0 | G13: =HLOOKUP('LCFS Categorized'!$C13,'LCFS Table'!$A$2:$CT$356,31,) -> 0 | H13: =HLOOKUP('LCFS Categorized'!$C13,'LCFS Table'!$A$2:$CT$356,32,) -> 0 | I13: =HLOOKUP('LCFS Categorized'!$C13,'LCFS Table'!$A$2:$CT$356,33,) -> 0 | J13: =HLOOKUP('LCFS Categorized'!$C13,'LCFS Table'!$A$2:$CT$356,34,) -> 0 | K13: =HLOOKUP('LCFS Categorized'!$C13,'LCFS Table'!$A$2:$CT$356,35,) -> 0 | L13: =HLOOKUP('LCFS Categorized'!$C13,'LCFS Table'!$A$2:$CT$356,36,) -> 0 | M13: =HLOOKUP('LCFS Categorized'!$C13,'LCFS Table'!$A$2:$CT$356,37,) -> 0 | N13: =HLOOKUP('LCFS Categorized'!$C13,'LCFS Table'!$A$2:$CT$356,38,) -> 0 | O13: =HLOOKUP('LCFS Categorized'!$C13,'LCFS Table'!$A$2:$CT$356,39,) -> 0 | P13: =HLOOKUP('LCFS Categorized'!$C13,'LCFS Table'!$A$2:$CT$356,40,) -> 0 | Q13: =HLOOKUP('LCFS Categorized'!$C13,'LCFS Table'!$A$2:$CT$356,41,) -> 0 | R13: =HLOOKUP('LCFS Categorized'!$C13,'LCFS Table'!$A$2:$CT$356,42,) -> 0 | S13: =HLOOKUP('LCFS Categorized'!$C13,'LCFS Table'!$A$2:$CT$356,43,) -> 0 | T13: =HLOOKUP('LCFS Categorized'!$C13,'LCFS Table'!$A$2:$CT$356,44,) -> 0 | U13: =HLOOKUP('LCFS Categorized'!$C13,'LCFS Table'!$A$2:$CT$356,45,) -> 0 | V13: =HLOOKUP('LCFS Categorized'!$C13,'LCFS Table'!$A$2:$CT$356,46,) -> 0 | W13: =HLOOKUP('LCFS Categorized'!$C13,'LCFS Table'!$A$2:$CT$356,47,) -> 0 | X13: =HLOOKUP('LCFS Categorized'!$C13,'LCFS Table'!$A$2:$CT$356,48,) -> 0 | Y13: =HLOOKUP('LCFS Categorized'!$C13,'LCFS Table'!$A$2:$CT$356,49,) -> 0 | Z13: =HLOOKUP('LCFS Categorized'!$C13,'LCFS Table'!$A$2:$CT$356,50,) -> 0 | AA13: =HLOOKUP('LCFS Categorized'!$C13,'LCFS Table'!$A$2:$CT$356,51,) -> 0 | AB13: =HLOOKUP('LCFS Categorized'!$C13,'LCFS Table'!$A$2:$CT$356,52,) -> 0 | AC13: =HLOOKUP('LCFS Categorized'!$C13,'LCFS Table'!$A$2:$CT$356,53,) -> 0
... A17: Blender | B17: Renewable Diesel | C17: RD Blender Cap N Trade Value | D17: =HLOOKUP('LCFS Categorized'!$C17,'LCFS Table'!$A$2:$CT$356,28,) -> 0.16 | E17: =HLOOKUP('LCFS Categorized'!$C17,'LCFS Table'!$A$2:$CT$356,29,) -> 0.16 | F17: =HLOOKUP('LCFS Categorized'!$C17,'LCFS Table'!$A$2:$CT$356,30,) -> 0.16 | G17: =HLOOKUP('LCFS Categorized'!$C17,'LCFS Table'!$A$2:$CT$356,31,) -> 0.16 | H17: =HLOOKUP('LCFS Categorized'!$C17,'LCFS Table'!$A$2:$CT$356,32,) -> 0.16 | I17: =HLOOKUP('LCFS Categorized'!$C17,'LCFS Table'!$A$2:$CT$356,33,) -> 0.16 | J17: =HLOOKUP('LCFS Categorized'!$C17,'LCFS Table'!$A$2:$CT$356,34,) -> 0.16 | K17: =HLOOKUP('LCFS Categorized'!$C17,'LCFS Table'!$A$2:$CT$356,35,) -> 0.16 | L17: =HLOOKUP('LCFS Categorized'!$C17,'LCFS Table'!$A$2:$CT$356,36,) -> 0.16 | M17: =HLOOKUP('LCFS Categorized'!$C17,'LCFS Table'!$A$2:$CT$356,37,) -> 0.16 | N17: =HLOOKUP('LCFS Categorized'!$C17,'LCFS Table'!$A$2:$CT$356,38,) -> 0.16 | O17: =HLOOKUP('LCFS Categorized'!$C17,'LCFS Table'!$A$2:$CT$356,39,) -> 0.16 | P17: =HLOOKUP('LCFS Categorized'!$C17,'LCFS Table'!$A$2:$CT$356,40,) -> 0.16 | Q17: =HLOOKUP('LCFS Categorized'!$C17,'LCFS Table'!$A$2:$CT$356,41,) -> 0.16 | R17: =HLOOKUP('LCFS Categorized'!$C17,'LCFS Table'!$A$2:$CT$356,42,) -> 0.16 | S17: =HLOOKUP('LCFS Categorized'!$C17,'LCFS Table'!$A$2:$CT$356,43,) -> 0.16 | T17: =HLOOKUP('LCFS Categorized'!$C17,'LCFS Table'!$A$2:$CT$356,44,) -> 0.16 | U17: =HLOOKUP('LCFS Categorized'!$C17,'LCFS Table'!$A$2:$CT$356,45,) -> 0.16 | V17: =HLOOKUP('LCFS Categorized'!$C17,'LCFS Table'!$A$2:$CT$356,46,) -> 0.16 | W17: =HLOOKUP('LCFS Categorized'!$C17,'LCFS Table'!$A$2:$CT$356,47,) -> 0.16 | X17: =HLOOKUP('LCFS Categorized'!$C17,'LCFS Table'!$A$2:$CT$356,48,) -> 0.16 | Y17: =HLOOKUP('LCFS Categorized'!$C17,'LCFS Table'!$A$2:$CT$356,49,) -> 0.16 | Z17: =HLOOKUP('LCFS Categorized'!$C17,'LCFS Table'!$A$2:$CT$356,50,) -> 0.16 | AA17: =HLOOKUP('LCFS Categorized'!$C17,'LCFS Table'!$A$2:$CT$356,51,) -> 0.16 | AB17: =HLOOKUP('LCFS Categorized'!$C17,'LCFS Table'!$A$2:$CT$356,52,) -> 0.16 | AC17: =HLOOKUP('LCFS Categorized'!$C17,'LCFS Table'!$A$2:$CT$356,53,) -> 0.16

Sheet LCFS Table
E1: Calcs | F1: Calcs | G1: Calcs | H1: Calcs | I1: Calcs | J1: Calcs | K1: Price Inputs | L1: Price Inputs | M1: Calcs | N1: Feedstock Inputs | O1: Feedstock Inputs | P1: Feedstock Inputs | Q1: Feedstock Inputs | R1: Feedstock Inputs | S1: Calcs | T1: Calcs | U1: Calcs | V1: Calcs | W1: Calcs | X1: Calcs | Y1: Calcs | Z1: Calcs | AA1: Static Control | AB1: Static Control | AC1: Static Control | AD1: Static Control | AE1: Static Control | AF1: Static Control | AG1: Static Control | AH1: Static Control | AI1: Static Control | AJ1: Static Control | AK1: Calcs | AL1: Calcs | AM1: Static Control | AN1: Static Control | AO1: Calcs | AP1: Calcs | AQ1: Input | AR1: Input | AS1: Calcs | AT1: Static Control | AU1: Static Control | AV1: Static Control | AW1: Static Control | AX1: Static Control | AY1: Static Control | AZ1: Static Control | BA1: Static Control | BB1: Static Control | BC1: Calcs | BD1: Calcs | BE1: Calcs | BF1: Calcs | BG1: Calcs | BH1: Calcs | BI1: Calcs | BJ1: Calcs | BK1: Calcs | BL1: Calcs | BM1: Calcs | BN1: Calcs | BO1: Calcs | BP1: Calcs | BQ1: Calcs | BR1: Calcs | BS1: Calcs | BT1: Calcs | BU1: Calcs | BV1: Calcs | BW1: Static Control | BX1: Static Control | BY1: Static Control | BZ1: Static Control | CA1: Static Control | CB1: Static Control | CC1: Static Control | CD1: Static Control | CE1: Static Control | CF1: Static Control | CG1: Static Control | CH1: Static Control | CI1: Static Control | CJ1: Static Control | CK1: Static Control | CL1: Static Control | CM1: Static Control | CN1: Static Control | CO1: Static Control | CP1: Static Control
A2: Week Start Date | B2: Week End Date | C2: Year | D2: WeekNumber | E2: RD Gross Margin | F2: BD Gross Margin | G2: RD Gross Margin w/Credits | H2: BD Gross Margins w/Credits & Glycerin Value | I2: RD Total Cost | J2: BD Total Cost | K2: RD Price (California LA Delivered $/gal) | L2: BD Price w/Credits (B100 West Cost Delivered Cents/gal) | M2: BD Price wo/Credits (B100 West Cost Delivered Cents/gal) | N2: Bleachable Fancy Tallow - Packer Chicago cents/lbs | O2: UCO SoCal cents/lbs | P2: DCO IL_WI cents/lbs | Q2: Soybean Oil (RBD) Central Illinois cents/lbs | R2: Yellow Grease Los Angeles cents/lbs | S2: Bleachable Fancy Tallow Delivered (Chicago to California) cents/lbs | T2: Soybean Oil Delivered (Central Illinois to California) cents/lbs | U2: DCO Delivered (Illinois to California) cents/lbs | V2: RD Bleachable Fancy Tallow Cost cents/gal | W2: RD UCO Cost cents/gal | X2: RD DCO Cost cents/gal | Y2: BD Soybean Oil Cost cents/gal | Z2: BD Yellow Grease Cost cents/gal | AA2: RD Yield | AB2: BD Yield | AC2: RD Bleachable Fancy Tallow % of Feedstock Mix | AD2: RD UCO % of Feedstock Mix | AE2: RD DCO % Feedstock Mix | AF2: BD Soybean Oil % of Feedstock Mix | AG2: BD Yellow Grease % of Feedstock Mix | AH2: Freight Cost (Illinois to California) cents/lbs | AI2: RD Fixed Cost $/MT | AJ2: RD Variable Cost $/MT | AK2: RD Fixed Cost cents/gal | AL2: RD Variable Costs cents/gal | AM2: BD Fixed Cost $/MT | AN2: BD Variable Cost $/MT | AO2: BD Fixed Cost cents/gal | AP2: BD Variable Cost cents/gal | AQ2: LCFS Weekly Average (Actual) | AR2: D4 RIN Weekly Average Actual | AS2: RD LCFS Credit Price | AT2: RD Cap N Trade Price | AU2: RD BTC Price | AV2: RD D4 RIN Price | AW2: RD Basis Price | AX2: BD LCFS Credit Price | AY2: BD Cap N Trade Price | AZ2: BD BTC Price | BA2: BD D4 RIN Price | BB2: BD Basis Price | BC2: RD Producer LCFS Credit Value | BD2: RD Producer Cap N Trade Value | BE2: RD Producer BTC Value | BF2: RD Producer D4 RIN Value | BG2: RD Producer Basis Value | BH2: BD Producer LCFS Credit Value | BI2: BD Producer Cap N Trade Value | BJ2: BD Producer BTC Value | BK2: BD Producer D4 RIN Value | BL2: BD Producer Basis Value | BM2: RD Blender LCFS Credit Value | BN2: RD Blender Cap N Trade Value | BO2: RD Blender BTC Value | BP2: RD Blender D4 RIN Value | BQ2: RD Blender Basis Value | BR2: BD Blender LCFS Credit Value | BS2: BD Blender Cap N Trade Value | BT2: BD Blender BTC Value | BU2: BD Blender D4 RIN Value | BV2: BD Blender Basis Value | BW2: RD Producer LCFS Credit Value % | BX2: RD Producer Cap N Trade % | BY2: RD Producer BTC % | BZ2: RD Producer D4 RIN % | CA2: RD Producer Basis % | CB2: BD Producer LCFS Credit Value % | CC2: BD Producer Cap N Trade % | CD2: BD Producer BTC % | CE2: BD Producer D4 RIN % | CF2: BD Producer Basis % | CG2: RD Blender LCFS Credit Value % | CH2: RD Blender Cap N Trade % | CI2: RD Blender BTC % | CJ2: RD Blender D4 RIN % | CK2: RD Blender Basis % | CL2: BD Blender LCFS Credit Value % | CM2: BD Blender Cap N Trade % | CN2: BD Blender BTC % | CO2: BD Blender D4 RIN % | CP2: BD Blender Basis % | CQ2: Glycerine Crude 80% (cents per pound) | CR2: Gylcerine Value in GM Calculation | CS2: Renewable LPG | CT2: Methanol | CW2: Renewable Diesel - Biodiesel Spread | CX2: Month | CY2: Year | DC2: 45Z Credit Estimate BFT | DD2: 45Z Credit Estimate DCO | DE2: 45Z Credit Estimated Revenue UCO | DF2: 45Z Credit Estimate YG | DG2: 45Z Credit Estimate SBO
A3: ='LCFS Table'!$B3-5 -> 43464 | B3: 43469 | C3: =YEAR(B3) -> 2019 | D3: W1 | F3: =('LCFS Table'!$M3)-'LCFS Table'!$J3 -> -2.887107 | H3: ='LCFS Table'!$F3+'LCFS Table'!$AX3+'LCFS Table'!$AY3+'LCFS Table'!$AZ3+'LCFS Table'!$BA3+('LCFS Table'!$CQ3*0.9/(0.8/0.99)/100)+(DG3*'LCFS Table'!$AF3)+(DF3*'LCFS Table'!$AG3) -> 0.13753867 | I3: =('LCFS Table'!$V3+'LCFS Table'!$W3+'LCFS Table'!$X3)/100+(('LCFS Table'!$AI3+'LCFS Table'!$AJ3)/340) -> 2.6963964 | J3: =(('LCFS Table'!$Y3+'LCFS Table'!$Z3)/100)+(('LCFS Table'!$AM3+'LCFS Table'!$AN3)/300) -> 3.1709926 | K3: #N/A | L3: 322.5 | M3: =('LCFS Table'!$L3/100)-'LCFS Table'!$AX3-'LCFS Table'!$AY3-'LCFS Table'!$AZ3-'LCFS Table'!$BA3 -> 0.28388559 | N3: 26 | O3: 24.3 | P3: 25.05 | Q3: 31.978 | R3: 22.65 | S3: ='LCFS Table'!$N3 + 'LCFS Table'!$AH3 -> 30.375 | T3: ='LCFS Table'!$Q3+'LCFS Table'!$AH3 -> 36.353 | U3: ='LCFS Table'!$P3+'LCFS Table'!$AH3 -> 29.425 | V3: =(('LCFS Table'!$S3/'LCFS Table'!$AA3)*'LCFS Table'!$AC3)*6.48 -> 104.69681 | W3: =(('LCFS Table'!$O3/'LCFS Table'!$AA3)*'LCFS Table'!$AD3)*6.48 -> 41.878723 | X3: =(('LCFS Table'!$U3/'LCFS Table'!$AA3)*'LCFS Table'!$AE3)*6.48 -> 50.71117 | Y3: =(('LCFS Table'!$T3/'LCFS Table'!$AB3)*'LCFS Table'!$AF3)*7.35 -> 208.74574 | Z3: =(('LCFS Table'!$R3/'LCFS Table'!$AB3)*'LCFS Table'!$AG3)*7.35 -> 43.353516 | AA3: 0.94 | AB3: 0.96 | AC3: 0.5 | AD3: 0.25 | AE3: 0.25 | AF3: 0.75 | AG3: 0.25 | AH3: 4.375 | AI3: 136 | AJ3: 110 | AK3: =('LCFS Table'!$AI3/340)*100 -> 40 | AL3: =('LCFS Table'!$AJ3/340)*100 -> 32.352941 | AM3: 105 | AN3: 90 | AO3: =('LCFS Table'!$AM3/300)*100 -> 35 | AP3: =('LCFS Table'!$AN3/300)*100 -> 30 | AQ3: 189.85 | AR3: 0.5275 | AS3: 1.6703042 | AT3: 0.16 | AU3: 1 | AV3: ='LCFS Table'!$AR3*1.7 -> 0.89675 | AW3: -2 | AX3: 1.1498644 | AY3: 0 | AZ3: 1 | BA3: ='LCFS Table'!$AR3*1.5 -> 0.79125 | BB3: -0.8 | BC3: ='LCFS Table'!$AS3*'LCFS Table'!$BW3 -> 1.6703042 | BD3: ='LCFS Table'!$AT3*'LCFS Table'!$BX3 -> 0 | BE3: ='LCFS Table'!$AU3*'LCFS Table'!$BY3 -> 1 | BF3: ='LCFS Table'!$AV3*'LCFS Table'!$BZ3 -> 0.89675 | BG3: ='LCFS Table'!$AW3*'LCFS Table'!$CA3 -> 2 | BH3: ='LCFS Table'!$AX3*'LCFS Table'!$CB3 -> 1.1498644 | BI3: ='LCFS Table'!$AY3*'LCFS Table'!$CC3 -> 0 | BJ3: ='LCFS Table'!$AZ3*'LCFS Table'!$CD3 -> 1 | BK3: ='LCFS Table'!$BA3*'LCFS Table'!$CE3 -> 0.79125 | BL3: ='LCFS Table'!$BB3*'LCFS Table'!$CF3 -> 0.8 | BM3: ='LCFS Table'!$AS3*'LCFS Table'!$CG3 -> 0 | BN3: ='LCFS Table'!$AT3*'LCFS Table'!$CH3 -> 0.16 | BO3: ='LCFS Table'!$AU3*'LCFS Table'!$CI3 -> 0 | BP3: ='LCFS Table'!$AV3*'LCFS Table'!$CJ3 -> 0 | BQ3: ='LCFS Table'!$AW3*'LCFS Table'!$CK3 -> -2 | BR3: ='LCFS Table'!$AX3*'LCFS Table'!$CL3 -> 0 | BS3: ='LCFS Table'!$AY3*'LCFS Table'!$CM3 -> 0 | BT3: ='LCFS Table'!$AZ3*'LCFS Table'!$CN3 -> 0 | BU3: ='LCFS Table'!$BA3*'LCFS Table'!$CO3 -> 0 | BV3: ='LCFS Table'!$BB3*'LCFS Table'!$CP3 -> -0.8 | BW3: 1 | BX3: 0 | BY3: 1 | BZ3: 1 | CA3: -1 | CB3: 1 | CC3: 0 | CD3: 1 | CE3: 1 | CF3: -1 | CG3: =1-'LCFS Table'!$BW3 -> 0 | CH3: =1-'LCFS Table'!$BX3 -> 1 | CI3: =1-'LCFS Table'!$BY3 -> 0 | CJ3: =1-'LCFS Table'!$BZ3 -> 0 | CK3: =-'LCFS Table'!$CA3 -> 1 | CL3: =1-'LCFS Table'!$CB3 -> 0 | CM3: =1-'LCFS Table'!$CC3 -> 1 | CN3: =1-'LCFS Table'!$CD3 -> 0 | CO3: =1-'LCFS Table'!$CE3 -> 0 | CP3: =-'LCFS Table'!$CF3 -> 1 | CQ3: 7.5 | CR3: =('LCFS Table'!$CQ3*0.9/(0.8/0.99)/100) -> 0.08353125 | CX3: =MONTH('LCFS Table'!$B3) -> 1 | CY3: =YEAR('LCFS Table'!$B3) -> 2019
A4: ='LCFS Table'!$B4-5 -> 43471 | B4: 43476 | C4: =YEAR(B4) -> 2019 | D4: W2 | F4: =('LCFS Table'!$M4)-'LCFS Table'!$J4 -> -2.8482971 | H4: ='LCFS Table'!$F4+'LCFS Table'!$AX4+'LCFS Table'!$AY4+'LCFS Table'!$AZ4+'LCFS Table'!$BA4+('LCFS Table'!$CQ4*0.9/(0.8/0.99)/100)+(DG4*'LCFS Table'!$AF4)+(DF4*'LCFS Table'!$AG4) -> 0.13512695 | I4: =('LCFS Table'!$V4+'LCFS Table'!$W4+'LCFS Table'!$X4)/100+(('LCFS Table'!$AI4+'LCFS Table'!$AJ4)/340) -> 2.6981198 | J4: =(('LCFS Table'!$Y4+'LCFS Table'!$Z4)/100)+(('LCFS Table'!$AM4+'LCFS Table'!$AN4)/300) -> 3.1734043 | K4: #N/A | L4: 322.5 | M4: =('LCFS Table'!$L4/100)-'LCFS Table'!$AX4-'LCFS Table'!$AY4-'LCFS Table'!$AZ4-'LCFS Table'!$BA4 -> 0.32510724 | N4: 26 | O4: 24.5 | P4: 24.95 | Q4: 31.82 | R4: 23.25 | S4: ='LCFS Table'!$N4 + 'LCFS Table'!$AH4 -> 30.375 | T4: ='LCFS Table'!$Q4+'LCFS Table'!$AH4 -> 36.195 | U4: ='LCFS Table'!$P4+'LCFS Table'!$AH4 -> 29.325 | V4: =(('LCFS Table'!$S4/'LCFS Table'!$AA4)*'LCFS Table'!$AC4)*6.48 -> 104.69681 | W4: =(('LCFS Table'!$O4/'LCFS Table'!$AA4)*'LCFS Table'!$AD4)*6.48 -> 42.223404 | X4: =(('LCFS Table'!$U4/'LCFS Table'!$AA4)*'LCFS Table'!$AE4)*6.48 -> 50.53883 | Y4: =(('LCFS Table'!$T4/'LCFS Table'!$AB4)*'LCFS Table'!$AF4)*7.35 -> 207.83848 | Z4: =(('LCFS Table'!$R4/'LCFS Table'!$AB4)*'LCFS Table'!$AG4)*7.35 -> 44.501953 | AA4: 0.94 | AB4: 0.96 | AC4: 0.5 | AD4: 0.25 | AE4: 0.25 | AF4: 0.75 | AG4: 0.25 | AH4: 4.375 | AI4: 136 | AJ4: 110 | AK4: =('LCFS Table'!$AI4/340)*100 -> 40 | AL4: =('LCFS Table'!$AJ4/340)*100 -> 32.352941 | AM4: 105 | AN4: 90 | AO4: =('LCFS Table'!$AM4/300)*100 -> 35 | AP4: =('LCFS Table'!$AN4/300)*100 -> 30 | AQ4: 190.35 | AR4: 0.498 | AS4: 1.6747032 | AT4: 0.16 | AU4: 1 | AV4: ='LCFS Table'!$AR4*1.7 -> 0.8466 | AW4: -1 | AX4: 1.1528928 | AY4: 0 | AZ4: 1 | BA4: ='LCFS Table'!$AR4*1.5 -> 0.747 | BB4: 0.2 | BC4: ='LCFS Table'!$AS4*'LCFS Table'!$BW4 -> 1.6747032 | BD4: ='LCFS Table'!$AT4*'LCFS Table'!$BX4 -> 0 | BE4: ='LCFS Table'!$AU4*'LCFS Table'!$BY4 -> 1 | BF4: ='LCFS Table'!$AV4*'LCFS Table'!$BZ4 -> 0.8466 | BG4: ='LCFS Table'!$AW4*'LCFS Table'!$CA4 -> 1 | BH4: ='LCFS Table'!$AX4*'LCFS Table'!$CB4 -> 1.1528928 | BI4: ='LCFS Table'!$AY4*'LCFS Table'!$CC4 -> 0 | BJ4: ='LCFS Table'!$AZ4*'LCFS Table'!$CD4 -> 1 | BK4: ='LCFS Table'!$BA4*'LCFS Table'!$CE4 -> 0.747 | BL4: ='LCFS Table'!$BB4*'LCFS Table'!$CF4 -> -0.2 | BM4: ='LCFS Table'!$AS4*'LCFS Table'!$CG4 -> 0 | BN4: ='LCFS Table'!$AT4*'LCFS Table'!$CH4 -> 0.16 | BO4: ='LCFS Table'!$AU4*'LCFS Table'!$CI4 -> 0 | BP4: ='LCFS Table'!$AV4*'LCFS Table'!$CJ4 -> 0 | BQ4: ='LCFS Table'!$AW4*'LCFS Table'!$CK4 -> -1 | BR4: ='LCFS Table'!$AX4*'LCFS Table'!$CL4 -> 0 | BS4: ='LCFS Table'!$AY4*'LCFS Table'!$CM4 -> 0 | BT4: ='LCFS Table'!$AZ4*'LCFS Table'!$CN4 -> 0 | BU4: ='LCFS Table'!$BA4*'LCFS Table'!$CO4 -> 0 | BV4: ='LCFS Table'!$BB4*'LCFS Table'!$CP4 -> 0.2 | BW4: 1 | BX4: 0 | BY4: 1 | BZ4: 1 | CA4: -1 | CB4: 1 | CC4: 0 | CD4: 1 | CE4: 1 | CF4: -1 | CG4: =1-'LCFS Table'!$BW4 -> 0 | CH4: =1-'LCFS Table'!$BX4 -> 1 | CI4: =1-'LCFS Table'!$BY4 -> 0 | CJ4: =1-'LCFS Table'!$BZ4 -> 0 | CK4: =-'LCFS Table'!$CA4 -> 1 | CL4: =1-'LCFS Table'!$CB4 -> 0 | CM4: =1-'LCFS Table'!$CC4 -> 1 | CN4: =1-'LCFS Table'!$CD4 -> 0 | CO4: =1-'LCFS Table'!$CE4 -> 0 | CP4: =-'LCFS Table'!$CF4 -> 1 | CQ4: 7.5 | CR4: =('LCFS Table'!$CQ4*0.9/(0.8/0.99)/100) -> 0.08353125 | CX4: =MONTH('LCFS Table'!$B4) -> 1 | CY4: =YEAR('LCFS Table'!$B4) -> 2019
A5: ='LCFS Table'!$B5-5 -> 43478 | B5: 43483 | C5: =YEAR(B5) -> 2019 | D5: W3 | F5: =('LCFS Table'!$M5)-'LCFS Table'!$J5 -> -2.9647864 | H5: ='LCFS Table'!$F5+'LCFS Table'!$AX5+'LCFS Table'!$AY5+'LCFS Table'!$AZ5+'LCFS Table'!$BA5+('LCFS Table'!$CQ5*0.9/(0.8/0.99)/100)+(DG5*'LCFS Table'!$AF5)+(DF5*'LCFS Table'!$AG5) -> 0.083447266 | I5: =('LCFS Table'!$V5+'LCFS Table'!$W5+'LCFS Table'!$X5)/100+(('LCFS Table'!$AI5+'LCFS Table'!$AJ5)/340) -> 2.7011358 | J5: =(('LCFS Table'!$Y5+'LCFS Table'!$Z5)/100)+(('LCFS Table'!$AM5+'LCFS Table'!$AN5)/300) -> 3.225084 | K5: #N/A | L5: 322.5 | M5: =('LCFS Table'!$L5/100)-'LCFS Table'!$AX5-'LCFS Table'!$AY5-'LCFS Table'!$AZ5-'LCFS Table'!$BA5 -> 0.26029754 | N5: 26 | O5: 24.875 | P5: 24.75 | Q5: 32.595 | R5: 23.625 | S5: ='LCFS Table'!$N5 + 'LCFS Table'!$AH5 -> 30.375 | T5: ='LCFS Table'!$Q5+'LCFS Table'!$AH5 -> 36.97 | U5: ='LCFS Table'!$P5+'LCFS Table'!$AH5 -> 29.125 | V5: =(('LCFS Table'!$S5/'LCFS Table'!$AA5)*'LCFS Table'!$AC5)*6.48 -> 104.69681 | W5: =(('LCFS Table'!$O5/'LCFS Table'!$AA5)*'LCFS Table'!$AD5)*6.48 -> 42.869681 | X5: =(('LCFS Table'!$U5/'LCFS Table'!$AA5)*'LCFS Table'!$AE5)*6.48 -> 50.194149 | Y5: =(('LCFS Table'!$T5/'LCFS Table'!$AB5)*'LCFS Table'!$AF5)*7.35 -> 212.28867 | Z5: =(('LCFS Table'!$R5/'LCFS Table'!$AB5)*'LCFS Table'!$AG5)*7.35 -> 45.219727 | AA5: 0.94 | AB5: 0.96 | AC5: 0.5 | AD5: 0.25 | AE5: 0.25 | AF5: 0.75 | AG5: 0.25 | AH5: 4.375 | AI5: 136 | AJ5: 110 | AK5: =('LCFS Table'!$AI5/340)*100 -> 40 | AL5: =('LCFS Table'!$AJ5/340)*100 -> 32.352941 | AM5: 105 | AN5: 90 | AO5: =('LCFS Table'!$AM5/300)*100 -> 35 | AP5: =('LCFS Table'!$AN5/300)*100 -> 30 | AQ5: 191.5 | AR5: 0.536563 | AS5: 1.6848209 | AT5: 0.16 | AU5: 1 | AV5: ='LCFS Table'!$AR5*1.7 -> 0.9121571 | AW5: 0 | AX5: 1.159858 | AY5: 0 | AZ5: 1 | BA5: ='LCFS Table'!$AR5*1.5 -> 0.8048445 | BB5: 1.2 | BC5: ='LCFS Table'!$AS5*'LCFS Table'!$BW5 -> 1.6848209 | BD5: ='LCFS Table'!$AT5*'LCFS Table'!$BX5 -> 0 | BE5: ='LCFS Table'!$AU5*'LCFS Table'!$BY5 -> 1 | BF5: ='LCFS Table'!$AV5*'LCFS Table'!$BZ5 -> 0.9121571 | BG5: ='LCFS Table'!$AW5*'LCFS Table'!$CA5 -> 0 | BH5: ='LCFS Table'!$AX5*'LCFS Table'!$CB5 -> 1.159858 | BI5: ='LCFS Table'!$AY5*'LCFS Table'!$CC5 -> 0 | BJ5: ='LCFS Table'!$AZ5*'LCFS Table'!$CD5 -> 1 | BK5: ='LCFS Table'!$BA5*'LCFS Table'!$CE5 -> 0.8048445 | BL5: ='LCFS Table'!$BB5*'LCFS Table'!$CF5 -> -1.2 | BM5: ='LCFS Table'!$AS5*'LCFS Table'!$CG5 -> 0 | BN5: ='LCFS Table'!$AT5*'LCFS Table'!$CH5 -> 0.16 | BO5: ='LCFS Table'!$AU5*'LCFS Table'!$CI5 -> 0 | BP5: ='LCFS Table'!$AV5*'LCFS Table'!$CJ5 -> 0 | BQ5: ='LCFS Table'!$AW5*'LCFS Table'!$CK5 -> 0 | BR5: ='LCFS Table'!$AX5*'LCFS Table'!$CL5 -> 0 | BS5: ='LCFS Table'!$AY5*'LCFS Table'!$CM5 -> 0 | BT5: ='LCFS Table'!$AZ5*'LCFS Table'!$CN5 -> 0 | BU5: ='LCFS Table'!$BA5*'LCFS Table'!$CO5 -> 0 | BV5: ='LCFS Table'!$BB5*'LCFS Table'!$CP5 -> 1.2 | BW5: 1 | BX5: 0 | BY5: 1 | BZ5: 1 | CA5: -1 | CB5: 1 | CC5: 0 | CD5: 1 | CE5: 1 | CF5: -1 | CG5: =1-'LCFS Table'!$BW5 -> 0 | CH5: =1-'LCFS Table'!$BX5 -> 1 | CI5: =1-'LCFS Table'!$BY5 -> 0 | CJ5: =1-'LCFS Table'!$BZ5 -> 0 | CK5: =-'LCFS Table'!$CA5 -> 1 | CL5: =1-'LCFS Table'!$CB5 -> 0 | CM5: =1-'LCFS Table'!$CC5 -> 1 | CN5: =1-'LCFS Table'!$CD5 -> 0 | CO5: =1-'LCFS Table'!$CE5 -> 0 | CP5: =-'LCFS Table'!$CF5 -> 1 | CQ5: 7.5 | CR5: =('LCFS Table'!$CQ5*0.9/(0.8/0.99)/100) -> 0.08353125 | CX5: =MONTH('LCFS Table'!$B5) -> 1 | CY5: =YEAR('LCFS Table'!$B5) -> 2019
A6: ='LCFS Table'!$B6-5 -> 43485 | B6: 43490 | C6: =YEAR(B6) -> 2019 | D6: W4 | F6: =('LCFS Table'!$M6)-'LCFS Table'!$J6 -> -3.047776 | H6: ='LCFS Table'!$F6+'LCFS Table'!$AX6+'LCFS Table'!$AY6+'LCFS Table'!$AZ6+'LCFS Table'!$BA6+('LCFS Table'!$CQ6*0.9/(0.8/0.99)/100)+(DG6*'LCFS Table'!$AF6)+(DF6*'LCFS Table'!$AG6) -> 0.041835547 | I6: =('LCFS Table'!$V6+'LCFS Table'!$W6+'LCFS Table'!$X6)/100+(('LCFS Table'!$AI6+'LCFS Table'!$AJ6)/340) -> 2.7101837 | J6: =(('LCFS Table'!$Y6+'LCFS Table'!$Z6)/100)+(('LCFS Table'!$AM6+'LCFS Table'!$AN6)/300) -> 3.2666957 | K6: #N/A | L6: 322.5 | M6: =('LCFS Table'!$L6/100)-'LCFS Table'!$AX6-'LCFS Table'!$AY6-'LCFS Table'!$AZ6-'LCFS Table'!$BA6 -> 0.21891975 | N6: 26 | O6: 25.3 | P6: 24.85 | Q6: 33.278 | R6: 23.75 | S6: ='LCFS Table'!$N6 + 'LCFS Table'!$AH6 -> 30.375 | T6: ='LCFS Table'!$Q6+'LCFS Table'!$AH6 -> 37.653 | U6: ='LCFS Table'!$P6+'LCFS Table'!$AH6 -> 29.225 | V6: =(('LCFS Table'!$S6/'LCFS Table'!$AA6)*'LCFS Table'!$AC6)*6.48 -> 104.69681 | W6: =(('LCFS Table'!$O6/'LCFS Table'!$AA6)*'LCFS Table'!$AD6)*6.48 -> 43.602128 | X6: =(('LCFS Table'!$U6/'LCFS Table'!$AA6)*'LCFS Table'!$AE6)*6.48 -> 50.366489 | Y6: =(('LCFS Table'!$T6/'LCFS Table'!$AB6)*'LCFS Table'!$AF6)*7.35 -> 216.21059 | Z6: =(('LCFS Table'!$R6/'LCFS Table'!$AB6)*'LCFS Table'!$AG6)*7.35 -> 45.458984 | AA6: 0.94 | AB6: 0.96 | AC6: 0.5 | AD6: 0.25 | AE6: 0.25 | AF6: 0.75 | AG6: 0.25 | AH6: 4.375 | AI6: 136 | AJ6: 110 | AK6: =('LCFS Table'!$AI6/340)*100 -> 40 | AL6: =('LCFS Table'!$AJ6/340)*100 -> 32.352941 | AM6: 105 | AN6: 90 | AO6: =('LCFS Table'!$AM6/300)*100 -> 35 | AP6: =('LCFS Table'!$AN6/300)*100 -> 30 | AQ6: 192.775 | AR6: 0.559 | AS6: 1.6960384 | AT6: 0.16 | AU6: 1 | AV6: ='LCFS Table'!$AR6*1.7 -> 0.9503 | AW6: 0 | AX6: 1.1675803 | AY6: 0 | AZ6: 1 | BA6: ='LCFS Table'!$AR6*1.5 -> 0.8385 | BB6: 1.2 | BC6: ='LCFS Table'!$AS6*'LCFS Table'!$BW6 -> 1.6960384 | BD6: ='LCFS Table'!$AT6*'LCFS Table'!$BX6 -> 0 | BE6: ='LCFS Table'!$AU6*'LCFS Table'!$BY6 -> 1 | BF6: ='LCFS Table'!$AV6*'LCFS Table'!$BZ6 -> 0.9503 | BG6: ='LCFS Table'!$AW6*'LCFS Table'!$CA6 -> 0 | BH6: ='LCFS Table'!$AX6*'LCFS Table'!$CB6 -> 1.1675803 | BI6: ='LCFS Table'!$AY6*'LCFS Table'!$CC6 -> 0 | BJ6: ='LCFS Table'!$AZ6*'LCFS Table'!$CD6 -> 1 | BK6: ='LCFS Table'!$BA6*'LCFS Table'!$CE6 -> 0.8385 | BL6: ='LCFS Table'!$BB6*'LCFS Table'!$CF6 -> -1.2 | BM6: ='LCFS Table'!$AS6*'LCFS Table'!$CG6 -> 0 | BN6: ='LCFS Table'!$AT6*'LCFS Table'!$CH6 -> 0.16 | BO6: ='LCFS Table'!$AU6*'LCFS Table'!$CI6 -> 0 | BP6: ='LCFS Table'!$AV6*'LCFS Table'!$CJ6 -> 0 | BQ6: ='LCFS Table'!$AW6*'LCFS Table'!$CK6 -> 0 | BR6: ='LCFS Table'!$AX6*'LCFS Table'!$CL6 -> 0 | BS6: ='LCFS Table'!$AY6*'LCFS Table'!$CM6 -> 0 | BT6: ='LCFS Table'!$AZ6*'LCFS Table'!$CN6 -> 0 | BU6: ='LCFS Table'!$BA6*'LCFS Table'!$CO6 -> 0 | BV6: ='LCFS Table'!$BB6*'LCFS Table'!$CP6 -> 1.2 | BW6: 1 | BX6: 0 | BY6: 1 | BZ6: 1 | CA6: -1 | CB6: 1 | CC6: 0 | CD6: 1 | CE6: 1 | CF6: -1 | CG6: =1-'LCFS Table'!$BW6 -> 0 | CH6: =1-'LCFS Table'!$BX6 -> 1 | CI6: =1-'LCFS Table'!$BY6 -> 0 | CJ6: =1-'LCFS Table'!$BZ6 -> 0 | CK6: =-'LCFS Table'!$CA6 -> 1 | CL6: =1-'LCFS Table'!$CB6 -> 0 | CM6: =1-'LCFS Table'!$CC6 -> 1 | CN6: =1-'LCFS Table'!$CD6 -> 0 | CO6: =1-'LCFS Table'!$CE6 -> 0 | CP6: =-'LCFS Table'!$CF6 -> 1 | CQ6: 7.5 | CR6: =('LCFS Table'!$CQ6*0.9/(0.8/0.99)/100) -> 0.08353125 | CX6: =MONTH('LCFS Table'!$B6) -> 1 | CY6: =YEAR('LCFS Table'!$B6) -> 2019
A7: ='LCFS Table'!$B7-5 -> 43492 | B7: 43497 | C7: =YEAR(B7) -> 2019 | D7: W5 | F7: =('LCFS Table'!$M7)-'LCFS Table'!$J7 -> -3.0741025 | H7: ='LCFS Table'!$F7+'LCFS Table'!$AX7+'LCFS Table'!$AY7+'LCFS Table'!$AZ7+'LCFS Table'!$BA7+('LCFS Table'!$CQ7*0.9/(0.8/0.99)/100)+(DG7*'LCFS Table'!$AF7)+(DF7*'LCFS Table'!$AG7) -> 0.037351172 | I7: =('LCFS Table'!$V7+'LCFS Table'!$W7+'LCFS Table'!$X7)/100+(('LCFS Table'!$AI7+'LCFS Table'!$AJ7)/340) -> 2.7162156 | J7: =(('LCFS Table'!$Y7+'LCFS Table'!$Z7)/100)+(('LCFS Table'!$AM7+'LCFS Table'!$AN7)/300) -> 3.2781801 | K7: #N/A | L7: 323.2 | M7: =('LCFS Table'!$L7/100)-'LCFS Table'!$AX7-'LCFS Table'!$AY7-'LCFS Table'!$AZ7-'LCFS Table'!$BA7 -> 0.20407761 | N7: 26 | O7: 25.5 | P7: 25 | Q7: 33.478 | R7: 23.75 | S7: ='LCFS Table'!$N7 + 'LCFS Table'!$AH7 -> 30.375 | T7: ='LCFS Table'!$Q7+'LCFS Table'!$AH7 -> 37.853 | U7: ='LCFS Table'!$P7+'LCFS Table'!$AH7 -> 29.375 | V7: =(('LCFS Table'!$S7/'LCFS Table'!$AA7)*'LCFS Table'!$AC7)*6.48 -> 104.69681 | W7: =(('LCFS Table'!$O7/'LCFS Table'!$AA7)*'LCFS Table'!$AD7)*6.48 -> 43.946809 | X7: =(('LCFS Table'!$U7/'LCFS Table'!$AA7)*'LCFS Table'!$AE7)*6.48 -> 50.625 | Y7: =(('LCFS Table'!$T7/'LCFS Table'!$AB7)*'LCFS Table'!$AF7)*7.35 -> 217.35902 | Z7: =(('LCFS Table'!$R7/'LCFS Table'!$AB7)*'LCFS Table'!$AG7)*7.35 -> 45.458984 | AA7: 0.94 | AB7: 0.96 | AC7: 0.5 | AD7: 0.25 | AE7: 0.25 | AF7: 0.75 | AG7: 0.25 | AH7: 4.375 | AI7: 136 | AJ7: 110 | AK7: =('LCFS Table'!$AI7/340)*100 -> 40 | AL7: =('LCFS Table'!$AJ7/340)*100 -> 32.352941 | AM7: 105 | AN7: 90 | AO7: =('LCFS Table'!$AM7/300)*100 -> 35 | AP7: =('LCFS Table'!$AN7/300)*100 -> 30 | AQ7: 194.4 | AR7: 0.567 | AS7: 1.7103352 | AT7: 0.16 | AU7: 1 | AV7: ='LCFS Table'!$AR7*1.7 -> 0.9639 | AW7: 0 | AX7: 1.1774224 | AY7: 0 | AZ7: 1 | BA7: ='LCFS Table'!$AR7*1.5 -> 0.8505 | BB7: 1.2 | BC7: ='LCFS Table'!$AS7*'LCFS Table'!$BW7 -> 1.7103352 | BD7: ='LCFS Table'!$AT7*'LCFS Table'!$BX7 -> 0 | BE7: ='LCFS Table'!$AU7*'LCFS Table'!$BY7 -> 1 | BF7: ='LCFS Table'!$AV7*'LCFS Table'!$BZ7 -> 0.9639 | BG7: ='LCFS Table'!$AW7*'LCFS Table'!$CA7 -> 0 | BH7: ='LCFS Table'!$AX7*'LCFS Table'!$CB7 -> 1.1774224 | BI7: ='LCFS Table'!$AY7*'LCFS Table'!$CC7 -> 0 | BJ7: ='LCFS Table'!$AZ7*'LCFS Table'!$CD7 -> 1 | BK7: ='LCFS Table'!$BA7*'LCFS Table'!$CE7 -> 0.8505 | BL7: ='LCFS Table'!$BB7*'LCFS Table'!$CF7 -> -1.2 | BM7: ='LCFS Table'!$AS7*'LCFS Table'!$CG7 -> 0 | BN7: ='LCFS Table'!$AT7*'LCFS Table'!$CH7 -> 0.16 | BO7: ='LCFS Table'!$AU7*'LCFS Table'!$CI7 -> 0 | BP7: ='LCFS Table'!$AV7*'LCFS Table'!$CJ7 -> 0 | BQ7: ='LCFS Table'!$AW7*'LCFS Table'!$CK7 -> 0 | BR7: ='LCFS Table'!$AX7*'LCFS Table'!$CL7 -> 0 | BS7: ='LCFS Table'!$AY7*'LCFS Table'!$CM7 -> 0 | BT7: ='LCFS Table'!$AZ7*'LCFS Table'!$CN7 -> 0 | BU7: ='LCFS Table'!$BA7*'LCFS Table'!$CO7 -> 0 | BV7: ='LCFS Table'!$BB7*'LCFS Table'!$CP7 -> 1.2 | BW7: 1 | BX7: 0 | BY7: 1 | BZ7: 1 | CA7: -1 | CB7: 1 | CC7: 0 | CD7: 1 | CE7: 1 | CF7: -1 | CG7: =1-'LCFS Table'!$BW7 -> 0 | CH7: =1-'LCFS Table'!$BX7 -> 1 | CI7: =1-'LCFS Table'!$BY7 -> 0 | CJ7: =1-'LCFS Table'!$BZ7 -> 0 | CK7: =-'LCFS Table'!$CA7 -> 1 | CL7: =1-'LCFS Table'!$CB7 -> 0 | CM7: =1-'LCFS Table'!$CC7 -> 1 | CN7: =1-'LCFS Table'!$CD7 -> 0 | CO7: =1-'LCFS Table'!$CE7 -> 0 | CP7: =-'LCFS Table'!$CF7 -> 1 | CQ7: 7.5 | CR7: =('LCFS Table'!$CQ7*0.9/(0.8/0.99)/100) -> 0.08353125 | CX7: =MONTH('LCFS Table'!$B7) -> 2 | CY7: =YEAR('LCFS Table'!$B7) -> 2019
A8: ='LCFS Table'!$B8-5 -> 43499 | B8: 43504 | C8: =YEAR(B8) -> 2019 | D8: W6 | F8: =('LCFS Table'!$M8)-'LCFS Table'!$J8 -> -2.9830297 | H8: ='LCFS Table'!$F8+'LCFS Table'!$AX8+'LCFS Table'!$AY8+'LCFS Table'!$AZ8+'LCFS Table'!$BA8+('LCFS Table'!$CQ8*0.9/(0.8/0.99)/100)+(DG8*'LCFS Table'!$AF8)+(DF8*'LCFS Table'!$AG8) -> 0.11743164 | I8: =('LCFS Table'!$V8+'LCFS Table'!$W8+'LCFS Table'!$X8)/100+(('LCFS Table'!$AI8+'LCFS Table'!$AJ8)/340) -> 2.709322 | J8: =(('LCFS Table'!$Y8+'LCFS Table'!$Z8)/100)+(('LCFS Table'!$AM8+'LCFS Table'!$AN8)/300) -> 3.2380996 | K8: #N/A | L8: 327.2 | M8: =('LCFS Table'!$L8/100)-'LCFS Table'!$AX8-'LCFS Table'!$AY8-'LCFS Table'!$AZ8-'LCFS Table'!$BA8 -> 0.25506988 | N8: 26 | O8: 25.5 | P8: 24.6 | Q8: 32.78 | R8: 23.75 | S8: ='LCFS Table'!$N8 + 'LCFS Table'!$AH8 -> 30.375 | T8: ='LCFS Table'!$Q8+'LCFS Table'!$AH8 -> 37.155 | U8: ='LCFS Table'!$P8+'LCFS Table'!$AH8 -> 28.975 | V8: =(('LCFS Table'!$S8/'LCFS Table'!$AA8)*'LCFS Table'!$AC8)*6.48 -> 104.69681 | W8: =(('LCFS Table'!$O8/'LCFS Table'!$AA8)*'LCFS Table'!$AD8)*6.48 -> 43.946809 | X8: =(('LCFS Table'!$U8/'LCFS Table'!$AA8)*'LCFS Table'!$AE8)*6.48 -> 49.935638 | Y8: =(('LCFS Table'!$T8/'LCFS Table'!$AB8)*'LCFS Table'!$AF8)*7.35 -> 213.35098 | Z8: =(('LCFS Table'!$R8/'LCFS Table'!$AB8)*'LCFS Table'!$AG8)*7.35 -> 45.458984 | AA8: 0.94 | AB8: 0.96 | AC8: 0.5 | AD8: 0.25 | AE8: 0.25 | AF8: 0.75 | AG8: 0.25 | AH8: 4.375 | AI8: 136 | AJ8: 110 | AK8: =('LCFS Table'!$AI8/340)*100 -> 40 | AL8: =('LCFS Table'!$AJ8/340)*100 -> 32.352941 | AM8: 105 | AN8: 90 | AO8: =('LCFS Table'!$AM8/300)*100 -> 35 | AP8: =('LCFS Table'!$AN8/300)*100 -> 30 | AQ8: 196.3 | AR8: 0.552 | AS8: 1.7270514 | AT8: 0.16 | AU8: 1 | AV8: ='LCFS Table'!$AR8*1.7 -> 0.9384 | AW8: 0 | AX8: 1.1889301 | AY8: 0 | AZ8: 1 | BA8: ='LCFS Table'!$AR8*1.5 -> 0.828 | BB8: 1.2 | BC8: ='LCFS Table'!$AS8*'LCFS Table'!$BW8 -> 1.7270514 | BD8: ='LCFS Table'!$AT8*'LCFS Table'!$BX8 -> 0 | BE8: ='LCFS Table'!$AU8*'LCFS Table'!$BY8 -> 1 | BF8: ='LCFS Table'!$AV8*'LCFS Table'!$BZ8 -> 0.9384 | BG8: ='LCFS Table'!$AW8*'LCFS Table'!$CA8 -> 0 | BH8: ='LCFS Table'!$AX8*'LCFS Table'!$CB8 -> 1.1889301 | BI8: ='LCFS Table'!$AY8*'LCFS Table'!$CC8 -> 0 | BJ8: ='LCFS Table'!$AZ8*'LCFS Table'!$CD8 -> 1 | BK8: ='LCFS Table'!$BA8*'LCFS Table'!$CE8 -> 0.828 | BL8: ='LCFS Table'!$BB8*'LCFS Table'!$CF8 -> -1.2 | BM8: ='LCFS Table'!$AS8*'LCFS Table'!$CG8 -> 0 | BN8: ='LCFS Table'!$AT8*'LCFS Table'!$CH8 -> 0.16 | BO8: ='LCFS Table'!$AU8*'LCFS Table'!$CI8 -> 0 | BP8: ='LCFS Table'!$AV8*'LCFS Table'!$CJ8 -> 0 | BQ8: ='LCFS Table'!$AW8*'LCFS Table'!$CK8 -> 0 | BR8: ='LCFS Table'!$AX8*'LCFS Table'!$CL8 -> 0 | BS8: ='LCFS Table'!$AY8*'LCFS Table'!$CM8 -> 0 | BT8: ='LCFS Table'!$AZ8*'LCFS Table'!$CN8 -> 0 | BU8: ='LCFS Table'!$BA8*'LCFS Table'!$CO8 -> 0 | BV8: ='LCFS Table'!$BB8*'LCFS Table'!$CP8 -> 1.2 | BW8: 1 | BX8: 0 | BY8: 1 | BZ8: 1 | CA8: -1 | CB8: 1 | CC8: 0 | CD8: 1 | CE8: 1 | CF8: -1 | CG8: =1-'LCFS Table'!$BW8 -> 0 | CH8: =1-'LCFS Table'!$BX8 -> 1 | CI8: =1-'LCFS Table'!$BY8 -> 0 | CJ8: =1-'LCFS Table'!$BZ8 -> 0 | CK8: =-'LCFS Table'!$CA8 -> 1 | CL8: =1-'LCFS Table'!$CB8 -> 0 | CM8: =1-'LCFS Table'!$CC8 -> 1 | CN8: =1-'LCFS Table'!$CD8 -> 0 | CO8: =1-'LCFS Table'!$CE8 -> 0 | CP8: =-'LCFS Table'!$CF8 -> 1 | CQ8: 7.5 | CR8: =('LCFS Table'!$CQ8*0.9/(0.8/0.99)/100) -> 0.08353125 | CX8: =MONTH('LCFS Table'!$B8) -> 2 | CY8: =YEAR('LCFS Table'!$B8) -> 2019
A9: ='LCFS Table'!$B9-5 -> 43506 | B9: 43511 | C9: =YEAR(B9) -> 2019 | D9: W7 | F9: =('LCFS Table'!$M9)-'LCFS Table'!$J9 -> -2.9668887 | H9: ='LCFS Table'!$F9+'LCFS Table'!$AX9+'LCFS Table'!$AY9+'LCFS Table'!$AZ9+'LCFS Table'!$BA9+('LCFS Table'!$CQ9*0.9/(0.8/0.99)/100)+(DG9*'LCFS Table'!$AF9)+(DF9*'LCFS Table'!$AG9) -> 0.13146094 | I9: =('LCFS Table'!$V9+'LCFS Table'!$W9+'LCFS Table'!$X9)/100+(('LCFS Table'!$AI9+'LCFS Table'!$AJ9)/340) -> 2.6989815 | J9: =(('LCFS Table'!$Y9+'LCFS Table'!$Z9)/100)+(('LCFS Table'!$AM9+'LCFS Table'!$AN9)/300) -> 3.2320703 | K9: #N/A | L9: 328 | M9: =('LCFS Table'!$L9/100)-'LCFS Table'!$AX9-'LCFS Table'!$AY9-'LCFS Table'!$AZ9-'LCFS Table'!$BA9 -> 0.26518157 | N9: 26 | O9: 25.5 | P9: 24 | Q9: 32.675 | R9: 23.75 | S9: ='LCFS Table'!$N9 + 'LCFS Table'!$AH9 -> 30.375 | T9: ='LCFS Table'!$Q9+'LCFS Table'!$AH9 -> 37.05 | U9: ='LCFS Table'!$P9+'LCFS Table'!$AH9 -> 28.375 | V9: =(('LCFS Table'!$S9/'LCFS Table'!$AA9)*'LCFS Table'!$AC9)*6.48 -> 104.69681 | W9: =(('LCFS Table'!$O9/'LCFS Table'!$AA9)*'LCFS Table'!$AD9)*6.48 -> 43.946809 | X9: =(('LCFS Table'!$U9/'LCFS Table'!$AA9)*'LCFS Table'!$AE9)*6.48 -> 48.901596 | Y9: =(('LCFS Table'!$T9/'LCFS Table'!$AB9)*'LCFS Table'!$AF9)*7.35 -> 212.74805 | Z9: =(('LCFS Table'!$R9/'LCFS Table'!$AB9)*'LCFS Table'!$AG9)*7.35 -> 45.458984 | AA9: 0.94 | AB9: 0.96 | AC9: 0.5 | AD9: 0.25 | AE9: 0.25 | AF9: 0.75 | AG9: 0.25 | AH9: 4.375 | AI9: 136 | AJ9: 110 | AK9: =('LCFS Table'!$AI9/340)*100 -> 40 | AL9: =('LCFS Table'!$AJ9/340)*100 -> 32.352941 | AM9: 105 | AN9: 90 | AO9: =('LCFS Table'!$AM9/300)*100 -> 35 | AP9: =('LCFS Table'!$AN9/300)*100 -> 30 | AQ9: 195.75 | AR9: 0.552813 | AS9: 1.7222125 | AT9: 0.16 | AU9: 1 | AV9: ='LCFS Table'!$AR9*1.7 -> 0.9397821 | AW9: 0 | AX9: 1.1855989 | AY9: 0 | AZ9: 1 | BA9: ='LCFS Table'!$AR9*1.5 -> 0.8292195 | BB9: 1.2 | BC9: ='LCFS Table'!$AS9*'LCFS Table'!$BW9 -> 1.7222125 | BD9: ='LCFS Table'!$AT9*'LCFS Table'!$BX9 -> 0 | BE9: ='LCFS Table'!$AU9*'LCFS Table'!$BY9 -> 1 | BF9: ='LCFS Table'!$AV9*'LCFS Table'!$BZ9 -> 0.9397821 | BG9: ='LCFS Table'!$AW9*'LCFS Table'!$CA9 -> 0 | BH9: ='LCFS Table'!$AX9*'LCFS Table'!$CB9 -> 1.1855989 | BI9: ='LCFS Table'!$AY9*'LCFS Table'!$CC9 -> 0 | BJ9: ='LCFS Table'!$AZ9*'LCFS Table'!$CD9 -> 1 | BK9: ='LCFS Table'!$BA9*'LCFS Table'!$CE9 -> 0.8292195 | BL9: ='LCFS Table'!$BB9*'LCFS Table'!$CF9 -> -1.2 | BM9: ='LCFS Table'!$AS9*'LCFS Table'!$CG9 -> 0 | BN9: ='LCFS Table'!$AT9*'LCFS Table'!$CH9 -> 0.16 | BO9: ='LCFS Table'!$AU9*'LCFS Table'!$CI9 -> 0 | BP9: ='LCFS Table'!$AV9*'LCFS Table'!$CJ9 -> 0 | BQ9: ='LCFS Table'!$AW9*'LCFS Table'!$CK9 -> 0 | BR9: ='LCFS Table'!$AX9*'LCFS Table'!$CL9 -> 0 | BS9: ='LCFS Table'!$AY9*'LCFS Table'!$CM9 -> 0 | BT9: ='LCFS Table'!$AZ9*'LCFS Table'!$CN9 -> 0 | BU9: ='LCFS Table'!$BA9*'LCFS Table'!$CO9 -> 0 | BV9: ='LCFS Table'!$BB9*'LCFS Table'!$CP9 -> 1.2 | BW9: 1 | BX9: 0 | BY9: 1 | BZ9: 1 | CA9: -1 | CB9: 1 | CC9: 0 | CD9: 1 | CE9: 1 | CF9: -1 | CG9: =1-'LCFS Table'!$BW9 -> 0 | CH9: =1-'LCFS Table'!$BX9 -> 1 | CI9: =1-'LCFS Table'!$BY9 -> 0 | CJ9: =1-'LCFS Table'!$BZ9 -> 0 | CK9: =-'LCFS Table'!$CA9 -> 1 | CL9: =1-'LCFS Table'!$CB9 -> 0 | CM9: =1-'LCFS Table'!$CC9 -> 1 | CN9: =1-'LCFS Table'!$CD9 -> 0 | CO9: =1-'LCFS Table'!$CE9 -> 0 | CP9: =-'LCFS Table'!$CF9 -> 1 | CQ9: 7.5 | CR9: =('LCFS Table'!$CQ9*0.9/(0.8/0.99)/100) -> 0.08353125 | CX9: =MONTH('LCFS Table'!$B9) -> 2 | CY9: =YEAR('LCFS Table'!$B9) -> 2019
A10: ='LCFS Table'!$B10-5 -> 43513 | B10: 43518 | C10: =YEAR(B10) -> 2019 | D10: W8 | F10: =('LCFS Table'!$M10)-'LCFS Table'!$J10 -> -2.9444553 | H10: ='LCFS Table'!$F10+'LCFS Table'!$AX10+'LCFS Table'!$AY10+'LCFS Table'!$AZ10+'LCFS Table'!$BA10+('LCFS Table'!$CQ10*0.9/(0.8/0.99)/100)+(DG10*'LCFS Table'!$AF10)+(DF10*'LCFS Table'!$AG10) -> 0.12390039 | I10: =('LCFS Table'!$V10+'LCFS Table'!$W10+'LCFS Table'!$X10)/100+(('LCFS Table'!$AI10+'LCFS Table'!$AJ10)/340) -> 2.6968273 | J10: =(('LCFS Table'!$Y10+'LCFS Table'!$Z10)/100)+(('LCFS Table'!$AM10+'LCFS Table'!$AN10)/300) -> 3.2396309 | K10: #N/A | L10: 328 | M10: =('LCFS Table'!$L10/100)-'LCFS Table'!$AX10-'LCFS Table'!$AY10-'LCFS Table'!$AZ10-'LCFS Table'!$BA10 -> 0.29517555 | N10: 26 | O10: 25.5 | P10: 23.875 | Q10: 32.59 | R10: 24.4 | S10: ='LCFS Table'!$N10 + 'LCFS Table'!$AH10 -> 30.375 | T10: ='LCFS Table'!$Q10+'LCFS Table'!$AH10 -> 36.965 | U10: ='LCFS Table'!$P10+'LCFS Table'!$AH10 -> 28.25 | V10: =(('LCFS Table'!$S10/'LCFS Table'!$AA10)*'LCFS Table'!$AC10)*6.48 -> 104.69681 | W10: =(('LCFS Table'!$O10/'LCFS Table'!$AA10)*'LCFS Table'!$AD10)*6.48 -> 43.946809 | X10: =(('LCFS Table'!$U10/'LCFS Table'!$AA10)*'LCFS Table'!$AE10)*6.48 -> 48.68617 | Y10: =(('LCFS Table'!$T10/'LCFS Table'!$AB10)*'LCFS Table'!$AF10)*7.35 -> 212.25996 | Z10: =(('LCFS Table'!$R10/'LCFS Table'!$AB10)*'LCFS Table'!$AG10)*7.35 -> 46.703125 | AA10: 0.94 | AB10: 0.96 | AC10: 0.5 | AD10: 0.25 | AE10: 0.25 | AF10: 0.75 | AG10: 0.25 | AH10: 4.375 | AI10: 136 | AJ10: 110 | AK10: =('LCFS Table'!$AI10/340)*100 -> 40 | AL10: =('LCFS Table'!$AJ10/340)*100 -> 32.352941 | AM10: 105 | AN10: 90 | AO10: =('LCFS Table'!$AM10/300)*100 -> 35 | AP10: =('LCFS Table'!$AN10/300)*100 -> 30 | AQ10: 196.2 | AR10: 0.531 | AS10: 1.7261716 | AT10: 0.16 | AU10: 1 | AV10: ='LCFS Table'!$AR10*1.7 -> 0.9027 | AW10: 0 | AX10: 1.1883244 | AY10: 0 | AZ10: 1 | BA10: ='LCFS Table'!$AR10*1.5 -> 0.7965 | BB10: 1.2 | BC10: ='LCFS Table'!$AS10*'LCFS Table'!$BW10 -> 1.7261716 | BD10: ='LCFS Table'!$AT10*'LCFS Table'!$BX10 -> 0 | BE10: ='LCFS Table'!$AU10*'LCFS Table'!$BY10 -> 1 | BF10: ='LCFS Table'!$AV10*'LCFS Table'!$BZ10 -> 0.9027 | BG10: ='LCFS Table'!$AW10*'LCFS Table'!$CA10 -> 0 | BH10: ='LCFS Table'!$AX10*'LCFS Table'!$CB10 -> 1.1883244 | BI10: ='LCFS Table'!$AY10*'LCFS Table'!$CC10 -> 0 | BJ10: ='LCFS Table'!$AZ10*'LCFS Table'!$CD10 -> 1 | BK10: ='LCFS Table'!$BA10*'LCFS Table'!$CE10 -> 0.7965 | BL10: ='LCFS Table'!$BB10*'LCFS Table'!$CF10 -> -1.2 | BM10: ='LCFS Table'!$AS10*'LCFS Table'!$CG10 -> 0 | BN10: ='LCFS Table'!$AT10*'LCFS Table'!$CH10 -> 0.16 | BO10: ='LCFS Table'!$AU10*'LCFS Table'!$CI10 -> 0 | BP10: ='LCFS Table'!$AV10*'LCFS Table'!$CJ10 -> 0 | BQ10: ='LCFS Table'!$AW10*'LCFS Table'!$CK10 -> 0 | BR10: ='LCFS Table'!$AX10*'LCFS Table'!$CL10 -> 0 | BS10: ='LCFS Table'!$AY10*'LCFS Table'!$CM10 -> 0 | BT10: ='LCFS Table'!$AZ10*'LCFS Table'!$CN10 -> 0 | BU10: ='LCFS Table'!$BA10*'LCFS Table'!$CO10 -> 0 | BV10: ='LCFS Table'!$BB10*'LCFS Table'!$CP10 -> 1.2 | BW10: 1 | BX10: 0 | BY10: 1 | BZ10: 1 | CA10: -1 | CB10: 1 | CC10: 0 | CD10: 1 | CE10: 1 | CF10: -1 | CG10: =1-'LCFS Table'!$BW10 -> 0 | CH10: =1-'LCFS Table'!$BX10 -> 1 | CI10: =1-'LCFS Table'!$BY10 -> 0 | CJ10: =1-'LCFS Table'!$BZ10 -> 0 | CK10: =-'LCFS Table'!$CA10 -> 1 | CL10: =1-'LCFS Table'!$CB10 -> 0 | CM10: =1-'LCFS Table'!$CC10 -> 1 | CN10: =1-'LCFS Table'!$CD10 -> 0 | CO10: =1-'LCFS Table'!$CE10 -> 0 | CP10: =-'LCFS Table'!$CF10 -> 1 | CQ10: 7.5 | CR10: =('LCFS Table'!$CQ10*0.9/(0.8/0.99)/100) -> 0.08353125 | CX10: =MONTH('LCFS Table'!$B10) -> 2 | CY10: =YEAR('LCFS Table'!$B10) -> 2019
A11: ='LCFS Table'!$B11-5 -> 43520 | B11: 43525 | C11: =YEAR(B11) -> 2019 | D11: W9 | F11: =('LCFS Table'!$M11)-'LCFS Table'!$J11 -> -2.8482016 | H11: ='LCFS Table'!$F11+'LCFS Table'!$AX11+'LCFS Table'!$AY11+'LCFS Table'!$AZ11+'LCFS Table'!$BA11+('LCFS Table'!$CQ11*0.9/(0.8/0.99)/100)+(DG11*'LCFS Table'!$AF11)+(DF11*'LCFS Table'!$AG11) -> 0.15050586 | I11: =('LCFS Table'!$V11+'LCFS Table'!$W11+'LCFS Table'!$X11)/100+(('LCFS Table'!$AI11+'LCFS Table'!$AJ11)/340) -> 2.6968273 | J11: =(('LCFS Table'!$Y11+'LCFS Table'!$Z11)/100)+(('LCFS Table'!$AM11+'LCFS Table'!$AN11)/300) -> 3.2130254 | K11: #N/A | L11: 328 | M11: =('LCFS Table'!$L11/100)-'LCFS Table'!$AX11-'LCFS Table'!$AY11-'LCFS Table'!$AZ11-'LCFS Table'!$BA11 -> 0.36482375 | N11: 26 | O11: 25.7 | P11: 23.675 | Q11: 32.26 | R11: 24 | S11: ='LCFS Table'!$N11 + 'LCFS Table'!$AH11 -> 30.375 | T11: ='LCFS Table'!$Q11+'LCFS Table'!$AH11 -> 36.635 | U11: ='LCFS Table'!$P11+'LCFS Table'!$AH11 -> 28.05 | V11: =(('LCFS Table'!$S11/'LCFS Table'!$AA11)*'LCFS Table'!$AC11)*6.48 -> 104.69681 | W11: =(('LCFS Table'!$O11/'LCFS Table'!$AA11)*'LCFS Table'!$AD11)*6.48 -> 44.291489 | X11: =(('LCFS Table'!$U11/'LCFS Table'!$AA11)*'LCFS Table'!$AE11)*6.48 -> 48.341489 | Y11: =(('LCFS Table'!$T11/'LCFS Table'!$AB11)*'LCFS Table'!$AF11)*7.35 -> 210.36504 | Z11: =(('LCFS Table'!$R11/'LCFS Table'!$AB11)*'LCFS Table'!$AG11)*7.35 -> 45.9375 | AA11: 0.94 | AB11: 0.96 | AC11: 0.5 | AD11: 0.25 | AE11: 0.25 | AF11: 0.75 | AG11: 0.25 | AH11: 4.375 | AI11: 136 | AJ11: 110 | AK11: =('LCFS Table'!$AI11/340)*100 -> 40 | AL11: =('LCFS Table'!$AJ11/340)*100 -> 32.352941 | AM11: 105 | AN11: 90 | AO11: =('LCFS Table'!$AM11/300)*100 -> 35 | AP11: =('LCFS Table'!$AN11/300)*100 -> 30 | AQ11: 195.35 | AR11: 0.488 | AS11: 1.7186933 | AT11: 0.16 | AU11: 1 | AV11: ='LCFS Table'!$AR11*1.7 -> 0.8296 | AW11: 0 | AX11: 1.1831763 | AY11: 0 | AZ11: 1 | BA11: ='LCFS Table'!$AR11*1.5 -> 0.732 | BB11: 1.2 | BC11: ='LCFS Table'!$AS11*'LCFS Table'!$BW11 -> 1.7186933 | BD11: ='LCFS Table'!$AT11*'LCFS Table'!$BX11 -> 0 | BE11: ='LCFS Table'!$AU11*'LCFS Table'!$BY11 -> 1 | BF11: ='LCFS Table'!$AV11*'LCFS Table'!$BZ11 -> 0.8296 | BG11: ='LCFS Table'!$AW11*'LCFS Table'!$CA11 -> 0 | BH11: ='LCFS Table'!$AX11*'LCFS Table'!$CB11 -> 1.1831763 | BI11: ='LCFS Table'!$AY11*'LCFS Table'!$CC11 -> 0 | BJ11: ='LCFS Table'!$AZ11*'LCFS Table'!$CD11 -> 1 | BK11: ='LCFS Table'!$BA11*'LCFS Table'!$CE11 -> 0.732 | BL11: ='LCFS Table'!$BB11*'LCFS Table'!$CF11 -> -1.2 | BM11: ='LCFS Table'!$AS11*'LCFS Table'!$CG11 -> 0 | BN11: ='LCFS Table'!$AT11*'LCFS Table'!$CH11 -> 0.16 | BO11: ='LCFS Table'!$AU11*'LCFS Table'!$CI11 -> 0 | BP11: ='LCFS Table'!$AV11*'LCFS Table'!$CJ11 -> 0 | BQ11: ='LCFS Table'!$AW11*'LCFS Table'!$CK11 -> 0 | BR11: ='LCFS Table'!$AX11*'LCFS Table'!$CL11 -> 0 | BS11: ='LCFS Table'!$AY11*'LCFS Table'!$CM11 -> 0 | BT11: ='LCFS Table'!$AZ11*'LCFS Table'!$CN11 -> 0 | BU11: ='LCFS Table'!$BA11*'LCFS Table'!$CO11 -> 0 | BV11: ='LCFS Table'!$BB11*'LCFS Table'!$CP11 -> 1.2 | BW11: 1 | BX11: 0 | BY11: 1 | BZ11: 1 | CA11: -1 | CB11: 1 | CC11: 0 | CD11: 1 | CE11: 1 | CF11: -1 | CG11: =1-'LCFS Table'!$BW11 -> 0 | CH11: =1-'LCFS Table'!$BX11 -> 1 | CI11: =1-'LCFS Table'!$BY11 -> 0 | CJ11: =1-'LCFS Table'!$BZ11 -> 0 | CK11: =-'LCFS Table'!$CA11 -> 1 | CL11: =1-'LCFS Table'!$CB11 -> 0 | CM11: =1-'LCFS Table'!$CC11 -> 1 | CN11: =1-'LCFS Table'!$CD11 -> 0 | CO11: =1-'LCFS Table'!$CE11 -> 0 | CP11: =-'LCFS Table'!$CF11 -> 1 | CQ11: 7.5 | CR11: =('LCFS Table'!$CQ11*0.9/(0.8/0.99)/100) -> 0.08353125 | CX11: =MONTH('LCFS Table'!$B11) -> 3 | CY11: =YEAR('LCFS Table'!$B11) -> 2019
A12: ='LCFS Table'!$B12-5 -> 43527 | B12: 43532 | C12: =YEAR(B12) -> 2019 | D12: W10 | F12: =('LCFS Table'!$M12)-'LCFS Table'!$J12 -> -2.7659145 | H12: ='LCFS Table'!$F12+'LCFS Table'!$AX12+'LCFS Table'!$AY12+'LCFS Table'!$AZ12+'LCFS Table'!$BA12+('LCFS Table'!$CQ12*0.9/(0.8/0.99)/100)+(DG12*'LCFS Table'!$AF12)+(DF12*'LCFS Table'!$AG12) -> 0.1590043 | I12: =('LCFS Table'!$V12+'LCFS Table'!$W12+'LCFS Table'!$X12)/100+(('LCFS Table'!$AI12+'LCFS Table'!$AJ12)/340) -> 2.6989815 | J12: =(('LCFS Table'!$Y12+'LCFS Table'!$Z12)/100)+(('LCFS Table'!$AM12+'LCFS Table'!$AN12)/300) -> 3.204527 | K12: #N/A | L12: 328 | M12: =('LCFS Table'!$L12/100)-'LCFS Table'!$AX12-'LCFS Table'!$AY12-'LCFS Table'!$AZ12-'LCFS Table'!$BA12 -> 0.43861241 | N12: 26 | O12: 25.75 | P12: 23.75 | Q12: 32.112 | R12: 24 | S12: ='LCFS Table'!$N12 + 'LCFS Table'!$AH12 -> 30.375 | T12: ='LCFS Table'!$Q12+'LCFS Table'!$AH12 -> 36.487 | U12: ='LCFS Table'!$P12+'LCFS Table'!$AH12 -> 28.125 | V12: =(('LCFS Table'!$S12/'LCFS Table'!$AA12)*'LCFS Table'!$AC12)*6.48 -> 104.69681 | W12: =(('LCFS Table'!$O12/'LCFS Table'!$AA12)*'LCFS Table'!$AD12)*6.48 -> 44.37766 | X12: =(('LCFS Table'!$U12/'LCFS Table'!$AA12)*'LCFS Table'!$AE12)*6.48 -> 48.470745 | Y12: =(('LCFS Table'!$T12/'LCFS Table'!$AB12)*'LCFS Table'!$AF12)*7.35 -> 209.5152 | Z12: =(('LCFS Table'!$R12/'LCFS Table'!$AB12)*'LCFS Table'!$AG12)*7.35 -> 45.9375 | AA12: 0.94 | AB12: 0.96 | AC12: 0.5 | AD12: 0.25 | AE12: 0.25 | AF12: 0.75 | AG12: 0.25 | AH12: 4.375 | AI12: 136 | AJ12: 110 | AK12: =('LCFS Table'!$AI12/340)*100 -> 40 | AL12: =('LCFS Table'!$AJ12/340)*100 -> 32.352941 | AM12: 105 | AN12: 90 | AO12: =('LCFS Table'!$AM12/300)*100 -> 35 | AP12: =('LCFS Table'!$AN12/300)*100 -> 30 | AQ12: 195.55 | AR12: 0.438 | AS12: 1.7204529 | AT12: 0.16 | AU12: 1 | AV12: ='LCFS Table'!$AR12*1.7 -> 0.7446 | AW12: 0 | AX12: 1.1843876 | AY12: 0 | AZ12: 1 | BA12: ='LCFS Table'!$AR12*1.5 -> 0.657 | BB12: 1.2 | BC12: ='LCFS Table'!$AS12*'LCFS Table'!$BW12 -> 1.7204529 | BD12: ='LCFS Table'!$AT12*'LCFS Table'!$BX12 -> 0 | BE12: ='LCFS Table'!$AU12*'LCFS Table'!$BY12 -> 1 | BF12: ='LCFS Table'!$AV12*'LCFS Table'!$BZ12 -> 0.7446 | BG12: ='LCFS Table'!$AW12*'LCFS Table'!$CA12 -> 0 | BH12: ='LCFS Table'!$AX12*'LCFS Table'!$CB12 -> 1.1843876 | BI12: ='LCFS Table'!$AY12*'LCFS Table'!$CC12 -> 0 | BJ12: ='LCFS Table'!$AZ12*'LCFS Table'!$CD12 -> 1 | BK12: ='LCFS Table'!$BA12*'LCFS Table'!$CE12 -> 0.657 | BL12: ='LCFS Table'!$BB12*'LCFS Table'!$CF12 -> -1.2 | BM12: ='LCFS Table'!$AS12*'LCFS Table'!$CG12 -> 0 | BN12: ='LCFS Table'!$AT12*'LCFS Table'!$CH12 -> 0.16 | BO12: ='LCFS Table'!$AU12*'LCFS Table'!$CI12 -> 0 | BP12: ='LCFS Table'!$AV12*'LCFS Table'!$CJ12 -> 0 | BQ12: ='LCFS Table'!$AW12*'LCFS Table'!$CK12 -> 0 | BR12: ='LCFS Table'!$AX12*'LCFS Table'!$CL12 -> 0 | BS12: ='LCFS Table'!$AY12*'LCFS Table'!$CM12 -> 0 | BT12: ='LCFS Table'!$AZ12*'LCFS Table'!$CN12 -> 0 | BU12: ='LCFS Table'!$BA12*'LCFS Table'!$CO12 -> 0 | BV12: ='LCFS Table'!$BB12*'LCFS Table'!$CP12 -> 1.2 | BW12: 1 | BX12: 0 | BY12: 1 | BZ12: 1 | CA12: -1 | CB12: 1 | CC12: 0 | CD12: 1 | CE12: 1 | CF12: -1 | CG12: =1-'LCFS Table'!$BW12 -> 0 | CH12: =1-'LCFS Table'!$BX12 -> 1 | CI12: =1-'LCFS Table'!$BY12 -> 0 | CJ12: =1-'LCFS Table'!$BZ12 -> 0 | CK12: =-'LCFS Table'!$CA12 -> 1 | CL12: =1-'LCFS Table'!$CB12 -> 0 | CM12: =1-'LCFS Table'!$CC12 -> 1 | CN12: =1-'LCFS Table'!$CD12 -> 0 | CO12: =1-'LCFS Table'!$CE12 -> 0 | CP12: =-'LCFS Table'!$CF12 -> 1 | CQ12: 7.5 | CR12: =('LCFS Table'!$CQ12*0.9/(0.8/0.99)/100) -> 0.08353125 | CX12: =MONTH('LCFS Table'!$B12) -> 3 | CY12: =YEAR('LCFS Table'!$B12) -> 2019
A13: ='LCFS Table'!$B13-5 -> 43534 | B13: 43539 | C13: =YEAR(B13) -> 2019 | D13: W11 | F13: =('LCFS Table'!$M13)-'LCFS Table'!$J13 -> -2.6410784 | H13: ='LCFS Table'!$F13+'LCFS Table'!$AX13+'LCFS Table'!$AY13+'LCFS Table'!$AZ13+'LCFS Table'!$BA13+('LCFS Table'!$CQ13*0.9/(0.8/0.99)/100)+(DG13*'LCFS Table'!$AF13)+(DF13*'LCFS Table'!$AG13) -> 0.19173477 | I13: =('LCFS Table'!$V13+'LCFS Table'!$W13+'LCFS Table'!$X13)/100+(('LCFS Table'!$AI13+'LCFS Table'!$AJ13)/340) -> 2.6989815 | J13: =(('LCFS Table'!$Y13+'LCFS Table'!$Z13)/100)+(('LCFS Table'!$AM13+'LCFS Table'!$AN13)/300) -> 3.1717965 | K13: #N/A | L13: 328 | M13: =('LCFS Table'!$L13/100)-'LCFS Table'!$AX13-'LCFS Table'!$AY13-'LCFS Table'!$AZ13-'LCFS Table'!$BA13 -> 0.53071808 | N13: 26 | O13: 25.75 | P13: 23.75 | Q13: 31.542 | R13: 24 | S13: ='LCFS Table'!$N13 + 'LCFS Table'!$AH13 -> 30.375 | T13: ='LCFS Table'!$Q13+'LCFS Table'!$AH13 -> 35.917 | U13: ='LCFS Table'!$P13+'LCFS Table'!$AH13 -> 28.125 | V13: =(('LCFS Table'!$S13/'LCFS Table'!$AA13)*'LCFS Table'!$AC13)*6.48 -> 104.69681 | W13: =(('LCFS Table'!$O13/'LCFS Table'!$AA13)*'LCFS Table'!$AD13)*6.48 -> 44.37766 | X13: =(('LCFS Table'!$U13/'LCFS Table'!$AA13)*'LCFS Table'!$AE13)*6.48 -> 48.470745 | Y13: =(('LCFS Table'!$T13/'LCFS Table'!$AB13)*'LCFS Table'!$AF13)*7.35 -> 206.24215 | Z13: =(('LCFS Table'!$R13/'LCFS Table'!$AB13)*'LCFS Table'!$AG13)*7.35 -> 45.9375 | AA13: 0.94 | AB13: 0.96 | AC13: 0.5 | AD13: 0.25 | AE13: 0.25 | AF13: 0.75 | AG13: 0.25 | AH13: 4.375 | AI13: 136 | AJ13: 110 | AK13: =('LCFS Table'!$AI13/340)*100 -> 40 | AL13: =('LCFS Table'!$AJ13/340)*100 -> 32.352941 | AM13: 105 | AN13: 90 | AO13: =('LCFS Table'!$AM13/300)*100 -> 35 | AP13: =('LCFS Table'!$AN13/300)*100 -> 30 | AQ13: 195.45 | AR13: 0.377 | AS13: 1.7195731 | AT13: 0.16 | AU13: 1 | AV13: ='LCFS Table'!$AR13*1.7 -> 0.6409 | AW13: 0 | AX13: 1.1837819 | AY13: 0 | AZ13: 1 | BA13: ='LCFS Table'!$AR13*1.5 -> 0.5655 | BB13: 1.2 | BC13: ='LCFS Table'!$AS13*'LCFS Table'!$BW13 -> 1.7195731 | BD13: ='LCFS Table'!$AT13*'LCFS Table'!$BX13 -> 0 | BE13: ='LCFS Table'!$AU13*'LCFS Table'!$BY13 -> 1 | BF13: ='LCFS Table'!$AV13*'LCFS Table'!$BZ13 -> 0.6409 | BG13: ='LCFS Table'!$AW13*'LCFS Table'!$CA13 -> 0 | BH13: ='LCFS Table'!$AX13*'LCFS Table'!$CB13 -> 1.1837819 | BI13: ='LCFS Table'!$AY13*'LCFS Table'!$CC13 -> 0 | BJ13: ='LCFS Table'!$AZ13*'LCFS Table'!$CD13 -> 1 | BK13: ='LCFS Table'!$BA13*'LCFS Table'!$CE13 -> 0.5655 | BL13: ='LCFS Table'!$BB13*'LCFS Table'!$CF13 -> -1.2 | BM13: ='LCFS Table'!$AS13*'LCFS Table'!$CG13 -> 0 | BN13: ='LCFS Table'!$AT13*'LCFS Table'!$CH13 -> 0.16 | BO13: ='LCFS Table'!$AU13*'LCFS Table'!$CI13 -> 0 | BP13: ='LCFS Table'!$AV13*'LCFS Table'!$CJ13 -> 0 | BQ13: ='LCFS Table'!$AW13*'LCFS Table'!$CK13 -> 0 | BR13: ='LCFS Table'!$AX13*'LCFS Table'!$CL13 -> 0 | BS13: ='LCFS Table'!$AY13*'LCFS Table'!$CM13 -> 0 | BT13: ='LCFS Table'!$AZ13*'LCFS Table'!$CN13 -> 0 | BU13: ='LCFS Table'!$BA13*'LCFS Table'!$CO13 -> 0 | BV13: ='LCFS Table'!$BB13*'LCFS Table'!$CP13 -> 1.2 | BW13: 1 | BX13: 0 | BY13: 1 | BZ13: 1 | CA13: -1 | CB13: 1 | CC13: 0 | CD13: 1 | CE13: 1 | CF13: -1 | CG13: =1-'LCFS Table'!$BW13 -> 0 | CH13: =1-'LCFS Table'!$BX13 -> 1 | CI13: =1-'LCFS Table'!$BY13 -> 0 | CJ13: =1-'LCFS Table'!$BZ13 -> 0 | CK13: =-'LCFS Table'!$CA13 -> 1 | CL13: =1-'LCFS Table'!$CB13 -> 0 | CM13: =1-'LCFS Table'!$CC13 -> 1 | CN13: =1-'LCFS Table'!$CD13 -> 0 | CO13: =1-'LCFS Table'!$CE13 -> 0 | CP13: =-'LCFS Table'!$CF13 -> 1 | CQ13: 7.5 | CR13: =('LCFS Table'!$CQ13*0.9/(0.8/0.99)/100) -> 0.08353125 | CX13: =MONTH('LCFS Table'!$B13) -> 3 | CY13: =YEAR('LCFS Table'!$B13) -> 2019
A14: ='LCFS Table'!$B14-5 -> 43541 | B14: 43546 | C14: =YEAR(B14) -> 2019 | D14: W12 | F14: =('LCFS Table'!$M14)-'LCFS Table'!$J14 -> -2.5967023 | H14: ='LCFS Table'!$F14+'LCFS Table'!$AX14+'LCFS Table'!$AY14+'LCFS Table'!$AZ14+'LCFS Table'!$BA14+('LCFS Table'!$CQ14*0.9/(0.8/0.99)/100)+(DG14*'LCFS Table'!$AF14)+(DF14*'LCFS Table'!$AG14) -> 0.2196418 | I14: =('LCFS Table'!$V14+'LCFS Table'!$W14+'LCFS Table'!$X14)/100+(('LCFS Table'!$AI14+'LCFS Table'!$AJ14)/340) -> 2.7058752 | J14: =(('LCFS Table'!$Y14+'LCFS Table'!$Z14)/100)+(('LCFS Table'!$AM14+'LCFS Table'!$AN14)/300) -> 3.1438895 | K14: #N/A | L14: 328 | M14: =('LCFS Table'!$L14/100)-'LCFS Table'!$AX14-'LCFS Table'!$AY14-'LCFS Table'!$AZ14-'LCFS Table'!$BA14 -> 0.54718714 | N14: 26.2 | O14: 25.75 | P14: 23.75 | Q14: 31.056 | R14: 24 | S14: ='LCFS Table'!$N14 + 'LCFS Table'!$AH14 -> 30.575 | T14: ='LCFS Table'!$Q14+'LCFS Table'!$AH14 -> 35.431 | U14: ='LCFS Table'!$P14+'LCFS Table'!$AH14 -> 28.125 | V14: =(('LCFS Table'!$S14/'LCFS Table'!$AA14)*'LCFS Table'!$AC14)*6.48 -> 105.38617 | W14: =(('LCFS Table'!$O14/'LCFS Table'!$AA14)*'LCFS Table'!$AD14)*6.48 -> 44.37766 | X14: =(('LCFS Table'!$U14/'LCFS Table'!$AA14)*'LCFS Table'!$AE14)*6.48 -> 48.470745 | Y14: =(('LCFS Table'!$T14/'LCFS Table'!$AB14)*'LCFS Table'!$AF14)*7.35 -> 203.45145 | Z14: =(('LCFS Table'!$R14/'LCFS Table'!$AB14)*'LCFS Table'!$AG14)*7.35 -> 45.9375 | AA14: 0.94 | AB14: 0.96 | AC14: 0.5 | AD14: 0.25 | AE14: 0.25 | AF14: 0.75 | AG14: 0.25 | AH14: 4.375 | AI14: 136 | AJ14: 110 | AK14: =('LCFS Table'!$AI14/340)*100 -> 40 | AL14: =('LCFS Table'!$AJ14/340)*100 -> 32.352941 | AM14: 105 | AN14: 90 | AO14: =('LCFS Table'!$AM14/300)*100 -> 35 | AP14: =('LCFS Table'!$AN14/300)*100 -> 30 | AQ14: 193.35 | AR14: 0.3745 | AS14: 1.7010973 | AT14: 0.16 | AU14: 1 | AV14: ='LCFS Table'!$AR14*1.7 -> 0.63665 | AW14: 0 | AX14: 1.1710629 | AY14: 0 | AZ14: 1 | BA14: ='LCFS Table'!$AR14*1.5 -> 0.56175 | BB14: 1.2 | BC14: ='LCFS Table'!$AS14*'LCFS Table'!$BW14 -> 1.7010973 | BD14: ='LCFS Table'!$AT14*'LCFS Table'!$BX14 -> 0 | BE14: ='LCFS Table'!$AU14*'LCFS Table'!$BY14 -> 1 | BF14: ='LCFS Table'!$AV14*'LCFS Table'!$BZ14 -> 0.63665 | BG14: ='LCFS Table'!$AW14*'LCFS Table'!$CA14 -> 0 | BH14: ='LCFS Table'!$AX14*'LCFS Table'!$CB14 -> 1.1710629 | BI14: ='LCFS Table'!$AY14*'LCFS Table'!$CC14 -> 0 | BJ14: ='LCFS Table'!$AZ14*'LCFS Table'!$CD14 -> 1 | BK14: ='LCFS Table'!$BA14*'LCFS Table'!$CE14 -> 0.56175 | BL14: ='LCFS Table'!$BB14*'LCFS Table'!$CF14 -> -1.2 | BM14: ='LCFS Table'!$AS14*'LCFS Table'!$CG14 -> 0 | BN14: ='LCFS Table'!$AT14*'LCFS Table'!$CH14 -> 0.16 | BO14: ='LCFS Table'!$AU14*'LCFS Table'!$CI14 -> 0 | BP14: ='LCFS Table'!$AV14*'LCFS Table'!$CJ14 -> 0 | BQ14: ='LCFS Table'!$AW14*'LCFS Table'!$CK14 -> 0 | BR14: ='LCFS Table'!$AX14*'LCFS Table'!$CL14 -> 0 | BS14: ='LCFS Table'!$AY14*'LCFS Table'!$CM14 -> 0 | BT14: ='LCFS Table'!$AZ14*'LCFS Table'!$CN14 -> 0 | BU14: ='LCFS Table'!$BA14*'LCFS Table'!$CO14 -> 0 | BV14: ='LCFS Table'!$BB14*'LCFS Table'!$CP14 -> 1.2 | BW14: 1 | BX14: 0 | BY14: 1 | BZ14: 1 | CA14: -1 | CB14: 1 | CC14: 0 | CD14: 1 | CE14: 1 | CF14: -1 | CG14: =1-'LCFS Table'!$BW14 -> 0 | CH14: =1-'LCFS Table'!$BX14 -> 1 | CI14: =1-'LCFS Table'!$BY14 -> 0 | CJ14: =1-'LCFS Table'!$BZ14 -> 0 | CK14: =-'LCFS Table'!$CA14 -> 1 | CL14: =1-'LCFS Table'!$CB14 -> 0 | CM14: =1-'LCFS Table'!$CC14 -> 1 | CN14: =1-'LCFS Table'!$CD14 -> 0 | CO14: =1-'LCFS Table'!$CE14 -> 0 | CP14: =-'LCFS Table'!$CF14 -> 1 | CQ14: 7.5 | CR14: =('LCFS Table'!$CQ14*0.9/(0.8/0.99)/100) -> 0.08353125 | CX14: =MONTH('LCFS Table'!$B14) -> 3 | CY14: =YEAR('LCFS Table'!$B14) -> 2019
... A25: ='LCFS Table'!$B25-5 -> 43618 | B25: 43623 | C25: =YEAR(B25) -> 2019 | D25: W23 | F25: =('LCFS Table'!$M25)-'LCFS Table'!$J25 -> -2.7012952 | H25: ='LCFS Table'!$F25+'LCFS Table'!$AX25+'LCFS Table'!$AY25+'LCFS Table'!$AZ25+'LCFS Table'!$BA25+('LCFS Table'!$CQ25*0.9/(0.8/0.99)/100)+(DG25*'LCFS Table'!$AF25)+(DF25*'LCFS Table'!$AG25) -> 0.16225195 | I25: =('LCFS Table'!$V25+'LCFS Table'!$W25+'LCFS Table'!$X25)/100+(('LCFS Table'!$AI25+'LCFS Table'!$AJ25)/340) -> 2.8368539 | J25: =(('LCFS Table'!$Y25+'LCFS Table'!$Z25)/100)+(('LCFS Table'!$AM25+'LCFS Table'!$AN25)/300) -> 3.1440043 | K25: #N/A | L25: 324.5 | M25: =('LCFS Table'!$L25/100)-'LCFS Table'!$AX25-'LCFS Table'!$AY25-'LCFS Table'!$AZ25-'LCFS Table'!$BA25 -> 0.44270905 | N25: 29.25 | O25: 25.75 | P25: 25.25 | Q25: 31.058 | R25: 24 | S25: ='LCFS Table'!$N25 + 'LCFS Table'!$AH25 -> 33.625 | T25: ='LCFS Table'!$Q25+'LCFS Table'!$AH25 -> 35.433 | U25: ='LCFS Table'!$P25+'LCFS Table'!$AH25 -> 29.625 | V25: =(('LCFS Table'!$S25/'LCFS Table'!$AA25)*'LCFS Table'!$AC25)*6.48 -> 115.89894 | W25: =(('LCFS Table'!$O25/'LCFS Table'!$AA25)*'LCFS Table'!$AD25)*6.48 -> 44.37766 | X25: =(('LCFS Table'!$U25/'LCFS Table'!$AA25)*'LCFS Table'!$AE25)*6.48 -> 51.055851 | Y25: =(('LCFS Table'!$T25/'LCFS Table'!$AB25)*'LCFS Table'!$AF25)*7.35 -> 203.46293 | Z25: =(('LCFS Table'!$R25/'LCFS Table'!$AB25)*'LCFS Table'!$AG25)*7.35 -> 45.9375 | AA25: 0.94 | AB25: 0.96 | AC25: 0.5 | AD25: 0.25 | AE25: 0.25 | AF25: 0.75 | AG25: 0.25 | AH25: 4.375 | AI25: 136 | AJ25: 110 | AK25: =('LCFS Table'!$AI25/340)*100 -> 40 | AL25: =('LCFS Table'!$AJ25/340)*100 -> 32.352941 | AM25: 105 | AN25: 90 | AO25: =('LCFS Table'!$AM25/300)*100 -> 35 | AP25: =('LCFS Table'!$AN25/300)*100 -> 30 | AQ25: 191.2 | AR25: 0.4295 | AS25: 1.6821815 | AT25: 0.16 | AU25: 1 | AV25: ='LCFS Table'!$AR25*1.7 -> 0.73015 | AW25: 0 | AX25: 1.158041 | AY25: 0 | AZ25: 1 | BA25: ='LCFS Table'!$AR25*1.5 -> 0.64425 | BB25: 1.2 | BC25: ='LCFS Table'!$AS25*'LCFS Table'!$BW25 -> 1.6821815 | BD25: ='LCFS Table'!$AT25*'LCFS Table'!$BX25 -> 0 | BE25: ='LCFS Table'!$AU25*'LCFS Table'!$BY25 -> 1 | BF25: ='LCFS Table'!$AV25*'LCFS Table'!$BZ25 -> 0.73015 | BG25: ='LCFS Table'!$AW25*'LCFS Table'!$CA25 -> 0 | BH25: ='LCFS Table'!$AX25*'LCFS Table'!$CB25 -> 1.158041 | BI25: ='LCFS Table'!$AY25*'LCFS Table'!$CC25 -> 0 | BJ25: ='LCFS Table'!$AZ25*'LCFS Table'!$CD25 -> 1 | BK25: ='LCFS Table'!$BA25*'LCFS Table'!$CE25 -> 0.64425 | BL25: ='LCFS Table'!$BB25*'LCFS Table'!$CF25 -> -1.2 | BM25: ='LCFS Table'!$AS25*'LCFS Table'!$CG25 -> 0 | BN25: ='LCFS Table'!$AT25*'LCFS Table'!$CH25 -> 0.16 | BO25: ='LCFS Table'!$AU25*'LCFS Table'!$CI25 -> 0 | BP25: ='LCFS Table'!$AV25*'LCFS Table'!$CJ25 -> 0 | BQ25: ='LCFS Table'!$AW25*'LCFS Table'!$CK25 -> 0 | BR25: ='LCFS Table'!$AX25*'LCFS Table'!$CL25 -> 0 | BS25: ='LCFS Table'!$AY25*'LCFS Table'!$CM25 -> 0 | BT25: ='LCFS Table'!$AZ25*'LCFS Table'!$CN25 -> 0 | BU25: ='LCFS Table'!$BA25*'LCFS Table'!$CO25 -> 0 | BV25: ='LCFS Table'!$BB25*'LCFS Table'!$CP25 -> 1.2 | BW25: 1 | BX25: 0 | BY25: 1 | BZ25: 1 | CA25: -1 | CB25: 1 | CC25: 0 | CD25: 1 | CE25: 1 | CF25: -1 | CG25: =1-'LCFS Table'!$BW25 -> 0 | CH25: =1-'LCFS Table'!$BX25 -> 1 | CI25: =1-'LCFS Table'!$BY25 -> 0 | CJ25: =1-'LCFS Table'!$BZ25 -> 0 | CK25: =-'LCFS Table'!$CA25 -> 1 | CL25: =1-'LCFS Table'!$CB25 -> 0 | CM25: =1-'LCFS Table'!$CC25 -> 1 | CN25: =1-'LCFS Table'!$CD25 -> 0 | CO25: =1-'LCFS Table'!$CE25 -> 0 | CP25: =-'LCFS Table'!$CF25 -> 1 | CQ25: 5.5 | CR25: =('LCFS Table'!$CQ25*0.9/(0.8/0.99)/100) -> 0.06125625 | CX25: =MONTH('LCFS Table'!$B25) -> 6 | CY25: =YEAR('LCFS Table'!$B25) -> 2019
A26: ='LCFS Table'!$B26-5 -> 43625 | B26: 43630 | C26: =YEAR(B26) -> 2019 | D26: W24 | E26: ='LCFS Table'!$K26-'LCFS Table'!$I26 -> -0.93020069 | F26: =('LCFS Table'!$M26)-'LCFS Table'!$J26 -> -2.7662551 | G26: ='LCFS Table'!$E26+'LCFS Table'!$AS26+'LCFS Table'!$AT26+'LCFS Table'!$AU26+'LCFS Table'!$AV26 -> 2.7163789 | H26: ='LCFS Table'!$F26+'LCFS Table'!$AX26+'LCFS Table'!$AY26+'LCFS Table'!$AZ26+'LCFS Table'!$BA26+('LCFS Table'!$CQ26*0.9/(0.8/0.99)/100)+(DG26*'LCFS Table'!$AF26)+(DF26*'LCFS Table'!$AG26) -> 0.16109883 | I26: =('LCFS Table'!$V26+'LCFS Table'!$W26+'LCFS Table'!$X26)/100+(('LCFS Table'!$AI26+'LCFS Table'!$AJ26)/340) -> 2.8403007 | J26: =(('LCFS Table'!$Y26+'LCFS Table'!$Z26)/100)+(('LCFS Table'!$AM26+'LCFS Table'!$AN26)/300) -> 3.1931574 | K26: ='[1]Fuel Values'!$C26 -> 1.9101 | L26: 329.3 | M26: =('LCFS Table'!$L26/100)-'LCFS Table'!$AX26-'LCFS Table'!$AY26-'LCFS Table'!$AZ26-'LCFS Table'!$BA26 -> 0.42690235 | N26: 29.25 | O26: 25.75 | P26: 25.45 | Q26: 31.914 | R26: 24 | S26: ='LCFS Table'!$N26 + 'LCFS Table'!$AH26 -> 33.625 | T26: ='LCFS Table'!$Q26+'LCFS Table'!$AH26 -> 36.289 | U26: ='LCFS Table'!$P26+'LCFS Table'!$AH26 -> 29.825 | V26: =(('LCFS Table'!$S26/'LCFS Table'!$AA26)*'LCFS Table'!$AC26)*6.48 -> 115.89894 | W26: =(('LCFS Table'!$O26/'LCFS Table'!$AA26)*'LCFS Table'!$AD26)*6.48 -> 44.37766 | X26: =(('LCFS Table'!$U26/'LCFS Table'!$AA26)*'LCFS Table'!$AE26)*6.48 -> 51.400532 | Y26: =(('LCFS Table'!$T26/'LCFS Table'!$AB26)*'LCFS Table'!$AF26)*7.35 -> 208.37824 | Z26: =(('LCFS Table'!$R26/'LCFS Table'!$AB26)*'LCFS Table'!$AG26)*7.35 -> 45.9375 | AA26: 0.94 | AB26: 0.96 | AC26: 0.5 | AD26: 0.25 | AE26: 0.25 | AF26: 0.75 | AG26: 0.25 | AH26: 4.375 | AI26: 136 | AJ26: 110 | AK26: =('LCFS Table'!$AI26/340)*100 -> 40 | AL26: =('LCFS Table'!$AJ26/340)*100 -> 32.352941 | AM26: 105 | AN26: 90 | AO26: =('LCFS Table'!$AM26/300)*100 -> 35 | AP26: =('LCFS Table'!$AN26/300)*100 -> 30 | AQ26: 192.2 | AR26: 0.468 | AS26: 1.6909795 | AT26: 0.16 | AU26: 1 | AV26: ='LCFS Table'!$AR26*1.7 -> 0.7956 | AW26: 0 | AX26: 1.1640977 | AY26: 0 | AZ26: 1 | BA26: ='LCFS Table'!$AR26*1.5 -> 0.702 | BB26: 1.2 | BC26: ='LCFS Table'!$AS26*'LCFS Table'!$BW26 -> 1.6909795 | BD26: ='LCFS Table'!$AT26*'LCFS Table'!$BX26 -> 0 | BE26: ='LCFS Table'!$AU26*'LCFS Table'!$BY26 -> 1 | BF26: ='LCFS Table'!$AV26*'LCFS Table'!$BZ26 -> 0.7956 | BG26: ='LCFS Table'!$AW26*'LCFS Table'!$CA26 -> 0 | BH26: ='LCFS Table'!$AX26*'LCFS Table'!$CB26 -> 1.1640977 | BI26: ='LCFS Table'!$AY26*'LCFS Table'!$CC26 -> 0 | BJ26: ='LCFS Table'!$AZ26*'LCFS Table'!$CD26 -> 1 | BK26: ='LCFS Table'!$BA26*'LCFS Table'!$CE26 -> 0.702 | BL26: ='LCFS Table'!$BB26*'LCFS Table'!$CF26 -> -1.2 | BM26: ='LCFS Table'!$AS26*'LCFS Table'!$CG26 -> 0 | BN26: ='LCFS Table'!$AT26*'LCFS Table'!$CH26 -> 0.16 | BO26: ='LCFS Table'!$AU26*'LCFS Table'!$CI26 -> 0 | BP26: ='LCFS Table'!$AV26*'LCFS Table'!$CJ26 -> 0 | BQ26: ='LCFS Table'!$AW26*'LCFS Table'!$CK26 -> 0 | BR26: ='LCFS Table'!$AX26*'LCFS Table'!$CL26 -> 0 | BS26: ='LCFS Table'!$AY26*'LCFS Table'!$CM26 -> 0 | BT26: ='LCFS Table'!$AZ26*'LCFS Table'!$CN26 -> 0 | BU26: ='LCFS Table'!$BA26*'LCFS Table'!$CO26 -> 0 | BV26: ='LCFS Table'!$BB26*'LCFS Table'!$CP26 -> 1.2 | BW26: 1 | BX26: 0 | BY26: 1 | BZ26: 1 | CA26: -1 | CB26: 1 | CC26: 0 | CD26: 1 | CE26: 1 | CF26: -1 | CG26: =1-'LCFS Table'!$BW26 -> 0 | CH26: =1-'LCFS Table'!$BX26 -> 1 | CI26: =1-'LCFS Table'!$BY26 -> 0 | CJ26: =1-'LCFS Table'!$BZ26 -> 0 | CK26: =-'LCFS Table'!$CA26 -> 1 | CL26: =1-'LCFS Table'!$CB26 -> 0 | CM26: =1-'LCFS Table'!$CC26 -> 1 | CN26: =1-'LCFS Table'!$CD26 -> 0 | CO26: =1-'LCFS Table'!$CE26 -> 0 | CP26: =-'LCFS Table'!$CF26 -> 1 | CQ26: 5.5 | CR26: =('LCFS Table'!$CQ26*0.9/(0.8/0.99)/100) -> 0.06125625 | CW26: ='LCFS Table'!$K26-'LCFS Table'!$M26 -> 1.4831977 | CX26: =MONTH('LCFS Table'!$B26) -> 6 | CY26: =YEAR('LCFS Table'!$B26) -> 2019
A27: ='LCFS Table'!$B27-5 -> 43632 | B27: 43637 | C27: =YEAR(B27) -> 2019 | D27: W25 | E27: ='LCFS Table'!$K27-'LCFS Table'!$I27 -> -0.93020069 | F27: =('LCFS Table'!$M27)-'LCFS Table'!$J27 -> -2.7207061 | G27: ='LCFS Table'!$E27+'LCFS Table'!$AS27+'LCFS Table'!$AT27+'LCFS Table'!$AU27+'LCFS Table'!$AV27 -> 2.6664971 | H27: ='LCFS Table'!$F27+'LCFS Table'!$AX27+'LCFS Table'!$AY27+'LCFS Table'!$AZ27+'LCFS Table'!$BA27+('LCFS Table'!$CQ27*0.9/(0.8/0.99)/100)+(DG27*'LCFS Table'!$AF27)+(DF27*'LCFS Table'!$AG27) -> 0.16109883 | I27: =('LCFS Table'!$V27+'LCFS Table'!$W27+'LCFS Table'!$X27)/100+(('LCFS Table'!$AI27+'LCFS Table'!$AJ27)/340) -> 2.8403007 | J27: =(('LCFS Table'!$Y27+'LCFS Table'!$Z27)/100)+(('LCFS Table'!$AM27+'LCFS Table'!$AN27)/300) -> 3.1931574 | K27: ='[1]Fuel Values'!$C26 -> 1.9101 | L27: ='[1]Fuel Values'!$B26 -> 329.3 | M27: =('LCFS Table'!$L27/100)-'LCFS Table'!$AX27-'LCFS Table'!$AY27-'LCFS Table'!$AZ27-'LCFS Table'!$BA27 -> 0.47245132 | N27: =[1]BFT!$B26 -> 29.25 | O27: =[1]UCO!$B26 -> 25.75 | P27: =[1]DCO!$B26 -> 25.45 | Q27: ='[1]Soybean Oil'!$B26 -> 31.914 | R27: ='[1]Yellow Grease'!$B26 -> 24 | S27: ='LCFS Table'!$N27 + 'LCFS Table'!$AH27 -> 33.625 | T27: ='LCFS Table'!$Q27+'LCFS Table'!$AH27 -> 36.289 | U27: ='LCFS Table'!$P27+'LCFS Table'!$AH27 -> 29.825 | V27: =(('LCFS Table'!$S27/'LCFS Table'!$AA27)*'LCFS Table'!$AC27)*6.48 -> 115.89894 | W27: =(('LCFS Table'!$O27/'LCFS Table'!$AA27)*'LCFS Table'!$AD27)*6.48 -> 44.37766 | X27: =(('LCFS Table'!$U27/'LCFS Table'!$AA27)*'LCFS Table'!$AE27)*6.48 -> 51.400532 | Y27: =(('LCFS Table'!$T27/'LCFS Table'!$AB27)*'LCFS Table'!$AF27)*7.35 -> 208.37824 | Z27: =(('LCFS Table'!$R27/'LCFS Table'!$AB27)*'LCFS Table'!$AG27)*7.35 -> 45.9375 | AA27: 0.94 | AB27: 0.96 | AC27: 0.5 | AD27: 0.25 | AE27: 0.25 | AF27: 0.75 | AG27: 0.25 | AH27: 4.375 | AI27: 136 | AJ27: 110 | AK27: =('LCFS Table'!$AI27/340)*100 -> 40 | AL27: =('LCFS Table'!$AJ27/340)*100 -> 32.352941 | AM27: 105 | AN27: 90 | AO27: =('LCFS Table'!$AM27/300)*100 -> 35 | AP27: =('LCFS Table'!$AN27/300)*100 -> 30 | AQ27: 193.1 | AR27: 0.434 | AS27: 1.6988978 | AT27: 0.16 | AU27: 1 | AV27: ='LCFS Table'!$AR27*1.7 -> 0.7378 | AW27: 0 | AX27: 1.1695487 | AY27: 0 | AZ27: 1 | BA27: ='LCFS Table'!$AR27*1.5 -> 0.651 | BB27: 1.2 | BC27: ='LCFS Table'!$AS27*'LCFS Table'!$BW27 -> 1.6988978 | BD27: ='LCFS Table'!$AT27*'LCFS Table'!$BX27 -> 0 | BE27: ='LCFS Table'!$AU27*'LCFS Table'!$BY27 -> 1 | BF27: ='LCFS Table'!$AV27*'LCFS Table'!$BZ27 -> 0.7378 | BG27: ='LCFS Table'!$AW27*'LCFS Table'!$CA27 -> 0 | BH27: ='LCFS Table'!$AX27*'LCFS Table'!$CB27 -> 1.1695487 | BI27: ='LCFS Table'!$AY27*'LCFS Table'!$CC27 -> 0 | BJ27: ='LCFS Table'!$AZ27*'LCFS Table'!$CD27 -> 1 | BK27: ='LCFS Table'!$BA27*'LCFS Table'!$CE27 -> 0.651 | BL27: ='LCFS Table'!$BB27*'LCFS Table'!$CF27 -> -1.2 | BM27: ='LCFS Table'!$AS27*'LCFS Table'!$CG27 -> 0 | BN27: ='LCFS Table'!$AT27*'LCFS Table'!$CH27 -> 0.16 | BO27: ='LCFS Table'!$AU27*'LCFS Table'!$CI27 -> 0 | BP27: ='LCFS Table'!$AV27*'LCFS Table'!$CJ27 -> 0 | BQ27: ='LCFS Table'!$AW27*'LCFS Table'!$CK27 -> 0 | BR27: ='LCFS Table'!$AX27*'LCFS Table'!$CL27 -> 0 | BS27: ='LCFS Table'!$AY27*'LCFS Table'!$CM27 -> 0 | BT27: ='LCFS Table'!$AZ27*'LCFS Table'!$CN27 -> 0 | BU27: ='LCFS Table'!$BA27*'LCFS Table'!$CO27 -> 0 | BV27: ='LCFS Table'!$BB27*'LCFS Table'!$CP27 -> 1.2 | BW27: 1 | BX27: 0 | BY27: 1 | BZ27: 1 | CA27: -1 | CB27: 1 | CC27: 0 | CD27: 1 | CE27: 1 | CF27: -1 | CG27: =1-'LCFS Table'!$BW27 -> 0 | CH27: =1-'LCFS Table'!$BX27 -> 1 | CI27: =1-'LCFS Table'!$BY27 -> 0 | CJ27: =1-'LCFS Table'!$BZ27 -> 0 | CK27: =-'LCFS Table'!$CA27 -> 1 | CL27: =1-'LCFS Table'!$CB27 -> 0 | CM27: =1-'LCFS Table'!$CC27 -> 1 | CN27: =1-'LCFS Table'!$CD27 -> 0 | CO27: =1-'LCFS Table'!$CE27 -> 0 | CP27: =-'LCFS Table'!$CF27 -> 1 | CQ27: 5.5 | CR27: =('LCFS Table'!$CQ27*0.9/(0.8/0.99)/100) -> 0.06125625 | CW27: ='LCFS Table'!$K27-'LCFS Table'!$M27 -> 1.4376487 | CX27: =MONTH('LCFS Table'!$B27) -> 6 | CY27: =YEAR('LCFS Table'!$B27) -> 2019
A28: ='LCFS Table'!$B28-5 -> 43639 | B28: 43644 | C28: =YEAR(B28) -> 2019 | D28: W26 | E28: ='LCFS Table'!$K28-'LCFS Table'!$I28 -> -0.89795601 | F28: =('LCFS Table'!$M28)-'LCFS Table'!$J28 -> -2.680724 | G28: ='LCFS Table'!$E28+'LCFS Table'!$AS28+'LCFS Table'!$AT28+'LCFS Table'!$AU28+'LCFS Table'!$AV28 -> 2.691658 | H28: ='LCFS Table'!$F28+'LCFS Table'!$AX28+'LCFS Table'!$AY28+'LCFS Table'!$AZ28+'LCFS Table'!$BA28+('LCFS Table'!$CQ28*0.9/(0.8/0.99)/100)+(DG28*'LCFS Table'!$AF28)+(DF28*'LCFS Table'!$AG28) -> 0.19047492 | I28: =('LCFS Table'!$V28+'LCFS Table'!$W28+'LCFS Table'!$X28)/100+(('LCFS Table'!$AI28+'LCFS Table'!$AJ28)/340) -> 2.848056 | J28: =(('LCFS Table'!$Y28+'LCFS Table'!$Z28)/100)+(('LCFS Table'!$AM28+'LCFS Table'!$AN28)/300) -> 3.1746676 | K28: ='[1]Fuel Values'!$C27 -> 1.9501 | L28: ='[1]Fuel Values'!$B27 -> 330.5 | M28: =('LCFS Table'!$L28/100)-'LCFS Table'!$AX28-'LCFS Table'!$AY28-'LCFS Table'!$AZ28-'LCFS Table'!$BA28 -> 0.49394359 | N28: =[1]BFT!$B27 -> 29.25 | O28: =[1]UCO!$B27 -> 25.75 | P28: =[1]DCO!$B27 -> 25.9 | Q28: ='[1]Soybean Oil'!$B27 -> 31.592 | R28: ='[1]Yellow Grease'!$B27 -> 24 | S28: ='LCFS Table'!$N28 + 'LCFS Table'!$AH28 -> 33.625 | T28: ='LCFS Table'!$Q28+'LCFS Table'!$AH28 -> 35.967 | U28: ='LCFS Table'!$P28+'LCFS Table'!$AH28 -> 30.275 | V28: =(('LCFS Table'!$S28/'LCFS Table'!$AA28)*'LCFS Table'!$AC28)*6.48 -> 115.89894 | W28: =(('LCFS Table'!$O28/'LCFS Table'!$AA28)*'LCFS Table'!$AD28)*6.48 -> 44.37766 | X28: =(('LCFS Table'!$U28/'LCFS Table'!$AA28)*'LCFS Table'!$AE28)*6.48 -> 52.176064 | Y28: =(('LCFS Table'!$T28/'LCFS Table'!$AB28)*'LCFS Table'!$AF28)*7.35 -> 206.52926 | Z28: =(('LCFS Table'!$R28/'LCFS Table'!$AB28)*'LCFS Table'!$AG28)*7.35 -> 45.9375 | AA28: 0.94 | AB28: 0.96 | AC28: 0.5 | AD28: 0.25 | AE28: 0.25 | AF28: 0.75 | AG28: 0.25 | AH28: 4.375 | AI28: 136 | AJ28: 110 | AK28: =('LCFS Table'!$AI28/340)*100 -> 40 | AL28: =('LCFS Table'!$AJ28/340)*100 -> 32.352941 | AM28: 105 | AN28: 90 | AO28: =('LCFS Table'!$AM28/300)*100 -> 35 | AP28: =('LCFS Table'!$AN28/300)*100 -> 30 | AQ28: 195 | AR28: 0.42 | AS28: 1.715614 | AT28: 0.16 | AU28: 1 | AV28: ='LCFS Table'!$AR28*1.7 -> 0.714 | AW28: 0 | AX28: 1.1810564 | AY28: 0 | AZ28: 1 | BA28: ='LCFS Table'!$AR28*1.5 -> 0.63 | BB28: 1.2 | BC28: ='LCFS Table'!$AS28*'LCFS Table'!$BW28 -> 1.715614 | BD28: ='LCFS Table'!$AT28*'LCFS Table'!$BX28 -> 0 | BE28: ='LCFS Table'!$AU28*'LCFS Table'!$BY28 -> 1 | BF28: ='LCFS Table'!$AV28*'LCFS Table'!$BZ28 -> 0.714 | BG28: ='LCFS Table'!$AW28*'LCFS Table'!$CA28 -> 0 | BH28: ='LCFS Table'!$AX28*'LCFS Table'!$CB28 -> 1.1810564 | BI28: ='LCFS Table'!$AY28*'LCFS Table'!$CC28 -> 0 | BJ28: ='LCFS Table'!$AZ28*'LCFS Table'!$CD28 -> 1 | BK28: ='LCFS Table'!$BA28*'LCFS Table'!$CE28 -> 0.63 | BL28: ='LCFS Table'!$BB28*'LCFS Table'!$CF28 -> -1.2 | BM28: ='LCFS Table'!$AS28*'LCFS Table'!$CG28 -> 0 | BN28: ='LCFS Table'!$AT28*'LCFS Table'!$CH28 -> 0.16 | BO28: ='LCFS Table'!$AU28*'LCFS Table'!$CI28 -> 0 | BP28: ='LCFS Table'!$AV28*'LCFS Table'!$CJ28 -> 0 | BQ28: ='LCFS Table'!$AW28*'LCFS Table'!$CK28 -> 0 | BR28: ='LCFS Table'!$AX28*'LCFS Table'!$CL28 -> 0 | BS28: ='LCFS Table'!$AY28*'LCFS Table'!$CM28 -> 0 | BT28: ='LCFS Table'!$AZ28*'LCFS Table'!$CN28 -> 0 | BU28: ='LCFS Table'!$BA28*'LCFS Table'!$CO28 -> 0 | BV28: ='LCFS Table'!$BB28*'LCFS Table'!$CP28 -> 1.2 | BW28: 1 | BX28: 0 | BY28: 1 | BZ28: 1 | CA28: -1 | CB28: 1 | CC28: 0 | CD28: 1 | CE28: 1 | CF28: -1 | CG28: =1-'LCFS Table'!$BW28 -> 0 | CH28: =1-'LCFS Table'!$BX28 -> 1 | CI28: =1-'LCFS Table'!$BY28 -> 0 | CJ28: =1-'LCFS Table'!$BZ28 -> 0 | CK28: =-'LCFS Table'!$CA28 -> 1 | CL28: =1-'LCFS Table'!$CB28 -> 0 | CM28: =1-'LCFS Table'!$CC28 -> 1 | CN28: =1-'LCFS Table'!$CD28 -> 0 | CO28: =1-'LCFS Table'!$CE28 -> 0 | CP28: =-'LCFS Table'!$CF28 -> 1 | CQ28: 5.4 | CR28: =('LCFS Table'!$CQ28*0.9/(0.8/0.99)/100) -> 0.0601425 | CW28: ='LCFS Table'!$K28-'LCFS Table'!$M28 -> 1.4561564 | CX28: =MONTH('LCFS Table'!$B28) -> 6 | CY28: =YEAR('LCFS Table'!$B28) -> 2019
A29: ='LCFS Table'!$B29-5 -> 43646 | B29: 43651 | C29: =YEAR(B29) -> 2019 | D29: W27 | E29: ='LCFS Table'!$K29-'LCFS Table'!$I29 -> -0.92877941 | F29: =('LCFS Table'!$M29)-'LCFS Table'!$J29 -> -2.6550827 | G29: ='LCFS Table'!$E29+'LCFS Table'!$AS29+'LCFS Table'!$AT29+'LCFS Table'!$AU29+'LCFS Table'!$AV29 -> 2.6435508 | H29: ='LCFS Table'!$F29+'LCFS Table'!$AX29+'LCFS Table'!$AY29+'LCFS Table'!$AZ29+'LCFS Table'!$BA29+('LCFS Table'!$CQ29*0.9/(0.8/0.99)/100)+(DG29*'LCFS Table'!$AF29)+(DF29*'LCFS Table'!$AG29) -> 0.19316895 | I29: =('LCFS Table'!$V29+'LCFS Table'!$W29+'LCFS Table'!$X29)/100+(('LCFS Table'!$AI29+'LCFS Table'!$AJ29)/340) -> 2.8497794 | J29: =(('LCFS Table'!$Y29+'LCFS Table'!$Z29)/100)+(('LCFS Table'!$AM29+'LCFS Table'!$AN29)/300) -> 3.1675186 | K29: ='[1]Fuel Values'!$C28 -> 1.921 | L29: ='[1]Fuel Values'!$B28 -> 330.5 | M29: =('LCFS Table'!$L29/100)-'LCFS Table'!$AX29-'LCFS Table'!$AY29-'LCFS Table'!$AZ29-'LCFS Table'!$BA29 -> 0.51243586 | N29: =[1]BFT!$B28 -> 29.25 | O29: =[1]UCO!$B28 -> 25.75 | P29: =[1]DCO!$B28 -> 26 | Q29: ='[1]Soybean Oil'!$B28 -> 31.4675 | R29: ='[1]Yellow Grease'!$B28 -> 24 | S29: ='LCFS Table'!$N29 + 'LCFS Table'!$AH29 -> 33.625 | T29: ='LCFS Table'!$Q29+'LCFS Table'!$AH29 -> 35.8425 | U29: ='LCFS Table'!$P29+'LCFS Table'!$AH29 -> 30.375 | V29: =(('LCFS Table'!$S29/'LCFS Table'!$AA29)*'LCFS Table'!$AC29)*6.48 -> 115.89894 | W29: =(('LCFS Table'!$O29/'LCFS Table'!$AA29)*'LCFS Table'!$AD29)*6.48 -> 44.37766 | X29: =(('LCFS Table'!$U29/'LCFS Table'!$AA29)*'LCFS Table'!$AE29)*6.48 -> 52.348404 | Y29: =(('LCFS Table'!$T29/'LCFS Table'!$AB29)*'LCFS Table'!$AF29)*7.35 -> 205.81436 | Z29: =(('LCFS Table'!$R29/'LCFS Table'!$AB29)*'LCFS Table'!$AG29)*7.35 -> 45.9375 | AA29: 0.94 | AB29: 0.96 | AC29: 0.5 | AD29: 0.25 | AE29: 0.25 | AF29: 0.75 | AG29: 0.25 | AH29: 4.375 | AI29: 136 | AJ29: 110 | AK29: =('LCFS Table'!$AI29/340)*100 -> 40 | AL29: =('LCFS Table'!$AJ29/340)*100 -> 32.352941 | AM29: 105 | AN29: 90 | AO29: =('LCFS Table'!$AM29/300)*100 -> 35 | AP29: =('LCFS Table'!$AN29/300)*100 -> 30 | AQ29: 196.9 | AR29: 0.4 | AS29: 1.7323302 | AT29: 0.16 | AU29: 1 | AV29: ='LCFS Table'!$AR29*1.7 -> 0.68 | AW29: 0 | AX29: 1.1925641 | AY29: 0 | AZ29: 1 | BA29: ='LCFS Table'!$AR29*1.5 -> 0.6 | BB29: 1.2 | BC29: ='LCFS Table'!$AS29*'LCFS Table'!$BW29 -> 1.7323302 | BD29: ='LCFS Table'!$AT29*'LCFS Table'!$BX29 -> 0 | BE29: ='LCFS Table'!$AU29*'LCFS Table'!$BY29 -> 1 | BF29: ='LCFS Table'!$AV29*'LCFS Table'!$BZ29 -> 0.68 | BG29: ='LCFS Table'!$AW29*'LCFS Table'!$CA29 -> 0 | BH29: ='LCFS Table'!$AX29*'LCFS Table'!$CB29 -> 1.1925641 | BI29: ='LCFS Table'!$AY29*'LCFS Table'!$CC29 -> 0 | BJ29: ='LCFS Table'!$AZ29*'LCFS Table'!$CD29 -> 1 | BK29: ='LCFS Table'!$BA29*'LCFS Table'!$CE29 -> 0.6 | BL29: ='LCFS Table'!$BB29*'LCFS Table'!$CF29 -> -1.2 | BM29: ='LCFS Table'!$AS29*'LCFS Table'!$CG29 -> 0 | BN29: ='LCFS Table'!$AT29*'LCFS Table'!$CH29 -> 0.16 | BO29: ='LCFS Table'!$AU29*'LCFS Table'!$CI29 -> 0 | BP29: ='LCFS Table'!$AV29*'LCFS Table'!$CJ29 -> 0 | BQ29: ='LCFS Table'!$AW29*'LCFS Table'!$CK29 -> 0 | BR29: ='LCFS Table'!$AX29*'LCFS Table'!$CL29 -> 0 | BS29: ='LCFS Table'!$AY29*'LCFS Table'!$CM29 -> 0 | BT29: ='LCFS Table'!$AZ29*'LCFS Table'!$CN29 -> 0 | BU29: ='LCFS Table'!$BA29*'LCFS Table'!$CO29 -> 0 | BV29: ='LCFS Table'!$BB29*'LCFS Table'!$CP29 -> 1.2 | BW29: 1 | BX29: 0 | BY29: 1 | BZ29: 1 | CA29: -1 | CB29: 1 | CC29: 0 | CD29: 1 | CE29: 1 | CF29: -1 | CG29: =1-'LCFS Table'!$BW29 -> 0 | CH29: =1-'LCFS Table'!$BX29 -> 1 | CI29: =1-'LCFS Table'!$BY29 -> 0 | CJ29: =1-'LCFS Table'!$BZ29 -> 0 | CK29: =-'LCFS Table'!$CA29 -> 1 | CL29: =1-'LCFS Table'!$CB29 -> 0 | CM29: =1-'LCFS Table'!$CC29 -> 1 | CN29: =1-'LCFS Table'!$CD29 -> 0 | CO29: =1-'LCFS Table'!$CE29 -> 0 | CP29: =-'LCFS Table'!$CF29 -> 1 | CQ29: 5 | CR29: =('LCFS Table'!$CQ29*0.9/(0.8/0.99)/100) -> 0.0556875 | CW29: ='LCFS Table'!$K29-'LCFS Table'!$M29 -> 1.4085641 | CX29: =MONTH('LCFS Table'!$B29) -> 7 | CY29: =YEAR('LCFS Table'!$B29) -> 2019
A30: ='LCFS Table'!$B30-5 -> 43653 | B30: 43658 | C30: =YEAR(B30) -> 2019 | D30: W28 | E30: ='LCFS Table'!$K30-'LCFS Table'!$I30 -> -0.90793686 | F30: =('LCFS Table'!$M30)-'LCFS Table'!$J30 -> -2.6802103 | G30: ='LCFS Table'!$E30+'LCFS Table'!$AS30+'LCFS Table'!$AT30+'LCFS Table'!$AU30+'LCFS Table'!$AV30 -> 2.6894606 | H30: ='LCFS Table'!$F30+'LCFS Table'!$AX30+'LCFS Table'!$AY30+'LCFS Table'!$AZ30+'LCFS Table'!$BA30+('LCFS Table'!$CQ30*0.9/(0.8/0.99)/100)+(DG30*'LCFS Table'!$AF30)+(DF30*'LCFS Table'!$AG30) -> 0.1877707 | I30: =('LCFS Table'!$V30+'LCFS Table'!$W30+'LCFS Table'!$X30)/100+(('LCFS Table'!$AI30+'LCFS Table'!$AJ30)/340) -> 2.8687369 | J30: =(('LCFS Table'!$Y30+'LCFS Table'!$Z30)/100)+(('LCFS Table'!$AM30+'LCFS Table'!$AN30)/300) -> 3.1789168 | K30: ='[1]Fuel Values'!$C29 -> 1.9608 | L30: ='[1]Fuel Values'!$B29 -> 331.1 | M30: =('LCFS Table'!$L30/100)-'LCFS Table'!$AX30-'LCFS Table'!$AY30-'LCFS Table'!$AZ30-'LCFS Table'!$BA30 -> 0.49870648 | N30: =[1]BFT!$B29 -> 29.8 | O30: =[1]UCO!$B29 -> 25.75 | P30: =[1]DCO!$B29 -> 26 | Q30: ='[1]Soybean Oil'!$B29 -> 31.666 | R30: ='[1]Yellow Grease'!$B29 -> 24 | S30: ='LCFS Table'!$N30 + 'LCFS Table'!$AH30 -> 34.175 | T30: ='LCFS Table'!$Q30+'LCFS Table'!$AH30 -> 36.041 | U30: ='LCFS Table'!$P30+'LCFS Table'!$AH30 -> 30.375 | V30: =(('LCFS Table'!$S30/'LCFS Table'!$AA30)*'LCFS Table'!$AC30)*6.48 -> 117.79468 | W30: =(('LCFS Table'!$O30/'LCFS Table'!$AA30)*'LCFS Table'!$AD30)*6.48 -> 44.37766 | X30: =(('LCFS Table'!$U30/'LCFS Table'!$AA30)*'LCFS Table'!$AE30)*6.48 -> 52.348404 | Y30: =(('LCFS Table'!$T30/'LCFS Table'!$AB30)*'LCFS Table'!$AF30)*7.35 -> 206.95418 | Z30: =(('LCFS Table'!$R30/'LCFS Table'!$AB30)*'LCFS Table'!$AG30)*7.35 -> 45.9375 | AA30: 0.94 | AB30: 0.96 | AC30: 0.5 | AD30: 0.25 | AE30: 0.25 | AF30: 0.75 | AG30: 0.25 | AH30: 4.375 | AI30: 136 | AJ30: 110 | AK30: =('LCFS Table'!$AI30/340)*100 -> 40 | AL30: =('LCFS Table'!$AJ30/340)*100 -> 32.352941 | AM30: 105 | AN30: 90 | AO30: =('LCFS Table'!$AM30/300)*100 -> 35 | AP30: =('LCFS Table'!$AN30/300)*100 -> 30 | AQ30: 198.3 | AR30: 0.4075 | AS30: 1.7446475 | AT30: 0.16 | AU30: 1 | AV30: ='LCFS Table'!$AR30*1.7 -> 0.69275 | AW30: 0 | AX30: 1.2010435 | AY30: 0 | AZ30: 1 | BA30: ='LCFS Table'!$AR30*1.5 -> 0.61125 | BB30: 1.2 | BC30: ='LCFS Table'!$AS30*'LCFS Table'!$BW30 -> 1.7446475 | BD30: ='LCFS Table'!$AT30*'LCFS Table'!$BX30 -> 0 | BE30: ='LCFS Table'!$AU30*'LCFS Table'!$BY30 -> 1 | BF30: ='LCFS Table'!$AV30*'LCFS Table'!$BZ30 -> 0.69275 | BG30: ='LCFS Table'!$AW30*'LCFS Table'!$CA30 -> 0 | BH30: ='LCFS Table'!$AX30*'LCFS Table'!$CB30 -> 1.2010435 | BI30: ='LCFS Table'!$AY30*'LCFS Table'!$CC30 -> 0 | BJ30: ='LCFS Table'!$AZ30*'LCFS Table'!$CD30 -> 1 | BK30: ='LCFS Table'!$BA30*'LCFS Table'!$CE30 -> 0.61125 | BL30: ='LCFS Table'!$BB30*'LCFS Table'!$CF30 -> -1.2 | BM30: ='LCFS Table'!$AS30*'LCFS Table'!$CG30 -> 0 | BN30: ='LCFS Table'!$AT30*'LCFS Table'!$CH30 -> 0.16 | BO30: ='LCFS Table'!$AU30*'LCFS Table'!$CI30 -> 0 | BP30: ='LCFS Table'!$AV30*'LCFS Table'!$CJ30 -> 0 | BQ30: ='LCFS Table'!$AW30*'LCFS Table'!$CK30 -> 0 | BR30: ='LCFS Table'!$AX30*'LCFS Table'!$CL30 -> 0 | BS30: ='LCFS Table'!$AY30*'LCFS Table'!$CM30 -> 0 | BT30: ='LCFS Table'!$AZ30*'LCFS Table'!$CN30 -> 0 | BU30: ='LCFS Table'!$BA30*'LCFS Table'!$CO30 -> 0 | BV30: ='LCFS Table'!$BB30*'LCFS Table'!$CP30 -> 1.2 | BW30: 1 | BX30: 0 | BY30: 1 | BZ30: 1 | CA30: -1 | CB30: 1 | CC30: 0 | CD30: 1 | CE30: 1 | CF30: -1 | CG30: =1-'LCFS Table'!$BW30 -> 0 | CH30: =1-'LCFS Table'!$BX30 -> 1 | CI30: =1-'LCFS Table'!$BY30 -> 0 | CJ30: =1-'LCFS Table'!$BZ30 -> 0 | CK30: =-'LCFS Table'!$CA30 -> 1 | CL30: =1-'LCFS Table'!$CB30 -> 0 | CM30: =1-'LCFS Table'!$CC30 -> 1 | CN30: =1-'LCFS Table'!$CD30 -> 0 | CO30: =1-'LCFS Table'!$CE30 -> 0 | CP30: =-'LCFS Table'!$CF30 -> 1 | CQ30: 5 | CR30: =('LCFS Table'!$CQ30*0.9/(0.8/0.99)/100) -> 0.0556875 | CW30: ='LCFS Table'!$K30-'LCFS Table'!$M30 -> 1.4620935 | CX30: =MONTH('LCFS Table'!$B30) -> 7 | CY30: =YEAR('LCFS Table'!$B30) -> 2019
A31: ='LCFS Table'!$B31-5 -> 43660 | B31: 43665 | C31: =YEAR(B31) -> 2019 | D31: W29 | E31: ='LCFS Table'!$K31-'LCFS Table'!$I31 -> -0.98094111 | F31: =('LCFS Table'!$M31)-'LCFS Table'!$J31 -> -2.7097843 | G31: ='LCFS Table'!$E31+'LCFS Table'!$AS31+'LCFS Table'!$AT31+'LCFS Table'!$AU31+'LCFS Table'!$AV31 -> 2.67158 | H31: ='LCFS Table'!$F31+'LCFS Table'!$AX31+'LCFS Table'!$AY31+'LCFS Table'!$AZ31+'LCFS Table'!$BA31+('LCFS Table'!$CQ31*0.9/(0.8/0.99)/100)+(DG31*'LCFS Table'!$AF31)+(DF31*'LCFS Table'!$AG31) -> 0.2099918 | I31: =('LCFS Table'!$V31+'LCFS Table'!$W31+'LCFS Table'!$X31)/100+(('LCFS Table'!$AI31+'LCFS Table'!$AJ31)/340) -> 2.8911411 | J31: =(('LCFS Table'!$Y31+'LCFS Table'!$Z31)/100)+(('LCFS Table'!$AM31+'LCFS Table'!$AN31)/300) -> 3.1686957 | K31: ='[1]Fuel Values'!$C30 -> 1.9102 | L31: ='[1]Fuel Values'!$B30 -> 332.3 | M31: =('LCFS Table'!$L31/100)-'LCFS Table'!$AX31-'LCFS Table'!$AY31-'LCFS Table'!$AZ31-'LCFS Table'!$BA31 -> 0.45891138 | N31: =[1]BFT!$B30 -> 30.7 | O31: =[1]UCO!$B30 -> 25.75 | P31: =[1]DCO!$B30 -> 25.5 | Q31: ='[1]Soybean Oil'!$B30 -> 31.488 | R31: ='[1]Yellow Grease'!$B30 -> 24 | S31: ='LCFS Table'!$N31 + 'LCFS Table'!$AH31 -> 35.075 | T31: ='LCFS Table'!$Q31+'LCFS Table'!$AH31 -> 35.863 | U31: ='LCFS Table'!$P31+'LCFS Table'!$AH31 -> 29.875 | V31: =(('LCFS Table'!$S31/'LCFS Table'!$AA31)*'LCFS Table'!$AC31)*6.48 -> 120.89681 | W31: =(('LCFS Table'!$O31/'LCFS Table'!$AA31)*'LCFS Table'!$AD31)*6.48 -> 44.37766 | X31: =(('LCFS Table'!$U31/'LCFS Table'!$AA31)*'LCFS Table'!$AE31)*6.48 -> 51.486702 | Y31: =(('LCFS Table'!$T31/'LCFS Table'!$AB31)*'LCFS Table'!$AF31)*7.35 -> 205.93207 | Z31: =(('LCFS Table'!$R31/'LCFS Table'!$AB31)*'LCFS Table'!$AG31)*7.35 -> 45.9375 | AA31: 0.94 | AB31: 0.96 | AC31: 0.5 | AD31: 0.25 | AE31: 0.25 | AF31: 0.75 | AG31: 0.25 | AH31: 4.375 | AI31: 136 | AJ31: 110 | AK31: =('LCFS Table'!$AI31/340)*100 -> 40 | AL31: =('LCFS Table'!$AJ31/340)*100 -> 32.352941 | AM31: 105 | AN31: 90 | AO31: =('LCFS Table'!$AM31/300)*100 -> 35 | AP31: =('LCFS Table'!$AN31/300)*100 -> 30 | AQ31: 196.45 | AR31: 0.4495 | AS31: 1.7283711 | AT31: 0.16 | AU31: 1 | AV31: ='LCFS Table'!$AR31*1.7 -> 0.76415 | AW31: 0 | AX31: 1.1898386 | AY31: 0 | AZ31: 1 | BA31: ='LCFS Table'!$AR31*1.5 -> 0.67425 | BB31: 1.2 | BC31: ='LCFS Table'!$AS31*'LCFS Table'!$BW31 -> 1.7283711 | BD31: ='LCFS Table'!$AT31*'LCFS Table'!$BX31 -> 0 | BE31: ='LCFS Table'!$AU31*'LCFS Table'!$BY31 -> 1 | BF31: ='LCFS Table'!$AV31*'LCFS Table'!$BZ31 -> 0.76415 | BG31: ='LCFS Table'!$AW31*'LCFS Table'!$CA31 -> 0 | BH31: ='LCFS Table'!$AX31*'LCFS Table'!$CB31 -> 1.1898386 | BI31: ='LCFS Table'!$AY31*'LCFS Table'!$CC31 -> 0 | BJ31: ='LCFS Table'!$AZ31*'LCFS Table'!$CD31 -> 1 | BK31: ='LCFS Table'!$BA31*'LCFS Table'!$CE31 -> 0.67425 | BL31: ='LCFS Table'!$BB31*'LCFS Table'!$CF31 -> -1.2 | BM31: ='LCFS Table'!$AS31*'LCFS Table'!$CG31 -> 0 | BN31: ='LCFS Table'!$AT31*'LCFS Table'!$CH31 -> 0.16 | BO31: ='LCFS Table'!$AU31*'LCFS Table'!$CI31 -> 0 | BP31: ='LCFS Table'!$AV31*'LCFS Table'!$CJ31 -> 0 | BQ31: ='LCFS Table'!$AW31*'LCFS Table'!$CK31 -> 0 | BR31: ='LCFS Table'!$AX31*'LCFS Table'!$CL31 -> 0 | BS31: ='LCFS Table'!$AY31*'LCFS Table'!$CM31 -> 0 | BT31: ='LCFS Table'!$AZ31*'LCFS Table'!$CN31 -> 0 | BU31: ='LCFS Table'!$BA31*'LCFS Table'!$CO31 -> 0 | BV31: ='LCFS Table'!$BB31*'LCFS Table'!$CP31 -> 1.2 | BW31: 1 | BX31: 0 | BY31: 1 | BZ31: 1 | CA31: -1 | CB31: 1 | CC31: 0 | CD31: 1 | CE31: 1 | CF31: -1 | CG31: =1-'LCFS Table'!$BW31 -> 0 | CH31: =1-'LCFS Table'!$BX31 -> 1 | CI31: =1-'LCFS Table'!$BY31 -> 0 | CJ31: =1-'LCFS Table'!$BZ31 -> 0 | CK31: =-'LCFS Table'!$CA31 -> 1 | CL31: =1-'LCFS Table'!$CB31 -> 0 | CM31: =1-'LCFS Table'!$CC31 -> 1 | CN31: =1-'LCFS Table'!$CD31 -> 0 | CO31: =1-'LCFS Table'!$CE31 -> 0 | CP31: =-'LCFS Table'!$CF31 -> 1 | CQ31: 5 | CR31: =('LCFS Table'!$CQ31*0.9/(0.8/0.99)/100) -> 0.0556875 | CW31: ='LCFS Table'!$K31-'LCFS Table'!$M31 -> 1.4512886 | CX31: =MONTH('LCFS Table'!$B31) -> 7 | CY31: =YEAR('LCFS Table'!$B31) -> 2019
A32: 43667 | B32: 43673 | C32: =YEAR(B32) -> 2019 | D32: W30 | E32: ='LCFS Table'!$K32-'LCFS Table'!$I32 -> -0.97747303 | F32: =('LCFS Table'!$M32)-'LCFS Table'!$J32 -> -2.6803075 | G32: ='LCFS Table'!$E32+'LCFS Table'!$AS32+'LCFS Table'!$AT32+'LCFS Table'!$AU32+'LCFS Table'!$AV32 -> 2.6838688 | H32: ='LCFS Table'!$F32+'LCFS Table'!$AX32+'LCFS Table'!$AY32+'LCFS Table'!$AZ32+'LCFS Table'!$BA32+('LCFS Table'!$CQ32*0.9/(0.8/0.99)/100)+(DG32*'LCFS Table'!$AF32)+(DF32*'LCFS Table'!$AG32) -> 0.24784883 | I32: =('LCFS Table'!$V32+'LCFS Table'!$W32+'LCFS Table'!$X32)/100+(('LCFS Table'!$AI32+'LCFS Table'!$AJ32)/340) -> 2.897173 | J32: =(('LCFS Table'!$Y32+'LCFS Table'!$Z32)/100)+(('LCFS Table'!$AM32+'LCFS Table'!$AN32)/300) -> 3.1628387 | K32: ='[1]Fuel Values'!$C31 -> 1.9197 | L32: ='[1]Fuel Values'!$B31 -> 335.5 | M32: =('LCFS Table'!$L32/100)-'LCFS Table'!$AX32-'LCFS Table'!$AY32-'LCFS Table'!$AZ32-'LCFS Table'!$BA32 -> 0.48253122 | N32: =[1]BFT!$B31 -> 31 | O32: =[1]UCO!$B31 -> 25.75 | P32: =[1]DCO!$B31 -> 25.25 | Q32: ='[1]Soybean Oil'!$B31 -> 31.386 | R32: ='[1]Yellow Grease'!$B31 -> 24 | S32: ='LCFS Table'!$N32 + 'LCFS Table'!$AH32 -> 35.375 | T32: ='LCFS Table'!$Q32+'LCFS Table'!$AH32 -> 35.761 | U32: ='LCFS Table'!$P32+'LCFS Table'!$AH32 -> 29.625 | V32: =(('LCFS Table'!$S32/'LCFS Table'!$AA32)*'LCFS Table'!$AC32)*6.48 -> 121.93085 | W32: =(('LCFS Table'!$O32/'LCFS Table'!$AA32)*'LCFS Table'!$AD32)*6.48 -> 44.37766 | X32: =(('LCFS Table'!$U32/'LCFS Table'!$AA32)*'LCFS Table'!$AE32)*6.48 -> 51.055851 | Y32: =(('LCFS Table'!$T32/'LCFS Table'!$AB32)*'LCFS Table'!$AF32)*7.35 -> 205.34637 | Z32: =(('LCFS Table'!$R32/'LCFS Table'!$AB32)*'LCFS Table'!$AG32)*7.35 -> 45.9375 | AA32: 0.94 | AB32: 0.96 | AC32: 0.5 | AD32: 0.25 | AE32: 0.25 | AF32: 0.75 | AG32: 0.25 | AH32: 4.375 | AI32: 136 | AJ32: 110 | AK32: =('LCFS Table'!$AI32/340)*100 -> 40 | AL32: =('LCFS Table'!$AJ32/340)*100 -> 32.352941 | AM32: 105 | AN32: 90 | AO32: =('LCFS Table'!$AM32/300)*100 -> 35 | AP32: =('LCFS Table'!$AN32/300)*100 -> 30 | AQ32: 196.1 | AR32: 0.4565 | AS32: 1.7252918 | AT32: 0.16 | AU32: 1 | AV32: ='LCFS Table'!$AR32*1.7 -> 0.77605 | AW32: 0 | AX32: 1.1877188 | AY32: 0 | AZ32: 1 | BA32: ='LCFS Table'!$AR32*1.5 -> 0.68475 | BB32: 1.2 | BC32: ='LCFS Table'!$AS32*'LCFS Table'!$BW32 -> 1.7252918 | BD32: ='LCFS Table'!$AT32*'LCFS Table'!$BX32 -> 0 | BE32: ='LCFS Table'!$AU32*'LCFS Table'!$BY32 -> 1 | BF32: ='LCFS Table'!$AV32*'LCFS Table'!$BZ32 -> 0.77605 | BG32: ='LCFS Table'!$AW32*'LCFS Table'!$CA32 -> 0 | BH32: ='LCFS Table'!$AX32*'LCFS Table'!$CB32 -> 1.1877188 | BI32: ='LCFS Table'!$AY32*'LCFS Table'!$CC32 -> 0 | BJ32: ='LCFS Table'!$AZ32*'LCFS Table'!$CD32 -> 1 | BK32: ='LCFS Table'!$BA32*'LCFS Table'!$CE32 -> 0.68475 | BL32: ='LCFS Table'!$BB32*'LCFS Table'!$CF32 -> -1.2 | BM32: ='LCFS Table'!$AS32*'LCFS Table'!$CG32 -> 0 | BN32: ='LCFS Table'!$AT32*'LCFS Table'!$CH32 -> 0.16 | BO32: ='LCFS Table'!$AU32*'LCFS Table'!$CI32 -> 0 | BP32: ='LCFS Table'!$AV32*'LCFS Table'!$CJ32 -> 0 | BQ32: ='LCFS Table'!$AW32*'LCFS Table'!$CK32 -> 0 | BR32: ='LCFS Table'!$AX32*'LCFS Table'!$CL32 -> 0 | BS32: ='LCFS Table'!$AY32*'LCFS Table'!$CM32 -> 0 | BT32: ='LCFS Table'!$AZ32*'LCFS Table'!$CN32 -> 0 | BU32: ='LCFS Table'!$BA32*'LCFS Table'!$CO32 -> 0 | BV32: ='LCFS Table'!$BB32*'LCFS Table'!$CP32 -> 1.2 | BW32: 1 | BX32: 0 | BY32: 1 | BZ32: 1 | CA32: -1 | CB32: 1 | CC32: 0 | CD32: 1 | CE32: 1 | CF32: -1 | CG32: =1-'LCFS Table'!$BW32 -> 0 | CH32: =1-'LCFS Table'!$BX32 -> 1 | CI32: =1-'LCFS Table'!$BY32 -> 0 | CJ32: =1-'LCFS Table'!$BZ32 -> 0 | CK32: =-'LCFS Table'!$CA32 -> 1 | CL32: =1-'LCFS Table'!$CB32 -> 0 | CM32: =1-'LCFS Table'!$CC32 -> 1 | CN32: =1-'LCFS Table'!$CD32 -> 0 | CO32: =1-'LCFS Table'!$CE32 -> 0 | CP32: =-'LCFS Table'!$CF32 -> 1 | CQ32: 5 | CR32: =('LCFS Table'!$CQ32*0.9/(0.8/0.99)/100) -> 0.0556875 | CW32: ='LCFS Table'!$K32-'LCFS Table'!$M32 -> 1.4371688 | CX32: =MONTH('LCFS Table'!$B32) -> 7 | CY32: =YEAR('LCFS Table'!$B32) -> 2019
A33: 43674 | B33: 43680 | C33: =YEAR(B33) -> 2019 | D33: W31 | E33: ='LCFS Table'!$K33-'LCFS Table'!$I33 -> -0.98327303 | F33: =('LCFS Table'!$M33)-'LCFS Table'!$J33 -> -2.6656341 | G33: ='LCFS Table'!$E33+'LCFS Table'!$AS33+'LCFS Table'!$AT33+'LCFS Table'!$AU33+'LCFS Table'!$AV33 -> 2.6945991 | H33: ='LCFS Table'!$F33+'LCFS Table'!$AX33+'LCFS Table'!$AY33+'LCFS Table'!$AZ33+'LCFS Table'!$BA33+('LCFS Table'!$CQ33*0.9/(0.8/0.99)/100)+(DG33*'LCFS Table'!$AF33)+(DF33*'LCFS Table'!$AG33) -> 0.2745793 | I33: =('LCFS Table'!$V33+'LCFS Table'!$W33+'LCFS Table'!$X33)/100+(('LCFS Table'!$AI33+'LCFS Table'!$AJ33)/340) -> 2.897173 | J33: =(('LCFS Table'!$Y33+'LCFS Table'!$Z33)/100)+(('LCFS Table'!$AM33+'LCFS Table'!$AN33)/300) -> 3.1333238 | K33: ='[1]Fuel Values'!$C32 -> 1.9139 | L33: ='[1]Fuel Values'!$B32 -> 335.5 | M33: =('LCFS Table'!$L33/100)-'LCFS Table'!$AX33-'LCFS Table'!$AY33-'LCFS Table'!$AZ33-'LCFS Table'!$BA33 -> 0.46768973 | N33: =[1]BFT!$B32 -> 31 | O33: =[1]UCO!$B32 -> 25.75 | P33: =[1]DCO!$B32 -> 25.25 | Q33: ='[1]Soybean Oil'!$B32 -> 30.872 | R33: ='[1]Yellow Grease'!$B32 -> 24 | S33: ='LCFS Table'!$N33 + 'LCFS Table'!$AH33 -> 35.375 | T33: ='LCFS Table'!$Q33+'LCFS Table'!$AH33 -> 35.247 | U33: ='LCFS Table'!$P33+'LCFS Table'!$AH33 -> 29.625 | V33: =(('LCFS Table'!$S33/'LCFS Table'!$AA33)*'LCFS Table'!$AC33)*6.48 -> 121.93085 | W33: =(('LCFS Table'!$O33/'LCFS Table'!$AA33)*'LCFS Table'!$AD33)*6.48 -> 44.37766 | X33: =(('LCFS Table'!$U33/'LCFS Table'!$AA33)*'LCFS Table'!$AE33)*6.48 -> 51.055851 | Y33: =(('LCFS Table'!$T33/'LCFS Table'!$AB33)*'LCFS Table'!$AF33)*7.35 -> 202.39488 | Z33: =(('LCFS Table'!$R33/'LCFS Table'!$AB33)*'LCFS Table'!$AG33)*7.35 -> 45.9375 | AA33: 0.94 | AB33: 0.96 | AC33: 0.5 | AD33: 0.25 | AE33: 0.25 | AF33: 0.75 | AG33: 0.25 | AH33: 4.375 | AI33: 136 | AJ33: 110 | AK33: =('LCFS Table'!$AI33/340)*100 -> 40 | AL33: =('LCFS Table'!$AJ33/340)*100 -> 32.352941 | AM33: 105 | AN33: 90 | AO33: =('LCFS Table'!$AM33/300)*100 -> 35 | AP33: =('LCFS Table'!$AN33/300)*100 -> 30 | AQ33: 195.95 | AR33: 0.467 | AS33: 1.7239721 | AT33: 0.16 | AU33: 1 | AV33: ='LCFS Table'!$AR33*1.7 -> 0.7939 | AW33: 0 | AX33: 1.1868103 | AY33: 0 | AZ33: 1 | BA33: ='LCFS Table'!$AR33*1.5 -> 0.7005 | BB33: 1.2 | BC33: ='LCFS Table'!$AS33*'LCFS Table'!$BW33 -> 1.7239721 | BD33: ='LCFS Table'!$AT33*'LCFS Table'!$BX33 -> 0 | BE33: ='LCFS Table'!$AU33*'LCFS Table'!$BY33 -> 1 | BF33: ='LCFS Table'!$AV33*'LCFS Table'!$BZ33 -> 0.7939 | BG33: ='LCFS Table'!$AW33*'LCFS Table'!$CA33 -> 0 | BH33: ='LCFS Table'!$AX33*'LCFS Table'!$CB33 -> 1.1868103 | BI33: ='LCFS Table'!$AY33*'LCFS Table'!$CC33 -> 0 | BJ33: ='LCFS Table'!$AZ33*'LCFS Table'!$CD33 -> 1 | BK33: ='LCFS Table'!$BA33*'LCFS Table'!$CE33 -> 0.7005 | BL33: ='LCFS Table'!$BB33*'LCFS Table'!$CF33 -> -1.2 | BM33: ='LCFS Table'!$AS33*'LCFS Table'!$CG33 -> 0 | BN33: ='LCFS Table'!$AT33*'LCFS Table'!$CH33 -> 0.16 | BO33: ='LCFS Table'!$AU33*'LCFS Table'!$CI33 -> 0 | BP33: ='LCFS Table'!$AV33*'LCFS Table'!$CJ33 -> 0 | BQ33: ='LCFS Table'!$AW33*'LCFS Table'!$CK33 -> 0 | BR33: ='LCFS Table'!$AX33*'LCFS Table'!$CL33 -> 0 | BS33: ='LCFS Table'!$AY33*'LCFS Table'!$CM33 -> 0 | BT33: ='LCFS Table'!$AZ33*'LCFS Table'!$CN33 -> 0 | BU33: ='LCFS Table'!$BA33*'LCFS Table'!$CO33 -> 0 | BV33: ='LCFS Table'!$BB33*'LCFS Table'!$CP33 -> 1.2 | BW33: 1 | BX33: 0 | BY33: 1 | BZ33: 1 | CA33: -1 | CB33: 1 | CC33: 0 | CD33: 1 | CE33: 1 | CF33: -1 | CG33: =1-'LCFS Table'!$BW33 -> 0 | CH33: =1-'LCFS Table'!$BX33 -> 1 | CI33: =1-'LCFS Table'!$BY33 -> 0 | CJ33: =1-'LCFS Table'!$BZ33 -> 0 | CK33: =-'LCFS Table'!$CA33 -> 1 | CL33: =1-'LCFS Table'!$CB33 -> 0 | CM33: =1-'LCFS Table'!$CC33 -> 1 | CN33: =1-'LCFS Table'!$CD33 -> 0 | CO33: =1-'LCFS Table'!$CE33 -> 0 | CP33: =-'LCFS Table'!$CF33 -> 1 | CQ33: 4.75 | CR33: =('LCFS Table'!$CQ33*0.9/(0.8/0.99)/100) -> 0.052903125 | CW33: ='LCFS Table'!$K33-'LCFS Table'!$M33 -> 1.4462103 | CX33: =MONTH('LCFS Table'!$B33) -> 8 | CY33: =YEAR('LCFS Table'!$B33) -> 2019
A34: 43681 | B34: 43687 | C34: =YEAR(B34) -> 2019 | D34: W32 | E34: ='LCFS Table'!$K34-'LCFS Table'!$I34 -> -1.0770198 | F34: =('LCFS Table'!$M34)-'LCFS Table'!$J34 -> -2.6129136 | G34: ='LCFS Table'!$E34+'LCFS Table'!$AS34+'LCFS Table'!$AT34+'LCFS Table'!$AU34+'LCFS Table'!$AV34 -> 2.5216533 | H34: ='LCFS Table'!$F34+'LCFS Table'!$AX34+'LCFS Table'!$AY34+'LCFS Table'!$AZ34+'LCFS Table'!$BA34+('LCFS Table'!$CQ34*0.9/(0.8/0.99)/100)+(DG34*'LCFS Table'!$AF34)+(DF34*'LCFS Table'!$AG34) -> 0.25827148 | I34: =('LCFS Table'!$V34+'LCFS Table'!$W34+'LCFS Table'!$X34)/100+(('LCFS Table'!$AI34+'LCFS Table'!$AJ34)/340) -> 2.9006198 | J34: =(('LCFS Table'!$Y34+'LCFS Table'!$Z34)/100)+(('LCFS Table'!$AM34+'LCFS Table'!$AN34)/300) -> 3.1496316 | K34: ='[1]Fuel Values'!$C33 -> 1.8236 | L34: ='[1]Fuel Values'!$B33 -> 335.5 | M34: =('LCFS Table'!$L34/100)-'LCFS Table'!$AX34-'LCFS Table'!$AY34-'LCFS Table'!$AZ34-'LCFS Table'!$BA34 -> 0.53671808 | N34: =[1]BFT!$B33 -> 31 | O34: =[1]UCO!$B33 -> 25.75 | P34: =[1]DCO!$B33 -> 25.45 | Q34: ='[1]Soybean Oil'!$B33 -> 31.156 | R34: ='[1]Yellow Grease'!$B33 -> 24 | S34: ='LCFS Table'!$N34 + 'LCFS Table'!$AH34 -> 35.375 | T34: ='LCFS Table'!$Q34+'LCFS Table'!$AH34 -> 35.531 | U34: ='LCFS Table'!$P34+'LCFS Table'!$AH34 -> 29.825 | V34: =(('LCFS Table'!$S34/'LCFS Table'!$AA34)*'LCFS Table'!$AC34)*6.48 -> 121.93085 | W34: =(('LCFS Table'!$O34/'LCFS Table'!$AA34)*'LCFS Table'!$AD34)*6.48 -> 44.37766 | X34: =(('LCFS Table'!$U34/'LCFS Table'!$AA34)*'LCFS Table'!$AE34)*6.48 -> 51.400532 | Y34: =(('LCFS Table'!$T34/'LCFS Table'!$AB34)*'LCFS Table'!$AF34)*7.35 -> 204.02566 | Z34: =(('LCFS Table'!$R34/'LCFS Table'!$AB34)*'LCFS Table'!$AG34)*7.35 -> 45.9375 | AA34: 0.94 | AB34: 0.96 | AC34: 0.5 | AD34: 0.25 | AE34: 0.25 | AF34: 0.75 | AG34: 0.25 | AH34: 4.375 | AI34: 136 | AJ34: 110 | AK34: =('LCFS Table'!$AI34/340)*100 -> 40 | AL34: =('LCFS Table'!$AJ34/340)*100 -> 32.352941 | AM34: 105 | AN34: 90 | AO34: =('LCFS Table'!$AM34/300)*100 -> 35 | AP34: =('LCFS Table'!$AN34/300)*100 -> 30 | AQ34: 195.45 | AR34: 0.423 | AS34: 1.7195731 | AT34: 0.16 | AU34: 1 | AV34: ='LCFS Table'!$AR34*1.7 -> 0.7191 | AW34: 0 | AX34: 1.1837819 | AY34: 0 | AZ34: 1 | BA34: ='LCFS Table'!$AR34*1.5 -> 0.6345 | BB34: 1.2 | BC34: ='LCFS Table'!$AS34*'LCFS Table'!$BW34 -> 1.7195731 | BD34: ='LCFS Table'!$AT34*'LCFS Table'!$BX34 -> 0 | BE34: ='LCFS Table'!$AU34*'LCFS Table'!$BY34 -> 1 | BF34: ='LCFS Table'!$AV34*'LCFS Table'!$BZ34 -> 0.7191 | BG34: ='LCFS Table'!$AW34*'LCFS Table'!$CA34 -> 0 | BH34: ='LCFS Table'!$AX34*'LCFS Table'!$CB34 -> 1.1837819 | BI34: ='LCFS Table'!$AY34*'LCFS Table'!$CC34 -> 0 | BJ34: ='LCFS Table'!$AZ34*'LCFS Table'!$CD34 -> 1 | BK34: ='LCFS Table'!$BA34*'LCFS Table'!$CE34 -> 0.6345 | BL34: ='LCFS Table'!$BB34*'LCFS Table'!$CF34 -> -1.2 | BM34: ='LCFS Table'!$AS34*'LCFS Table'!$CG34 -> 0 | BN34: ='LCFS Table'!$AT34*'LCFS Table'!$CH34 -> 0.16 | BO34: ='LCFS Table'!$AU34*'LCFS Table'!$CI34 -> 0 | BP34: ='LCFS Table'!$AV34*'LCFS Table'!$CJ34 -> 0 | BQ34: ='LCFS Table'!$AW34*'LCFS Table'!$CK34 -> 0 | BR34: ='LCFS Table'!$AX34*'LCFS Table'!$CL34 -> 0 | BS34: ='LCFS Table'!$AY34*'LCFS Table'!$CM34 -> 0 | BT34: ='LCFS Table'!$AZ34*'LCFS Table'!$CN34 -> 0 | BU34: ='LCFS Table'!$BA34*'LCFS Table'!$CO34 -> 0 | BV34: ='LCFS Table'!$BB34*'LCFS Table'!$CP34 -> 1.2 | BW34: 1 | BX34: 0 | BY34: 1 | BZ34: 1 | CA34: -1 | CB34: 1 | CC34: 0 | CD34: 1 | CE34: 1 | CF34: -1 | CG34: =1-'LCFS Table'!$BW34 -> 0 | CH34: =1-'LCFS Table'!$BX34 -> 1 | CI34: =1-'LCFS Table'!$BY34 -> 0 | CJ34: =1-'LCFS Table'!$BZ34 -> 0 | CK34: =-'LCFS Table'!$CA34 -> 1 | CL34: =1-'LCFS Table'!$CB34 -> 0 | CM34: =1-'LCFS Table'!$CC34 -> 1 | CN34: =1-'LCFS Table'!$CD34 -> 0 | CO34: =1-'LCFS Table'!$CE34 -> 0 | CP34: =-'LCFS Table'!$CF34 -> 1 | CQ34: 4.75 | CR34: =('LCFS Table'!$CQ34*0.9/(0.8/0.99)/100) -> 0.052903125 | CW34: ='LCFS Table'!$K34-'LCFS Table'!$M34 -> 1.2868819 | CX34: =MONTH('LCFS Table'!$B34) -> 8 | CY34: =YEAR('LCFS Table'!$B34) -> 2019
A35: 43688 | B35: 43694 | C35: =YEAR(B35) -> 2019 | D35: W33 | E35: ='LCFS Table'!$K35-'LCFS Table'!$I35 -> -1.0666518 | F35: =('LCFS Table'!$M35)-'LCFS Table'!$J35 -> -2.7028644 | G35: ='LCFS Table'!$E35+'LCFS Table'!$AS35+'LCFS Table'!$AT35+'LCFS Table'!$AU35+'LCFS Table'!$AV35 -> 2.6087371 | H35: ='LCFS Table'!$F35+'LCFS Table'!$AX35+'LCFS Table'!$AY35+'LCFS Table'!$AZ35+'LCFS Table'!$BA35+('LCFS Table'!$CQ35*0.9/(0.8/0.99)/100)+(DG35*'LCFS Table'!$AF35)+(DF35*'LCFS Table'!$AG35) -> 0.23234258 | I35: =('LCFS Table'!$V35+'LCFS Table'!$W35+'LCFS Table'!$X35)/100+(('LCFS Table'!$AI35+'LCFS Table'!$AJ35)/340) -> 2.9066518 | J35: =(('LCFS Table'!$Y35+'LCFS Table'!$Z35)/100)+(('LCFS Table'!$AM35+'LCFS Table'!$AN35)/300) -> 3.2055605 | K35: ='[1]Fuel Values'!$C34 -> 1.84 | L35: ='[1]Fuel Values'!$B34 -> 338.5 | M35: =('LCFS Table'!$L35/100)-'LCFS Table'!$AX35-'LCFS Table'!$AY35-'LCFS Table'!$AZ35-'LCFS Table'!$BA35 -> 0.50269617 | N35: =[1]BFT!$B34 -> 31 | O35: =[1]UCO!$B34 -> 26.35 | P35: =[1]DCO!$B34 -> 25.2 | Q35: ='[1]Soybean Oil'!$B34 -> 32.13 | R35: ='[1]Yellow Grease'!$B34 -> 24 | S35: ='LCFS Table'!$N35 + 'LCFS Table'!$AH35 -> 35.375 | T35: ='LCFS Table'!$Q35+'LCFS Table'!$AH35 -> 36.505 | U35: ='LCFS Table'!$P35+'LCFS Table'!$AH35 -> 29.575 | V35: =(('LCFS Table'!$S35/'LCFS Table'!$AA35)*'LCFS Table'!$AC35)*6.48 -> 121.93085 | W35: =(('LCFS Table'!$O35/'LCFS Table'!$AA35)*'LCFS Table'!$AD35)*6.48 -> 45.411702 | X35: =(('LCFS Table'!$U35/'LCFS Table'!$AA35)*'LCFS Table'!$AE35)*6.48 -> 50.969681 | Y35: =(('LCFS Table'!$T35/'LCFS Table'!$AB35)*'LCFS Table'!$AF35)*7.35 -> 209.61855 | Z35: =(('LCFS Table'!$R35/'LCFS Table'!$AB35)*'LCFS Table'!$AG35)*7.35 -> 45.9375 | AA35: 0.94 | AB35: 0.96 | AC35: 0.5 | AD35: 0.25 | AE35: 0.25 | AF35: 0.75 | AG35: 0.25 | AH35: 4.375 | AI35: 136 | AJ35: 110 | AK35: =('LCFS Table'!$AI35/340)*100 -> 40 | AL35: =('LCFS Table'!$AJ35/340)*100 -> 32.352941 | AM35: 105 | AN35: 90 | AO35: =('LCFS Table'!$AM35/300)*100 -> 35 | AP35: =('LCFS Table'!$AN35/300)*100 -> 30 | AQ35: 197.6 | AR35: 0.457 | AS35: 1.7384889 | AT35: 0.16 | AU35: 1 | AV35: ='LCFS Table'!$AR35*1.7 -> 0.7769 | AW35: 0 | AX35: 1.1968038 | AY35: 0 | AZ35: 1 | BA35: ='LCFS Table'!$AR35*1.5 -> 0.6855 | BB35: 1.2 | BC35: ='LCFS Table'!$AS35*'LCFS Table'!$BW35 -> 1.7384889 | BD35: ='LCFS Table'!$AT35*'LCFS Table'!$BX35 -> 0 | BE35: ='LCFS Table'!$AU35*'LCFS Table'!$BY35 -> 1 | BF35: ='LCFS Table'!$AV35*'LCFS Table'!$BZ35 -> 0.7769 | BG35: ='LCFS Table'!$AW35*'LCFS Table'!$CA35 -> 0 | BH35: ='LCFS Table'!$AX35*'LCFS Table'!$CB35 -> 1.1968038 | BI35: ='LCFS Table'!$AY35*'LCFS Table'!$CC35 -> 0 | BJ35: ='LCFS Table'!$AZ35*'LCFS Table'!$CD35 -> 1 | BK35: ='LCFS Table'!$BA35*'LCFS Table'!$CE35 -> 0.6855 | BL35: ='LCFS Table'!$BB35*'LCFS Table'!$CF35 -> -1.2 | BM35: ='LCFS Table'!$AS35*'LCFS Table'!$CG35 -> 0 | BN35: ='LCFS Table'!$AT35*'LCFS Table'!$CH35 -> 0.16 | BO35: ='LCFS Table'!$AU35*'LCFS Table'!$CI35 -> 0 | BP35: ='LCFS Table'!$AV35*'LCFS Table'!$CJ35 -> 0 | BQ35: ='LCFS Table'!$AW35*'LCFS Table'!$CK35 -> 0 | BR35: ='LCFS Table'!$AX35*'LCFS Table'!$CL35 -> 0 | BS35: ='LCFS Table'!$AY35*'LCFS Table'!$CM35 -> 0 | BT35: ='LCFS Table'!$AZ35*'LCFS Table'!$CN35 -> 0 | BU35: ='LCFS Table'!$BA35*'LCFS Table'!$CO35 -> 0 | BV35: ='LCFS Table'!$BB35*'LCFS Table'!$CP35 -> 1.2 | BW35: 1 | BX35: 0 | BY35: 1 | BZ35: 1 | CA35: -1 | CB35: 1 | CC35: 0 | CD35: 1 | CE35: 1 | CF35: -1 | CG35: =1-'LCFS Table'!$BW35 -> 0 | CH35: =1-'LCFS Table'!$BX35 -> 1 | CI35: =1-'LCFS Table'!$BY35 -> 0 | CJ35: =1-'LCFS Table'!$BZ35 -> 0 | CK35: =-'LCFS Table'!$CA35 -> 1 | CL35: =1-'LCFS Table'!$CB35 -> 0 | CM35: =1-'LCFS Table'!$CC35 -> 1 | CN35: =1-'LCFS Table'!$CD35 -> 0 | CO35: =1-'LCFS Table'!$CE35 -> 0 | CP35: =-'LCFS Table'!$CF35 -> 1 | CQ35: 4.75 | CR35: =('LCFS Table'!$CQ35*0.9/(0.8/0.99)/100) -> 0.052903125 | CW35: ='LCFS Table'!$K35-'LCFS Table'!$M35 -> 1.3373038 | CX35: =MONTH('LCFS Table'!$B35) -> 8 | CY35: =YEAR('LCFS Table'!$B35) -> 2019
A36: 43695 | B36: 43701 | C36: =YEAR(B36) -> 2019 | D36: W34 | E36: ='LCFS Table'!$K36-'LCFS Table'!$I36 -> -1.0477347 | F36: =('LCFS Table'!$M36)-'LCFS Table'!$J36 -> -2.6957824 | G36: ='LCFS Table'!$E36+'LCFS Table'!$AS36+'LCFS Table'!$AT36+'LCFS Table'!$AU36+'LCFS Table'!$AV36 -> 2.672331 | H36: ='LCFS Table'!$F36+'LCFS Table'!$AX36+'LCFS Table'!$AY36+'LCFS Table'!$AZ36+'LCFS Table'!$BA36+('LCFS Table'!$CQ36*0.9/(0.8/0.99)/100)+(DG36*'LCFS Table'!$AF36)+(DF36*'LCFS Table'!$AG36) -> 0.27611523 | I36: =('LCFS Table'!$V36+'LCFS Table'!$W36+'LCFS Table'!$X36)/100+(('LCFS Table'!$AI36+'LCFS Table'!$AJ36)/340) -> 2.8980347 | J36: =(('LCFS Table'!$Y36+'LCFS Table'!$Z36)/100)+(('LCFS Table'!$AM36+'LCFS Table'!$AN36)/300) -> 3.1817879 | K36: ='[1]Fuel Values'!$C35 -> 1.8503 | L36: ='[1]Fuel Values'!$B35 -> 340.5 | M36: =('LCFS Table'!$L36/100)-'LCFS Table'!$AX36-'LCFS Table'!$AY36-'LCFS Table'!$AZ36-'LCFS Table'!$BA36 -> 0.48600545 | N36: =[1]BFT!$B35 -> 31 | O36: =[1]UCO!$B35 -> 26.5 | P36: =[1]DCO!$B35 -> 24.55 | Q36: ='[1]Soybean Oil'!$B35 -> 31.816 | R36: ='[1]Yellow Grease'!$B35 -> 23.7 | S36: ='LCFS Table'!$N36 + 'LCFS Table'!$AH36 -> 35.375 | T36: ='LCFS Table'!$Q36+'LCFS Table'!$AH36 -> 36.191 | U36: ='LCFS Table'!$P36+'LCFS Table'!$AH36 -> 28.925 | V36: =(('LCFS Table'!$S36/'LCFS Table'!$AA36)*'LCFS Table'!$AC36)*6.48 -> 121.93085 | W36: =(('LCFS Table'!$O36/'LCFS Table'!$AA36)*'LCFS Table'!$AD36)*6.48 -> 45.670213 | X36: =(('LCFS Table'!$U36/'LCFS Table'!$AA36)*'LCFS Table'!$AE36)*6.48 -> 49.849468 | Y36: =(('LCFS Table'!$T36/'LCFS Table'!$AB36)*'LCFS Table'!$AF36)*7.35 -> 207.81551 | Z36: =(('LCFS Table'!$R36/'LCFS Table'!$AB36)*'LCFS Table'!$AG36)*7.35 -> 45.363281 | AA36: 0.94 | AB36: 0.96 | AC36: 0.5 | AD36: 0.25 | AE36: 0.25 | AF36: 0.75 | AG36: 0.25 | AH36: 4.375 | AI36: 136 | AJ36: 110 | AK36: =('LCFS Table'!$AI36/340)*100 -> 40 | AL36: =('LCFS Table'!$AJ36/340)*100 -> 32.352941 | AM36: 105 | AN36: 90 | AO36: =('LCFS Table'!$AM36/300)*100 -> 35 | AP36: =('LCFS Table'!$AN36/300)*100 -> 30 | AQ36: 199.2 | AR36: 0.475 | AS36: 1.7525657 | AT36: 0.16 | AU36: 1 | AV36: ='LCFS Table'!$AR36*1.7 -> 0.8075 | AW36: 0 | AX36: 1.2064945 | AY36: 0 | AZ36: 1 | BA36: ='LCFS Table'!$AR36*1.5 -> 0.7125 | BB36: 1.2 | BC36: ='LCFS Table'!$AS36*'LCFS Table'!$BW36 -> 1.7525657 | BD36: ='LCFS Table'!$AT36*'LCFS Table'!$BX36 -> 0 | BE36: ='LCFS Table'!$AU36*'LCFS Table'!$BY36 -> 1 | BF36: ='LCFS Table'!$AV36*'LCFS Table'!$BZ36 -> 0.8075 | BG36: ='LCFS Table'!$AW36*'LCFS Table'!$CA36 -> 0 | BH36: ='LCFS Table'!$AX36*'LCFS Table'!$CB36 -> 1.2064945 | BI36: ='LCFS Table'!$AY36*'LCFS Table'!$CC36 -> 0 | BJ36: ='LCFS Table'!$AZ36*'LCFS Table'!$CD36 -> 1 | BK36: ='LCFS Table'!$BA36*'LCFS Table'!$CE36 -> 0.7125 | BL36: ='LCFS Table'!$BB36*'LCFS Table'!$CF36 -> -1.2 | BM36: ='LCFS Table'!$AS36*'LCFS Table'!$CG36 -> 0 | BN36: ='LCFS Table'!$AT36*'LCFS Table'!$CH36 -> 0.16 | BO36: ='LCFS Table'!$AU36*'LCFS Table'!$CI36 -> 0 | BP36: ='LCFS Table'!$AV36*'LCFS Table'!$CJ36 -> 0 | BQ36: ='LCFS Table'!$AW36*'LCFS Table'!$CK36 -> 0 | BR36: ='LCFS Table'!$AX36*'LCFS Table'!$CL36 -> 0 | BS36: ='LCFS Table'!$AY36*'LCFS Table'!$CM36 -> 0 | BT36: ='LCFS Table'!$AZ36*'LCFS Table'!$CN36 -> 0 | BU36: ='LCFS Table'!$BA36*'LCFS Table'!$CO36 -> 0 | BV36: ='LCFS Table'!$BB36*'LCFS Table'!$CP36 -> 1.2 | BW36: 1 | BX36: 0 | BY36: 1 | BZ36: 1 | CA36: -1 | CB36: 1 | CC36: 0 | CD36: 1 | CE36: 1 | CF36: -1 | CG36: =1-'LCFS Table'!$BW36 -> 0 | CH36: =1-'LCFS Table'!$BX36 -> 1 | CI36: =1-'LCFS Table'!$BY36 -> 0 | CJ36: =1-'LCFS Table'!$BZ36 -> 0 | CK36: =-'LCFS Table'!$CA36 -> 1 | CL36: =1-'LCFS Table'!$CB36 -> 0 | CM36: =1-'LCFS Table'!$CC36 -> 1 | CN36: =1-'LCFS Table'!$CD36 -> 0 | CO36: =1-'LCFS Table'!$CE36 -> 0 | CP36: =-'LCFS Table'!$CF36 -> 1 | CQ36: 4.75 | CR36: =('LCFS Table'!$CQ36*0.9/(0.8/0.99)/100) -> 0.052903125 | CW36: ='LCFS Table'!$K36-'LCFS Table'!$M36 -> 1.3642945 | CX36: =MONTH('LCFS Table'!$B36) -> 8 | CY36: =YEAR('LCFS Table'!$B36) -> 2019
A37: 43702 | B37: 43708 | C37: =YEAR(B37) -> 2019 | D37: W35 | E37: ='LCFS Table'!$K37-'LCFS Table'!$I37 -> -1.0189581 | F37: =('LCFS Table'!$M37)-'LCFS Table'!$J37 -> -2.6518968 | G37: ='LCFS Table'!$E37+'LCFS Table'!$AS37+'LCFS Table'!$AT37+'LCFS Table'!$AU37+'LCFS Table'!$AV37 -> 2.6928984 | H37: ='LCFS Table'!$F37+'LCFS Table'!$AX37+'LCFS Table'!$AY37+'LCFS Table'!$AZ37+'LCFS Table'!$BA37+('LCFS Table'!$CQ37*0.9/(0.8/0.99)/100)+(DG37*'LCFS Table'!$AF37)+(DF37*'LCFS Table'!$AG37) -> 0.31352539 | I37: =('LCFS Table'!$V37+'LCFS Table'!$W37+'LCFS Table'!$X37)/100+(('LCFS Table'!$AI37+'LCFS Table'!$AJ37)/340) -> 2.8592581 | J37: =(('LCFS Table'!$Y37+'LCFS Table'!$Z37)/100)+(('LCFS Table'!$AM37+'LCFS Table'!$AN37)/300) -> 3.1463777 | K37: ='[1]Fuel Values'!$C36 -> 1.8403 | L37: ='[1]Fuel Values'!$B36 -> 340.7 | M37: =('LCFS Table'!$L37/100)-'LCFS Table'!$AX37-'LCFS Table'!$AY37-'LCFS Table'!$AZ37-'LCFS Table'!$BA37 -> 0.49448097 | N37: =[1]BFT!$B36 -> 30.1 | O37: =[1]UCO!$B36 -> 26.5 | P37: =[1]DCO!$B36 -> 24.1 | Q37: ='[1]Soybean Oil'!$B36 -> 31.266 | R37: ='[1]Yellow Grease'!$B36 -> 23.5 | S37: ='LCFS Table'!$N37 + 'LCFS Table'!$AH37 -> 34.475 | T37: ='LCFS Table'!$Q37+'LCFS Table'!$AH37 -> 35.641 | U37: ='LCFS Table'!$P37+'LCFS Table'!$AH37 -> 28.475 | V37: =(('LCFS Table'!$S37/'LCFS Table'!$AA37)*'LCFS Table'!$AC37)*6.48 -> 118.82872 | W37: =(('LCFS Table'!$O37/'LCFS Table'!$AA37)*'LCFS Table'!$AD37)*6.48 -> 45.670213 | X37: =(('LCFS Table'!$U37/'LCFS Table'!$AA37)*'LCFS Table'!$AE37)*6.48 -> 49.073936 | Y37: =(('LCFS Table'!$T37/'LCFS Table'!$AB37)*'LCFS Table'!$AF37)*7.35 -> 204.6573 | Z37: =(('LCFS Table'!$R37/'LCFS Table'!$AB37)*'LCFS Table'!$AG37)*7.35 -> 44.980469 | AA37: 0.94 | AB37: 0.96 | AC37: 0.5 | AD37: 0.25 | AE37: 0.25 | AF37: 0.75 | AG37: 0.25 | AH37: 4.375 | AI37: 136 | AJ37: 110 | AK37: =('LCFS Table'!$AI37/340)*100 -> 40 | AL37: =('LCFS Table'!$AJ37/340)*100 -> 32.352941 | AM37: 105 | AN37: 90 | AO37: =('LCFS Table'!$AM37/300)*100 -> 35 | AP37: =('LCFS Table'!$AN37/300)*100 -> 30 | AQ37: 198.75 | AR37: 0.4725 | AS37: 1.7486066 | AT37: 0.16 | AU37: 1 | AV37: ='LCFS Table'!$AR37*1.7 -> 0.80325 | AW37: 0 | AX37: 1.203769 | AY37: 0 | AZ37: 1 | BA37: ='LCFS Table'!$AR37*1.5 -> 0.70875 | BB37: 1.2 | BC37: ='LCFS Table'!$AS37*'LCFS Table'!$BW37 -> 1.7486066 | BD37: ='LCFS Table'!$AT37*'LCFS Table'!$BX37 -> 0 | BE37: ='LCFS Table'!$AU37*'LCFS Table'!$BY37 -> 1 | BF37: ='LCFS Table'!$AV37*'LCFS Table'!$BZ37 -> 0.80325 | BG37: ='LCFS Table'!$AW37*'LCFS Table'!$CA37 -> 0 | BH37: ='LCFS Table'!$AX37*'LCFS Table'!$CB37 -> 1.203769 | BI37: ='LCFS Table'!$AY37*'LCFS Table'!$CC37 -> 0 | BJ37: ='LCFS Table'!$AZ37*'LCFS Table'!$CD37 -> 1 | BK37: ='LCFS Table'!$BA37*'LCFS Table'!$CE37 -> 0.70875 | BL37: ='LCFS Table'!$BB37*'LCFS Table'!$CF37 -> -1.2 | BM37: ='LCFS Table'!$AS37*'LCFS Table'!$CG37 -> 0 | BN37: ='LCFS Table'!$AT37*'LCFS Table'!$CH37 -> 0.16 | BO37: ='LCFS Table'!$AU37*'LCFS Table'!$CI37 -> 0 | BP37: ='LCFS Table'!$AV37*'LCFS Table'!$CJ37 -> 0 | BQ37: ='LCFS Table'!$AW37*'LCFS Table'!$CK37 -> 0 | BR37: ='LCFS Table'!$AX37*'LCFS Table'!$CL37 -> 0 | BS37: ='LCFS Table'!$AY37*'LCFS Table'!$CM37 -> 0 | BT37: ='LCFS Table'!$AZ37*'LCFS Table'!$CN37 -> 0 | BU37: ='LCFS Table'!$BA37*'LCFS Table'!$CO37 -> 0 | BV37: ='LCFS Table'!$BB37*'LCFS Table'!$CP37 -> 1.2 | BW37: 1 | BX37: 0 | BY37: 1 | BZ37: 1 | CA37: -1 | CB37: 1 | CC37: 0 | CD37: 1 | CE37: 1 | CF37: -1 | CG37: =1-'LCFS Table'!$BW37 -> 0 | CH37: =1-'LCFS Table'!$BX37 -> 1 | CI37: =1-'LCFS Table'!$BY37 -> 0 | CJ37: =1-'LCFS Table'!$BZ37 -> 0 | CK37: =-'LCFS Table'!$CA37 -> 1 | CL37: =1-'LCFS Table'!$CB37 -> 0 | CM37: =1-'LCFS Table'!$CC37 -> 1 | CN37: =1-'LCFS Table'!$CD37 -> 0 | CO37: =1-'LCFS Table'!$CE37 -> 0 | CP37: =-'LCFS Table'!$CF37 -> 1 | CQ37: 4.75 | CR37: =('LCFS Table'!$CQ37*0.9/(0.8/0.99)/100) -> 0.052903125 | CW37: ='LCFS Table'!$K37-'LCFS Table'!$M37 -> 1.345819 | CX37: =MONTH('LCFS Table'!$B37) -> 8 | CY37: =YEAR('LCFS Table'!$B37) -> 2019
A38: 43709 | B38: 43715 | C38: =YEAR(B38) -> 2019 | D38: W36 | E38: ='LCFS Table'!$K38-'LCFS Table'!$I38 -> -0.92513154 | F38: =('LCFS Table'!$M38)-'LCFS Table'!$J38 -> -2.6752638 | G38: ='LCFS Table'!$E38+'LCFS Table'!$AS38+'LCFS Table'!$AT38+'LCFS Table'!$AU38+'LCFS Table'!$AV38 -> 2.7990125 | H38: ='LCFS Table'!$F38+'LCFS Table'!$AX38+'LCFS Table'!$AY38+'LCFS Table'!$AZ38+'LCFS Table'!$BA38+('LCFS Table'!$CQ38*0.9/(0.8/0.99)/100)+(DG38*'LCFS Table'!$AF38)+(DF38*'LCFS Table'!$AG38) -> 0.29878203 | I38: =('LCFS Table'!$V38+'LCFS Table'!$W38+'LCFS Table'!$X38)/100+(('LCFS Table'!$AI38+'LCFS Table'!$AJ38)/340) -> 2.8002315 | J38: =(('LCFS Table'!$Y38+'LCFS Table'!$Z38)/100)+(('LCFS Table'!$AM38+'LCFS Table'!$AN38)/300) -> 3.1641211 | K38: ='[1]Fuel Values'!$C37 -> 1.8751 | L38: ='[1]Fuel Values'!$B37 -> 341 | M38: =('LCFS Table'!$L38/100)-'LCFS Table'!$AX38-'LCFS Table'!$AY38-'LCFS Table'!$AZ38-'LCFS Table'!$BA38 -> 0.48885726 | N38: =[1]BFT!$B37 -> 28.5 | O38: =[1]UCO!$B37 -> 26.5 | P38: =[1]DCO!$B37 -> 23.875 | Q38: ='[1]Soybean Oil'!$B37 -> 31.575 | R38: ='[1]Yellow Grease'!$B37 -> 23.5 | S38: ='LCFS Table'!$N38 + 'LCFS Table'!$AH38 -> 32.875 | T38: ='LCFS Table'!$Q38+'LCFS Table'!$AH38 -> 35.95 | U38: ='LCFS Table'!$P38+'LCFS Table'!$AH38 -> 28.25 | V38: =(('LCFS Table'!$S38/'LCFS Table'!$AA38)*'LCFS Table'!$AC38)*6.48 -> 113.31383 | W38: =(('LCFS Table'!$O38/'LCFS Table'!$AA38)*'LCFS Table'!$AD38)*6.48 -> 45.670213 | X38: =(('LCFS Table'!$U38/'LCFS Table'!$AA38)*'LCFS Table'!$AE38)*6.48 -> 48.68617 | Y38: =(('LCFS Table'!$T38/'LCFS Table'!$AB38)*'LCFS Table'!$AF38)*7.35 -> 206.43164 | Z38: =(('LCFS Table'!$R38/'LCFS Table'!$AB38)*'LCFS Table'!$AG38)*7.35 -> 44.980469 | AA38: 0.94 | AB38: 0.96 | AC38: 0.5 | AD38: 0.25 | AE38: 0.25 | AF38: 0.75 | AG38: 0.25 | AH38: 4.375 | AI38: 136 | AJ38: 110 | AK38: =('LCFS Table'!$AI38/340)*100 -> 40 | AL38: =('LCFS Table'!$AJ38/340)*100 -> 32.352941 | AM38: 105 | AN38: 90 | AO38: =('LCFS Table'!$AM38/300)*100 -> 35 | AP38: =('LCFS Table'!$AN38/300)*100 -> 30 | AQ38: 200.05 | AR38: 0.473 | AS38: 1.760044 | AT38: 0.16 | AU38: 1 | AV38: ='LCFS Table'!$AR38*1.7 -> 0.8041 | AW38: 0 | AX38: 1.2116427 | AY38: 0 | AZ38: 1 | BA38: ='LCFS Table'!$AR38*1.5 -> 0.7095 | BB38: 1.2 | BC38: ='LCFS Table'!$AS38*'LCFS Table'!$BW38 -> 1.760044 | BD38: ='LCFS Table'!$AT38*'LCFS Table'!$BX38 -> 0 | BE38: ='LCFS Table'!$AU38*'LCFS Table'!$BY38 -> 1 | BF38: ='LCFS Table'!$AV38*'LCFS Table'!$BZ38 -> 0.8041 | BG38: ='LCFS Table'!$AW38*'LCFS Table'!$CA38 -> 0 | BH38: ='LCFS Table'!$AX38*'LCFS Table'!$CB38 -> 1.2116427 | BI38: ='LCFS Table'!$AY38*'LCFS Table'!$CC38 -> 0 | BJ38: ='LCFS Table'!$AZ38*'LCFS Table'!$CD38 -> 1 | BK38: ='LCFS Table'!$BA38*'LCFS Table'!$CE38 -> 0.7095 | BL38: ='LCFS Table'!$BB38*'LCFS Table'!$CF38 -> -1.2 | BM38: ='LCFS Table'!$AS38*'LCFS Table'!$CG38 -> 0 | BN38: ='LCFS Table'!$AT38*'LCFS Table'!$CH38 -> 0.16 | BO38: ='LCFS Table'!$AU38*'LCFS Table'!$CI38 -> 0 | BP38: ='LCFS Table'!$AV38*'LCFS Table'!$CJ38 -> 0 | BQ38: ='LCFS Table'!$AW38*'LCFS Table'!$CK38 -> 0 | BR38: ='LCFS Table'!$AX38*'LCFS Table'!$CL38 -> 0 | BS38: ='LCFS Table'!$AY38*'LCFS Table'!$CM38 -> 0 | BT38: ='LCFS Table'!$AZ38*'LCFS Table'!$CN38 -> 0 | BU38: ='LCFS Table'!$BA38*'LCFS Table'!$CO38 -> 0 | BV38: ='LCFS Table'!$BB38*'LCFS Table'!$CP38 -> 1.2 | BW38: 1 | BX38: 0 | BY38: 1 | BZ38: 1 | CA38: -1 | CB38: 1 | CC38: 0 | CD38: 1 | CE38: 1 | CF38: -1 | CG38: =1-'LCFS Table'!$BW38 -> 0 | CH38: =1-'LCFS Table'!$BX38 -> 1 | CI38: =1-'LCFS Table'!$BY38 -> 0 | CJ38: =1-'LCFS Table'!$BZ38 -> 0 | CK38: =-'LCFS Table'!$CA38 -> 1 | CL38: =1-'LCFS Table'!$CB38 -> 0 | CM38: =1-'LCFS Table'!$CC38 -> 1 | CN38: =1-'LCFS Table'!$CD38 -> 0 | CO38: =1-'LCFS Table'!$CE38 -> 0 | CP38: =-'LCFS Table'!$CF38 -> 1 | CQ38: 4.75 | CR38: =('LCFS Table'!$CQ38*0.9/(0.8/0.99)/100) -> 0.052903125 | CW38: ='LCFS Table'!$K38-'LCFS Table'!$M38 -> 1.3862427 | CX38: =MONTH('LCFS Table'!$B38) -> 9 | CY38: =YEAR('LCFS Table'!$B38) -> 2019
A39: 43716 | B39: 43722 | C39: =YEAR(B39) -> 2019 | D39: W37 | E39: ='LCFS Table'!$K39-'LCFS Table'!$I39 -> -0.87866771 | F39: =('LCFS Table'!$M39)-'LCFS Table'!$J39 -> -2.7286913 | G39: ='LCFS Table'!$E39+'LCFS Table'!$AS39+'LCFS Table'!$AT39+'LCFS Table'!$AU39+'LCFS Table'!$AV39 -> 2.9241162 | H39: ='LCFS Table'!$F39+'LCFS Table'!$AX39+'LCFS Table'!$AY39+'LCFS Table'!$AZ39+'LCFS Table'!$BA39+('LCFS Table'!$CQ39*0.9/(0.8/0.99)/100)+(DG39*'LCFS Table'!$AF39)+(DF39*'LCFS Table'!$AG39) -> 0.31465742 | I39: =('LCFS Table'!$V39+'LCFS Table'!$W39+'LCFS Table'!$X39)/100+(('LCFS Table'!$AI39+'LCFS Table'!$AJ39)/340) -> 2.7881677 | J39: =(('LCFS Table'!$Y39+'LCFS Table'!$Z39)/100)+(('LCFS Table'!$AM39+'LCFS Table'!$AN39)/300) -> 3.1662457 | K39: ='[1]Fuel Values'!$C38 -> 1.9095 | L39: ='[1]Fuel Values'!$B38 -> 342.8 | M39: =('LCFS Table'!$L39/100)-'LCFS Table'!$AX39-'LCFS Table'!$AY39-'LCFS Table'!$AZ39-'LCFS Table'!$BA39 -> 0.43755442 | N39: =[1]BFT!$B38 -> 28.1 | O39: =[1]UCO!$B38 -> 26.5 | P39: =[1]DCO!$B38 -> 23.975 | Q39: ='[1]Soybean Oil'!$B38 -> 31.612 | R39: ='[1]Yellow Grease'!$B38 -> 23.5 | S39: ='LCFS Table'!$N39 + 'LCFS Table'!$AH39 -> 32.475 | T39: ='LCFS Table'!$Q39+'LCFS Table'!$AH39 -> 35.987 | U39: ='LCFS Table'!$P39+'LCFS Table'!$AH39 -> 28.35 | V39: =(('LCFS Table'!$S39/'LCFS Table'!$AA39)*'LCFS Table'!$AC39)*6.48 -> 111.93511 | W39: =(('LCFS Table'!$O39/'LCFS Table'!$AA39)*'LCFS Table'!$AD39)*6.48 -> 45.670213 | X39: =(('LCFS Table'!$U39/'LCFS Table'!$AA39)*'LCFS Table'!$AE39)*6.48 -> 48.858511 | Y39: =(('LCFS Table'!$T39/'LCFS Table'!$AB39)*'LCFS Table'!$AF39)*7.35 -> 206.6441 | Z39: =(('LCFS Table'!$R39/'LCFS Table'!$AB39)*'LCFS Table'!$AG39)*7.35 -> 44.980469 | AA39: 0.94 | AB39: 0.96 | AC39: 0.5 | AD39: 0.25 | AE39: 0.25 | AF39: 0.75 | AG39: 0.25 | AH39: 4.375 | AI39: 136 | AJ39: 110 | AK39: =('LCFS Table'!$AI39/340)*100 -> 40 | AL39: =('LCFS Table'!$AJ39/340)*100 -> 32.352941 | AM39: 105 | AN39: 90 | AO39: =('LCFS Table'!$AM39/300)*100 -> 35 | AP39: =('LCFS Table'!$AN39/300)*100 -> 30 | AQ39: 200.1 | AR39: 0.519 | AS39: 1.7604839 | AT39: 0.16 | AU39: 1 | AV39: ='LCFS Table'!$AR39*1.7 -> 0.8823 | AW39: 0 | AX39: 1.2119456 | AY39: 0 | AZ39: 1 | BA39: ='LCFS Table'!$AR39*1.5 -> 0.7785 | BB39: 1.2 | BC39: ='LCFS Table'!$AS39*'LCFS Table'!$BW39 -> 1.7604839 | BD39: ='LCFS Table'!$AT39*'LCFS Table'!$BX39 -> 0 | BE39: ='LCFS Table'!$AU39*'LCFS Table'!$BY39 -> 1 | BF39: ='LCFS Table'!$AV39*'LCFS Table'!$BZ39 -> 0.8823 | BG39: ='LCFS Table'!$AW39*'LCFS Table'!$CA39 -> 0 | BH39: ='LCFS Table'!$AX39*'LCFS Table'!$CB39 -> 1.2119456 | BI39: ='LCFS Table'!$AY39*'LCFS Table'!$CC39 -> 0 | BJ39: ='LCFS Table'!$AZ39*'LCFS Table'!$CD39 -> 1 | BK39: ='LCFS Table'!$BA39*'LCFS Table'!$CE39 -> 0.7785 | BL39: ='LCFS Table'!$BB39*'LCFS Table'!$CF39 -> -1.2 | BM39: ='LCFS Table'!$AS39*'LCFS Table'!$CG39 -> 0 | BN39: ='LCFS Table'!$AT39*'LCFS Table'!$CH39 -> 0.16 | BO39: ='LCFS Table'!$AU39*'LCFS Table'!$CI39 -> 0 | BP39: ='LCFS Table'!$AV39*'LCFS Table'!$CJ39 -> 0 | BQ39: ='LCFS Table'!$AW39*'LCFS Table'!$CK39 -> 0 | BR39: ='LCFS Table'!$AX39*'LCFS Table'!$CL39 -> 0 | BS39: ='LCFS Table'!$AY39*'LCFS Table'!$CM39 -> 0 | BT39: ='LCFS Table'!$AZ39*'LCFS Table'!$CN39 -> 0 | BU39: ='LCFS Table'!$BA39*'LCFS Table'!$CO39 -> 0 | BV39: ='LCFS Table'!$BB39*'LCFS Table'!$CP39 -> 1.2 | BW39: 1 | BX39: 0 | BY39: 1 | BZ39: 1 | CA39: -1 | CB39: 1 | CC39: 0 | CD39: 1 | CE39: 1 | CF39: -1 | CG39: =1-'LCFS Table'!$BW39 -> 0 | CH39: =1-'LCFS Table'!$BX39 -> 1 | CI39: =1-'LCFS Table'!$BY39 -> 0 | CJ39: =1-'LCFS Table'!$BZ39 -> 0 | CK39: =-'LCFS Table'!$CA39 -> 1 | CL39: =1-'LCFS Table'!$CB39 -> 0 | CM39: =1-'LCFS Table'!$CC39 -> 1 | CN39: =1-'LCFS Table'!$CD39 -> 0 | CO39: =1-'LCFS Table'!$CE39 -> 0 | CP39: =-'LCFS Table'!$CF39 -> 1 | CQ39: 4.75 | CR39: =('LCFS Table'!$CQ39*0.9/(0.8/0.99)/100) -> 0.052903125 | CW39: ='LCFS Table'!$K39-'LCFS Table'!$M39 -> 1.4719456 | CX39: =MONTH('LCFS Table'!$B39) -> 9 | CY39: =YEAR('LCFS Table'!$B39) -> 2019
A40: 43723 | B40: 43729 | C40: =YEAR(B40) -> 2019 | D40: W38 | E40: ='LCFS Table'!$K40-'LCFS Table'!$I40 -> -0.7468709 | F40: =('LCFS Table'!$M40)-'LCFS Table'!$J40 -> -2.7209394 | G40: ='LCFS Table'!$E40+'LCFS Table'!$AS40+'LCFS Table'!$AT40+'LCFS Table'!$AU40+'LCFS Table'!$AV40 -> 3.0015392 | H40: ='LCFS Table'!$F40+'LCFS Table'!$AX40+'LCFS Table'!$AY40+'LCFS Table'!$AZ40+'LCFS Table'!$BA40+('LCFS Table'!$CQ40*0.9/(0.8/0.99)/100)+(DG40*'LCFS Table'!$AF40)+(DF40*'LCFS Table'!$AG40) -> 0.2760557 | I40: =('LCFS Table'!$V40+'LCFS Table'!$W40+'LCFS Table'!$X40)/100+(('LCFS Table'!$AI40+'LCFS Table'!$AJ40)/340) -> 2.7644709 | J40: =(('LCFS Table'!$Y40+'LCFS Table'!$Z40)/100)+(('LCFS Table'!$AM40+'LCFS Table'!$AN40)/300) -> 3.2224043 | K40: ='[1]Fuel Values'!$C39 -> 2.0176 | L40: ='[1]Fuel Values'!$B39 -> 344.5 | M40: =('LCFS Table'!$L40/100)-'LCFS Table'!$AX40-'LCFS Table'!$AY40-'LCFS Table'!$AZ40-'LCFS Table'!$BA40 -> 0.50146486 | N40: =[1]BFT!$B39 -> 27.5 | O40: =[1]UCO!$B39 -> 26.5 | P40: =[1]DCO!$B39 -> 23.8 | Q40: ='[1]Soybean Oil'!$B39 -> 32.69 | R40: ='[1]Yellow Grease'!$B39 -> 23.2 | S40: ='LCFS Table'!$N40 + 'LCFS Table'!$AH40 -> 31.875 | T40: ='LCFS Table'!$Q40+'LCFS Table'!$AH40 -> 37.065 | U40: ='LCFS Table'!$P40+'LCFS Table'!$AH40 -> 28.175 | V40: =(('LCFS Table'!$S40/'LCFS Table'!$AA40)*'LCFS Table'!$AC40)*6.48 -> 109.86702 | W40: =(('LCFS Table'!$O40/'LCFS Table'!$AA40)*'LCFS Table'!$AD40)*6.48 -> 45.670213 | X40: =(('LCFS Table'!$U40/'LCFS Table'!$AA40)*'LCFS Table'!$AE40)*6.48 -> 48.556915 | Y40: =(('LCFS Table'!$T40/'LCFS Table'!$AB40)*'LCFS Table'!$AF40)*7.35 -> 212.83418 | Z40: =(('LCFS Table'!$R40/'LCFS Table'!$AB40)*'LCFS Table'!$AG40)*7.35 -> 44.40625 | AA40: 0.94 | AB40: 0.96 | AC40: 0.5 | AD40: 0.25 | AE40: 0.25 | AF40: 0.75 | AG40: 0.25 | AH40: 4.375 | AI40: 136 | AJ40: 110 | AK40: =('LCFS Table'!$AI40/340)*100 -> 40 | AL40: =('LCFS Table'!$AJ40/340)*100 -> 32.352941 | AM40: 105 | AN40: 90 | AO40: =('LCFS Table'!$AM40/300)*100 -> 35 | AP40: =('LCFS Table'!$AN40/300)*100 -> 30 | AQ40: 199.475 | AR40: 0.49025 | AS40: 1.7549851 | AT40: 0.16 | AU40: 1 | AV40: ='LCFS Table'!$AR40*1.7 -> 0.833425 | AW40: 0 | AX40: 1.2081601 | AY40: 0 | AZ40: 1 | BA40: ='LCFS Table'!$AR40*1.5 -> 0.735375 | BB40: 1.2 | BC40: ='LCFS Table'!$AS40*'LCFS Table'!$BW40 -> 1.7549851 | BD40: ='LCFS Table'!$AT40*'LCFS Table'!$BX40 -> 0 | BE40: ='LCFS Table'!$AU40*'LCFS Table'!$BY40 -> 1 | BF40: ='LCFS Table'!$AV40*'LCFS Table'!$BZ40 -> 0.833425 | BG40: ='LCFS Table'!$AW40*'LCFS Table'!$CA40 -> 0 | BH40: ='LCFS Table'!$AX40*'LCFS Table'!$CB40 -> 1.2081601 | BI40: ='LCFS Table'!$AY40*'LCFS Table'!$CC40 -> 0 | BJ40: ='LCFS Table'!$AZ40*'LCFS Table'!$CD40 -> 1 | BK40: ='LCFS Table'!$BA40*'LCFS Table'!$CE40 -> 0.735375 | BL40: ='LCFS Table'!$BB40*'LCFS Table'!$CF40 -> -1.2 | BM40: ='LCFS Table'!$AS40*'LCFS Table'!$CG40 -> 0 | BN40: ='LCFS Table'!$AT40*'LCFS Table'!$CH40 -> 0.16 | BO40: ='LCFS Table'!$AU40*'LCFS Table'!$CI40 -> 0 | BP40: ='LCFS Table'!$AV40*'LCFS Table'!$CJ40 -> 0 | BQ40: ='LCFS Table'!$AW40*'LCFS Table'!$CK40 -> 0 | BR40: ='LCFS Table'!$AX40*'LCFS Table'!$CL40 -> 0 | BS40: ='LCFS Table'!$AY40*'LCFS Table'!$CM40 -> 0 | BT40: ='LCFS Table'!$AZ40*'LCFS Table'!$CN40 -> 0 | BU40: ='LCFS Table'!$BA40*'LCFS Table'!$CO40 -> 0 | BV40: ='LCFS Table'!$BB40*'LCFS Table'!$CP40 -> 1.2 | BW40: 1 | BX40: 0 | BY40: 1 | BZ40: 1 | CA40: -1 | CB40: 1 | CC40: 0 | CD40: 1 | CE40: 1 | CF40: -1 | CG40: =1-'LCFS Table'!$BW40 -> 0 | CH40: =1-'LCFS Table'!$BX40 -> 1 | CI40: =1-'LCFS Table'!$BY40 -> 0 | CJ40: =1-'LCFS Table'!$BZ40 -> 0 | CK40: =-'LCFS Table'!$CA40 -> 1 | CL40: =1-'LCFS Table'!$CB40 -> 0 | CM40: =1-'LCFS Table'!$CC40 -> 1 | CN40: =1-'LCFS Table'!$CD40 -> 0 | CO40: =1-'LCFS Table'!$CE40 -> 0 | CP40: =-'LCFS Table'!$CF40 -> 1 | CQ40: 4.8 | CR40: =('LCFS Table'!$CQ40*0.9/(0.8/0.99)/100) -> 0.05346 | CW40: ='LCFS Table'!$K40-'LCFS Table'!$M40 -> 1.5161351 | CX40: =MONTH('LCFS Table'!$B40) -> 9 | CY40: =YEAR('LCFS Table'!$B40) -> 2019
A41: 43730 | B41: 43736 | C41: =YEAR(B41) -> 2019 | D41: W39 | E41: ='LCFS Table'!$K41-'LCFS Table'!$I41 -> -0.7960092 | F41: =('LCFS Table'!$M41)-'LCFS Table'!$J41 -> -2.7333578 | G41: ='LCFS Table'!$E41+'LCFS Table'!$AS41+'LCFS Table'!$AT41+'LCFS Table'!$AU41+'LCFS Table'!$AV41 -> 3.0439661 | H41: ='LCFS Table'!$F41+'LCFS Table'!$AX41+'LCFS Table'!$AY41+'LCFS Table'!$AZ41+'LCFS Table'!$BA41+('LCFS Table'!$CQ41*0.9/(0.8/0.99)/100)+(DG41*'LCFS Table'!$AF41)+(DF41*'LCFS Table'!$AG41) -> 0.34678555 | I41: =('LCFS Table'!$V41+'LCFS Table'!$W41+'LCFS Table'!$X41)/100+(('LCFS Table'!$AI41+'LCFS Table'!$AJ41)/340) -> 2.7636092 | J41: =(('LCFS Table'!$Y41+'LCFS Table'!$Z41)/100)+(('LCFS Table'!$AM41+'LCFS Table'!$AN41)/300) -> 3.173902 | K41: ='[1]Fuel Values'!$C40 -> 1.9676 | L41: ='[1]Fuel Values'!$B40 -> 346.5 | M41: =('LCFS Table'!$L41/100)-'LCFS Table'!$AX41-'LCFS Table'!$AY41-'LCFS Table'!$AZ41-'LCFS Table'!$BA41 -> 0.44054411 | N41: =[1]BFT!$B40 -> 27.5 | O41: =[1]UCO!$B40 -> 26.5 | P41: =[1]DCO!$B40 -> 23.75 | Q41: ='[1]Soybean Oil'!$B40 -> 31.912 | R41: ='[1]Yellow Grease'!$B40 -> 23 | S41: ='LCFS Table'!$N41 + 'LCFS Table'!$AH41 -> 31.875 | T41: ='LCFS Table'!$Q41+'LCFS Table'!$AH41 -> 36.287 | U41: ='LCFS Table'!$P41+'LCFS Table'!$AH41 -> 28.125 | V41: =(('LCFS Table'!$S41/'LCFS Table'!$AA41)*'LCFS Table'!$AC41)*6.48 -> 109.86702 | W41: =(('LCFS Table'!$O41/'LCFS Table'!$AA41)*'LCFS Table'!$AD41)*6.48 -> 45.670213 | X41: =(('LCFS Table'!$U41/'LCFS Table'!$AA41)*'LCFS Table'!$AE41)*6.48 -> 48.470745 | Y41: =(('LCFS Table'!$T41/'LCFS Table'!$AB41)*'LCFS Table'!$AF41)*7.35 -> 208.36676 | Z41: =(('LCFS Table'!$R41/'LCFS Table'!$AB41)*'LCFS Table'!$AG41)*7.35 -> 44.023438 | AA41: 0.94 | AB41: 0.96 | AC41: 0.5 | AD41: 0.25 | AE41: 0.25 | AF41: 0.75 | AG41: 0.25 | AH41: 4.375 | AI41: 136 | AJ41: 110 | AK41: =('LCFS Table'!$AI41/340)*100 -> 40 | AL41: =('LCFS Table'!$AJ41/340)*100 -> 32.352941 | AM41: 105 | AN41: 90 | AO41: =('LCFS Table'!$AM41/300)*100 -> 35 | AP41: =('LCFS Table'!$AN41/300)*100 -> 30 | AQ41: 199.4 | AR41: 0.5445 | AS41: 1.7543253 | AT41: 0.16 | AU41: 1 | AV41: ='LCFS Table'!$AR41*1.7 -> 0.92565 | AW41: 0 | AX41: 1.2077059 | AY41: 0 | AZ41: 1 | BA41: ='LCFS Table'!$AR41*1.5 -> 0.81675 | BB41: 1.2 | BC41: ='LCFS Table'!$AS41*'LCFS Table'!$BW41 -> 1.7543253 | BD41: ='LCFS Table'!$AT41*'LCFS Table'!$BX41 -> 0 | BE41: ='LCFS Table'!$AU41*'LCFS Table'!$BY41 -> 1 | BF41: ='LCFS Table'!$AV41*'LCFS Table'!$BZ41 -> 0.92565 | BG41: ='LCFS Table'!$AW41*'LCFS Table'!$CA41 -> 0 | BH41: ='LCFS Table'!$AX41*'LCFS Table'!$CB41 -> 1.2077059 | BI41: ='LCFS Table'!$AY41*'LCFS Table'!$CC41 -> 0 | BJ41: ='LCFS Table'!$AZ41*'LCFS Table'!$CD41 -> 1 | BK41: ='LCFS Table'!$BA41*'LCFS Table'!$CE41 -> 0.81675 | BL41: ='LCFS Table'!$BB41*'LCFS Table'!$CF41 -> -1.2 | BM41: ='LCFS Table'!$AS41*'LCFS Table'!$CG41 -> 0 | BN41: ='LCFS Table'!$AT41*'LCFS Table'!$CH41 -> 0.16 | BO41: ='LCFS Table'!$AU41*'LCFS Table'!$CI41 -> 0 | BP41: ='LCFS Table'!$AV41*'LCFS Table'!$CJ41 -> 0 | BQ41: ='LCFS Table'!$AW41*'LCFS Table'!$CK41 -> 0 | BR41: ='LCFS Table'!$AX41*'LCFS Table'!$CL41 -> 0 | BS41: ='LCFS Table'!$AY41*'LCFS Table'!$CM41 -> 0 | BT41: ='LCFS Table'!$AZ41*'LCFS Table'!$CN41 -> 0 | BU41: ='LCFS Table'!$BA41*'LCFS Table'!$CO41 -> 0 | BV41: ='LCFS Table'!$BB41*'LCFS Table'!$CP41 -> 1.2 | BW41: 1 | BX41: 0 | BY41: 1 | BZ41: 1 | CA41: -1 | CB41: 1 | CC41: 0 | CD41: 1 | CE41: 1 | CF41: -1 | CG41: =1-'LCFS Table'!$BW41 -> 0 | CH41: =1-'LCFS Table'!$BX41 -> 1 | CI41: =1-'LCFS Table'!$BY41 -> 0 | CJ41: =1-'LCFS Table'!$BZ41 -> 0 | CK41: =-'LCFS Table'!$CA41 -> 1 | CL41: =1-'LCFS Table'!$CB41 -> 0 | CM41: =1-'LCFS Table'!$CC41 -> 1 | CN41: =1-'LCFS Table'!$CD41 -> 0 | CO41: =1-'LCFS Table'!$CE41 -> 0 | CP41: =-'LCFS Table'!$CF41 -> 1 | CQ41: 5 | CR41: =('LCFS Table'!$CQ41*0.9/(0.8/0.99)/100) -> 0.0556875 | CW41: ='LCFS Table'!$K41-'LCFS Table'!$M41 -> 1.5270559 | CX41: =MONTH('LCFS Table'!$B41) -> 9 | CY41: =YEAR('LCFS Table'!$B41) -> 2019
A42: 43737 | B42: 43743 | C42: =YEAR(B42) -> 2019 | D42: W40 | E42: ='LCFS Table'!$K42-'LCFS Table'!$I42 -> -0.85549218 | F42: =('LCFS Table'!$M42)-'LCFS Table'!$J42 -> -2.8231687 | G42: ='LCFS Table'!$E42+'LCFS Table'!$AS42+'LCFS Table'!$AT42+'LCFS Table'!$AU42+'LCFS Table'!$AV42 -> 3.0036301 | H42: ='LCFS Table'!$F42+'LCFS Table'!$AX42+'LCFS Table'!$AY42+'LCFS Table'!$AZ42+'LCFS Table'!$BA42+('LCFS Table'!$CQ42*0.9/(0.8/0.99)/100)+(DG42*'LCFS Table'!$AF42)+(DF42*'LCFS Table'!$AG42) -> 0.27130977 | I42: =('LCFS Table'!$V42+'LCFS Table'!$W42+'LCFS Table'!$X42)/100+(('LCFS Table'!$AI42+'LCFS Table'!$AJ42)/340) -> 2.7549922 | J42: =(('LCFS Table'!$Y42+'LCFS Table'!$Z42)/100)+(('LCFS Table'!$AM42+'LCFS Table'!$AN42)/300) -> 3.1953777 | K42: ='[1]Fuel Values'!$C41 -> 1.8995 | L42: ='[1]Fuel Values'!$B41 -> 341.1 | M42: =('LCFS Table'!$L42/100)-'LCFS Table'!$AX42-'LCFS Table'!$AY42-'LCFS Table'!$AZ42-'LCFS Table'!$BA42 -> 0.37220906 | N42: =[1]BFT!$B41 -> 27.35 | O42: =[1]UCO!$B41 -> 26.5 | P42: =[1]DCO!$B41 -> 23.55 | Q42: ='[1]Soybean Oil'!$B41 -> 32.286 | R42: ='[1]Yellow Grease'!$B41 -> 23 | S42: ='LCFS Table'!$N42 + 'LCFS Table'!$AH42 -> 31.725 | T42: ='LCFS Table'!$Q42+'LCFS Table'!$AH42 -> 36.661 | U42: ='LCFS Table'!$P42+'LCFS Table'!$AH42 -> 27.925 | V42: =(('LCFS Table'!$S42/'LCFS Table'!$AA42)*'LCFS Table'!$AC42)*6.48 -> 109.35 | W42: =(('LCFS Table'!$O42/'LCFS Table'!$AA42)*'LCFS Table'!$AD42)*6.48 -> 45.670213 | X42: =(('LCFS Table'!$U42/'LCFS Table'!$AA42)*'LCFS Table'!$AE42)*6.48 -> 48.126064 | Y42: =(('LCFS Table'!$T42/'LCFS Table'!$AB42)*'LCFS Table'!$AF42)*7.35 -> 210.51434 | Z42: =(('LCFS Table'!$R42/'LCFS Table'!$AB42)*'LCFS Table'!$AG42)*7.35 -> 44.023438 | AA42: 0.94 | AB42: 0.96 | AC42: 0.5 | AD42: 0.25 | AE42: 0.25 | AF42: 0.75 | AG42: 0.25 | AH42: 4.375 | AI42: 136 | AJ42: 110 | AK42: =('LCFS Table'!$AI42/340)*100 -> 40 | AL42: =('LCFS Table'!$AJ42/340)*100 -> 32.352941 | AM42: 105 | AN42: 90 | AO42: =('LCFS Table'!$AM42/300)*100 -> 35 | AP42: =('LCFS Table'!$AN42/300)*100 -> 30 | AQ42: 200.9 | AR42: 0.548 | AS42: 1.7675223 | AT42: 0.16 | AU42: 1 | AV42: ='LCFS Table'!$AR42*1.7 -> 0.9316 | AW42: 0 | AX42: 1.2167909 | AY42: 0 | AZ42: 1 | BA42: ='LCFS Table'!$AR42*1.5 -> 0.822 | BB42: 1.2 | BC42: ='LCFS Table'!$AS42*'LCFS Table'!$BW42 -> 1.7675223 | BD42: ='LCFS Table'!$AT42*'LCFS Table'!$BX42 -> 0 | BE42: ='LCFS Table'!$AU42*'LCFS Table'!$BY42 -> 1 | BF42: ='LCFS Table'!$AV42*'LCFS Table'!$BZ42 -> 0.9316 | BG42: ='LCFS Table'!$AW42*'LCFS Table'!$CA42 -> 0 | BH42: ='LCFS Table'!$AX42*'LCFS Table'!$CB42 -> 1.2167909 | BI42: ='LCFS Table'!$AY42*'LCFS Table'!$CC42 -> 0 | BJ42: ='LCFS Table'!$AZ42*'LCFS Table'!$CD42 -> 1 | BK42: ='LCFS Table'!$BA42*'LCFS Table'!$CE42 -> 0.822 | BL42: ='LCFS Table'!$BB42*'LCFS Table'!$CF42 -> -1.2 | BM42: ='LCFS Table'!$AS42*'LCFS Table'!$CG42 -> 0 | BN42: ='LCFS Table'!$AT42*'LCFS Table'!$CH42 -> 0.16 | BO42: ='LCFS Table'!$AU42*'LCFS Table'!$CI42 -> 0 | BP42: ='LCFS Table'!$AV42*'LCFS Table'!$CJ42 -> 0 | BQ42: ='LCFS Table'!$AW42*'LCFS Table'!$CK42 -> 0 | BR42: ='LCFS Table'!$AX42*'LCFS Table'!$CL42 -> 0 | BS42: ='LCFS Table'!$AY42*'LCFS Table'!$CM42 -> 0 | BT42: ='LCFS Table'!$AZ42*'LCFS Table'!$CN42 -> 0 | BU42: ='LCFS Table'!$BA42*'LCFS Table'!$CO42 -> 0 | BV42: ='LCFS Table'!$BB42*'LCFS Table'!$CP42 -> 1.2 | BW42: 1 | BX42: 0 | BY42: 1 | BZ42: 1 | CA42: -1 | CB42: 1 | CC42: 0 | CD42: 1 | CE42: 1 | CF42: -1 | CG42: =1-'LCFS Table'!$BW42 -> 0 | CH42: =1-'LCFS Table'!$BX42 -> 1 | CI42: =1-'LCFS Table'!$BY42 -> 0 | CJ42: =1-'LCFS Table'!$BZ42 -> 0 | CK42: =-'LCFS Table'!$CA42 -> 1 | CL42: =1-'LCFS Table'!$CB42 -> 0 | CM42: =1-'LCFS Table'!$CC42 -> 1 | CN42: =1-'LCFS Table'!$CD42 -> 0 | CO42: =1-'LCFS Table'!$CE42 -> 0 | CP42: =-'LCFS Table'!$CF42 -> 1 | CQ42: 5 | CR42: =('LCFS Table'!$CQ42*0.9/(0.8/0.99)/100) -> 0.0556875 | CW42: ='LCFS Table'!$K42-'LCFS Table'!$M42 -> 1.5272909 | CX42: =MONTH('LCFS Table'!$B42) -> 10 | CY42: =YEAR('LCFS Table'!$B42) -> 2019
A43: 43744 | B43: 43750 | C43: =YEAR(B43) -> 2019 | D43: W41 | E43: ='LCFS Table'!$K43-'LCFS Table'!$I43 -> -0.78401558 | F43: =('LCFS Table'!$M43)-'LCFS Table'!$J43 -> -2.9157658 | G43: ='LCFS Table'!$E43+'LCFS Table'!$AS43+'LCFS Table'!$AT43+'LCFS Table'!$AU43+'LCFS Table'!$AV43 -> 3.1168831 | H43: ='LCFS Table'!$F43+'LCFS Table'!$AX43+'LCFS Table'!$AY43+'LCFS Table'!$AZ43+'LCFS Table'!$BA43+('LCFS Table'!$CQ43*0.9/(0.8/0.99)/100)+(DG43*'LCFS Table'!$AF43)+(DF43*'LCFS Table'!$AG43) -> 0.21241758 | I43: =('LCFS Table'!$V43+'LCFS Table'!$W43+'LCFS Table'!$X43)/100+(('LCFS Table'!$AI43+'LCFS Table'!$AJ43)/340) -> 2.7162156 | J43: =(('LCFS Table'!$Y43+'LCFS Table'!$Z43)/100)+(('LCFS Table'!$AM43+'LCFS Table'!$AN43)/300) -> 3.2182699 | K43: ='[1]Fuel Values'!$C42 -> 1.9322 | L43: ='[1]Fuel Values'!$B42 -> 337.5 | M43: =('LCFS Table'!$L43/100)-'LCFS Table'!$AX43-'LCFS Table'!$AY43-'LCFS Table'!$AZ43-'LCFS Table'!$BA43 -> 0.30250417 | N43: =[1]BFT!$B42 -> 26.5 | O43: =[1]UCO!$B42 -> 26.5 | P43: =[1]DCO!$B42 -> 23 | Q43: ='[1]Soybean Oil'!$B42 -> 32.818 | R43: ='[1]Yellow Grease'!$B42 -> 22.6 | S43: ='LCFS Table'!$N43 + 'LCFS Table'!$AH43 -> 30.875 | T43: ='LCFS Table'!$Q43+'LCFS Table'!$AH43 -> 37.193 | U43: ='LCFS Table'!$P43+'LCFS Table'!$AH43 -> 27.375 | V43: =(('LCFS Table'!$S43/'LCFS Table'!$AA43)*'LCFS Table'!$AC43)*6.48 -> 106.42021 | W43: =(('LCFS Table'!$O43/'LCFS Table'!$AA43)*'LCFS Table'!$AD43)*6.48 -> 45.670213 | X43: =(('LCFS Table'!$U43/'LCFS Table'!$AA43)*'LCFS Table'!$AE43)*6.48 -> 47.178191 | Y43: =(('LCFS Table'!$T43/'LCFS Table'!$AB43)*'LCFS Table'!$AF43)*7.35 -> 213.56918 | Z43: =(('LCFS Table'!$R43/'LCFS Table'!$AB43)*'LCFS Table'!$AG43)*7.35 -> 43.257812 | AA43: 0.94 | AB43: 0.96 | AC43: 0.5 | AD43: 0.25 | AE43: 0.25 | AF43: 0.75 | AG43: 0.25 | AH43: 4.375 | AI43: 136 | AJ43: 110 | AK43: =('LCFS Table'!$AI43/340)*100 -> 40 | AL43: =('LCFS Table'!$AJ43/340)*100 -> 32.352941 | AM43: 105 | AN43: 90 | AO43: =('LCFS Table'!$AM43/300)*100 -> 35 | AP43: =('LCFS Table'!$AN43/300)*100 -> 30 | AQ43: 202.75 | AR43: 0.563 | AS43: 1.7837987 | AT43: 0.16 | AU43: 1 | AV43: ='LCFS Table'!$AR43*1.7 -> 0.9571 | AW43: 0 | AX43: 1.2279958 | AY43: 0 | AZ43: 1 | BA43: ='LCFS Table'!$AR43*1.5 -> 0.8445 | BB43: 1.2 | BC43: ='LCFS Table'!$AS43*'LCFS Table'!$BW43 -> 1.7837987 | BD43: ='LCFS Table'!$AT43*'LCFS Table'!$BX43 -> 0 | BE43: ='LCFS Table'!$AU43*'LCFS Table'!$BY43 -> 1 | BF43: ='LCFS Table'!$AV43*'LCFS Table'!$BZ43 -> 0.9571 | BG43: ='LCFS Table'!$AW43*'LCFS Table'!$CA43 -> 0 | BH43: ='LCFS Table'!$AX43*'LCFS Table'!$CB43 -> 1.2279958 | BI43: ='LCFS Table'!$AY43*'LCFS Table'!$CC43 -> 0 | BJ43: ='LCFS Table'!$AZ43*'LCFS Table'!$CD43 -> 1 | BK43: ='LCFS Table'!$BA43*'LCFS Table'!$CE43 -> 0.8445 | BL43: ='LCFS Table'!$BB43*'LCFS Table'!$CF43 -> -1.2 | BM43: ='LCFS Table'!$AS43*'LCFS Table'!$CG43 -> 0 | BN43: ='LCFS Table'!$AT43*'LCFS Table'!$CH43 -> 0.16 | BO43: ='LCFS Table'!$AU43*'LCFS Table'!$CI43 -> 0 | BP43: ='LCFS Table'!$AV43*'LCFS Table'!$CJ43 -> 0 | BQ43: ='LCFS Table'!$AW43*'LCFS Table'!$CK43 -> 0 | BR43: ='LCFS Table'!$AX43*'LCFS Table'!$CL43 -> 0 | BS43: ='LCFS Table'!$AY43*'LCFS Table'!$CM43 -> 0 | BT43: ='LCFS Table'!$AZ43*'LCFS Table'!$CN43 -> 0 | BU43: ='LCFS Table'!$BA43*'LCFS Table'!$CO43 -> 0 | BV43: ='LCFS Table'!$BB43*'LCFS Table'!$CP43 -> 1.2 | BW43: 1 | BX43: 0 | BY43: 1 | BZ43: 1 | CA43: -1 | CB43: 1 | CC43: 0 | CD43: 1 | CE43: 1 | CF43: -1 | CG43: =1-'LCFS Table'!$BW43 -> 0 | CH43: =1-'LCFS Table'!$BX43 -> 1 | CI43: =1-'LCFS Table'!$BY43 -> 0 | CJ43: =1-'LCFS Table'!$BZ43 -> 0 | CK43: =-'LCFS Table'!$CA43 -> 1 | CL43: =1-'LCFS Table'!$CB43 -> 0 | CM43: =1-'LCFS Table'!$CC43 -> 1 | CN43: =1-'LCFS Table'!$CD43 -> 0 | CO43: =1-'LCFS Table'!$CE43 -> 0 | CP43: =-'LCFS Table'!$CF43 -> 1 | CQ43: 5 | CR43: =('LCFS Table'!$CQ43*0.9/(0.8/0.99)/100) -> 0.0556875 | CW43: ='LCFS Table'!$K43-'LCFS Table'!$M43 -> 1.6296958 | CX43: =MONTH('LCFS Table'!$B43) -> 10 | CY43: =YEAR('LCFS Table'!$B43) -> 2019
... A106: 44185 | B106: 44191 | C106: =YEAR(B106) -> 2020 | D106: W52 | E106: ='LCFS Table'!$K106-'LCFS Table'!$I106 -> -1.9595624 | F106: =('LCFS Table'!$M106)-'LCFS Table'!$J106 -> -3.2509776 | G106: ='LCFS Table'!$E106+'LCFS Table'!$AS106+'LCFS Table'!$AT106+'LCFS Table'!$AU106+'LCFS Table'!$AV106 -> 2.5653123 | H106: ='LCFS Table'!$F106+'LCFS Table'!$AX106+'LCFS Table'!$AY106+'LCFS Table'!$AZ106+'LCFS Table'!$BA106+('LCFS Table'!$CQ106*0.9/(0.8/0.99)/100)+(DG106*'LCFS Table'!$AF106)+(DF106*'LCFS Table'!$AG106) -> 0.45465684 | I106: =('LCFS Table'!$V106+'LCFS Table'!$W106+'LCFS Table'!$X106)/100+(('LCFS Table'!$AI106+'LCFS Table'!$AJ106)/340) -> 3.4486624 | J106: =(('LCFS Table'!$Y106+'LCFS Table'!$Z106)/100)+(('LCFS Table'!$AM106+'LCFS Table'!$AN106)/300) -> 4.1233057 | K106: ='[1]Fuel Values'!$C105 -> 1.4891 | L106: ='[1]Fuel Values'!$B105 -> 450 | M106: =('LCFS Table'!$L106/100)-'LCFS Table'!$AX106-'LCFS Table'!$AY106-'LCFS Table'!$AZ106-'LCFS Table'!$BA106 -> 0.87232804 | N106: =[1]BFT!$B105 -> 37.5 | O106: =[1]UCO!$B105 -> 34.25 | P106: =[1]DCO!$B105 -> 35.75 | Q106: ='[1]Soybean Oil'!$B105 -> 46.8625 | R106: ='[1]Yellow Grease'!$B105 -> 27.75 | S106: ='LCFS Table'!$N106 + 'LCFS Table'!$AH106 -> 41.875 | T106: ='LCFS Table'!$Q106+'LCFS Table'!$AH106 -> 51.2375 | U106: ='LCFS Table'!$P106+'LCFS Table'!$AH106 -> 40.125 | V106: =(('LCFS Table'!$S106/'LCFS Table'!$AA106)*'LCFS Table'!$AC106)*6.48 -> 144.33511 | W106: =(('LCFS Table'!$O106/'LCFS Table'!$AA106)*'LCFS Table'!$AD106)*6.48 -> 59.026596 | X106: =(('LCFS Table'!$U106/'LCFS Table'!$AA106)*'LCFS Table'!$AE106)*6.48 -> 69.151596 | Y106: =(('LCFS Table'!$T106/'LCFS Table'!$AB106)*'LCFS Table'!$AF106)*7.35 -> 294.21533 | Z106: =(('LCFS Table'!$R106/'LCFS Table'!$AB106)*'LCFS Table'!$AG106)*7.35 -> 53.115234 | AA106: 0.94 | AB106: 0.96 | AC106: 0.5 | AD106: 0.25 | AE106: 0.25 | AF106: 0.75 | AG106: 0.25 | AH106: 4.375 | AI106: 136 | AJ106: 110 | AK106: =('LCFS Table'!$AI106/340)*100 -> 40 | AL106: =('LCFS Table'!$AJ106/340)*100 -> 32.352941 | AM106: 105 | AN106: 90 | AO106: =('LCFS Table'!$AM106/300)*100 -> 35 | AP106: =('LCFS Table'!$AN106/300)*100 -> 30 | AQ106: 198.375 | AR106: 0.97125 | AS106: 1.7137497 | AT106: 0.16 | AU106: 1 | AV106: ='LCFS Table'!$AR106*1.7 -> 1.651125 | AW106: 0 | AX106: 1.170797 | AY106: 0 | AZ106: 1 | BA106: ='LCFS Table'!$AR106*1.5 -> 1.456875 | BB106: 1.2 | BC106: ='LCFS Table'!$AS106*'LCFS Table'!$BW106 -> 1.7137497 | BD106: ='LCFS Table'!$AT106*'LCFS Table'!$BX106 -> 0 | BE106: ='LCFS Table'!$AU106*'LCFS Table'!$BY106 -> 1 | BF106: ='LCFS Table'!$AV106*'LCFS Table'!$BZ106 -> 1.651125 | BG106: ='LCFS Table'!$AW106*'LCFS Table'!$CA106 -> 0 | BH106: ='LCFS Table'!$AX106*'LCFS Table'!$CB106 -> 1.170797 | BI106: ='LCFS Table'!$AY106*'LCFS Table'!$CC106 -> 0 | BJ106: ='LCFS Table'!$AZ106*'LCFS Table'!$CD106 -> 1 | BK106: ='LCFS Table'!$BA106*'LCFS Table'!$CE106 -> 1.456875 | BL106: ='LCFS Table'!$BB106*'LCFS Table'!$CF106 -> -1.2 | BM106: ='LCFS Table'!$AS106*'LCFS Table'!$CG106 -> 0 | BN106: ='LCFS Table'!$AT106*'LCFS Table'!$CH106 -> 0.16 | BO106: ='LCFS Table'!$AU106*'LCFS Table'!$CI106 -> 0 | BP106: ='LCFS Table'!$AV106*'LCFS Table'!$CJ106 -> 0 | BQ106: ='LCFS Table'!$AW106*'LCFS Table'!$CK106 -> 0 | BR106: ='LCFS Table'!$AX106*'LCFS Table'!$CL106 -> 0 | BS106: ='LCFS Table'!$AY106*'LCFS Table'!$CM106 -> 0 | BT106: ='LCFS Table'!$AZ106*'LCFS Table'!$CN106 -> 0 | BU106: ='LCFS Table'!$BA106*'LCFS Table'!$CO106 -> 0 | BV106: ='LCFS Table'!$BB106*'LCFS Table'!$CP106 -> 1.2 | BW106: 1 | BX106: 0 | BY106: 1 | BZ106: 1 | CA106: -1 | CB106: 1 | CC106: 0 | CD106: 1 | CE106: 1 | CF106: -1 | CG106: =1-'LCFS Table'!$BW106 -> 0 | CH106: =1-'LCFS Table'!$BX106 -> 1 | CI106: =1-'LCFS Table'!$BY106 -> 0 | CJ106: =1-'LCFS Table'!$BZ106 -> 0 | CK106: =-'LCFS Table'!$CA106 -> 1 | CL106: =1-'LCFS Table'!$CB106 -> 0 | CM106: =1-'LCFS Table'!$CC106 -> 1 | CN106: =1-'LCFS Table'!$CD106 -> 0 | CO106: =1-'LCFS Table'!$CE106 -> 0 | CP106: =-'LCFS Table'!$CF106 -> 1 | CQ106: 7 | CR106: =('LCFS Table'!$CQ106*0.9/(0.8/0.99)/100) -> 0.0779625 | CW106: ='LCFS Table'!$K106-'LCFS Table'!$M106 -> 0.61677196 | CX106: =MONTH('LCFS Table'!$B106) -> 12 | CY106: =YEAR('LCFS Table'!$B106) -> 2020
A107: 44192 | B107: 44198 | C107: =YEAR(B107) -> 2021 | D107: W53 | E107: ='LCFS Table'!$K107-'LCFS Table'!$I107 -> -1.9672794 | F107: =('LCFS Table'!$M107)-'LCFS Table'!$J107 -> -3.3816271 | G107: ='LCFS Table'!$E107+'LCFS Table'!$AS107+'LCFS Table'!$AT107+'LCFS Table'!$AU107+'LCFS Table'!$AV107 -> 2.5861735 | H107: ='LCFS Table'!$F107+'LCFS Table'!$AX107+'LCFS Table'!$AY107+'LCFS Table'!$AZ107+'LCFS Table'!$BA107+('LCFS Table'!$CQ107*0.9/(0.8/0.99)/100)+(DG107*'LCFS Table'!$AF107)+(DF107*'LCFS Table'!$AG107) -> 0.34818711 | I107: =('LCFS Table'!$V107+'LCFS Table'!$W107+'LCFS Table'!$X107)/100+(('LCFS Table'!$AI107+'LCFS Table'!$AJ107)/340) -> 3.4572794 | J107: =(('LCFS Table'!$Y107+'LCFS Table'!$Z107)/100)+(('LCFS Table'!$AM107+'LCFS Table'!$AN107)/300) -> 4.2297754 | K107: ='[1]Fuel Values'!$C106 -> 1.49 | L107: ='[1]Fuel Values'!$B106 -> 450 | M107: =('LCFS Table'!$L107/100)-'LCFS Table'!$AX107-'LCFS Table'!$AY107-'LCFS Table'!$AZ107-'LCFS Table'!$BA107 -> 0.84814831 | N107: =[1]BFT!$B106 -> 37.5 | O107: =[1]UCO!$B106 -> 34.75 | P107: =[1]DCO!$B106 -> 35.75 | Q107: ='[1]Soybean Oil'!$B106 -> 48.55 | R107: ='[1]Yellow Grease'!$B106 -> 28.25 | S107: ='LCFS Table'!$N107 + 'LCFS Table'!$AH107 -> 41.875 | T107: ='LCFS Table'!$Q107+'LCFS Table'!$AH107 -> 52.925 | U107: ='LCFS Table'!$P107+'LCFS Table'!$AH107 -> 40.125 | V107: =(('LCFS Table'!$S107/'LCFS Table'!$AA107)*'LCFS Table'!$AC107)*6.48 -> 144.33511 | W107: =(('LCFS Table'!$O107/'LCFS Table'!$AA107)*'LCFS Table'!$AD107)*6.48 -> 59.888298 | X107: =(('LCFS Table'!$U107/'LCFS Table'!$AA107)*'LCFS Table'!$AE107)*6.48 -> 69.151596 | Y107: =(('LCFS Table'!$T107/'LCFS Table'!$AB107)*'LCFS Table'!$AF107)*7.35 -> 303.90527 | Z107: =(('LCFS Table'!$R107/'LCFS Table'!$AB107)*'LCFS Table'!$AG107)*7.35 -> 54.072266 | AA107: 0.94 | AB107: 0.96 | AC107: 0.5 | AD107: 0.25 | AE107: 0.25 | AF107: 0.75 | AG107: 0.25 | AH107: 4.375 | AI107: 136 | AJ107: 110 | AK107: =('LCFS Table'!$AI107/340)*100 -> 40 | AL107: =('LCFS Table'!$AJ107/340)*100 -> 32.352941 | AM107: 105 | AN107: 90 | AO107: =('LCFS Table'!$AM107/300)*100 -> 35 | AP107: =('LCFS Table'!$AN107/300)*100 -> 30 | AQ107: =[3]Sheet1!$K58 -> 198.9773 | AR107: 0.985 | AS107: 1.7189529 | AT107: 0.16 | AU107: 1 | AV107: ='LCFS Table'!$AR107*1.7 -> 1.6745 | AW107: 0 | AX107: 1.1743517 | AY107: 0 | AZ107: 1 | BA107: ='LCFS Table'!$AR107*1.5 -> 1.4775 | BB107: 1.2 | BC107: ='LCFS Table'!$AS107*'LCFS Table'!$BW107 -> 1.7189529 | BD107: ='LCFS Table'!$AT107*'LCFS Table'!$BX107 -> 0 | BE107: ='LCFS Table'!$AU107*'LCFS Table'!$BY107 -> 1 | BF107: ='LCFS Table'!$AV107*'LCFS Table'!$BZ107 -> 1.6745 | BG107: ='LCFS Table'!$AW107*'LCFS Table'!$CA107 -> 0 | BH107: ='LCFS Table'!$AX107*'LCFS Table'!$CB107 -> 1.1743517 | BI107: ='LCFS Table'!$AY107*'LCFS Table'!$CC107 -> 0 | BJ107: ='LCFS Table'!$AZ107*'LCFS Table'!$CD107 -> 1 | BK107: ='LCFS Table'!$BA107*'LCFS Table'!$CE107 -> 1.4775 | BL107: ='LCFS Table'!$BB107*'LCFS Table'!$CF107 -> -1.2 | BM107: ='LCFS Table'!$AS107*'LCFS Table'!$CG107 -> 0 | BN107: ='LCFS Table'!$AT107*'LCFS Table'!$CH107 -> 0.16 | BO107: ='LCFS Table'!$AU107*'LCFS Table'!$CI107 -> 0 | BP107: ='LCFS Table'!$AV107*'LCFS Table'!$CJ107 -> 0 | BQ107: ='LCFS Table'!$AW107*'LCFS Table'!$CK107 -> 0 | BR107: ='LCFS Table'!$AX107*'LCFS Table'!$CL107 -> 0 | BS107: ='LCFS Table'!$AY107*'LCFS Table'!$CM107 -> 0 | BT107: ='LCFS Table'!$AZ107*'LCFS Table'!$CN107 -> 0 | BU107: ='LCFS Table'!$BA107*'LCFS Table'!$CO107 -> 0 | BV107: ='LCFS Table'!$BB107*'LCFS Table'!$CP107 -> 1.2 | BW107: 1 | BX107: 0 | BY107: 1 | BZ107: 1 | CA107: -1 | CB107: 1 | CC107: 0 | CD107: 1 | CE107: 1 | CF107: -1 | CG107: =1-'LCFS Table'!$BW107 -> 0 | CH107: =1-'LCFS Table'!$BX107 -> 1 | CI107: =1-'LCFS Table'!$BY107 -> 0 | CJ107: =1-'LCFS Table'!$BZ107 -> 0 | CK107: =-'LCFS Table'!$CA107 -> 1 | CL107: =1-'LCFS Table'!$CB107 -> 0 | CM107: =1-'LCFS Table'!$CC107 -> 1 | CN107: =1-'LCFS Table'!$CD107 -> 0 | CO107: =1-'LCFS Table'!$CE107 -> 0 | CP107: =-'LCFS Table'!$CF107 -> 1 | CQ107: 7 | CR107: =('LCFS Table'!$CQ107*0.9/(0.8/0.99)/100) -> 0.0779625 | CW107: ='LCFS Table'!$K107-'LCFS Table'!$M107 -> 0.64185169 | CX107: =MONTH('LCFS Table'!$B107) -> 1 | CY107: =YEAR('LCFS Table'!$B107) -> 2021
A108: 44199 | B108: 44205 | C108: =YEAR(B108) -> 2021 | D108: W1 | E108: ='LCFS Table'!$K108-'LCFS Table'!$I108 -> -1.9744432 | F108: =('LCFS Table'!$M108)-'LCFS Table'!$J108 -> -3.476905 | G108: ='LCFS Table'!$E108+'LCFS Table'!$AS108+'LCFS Table'!$AT108+'LCFS Table'!$AU108+'LCFS Table'!$AV108 -> 2.61894 | H108: ='LCFS Table'!$F108+'LCFS Table'!$AX108+'LCFS Table'!$AY108+'LCFS Table'!$AZ108+'LCFS Table'!$BA108+('LCFS Table'!$CQ108*0.9/(0.8/0.99)/100)+(DG108*'LCFS Table'!$AF108)+(DF108*'LCFS Table'!$AG108) -> 0.28686773 | I108: =('LCFS Table'!$V108+'LCFS Table'!$W108+'LCFS Table'!$X108)/100+(('LCFS Table'!$AI108+'LCFS Table'!$AJ108)/340) -> 3.5098432 | J108: =(('LCFS Table'!$Y108+'LCFS Table'!$Z108)/100)+(('LCFS Table'!$AM108+'LCFS Table'!$AN108)/300) -> 4.2933223 | K108: ='[1]Fuel Values'!$C107 -> 1.5354 | L108: ='[1]Fuel Values'!$B107 -> 450 | M108: =('LCFS Table'!$L108/100)-'LCFS Table'!$AX108-'LCFS Table'!$AY108-'LCFS Table'!$AZ108-'LCFS Table'!$BA108 -> 0.81641726 | N108: =[1]BFT!$B107 -> 38 | O108: =[1]UCO!$B107 -> 35.15 | P108: =[1]DCO!$B107 -> 37.4 | Q108: ='[1]Soybean Oil'!$B107 -> 49.39 | R108: ='[1]Yellow Grease'!$B107 -> 29.05 | S108: ='LCFS Table'!$N108 + 'LCFS Table'!$AH108 -> 42.375 | T108: ='LCFS Table'!$Q108+'LCFS Table'!$AH108 -> 53.765 | U108: ='LCFS Table'!$P108+'LCFS Table'!$AH108 -> 41.775 | V108: =(('LCFS Table'!$S108/'LCFS Table'!$AA108)*'LCFS Table'!$AC108)*6.48 -> 146.05851 | W108: =(('LCFS Table'!$O108/'LCFS Table'!$AA108)*'LCFS Table'!$AD108)*6.48 -> 60.57766 | X108: =(('LCFS Table'!$U108/'LCFS Table'!$AA108)*'LCFS Table'!$AE108)*6.48 -> 71.995213 | Y108: =(('LCFS Table'!$T108/'LCFS Table'!$AB108)*'LCFS Table'!$AF108)*7.35 -> 308.72871 | Z108: =(('LCFS Table'!$R108/'LCFS Table'!$AB108)*'LCFS Table'!$AG108)*7.35 -> 55.603516 | AA108: 0.94 | AB108: 0.96 | AC108: 0.5 | AD108: 0.25 | AE108: 0.25 | AF108: 0.75 | AG108: 0.25 | AH108: 4.375 | AI108: 136 | AJ108: 110 | AK108: =('LCFS Table'!$AI108/340)*100 -> 40 | AL108: =('LCFS Table'!$AJ108/340)*100 -> 32.352941 | AM108: 105 | AN108: 90 | AO108: =('LCFS Table'!$AM108/300)*100 -> 35 | AP108: =('LCFS Table'!$AN108/300)*100 -> 30 | AQ108: 199.3 | AR108: 1.026 | AS108: 1.6891833 | AT108: 0.16 | AU108: 1 | AV108: ='LCFS Table'!$AR108*1.7 -> 1.7442 | AW108: 0 | AX108: 1.1445827 | AY108: 0 | AZ108: 1 | BA108: ='LCFS Table'!$AR108*1.5 -> 1.539 | BB108: 1.2 | BC108: ='LCFS Table'!$AS108*'LCFS Table'!$BW108 -> 1.6891833 | BD108: ='LCFS Table'!$AT108*'LCFS Table'!$BX108 -> 0 | BE108: ='LCFS Table'!$AU108*'LCFS Table'!$BY108 -> 1 | BF108: ='LCFS Table'!$AV108*'LCFS Table'!$BZ108 -> 1.7442 | BG108: ='LCFS Table'!$AW108*'LCFS Table'!$CA108 -> 0 | BH108: ='LCFS Table'!$AX108*'LCFS Table'!$CB108 -> 1.1445827 | BI108: ='LCFS Table'!$AY108*'LCFS Table'!$CC108 -> 0 | BJ108: ='LCFS Table'!$AZ108*'LCFS Table'!$CD108 -> 1 | BK108: ='LCFS Table'!$BA108*'LCFS Table'!$CE108 -> 1.539 | BL108: ='LCFS Table'!$BB108*'LCFS Table'!$CF108 -> -1.2 | BM108: ='LCFS Table'!$AS108*'LCFS Table'!$CG108 -> 0 | BN108: ='LCFS Table'!$AT108*'LCFS Table'!$CH108 -> 0.16 | BO108: ='LCFS Table'!$AU108*'LCFS Table'!$CI108 -> 0 | BP108: ='LCFS Table'!$AV108*'LCFS Table'!$CJ108 -> 0 | BQ108: ='LCFS Table'!$AW108*'LCFS Table'!$CK108 -> 0 | BR108: ='LCFS Table'!$AX108*'LCFS Table'!$CL108 -> 0 | BS108: ='LCFS Table'!$AY108*'LCFS Table'!$CM108 -> 0 | BT108: ='LCFS Table'!$AZ108*'LCFS Table'!$CN108 -> 0 | BU108: ='LCFS Table'!$BA108*'LCFS Table'!$CO108 -> 0 | BV108: ='LCFS Table'!$BB108*'LCFS Table'!$CP108 -> 1.2 | BW108: 1 | BX108: 0 | BY108: 1 | BZ108: 1 | CA108: -1 | CB108: 1 | CC108: 0 | CD108: 1 | CE108: 1 | CF108: -1 | CG108: =1-'LCFS Table'!$BW108 -> 0 | CH108: =1-'LCFS Table'!$BX108 -> 1 | CI108: =1-'LCFS Table'!$BY108 -> 0 | CJ108: =1-'LCFS Table'!$BZ108 -> 0 | CK108: =-'LCFS Table'!$CA108 -> 1 | CL108: =1-'LCFS Table'!$CB108 -> 0 | CM108: =1-'LCFS Table'!$CC108 -> 1 | CN108: =1-'LCFS Table'!$CD108 -> 0 | CO108: =1-'LCFS Table'!$CE108 -> 0 | CP108: =-'LCFS Table'!$CF108 -> 1 | CQ108: 7.2 | CR108: =('LCFS Table'!$CQ108*0.9/(0.8/0.99)/100) -> 0.08019 | CW108: ='LCFS Table'!$K108-'LCFS Table'!$M108 -> 0.71898274 | CX108: =MONTH('LCFS Table'!$B108) -> 1 | CY108: =YEAR('LCFS Table'!$B108) -> 2021
A109: 44206 | B109: 44212 | C109: =YEAR(B109) -> 2021 | D109: W2 | E109: ='LCFS Table'!$K109-'LCFS Table'!$I109 -> -2.0259049 | F109: =('LCFS Table'!$M109)-'LCFS Table'!$J109 -> -3.3583147 | G109: ='LCFS Table'!$E109+'LCFS Table'!$AS109+'LCFS Table'!$AT109+'LCFS Table'!$AU109+'LCFS Table'!$AV109 -> 2.4590582 | H109: ='LCFS Table'!$F109+'LCFS Table'!$AX109+'LCFS Table'!$AY109+'LCFS Table'!$AZ109+'LCFS Table'!$BA109+('LCFS Table'!$CQ109*0.9/(0.8/0.99)/100)+(DG109*'LCFS Table'!$AF109)+(DF109*'LCFS Table'!$AG109) -> 0.30992383 | I109: =('LCFS Table'!$V109+'LCFS Table'!$W109+'LCFS Table'!$X109)/100+(('LCFS Table'!$AI109+'LCFS Table'!$AJ109)/340) -> 3.6322049 | J109: =(('LCFS Table'!$Y109+'LCFS Table'!$Z109)/100)+(('LCFS Table'!$AM109+'LCFS Table'!$AN109)/300) -> 4.2736074 | K109: ='[1]Fuel Values'!$C108 -> 1.6063 | L109: ='[1]Fuel Values'!$B108 -> 450 | M109: =('LCFS Table'!$L109/100)-'LCFS Table'!$AX109-'LCFS Table'!$AY109-'LCFS Table'!$AZ109-'LCFS Table'!$BA109 -> 0.91529269 | N109: =[1]BFT!$B108 -> 40 | O109: =[1]UCO!$B108 -> 35.95 | P109: =[1]DCO!$B108 -> 39.7 | Q109: ='[1]Soybean Oil'!$B108 -> 48.58 | R109: ='[1]Yellow Grease'!$B108 -> 30.45 | S109: ='LCFS Table'!$N109 + 'LCFS Table'!$AH109 -> 44.375 | T109: ='LCFS Table'!$Q109+'LCFS Table'!$AH109 -> 52.955 | U109: ='LCFS Table'!$P109+'LCFS Table'!$AH109 -> 44.075 | V109: =(('LCFS Table'!$S109/'LCFS Table'!$AA109)*'LCFS Table'!$AC109)*6.48 -> 152.95213 | W109: =(('LCFS Table'!$O109/'LCFS Table'!$AA109)*'LCFS Table'!$AD109)*6.48 -> 61.956383 | X109: =(('LCFS Table'!$U109/'LCFS Table'!$AA109)*'LCFS Table'!$AE109)*6.48 -> 75.959043 | Y109: =(('LCFS Table'!$T109/'LCFS Table'!$AB109)*'LCFS Table'!$AF109)*7.35 -> 304.07754 | Z109: =(('LCFS Table'!$R109/'LCFS Table'!$AB109)*'LCFS Table'!$AG109)*7.35 -> 58.283203 | AA109: 0.94 | AB109: 0.96 | AC109: 0.5 | AD109: 0.25 | AE109: 0.25 | AF109: 0.75 | AG109: 0.25 | AH109: 4.375 | AI109: 136 | AJ109: 110 | AK109: =('LCFS Table'!$AI109/340)*100 -> 40 | AL109: =('LCFS Table'!$AJ109/340)*100 -> 32.352941 | AM109: 105 | AN109: 90 | AO109: =('LCFS Table'!$AM109/300)*100 -> 35 | AP109: =('LCFS Table'!$AN109/300)*100 -> 30 | AQ109: 201.15 | AR109: 0.953 | AS109: 1.7048631 | AT109: 0.16 | AU109: 1 | AV109: ='LCFS Table'!$AR109*1.7 -> 1.6201 | AW109: 0 | AX109: 1.1552073 | AY109: 0 | AZ109: 1 | BA109: ='LCFS Table'!$AR109*1.5 -> 1.4295 | BB109: 1.2 | BC109: ='LCFS Table'!$AS109*'LCFS Table'!$BW109 -> 1.7048631 | BD109: ='LCFS Table'!$AT109*'LCFS Table'!$BX109 -> 0 | BE109: ='LCFS Table'!$AU109*'LCFS Table'!$BY109 -> 1 | BF109: ='LCFS Table'!$AV109*'LCFS Table'!$BZ109 -> 1.6201 | BG109: ='LCFS Table'!$AW109*'LCFS Table'!$CA109 -> 0 | BH109: ='LCFS Table'!$AX109*'LCFS Table'!$CB109 -> 1.1552073 | BI109: ='LCFS Table'!$AY109*'LCFS Table'!$CC109 -> 0 | BJ109: ='LCFS Table'!$AZ109*'LCFS Table'!$CD109 -> 1 | BK109: ='LCFS Table'!$BA109*'LCFS Table'!$CE109 -> 1.4295 | BL109: ='LCFS Table'!$BB109*'LCFS Table'!$CF109 -> -1.2 | BM109: ='LCFS Table'!$AS109*'LCFS Table'!$CG109 -> 0 | BN109: ='LCFS Table'!$AT109*'LCFS Table'!$CH109 -> 0.16 | BO109: ='LCFS Table'!$AU109*'LCFS Table'!$CI109 -> 0 | BP109: ='LCFS Table'!$AV109*'LCFS Table'!$CJ109 -> 0 | BQ109: ='LCFS Table'!$AW109*'LCFS Table'!$CK109 -> 0 | BR109: ='LCFS Table'!$AX109*'LCFS Table'!$CL109 -> 0 | BS109: ='LCFS Table'!$AY109*'LCFS Table'!$CM109 -> 0 | BT109: ='LCFS Table'!$AZ109*'LCFS Table'!$CN109 -> 0 | BU109: ='LCFS Table'!$BA109*'LCFS Table'!$CO109 -> 0 | BV109: ='LCFS Table'!$BB109*'LCFS Table'!$CP109 -> 1.2 | BW109: 1 | BX109: 0 | BY109: 1 | BZ109: 1 | CA109: -1 | CB109: 1 | CC109: 0 | CD109: 1 | CE109: 1 | CF109: -1 | CG109: =1-'LCFS Table'!$BW109 -> 0 | CH109: =1-'LCFS Table'!$BX109 -> 1 | CI109: =1-'LCFS Table'!$BY109 -> 0 | CJ109: =1-'LCFS Table'!$BZ109 -> 0 | CK109: =-'LCFS Table'!$CA109 -> 1 | CL109: =1-'LCFS Table'!$CB109 -> 0 | CM109: =1-'LCFS Table'!$CC109 -> 1 | CN109: =1-'LCFS Table'!$CD109 -> 0 | CO109: =1-'LCFS Table'!$CE109 -> 0 | CP109: =-'LCFS Table'!$CF109 -> 1 | CQ109: 7.5 | CR109: =('LCFS Table'!$CQ109*0.9/(0.8/0.99)/100) -> 0.08353125 | CW109: ='LCFS Table'!$K109-'LCFS Table'!$M109 -> 0.69100731 | CX109: =MONTH('LCFS Table'!$B109) -> 1 | CY109: =YEAR('LCFS Table'!$B109) -> 2021
A110: 44213 | B110: 44219 | C110: =YEAR(B110) -> 2021 | D110: W3 | E110: ='LCFS Table'!$K110-'LCFS Table'!$I110 -> -2.077422 | F110: =('LCFS Table'!$M110)-'LCFS Table'!$J110 -> -3.2524885 | G110: ='LCFS Table'!$E110+'LCFS Table'!$AS110+'LCFS Table'!$AT110+'LCFS Table'!$AU110+'LCFS Table'!$AV110 -> 2.5063543 | H110: ='LCFS Table'!$F110+'LCFS Table'!$AX110+'LCFS Table'!$AY110+'LCFS Table'!$AZ110+'LCFS Table'!$BA110+('LCFS Table'!$CQ110*0.9/(0.8/0.99)/100)+(DG110*'LCFS Table'!$AF110)+(DF110*'LCFS Table'!$AG110) -> 0.50298145 | I110: =('LCFS Table'!$V110+'LCFS Table'!$W110+'LCFS Table'!$X110)/100+(('LCFS Table'!$AI110+'LCFS Table'!$AJ110)/340) -> 3.681322 | J110: =(('LCFS Table'!$Y110+'LCFS Table'!$Z110)/100)+(('LCFS Table'!$AM110+'LCFS Table'!$AN110)/300) -> 4.3205498 | K110: ='[1]Fuel Values'!$C109 -> 1.6039 | L110: ='[1]Fuel Values'!$B109 -> 474 | M110: =('LCFS Table'!$L110/100)-'LCFS Table'!$AX110-'LCFS Table'!$AY110-'LCFS Table'!$AZ110-'LCFS Table'!$BA110 -> 1.0680613 | N110: =[1]BFT!$B109 -> 40 | O110: =[1]UCO!$B109 -> 37.5 | P110: =[1]DCO!$B109 -> 41 | Q110: ='[1]Soybean Oil'!$B109 -> 48.985 | R110: ='[1]Yellow Grease'!$B109 -> 31.6875 | S110: ='LCFS Table'!$N110 + 'LCFS Table'!$AH110 -> 44.375 | T110: ='LCFS Table'!$Q110+'LCFS Table'!$AH110 -> 53.36 | U110: ='LCFS Table'!$P110+'LCFS Table'!$AH110 -> 45.375 | V110: =(('LCFS Table'!$S110/'LCFS Table'!$AA110)*'LCFS Table'!$AC110)*6.48 -> 152.95213 | W110: =(('LCFS Table'!$O110/'LCFS Table'!$AA110)*'LCFS Table'!$AD110)*6.48 -> 64.62766 | X110: =(('LCFS Table'!$U110/'LCFS Table'!$AA110)*'LCFS Table'!$AE110)*6.48 -> 78.199468 | Y110: =(('LCFS Table'!$T110/'LCFS Table'!$AB110)*'LCFS Table'!$AF110)*7.35 -> 306.40312 | Z110: =(('LCFS Table'!$R110/'LCFS Table'!$AB110)*'LCFS Table'!$AG110)*7.35 -> 60.651855 | AA110: 0.94 | AB110: 0.96 | AC110: 0.5 | AD110: 0.25 | AE110: 0.25 | AF110: 0.75 | AG110: 0.25 | AH110: 4.375 | AI110: 136 | AJ110: 110 | AK110: =('LCFS Table'!$AI110/340)*100 -> 40 | AL110: =('LCFS Table'!$AJ110/340)*100 -> 32.352941 | AM110: 105 | AN110: 90 | AO110: =('LCFS Table'!$AM110/300)*100 -> 35 | AP110: =('LCFS Table'!$AN110/300)*100 -> 30 | AQ110: 201.125 | AR110: 1.01125 | AS110: 1.7046512 | AT110: 0.16 | AU110: 1 | AV110: ='LCFS Table'!$AR110*1.7 -> 1.719125 | AW110: 0 | AX110: 1.1550637 | AY110: 0 | AZ110: 1 | BA110: ='LCFS Table'!$AR110*1.5 -> 1.516875 | BB110: 1.2 | BC110: ='LCFS Table'!$AS110*'LCFS Table'!$BW110 -> 1.7046512 | BD110: ='LCFS Table'!$AT110*'LCFS Table'!$BX110 -> 0 | BE110: ='LCFS Table'!$AU110*'LCFS Table'!$BY110 -> 1 | BF110: ='LCFS Table'!$AV110*'LCFS Table'!$BZ110 -> 1.719125 | BG110: ='LCFS Table'!$AW110*'LCFS Table'!$CA110 -> 0 | BH110: ='LCFS Table'!$AX110*'LCFS Table'!$CB110 -> 1.1550637 | BI110: ='LCFS Table'!$AY110*'LCFS Table'!$CC110 -> 0 | BJ110: ='LCFS Table'!$AZ110*'LCFS Table'!$CD110 -> 1 | BK110: ='LCFS Table'!$BA110*'LCFS Table'!$CE110 -> 1.516875 | BL110: ='LCFS Table'!$BB110*'LCFS Table'!$CF110 -> -1.2 | BM110: ='LCFS Table'!$AS110*'LCFS Table'!$CG110 -> 0 | BN110: ='LCFS Table'!$AT110*'LCFS Table'!$CH110 -> 0.16 | BO110: ='LCFS Table'!$AU110*'LCFS Table'!$CI110 -> 0 | BP110: ='LCFS Table'!$AV110*'LCFS Table'!$CJ110 -> 0 | BQ110: ='LCFS Table'!$AW110*'LCFS Table'!$CK110 -> 0 | BR110: ='LCFS Table'!$AX110*'LCFS Table'!$CL110 -> 0 | BS110: ='LCFS Table'!$AY110*'LCFS Table'!$CM110 -> 0 | BT110: ='LCFS Table'!$AZ110*'LCFS Table'!$CN110 -> 0 | BU110: ='LCFS Table'!$BA110*'LCFS Table'!$CO110 -> 0 | BV110: ='LCFS Table'!$BB110*'LCFS Table'!$CP110 -> 1.2 | BW110: 1 | BX110: 0 | BY110: 1 | BZ110: 1 | CA110: -1 | CB110: 1 | CC110: 0 | CD110: 1 | CE110: 1 | CF110: -1 | CG110: =1-'LCFS Table'!$BW110 -> 0 | CH110: =1-'LCFS Table'!$BX110 -> 1 | CI110: =1-'LCFS Table'!$BY110 -> 0 | CJ110: =1-'LCFS Table'!$BZ110 -> 0 | CK110: =-'LCFS Table'!$CA110 -> 1 | CL110: =1-'LCFS Table'!$CB110 -> 0 | CM110: =1-'LCFS Table'!$CC110 -> 1 | CN110: =1-'LCFS Table'!$CD110 -> 0 | CO110: =1-'LCFS Table'!$CE110 -> 0 | CP110: =-'LCFS Table'!$CF110 -> 1 | CQ110: 7.5 | CR110: =('LCFS Table'!$CQ110*0.9/(0.8/0.99)/100) -> 0.08353125 | CW110: ='LCFS Table'!$K110-'LCFS Table'!$M110 -> 0.53583874 | CX110: =MONTH('LCFS Table'!$B110) -> 1 | CY110: =YEAR('LCFS Table'!$B110) -> 2021
A111: 44220 | B111: 44226 | C111: =YEAR(B111) -> 2021 | D111: W4 | E111: ='LCFS Table'!$K111-'LCFS Table'!$I111 -> -2.1306943 | F111: =('LCFS Table'!$M111)-'LCFS Table'!$J111 -> -3.4053858 | G111: ='LCFS Table'!$E111+'LCFS Table'!$AS111+'LCFS Table'!$AT111+'LCFS Table'!$AU111+'LCFS Table'!$AV111 -> 2.5972326 | H111: ='LCFS Table'!$F111+'LCFS Table'!$AX111+'LCFS Table'!$AY111+'LCFS Table'!$AZ111+'LCFS Table'!$BA111+('LCFS Table'!$CQ111*0.9/(0.8/0.99)/100)+(DG111*'LCFS Table'!$AF111)+(DF111*'LCFS Table'!$AG111) -> 0.48265586 | I111: =('LCFS Table'!$V111+'LCFS Table'!$W111+'LCFS Table'!$X111)/100+(('LCFS Table'!$AI111+'LCFS Table'!$AJ111)/340) -> 3.7381943 | J111: =(('LCFS Table'!$Y111+'LCFS Table'!$Z111)/100)+(('LCFS Table'!$AM111+'LCFS Table'!$AN111)/300) -> 4.4208754 | K111: ='[1]Fuel Values'!$C110 -> 1.6075 | L111: ='[1]Fuel Values'!$B110 -> 482 | M111: =('LCFS Table'!$L111/100)-'LCFS Table'!$AX111-'LCFS Table'!$AY111-'LCFS Table'!$AZ111-'LCFS Table'!$BA111 -> 1.0154896 | N111: =[1]BFT!$B110 -> 41 | O111: =[1]UCO!$B110 -> 38 | P111: =[1]DCO!$B110 -> 41.8 | Q111: ='[1]Soybean Oil'!$B110 -> 50.628 | R111: ='[1]Yellow Grease'!$B110 -> 32 | S111: ='LCFS Table'!$N111 + 'LCFS Table'!$AH111 -> 45.375 | T111: ='LCFS Table'!$Q111+'LCFS Table'!$AH111 -> 55.003 | U111: ='LCFS Table'!$P111+'LCFS Table'!$AH111 -> 46.175 | V111: =(('LCFS Table'!$S111/'LCFS Table'!$AA111)*'LCFS Table'!$AC111)*6.48 -> 156.39894 | W111: =(('LCFS Table'!$O111/'LCFS Table'!$AA111)*'LCFS Table'!$AD111)*6.48 -> 65.489362 | X111: =(('LCFS Table'!$U111/'LCFS Table'!$AA111)*'LCFS Table'!$AE111)*6.48 -> 79.578191 | Y111: =(('LCFS Table'!$T111/'LCFS Table'!$AB111)*'LCFS Table'!$AF111)*7.35 -> 315.83754 | Z111: =(('LCFS Table'!$R111/'LCFS Table'!$AB111)*'LCFS Table'!$AG111)*7.35 -> 61.25 | AA111: 0.94 | AB111: 0.96 | AC111: 0.5 | AD111: 0.25 | AE111: 0.25 | AF111: 0.75 | AG111: 0.25 | AH111: 4.375 | AI111: 136 | AJ111: 110 | AK111: =('LCFS Table'!$AI111/340)*100 -> 40 | AL111: =('LCFS Table'!$AJ111/340)*100 -> 32.352941 | AM111: 105 | AN111: 90 | AO111: =('LCFS Table'!$AM111/300)*100 -> 35 | AP111: =('LCFS Table'!$AN111/300)*100 -> 30 | AQ111: 198.025 | AR111: 1.1115 | AS111: 1.6783769 | AT111: 0.16 | AU111: 1 | AV111: ='LCFS Table'!$AR111*1.7 -> 1.88955 | AW111: 0 | AX111: 1.1372604 | AY111: 0 | AZ111: 1 | BA111: ='LCFS Table'!$AR111*1.5 -> 1.66725 | BB111: 1.2 | BC111: ='LCFS Table'!$AS111*'LCFS Table'!$BW111 -> 1.6783769 | BD111: ='LCFS Table'!$AT111*'LCFS Table'!$BX111 -> 0 | BE111: ='LCFS Table'!$AU111*'LCFS Table'!$BY111 -> 1 | BF111: ='LCFS Table'!$AV111*'LCFS Table'!$BZ111 -> 1.88955 | BG111: ='LCFS Table'!$AW111*'LCFS Table'!$CA111 -> 0 | BH111: ='LCFS Table'!$AX111*'LCFS Table'!$CB111 -> 1.1372604 | BI111: ='LCFS Table'!$AY111*'LCFS Table'!$CC111 -> 0 | BJ111: ='LCFS Table'!$AZ111*'LCFS Table'!$CD111 -> 1 | BK111: ='LCFS Table'!$BA111*'LCFS Table'!$CE111 -> 1.66725 | BL111: ='LCFS Table'!$BB111*'LCFS Table'!$CF111 -> -1.2 | BM111: ='LCFS Table'!$AS111*'LCFS Table'!$CG111 -> 0 | BN111: ='LCFS Table'!$AT111*'LCFS Table'!$CH111 -> 0.16 | BO111: ='LCFS Table'!$AU111*'LCFS Table'!$CI111 -> 0 | BP111: ='LCFS Table'!$AV111*'LCFS Table'!$CJ111 -> 0 | BQ111: ='LCFS Table'!$AW111*'LCFS Table'!$CK111 -> 0 | BR111: ='LCFS Table'!$AX111*'LCFS Table'!$CL111 -> 0 | BS111: ='LCFS Table'!$AY111*'LCFS Table'!$CM111 -> 0 | BT111: ='LCFS Table'!$AZ111*'LCFS Table'!$CN111 -> 0 | BU111: ='LCFS Table'!$BA111*'LCFS Table'!$CO111 -> 0 | BV111: ='LCFS Table'!$BB111*'LCFS Table'!$CP111 -> 1.2 | BW111: 1 | BX111: 0 | BY111: 1 | BZ111: 1 | CA111: -1 | CB111: 1 | CC111: 0 | CD111: 1 | CE111: 1 | CF111: -1 | CG111: =1-'LCFS Table'!$BW111 -> 0 | CH111: =1-'LCFS Table'!$BX111 -> 1 | CI111: =1-'LCFS Table'!$BY111 -> 0 | CJ111: =1-'LCFS Table'!$BZ111 -> 0 | CK111: =-'LCFS Table'!$CA111 -> 1 | CL111: =1-'LCFS Table'!$CB111 -> 0 | CM111: =1-'LCFS Table'!$CC111 -> 1 | CN111: =1-'LCFS Table'!$CD111 -> 0 | CO111: =1-'LCFS Table'!$CE111 -> 0 | CP111: =-'LCFS Table'!$CF111 -> 1 | CQ111: 7.5 | CR111: =('LCFS Table'!$CQ111*0.9/(0.8/0.99)/100) -> 0.08353125 | CW111: ='LCFS Table'!$K111-'LCFS Table'!$M111 -> 0.59201039 | CX111: =MONTH('LCFS Table'!$B111) -> 1 | CY111: =YEAR('LCFS Table'!$B111) -> 2021
A112: 44227 | B112: 44233 | C112: =YEAR(B112) -> 2021 | D112: W5 | E112: ='LCFS Table'!$K112-'LCFS Table'!$I112 -> -2.1110688 | F112: =('LCFS Table'!$M112)-'LCFS Table'!$J112 -> -3.3912955 | G112: ='LCFS Table'!$E112+'LCFS Table'!$AS112+'LCFS Table'!$AT112+'LCFS Table'!$AU112+'LCFS Table'!$AV112 -> 2.5857446 | H112: ='LCFS Table'!$F112+'LCFS Table'!$AX112+'LCFS Table'!$AY112+'LCFS Table'!$AZ112+'LCFS Table'!$BA112+('LCFS Table'!$CQ112*0.9/(0.8/0.99)/100)+(DG112*'LCFS Table'!$AF112)+(DF112*'LCFS Table'!$AG112) -> 0.48645352 | I112: =('LCFS Table'!$V112+'LCFS Table'!$W112+'LCFS Table'!$X112)/100+(('LCFS Table'!$AI112+'LCFS Table'!$AJ112)/340) -> 3.8062688 | J112: =(('LCFS Table'!$Y112+'LCFS Table'!$Z112)/100)+(('LCFS Table'!$AM112+'LCFS Table'!$AN112)/300) -> 4.4254309 | K112: ='[1]Fuel Values'!$C111 -> 1.6952 | L112: ='[1]Fuel Values'!$B111 -> 482 | M112: =('LCFS Table'!$L112/100)-'LCFS Table'!$AX112-'LCFS Table'!$AY112-'LCFS Table'!$AZ112-'LCFS Table'!$BA112 -> 1.0341354 | N112: =[1]BFT!$B111 -> 42.5 | O112: =[1]UCO!$B111 -> 38.6 | P112: =[1]DCO!$B111 -> 42.15 | Q112: ='[1]Soybean Oil'!$B111 -> 50.174 | R112: ='[1]Yellow Grease'!$B111 -> 33.6 | S112: ='LCFS Table'!$N112 + 'LCFS Table'!$AH112 -> 46.875 | T112: ='LCFS Table'!$Q112+'LCFS Table'!$AH112 -> 54.549 | U112: ='LCFS Table'!$P112+'LCFS Table'!$AH112 -> 46.525 | V112: =(('LCFS Table'!$S112/'LCFS Table'!$AA112)*'LCFS Table'!$AC112)*6.48 -> 161.56915 | W112: =(('LCFS Table'!$O112/'LCFS Table'!$AA112)*'LCFS Table'!$AD112)*6.48 -> 66.523404 | X112: =(('LCFS Table'!$U112/'LCFS Table'!$AA112)*'LCFS Table'!$AE112)*6.48 -> 80.181383 | Y112: =(('LCFS Table'!$T112/'LCFS Table'!$AB112)*'LCFS Table'!$AF112)*7.35 -> 313.23059 | Z112: =(('LCFS Table'!$R112/'LCFS Table'!$AB112)*'LCFS Table'!$AG112)*7.35 -> 64.3125 | AA112: 0.94 | AB112: 0.96 | AC112: 0.5 | AD112: 0.25 | AE112: 0.25 | AF112: 0.75 | AG112: 0.25 | AH112: 4.375 | AI112: 136 | AJ112: 110 | AK112: =('LCFS Table'!$AI112/340)*100 -> 40 | AL112: =('LCFS Table'!$AJ112/340)*100 -> 32.352941 | AM112: 105 | AN112: 90 | AO112: =('LCFS Table'!$AM112/300)*100 -> 35 | AP112: =('LCFS Table'!$AN112/300)*100 -> 30 | AQ112: 192.95 | AR112: 1.1185 | AS112: 1.6353633 | AT112: 0.16 | AU112: 1 | AV112: ='LCFS Table'!$AR112*1.7 -> 1.90145 | AW112: 0 | AX112: 1.1081146 | AY112: 0 | AZ112: 1 | BA112: ='LCFS Table'!$AR112*1.5 -> 1.67775 | BB112: 1.2 | BC112: ='LCFS Table'!$AS112*'LCFS Table'!$BW112 -> 1.6353633 | BD112: ='LCFS Table'!$AT112*'LCFS Table'!$BX112 -> 0 | BE112: ='LCFS Table'!$AU112*'LCFS Table'!$BY112 -> 1 | BF112: ='LCFS Table'!$AV112*'LCFS Table'!$BZ112 -> 1.90145 | BG112: ='LCFS Table'!$AW112*'LCFS Table'!$CA112 -> 0 | BH112: ='LCFS Table'!$AX112*'LCFS Table'!$CB112 -> 1.1081146 | BI112: ='LCFS Table'!$AY112*'LCFS Table'!$CC112 -> 0 | BJ112: ='LCFS Table'!$AZ112*'LCFS Table'!$CD112 -> 1 | BK112: ='LCFS Table'!$BA112*'LCFS Table'!$CE112 -> 1.67775 | BL112: ='LCFS Table'!$BB112*'LCFS Table'!$CF112 -> -1.2 | BM112: ='LCFS Table'!$AS112*'LCFS Table'!$CG112 -> 0 | BN112: ='LCFS Table'!$AT112*'LCFS Table'!$CH112 -> 0.16 | BO112: ='LCFS Table'!$AU112*'LCFS Table'!$CI112 -> 0 | BP112: ='LCFS Table'!$AV112*'LCFS Table'!$CJ112 -> 0 | BQ112: ='LCFS Table'!$AW112*'LCFS Table'!$CK112 -> 0 | BR112: ='LCFS Table'!$AX112*'LCFS Table'!$CL112 -> 0 | BS112: ='LCFS Table'!$AY112*'LCFS Table'!$CM112 -> 0 | BT112: ='LCFS Table'!$AZ112*'LCFS Table'!$CN112 -> 0 | BU112: ='LCFS Table'!$BA112*'LCFS Table'!$CO112 -> 0 | BV112: ='LCFS Table'!$BB112*'LCFS Table'!$CP112 -> 1.2 | BW112: 1 | BX112: 0 | BY112: 1 | BZ112: 1 | CA112: -1 | CB112: 1 | CC112: 0 | CD112: 1 | CE112: 1 | CF112: -1 | CG112: =1-'LCFS Table'!$BW112 -> 0 | CH112: =1-'LCFS Table'!$BX112 -> 1 | CI112: =1-'LCFS Table'!$BY112 -> 0 | CJ112: =1-'LCFS Table'!$BZ112 -> 0 | CK112: =-'LCFS Table'!$CA112 -> 1 | CL112: =1-'LCFS Table'!$CB112 -> 0 | CM112: =1-'LCFS Table'!$CC112 -> 1 | CN112: =1-'LCFS Table'!$CD112 -> 0 | CO112: =1-'LCFS Table'!$CE112 -> 0 | CP112: =-'LCFS Table'!$CF112 -> 1 | CQ112: 8.25 | CR112: =('LCFS Table'!$CQ112*0.9/(0.8/0.99)/100) -> 0.091884375 | CW112: ='LCFS Table'!$K112-'LCFS Table'!$M112 -> 0.66106459 | CX112: =MONTH('LCFS Table'!$B112) -> 2 | CY112: =YEAR('LCFS Table'!$B112) -> 2021
A113: 44234 | B113: 44240 | C113: =YEAR(B113) -> 2021 | D113: W6 | E113: ='LCFS Table'!$K113-'LCFS Table'!$I113 -> -2.0761603 | F113: =('LCFS Table'!$M113)-'LCFS Table'!$J113 -> -3.2472916 | G113: ='LCFS Table'!$E113+'LCFS Table'!$AS113+'LCFS Table'!$AT113+'LCFS Table'!$AU113+'LCFS Table'!$AV113 -> 2.5267366 | H113: ='LCFS Table'!$F113+'LCFS Table'!$AX113+'LCFS Table'!$AY113+'LCFS Table'!$AZ113+'LCFS Table'!$BA113+('LCFS Table'!$CQ113*0.9/(0.8/0.99)/100)+(DG113*'LCFS Table'!$AF113)+(DF113*'LCFS Table'!$AG113) -> 0.54819727 | I113: =('LCFS Table'!$V113+'LCFS Table'!$W113+'LCFS Table'!$X113)/100+(('LCFS Table'!$AI113+'LCFS Table'!$AJ113)/340) -> 3.8424603 | J113: =(('LCFS Table'!$Y113+'LCFS Table'!$Z113)/100)+(('LCFS Table'!$AM113+'LCFS Table'!$AN113)/300) -> 4.5016871 | K113: ='[1]Fuel Values'!$C112 -> 1.7663 | L113: ='[1]Fuel Values'!$B112 -> 495.8 | M113: =('LCFS Table'!$L113/100)-'LCFS Table'!$AX113-'LCFS Table'!$AY113-'LCFS Table'!$AZ113-'LCFS Table'!$BA113 -> 1.2543955 | N113: =[1]BFT!$B112 -> 42.9 | O113: =[1]UCO!$B112 -> 39 | P113: =[1]DCO!$B112 -> 43.05 | Q113: ='[1]Soybean Oil'!$B112 -> 51.202 | R113: ='[1]Yellow Grease'!$B112 -> 34.5 | S113: ='LCFS Table'!$N113 + 'LCFS Table'!$AH113 -> 47.275 | T113: ='LCFS Table'!$Q113+'LCFS Table'!$AH113 -> 55.577 | U113: ='LCFS Table'!$P113+'LCFS Table'!$AH113 -> 47.425 | V113: =(('LCFS Table'!$S113/'LCFS Table'!$AA113)*'LCFS Table'!$AC113)*6.48 -> 162.94787 | W113: =(('LCFS Table'!$O113/'LCFS Table'!$AA113)*'LCFS Table'!$AD113)*6.48 -> 67.212766 | X113: =(('LCFS Table'!$U113/'LCFS Table'!$AA113)*'LCFS Table'!$AE113)*6.48 -> 81.732447 | Y113: =(('LCFS Table'!$T113/'LCFS Table'!$AB113)*'LCFS Table'!$AF113)*7.35 -> 319.13355 | Z113: =(('LCFS Table'!$R113/'LCFS Table'!$AB113)*'LCFS Table'!$AG113)*7.35 -> 66.035156 | AA113: 0.94 | AB113: 0.96 | AC113: 0.5 | AD113: 0.25 | AE113: 0.25 | AF113: 0.75 | AG113: 0.25 | AH113: 4.375 | AI113: 136 | AJ113: 110 | AK113: =('LCFS Table'!$AI113/340)*100 -> 40 | AL113: =('LCFS Table'!$AJ113/340)*100 -> 32.352941 | AM113: 105 | AN113: 90 | AO113: =('LCFS Table'!$AM113/300)*100 -> 35 | AP113: =('LCFS Table'!$AN113/300)*100 -> 30 | AQ113: 192.6 | AR113: 1.065 | AS113: 1.6323969 | AT113: 0.16 | AU113: 1 | AV113: ='LCFS Table'!$AR113*1.7 -> 1.8105 | AW113: 0 | AX113: 1.1061045 | AY113: 0 | AZ113: 1 | BA113: ='LCFS Table'!$AR113*1.5 -> 1.5975 | BB113: 1.2 | BC113: ='LCFS Table'!$AS113*'LCFS Table'!$BW113 -> 1.6323969 | BD113: ='LCFS Table'!$AT113*'LCFS Table'!$BX113 -> 0 | BE113: ='LCFS Table'!$AU113*'LCFS Table'!$BY113 -> 1 | BF113: ='LCFS Table'!$AV113*'LCFS Table'!$BZ113 -> 1.8105 | BG113: ='LCFS Table'!$AW113*'LCFS Table'!$CA113 -> 0 | BH113: ='LCFS Table'!$AX113*'LCFS Table'!$CB113 -> 1.1061045 | BI113: ='LCFS Table'!$AY113*'LCFS Table'!$CC113 -> 0 | BJ113: ='LCFS Table'!$AZ113*'LCFS Table'!$CD113 -> 1 | BK113: ='LCFS Table'!$BA113*'LCFS Table'!$CE113 -> 1.5975 | BL113: ='LCFS Table'!$BB113*'LCFS Table'!$CF113 -> -1.2 | BM113: ='LCFS Table'!$AS113*'LCFS Table'!$CG113 -> 0 | BN113: ='LCFS Table'!$AT113*'LCFS Table'!$CH113 -> 0.16 | BO113: ='LCFS Table'!$AU113*'LCFS Table'!$CI113 -> 0 | BP113: ='LCFS Table'!$AV113*'LCFS Table'!$CJ113 -> 0 | BQ113: ='LCFS Table'!$AW113*'LCFS Table'!$CK113 -> 0 | BR113: ='LCFS Table'!$AX113*'LCFS Table'!$CL113 -> 0 | BS113: ='LCFS Table'!$AY113*'LCFS Table'!$CM113 -> 0 | BT113: ='LCFS Table'!$AZ113*'LCFS Table'!$CN113 -> 0 | BU113: ='LCFS Table'!$BA113*'LCFS Table'!$CO113 -> 0 | BV113: ='LCFS Table'!$BB113*'LCFS Table'!$CP113 -> 1.2 | BW113: 1 | BX113: 0 | BY113: 1 | BZ113: 1 | CA113: -1 | CB113: 1 | CC113: 0 | CD113: 1 | CE113: 1 | CF113: -1 | CG113: =1-'LCFS Table'!$BW113 -> 0 | CH113: =1-'LCFS Table'!$BX113 -> 1 | CI113: =1-'LCFS Table'!$BY113 -> 0 | CJ113: =1-'LCFS Table'!$BZ113 -> 0 | CK113: =-'LCFS Table'!$CA113 -> 1 | CL113: =1-'LCFS Table'!$CB113 -> 0 | CM113: =1-'LCFS Table'!$CC113 -> 1 | CN113: =1-'LCFS Table'!$CD113 -> 0 | CO113: =1-'LCFS Table'!$CE113 -> 0 | CP113: =-'LCFS Table'!$CF113 -> 1 | CQ113: 8.25 | CR113: =('LCFS Table'!$CQ113*0.9/(0.8/0.99)/100) -> 0.091884375 | CW113: ='LCFS Table'!$K113-'LCFS Table'!$M113 -> 0.51190454 | CX113: =MONTH('LCFS Table'!$B113) -> 2 | CY113: =YEAR('LCFS Table'!$B113) -> 2021
A114: 44241 | B114: 44247 | C114: =YEAR(B114) -> 2021 | D114: W7 | E114: ='LCFS Table'!$K114-'LCFS Table'!$I114 -> -2.054539 | F114: =('LCFS Table'!$M114)-'LCFS Table'!$J114 -> -3.2072685 | G114: ='LCFS Table'!$E114+'LCFS Table'!$AS114+'LCFS Table'!$AT114+'LCFS Table'!$AU114+'LCFS Table'!$AV114 -> 2.5198853 | H114: ='LCFS Table'!$F114+'LCFS Table'!$AX114+'LCFS Table'!$AY114+'LCFS Table'!$AZ114+'LCFS Table'!$BA114+('LCFS Table'!$CQ114*0.9/(0.8/0.99)/100)+(DG114*'LCFS Table'!$AF114)+(DF114*'LCFS Table'!$AG114) -> 0.56605547 | I114: =('LCFS Table'!$V114+'LCFS Table'!$W114+'LCFS Table'!$X114)/100+(('LCFS Table'!$AI114+'LCFS Table'!$AJ114)/340) -> 3.892439 | J114: =(('LCFS Table'!$Y114+'LCFS Table'!$Z114)/100)+(('LCFS Table'!$AM114+'LCFS Table'!$AN114)/300) -> 4.5786133 | K114: ='[1]Fuel Values'!$C113 -> 1.8379 | L114: ='[1]Fuel Values'!$B113 -> 505 | M114: =('LCFS Table'!$L114/100)-'LCFS Table'!$AX114-'LCFS Table'!$AY114-'LCFS Table'!$AZ114-'LCFS Table'!$BA114 -> 1.3713448 | N114: =[1]BFT!$B113 -> 44 | O114: =[1]UCO!$B113 -> 39 | P114: =[1]DCO!$B113 -> 43.75 | Q114: ='[1]Soybean Oil'!$B113 -> 52.25 | R114: ='[1]Yellow Grease'!$B113 -> 35.375 | S114: ='LCFS Table'!$N114 + 'LCFS Table'!$AH114 -> 48.375 | T114: ='LCFS Table'!$Q114+'LCFS Table'!$AH114 -> 56.625 | U114: ='LCFS Table'!$P114+'LCFS Table'!$AH114 -> 48.125 | V114: =(('LCFS Table'!$S114/'LCFS Table'!$AA114)*'LCFS Table'!$AC114)*6.48 -> 166.73936 | W114: =(('LCFS Table'!$O114/'LCFS Table'!$AA114)*'LCFS Table'!$AD114)*6.48 -> 67.212766 | X114: =(('LCFS Table'!$U114/'LCFS Table'!$AA114)*'LCFS Table'!$AE114)*6.48 -> 82.93883 | Y114: =(('LCFS Table'!$T114/'LCFS Table'!$AB114)*'LCFS Table'!$AF114)*7.35 -> 325.15137 | Z114: =(('LCFS Table'!$R114/'LCFS Table'!$AB114)*'LCFS Table'!$AG114)*7.35 -> 67.709961 | AA114: 0.94 | AB114: 0.96 | AC114: 0.5 | AD114: 0.25 | AE114: 0.25 | AF114: 0.75 | AG114: 0.25 | AH114: 4.375 | AI114: 136 | AJ114: 110 | AK114: =('LCFS Table'!$AI114/340)*100 -> 40 | AL114: =('LCFS Table'!$AJ114/340)*100 -> 32.352941 | AM114: 105 | AN114: 90 | AO114: =('LCFS Table'!$AM114/300)*100 -> 35 | AP114: =('LCFS Table'!$AN114/300)*100 -> 30 | AQ114: 192.5 | AR114: 1.04875 | AS114: 1.6315493 | AT114: 0.16 | AU114: 1 | AV114: ='LCFS Table'!$AR114*1.7 -> 1.782875 | AW114: 0 | AX114: 1.1055302 | AY114: 0 | AZ114: 1 | BA114: ='LCFS Table'!$AR114*1.5 -> 1.573125 | BB114: 1.2 | BC114: ='LCFS Table'!$AS114*'LCFS Table'!$BW114 -> 1.6315493 | BD114: ='LCFS Table'!$AT114*'LCFS Table'!$BX114 -> 0 | BE114: ='LCFS Table'!$AU114*'LCFS Table'!$BY114 -> 1 | BF114: ='LCFS Table'!$AV114*'LCFS Table'!$BZ114 -> 1.782875 | BG114: ='LCFS Table'!$AW114*'LCFS Table'!$CA114 -> 0 | BH114: ='LCFS Table'!$AX114*'LCFS Table'!$CB114 -> 1.1055302 | BI114: ='LCFS Table'!$AY114*'LCFS Table'!$CC114 -> 0 | BJ114: ='LCFS Table'!$AZ114*'LCFS Table'!$CD114 -> 1 | BK114: ='LCFS Table'!$BA114*'LCFS Table'!$CE114 -> 1.573125 | BL114: ='LCFS Table'!$BB114*'LCFS Table'!$CF114 -> -1.2 | BM114: ='LCFS Table'!$AS114*'LCFS Table'!$CG114 -> 0 | BN114: ='LCFS Table'!$AT114*'LCFS Table'!$CH114 -> 0.16 | BO114: ='LCFS Table'!$AU114*'LCFS Table'!$CI114 -> 0 | BP114: ='LCFS Table'!$AV114*'LCFS Table'!$CJ114 -> 0 | BQ114: ='LCFS Table'!$AW114*'LCFS Table'!$CK114 -> 0 | BR114: ='LCFS Table'!$AX114*'LCFS Table'!$CL114 -> 0 | BS114: ='LCFS Table'!$AY114*'LCFS Table'!$CM114 -> 0 | BT114: ='LCFS Table'!$AZ114*'LCFS Table'!$CN114 -> 0 | BU114: ='LCFS Table'!$BA114*'LCFS Table'!$CO114 -> 0 | BV114: ='LCFS Table'!$BB114*'LCFS Table'!$CP114 -> 1.2 | BW114: 1 | BX114: 0 | BY114: 1 | BZ114: 1 | CA114: -1 | CB114: 1 | CC114: 0 | CD114: 1 | CE114: 1 | CF114: -1 | CG114: =1-'LCFS Table'!$BW114 -> 0 | CH114: =1-'LCFS Table'!$BX114 -> 1 | CI114: =1-'LCFS Table'!$BY114 -> 0 | CJ114: =1-'LCFS Table'!$BZ114 -> 0 | CK114: =-'LCFS Table'!$CA114 -> 1 | CL114: =1-'LCFS Table'!$CB114 -> 0 | CM114: =1-'LCFS Table'!$CC114 -> 1 | CN114: =1-'LCFS Table'!$CD114 -> 0 | CO114: =1-'LCFS Table'!$CE114 -> 0 | CP114: =-'LCFS Table'!$CF114 -> 1 | CQ114: 8.5 | CR114: =('LCFS Table'!$CQ114*0.9/(0.8/0.99)/100) -> 0.09466875 | CW114: ='LCFS Table'!$K114-'LCFS Table'!$M114 -> 0.46655524 | CX114: =MONTH('LCFS Table'!$B114) -> 2 | CY114: =YEAR('LCFS Table'!$B114) -> 2021
