Workbook

Sheet US EIA
A1: Fats and Oils Used in Methyl Esters (Biodiesel) Production | B1: Vegetable Oils (mil. lbs.) | H1: Animal Fats (mil. lbs.) | L1: Recycled Feeds (mil. lbs.) | BZ1: http://www.biodieselmagazine.com/plants/listplants/USA/ | CI1: 0.97 | CJ1: 0.775 | CK1: 0.94 | CN1: 0.97 | CO1: 0.9985 | CU1: % of feedstock use | DI1: 0.97 | DJ1: 0.9985 | DK1: 0.98875 | DL1: 0.9925 | DM1: 0.775 | DN1: 0.991 | DO1: 0.955 | DP1: 0.94 | DQ1: 0.998 | DR1: 0.97 | DS1: 0.775 | DT1: 0.94 | DU1: 0.955 | DW1: EIA | EK1: Animal Fats | EM1: Recycled Feeds
B2: Canola Oil | C2: Corn Oil | D2: Cottonseed Oil | E2: Palm Oil | F2: Soybean Oil | G2: Other (Sunflower Oil, Sorghum Oil) | H2: Poultry Fat | I2: Tallow | J2: White Grease | K2: Other (Lard) | L2: Yellow Grease | M2: Other Grease | N2: Advanced Feedstocks (Camolina) | O2: Other | P2: Total | Q2: EIA Yield | R2: Annual capacity (mil. gal.) | S2: Production (mil. gal.) | T2: Sales of B100 | U2: Sales of B100 Included in Biodiesel Blends | V2: Ending Stocks of B100 | W2: B100 Stock Change | X2: U.S. Biodiesel Sales | Y2: Sales vs. 5-Yr Avg. | Z2: Days of Next Months Sales | AA2: Imports | AB2: Exports | AC2: Yr/Yr Feedstk | AD2: Yield vs 5Yr | AE2: EPA EMTS | AF2: Conversion Rate | AG2: Delta to 5-Yr Average | AH2: Vegetable Oils | AI2: Daily average VO Use | AJ2: Change from 5-Yr Avg | AK2: Vegetable Oils Other than SBO | AL2: Daily Average Other VO Use | AM2: Change from 5-Yr Avg | AN2: Animal Fats & Greases | AO2: % Soybean Oil | AP2: % Vegoil | AQ2: % Animal Fats | AR2: Used Capacity | AS2: Unused Capacity | AT2: Capacity Utilization | AU2: Capacity Utilization change from 5-Yr Average | AV2: HOBO Spread | AX2: Biodiesel Daily Production | AY2: Change from 5-Yr Avg | AZ2: Change from Last Year | BA2: Average Daily SBO Use | BB2: Change from 5-Yr Avg | BC2: Change from Last Year | BD2: VO Use per gallon | BE2: SBO Use per gallon | BF2: SBO Central Ill | BG2: 3-month average SBO Central Ill | BH2: Corn Oil Use per gallon | BI2: Canola Oil Use per gallon | BJ2: Yellow Grease Use per gallon | BK2: UCO | BL2: CWG | BM2: Tallow | BN2: Year-over-Year Change in Capacity | BO2: Canola Oil % of Feedstock Mix | BP2: Corn Oil % of Feedstock Mix | BQ2: SBO % of Feedstock Mix | BR2: Poultry Fat % of Feedstock Mix | BS2: Tallow % of Feedstock Mix | BT2: CWG % of Feedstock Mix | BU2: UCO / Yellow Grease % of Feedstock Mix | BV2: EMTS Biodiesel Production (mil. gal.) | BW2: EIA Biodiesel Production (mil. gal.) | BX2: Delta | BY2: Change from 5-Yr. Avg for Month | BZ2: EPA EMTS | CA2: Annual Capacity | CB2: Used Capacity | CC2: Unused Capacity | CD2: Capacity Utilization | CE2: Net Exports | CF2: Net exports as % of production | CG2: Domestic Use | CI2: Inedible Tallow | CJ2: Yellow Grease | CK2: Other Grease | CL2: check | CN2: Crude soybean oil | CO2: Once-refined soybean oil | CP2: Percent crude | CU2: Crude soybean oil | CV2: Once-refined soybean oil | CW2: Edible Tallow | CX2: Lard | CY2: Poultry Fat | CZ2: Cottonseed Oil | DA2: Corn Oil (food grade) | DB2: Palm Oil | DC2: Canola Oil | DD2: Inedible Tallow | DE2: Yellow Grease | DF2: Other Grease | DG2: Corn Oil (industrial grade) | DI2: Crude soybean oil | DJ2: Once-refined soybean oil | DK2: Edible Tallow | DL2: Lard | DM2: Poultry Fat | DN2: Cottonseed Oil | DO2: Corn Oil (food grade) | DP2: Palm Oil | DQ2: Canola Oil | DR2: Inedible Tallow | DS2: Yellow Grease | DT2: Other Grease | DU2: Corn Oil (industrial grade) | DW2: Annual capacity (mil. gal.) | DX2: Production (mil. gal.) | DY2: Sales of B100 | DZ2: Sales of B100 Included in Biodiesel Blends | EA2: Ending Stocks of B100 | EB2: B100 Stock Change | EC2: Canola Oil | ED2: Corn Oil | EE2: Cottonseed Oil | EF2: Palm Oil | EG2: Soybean Oil | EH2: Other | EI2: Poultry | EJ2: Tallow | EK2: White Grease | EL2: Other | EM2: Yellow Grease | EN2: Other | EO2: Algae | EP2: Other | EQ2: Total | ER2: pounds of feedstock per gallon of biodiesel | ES2: EIA | ET2: Informa | EU2: diff. | EW2: RD Capacity | EX2: Combined Capacity
A3: 36069 | B3: 0 | C3: 0 | D3: 0 | E3: 0 | F3: 0.14845193 | G3: 0 | H3: 0 | I3: 0.021307777 | J3: 0 | K3: 0 | L3: 0 | P3: 0.16975971 | Q3: 7.215755 | S3: 0.023526257 | V3: 0 | AH3: =AK3+F3 -> 0.14845193 | AK3: =SUM(B3:E3,G3) -> 0 | AN3: =SUM(H3:M3) -> 0.021307777 | AO3: =F3/P3 -> 0.87448272 | AP3: =SUM(B3:G3)/P3 -> 0.87448272 | AQ3: =SUM(H3:M3)/P3 -> 0.12551728 | AR3: =S3/(A4-A3)*365 -> 0.2770027 | AS3: =R3-AR3 -> -0.2770027 | AT3: =(S3/(A4-A3)*365)/R3 -> #DIV/0! | BE3: =F3/S3 -> 6.310053
A4: 36100 | B4: 0 | C4: 0 | D4: 0 | E4: 0 | F4: 0.14845193 | G4: 0 | H4: 0 | I4: 0.021307777 | J4: 0 | K4: 0 | L4: 0 | P4: 0.16975971 | Q4: 7.215755 | S4: 0.023526257 | V4: 0 | AH4: =AK4+F4 -> 0.14845193 | AK4: =SUM(B4:E4,G4) -> 0 | AN4: =SUM(H4:M4) -> 0.021307777 | AO4: =F4/P4 -> 0.87448272 | AP4: =SUM(B4:G4)/P4 -> 0.87448272 | AQ4: =SUM(H4:M4)/P4 -> 0.12551728 | AR4: =S4/(A5-A4)*365 -> 0.28623613 | AS4: =R4-AR4 -> -0.28623613 | AT4: =(S4/(A5-A4)*365)/R4 -> #DIV/0! | BE4: =F4/S4 -> 6.310053
A5: 36130 | B5: 0 | C5: 0 | D5: 0 | E5: 0 | F5: 0.14845193 | G5: 0 | H5: 0 | I5: 0.021307777 | J5: 0 | K5: 0 | L5: 0 | P5: 0.16975971 | Q5: 7.215755 | S5: 0.023526257 | V5: 0 | AH5: =AK5+F5 -> 0.14845193 | AK5: =SUM(B5:E5,G5) -> 0 | AN5: =SUM(H5:M5) -> 0.021307777 | AO5: =F5/P5 -> 0.87448272 | AP5: =SUM(B5:G5)/P5 -> 0.87448272 | AQ5: =SUM(H5:M5)/P5 -> 0.12551728 | AR5: =S5/(A6-A5)*365 -> 0.2770027 | AS5: =R5-AR5 -> -0.2770027 | AT5: =(S5/(A6-A5)*365)/R5 -> #DIV/0! | BE5: =F5/S5 -> 6.310053
A6: 36161 | B6: 0 | C6: 0 | D6: 0 | E6: 0 | F6: 0.15748481 | G6: 0 | H6: 0 | I6: 0.022604295 | J6: 0 | K6: 0 | L6: 0 | P6: 0.1800891 | Q6: 7.215755 | S6: 0.024957763 | V6: 0 | AH6: =AK6+F6 -> 0.15748481 | AK6: =SUM(B6:E6,G6) -> 0 | AN6: =SUM(H6:M6) -> 0.022604295 | AO6: =F6/P6 -> 0.87448272 | AP6: =SUM(B6:G6)/P6 -> 0.87448272 | AQ6: =SUM(H6:M6)/P6 -> 0.12551728 | AR6: =S6/(A7-A6)*365 -> 0.29385753 | AS6: =R6-AR6 -> -0.29385753 | AT6: =(S6/(A7-A6)*365)/R6 -> #DIV/0! | BE6: =F6/S6 -> 6.310053
A7: 36192 | B7: 0 | C7: 0 | D7: 0 | E7: 0 | F7: 0.15748481 | G7: 0 | H7: 0 | I7: 0.022604295 | J7: 0 | K7: 0 | L7: 0 | P7: 0.1800891 | Q7: 7.215755 | S7: 0.024957763 | V7: 0 | AH7: =AK7+F7 -> 0.15748481 | AK7: =SUM(B7:E7,G7) -> 0 | AN7: =SUM(H7:M7) -> 0.022604295 | AO7: =F7/P7 -> 0.87448272 | AP7: =SUM(B7:G7)/P7 -> 0.87448272 | AQ7: =SUM(H7:M7)/P7 -> 0.12551728 | AR7: =S7/(A8-A7)*365 -> 0.32534227 | AS7: =R7-AR7 -> -0.32534227 | AT7: =(S7/(A8-A7)*365)/R7 -> #DIV/0! | BE7: =F7/S7 -> 6.310053
A8: 36220 | B8: 0 | C8: 0 | D8: 0 | E8: 0 | F8: 0.15748481 | G8: 0 | H8: 0 | I8: 0.022604295 | J8: 0 | K8: 0 | L8: 0 | P8: 0.1800891 | Q8: 7.215755 | S8: 0.024957763 | V8: 0 | AH8: =AK8+F8 -> 0.15748481 | AK8: =SUM(B8:E8,G8) -> 0 | AN8: =SUM(H8:M8) -> 0.022604295 | AO8: =F8/P8 -> 0.87448272 | AP8: =SUM(B8:G8)/P8 -> 0.87448272 | AQ8: =SUM(H8:M8)/P8 -> 0.12551728 | AR8: =S8/(A9-A8)*365 -> 0.29385753 | AS8: =R8-AR8 -> -0.29385753 | AT8: =(S8/(A9-A8)*365)/R8 -> #DIV/0! | BE8: =F8/S8 -> 6.310053
A9: 36251 | B9: 0 | C9: 0 | D9: 0 | E9: 0 | F9: 0.34572022 | G9: 0 | H9: 0 | I9: 0.049622322 | J9: 0 | K9: 0 | L9: 0 | P9: 0.39534254 | Q9: 7.215755 | S9: 0.054788798 | V9: 0 | AH9: =AK9+F9 -> 0.34572022 | AK9: =SUM(B9:E9,G9) -> 0 | AN9: =SUM(H9:M9) -> 0.049622322 | AO9: =F9/P9 -> 0.87448272 | AP9: =SUM(B9:G9)/P9 -> 0.87448272 | AQ9: =SUM(H9:M9)/P9 -> 0.12551728 | AR9: =S9/(A10-A9)*365 -> 0.66659704 | AS9: =R9-AR9 -> -0.66659704 | AT9: =(S9/(A10-A9)*365)/R9 -> #DIV/0! | BE9: =F9/S9 -> 6.310053
A10: 36281 | B10: 0 | C10: 0 | D10: 0 | E10: 0 | F10: 0.34572022 | G10: 0 | H10: 0 | I10: 0.049622322 | J10: 0 | K10: 0 | L10: 0 | P10: 0.39534254 | Q10: 7.215755 | S10: 0.054788798 | V10: 0 | AH10: =AK10+F10 -> 0.34572022 | AK10: =SUM(B10:E10,G10) -> 0 | AN10: =SUM(H10:M10) -> 0.049622322 | AO10: =F10/P10 -> 0.87448272 | AP10: =SUM(B10:G10)/P10 -> 0.87448272 | AQ10: =SUM(H10:M10)/P10 -> 0.12551728 | AR10: =S10/(A11-A10)*365 -> 0.64509391 | AS10: =R10-AR10 -> -0.64509391 | AT10: =(S10/(A11-A10)*365)/R10 -> #DIV/0! | BE10: =F10/S10 -> 6.310053
A11: 36312 | B11: 0 | C11: 0 | D11: 0 | E11: 0 | F11: 0.34572022 | G11: 0 | H11: 0 | I11: 0.049622322 | J11: 0 | K11: 0 | L11: 0 | P11: 0.39534254 | Q11: 7.215755 | S11: 0.054788798 | V11: 0 | AH11: =AK11+F11 -> 0.34572022 | AK11: =SUM(B11:E11,G11) -> 0 | AN11: =SUM(H11:M11) -> 0.049622322 | AO11: =F11/P11 -> 0.87448272 | AP11: =SUM(B11:G11)/P11 -> 0.87448272 | AQ11: =SUM(H11:M11)/P11 -> 0.12551728 | AR11: =S11/(A12-A11)*365 -> 0.66659704 | AS11: =R11-AR11 -> -0.66659704 | AT11: =(S11/(A12-A11)*365)/R11 -> #DIV/0! | BE11: =F11/S11 -> 6.310053
A12: 36342 | B12: 0 | C12: 0 | D12: 0 | E12: 0 | F12: 0.40001855 | G12: 0 | H12: 0 | I12: 0.057415934 | J12: 0 | K12: 0 | L12: 0 | P12: 0.45743448 | Q12: 7.215755 | S12: 0.063393849 | V12: 0 | AH12: =AK12+F12 -> 0.40001855 | AK12: =SUM(B12:E12,G12) -> 0 | AN12: =SUM(H12:M12) -> 0.057415934 | AO12: =F12/P12 -> 0.87448272 | AP12: =SUM(B12:G12)/P12 -> 0.87448272 | AQ12: =SUM(H12:M12)/P12 -> 0.12551728 | AR12: =S12/(A13-A12)*365 -> 0.74641145 | AS12: =R12-AR12 -> -0.74641145 | AT12: =(S12/(A13-A12)*365)/R12 -> #DIV/0! | BE12: =F12/S12 -> 6.310053
A13: 36373 | B13: 0 | C13: 0 | D13: 0 | E13: 0 | F13: 0.40001855 | G13: 0 | H13: 0 | I13: 0.057415934 | J13: 0 | K13: 0 | L13: 0 | P13: 0.45743448 | Q13: 7.215755 | S13: 0.063393849 | V13: 0 | AH13: =AK13+F13 -> 0.40001855 | AK13: =SUM(B13:E13,G13) -> 0 | AN13: =SUM(H13:M13) -> 0.057415934 | AO13: =F13/P13 -> 0.87448272 | AP13: =SUM(B13:G13)/P13 -> 0.87448272 | AQ13: =SUM(H13:M13)/P13 -> 0.12551728 | AR13: =S13/(A14-A13)*365 -> 0.74641145 | AS13: =R13-AR13 -> -0.74641145 | AT13: =(S13/(A14-A13)*365)/R13 -> #DIV/0! | BE13: =F13/S13 -> 6.310053
A14: 36404 | B14: 0 | C14: 0 | D14: 0 | E14: 0 | F14: 0.40001855 | G14: 0 | H14: 0 | I14: 0.057415934 | J14: 0 | K14: 0 | L14: 0 | P14: 0.45743448 | Q14: 7.215755 | S14: 0.063393849 | V14: 0 | AH14: =AK14+F14 -> 0.40001855 | AK14: =SUM(B14:E14,G14) -> 0 | AN14: =SUM(H14:M14) -> 0.057415934 | AO14: =F14/P14 -> 0.87448272 | AP14: =SUM(B14:G14)/P14 -> 0.87448272 | AQ14: =SUM(H14:M14)/P14 -> 0.12551728 | AR14: =S14/(A15-A14)*365 -> 0.77129183 | AS14: =R14-AR14 -> -0.77129183 | AT14: =(S14/(A15-A14)*365)/R14 -> #DIV/0! | BE14: =F14/S14 -> 6.310053
... A17: 36495 | B17: 0 | C17: 0 | D17: 0 | E17: 0 | F17: 0.59380771 | G17: 0 | H17: 0 | I17: 0.08523111 | J17: 0 | K17: 0 | L17: 0 | P17: 0.67903882 | Q17: 7.215755 | S17: 0.094105028 | V17: 0 | AH17: =AK17+F17 -> 0.59380771 | AK17: =SUM(B17:E17,G17) -> 0 | AN17: =SUM(H17:M17) -> 0.08523111 | AO17: =F17/P17 -> 0.87448272 | AP17: =SUM(B17:G17)/P17 -> 0.87448272 | AQ17: =SUM(H17:M17)/P17 -> 0.12551728 | AR17: =S17/(A18-A17)*365 -> 1.1080108 | AS17: =R17-AR17 -> -1.1080108 | AT17: =(S17/(A18-A17)*365)/R17 -> #DIV/0! | BE17: =F17/S17 -> 6.310053
A18: 36526 | B18: 0 | C18: 0 | D18: 0 | E18: 0 | F18: 0.62993923 | G18: 0 | H18: 0 | I18: 0.090417181 | J18: 0 | K18: 0 | L18: 0 | P18: 0.72035642 | Q18: 7.215755 | S18: 0.099831053 | V18: 0 | AH18: =AK18+F18 -> 0.62993923 | AK18: =SUM(B18:E18,G18) -> 0 | AN18: =SUM(H18:M18) -> 0.090417181 | AO18: =F18/P18 -> 0.87448272 | AP18: =SUM(B18:G18)/P18 -> 0.87448272 | AQ18: =SUM(H18:M18)/P18 -> 0.12551728 | AR18: =S18/(A19-A18)*365 -> 1.1754301 | AS18: =R18-AR18 -> -1.1754301 | AT18: =(S18/(A19-A18)*365)/R18 -> #DIV/0! | AV18: =#REF! -> #REF! | BE18: =F18/S18 -> 6.310053
A19: 36557 | B19: 0 | C19: 0 | D19: 0 | E19: 0 | F19: 0.62993923 | G19: 0 | H19: 0 | I19: 0.090417181 | J19: 0 | K19: 0 | L19: 0 | P19: 0.72035642 | Q19: 7.215755 | S19: 0.099831053 | V19: 0 | AH19: =AK19+F19 -> 0.62993923 | AK19: =SUM(B19:E19,G19) -> 0 | AN19: =SUM(H19:M19) -> 0.090417181 | AO19: =F19/P19 -> 0.87448272 | AP19: =SUM(B19:G19)/P19 -> 0.87448272 | AQ19: =SUM(H19:M19)/P19 -> 0.12551728 | AR19: =S19/(A20-A19)*365 -> 1.2564943 | AS19: =R19-AR19 -> -1.2564943 | AT19: =(S19/(A20-A19)*365)/R19 -> #DIV/0! | AV19: =#REF! -> #REF! | BE19: =F19/S19 -> 6.310053
A20: 36586 | B20: 0 | C20: 0 | D20: 0 | E20: 0 | F20: 0.62993923 | G20: 0 | H20: 0 | I20: 0.090417181 | J20: 0 | K20: 0 | L20: 0 | P20: 0.72035642 | Q20: 7.215755 | S20: 0.099831053 | V20: 0 | AH20: =AK20+F20 -> 0.62993923 | AK20: =SUM(B20:E20,G20) -> 0 | AN20: =SUM(H20:M20) -> 0.090417181 | AO20: =F20/P20 -> 0.87448272 | AP20: =SUM(B20:G20)/P20 -> 0.87448272 | AQ20: =SUM(H20:M20)/P20 -> 0.12551728 | AR20: =S20/(A21-A20)*365 -> 1.1754301 | AS20: =R20-AR20 -> -1.1754301 | AT20: =(S20/(A21-A20)*365)/R20 -> #DIV/0! | AV20: ='[1]Monthly SBO'!$K4 -> 0.53514348 | BE20: =F20/S20 -> 6.310053
A21: 36617 | B21: 0 | C21: 0 | D21: 0 | E21: 0 | F21: 1.3828809 | G21: 0 | H21: 0 | I21: 0.19848929 | J21: 0 | K21: 0 | L21: 0 | P21: 1.5813702 | Q21: 7.215755 | S21: 0.21915519 | V21: 0 | AH21: =AK21+F21 -> 1.3828809 | AK21: =SUM(B21:E21,G21) -> 0 | AN21: =SUM(H21:M21) -> 0.19848929 | AO21: =F21/P21 -> 0.87448272 | AP21: =SUM(B21:G21)/P21 -> 0.87448272 | AQ21: =SUM(H21:M21)/P21 -> 0.12551728 | AR21: =S21/(A22-A21)*365 -> 2.6663882 | AS21: =R21-AR21 -> -2.6663882 | AT21: =(S21/(A22-A21)*365)/R21 -> #DIV/0! | AV21: ='[1]Monthly SBO'!$K5 -> 0.68330421 | BE21: =F21/S21 -> 6.310053
A22: 36647 | B22: 0 | C22: 0 | D22: 0 | E22: 0 | F22: 1.3828809 | G22: 0 | H22: 0 | I22: 0.19848929 | J22: 0 | K22: 0 | L22: 0 | P22: 1.5813702 | Q22: 7.215755 | S22: 0.21915519 | V22: 0 | AH22: =AK22+F22 -> 1.3828809 | AK22: =SUM(B22:E22,G22) -> 0 | AN22: =SUM(H22:M22) -> 0.19848929 | AO22: =F22/P22 -> 0.87448272 | AP22: =SUM(B22:G22)/P22 -> 0.87448272 | AQ22: =SUM(H22:M22)/P22 -> 0.12551728 | AR22: =S22/(A23-A22)*365 -> 2.5803756 | AS22: =R22-AR22 -> -2.5803756 | AT22: =(S22/(A23-A22)*365)/R22 -> #DIV/0! | AV22: ='[1]Monthly SBO'!$K6 -> 0.57093273 | BE22: =F22/S22 -> 6.310053
A23: 36678 | B23: 0 | C23: 0 | D23: 0 | E23: 0 | F23: 1.3828809 | G23: 0 | H23: 0 | I23: 0.19848929 | J23: 0 | K23: 0 | L23: 0 | P23: 1.5813702 | Q23: 7.215755 | S23: 0.21915519 | V23: 0 | AH23: =AK23+F23 -> 1.3828809 | AK23: =SUM(B23:E23,G23) -> 0 | AN23: =SUM(H23:M23) -> 0.19848929 | AO23: =F23/P23 -> 0.87448272 | AP23: =SUM(B23:G23)/P23 -> 0.87448272 | AQ23: =SUM(H23:M23)/P23 -> 0.12551728 | AR23: =S23/(A24-A23)*365 -> 2.6663882 | AS23: =R23-AR23 -> -2.6663882 | AT23: =(S23/(A24-A23)*365)/R23 -> #DIV/0! | AV23: ='[1]Monthly SBO'!$K7 -> 0.45927273 | BE23: =F23/S23 -> 6.310053
A24: 36708 | B24: 0 | C24: 0 | D24: 0 | E24: 0 | F24: 1.6000742 | G24: 0 | H24: 0 | I24: 0.22966374 | J24: 0 | K24: 0 | L24: 0 | P24: 1.8297379 | Q24: 7.215755 | S24: 0.2535754 | V24: 0 | AH24: =AK24+F24 -> 1.6000742 | AK24: =SUM(B24:E24,G24) -> 0 | AN24: =SUM(H24:M24) -> 0.22966374 | AO24: =F24/P24 -> 0.87448272 | AP24: =SUM(B24:G24)/P24 -> 0.87448272 | AQ24: =SUM(H24:M24)/P24 -> 0.12551728 | AR24: =S24/(A25-A24)*365 -> 2.9856458 | AS24: =R24-AR24 -> -2.9856458 | AT24: =(S24/(A25-A24)*365)/R24 -> #DIV/0! | AV24: ='[1]Monthly SBO'!$K8 -> 0.39142737 | BE24: =F24/S24 -> 6.310053
A25: 36739 | B25: 0 | C25: 0 | D25: 0 | E25: 0 | F25: 1.6000742 | G25: 0 | H25: 0 | I25: 0.22966374 | J25: 0 | K25: 0 | L25: 0 | P25: 1.8297379 | Q25: 7.215755 | S25: 0.2535754 | V25: 0 | AH25: =AK25+F25 -> 1.6000742 | AK25: =SUM(B25:E25,G25) -> 0 | AN25: =SUM(H25:M25) -> 0.22966374 | AO25: =F25/P25 -> 0.87448272 | AP25: =SUM(B25:G25)/P25 -> 0.87448272 | AQ25: =SUM(H25:M25)/P25 -> 0.12551728 | AR25: =S25/(A26-A25)*365 -> 2.9856458 | AS25: =R25-AR25 -> -2.9856458 | AT25: =(S25/(A26-A25)*365)/R25 -> #DIV/0! | AV25: ='[1]Monthly SBO'!$K9 -> 0.27568522 | BE25: =F25/S25 -> 6.310053
A26: 36770 | B26: 0 | C26: 0 | D26: 0 | E26: 0 | F26: 1.6000742 | G26: 0 | H26: 0 | I26: 0.22966374 | J26: 0 | K26: 0 | L26: 0 | P26: 1.8297379 | Q26: 7.215755 | S26: 0.2535754 | V26: 0 | AH26: =AK26+F26 -> 1.6000742 | AK26: =SUM(B26:E26,G26) -> 0 | AN26: =SUM(H26:M26) -> 0.22966374 | AO26: =F26/P26 -> 0.87448272 | AP26: =SUM(B26:G26)/P26 -> 0.87448272 | AQ26: =SUM(H26:M26)/P26 -> 0.12551728 | AR26: =S26/(A27-A26)*365 -> 3.0851673 | AS26: =R26-AR26 -> -3.0851673 | AT26: =(S26/(A27-A26)*365)/R26 -> #DIV/0! | AV26: ='[1]Monthly SBO'!$K10 -> 0.184375 | BE26: =F26/S26 -> 6.310053
A27: 36800 | B27: 0 | C27: 0 | D27: 0 | E27: 0 | F27: 0.10594551 | G27: 0 | H27: 0 | I27: 0.015206696 | J27: 0 | K27: 0 | L27: 0 | P27: 0.1211522 | Q27: 7.215755 | S27: 0.016789955 | V27: 0 | AH27: =AK27+F27 -> 0.10594551 | AK27: =SUM(B27:E27,G27) -> 0 | AN27: =SUM(H27:M27) -> 0.015206696 | AO27: =F27/P27 -> 0.87448272 | AP27: =SUM(B27:G27)/P27 -> 0.87448272 | AQ27: =SUM(H27:M27)/P27 -> 0.12551728 | AR27: =S27/(A28-A27)*365 -> 0.19768818 | AS27: =R27-AR27 -> -0.19768818 | AT27: =(S27/(A28-A27)*365)/R27 -> #DIV/0! | AV27: ='[1]Monthly SBO'!$K11 -> 0.16036364 | BE27: =F27/S27 -> 6.310053
A28: 36831 | B28: 0 | C28: 0 | D28: 0 | E28: 0 | F28: 0.10594551 | G28: 0 | H28: 0 | I28: 0.015206696 | J28: 0 | K28: 0 | L28: 0 | P28: 0.1211522 | Q28: 7.215755 | S28: 0.016789955 | V28: 0 | AH28: =AK28+F28 -> 0.10594551 | AK28: =SUM(B28:E28,G28) -> 0 | AN28: =SUM(H28:M28) -> 0.015206696 | AO28: =F28/P28 -> 0.87448272 | AP28: =SUM(B28:G28)/P28 -> 0.87448272 | AQ28: =SUM(H28:M28)/P28 -> 0.12551728 | AR28: =S28/(A29-A28)*365 -> 0.20427779 | AS28: =R28-AR28 -> -0.20427779 | AT28: =(S28/(A29-A28)*365)/R28 -> #DIV/0! | AV28: ='[1]Monthly SBO'!$K12 -> 0.119312 | BE28: =F28/S28 -> 6.310053
A29: 36861 | B29: 0 | C29: 0 | D29: 0 | E29: 0 | F29: 0.10594551 | G29: 0 | H29: 0 | I29: 0.015206696 | J29: 0 | K29: 0 | L29: 0 | P29: 0.1211522 | Q29: 7.215755 | S29: 0.016789955 | V29: 0 | AH29: =AK29+F29 -> 0.10594551 | AK29: =SUM(B29:E29,G29) -> 0 | AN29: =SUM(H29:M29) -> 0.015206696 | AO29: =F29/P29 -> 0.87448272 | AP29: =SUM(B29:G29)/P29 -> 0.87448272 | AQ29: =SUM(H29:M29)/P29 -> 0.12551728 | AR29: =S29/(A30-A29)*365 -> 0.19768818 | AS29: =R29-AR29 -> -0.19768818 | AT29: =(S29/(A30-A29)*365)/R29 -> #DIV/0! | AV29: ='[1]Monthly SBO'!$K13 -> 0.195629 | BE29: =F29/S29 -> 6.310053
A30: 36892 | B30: 0 | C30: 0 | D30: 0 | E30: 0 | F30: 3.6232369 | G30: 0 | H30: 0 | I30: 0.52005471 | J30: 0 | K30: 0 | L30: 0 | S30: 0.728 | V30: 0.5 | AH30: =AK30+F30 -> 3.6232369 | AK30: =SUM(B30:E30,G30) -> 0 | AN30: =SUM(H30:M30) -> 0.52005471 | AO30: =F30/P30 -> #DIV/0! | AP30: =SUM(B30:G30)/P30 -> #DIV/0! | AQ30: =SUM(H30:M30)/P30 -> #DIV/0! | AR30: =S30/(A31-A30)*365 -> 8.5716129 | AS30: =R30-AR30 -> -8.5716129 | AT30: =(S30/(A31-A30)*365)/R30 -> #DIV/0! | AV30: ='[1]Monthly SBO'!$K14 -> 0.26882 | BE30: =F30/S30 -> 4.9769737 | BN30: =AR30-AR18 -> 7.3961828
A31: 36923 | B31: 0 | C31: 0 | D31: 0 | E31: 0 | F31: 3.6232369 | G31: 0 | H31: 0 | I31: 0.52005471 | J31: 0 | K31: 0 | L31: 0 | S31: 0.658 | V31: 0.5 | AH31: =AK31+F31 -> 3.6232369 | AK31: =SUM(B31:E31,G31) -> 0 | AN31: =SUM(H31:M31) -> 0.52005471 | AO31: =F31/P31 -> #DIV/0! | AP31: =SUM(B31:G31)/P31 -> #DIV/0! | AQ31: =SUM(H31:M31)/P31 -> #DIV/0! | AR31: =S31/(A32-A31)*365 -> 8.5775 | AS31: =R31-AR31 -> -8.5775 | AT31: =(S31/(A32-A31)*365)/R31 -> #DIV/0! | AV31: ='[1]Monthly SBO'!$K15 -> 0.34352105 | BE31: =F31/S31 -> 5.506439 | BN31: =AR31-AR19 -> 7.3210057
A32: 36951 | B32: 0 | C32: 0 | D32: 0 | E32: 0 | F32: 3.6232369 | G32: 0 | H32: 0 | I32: 0.52005471 | J32: 0 | K32: 0 | L32: 0 | S32: 0.728 | V32: 0.5 | AH32: =AK32+F32 -> 3.6232369 | AK32: =SUM(B32:E32,G32) -> 0 | AN32: =SUM(H32:M32) -> 0.52005471 | AO32: =F32/P32 -> #DIV/0! | AP32: =SUM(B32:G32)/P32 -> #DIV/0! | AQ32: =SUM(H32:M32)/P32 -> #DIV/0! | AR32: =S32/(A33-A32)*365 -> 8.5716129 | AS32: =R32-AR32 -> -8.5716129 | AT32: =(S32/(A33-A32)*365)/R32 -> #DIV/0! | AV32: ='[1]Monthly SBO'!$K16 -> 0.48214 | BE32: =F32/S32 -> 4.9769737 | BN32: =AR32-AR20 -> 7.3961828
A33: 36982 | B33: 0 | C33: 0 | D33: 0 | E33: 0 | F33: 6.6667471 | G33: 0 | H33: 0 | I33: 0.95689941 | J33: 0 | K33: 0 | L33: 0 | S33: 0.705 | V33: 0.5 | AH33: =AK33+F33 -> 6.6667471 | AK33: =SUM(B33:E33,G33) -> 0 | AN33: =SUM(H33:M33) -> 0.95689941 | AO33: =F33/P33 -> #DIV/0! | AP33: =SUM(B33:G33)/P33 -> #DIV/0! | AQ33: =SUM(H33:M33)/P33 -> #DIV/0! | AR33: =S33/(A34-A33)*365 -> 8.5775 | AS33: =R33-AR33 -> -8.5775 | AT33: =(S33/(A34-A33)*365)/R33 -> #DIV/0! | AV33: ='[1]Monthly SBO'!$K17 -> 0.393732 | BE33: =F33/S33 -> 9.4563788 | BN33: =AR33-AR21 -> 5.9111118
A34: 37012 | B34: 0 | C34: 0 | D34: 0 | E34: 0 | F34: 6.6667471 | G34: 0 | H34: 0 | I34: 0.95689941 | J34: 0 | K34: 0 | L34: 0 | S34: 0.728 | V34: 0.5 | AH34: =AK34+F34 -> 6.6667471 | AK34: =SUM(B34:E34,G34) -> 0 | AN34: =SUM(H34:M34) -> 0.95689941 | AO34: =F34/P34 -> #DIV/0! | AP34: =SUM(B34:G34)/P34 -> #DIV/0! | AQ34: =SUM(H34:M34)/P34 -> #DIV/0! | AR34: =S34/(A35-A34)*365 -> 8.5716129 | AS34: =R34-AR34 -> -8.5716129 | AT34: =(S34/(A35-A34)*365)/R34 -> #DIV/0! | AV34: ='[1]Monthly SBO'!$K18 -> 0.33968818 | BE34: =F34/S34 -> 9.1576196 | BN34: =AR34-AR22 -> 5.9912373
A35: 37043 | B35: 0 | C35: 0 | D35: 0 | E35: 0 | F35: 6.6667471 | G35: 0 | H35: 0 | I35: 0.95689941 | J35: 0 | K35: 0 | L35: 0 | S35: 0.705 | V35: 0.5 | AH35: =AK35+F35 -> 6.6667471 | AK35: =SUM(B35:E35,G35) -> 0 | AN35: =SUM(H35:M35) -> 0.95689941 | AO35: =F35/P35 -> #DIV/0! | AP35: =SUM(B35:G35)/P35 -> #DIV/0! | AQ35: =SUM(H35:M35)/P35 -> #DIV/0! | AR35: =S35/(A36-A35)*365 -> 8.5775 | AS35: =R35-AR35 -> -8.5775 | AT35: =(S35/(A36-A35)*365)/R35 -> #DIV/0! | AV35: ='[1]Monthly SBO'!$K19 -> 0.38598381 | BE35: =F35/S35 -> 9.4563788 | BN35: =AR35-AR23 -> 5.9111118
A36: 37073 | B36: 0 | C36: 0 | D36: 0 | E36: 0 | F36: 10.637581 | G36: 0 | H36: 0 | I36: 1.5268458 | J36: 0 | K36: 0 | L36: 0 | S36: 0.728 | V36: 0.5 | AH36: =AK36+F36 -> 10.637581 | AK36: =SUM(B36:E36,G36) -> 0 | AN36: =SUM(H36:M36) -> 1.5268458 | AO36: =F36/P36 -> #DIV/0! | AP36: =SUM(B36:G36)/P36 -> #DIV/0! | AQ36: =SUM(H36:M36)/P36 -> #DIV/0! | AR36: =S36/(A37-A36)*365 -> 8.5716129 | AS36: =R36-AR36 -> -8.5716129 | AT36: =(S36/(A37-A36)*365)/R36 -> #DIV/0! | AV36: ='[1]Monthly SBO'!$K20 -> 0.61822 | BE36: =F36/S36 -> 14.612061 | BN36: =AR36-AR24 -> 5.5859671
A37: 37104 | B37: 0 | C37: 0 | D37: 0 | E37: 0 | F37: 10.637581 | G37: 0 | H37: 0 | I37: 1.5268458 | J37: 0 | K37: 0 | L37: 0 | S37: 0.728 | V37: 0.5 | AH37: =AK37+F37 -> 10.637581 | AK37: =SUM(B37:E37,G37) -> 0 | AN37: =SUM(H37:M37) -> 1.5268458 | AO37: =F37/P37 -> #DIV/0! | AP37: =SUM(B37:G37)/P37 -> #DIV/0! | AQ37: =SUM(H37:M37)/P37 -> #DIV/0! | AR37: =S37/(A38-A37)*365 -> 8.5716129 | AS37: =R37-AR37 -> -8.5716129 | AT37: =(S37/(A38-A37)*365)/R37 -> #DIV/0! | AV37: ='[1]Monthly SBO'!$K21 -> 0.63132 | BE37: =F37/S37 -> 14.612061 | BN37: =AR37-AR25 -> 5.5859671
A38: 37135 | B38: 0 | C38: 0 | D38: 0 | E38: 0 | F38: 10.637581 | G38: 0 | H38: 0 | I38: 1.5268458 | J38: 0 | K38: 0 | L38: 0 | S38: 0.705 | V38: 0.5 | AH38: =AK38+F38 -> 10.637581 | AK38: =SUM(B38:E38,G38) -> 0 | AN38: =SUM(H38:M38) -> 1.5268458 | AO38: =F38/P38 -> #DIV/0! | AP38: =SUM(B38:G38)/P38 -> #DIV/0! | AQ38: =SUM(H38:M38)/P38 -> #DIV/0! | AR38: =S38/(A39-A38)*365 -> 8.5775 | AS38: =R38-AR38 -> -8.5775 | AT38: =(S38/(A39-A38)*365)/R38 -> #DIV/0! | AV38: ='[1]Monthly SBO'!$K22 -> 0.50657 | BE38: =F38/S38 -> 15.088767 | BN38: =AR38-AR26 -> 5.4923327
A39: 37165 | B39: 0 | C39: 0 | D39: 0 | E39: 0 | F39: 4.705331 | G39: 0 | H39: 0 | I39: 0.67537112 | J39: 0 | K39: 0 | L39: 0 | S39: 0.728 | V39: 0.5 | AH39: =AK39+F39 -> 4.705331 | AK39: =SUM(B39:E39,G39) -> 0 | AN39: =SUM(H39:M39) -> 0.67537112 | AO39: =F39/P39 -> #DIV/0! | AP39: =SUM(B39:G39)/P39 -> #DIV/0! | AQ39: =SUM(H39:M39)/P39 -> #DIV/0! | AR39: =S39/(A40-A39)*365 -> 8.5716129 | AS39: =R39-AR39 -> -8.5716129 | AT39: =(S39/(A40-A39)*365)/R39 -> #DIV/0! | AV39: ='[1]Monthly SBO'!$K23 -> 0.51720348 | BE39: =F39/S39 -> 6.4633667 | BN39: =AR39-AR27 -> 8.3739247
A40: 37196 | B40: 0 | C40: 0 | D40: 0 | E40: 0 | F40: 4.705331 | G40: 0 | H40: 0 | I40: 0.67537112 | J40: 0 | K40: 0 | L40: 0 | S40: 0.705 | V40: 0.5 | AH40: =AK40+F40 -> 4.705331 | AK40: =SUM(B40:E40,G40) -> 0 | AN40: =SUM(H40:M40) -> 0.67537112 | AO40: =F40/P40 -> #DIV/0! | AP40: =SUM(B40:G40)/P40 -> #DIV/0! | AQ40: =SUM(H40:M40)/P40 -> #DIV/0! | AR40: =S40/(A41-A40)*365 -> 8.5775 | AS40: =R40-AR40 -> -8.5775 | AT40: =(S40/(A41-A40)*365)/R40 -> #DIV/0! | AV40: ='[1]Monthly SBO'!$K24 -> 0.65499 | BE40: =F40/S40 -> 6.6742283 | BN40: =AR40-AR28 -> 8.3732222
A41: 37226 | B41: 0 | C41: 0 | D41: 0 | E41: 0 | F41: 4.705331 | G41: 0 | H41: 0 | I41: 0.67537112 | J41: 0 | K41: 0 | L41: 0 | S41: 0.728 | V41: 0.5 | AH41: =AK41+F41 -> 4.705331 | AK41: =SUM(B41:E41,G41) -> 0 | AN41: =SUM(H41:M41) -> 0.67537112 | AO41: =F41/P41 -> #DIV/0! | AP41: =SUM(B41:G41)/P41 -> #DIV/0! | AQ41: =SUM(H41:M41)/P41 -> #DIV/0! | AR41: =S41/(A42-A41)*365 -> 8.5716129 | AS41: =R41-AR41 -> -8.5716129 | AT41: =(S41/(A42-A41)*365)/R41 -> #DIV/0! | AV41: ='[1]Monthly SBO'!$K25 -> 0.66284842 | BE41: =F41/S41 -> 6.4633667 | BN41: =AR41-AR29 -> 8.3739247
... A125: 39783 | B125: 24.1 | C125: 3 | D125: 0 | E125: 65.586 | F125: 207 | G125: 0 | H125: 9 | I125: 0 | J125: 0 | K125: 13 | L125: 0 | S125: 44.168 | V125: 26.893261 | AH125: =AK125+F125 -> 299.686 | AK125: =SUM(B125:E125,G125) -> 92.686 | AN125: =SUM(H125:M125) -> 22 | AO125: =F125/P125 -> #DIV/0! | AP125: =SUM(B125:G125)/P125 -> #DIV/0! | AQ125: =SUM(H125:M125)/P125 -> #DIV/0! | AR125: =S125/(A126-A125)*365 -> 520.04258 | AS125: =R125-AR125 -> -520.04258 | AT125: =(S125/(A126-A125)*365)/R125 -> #DIV/0! | AV125: ='[1]Monthly SBO'!$K109 -> 0.91726545 | BE125: =F125/S125 -> 4.686651 | BN125: =AR125-AR113 -> 12.763226
A126: 39814 | B126: 44 | C126: 0 | D126: 0 | E126: 0 | F126: 152 | G126: 0 | H126: 16 | I126: 69 | J126: 12 | K126: 1 | L126: 3 | M126: 0 | N126: 0 | O126: =MROUND((O127/SUM(H127:N127,B127:F127))*SUM(B126:F126,H126:N126),1) -> 0 | P126: 297 | Q126: 7.0075699 | R126: 2148.033 | S126: 42.382738 | T126: 13.934949 | U126: 20.565349 | V126: 34.287863 | W126: 7.394602 | X126: =T126+U126 -> 34.500298 | Z126: =V126/(X127/31) -> 26.749492 | AA126: =P126-SUM(B126:O126) -> 0 | AB126: =P126-AA126 -> 297 | AF126: =(2204.622/300)/Q126 -> 1.0486859 | AH126: =AK126+F126 -> 196 | AI126: =AH126/31 -> 6.3225806 | AK126: =SUM(B126:E126,G126) -> 44 | AL126: =AK126/31 -> 1.4193548 | AN126: =SUM(H126:M126) -> 101 | AO126: =F126/P126 -> 0.51178451 | AP126: =SUM(B126:G126)/P126 -> 0.65993266 | AQ126: =SUM(H126:M126)/P126 -> 0.34006734 | AR126: =S126/(A127-A126)*365 -> 499.02256 | AS126: =R126-AR126 -> 1649.0104 | AT126: =(S126/(A127-A126)*365)/R126 -> 0.23231606 | AV126: ='[1]Monthly SBO'!$K110 -> 1.134549 | AZ126: =AX126-AX114 -> 0 | BA126: =F126/31 -> 4.9032258 | BD126: =AH126/X126 -> 5.6811103 | BE126: =F126/S126 -> 3.5863658 | BF126: =#REF! -> #REF! | BH126: =C126/S126 -> 0 | BI126: =B126/S126 -> 1.0381585 | BJ126: =SUM(L126:M126)*#REF!/S126 -> #REF! | BK126: =SUM(L126:M126)*'[12]Yellow Grease Complex'!$BH$120/S126 -> 0 | BL126: =J127/S127 -> 0.29911666 | BM126: =I127/S127 -> 1.25629 | BN126: =AR126-AR114 -> -92.866149 | BO126: =B126/$P126 -> 0.14814815 | BP126: =C126/$P126 -> 0 | BQ126: =F126/$P126 -> 0.51178451 | BR126: =H126/$P126 -> 0.053872054 | BS126: =I126/$P126 -> 0.23232323 | BT126: =J126/$P126 -> 0.04040404 | BU126: {=SUM(K126:M126/$P126)} -> 0.013468013
A127: 39845 | B127: 15 | C127: 0 | D127: 0 | E127: 0 | F127: 146 | G127: 0 | H127: 15 | I127: 42 | J127: 10 | K127: 0 | L127: 4 | M127: 0 | N127: 0 | O127: =MROUND((O128/SUM(H128:N128,B128:F128))*SUM(B127:F127,H127:N127),1) -> 0 | P127: 232 | Q127: 6.9395065 | R127: 2148.033 | S127: 33.431772 | T127: 18.031419 | U127: 21.704803 | V127: 30.371949 | W127: =V127-V126 -> -3.915914 | X127: =T127+U127 -> 39.736222 | Z127: =V127/(X128/28) -> 31.113861 | AA127: =P127-SUM(B127:O127) -> 0 | AB127: =P127-AA127 -> 232 | AF127: =(2204.622/300)/Q127 -> 1.0589716 | AH127: =AK127+F127 -> 161 | AI127: =AH127/28 -> 5.75 | AK127: =SUM(B127:E127,G127) -> 15 | AL127: =AK127/28 -> 0.53571429 | AN127: =SUM(H127:M127) -> 71 | AO127: =F127/P127 -> 0.62931034 | AP127: =SUM(B127:G127)/P127 -> 0.69396552 | AQ127: =SUM(H127:M127)/P127 -> 0.30603448 | AR127: =S127/(A128-A127)*365 -> 435.80703 | AS127: =R127-AR127 -> 1712.226 | AT127: =(S127/(A128-A127)*365)/R127 -> 0.20288656 | AV127: ='[1]Monthly SBO'!$K111 -> 1.1494758 | AZ127: =AX127-AX115 -> 0 | BA127: =F127/28 -> 5.2142857 | BD127: =AH127/X127 -> 4.0517189 | BE127: =F127/S127 -> 4.3671032 | BF127: =[2]Prices!$L472 -> 28.93 | BH127: =C127/S127 -> 0 | BI127: =B127/S127 -> 0.44867499 | BJ127: =SUM(L127:M127)*'[12]Yellow Grease Complex'!$BH$119/S127 -> 0 | BK127: =SUM(L127:M127)*'[12]Yellow Grease Complex'!$BH$120/S127 -> 0 | BL127: =J128/S128 -> 0.75204665 | BM127: =I128/S128 -> 1.3160816 | BN127: =AR127-AR115 -> -131.89383 | BO127: =B127/$P127 -> 0.064655172 | BP127: =C127/$P127 -> 0 | BQ127: =F127/$P127 -> 0.62931034 | BR127: =H127/$P127 -> 0.064655172 | BS127: =I127/$P127 -> 0.18103448 | BT127: =J127/$P127 -> 0.043103448 | BU127: {=SUM(K127:M127/$P127)} -> 0.017241379
A128: 39873 | B128: 0 | C128: 0 | D128: 0 | E128: 0 | F128: 102 | G128: 0 | H128: 7 | I128: 35 | J128: 20 | K128: 0 | L128: 6 | M128: 0 | N128: 0 | O128: 0 | P128: 170 | Q128: 6.3923965 | R128: 2093.283 | S128: 26.594095 | T128: 11.987791 | U128: 15.344547 | V128: 29.673167 | W128: =V128-V127 -> -0.698782 | X128: =T128+U128 -> 27.332338 | Z128: =V128/(X129/31) -> 31.501081 | AA128: =P128-SUM(B128:O128) -> 0 | AB128: =P128-AA128 -> 170 | AF128: =(2204.622/300)/Q128 -> 1.1496064 | AH128: =AK128+F128 -> 102 | AI128: =AH128/31 -> 3.2903226 | AK128: =SUM(B128:E128,G128) -> 0 | AL128: =AK128/31 -> 0 | AN128: =SUM(H128:M128) -> 68 | AO128: =F128/P128 -> 0.6 | AP128: =SUM(B128:G128)/P128 -> 0.6 | AQ128: =SUM(H128:M128)/P128 -> 0.4 | AR128: =S128/(A129-A128)*365 -> 313.12402 | AS128: =R128-AR128 -> 1780.159 | AT128: =(S128/(A129-A128)*365)/R128 -> 0.14958514 | AV128: ='[1]Monthly SBO'!$K112 -> 1.0955618 | AZ128: =AX128-AX116 -> 0 | BA128: =F128/31 -> 3.2903226 | BD128: =AH128/X128 -> 3.7318432 | BE128: =F128/S128 -> 3.8354379 | BF128: =[2]Prices!$L473 -> 28.23 | BG128: =AVERAGE(BF126:BF128) -> #REF! | BH128: =C128/S128 -> 0 | BI128: =B128/S128 -> 0 | BJ128: =SUM(L128:M128)*'[12]Yellow Grease Complex'!$BH$119/S128 -> 0 | BK128: =SUM(L128:M128)*'[12]Yellow Grease Complex'!$BH$120/S128 -> 0 | BL128: =J129/S129 -> 1.1359309 | BM128: =I129/S129 -> 0.99393956 | BN128: =AR128-AR116 -> -274.1963 | BO128: =B128/$P128 -> 0 | BP128: =C128/$P128 -> 0 | BQ128: =F128/$P128 -> 0.6 | BR128: =H128/$P128 -> 0.041176471 | BS128: =I128/$P128 -> 0.20588235 | BT128: =J128/$P128 -> 0.11764706 | BU128: {=SUM(K128:M128/$P128)} -> 0.035294118
A129: 39904 | B129: 0 | C129: 4 | D129: 0 | E129: 0 | F129: 102 | G129: 0 | H129: 8 | I129: 28 | J129: 32 | K129: 2 | L129: 12 | M129: 0 | N129: 0 | O129: 0 | P129: 188 | Q129: 6.6735942 | R129: 2080.783 | S129: 28.170727 | T129: 12.790476 | U129: 16.410686 | V129: 28.575462 | W129: =V129-V128 -> -1.097705 | X129: =T129+U129 -> 29.201162 | Z129: =V129/(X130/30) -> 21.918238 | AA129: =P129-SUM(B129:O129) -> 0 | AB129: =P129-AA129 -> 188 | AF129: =(2204.622/300)/Q129 -> 1.1011667 | AH129: =AK129+F129 -> 106 | AI129: =AH129/30 -> 3.5333333 | AK129: =SUM(B129:E129,G129) -> 4 | AL129: =AK129/30 -> 0.13333333 | AN129: =SUM(H129:M129) -> 82 | AO129: =F129/P129 -> 0.54255319 | AP129: =SUM(B129:G129)/P129 -> 0.56382979 | AQ129: =SUM(H129:M129)/P129 -> 0.43617021 | AR129: =S129/(A130-A129)*365 -> 342.74385 | AS129: =R129-AR129 -> 1738.0392 | AT129: =(S129/(A130-A129)*365)/R129 -> 0.16471869 | AV129: ='[1]Monthly SBO'!$K113 -> 1.338721 | AZ129: =AX129-AX117 -> 0 | BA129: =F129/30 -> 3.4 | BD129: =AH129/X129 -> 3.6299925 | BE129: =F129/S129 -> 3.6207798 | BF129: =[2]Prices!$L474 -> 32.76 | BG129: =AVERAGE(BF127:BF129) -> 29.973333 | BH129: =C129/S129 -> 0.14199137 | BI129: =B129/S129 -> 0 | BJ129: =SUM(L129:M129)*'[12]Yellow Grease Complex'!$BH$119/S129 -> 0 | BK129: =SUM(L129:M129)*'[12]Yellow Grease Complex'!$BH$120/S129 -> 0 | BL129: =J130/S130 -> 0.93455545 | BM129: =I130/S130 -> 1.5264406 | BN129: =AR129-AR117 -> -305.44749 | BO129: =B129/$P129 -> 0 | BP129: =C129/$P129 -> 0.021276596 | BQ129: =F129/$P129 -> 0.54255319 | BR129: =H129/$P129 -> 0.042553191 | BS129: =I129/$P129 -> 0.14893617 | BT129: =J129/$P129 -> 0.17021277 | BU129: {=SUM(K129:M129/$P129)} -> 0.074468085
A130: 39934 | B130: 2 | C130: 8 | D130: 0 | E130: 0 | F130: 94 | G130: 0 | H130: 10 | I130: 49 | J130: 30 | K130: 0 | L130: 13 | M130: 1 | N130: 0 | O130: 0 | P130: 207 | Q130: 6.4484326 | R130: 2140.783 | S130: 32.100824 | T130: 19.078331 | U130: 20.033566 | V130: 21.458951 | W130: =V130-V129 -> -7.116511 | X130: =T130+U130 -> 39.111897 | Z130: =V130/(X131/31) -> 16.961597 | AA130: =P130-SUM(B130:O130) -> 0 | AB130: =P130-AA130 -> 207 | AF130: =(2204.622/300)/Q130 -> 1.1396165 | AH130: =AK130+F130 -> 104 | AI130: =AH130/31 -> 3.3548387 | AK130: =SUM(B130:E130,G130) -> 10 | AL130: =AK130/31 -> 0.32258065 | AN130: =SUM(H130:M130) -> 103 | AO130: =F130/P130 -> 0.45410628 | AP130: =SUM(B130:G130)/P130 -> 0.50241546 | AQ130: =SUM(H130:M130)/P130 -> 0.49758454 | AR130: =S130/(A131-A130)*365 -> 377.96131 | AS130: =R130-AR130 -> 1762.8217 | AT130: =(S130/(A131-A130)*365)/R130 -> 0.17655284 | AV130: ='[1]Monthly SBO'!$K114 -> 1.412795 | AZ130: =AX130-AX118 -> 0 | BA130: =F130/31 -> 3.0322581 | BD130: =AH130/X130 -> 2.6590375 | BE130: =F130/S130 -> 2.9282737 | BF130: =[2]Prices!$L475 -> 36.06 | BG130: =AVERAGE(BF128:BF130) -> 32.35 | BH130: =C130/S130 -> 0.24921479 | BI130: =B130/S130 -> 0.062303697 | BJ130: =SUM(L130:M130)*'[12]Yellow Grease Complex'!$BH$119/S130 -> 0 | BK130: =SUM(L130:M130)*'[12]Yellow Grease Complex'!$BH$120/S130 -> 0 | BL130: =J131/S131 -> 1.0122762 | BM130: =I131/S131 -> 1.220686 | BN130: =AR130-AR118 -> -261.02417 | BO130: =B130/$P130 -> 0.0096618357 | BP130: =C130/$P130 -> 0.038647343 | BQ130: =F130/$P130 -> 0.45410628 | BR130: =H130/$P130 -> 0.048309179 | BS130: =I130/$P130 -> 0.23671498 | BT130: =J130/$P130 -> 0.14492754 | BU130: {=SUM(K130:M130/$P130)} -> 0.06763285
A131: 39965 | B131: 2 | C131: 4 | D131: 0 | E131: 0 | F131: 112 | G131: 0 | H131: 11 | I131: 41 | J131: 34 | K131: 20 | L131: 12 | M131: 0 | N131: 0 | O131: 0 | P131: 236 | Q131: 7.0263877 | R131: 2082.783 | S131: 33.587671 | T131: 18.689134 | U131: 20.530492 | V131: 15.989069 | W131: =V131-V130 -> -5.469882 | X131: =T131+U131 -> 39.219626 | Z131: =V131/(X132/30) -> 10.578129 | AA131: =P131-SUM(B131:O131) -> 0 | AB131: =P131-AA131 -> 236 | AF131: =(2204.622/300)/Q131 -> 1.0458774 | AH131: =AK131+F131 -> 118 | AI131: =AH131/30 -> 3.9333333 | AK131: =SUM(B131:E131,G131) -> 6 | AL131: =AK131/30 -> 0.2 | AN131: =SUM(H131:M131) -> 118 | AO131: =F131/P131 -> 0.47457627 | AP131: =SUM(B131:G131)/P131 -> 0.5 | AQ131: =SUM(H131:M131)/P131 -> 0.5 | AR131: =S131/(A132-A131)*365 -> 408.65 | AS131: =R131-AR131 -> 1674.133 | AT131: =(S131/(A132-A131)*365)/R131 -> 0.19620383 | AV131: ='[1]Monthly SBO'!$K115 -> 1.0787873 | AZ131: =AX131-AX119 -> 0 | BA131: =F131/30 -> 3.7333333 | BD131: =AH131/X131 -> 3.0086977 | BE131: =F131/S131 -> 3.3345569 | BF131: =[2]Prices!$L476 -> 35.66 | BG131: =AVERAGE(BF129:BF131) -> 34.826667 | BH131: =C131/S131 -> 0.11909132 | BI131: =B131/S131 -> 0.059545659 | BJ131: =SUM(L131:M131)*'[12]Yellow Grease Complex'!$BH$119/S131 -> 0 | BK131: =SUM(L131:M131)*'[12]Yellow Grease Complex'!$BH$120/S131 -> 0 | BL131: =J132/S132 -> 0.76290416 | BM131: =I132/S132 -> 1.2483886 | BN131: =AR131-AR119 -> -329.6355 | BO131: =B131/$P131 -> 0.0084745763 | BP131: =C131/$P131 -> 0.016949153 | BQ131: =F131/$P131 -> 0.47457627 | BR131: =H131/$P131 -> 0.046610169 | BS131: =I131/$P131 -> 0.17372881 | BT131: =J131/$P131 -> 0.1440678 | BU131: {=SUM(K131:M131/$P131)} -> 0.13559322
A132: 39995 | B132: 0 | C132: 10 | D132: 0 | E132: 0 | F132: 164 | G132: 0 | H132: 7 | I132: 54 | J132: 33 | K132: 10 | L132: 18 | M132: 1 | N132: 0 | O132: 0 | P132: 297 | Q132: 6.8661374 | R132: 2037.033 | S132: 43.255761 | T132: 22.61878 | U132: 22.726864 | V132: 13.943812 | W132: =V132-V131 -> -2.045257 | X132: =T132+U132 -> 45.345644 | Z132: =V132/(X133/31) -> 10.445078 | AA132: =P132-SUM(B132:O132) -> 0 | AB132: =P132-AA132 -> 297 | AF132: =(2204.622/300)/Q132 -> 1.0702873 | AH132: =AK132+F132 -> 174 | AI132: =AH132/31 -> 5.6129032 | AK132: =SUM(B132:E132,G132) -> 10 | AL132: =AK132/31 -> 0.32258065 | AN132: =SUM(H132:M132) -> 123 | AO132: =F132/P132 -> 0.55218855 | AP132: =SUM(B132:G132)/P132 -> 0.58585859 | AQ132: =SUM(H132:M132)/P132 -> 0.41414141 | AR132: =S132/(A133-A132)*365 -> 509.3017 | AS132: =R132-AR132 -> 1527.7313 | AT132: =(S132/(A133-A132)*365)/R132 -> 0.25002133 | AV132: ='[1]Monthly SBO'!$K116 -> 0.92557636 | AZ132: =AX132-AX120 -> 0 | BA132: =F132/31 -> 5.2903226 | BD132: =AH132/X132 -> 3.8371933 | BE132: =F132/S132 -> 3.7914025 | BF132: =[2]Prices!$L477 -> 31.08 | BG132: =AVERAGE(BF130:BF132) -> 34.266667 | BH132: =C132/S132 -> 0.23118308 | BI132: =B132/S132 -> 0 | BJ132: =SUM(L132:M132)*'[12]Yellow Grease Complex'!$BH$119/S132 -> 0 | BK132: =SUM(L132:M132)*'[12]Yellow Grease Complex'!$BH$120/S132 -> 0 | BL132: =J133/S133 -> 0.68895181 | BM132: =I133/S133 -> 1.3112309 | BN132: =AR132-AR120 -> -283.87862 | BO132: =B132/$P132 -> 0 | BP132: =C132/$P132 -> 0.033670034 | BQ132: =F132/$P132 -> 0.55218855 | BR132: =H132/$P132 -> 0.023569024 | BS132: =I132/$P132 -> 0.18181818 | BT132: =J132/$P132 -> 0.11111111 | BU132: {=SUM(K132:M132/$P132)} -> 0.097643098
A133: 40026 | B133: 0 | C133: 10 | D133: 0 | E133: 0 | F133: 168 | G133: 0 | H133: 13 | I133: 59 | J133: 31 | K133: 7 | L133: 21 | M133: 2 | N133: 0 | O133: 0 | P133: 311 | Q133: 6.9117424 | R133: 2030.533 | S133: 44.99589 | T133: 22.171838 | U133: 19.212073 | V133: 17.814045 | W133: =V133-V132 -> 3.870233 | X133: =T133+U133 -> 41.383911 | Z133: =V133/(X134/31) -> 11.25864 | AA133: =P133-SUM(B133:O133) -> 0 | AB133: =P133-AA133 -> 311 | AF133: =(2204.622/300)/Q133 -> 1.0632254 | AH133: =AK133+F133 -> 178 | AI133: =AH133/31 -> 5.7419355 | AK133: =SUM(B133:E133,G133) -> 10 | AL133: =AK133/31 -> 0.32258065 | AN133: =SUM(H133:M133) -> 133 | AO133: =F133/P133 -> 0.54019293 | AP133: =SUM(B133:G133)/P133 -> 0.57234727 | AQ133: =SUM(H133:M133)/P133 -> 0.42765273 | AR133: =S133/(A134-A133)*365 -> 529.79032 | AS133: =R133-AR133 -> 1500.7427 | AT133: =(S133/(A134-A133)*365)/R133 -> 0.26091195 | AV133: ='[1]Monthly SBO'!$K117 -> 0.9036 | AZ133: =AX133-AX121 -> 0 | BA133: =F133/31 -> 5.4193548 | BD133: =AH133/X133 -> 4.3011884 | BE133: =F133/S133 -> 3.7336743 | BF133: =[2]Prices!$L478 -> 33.69 | BG133: =AVERAGE(BF131:BF133) -> 33.476667 | BH133: =C133/S133 -> 0.22224252 | BI133: =B133/S133 -> 0 | BJ133: =SUM(L133:M133)*'[12]Yellow Grease Complex'!$BH$119/S133 -> 0 | BK133: =SUM(L133:M133)*'[12]Yellow Grease Complex'!$BH$120/S133 -> 0 | BL133: =J134/S134 -> 0.57475231 | BM133: =I134/S134 -> 0.88265533 | BN133: =AR133-AR121 -> -272.67984 | BO133: =B133/$P133 -> 0 | BP133: =C133/$P133 -> 0.032154341 | BQ133: =F133/$P133 -> 0.54019293 | BR133: =H133/$P133 -> 0.041800643 | BS133: =I133/$P133 -> 0.18971061 | BT133: =J133/$P133 -> 0.099678457 | BU133: {=SUM(K133:M133/$P133)} -> 0.096463023
A134: 40057 | B134: 8 | C134: 12 | D134: 0 | E134: 0 | F134: 215 | G134: 0 | H134: 10 | I134: 43 | J134: 28 | K134: 9 | L134: 16 | M134: 2 | N134: 0 | O134: 0 | P134: 343 | Q134: 7.0407157 | R134: 2028.783 | S134: 48.716638 | T134: 28.516524 | U134: 20.533398 | V134: 18.181374 | W134: =V134-V133 -> 0.367329 | X134: =T134+U134 -> 49.049922 | Z134: =V134/(X135/30) -> 10.224065 | AA134: =P134-SUM(B134:O134) -> 0 | AB134: =P134-AA134 -> 343 | AF134: =(2204.622/300)/Q134 -> 1.043749 | AH134: =AK134+F134 -> 235 | AI134: =AH134/30 -> 7.8333333 | AK134: =SUM(B134:E134,G134) -> 20 | AL134: =AK134/30 -> 0.66666667 | AN134: =SUM(H134:M134) -> 108 | AO134: =F134/P134 -> 0.62682216 | AP134: =SUM(B134:G134)/P134 -> 0.6851312 | AQ134: =SUM(H134:M134)/P134 -> 0.3148688 | AR134: =S134/(A135-A134)*365 -> 592.7191 | AS134: =R134-AR134 -> 1436.0639 | AT134: =(S134/(A135-A134)*365)/R134 -> 0.292155 | AV134: ='[1]Monthly SBO'!$K118 -> 0.82393524 | AZ134: =AX134-AX122 -> 0 | BA134: =F134/30 -> 7.1666667 | BD134: =AH134/X134 -> 4.7910372 | BE134: =F134/S134 -> 4.4132766 | BF134: =[2]Prices!$L479 -> 30.96 | BG134: =AVERAGE(BF132:BF134) -> 31.91 | BH134: =C134/S134 -> 0.24632242 | BI134: =B134/S134 -> 0.16421494 | BJ134: =SUM(L134:M134)*'[12]Yellow Grease Complex'!$BH$119/S134 -> 0 | BK134: =SUM(L134:M134)*'[12]Yellow Grease Complex'!$BH$120/S134 -> 0 | BL134: =J135/S135 -> 0.62669614 | BM134: =I135/S135 -> 0.52224678 | BN134: =AR134-AR122 -> -174.0729 | BO134: =B134/$P134 -> 0.023323615 | BP134: =C134/$P134 -> 0.034985423 | BQ134: =F134/$P134 -> 0.62682216 | BR134: =H134/$P134 -> 0.029154519 | BS134: =I134/$P134 -> 0.12536443 | BT134: =J134/$P134 -> 0.081632653 | BU134: {=SUM(K134:M134/$P134)} -> 0.078717201
A135: 40087 | B135: 65 | C135: 10 | D135: 0 | E135: 0 | F135: 244 | G135: 0 | H135: 11 | I135: 30 | J135: 36 | K135: 0 | L135: 20 | M135: 2 | N135: 0 | O135: 0 | P135: 418 | Q135: 7.2766385 | R135: 1997.433 | S135: 57.444107 | T135: 29.534724 | U135: 23.81404 | V135: 22.822595 | W135: =V135-V134 -> 4.641221 | X135: =T135+U135 -> 53.348764 | Z135: =V135/(X136/31) -> 10.715982 | AA135: =P135-SUM(B135:O135) -> 0 | AB135: =P135-AA135 -> 418 | AF135: =(2204.622/300)/Q135 -> 1.0099086 | AH135: =AK135+F135 -> 319 | AI135: =AH135/31 -> 10.290323 | AK135: =SUM(B135:E135,G135) -> 75 | AL135: =AK135/31 -> 2.4193548 | AN135: =SUM(H135:M135) -> 99 | AO135: =F135/P135 -> 0.58373206 | AP135: =SUM(B135:G135)/P135 -> 0.76315789 | AQ135: =SUM(H135:M135)/P135 -> 0.23684211 | AR135: =S135/(A136-A135)*365 -> 676.35803 | AS135: =R135-AR135 -> 1321.075 | AT135: =(S135/(A136-A135)*365)/R135 -> 0.33861363 | AV135: ='[1]Monthly SBO'!$K119 -> 0.799709 | AZ135: =AX135-AX123 -> 0 | BA135: =F135/31 -> 7.8709677 | BD135: =AH135/X135 -> 5.97952 | BE135: =F135/S135 -> 4.2476072 | BF135: =[2]Prices!$L480 -> 33.15 | BG135: =AVERAGE(BF133:BF135) -> 32.6 | BH135: =C135/S135 -> 0.17408226 | BI135: =B135/S135 -> 1.1315347 | BJ135: =SUM(L135:M135)*'[12]Yellow Grease Complex'!$BH$119/S135 -> 0 | BK135: =SUM(L135:M135)*'[12]Yellow Grease Complex'!$BH$120/S135 -> 0 | BL135: =J136/S136 -> 0.61241763 | BM135: =I136/S136 -> 0.65952668 | BN135: =AR135-AR123 -> -47.931482 | BO135: =B135/$P135 -> 0.15550239 | BP135: =C135/$P135 -> 0.023923445 | BQ135: =F135/$P135 -> 0.58373206 | BR135: =H135/$P135 -> 0.026315789 | BS135: =I135/$P135 -> 0.071770335 | BT135: =J135/$P135 -> 0.086124402 | BU135: {=SUM(K135:M135/$P135)} -> 0.052631579
A136: 40118 | B136: 99 | C136: 11 | D136: 0 | E136: 0 | F136: 237 | G136: 0 | H136: 13 | I136: 42 | J136: 39 | K136: 0 | L136: 15 | M136: 2 | N136: 0 | O136: 0 | P136: 458 | Q136: 7.1919814 | R136: 1997.433 | S136: 63.682033 | T136: 31.097713 | U136: 34.925209 | V136: 20.978598 | W136: =V136-V135 -> -1.843997 | X136: =T136+U136 -> 66.022922 | Z136: =V136/(X137/30) -> 8.9900846 | AA136: =P136-SUM(B136:O136) -> 0 | AB136: =P136-AA136 -> 458 | AF136: =(2204.622/300)/Q136 -> 1.0217963 | AH136: =AK136+F136 -> 347 | AI136: =AH136/30 -> 11.566667 | AK136: =SUM(B136:E136,G136) -> 110 | AL136: =AK136/30 -> 3.6666667 | AN136: =SUM(H136:M136) -> 111 | AO136: =F136/P136 -> 0.51746725 | AP136: =SUM(B136:G136)/P136 -> 0.75764192 | AQ136: =SUM(H136:M136)/P136 -> 0.24235808 | AR136: =S136/(A137-A136)*365 -> 774.79807 | AS136: =R136-AR136 -> 1222.6349 | AT136: =(S136/(A137-A136)*365)/R136 -> 0.3878969 | AV136: ='[1]Monthly SBO'!$K120 -> 0.92567 | AZ136: =AX136-AX124 -> 0 | BA136: =F136/30 -> 7.9 | BD136: =AH136/X136 -> 5.2557504 | BE136: =F136/S136 -> 3.7216149 | BF136: =[2]Prices!$L481 -> 36.59 | BG136: =AVERAGE(BF134:BF136) -> 33.566667 | BH136: =C136/S136 -> 0.17273318 | BI136: =B136/S136 -> 1.5545986 | BJ136: =SUM(L136:M136)*'[12]Yellow Grease Complex'!$BH$119/S136 -> 0 | BK136: =SUM(L136:M136)*'[12]Yellow Grease Complex'!$BH$120/S136 -> 0 | BL136: =J137/S137 -> 0.47198435 | BM136: =I137/S137 -> 0.63473758 | BN136: =AR136-AR124 -> 39.992235 | BO136: =B136/$P136 -> 0.21615721 | BP136: =C136/$P136 -> 0.024017467 | BQ136: =F136/$P136 -> 0.51746725 | BR136: =H136/$P136 -> 0.028384279 | BS136: =I136/$P136 -> 0.091703057 | BT136: =J136/$P136 -> 0.085152838 | BU136: {=SUM(K136:M136/$P136)} -> 0.037117904
A137: 40148 | B137: 85 | C137: 12 | D137: 0 | E137: 0 | F137: 241 | G137: 0 | H137: 13 | I137: 39 | J137: 29 | K137: 0 | L137: 16 | M137: 2 | N137: 0 | O137: 0 | P137: 437 | Q137: 7.1123159 | R137: 1997.933 | S137: 61.442715 | T137: 26.027815 | U137: 43.977971 | V137: 12.749138 | W137: =V137-V136 -> -8.22946 | X137: =T137+U137 -> 70.005786 | Z137: =V137/(X138/31) -> 19.346016 | AA137: =P137-SUM(B137:O137) -> 0 | AB137: =P137-AA137 -> 437 | AC137: Yr/Yr Feedstk | AD137: Yield vs 5Yr | AF137: =(2204.622/300)/Q137 -> 1.0332415 | AH137: =AK137+F137 -> 338 | AI137: =AH137/31 -> 10.903226 | AK137: =SUM(B137:E137,G137) -> 97 | AL137: =AK137/31 -> 3.1290323 | AN137: =SUM(H137:M137) -> 99 | AO137: =F137/P137 -> 0.55148741 | AP137: =SUM(B137:G137)/P137 -> 0.77345538 | AQ137: =SUM(H137:M137)/P137 -> 0.22654462 | AR137: =S137/(A138-A137)*365 -> 723.43842 | AS137: =R137-AR137 -> 1274.4946 | AT137: =(S137/(A138-A137)*365)/R137 -> 0.36209343 | AV137: ='[1]Monthly SBO'!$K121 -> 0.99244455 | AZ137: =AX137-AX125 -> 0 | BA137: =F137/31 -> 7.7741935 | BD137: =AH137/X137 -> 4.8281723 | BE137: =F137/S137 -> 3.9223527 | BF137: =[2]Prices!$L482 -> 36.81 | BG137: =AVERAGE(BF135:BF137) -> 35.516667 | BH137: =C137/S137 -> 0.19530387 | BI137: =B137/S137 -> 1.3834024 | BJ137: =SUM(L137:M137)*'[12]Yellow Grease Complex'!$BH$119/S137 -> 0 | BK137: =SUM(L137:M137)*'[12]Yellow Grease Complex'!$BH$120/S137 -> 0 | BL137: =J138/S138 -> 0.71409938 | BM137: =I138/S138 -> 0.86443609 | BN137: =AR137-AR125 -> 203.39584 | BO137: =B137/$P137 -> 0.19450801 | BP137: =C137/$P137 -> 0.027459954 | BQ137: =F137/$P137 -> 0.55148741 | BR137: =H137/$P137 -> 0.029748284 | BS137: =I137/$P137 -> 0.089244851 | BT137: =J137/$P137 -> 0.066361556 | BU137: {=SUM(K137:M137/$P137)} -> 0.041189931
A138: 40179 | B138: 33 | C138: 3 | D138: 0 | E138: 0 | F138: 90 | G138: 0 | H138: 4 | I138: 23 | J138: 19 | K138: 6 | L138: 8 | M138: 1 | N138: 0 | O138: 3 | P138: 190 | Q138: 7.1409938 | R138: 2026.1995 | S138: 26.606941 | T138: 13.176609 | U138: 7.252573 | V138: 17.545787 | W138: =V138-V137 -> 4.796649 | X138: =T138+U138 -> 20.429182 | Z138: =V138/(X139/31) -> 19.120268 | AA138: =P138-SUM(B138:O138) -> 0 | AB138: =P138-AA138 -> 190 | AC138: =AB138/AB126-1 -> -0.36026936 | AD138: =Q138/AVERAGE(Q126,Q114,Q102,Q90,Q78)-1 -> 0.01903996 | AF138: =(2204.622/300)/Q138 -> 1.0290921 | AH138: =AK138+F138 -> 126 | AI138: =AH138/31 -> 4.0645161 | AK138: =SUM(B138:E138,G138) -> 36 | AL138: =AK138/31 -> 1.1612903 | AN138: =SUM(H138:M138) -> 61 | AO138: =F138/P138 -> 0.47368421 | AP138: =SUM(B138:G138)/P138 -> 0.66315789 | AQ138: =SUM(H138:M138)/P138 -> 0.32105263 | AR138: =S138/(A139-A138)*365 -> 313.27527 | AS138: =R138-AR138 -> 1712.9242 | AT138: =(S138/(A139-A138)*365)/R138 -> 0.15461225 | AV138: ='[1]Monthly SBO'!$K122 -> 0.83101474 | AZ138: =AX138-AX126 -> 0 | BA138: =F138/31 -> 2.9032258 | BD138: =AH138/X138 -> 6.1676478 | BE138: =F138/S138 -> 3.382576 | BF138: =[2]Prices!$L483 -> 34.88 | BG138: =AVERAGE(BF136:BF138) -> 36.093333 | BH138: =C138/S138 -> 0.11275253 | BI138: =B138/S138 -> 1.2402779 | BJ138: =SUM(L138:M138)*'[12]Yellow Grease Complex'!$BH$119/S138 -> 0 | BK138: =SUM(L138:M138)*'[12]Yellow Grease Complex'!$BH$120/S138 -> 0 | BL138: =J139/S139 -> 0.58126933 | BM138: =I139/S139 -> 0.92319247 | BN138: =AR138-AR126 -> -185.74729 | BO138: =B138/$P138 -> 0.17368421 | BP138: =C138/$P138 -> 0.015789474 | BQ138: =F138/$P138 -> 0.47368421 | BR138: =H138/$P138 -> 0.021052632 | BS138: =I138/$P138 -> 0.12105263 | BT138: =J138/$P138 -> 0.1 | BU138: {=SUM(K138:M138/$P138)} -> 0.078947368 | BV138: =[3]Biodiesel!$B3/1000000 -> 0.485714 | BW138: =S138 -> 26.606941 | BX138: =BW138-BV138 -> 26.121227
A139: 40210 | B139: 30 | C139: 8 | D139: 0 | E139: 0 | F139: 102 | G139: 0 | H139: 2 | I139: 27 | J139: 17 | K139: 4 | L139: 9 | M139: 1 | N139: 0 | O139: 2 | P139: 202 | Q139: 6.9068474 | R139: 2025.9495 | S139: 29.246339 | T139: 20.439035 | U139: 8.008233 | V139: 17.833493 | W139: =V139-V138 -> 0.287706 | X139: =T139+U139 -> 28.447268 | Z139: =V139/(X140/28) -> 14.489027 | AA139: =P139-SUM(B139:O139) -> 0 | AB139: =P139-AA139 -> 202 | AC139: =AB139/AB127-1 -> -0.12931034 | AD139: =Q139/AVERAGE(Q127,Q115,Q103,Q91,Q79)-1 -> -0.0047062631 | AF139: =(2204.622/300)/Q139 -> 1.0639789 | AH139: =AK139+F139 -> 140 | AI139: =AH139/28 -> 5 | AK139: =SUM(B139:E139,G139) -> 38 | AL139: =AK139/28 -> 1.3571429 | AN139: =SUM(H139:M139) -> 60 | AO139: =F139/P139 -> 0.5049505 | AP139: =SUM(B139:G139)/P139 -> 0.69306931 | AQ139: =SUM(H139:M139)/P139 -> 0.2970297 | AR139: =S139/(A140-A139)*365 -> 381.24692 | AS139: =R139-AR139 -> 1644.7026 | AT139: =(S139/(A140-A139)*365)/R139 -> 0.18818185 | AV139: ='[1]Monthly SBO'!$K123 -> 0.90712 | AZ139: =AX139-AX127 -> 0 | BA139: =F139/28 -> 3.6428571 | BD139: =AH139/X139 -> 4.9213865 | BE139: =F139/S139 -> 3.487616 | BF139: =[2]Prices!$L484 -> 34.69 | BG139: =AVERAGE(BF137:BF139) -> 35.46 | BH139: =C139/S139 -> 0.27353851 | BI139: =B139/S139 -> 1.0257694 | BJ139: =SUM(L139:M139)*'[12]Yellow Grease Complex'!$BH$119/S139 -> 0 | BK139: =SUM(L139:M139)*'[12]Yellow Grease Complex'!$BH$120/S139 -> 0 | BL139: =J140/S140 -> 1.0067495 | BM139: =I140/S140 -> 0.50337477 | BN139: =AR139-AR127 -> -54.560109 | BO139: =B139/$P139 -> 0.14851485 | BP139: =C139/$P139 -> 0.03960396 | BQ139: =F139/$P139 -> 0.5049505 | BR139: =H139/$P139 -> 0.0099009901 | BS139: =I139/$P139 -> 0.13366337 | BT139: =J139/$P139 -> 0.084158416 | BU139: {=SUM(K139:M139/$P139)} -> 0.069306931 | BV139: =[3]Biodiesel!$B4/1000000 -> 0.538632 | BW139: =S139 -> 29.246339 | BX139: =BW139-BV139 -> 28.707707
A140: 40238 | B140: 22 | C140: 3 | D140: 0 | E140: 0 | F140: 112 | G140: 0 | H140: 6 | I140: 17 | J140: 34 | K140: 10 | L140: 19 | M140: 1 | N140: 0 | O140: 2 | P140: 226 | Q140: 6.6919234 | R140: 1972.2495 | S140: 33.772054 | T140: 24.702851 | U140: 9.76032 | V140: 16.745957 | W140: =V140-V139 -> -1.087536 | X140: =T140+U140 -> 34.463171 | Z140: =V140/(X141/31) -> 17.061895 | AA140: =P140-SUM(B140:O140) -> 0 | AB140: =P140-AA140 -> 226 | AC140: =AB140/AB128-1 -> 0.32941176 | AD140: =Q140/AVERAGE(Q128,Q116,Q104,Q92,Q80)-1 -> 0.046856752 | AF140: =(2204.622/300)/Q140 -> 1.0981506 | AH140: =AK140+F140 -> 137 | AI140: =AH140/31 -> 4.4193548 | AK140: =SUM(B140:E140,G140) -> 25 | AL140: =AK140/31 -> 0.80645161 | AN140: =SUM(H140:M140) -> 87 | AO140: =F140/P140 -> 0.49557522 | AP140: =SUM(B140:G140)/P140 -> 0.60619469 | AQ140: =SUM(H140:M140)/P140 -> 0.38495575 | AR140: =S140/(A141-A140)*365 -> 397.6387 | AS140: =R140-AR140 -> 1574.6108 | AT140: =(S140/(A141-A140)*365)/R140 -> 0.20161683 | AV140: ='[1]Monthly SBO'!$K124 -> 0.89959565 | AZ140: =AX140-AX128 -> 0 | BA140: =F140/31 -> 3.6129032 | BD140: =AH140/X140 -> 3.9752581 | BE140: =F140/S140 -> 3.3163514 | BF140: =[2]Prices!$L485 -> 36.39 | BG140: =AVERAGE(BF138:BF140) -> 35.32 | BH140: =C140/S140 -> 0.088830842 | BI140: =B140/S140 -> 0.65142618 | BJ140: =SUM(L140:M140)*'[12]Yellow Grease Complex'!$BH$119/S140 -> 0 | BK140: =SUM(L140:M140)*'[12]Yellow Grease Complex'!$BH$120/S140 -> 0 | BL140: =J141/S141 -> 0.76045988 | BM140: =I141/S141 -> 0.81895679 | BN140: =AR140-AR128 -> 84.514679 | BO140: =B140/$P140 -> 0.097345133 | BP140: =C140/$P140 -> 0.013274336 | BQ140: =F140/$P140 -> 0.49557522 | BR140: =H140/$P140 -> 0.026548673 | BS140: =I140/$P140 -> 0.075221239 | BT140: =J140/$P140 -> 0.15044248 | BU140: {=SUM(K140:M140/$P140)} -> 0.13274336 | BV140: =[3]Biodiesel!$B5/1000000 -> 0.810795 | BW140: =S140 -> 33.772054 | BX140: =BW140-BV140 -> 32.961259
A141: 40269 | B141: 30 | C141: 4 | D141: 0 | E141: 0 | F141: 127 | G141: 0 | H141: 5 | I141: 28 | J141: 26 | K141: 2 | L141: 15 | M141: 0 | N141: 0 | O141: 0 | P141: 237 | Q141: 6.9318843 | R141: 1950.2495 | S141: 34.189838 | T141: 22.748555 | U141: 7.677413 | V141: 19.816669 | W141: =V141-V140 -> 3.070712 | X141: =T141+U141 -> 30.425968 | Z141: =V141/(X142/30) -> 19.318734 | AA141: =P141-SUM(B141:O141) -> 0 | AB141: =P141-AA141 -> 237 | AC141: =AB141/AB129-1 -> 0.2606383 | AD141: =Q141/AVERAGE(Q129,Q117,Q105,Q93,Q81)-1 -> 0.038703294 | AF141: =(2204.622/300)/Q141 -> 1.060136 | AH141: =AK141+F141 -> 161 | AI141: =AH141/30 -> 5.3666667 | AK141: =SUM(B141:E141,G141) -> 34 | AL141: =AK141/30 -> 1.1333333 | AN141: =SUM(H141:M141) -> 76 | AO141: =F141/P141 -> 0.53586498 | AP141: =SUM(B141:G141)/P141 -> 0.67932489 | AQ141: =SUM(H141:M141)/P141 -> 0.32067511 | AR141: =S141/(A142-A141)*365 -> 415.97636 | AS141: =R141-AR141 -> 1534.2731 | AT141: =(S141/(A142-A141)*365)/R141 -> 0.21329392 | AV141: ='[1]Monthly SBO'!$K125 -> 0.76137238 | AZ141: =AX141-AX129 -> 0 | BA141: =F141/30 -> 4.2333333 | BD141: =AH141/X141 -> 5.2915325 | BE141: =F141/S141 -> 3.714554 | BF141: =[2]Prices!$L486 -> 37.11 | BG141: =AVERAGE(BF139:BF141) -> 36.063333 | BH141: =C141/S141 -> 0.11699383 | BI141: =B141/S141 -> 0.8774537 | BJ141: =SUM(L141:M141)*'[12]Yellow Grease Complex'!$BH$119/S141 -> 0 | BK141: =SUM(L141:M141)*'[12]Yellow Grease Complex'!$BH$120/S141 -> 0 | BL141: =J142/S142 -> 0.72066282 | BM141: =I142/S142 -> 0.59533016 | BN141: =AR141-AR129 -> 73.232517 | BO141: =B141/$P141 -> 0.12658228 | BP141: =C141/$P141 -> 0.016877637 | BQ141: =F141/$P141 -> 0.53586498 | BR141: =H141/$P141 -> 0.021097046 | BS141: =I141/$P141 -> 0.11814346 | BT141: =J141/$P141 -> 0.10970464 | BU141: {=SUM(K141:M141/$P141)} -> 0.071729958 | BV141: =[3]Biodiesel!$B6/1000000 -> 0.522149 | BW141: =S141 -> 34.189838 | BX141: =BW141-BV141 -> 33.667689
A142: 40299 | B142: 36 | C142: 8 | D142: 0 | E142: 0 | F142: 98 | G142: 0 | H142: 7 | I142: 19 | J142: 23 | K142: 6 | L142: 21 | M142: 2 | N142: 0 | O142: 2 | P142: 222 | Q142: 6.9559629 | R142: 1938.7495 | S142: 31.915064 | T142: 20.127531 | U142: 10.645711 | V142: 20.805157 | W142: =V142-V141 -> 0.988488 | X142: =T142+U142 -> 30.773242 | Z142: =V142/(X143/31) -> 21.026787 | AA142: =P142-SUM(B142:O142) -> 0 | AB142: =P142-AA142 -> 222 | AC142: =AB142/AB130-1 -> 0.072463768 | AD142: =Q142/AVERAGE(Q130,Q118,Q106,Q94,Q82)-1 -> 0.078705989 | AF142: =(2204.622/300)/Q142 -> 1.0564662 | AH142: =AK142+F142 -> 142 | AI142: =AH142/31 -> 4.5806452 | AK142: =SUM(B142:E142,G142) -> 44 | AL142: =AK142/31 -> 1.4193548 | AN142: =SUM(H142:M142) -> 78 | AO142: =F142/P142 -> 0.44144144 | AP142: =SUM(B142:G142)/P142 -> 0.63963964 | AQ142: =SUM(H142:M142)/P142 -> 0.35135135 | AR142: =S142/(A143-A142)*365 -> 375.77414 | AS142: =R142-AR142 -> 1562.9754 | AT142: =(S142/(A143-A142)*365)/R142 -> 0.19382295 | AV142: ='[1]Monthly SBO'!$K126 -> 0.820474 | AZ142: =AX142-AX130 -> 0 | BA142: =F142/31 -> 3.1612903 | BD142: =AH142/X142 -> 4.6143984 | BE142: =F142/S142 -> 3.0706503 | BF142: =[2]Prices!$L487 -> 35.41 | BG142: =AVERAGE(BF140:BF142) -> 36.303333 | BH142: =C142/S142 -> 0.25066533 | BI142: =B142/S142 -> 1.127994 | BJ142: =SUM(L142:M142)*'[12]Yellow Grease Complex'!$BH$119/S142 -> 0 | BK142: =SUM(L142:M142)*'[12]Yellow Grease Complex'!$BH$120/S142 -> 0 | BL142: =J143/S143 -> 0.73892643 | BM142: =I143/S143 -> 0.33251689 | BN142: =AR142-AR130 -> -2.1871742 | BO142: =B142/$P142 -> 0.16216216 | BP142: =C142/$P142 -> 0.036036036 | BQ142: =F142/$P142 -> 0.44144144 | BR142: =H142/$P142 -> 0.031531532 | BS142: =I142/$P142 -> 0.085585586 | BT142: =J142/$P142 -> 0.1036036 | BU142: {=SUM(K142:M142/$P142)} -> 0.13063063 | BV142: =[3]Biodiesel!$B7/1000000 -> 0.485714 | BW142: =S142 -> 31.915064 | BX142: =BW142-BV142 -> 31.42935
A143: 40330 | B143: 28 | C143: 1 | D143: 0 | E143: 0 | F143: 89 | G143: 0 | H143: 8 | I143: 9 | J143: 20 | K143: 3 | L143: 29 | M143: 2 | N143: 0 | O143: 1 | P143: 190 | Q143: 7.0198011 | R143: 1965.7975 | S143: 27.066294 | T143: 21.910251 | U143: 8.762998 | V143: 16.810546 | W143: =V143-V142 -> -3.994611 | X143: =T143+U143 -> 30.673249 | Z143: =V143/(X144/30) -> 18.199698 | AA143: =P143-SUM(B143:O143) -> 0 | AB143: =P143-AA143 -> 190 | AC143: =AB143/AB131-1 -> -0.19491525 | AD143: =Q143/AVERAGE(Q131,Q119,Q107,Q95,Q83)-1 -> -0.00093741804 | AF143: =(2204.622/300)/Q143 -> 1.0468587 | AH143: =AK143+F143 -> 118 | AI143: =AH143/30 -> 3.9333333 | AK143: =SUM(B143:E143,G143) -> 29 | AL143: =AK143/30 -> 0.96666667 | AN143: =SUM(H143:M143) -> 71 | AO143: =F143/P143 -> 0.46842105 | AP143: =SUM(B143:G143)/P143 -> 0.62105263 | AQ143: =SUM(H143:M143)/P143 -> 0.37368421 | AR143: =S143/(A144-A143)*365 -> 329.30658 | AS143: =R143-AR143 -> 1636.4909 | AT143: =(S143/(A144-A143)*365)/R143 -> 0.16751806 | AV143: ='[1]Monthly SBO'!$K127 -> 0.78568273 | AZ143: =AX143-AX131 -> 0 | BA143: =F143/30 -> 2.9666667 | BD143: =AH143/X143 -> 3.8470004 | BE143: =F143/S143 -> 3.2882226 | BF143: =[2]Prices!$L488 -> 34.47 | BG143: =AVERAGE(BF141:BF143) -> 35.663333 | BH143: =C143/S143 -> 0.036946322 | BI143: =B143/S143 -> 1.034497 | BJ143: =SUM(L143:M143)*'[12]Yellow Grease Complex'!$BH$119/S143 -> 0 | BK143: =SUM(L143:M143)*'[12]Yellow Grease Complex'!$BH$120/S143 -> 0 | BL143: =J144/S144 -> 1.1595261 | BM143: =I144/S144 -> 0.28988153 | BN143: =AR143-AR131 -> -79.34342 | BO143: =B143/$P143 -> 0.14736842 | BP143: =C143/$P143 -> 0.0052631579 | BQ143: =F143/$P143 -> 0.46842105 | BR143: =H143/$P143 -> 0.042105263 | BS143: =I143/$P143 -> 0.047368421 | BT143: =J143/$P143 -> 0.10526316 | BU143: {=SUM(K143:M143/$P143)} -> 0.17894737 | BV143: =[3]Biodiesel!$B8/1000000 -> 0.637838 | BW143: =S143 -> 27.066294 | BX143: =BW143-BV143 -> 26.428456
A144: 40360 | B144: 17 | C144: 11 | D144: 0 | E144: 0 | F144: 96 | G144: 0 | H144: 7 | I144: 8 | J144: 32 | K144: 2 | L144: 29 | M144: 2 | N144: 0 | O144: 1 | P144: 205 | Q144: 7.4282142 | R144: 1962.3475 | S144: 27.597481 | T144: 19.490473 | U144: 8.219678 | V144: 16.448883 | W144: =V144-V143 -> -0.361663 | X144: =T144+U144 -> 27.710151 | Z144: =V144/(X145/31) -> 19.25839 | AA144: =P144-SUM(B144:O144) -> 0 | AB144: =P144-AA144 -> 205 | AC144: =AB144/AB132-1 -> -0.30976431 | AD144: =Q144/AVERAGE(Q132,Q120,Q108,Q96,Q84)-1 -> 0.081862147 | AF144: =(2204.622/300)/Q144 -> 0.98930104 | AH144: =AK144+F144 -> 124 | AI144: =AH144/31 -> 4 | AK144: =SUM(B144:E144,G144) -> 28 | AL144: =AK144/31 -> 0.90322581 | AN144: =SUM(H144:M144) -> 80 | AO144: =F144/P144 -> 0.46829268 | AP144: =SUM(B144:G144)/P144 -> 0.60487805 | AQ144: =SUM(H144:M144)/P144 -> 0.3902439 | AR144: =S144/(A145-A144)*365 -> 324.93808 | AS144: =R144-AR144 -> 1637.4094 | AT144: =(S144/(A145-A144)*365)/R144 -> 0.16558641 | AV144: ='[1]Monthly SBO'!$K128 -> 0.8749419 | AZ144: =AX144-AX132 -> 0 | BA144: =F144/31 -> 3.0967742 | BD144: =AH144/X144 -> 4.4748944 | BE144: =F144/S144 -> 3.4785784 | BF144: =[2]Prices!$L489 -> 35.07 | BG144: =AVERAGE(BF142:BF144) -> 34.983333 | BH144: =C144/S144 -> 0.3985871 | BI144: =B144/S144 -> 0.61599825 | BJ144: =SUM(L144:M144)*'[12]Yellow Grease Complex'!$BH$119/S144 -> 0 | BK144: =SUM(L144:M144)*'[12]Yellow Grease Complex'!$BH$120/S144 -> 0 | BL144: =J145/S145 -> 1.0937954 | BM144: =I145/S145 -> 0.25521893 | BN144: =AR144-AR132 -> -184.36362 | BO144: =B144/$P144 -> 0.082926829 | BP144: =C144/$P144 -> 0.053658537 | BQ144: =F144/$P144 -> 0.46829268 | BR144: =H144/$P144 -> 0.034146341 | BS144: =I144/$P144 -> 0.03902439 | BT144: =J144/$P144 -> 0.15609756 | BU144: {=SUM(K144:M144/$P144)} -> 0.16097561 | BV144: =[3]Biodiesel!$B9/1000000 -> 34.054859 | BW144: =S144 -> 27.597481 | BX144: =BW144-BV144 -> -6.457378
A145: 40391 | B145: 19 | C145: 12 | D145: 0 | E145: 0 | F145: 84 | G145: 0 | H145: 13 | I145: 7 | J145: 30 | K145: 1 | L145: 30 | M145: 1 | N145: 0 | O145: 1 | P145: 198 | Q145: 7.2190496 | R145: 2015.3475 | S145: 27.427433 | T145: 19.340841 | U145: 7.136729 | V145: 17.568675 | W145: =V145-V144 -> 1.119792 | X145: =T145+U145 -> 26.47757 | Z145: =V145/(X146/31) -> 17.44949 | AA145: =P145-SUM(B145:O145) -> 0 | AB145: =P145-AA145 -> 198 | AC145: =AB145/AB133-1 -> -0.36334405 | AD145: =Q145/AVERAGE(Q133,Q121,Q109,Q97,Q85)-1 -> 0.044461617 | AF145: =(2204.622/300)/Q145 -> 1.017965 | AH145: =AK145+F145 -> 115 | AI145: =AH145/31 -> 3.7096774 | AK145: =SUM(B145:E145,G145) -> 31 | AL145: =AK145/31 -> 1 | AN145: =SUM(H145:M145) -> 82 | AO145: =F145/P145 -> 0.42424242 | AP145: =SUM(B145:G145)/P145 -> 0.58080808 | AQ145: =SUM(H145:M145)/P145 -> 0.41414141 | AR145: =S145/(A146-A145)*365 -> 322.9359 | AS145: =R145-AR145 -> 1692.4116 | AT145: =(S145/(A146-A145)*365)/R145 -> 0.16023832 | AV145: ='[1]Monthly SBO'!$K129 -> 1.0332091 | AZ145: =AX145-AX133 -> 0 | BA145: =F145/31 -> 2.7096774 | BD145: =AH145/X145 -> 4.3432989 | BE145: =F145/S145 -> 3.0626271 | BF145: =[2]Prices!$L490 -> 37.57 | BG145: =AVERAGE(BF143:BF145) -> 35.703333 | BH145: =C145/S145 -> 0.43751816 | BI145: =B145/S145 -> 0.69273709 | BJ145: =SUM(L145:M145)*'[12]Yellow Grease Complex'!$BH$119/S145 -> 0 | BK145: =SUM(L145:M145)*'[12]Yellow Grease Complex'!$BH$120/S145 -> 0 | BL145: =J146/S146 -> 1.0870681 | BM145: =I146/S146 -> 0.36235604 | BN145: =AR145-AR133 -> -206.85441 | BO145: =B145/$P145 -> 0.095959596 | BP145: =C145/$P145 -> 0.060606061 | BQ145: =F145/$P145 -> 0.42424242 | BR145: =H145/$P145 -> 0.065656566 | BS145: =I145/$P145 -> 0.035353535 | BT145: =J145/$P145 -> 0.15151515 | BU145: {=SUM(K145:M145/$P145)} -> 0.16161616 | BV145: =[3]Biodiesel!$B10/1000000 -> 28.833177 | BW145: =S145 -> 27.427433 | BX145: =BW145-BV145 -> -1.405744
A146: 40422 | B146: 11 | C146: 19 | D146: 0 | E146: 0 | F146: 102 | G146: 0 | H146: 13 | I146: 11 | J146: 33 | K146: 1 | L146: 27 | M146: 5 | N146: 0 | O146: 1 | P146: 223 | Q146: 7.3459452 | R146: 2020.8475 | S146: 30.356883 | T146: 25.141186 | U146: 6.070552 | V146: 16.740273 | W146: =V146-V145 -> -0.828402 | X146: =T146+U146 -> 31.211738 | Z146: =V146/(X147/30) -> 17.628144 | AA146: =P146-SUM(B146:O146) -> 0 | AB146: =P146-AA146 -> 223 | AC146: =AB146/AB134-1 -> -0.34985423 | AD146: =Q146/AVERAGE(Q134,Q122,Q110,Q98,Q86)-1 -> 0.043352055 | AF146: =(2204.622/300)/Q146 -> 1.0003805 | AH146: =AK146+F146 -> 132 | AI146: =AH146/30 -> 4.4 | AK146: =SUM(B146:E146,G146) -> 30 | AL146: =AK146/30 -> 1 | AN146: =SUM(H146:M146) -> 90 | AO146: =F146/P146 -> 0.4573991 | AP146: =SUM(B146:G146)/P146 -> 0.59192825 | AQ146: =SUM(H146:M146)/P146 -> 0.40358744 | AR146: =S146/(A147-A146)*365 -> 369.34208 | AS146: =R146-AR146 -> 1651.5054 | AT146: =(S146/(A147-A146)*365)/R146 -> 0.18276593 | AV146: ='[1]Monthly SBO'!$K130 -> 1.0940895 | AZ146: =AX146-AX134 -> 0 | BA146: =F146/30 -> 3.4 | BD146: =AH146/X146 -> 4.2291781 | BE146: =F146/S146 -> 3.3600288 | BF146: =[2]Prices!$L491 -> 39.21 | BG146: =AVERAGE(BF144:BF146) -> 37.283333 | BH146: =C146/S146 -> 0.62588771 | BI146: =B146/S146 -> 0.36235604 | BJ146: =SUM(L146:M146)*'[12]Yellow Grease Complex'!$BH$119/S146 -> 0 | BK146: =SUM(L146:M146)*'[12]Yellow Grease Complex'!$BH$120/S146 -> 0 | BL146: =J147/S147 -> 1.1265883 | BM146: =I147/S147 -> 0.31685297 | BN146: =AR146-AR134 -> -223.37702 | BO146: =B146/$P146 -> 0.049327354 | BP146: =C146/$P146 -> 0.085201794 | BQ146: =F146/$P146 -> 0.4573991 | BR146: =H146/$P146 -> 0.058295964 | BS146: =I146/$P146 -> 0.049327354 | BT146: =J146/$P146 -> 0.14798206 | BU146: {=SUM(K146:M146/$P146)} -> 0.14798206 | BV146: =[3]Biodiesel!$B11/1000000 -> 35.676995 | BW146: =S146 -> 30.356883 | BX146: =BW146-BV146 -> -5.320112
A147: 40452 | B147: 10 | C147: 14 | D147: 0 | E147: 0 | F147: 105 | G147: 0 | H147: 14 | I147: 9 | J147: 32 | K147: 1 | L147: 19 | M147: 8 | N147: 0 | O147: 4 | P147: 216 | Q147: 7.6044712 | R147: 2021.3475 | S147: 28.404342 | T147: 24.665922 | U147: 3.823077 | V147: 16.518501 | W147: =V147-V146 -> -0.221772 | X147: =T147+U147 -> 28.488999 | Z147: =V147/(X148/31) -> 23.582125 | AA147: =P147-SUM(B147:O147) -> 0 | AB147: =P147-AA147 -> 216 | AC147: =AB147/AB135-1 -> -0.48325359 | AD147: =Q147/AVERAGE(Q135,Q123,Q111,Q99,Q87)-1 -> 0.045052765 | AF147: =(2204.622/300)/Q147 -> 0.96637095 | AH147: =AK147+F147 -> 129 | AI147: =AH147/31 -> 4.1612903 | AK147: =SUM(B147:E147,G147) -> 24 | AL147: =AK147/31 -> 0.77419355 | AN147: =SUM(H147:M147) -> 83 | AO147: =F147/P147 -> 0.48611111 | AP147: =SUM(B147:G147)/P147 -> 0.59722222 | AQ147: =SUM(H147:M147)/P147 -> 0.38425926 | AR147: =S147/(A148-A147)*365 -> 334.43822 | AS147: =R147-AR147 -> 1686.9093 | AT147: =(S147/(A148-A147)*365)/R147 -> 0.16545311 | AV147: ='[1]Monthly SBO'!$K131 -> 1.3064448 | AZ147: =AX147-AX135 -> 0 | BA147: =F147/31 -> 3.3870968 | BD147: =AH147/X147 -> 4.5280636 | BE147: =F147/S147 -> 3.6966179 | BF147: =[2]Prices!$L492 -> 44.02 | BG147: =AVERAGE(BF145:BF147) -> 40.266667 | BH147: =C147/S147 -> 0.49288239 | BI147: =B147/S147 -> 0.35205885 | BJ147: =SUM(L147:M147)*'[12]Yellow Grease Complex'!$BH$119/S147 -> 0 | BK147: =SUM(L147:M147)*'[12]Yellow Grease Complex'!$BH$120/S147 -> 0 | BL147: =J148/S148 -> 1.4435409 | BM147: =I148/S148 -> 0.18044261 | BN147: =AR147-AR135 -> -341.91981 | BO147: =B147/$P147 -> 0.046296296 | BP147: =C147/$P147 -> 0.064814815 | BQ147: =F147/$P147 -> 0.48611111 | BR147: =H147/$P147 -> 0.064814815 | BS147: =I147/$P147 -> 0.041666667 | BT147: =J147/$P147 -> 0.14814815 | BU147: {=SUM(K147:M147/$P147)} -> 0.12962963 | BV147: =[3]Biodiesel!$B12/1000000 -> 39.280236 | BW147: =S147 -> 28.404342 | BX147: =BW147-BV147 -> -10.875894
A148: 40483 | B148: 4 | C148: 11 | D148: 0 | E148: 0 | F148: 73 | G148: 0 | H148: 9 | I148: 4 | J148: 32 | K148: 2 | L148: 13 | M148: 8 | N148: 0 | O148: 8 | P148: 164 | Q148: 7.398147 | R148: 2013.3475 | S148: 22.167713 | T148: 17.389897 | U148: 4.324581 | V148: 18.235435 | W148: =V148-V147 -> 1.716934 | X148: =T148+U148 -> 21.714478 | Z148: =V148/(X149/30) -> 18.864829 | AA148: =P148-SUM(B148:O148) -> 0 | AB148: =P148-AA148 -> 164 | AC148: =AB148/AB136-1 -> -0.6419214 | AD148: =Q148/AVERAGE(Q136,Q124,Q112,Q100,Q88)-1 -> 0.028666033 | AF148: =(2204.622/300)/Q148 -> 0.9933217 | AH148: =AK148+F148 -> 88 | AI148: =AH148/30 -> 2.9333333 | AK148: =SUM(B148:E148,G148) -> 15 | AL148: =AK148/30 -> 0.5 | AN148: =SUM(H148:M148) -> 68 | AO148: =F148/P148 -> 0.44512195 | AP148: =SUM(B148:G148)/P148 -> 0.53658537 | AQ148: =SUM(H148:M148)/P148 -> 0.41463415 | AR148: =S148/(A149-A148)*365 -> 269.70717 | AS148: =R148-AR148 -> 1743.6403 | AT148: =(S148/(A149-A148)*365)/R148 -> 0.13395957 | AV148: ='[1]Monthly SBO'!$K132 -> 1.5374924 | AZ148: =AX148-AX136 -> 0 | BA148: =F148/30 -> 2.4333333 | BD148: =AH148/X148 -> 4.0525957 | BE148: =F148/S148 -> 3.2930776 | BF148: =[2]Prices!$L493 -> 47.62 | BG148: =AVERAGE(BF146:BF148) -> 43.616667 | BH148: =C148/S148 -> 0.49621718 | BI148: =B148/S148 -> 0.18044261 | BJ148: =SUM(L148:M148)*'[12]Yellow Grease Complex'!$BH$119/S148 -> 0 | BK148: =SUM(L148:M148)*'[12]Yellow Grease Complex'!$BH$120/S148 -> 0 | BL148: =J149/S149 -> 1.4173067 | BM148: =I149/S149 -> 0.32395581 | BN148: =AR148-AR136 -> -505.09089 | BO148: =B148/$P148 -> 0.024390244 | BP148: =C148/$P148 -> 0.067073171 | BQ148: =F148/$P148 -> 0.44512195 | BR148: =H148/$P148 -> 0.054878049 | BS148: =I148/$P148 -> 0.024390244 | BT148: =J148/$P148 -> 0.19512195 | BU148: {=SUM(K148:M148/$P148)} -> 0.1402439 | BV148: =[3]Biodiesel!$B13/1000000 -> 34.240264 | BW148: =S148 -> 22.167713 | BX148: =BW148-BV148 -> -12.072551
A149: 40513 | B149: 8 | C149: 18 | D149: 0 | E149: 0 | F149: 63 | G149: 0 | H149: 11 | I149: 8 | J149: 35 | K149: 3 | L149: 25 | M149: 10 | N149: 0 | O149: 8 | P149: 189 | Q149: 7.653456 | R149: 2014.2975 | S149: 24.694726 | T149: 21.591125 | U149: 7.407975 | V149: 12.805789 | W149: =V149-V148 -> -5.429646 | X149: =T149+U149 -> 28.9991 | Z149: =V149/(X150/31) -> 12.74081 | AA149: =P149-SUM(B149:O149) -> 0 | AB149: =P149-AA149 -> 189 | AC149: =AB149/AB137-1 -> -0.56750572 | AD149: =Q149/AVERAGE(Q137,Q125,Q113,Q101,Q89)-1 -> 0.07608494 | AF149: =(2204.622/300)/Q149 -> 0.96018582 | AH149: =AK149+F149 -> 89 | AI149: =AH149/31 -> 2.8709677 | AK149: =SUM(B149:E149,G149) -> 26 | AL149: =AK149/31 -> 0.83870968 | AN149: =SUM(H149:M149) -> 92 | AO149: =F149/P149 -> 0.33333333 | AP149: =SUM(B149:G149)/P149 -> 0.47089947 | AQ149: =SUM(H149:M149)/P149 -> 0.48677249 | AR149: =S149/(A150-A149)*365 -> 290.76048 | AS149: =R149-AR149 -> 1723.537 | AT149: =(S149/(A150-A149)*365)/R149 -> 0.14434833 | AV149: ='[1]Monthly SBO'!$K133 -> 1.6742095 | AZ149: =AX149-AX137 -> 0 | BA149: =F149/31 -> 2.0322581 | BD149: =AH149/X149 -> 3.0690608 | BE149: =F149/S149 -> 2.551152 | BF149: =[2]Prices!$L494 -> 51.51 | BG149: =AVERAGE(BF147:BF149) -> 47.716667 | BH149: =C149/S149 -> 0.72890058 | BI149: =B149/S149 -> 0.32395581 | BJ149: =SUM(L149:M149)*'[12]Yellow Grease Complex'!$BH$119/S149 -> 0 | BK149: =SUM(L149:M149)*'[12]Yellow Grease Complex'!$BH$120/S149 -> 0 | BL149: =J150/S150 -> 0.87680919 | BM149: =I150/S150 -> 0.31112584 | BN149: =AR149-AR137 -> -432.67793 | BO149: =B149/$P149 -> 0.042328042 | BP149: =C149/$P149 -> 0.095238095 | BQ149: =F149/$P149 -> 0.33333333 | BR149: =H149/$P149 -> 0.058201058 | BS149: =I149/$P149 -> 0.042328042 | BT149: =J149/$P149 -> 0.18518519 | BU149: {=SUM(K149:M149/$P149)} -> 0.2010582 | BV149: =[3]Biodiesel!$B14/1000000 -> 38.225439 | BW149: =S149 -> 24.694726 | BX149: =BW149-BV149 -> -13.530713
A150: 40544 | B150: 8 | C150: 17 | D150: 0 | E150: 0 | F150: 150 | G150: 0 | H150: 14 | I150: 11 | J150: 31 | K150: 3 | L150: 18 | M150: 10 | N150: 0 | O150: 7 | P150: 269 | Q150: 7.608441 | R150: 2114.4475 | S150: 35.355469 | T150: 21.760435 | U150: 9.397668 | V150: 16.705962 | W150: =V150-V149 -> 3.900173 | X150: =T150+U150 -> 31.158103 | Z150: =V150/(X151/31) -> 12.853448 | AA150: =P150-SUM(B150:O150) -> 0 | AB150: =P150-AA150 -> 269 | AC150: =AB150/AB138-1 -> 0.41578947 | AD150: =Q150/AVERAGE(Q138,Q126,Q114,Q102,Q90)-1 -> 0.075507192 | AF150: =(2204.622/300)/Q150 -> 0.96586673 | AH150: =AK150+F150 -> 175 | AI150: =AH150/31 -> 5.6451613 | AK150: =SUM(B150:E150,G150) -> 25 | AL150: =AK150/31 -> 0.80645161 | AN150: =SUM(H150:M150) -> 87 | AO150: =F150/P150 -> 0.55762082 | AP150: =SUM(B150:G150)/P150 -> 0.65055762 | AQ150: =SUM(H150:M150)/P150 -> 0.32342007 | AR150: =S150/(A151-A150)*365 -> 416.28213 | AS150: =R150-AR150 -> 1698.1654 | AT150: =(S150/(A151-A150)*365)/R150 -> 0.19687513 | AV150: ='[1]Monthly SBO'!$K134 -> 1.7187589 | AX150: =S150/31 -> 1.140499 | AZ150: =AX150-AX138 -> 1.140499 | BA150: =F150/31 -> 4.8387097 | BD150: =AH150/X150 -> 5.6165165 | BE150: =F150/S150 -> 4.2426251 | BF150: =[2]Prices!$L495 -> 53.84 | BG150: =AVERAGE(BF148:BF150) -> 50.99 | BH150: =C150/S150 -> 0.48083084 | BI150: =B150/S150 -> 0.22627334 | BJ150: =SUM(L150:M150)*'[12]Yellow Grease Complex'!$BH$119/S150 -> 0 | BK150: =SUM(L150:M150)*'[12]Yellow Grease Complex'!$BH$120/S150 -> 0 | BL150: =J151/S151 -> 1.1898165 | BM150: =I151/S151 -> 0.27266628 | BN150: =AR150-AR138 -> 103.00686 | BO150: =B150/$P150 -> 0.029739777 | BP150: =C150/$P150 -> 0.063197026 | BQ150: =F150/$P150 -> 0.55762082 | BR150: =H150/$P150 -> 0.05204461 | BS150: =I150/$P150 -> 0.040892193 | BT150: =J150/$P150 -> 0.11524164 | BU150: {=SUM(K150:M150/$P150)} -> 0.11524164 | BV150: =[3]Biodiesel!$C3/1000000 -> 32.877627 | BW150: =S150 -> 35.355469 | BX150: =BW150-BV150 -> 2.477842
A151: 40575 | B151: 26 | C151: 13 | D151: 0 | E151: 0 | F151: 150 | G151: 0 | H151: 14 | I151: 11 | J151: 48 | K151: 2 | L151: 19 | M151: 11 | N151: 0 | O151: 4 | P151: 298 | Q151: 7.3867775 | R151: 2103.5975 | S151: 40.342355 | T151: 27.263997 | U151: 13.027514 | V151: 17.367083 | W151: =V151-V150 -> 0.661121 | X151: =T151+U151 -> 40.291511 | Z151: =V151/(X152/28) -> 8.4300275 | AA151: =P151-SUM(B151:O151) -> 0 | AB151: =P151-AA151 -> 298 | AC151: =AB151/AB139-1 -> 0.47524752 | AD151: =Q151/AVERAGE(Q139,Q127,Q115,Q103,Q91)-1 -> 0.066963555 | AF151: =(2204.622/300)/Q151 -> 0.9948506 | AH151: =AK151+F151 -> 189 | AI151: =AH151/28 -> 6.75 | AK151: =SUM(B151:E151,G151) -> 39 | AL151: =AK151/28 -> 1.3928571 | AN151: =SUM(H151:M151) -> 105 | AO151: =F151/P151 -> 0.5033557 | AP151: =SUM(B151:G151)/P151 -> 0.63422819 | AQ151: =SUM(H151:M151)/P151 -> 0.35234899 | AR151: =S151/(A152-A151)*365 -> 525.89141 | AS151: =R151-AR151 -> 1577.7061 | AT151: =(S151/(A152-A151)*365)/R151 -> 0.24999622 | AV151: ='[1]Monthly SBO'!$K135 -> 1.5910684 | AX151: =S151/28 -> 1.4407984 | AZ151: =AX151-AX139 -> 1.4407984 | BA151: =F151/28 -> 5.3571429 | BD151: =AH151/X151 -> 4.6908144 | BE151: =F151/S151 -> 3.7181766 | BF151: =[2]Prices!$L496 -> 54.21 | BG151: =AVERAGE(BF149:BF151) -> 53.186667 | BH151: =C151/S151 -> 0.32224197 | BI151: =B151/S151 -> 0.64448394 | BJ151: =SUM(L151:M151)*'[12]Yellow Grease Complex'!$BH$119/S151 -> 0 | BK151: =SUM(L151:M151)*'[12]Yellow Grease Complex'!$BH$120/S151 -> 0 | BL151: =J152/S152 -> 1.0068775 | BM151: =I152/S152 -> 0.45309486 | BN151: =AR151-AR139 -> 144.64449 | BO151: =B151/$P151 -> 0.087248322 | BP151: =C151/$P151 -> 0.043624161 | BQ151: =F151/$P151 -> 0.5033557 | BR151: =H151/$P151 -> 0.046979866 | BS151: =I151/$P151 -> 0.036912752 | BT151: =J151/$P151 -> 0.16107383 | BU151: {=SUM(K151:M151/$P151)} -> 0.10738255 | BV151: =[3]Biodiesel!$C4/1000000 -> 41.535834 | BW151: =S151 -> 40.342355 | BX151: =BW151-BV151 -> -1.193479
A152: 40603 | B152: 68 | C152: 14 | D152: 0 | E152: 0 | F152: 190 | G152: 0 | H152: 19 | I152: 27 | J152: 60 | K152: 12 | L152: 33 | M152: 10 | N152: 0 | O152: 7 | P152: 440 | Q152: 7.3837682 | R152: 2081.4975 | S152: 59.59017 | T152: 40.879532 | U152: 16.804541 | V152: 19.178192 | W152: =V152-V151 -> 1.811109 | X152: =T152+U152 -> 57.684073 | Z152: =V152/(X153/31) -> 8.598894 | AA152: =P152-SUM(B152:O152) -> 0 | AB152: =P152-AA152 -> 440 | AC152: =AB152/AB140-1 -> 0.94690265 | AD152: =Q152/AVERAGE(Q140,Q128,Q116,Q104,Q92)-1 -> 0.12864378 | AF152: =(2204.622/300)/Q152 -> 0.99525606 | AH152: =AK152+F152 -> 272 | AI152: =AH152/31 -> 8.7741935 | AK152: =SUM(B152:E152,G152) -> 82 | AL152: =AK152/31 -> 2.6451613 | AN152: =SUM(H152:M152) -> 161 | AO152: =F152/P152 -> 0.43181818 | AP152: =SUM(B152:G152)/P152 -> 0.61818182 | AQ152: =SUM(H152:M152)/P152 -> 0.36590909 | AR152: =S152/(A153-A152)*365 -> 701.6262 | AS152: =R152-AR152 -> 1379.8713 | AT152: =(S152/(A153-A152)*365)/R152 -> 0.33707761 | AV152: ='[1]Monthly SBO'!$K136 -> 1.24764 | AX152: =S152/31 -> 1.9222635 | AZ152: =AX152-AX140 -> 1.9222635 | BA152: =F152/31 -> 6.1290323 | BD152: =AH152/X152 -> 4.7153397 | BE152: =F152/S152 -> 3.1884453 | BF152: =[2]Prices!$L497 -> 54.07 | BG152: =AVERAGE(BF150:BF152) -> 54.04 | BH152: =C152/S152 -> 0.23493808 | BI152: =B152/S152 -> 1.1411278 | BJ152: =SUM(L152:M152)*'[12]Yellow Grease Complex'!$BH$119/S152 -> 0 | BK152: =SUM(L152:M152)*'[12]Yellow Grease Complex'!$BH$120/S152 -> 0 | BL152: =J153/S153 -> 0.77408422 | BM152: =I153/S153 -> 0.66149015 | BN152: =AR152-AR140 -> 303.98749 | BO152: =B152/$P152 -> 0.15454545 | BP152: =C152/$P152 -> 0.031818182 | BQ152: =F152/$P152 -> 0.43181818 | BR152: =H152/$P152 -> 0.043181818 | BS152: =I152/$P152 -> 0.061363636 | BT152: =J152/$P152 -> 0.13636364 | BU152: {=SUM(K152:M152/$P152)} -> 0.125 | BV152: =[3]Biodiesel!$C5/1000000 -> 63.344564 | BW152: =S152 -> 59.59017 | BX152: =BW152-BV152 -> -3.754394
A153: 40634 | B153: 88 | C153: 20 | D153: 0 | E153: 0 | F153: 236 | G153: 0 | H153: 15 | I153: 47 | J153: 55 | K153: 8 | L153: 52 | M153: 11 | N153: 0 | O153: 0 | P153: 532 | Q153: 7.4875056 | R153: 2101.3975 | S153: 71.0517 | T153: 47.320311 | U153: 21.819273 | V153: 21.000047 | W153: =V153-V152 -> 1.821855 | X153: =T153+U153 -> 69.139584 | Z153: =V153/(X154/30) -> 8.2109428 | AA153: =P153-SUM(B153:O153) -> 0 | AB153: =P153-AA153 -> 532 | AC153: =AB153/AB141-1 -> 1.2447257 | AD153: =Q153/AVERAGE(Q141,Q129,Q117,Q105,Q93)-1 -> 0.10066039 | AF153: =(2204.622/300)/Q153 -> 0.98146705 | AH153: =AK153+F153 -> 344 | AI153: =AH153/30 -> 11.466667 | AK153: =SUM(B153:E153,G153) -> 108 | AL153: =AK153/30 -> 3.6 | AN153: =SUM(H153:M153) -> 188 | AO153: =F153/P153 -> 0.44360902 | AP153: =SUM(B153:G153)/P153 -> 0.64661654 | AQ153: =SUM(H153:M153)/P153 -> 0.35338346 | AR153: =S153/(A154-A153)*365 -> 864.46235 | AS153: =R153-AR153 -> 1236.9352 | AT153: =(S153/(A154-A153)*365)/R153 -> 0.41137498 | AV153: ='[1]Monthly SBO'!$K137 -> 1.201901 | AX153: =S153/30 -> 2.36839 | AZ153: =AX153-AX141 -> 2.36839 | BA153: =F153/30 -> 7.8666667 | BD153: =AH153/X153 -> 4.9754421 | BE153: =F153/S153 -> 3.321525 | BF153: =[2]Prices!$L498 -> 56.65 | BG153: =AVERAGE(BF151:BF153) -> 54.976667 | BH153: =C153/S153 -> 0.28148517 | BI153: =B153/S153 -> 1.2385348 | BJ153: =SUM(L153:M153)*'[12]Yellow Grease Complex'!$BH$119/S153 -> 0 | BK153: =SUM(L153:M153)*'[12]Yellow Grease Complex'!$BH$120/S153 -> 0 | BL153: =J154/S154 -> 0.73837399 | BM153: =I154/S154 -> 0.46634147 | BN153: =AR153-AR141 -> 448.48599 | BO153: =B153/$P153 -> 0.16541353 | BP153: =C153/$P153 -> 0.037593985 | BQ153: =F153/$P153 -> 0.44360902 | BR153: =H153/$P153 -> 0.028195489 | BS153: =I153/$P153 -> 0.088345865 | BT153: =J153/$P153 -> 0.10338346 | BU153: {=SUM(K153:M153/$P153)} -> 0.13345865 | BV153: =[3]Biodiesel!$C6/1000000 -> 70.426398 | BW153: =S153 -> 71.0517 | BX153: =BW153-BV153 -> 0.625302
A154: 40664 | B154: 113 | C154: 21 | D154: 0 | E154: 0 | F154: 264 | G154: 0 | H154: 16 | I154: 36 | J154: 57 | K154: 10 | L154: 41 | M154: 15 | N154: 0 | O154: 0 | P154: 573 | Q154: 7.4226017 | R154: 2064.3975 | S154: 77.196652 | T154: 49.520679 | U154: 27.20637 | V154: 23.448551 | W154: =V154-V153 -> 2.448504 | X154: =T154+U154 -> 76.727049 | Z154: =V154/(X155/31) -> 8.4777617 | AA154: =P154-SUM(B154:O154) -> 0 | AB154: =P154-AA154 -> 573 | AC154: =AB154/AB142-1 -> 1.5810811 | AD154: =Q154/AVERAGE(Q142,Q130,Q118,Q106,Q94)-1 -> 0.10748772 | AF154: =(2204.622/300)/Q154 -> 0.99004908 | AH154: =AK154+F154 -> 398 | AI154: =AH154/31 -> 12.83871 | AK154: =SUM(B154:E154,G154) -> 134 | AL154: =AK154/31 -> 4.3225806 | AN154: =SUM(H154:M154) -> 175 | AO154: =F154/P154 -> 0.46073298 | AP154: =SUM(B154:G154)/P154 -> 0.69458988 | AQ154: =SUM(H154:M154)/P154 -> 0.30541012 | AR154: =S154/(A155-A154)*365 -> 908.92832 | AS154: =R154-AR154 -> 1155.4692 | AT154: =(S154/(A155-A154)*365)/R154 -> 0.44028746 | AV154: ='[1]Monthly SBO'!$K138 -> 1.3640419 | AX154: =S154/31 -> 2.4902146 | AZ154: =AX154-AX142 -> 2.4902146 | BA154: =F154/31 -> 8.516129 | BD154: =AH154/X154 -> 5.1872189 | BE154: =F154/S154 -> 3.4198374 | BF154: =[2]Prices!$L499 -> 56.09 | BG154: =AVERAGE(BF152:BF154) -> 55.603333 | BH154: =C154/S154 -> 0.27203252 | BI154: =B154/S154 -> 1.4637941 | BJ154: =SUM(L154:M154)*'[12]Yellow Grease Complex'!$BH$119/S154 -> 0 | BK154: =SUM(L154:M154)*'[12]Yellow Grease Complex'!$BH$120/S154 -> 0 | BL154: =J155/S155 -> 0.67575006 | BM154: =I155/S155 -> 0.60203187 | BN154: =AR154-AR142 -> 533.15418 | BO154: =B154/$P154 -> 0.19720768 | BP154: =C154/$P154 -> 0.036649215 | BQ154: =F154/$P154 -> 0.46073298 | BR154: =H154/$P154 -> 0.027923211 | BS154: =I154/$P154 -> 0.062827225 | BT154: =J154/$P154 -> 0.09947644 | BU154: {=SUM(K154:M154/$P154)} -> 0.11518325 | BV154: =[3]Biodiesel!$C7/1000000 -> 77.786553 | BW154: =S154 -> 77.196652 | BX154: =BW154-BV154 -> -0.589901
A155: 40695 | B155: 75 | C155: 34 | D155: 0 | E155: 0 | F155: 311 | G155: 0 | H155: 23 | I155: 49 | J155: 55 | K155: 7 | L155: 50 | M155: 18 | N155: 0 | O155: 1 | P155: 623 | Q155: 7.6544052 | R155: 2068.9975 | S155: 81.39104 | T155: 61.776718 | U155: 23.965853 | V155: 19.302451 | W155: =V155-V154 -> -4.1461 | X155: =T155+U155 -> 85.742571 | Z155: =V155/(X156/30) -> 6.5516814 | AA155: =P155-SUM(B155:O155) -> 0 | AB155: =P155-AA155 -> 623 | AC155: =AB155/AB143-1 -> 2.2789474 | AD155: =Q155/AVERAGE(Q143,Q131,Q119,Q107,Q95)-1 -> 0.089890688 | AF155: =(2204.622/300)/Q155 -> 0.96006676 | AH155: =AK155+F155 -> 420 | AI155: =AH155/30 -> 14 | AK155: =SUM(B155:E155,G155) -> 109 | AL155: =AK155/30 -> 3.6333333 | AN155: =SUM(H155:M155) -> 202 | AO155: =F155/P155 -> 0.49919743 | AP155: =SUM(B155:G155)/P155 -> 0.6741573 | AQ155: =SUM(H155:M155)/P155 -> 0.32423756 | AR155: =S155/(A156-A155)*365 -> 990.25765 | AS155: =R155-AR155 -> 1078.7398 | AT155: =(S155/(A156-A155)*365)/R155 -> 0.47861713 | AV155: ='[1]Monthly SBO'!$K139 -> 1.3289927 | AX155: =S155/30 -> 2.7130347 | AZ155: =AX155-AX143 -> 2.7130347 | BA155: =F155/30 -> 10.366667 | BD155: =AH155/X155 -> 4.8983836 | BE155: =F155/S155 -> 3.8210594 | BF155: =[2]Prices!$L500 -> 55.68 | BG155: =AVERAGE(BF153:BF155) -> 56.14 | BH155: =C155/S155 -> 0.4177364 | BI155: =B155/S155 -> 0.92147735 | BJ155: =SUM(L155:M155)*'[12]Yellow Grease Complex'!$BH$119/S155 -> 0 | BK155: =SUM(L155:M155)*'[12]Yellow Grease Complex'!$BH$120/S155 -> 0 | BL155: =J156/S156 -> 0.53446924 | BM155: =I156/S156 -> 0.69808227 | BN155: =AR155-AR143 -> 660.95108 | BO155: =B155/$P155 -> 0.12038523 | BP155: =C155/$P155 -> 0.054574639 | BQ155: =F155/$P155 -> 0.49919743 | BR155: =H155/$P155 -> 0.036918138 | BS155: =I155/$P155 -> 0.078651685 | BT155: =J155/$P155 -> 0.088282504 | BU155: {=SUM(K155:M155/$P155)} -> 0.12038523 | BV155: =[3]Biodiesel!$C8/1000000 -> 77.961734 | BW155: =S155 -> 81.39104 | BX155: =BW155-BV155 -> 3.429306
A156: 40725 | B156: 77 | C156: 35 | D156: 0 | E156: 0 | F156: 367 | G156: 0 | H156: 26 | I156: 64 | J156: 49 | K156: 6 | L156: 45 | M156: 20 | N156: 0 | O156: 2 | P156: 691 | Q156: 7.5371071 | R156: 1958.4975 | S156: 91.679738 | T156: 65.997152 | U156: 22.388332 | V156: 22.956565 | W156: =V156-V155 -> 3.654114 | X156: =T156+U156 -> 88.385484 | Z156: =V156/(X157/31) -> 7.507235 | AA156: =P156-SUM(B156:O156) -> 0 | AB156: =P156-AA156 -> 691 | AC156: =AB156/AB144-1 -> 2.3707317 | AD156: =Q156/AVERAGE(Q144,Q132,Q120,Q108,Q96)-1 -> 0.054557387 | AF156: =(2204.622/300)/Q156 -> 0.97500804 | AH156: =AK156+F156 -> 479 | AI156: =AH156/31 -> 15.451613 | AK156: =SUM(B156:E156,G156) -> 112 | AL156: =AK156/31 -> 3.6129032 | AN156: =SUM(H156:M156) -> 210 | AO156: =F156/P156 -> 0.53111433 | AP156: =SUM(B156:G156)/P156 -> 0.69319826 | AQ156: =SUM(H156:M156)/P156 -> 0.30390738 | AR156: =S156/(A157-A156)*365 -> 1079.455 | AS156: =R156-AR156 -> 879.04252 | AT156: =(S156/(A157-A156)*365)/R156 -> 0.55116485 | AV156: ='[1]Monthly SBO'!$K140 -> 1.204671 | AX156: =S156/31 -> 2.9574109 | AZ156: =AX156-AX144 -> 2.9574109 | BA156: =F156/31 -> 11.83871 | BD156: =AH156/X156 -> 5.419442 | BE156: =F156/S156 -> 4.0030655 | BF156: =[2]Prices!$L501 -> 55.16 | BG156: =AVERAGE(BF154:BF156) -> 55.643333 | BH156: =C156/S156 -> 0.38176374 | BI156: =B156/S156 -> 0.83988024 | BJ156: =SUM(L156:M156)*'[12]Yellow Grease Complex'!$BH$119/S156 -> 0 | BK156: =SUM(L156:M156)*'[12]Yellow Grease Complex'!$BH$120/S156 -> 0 | BL156: =J157/S157 -> 0.50269733 | BM156: =I157/S157 -> 0.39796872 | BN156: =AR156-AR144 -> 754.5169 | BO156: =B156/$P156 -> 0.11143271 | BP156: =C156/$P156 -> 0.05065123 | BQ156: =F156/$P156 -> 0.53111433 | BR156: =H156/$P156 -> 0.037626628 | BS156: =I156/$P156 -> 0.092619392 | BT156: =J156/$P156 -> 0.070911722 | BU156: {=SUM(K156:M156/$P156)} -> 0.10274964 | BV156: =[3]Biodiesel!$C9/1000000 -> 86.877103 | BW156: =S156 -> 91.679738 | BX156: =BW156-BV156 -> 4.802635
A157: 40756 | B157: 84 | C157: 37 | D157: 0 | E157: 0 | F157: 398 | G157: 0 | H157: 34 | I157: 38 | J157: 48 | K157: 15 | L157: 47 | M157: 19 | N157: 0 | O157: 5 | P157: 725 | Q157: 7.5928243 | R157: 2007.6575 | S157: 95.484891 | T157: 64.352621 | U157: 30.443068 | V157: 25.141057 | W157: =V157-V156 -> 2.184492 | X157: =T157+U157 -> 94.795689 | Z157: =V157/(X158/31) -> 7.4275506 | AA157: =P157-SUM(B157:O157) -> 0 | AB157: =P157-AA157 -> 725 | AC157: =AB157/AB145-1 -> 2.6616162 | AD157: =Q157/AVERAGE(Q145,Q133,Q121,Q109,Q97)-1 -> 0.074649501 | AF157: =(2204.622/300)/Q157 -> 0.96785329 | AH157: =AK157+F157 -> 519 | AI157: =AH157/31 -> 16.741935 | AK157: =SUM(B157:E157,G157) -> 121 | AL157: =AK157/31 -> 3.9032258 | AN157: =SUM(H157:M157) -> 201 | AO157: =F157/P157 -> 0.54896552 | AP157: =SUM(B157:G157)/P157 -> 0.71586207 | AQ157: =SUM(H157:M157)/P157 -> 0.27724138 | AR157: =S157/(A158-A157)*365 -> 1124.2576 | AS157: =R157-AR157 -> 883.39991 | AT157: =(S157/(A158-A157)*365)/R157 -> 0.55998475 | AV157: ='[1]Monthly SBO'!$K141 -> 1.2680296 | AX157: =S157/31 -> 3.0801578 | AZ157: =AX157-AX145 -> 3.0801578 | BA157: =F157/31 -> 12.83871 | BD157: =AH157/X157 -> 5.4749325 | BE157: =F157/S157 -> 4.1681987 | BF157: =[2]Prices!$L502 -> 54.39 | BG157: =AVERAGE(BF155:BF157) -> 55.076667 | BH157: =C157/S157 -> 0.38749586 | BI157: =B157/S157 -> 0.87972033 | BJ157: =SUM(L157:M157)*'[12]Yellow Grease Complex'!$BH$119/S157 -> 0 | BK157: =SUM(L157:M157)*'[12]Yellow Grease Complex'!$BH$120/S157 -> 0 | BL157: =J158/S158 -> 0.4169179 | BM157: =I158/S158 -> 0.51072443 | BN157: =AR157-AR145 -> 801.32168 | BO157: =B157/$P157 -> 0.11586207 | BP157: =C157/$P157 -> 0.051034483 | BQ157: =F157/$P157 -> 0.54896552 | BR157: =H157/$P157 -> 0.046896552 | BS157: =I157/$P157 -> 0.052413793 | BT157: =J157/$P157 -> 0.066206897 | BU157: {=SUM(K157:M157/$P157)} -> 0.11172414 | BV157: =[3]Biodiesel!$C10/1000000 -> 101.06452 | BW157: =S157 -> 95.484891 | BX157: =BW157-BV157 -> -5.579627
A158: 40787 | B158: 84 | C158: 27 | D158: 0 | E158: 0 | F158: 430 | G158: 0 | H158: 20 | I158: 49 | J158: 40 | K158: 4 | L158: 50 | M158: 21 | N158: 0 | O158: 0 | P158: 725 | Q158: 7.5566369 | R158: 2087.0947 | S158: 95.942151 | T158: 67.886833 | U158: 37.043151 | V158: 21.060061 | W158: =V158-V157 -> -4.080996 | X158: =T158+U158 -> 104.92998 | Z158: =V158/(X159/30) -> 6.0226999 | AA158: =P158-SUM(B158:O158) -> 0 | AB158: =P158-AA158 -> 725 | AC158: =AB158/AB146-1 -> 2.2511211 | AD158: =Q158/AVERAGE(Q146,Q134,Q122,Q110,Q98)-1 -> 0.050506011 | AF158: =(2204.622/300)/Q158 -> 0.97248817 | AH158: =AK158+F158 -> 541 | AI158: =AH158/30 -> 18.033333 | AK158: =SUM(B158:E158,G158) -> 111 | AL158: =AK158/30 -> 3.7 | AN158: =SUM(H158:M158) -> 184 | AO158: =F158/P158 -> 0.59310345 | AP158: =SUM(B158:G158)/P158 -> 0.7462069 | AQ158: =SUM(H158:M158)/P158 -> 0.2537931 | AR158: =S158/(A159-A158)*365 -> 1167.2962 | AS158: =R158-AR158 -> 919.79848 | AT158: =(S158/(A159-A158)*365)/R158 -> 0.5592924 | AV158: ='[1]Monthly SBO'!$K142 -> 1.26702 | AX158: =S158/30 -> 3.1980717 | AZ158: =AX158-AX146 -> 3.1980717 | BA158: =F158/30 -> 14.333333 | BD158: =AH158/X158 -> 5.155819 | BE158: =F158/S158 -> 4.4818674 | BF158: =[2]Prices!$L503 -> 55.13 | BG158: =AVERAGE(BF156:BF158) -> 54.893333 | BH158: =C158/S158 -> 0.28141958 | BI158: =B158/S158 -> 0.87552759 | BJ158: =SUM(L158:M158)*'[12]Yellow Grease Complex'!$BH$119/S158 -> 0 | BK158: =SUM(L158:M158)*'[12]Yellow Grease Complex'!$BH$120/S158 -> 0 | BL158: =J159/S159 -> 0.27529257 | BM158: =I159/S159 -> 0.37022104 | BN158: =AR158-AR146 -> 797.95409 | BO158: =B158/$P158 -> 0.11586207 | BP158: =C158/$P158 -> 0.037241379 | BQ158: =F158/$P158 -> 0.59310345 | BR158: =H158/$P158 -> 0.027586207 | BS158: =I158/$P158 -> 0.067586207 | BT158: =J158/$P158 -> 0.055172414 | BU158: {=SUM(K158:M158/$P158)} -> 0.10344828 | BV158: =[3]Biodiesel!$C11/1000000 -> 114.50415 | BW158: =S158 -> 95.942151 | BX158: =BW158-BV158 -> -18.562003 | EW158: ='[4]Renewable Diesel'!$AX21 -> 40 | EX158: =EW158+R158 -> 2127.0947
A159: 40817 | B159: 69 | C159: 30 | D159: 0 | E159: 0 | F159: 527 | G159: 0 | H159: 31 | I159: 39 | J159: 29 | K159: 7 | L159: 42 | M159: 21 | N159: 0 | O159: 0 | P159: 795 | Q159: 7.5468135 | R159: 2118.9382 | S159: 105.34247 | T159: 69.074421 | U159: 35.829002 | V159: 25.484167 | W159: =V159-V158 -> 4.424106 | X159: =T159+U159 -> 104.90342 | Z159: =V159/(X160/31) -> 7.505007 | AA159: =P159-SUM(B159:O159) -> 0 | AB159: =P159-AA159 -> 795 | AC159: =AB159/AB147-1 -> 2.6805556 | AD159: =Q159/AVERAGE(Q147,Q135,Q123,Q111,Q99)-1 -> 0.014281008 | AF159: =(2204.622/300)/Q159 -> 0.97375403 | AH159: =AK159+F159 -> 626 | AI159: =AH159/31 -> 20.193548 | AK159: =SUM(B159:E159,G159) -> 99 | AL159: =AK159/31 -> 3.1935484 | AN159: =SUM(H159:M159) -> 169 | AO159: =F159/P159 -> 0.66289308 | AP159: =SUM(B159:G159)/P159 -> 0.78742138 | AQ159: =SUM(H159:M159)/P159 -> 0.21257862 | AR159: =S159/(A160-A159)*365 -> 1240.3227 | AS159: =R159-AR159 -> 878.61547 | AT159: =(S159/(A160-A159)*365)/R159 -> 0.58535105 | AV159: ='[1]Monthly SBO'!$K143 -> 0.92302857 | AX159: =S159/31 -> 3.3981443 | AZ159: =AX159-AX147 -> 3.3981443 | BA159: =F159/31 -> 17 | BD159: =AH159/X159 -> 5.9673935 | BE159: =F159/S159 -> 5.0027304 | BF159: =[2]Prices!$L504 -> 51.73 | BG159: =AVERAGE(BF157:BF159) -> 53.75 | BH159: =C159/S159 -> 0.28478541 | BI159: =B159/S159 -> 0.65500645 | BJ159: =SUM(L159:M159)*'[12]Yellow Grease Complex'!$BH$119/S159 -> 0 | BK159: =SUM(L159:M159)*'[12]Yellow Grease Complex'!$BH$120/S159 -> 0 | BL159: =J160/S160 -> 0.33413744 | BM159: =I160/S160 -> 0.29595031 | BN159: =AR159-AR147 -> 905.88446 | BO159: =B159/$P159 -> 0.086792453 | BP159: =C159/$P159 -> 0.037735849 | BQ159: =F159/$P159 -> 0.66289308 | BR159: =H159/$P159 -> 0.038993711 | BS159: =I159/$P159 -> 0.049056604 | BT159: =J159/$P159 -> 0.036477987 | BU159: {=SUM(K159:M159/$P159)} -> 0.088050314 | BV159: =[3]Biodiesel!$C12/1000000 -> 111.94831 | BW159: =S159 -> 105.34247 | BX159: =BW159-BV159 -> -6.605833 | EW159: ='[4]Renewable Diesel'!$AX22 -> 40 | EX159: =EW159+R159 -> 2158.9382
A160: 40848 | B160: 84 | C160: 27 | D160: 0 | E160: 0 | F160: 538 | G160: 0 | H160: 13 | I160: 31 | J160: 35 | K160: 8 | L160: 39 | M160: 20 | N160: 0 | O160: 0 | P160: 795 | Q160: 7.5896933 | R160: 2097.7632 | S160: 104.74732 | T160: 66.378486 | U160: 38.885796 | V160: 26.067302 | W160: =V160-V159 -> 0.583135 | X160: =T160+U160 -> 105.26428 | Z160: =V160/(X161/30) -> 6.4891842 | AA160: =P160-SUM(B160:O160) -> 0 | AB160: =P160-AA160 -> 795 | AC160: =AB160/AB148-1 -> 3.847561 | AD160: =Q160/AVERAGE(Q148,Q136,Q124,Q112,Q100)-1 -> 0.04038746 | AF160: =(2204.622/300)/Q160 -> 0.96825256 | AH160: =AK160+F160 -> 649 | AI160: =AH160/30 -> 21.633333 | AK160: =SUM(B160:E160,G160) -> 111 | AL160: =AK160/30 -> 3.7 | AN160: =SUM(H160:M160) -> 146 | AO160: =F160/P160 -> 0.67672956 | AP160: =SUM(B160:G160)/P160 -> 0.8163522 | AQ160: =SUM(H160:M160)/P160 -> 0.1836478 | AR160: =S160/(A161-A160)*365 -> 1274.4257 | AS160: =R160-AR160 -> 823.33749 | AT160: =(S160/(A161-A160)*365)/R160 -> 0.60751647 | AV160: ='[1]Monthly SBO'!$K144 -> 0.7922381 | AX160: =S160/30 -> 3.4915772 | AZ160: =AX160-AX148 -> 3.4915772 | BA160: =F160/30 -> 17.933333 | BD160: =AH160/X160 -> 6.1654342 | BE160: =F160/S160 -> 5.1361698 | BF160: =[2]Prices!$L505 -> 51.44 | BG160: =AVERAGE(BF158:BF160) -> 52.766667 | BH160: =C160/S160 -> 0.25776317 | BI160: =B160/S160 -> 0.80192986 | BJ160: =SUM(L160:M160)*'[12]Yellow Grease Complex'!$BH$119/S160 -> 0 | BK160: =SUM(L160:M160)*'[12]Yellow Grease Complex'!$BH$120/S160 -> 0 | BL160: =J161/S161 -> 0.23775269 | BM160: =I161/S161 -> 0.24689703 | BN160: =AR160-AR148 -> 1004.7185 | BO160: =B160/$P160 -> 0.10566038 | BP160: =C160/$P160 -> 0.033962264 | BQ160: =F160/$P160 -> 0.67672956 | BR160: =H160/$P160 -> 0.016352201 | BS160: =I160/$P160 -> 0.038993711 | BT160: =J160/$P160 -> 0.044025157 | BU160: {=SUM(K160:M160/$P160)} -> 0.08427673 | BV160: =[3]Biodiesel!$C13/1000000 -> 105.48354 | BW160: =S160 -> 104.74732 | BX160: =BW160-BV160 -> -0.736229 | EW160: ='[4]Renewable Diesel'!$AX23 -> 120 | EX160: =EW160+R160 -> 2217.7632
A161: 40878 | B161: 71 | C161: 30 | D161: 0 | E161: 0 | F161: 592 | G161: 0 | H161: 15 | I161: 27 | J161: 26 | K161: 5 | L161: 35 | M161: 20 | N161: 0 | O161: 0 | P161: 821 | Q161: 7.5074984 | R161: 2089.9382 | S161: 109.35733 | T161: 58.729838 | U161: 61.781314 | V161: 14.096103 | W161: =V161-V160 -> -11.971199 | X161: =T161+U161 -> 120.51115 | Z161: =V161/(X162/31) -> 7.1755793 | AA161: =P161-SUM(B161:O161) -> 0 | AB161: =P161-AA161 -> 821 | AC161: =AB161/AB149-1 -> 3.3439153 | AD161: =Q161/AVERAGE(Q149,Q137,Q125,Q113,Q101)-1 -> 0.016878557 | AF161: =(2204.622/300)/Q161 -> 0.97885335 | AH161: =AK161+F161 -> 693 | AI161: =AH161/31 -> 22.354839 | AK161: =SUM(B161:E161,G161) -> 101 | AL161: =AK161/31 -> 3.2580645 | AN161: =SUM(H161:M161) -> 128 | AO161: =F161/P161 -> 0.72107186 | AP161: =SUM(B161:G161)/P161 -> 0.84409257 | AQ161: =SUM(H161:M161)/P161 -> 0.15590743 | AR161: =S161/(A162-A161)*365 -> 1287.5944 | AS161: =R161-AR161 -> 802.34376 | AT161: =(S161/(A162-A161)*365)/R161 -> 0.6160921 | AV161: ='[1]Monthly SBO'!$K145 -> 0.895025 | AX161: =S161/31 -> 3.5276559 | AZ161: =AX161-AX149 -> 3.5276559 | BA161: =F161/31 -> 19.096774 | BD161: =AH161/X161 -> 5.7505051 | BE161: =F161/S161 -> 5.4134459 | BF161: =[2]Prices!$L506 -> 50.17 | BG161: =AVERAGE(BF159:BF161) -> 51.113333 | BH161: =C161/S161 -> 0.27433003 | BI161: =B161/S161 -> 0.64924773 | BJ161: =SUM(L161:M161)*'[12]Yellow Grease Complex'!$BH$119/S161 -> 0 | BK161: =SUM(L161:M161)*'[12]Yellow Grease Complex'!$BH$120/S161 -> 0 | BL161: =J162/S162 -> 0.39431104 | BM161: =I162/S162 -> 0.35352025 | BN161: =AR161-AR149 -> 996.83391 | BO161: =B161/$P161 -> 0.086479903 | BP161: =C161/$P161 -> 0.036540804 | BQ161: =F161/$P161 -> 0.72107186 | BR161: =H161/$P161 -> 0.018270402 | BS161: =I161/$P161 -> 0.032886724 | BT161: =J161/$P161 -> 0.031668697 | BU161: {=SUM(K161:M161/$P161)} -> 0.073081608 | BV161: =[3]Biodiesel!$C14/1000000 -> 150.88892 | BW161: =S161 -> 109.35733 | BX161: =BW161-BV161 -> -41.53159 | EW161: ='[4]Renewable Diesel'!$AX24 -> 120 | EX161: =EW161+R161 -> 2209.9382
A162: 40909 | B162: 73 | C162: 50 | D162: 0 | E162: 0 | F162: 306 | G162: 0 | H162: 20 | I162: 26 | J162: 29 | K162: 3 | L162: 37 | M162: 18 | N162: 0 | O162: 0 | P162: 562 | Q162: 7.6414761 | R162: 2248 | S162: 73.546 | T162: 44.898107 | U162: 16 | V162: 26.183079 | W162: =V162-V161 -> 12.086976 | X162: =T162+U162 -> 60.898107 | Z162: =V162/(X163/31) -> 11.248802 | AA162: =P162-SUM(B162:O162) -> 0 | AB162: =P162-AA162 -> 562 | AC162: =AB162/AB150-1 -> 1.0892193 | AD162: =Q162/AVERAGE(Q150,Q138,Q126,Q114,Q102)-1 -> 0.053657365 | AF162: =(2204.622/300)/Q162 -> 0.96169116 | AH162: =AK162+F162 -> 429 | AI162: =AH162/31 -> 13.83871 | AK162: =SUM(B162:E162,G162) -> 123 | AL162: =AK162/31 -> 3.9677419 | AN162: =SUM(H162:M162) -> 133 | AO162: =F162/P162 -> 0.54448399 | AP162: =SUM(B162:G162)/P162 -> 0.7633452 | AQ162: =SUM(H162:M162)/P162 -> 0.2366548 | AR162: =S162/(A163-A162)*365 -> 865.94484 | AS162: =R162-AR162 -> 1382.0552 | AT162: =(S162/(A163-A162)*365)/R162 -> 0.38520678 | AV162: ='[1]Monthly SBO'!$K146 -> 0.85043579 | AX162: =S162/31 -> 2.3724516 | AZ162: =AX162-AX150 -> 1.2319526 | BA162: =F162/31 -> 9.8709677 | BD162: =AH162/X162 -> 7.0445539 | BE162: =F162/S162 -> 4.1606614 | BF162: =[2]Prices!$L507 -> 50.99 | BG162: =AVERAGE(BF160:BF162) -> 50.866667 | BH162: =C162/S162 -> 0.67984663 | BI162: =B162/S162 -> 0.99257607 | BJ162: =SUM(L162:M162)*'[12]Yellow Grease Complex'!$BH$119/S162 -> 0 | BK162: =SUM(L162:M162)*'[12]Yellow Grease Complex'!$BH$120/S162 -> 0 | BL162: =J163/S163 -> 0.36599525 | BM162: =I163/S163 -> 0.25241052 | BN162: =AR162-AR150 -> 449.6627 | BO162: =B162/$P162 -> 0.12989324 | BP162: =C162/$P162 -> 0.088967972 | BQ162: =F162/$P162 -> 0.54448399 | BR162: =H162/$P162 -> 0.035587189 | BS162: =I162/$P162 -> 0.046263345 | BT162: =J162/$P162 -> 0.051601423 | BU162: {=SUM(K162:M162/$P162)} -> 0.10320285 | BV162: =[3]Biodiesel!$D3/1000000 -> 60.11773 | BW162: =S162 -> 73.546 | BX162: =BW162-BV162 -> 13.42827 | EW162: ='[4]Renewable Diesel'!$AX25 -> 160 | EX162: =EW162+R162 -> 2408
A163: 40940 | B163: 90 | C163: 51 | D163: 0 | E163: 0 | F163: 321 | G163: 0 | H163: 8 | I163: 20 | J163: 29 | K163: 4 | L163: 41 | M163: 22 | N163: 0 | O163: 0 | P163: 586 | Q163: 7.3956282 | R163: 2248 | S163: 79.236 | T163: 57.156613 | U163: 15 | V163: 33.334476 | W163: =V163-V162 -> 7.151397 | X163: =T163+U163 -> 72.156613 | Z163: =V163/(X164/28) -> 10.192401 | AA163: =P163-SUM(B163:O163) -> 0 | AB163: =P163-AA163 -> 586 | AC163: =AB163/AB151-1 -> 0.96644295 | AD163: =Q163/AVERAGE(Q151,Q139,Q127,Q115,Q103)-1 -> 0.044918167 | AF163: =(2204.622/300)/Q163 -> 0.99366 | AH163: =AK163+F163 -> 462 | AI163: =AH163/29 -> 15.931034 | AK163: =SUM(B163:E163,G163) -> 141 | AL163: =AK163/29 -> 4.862069 | AN163: =SUM(H163:M163) -> 124 | AO163: =F163/P163 -> 0.54778157 | AP163: =SUM(B163:G163)/P163 -> 0.7883959 | AQ163: =SUM(H163:M163)/P163 -> 0.2116041 | AR163: =S163/(A164-A163)*365 -> 997.28069 | AS163: =R163-AR163 -> 1250.7193 | AT163: =(S163/(A164-A163)*365)/R163 -> 0.4436302 | AV163: ='[1]Monthly SBO'!$K147 -> 0.835248 | AX163: =S163/28 -> 2.8298571 | AZ163: =AX163-AX151 -> 1.3890588 | BA163: =F163/29 -> 11.068966 | BD163: =AH163/X163 -> 6.4027396 | BE163: =F163/S163 -> 4.0511889 | BF163: =[2]Prices!$L508 -> 52.36 | BG163: =AVERAGE(BF161:BF163) -> 51.173333 | BH163: =C163/S163 -> 0.64364683 | BI163: =B163/S163 -> 1.1358473 | BJ163: =SUM(L163:M163)*'[12]Yellow Grease Complex'!$BH$119/S163 -> 0 | BK163: =SUM(L163:M163)*'[12]Yellow Grease Complex'!$BH$120/S163 -> 0 | BL163: =J164/S164 -> 0.32795904 | BM163: =I164/S164 -> 0.25390377 | BN163: =AR163-AR151 -> 471.38928 | BO163: =B163/$P163 -> 0.15358362 | BP163: =C163/$P163 -> 0.087030717 | BQ163: =F163/$P163 -> 0.54778157 | BR163: =H163/$P163 -> 0.013651877 | BS163: =I163/$P163 -> 0.034129693 | BT163: =J163/$P163 -> 0.049488055 | BU163: {=SUM(K163:M163/$P163)} -> 0.11433447 | BV163: =[3]Biodiesel!$D4/1000000 -> 72.510777 | BW163: =S163 -> 79.236 | BX163: =BW163-BV163 -> 6.725223 | EW163: ='[4]Renewable Diesel'!$AX26 -> 160 | EX163: =EW163+R163 -> 2408
A164: 40969 | B164: 117 | C164: 54 | D164: 0 | E164: 0 | F164: 388 | G164: 0 | H164: 11 | I164: 24 | J164: 31 | K164: 6 | L164: 61 | M164: 21 | N164: 0 | O164: 0 | P164: 713 | Q164: 7.5430578 | R164: 2233 | S164: 94.524 | T164: 74.57463 | U164: 17 | V164: 35.508702 | W164: =V164-V163 -> 2.174226 | X164: =T164+U164 -> 91.57463 | Z164: =V164/(X165/31) -> 11.982909 | AA164: =P164-SUM(B164:O164) -> 0 | AB164: =P164-AA164 -> 713 | AC164: =AB164/AB152-1 -> 0.62045455 | AD164: =Q164/AVERAGE(Q152,Q140,Q128,Q116,Q104)-1 -> 0.10558316 | AF164: =(2204.622/300)/Q164 -> 0.97423885 | AH164: =AK164+F164 -> 559 | AI164: =AH164/31 -> 18.032258 | AK164: =SUM(B164:E164,G164) -> 171 | AL164: =AK164/31 -> 5.516129 | AN164: =SUM(H164:M164) -> 154 | AO164: =F164/P164 -> 0.54417952 | AP164: =SUM(B164:G164)/P164 -> 0.78401122 | AQ164: =SUM(H164:M164)/P164 -> 0.21598878 | AR164: =S164/(A165-A164)*365 -> 1112.9439 | AS164: =R164-AR164 -> 1120.0561 | AT164: =(S164/(A165-A164)*365)/R164 -> 0.49840747 | AV164: ='[1]Monthly SBO'!$K148 -> 0.89566909 | AX164: =S164/31 -> 3.0491613 | AZ164: =AX164-AX152 -> 1.1268977 | BA164: =F164/31 -> 12.516129 | BD164: =AH164/X164 -> 6.1043108 | BE164: =F164/S164 -> 4.1047776 | BF164: =[2]Prices!$L509 -> 53.43 | BG164: =AVERAGE(BF162:BF164) -> 52.26 | BH164: =C164/S164 -> 0.57128348 | BI164: =B164/S164 -> 1.2377809 | BJ164: =SUM(L164:M164)*'[12]Yellow Grease Complex'!$BH$119/S164 -> 0 | BK164: =SUM(L164:M164)*'[12]Yellow Grease Complex'!$BH$120/S164 -> 0 | BL164: =J165/S165 -> 0.43643486 | BM164: =I165/S165 -> 0.47901387 | BN164: =AR164-AR152 -> 411.31768 | BO164: =B164/$P164 -> 0.16409537 | BP164: =C164/$P164 -> 0.075736325 | BQ164: =F164/$P164 -> 0.54417952 | BR164: =H164/$P164 -> 0.01542777 | BS164: =I164/$P164 -> 0.033660589 | BT164: =J164/$P164 -> 0.043478261 | BU164: {=SUM(K164:M164/$P164)} -> 0.12342216 | BV164: =[3]Biodiesel!$D5/1000000 -> 95.153437 | BW164: =S164 -> 94.524 | BX164: =BW164-BV164 -> -0.629437 | EW164: ='[4]Renewable Diesel'!$AX27 -> 160 | EX164: =EW164+R164 -> 2393
A165: 41000 | B165: 112 | C165: 54 | D165: 0 | E165: 0 | F165: 350 | G165: 0 | H165: 13 | I165: 45 | J165: 41 | K165: 5 | L165: 67 | M165: 24 | N165: 0 | O165: 0 | P165: 711 | Q165: 7.5684191 | R165: 2203 | S165: 93.943 | T165: 67.861647 | U165: 24 | V165: 40.219206 | W165: =V165-V164 -> 4.710504 | X165: =T165+U165 -> 91.861647 | Z165: =V165/(X166/30) -> 10.947696 | AA165: =P165-SUM(B165:O165) -> 0 | AB165: =P165-AA165 -> 711 | AC165: =AB165/AB153-1 -> 0.33646617 | AD165: =Q165/AVERAGE(Q153,Q141,Q129,Q117,Q105)-1 -> 0.076436478 | AF165: =(2204.622/300)/Q165 -> 0.97097424 | AH165: =AK165+F165 -> 516 | AI165: =AH165/30 -> 17.2 | AK165: =SUM(B165:E165,G165) -> 166 | AL165: =AK165/30 -> 5.5333333 | AN165: =SUM(H165:M165) -> 195 | AO165: =F165/P165 -> 0.49226442 | AP165: =SUM(B165:G165)/P165 -> 0.7257384 | AQ165: =SUM(H165:M165)/P165 -> 0.2742616 | AR165: =S165/(A166-A165)*365 -> 1142.9732 | AS165: =R165-AR165 -> 1060.0268 | AT165: =(S165/(A166-A165)*365)/R165 -> 0.51882577 | AV165: ='[1]Monthly SBO'!$K149 -> 1.088425 | AX165: =S165/30 -> 3.1314333 | AZ165: =AX165-AX153 -> 0.76304333 | BA165: =F165/30 -> 11.666667 | BD165: =AH165/X165 -> 5.6171429 | BE165: =F165/S165 -> 3.7256634 | BF165: =[2]Prices!$L510 -> 54.96 | BG165: =AVERAGE(BF163:BF165) -> 53.583333 | BH165: =C165/S165 -> 0.57481664 | BI165: =B165/S165 -> 1.1922123 | BJ165: =SUM(L165:M165)*'[12]Yellow Grease Complex'!$BH$119/S165 -> 0 | BK165: =SUM(L165:M165)*'[12]Yellow Grease Complex'!$BH$120/S165 -> 0 | BL165: =J166/S166 -> 0.37265863 | BM165: =I166/S166 -> 0.4903403 | BN165: =AR165-AR153 -> 278.51082 | BO165: =B165/$P165 -> 0.15752461 | BP165: =C165/$P165 -> 0.075949367 | BQ165: =F165/$P165 -> 0.49226442 | BR165: =H165/$P165 -> 0.018284107 | BS165: =I165/$P165 -> 0.063291139 | BT165: =J165/$P165 -> 0.05766526 | BU165: {=SUM(K165:M165/$P165)} -> 0.1350211 | BV165: =[3]Biodiesel!$D6/1000000 -> 92.581599 | BW165: =S165 -> 93.943 | BX165: =BW165-BV165 -> 1.361401 | EW165: ='[4]Renewable Diesel'!$AX28 -> 160 | EX165: =EW165+R165 -> 2363
A166: 41030 | B166: 85 | C166: 56 | D166: 0 | E166: 0 | F166: 429 | G166: 0 | H166: 16 | I166: 50 | J166: 38 | K166: 5 | L166: 61 | M166: 27 | N166: 0 | O166: 0 | P166: 767 | Q166: 7.5218201 | R166: 2199 | S166: 101.97 | T166: 77.212797 | U166: 33 | V166: 36.869796 | W166: =V166-V165 -> -3.34941 | X166: =T166+U166 -> 110.2128 | Z166: =V166/(X167/31) -> 11.590422 | AA166: =P166-SUM(B166:O166) -> 0 | AB166: =P166-AA166 -> 767 | AC166: =AB166/AB154-1 -> 0.33856894 | AD166: =Q166/AVERAGE(Q154,Q142,Q130,Q118,Q106)-1 -> 0.083471624 | AF166: =(2204.622/300)/Q166 -> 0.97698959 | AH166: =AK166+F166 -> 570 | AI166: =AH166/31 -> 18.387097 | AK166: =SUM(B166:E166,G166) -> 141 | AL166: =AK166/31 -> 4.5483871 | AN166: =SUM(H166:M166) -> 197 | AO166: =F166/P166 -> 0.55932203 | AP166: =SUM(B166:G166)/P166 -> 0.74315515 | AQ166: =SUM(H166:M166)/P166 -> 0.25684485 | AR166: =S166/(A167-A166)*365 -> 1200.6145 | AS166: =R166-AR166 -> 998.38548 | AT166: =(S166/(A167-A166)*365)/R166 -> 0.54598204 | AV166: ='[1]Monthly SBO'!$K150 -> 0.99234545 | AX166: =S166/31 -> 3.2893548 | AZ166: =AX166-AX154 -> 0.79914026 | BA166: =F166/31 -> 13.83871 | BD166: =AH166/X166 -> 5.1718132 | BE166: =F166/S166 -> 4.2071197 | BF166: =[2]Prices!$L511 -> 50.69 | BG166: =AVERAGE(BF164:BF166) -> 53.026667 | BH166: =C166/S166 -> 0.54918113 | BI166: =B166/S166 -> 0.8335785 | BJ166: =SUM(L166:M166)*'[12]Yellow Grease Complex'!$BH$119/S166 -> 0 | BK166: =SUM(L166:M166)*'[12]Yellow Grease Complex'!$BH$120/S166 -> 0 | BL166: =J167/S167 -> 0.41767516 | BM166: =I167/S167 -> 0.29986934 | BN166: =AR166-AR154 -> 291.68619 | BO166: =B166/$P166 -> 0.11082138 | BP166: =C166/$P166 -> 0.073011734 | BQ166: =F166/$P166 -> 0.55932203 | BR166: =H166/$P166 -> 0.020860495 | BS166: =I166/$P166 -> 0.065189048 | BT166: =J166/$P166 -> 0.049543677 | BU166: {=SUM(K166:M166/$P166)} -> 0.12125163 | BV166: =[3]Biodiesel!$D7/1000000 -> 107.97218 | BW166: =S166 -> 101.97 | BX166: =BW166-BV166 -> -6.002177 | EW166: ='[4]Renewable Diesel'!$AX29 -> 160 | EX166: =EW166+R166 -> 2359
A167: 41061 | B167: 103 | C167: 55 | D167: 0 | E167: 0 | F167: 369 | G167: 0 | H167: 14 | I167: 28 | J167: 39 | K167: 4 | L167: 64 | M167: 27 | N167: 0 | O167: 0 | P167: 703 | Q167: 7.5288624 | R167: 2183 | S167: 93.374 | T167: 79.612776 | U167: 19 | V167: 30.529573 | W167: =V167-V166 -> -6.340223 | X167: =T167+U167 -> 98.612776 | Z167: =V167/(X168/30) -> 10.16559 | AA167: =P167-SUM(B167:O167) -> 0 | AB167: =P167-AA167 -> 703 | AC167: =AB167/AB155-1 -> 0.12841091 | AD167: =Q167/AVERAGE(Q155,Q143,Q131,Q119,Q107)-1 -> 0.040828064 | AF167: =(2204.622/300)/Q167 -> 0.97607575 | AH167: =AK167+F167 -> 527 | AI167: =AH167/30 -> 17.566667 | AK167: =SUM(B167:E167,G167) -> 158 | AL167: =AK167/30 -> 5.2666667 | AN167: =SUM(H167:M167) -> 176 | AO167: =F167/P167 -> 0.52489331 | AP167: =SUM(B167:G167)/P167 -> 0.74964438 | AQ167: =SUM(H167:M167)/P167 -> 0.25035562 | AR167: =S167/(A168-A167)*365 -> 1136.0503 | AS167: =R167-AR167 -> 1046.9497 | AT167: =(S167/(A168-A167)*365)/R167 -> 0.52040785 | AV167: ='[1]Monthly SBO'!$K151 -> 1.1665714 | AX167: =S167/30 -> 3.1124667 | AZ167: =AX167-AX155 -> 0.399432 | BA167: =F167/30 -> 12.3 | BD167: =AH167/X167 -> 5.3441351 | BE167: =F167/S167 -> 3.9518496 | BF167: =[2]Prices!$L512 -> 48.65 | BG167: =AVERAGE(BF165:BF167) -> 51.433333 | BH167: =C167/S167 -> 0.58902907 | BI167: =B167/S167 -> 1.1030908 | BJ167: =SUM(L167:M167)*'[12]Yellow Grease Complex'!$BH$119/S167 -> 0 | BK167: =SUM(L167:M167)*'[12]Yellow Grease Complex'!$BH$120/S167 -> 0 | BL167: =J168/S168 -> 0.34707838 | BM167: =I168/S168 -> 0.33588231 | BN167: =AR167-AR155 -> 145.79268 | BO167: =B167/$P167 -> 0.14651494 | BP167: =C167/$P167 -> 0.078236131 | BQ167: =F167/$P167 -> 0.52489331 | BR167: =H167/$P167 -> 0.019914651 | BS167: =I167/$P167 -> 0.039829303 | BT167: =J167/$P167 -> 0.055476529 | BU167: {=SUM(K167:M167/$P167)} -> 0.13513514 | BV167: =[3]Biodiesel!$D8/1000000 -> 106.61364 | BW167: =S167 -> 93.374 | BX167: =BW167-BV167 -> -13.239644 | EW167: ='[4]Renewable Diesel'!$AX30 -> 160 | EX167: =EW167+R167 -> 2343
A168: 41091 | B168: 66 | C168: 54 | D168: 0 | E168: 0 | F168: 347 | G168: 0 | H168: 20 | I168: 30 | J168: 31 | K168: 4 | L168: 65 | M168: 25 | N168: 0 | O168: 0 | P168: 642 | Q168: 7.1878814 | R168: 2180 | S168: 89.317 | T168: 72.096803 | U168: 18 | V168: 29.298923 | W168: =V168-V167 -> -1.23065 | X168: =T168+U168 -> 90.096803 | Z168: =V168/(X169/31) -> 9.9742397 | AA168: =P168-SUM(B168:O168) -> 0 | AB168: =P168-AA168 -> 642 | AC168: =AB168/AB156-1 -> -0.070911722 | AD168: =Q168/AVERAGE(Q156,Q144,Q132,Q120,Q108)-1 -> -0.01226737 | AF168: =(2204.622/300)/Q168 -> 1.0223791 | AH168: =AK168+F168 -> 467 | AI168: =AH168/31 -> 15.064516 | AK168: =SUM(B168:E168,G168) -> 120 | AL168: =AK168/31 -> 3.8709677 | AN168: =SUM(H168:M168) -> 175 | AO168: =F168/P168 -> 0.54049844 | AP168: =SUM(B168:G168)/P168 -> 0.72741433 | AQ168: =SUM(H168:M168)/P168 -> 0.27258567 | AR168: =S168/(A169-A168)*365 -> 1051.6356 | AS168: =R168-AR168 -> 1128.3644 | AT168: =(S168/(A169-A168)*365)/R168 -> 0.48240167 | AV168: ='[1]Monthly SBO'!$K152 -> 1.239481 | AX168: =S168/31 -> 2.8811935 | AZ168: =AX168-AX156 -> -0.076217355 | BA168: =F168/31 -> 11.193548 | BD168: =AH168/X168 -> 5.1833138 | BE168: =F168/S168 -> 3.8850387 | BF168: =[2]Prices!$L513 -> 51.96 | BG168: =AVERAGE(BF166:BF168) -> 50.433333 | BH168: =C168/S168 -> 0.60458815 | BI168: =B168/S168 -> 0.73894108 | BJ168: =SUM(L168:M168)*'[12]Yellow Grease Complex'!$BH$119/S168 -> 0 | BK168: =SUM(L168:M168)*'[12]Yellow Grease Complex'!$BH$120/S168 -> 0 | BL168: =J169/S169 -> 0.3719709 | BM168: =I169/S169 -> 0.4813741 | BN168: =AR168-AR156 -> -27.819335 | BO168: =B168/$P168 -> 0.10280374 | BP168: =C168/$P168 -> 0.08411215 | BQ168: =F168/$P168 -> 0.54049844 | BR168: =H168/$P168 -> 0.031152648 | BS168: =I168/$P168 -> 0.046728972 | BT168: =J168/$P168 -> 0.048286604 | BU168: {=SUM(K168:M168/$P168)} -> 0.14641745 | BV168: =[3]Biodiesel!$D9/1000000 -> 97.342403 | BW168: =S168 -> 89.317 | BX168: =BW168-BV168 -> -8.025403 | EW168: ='[4]Renewable Diesel'!$AX31 -> 160 | EX168: =EW168+R168 -> 2340
A169: 41122 | B169: 48 | C169: 59 | D169: 0 | E169: 0 | F169: 385 | G169: 0 | H169: 21 | I169: 44 | J169: 34 | K169: 4 | L169: 70 | M169: 28 | N169: 0 | O169: 0 | P169: 693 | Q169: 7.5816421 | R169: 2180 | S169: 91.405 | T169: 73.061238 | U169: 18 | V169: 29.839125 | W169: =V169-V168 -> 0.540202 | X169: =T169+U169 -> 91.061238 | Z169: =V169/(X170/31) -> 11.75932 | AA169: =P169-SUM(B169:O169) -> 0 | AB169: =P169-AA169 -> 693 | AC169: =AB169/AB157-1 -> -0.044137931 | AD169: =Q169/AVERAGE(Q157,Q145,Q133,Q121,Q109)-1 -> 0.047013817 | AF169: =(2204.622/300)/Q169 -> 0.96928078 | AH169: =AK169+F169 -> 492 | AI169: =AH169/31 -> 15.870968 | AK169: =SUM(B169:E169,G169) -> 107 | AL169: =AK169/31 -> 3.4516129 | AN169: =SUM(H169:M169) -> 201 | AO169: =F169/P169 -> 0.55555556 | AP169: =SUM(B169:G169)/P169 -> 0.70995671 | AQ169: =SUM(H169:M169)/P169 -> 0.29004329 | AR169: =S169/(A170-A169)*365 -> 1076.2202 | AS169: =R169-AR169 -> 1103.7798 | AT169: =(S169/(A170-A169)*365)/R169 -> 0.49367897 | AV169: ='[1]Monthly SBO'!$K153 -> 1.042773 | AX169: =S169/31 -> 2.9485484 | AZ169: =AX169-AX157 -> -0.13160939 | BA169: =F169/31 -> 12.419355 | BD169: =AH169/X169 -> 5.4029575 | BE169: =F169/S169 -> 4.2120234 | BF169: =[2]Prices!$L514 -> 52.65 | BG169: =AVERAGE(BF167:BF169) -> 51.086667 | BH169: =C169/S169 -> 0.64547891 | BI169: =B169/S169 -> 0.52513539 | BJ169: =SUM(L169:M169)*'[12]Yellow Grease Complex'!$BH$119/S169 -> 0 | BK169: =SUM(L169:M169)*'[12]Yellow Grease Complex'!$BH$120/S169 -> 0 | BL169: =J170/S170 -> 0.40316177 | BM169: =I170/S170 -> 0.59863414 | BN169: =AR169-AR157 -> -48.037426 | BO169: =B169/$P169 -> 0.069264069 | BP169: =C169/$P169 -> 0.085137085 | BQ169: =F169/$P169 -> 0.55555556 | BR169: =H169/$P169 -> 0.03030303 | BS169: =I169/$P169 -> 0.063492063 | BT169: =J169/$P169 -> 0.049062049 | BU169: {=SUM(K169:M169/$P169)} -> 0.14718615 | BV169: =[3]Biodiesel!$D10/1000000 -> 96.25435 | BW169: =S169 -> 91.405 | BX169: =BW169-BV169 -> -4.84935 | EW169: ='[4]Renewable Diesel'!$AX32 -> 160 | EX169: =EW169+R169 -> 2340
A170: 41153 | B170: 46 | C170: 55 | D170: 0 | E170: 0 | F170: 322 | G170: 0 | H170: 19 | I170: 49 | J170: 33 | K170: 4 | L170: 65 | M170: 25 | N170: 0 | O170: 0 | P170: 618 | Q170: 7.5501203 | R170: 2210 | S170: 81.853 | T170: 61.662106 | U170: 17 | V170: 32.193562 | W170: =V170-V169 -> 2.354437 | X170: =T170+U170 -> 78.662106 | Z170: =V170/(X171/30) -> 13.046369 | AA170: =P170-SUM(B170:O170) -> 0 | AB170: =P170-AA170 -> 618 | AC170: =AB170/AB158-1 -> -0.14758621 | AD170: =Q170/AVERAGE(Q158,Q146,Q134,Q122,Q110)-1 -> 0.032222282 | AF170: =(2204.622/300)/Q170 -> 0.97332753 | AH170: =AK170+F170 -> 423 | AI170: =AH170/30 -> 14.1 | AK170: =SUM(B170:E170,G170) -> 101 | AL170: =AK170/30 -> 3.3666667 | AN170: =SUM(H170:M170) -> 195 | AO170: =F170/P170 -> 0.5210356 | AP170: =SUM(B170:G170)/P170 -> 0.68446602 | AQ170: =SUM(H170:M170)/P170 -> 0.31553398 | AR170: =S170/(A171-A170)*365 -> 995.87817 | AS170: =R170-AR170 -> 1214.1218 | AT170: =(S170/(A171-A170)*365)/R170 -> 0.4506236 | AV170: ='[1]Monthly SBO'!$K154 -> 1.0364632 | AX170: =S170/30 -> 2.7284333 | AZ170: =AX170-AX158 -> -0.46963837 | BA170: =F170/30 -> 10.733333 | BD170: =AH170/X170 -> 5.3774304 | BE170: =F170/S170 -> 3.9338815 | BF170: =[2]Prices!$L515 -> 53.81 | BG170: =AVERAGE(BF168:BF170) -> 52.806667 | BH170: =C170/S170 -> 0.67193628 | BI170: =B170/S170 -> 0.56198307 | BJ170: =SUM(L170:M170)*'[12]Yellow Grease Complex'!$BH$119/S170 -> 0 | BK170: =SUM(L170:M170)*'[12]Yellow Grease Complex'!$BH$120/S170 -> 0 | BL170: =J171/S171 -> 0.54461167 | BM170: =I171/S171 -> 0.5844613 | BN170: =AR170-AR158 -> -171.418 | BO170: =B170/$P170 -> 0.074433657 | BP170: =C170/$P170 -> 0.088996764 | BQ170: =F170/$P170 -> 0.5210356 | BR170: =H170/$P170 -> 0.030744337 | BS170: =I170/$P170 -> 0.079288026 | BT170: =J170/$P170 -> 0.053398058 | BU170: {=SUM(K170:M170/$P170)} -> 0.15210356 | BV170: =[3]Biodiesel!$D11/1000000 -> 81.339106 | BW170: =S170 -> 81.853 | BX170: =BW170-BV170 -> 0.513894 | EW170: ='[4]Renewable Diesel'!$AX33 -> 160 | EX170: =EW170+R170 -> 2370
A171: 41183 | B171: 16 | C171: 59 | D171: 0 | E171: 0 | F171: 307 | G171: 0 | H171: 14 | I171: 44 | J171: 41 | K171: 4 | L171: 60 | M171: 29 | N171: 0 | O171: 0 | P171: 574 | Q171: 7.6245633 | R171: 2210 | S171: 75.283 | T171: 62.028784 | U171: 12 | V171: 33.084848 | W171: =V171-V170 -> 0.891286 | X171: =T171+U171 -> 74.028784 | Z171: =V171/(X172/31) -> 15.711949 | AA171: =P171-SUM(B171:O171) -> 0 | AB171: =P171-AA171 -> 574 | AC171: =AB171/AB159-1 -> -0.27798742 | AD171: =Q171/AVERAGE(Q159,Q147,Q135,Q123,Q111)-1 -> 0.019875528 | AF171: =(2204.622/300)/Q171 -> 0.96382438 | AH171: =AK171+F171 -> 382 | AI171: =AH171/31 -> 12.322581 | AK171: =SUM(B171:E171,G171) -> 75 | AL171: =AK171/31 -> 2.4193548 | AN171: =SUM(H171:M171) -> 192 | AO171: =F171/P171 -> 0.53484321 | AP171: =SUM(B171:G171)/P171 -> 0.66550523 | AQ171: =SUM(H171:M171)/P171 -> 0.33449477 | AR171: =S171/(A172-A171)*365 -> 886.39661 | AS171: =R171-AR171 -> 1323.6034 | AT171: =(S171/(A172-A171)*365)/R171 -> 0.40108444 | AV171: ='[1]Monthly SBO'!$K155 -> 0.71946174 | AX171: =S171/31 -> 2.4284839 | AZ171: =AX171-AX159 -> -0.96966045 | BA171: =F171/31 -> 9.9032258 | BD171: =AH171/X171 -> 5.160155 | BE171: =F171/S171 -> 4.0779459 | BF171: =[2]Prices!$L516 -> 49.31 | BG171: =AVERAGE(BF169:BF171) -> 51.923333 | BH171: =C171/S171 -> 0.78370947 | BI171: =B171/S171 -> 0.21253138 | BJ171: =SUM(L171:M171)*'[12]Yellow Grease Complex'!$BH$119/S171 -> 0 | BK171: =SUM(L171:M171)*'[12]Yellow Grease Complex'!$BH$120/S171 -> 0 | BL171: =J172/S172 -> 0.48926244 | BM171: =I172/S172 -> 0.38442049 | BN171: =AR171-AR159 -> -353.92606 | BO171: =B171/$P171 -> 0.027874564 | BP171: =C171/$P171 -> 0.10278746 | BQ171: =F171/$P171 -> 0.53484321 | BR171: =H171/$P171 -> 0.024390244 | BS171: =I171/$P171 -> 0.076655052 | BT171: =J171/$P171 -> 0.071428571 | BU171: {=SUM(K171:M171/$P171)} -> 0.16202091 | BV171: =[3]Biodiesel!$D12/1000000 -> 80.600435 | BW171: =S171 -> 75.283 | BX171: =BW171-BV171 -> -5.317435 | EW171: ='[4]Renewable Diesel'!$AX34 -> 160 | EX171: =EW171+R171 -> 2370
A172: 41214 | B172: 18 | C172: 48 | D172: 0 | E172: 0 | F172: 246 | G172: 0 | H172: 11 | I172: 22 | J172: 28 | K172: 4 | L172: 36 | M172: 23 | N172: 0 | O172: 0 | P172: 436 | Q172: 7.6185151 | R172: 2172 | S172: 57.229 | T172: 53.277088 | U172: 12 | V172: 25.568331 | W172: =V172-V171 -> -7.516517 | X172: =T172+U172 -> 65.277088 | Z172: =V172/(X173/30) -> 14.199464 | AA172: =P172-SUM(B172:O172) -> 0 | AB172: =P172-AA172 -> 436 | AC172: =AB172/AB160-1 -> -0.45157233 | AD172: =Q172/AVERAGE(Q160,Q148,Q136,Q124,Q112)-1 -> 0.030465684 | AF172: =(2204.622/300)/Q172 -> 0.96458954 | AH172: =AK172+F172 -> 312 | AI172: =AH172/30 -> 10.4 | AK172: =SUM(B172:E172,G172) -> 66 | AL172: =AK172/30 -> 2.2 | AN172: =SUM(H172:M172) -> 124 | AO172: =F172/P172 -> 0.56422018 | AP172: =SUM(B172:G172)/P172 -> 0.71559633 | AQ172: =SUM(H172:M172)/P172 -> 0.28440367 | AR172: =S172/(A173-A172)*365 -> 696.28617 | AS172: =R172-AR172 -> 1475.7138 | AT172: =(S172/(A173-A172)*365)/R172 -> 0.32057374 | AV172: ='[1]Monthly SBO'!$K156 -> 0.68011429 | AX172: =S172/30 -> 1.9076333 | AZ172: =AX172-AX160 -> -1.5839438 | BA172: =F172/30 -> 8.2 | BD172: =AH172/X172 -> 4.779625 | BE172: =F172/S172 -> 4.29852 | BF172: =[2]Prices!$L517 -> 46.27 | BG172: =AVERAGE(BF170:BF172) -> 49.796667 | BH172: =C172/S172 -> 0.83873561 | BI172: =B172/S172 -> 0.31452585 | BJ172: =SUM(L172:M172)*'[12]Yellow Grease Complex'!$BH$119/S172 -> 0 | BK172: =SUM(L172:M172)*'[12]Yellow Grease Complex'!$BH$120/S172 -> 0 | BL172: =J173/S173 -> 0.59289877 | BM172: =I173/S173 -> 0.050819894 | BN172: =AR172-AR160 -> -578.1395 | BO172: =B172/$P172 -> 0.041284404 | BP172: =C172/$P172 -> 0.11009174 | BQ172: =F172/$P172 -> 0.56422018 | BR172: =H172/$P172 -> 0.025229358 | BS172: =I172/$P172 -> 0.050458716 | BT172: =J172/$P172 -> 0.064220183 | BU172: {=SUM(K172:M172/$P172)} -> 0.14449541 | BV172: =[3]Biodiesel!$D13/1000000 -> 68.079027 | BW172: =S172 -> 57.229 | BX172: =BW172-BV172 -> -10.850027 | EW172: ='[4]Renewable Diesel'!$AX35 -> 160 | EX172: =EW172+R172 -> 2332
A173: 41244 | B173: 16 | C173: 50 | D173: 0 | E173: 0 | F173: 273 | G173: 0 | H173: 9 | I173: 3 | J173: 35 | K173: 2 | L173: 45 | M173: 21 | N173: 0 | O173: 0 | P173: 454 | Q173: 7.690744 | R173: 2104 | S173: 59.032 | T173: 44.019638 | U173: 10 | V173: 30.548952 | W173: =V173-V172 -> 4.980621 | X173: =T173+U173 -> 54.019638 | Z173: =V173/(X174/31) -> 14.216639 | AA173: =P173-SUM(B173:O173) -> 0 | AB173: =P173-AA173 -> 454 | AC173: =AB173/AB161-1 -> -0.44701583 | AD173: =Q173/AVERAGE(Q161,Q149,Q137,Q125,Q113)-1 -> 0.035870871 | AF173: =(2204.622/300)/Q173 -> 0.95553044 | AH173: =AK173+F173 -> 339 | AI173: =AH173/31 -> 10.935484 | AK173: =SUM(B173:E173,G173) -> 66 | AL173: =AK173/31 -> 2.1290323 | AN173: =SUM(H173:M173) -> 115 | AO173: =F173/P173 -> 0.60132159 | AP173: =SUM(B173:G173)/P173 -> 0.74669604 | AQ173: =SUM(H173:M173)/P173 -> 0.25330396 | AR173: =S173/(A174-A173)*365 -> 695.05419 | AS173: =R173-AR173 -> 1408.9458 | AT173: =(S173/(A174-A173)*365)/R173 -> 0.33034895 | AV173: ='[1]Monthly SBO'!$K157 -> 0.753909 | AX173: =S173/31 -> 1.9042581 | AZ173: =AX173-AX161 -> -1.6233978 | BA173: =F173/31 -> 8.8064516 | BD173: =AH173/X173 -> 6.2754956 | BE173: =F173/S173 -> 4.6246104 | BF173: =[2]Prices!$L518 -> 47.16 | BG173: =AVERAGE(BF171:BF173) -> 47.58 | BH173: =C173/S173 -> 0.84699824 | BI173: =B173/S173 -> 0.27103944 | BJ173: =SUM(L173:M173)*'[12]Yellow Grease Complex'!$BH$119/S173 -> 0 | BK173: =SUM(L173:M173)*'[12]Yellow Grease Complex'!$BH$120/S173 -> 0 | BL173: =J174/S174 -> 0.45016264 | BM173: =I174/S174 -> 0.21782063 | BN173: =AR173-AR161 -> -592.5402 | BO173: =B173/$P173 -> 0.035242291 | BP173: =C173/$P173 -> 0.11013216 | BQ173: =F173/$P173 -> 0.60132159 | BR173: =H173/$P173 -> 0.019823789 | BS173: =I173/$P173 -> 0.0066079295 | BT173: =J173/$P173 -> 0.077092511 | BU173: {=SUM(K173:M173/$P173)} -> 0.14977974 | BV173: =[3]Biodiesel!$D14/1000000 -> 58.155836 | BW173: =S173 -> 59.032 | BX173: =BW173-BV173 -> 0.876164 | EW173: ='[4]Renewable Diesel'!$AX36 -> 160 | EX173: =EW173+R173 -> 2264
A174: 41275 | B174: 16 | C174: 60 | D174: 0 | E174: 2 | F174: 313 | G174: 0 | H174: 7 | I174: 15 | J174: 31 | K174: 3 | L174: 54 | M174: 23 | N174: 0 | O174: 1 | P174: 525 | Q174: 7.6237221 | R174: 2112 | S174: 68.864 | T174: 51.613318 | U174: 15 | V174: 31.469879 | W174: =V174-V173 -> 0.920927 | X174: =T174+U174 -> 66.613318 | Z174: =V174/(X175/31) -> 14.201442 | AA174: =P174-SUM(B174:O174) -> 0 | AB174: =P174-AA174 -> 525 | AC174: =AB174/AB162-1 -> -0.065836299 | AD174: =Q174/AVERAGE(Q162,Q150,Q138,Q126,Q114)-1 -> 0.037294706 | AF174: =(2204.622/300)/Q174 -> 0.96393073 | AH174: =AK174+F174 -> 391 | AI174: =AH174/31 -> 12.612903 | AK174: =SUM(B174:E174,G174) -> 78 | AL174: =AK174/31 -> 2.516129 | AN174: =SUM(H174:M174) -> 133 | AO174: =F174/P174 -> 0.59619048 | AP174: =SUM(B174:G174)/P174 -> 0.7447619 | AQ174: =SUM(H174:M174)/P174 -> 0.25333333 | AR174: =S174/(A175-A174)*365 -> 810.81806 | AS174: =R174-AR174 -> 1301.1819 | AT174: =(S174/(A175-A174)*365)/R174 -> 0.38391007 | AU174: =AT174/AVERAGE(AT162,AT150,AT138,AT126,AT114)-1 -> #DIV/0! | AV174: ='[1]Monthly SBO'!$K158 -> 0.81215714 | AX174: =S174/31 -> 2.2214194 | AZ174: =AX174-AX162 -> -0.15103226 | BA174: =F174/31 -> 10.096774 | BD174: =AH174/X174 -> 5.8696971 | BE174: =F174/S174 -> 4.5451905 | BF174: =[2]Prices!$L519 -> 48.85 | BG174: =AVERAGE(BF172:BF174) -> 47.426667 | BH174: =C174/S174 -> 0.87128253 | BI174: =B174/S174 -> 0.23234201 | BJ174: =SUM(L174:M174)*'[12]Yellow Grease Complex'!$BH$119/S174 -> 0 | BK174: =SUM(L174:M174)*'[12]Yellow Grease Complex'!$BH$120/S174 -> 0 | BL174: =J175/S175 -> 0.45561979 | BM174: =I175/S175 -> 0.39866731 | BN174: =AR174-AR162 -> -55.126774 | BO174: =B174/$P174 -> 0.03047619 | BP174: =C174/$P174 -> 0.11428571 | BQ174: =F174/$P174 -> 0.59619048 | BR174: =H174/$P174 -> 0.013333333 | BS174: =I174/$P174 -> 0.028571429 | BT174: =J174/$P174 -> 0.059047619 | BU174: {=SUM(K174:M174/$P174)} -> 0.15238095 | BV174: =[3]Biodiesel!$E3/1000000 -> 71.15781 | BW174: =S174 -> 68.864 | BX174: =BW174-BV174 -> -2.29381 | EW174: ='[4]Renewable Diesel'!$AX37 -> 160 | EX174: =EW174+R174 -> 2272
A175: 41306 | B175: 38 | C175: 61 | D175: 0 | E175: 3 | F175: 287 | G175: 0 | H175: 8 | I175: 28 | J175: 32 | K175: 3 | L175: 59 | M175: 23 | N175: 0 | O175: 0 | P175: 542 | Q175: 7.7170601 | R175: 2121 | S175: 70.234 | T175: 45.694874 | U175: 23 | V175: 33.00042 | W175: =V175-V174 -> 1.530541 | X175: =T175+U175 -> 68.694874 | Z175: =V175/(X176/28) -> 9.3782425 | AA175: =P175-SUM(B175:O175) -> 0 | AB175: =P175-AA175 -> 542 | AC175: =AB175/AB163-1 -> -0.075085324 | AD175: =Q175/AVERAGE(Q163,Q151,Q139,Q127,Q115)-1 -> 0.078224863 | AF175: =(2204.622/300)/Q175 -> 0.95227197 | AH175: =AK175+F175 -> 389 | AI175: =AH175/28 -> 13.892857 | AK175: =SUM(B175:E175,G175) -> 102 | AL175: =AK175/28 -> 3.6428571 | AN175: =SUM(H175:M175) -> 153 | AO175: =F175/P175 -> 0.5295203 | AP175: =SUM(B175:G175)/P175 -> 0.71771218 | AQ175: =SUM(H175:M175)/P175 -> 0.28228782 | AR175: =S175/(A176-A175)*365 -> 915.55036 | AS175: =R175-AR175 -> 1205.4496 | AT175: =(S175/(A176-A175)*365)/R175 -> 0.43165976 | AU175: =AT175/AVERAGE(AT163,AT151,AT139,AT127,AT115)-1 -> #DIV/0! | AV175: ='[1]Monthly SBO'!$K159 -> 0.74859579 | AX175: =S175/28 -> 2.5083571 | AZ175: =AX175-AX163 -> -0.3215 | BA175: =F175/28 -> 10.25 | BD175: =AH175/X175 -> 5.6627224 | BE175: =F175/S175 -> 4.0863399 | BF175: =[2]Prices!$L520 -> 49.33 | BG175: =AVERAGE(BF173:BF175) -> 48.446667 | BH175: =C175/S175 -> 0.86852522 | BI175: =B175/S175 -> 0.5410485 | BJ175: =SUM(L175:M175)*'[12]Yellow Grease Complex'!$BH$119/S175 -> 0 | BK175: =SUM(L175:M175)*'[12]Yellow Grease Complex'!$BH$120/S175 -> 0 | BL175: =J176/S176 -> 0.3554362 | BM175: =I176/S176 -> 0.52328107 | BN175: =AR175-AR163 -> -81.730333 | BO175: =B175/$P175 -> 0.070110701 | BP175: =C175/$P175 -> 0.11254613 | BQ175: =F175/$P175 -> 0.5295203 | BR175: =H175/$P175 -> 0.014760148 | BS175: =I175/$P175 -> 0.051660517 | BT175: =J175/$P175 -> 0.05904059 | BU175: {=SUM(K175:M175/$P175)} -> 0.15682657 | BV175: =[3]Biodiesel!$E4/1000000 -> 74.511501 | BW175: =S175 -> 70.234 | BX175: =BW175-BV175 -> -4.277501 | EW175: ='[4]Renewable Diesel'!$AX38 -> 160 | EX175: =EW175+R175 -> 2281
A176: 41334 | B176: 39 | C176: 71 | D176: 0 | E176: 25 | F176: 443 | G176: 0 | H176: 9 | I176: 53 | J176: 36 | K176: 2 | L176: 77 | M176: 15 | N176: 0 | O176: 0 | P176: 770 | Q176: 7.6023854 | R176: 2140 | S176: 101.284 | T176: 69.527177 | U176: 29 | V176: 34.649788 | W176: =V176-V175 -> 1.649368 | X176: =T176+U176 -> 98.527177 | Z176: =V176/(X177/31) -> 9.7762573 | AA176: =P176-SUM(B176:O176) -> 0 | AB176: =P176-AA176 -> 770 | AC176: =AB176/AB164-1 -> 0.079943899 | AD176: =Q176/AVERAGE(Q164,Q152,Q140,Q128,Q116)-1 -> 0.085622899 | AF176: =(2204.622/300)/Q176 -> 0.96663608 | AH176: =AK176+F176 -> 578 | AI176: =AH176/31 -> 18.645161 | AK176: =SUM(B176:E176,G176) -> 135 | AL176: =AK176/31 -> 4.3548387 | AN176: =SUM(H176:M176) -> 192 | AO176: =F176/P176 -> 0.57532468 | AP176: =SUM(B176:G176)/P176 -> 0.75064935 | AQ176: =SUM(H176:M176)/P176 -> 0.24935065 | AR176: =S176/(A177-A176)*365 -> 1192.5374 | AS176: =R176-AR176 -> 947.46258 | AT176: =(S176/(A177-A176)*365)/R176 -> 0.55726048 | AU176: =AT176/AVERAGE(AT164,AT152,AT140,AT128,AT116)-1 -> #DIV/0! | AV176: ='[1]Monthly SBO'!$K160 -> 0.877599 | AX176: =S176/31 -> 3.2672258 | AZ176: =AX176-AX164 -> 0.21806452 | BA176: =F176/31 -> 14.290323 | BD176: =AH176/X176 -> 5.8664017 | BE176: =F176/S176 -> 4.3738399 | BF176: =[2]Prices!$L521 -> 48.62 | BG176: =AVERAGE(BF174:BF176) -> 48.933333 | BH176: =C176/S176 -> 0.70099917 | BI176: =B176/S176 -> 0.38505588 | BJ176: =SUM(L176:M176)*'[12]Yellow Grease Complex'!$BH$119/S176 -> 0 | BK176: =SUM(L176:M176)*'[12]Yellow Grease Complex'!$BH$120/S176 -> 0 | BL176: =J177/S177 -> 0.44851849 | BM176: =I177/S177 -> 0.52327157 | BN176: =AR176-AR164 -> 79.593548 | BO176: =B176/$P176 -> 0.050649351 | BP176: =C176/$P176 -> 0.092207792 | BQ176: =F176/$P176 -> 0.57532468 | BR176: =H176/$P176 -> 0.011688312 | BS176: =I176/$P176 -> 0.068831169 | BT176: =J176/$P176 -> 0.046753247 | BU176: {=SUM(K176:M176/$P176)} -> 0.12207792 | BV176: =[3]Biodiesel!$E5/1000000 -> 101.03234 | BW176: =S176 -> 101.284 | BX176: =BW176-BV176 -> 0.251665 | EW176: ='[4]Renewable Diesel'!$AX39 -> 160 | EX176: =EW176+R176 -> 2300
A177: 41365 | B177: 47 | C177: 71 | D177: 0 | E177: 45 | F177: 423 | G177: 0 | H177: 15 | I177: 56 | J177: 48 | K177: 2 | L177: 84 | M177: 20 | N177: 0 | O177: 3 | P177: 814 | Q177: 7.606126 | R177: 2141 | S177: 107.019 | T177: 78.872663 | U177: 31 | V177: 33.829733 | W177: =V177-V176 -> -0.820055 | X177: =T177+U177 -> 109.87266 | Z177: =V177/(X178/30) -> 8.6857502 | AA177: =P177-SUM(B177:O177) -> 0 | AB177: =P177-AA177 -> 814 | AC177: =AB177/AB165-1 -> 0.14486639 | AD177: =Q177/AVERAGE(Q165,Q153,Q141,Q129,Q117)-1 -> 0.061514814 | AF177: =(2204.622/300)/Q177 -> 0.9661607 | AH177: =AK177+F177 -> 586 | AI177: =AH177/30 -> 19.533333 | AK177: =SUM(B177:E177,G177) -> 163 | AL177: =AK177/30 -> 5.4333333 | AN177: =SUM(H177:M177) -> 225 | AO177: =F177/P177 -> 0.51965602 | AP177: =SUM(B177:G177)/P177 -> 0.71990172 | AQ177: =SUM(H177:M177)/P177 -> 0.27641278 | AR177: =S177/(A178-A177)*365 -> 1302.0645 | AS177: =R177-AR177 -> 838.9355 | AT177: =(S177/(A178-A177)*365)/R177 -> 0.60815717 | AU177: =AT177/AVERAGE(AT165,AT153,AT141,AT129,AT117)-1 -> #DIV/0! | AV177: ='[1]Monthly SBO'!$K161 -> 0.85141909 | AX177: =S177/30 -> 3.5673 | AZ177: =AX177-AX165 -> 0.43586667 | BA177: =F177/30 -> 14.1 | BD177: =AH177/X177 -> 5.3334468 | BE177: =F177/S177 -> 3.9525692 | BF177: =[2]Prices!$L522 -> 49.28 | BG177: =AVERAGE(BF175:BF177) -> 49.076667 | BH177: =C177/S177 -> 0.6634336 | BI177: =B177/S177 -> 0.43917435 | BJ177: =SUM(L177:M177)*'[12]Yellow Grease Complex'!$BH$119/S177 -> 0 | BK177: =SUM(L177:M177)*'[12]Yellow Grease Complex'!$BH$120/S177 -> 0 | BL177: =J178/S178 -> 0.36903358 | BM177: =I178/S178 -> 0.54904996 | BN177: =AR177-AR165 -> 159.09133 | BO177: =B177/$P177 -> 0.057739558 | BP177: =C177/$P177 -> 0.087223587 | BQ177: =F177/$P177 -> 0.51965602 | BR177: =H177/$P177 -> 0.018427518 | BS177: =I177/$P177 -> 0.068796069 | BT177: =J177/$P177 -> 0.058968059 | BU177: {=SUM(K177:M177/$P177)} -> 0.13022113 | BV177: =[3]Biodiesel!$E6/1000000 -> 110.96067 | BW177: =S177 -> 107.019 | BX177: =BW177-BV177 -> -3.941668 | EW177: ='[4]Renewable Diesel'!$AX40 -> 160 | EX177: =EW177+R177 -> 2301
A178: 41395 | B178: 33 | C178: 91 | D178: 0 | E178: 35 | F178: 416 | G178: 0 | H178: 20 | I178: 61 | J178: 41 | K178: 2 | L178: 92 | M178: 20 | N178: 0 | O178: 2 | P178: 813 | Q178: 7.3176659 | R178: 2153 | S178: 111.101 | T178: 76.845634 | U178: 40 | V178: 26.721242 | W178: =V178-V177 -> -7.108491 | X178: =T178+U178 -> 116.84563 | Z178: =V178/(X179/31) -> 7.2408997 | AA178: =P178-SUM(B178:O178) -> 0 | AB178: =P178-AA178 -> 813 | AC178: =AB178/AB166-1 -> 0.059973924 | AD178: =Q178/AVERAGE(Q166,Q154,Q142,Q130,Q118)-1 -> 0.032517982 | AF178: =(2204.622/300)/Q178 -> 1.0042464 | AH178: =AK178+F178 -> 575 | AI178: =AH178/31 -> 18.548387 | AK178: =SUM(B178:E178,G178) -> 159 | AL178: =AK178/31 -> 5.1290323 | AN178: =SUM(H178:M178) -> 236 | AO178: =F178/P178 -> 0.51168512 | AP178: =SUM(B178:G178)/P178 -> 0.70725707 | AQ178: =SUM(H178:M178)/P178 -> 0.2902829 | AR178: =S178/(A179-A178)*365 -> 1308.1247 | AS178: =R178-AR178 -> 844.87532 | AT178: =(S178/(A179-A178)*365)/R178 -> 0.60758229 | AU178: =AT178/AVERAGE(AT166,AT154,AT142,AT130,AT118)-1 -> #DIV/0! | AV178: ='[1]Monthly SBO'!$K162 -> 0.84904364 | AX178: =S178/31 -> 3.5839032 | AZ178: =AX178-AX166 -> 0.29454839 | BA178: =F178/31 -> 13.419355 | BD178: =AH178/X178 -> 4.9210226 | BE178: =F178/S178 -> 3.7443407 | BF178: =[2]Prices!$L523 -> 49.31 | BG178: =AVERAGE(BF176:BF178) -> 49.07 | BH178: =C178/S178 -> 0.81907454 | BI178: =B178/S178 -> 0.29702703 | BJ178: =SUM(L178:M178)*'[12]Yellow Grease Complex'!$BH$119/S178 -> 0 | BK178: =SUM(L178:M178)*'[12]Yellow Grease Complex'!$BH$120/S178 -> 0 | BL178: =J179/S179 -> 0.36165089 | BM178: =I179/S179 -> 0.5116037 | BN178: =AR178-AR166 -> 107.51016 | BO178: =B178/$P178 -> 0.040590406 | BP178: =C178/$P178 -> 0.11193112 | BQ178: =F178/$P178 -> 0.51168512 | BR178: =H178/$P178 -> 0.024600246 | BS178: =I178/$P178 -> 0.07503075 | BT178: =J178/$P178 -> 0.050430504 | BU178: {=SUM(K178:M178/$P178)} -> 0.1402214 | BV178: =[3]Biodiesel!$E7/1000000 -> 118.93685 | BW178: =S178 -> 111.101 | BX178: =BW178-BV178 -> -7.835855 | EW178: ='[4]Renewable Diesel'!$AX41 -> 160 | EX178: =EW178+R178 -> 2313
A179: 41426 | B179: 28 | C179: 98 | D179: 0 | E179: 30 | F179: 486 | G179: 0 | H179: 19 | I179: 58 | J179: 41 | K179: 4 | L179: 94 | M179: 26 | N179: 0 | O179: 2 | P179: 886 | Q179: 7.8151876 | R179: 2162 | S179: 113.369 | T179: 78.399942 | U179: 36 | V179: 28.18997 | W179: =V179-V178 -> 1.468728 | X179: =T179+U179 -> 114.39994 | Z179: =V179/(X180/30) -> 6.5984823 | AA179: =P179-SUM(B179:O179) -> 0 | AB179: =P179-AA179 -> 886 | AC179: =AB179/AB167-1 -> 0.26031294 | AD179: =Q179/AVERAGE(Q167,Q155,Q143,Q131,Q119)-1 -> 0.069494752 | AF179: =(2204.622/300)/Q179 -> 0.94031524 | AH179: =AK179+F179 -> 642 | AI179: =AH179/30 -> 21.4 | AK179: =SUM(B179:E179,G179) -> 156 | AL179: =AK179/30 -> 5.2 | AN179: =SUM(H179:M179) -> 242 | AO179: =F179/P179 -> 0.54853273 | AP179: =SUM(B179:G179)/P179 -> 0.72460497 | AQ179: =SUM(H179:M179)/P179 -> 0.2731377 | AR179: =S179/(A180-A179)*365 -> 1379.3228 | AS179: =R179-AR179 -> 782.67717 | AT179: =(S179/(A180-A179)*365)/R179 -> 0.63798466 | AU179: =AT179/AVERAGE(AT167,AT155,AT143,AT131,AT119)-1 -> #DIV/0! | AV179: ='[1]Monthly SBO'!$K163 -> 0.759517 | AX179: =S179/30 -> 3.7789667 | AZ179: =AX179-AX167 -> 0.6665 | BA179: =F179/30 -> 16.2 | BD179: =AH179/X179 -> 5.611891 | BE179: =F179/S179 -> 4.2868862 | BF179: =[2]Prices!$L524 -> 47.84 | BG179: =AVERAGE(BF177:BF179) -> 48.81 | BH179: =C179/S179 -> 0.86443384 | BI179: =B179/S179 -> 0.2469811 | BJ179: =SUM(L179:M179)*'[12]Yellow Grease Complex'!$BH$119/S179 -> 0 | BK179: =SUM(L179:M179)*'[12]Yellow Grease Complex'!$BH$120/S179 -> 0 | BL179: =J180/S180 -> 0.33326616 | BM179: =I180/S180 -> 0.38751879 | BN179: =AR179-AR167 -> 243.2725 | BO179: =B179/$P179 -> 0.031602709 | BP179: =C179/$P179 -> 0.11060948 | BQ179: =F179/$P179 -> 0.54853273 | BR179: =H179/$P179 -> 0.021444695 | BS179: =I179/$P179 -> 0.065462754 | BT179: =J179/$P179 -> 0.046275395 | BU179: {=SUM(K179:M179/$P179)} -> 0.13995485 | BV179: =[3]Biodiesel!$E8/1000000 -> 117.47259 | BW179: =S179 -> 113.369 | BX179: =BW179-BV179 -> -4.103586 | EW179: ='[4]Renewable Diesel'!$AX42 -> 160 | EX179: =EW179+R179 -> 2322
A180: 41456 | B180: 55 | C180: 108 | D180: 0 | E180: 93 | F180: 480 | G180: 2 | H180: 17 | I180: 50 | J180: 43 | K180: 2 | L180: 101 | M180: 31 | N180: 0 | O180: 2 | P180: 984 | Q180: 7.6263699 | R180: 2156 | S180: 129.026 | T180: 88.165699 | U180: 40 | V180: 29.825256 | W180: =V180-V179 -> 1.635286 | X180: =T180+U180 -> 128.1657 | Z180: =V180/(X181/31) -> 7.0669246 | AA180: =P180-SUM(B180:O180) -> 0 | AB180: =P180-AA180 -> 984 | AC180: =AB180/AB168-1 -> 0.53271028 | AD180: =Q180/AVERAGE(Q168,Q156,Q144,Q132,Q120)-1 -> 0.051212035 | AF180: =(2204.622/300)/Q180 -> 0.96359606 | AH180: =AK180+F180 -> 738 | AI180: =AH180/31 -> 23.806452 | AK180: =SUM(B180:E180,G180) -> 258 | AL180: =AK180/31 -> 8.3225806 | AN180: =SUM(H180:M180) -> 244 | AO180: =F180/P180 -> 0.48780488 | AP180: =SUM(B180:G180)/P180 -> 0.75 | AQ180: =SUM(H180:M180)/P180 -> 0.24796748 | AR180: =S180/(A181-A180)*365 -> 1519.1771 | AS180: =R180-AR180 -> 636.8229 | AT180: =(S180/(A181-A180)*365)/R180 -> 0.7046276 | AU180: =AT180/AVERAGE(AT168,AT156,AT144,AT132,AT120)-1 -> #DIV/0! | AV180: ='[1]Monthly SBO'!$K164 -> 0.43276091 | AX180: =S180/31 -> 4.162129 | AZ180: =AX180-AX168 -> 1.2809355 | BA180: =F180/31 -> 15.483871 | BD180: =AH180/X180 -> 5.7581709 | BE180: =F180/S180 -> 3.7201804 | BF180: =[2]Prices!$L525 -> 45.19 | BG180: =AVERAGE(BF178:BF180) -> 47.446667 | BH180: =C180/S180 -> 0.8370406 | BI180: =B180/S180 -> 0.42627067 | BJ180: =SUM(L180:M180)*'[12]Yellow Grease Complex'!$BH$119/S180 -> 0 | BK180: =SUM(L180:M180)*'[12]Yellow Grease Complex'!$BH$120/S180 -> 0 | BL180: =J181/S181 -> 0.31631165 | BM180: =I181/S181 -> 0.39346084 | BN180: =AR180-AR168 -> 467.54145 | BO180: =B180/$P180 -> 0.055894309 | BP180: =C180/$P180 -> 0.1097561 | BQ180: =F180/$P180 -> 0.48780488 | BR180: =H180/$P180 -> 0.017276423 | BS180: =I180/$P180 -> 0.050813008 | BT180: =J180/$P180 -> 0.043699187 | BU180: {=SUM(K180:M180/$P180)} -> 0.13617886 | BV180: =[3]Biodiesel!$E9/1000000 -> 128.36795 | BW180: =S180 -> 129.026 | BX180: =BW180-BV180 -> 0.658053 | EW180: ='[4]Renewable Diesel'!$AX43 -> 160 | EX180: =EW180+R180 -> 2316
A181: 41487 | B181: 79 | C181: 106 | D181: 0 | E181: 50 | F181: 513 | G181: 2 | H181: 17 | I181: 51 | J181: 41 | K181: 2 | L181: 97 | M181: 31 | N181: 0 | O181: 2 | P181: 991 | Q181: 7.6454841 | R181: 2153 | S181: 129.619 | T181: 90.832432 | U181: 40 | V181: 27.988645 | W181: =V181-V180 -> -1.836611 | X181: =T181+U181 -> 130.83243 | Z181: =V181/(X182/31) -> 6.7329411 | AA181: =P181-SUM(B181:O181) -> 0 | AB181: =P181-AA181 -> 991 | AC181: =AB181/AB169-1 -> 0.43001443 | AD181: =Q181/AVERAGE(Q169,Q157,Q145,Q133,Q121)-1 -> 0.043564804 | AF181: =(2204.622/300)/Q181 -> 0.96118701 | AH181: =AK181+F181 -> 750 | AI181: =AH181/31 -> 24.193548 | AK181: =SUM(B181:E181,G181) -> 237 | AL181: =AK181/31 -> 7.6451613 | AN181: =SUM(H181:M181) -> 239 | AO181: =F181/P181 -> 0.51765893 | AP181: =SUM(B181:G181)/P181 -> 0.7568113 | AQ181: =SUM(H181:M181)/P181 -> 0.24117053 | AR181: =S181/(A182-A181)*365 -> 1526.1592 | AS181: =R181-AR181 -> 626.84081 | AT181: =(S181/(A182-A181)*365)/R181 -> 0.70885239 | AU181: =AT181/AVERAGE(AT169,AT157,AT145,AT133,AT121)-1 -> #DIV/0! | AV181: ='[1]Monthly SBO'!$K165 -> 0.18257909 | AX181: =S181/31 -> 4.1812581 | AZ181: =AX181-AX169 -> 1.2327097 | BA181: =F181/31 -> 16.548387 | BD181: =AH181/X181 -> 5.7325236 | BE181: =F181/S181 -> 3.9577531 | BF181: =[2]Prices!$L526 -> 42.33 | BG181: =AVERAGE(BF179:BF181) -> 45.12 | BH181: =C181/S181 -> 0.81778134 | BI181: =B181/S181 -> 0.60947855 | BJ181: =SUM(L181:M181)*'[12]Yellow Grease Complex'!$BH$119/S181 -> 0 | BK181: =SUM(L181:M181)*'[12]Yellow Grease Complex'!$BH$120/S181 -> 0 | BL181: =J182/S182 -> 0.29905954 | BM181: =I182/S182 -> 0.39349939 | BN181: =AR181-AR169 -> 449.93903 | BO181: =B181/$P181 -> 0.079717457 | BP181: =C181/$P181 -> 0.10696266 | BQ181: =F181/$P181 -> 0.51765893 | BR181: =H181/$P181 -> 0.01715439 | BS181: =I181/$P181 -> 0.051463169 | BT181: =J181/$P181 -> 0.041372351 | BU181: {=SUM(K181:M181/$P181)} -> 0.13118063 | BV181: =[3]Biodiesel!$E10/1000000 -> 129.93833 | BW181: =S181 -> 129.619 | BX181: =BW181-BV181 -> -0.319329 | EW181: ='[4]Renewable Diesel'!$AX44 -> 160 | EX181: =EW181+R181 -> 2313
A182: 41518 | B182: 44 | C182: 95 | D182: 0 | E182: 93 | F182: 502 | G182: 2 | H182: 14 | I182: 50 | J182: 38 | K182: 2 | L182: 108 | M182: 22 | N182: 0 | O182: 2 | P182: 972.10748 | Q182: 7.650474 | R182: 2153 | S182: 127.065 | T182: 91.86612 | U182: 37 | V182: 26.675295 | W182: =V182-V181 -> -1.31335 | X182: =T182+U182 -> 128.86612 | Z182: =V182/(X183/30) -> 5.6583566 | AA182: =P182-SUM(B182:O182) -> 0.107482 | AB182: =P182-AA182 -> 972 | AC182: =AB182/AB170-1 -> 0.57281553 | AD182: =Q182/AVERAGE(Q170,Q158,Q146,Q134,Q122)-1 -> 0.037583906 | AF182: =(2204.622/300)/Q182 -> 0.96056009 | AH182: =AK182+F182 -> 736 | AI182: =AH182/30 -> 24.533333 | AK182: =SUM(B182:E182,G182) -> 234 | AL182: =AK182/30 -> 7.8 | AN182: =SUM(H182:M182) -> 234 | AO182: =F182/P182 -> 0.5164038 | AP182: =SUM(B182:G182)/P182 -> 0.75711793 | AQ182: =SUM(H182:M182)/P182 -> 0.24071412 | AR182: =S182/(A183-A182)*365 -> 1545.9575 | AS182: =R182-AR182 -> 607.0425 | AT182: =(S182/(A183-A182)*365)/R182 -> 0.71804807 | AU182: =AT182/AVERAGE(AT170,AT158,AT146,AT134,AT122)-1 -> #DIV/0! | AV182: ='[1]Monthly SBO'!$K166 -> 0.172562 | AX182: =S182/30 -> 4.2355 | AZ182: =AX182-AX170 -> 1.5070667 | BA182: =F182/30 -> 16.733333 | BD182: =AH182/X182 -> 5.7113538 | BE182: =F182/S182 -> 3.9507339 | BF182: =[2]Prices!$L527 -> 42.12 | BG182: =AVERAGE(BF180:BF182) -> 43.213333 | BH182: =C182/S182 -> 0.74764884 | BI182: =B182/S182 -> 0.34627946 | BJ182: =SUM(L182:M182)*'[12]Yellow Grease Complex'!$BH$119/S182 -> 0 | BK182: =SUM(L182:M182)*'[12]Yellow Grease Complex'!$BH$120/S182 -> 0 | BL182: =J183/S183 -> 0.26194391 | BM182: =I183/S183 -> 0.16735306 | BN182: =AR182-AR170 -> 550.07933 | BO182: =B182/$P182 -> 0.045262485 | BP182: =C182/$P182 -> 0.097725819 | BQ182: =F182/$P182 -> 0.5164038 | BR182: =H182/$P182 -> 0.0144017 | BS182: =I182/$P182 -> 0.051434642 | BT182: =J182/$P182 -> 0.039090328 | BU182: {=SUM(K182:M182/$P182)} -> 0.13578745 | BV182: =[3]Biodiesel!$E11/1000000 -> 127.64734 | BW182: =S182 -> 127.065 | BX182: =BW182-BV182 -> -0.582342 | EW182: ='[4]Renewable Diesel'!$AX45 -> 160 | EX182: =EW182+R182 -> 2313
A183: 41548 | B183: 82 | C183: 103 | D183: 0 | E183: 100 | F183: 551 | G183: 0 | H183: 13 | I183: 23 | J183: 36 | K183: 1 | L183: 107 | M183: 28 | N183: 0 | O183: 2 | P183: 1046 | Q183: 7.610926 | R183: 2137 | S183: 137.434 | T183: 99.429553 | U183: 42 | V183: 22.749717 | W183: =V183-V182 -> -3.925578 | X183: =T183+U183 -> 141.42955 | Z183: =V183/(X184/31) -> 5.8661612 | AA183: =P183-SUM(B183:O183) -> 0 | AB183: =P183-AA183 -> 1046 | AC183: =AB183/AB171-1 -> 0.82229965 | AD183: =Q183/AVERAGE(Q171,Q159,Q147,Q135,Q123)-1 -> 0.013017807 | AF183: =(2204.622/300)/Q183 -> 0.96555137 | AH183: =AK183+F183 -> 836 | AI183: =AH183/31 -> 26.967742 | AK183: =SUM(B183:E183,G183) -> 285 | AL183: =AK183/31 -> 9.1935484 | AN183: =SUM(H183:M183) -> 208 | AO183: =F183/P183 -> 0.52676864 | AP183: =SUM(B183:G183)/P183 -> 0.79923518 | AQ183: =SUM(H183:M183)/P183 -> 0.19885277 | AR183: =S183/(A184-A183)*365 -> 1618.1745 | AS183: =R183-AR183 -> 518.82548 | AT183: =(S183/(A184-A183)*365)/R183 -> 0.75721784 | AU183: =AT183/AVERAGE(AT171,AT159,AT147,AT135,AT123)-1 -> #DIV/0! | AV183: ='[1]Monthly SBO'!$K167 -> 0.10357391 | AX183: =S183/31 -> 4.4333548 | AZ183: =AX183-AX171 -> 2.004871 | BA183: =F183/31 -> 17.774194 | BD183: =AH183/X183 -> 5.9110701 | BE183: =F183/S183 -> 4.0091971 | BF183: =[2]Prices!$L528 -> 39.66 | BG183: =AVERAGE(BF181:BF183) -> 41.37 | BH183: =C183/S183 -> 0.74945065 | BI183: =B183/S183 -> 0.59665003 | BJ183: =SUM(L183:M183)*'[12]Yellow Grease Complex'!$BH$119/S183 -> 0 | BK183: =SUM(L183:M183)*'[12]Yellow Grease Complex'!$BH$120/S183 -> 0 | BL183: =J184/S184 -> 0.26287102 | BM183: =I184/S184 -> 0.092778005 | BN183: =AR183-AR171 -> 731.7779 | BO183: =B183/$P183 -> 0.078393881 | BP183: =C183/$P183 -> 0.098470363 | BQ183: =F183/$P183 -> 0.52676864 | BR183: =H183/$P183 -> 0.012428298 | BS183: =I183/$P183 -> 0.021988528 | BT183: =J183/$P183 -> 0.034416826 | BU183: {=SUM(K183:M183/$P183)} -> 0.13001912 | BV183: =[3]Biodiesel!$E12/1000000 -> 130.30029 | BW183: =S183 -> 137.434 | BX183: =BW183-BV183 -> 7.133708 | EW183: ='[4]Renewable Diesel'!$AX46 -> 160 | EX183: =EW183+R183 -> 2297
A184: 41579 | B184: 80 | C184: 98 | D184: 0 | E184: 93 | F184: 535 | G184: 0 | H184: 11 | I184: 12 | J184: 34 | K184: 0 | L184: 91 | M184: 32 | N184: 0 | O184: 2 | P184: 988 | Q184: 7.6387224 | R184: 2136 | S184: 129.341 | T184: 87.221932 | U184: 33 | V184: 33.702917 | W184: =V184-V183 -> 10.9532 | X184: =T184+U184 -> 120.22193 | Z184: =V184/(X185/30) -> 6.8372787 | AA184: =P184-SUM(B184:O184) -> 0 | AB184: =P184-AA184 -> 988 | AC184: =AB184/AB172-1 -> 1.266055 | AD184: =Q184/AVERAGE(Q172,Q160,Q148,Q136,Q124)-1 -> 0.025389097 | AF184: =(2204.622/300)/Q184 -> 0.96203783 | AH184: =AK184+F184 -> 806 | AI184: =AH184/30 -> 26.866667 | AK184: =SUM(B184:E184,G184) -> 271 | AL184: =AK184/30 -> 9.0333333 | AN184: =SUM(H184:M184) -> 180 | AO184: =F184/P184 -> 0.54149798 | AP184: =SUM(B184:G184)/P184 -> 0.81578947 | AQ184: =SUM(H184:M184)/P184 -> 0.18218623 | AR184: =S184/(A185-A184)*365 -> 1573.6488 | AS184: =R184-AR184 -> 562.35117 | AT184: =(S184/(A185-A184)*365)/R184 -> 0.73672698 | AU184: =AT184/AVERAGE(AT172,AT160,AT148,AT136,AT124)-1 -> #DIV/0! | AV184: ='[1]Monthly SBO'!$K168 -> 0.158019 | AX184: =S184/30 -> 4.3113667 | AZ184: =AX184-AX172 -> 2.4037333 | BA184: =F184/30 -> 17.833333 | BD184: =AH184/X184 -> 6.7042676 | BE184: =F184/S184 -> 4.1363527 | BF184: =[2]Prices!$L529 -> 39.58 | BG184: =AVERAGE(BF182:BF184) -> 40.453333 | BH184: =C184/S184 -> 0.75768704 | BI184: =B184/S184 -> 0.61852004 | BJ184: =SUM(L184:M184)*'[12]Yellow Grease Complex'!$BH$119/S184 -> 0 | BK184: =SUM(L184:M184)*'[12]Yellow Grease Complex'!$BH$120/S184 -> 0 | BL184: =J185/S185 -> 0.3330866 | BM184: =I185/S185 -> 0.059215396 | BN184: =AR184-AR172 -> 877.36267 | BO184: =B184/$P184 -> 0.08097166 | BP184: =C184/$P184 -> 0.099190283 | BQ184: =F184/$P184 -> 0.54149798 | BR184: =H184/$P184 -> 0.011133603 | BS184: =I184/$P184 -> 0.012145749 | BT184: =J184/$P184 -> 0.034412955 | BU184: {=SUM(K184:M184/$P184)} -> 0.12449393 | BV184: =[3]Biodiesel!$E13/1000000 -> 110.33179 | BW184: =S184 -> 129.341 | BX184: =BW184-BV184 -> 19.009212 | EW184: ='[4]Renewable Diesel'!$AX47 -> 160 | EX184: =EW184+R184 -> 2296
A185: 41609 | B185: 105 | C185: 104 | D185: 0 | E185: 63.34642 | F185: 559 | G185: 0 | H185: 11 | I185: 8 | J185: 45 | K185: 1 | L185: 84 | M185: 39 | N185: 0 | O185: 3 | P185: 1022.3464 | Q185: 7.567331 | R185: 2116 | S185: 135.1 | T185: 78.878645 | U185: 69 | V185: 19.967759 | W185: =V185-V184 -> -13.735158 | X185: =T185+U185 -> 147.87865 | Z185: =V185/(X186/31) -> 9.3787959 | AA185: =P185-SUM(B185:O185) -> 0 | AB185: =P185-AA185 -> 1022.3464 | AC185: =AB185/AB173-1 -> 1.2518644 | AD185: =Q185/AVERAGE(Q173,Q161,Q149,Q137,Q125)-1 -> 0.01018921 | AF185: =(2204.622/300)/Q185 -> 0.97111386 | AH185: =AK185+F185 -> 831.34642 | AI185: =AH185/31 -> 26.817626 | AK185: =SUM(B185:E185,G185) -> 272.34642 | AL185: =AK185/31 -> 8.7853684 | AN185: =SUM(H185:M185) -> 188 | AO185: =F185/P185 -> 0.54678139 | AP185: =SUM(B185:G185)/P185 -> 0.81317487 | AQ185: =SUM(H185:M185)/P185 -> 0.1838907 | AR185: =S185/(A186-A185)*365 -> 1590.6935 | AS185: =R185-AR185 -> 525.30645 | AT185: =(S185/(A186-A185)*365)/R185 -> 0.75174553 | AU185: =AT185/AVERAGE(AT173,AT161,AT149,AT137,AT125)-1 -> #DIV/0! | AV185: ='[1]Monthly SBO'!$K169 -> -0.033975238 | AX185: =S185/31 -> 4.3580645 | AZ185: =AX185-AX173 -> 2.4538065 | BA185: =F185/31 -> 18.032258 | BD185: =AH185/X185 -> 5.6218152 | BE185: =F185/S185 -> 4.1376758 | BF185: =[2]Prices!$L530 -> 37.63 | BG185: =AVERAGE(BF183:BF185) -> 38.956667 | BH185: =C185/S185 -> 0.76980015 | BI185: =B185/S185 -> 0.77720207 | BJ185: =SUM(L185:M185)*'[12]Yellow Grease Complex'!$BH$119/S185 -> 0 | BK185: =SUM(L185:M185)*'[12]Yellow Grease Complex'!$BH$120/S185 -> 0 | BL185: =J186/S186 -> 0.34246575 | BM185: =I186/S186 -> 0.068493151 | BN185: =AR185-AR173 -> 895.63935 | BO185: =B185/$P185 -> 0.10270491 | BP185: =C185/$P185 -> 0.10172677 | BQ185: =F185/$P185 -> 0.54678139 | BR185: =H185/$P185 -> 0.010759562 | BS185: =I185/$P185 -> 0.0078251362 | BT185: =J185/$P185 -> 0.044016391 | BU185: {=SUM(K185:M185/$P185)} -> 0.12128961 | BV185: =[3]Biodiesel!$E14/1000000 -> 158.43172 | BW185: =S185 -> 135.1 | BX185: =BW185-BV185 -> -23.331724 | EW185: ='[4]Renewable Diesel'!$AX48 -> 160 | EX185: =EW185+R185 -> 2276
...

Sheet SBO Fuel Value
B1: B100 Upper Midwest | C1: SBO Energy Value | D1: SBO Central Illinois | E1: Energy Profit/Loss
A2: 38384 | B2: 247.75 | C2: =B2/7.6 -> 32.598684 | D2: =[2]Prices!$L424 -> 20.7 | E2: =C2-D2 -> 11.898684
A3: 38412 | B3: 266.2 | C3: =B3/7.6 -> 35.026316 | D3: =[2]Prices!$L425 -> 23.6 | E3: =C3-D3 -> 11.426316
A4: 38443 | B4: 274.5 | C4: =B4/7.6 -> 36.118421 | D4: =[2]Prices!$L426 -> 23.09 | E4: =C4-D4 -> 13.028421
A5: 38473 | B5: 271.5 | C5: =B5/7.6 -> 35.723684 | D5: =[2]Prices!$L427 -> 23.38 | E5: =C5-D5 -> 12.343684
A6: 38504 | B6: 285.8 | C6: =B6/7.6 -> 37.605263 | D6: =[2]Prices!$L428 -> 24.71 | E6: =C6-D6 -> 12.895263
A7: 38534 | B7: 293.25 | C7: =B7/7.6 -> 38.585526 | D7: =[2]Prices!$L429 -> 25.46 | E7: =C7-D7 -> 13.125526
A8: 38565 | B8: 306 | C8: =B8/7.6 -> 40.263158 | D8: =[2]Prices!$L430 -> 23.6 | E8: =C8-D8 -> 16.663158
A9: 38596 | B9: 303 | C9: =B9/7.6 -> 39.868421 | D9: =[2]Prices!$L431 -> 23.19 | E9: =C9-D9 -> 16.678421
A10: 38626 | B10: 300.25 | C10: =B10/7.6 -> 39.506579 | D10: =[2]Prices!$L432 -> 24.21 | E10: =C10-D10 -> 15.296579
A11: 38657 | B11: 291.5 | C11: =B11/7.6 -> 38.355263 | D11: =[2]Prices!$L433 -> 22.52 | E11: =C11-D11 -> 15.835263
A12: 38687 | B12: 263.125 | C12: =B12/7.6 -> 34.621711 | D12: =[2]Prices!$L434 -> 21 | E12: =C12-D12 -> 13.621711
A13: 38718 | B13: 257.5 | C13: =B13/7.6 -> 33.881579 | D13: =[2]Prices!$L435 -> 21.63 | E13: =C13-D13 -> 12.251579
... A48: 39783 | B48: 314 | C48: =B48/7.6 -> 41.315789 | D48: =[2]Prices!$L470 -> 29.3 | E48: =C48-D48 -> 12.015789
A49: 39814 | B49: 322.5 | C49: =B49/'US EIA'!Q126 -> 46.02166 | D49: =[2]Prices!$L471 -> 32.16 | E49: =C49-D49 -> 13.86166
A50: 39845 | B50: 297.5 | C50: =B50/'US EIA'!Q127 -> 42.870483 | D50: =[2]Prices!$L472 -> 28.93 | E50: =C50-D50 -> 13.940483
A51: 39873 | B51: 277.5 | C51: =B51/'US EIA'!Q128 -> 43.410949 | D51: =[2]Prices!$L473 -> 28.23 | E51: =C51-D51 -> 15.180949
A52: 39904 | B52: 287 | C52: =B52/'US EIA'!Q129 -> 43.005312 | D52: =[2]Prices!$L474 -> 32.76 | E52: =C52-D52 -> 10.245312
A53: 39934 | B53: 297.5 | C53: =B53/'US EIA'!Q130 -> 46.135242 | D53: =[2]Prices!$L475 -> 36.06 | E53: =C53-D53 -> 10.075242
A54: 39965 | B54: 310 | C54: =B54/'US EIA'!Q131 -> 44.119398 | D54: =[2]Prices!$L476 -> 35.66 | E54: =C54-D54 -> 8.4593983
A55: 39995 | B55: 294 | C55: =B55/'US EIA'!Q132 -> 42.818834 | D55: =[2]Prices!$L477 -> 31.08 | E55: =C55-D55 -> 11.738834
A56: 40026 | B56: 314.375 | C56: =B56/'US EIA'!Q133 -> 45.484189 | D56: =[2]Prices!$L478 -> 33.69 | E56: =C56-D56 -> 11.794189
A57: 40057 | B57: 309 | C57: =B57/'US EIA'!Q134 -> 43.887584 | D57: =[2]Prices!$L479 -> 30.96 | E57: =C57-D57 -> 12.927584
A58: 40087 | B58: 315 | C58: =B58/'US EIA'!Q135 -> 43.289219 | D58: =[2]Prices!$L480 -> 33.15 | E58: =C58-D58 -> 10.139219
A59: 40118 | B59: 332.5 | C59: =B59/'US EIA'!Q136 -> 46.232044 | D59: =[2]Prices!$L481 -> 36.59 | E59: =C59-D59 -> 9.6420436
A60: 40148 | B60: 328 | C60: =B60/'US EIA'!Q137 -> 46.117187 | D60: =[2]Prices!$L482 -> 36.81 | E60: =C60-D60 -> 9.3071865
... A180: 43800 | B180: 292.0952 | C180: =B180/'US EIA'!Q257 -> 37.975231 | D180: =[2]Prices!$L602 -> 32.27 | E180: =C180-D180 -> 5.7052313
A181: 43831 | B181: 309.8409 | C181: =B181/'US EIA'!Q258 -> 39.845183 | D181: =[2]Prices!$L603 -> 33.04 | E181: =C181-D181 -> 6.8051829 | K181: Biodiesel less RIN value
A182: 43862 | B182: 301.2895 | C182: =B182/'US EIA'!Q259 -> 39.493758 | D182: =[2]Prices!$L604 -> 30.26 | E182: =C182-D182 -> 9.2337577 | K182: =B182-50 -> 251.2895 | L182: =K182/7.6 -> 33.064408
A183: 43891 | B183: 289.8409 | C183: =B183/'US EIA'!Q260 -> 38.090493 | D183: =[2]Prices!$L605 -> 27.04 | E183: =C183-D183 -> 11.050493 | K183: Heating Oil
A184: 43922 | B184: 277 | C184: =B184/'US EIA'!Q261 -> 37.278505 | D184: =[2]Prices!$L606 -> 25.69 | E184: =C184-D184 -> 11.588505 | K184: =L212 -> --- | L184: =K184/7.6*100 -> #VALUE!
A185: 43952 | B185: 268.175 | C185: =B185/'US EIA'!Q262 -> 35.507491 | D185: =[2]Prices!$L607 -> 25.27 | E185: =C185-D185 -> 10.237491 | K185: Biodiesel with RINs
A186: 43983 | B186: 280.4773 | C186: =B186/'US EIA'!Q263 -> 37.281754 | D186: =[2]Prices!$L608 -> 26.61 | E186: =C186-D186 -> 10.671754 | K186: =B182 -> 301.2895 | L186: =K186/7.6 -> 39.643355
A187: 44013 | B187: =([6]Forecasts!$B8-[6]Forecasts!$I$4)*100 -> 341.68 | C187: =B187/'US EIA'!Q264 -> 44.710953 | D187: =[2]Prices!$L609 -> 28.71 | E187: =C187-D187 -> 16.000953
A188: 44044 | B188: =([6]Forecasts!$B9-[6]Forecasts!$I$4)*100 -> 347.5238 | C188: =B188/'US EIA'!Q265 -> 45.719435 | D188: =[2]Prices!$L610 -> 32.13 | E188: =C188-D188 -> 13.589435 | K188: {=[7]!'QHOh0[INTERVAL:DAILY,COMPRESSION:1,SORT:ASC,SPAN:25]?DATE,CLOSE'} -> --- | L188: ---
A189: 44075 | B189: =([6]Forecasts!$B10-[6]Forecasts!$I$4)*100 -> 374.1429 | C189: =B189/'US EIA'!Q266 -> 49.532657 | D189: =[2]Prices!$L611 -> 34.2 | E189: =C189-D189 -> 15.332657 | K189: --- | L189: ---
A190: 44105 | B190: =([6]Forecasts!$B11-[6]Forecasts!$I$4)*100 -> 379.8864 | C190: =B190/'US EIA'!Q267 -> 51.950277 | D190: =[2]Prices!$L612 -> 33.91 | E190: =C190-D190 -> 18.040277 | K190: --- | L190: ---
A191: 44136 | B191: =([6]Forecasts!$B12-[6]Forecasts!$I$4)*100 -> 392.8947 | C191: =B191/'US EIA'!Q268 -> 52.501858 | D191: =[2]Prices!$L613 -> 37.79 | E191: =C191-D191 -> 14.711858 | K191: --- | L191: ---
A192: 44166 | B192: =([6]Forecasts!$B13-[6]Forecasts!$I$4) -> 438.8273 | C192: =B192/'US EIA'!Q269 -> 59.170059 | D192: =[2]Prices!$L614 -> 40.85 | E192: =C192-D192 -> 18.320059 | K192: --- | L192: ---
A193: 44197 | B193: =([6]Forecasts!$B14-[6]Forecasts!$I$4) -> 463.3237 | C193: =B193/'US EIA'!Q270 -> 59.76011 | D193: =[2]Prices!$L615 -> 44.31 | E193: =C193-D193 -> 15.45011 | K193: --- | L193: ---
A194: 44228 | B194: =([6]Forecasts!$B15-[6]Forecasts!$I$4) -> 497.4289 | C194: =B194/'US EIA'!Q271 -> 65.28076 | D194: =[2]Prices!$L616 -> 48.37 | E194: =C194-D194 -> 16.91076 | K194: --- | L194: ---
A195: 44256 | B195: =([6]Forecasts!$B16-[6]Forecasts!$I$4) -> 541.3717 | C195: =B195/'US EIA'!Q272 -> 72.781141 | D195: =[2]Prices!$L617 -> 56 | E195: =C195-D195 -> 16.781141 | K195: --- | L195: ---
A196: 44287 | B196: =([6]Forecasts!$B17-[6]Forecasts!$I$4) -> 574.1357 | C196: =B196/'US EIA'!Q273 -> 75.286082 | D196: =[2]Prices!$L618 -> 62.88 | E196: =C196-D196 -> 12.406082 | K196: --- | L196: ---
A197: 44317 | B197: =([6]Forecasts!$B18-[6]Forecasts!$I$4) -> 605.85 | C197: =B197/'US EIA'!Q274 -> 78.121902 | D197: =[2]Prices!$L619 -> 74.75 | E197: =C197-D197 -> 3.3719021 | K197: --- | L197: ---
A198: 44348 | B198: =([6]Forecasts!$B19-[6]Forecasts!$I$4) -> 642.1227 | C198: =B198/'US EIA'!Q275 -> 83.183398 | D198: =[2]Prices!$L620 -> 74.75 | E198: =C198-D198 -> 8.4333981 | K198: --- | L198: ---
A199: 44378 | B199: =([6]Forecasts!$B20-[6]Forecasts!$I$4) -> 636.0405 | C199: =B199/'US EIA'!Q276 -> 84.505654 | D199: =[2]Prices!$L621 -> 72.93 | E199: =C199-D199 -> 11.575654 | K199: --- | L199: ---
A200: 44409 | B200: =([6]Forecasts!$B21-[6]Forecasts!$I$4) -> 634.85 | C200: =B200/'US EIA'!Q277 -> 97.382929 | D200: =[2]Prices!$L622 -> 70.01 | E200: =C200-D200 -> 27.372929 | K200: --- | L200: ---
A201: 44440 | B201: =([6]Forecasts!$B22-[6]Forecasts!$I$4) -> 598.8976 | C201: =B201/'US EIA'!Q278 -> 86.359719 | D201: =[2]Prices!$L623 -> 65.93 | E201: =C201-D201 -> 20.429719 | K201: --- | L201: ---
A202: 44470 | B202: =([6]Forecasts!$B23-[6]Forecasts!$I$4) -> 608.6595 | C202: =B202/'US EIA'!Q279 -> 79.22912 | D202: =[2]Prices!$L624 -> 70.42 | E202: =C202-D202 -> 8.8091199 | K202: --- | L202: ---
A203: 44501 | B203: =([6]Forecasts!$B24-[6]Forecasts!$I$4) -> 636.85 | C203: =B203/'US EIA'!Q280 -> 89.248598 | D203: =[2]Prices!$L625 -> 66.46 | E203: =C203-D203 -> 22.788598 | K203: --- | L203: ---
... A212: 44774 | B212: =([6]Forecasts!$B33-[6]Forecasts!$I$4) -> 749.8065 | C212: =B212/'US EIA'!Q289 -> 92.343522 | D212: =[2]Prices!$L634 -> 72.335 | E212: =C212-D212 -> 20.008522 | K212: --- | L212: ---
A213: 44805 | B213: =([6]Forecasts!$B34-[6]Forecasts!$I$4) -> 769.85 | C213: =B213/'US EIA'!Q290 -> 96.11672 | D213: =[2]Prices!$L635 -> 70.626 | E213: =C213-D213 -> 25.49072
A214: 44835 | B214: =([6]Forecasts!$B35-[6]Forecasts!$I$4) -> 796.39762 | C214: =B214/'US EIA'!Q291 -> 98.069739 | D214: =[2]Prices!$L636 -> 72.67 | E214: =C214-D214 -> 25.399739
A215: 44866 | B215: =([6]Forecasts!$B36-[6]Forecasts!$I$4) -> 804.45 | C215: =B215/'US EIA'!Q292 -> 101.80023 | D215: =[2]Prices!$L637 -> 79.18 | E215: =C215-D215 -> 22.62023
A216: 44896 | B216: =([6]Forecasts!$B37-[6]Forecasts!$I$4) -> 769.85 | C216: =B216/'US EIA'!Q293 -> 93.021816 | D216: =[2]Prices!$L638 -> 68.14 | E216: =C216-D216 -> 24.881816
A217: 44927 | B217: =([6]Forecasts!$B38-[6]Forecasts!$I$4) -> 745.1 | C217: =B217/'US EIA'!Q294 -> 97.811865 | D217: =[2]Prices!$L639 -> 66 | E217: =C217-D217 -> 31.811865
A218: 44958 | B218: =([6]Forecasts!$B39-[6]Forecasts!$I$4) -> 707.4816 | C218: =B218/'US EIA'!Q295 -> 87.453591 | D218: =[2]Prices!$L640 -> 63.2425 | E218: =C218-D218 -> 24.211091
A219: 44986 | B219: =([6]Forecasts!$B40-[6]Forecasts!$I$4) -> 636.3717 | C219: =B219/'US EIA'!Q296 -> 77.616897 | D219: =[2]Prices!$L641 -> 58.83 | E219: =C219-D219 -> 18.786897
A220: 45017 | B220: =([6]Forecasts!$B41-[6]Forecasts!$I$4) -> 604.85 | C220: =B220/'US EIA'!Q297 -> 75.05953 | D220: =[2]Prices!$L642 -> 55.475 | E220: =C220-D220 -> 19.58453
A221: 45047 | B221: =([6]Forecasts!$B42-[6]Forecasts!$I$4) -> 594.35 | C221: =B221/'US EIA'!Q298 -> 73.570381 | D221: =[2]Prices!$L643 -> 52.485 | E221: =C221-D221 -> 21.085381
A222: 45078 | B222: =([6]Forecasts!$B43-[6]Forecasts!$I$4) -> 580.0881 | C222: =B222/'US EIA'!Q299 -> 73.875155 | D222: =[2]Prices!$L644 -> 60.008 | E222: =C222-D222 -> 13.867155
A223: 45108 | B223: =([6]Forecasts!$B44-[6]Forecasts!$I$4) -> 594.85 | C223: =B223/'US EIA'!Q300 -> 76.778138 | D223: =[2]Prices!$L645 -> 70.8875 | E223: =C223-D223 -> 5.8906376
A224: 45139 | B224: =([6]Forecasts!$B45-[6]Forecasts!$I$4) -> 657.8935 | C224: =B224/'US EIA'!Q301 -> 83.302395 | D224: =[2]Prices!$L646 -> 70.967 | E224: =C224-D224 -> 12.335395
... A261: 46266 | B261: =([6]Forecasts!$B82-[6]Forecasts!$I$4) -> 472.35 | C261: =B261/'US EIA'!Q338 -> 60.789925 | D261: =[2]Prices!$L683 -> 50.981244 | E261: =C261-D261 -> 9.8086811
A262: 46296 | B262: =([6]Forecasts!$B83-[6]Forecasts!$I$4) -> 474.85 | C262: =B262/'US EIA'!Q339 -> 61.966081 | D262: ='[5]Soy Complex'!$BP513 -> 54.634144 | E262: =C262-D262 -> 7.3319368
A263: 46327 | B263: =([6]Forecasts!$B84-[6]Forecasts!$I$4) -> 477.35 | C263: =B263/'US EIA'!Q340 -> 62.285731 | D263: ='[5]Soy Complex'!$BP514 -> 53.962779 | E263: =C263-D263 -> 8.3229519
A264: 46357 | B264: =([6]Forecasts!$B85-[6]Forecasts!$I$4) -> 479.85 | C264: =B264/'US EIA'!Q341 -> 64.983426 | D264: ='[5]Soy Complex'!$BP515 -> 55.919264 | E264: =C264-D264 -> 9.0641618
A265: 46388 | B265: =([6]Forecasts!$B86-[6]Forecasts!$I$4) -> 484.85 | C265: =B265/'US EIA'!Q342 -> 57.446729 | D265: ='[5]Soy Complex'!$BP516 -> 57.50602 | E265: =C265-D265 -> -0.059290948
A266: 46419 | B266: =([6]Forecasts!$B87-[6]Forecasts!$I$4) -> 487.35 | C266: =B266/'US EIA'!Q343 -> 57.879614 | D266: ='[5]Soy Complex'!$BP517 -> 59.403723 | E266: =C266-D266 -> -1.5241091
A267: 46447 | B267: =([6]Forecasts!$B88-[6]Forecasts!$I$4) -> 489.85 | C267: =B267/'US EIA'!Q344 -> 60.024444 | D267: ='[5]Soy Complex'!$BP518 -> 66.140754 | E267: =C267-D267 -> -6.1163093
A268: 46478 | B268: =([6]Forecasts!$B89-[6]Forecasts!$I$4) -> 492.35 | C268: =B268/'US EIA'!Q345 -> 60.815325 | D268: ='[5]Soy Complex'!$BP519 -> 69.784913 | E268: =C268-D268 -> -8.9695876
A269: 46508 | B269: =([6]Forecasts!$B90-[6]Forecasts!$I$4) -> 494.85 | C269: =B269/'US EIA'!Q346 -> 61.62379 | D269: ='[5]Soy Complex'!$BP520 -> 70.049877 | E269: =C269-D269 -> -8.4260869
A270: 46539 | B270: =([6]Forecasts!$B91-[6]Forecasts!$I$4) -> 497.35 | C270: =B270/'US EIA'!Q347 -> 62.476483 | D270: ='[5]Soy Complex'!$BP521 -> 70.371913 | E270: =C270-D270 -> -7.8954296
A271: 46569 | B271: =([6]Forecasts!$B92-[6]Forecasts!$I$4) -> 499.85 | C271: =B271/'US EIA'!Q348 -> 63.835259 | D271: ='[5]Soy Complex'!$BP522 -> 70.257028 | E271: =C271-D271 -> -6.4217687
A272: 46600 | B272: =([6]Forecasts!$B93-[6]Forecasts!$I$4) -> 502.35 | C272: =B272/'US EIA'!Q349 -> 63.106313 | D272: ='[5]Soy Complex'!$BP523 -> 65.829108 | E272: =C272-D272 -> -2.7227946
A273: 46631 | B273: =([6]Forecasts!$B94-[6]Forecasts!$I$4) -> 497.85 | C273: =B273/'US EIA'!Q350 -> 62.716975 | D273: ='[5]Soy Complex'!$BP524 -> 63.128725 | E273: =C273-D273 -> -0.41174973
A274: 46661 | B274: =([6]Forecasts!$B95-[6]Forecasts!$I$4) -> 499.85 | C274: =B274/'US EIA'!Q351 -> 65.295555 | D274: ='[5]Soy Complex'!$BQ513 -> 61.188329 | E274: =C274-D274 -> 4.1072257
A275: 46692 | B275: =([6]Forecasts!$B96-[6]Forecasts!$I$4) -> 502.35 | C275: =B275/'US EIA'!Q352 -> 64.667123 | D275: ='[5]Soy Complex'!$BQ514 -> 56.217345 | E275: =C275-D275 -> 8.4497779
A276: 46722 | B276: =([6]Forecasts!$B97-[6]Forecasts!$I$4) -> 504.85 | C276: =B276/'US EIA'!Q353 -> 68.894475 | D276: ='[5]Soy Complex'!$BQ515 -> 63.266559 | E276: =C276-D276 -> 5.6279162
A277: 46753 | B277: =([6]Forecasts!$B98-[6]Forecasts!$I$4) -> 467.35 | C277: =B277/'US EIA'!Q354 -> 54.983802 | D277: ='[5]Soy Complex'!$BQ516 -> 64.842258 | E277: =C277-D277 -> -9.8584566
A278: 46784 | B278: =([6]Forecasts!$B99-[6]Forecasts!$I$4) -> 469.85 | C278: =B278/'US EIA'!Q355 -> 56.31265 | D278: ='[5]Soy Complex'!$BQ517 -> 59.592069 | E278: =C278-D278 -> -3.2794187
A279: 46813 | B279: =([6]Forecasts!$B100-[6]Forecasts!$I$4) -> 472.35 | C279: =B279/'US EIA'!Q356 -> 58.743908 | D279: ='[5]Soy Complex'!$BQ518 -> 61.179177 | E279: =C279-D279 -> -2.4352692
A280: 46844 | B280: =([6]Forecasts!$B101-[6]Forecasts!$I$4) -> 474.85 | C280: =B280/'US EIA'!Q357 -> 59.104139 | D280: ='[5]Soy Complex'!$BQ519 -> 58.21205 | E280: =C280-D280 -> 0.8920894
A281: 46874 | B281: =([6]Forecasts!$B102-[6]Forecasts!$I$4) -> 497.35 | C281: =B281/'US EIA'!Q358 -> 62.090522 | D281: ='[5]Soy Complex'!$BQ520 -> 60.979427 | E281: =C281-D281 -> 1.1110945
A282: 46905 | B282: =([6]Forecasts!$B103-[6]Forecasts!$I$4) -> 512.35 | C282: =B282/'US EIA'!Q359 -> 64.463431 | D282: ='[5]Soy Complex'!$BQ521 -> 62.78074 | E282: =C282-D282 -> 1.6826909
A283: 46935 | B283: =([6]Forecasts!$B104-[6]Forecasts!$I$4) -> 517.35 | C283: =B283/'US EIA'!Q360 -> 66.648157 | D283: ='[5]Soy Complex'!$BQ522 -> 64.17437 | E283: =C283-D283 -> 2.4737879
A284: 46966 | B284: =([6]Forecasts!$B105-[6]Forecasts!$I$4) -> 522.35 | C284: =B284/'US EIA'!Q361 -> 65.894391 | D284: ='[5]Soy Complex'!$BQ523 -> 60.732584 | E284: =C284-D284 -> 5.1618073
A285: 46997 | B285: =([6]Forecasts!$B106-[6]Forecasts!$I$4) -> 549.85 | C285: =B285/'US EIA'!Q362 -> 69.403481 | D285: ='[5]Soy Complex'!$BQ524 -> 46.023291 | E285: =C285-D285 -> 23.380189
A286: 47027 | B286: =([6]Forecasts!$B107-[6]Forecasts!$I$4) -> 559.85 | C286: =B286/'US EIA'!Q363 -> 74.046623 | D286: ='[5]Soy Complex'!$BR513 -> 43.058026 | E286: =C286-D286 -> 30.988596
A287: 47058 | B287: =([6]Forecasts!$B108-[6]Forecasts!$I$4) -> 569.85 | C287: =B287/'US EIA'!Q364 -> 73.623541 | D287: ='[5]Soy Complex'!$BR514 -> 37.235145 | E287: =C287-D287 -> 36.388396
A288: 47088 | B288: =([6]Forecasts!$B109-[6]Forecasts!$I$4) -> 582.35 | C288: =B288/'US EIA'!Q365 -> 81.594117 | D288: ='[5]Soy Complex'!$BR515 -> 39.825943 | E288: =C288-D288 -> 41.768174
A289: 47119 | B289: =([6]Forecasts!$B110-[6]Forecasts!$I$4) -> 582.35 | C289: =B289/'US EIA'!Q366 -> 68.899356 | D289: ='[5]Soy Complex'!$BR516 -> 38.454804 | E289: =C289-D289 -> 30.444553
A290: 47150 | B290: =([6]Forecasts!$B111-[6]Forecasts!$I$4) -> 569.85 | C290: =B290/'US EIA'!Q367 -> 69.682319 | D290: ='[5]Soy Complex'!$BR517 -> 38.541053 | E290: =C290-D290 -> 31.141266
A291: 47178 | B291: =([6]Forecasts!$B112-[6]Forecasts!$I$4) -> 577.35 | C291: =B291/'US EIA'!Q368 -> 73.974511 | D291: ='[5]Soy Complex'!$BR518 -> 46.725473 | E291: =C291-D291 -> 27.249038
A292: 47209 | B292: =([6]Forecasts!$B113-[6]Forecasts!$I$4) -> 582.35 | C292: =B292/'US EIA'!Q369 -> 72.528717 | D292: ='[5]Soy Complex'!$BR519 -> 49.698145 | E292: =C292-D292 -> 22.830572
A293: 47239 | B293: =([6]Forecasts!$B114-[6]Forecasts!$I$4) -> 614.85 | C293: =B293/'US EIA'!Q370 -> 78.915989 | D293: ='[5]Soy Complex'!$BR520 -> 50.94113 | E293: =C293-D293 -> 27.974858
A294: 47270 | B294: =([6]Forecasts!$B115-[6]Forecasts!$I$4) -> 614.85 | C294: =B294/'US EIA'!Q371 -> 79.212138 | D294: ='[5]Soy Complex'!$BR521 -> 50.955965 | E294: =C294-D294 -> 28.256173
A295: 47300 | B295: =([6]Forecasts!$B116-[6]Forecasts!$I$4) -> 634.85 | C295: =B295/'US EIA'!Q372 -> 83.90169 | D295: ='[5]Soy Complex'!$BR522 -> 46.345028 | E295: =C295-D295 -> 37.556662
A296: 47331 | B296: =([6]Forecasts!$B117-[6]Forecasts!$I$4) -> 632.35 | C296: =B296/'US EIA'!Q373 -> 81.829994 | D296: ='[5]Soy Complex'!$BR523 -> 36.281096 | E296: =C296-D296 -> 45.548898
A297: 47362 | B297: =([6]Forecasts!$B118-[6]Forecasts!$I$4) -> 627.35 | C297: =B297/'US EIA'!Q374 -> 79.229369 | D297: ='[5]Soy Complex'!$BR524 -> 14.693293 | E297: =C297-D297 -> 64.536076
...

Sheet US LCFS
A1: Date | B1: BD – Other | C1: BD-Canola | D1: BD-Corn Oil | E1: BD-SBO | F1: BD-UCO | G1: BD-Tallow | H1: Biodiesel Production | I1: RD-Other-Gallons (includes soybean oil before 7-21) | J1: RD-Tallow | K1: RD - Soybean Oil | L1: RD-Fish Oil | M1: RD-UCO | N1: RD-Corn Oil | O1: Renewable Diesel Production | P1: BD – Other-Pounds | Q1: BD-Canola-Pounds | R1: BD-Corn Oil-Pounds | S1: BD-SBO-Pounds | T1: BD-Tallow-Pounds | U1: BD-UCO-Pounds | V1: Biodiesel Feedstock Use | W1: RD-Corn Oil-Pounds | X1: RD-Fish Oil-Pounds | Y1: RD-Other (soybean oil)-Pounds | Z1: RD - Soybean Oil | AA1: RD-Tallow-Pounds | AB1: RD-UCO-Pounds | AC1: Renewable Diesel Feedstock Use | AD1: Biodiesel Vegetable Oil Production | AE1: Biodiesel Animal Fat and Grease Production | AF1: Biodiesel Vegetable Oil Feedstocks | AG1: Biodiesel Animal Fat and Grease Feadstocks | AH1: Biodiesel Vegetable Oil Percentage of Total Feedstocks | AI1: Biodiesel Animal Fats and Grease Percentage of Total Feedstocks | AJ1: Biodiesel Production from Vegetable Oil Percentage | AK1: Biodiesel Production from Animal Fat and Grease Percentage | AL1: Renewable Diesel Vegetable Oil Production | AM1: Renewable Diesel Animal Fat and Grease Production | AN1: Renewable Diesel Vegetable Oil Feedstocks | AO1: Renewable Diesel Animal Fat and Grease Feedstocks | AP1: Renewable Diesel Vegetable Oil Percentage of Total Feedstocks | AQ1: Renewable Diesel Animal Fat and Grease Percentage of Total Feedstocks | AR1: Renewable Diesel Production from Vegetable Oil Percentage | AS1: Renewable Diesel Production from Animal Fat and Grease Percentage | AT1: Combined Vegetable Oil Production | AU1: Combined Animal Fat and Grease Production | AV1: Combined Vegetable Oil Feedstocks | AW1: Combined Animal Fat and Grease Feedstocks | AX1: Vegetable Oil Total Feedstocks Percentage | AY1: Animal Fat and Grease Total Feedstock Percentage | AZ1: Vegetable Oil Production Percentage | BA1: Animal Fat and Grease Production Percentage | BB1: Soybean Oil Percent of RD Feedstocks | BC1: Soybean Oil Percent of BD Feedstocks | BD1: Soybean Oil Percent of Total Feedstocks
A2: 40544 | B2: 14611 | C2: 10940 | D2: 25023 | E2: 870698 | F2: 1033077 | G2: 0 | H2: 1954349 | I2: 0 | J2: 325266 | L2: 0 | M2: 0 | N2: 0 | O2: 325266 | P2: =B2*7.7347 -> 113011.7 | Q2: =C2*7.4 -> 80956 | R2: =D2*8.2 -> 205188.6 | S2: =E2*7.4 -> 6443165.2 | T2: =G2*7.75 -> 0 | U2: =F2*8.01 -> 8274946.8 | V2: =SUM(P2:U2) -> 15117268 | W2: =N2*9.375 -> 0 | X2: =L2*9.375 -> 0 | Y2: =I2*8.5 -> 0 | AA2: =J2*9.375 -> 3049368.8 | AB2: =M2*9.375 -> 0 | AC2: =SUM(W2:AB2) -> 3049368.8 | AD2: =C2+E2 -> 881638 | AE2: =F2+G2+D2 -> 1058100 | AF2: =Q2+S2 -> 6524121.2 | AG2: =T2+U2+R2 -> 8480135.4 | AH2: =AF2/(AF2+AG2) -> 0.43481802 | AI2: =AG2/(AF2+AG2) -> 0.56518198 | AJ2: =AD2/(AD2+AE2) -> 0.45451396 | AK2: =AE2/(AE2+AD2) -> 0.54548604 | AL2: =I2 -> 0 | AM2: =L2+J2+M2+N2 -> 325266 | AN2: =Y2 -> 0 | AO2: =X2+AA2+AB2+W2 -> 3049368.8 | AP2: =AN2/(AN2+AO2) -> 0 | AQ2: =AO2/(AO2+AN2) -> 1 | AR2: =AL2/(AL2+AM2) -> 0 | AS2: =AM2/(AM2+AL2) -> 1 | AT2: =C2+E2+I2+K2 -> 881638 | AU2: =G2+F2+L2+J2+M2+D2+N2 -> 1383366 | AV2: =AN2+AF2 -> 6524121.2 | AW2: =AO2+AG2 -> 11529504 | AX2: =AV2/(AV2+AW2) -> 0.36137458 | AY2: =AW2/(AV2+AW2) -> 0.63862542 | AZ2: =AT2/(AT2+AU2) -> 0.38924346 | BA2: =AU2/(AU2+AT2) -> 0.61075654 | BC2: =E2/H2 -> 0.44551818 | BD2: =(Z2+S2)/(V2+AC2) -> 0.35467022
A3: 40634 | B3: 0 | C3: 27416 | D3: 0 | E3: 651734 | F3: 1944037 | G3: 0 | H3: 2623187 | I3: 0 | J3: 356935 | L3: 0 | M3: 0 | N3: 0 | O3: 356935 | P3: =B3*7.7347 -> 0 | Q3: =C3*7.4 -> 202878.4 | R3: =D3*8.2 -> 0 | S3: =E3*7.4 -> 4822831.6 | T3: =G3*7.75 -> 0 | U3: =F3*8.01 -> 15571736 | V3: =SUM(P3:U3) -> 20597446 | W3: =N3*9.375 -> 0 | X3: =L3*9.375 -> 0 | Y3: =I3*8.5 -> 0 | AA3: =J3*9.375 -> 3346265.6 | AB3: =M3*9.375 -> 0 | AC3: =SUM(W3:AB3) -> 3346265.6 | AD3: =C3+E3 -> 679150 | AE3: =F3+G3+D3 -> 1944037 | AF3: =Q3+S3 -> 5025710 | AG3: =T3+U3+R3 -> 15571736 | AH3: =AF3/(AF3+AG3) -> 0.24399675 | AI3: =AG3/(AF3+AG3) -> 0.75600325 | AJ3: =AD3/(AD3+AE3) -> 0.25890262 | AK3: =AE3/(AE3+AD3) -> 0.74109738 | AL3: =I3 -> 0 | AM3: =L3+J3+M3+N3 -> 356935 | AN3: =Y3 -> 0 | AO3: =X3+AA3+AB3+W3 -> 3346265.6 | AP3: =AN3/(AN3+AO3) -> 0 | AQ3: =AO3/(AO3+AN3) -> 1 | AR3: =AL3/(AL3+AM3) -> 0 | AS3: =AM3/(AM3+AL3) -> 1 | AT3: =C3+E3+I3+K3 -> 679150 | AU3: =G3+F3+L3+J3+M3+D3+N3 -> 2300972 | AV3: =AN3+AF3 -> 5025710 | AW3: =AO3+AG3 -> 18918002 | AX3: =AV3/(AV3+AW3) -> 0.20989686 | AY3: =AW3/(AV3+AW3) -> 0.79010314 | AZ3: =AT3/(AT3+AU3) -> 0.22789335 | BA3: =AU3/(AU3+AT3) -> 0.77210665 | BC3: =E3/H3 -> 0.24845122 | BD3: =(Z3+S3)/(V3+AC3) -> 0.20142372
A4: 40725 | B4: 0 | C4: 0 | D4: 0 | E4: 1563756 | F4: 1913858 | G4: 0 | H4: 3477614 | I4: 0 | J4: 462226 | L4: 0 | M4: 0 | N4: 0 | O4: 462226 | P4: =B4*7.7347 -> 0 | Q4: =C4*7.4 -> 0 | R4: =D4*8.2 -> 0 | S4: =E4*7.4 -> 11571794 | T4: =G4*7.75 -> 0 | U4: =F4*8.01 -> 15330003 | V4: =SUM(P4:U4) -> 26901797 | W4: =N4*9.375 -> 0 | X4: =L4*9.375 -> 0 | Y4: =I4*8.5 -> 0 | AA4: =J4*9.375 -> 4333368.8 | AB4: =M4*9.375 -> 0 | AC4: =SUM(W4:AB4) -> 4333368.8 | AD4: =C4+E4 -> 1563756 | AE4: =F4+G4+D4 -> 1913858 | AF4: =Q4+S4 -> 11571794 | AG4: =T4+U4+R4 -> 15330003 | AH4: =AF4/(AF4+AG4) -> 0.4301495 | AI4: =AG4/(AF4+AG4) -> 0.5698505 | AJ4: =AD4/(AD4+AE4) -> 0.44966348 | AK4: =AE4/(AE4+AD4) -> 0.55033652 | AL4: =I4 -> 0 | AM4: =L4+J4+M4+N4 -> 462226 | AN4: =Y4 -> 0 | AO4: =X4+AA4+AB4+W4 -> 4333368.8 | AP4: =AN4/(AN4+AO4) -> 0 | AQ4: =AO4/(AO4+AN4) -> 1 | AR4: =AL4/(AL4+AM4) -> 0 | AS4: =AM4/(AM4+AL4) -> 1 | AT4: =C4+E4+I4+K4 -> 1563756 | AU4: =G4+F4+L4+J4+M4+D4+N4 -> 2376084 | AV4: =AN4+AF4 -> 11571794 | AW4: =AO4+AG4 -> 19663371 | AX4: =AV4/(AV4+AW4) -> 0.37047328 | AY4: =AW4/(AV4+AW4) -> 0.62952672 | AZ4: =AT4/(AT4+AU4) -> 0.3969085 | BA4: =AU4/(AU4+AT4) -> 0.6030915 | BC4: =E4/H4 -> 0.44966348 | BD4: =(Z4+S4)/(V4+AC4) -> 0.37047328
A5: 40817 | B5: 0 | C5: 0 | D5: 148236 | E5: 2068926 | F5: 2149901 | G5: 115379 | H5: 4482442 | I5: 0 | J5: 659061 | L5: 0 | M5: 0 | N5: 0 | O5: 659061 | P5: =B5*7.7347 -> 0 | Q5: =C5*7.4 -> 0 | R5: =D5*8.2 -> 1215535.2 | S5: =E5*7.4 -> 15310052 | T5: =G5*7.75 -> 894187.25 | U5: =F5*8.01 -> 17220707 | V5: =SUM(P5:U5) -> 34640482 | W5: =N5*9.375 -> 0 | X5: =L5*9.375 -> 0 | Y5: =I5*8.5 -> 0 | AA5: =J5*9.375 -> 6178696.9 | AB5: =M5*9.375 -> 0 | AC5: =SUM(W5:AB5) -> 6178696.9 | AD5: =C5+E5 -> 2068926 | AE5: =F5+G5+D5 -> 2413516 | AF5: =Q5+S5 -> 15310052 | AG5: =T5+U5+R5 -> 19330429 | AH5: =AF5/(AF5+AG5) -> 0.44196996 | AI5: =AG5/(AF5+AG5) -> 0.55803004 | AJ5: =AD5/(AD5+AE5) -> 0.46156225 | AK5: =AE5/(AE5+AD5) -> 0.53843775 | AL5: =I5 -> 0 | AM5: =L5+J5+M5+N5 -> 659061 | AN5: =Y5 -> 0 | AO5: =X5+AA5+AB5+W5 -> 6178696.9 | AP5: =AN5/(AN5+AO5) -> 0 | AQ5: =AO5/(AO5+AN5) -> 1 | AR5: =AL5/(AL5+AM5) -> 0 | AS5: =AM5/(AM5+AL5) -> 1 | AT5: =C5+E5+I5+K5 -> 2068926 | AU5: =G5+F5+L5+J5+M5+D5+N5 -> 3072577 | AV5: =AN5+AF5 -> 15310052 | AW5: =AO5+AG5 -> 25509126 | AX5: =AV5/(AV5+AW5) -> 0.37507007 | AY5: =AW5/(AV5+AW5) -> 0.62492993 | AZ5: =AT5/(AT5+AU5) -> 0.40239712 | BA5: =AU5/(AU5+AT5) -> 0.59760288 | BC5: =E5/H5 -> 0.46156225 | BD5: =(Z5+S5)/(V5+AC5) -> 0.37507007
A6: 40909 | B6: 0 | C6: 24565 | D6: 0 | E6: 1669261 | F6: 2802400 | G6: 509976 | H6: 5006202 | I6: 0 | J6: 712233 | L6: 0 | M6: 0 | N6: 0 | O6: 712233 | P6: =B6*7.7347 -> 0 | Q6: =C6*7.4 -> 181781 | R6: =D6*8.2 -> 0 | S6: =E6*7.4 -> 12352531 | T6: =G6*7.75 -> 3952314 | U6: =F6*8.01 -> 22447224 | V6: =SUM(P6:U6) -> 38933850 | W6: =N6*9.375 -> 0 | X6: =L6*9.375 -> 0 | Y6: =I6*8.5 -> 0 | AA6: =J6*9.375 -> 6677184.4 | AB6: =M6*9.375 -> 0 | AC6: =SUM(W6:AB6) -> 6677184.4 | AD6: =C6+E6 -> 1693826 | AE6: =F6+G6+D6 -> 3312376 | AF6: =Q6+S6 -> 12534312 | AG6: =T6+U6+R6 -> 26399538 | AH6: =AF6/(AF6+AG6) -> 0.32193868 | AI6: =AG6/(AF6+AG6) -> 0.67806132 | AJ6: =AD6/(AD6+AE6) -> 0.33834552 | AK6: =AE6/(AE6+AD6) -> 0.66165448 | AL6: =I6 -> 0 | AM6: =L6+J6+M6+N6 -> 712233 | AN6: =Y6 -> 0 | AO6: =X6+AA6+AB6+W6 -> 6677184.4 | AP6: =AN6/(AN6+AO6) -> 0 | AQ6: =AO6/(AO6+AN6) -> 1 | AR6: =AL6/(AL6+AM6) -> 0 | AS6: =AM6/(AM6+AL6) -> 1 | AT6: =C6+E6+I6+K6 -> 1693826 | AU6: =G6+F6+L6+J6+M6+D6+N6 -> 4024609 | AV6: =AN6+AF6 -> 12534312 | AW6: =AO6+AG6 -> 33076722 | AX6: =AV6/(AV6+AW6) -> 0.27480877 | AY6: =AW6/(AV6+AW6) -> 0.72519123 | AZ6: =AT6/(AT6+AU6) -> 0.29620447 | BA6: =AU6/(AU6+AT6) -> 0.70379553 | BC6: =E6/H6 -> 0.3334386 | BD6: =(Z6+S6)/(V6+AC6) -> 0.27082331
A7: 41000 | B7: 0 | C7: 0 | D7: 1814 | E7: 2410111 | F7: 3166831 | G7: 923648 | H7: 6502404 | I7: 0 | J7: 723231 | L7: 0 | M7: 0 | N7: 0 | O7: 723231 | P7: =B7*7.7347 -> 0 | Q7: =C7*7.4 -> 0 | R7: =D7*8.2 -> 14874.8 | S7: =E7*7.4 -> 17834821 | T7: =G7*7.75 -> 7158272 | U7: =F7*8.01 -> 25366316 | V7: =SUM(P7:U7) -> 50374285 | W7: =N7*9.375 -> 0 | X7: =L7*9.375 -> 0 | Y7: =I7*8.5 -> 0 | AA7: =J7*9.375 -> 6780290.6 | AB7: =M7*9.375 -> 0 | AC7: =SUM(W7:AB7) -> 6780290.6 | AD7: =C7+E7 -> 2410111 | AE7: =F7+G7+D7 -> 4092293 | AF7: =Q7+S7 -> 17834821 | AG7: =T7+U7+R7 -> 32539463 | AH7: =AF7/(AF7+AG7) -> 0.35404615 | AI7: =AG7/(AF7+AG7) -> 0.64595385 | AJ7: =AD7/(AD7+AE7) -> 0.37064922 | AK7: =AE7/(AE7+AD7) -> 0.62935078 | AL7: =I7 -> 0 | AM7: =L7+J7+M7+N7 -> 723231 | AN7: =Y7 -> 0 | AO7: =X7+AA7+AB7+W7 -> 6780290.6 | AP7: =AN7/(AN7+AO7) -> 0 | AQ7: =AO7/(AO7+AN7) -> 1 | AR7: =AL7/(AL7+AM7) -> 0 | AS7: =AM7/(AM7+AL7) -> 1 | AT7: =C7+E7+I7+K7 -> 2410111 | AU7: =G7+F7+L7+J7+M7+D7+N7 -> 4815524 | AV7: =AN7+AF7 -> 17834821 | AW7: =AO7+AG7 -> 39319754 | AX7: =AV7/(AV7+AW7) -> 0.31204538 | AY7: =AW7/(AV7+AW7) -> 0.68795462 | AZ7: =AT7/(AT7+AU7) -> 0.33355006 | BA7: =AU7/(AU7+AT7) -> 0.66644994 | BC7: =E7/H7 -> 0.37064922 | BD7: =(Z7+S7)/(V7+AC7) -> 0.31204538
A8: 41091 | B8: 0 | C8: 22178 | D8: 27357 | E8: 1054670 | F8: 3118400 | G8: 18090 | H8: 4240695 | I8: 0 | J8: 843696 | L8: 0 | M8: 0 | N8: 0 | O8: 843696 | P8: =B8*7.7347 -> 0 | Q8: =C8*7.4 -> 164117.2 | R8: =D8*8.2 -> 224327.4 | S8: =E8*7.4 -> 7804558 | T8: =G8*7.75 -> 140197.5 | U8: =F8*8.01 -> 24978384 | V8: =SUM(P8:U8) -> 33311584 | W8: =N8*9.375 -> 0 | X8: =L8*9.375 -> 0 | Y8: =I8*8.5 -> 0 | AA8: =J8*9.375 -> 7909650 | AB8: =M8*9.375 -> 0 | AC8: =SUM(W8:AB8) -> 7909650 | AD8: =C8+E8 -> 1076848 | AE8: =F8+G8+D8 -> 3163847 | AF8: =Q8+S8 -> 7968675.2 | AG8: =T8+U8+R8 -> 25342909 | AH8: =AF8/(AF8+AG8) -> 0.23921634 | AI8: =AG8/(AF8+AG8) -> 0.76078366 | AJ8: =AD8/(AD8+AE8) -> 0.25393196 | AK8: =AE8/(AE8+AD8) -> 0.74606804 | AL8: =I8 -> 0 | AM8: =L8+J8+M8+N8 -> 843696 | AN8: =Y8 -> 0 | AO8: =X8+AA8+AB8+W8 -> 7909650 | AP8: =AN8/(AN8+AO8) -> 0 | AQ8: =AO8/(AO8+AN8) -> 1 | AR8: =AL8/(AL8+AM8) -> 0 | AS8: =AM8/(AM8+AL8) -> 1 | AT8: =C8+E8+I8+K8 -> 1076848 | AU8: =G8+F8+L8+J8+M8+D8+N8 -> 4007543 | AV8: =AN8+AF8 -> 7968675.2 | AW8: =AO8+AG8 -> 33252559 | AX8: =AV8/(AV8+AW8) -> 0.19331481 | AY8: =AW8/(AV8+AW8) -> 0.80668519 | AZ8: =AT8/(AT8+AU8) -> 0.21179488 | BA8: =AU8/(AU8+AT8) -> 0.78820512 | BC8: =E8/H8 -> 0.24870216 | BD8: =(Z8+S8)/(V8+AC8) -> 0.18933344
A9: 41183 | B9: 0 | C9: 131655 | D9: 44127 | E9: 340866 | F9: 3228284 | G9: 481712 | H9: 4226644 | I9: 0 | J9: 6535747 | L9: 0 | M9: 0 | N9: 0 | O9: 6535747 | P9: =B9*7.7347 -> 0 | Q9: =C9*7.4 -> 974247 | R9: =D9*8.2 -> 361841.4 | S9: =E9*7.4 -> 2522408.4 | T9: =G9*7.75 -> 3733268 | U9: =F9*8.01 -> 25858555 | V9: =SUM(P9:U9) -> 33450320 | W9: =N9*9.375 -> 0 | X9: =L9*9.375 -> 0 | Y9: =I9*8.5 -> 0 | AA9: =J9*9.375 -> 61272628 | AB9: =M9*9.375 -> 0 | AC9: =SUM(W9:AB9) -> 61272628 | AD9: =C9+E9 -> 472521 | AE9: =F9+G9+D9 -> 3754123 | AF9: =Q9+S9 -> 3496655.4 | AG9: =T9+U9+R9 -> 29953664 | AH9: =AF9/(AF9+AG9) -> 0.10453279 | AI9: =AG9/(AF9+AG9) -> 0.89546721 | AJ9: =AD9/(AD9+AE9) -> 0.11179579 | AK9: =AE9/(AE9+AD9) -> 0.88820421 | AL9: =I9 -> 0 | AM9: =L9+J9+M9+N9 -> 6535747 | AN9: =Y9 -> 0 | AO9: =X9+AA9+AB9+W9 -> 61272628 | AP9: =AN9/(AN9+AO9) -> 0 | AQ9: =AO9/(AO9+AN9) -> 1 | AR9: =AL9/(AL9+AM9) -> 0 | AS9: =AM9/(AM9+AL9) -> 1 | AT9: =C9+E9+I9+K9 -> 472521 | AU9: =G9+F9+L9+J9+M9+D9+N9 -> 10289870 | AV9: =AN9+AF9 -> 3496655.4 | AW9: =AO9+AG9 -> 91226292 | AX9: =AV9/(AV9+AW9) -> 0.036914554 | AY9: =AW9/(AV9+AW9) -> 0.96308545 | AZ9: =AT9/(AT9+AU9) -> 0.043904835 | BA9: =AU9/(AU9+AT9) -> 0.95609517 | BC9: =E9/H9 -> 0.080646962 | BD9: =(Z9+S9)/(V9+AC9) -> 0.026629328
A10: 41275 | B10: 48113 | C10: 375643 | D10: 164403 | E10: 825069 | F10: 3706822 | G10: 361482 | H10: 5481532 | I10: 390768 | J10: 6854255 | L10: 937168 | M10: 0 | N10: 0 | O10: 8182191 | P10: =B10*7.7347 -> 372139.62 | Q10: =C10*7.4 -> 2779758.2 | R10: =D10*8.2 -> 1348104.6 | S10: =E10*7.4 -> 6105510.6 | T10: =G10*7.75 -> 2801485.5 | U10: =F10*8.01 -> 29691644 | V10: =SUM(P10:U10) -> 43098643 | W10: =N10*9.375 -> 0 | X10: =L10*9.375 -> 8785950 | Y10: =I10*8.5 -> 3321528 | AA10: =J10*9.375 -> 64258641 | AB10: =M10*9.375 -> 0 | AC10: =SUM(W10:AB10) -> 76366119 | AD10: =C10+E10 -> 1200712 | AE10: =F10+G10+D10 -> 4232707 | AF10: =Q10+S10 -> 8885268.8 | AG10: =T10+U10+R10 -> 33841234 | AH10: =AF10/(AF10+AG10) -> 0.20795685 | AI10: =AG10/(AF10+AG10) -> 0.79204315 | AJ10: =AD10/(AD10+AE10) -> 0.22098645 | AK10: =AE10/(AE10+AD10) -> 0.77901355 | AL10: =I10 -> 390768 | AM10: =L10+J10+M10+N10 -> 7791423 | AN10: =Y10 -> 3321528 | AO10: =X10+AA10+AB10+W10 -> 73044591 | AP10: =AN10/(AN10+AO10) -> 0.043494786 | AQ10: =AO10/(AO10+AN10) -> 0.95650521 | AR10: =AL10/(AL10+AM10) -> 0.047758357 | AS10: =AM10/(AM10+AL10) -> 0.95224164 | AT10: =C10+E10+I10+K10 -> 1591480 | AU10: =G10+F10+L10+J10+M10+D10+N10 -> 12024130 | AV10: =AN10+AF10 -> 12206797 | AW10: =AO10+AG10 -> 1.0688582e+08 | AX10: =AV10/(AV10+AW10) -> 0.10249835 | AY10: =AW10/(AV10+AW10) -> 0.89750165 | AZ10: =AT10/(AT10+AU10) -> 0.11688643 | BA10: =AU10/(AU10+AT10) -> 0.88311357 | BC10: =E10/H10 -> 0.15051796 | BD10: =(Z10+S10)/(V10+AC10) -> 0.05110721
A11: 41365 | B11: 238215 | C11: 1412876 | D11: 1878142 | E11: 1102942 | F11: 7575367 | G11: 1767661 | H11: 13975203 | I11: 1038114 | J11: 21591648 | L11: 932820 | M11: 0 | N11: 0 | O11: 23562582 | P11: =B11*7.7347 -> 1842521.6 | Q11: =C11*7.4 -> 10455282 | R11: =D11*8.2 -> 15400764 | S11: =E11*7.4 -> 8161770.8 | T11: =G11*7.75 -> 13699373 | U11: =F11*8.01 -> 60678690 | V11: =SUM(P11:U11) -> 1.102384e+08 | W11: =N11*9.375 -> 0 | X11: =L11*9.375 -> 8745187.5 | Y11: =I11*8.5 -> 8823969 | AA11: =J11*9.375 -> 202421700 | AB11: =M11*9.375 -> 0 | AC11: =SUM(W11:AB11) -> 2.1999086e+08 | AD11: =C11+E11 -> 2515818 | AE11: =F11+G11+D11 -> 11221170 | AF11: =Q11+S11 -> 18617053 | AG11: =T11+U11+R11 -> 89778827 | AH11: =AF11/(AF11+AG11) -> 0.17175056 | AI11: =AG11/(AF11+AG11) -> 0.82824944 | AJ11: =AD11/(AD11+AE11) -> 0.18314189 | AK11: =AE11/(AE11+AD11) -> 0.81685811 | AL11: =I11 -> 1038114 | AM11: =L11+J11+M11+N11 -> 22524468 | AN11: =Y11 -> 8823969 | AO11: =X11+AA11+AB11+W11 -> 2.1116689e+08 | AP11: =AN11/(AN11+AO11) -> 0.040110617 | AQ11: =AO11/(AO11+AN11) -> 0.95988938 | AR11: =AL11/(AL11+AM11) -> 0.044057735 | AS11: =AM11/(AM11+AL11) -> 0.95594226 | AT11: =C11+E11+I11+K11 -> 3553932 | AU11: =G11+F11+L11+J11+M11+D11+N11 -> 33745638 | AV11: =AN11+AF11 -> 27441022 | AW11: =AO11+AG11 -> 3.0094571e+08 | AX11: =AV11/(AV11+AW11) -> 0.083563126 | AY11: =AW11/(AV11+AW11) -> 0.91643687 | AZ11: =AT11/(AT11+AU11) -> 0.095280777 | BA11: =AU11/(AU11+AT11) -> 0.90471922 | BC11: =E11/H11 -> 0.078921358 | BD11: =(Z11+S11)/(V11+AC11) -> 0.024715468
A12: 41456 | B12: 154147 | C12: 1324144 | D12: 2835089 | E12: 1536385 | F12: 6972497 | G12: 1114087 | H12: 13936349 | I12: 4832319 | J12: 33784673 | L12: 1792400 | M12: 0 | N12: 0 | O12: 40409392 | P12: =B12*7.7347 -> 1192280.8 | Q12: =C12*7.4 -> 9798665.6 | R12: =D12*8.2 -> 23247730 | S12: =E12*7.4 -> 11369249 | T12: =G12*7.75 -> 8634174.2 | U12: =F12*8.01 -> 55849701 | V12: =SUM(P12:U12) -> 1.100918e+08 | W12: =N12*9.375 -> 0 | X12: =L12*9.375 -> 16803750 | Y12: =I12*8.5 -> 41074712 | AA12: =J12*9.375 -> 3.1673131e+08 | AB12: =M12*9.375 -> 0 | AC12: =SUM(W12:AB12) -> 3.7460977e+08 | AD12: =C12+E12 -> 2860529 | AE12: =F12+G12+D12 -> 10921673 | AF12: =Q12+S12 -> 21167915 | AG12: =T12+U12+R12 -> 87731605 | AH12: =AF12/(AF12+AG12) -> 0.19438024 | AI12: =AG12/(AF12+AG12) -> 0.80561976 | AJ12: =AD12/(AD12+AE12) -> 0.20755239 | AK12: =AE12/(AE12+AD12) -> 0.79244761 | AL12: =I12 -> 4832319 | AM12: =L12+J12+M12+N12 -> 35577073 | AN12: =Y12 -> 41074712 | AO12: =X12+AA12+AB12+W12 -> 3.3353506e+08 | AP12: =AN12/(AN12+AO12) -> 0.10964666 | AQ12: =AO12/(AO12+AN12) -> 0.89035334 | AR12: =AL12/(AL12+AM12) -> 0.11958406 | AS12: =AM12/(AM12+AL12) -> 0.88041594 | AT12: =C12+E12+I12+K12 -> 7692848 | AU12: =G12+F12+L12+J12+M12+D12+N12 -> 46498746 | AV12: =AN12+AF12 -> 62242626 | AW12: =AO12+AG12 -> 4.2126666e+08 | AX12: =AV12/(AV12+AW12) -> 0.12873098 | AY12: =AW12/(AV12+AW12) -> 0.87126902 | AZ12: =AT12/(AT12+AU12) -> 0.14195648 | BA12: =AU12/(AU12+AT12) -> 0.85804352 | BC12: =E12/H12 -> 0.11024301 | BD12: =(Z12+S12)/(V12+AC12) -> 0.023456184
A13: 41548 | B13: 718187 | C13: 2160645 | D13: 6026311 | E13: 935394 | F13: 15668412 | G13: 999096 | H13: 26508045 | I13: 12775821 | J13: 29585820 | L13: 2423216 | M13: 0 | N13: 0 | O13: 44784857 | P13: =B13*7.7347 -> 5554961 | Q13: =C13*7.4 -> 15988773 | R13: =D13*8.2 -> 49415750 | S13: =E13*7.4 -> 6921915.6 | T13: =G13*7.75 -> 7742994 | U13: =F13*8.01 -> 1.2550398e+08 | V13: =SUM(P13:U13) -> 2.1112837e+08 | W13: =N13*9.375 -> 0 | X13: =L13*9.375 -> 22717650 | Y13: =I13*8.5 -> 1.0859448e+08 | AA13: =J13*9.375 -> 2.7736706e+08 | AB13: =M13*9.375 -> 0 | AC13: =SUM(W13:AB13) -> 408679191 | AD13: =C13+E13 -> 3096039 | AE13: =F13+G13+D13 -> 22693819 | AF13: =Q13+S13 -> 22910689 | AG13: =T13+U13+R13 -> 1.8266272e+08 | AH13: =AF13/(AF13+AG13) -> 0.11144772 | AI13: =AG13/(AF13+AG13) -> 0.88855228 | AJ13: =AD13/(AD13+AE13) -> 0.1200487 | AK13: =AE13/(AE13+AD13) -> 0.8799513 | AL13: =I13 -> 12775821 | AM13: =L13+J13+M13+N13 -> 32009036 | AN13: =Y13 -> 1.0859448e+08 | AO13: =X13+AA13+AB13+W13 -> 3.0008471e+08 | AP13: =AN13/(AN13+AO13) -> 0.2657206 | AQ13: =AO13/(AO13+AN13) -> 0.7342794 | AR13: =AL13/(AL13+AM13) -> 0.285271 | AS13: =AM13/(AM13+AL13) -> 0.714729 | AT13: =C13+E13+I13+K13 -> 15871860 | AU13: =G13+F13+L13+J13+M13+D13+N13 -> 54702855 | AV13: =AN13+AF13 -> 1.3150517e+08 | AW13: =AO13+AG13 -> 4.8274744e+08 | AX13: =AV13/(AV13+AW13) -> 0.21408972 | AY13: =AW13/(AV13+AW13) -> 0.78591028 | AZ13: =AT13/(AT13+AU13) -> 0.22489443 | BA13: =AU13/(AU13+AT13) -> 0.77510557 | BC13: =E13/H13 -> 0.035287174 | BD13: =(Z13+S13)/(V13+AC13) -> 0.011167846
... A38: 43831 | B38: 0 | C38: 187901 | D38: 31207277 | E38: 70933 | F38: 22530507 | G38: 2353314 | H38: 56349932 | I38: 13981305 | J38: 46730395 | L38: 4233964 | M38: 45856543 | N38: 20171269 | O38: 130973476 | P38: =B38*7.7347 -> 0 | Q38: =C38*7.4 -> 1390467.4 | R38: =D38*8.2 -> 2.5589967e+08 | S38: =E38*7.4 -> 524904.2 | T38: =G38*7.75 -> 18238184 | U38: =F38*8.01 -> 1.8046936e+08 | V38: =SUM(P38:U38) -> 4.5652259e+08 | W38: =N38*9.375 -> 1.8910565e+08 | X38: =L38*9.375 -> 39693412 | Y38: =I38*8.5 -> 1.1884109e+08 | AA38: =J38*9.375 -> 4.3809745e+08 | AB38: =M38*9.375 -> 4.2990509e+08 | AC38: =SUM(W38:AB38) -> 1.2156427e+09 | AD38: =C38+E38 -> 258834 | AE38: =F38+G38+D38 -> 56091098 | AF38: =Q38+S38 -> 1915371.6 | AG38: =T38+U38+R38 -> 4.5460722e+08 | AH38: =AF38/(AF38+AG38) -> 0.0041955681 | AI38: =AG38/(AF38+AG38) -> 0.99580443 | AJ38: =AD38/(AD38+AE38) -> 0.004593333 | AK38: =AE38/(AE38+AD38) -> 0.99540667 | AL38: =I38 -> 13981305 | AM38: =L38+J38+M38+N38 -> 116992171 | AN38: =Y38 -> 1.1884109e+08 | AO38: =X38+AA38+AB38+W38 -> 1.0968016e+09 | AP38: =AN38/(AN38+AO38) -> 0.097759887 | AQ38: =AO38/(AO38+AN38) -> 0.90224011 | AR38: =AL38/(AL38+AM38) -> 0.10674913 | AS38: =AM38/(AM38+AL38) -> 0.89325087 | AT38: =C38+E38+I38+K38 -> 14240139 | AU38: =G38+F38+L38+J38+M38+D38+N38 -> 173083269 | AV38: =AN38+AF38 -> 1.2075646e+08 | AW38: =AO38+AG38 -> 1.5514088e+09 | AX38: =AV38/(AV38+AW38) -> 0.072215627 | AY38: =AW38/(AV38+AW38) -> 0.92778437 | AZ38: =AT38/(AT38+AU38) -> 0.076019005 | BA38: =AU38/(AU38+AT38) -> 0.923981 | BC38: =E38/H38 -> 0.0012587948 | BD38: =(Z38+S38)/(V38+AC38) -> 0.00031390689
A39: 43922 | B39: -9925 | C39: 774081 | D39: 18400302 | E39: 102497 | F39: 25410864 | G39: 14593494 | H39: 59271313 | I39: 25795947 | J39: 65028950 | L39: 1426242 | M39: 37327016 | N39: 22416384 | O39: 151994539 | P39: =B39*7.7347 -> -76766.898 | Q39: =C39*7.4 -> 5728199.4 | R39: =D39*8.2 -> 1.5088248e+08 | S39: =E39*7.4 -> 758477.8 | T39: =G39*7.75 -> 1.1309958e+08 | U39: =F39*8.01 -> 2.0354102e+08 | V39: =SUM(P39:U39) -> 4.7393299e+08 | W39: =N39*9.375 -> 210153600 | X39: =L39*9.375 -> 13371019 | Y39: =I39*8.5 -> 2.1926555e+08 | AA39: =J39*9.375 -> 6.0964641e+08 | AB39: =M39*8.01 -> 2.989894e+08 | AC39: =SUM(W39:AB39) -> 1.351426e+09 | AD39: =C39+E39 -> 876578 | AE39: =F39+G39+D39 -> 58404660 | AF39: =Q39+S39 -> 6486677.2 | AG39: =T39+U39+R39 -> 4.6752308e+08 | AH39: =AF39/(AF39+AG39) -> 0.013684691 | AI39: =AG39/(AF39+AG39) -> 0.98631531 | AJ39: =AD39/(AD39+AE39) -> 0.014786769 | AK39: =AE39/(AE39+AD39) -> 0.98521323 | AL39: =I39 -> 25795947 | AM39: =L39+J39+M39+N39 -> 126198592 | AN39: =Y39 -> 2.1926555e+08 | AO39: =X39+AA39+AB39+W39 -> 1.1321604e+09 | AP39: =AN39/(AN39+AO39) -> 0.16224755 | AQ39: =AO39/(AO39+AN39) -> 0.83775245 | AR39: =AL39/(AL39+AM39) -> 0.16971628 | AS39: =AM39/(AM39+AL39) -> 0.83028372 | AT39: =C39+E39+I39+K39 -> 26672525 | AU39: =G39+F39+L39+J39+M39+D39+N39 -> 184603252 | AV39: =AN39+AF39 -> 2.2575223e+08 | AW39: =AO39+AG39 -> 1.5996835e+09 | AX39: =AV39/(AV39+AW39) -> 0.12367032 | AY39: =AW39/(AV39+AW39) -> 0.87632968 | AZ39: =AT39/(AT39+AU39) -> 0.12624507 | BA39: =AU39/(AU39+AT39) -> 0.87375493 | BC39: =E39/H39 -> 0.0017292851 | BD39: =(Z39+S39)/(V39+AC39) -> 0.00041552255
A40: 44013 | B40: -7382 | C40: 612455 | D40: 26944901 | E40: 235578 | F40: 26666726 | G40: 15257995 | H40: 69710273 | I40: 19434959 | J40: 47581898 | L40: 1017173 | M40: 51907147 | N40: 20131541 | O40: 140072718 | P40: =B40*7.7347 -> -57097.555 | Q40: =C40*7.4 -> 4532167 | R40: =D40*8.2 -> 2.2094819e+08 | S40: =E40*7.4 -> 1743277.2 | T40: =G40*7.75 -> 1.1824946e+08 | U40: =F40*8.01 -> 2.1360048e+08 | V40: =SUM(P40:U40) -> 5.5901647e+08 | W40: =N40*9.375 -> 1.887332e+08 | X40: =L40*9.375 -> 9535996.9 | Y40: =I40*8.5 -> 1.6519715e+08 | AA40: =J40*9.375 -> 4.4608029e+08 | AB40: =M40*8.01 -> 4.1577625e+08 | AC40: =SUM(W40:AB40) -> 1.2253229e+09 | AD40: =C40+E40 -> 848033 | AE40: =F40+G40+D40 -> 68869622 | AF40: =Q40+S40 -> 6275444.2 | AG40: =T40+U40+R40 -> 5.5279812e+08 | AH40: =AF40/(AF40+AG40) -> 0.01122472 | AI40: =AG40/(AF40+AG40) -> 0.98877528 | AJ40: =AD40/(AD40+AE40) -> 0.01216382 | AK40: =AE40/(AE40+AD40) -> 0.98783618 | AL40: =I40 -> 19434959 | AM40: =L40+J40+M40+N40 -> 120637759 | AN40: =Y40 -> 1.6519715e+08 | AO40: =X40+AA40+AB40+W40 -> 1.0601257e+09 | AP40: =AN40/(AN40+AO40) -> 0.13481928 | AQ40: =AO40/(AO40+AN40) -> 0.86518072 | AR40: =AL40/(AL40+AM40) -> 0.13874907 | AS40: =AM40/(AM40+AL40) -> 0.86125093 | AT40: =C40+E40+I40+K40 -> 20282992 | AU40: =G40+F40+L40+J40+M40+D40+N40 -> 189507381 | AV40: =AN40+AF40 -> 1.714726e+08 | AW40: =AO40+AG40 -> 1.6129239e+09 | AX40: =AV40/(AV40+AW40) -> 0.096095571 | AY40: =AW40/(AV40+AW40) -> 0.90390443 | AZ40: =AT40/(AT40+AU40) -> 0.096682187 | BA40: =AU40/(AU40+AT40) -> 0.90331781 | BC40: =E40/H40 -> 0.0033793871 | BD40: =(Z40+S40)/(V40+AC40) -> 0.00097698747
A41: 44105 | B41: 151683 | C41: 7851393 | D41: 34040398 | E41: 2770353 | F41: 26590353 | G41: 9708919 | H41: 81113099 | I41: 27045758 | J41: 41819938 | L41: 3172741 | M41: 64069314 | N41: 29842747 | O41: 165950498 | P41: =B41*7.7347 -> 1173222.5 | Q41: =C41*7.4 -> 58100308 | R41: =D41*8.2 -> 2.7913126e+08 | S41: =E41*7.4 -> 20500612 | T41: =G41*7.75 -> 75244122 | U41: =F41*8.01 -> 2.1298873e+08 | V41: =SUM(P41:U41) -> 6.4713826e+08 | W41: =N41*9.375 -> 2.7977575e+08 | X41: =L41*9.375 -> 29744447 | Y41: =I41*8.5 -> 229888943 | AA41: =J41*9.375 -> 3.9206192e+08 | AB41: =M41*8.01 -> 5.1319521e+08 | AC41: =SUM(W41:AB41) -> 1.4446663e+09 | AD41: =C41+E41 -> 10621746 | AE41: =F41+G41+D41 -> 70339670 | AF41: =Q41+S41 -> 78600920 | AG41: =T41+U41+R41 -> 5.6736411e+08 | AH41: =AF41/(AF41+AG41) -> 0.12167984 | AI41: =AG41/(AF41+AG41) -> 0.87832016 | AJ41: =AD41/(AD41+AE41) -> 0.13119516 | AK41: =AE41/(AE41+AD41) -> 0.86880484 | AL41: =I41 -> 27045758 | AM41: =L41+J41+M41+N41 -> 138904740 | AN41: =Y41 -> 229888943 | AO41: =X41+AA41+AB41+W41 -> 1.2147773e+09 | AP41: =AN41/(AN41+AO41) -> 0.15912945 | AQ41: =AO41/(AO41+AN41) -> 0.84087055 | AR41: =AL41/(AL41+AM41) -> 0.16297485 | AS41: =AM41/(AM41+AL41) -> 0.83702515 | AT41: =C41+E41+I41+K41 -> 37667504 | AU41: =G41+F41+L41+J41+M41+D41+N41 -> 209244410 | AV41: =AN41+AF41 -> 3.0848986e+08 | AW41: =AO41+AG41 -> 1.7821414e+09 | AX41: =AV41/(AV41+AW41) -> 0.14755823 | AY41: =AW41/(AV41+AW41) -> 0.85244177 | AZ41: =AT41/(AT41+AU41) -> 0.15255442 | BA41: =AU41/(AU41+AT41) -> 0.84744558 | BC41: =E41/H41 -> 0.0341542 | BD41: =(Z41+S41)/(V41+AC41) -> 0.0098004436
A42: 44197 | B42: 5006355 | C42: 31618 | D42: 29749624 | E42: 38694 | F42: 16983652 | G42: 9612083 | H42: 61422026 | I42: 45498151 | J42: 48680629 | K42: 0 | L42: 0 | M42: 80800501 | N42: 24110480 | O42: 199089761 | P42: =B42*7.7347 -> 38722654 | Q42: =C42*7.4 -> 233973.2 | R42: =D42*8.2 -> 2.4394692e+08 | S42: =E42*7.4 -> 286335.6 | T42: =G42*7.75 -> 74493643 | U42: =F42*8.01 -> 1.3603905e+08 | V42: =SUM(P42:U42) -> 4.9372258e+08 | W42: =N42*9.375 -> 226035750 | X42: =L42*9.375 -> 0 | Y42: =I42*8.5 -> 3.8673428e+08 | AA42: =J42*9.375 -> 4.563809e+08 | AB42: =M42*8.01 -> 6.4721201e+08 | AC42: =SUM(W42:AB42) -> 1.7163629e+09 | AD42: =C42+E42 -> 70312 | AE42: =F42+G42+D42 -> 56345359 | AF42: =Q42+S42 -> 520308.8 | AG42: =T42+U42+R42 -> 4.5447961e+08 | AH42: =AF42/(AF42+AG42) -> 0.001143536 | AI42: =AG42/(AF42+AG42) -> 0.99885646 | AJ42: =AD42/(AD42+AE42) -> 0.0012463204 | AK42: =AE42/(AE42+AD42) -> 0.99875368 | AL42: =I42 -> 45498151 | AM42: =L42+J42+M42+N42 -> 153591610 | AN42: =Y42 -> 3.8673428e+08 | AO42: =X42+AA42+AB42+W42 -> 1.3296287e+09 | AP42: =AN42/(AN42+AO42) -> 0.22532197 | AQ42: =AO42/(AO42+AN42) -> 0.77467803 | AR42: =AL42/(AL42+AM42) -> 0.22853084 | AS42: =AM42/(AM42+AL42) -> 0.77146916 | AT42: =C42+E42+I42+K42 -> 45568463 | AU42: =G42+F42+L42+J42+M42+D42+N42 -> 209936969 | AV42: =AN42+AF42 -> 3.8725459e+08 | AW42: =AO42+AG42 -> 1.7841083e+09 | AX42: =AV42/(AV42+AW42) -> 0.17834633 | AY42: =AW42/(AV42+AW42) -> 0.82165367 | AZ42: =AT42/(AT42+AU42) -> 0.17834636 | BA42: =AU42/(AU42+AT42) -> 0.82165364 | BC42: =E42/H42 -> 0.00062996945 | BD42: =(Z42+S42)/(V42+AC42) -> 0.00012955861
A43: 44287 | B43: 2432664 | C43: 0 | D43: 32492361 | E43: 294918 | F43: 22564242 | G43: 20369410 | H43: 78153595 | I43: 52555692 | J43: 73708925 | K43: 0 | L43: 0 | M43: 59225747 | N43: 33295373 | O43: 218785737 | P43: =B43*7.7347 -> 18815926 | Q43: =C43*7.4 -> 0 | R43: =D43*8.2 -> 2.6643736e+08 | S43: =E43*7.4 -> 2182393.2 | T43: =G43*7.75 -> 1.5786293e+08 | U43: =F43*8.01 -> 1.8073958e+08 | V43: =SUM(P43:U43) -> 6.2603819e+08 | W43: =N43*9.375 -> 3.1214412e+08 | X43: =L43*9.375 -> 0 | Y43: =I43*8.5 -> 446723382 | AA43: =J43*9.375 -> 6.9102117e+08 | AB43: =M43*8.01 -> 4.7439823e+08 | AC43: =SUM(W43:AB43) -> 1.9242869e+09 | AD43: =C43+E43 -> 294918 | AE43: =F43+G43+D43 -> 75426013 | AF43: =Q43+S43 -> 2182393.2 | AG43: =T43+U43+R43 -> 6.0503987e+08 | AH43: =AF43/(AF43+AG43) -> 0.0035940599 | AI43: =AG43/(AF43+AG43) -> 0.99640594 | AJ43: =AD43/(AD43+AE43) -> 0.0038948016 | AK43: =AE43/(AE43+AD43) -> 0.9961052 | AL43: =I43 -> 52555692 | AM43: =L43+J43+M43+N43 -> 166230045 | AN43: =Y43 -> 446723382 | AO43: =X43+AA43+AB43+W43 -> 1.4775635e+09 | AP43: =AN43/(AN43+AO43) -> 0.23215009 | AQ43: =AO43/(AO43+AN43) -> 0.76784991 | AR43: =AL43/(AL43+AM43) -> 0.24021535 | AS43: =AM43/(AM43+AL43) -> 0.75978465 | AT43: =C43+E43+I43+K43 -> 52850610 | AU43: =G43+F43+L43+J43+M43+D43+N43 -> 241656058 | AV43: =AN43+AF43 -> 4.4890578e+08 | AW43: =AO43+AG43 -> 2.0826034e+09 | AX43: =AV43/(AV43+AW43) -> 0.17732734 | AY43: =AW43/(AV43+AW43) -> 0.82267266 | AZ43: =AT43/(AT43+AU43) -> 0.17945471 | BA43: =AU43/(AU43+AT43) -> 0.82054529 | BC43: =E43/H43 -> 0.0037735692 | BD43: =(Z43+S43)/(V43+AC43) -> 0.00085573137
A44: 44378 | B44: 514121 | C44: 2190767 | D44: 29316204 | E44: 0 | F44: 26693620 | G44: 18904890 | H44: 77619602 | I44: 5616364 | J44: 64277113 | K44: 74895320 | L44: 0 | M44: 57459087 | N44: 48004593 | O44: 250252477 | P44: =B44*7.7347 -> 3976571.7 | Q44: =C44*7.4 -> 16211676 | R44: =D44*8.2 -> 2.4039287e+08 | S44: =E44*7.4 -> 0 | T44: =G44*7.75 -> 1.465129e+08 | U44: =F44*8.01 -> 2.138159e+08 | V44: =SUM(P44:U44) -> 6.2090991e+08 | W44: =N44*9.375 -> 4.5004306e+08 | X44: =L44*9.375 -> 0 | Y44: =I44*8.5 -> 47739094 | Z44: =K44*7.5 -> 561714900 | AA44: =J44*9.375 -> 6.0259793e+08 | AB44: =M44*8.01 -> 4.6024729e+08 | AC44: =SUM(W44:AB44) -> 2.1223423e+09 | AD44: =C44+E44 -> 2190767 | AE44: =F44+G44+D44 -> 74914714 | AF44: =Q44+S44 -> 16211676 | AG44: =T44+U44+R44 -> 6.0072167e+08 | AH44: =AF44/(AF44+AG44) -> 0.02627784 | AI44: =AG44/(AF44+AG44) -> 0.97372216 | AJ44: =AD44/(AD44+AE44) -> 0.028412598 | AK44: =AE44/(AE44+AD44) -> 0.9715874 | AL44: =K44 -> 74895320 | AM44: =L44+J44+M44+N44 -> 169740793 | AN44: =Z44 -> 561714900 | AO44: =X44+AA44+AB44+W44 -> 1.5128883e+09 | AP44: =AN44/(AN44+AO44) -> 0.27075776 | AQ44: =AO44/(AO44+AN44) -> 0.72924224 | AR44: =AL44/(AL44+AM44) -> 0.30614989 | AS44: =AM44/(AM44+AL44) -> 0.69385011 | AT44: =C44+E44+I44+K44 -> 82702451 | AU44: =G44+F44+L44+J44+M44+D44+N44 -> 244655507 | AV44: =AN44+AF44 -> 5.7792658e+08 | AW44: =AO44+AG44 -> 2.1136099e+09 | AX44: =AV44/(AV44+AW44) -> 0.21471995 | AY44: =AW44/(AV44+AW44) -> 0.78528005 | AZ44: =AT44/(AT44+AU44) -> 0.25263614 | BA44: =AU44/(AU44+AT44) -> 0.74736386 | BB44: =Z44/AC44 -> 0.26466744 | BC44: =E44/H44 -> 0 | BD44: =(Z44+S44)/(V44+AC44) -> 0.2047624
A45: 44470 | B45: -1150 | C45: 1059115 | D45: 22458404 | E45: 4331846 | F45: 35350380 | G45: 9677862 | H45: 72876457 | I45: 7724450 | J45: 60285079 | K45: 74757273 | L45: 0 | M45: 89164045 | N45: 40948018 | O45: 272878865 | P45: =B45*7.7347 -> -8894.905 | Q45: =C45*7.4 -> 7837451 | R45: =D45*8.2 -> 1.8415891e+08 | S45: =E45*7.4 -> 32055660 | T45: =G45*7.75 -> 75003430 | U45: =F45*8.01 -> 2.8315654e+08 | V45: =SUM(P45:U45) -> 5.822031e+08 | W45: =N45*9.375 -> 3.8388767e+08 | X45: =L45*9.375 -> 0 | Y45: =I45*8.5 -> 65657825 | Z45: =K45*7.5 -> 5.6067955e+08 | AA45: =J45*9.375 -> 5.6517262e+08 | AB45: =M45*8.01 -> 7.14204e+08 | AC45: =SUM(W45:AB45) -> 2.2896017e+09 | AD45: =C45+E45 -> 5390961 | AE45: =F45+G45+D45 -> 67486646 | AF45: =Q45+S45 -> 39893111 | AG45: =T45+U45+R45 -> 5.4231889e+08 | AH45: =AF45/(AF45+AG45) -> 0.068519906 | AI45: =AG45/(AF45+AG45) -> 0.93148009 | AJ45: =AD45/(AD45+AE45) -> 0.073972805 | AK45: =AE45/(AE45+AD45) -> 0.9260272 | AL45: =K45 -> 74757273 | AM45: =L45+J45+M45+N45 -> 190397142 | AN45: =Z45 -> 5.6067955e+08 | AO45: =X45+AA45+AB45+W45 -> 1.6632643e+09 | AP45: =AN45/(AN45+AO45) -> 0.25211048 | AQ45: =AO45/(AO45+AN45) -> 0.74788952 | AR45: =AL45/(AL45+AM45) -> 0.28193863 | AS45: =AM45/(AM45+AL45) -> 0.71806137 | AT45: =C45+E45+I45+K45 -> 87872684 | AU45: =G45+F45+L45+J45+M45+D45+N45 -> 257883788 | AV45: =AN45+AF45 -> 6.0057266e+08 | AW45: =AO45+AG45 -> 2.2055832e+09 | AX45: =AV45/(AV45+AW45) -> 0.21401971 | AY45: =AW45/(AV45+AW45) -> 0.78598029 | AZ45: =AT45/(AT45+AU45) -> 0.25414617 | BA45: =AU45/(AU45+AT45) -> 0.74585383 | BB45: =Z45/AC45 -> 0.24488083 | BC45: =E45/H45 -> 0.059440952 | BD45: =(Z45+S45)/(V45+AC45) -> 0.20639816 | BH45: Feedstock replacement if 7% rule imposed in 2021
A46: 44562 | B46: -2783 | C46: 3236463 | D46: 34878837 | E46: 3362087 | F46: 21359198 | G46: 8045158 | H46: 70878960 | I46: 4664696 | J46: 88019352 | K46: 70879632 | L46: 0 | M46: 75947990 | N46: 74389828 | O46: 313529997 | P46: =B46*7.7347 -> -21525.67 | Q46: =C46*7.4 -> 23949826 | R46: =D46*8.2 -> 2.8600646e+08 | S46: =E46*7.4 -> 24879444 | T46: =G46*7.75 -> 62349974 | U46: =F46*8.01 -> 1.7108718e+08 | V46: =SUM(P46:U46) -> 5.6825136e+08 | W46: =N46*9.375 -> 6.9740464e+08 | X46: =L46*9.375 -> 0 | Y46: =I46*8.5 -> 39649916 | Z46: =K46*7.5 -> 531597240 | AA46: =J46*9.375 -> 825181425 | AB46: =M46*8.01 -> 6.083434e+08 | AC46: =SUM(W46:AB46) -> 2.7021766e+09 | AD46: =C46+E46 -> 6598550 | AE46: =F46+G46+D46 -> 64283193 | AF46: =Q46+S46 -> 48829270 | AG46: =T46+U46+R46 -> 5.1944361e+08 | AH46: =AF46/(AF46+AG46) -> 0.085925743 | AI46: =AG46/(AF46+AG46) -> 0.91407426 | AJ46: =AD46/(AD46+AE46) -> 0.093092378 | AK46: =AE46/(AE46+AD46) -> 0.90690762 | AL46: =K46 -> 70879632 | AM46: =L46+J46+M46+N46 -> 238357170 | AN46: =Z46 -> 531597240 | AO46: =X46+AA46+AB46+W46 -> 2.1309295e+09 | AP46: =AN46/(AN46+AO46) -> 0.19965893 | AQ46: =AO46/(AO46+AN46) -> 0.80034107 | AR46: =AL46/(AL46+AM46) -> 0.22920827 | AS46: =AM46/(AM46+AL46) -> 0.77079173 | AT46: =C46+E46+I46+K46 -> 82142878 | AU46: =G46+F46+L46+J46+M46+D46+N46 -> 302640363 | AV46: =AN46+AF46 -> 580426510 | AW46: =AO46+AG46 -> 2.6503731e+09 | AX46: =AV46/(AV46+AW46) -> 0.17965414 | AY46: =AW46/(AV46+AW46) -> 0.82034586 | AZ46: =AT46/(AT46+AU46) -> 0.21347832 | BA46: =AU46/(AU46+AT46) -> 0.78652168 | BB46: =Z46/AC46 -> 0.19672927 | BC46: =E46/H46 -> 0.047434203 | BD46: =(Z46+S46)/(V46+AC46) -> 0.17015409 | BH46: =0.07*SUM(AV43:AW46) -> 7.8820008e+08 | BI46: 7% of total feedstock use
A47: 44652 | B47: -55015 | C47: 3625020 | D47: 12508989 | E47: 2095108 | F47: 24600969 | G47: 24420189 | H47: 67195260 | I47: 20544053 | J47: 107619798 | K47: 58936820 | L47: 0 | M47: 94964524 | N47: 64876703 | O47: 345932564 | P47: =B47*7.7347 -> -425524.52 | Q47: =C47*7.4 -> 26825148 | R47: =D47*8.2 -> 1.0257371e+08 | S47: =E47*7.4 -> 15503799 | T47: =G47*7.75 -> 1.8925646e+08 | U47: =F47*8.01 -> 1.9705376e+08 | V47: =SUM(P47:U47) -> 5.3078736e+08 | W47: =N47*9.375 -> 6.0821909e+08 | X47: =L47*9.375 -> 0 | Y47: =I47*8.5 -> 1.7462445e+08 | Z47: =K47*7.5 -> 442026150 | AA47: =J47*9.375 -> 1.0089356e+09 | AB47: =M47*8.01 -> 7.6066584e+08 | AC47: =SUM(W47:AB47) -> 2.9944711e+09 | AD47: =C47+E47 -> 5720128 | AE47: =F47+G47+D47 -> 61530147 | AF47: =Q47+S47 -> 42328947 | AG47: =T47+U47+R47 -> 4.8888394e+08 | AH47: =AF47/(AF47+AG47) -> 0.079683585 | AI47: =AG47/(AF47+AG47) -> 0.92031641 | AJ47: =AD47/(AD47+AE47) -> 0.085057318 | AK47: =AE47/(AE47+AD47) -> 0.91494268 | AL47: =K47 -> 58936820 | AM47: =L47+J47+M47+N47 -> 267461025 | AN47: =Z47 -> 442026150 | AO47: =X47+AA47+AB47+W47 -> 2.3778205e+09 | AP47: =AN47/(AN47+AO47) -> 0.15675538 | AQ47: =AO47/(AO47+AN47) -> 0.84324462 | AR47: =AL47/(AL47+AM47) -> 0.18056743 | AS47: =AM47/(AM47+AL47) -> 0.81943257 | AT47: =C47+E47+I47+K47 -> 85201001 | AU47: =G47+F47+L47+J47+M47+N47+D47 -> 328991172 | AV47: =AN47+AF47 -> 4.843551e+08 | AW47: =AO47+AG47 -> 2.8667045e+09 | AX47: =AV47/(AV47+AW47) -> 0.1445379 | AY47: =AW47/(AV47+AW47) -> 0.8554621 | AZ47: =AT47/(AT47+AU47) -> 0.20570403 | BA47: =AU47/(AU47+AT47) -> 0.79429597 | BB47: =Z47/AC47 -> 0.1476141 | BC47: =E47/H47 -> 0.031179402 | BD47: =(Z47+S47)/(V47+AC47) -> 0.12978621 | BH47: =SUM(AV43:AV46) -> 2.2078315e+09 | BI47: Veg oil feedstock use
A48: 44743 | B48: 1013735 | C48: 6251085 | D48: 19825789 | E48: 1498018 | F48: 22814059 | G48: 20904215 | H48: 72306901 | I48: 46423957 | J48: 65064766 | K48: 60788652 | L48: 0 | M48: 94011535 | N48: 85958683 | O48: 351185786 | P48: =B48*7.7347 -> 7840936.1 | Q48: =C48*7.4 -> 46258029 | R48: =D48*8.2 -> 1.6257147e+08 | S48: =E48*7.4 -> 11085333 | T48: =G48*7.75 -> 1.6200767e+08 | U48: =F48*8.01 -> 1.8274061e+08 | V48: =SUM(P48:U48) -> 5.7250405e+08 | W48: =N48*9.375 -> 8.0586265e+08 | X48: =L48*9.375 -> 0 | Y48: =I48*8.5 -> 3.9460363e+08 | Z48: =K48*7.5 -> 455914890 | AA48: =J48*9.375 -> 6.0998218e+08 | AB48: =M48*8.01 -> 7.530324e+08 | AC48: =SUM(W48:AB48) -> 3.0193958e+09 | AD48: =C48+E48 -> 7749103 | AE48: =F48+G48+D48 -> 63544063 | AF48: =Q48+S48 -> 57343362 | AG48: =T48+U48+R48 -> 5.0731975e+08 | AH48: =AF48/(AF48+AG48) -> 0.10155323 | AI48: =AG48/(AF48+AG48) -> 0.89844677 | AJ48: =AD48/(AD48+AE48) -> 0.10869349 | AK48: =AE48/(AE48+AD48) -> 0.89130651 | AL48: =K48 -> 60788652 | AM48: =L48+J48+M48+N48 -> 245034984 | AN48: =Z48 -> 455914890 | AO48: =X48+AA48+AB48+W48 -> 2.1688772e+09 | AP48: =AN48/(AN48+AO48) -> 0.17369562 | AQ48: =AO48/(AO48+AN48) -> 0.82630438 | AR48: =AL48/(AL48+AM48) -> 0.19877029 | AS48: =AM48/(AM48+AL48) -> 0.80122971 | AT48: =C48+E48+I48+K48 -> 114961712 | AU48: =G48+F48+L48+J48+M48+N48+D48 -> 308579047 | AV48: =AN48+AF48 -> 5.1325825e+08 | AW48: =AO48+AG48 -> 2.676197e+09 | AX48: =AV48/(AV48+AW48) -> 0.16092349 | AY48: =AW48/(AV48+AW48) -> 0.83907651 | AZ48: =AT48/(AT48+AU48) -> 0.2714301 | BA48: =AU48/(AU48+AT48) -> 0.7285699 | BB48: =Z48/AC48 -> 0.15099541 | BC48: =E48/H48 -> 0.020717497 | BD48: =(Z48+S48)/(V48+AC48) -> 0.13001482 | BH48: =BH47-BH46 -> 1.4196314e+09 | BI48: Feedstock replacement
A49: 44835 | B49: 602132 | C49: 10679716 | D49: 20777689 | E49: 2001397 | F49: 20388494 | G49: 16783223 | H49: 71232651 | I49: 43543499 | J49: 87236011 | K49: 53723484 | L49: =(AVERAGE(L37:L48)/AVERAGE($O37:$O48))*$O49*0 -> 0 | M49: 128171054 | N49: 59465241 | O49: 370331676 | P49: =B49*7.7347 -> 4657310.4 | Q49: =C49*7.4 -> 79029898 | R49: =D49*8.2 -> 1.7037705e+08 | S49: =E49*7.4 -> 14810338 | T49: =G49*7.75 -> 1.3006998e+08 | U49: =F49*8.01 -> 1.6331184e+08 | V49: =SUM(P49:U49) -> 5.6225641e+08 | W49: =N49*9.375 -> 5.5748663e+08 | X49: =L49*9.375 -> 0 | Y49: =I49*8.5 -> 3.7011974e+08 | Z49: =K49*7.5 -> 402926130 | AA49: =J49*9.375 -> 8.178376e+08 | AB49: =M49*8.01 -> 1.0266501e+09 | AC49: =SUM(W49:AB49) -> 3.1750203e+09 | AD49: =C49+E49 -> 12681113 | AE49: =F49+G49+D49 -> 57949406 | AF49: =Q49+S49 -> 93840236 | AG49: =T49+U49+R49 -> 4.6375886e+08 | AH49: =AF49/(AF49+AG49) -> 0.16829338 | AI49: =AG49/(AF49+AG49) -> 0.83170662 | AJ49: =AD49/(AD49+AE49) -> 0.17954155 | AK49: =AE49/(AE49+AD49) -> 0.82045845 | AL49: =K49 -> 53723484 | AM49: =L49+J49+M49+N49 -> 274872306 | AN49: =Z49 -> 402926130 | AO49: =X49+AA49+AB49+W49 -> 2.4019744e+09 | AP49: =AN49/(AN49+AO49) -> 0.14365077 | AQ49: =AO49/(AO49+AN49) -> 0.85634923 | AR49: =AL49/(AL49+AM49) -> 0.16349413 | AS49: =AM49/(AM49+AL49) -> 0.83650587 | AT49: =C49+E49+I49+K49 -> 109948096 | AU49: =G49+F49+L49+J49+M49+N49+D49 -> 332821712 | AV49: =AN49+AF49 -> 4.9676637e+08 | AW49: =AO49+AG49 -> 2.8657332e+09 | AX49: =AV49/(AV49+AW49) -> 0.14773723 | AY49: =AW49/(AV49+AW49) -> 0.85226277 | AZ49: =AT49/(AT49+AU49) -> 0.24831886 | BA49: =AU49/(AU49+AT49) -> 0.75168114 | BB49: =Z49/AC49 -> 0.12690506 | BC49: =E49/H49 -> 0.028096624 | BD49: =(Z49+S49)/(V49+AC49) -> 0.11177563 | BH49: =BH48/7.5 -> 1.8928419e+08 | BI49: Gallons needed to replace shortfall
A50: 44927 | B50: -53014 | C50: 21209020 | D50: 24940888 | E50: 705711 | F50: 14748537 | G50: 6989876 | H50: ='[8]Fuel Vol and Credit Gen'!$AY$12 -> 68541019 | I50: 43633178 | J50: 100889396 | K50: 80873905 | L50: =(AVERAGE(L38:L49)/AVERAGE($O38:$O49))*$O50*0 -> 0 | M50: 145112910 | N50: 34269429 | O50: 404778818 | P50: =B50*7.7347 -> -410047.39 | Q50: =C50*7.4 -> 156946748 | R50: =D50*8.2 -> 2.0451528e+08 | S50: =E50*7.4 -> 5222261.4 | T50: =G50*7.75 -> 54171539 | U50: =F50*8.01 -> 1.1813578e+08 | V50: =SUM(P50:U50) -> 5.3858156e+08 | W50: =N50*9.375 -> 3.212759e+08 | X50: =L50*9.375 -> 0 | Y50: =I50*8.5 -> 370882013 | Z50: =K50*7.5 -> 6.0655429e+08 | AA50: =J50*9.375 -> 9.4583809e+08 | AB50: =M50*8.01 -> 1.1623544e+09 | AC50: =SUM(W50:AB50) -> 3.4069047e+09 | AD50: =C50+E50 -> 21914731 | AE50: =F50+G50+D50 -> 46679301 | AF50: =Q50+S50 -> 1.6216901e+08 | AG50: =T50+U50+R50 -> 3.768226e+08 | AH50: =AF50/(AF50+AG50) -> 0.30087483 | AI50: =AG50/(AF50+AG50) -> 0.69912517 | AJ50: =AD50/(AD50+AE50) -> 0.31948451 | AK50: =AE50/(AE50+AD50) -> 0.68051549 | AL50: =K50 -> 80873905 | AM50: =L50+J50+M50+N50 -> 280271735 | AN50: =Z50 -> 6.0655429e+08 | AO50: =X50+AA50+AB50+W50 -> 2.4294684e+09 | AP50: =AN50/(AN50+AO50) -> 0.19978582 | AQ50: =AO50/(AO50+AN50) -> 0.80021418 | AR50: =AL50/(AL50+AM50) -> 0.22393709 | AS50: =AM50/(AM50+AL50) -> 0.77606291 | AT50: =C50+E50+I50+K50 -> 146421814 | AU50: =G50+F50+L50+J50+M50+N50+D50 -> 326951036 | AV50: =AN50+AF50 -> 7.687233e+08 | AW50: =AO50+AG50 -> 2.806291e+09 | AX50: =AV50/(AV50+AW50) -> 0.21502664 | AY50: =AW50/(AV50+AW50) -> 0.78497336 | AZ50: =AT50/(AT50+AU50) -> 0.30931604 | BA50: =AU50/(AU50+AT50) -> 0.69068396 | BB50: =Z50/AC50 -> 0.17803676 | BC50: =E50/H50 -> 0.010296185 | BD50: =(Z50+S50)/(V50+AC50) -> 0.15505733 | BH50: =BH49*9.5 -> 1.7981998e+09 | BI50: Fats and greases required based on 9.5 pound conversion rate
