Workbook

Sheet Chicago Fuel Prices
B1: 2020 | C1: 2021 | D1: 2022 | E1: 2023 | F1: 2024 | G1: 2025 | H1: 2026 | I1: 2027 | J1: 2028 | K1: 2029 | L1: 2030 | M1: 2031 | N1: 2032 | O1: 2033 | P1: 2034 | Q1: 2035 | R1: 2036 | S1: 2037 | T1: 2038 | U1: 2039 | V1: 2040 | W1: 2041 | X1: 2042 | Y1: 2043 | Z1: 2044 | AA1: 2045 | AB1: 2046 | AC1: 2047 | AD1: 2048 | AE1: 2049 | AF1: 2050
A2: Chicago
A3: USLD Price | C3: 320.8 | D3: 490.71667 | E3: 411.425 | F3: 369.825 | G3: 354.275 | H3: 378.9 | I3: 388.8 | J3: 399.7 | K3: 410.9 | L3: 420.1 | M3: 432 | N3: 442.1 | O3: 452.8 | P3: 463.4 | Q3: 474.3 | R3: 484.3 | S3: 495 | T3: 506.2 | U3: 516.1 | V3: 527.6 | W3: 538 | X3: 548.5 | Y3: 559 | Z3: 570.9 | AA3: 580.5 | AB3: 591.1 | AC3: 602.5 | AD3: 612.2 | AE3: 623.3 | AF3: 634.7
A4: Weighted RIN | B4: -4.55 | C4: -9.33 | D4: -10.7 | E4: -7.24 | F4: -3.84 | G4: 91.839164 | H4: 91.717007 | I4: 75.007408 | J4: 72.350621 | K4: 73.160933 | L4: 101.05405 | M4: 94.959033 | N4: 76.546247 | O4: 104.89656 | P4: 131.01263 | Q4: 133.80709 | R4: 142.81413 | S4: 101.55332 | T4: 107.28053 | U4: 92.589189 | V4: 80.803058 | W4: 95.819228 | X4: 115.77721 | Y4: 113.00788 | Z4: 124.89368 | AA4: 124.27379 | AB4: 119.79344 | AC4: 118.24766 | AD4: 113.52253 | AE4: 148.6609 | AF4: 134.59396
A5: Density Adjustment | B5: =(B3*129.7/134.5)-B3 -> 0 | C5: =(C3*129.65/134.47)-C3 -> -11.498892 | D5: =(D3*129.65/134.47)-D3 -> -17.589457 | E5: =(E3*129.65/134.47)-E3 -> -14.747293 | F5: =(F3*129.65/134.47)-F3 -> -13.256165 | G5: =(G3*129.65/134.47)-G3 -> -12.698784 | H5: =(H3*129.65/134.47)-H3 -> -13.581453 | I5: =(I3*129.65/134.47)-I3 -> -13.936313 | J5: =(J3*129.65/134.47)-J3 -> -14.327017 | ... AF5: =(AF3*129.65/134.47)-AF3 -> -22.750457
A6: Cap-n-Trade | C6: 26 | D6: 32 | E6: 35 | F6: 35.84 | G6: 30 | H6: 31.430388 | I6: 33.680448 | J6: 34.901033 | K6: 41.871263 | L6: 45.183403 | M6: 47.531854 | N6: 46.468625 | O6: 39.359547 | P6: 37.341523 | Q6: 41.566091 | R6: 39.461322 | S6: 39.461322 | T6: 39.461322 | U6: 36.642656 | V6: 39.461322 | W6: 39.461322 | X6: 36.642656 | Y6: 36.642656 | Z6: 36.642656 | AA6: 36.642656 | AB6: 33.82399 | AC6: 36.642656 | AD6: 33.82399 | AE6: 33.82399 | AF6: 33.82399
A7: RD Stipulated Value | B7: =B3+B4+B5+C6 -> 21.45 | C7: =C3+C4+C5+C6 -> 325.97111 | D7: =D3+D4+D5+D6 -> 494.42721 | E7: =E3+E4+E5+E6 -> 424.43771 | F7: =F3+F4+F5+F6 -> 388.56884 | G7: =G3+G4+G5+G6 -> 463.41538 | H7: =H3+H4+H5+H6 -> 488.46594 | I7: =I3+I4+I5+I6 -> 483.55154 | J7: =J3+J4+J5+J6 -> 492.62464 | ... AF7: =AF3+AF4+AF5+AF6 -> 780.3675
A8: Blender's Tax Credit Value | B8: 1 | C8: 100 | D8: 100 | E8: 100 | F8: 100 | G8: 0 | H8: 0 | I8: 0 | J8: 0 | K8: 0 | L8: 0 | M8: 0 | N8: 0 | O8: 0 | P8: 0 | Q8: 0 | R8: 0 | S8: 0 | T8: 0 | U8: 0 | V8: 0 | W8: 0 | X8: 0 | Y8: 0 | Z8: 0 | AA8: 0 | AB8: 0 | AC8: 0 | AD8: 0 | AE8: 0 | AF8: 0
A9: 45Z Credit Value - 35 CI score | G9: 65 | H9: =G9*1.02 -> 66.3 | I9: =H9*1.02 -> 67.626 | J9: =I9*1.02 -> 68.97852 | K9: =J9*1.02 -> 70.35809 | L9: =K9*1.02 -> 71.765252 | M9: =L9*1.02 -> 73.200557 | N9: =M9*1.02 -> 74.664568 | O9: =N9*1.02 -> 76.15786 | ... AF9: =AE9*1.02 -> 106.63939
A10: D4 RIN Forecast Value | B10: =B29 -> 108.38639 | C10: =C29 -> 253.61129 | D10: =D29 -> 282.97606 | E10: =E29 -> 228.91778 | F10: =F29 -> 99.997132 | G10: =G29 -> 127.16176 | H10: =H29 -> 131.91909 | I10: =I29 -> 136.85069 | ... AF10: =AF29 -> 131.75
A11: Total RD Value | B11: =SUM(B7:B10) -> 130.83639 | C11: =SUM(C7:C10) -> 679.58239 | D11: =SUM(D7:D10) -> 877.40327 | E11: =SUM(E7:E10) -> 753.35549 | F11: =SUM(F7:F10) -> 588.56597 | G11: =SUM(G7:G10) -> 655.57714 | H11: =SUM(H7:H10) -> 686.68503 | I11: =SUM(I7:I10) -> 688.02823 | ... AF11: =SUM(AF7:AF10) -> 1018.7569
A12: Transport and Storage Fee | C12: -50 | D12: -50 | E12: -50 | F12: -50 | G12: -50 | H12: -50 | I12: -50 | J12: -50 | K12: -50 | L12: -50 | M12: -50 | N12: -50 | O12: -50 | P12: -50 | Q12: -50 | R12: -50 | S12: -50 | T12: -50 | U12: -50 | V12: -50 | W12: -50 | X12: -50 | Y12: -50 | Z12: -50 | AA12: -50 | AB12: -50 | AC12: -50 | AD12: -50 | AE12: -50 | AF12: -50
A13: RD Value versus Net Offtaker Costs | C13: =C11+C12 -> 629.58239 | D13: =D11+D12 -> 827.40327 | E13: =E11+E12 -> 703.35549 | F13: =F11+F12 -> 538.56597 | G13: =G11+G12 -> 605.57714 | H13: =H11+H12 -> 636.68503 | I13: =I11+I12 -> 638.02823 | J13: =J11+J12 -> 660.39554 | ... AF13: =AF11+AF12 -> 968.75689
A15: Jet Fuel Price | B15: 174.91628 | C15: 225.06364 | D15: 282.4 | E15: 490.71667 | F15: 411.425 | G15: 369.825 | H15: 378.8 | I15: 388.5 | J15: 399.1 | K15: 410 | L15: 419 | M15: 430.6 | N15: 440.4 | O15: 450.8 | P15: 461.2 | Q15: 471.8 | R15: 481.6 | S15: 492 | T15: 502.9 | U15: 512.6 | V15: 523.8 | W15: 533.9 | X15: 544.1 | Y15: 554.4 | Z15: 566 | AA15: 575.3 | AB15: 585.7 | AC15: 596.8 | AD15: 606.2 | AE15: 617.1 | AF15: 628.2
A16: Density Adjustment | C16: =C15*126.4/142.2-C15 -> -25.007071 | D16: =D15*126.4/142.2-D15 -> -31.377778 | E16: =E15*126.4/142.2-E15 -> -54.524074 | F16: =F15*126.4/142.2-F15 -> -45.713889 | G16: =G15*126.4/142.2-G15 -> -41.091667 | H16: =H15*126.4/142.2-H15 -> -42.088889 | I16: =I15*126.4/142.2-I15 -> -43.166667 | J16: =J15*126.4/142.2-J15 -> -44.344444 | ... AF16: =AF15*126.4/142.2-AF15 -> -69.8
A17: SAF Stipulated Value | C17: =C15+C16 -> 200.05657 | D17: =D15+D16 -> 251.02222 | E17: =E15+E16 -> 436.19259 | F17: =F15+F16 -> 365.71111 | G17: =G15+G16 -> 328.73333 | H17: =H15+H16 -> 336.71111 | I17: =I15+I16 -> 345.33333 | J17: =J15+J16 -> 354.75556 | ... AF17: =AF15+AF16 -> 558.4
A18: IL SAF Purchase Credit Value | C18: 0 | D18: 0 | E18: 150 | F18: 150 | G18: 150 | H18: 150 | I18: 150 | J18: 150 | K18: 150 | L18: 150 | M18: 150 | N18: 150 | O18: 150 | P18: 150 | Q18: 150 | R18: 150 | S18: 150 | T18: 150 | U18: 150 | V18: 150 | W18: 150 | X18: 150 | Y18: 150 | Z18: 150 | AA18: 150 | AB18: 150 | AC18: 150 | AD18: 150 | AE18: 150 | AF18: 150
A19: 40B Credit Value - 35 CI score | C19: 0 | D19: 0 | E19: 140 | F19: 140 | G19: 0 | H19: 0 | I19: 0 | J19: 0 | K19: 0 | L19: 0 | M19: 0 | N19: 0 | O19: 0 | P19: 0 | Q19: 0 | R19: 0 | S19: 0 | T19: 0 | U19: 0 | V19: 0 | W19: 0 | X19: 0 | Y19: 0 | Z19: 0 | AA19: 0 | AB19: 0 | AC19: 0 | AD19: 0 | AE19: 0 | AF19: 0
A20: 45Z Credit Value - 35 CI score | G20: 140 | H20: =G20*1.02 -> 142.8 | I20: =H20*1.02 -> 145.656 | J20: =I20*1.02 -> 148.56912 | K20: =J20*1.02 -> 151.5405 | L20: =K20*1.02 -> 154.57131 | M20: =L20*1.02 -> 157.66274 | N20: =M20*1.02 -> 160.81599 | O20: =N20*1.02 -> 164.03231 | ... AF20: =AE20*1.02 -> 229.68484
A21: SAF Stipulated RIN Value | C21: =C30 -> 238.69297 | D21: =D30 -> 266.33041 | E21: =E30 -> 215.45203 | F21: =F30 -> 94.114948 | G21: =G30 -> 119.68166 | H21: =H30 -> 124.15915 | I21: =I30 -> 128.80065 | J21: =J30 -> 140.03989 | ... AF21: =AF30 -> 124
A22: SAF Market Premium | C22: 100 | D22: 100 | E22: 100 | F22: 100 | G22: 100 | H22: 100 | I22: 100 | J22: 100 | K22: 100 | L22: 100 | M22: 100 | N22: 100 | O22: 100 | P22: 100 | Q22: 100 | R22: 100 | S22: 100 | T22: 100 | U22: 100 | V22: 100 | W22: 100 | X22: 100 | Y22: 100 | Z22: 100 | AA22: 100 | AB22: 100 | AC22: 100 | AD22: 100 | AE22: 100 | AF22: 100
A23: Total SAF Value | C23: =SUM(C17:C22) -> 538.74954 | D23: =SUM(D17:D22) -> 617.35263 | E23: =SUM(E17:E22) -> 1041.6446 | F23: =SUM(F17:F22) -> 849.82606 | G23: =SUM(G17:G22) -> 838.41499 | H23: =SUM(H17:H22) -> 853.67026 | I23: =SUM(I17:I22) -> 869.78998 | J23: =SUM(J17:J22) -> 893.36457 | ... AF23: =SUM(AF17:AF22) -> 1162.0848
A24: Transport and Storage Fee | C24: -50 | D24: -50 | E24: -50 | F24: -50 | G24: -50 | H24: -50 | I24: -50 | J24: -50 | K24: -50 | L24: -50 | M24: -50 | N24: -50 | O24: -50 | P24: -50 | Q24: -50 | R24: -50 | S24: -50 | T24: -50 | U24: -50 | V24: -50 | W24: -50 | X24: -50 | Y24: -50 | Z24: -50 | AA24: -50 | AB24: -50 | AC24: -50 | AD24: -50 | AE24: -50 | AF24: -50
A25: SAF Value Net of Offtaker Costs | C25: =C23+C24 -> 488.74954 | D25: =D23+D24 -> 567.35263 | E25: =E23+E24 -> 991.64462 | F25: =F23+F24 -> 799.82606 | G25: =G23+G24 -> 788.41499 | H25: =H23+H24 -> 803.67026 | I25: =I23+I24 -> 819.78998 | J25: =J23+J24 -> 843.36457 | ... AF25: =AF23+AF24 -> 1112.0848
A26: SAF - RD | C26: =C25-C13 -> -140.83285 | D26: =D25-D13 -> -260.05064 | E26: =E25-E13 -> 288.28913 | F26: =F25-F13 -> 261.26009 | G26: =G25-G13 -> 182.83785 | H26: =H25-H13 -> 166.98522 | I26: =I25-I13 -> 181.76175 | J26: =J25-J13 -> 182.96903 | ... AF26: =AF25-AF13 -> 143.32795
A28: RIN Price | B28: 63.756698 | C28: 149.18311 | D28: 166.4565 | E28: 134.65752 | F28: 58.821842 | G28: 74.801035 | H28: 77.599466 | I28: 80.500404 | J28: 87.524932 | K28: 95.890021 | L28: 95.633568 | M28: 100.12276 | N28: 100.42462 | O28: 100.93658 | P28: 98.069245 | Q28: 97.652846 | R28: 93.1 | S28: 92.9 | T28: 91.1 | U28: 88.3 | V28: 89.1 | W28: 92.7 | X28: 87.1 | Y28: 88.1 | Z28: 82.8 | AA28: 86.2 | AB28: 81 | AC28: 84.3 | AD28: 79.2 | AE28: 82.4 | AF28: 77.5
A29: RD RIN Stipulated Value | B29: =B28*1.7 -> 108.38639 | C29: =C28*1.7 -> 253.61129 | D29: =D28*1.7 -> 282.97606 | E29: =E28*1.7 -> 228.91778 | F29: =F28*1.7 -> 99.997132 | G29: =G28*1.7 -> 127.16176 | H29: =H28*1.7 -> 131.91909 | I29: =I28*1.7 -> 136.85069 | ... AF29: =AF28*1.7 -> 131.75
A30: SAF RIN Stipulated Value | C30: =C28*1.6 -> 238.69297 | D30: =D28*1.6 -> 266.33041 | E30: =E28*1.6 -> 215.45203 | F30: =F28*1.6 -> 94.114948 | G30: =G28*1.6 -> 119.68166 | H30: =H28*1.6 -> 124.15915 | I30: =I28*1.6 -> 128.80065 | J30: =J28*1.6 -> 140.03989 | ... AF30: =AF28*1.6 -> 124

Sheet California Fuel Prices
B1: 2020 | C1: 2021 | D1: 2022 | E1: 2023 | F1: 2024 | G1: 2025 | H1: 2026 | I1: 2027 | J1: 2028 | K1: 2029 | L1: 2030 | M1: 2031 | N1: 2032 | O1: 2033 | P1: 2034 | Q1: 2035 | R1: 2036 | S1: 2037 | T1: 2038 | U1: 2039 | V1: 2040 | W1: 2041 | X1: 2042 | Y1: 2043 | Z1: 2044 | AA1: 2045 | AB1: 2046 | AC1: 2047 | AD1: 2048 | AE1: 2049 | AF1: 2050
A2: California | G2: 2022 dollars for 45z
A3: USLD Price | C3: 384.68333 | D3: 562.48333 | E3: 494.275 | F3: 441.63333 | G3: 426.725 | H3: 428.3 | I3: 439 | J3: 450.9 | K3: 462.2 | L3: 473.9 | M3: 484.1 | N3: 495.4 | O3: 507.6 | P3: 518.2 | Q3: 529.3 | R3: 541 | S3: 552.9 | T3: 563.9 | U3: 575 | V3: 585.5 | W3: 597.3 | X3: 608.1 | Y3: 619.7 | Z3: 630.6 | AA3: 642.8 | AB3: 653.3 | AC3: 664.6 | AD3: 675.1 | AE3: 687.7 | AF3: 698
A4: Weighted RIN | B4: -4.55 | C4: -9.33 | D4: -10.7 | E4: -7.24 | F4: -3.84 | G4: 91.839164 | H4: 91.717007 | I4: 75.007408 | J4: 72.350621 | K4: 73.160933 | L4: 101.05405 | M4: 94.959033 | N4: 76.546247 | O4: 104.89656 | P4: 131.01263 | Q4: 133.80709 | R4: 142.81413 | S4: 101.55332 | T4: 107.28053 | U4: 92.589189 | V4: 80.803058 | W4: 95.819228 | X4: 115.77721 | Y4: 113.00788 | Z4: 124.89368 | AA4: 124.27379 | AB4: 119.79344 | AC4: 118.24766 | AD4: 113.52253 | AE4: 148.6609 | AF4: 134.59396
A5: Density Adjustment | B5: =(B3*129.7/134.5)-B3 -> 0 | C5: =(C3*129.65/134.47)-C3 -> -13.788753 | D5: =(D3*129.65/134.47)-D3 -> -20.161892 | E5: =(E3*129.65/134.47)-E3 -> -17.717004 | F5: =(F3*129.65/134.47)-F3 -> -15.830093 | G5: =(G3*129.65/134.47)-G3 -> -15.295713 | H5: =(H3*129.65/134.47)-H3 -> -15.352168 | I5: =(I3*129.65/134.47)-I3 -> -15.735703 | J5: =(J3*129.65/134.47)-J3 -> -16.162252 | ... AF5: =(AF3*129.65/134.47)-AF3 -> -25.01941
A6: Cap-n-Trade | C6: 26 | D6: 32 | E6: 35 | F6: 35.84 | G6: 30 | H6: 31.430388 | I6: 33.680448 | J6: 34.901033 | K6: 41.871263 | L6: 45.183403 | M6: 47.531854 | N6: 46.468625 | O6: 39.359547 | P6: 37.341523 | Q6: 41.566091 | R6: 39.461322 | S6: 39.461322 | T6: 39.461322 | U6: 36.642656 | V6: 39.461322 | W6: 39.461322 | X6: 36.642656 | Y6: 36.642656 | Z6: 36.642656 | AA6: 36.642656 | AB6: 33.82399 | AC6: 36.642656 | AD6: 33.82399 | AE6: 33.82399 | AF6: 33.82399
A7: RD Stipulated Value | B7: =B3+B4+B5+C6 -> 21.45 | C7: =C3+C4+C5+C6 -> 387.56458 | D7: =D3+D4+D5+D6 -> 563.62144 | E7: =E3+E4+E5+E6 -> 504.318 | F7: =F3+F4+F5+F6 -> 457.80324 | G7: =G3+G4+G5+G6 -> 533.26845 | H7: =H3+H4+H5+H6 -> 536.09523 | I7: =I3+I4+I5+I6 -> 531.95215 | J7: =J3+J4+J5+J6 -> 541.9894 | ... AF7: =AF3+AF4+AF5+AF6 -> 841.39855
A8: Blender's Tax Credit | B8: 100 | C8: 100 | D8: 100 | E8: 100 | F8: 100 | G8: 0 | H8: 0 | I8: 0 | J8: 0 | K8: 0 | L8: 0 | M8: 0 | N8: 0 | O8: 0 | P8: 0 | Q8: 0 | R8: 0 | S8: 0 | T8: 0 | U8: 0 | V8: 0 | W8: 0 | X8: 0 | Y8: 0 | Z8: 0 | AA8: 0 | AB8: 0 | AC8: 0 | AD8: 0 | AE8: 0 | AF8: 0
A9: 45Z Credit - 35 CI score | C9: 0 | D9: 0 | E9: 0 | F9: 0 | G9: 140 | H9: =G9*1.02 -> 142.8 | I9: =H9*1.02 -> 145.656 | J9: =I9*1.02 -> 148.56912 | K9: =J9*1.02 -> 151.5405 | L9: =K9*1.02 -> 154.57131 | M9: =L9*1.02 -> 157.66274 | N9: =M9*1.02 -> 160.81599 | O9: =N9*1.02 -> 164.03231 | ... AF9: =AE9*1.02 -> 229.68484
A10: LCFS Equivalent Value | B10: =B28 -> 177.73874 | C10: 151.72749 | D10: 81.17199 | E10: 57.300076 | F10: 45.677311 | G10: 54.45594 | H10: 58.777948 | I10: 57.38316 | J10: 58.417826 | K10: 65.822491 | L10: 58.171766 | M10: 53.117415 | N10: 49.252906 | O10: 48.903253 | P10: 53.756183 | Q10: 48.495833 | R10: 49.461693 | S10: 44.01644 | T10: 37.562472 | U10: 33.757977 | V10: 31.333084 | W10: 30.466378 | X10: 28.420766 | Y10: 24.868954 | Z10: 21.491001 | AA10: 18.161867 | AB10: 14.878649 | AC10: 11.644319 | AD10: 8.4602963 | AE10: 5.327146 | AF10: 2.242752
A11: RD Stipulated RIN Value | B11: =B34 -> 108.38639 | C11: =C34 -> 253.61129 | D11: =D34 -> 282.97606 | E11: =E34 -> 228.91778 | F11: =F34 -> 99.997132 | G11: =G34 -> 127.16176 | H11: =H34 -> 131.91909 | I11: =I34 -> 136.85069 | ... AF11: =AF34 -> 131.75
A12: Total RD Value | B12: =SUM(B7:B11) -> 407.57513 | C12: =SUM(C7:C11) -> 892.90336 | D12: =SUM(D7:D11) -> 1027.7695 | E12: =SUM(E7:E11) -> 890.53585 | F12: =SUM(F7:F11) -> 703.47768 | G12: =SUM(G7:G11) -> 854.88615 | H12: =SUM(H7:H11) -> 869.59227 | I12: =SUM(I7:I11) -> 871.842 | ... AF12: =SUM(AF7:AF11) -> 1205.0761
A13: Transport and Storage Fee | C13: -50 | D13: -50 | E13: -50 | F13: -50 | G13: -50 | H13: -50 | I13: -50 | J13: -50 | K13: -50 | L13: -50 | M13: -50 | N13: -50 | O13: -50 | P13: -50 | Q13: -50 | R13: -50 | S13: -50 | T13: -50 | U13: -50 | V13: -50 | W13: -50 | X13: -50 | Y13: -50 | Z13: -50 | AA13: -50 | AB13: -50 | AC13: -50 | AD13: -50 | AE13: -50 | AF13: -50
A14: RD Value versus Net Offtaker Costs | C14: =C12+C13 -> 842.90336 | D14: =D12+D13 -> 977.76949 | E14: =E12+E13 -> 840.53585 | F14: =F12+F13 -> 653.47768 | G14: =G12+G13 -> 804.88615 | H14: =H12+H13 -> 819.59227 | I14: =I12+I13 -> 821.842 | J14: =J12+J13 -> 847.76873 | ... AF14: =AF12+AF13 -> 1155.0761
A16: Jet Fuel Price | B16: 157.98261 | C16: 185.8 | D16: 337.4 | E16: 269.9 | F16: 310.7 | G16: 331.6 | H16: 427 | I16: 437.4 | J16: 449 | K16: 460 | L16: 471.4 | M16: 481.4 | N16: 492.4 | O16: 504.3 | P16: 514.6 | Q16: 525.4 | R16: 536.8 | S16: 548.4 | T16: 559.2 | U16: 570 | V16: 580.2 | W16: 591.7 | X16: 602.2 | Y16: 613.6 | Z16: 624.2 | AA16: 636.1 | AB16: 646.3 | AC16: 657.3 | AD16: 667.6 | AE16: 679.8 | AF16: 689.9
A17: Density Adjustment | C17: =C16*126.4/142.2-C16 -> -20.644444 | D17: =D16*126.4/142.2-D16 -> -37.488889 | E17: =E16*126.4/142.2-E16 -> -29.988889 | F17: =F16*126.4/142.2-F16 -> -34.522222 | G17: =G16*126.4/142.2-G16 -> -36.844444 | H17: =H16*126.4/142.2-H16 -> -47.444444 | I17: =I16*126.4/142.2-I16 -> -48.6 | J17: =J16*126.4/142.2-J16 -> -49.888889 | ... AF17: =AF16*126.4/142.2-AF16 -> -76.655556
A18: SAF Stipulated Value | C18: =C16+C17 -> 165.15556 | D18: =D16+D17 -> 299.91111 | E18: =E16+E17 -> 239.91111 | F18: =F16+F17 -> 276.17778 | G18: =G16+G17 -> 294.75556 | H18: =H16+H17 -> 379.55556 | I18: =I16+I17 -> 388.8 | J18: =J16+J17 -> 399.11111 | ... AF18: =AF16+AF17 -> 613.24444
A19: 40B Credit Value - 35 CI score | C19: 0 | D19: 0 | E19: 140 | F19: 140 | G19: 0 | H19: 0 | I19: 0 | J19: 0 | K19: 0 | L19: 0 | M19: 0 | N19: 0 | O19: 0 | P19: 0 | Q19: 0 | R19: 0 | S19: 0 | T19: 0 | U19: 0 | V19: 0 | W19: 0 | X19: 0 | Y19: 0 | Z19: 0 | AA19: 0 | AB19: 0 | AC19: 0 | AD19: 0 | AE19: 0 | AF19: 0
A20: 45Z Credit Value - 35 CI score | G20: =G9 -> 140 | H20: =H9 -> 142.8 | I20: =I9 -> 145.656 | J20: =J9 -> 148.56912 | K20: =K9 -> 151.5405 | L20: =L9 -> 154.57131 | M20: =M9 -> 157.66274 | N20: =N9 -> 160.81599 | ... AF20: =AF9 -> 229.68484
A21: LCFS / Equivalent Value | C21: 127.74738 | D21: 69.483949 | E21: 49.92131 | F21: 40.550195 | G21: 49.324498 | H21: 54.397952 | I21: 54.350212 | J21: 56.727411 | K21: 65.664952 | L21: 59.755948 | M21: 56.256787 | N21: 53.902402 | O21: 55.441938 | P21: 63.310768 | Q21: 59.523771 | R21: 63.500575 | S21: 59.357042 | T21: 53.466521 | U21: 51.011276 | V21: 50.607737 | W21: 53.031159 | X21: 53.855113 | Y21: 51.954776 | Z21: 50.312487 | AA21: 48.691451 | AB21: 47.082794 | AC21: 45.492351 | AD21: 43.92476 | AE21: 42.387378 | AF21: 40.877616
A22: SAF Stipulated RIN Value | C22: =C35 -> 238.69297 | D22: =D35 -> 266.33041 | E22: =E35 -> 215.45203 | F22: =F35 -> 94.114948 | G22: =G35 -> 119.68166 | H22: =H35 -> 124.15915 | I22: =I35 -> 128.80065 | J22: =J35 -> 140.03989 | ... AF22: =AF35 -> 124
A23: SAF Market Premium | C23: 250 | D23: 250 | E23: 250 | F23: 250 | G23: 250 | H23: 250 | I23: 250 | J23: 250 | K23: 250 | L23: 250 | M23: 250 | N23: 250 | O23: 250 | P23: 250 | Q23: 250 | R23: 250 | S23: 250 | T23: 250 | U23: 250 | V23: 250 | W23: 250 | X23: 250 | Y23: 250 | Z23: 250 | AA23: 250 | AB23: 250 | AC23: 250 | AD23: 250 | AE23: 250 | AF23: 250
A24: Total SAF Value | C24: =SUM(C18:C23) -> 781.59591 | D24: =SUM(D18:D23) -> 885.72547 | E24: =SUM(E18:E23) -> 895.28445 | F24: =SUM(F18:F23) -> 800.84292 | G24: =SUM(G18:G23) -> 853.76171 | H24: =SUM(H18:H23) -> 950.91265 | I24: =SUM(I18:I23) -> 967.60686 | J24: =SUM(J18:J23) -> 994.44753 | ... AF24: =SUM(AF18:AF23) -> 1257.8069
A25: Transport and Storage Fee | C25: -50 | D25: -50 | E25: -50 | F25: -50 | G25: -50 | H25: -50 | I25: -50 | J25: -50 | K25: -50 | L25: -50 | M25: -50 | N25: -50 | O25: -50 | P25: -50 | Q25: -50 | R25: -50 | S25: -50 | T25: -50 | U25: -50 | V25: -50 | W25: -50 | X25: -50 | Y25: -50 | Z25: -50 | AA25: -50 | AB25: -50 | AC25: -50 | AD25: -50 | AE25: -50 | AF25: -50
A26: SAF Value Net of Offtaker Costs | C26: =C24+C25 -> 731.59591 | D26: =D24+D25 -> 835.72547 | E26: =E24+E25 -> 845.28445 | F26: =F24+F25 -> 750.84292 | G26: =G24+G25 -> 803.76171 | H26: =H24+H25 -> 900.91265 | I26: =I24+I25 -> 917.60686 | J26: =J24+J25 -> 944.44753 | ... AF26: =AF24+AF25 -> 1207.8069
A27: SAF - RD | C27: =C26-C14 -> -111.30745 | D27: =D26-D14 -> -142.04402 | E27: =E26-E14 -> 4.7485965 | F27: =F26-F14 -> 97.365238 | G27: =G26-G14 -> -1.1244406 | H27: =H26-H14 -> 81.320385 | I27: =I26-I14 -> 95.764858 | J27: =J26-J14 -> 96.6788 | ... AF27: =AF26-AF14 -> 52.730763
A28: LCFS Credit Price | B28: 177.73874 | D28: 98.858071 | E28: 72.666232 | F28: 60.42136 | G28: 75.27557 | H28: 85.079045 | I28: 87.168118 | J28: 93.357077 | K28: 110.96401 | L28: 103.76154 | M28: 100.34017 | N28: 98.78514 | O28: 104.43593 | P28: 122.62174 | Q28: 118.58103 | R28: 130.16688 | S28: 125.24582 | T28: 116.17659 | U28: 114.19158 | V28: 116.76426 | W28: 126.16884 | X28: 132.18691 | Y28: 131.6286 | Z28: 131.64297 | AA28: 131.64894 | AB28: 131.62184 | AC28: 131.57618 | AD28: 131.52501 | AE28: 131.49171 | AF28: 131.47114
A29: CARB Diesel Compliance Standard | B29: 92.91625 | C29: 91.660625 | D29: 90.405 | E29: 89.149375 | F29: 87.89375 | G29: 86.638125 | H29: 85.3825 | I29: 84.126875 | J29: 82.87125 | K29: 81.615625 | L29: 80.36 | M29: =L29*0.985 -> 79.1546 | N29: =M29*0.985 -> 77.967281 | O29: =N29*0.985 -> 76.797772 | P29: =O29*0.985 -> 75.645805 | Q29: =P29*0.985 -> 74.511118 | R29: =Q29*0.985 -> 73.393451 | S29: =R29*0.985 -> 72.29255 | T29: =S29*0.985 -> 71.208161 | ... AF29: =AE29*0.985 -> 59.397004
A30: HOBO Target Post-Blend CI
A31: LCFS Compliance Deficits
A33: RIN Price | B33: 63.756698 | C33: 149.18311 | D33: 166.4565 | E33: 134.65752 | F33: 58.821842 | G33: 74.801035 | H33: 77.599466 | I33: 80.500404 | J33: 87.524932 | K33: 95.890021 | L33: 95.633568 | M33: 100.12276 | N33: 100.42462 | O33: 100.93658 | P33: 98.069245 | Q33: 97.652846 | R33: 93.1 | S33: 92.9 | T33: 91.1 | U33: 88.3 | V33: 89.1 | W33: 92.7 | X33: 87.1 | Y33: 88.1 | Z33: 82.8 | AA33: 86.2 | AB33: 81 | AC33: 84.3 | AD33: 79.2 | AE33: 82.4 | AF33: 77.5
A34: RD RIN Stipulated Value | B34: =B33*1.7 -> 108.38639 | C34: =C33*1.7 -> 253.61129 | D34: =D33*1.7 -> 282.97606 | E34: =E33*1.7 -> 228.91778 | F34: =F33*1.7 -> 99.997132 | G34: =G33*1.7 -> 127.16176 | H34: =H33*1.7 -> 131.91909 | I34: =I33*1.7 -> 136.85069 | ... AF34: =AF33*1.7 -> 131.75
A35: SAF RIN Stipulated Value | C35: =C33*1.6 -> 238.69297 | D35: =D33*1.6 -> 266.33041 | E35: =E33*1.6 -> 215.45203 | F35: =F33*1.6 -> 94.114948 | G35: =G33*1.6 -> 119.68166 | H35: =H33*1.6 -> 124.15915 | I35: =I33*1.6 -> 128.80065 | J35: =J33*1.6 -> 140.03989 | ... AF35: =AF33*1.6 -> 124

Sheet Canada Fuel Prices
B1: 2020 | C1: 2021 | D1: 2022 | E1: 2023 | F1: 2024 | G1: 2025 | H1: 2026 | I1: 2027 | J1: 2028 | K1: 2029 | L1: 2030 | M1: 2031 | N1: 2032 | O1: 2033 | P1: 2034 | Q1: 2035 | R1: 2036 | S1: 2037 | T1: 2038 | U1: 2039 | V1: 2040 | W1: 2041 | X1: 2042 | Y1: 2043 | Z1: 2044 | AA1: 2045 | AB1: 2046 | AC1: 2047 | AD1: 2048 | AE1: 2049 | AF1: 2050
A2: Canada
A3: USLD Price | C3: 379.2 | D3: 511.8 | E3: 426.1 | F3: 450.5 | G3: 421.2 | H3: 428.4 | I3: 443.1 | J3: 459.9 | K3: 474.7 | L3: 490.4 | M3: 506.7 | N3: 521.3 | O3: 537.9 | P3: 553.5 | Q3: 518.9 | R3: 534.4 | S3: 550.5 | T3: 565.9 | U3: 581.6 | V3: 572.6 | W3: 588.7 | X3: 603.9 | Y3: 619.9 | Z3: 635.4 | AA3: 625.3 | AB3: 641.5 | AC3: 658 | AD3: 672.5 | AE3: 688.4 | AF3: 705.5
A4: Density Adjustment | B4: =(B3*129.7/134.5)-B3 -> 0 | C4: =(C3*129.65/134.47)-C3 -> -13.592206 | D4: =(D3*129.65/134.47)-D3 -> -18.345177 | E4: =(E3*129.65/134.47)-E3 -> -15.27331 | F4: =(F3*129.65/134.47)-F3 -> -16.147914 | G4: =(G3*129.65/134.47)-G3 -> -15.097672 | H4: =(H3*129.65/134.47)-H3 -> -15.355752 | I4: =(I3*129.65/134.47)-I3 -> -15.882665 | J4: =(J3*129.65/134.47)-J3 -> -16.484852 | ... AF4: =(AF3*129.65/134.47)-AF3 -> -25.288243
A5: RD Stipulated Value | B5: =B3+#REF!+B4+#REF! -> #REF! | C5: =SUM(C3:C4) -> 365.60779 | D5: =SUM(D3:D4) -> 493.45482 | E5: =SUM(E3:E4) -> 410.82669 | F5: =SUM(F3:F4) -> 434.35209 | G5: =SUM(G3:G4) -> 406.10233 | H5: =SUM(H3:H4) -> 413.04425 | I5: =SUM(I3:I4) -> 427.21733 | J5: =SUM(J3:J4) -> 443.41515 | ... AF5: =SUM(AF3:AF4) -> 680.21176
A6: CFR Equivalent Value | B6: =B22 -> 0 | C6: 0 | D6: =(('Canada Fuel Prices'!D23-'CFR Example'!$B$6)*('CFR Example'!$B$9*1000)/1000000)*'Canada Fuel Prices'!D22/'CFR Example'!$B$3/'Canada Fuel Prices'!D27*100 -> 68.187521 | E6: =(('Canada Fuel Prices'!E23-'CFR Example'!$B$6)*('CFR Example'!$B$9*1000)/1000000)*'Canada Fuel Prices'!E22/'CFR Example'!$B$3/'Canada Fuel Prices'!E27*100 -> 58.059833 | F6: =(('Canada Fuel Prices'!F23-'CFR Example'!$B$6)*('CFR Example'!$B$9*1000)/1000000)*'Canada Fuel Prices'!F22/'CFR Example'!$B$3/'Canada Fuel Prices'!F27*100 -> 57.330835 | G6: =(('Canada Fuel Prices'!G23-'CFR Example'!$B$6)*('CFR Example'!$B$9*1000)/1000000)*'Canada Fuel Prices'!G22/'CFR Example'!$B$3/'Canada Fuel Prices'!G27*100 -> 57.80702 | H6: =(('Canada Fuel Prices'!H23-'CFR Example'!$B$6)*('CFR Example'!$B$9*1000)/1000000)*'Canada Fuel Prices'!H22/'CFR Example'!$B$3/'Canada Fuel Prices'!H27*100 -> 65.517167 | I6: =(('Canada Fuel Prices'!I23-'CFR Example'!$B$6)*('CFR Example'!$B$9*1000)/1000000)*'Canada Fuel Prices'!I22/'CFR Example'!$B$3/'Canada Fuel Prices'!I27*100 -> 68.301854 | J6: =(('Canada Fuel Prices'!J23-'CFR Example'!$B$6)*('CFR Example'!$B$9*1000)/1000000)*'Canada Fuel Prices'!J22/'CFR Example'!$B$3/'Canada Fuel Prices'!J27*100 -> 69.780966 | K6: =(('Canada Fuel Prices'!K23-'CFR Example'!$B$6)*('CFR Example'!$B$9*1000)/1000000)*'Canada Fuel Prices'!K22/'CFR Example'!$B$3/'Canada Fuel Prices'!K27*100 -> 73.162774 | ... AF6: =(('Canada Fuel Prices'!AF23-'CFR Example'!$B$6)*('CFR Example'!$B$9*1000)/1000000)*'Canada Fuel Prices'!AF22/'CFR Example'!$B$3/'Canada Fuel Prices'!AF27*100 -> 76.858325
A7: CFR Blender Credit/Shortfall | C7: 0 | D7: =(('Canada Fuel Prices'!D23-'CFR Example'!$G$19)*('CFR Example'!$B$9*1000)/1000000)*'Canada Fuel Prices'!D22/'CFR Example'!$B$3/'Canada Fuel Prices'!D27*100 -> -1.2725288 | E7: =(('Canada Fuel Prices'!E23-'CFR Example'!$G$19)*('CFR Example'!$B$9*1000)/1000000)*'Canada Fuel Prices'!E22/'CFR Example'!$B$3/'Canada Fuel Prices'!E27*100 -> -2.0656292 | F7: =(('Canada Fuel Prices'!F23-'CFR Example'!$G$19)*('CFR Example'!$B$9*1000)/1000000)*'Canada Fuel Prices'!F22/'CFR Example'!$B$3/'Canada Fuel Prices'!F27*100 -> -3.7199912 | G7: =(('Canada Fuel Prices'!G23-'CFR Example'!$G$19)*('CFR Example'!$B$9*1000)/1000000)*'Canada Fuel Prices'!G22/'CFR Example'!$B$3/'Canada Fuel Prices'!G27*100 -> -5.5438379 | H7: =(('Canada Fuel Prices'!H23-'CFR Example'!$G$19)*('CFR Example'!$B$9*1000)/1000000)*'Canada Fuel Prices'!H22/'CFR Example'!$B$3/'Canada Fuel Prices'!H27*100 -> -8.4372731 | I7: =(('Canada Fuel Prices'!I23-'CFR Example'!$G$19)*('CFR Example'!$B$9*1000)/1000000)*'Canada Fuel Prices'!I22/'CFR Example'!$B$3/'Canada Fuel Prices'!I27*100 -> -11.18035 | J7: =(('Canada Fuel Prices'!J23-'CFR Example'!$G$19)*('CFR Example'!$B$9*1000)/1000000)*'Canada Fuel Prices'!J22/'CFR Example'!$B$3/'Canada Fuel Prices'!J27*100 -> -14.014065 | K7: =(('Canada Fuel Prices'!K23-'CFR Example'!$G$19)*('CFR Example'!$B$9*1000)/1000000)*'Canada Fuel Prices'!K22/'CFR Example'!$B$3/'Canada Fuel Prices'!K27*100 -> -17.589583 | ... AF7: =(('Canada Fuel Prices'!AF23-'CFR Example'!$G$19)*('CFR Example'!$B$9*1000)/1000000)*'Canada Fuel Prices'!AF22/'CFR Example'!$B$3/'Canada Fuel Prices'!AF27*100 -> -21.728161
A8: Total RD Value | B8: =SUM(B5:B6) -> #REF! | C8: =SUM(C5:C6) -> 365.60779 | D8: =SUM(D5:D7) -> 560.36981 | E8: =SUM(E5:E7) -> 466.82089 | F8: =SUM(F5:F7) -> 487.96293 | G8: =SUM(G5:G7) -> 458.36551 | H8: =SUM(H5:H7) -> 470.12414 | I8: =SUM(I5:I7) -> 484.33884 | J8: =SUM(J5:J7) -> 499.18205 | K8: =SUM(K5:K7) -> 513.25784 | ... AF8: =SUM(AF5:AF7) -> 735.34192
A9: Transport and Storage Fee | C9: -50 | D9: -50 | E9: -50 | F9: -50 | G9: -50 | H9: -50 | I9: -50 | J9: -50 | K9: -50 | L9: -50 | M9: -50 | N9: -50 | O9: -50 | P9: -50 | Q9: -50 | R9: -50 | S9: -50 | T9: -50 | U9: -50 | V9: -50 | W9: -50 | X9: -50 | Y9: -50 | Z9: -50 | AA9: -50 | AB9: -50 | AC9: -50 | AD9: -50 | AE9: -50 | AF9: -50
A10: RD Value versus Net Offtaker Costs | C10: =C8+C9 -> 315.60779 | D10: =D8+D9 -> 510.36981 | E10: =E8+E9 -> 416.82089 | F10: =F8+F9 -> 437.96293 | G10: =G8+G9 -> 408.36551 | H10: =H8+H9 -> 420.12414 | I10: =I8+I9 -> 434.33884 | J10: =J8+J9 -> 449.18205 | ... AF10: =AF8+AF9 -> 685.34192
A12: Jet Fuel Price | C12: 362.4 | D12: 378.6 | E12: 314.2 | F12: 312 | G12: 356.6 | H12: 427.1 | I12: 441.4 | J12: 457.8 | K12: 472.2 | L12: 487.5 | M12: 503.4 | N12: 517.6 | O12: 533.8 | P12: 549 | Q12: 515.3 | R12: 530.4 | S12: 546.1 | T12: 561.1 | U12: 576.4 | V12: 567.6 | W12: 583.3 | X12: 598.2 | Y12: 613.8 | Z12: 628.9 | AA12: 619 | AB12: 634.8 | AC12: 650.9 | AD12: 665 | AE12: 680.5 | AF12: 697.2
A13: Density Adjustment | C13: =C12*126.4/142.2-C12 -> -40.266667 | D13: =D12*126.4/142.2-D12 -> -42.066667 | E13: =E12*126.4/142.2-E12 -> -34.911111 | F13: =F12*126.4/142.2-F12 -> -34.666667 | G13: =G12*126.4/142.2-G12 -> -39.622222 | H13: =H12*126.4/142.2-H12 -> -47.455556 | I13: =I12*126.4/142.2-I12 -> -49.044444 | J13: =J12*126.4/142.2-J12 -> -50.866667 | ... AF13: =AF12*126.4/142.2-AF12 -> -77.466667
A14: SAF Stipulated Value | C14: =C12+C13 -> 322.13333 | D14: =D12+D13 -> 336.53333 | E14: =E12+E13 -> 279.28889 | F14: =F12+F13 -> 277.33333 | G14: =G12+G13 -> 316.97778 | H14: =H12+H13 -> 379.64444 | I14: =I12+I13 -> 392.35556 | J14: =J12+J13 -> 406.93333 | ... AF14: =AF12+AF13 -> 619.73333
A15: CFR / Equivalent Value | C15: 0 | D15: =(('Canada Fuel Prices'!D22-'CFR Example'!$B$6)*('CFR Example'!$B$9*1000)/1000000)*'Canada Fuel Prices'!D24/'CFR Example'!$B$3/'Canada Fuel Prices'!D27*100 -> 83.239085 | E15: =(('Canada Fuel Prices'!E22-'CFR Example'!$B$6)*('CFR Example'!$B$9*1000)/1000000)*'Canada Fuel Prices'!E24/'CFR Example'!$B$3/'Canada Fuel Prices'!E27*100 -> 69.363167 | F15: =(('Canada Fuel Prices'!F22-'CFR Example'!$B$6)*('CFR Example'!$B$9*1000)/1000000)*'Canada Fuel Prices'!F24/'CFR Example'!$B$3/'Canada Fuel Prices'!F27*100 -> 71.015534 | G15: =(('Canada Fuel Prices'!G22-'CFR Example'!$B$6)*('CFR Example'!$B$9*1000)/1000000)*'Canada Fuel Prices'!G24/'CFR Example'!$B$3/'Canada Fuel Prices'!G27*100 -> 75.020374 | H15: =(('Canada Fuel Prices'!H22-'CFR Example'!$B$6)*('CFR Example'!$B$9*1000)/1000000)*'Canada Fuel Prices'!H24/'CFR Example'!$B$3/'Canada Fuel Prices'!H27*100 -> 91.310284 | I15: =(('Canada Fuel Prices'!I22-'CFR Example'!$B$6)*('CFR Example'!$B$9*1000)/1000000)*'Canada Fuel Prices'!I24/'CFR Example'!$B$3/'Canada Fuel Prices'!I27*100 -> 100.32593 | J15: =(('Canada Fuel Prices'!J22-'CFR Example'!$B$6)*('CFR Example'!$B$9*1000)/1000000)*'Canada Fuel Prices'!J24/'CFR Example'!$B$3/'Canada Fuel Prices'!J27*100 -> 107.22881 | K15: =(('Canada Fuel Prices'!K22-'CFR Example'!$B$6)*('CFR Example'!$B$9*1000)/1000000)*'Canada Fuel Prices'!K24/'CFR Example'!$B$3/'Canada Fuel Prices'!K27*100 -> 118.30485 | ... AF15: =(('Canada Fuel Prices'!AF22-'CFR Example'!$B$6)*('CFR Example'!$B$9*1000)/1000000)*'Canada Fuel Prices'!AF24/'CFR Example'!$B$3/'Canada Fuel Prices'!AF27*100 -> 130.73195
A16: CFR Blender Credit/Shortfall | D16: =(('Canada Fuel Prices'!D22-'CFR Example'!$I$19)*('CFR Example'!$B$9*1000)/1000000)*'Canada Fuel Prices'!D24/'CFR Example'!$B$3/'Canada Fuel Prices'!D27*100 -> 40.638869 | E16: =(('Canada Fuel Prices'!E22-'CFR Example'!$I$19)*('CFR Example'!$B$9*1000)/1000000)*'Canada Fuel Prices'!E24/'CFR Example'!$B$3/'Canada Fuel Prices'!E27*100 -> 28.287657 | F16: =(('Canada Fuel Prices'!F22-'CFR Example'!$I$19)*('CFR Example'!$B$9*1000)/1000000)*'Canada Fuel Prices'!F24/'CFR Example'!$B$3/'Canada Fuel Prices'!F27*100 -> 30.221155 | G16: =(('Canada Fuel Prices'!G22-'CFR Example'!$I$19)*('CFR Example'!$B$9*1000)/1000000)*'Canada Fuel Prices'!G24/'CFR Example'!$B$3/'Canada Fuel Prices'!G27*100 -> 34.765181 | H16: =(('Canada Fuel Prices'!H22-'CFR Example'!$I$19)*('CFR Example'!$B$9*1000)/1000000)*'Canada Fuel Prices'!H24/'CFR Example'!$B$3/'Canada Fuel Prices'!H27*100 -> 50.147079 | I16: =(('Canada Fuel Prices'!I22-'CFR Example'!$I$19)*('CFR Example'!$B$9*1000)/1000000)*'Canada Fuel Prices'!I24/'CFR Example'!$B$3/'Canada Fuel Prices'!I27*100 -> 59.506955 | J16: =(('Canada Fuel Prices'!J22-'CFR Example'!$I$19)*('CFR Example'!$B$9*1000)/1000000)*'Canada Fuel Prices'!J24/'CFR Example'!$B$3/'Canada Fuel Prices'!J27*100 -> 66.473472 | K16: =(('Canada Fuel Prices'!K22-'CFR Example'!$I$19)*('CFR Example'!$B$9*1000)/1000000)*'Canada Fuel Prices'!K24/'CFR Example'!$B$3/'Canada Fuel Prices'!K27*100 -> 77.559257 | ... AF16: =(('Canada Fuel Prices'!AF22-'CFR Example'!$I$19)*('CFR Example'!$B$9*1000)/1000000)*'Canada Fuel Prices'!AF24/'CFR Example'!$B$3/'Canada Fuel Prices'!AF27*100 -> 89.927359
A17: SAF Market Premium | C17: 100 | D17: 100 | E17: 100 | F17: 100 | G17: 100 | H17: 100 | I17: 100 | J17: 100 | K17: 100 | L17: 100 | M17: 100 | N17: 100 | O17: 100 | P17: 100 | Q17: 100 | R17: 100 | S17: 100 | T17: 100 | U17: 100 | V17: 100 | W17: 100 | X17: 100 | Y17: 100 | Z17: 100 | AA17: 100 | AB17: 100 | AC17: 100 | AD17: 100 | AE17: 100 | AF17: 100
A18: Total SAF Value | C18: =SUM(C14:C17) -> 422.13333 | D18: =SUM(D14:D17) -> 560.41129 | E18: =SUM(E14:E17) -> 476.93971 | F18: =SUM(F14:F17) -> 478.57002 | G18: =SUM(G14:G17) -> 526.76333 | H18: =SUM(H14:H17) -> 621.10181 | I18: =SUM(I14:I17) -> 652.18844 | J18: =SUM(J14:J17) -> 680.63562 | ... AF18: =SUM(AF14:AF17) -> 940.39264
A19: Transport and Storage Fee | C19: -50 | D19: -50 | E19: -50 | F19: -50 | G19: -50 | H19: -50 | I19: -50 | J19: -50 | K19: -50 | L19: -50 | M19: -50 | N19: -50 | O19: -50 | P19: -50 | Q19: -50 | R19: -50 | S19: -50 | T19: -50 | U19: -50 | V19: -50 | W19: -50 | X19: -50 | Y19: -50 | Z19: -50 | AA19: -50 | AB19: -50 | AC19: -50 | AD19: -50 | AE19: -50 | AF19: -50
A20: SAF Value Net of Offtaker Costs | C20: =C18+C19 -> 372.13333 | D20: =D18+D19 -> 510.41129 | E20: =E18+E19 -> 426.93971 | F20: =F18+F19 -> 428.57002 | G20: =G18+G19 -> 476.76333 | H20: =H18+H19 -> 571.10181 | I20: =I18+I19 -> 602.18844 | J20: =J18+J19 -> 630.63562 | ... AF20: =AF18+AF19 -> 890.39264
A21: SAF - RD | C21: =C20-C10 -> 56.52554 | D21: =D20-D10 -> 0.041473282 | E21: =E20-E10 -> 10.118819 | F21: =F20-F10 -> -9.3929074 | G21: =G20-G10 -> 68.397823 | H21: =H20-H10 -> 150.97767 | I21: =I20-I10 -> 167.8496 | J21: =J20-J10 -> 181.45357 | ... AF21: =AF20-AF10 -> 205.05072
A22: CFR Credit Price | B22: 0 | C22: 0 | D22: 141.8 | E22: 127.3 | F22: 130.15 | G22: 136.8622 | H22: 156.24568 | I22: 169.34047 | J22: 178.8079 | K22: 193.70027 | L22: 211.70697 | M22: 209.80515 | N22: 206.66242 | O22: 205.58782 | P22: 208.54782 | Q22: 226.26267 | R22: 217.26021 | S22: 227.64044 | T22: 221.13204 | U22: 209.7275 | V22: 208.88585 | W22: 215.45881 | X22: 217.62777 | Y22: 224.06733 | Z22: 216.85432 | AA22: 221.31848 | AB22: 214.64799 | AC22: 218.99837 | AD22: 212.33588 | AE22: 216.58419 | AF22: 210.11708
A23: CFR Diesel Compliance Standard | B23: 92.91625 | C23: 91.660625 | D23: 90.405 | E23: 89.5 | F23: 88 | G23: 86.5 | H23: =G23-1.5 -> 85 | I23: =H23-1.5 -> 83.5 | J23: =I23-1.5 -> 82 | K23: =J23-1.5 -> 80.5 | L23: =K23-1.5 -> 79 | M23: =L23 -> 79 | N23: =M23 -> 79 | O23: =N23 -> 79 | P23: =O23 -> 79 | Q23: =P23 -> 79 | R23: =Q23 -> 79 | S23: =R23 -> 79 | T23: =S23 -> 79 | ... AF23: =AE23 -> 79
A24: CFR SAF Compliance Standard | D24: 89.8 | E24: 89.8 | F24: 89.8 | G24: 89.8 | H24: 89.8 | I24: 89.8 | J24: 89.8 | K24: 89.8 | L24: 89.8 | M24: 89.8 | N24: 89.8 | O24: 89.8 | P24: 89.8 | Q24: 89.8 | R24: 89.8 | S24: 89.8 | T24: 89.8 | U24: 89.8 | V24: 89.8 | W24: 89.8 | X24: 89.8 | Y24: 89.8 | Z24: 89.8 | AA24: 89.8 | AB24: 89.8 | AC24: 89.8 | AD24: 89.8 | AE24: 89.8 | AF24: 89.8
A25: HOBO Target Post-Blend CI
A26: CFR Compliance Deficits
A27: U$/C$ Average Rate | D27: 1.3012 | E27: 1.3495 | F27: 1.3588 | G27: 1.377 | H27: 1.346625 | I27: 1.3579812 | J27: 1.3601016 | K27: 1.360427 | L27: 1.3562837 | M27: 1.3586984 | N27: 1.3588776 | O27: 1.3585717 | P27: 1.3581078 | Q27: 1.3585639 | R27: 1.3585303 | S27: 1.3584434 | T27: 1.3584113 | U27: 1.3584872 | V27: 1.3584681 | W27: 1.3584525 | X27: 1.3584548 | Y27: 1.3584656 | Z27: 1.3584602 | AA27: 1.3584583 | AB27: 1.3584597 | AC27: 1.358461 | AD27: 1.3584598 | AE27: 1.3584597 | AF27: 1.3584601
A28: RIN Price | B28: 63.756698 | C28: 149.18311 | D28: 166.4565 | E28: 134.65752 | F28: 58.821842 | G28: 74.801035 | H28: 77.599466 | I28: 80.500404 | J28: 87.524932 | K28: 95.890021 | L28: 95.633568 | M28: 100.12276 | N28: 100.42462 | O28: 100.93658 | P28: 98.069245 | Q28: 97.652846 | R28: 93.1 | S28: 92.9 | T28: 91.1 | U28: 88.3 | V28: 89.1 | W28: 92.7 | X28: 87.1 | Y28: 88.1 | Z28: 82.8 | AA28: 86.2 | AB28: 81 | AC28: 84.3 | AD28: 79.2 | AE28: 82.4 | AF28: 77.5
A29: RD RIN Stipulated Value | B29: =B28*1.7 -> 108.38639 | C29: =C28*1.7 -> 253.61129 | D29: =D28*1.7 -> 282.97606 | E29: =E28*1.7 -> 228.91778 | F29: =F28*1.7 -> 99.997132 | G29: =G28*1.7 -> 127.16176 | H29: =H28*1.7 -> 131.91909 | I29: =I28*1.7 -> 136.85069 | ... AF29: =AF28*1.7 -> 131.75
A30: SAF RIN Stipulated Value | C30: =C28*1.6 -> 238.69297 | D30: =D28*1.6 -> 266.33041 | E30: =E28*1.6 -> 215.45203 | F30: =F28*1.6 -> 94.114948 | G30: =G28*1.6 -> 119.68166 | H30: =H28*1.6 -> 124.15915 | I30: =I28*1.6 -> 128.80065 | J30: =J28*1.6 -> 140.03989 | ... AF30: =AF28*1.6 -> 124

Sheet Comparison
A1: RD Price | B1: Chicago | C1: California | D1: Canada | E1: RD Value | F1: Chicago | G1: California | H1: Canada | I1: SAF Price | J1: Chicago | K1: California | L1: Canada | M1: SAF Value | N1: Chicago | O1: California | P1: Canada | Q1: ULSD | R1: Chicago | S1: California | T1: Canada | U1: Jet | V1: Chicago | W1: California | X1: Canada | Y1: SAF - RD Value | Z1: Chicago | AA1: California | AB1: Canada
A2: 2021 | B2: 325.97111 | C2: 387.56458 | D2: 365.60779 | F2: 679.58239 | G2: 892.90336 | H2: 365.60779 | J2: 200.05657 | K2: 165.15556 | L2: 322.13333 | N2: 538.74954 | O2: 831.59591 | P2: 622.13333 | R2: 320.8 | S2: 384.68333 | T2: 379.2 | V2: 225.06364 | W2: 185.8 | X2: 362.4 | Z2: =N2-F2 -> -140.83285 | AA2: =O2-G2 -> -61.307452 | AB2: =P2-H2 -> 256.52554
A3: 2022 | B3: 494.42721 | C3: 563.62144 | D3: 493.45482 | F3: 877.40327 | G3: 1027.7695 | H3: 560.36981 | J3: 251.02222 | K3: 299.91111 | L3: 336.53333 | N3: 617.35263 | O3: 935.72547 | P3: 760.41129 | R3: 490.71667 | S3: 562.48333 | T3: 511.8 | V3: 282.4 | W3: 337.4 | X3: 378.6 | Z3: =N3-F3 -> -260.05064 | AA3: =O3-G3 -> -92.044022 | AB3: =P3-H3 -> 200.04147
A4: 2023 | B4: 424.43771 | C4: 504.318 | D4: 410.81392 | F4: 753.35549 | G4: 890.53585 | H4: 466.80813 | J4: 436.19259 | K4: 239.91111 | L4: 279.25809 | N4: 1041.6446 | O4: 945.28445 | P4: 676.90892 | R4: 411.425 | S4: 494.275 | T4: 426.08676 | V4: 490.71667 | W4: 269.9 | X4: 314.16535 | Z4: =N4-F4 -> 288.28913 | AA4: =O4-G4 -> 54.748597 | AB4: =P4-H4 -> 210.10079
A5: 2024 | B5: 388.56884 | C5: 457.80324 | D5: 434.32492 | F5: 588.56597 | G5: 703.47768 | H5: 487.93577 | J5: 365.71111 | K5: 276.17778 | L5: 277.34677 | N5: 849.82606 | O5: 850.84292 | P5: 678.58346 | R5: 369.825 | S5: 441.63333 | T5: 450.47183 | V5: 411.425 | W5: 310.7 | X5: 312.01512 | Z5: =N5-F5 -> 261.26009 | AA5: =O5-G5 -> 147.36524 | AB5: =P5-H5 -> 190.64769
A6: 2025 | B6: 463.41538 | C6: 533.26845 | D6: 406.05522 | F6: 655.57714 | G6: 854.88615 | H6: 458.3184 | J6: 328.73333 | K6: 294.75556 | L6: 405.87876 | N6: 838.41499 | O6: 903.76171 | P6: 815.66431 | R6: 354.275 | S6: 426.725 | T6: 421.15114 | V6: 369.825 | W6: 331.6 | X6: 456.6136 | Z6: =N6-F6 -> 182.83785 | AA6: =O6-G6 -> 48.875559 | AB6: =P6-H6 -> 357.34591
A7: 2026 | B7: 289.13642 | C7: 350.33137 | D7: 429.16493 | F7: 486.05551 | G7: 681.02841 | H7: 486.24482 | J7: 203.82222 | K7: 283.91111 | L7: 283.91111 | N7: 717.98137 | O7: 902.46821 | P7: 725.36847 | R7: 172.16 | S7: 235.63 | T7: 445.12 | V7: 229.3 | W7: 319.4 | X7: 319.4 | Z7: =N7-F7 -> 231.92586 | AA7: =O7-G7 -> 221.43979 | AB7: =P7-H7 -> 239.12365
A8: 2027 | B8: 277.6754 | C8: 339.72846 | D8: 436.94566 | F8: 479.52609 | G8: 673.9623 | H8: 494.06717 | J8: 200.56889 | K8: 279.37778 | L8: 279.37778 | N8: 719.36953 | O8: 902.52864 | P8: 739.21066 | R8: 175.27 | S8: 239.63 | T8: 453.19 | V8: 225.64 | W8: 314.3 | X8: 314.3 | Z8: =N8-F8 -> 239.84344 | AA8: =O8-G8 -> 228.56633 | AB8: =P8-H8 -> 245.14349
A9: 2028 | B9: 279.70052 | C9: 342.48633 | D9: 445.92195 | F9: 493.4929 | G9: 689.69654 | H9: 501.68885 | J9: 197.06667 | K9: 274.48889 | L9: 274.48889 | N9: 727.10656 | O9: 911.25619 | P9: 748.19117 | R9: 178.86 | S9: 243.98 | T9: 462.5 | V9: 221.7 | W9: 308.8 | X9: 308.8 | Z9: =N9-F9 -> 233.61365 | AA9: =O9-G9 -> 221.55965 | AB9: =P9-H9 -> 246.50232
A10: 2029 | B10: 290.77847 | C10: 355.09729 | D10: 454.45473 | F10: 518.79151 | G10: 723.93282 | H10: 510.02792 | J10: 219.73333 | K10: 306.13333 | L10: 306.13333 | N10: 763.15737 | O10: 965.22232 | P10: 801.99744 | R10: 182.28 | S10: 248.99 | T10: 471.35 | V10: 247.2 | W10: 344.4 | X10: 344.4 | Z10: =N10-F10 -> 244.36586 | AA10: =O10-G10 -> 241.2895 | AB10: =P10-H10 -> 291.96952
A11: 2030 | B11: 325.28114 | C11: 390.89193 | D11: 463.02607 | F11: 552.85821 | G11: 751.64076 | H11: 518.66252 | J11: 215.84889 | K11: 300.71111 | L11: 300.71111 | N11: 758.8626 | O11: 953.48077 | P11: 824.10214 | R11: 185.7 | S11: 253.75 | T11: 480.24 | V11: 242.83 | W11: 338.3 | X11: 338.3 | Z11: =N11-F11 -> 206.00439 | AA11: =O11-G11 -> 201.84001 | AB11: =P11-H11 -> 305.43962
A12: 2031 | B12: 324.84163 | C12: 391.76367 | D12: 471.60706 | F12: 560.05033 | G12: 755.08978 | H12: 526.64572 | J12: 212.54222 | K12: 296.08889 | L12: 296.08889 | N12: 762.73865 | O12: 952.5421 | P12: 816.24384 | R12: 189.13 | S12: 258.54 | T12: 489.14 | V12: 239.11 | W12: 333.1 | X12: 333.1 | Z12: =N12-F12 -> 202.68832 | AA12: =O12-G12 -> 197.45232 | AB12: =P12-H12 -> 289.59811
A13: 2032 | B13: 308.67267 | C13: 376.90596 | D13: 480.1784 | F13: 544.39452 | G13: 736.88071 | H13: 534.38547 | J13: 210.69333 | K13: 293.51111 | L13: 293.51111 | N13: 761.37272 | O13: 948.0929 | P13: 808.94611 | R13: 192.56 | S13: 263.33 | T13: 498.03 | V13: 237.03 | W13: 330.2 | X13: 330.2 | Z13: =N13-F13 -> 216.9782 | AA13: =O13-G13 -> 211.21219 | AB13: =P13-H13 -> 274.56064
... A31: 2050 | B31: 413.60272 | C31: 505.39997 | D31: 634.52042 | F31: 610.35272 | G31: 779.39272 | H31: 689.65059 | J31: 175.54667 | K31: 251.46667 | L31: 251.46667 | N31: 689.54667 | O31: 856.34428 | P31: 772.12597 | R31: 254.3 | S31: 349.51 | T31: 658.11 | V31: 197.49 | W31: 282.9 | X31: 282.9 | Z31: =N31-F31 -> 79.193949 | AA31: =O31-G31 -> 76.951561 | AB31: =P31-H31 -> 82.475383
A55: =A3 -> 2022 | B55: =B3-B2 -> 168.4561 | C55: =C3-C2 -> 176.05686 | D55: =D3-D2 -> 127.84703
A56: =A4 -> 2023 | B56: =B4-B3 -> -69.989502 | C56: =C4-C3 -> -59.303445 | D56: =D4-D3 -> -82.640898
A57: =A5 -> 2024 | B57: =B5-B4 -> -35.868872 | C57: =C5-C4 -> -46.514756 | D57: =D5-D4 -> 23.510999
A58: =A6 -> 2025 | B58: =B6-B5 -> 74.846544 | C58: =C6-C5 -> 75.465211 | D58: =D6-D5 -> -28.269706
A59: =A7 -> 2026 | B59: =B7-B6 -> -174.27896 | C59: =C7-C6 -> -182.93708 | D59: =D7-D6 -> 23.109711
A60: =A8 -> 2027 | B60: =B8-B7 -> -11.461015 | C60: =C8-C7 -> -10.602917 | D60: =D8-D7 -> 7.7807355
A61: =A9 -> 2028 | B61: =B9-B8 -> 2.0251163 | C61: =C9-C8 -> 2.7578745 | D61: =D9-D8 -> 8.9762884
A62: =A10 -> 2029 | B62: =B10-B9 -> 11.077954 | C62: =C10-C9 -> 12.610961 | D62: =D10-D9 -> 8.5327768
A63: =A11 -> 2030 | B63: =B11-B10 -> 34.502669 | C63: =C11-C10 -> 35.794637 | D63: =D11-D10 -> 8.5713431
A64: =A12 -> 2031 | B64: =B12-B11 -> -0.43951253 | C64: =C12-C11 -> 0.87173905 | D64: =D12-D11 -> 8.5809846
A65: =A13 -> 2032 | B65: =B13-B12 -> -16.168961 | C65: =C13-C12 -> -14.85771 | D65: =D13-D12 -> 8.5713431
A66: =A14 -> 2033 | B66: =B14-B13 -> 24.548286 | C66: =C14-C13 -> 25.859538 | D66: =D14-D13 -> 8.5713431
... A83: =A31 -> 2050 | B83: =B31-B30 -> -10.750235 | C83: =C31-C30 -> -9.4486254 | D83: =D31-D30 -> 8.5713431

Sheet CFR Example
A1: Assumptions
A2: gallons per tonne | E2: Blended Fuel CI
A3: RD | B3: 317 | E3: Diesel CI | G3: 93
A4: SAF | B4: 330 | E4: RD CI | G4: =B6 -> 35
A5: CI Scores of Feedstock Mix | E5: Jet Fuel CI | G5: 89.8
A6: RD | B6: 35 | E6: SAF CI | G6: =B7 -> 35
A7: SAF | B7: 35
A8: Energy Density | E8: Blend Rates
A9: RD | B9: 35.8 | C9: MJ/L | E9: RD | F9: =[1]Diesel!J$12 -> 0.026914156 | G9: 2023 Rate
A10: SAF | B10: 33.7 | E10: SAF | F10: ='[1]Jet Fuel'!$H$15 -> 0.0025866024 | G10: 2024 Rate
A11: 2023 Avg CFR price | B11: 127.3 | C11: C$/tonne reduction
A12: Carbon Reduction Target
A13: 2023
A14: RD | B14: 89.5
A15: SAF | B15: 89.8
A17: Calculation Steps | B17: RD | D17: SAF | G17: RD | I17: SAF
A18: Target CI | B18: =B14 -> 89.5 | D18: =B15 -> 89.8 | F18: =A18 -> Target CI | G18: =B14 -> 89.5 | I18: =B15 -> 89.8
A19: RD CI | B19: =B6 -> 35 | C19: Subtract fuel CI from target | D19: =B7 -> 35 | F19: Blend CI | G19: =(G4*F9)+(G3*(1-F9)) -> 91.438979 | H19: =C19 -> Subtract fuel CI from target | I19: =(G6*F10)+(G5*(1-F10)) -> 89.658254
A20: Carbon reduction beyond target | B20: =B18-B19 -> 54.5 | C20: gCO2e/MJ | D20: =D18-D19 -> 54.8 | F20: =A20 -> Carbon reduction beyond target | G20: =G18-G19 -> -1.9389789 | H20: =C20 -> gCO2e/MJ | I20: =I18-I19 -> 0.14174581
A21: Multiply by energy density converted to MJ/m3 | B21: =B9*1000 -> 35800 | D21: =B10*1000 -> 33700 | F21: =A21 -> Multiply by energy density converted to MJ/m3 | G21: =B9*1000 -> 35800 | I21: =B10*1000 -> 33700
B22: =B20*B21 -> 1951100 | C22: MJ/m3 | D22: =D20*D21 -> 1846760 | G22: =G20*G21 -> -69415.446 | H22: =C22 -> MJ/m3 | I22: =I20*I21 -> 4776.8339
A23: Divide by 1,000,000 to convert from grams of reduction to tonnes | B23: =B22/1000000 -> 1.9511 | C23: tonnes of carbon reduction | D23: =D22/1000000 -> 1.84676 | F23: =A23 -> Divide by 1,000,000 to convert from grams of reduction to tonnes | G23: =G22/1000000 -> -0.069415446 | H23: =C23 -> tonnes of carbon reduction | I23: =I22/1000000 -> 0.0047768339
A24: Multiply by average price | B24: =B11 -> 127.3 | C24: C$/tonne | D24: =B11 -> 127.3 | F24: =A24 -> Multiply by average price | G24: =B11 -> 127.3 | H24: =C24 -> C$/tonne | I24: =B11 -> 127.3
A25: CFR Credit Value | B25: =B11*B23 -> 248.37503 | C25: C$/tonne | D25: =D24*D23 -> 235.09255 | F25: =A25 -> CFR Credit Value | G25: =G24*G23 -> -8.8365863 | H25: =C25 -> C$/tonne | I25: =I24*I23 -> 0.60809096
A26: Convert to C$/gal | B26: =B3 -> 317 | C26: tonnes per gallon | D26: =B4 -> 330 | F26: =A26 -> Convert to C$/gal | G26: =B3 -> 317 | H26: =C26 -> tonnes per gallon | I26: =B4 -> 330
A27: C$/gal | B27: =B25/B26 -> 0.78351744 | C27: C$/gal | D27: =D25/D26 -> 0.71240166 | F27: =A27 -> C$/gal | G27: =G25/G26 -> -0.027875666 | H27: =C27 -> C$/gal | I27: =I25/I26 -> 0.0018426999
A28: U$/C$ | B28: 1.3495 | C28: U$/C$ | D28: 1.3495 | F28: =A28 -> U$/C$ | G28: 1.3495 | I28: 1.3495
A29: U$/gal | B29: =B27*B28 -> 1.0573568 | C29: U$/gal | D29: =D27*D28 -> 0.96138604 | F29: =A29 -> U$/gal | G29: =G27*G28 -> -0.037618212 | I29: =I27*I28 -> 0.0024867235

Sheet CI Score Assumption
A2: Blended CI based on Feedstock Mix Assumptions and Average of Approved CI scores under LCFS
A3: DCO CI Avg | B3: 37.676111 | C3: =B3*D3/100 -> 11.302833 | D3: 30
A4: UCO CI Avg | B4: 24.987143 | C4: =B4*D4/100 -> 7.4961429 | D4: 30
A5: Tallow CI Avg | B5: 36.087797 | C5: =B5*D5/100 -> 7.2175593 | D5: 20
A6: CWG CI Avg | B6: 43.91 | C6: =B6*D6/100 -> 8.782 | D6: 20
C7: =SUM(C3:C6) -> 34.798536
A8: Blended CI based on Feedstock Mix Assumptions and Max of Approved CI scores under LCFS
A9: DCO CI Max | B9: 78.6 | C9: =B9*D9/100 -> 23.58 | D9: 30
A10: UCO CI Max | B10: 35.72 | C10: =B10*D10/100 -> 10.716 | D10: 30
A11: Tallow CI Max | B11: 51.9 | C11: =B11*D11/100 -> 10.38 | D11: 20
A12: CWG CI Max | B12: 51.9 | C12: =B12*D12/100 -> 10.38 | D12: 20
C13: =SUM(C9:C12) -> 55.056
A14: Blended CI based on Feedstock Mix Assumptions and Min of Approved CI scores under LCFS
A15: DCO CI Min | B15: 25.46 | C15: =B15*D15/100 -> 7.638 | D15: 30
A16: UCO CI Min | B16: 17.92 | C16: =B16*D16/100 -> 5.376 | D16: 30
A17: Tallow CI Min | B17: 15.64 | C17: =B17*D17/100 -> 3.128 | D17: 20
A18: CWG CI Min | B18: 38.75 | C18: =B18*D18/100 -> 7.75 | D18: 20
C19: =SUM(C15:C18) -> 23.892
