Workbook

Sheet Data Sources
A2: Data Series and Source | B2: Link | C2: Web Page
A3: EIA - Short-Term Energy Outlook - Biofuel Data | B3: Selected Data Table | C3: https://www.eia.gov/outlooks/steo/data/browser | G3: Where is this data used/input
A4: EIA - Monthly Energy Review | B4: Production and Consumption by Source | C4: https://www.eia.gov/totalenergy/data/monthly/ | G4: Table 10.1 Renewable Energy Production
A5: EIA - Stocks | B5: Petroleum & Other Liquids Data | C5: https://www.eia.gov/dnav/pet/pet_stoc_typ_d_nus_SAE_mbbl_m.htm | G5: Where is this data used/input
A6: EIA - Biodiesel Data | B6: Biodiesel Overview | C6: https://www.eia.gov/totalenergy/data/monthly/ | G6: Table 10.4a Biodiesel Overview
A7: EIA - Renewable Diesel Data | B7: Renewable Diesel Overview | C7: https://www.eia.gov/totalenergy/data/monthly/ | G7: Table 10.4b Renewable Dieserl Fuel Overview
A8: EIA - Other Biofuels Data | B8: Other Biofuels Overview | C8: https://www.eia.gov/totalenergy/data/monthly/ | G8: Table 10.4c Other Biofuels Overview
A9: EIA - Residential & Commercial Renewable Energy Consumption | B9: Consumption: residential and commercial sectors | C9: https://www.eia.gov/totalenergy/data/monthly/ | G9: Table 10.2a Renewable Energy Consumption Residential and Commercial Sectors
A10: EIA - Transportation & Electric Power Renewable Energy Consumption | B10: Consumption: transportation and electric power sectors | C10: https://www.eia.gov/totalenergy/data/monthly/ | G10: Table 10.2c Renewable Energy Consumption Transportation and Electric Power Sectors
A11: for Diesel data - See html links in the data entry spreadsheet
A12: Jet SAF Prices | C12: Webpage location for data
A13: RIN prices | C13: Location for data
A14: monthly_data columns CL and CM where does this data come from? These are included in the supply demand for Diesel
A19: Notes:
B20: Calculated field
B21: Table 10.1 Renewable Energy Production and Consumption by Source - first and last columns highlighted for this file
B22: Table 10.4a Biodiesel Overview - first and last columns highlighted for this file
B23: Table 10.4b Renewable Diesel Fuel Overview - first and last columns highlighted for this file
B24: Table 10.4c Other Biofuels Overview - first and last columns highlighted for this file
B25: Table 10.2a Renewable Energy Consumption Residential and Commercial Sectors - first and last columns highlighted for this file
B26: Table 10.2c Renewable Energy Consumption Transportation and Electric Power Sectors - first and last columns highlighted for this file
A27: Data being pulled from another workbook | B27: Data being pulled from another workbook

Sheet Graph Dashboard

Sheet annual_data
A1: Annual Total | B1: Biodiesel Feedstock | C1: Biodiesel Losses and Co-products | D1: Biodiesel Losses and Co-products | E1: Biodiesel Production | F1: Biodiesel Production | G1: Biodiesel Production | H1: Biodiesel Imports | I1: Biodiesel Exports | J1: Biodiesel Net Imports | K1: Biodiesel Stocks | L1: Biodiesel Stock Change | M1: Biodiesel Consumption | N1: Biodiesel Consumption | O1: Biodiesel Consumption | P1: Wood Energy Production | Q1: Biofuels Production | R1: Total Biomass Energy Production | S1: Total Renewable Energy Production | T1: Hydroelectric Power Consumption | U1: Geothermal Energy Consumption | V1: Solar Energy Consumption | W1: Wind Energy Consumption | X1: Wood Energy Consumption | Y1: Waste Energy Consumption | Z1: Biofuels Consumption | AA1: Total Biomass Energy Consumption | AB1: Total Renewable Energy Consumption | AC1: Renewable Diesel Fuel Production | AD1: Renewable Diesel Fuel Production | AE1: Renewable Diesel Fuel Production | AF1: Renewable Diesel Fuel Imports | AG1: Renewable Diesel Fuel Stocks | AH1: Renewable Diesel Fuel Stock Change | AI1: Renewable Diesel Fuel Consumption | AJ1: Renewable Diesel Fuel Consumption | AK1: Renewable Diesel Fuel Consumption | AL1: Other Biofuels Feedstock | AM1: Other Biofuels Losses and Co-products | AN1: Other Biofuels Production | AO1: Other Biofuels Production | AP1: Other Biofuels Production | AQ1: Other Biofuels Imports | AR1: Other Biofuels Stocks | AS1: Other Biofuels Stock Change | AT1: Other Biofuels Consumption | AU1: Other Biofuels Consumption | AV1: Other Biofuels Consumption | AW1: Geothermal Energy Consumed by the Residential Sector | AX1: Solar Energy Consumed by the Residential Sector | AY1: Wood Energy Consumed by the Residential Sector | AZ1: Total Renewable Energy Consumed by the Residential Sector | BA1: Hydroelectric Power Consumed by the Commercial Sector | BB1: Geothermal Energy Consumed by the Commercial Sector | BC1: Solar Energy Consumed by the Commercial Sector | BD1: Wind Energy Consumed by the Commercial Sector | BE1: Wood Energy Consumed by the Commercial Sector | BF1: Waste Energy Consumed by the Commercial Sector | BG1: Fuel Ethanol, Excluding Denaturant, Consumed by the Commercial Sector | BH1: Biomass Energy Consumed by the Commercial Sector | BI1: Total Renewable Energy Consumed by the Commercial Sector | BJ1: Fuel Ethanol, Excluding Denaturant, Consumed by the Transportation Sector | BK1: Biodiesel Consumed by the Transportation Sector | BL1: Renewable Diesel Fuel Consumed by the Transportation Sector | BM1: Other Biofuels Consumed by the Transportation Sector | BN1: Biomass Energy Consumed by the Transportation Sector | BO1: Conventional Hydroelectric Power Consumed by the Electric Power Sector | BP1: Geothermal Energy Consumed by the Electric Power Sector | BQ1: Solar Energy Consumed by the Electric Power Sector | BR1: Wind Energy Consumed by the Electric Power Sector | BS1: Wood Energy Consumed by the Electric Power Sector | BT1: Waste Energy Consumed by the Electric Power Sector | BU1: Biomass Energy Consumed by the Electric Power Sector | BV1: Total Renewable Energy Consumed by the Electric Power Sector | BW1: U.S. Refinery and Blender Net Production of Distillate Fuel Oil Thousand Barrels | BX1: U.S. Imports of Distillate Fuel Oil Thousand Barrels | BY1: U.S. Product Supplied of Distillate Fuel Oil Thousand Barrels | BZ1: U.S. Ending Stocks of Distillate Fuel Oil Thousand Barrels | CA1: Distillate Fuel Oil Refinery and Blender Net Production | CB1: Distillate Fuel Oil Imports | CC1: Distillate Fuel Oil Product Supplied | CD1: Distillate Fuel Oil Stocks
B2: (Trillion Btu) | C2: (Trillion Btu) | D2: (Thousand Barrels) | E2: (Thousand Barrels) | F2: (Million Gallons) | G2: (Trillion Btu) | H2: (Thousand Barrels) | I2: (Thousand Barrels) | J2: (Thousand Barrels) | K2: (Thousand Barrels) | L2: (Thousand Barrels) | M2: (Thousand Barrels) | N2: (Million Gallons) | O2: (Trillion Btu) | P2: (Trillion Btu) | Q2: (Trillion Btu) | R2: (Trillion Btu) | S2: (Trillion Btu) | T2: (Trillion Btu) | U2: (Trillion Btu) | V2: (Trillion Btu) | W2: (Trillion Btu) | X2: (Trillion Btu) | Y2: (Trillion Btu) | Z2: (Trillion Btu) | AA2: (Trillion Btu) | AB2: (Trillion Btu) | AC2: (Thousand Barrels) | AD2: (Million Gallons) | AE2: (Trillion Btu) | AF2: (Thousand Barrels) | AG2: (Thousand Barrels) | AH2: (Thousand Barrels) | AI2: (Thousand Barrels) | AJ2: (Million Gallons) | AK2: (Trillion Btu) | AL2: (Trillion Btu) | AM2: (Trillion Btu) | AN2: (Thousand Barrels) | AO2: (Million Gallons) | AP2: (Trillion Btu) | AQ2: (Thousand Barrels) | AR2: (Thousand Barrels) | AS2: (Thousand Barrels) | AT2: (Thousand Barrels) | AU2: (Million Gallons) | AV2: (Trillion Btu) | AW2: (Trillion Btu) | AX2: (Trillion Btu) | AY2: (Trillion Btu) | AZ2: (Trillion Btu) | BA2: (Trillion Btu) | BB2: (Trillion Btu) | BC2: (Trillion Btu) | BD2: (Trillion Btu) | BE2: (Trillion Btu) | BF2: (Trillion Btu) | BG2: (Trillion Btu) | BH2: (Trillion Btu) | BI2: (Trillion Btu) | BJ2: (Trillion Btu) | BK2: (Trillion Btu) | BL2: (Trillion Btu) | BM2: (Trillion Btu) | BN2: (Trillion Btu) | BO2: (Trillion Btu) | BP2: (Trillion Btu) | BQ2: (Trillion Btu) | BR2: (Trillion Btu) | BS2: (Trillion Btu) | BT2: (Trillion Btu) | BU2: (Trillion Btu) | BV2: (Trillion Btu) | BW2: https://www.eia.gov/dnav/pet/hist/LeafHandler.ashx?n=pet&s=mdirpus1&f=a | BX2: https://www.eia.gov/dnav/pet/hist/LeafHandler.ashx?n=pet&s=mdiimus1&f=a | BY2: https://www.eia.gov/dnav/pet/hist/LeafHandler.ashx?n=pet&s=mdiupus1&f=a | BZ2: https://www.eia.gov/dnav/pet/hist/LeafHandler.ashx?n=pet&s=mdistus1&f=a | CA2: (Million gallons) | CB2: (Million gallons) | CC2: (Million gallons) | CD2: (Million gallons)
A3: 1949 | P3: 1549.262 | Q3: Not Available | R3: 1549.262 | S3: 2973.984 | T3: 1424.722 | U3: Not Available | V3: Not Available | W3: Not Available | X3: 1549.262 | Y3: Not Available | Z3: Not Available | AA3: 1549.262 | AB3: 2973.984 | AW3: Not Available | AX3: Not Available | AY3: 1055.186 | AZ3: 1055.186 | BA3: Not Available | BB3: Not Available | BC3: Not Available | BD3: Not Available | BE3: 19.986 | BF3: Not Available | BG3: Not Available | BH3: 19.986 | BI3: 19.986 | BJ3: Not Available | BK3: Not Available | BL3: Not Available | BM3: Not Available | BN3: Not Available | BO3: 1349.185 | BP3: Not Available | BQ3: Not Available | BR3: Not Available | BS3: 5.803 | BT3: Not Available | BU3: 5.803 | BV3: 1354.988 | BW3: 340825 | BX3: 1825 | BY3: 329278 | BZ3: 75207 | CA3: =BW3*42/1000 -> 14314.65 | CB3: =BX3*42/1000 -> 76.65 | CC3: =BY3*42/1000 -> 13829.676 | CD3: =BZ3*42/1000 -> 3158.694
A4: 1950 | P4: 1562.307 | Q4: Not Available | R4: 1562.307 | S4: 2977.718 | T4: 1415.411 | U4: Not Available | V4: Not Available | W4: Not Available | X4: 1562.307 | Y4: Not Available | Z4: Not Available | AA4: 1562.307 | AB4: 2977.718 | AW4: Not Available | AX4: Not Available | AY4: 1005.529 | AZ4: 1005.529 | BA4: Not Available | BB4: Not Available | BC4: Not Available | BD4: Not Available | BE4: 19.075 | BF4: Not Available | BG4: Not Available | BH4: 19.075 | BI4: 19.075 | BJ4: Not Available | BK4: Not Available | BL4: Not Available | BM4: Not Available | BN4: Not Available | BO4: 1346.015 | BP4: Not Available | BQ4: Not Available | BR4: Not Available | BS4: 5.466 | BT4: Not Available | BU4: 5.466 | BV4: 1351.481 | BW4: 398912 | BX4: 2340 | BY4: 394715 | BZ4: 71948 | CA4: =BW4*42/1000 -> 16754.304 | CB4: =BX4*42/1000 -> 98.28 | CC4: =BY4*42/1000 -> 16578.03 | CD4: =BZ4*42/1000 -> 3021.816
A5: 1951 | P5: 1534.669 | Q5: Not Available | R5: 1534.669 | S5: 2958.464 | T5: 1423.795 | U5: Not Available | V5: Not Available | W5: Not Available | X5: 1534.669 | Y5: Not Available | Z5: Not Available | AA5: 1534.669 | AB5: 2958.464 | AW5: Not Available | AX5: Not Available | AY5: 958.212 | AZ5: 958.212 | BA5: Not Available | BB5: Not Available | BC5: Not Available | BD5: Not Available | BE5: 18.198 | BF5: Not Available | BG5: Not Available | BH5: 18.198 | BI5: 18.198 | BJ5: Not Available | BK5: Not Available | BL5: Not Available | BM5: Not Available | BN5: Not Available | BO5: 1360.698 | BP5: Not Available | BQ5: Not Available | BR5: Not Available | BS5: 5.331 | BT5: Not Available | BU5: 5.331 | BV5: 1366.029 | BW5: 475801 | BX5: 1767 | BY5: 449102 | BZ5: 80722 | CA5: =BW5*42/1000 -> 19983.642 | CB5: =BX5*42/1000 -> 74.214 | CC5: =BY5*42/1000 -> 18862.284 | CD5: =BZ5*42/1000 -> 3390.324
A6: 1952 | P6: 1474.369 | Q6: Not Available | R6: 1474.369 | S6: 2940.181 | T6: 1465.812 | U6: Not Available | V6: Not Available | W6: Not Available | X6: 1474.369 | Y6: Not Available | Z6: Not Available | AA6: 1474.369 | AB6: 2940.181 | AW6: Not Available | AX6: Not Available | AY6: 899.164 | AZ6: 899.164 | BA6: Not Available | BB6: Not Available | BC6: Not Available | BD6: Not Available | BE6: 17.114 | BF6: Not Available | BG6: Not Available | BH6: 17.114 | BI6: 17.114 | BJ6: Not Available | BK6: Not Available | BL6: Not Available | BM6: Not Available | BN6: Not Available | BO6: 1404.274 | BP6: Not Available | BQ6: Not Available | BR6: Not Available | BS6: 6.435 | BT6: Not Available | BU6: 6.435 | BV6: 1410.709 | BW6: 521264 | BX6: 2674 | BY6: 479764 | BZ6: 99582 | CA6: =BW6*42/1000 -> 21893.088 | CB6: =BX6*42/1000 -> 112.308 | CC6: =BY6*42/1000 -> 20150.088 | CD6: =BZ6*42/1000 -> 4182.444
A7: 1953 | P7: 1418.601 | Q7: Not Available | R7: 1418.601 | S7: 2831.46 | T7: 1412.859 | U7: Not Available | V7: Not Available | W7: Not Available | X7: 1418.601 | Y7: Not Available | Z7: Not Available | AA7: 1418.601 | AB7: 2831.46 | AW7: Not Available | AX7: Not Available | AY7: 831.947 | AZ7: 831.947 | BA7: Not Available | BB7: Not Available | BC7: Not Available | BD7: Not Available | BE7: 15.738 | BF7: Not Available | BG7: Not Available | BH7: 15.738 | BI7: 15.738 | BJ7: Not Available | BK7: Not Available | BL7: Not Available | BM7: Not Available | BN7: Not Available | BO7: 1356.353 | BP7: Not Available | BQ7: Not Available | BR7: Not Available | BS7: 5.019 | BT7: Not Available | BU7: 5.019 | BV7: 1361.372 | BW7: 528111 | BX7: 3379 | BY7: 488075 | BZ7: 111741 | CA7: =BW7*42/1000 -> 22180.662 | CB7: =BX7*42/1000 -> 141.918 | CC7: =BY7*42/1000 -> 20499.15 | CD7: =BZ7*42/1000 -> 4693.122
A8: 1954 | P8: 1394.327 | Q8: Not Available | R8: 1394.327 | S8: 2754.099 | T8: 1359.772 | U8: Not Available | V8: Not Available | W8: Not Available | X8: 1394.327 | Y8: Not Available | Z8: Not Available | AA8: 1394.327 | AB8: 2754.099 | AW8: Not Available | AX8: Not Available | AY8: 799.748 | AZ8: 799.748 | BA8: Not Available | BB8: Not Available | BC8: Not Available | BD8: Not Available | BE8: 15.17 | BF8: Not Available | BG8: Not Available | BH8: 15.17 | BI8: 15.17 | BJ8: Not Available | BK8: Not Available | BL8: Not Available | BM8: Not Available | BN8: Not Available | BO8: 1304.094 | BP8: Not Available | BQ8: Not Available | BR8: Not Available | BS8: 3.209 | BT8: Not Available | BU8: 3.209 | BV8: 1307.303 | BW8: 542278 | BX8: 3195 | BY8: 526369 | BZ8: 108144 | CA8: =BW8*42/1000 -> 22775.676 | CB8: =BX8*42/1000 -> 134.19 | CC8: =BY8*42/1000 -> 22107.498 | CD8: =BZ8*42/1000 -> 4542.048
A9: 1955 | P9: 1424.143 | Q9: Not Available | R9: 1424.143 | S9: 2783.987 | T9: 1359.844 | U9: Not Available | V9: Not Available | W9: Not Available | X9: 1424.143 | Y9: Not Available | Z9: Not Available | AA9: 1424.143 | AB9: 2783.987 | AW9: Not Available | AX9: Not Available | AY9: 775.066 | AZ9: 775.066 | BA9: Not Available | BB9: Not Available | BC9: Not Available | BD9: Not Available | BE9: 14.706 | BF9: Not Available | BG9: Not Available | BH9: 14.706 | BI9: 14.706 | BJ9: Not Available | BK9: Not Available | BL9: Not Available | BM9: Not Available | BN9: Not Available | BO9: 1321.695 | BP9: Not Available | BQ9: Not Available | BR9: Not Available | BS9: 3.234 | BT9: Not Available | BU9: 3.234 | BV9: 1324.929 | BW9: 602547 | BX9: 4413 | BY9: 581128 | BZ9: 111333 | CA9: =BW9*42/1000 -> 25306.974 | CB9: =BX9*42/1000 -> 185.346 | CC9: =BY9*42/1000 -> 24407.376 | CD9: =BZ9*42/1000 -> 4675.986
A10: 1956 | P10: 1415.871 | Q10: Not Available | R10: 1415.871 | S10: 2850.582 | T10: 1434.711 | U10: Not Available | V10: Not Available | W10: Not Available | X10: 1415.871 | Y10: Not Available | Z10: Not Available | AA10: 1415.871 | AB10: 2850.582 | AW10: Not Available | AX10: Not Available | AY10: 738.706 | AZ10: 738.706 | BA10: Not Available | BB10: Not Available | BC10: Not Available | BD10: Not Available | BE10: 14.018 | BF10: Not Available | BG10: Not Available | BH10: 14.018 | BI10: 14.018 | BJ10: Not Available | BK10: Not Available | BL10: Not Available | BM10: Not Available | BN10: Not Available | BO10: 1397.96 | BP10: Not Available | BQ10: Not Available | BR10: Not Available | BS10: 1.738 | BT10: Not Available | BU10: 1.738 | BV10: 1399.698 | BW10: 665687 | BX10: 5159 | BY10: 615856 | BZ10: 133981 | CA10: =BW10*42/1000 -> 27958.854 | CB10: =BX10*42/1000 -> 216.678 | CC10: =BY10*42/1000 -> 25865.952 | CD10: =BZ10*42/1000 -> 5627.202
A11: 1957 | P11: 1333.581 | Q11: Not Available | R11: 1333.581 | S11: 2849.194 | T11: 1515.613 | U11: Not Available | V11: Not Available | W11: Not Available | X11: 1333.581 | Y11: Not Available | Z11: Not Available | AA11: 1333.581 | AB11: 2849.194 | AW11: Not Available | AX11: Not Available | AY11: 701.812 | AZ11: 701.812 | BA11: Not Available | BB11: Not Available | BC11: Not Available | BD11: Not Available | BE11: 13.33 | BF11: Not Available | BG11: Not Available | BH11: 13.33 | BI11: 13.33 | BJ11: Not Available | BK11: Not Available | BL11: Not Available | BM11: Not Available | BN11: Not Available | BO11: 1480.092 | BP11: Not Available | BQ11: Not Available | BR11: Not Available | BS11: 2.008 | BT11: Not Available | BU11: 2.008 | BV11: 1482.1 | BW11: 668573 | BX11: 8566 | BY11: 616090 | BZ11: 149449 | CA11: =BW11*42/1000 -> 28080.066 | CB11: =BX11*42/1000 -> 359.772 | CC11: =BY11*42/1000 -> 25875.78 | CD11: =BZ11*42/1000 -> 6276.858
A12: 1958 | P12: 1323.123 | Q12: Not Available | R12: 1323.123 | S12: 2915.09 | T12: 1591.967 | U12: Not Available | V12: Not Available | W12: Not Available | X12: 1323.123 | Y12: Not Available | Z12: Not Available | AA12: 1323.123 | AB12: 2915.09 | AW12: Not Available | AX12: Not Available | AY12: 688.447 | AZ12: 688.447 | BA12: Not Available | BB12: Not Available | BC12: Not Available | BD12: Not Available | BE12: 13.089 | BF12: Not Available | BG12: Not Available | BH12: 13.089 | BI12: 13.089 | BJ12: Not Available | BK12: Not Available | BL12: Not Available | BM12: Not Available | BN12: Not Available | BO12: 1554.805 | BP12: Not Available | BQ12: Not Available | BR12: Not Available | BS12: 1.94 | BT12: Not Available | BU12: 1.94 | BV12: 1556.745 | BW12: 631405 | BX12: 14892 | BY12: 653426 | BZ12: 125101 | CA12: =BW12*42/1000 -> 26519.01 | CB12: =BX12*42/1000 -> 625.464 | CC12: =BY12*42/1000 -> 27443.892 | CD12: =BZ12*42/1000 -> 5254.242
A13: 1959 | P13: 1352.874 | Q13: Not Available | R13: 1352.874 | S13: 2901.339 | T13: 1548.465 | U13: Not Available | V13: Not Available | W13: Not Available | X13: 1352.874 | Y13: Not Available | Z13: Not Available | AA13: 1352.874 | AB13: 2901.339 | AW13: Not Available | AX13: Not Available | AY13: 646.926 | AZ13: 646.926 | BA13: Not Available | BB13: Not Available | BC13: Not Available | BD13: Not Available | BE13: 12.298 | BF13: Not Available | BG13: Not Available | BH13: 12.298 | BI13: 12.298 | BJ13: Not Available | BK13: Not Available | BL13: Not Available | BM13: Not Available | BN13: Not Available | BO13: 1511.462 | BP13: Not Available | BQ13: Not Available | BR13: Not Available | BS13: 1.677 | BT13: Not Available | BU13: 1.677 | BV13: 1513.139 | BW13: 678938 | BX13: 17658 | BY13: 659332 | BZ13: 151030 | CA13: =BW13*42/1000 -> 28515.396 | CB13: =BX13*42/1000 -> 741.636 | CC13: =BY13*42/1000 -> 27691.944 | CD13: =BZ13*42/1000 -> 6343.26
A14: 1960 | P14: 1319.87 | Q14: Not Available | R14: 1319.87 | S14: 2928.204 | T14: 1607.975 | U14: 0.359 | V14: Not Available | W14: Not Available | X14: 1319.87 | Y14: Not Available | Z14: Not Available | AA14: 1319.87 | AB14: 2928.204 | AW14: Not Available | AX14: Not Available | AY14: 626.63 | AZ14: 626.63 | BA14: Not Available | BB14: Not Available | BC14: Not Available | BD14: Not Available | BE14: 11.868 | BF14: Not Available | BG14: Not Available | BH14: 11.868 | BI14: 11.868 | BJ14: Not Available | BK14: Not Available | BL14: Not Available | BM14: Not Available | BN14: Not Available | BO14: 1569.167 | BP14: 0.359 | BQ14: Not Available | BR14: Not Available | BS14: 1.508 | BT14: Not Available | BU14: 1.508 | BV14: 1571.034 | BW14: 665416 | BX14: 12771 | BY14: 685268 | BZ14: 138455 | CA14: =BW14*42/1000 -> 27947.472 | CB14: =BX14*42/1000 -> 536.382 | CC14: =BY14*42/1000 -> 28781.256 | CD14: =BZ14*42/1000 -> 5815.11
A15: 1961 | P15: 1294.762 | Q15: Not Available | R15: 1294.762 | S15: 2952.226 | T15: 1656.463 | U15: 1.001 | V15: Not Available | W15: Not Available | X15: 1294.762 | Y15: Not Available | Z15: Not Available | AA15: 1294.762 | AB15: 2952.226 | AW15: Not Available | AX15: Not Available | AY15: 586.864 | AZ15: 586.864 | BA15: Not Available | BB15: Not Available | BC15: Not Available | BD15: Not Available | BE15: 11.146 | BF15: Not Available | BG15: Not Available | BH15: 11.146 | BI15: 11.146 | BJ15: Not Available | BK15: Not Available | BL15: Not Available | BM15: Not Available | BN15: Not Available | BO15: 1620.627 | BP15: 1.001 | BQ15: Not Available | BR15: Not Available | BS15: 1.339 | BT15: Not Available | BU15: 1.339 | BV15: 1622.967 | BW15: 696015 | BX15: 17377 | BY15: 694356 | BZ15: 152018 | CA15: =BW15*42/1000 -> 29232.63 | CB15: =BX15*42/1000 -> 729.834 | CC15: =BY15*42/1000 -> 29162.952 | CD15: =BZ15*42/1000 -> 6384.756
A16: 1962 | P16: 1300.242 | Q16: Not Available | R16: 1300.242 | S16: 3117.444 | T16: 1816.141 | U16: 1.061 | V16: Not Available | W16: Not Available | X16: 1300.242 | Y16: Not Available | Z16: Not Available | AA16: 1300.242 | AB16: 3117.444 | AW16: Not Available | AX16: Not Available | AY16: 560.084 | AZ16: 560.084 | BA16: Not Available | BB16: Not Available | BC16: Not Available | BD16: Not Available | BE16: 10.63 | BF16: Not Available | BG16: Not Available | BH16: 10.63 | BI16: 10.63 | BJ16: Not Available | BK16: Not Available | BL16: Not Available | BM16: Not Available | BN16: Not Available | BO16: 1780.151 | BP16: 1.061 | BQ16: Not Available | BR16: Not Available | BS16: 1.349 | BT16: Not Available | BU16: 1.349 | BV16: 1782.561 | BW16: 719590 | BX16: 11831 | BY16: 732405 | BZ16: 144505 | CA16: =BW16*42/1000 -> 30222.78 | CB16: =BX16*42/1000 -> 496.902 | CC16: =BY16*42/1000 -> 30761.01 | CD16: =BZ16*42/1000 -> 6069.21
A17: 1963 | P17: 1323.316 | Q17: Not Available | R17: 1323.316 | S17: 3096.431 | T17: 1771.355 | U17: 1.76 | V17: Not Available | W17: Not Available | X17: 1323.316 | Y17: Not Available | Z17: Not Available | AA17: 1323.316 | AB17: 3096.431 | AW17: Not Available | AX17: Not Available | AY17: 536.967 | AZ17: 536.967 | BA17: Not Available | BB17: Not Available | BC17: Not Available | BD17: Not Available | BE17: 10.165 | BF17: Not Available | BG17: Not Available | BH17: 10.165 | BI17: 10.165 | BJ17: Not Available | BK17: Not Available | BL17: Not Available | BM17: Not Available | BN17: Not Available | BO17: 1737.441 | BP17: 1.76 | BQ17: Not Available | BR17: Not Available | BS17: 1.341 | BT17: Not Available | BU17: 1.341 | BV17: 1740.542 | BW17: 764597 | BX17: 9210 | BY17: 747254 | BZ17: 156677 | CA17: =BW17*42/1000 -> 32113.074 | CB17: =BX17*42/1000 -> 386.82 | CC17: =BY17*42/1000 -> 31384.668 | CD17: =BZ17*42/1000 -> 6580.434
A18: 1964 | P18: 1336.802 | Q18: Not Available | R18: 1336.802 | S18: 3225.248 | T18: 1886.314 | U18: 2.132 | V18: Not Available | W18: Not Available | X18: 1336.802 | Y18: Not Available | Z18: Not Available | AA18: 1336.802 | AB18: 3225.248 | AW18: Not Available | AX18: Not Available | AY18: 499.058 | AZ18: 499.058 | BA18: Not Available | BB18: Not Available | BC18: Not Available | BD18: Not Available | BE18: 9.46 | BF18: Not Available | BG18: Not Available | BH18: 9.46 | BI18: 9.46 | BJ18: Not Available | BK18: Not Available | BL18: Not Available | BM18: Not Available | BN18: Not Available | BO18: 1852.542 | BP18: 2.132 | BQ18: Not Available | BR18: Not Available | BS18: 1.549 | BT18: Not Available | BU18: 1.549 | BV18: 1856.223 | BW18: 742046 | BX18: 11885 | BY18: 750424 | BZ18: 155846 | CA18: =BW18*42/1000 -> 31165.932 | CB18: =BX18*42/1000 -> 499.17 | CC18: =BY18*42/1000 -> 31517.808 | CD18: =BZ18*42/1000 -> 6545.532
A19: 1965 | P19: 1334.761 | Q19: Not Available | R19: 1334.761 | S19: 3395.816 | T19: 2059.077 | U19: 1.978 | V19: Not Available | W19: Not Available | X19: 1334.761 | Y19: Not Available | Z19: Not Available | AA19: 1334.761 | AB19: 3395.816 | AW19: Not Available | AX19: Not Available | AY19: 468.15 | AZ19: 468.15 | BA19: Not Available | BB19: Not Available | BC19: Not Available | BD19: Not Available | BE19: 8.858 | BF19: Not Available | BG19: Not Available | BH19: 8.858 | BI19: 8.858 | BJ19: Not Available | BK19: Not Available | BL19: Not Available | BM19: Not Available | BN19: Not Available | BO19: 2026.32 | BP19: 1.978 | BQ19: Not Available | BR19: Not Available | BS19: 2.81 | BT19: Not Available | BU19: 2.81 | BV19: 2031.108 | BW19: 765071 | BX19: 13002 | BY19: 775814 | BZ19: 155407 | CA19: =BW19*42/1000 -> 32132.982 | CB19: =BX19*42/1000 -> 546.084 | CC19: =BY19*42/1000 -> 32584.188 | CD19: =BZ19*42/1000 -> 6527.094
A20: 1966 | P20: 1368.985 | Q20: Not Available | R20: 1368.985 | S20: 3432.462 | T20: 2061.519 | U20: 1.958 | V20: Not Available | W20: Not Available | X20: 1368.985 | Y20: Not Available | Z20: Not Available | AA20: 1368.985 | AB20: 3432.462 | AW20: Not Available | AX20: Not Available | AY20: 454.974 | AZ20: 454.974 | BA20: Not Available | BB20: Not Available | BC20: Not Available | BD20: Not Available | BE20: 8.617 | BF20: Not Available | BG20: Not Available | BH20: 8.617 | BI20: 8.617 | BJ20: Not Available | BK20: Not Available | BL20: Not Available | BM20: Not Available | BN20: Not Available | BO20: 2028.381 | BP20: 1.958 | BQ20: Not Available | BR20: Not Available | BS20: 3.478 | BT20: Not Available | BU20: 3.478 | BV20: 2033.817 | BW20: 784727 | BX20: 13845 | BY20: 797380 | BZ20: 154096 | CA20: =BW20*42/1000 -> 32958.534 | CB20: =BX20*42/1000 -> 581.49 | CC20: =BY20*42/1000 -> 33489.96 | CD20: =BZ20*42/1000 -> 6472.032
A21: 1967 | P21: 1340.249 | Q21: Not Available | R21: 1340.249 | S21: 3690.213 | T21: 2346.664 | U21: 3.3 | V21: Not Available | W21: Not Available | X21: 1340.249 | Y21: Not Available | Z21: Not Available | AA21: 1340.249 | AB21: 3690.213 | AW21: Not Available | AX21: Not Available | AY21: 433.973 | AZ21: 433.973 | BA21: Not Available | BB21: Not Available | BC21: Not Available | BD21: Not Available | BE21: 8.325 | BF21: Not Available | BG21: Not Available | BH21: 8.325 | BI21: 8.325 | BJ21: Not Available | BK21: Not Available | BL21: Not Available | BM21: Not Available | BN21: Not Available | BO21: 2310.877 | BP21: 3.3 | BQ21: Not Available | BR21: Not Available | BS21: 3.293 | BT21: Not Available | BU21: 3.293 | BV21: 2317.47 | BW21: 804429 | BX21: 18492 | BY21: 818150 | BZ21: 159703 | CA21: =BW21*42/1000 -> 33786.018 | CB21: =BX21*42/1000 -> 776.664 | CC21: =BY21*42/1000 -> 34362.3 | CD21: =BZ21*42/1000 -> 6707.526
A22: 1968 | P22: 1419.495 | Q22: Not Available | R22: 1419.495 | S22: 3772.656 | T22: 2348.629 | U22: 4.532 | V22: Not Available | W22: Not Available | X22: 1419.495 | Y22: Not Available | Z22: Not Available | AA22: 1419.495 | AB22: 3772.656 | AW22: Not Available | AX22: Not Available | AY22: 425.511 | AZ22: 425.511 | BA22: Not Available | BB22: Not Available | BC22: Not Available | BD22: Not Available | BE22: 8.136 | BF22: Not Available | BG22: Not Available | BH22: 8.136 | BI22: 8.136 | BJ22: Not Available | BK22: Not Available | BL22: Not Available | BM22: Not Available | BN22: Not Available | BO22: 2313.457 | BP22: 4.532 | BQ22: Not Available | BR22: Not Available | BS22: 3.9 | BT22: Not Available | BU22: 3.9 | BV22: 2321.889 | BW22: 839373 | BX22: 48148 | BY22: 875539 | BZ22: 173158 | CA22: =BW22*42/1000 -> 35253.666 | CB22: =BX22*42/1000 -> 2022.216 | CC22: =BY22*42/1000 -> 36772.638 | CD22: =BZ22*42/1000 -> 7272.636
A23: 1969 | P23: 1440.487 | Q23: Not Available | R23: 1440.487 | S23: 4094.892 | T23: 2647.983 | U23: 6.422 | V23: Not Available | W23: Not Available | X23: 1440.487 | Y23: Not Available | Z23: Not Available | AA23: 1440.487 | AB23: 4094.892 | AW23: Not Available | AX23: Not Available | AY23: 415.053 | AZ23: 415.053 | BA23: Not Available | BB23: Not Available | BC23: Not Available | BD23: Not Available | BE23: 7.86 | BF23: Not Available | BG23: Not Available | BH23: 7.86 | BI23: 7.86 | BJ23: Not Available | BK23: Not Available | BL23: Not Available | BM23: Not Available | BN23: Not Available | BO23: 2613.763 | BP23: 6.422 | BQ23: Not Available | BR23: Not Available | BS23: 3.342 | BT23: Not Available | BU23: 3.342 | BV23: 2623.527 | BW23: 846863 | BX23: 50853 | BY23: 900262 | BZ23: 171714 | CA23: =BW23*42/1000 -> 35568.246 | CB23: =BX23*42/1000 -> 2135.826 | CC23: =BY23*42/1000 -> 37811.004 | CD23: =BZ23*42/1000 -> 7211.988
A24: 1970 | P24: 1428.649 | Q24: Not Available | R24: 1430.962 | S24: 4070.021 | T24: 2633.547 | U24: 5.511 | V24: Not Available | W24: Not Available | X24: 1428.649 | Y24: 2.313 | Z24: Not Available | AA24: 1430.962 | AB24: 4070.021 | AW24: Not Available | AX24: Not Available | AY24: 400.777 | AZ24: 400.777 | BA24: Not Available | BB24: Not Available | BC24: Not Available | BD24: Not Available | BE24: 7.534 | BF24: Not Available | BG24: Not Available | BH24: 7.534 | BI24: 7.534 | BJ24: Not Available | BK24: Not Available | BL24: Not Available | BM24: Not Available | BN24: Not Available | BO24: 2599.507 | BP24: 5.511 | BQ24: Not Available | BR24: Not Available | BS24: 1.427 | BT24: 2.313 | BU24: 3.74 | BV24: 2608.759 | BW24: 895756 | BX24: 53825 | BY24: 927211 | BZ24: 195271 | CA24: =BW24*42/1000 -> 37621.752 | CB24: =BX24*42/1000 -> 2260.65 | CC24: =BY24*42/1000 -> 38942.862 | CD24: =BZ24*42/1000 -> 8201.382
A25: 1971 | P25: 1430.229 | Q25: Not Available | R25: 1432.323 | S25: 4262.213 | T25: 2824.151 | U25: 5.739 | V25: Not Available | W25: Not Available | X25: 1430.229 | Y25: 2.094 | Z25: Not Available | AA25: 1432.323 | AB25: 4262.213 | AW25: Not Available | AX25: Not Available | AY25: 381.874 | AZ25: 381.874 | BA25: Not Available | BB25: Not Available | BC25: Not Available | BD25: Not Available | BE25: 7.19 | BF25: Not Available | BG25: Not Available | BH25: 7.19 | BI25: 7.19 | BJ25: Not Available | BK25: Not Available | BL25: Not Available | BM25: Not Available | BN25: Not Available | BO25: 2790.405 | BP25: 5.739 | BQ25: Not Available | BR25: Not Available | BS25: 1.167 | BT25: 2.094 | BU25: 3.261 | BV25: 2799.405 | BW25: 910824 | BX25: 55778 | BY25: 971316 | BZ25: 190622 | CA25: =BW25*42/1000 -> 38254.608 | CB25: =BX25*42/1000 -> 2342.676 | CC25: =BY25*42/1000 -> 40795.272 | CD25: =BZ25*42/1000 -> 8006.124
A26: 1972 | P26: 1500.992 | Q26: Not Available | R26: 1503.065 | S26: 4382.009 | T26: 2863.865 | U26: 15.079 | V26: Not Available | W26: Not Available | X26: 1500.992 | Y26: 2.073 | Z26: Not Available | AA26: 1503.065 | AB26: 4382.009 | AW26: Not Available | AX26: Not Available | AY26: 379.776 | AZ26: 379.776 | BA26: Not Available | BB26: Not Available | BC26: Not Available | BD26: Not Available | BE26: 7.19 | BF26: Not Available | BG26: Not Available | BH26: 7.19 | BI26: 7.19 | BJ26: Not Available | BK26: Not Available | BL26: Not Available | BM26: Not Available | BN26: Not Available | BO26: 2829.445 | BP26: 15.079 | BQ26: Not Available | BR26: Not Available | BS26: 1.358 | BT26: 2.073 | BU26: 3.431 | BV26: 2847.955 | BW26: 976665 | BX26: 66449 | BY26: 1067110 | BZ26: 154319 | CA26: =BW26*42/1000 -> 41019.93 | CB26: =BX26*42/1000 -> 2790.858 | CC26: =BY26*42/1000 -> 44818.62 | CD26: =BZ26*42/1000 -> 6481.398
A27: 1973 | P27: 1527.012 | Q27: Not Available | R27: 1529.068 | S27: 4410.938 | T27: 2861.448 | U27: 20.422 | V27: Not Available | W27: Not Available | X27: 1527.012 | Y27: 2.056 | Z27: Not Available | AA27: 1529.068 | AB27: 4410.938 | AW27: Not Available | AX27: Not Available | AY27: 354.096 | AZ27: 354.096 | BA27: Not Available | BB27: Not Available | BC27: Not Available | BD27: Not Available | BE27: 6.708 | BF27: Not Available | BG27: Not Available | BH27: 6.708 | BI27: 6.708 | BJ27: Not Available | BK27: Not Available | BL27: Not Available | BM27: Not Available | BN27: Not Available | BO27: 2826.675 | BP27: 20.422 | BQ27: Not Available | BR27: Not Available | BS27: 1.355 | BT27: 2.056 | BU27: 3.411 | BV27: 2850.507 | BW27: 1029343 | BX27: 143149 | BY27: 1128714 | BZ27: 196461 | CA27: =BW27*42/1000 -> 43232.406 | CB27: =BX27*42/1000 -> 6012.258 | CC27: =BY27*42/1000 -> 47405.988 | CD27: =BZ27*42/1000 -> 8251.362
A28: 1974 | P28: 1537.76 | Q28: Not Available | R28: 1539.662 | S28: 4741.852 | T28: 3176.58 | U28: 25.61 | V28: Not Available | W28: Not Available | X28: 1537.76 | Y28: 1.902 | Z28: Not Available | AA28: 1539.662 | AB28: 4741.852 | AW28: Not Available | AX28: Not Available | AY28: 370.952 | AZ28: 370.952 | BA28: Not Available | BB28: Not Available | BC28: Not Available | BD28: Not Available | BE28: 7.018 | BF28: Not Available | BG28: Not Available | BH28: 7.018 | BI28: 7.018 | BJ28: Not Available | BK28: Not Available | BL28: Not Available | BM28: Not Available | BN28: Not Available | BO28: 3143.378 | BP28: 25.61 | BQ28: Not Available | BR28: Not Available | BS28: 0.716 | BT28: 1.902 | BU28: 2.618 | BV28: 3171.606 | BW28: 974025 | BX28: 105579 | BY28: 1075916 | BZ28: 200068 | CA28: =BW28*42/1000 -> 40909.05 | CB28: =BX28*42/1000 -> 4434.318 | CC28: =BY28*42/1000 -> 45188.472 | CD28: =BZ28*42/1000 -> 8402.856
A29: 1975 | P29: 1496.928 | Q29: Not Available | R29: 1498.734 | S29: 4687.12 | T29: 3154.607 | U29: 33.78 | V29: Not Available | W29: Not Available | X29: 1496.928 | Y29: 1.806 | Z29: Not Available | AA29: 1498.734 | AB29: 4687.12 | AW29: Not Available | AX29: Not Available | AY29: 425.408 | AZ29: 425.408 | BA29: Not Available | BB29: Not Available | BC29: Not Available | BD29: Not Available | BE29: 8.067 | BF29: Not Available | BG29: Not Available | BH29: 8.067 | BI29: 8.067 | BJ29: Not Available | BK29: Not Available | BL29: Not Available | BM29: Not Available | BN29: Not Available | BO29: 3122.285 | BP29: 33.78 | BQ29: Not Available | BR29: Not Available | BS29: 0.183 | BT29: 1.806 | BU29: 1.989 | BV29: 3158.054 | BW29: 968650 | BX29: 56679 | BY29: 1040571 | BZ29: 208833 | CA29: =BW29*42/1000 -> 40683.3 | CB29: =BX29*42/1000 -> 2380.518 | CC29: =BY29*42/1000 -> 43703.982 | CD29: =BZ29*42/1000 -> 8770.986
A30: 1976 | P30: 1711.484 | Q30: Not Available | R30: 1713.373 | S30: 4727.151 | T30: 2976.265 | U30: 37.513 | V30: Not Available | W30: Not Available | X30: 1711.484 | Y30: 1.889 | Z30: Not Available | AA30: 1713.373 | AB30: 4727.151 | AW30: Not Available | AX30: Not Available | AY30: 481.634 | AZ30: 481.634 | BA30: Not Available | BB30: Not Available | BC30: Not Available | BD30: Not Available | BE30: 9.099 | BF30: Not Available | BG30: Not Available | BH30: 9.099 | BI30: 9.099 | BJ30: Not Available | BK30: Not Available | BL30: Not Available | BM30: Not Available | BN30: Not Available | BO30: 2942.893 | BP30: 37.513 | BQ30: Not Available | BR30: Not Available | BS30: 0.875 | BT30: 1.889 | BU30: 2.764 | BV30: 2983.17 | BW30: 1070032 | BX30: 53520 | BY30: 1146695 | BZ30: 185986 | CA30: =BW30*42/1000 -> 44941.344 | CB30: =BX30*42/1000 -> 2247.84 | CC30: =BY30*42/1000 -> 48161.19 | CD30: =BZ30*42/1000 -> 7811.412
A31: 1977 | P31: 1836.524 | Q31: Not Available | R31: 1838.332 | S31: 4208.966 | T31: 2333.252 | U31: 37.382 | V31: Not Available | W31: Not Available | X31: 1836.524 | Y31: 1.808 | Z31: Not Available | AA31: 1838.332 | AB31: 4208.966 | AW31: Not Available | AX31: Not Available | AY31: 541.783 | AZ31: 541.783 | BA31: Not Available | BB31: Not Available | BC31: Not Available | BD31: Not Available | BE31: 10.286 | BF31: Not Available | BG31: Not Available | BH31: 10.286 | BI31: 10.286 | BJ31: Not Available | BK31: Not Available | BL31: Not Available | BM31: Not Available | BN31: Not Available | BO31: 2300.652 | BP31: 37.382 | BQ31: Not Available | BR31: Not Available | BS31: 3.21 | BT31: 1.808 | BU31: 5.018 | BV31: 2343.051 | BW31: 1196143 | BX31: 91318 | BY31: 1223328 | BZ31: 250295 | CA31: =BW31*42/1000 -> 50238.006 | CB31: =BX31*42/1000 -> 3835.356 | CC31: =BY31*42/1000 -> 51379.776 | CD31: =BZ31*42/1000 -> 10512.39
A32: 1978 | P32: 2036.15 | Q32: Not Available | R32: 2037.605 | S32: 5005.44 | T32: 2936.983 | U32: 30.851 | V32: Not Available | W32: Not Available | X32: 2036.15 | Y32: 1.455 | Z32: Not Available | AA32: 2037.605 | AB32: 5005.44 | AW32: Not Available | AX32: Not Available | AY32: 621.849 | AZ32: 621.849 | BA32: Not Available | BB32: Not Available | BC32: Not Available | BD32: Not Available | BE32: 11.834 | BF32: Not Available | BG32: Not Available | BH32: 11.834 | BI32: 11.834 | BJ32: Not Available | BK32: Not Available | BL32: Not Available | BM32: Not Available | BN32: Not Available | BO32: 2905.42 | BP32: 30.851 | BQ32: Not Available | BR32: Not Available | BS32: 2.043 | BT32: 1.455 | BU32: 3.498 | BV32: 2939.769 | BW32: 1155969 | BX32: 63288 | BY32: 1252556 | BZ32: 216463 | CA32: =BW32*42/1000 -> 48550.698 | CB32: =BX32*42/1000 -> 2658.096 | CC32: =BY32*42/1000 -> 52607.352 | CD32: =BZ32*42/1000 -> 9091.446
A33: 1979 | P33: 2149.854 | Q33: Not Available | R33: 2151.906 | S33: 5122.854 | T33: 2930.686 | U33: 40.262 | V33: Not Available | W33: Not Available | X33: 2149.854 | Y33: 2.052 | Z33: Not Available | AA33: 2151.906 | AB33: 5122.854 | AW33: Not Available | AX33: Not Available | AY33: 728.076 | AZ33: 728.076 | BA33: Not Available | BB33: Not Available | BC33: Not Available | BD33: Not Available | BE33: 13.812 | BF33: Not Available | BG33: Not Available | BH33: 13.812 | BI33: 13.812 | BJ33: Not Available | BK33: Not Available | BL33: Not Available | BM33: Not Available | BN33: Not Available | BO33: 2896.591 | BP33: 40.262 | BQ33: Not Available | BR33: Not Available | BS33: 3.104 | BT33: 2.052 | BU33: 5.156 | BV33: 2942.01 | BW33: 1150594 | BX33: 70489 | BY33: 1208456 | BZ33: 228729 | CA33: =BW33*42/1000 -> 48324.948 | CB33: =BX33*42/1000 -> 2960.538 | CC33: =BY33*42/1000 -> 50755.152 | CD33: =BZ33*42/1000 -> 9606.618
A34: 1980 | P34: 2473.861 | Q34: Not Available | R34: 2475.5 | S34: 5428.342 | T34: 2900.144 | U34: 52.699 | V34: Not Available | W34: Not Available | X34: 2473.861 | Y34: 1.639 | Z34: Not Available | AA34: 2475.5 | AB34: 5428.342 | AW34: Not Available | AX34: Not Available | AY34: 850 | AZ34: 850 | BA34: Not Available | BB34: Not Available | BC34: Not Available | BD34: Not Available | BE34: 21 | BF34: Not Available | BG34: Not Available | BH34: 21 | BI34: 21 | BJ34: Not Available | BK34: Not Available | BL34: Not Available | BM34: Not Available | BN34: Not Available | BO34: 2867.306 | BP34: 52.699 | BQ34: Not Available | BR34: Not Available | BS34: 2.861 | BT34: 1.639 | BU34: 4.5 | BV34: 2924.505 | BW34: 973981 | BX34: 51908 | BY34: 1048975 | BZ34: 205113 | CA34: =BW34*42/1000 -> 40907.202 | CB34: =BX34*42/1000 -> 2180.136 | CC34: =BY34*42/1000 -> 44056.95 | CD34: =BZ34*42/1000 -> 8614.746
A35: 1981 | P35: 2495.563 | Q35: 12.72 | R35: 2596.283 | S35: 5413.688 | T35: 2757.968 | U35: 59.437 | V35: Not Available | W35: Not Available | X35: 2495.563 | Y35: 88 | Z35: 12.72 | AA35: 2596.283 | AB35: 5413.688 | AW35: Not Available | AX35: Not Available | AY35: 870 | AZ35: 870 | BA35: Not Available | BB35: Not Available | BC35: Not Available | BD35: Not Available | BE35: 21 | BF35: Not Available | BG35: 0.05 | BH35: 21.05 | BI35: 21.05 | BJ35: 6.723 | BK35: Not Available | BL35: Not Available | BM35: Not Available | BN35: 6.723 | BO35: 2724.925 | BP35: 59.437 | BQ35: Not Available | BR35: Not Available | BS35: 2.563 | BT35: 1.282 | BU35: 3.845 | BV35: 2788.207 | BW35: 953732 | BX35: 63071 | BY35: 1032476 | BZ35: 191541 | CA35: =BW35*42/1000 -> 40056.744 | CB35: =BX35*42/1000 -> 2648.982 | CC35: =BY35*42/1000 -> 43363.992 | CD35: =BZ35*42/1000 -> 8044.722
A36: 1982 | P36: 2510.048 | Q36: 34.404 | R36: 2663.452 | S36: 5979.637 | T36: 3265.558 | U36: 50.627 | V36: Not Available | W36: Not Available | X36: 2510.048 | Y36: 119 | Z36: 34.404 | AA36: 2663.452 | AB36: 5979.637 | AW36: Not Available | AX36: Not Available | AY36: 970 | AZ36: 970 | BA36: Not Available | BB36: Not Available | BC36: Not Available | BD36: Not Available | BE36: 22 | BF36: Not Available | BG36: 0.13 | BH36: 22.13 | BI36: 22.13 | BJ36: 18.285 | BK36: Not Available | BL36: Not Available | BM36: Not Available | BN36: 18.285 | BO36: 3232.512 | BP36: 50.627 | BQ36: Not Available | BR36: Not Available | BS36: 2.048 | BT36: 1.307 | BU36: 3.355 | BV36: 3286.494 | BW36: 951242 | BX36: 34040 | BY36: 974864 | BZ36: 178592 | CA36: =BW36*42/1000 -> 39952.164 | CB36: =BX36*42/1000 -> 1429.68 | CC36: =BY36*42/1000 -> 40944.288 | CD36: =BZ36*42/1000 -> 7500.864
A37: 1983 | P37: 2684.271 | Q37: 63.143 | R37: 2904.414 | S37: 6495.612 | T37: 3527.26 | U37: 63.91 | V37: Not Available | W37: 0.028 | X37: 2684.271 | Y37: 157 | Z37: 63.143 | AA37: 2904.414 | AB37: 6495.612 | AW37: Not Available | AX37: Not Available | AY37: 970 | AZ37: 970 | BA37: Not Available | BB37: Not Available | BC37: Not Available | BD37: Not Available | BE37: 22 | BF37: Not Available | BG37: 0.276 | BH37: 22.276 | BI37: 22.276 | BJ37: 33.72 | BK37: Not Available | BL37: Not Available | BM37: Not Available | BN37: 33.72 | BO37: 3494.005 | BP37: 63.91 | BQ37: Not Available | BR37: 0.028 | BS37: 2.271 | BT37: 1.712 | BU37: 3.983 | BV37: 3561.926 | BW37: 896504 | BX37: 63542 | BY37: 981927 | BZ37: 140263 | CA37: =BW37*42/1000 -> 37653.168 | CB37: =BX37*42/1000 -> 2668.764 | CC37: =BY37*42/1000 -> 41240.934 | CD37: =BZ37*42/1000 -> 5891.046
A38: 1984 | P38: 2685.817 | Q38: 77.302 | R38: 2971.12 | S38: 6437.864 | T38: 3385.811 | U38: 80.811 | V38: 0.055 | W38: 0.068 | X38: 2685.817 | Y38: 208 | Z38: 77.302 | AA38: 2971.12 | AB38: 6437.864 | AW38: Not Available | AX38: Not Available | AY38: 980 | AZ38: 980 | BA38: Not Available | BB38: Not Available | BC38: Not Available | BD38: Not Available | BE38: 22 | BF38: Not Available | BG38: 0.351 | BH38: 22.351 | BI38: 22.351 | BJ38: 41.265 | BK38: Not Available | BL38: Not Available | BM38: Not Available | BN38: 41.265 | BO38: 3352.809 | BP38: 80.811 | BQ38: 0.055 | BR38: 0.068 | BS38: 4.817 | BT38: 4.432 | BU38: 9.249 | BV38: 3442.991 | BW38: 980727 | BX38: 99439 | BY38: 1041218 | BZ38: 161072 | CA38: =BW38*42/1000 -> 41190.534 | CB38: =BX38*42/1000 -> 4176.438 | CC38: =BY38*42/1000 -> 43731.156 | CD38: =BZ38*42/1000 -> 6765.024
A39: 1985 | P39: 2686.765 | Q39: 93.151 | R39: 3016.233 | S39: 6084.017 | T39: 2970.192 | U39: 97.421 | V39: 0.111 | W39: 0.06 | X39: 2686.765 | Y39: 236.317 | Z39: 93.151 | AA39: 3016.233 | AB39: 6084.017 | AW39: Not Available | AX39: Not Available | AY39: 1010 | AZ39: 1010 | BA39: Not Available | BB39: Not Available | BC39: Not Available | BD39: Not Available | BE39: 24 | BF39: Not Available | BG39: 0.374 | BH39: 24.374 | BI39: 24.374 | BJ39: 49.738 | BK39: Not Available | BL39: Not Available | BM39: Not Available | BN39: 49.738 | BO39: 2937.168 | BP39: 97.421 | BQ39: 0.111 | BR39: 0.06 | BS39: 7.765 | BT39: 6.682 | BU39: 14.447 | BV39: 3049.207 | BW39: 980351 | BX39: 73089 | BY39: 1046827 | BZ39: 143673 | CA39: =BW39*42/1000 -> 41174.742 | CB39: =BX39*42/1000 -> 3069.738 | CC39: =BY39*42/1000 -> 43966.734 | CD39: =BZ39*42/1000 -> 6034.266
A40: 1986 | P40: 2562.134 | Q40: 107.099 | R40: 2932.095 | S40: 6111.14 | T40: 3071.179 | U40: 107.677 | V40: 0.147 | W40: 0.044 | X40: 2562.134 | Y40: 262.861 | Z40: 107.099 | AA40: 2932.095 | AB40: 6111.14 | AW40: Not Available | AX40: Not Available | AY40: 920 | AZ40: 920 | BA40: Not Available | BB40: Not Available | BC40: Not Available | BD40: Not Available | BE40: 27 | BF40: Not Available | BG40: 0.464 | BH40: 27.464 | BI40: 27.464 | BJ40: 57.437 | BK40: Not Available | BL40: Not Available | BM40: Not Available | BN40: 57.437 | BO40: 3038.157 | BP40: 107.677 | BQ40: 0.147 | BR40: 0.044 | BS40: 5.134 | BT40: 7.158 | BU40: 12.292 | BV40: 3158.317 | BW40: 1020716 | BX40: 90296 | BY40: 1063741 | BZ40: 155097 | CA40: =BW40*42/1000 -> 42870.072 | CB40: =BX40*42/1000 -> 3792.432 | CC40: =BY40*42/1000 -> 44677.122 | CD40: =BZ40*42/1000 -> 6514.074
A41: 1987 | P41: 2463.159 | Q41: 122.725 | R41: 2874.884 | S41: 5621.807 | T41: 2634.508 | U41: 112.27 | V41: 0.109 | W41: 0.037 | X41: 2463.159 | Y41: 289 | Z41: 122.725 | AA41: 2874.884 | AB41: 5621.807 | AW41: Not Available | AX41: Not Available | AY41: 850 | AZ41: 850 | BA41: Not Available | BB41: Not Available | BC41: Not Available | BD41: Not Available | BE41: 29 | BF41: Not Available | BG41: 0.542 | BH41: 29.542 | BI41: 29.542 | BJ41: 66.071 | BK41: Not Available | BL41: Not Available | BM41: Not Available | BN41: 66.071 | BO41: 2601.572 | BP41: 112.27 | BQ41: 0.109 | BR41: 0.037 | BS41: 8.159 | BT41: 7.23 | BU41: 15.389 | BV41: 2729.377 | BW41: 996119 | BX41: 93176 | BY41: 1086413 | BZ41: 134485 | CA41: =BW41*42/1000 -> 41836.998 | CB41: =BX41*42/1000 -> 3913.392 | CC41: =BY41*42/1000 -> 45629.346 | CD41: =BZ41*42/1000 -> 5648.37
A42: 1988 | P42: 2576.663 | Q42: 124.058 | R42: 3016.049 | S42: 5456.754 | T42: 2334.265 | U42: 106.338 | V42: 0.094 | W42: 0.009 | X42: 2576.663 | Y42: 315.328 | Z42: 124.058 | AA42: 3016.049 | AB42: 5456.754 | AW42: Not Available | AX42: Not Available | AY42: 910 | AZ42: 910 | BA42: Not Available | BB42: Not Available | BC42: Not Available | BD42: Not Available | BE42: 32 | BF42: Not Available | BG42: 0.537 | BH42: 32.537 | BI42: 32.537 | BJ42: 67.125 | BK42: Not Available | BL42: Not Available | BM42: Not Available | BN42: 67.125 | BO42: 2301.629 | BP42: 106.338 | BQ42: 0.094 | BR42: 0.009 | BS42: 9.663 | BT42: 7.622 | BU42: 17.285 | BV42: 2425.355 | BW42: 1045786 | BX42: 110354 | BY42: 1142510 | BZ42: 123517 | CA42: =BW42*42/1000 -> 43923.012 | CB42: =BX42*42/1000 -> 4634.868 | CC42: =BY42*42/1000 -> 47985.42 | CD42: =BZ42*42/1000 -> 5187.714
A43: 1989 | P43: 2679.623 | Q43: 125.378 | R43: 3159.357 | S43: 6234.641 | T43: 2837.263 | U43: 161.539 | V43: 54.449 | W43: 22.033 | X43: 2679.623 | Y43: 354.356 | Z43: 125.378 | AA43: 3159.357 | AB43: 6234.641 | AW43: 5 | AX43: 51.654 | AY43: 920 | AZ43: 976.654 | BA43: 0.685 | BB43: 2.5 | BC43: 0.148 | BD43: No Data Reported | BE43: 76.485 | BF43: 21.995 | BG43: 0.505 | BH43: 98.985 | BI43: 102.318 | BJ43: 68.091 | BK43: Not Available | BL43: Not Available | BM43: Not Available | BN43: 68.091 | BO43: 2808.182 | BP43: 152.239 | BQ43: 2.614 | BR43: 22.033 | BS43: 99.575 | BT43: 131.955 | BU43: 231.53 | BV43: 3216.598 | BW43: 1057975 | BX43: 111674 | BY43: 1152224 | BZ43: 105700 | CA43: =BW43*42/1000 -> 44434.95 | CB43: =BX43*42/1000 -> 4690.308 | CC43: =BY43*42/1000 -> 48393.408 | CD43: =BZ43*42/1000 -> 4439.4
A44: 1990 | P44: 2216.166 | Q44: 110.867 | R44: 2735.112 | S44: 6040.005 | T44: 3046.391 | U44: 170.747 | V44: 58.748 | W44: 29.007 | X44: 2216.166 | Y44: 408.079 | Z44: 110.867 | AA44: 2735.112 | AB44: 6040.005 | AW44: 5.5 | AX44: 54.724 | AY44: 580 | AZ44: 640.224 | BA44: 1.432 | BB44: 2.8 | BC44: 0.168 | BD44: No Data Reported | BE44: 65.738 | BF44: 27.765 | BG44: 0.495 | BH44: 93.998 | BI44: 98.398 | BJ44: 60.421 | BK44: Not Available | BL44: Not Available | BM44: Not Available | BN44: 60.421 | BO44: 3014.012 | BP44: 160.547 | BQ44: 3.818 | BR44: 29.007 | BS44: 128.516 | BT44: 187.991 | BU44: 316.507 | BV44: 3523.892 | BW44: 1067485 | BX44: 101455 | BY44: 1102503 | BZ44: 132204 | CA44: =BW44*42/1000 -> 44834.37 | CB44: =BX44*42/1000 -> 4261.11 | CC44: =BY44*42/1000 -> 46305.126 | CD44: =BZ44*42/1000 -> 5552.568
A45: 1991 | P45: 2214.082 | Q45: 128 | R45: 2781.797 | S45: 6067.763 | T45: 3015.943 | U45: 177.626 | V45: 61.601 | W45: 30.796 | X45: 2214.082 | Y45: 439.715 | Z45: 128 | AA45: 2781.797 | AB45: 6067.763 | AW45: 5.9 | AX45: 56.448 | AY45: 610 | AZ45: 672.348 | BA45: 1.369 | BB45: 3 | BC45: 0.188 | BD45: No Data Reported | BE45: 68.44 | BF45: 26.485 | BG45: 0.442 | BH45: 95.367 | BI45: 99.924 | BJ45: 70.095 | BK45: Not Available | BL45: Not Available | BM45: Not Available | BN45: 70.095 | BO45: 2984.899 | BP45: 166.626 | BQ45: 4.923 | BR45: 30.796 | BS45: 125.795 | BT45: 228.556 | BU45: 354.351 | BV45: 3541.595 | BW45: 1081018 | BX45: 74778 | BY45: 1066081 | BZ45: 143515 | CA45: =BW45*42/1000 -> 45402.756 | CB45: =BX45*42/1000 -> 3140.676 | CC45: =BY45*42/1000 -> 44775.402 | CD45: =BZ45*42/1000 -> 6027.63
A46: 1992 | P46: 2313.471 | Q46: 145.005 | R46: 2931.678 | S46: 5820.533 | T46: 2617.436 | U46: 178.699 | V46: 62.856 | W46: 29.863 | X46: 2313.471 | Y46: 473.202 | Z46: 145.005 | AA46: 2931.678 | AB46: 5820.533 | AW46: 6.4 | AX46: 58.473 | AY46: 640 | AZ46: 704.873 | BA46: 1.266 | BB46: 3.2 | BC46: 0.205 | BD46: No Data Reported | BE46: 72.027 | BF46: 32.452 | BG46: 0.463 | BH46: 104.942 | BI46: 109.614 | BJ46: 79.746 | BK46: Not Available | BL46: Not Available | BM46: Not Available | BN46: 79.746 | BO46: 2585.662 | BP46: 166.899 | BQ46: 4.133 | BR46: 29.863 | BS46: 140.221 | BT46: 262.236 | BU46: 402.457 | BV46: 3189.014 | BW46: 1088324 | BX46: 79076 | BY46: 1090273 | BZ46: 140607 | CA46: =BW46*42/1000 -> 45709.608 | CB46: =BX46*42/1000 -> 3321.192 | CC46: =BY46*42/1000 -> 45791.466 | CD46: =BZ46*42/1000 -> 5905.494
A47: 1993 | P47: 2259.774 | Q47: 169.336 | R47: 2908.446 | S47: 6081.883 | T47: 2891.613 | U47: 185.673 | V47: 65.164 | W47: 30.987 | X47: 2259.774 | Y47: 479.336 | Z47: 169.062 | AA47: 2908.172 | AB47: 6081.609 | AW47: 6.8 | AX47: 60.122 | AY47: 550 | AZ47: 616.922 | BA47: 1.028 | BB47: 3.4 | BC47: 0.224 | BD47: No Data Reported | BE47: 75.597 | BF47: 33.392 | BG47: 0.196 | BH47: 109.185 | BI47: 113.838 | BJ47: 93.66 | BK47: Not Available | BL47: Not Available | BM47: Not Available | BN47: 93.66 | BO47: 2860.991 | BP47: 173.073 | BQ47: 4.767 | BR47: 30.987 | BS47: 149.832 | BT47: 264.787 | BU47: 414.619 | BV47: 3484.438 | BW47: 1143075 | BX47: 67184 | BY47: 1110043 | BZ47: 140867 | CA47: =BW47*42/1000 -> 48009.15 | CB47: =BX47*42/1000 -> 2821.728 | CC47: =BY47*42/1000 -> 46621.806 | CD47: =BZ47*42/1000 -> 5916.414
A48: 1994 | P48: 2323.82 | Q48: 188.391 | R48: 3027.534 | S48: 5987.113 | T48: 2683.457 | U48: 173.464 | V48: 67.097 | W48: 35.56 | X48: 2323.82 | Y48: 515.323 | Z48: 188.391 | AA48: 3027.534 | AB48: 5987.113 | AW48: 6.2 | AX48: 61.77 | AY48: 520 | AZ48: 587.97 | BA48: 0.957 | BB48: 4.2 | BC48: 0.251 | BD48: No Data Reported | BE48: 71.715 | BF48: 34.522 | BG48: 0.185 | BH48: 106.422 | BI48: 111.831 | BJ48: 104.84 | BK48: Not Available | BL48: Not Available | BM48: Not Available | BN48: 104.84 | BO48: 2620.314 | BP48: 160.264 | BQ48: 5.02 | BR48: 35.56 | BS48: 152.335 | BT48: 281.554 | BU48: 433.889 | BV48: 3255.047 | BW48: 1169688 | BX48: 74193 | BY48: 1154217 | BZ48: 145220 | CA48: =BW48*42/1000 -> 49126.896 | CB48: =BX48*42/1000 -> 3116.106 | CC48: =BY48*42/1000 -> 48477.114 | CD48: =BZ48*42/1000 -> 6099.24
A49: 1995 | P49: 2369.869 | Q49: 197.737 | R49: 3099.082 | S49: 6557.275 | T49: 3205.307 | U49: 152.057 | V49: 68.199 | W49: 32.63 | X49: 2369.869 | Y49: 531.476 | Z49: 199.797 | AA49: 3101.142 | AB49: 6559.335 | AW49: 6.6 | AX49: 62.725 | AY49: 520 | AZ49: 589.325 | BA49: 1.22 | BB49: 4.5 | BC49: 0.287 | BD49: No Data Reported | BE49: 72.379 | BF49: 40.198 | BG49: 0.14 | BH49: 112.717 | BI49: 118.724 | BJ49: 112.49 | BK49: Not Available | BL49: Not Available | BM49: Not Available | BN49: 112.49 | BO49: 3149.392 | BP49: 137.957 | BQ49: 5.123 | BR49: 32.63 | BS49: 125.412 | BT49: 296.252 | BU49: 421.664 | BV49: 3746.766 | BW49: 1151735 | BX49: 70601 | BY49: 1170419 | BZ49: 130214 | CA49: =BW49*42/1000 -> 48372.87 | CB49: =BX49*42/1000 -> 2965.242 | CC49: =BY49*42/1000 -> 49157.598 | CD49: =BZ49*42/1000 -> 5468.988
A50: 1996 | P50: 2437.027 | Q50: 141.284 | R50: 3155.301 | S50: 7010.851 | T50: 3589.656 | U50: 163.359 | V50: 69.095 | W50: 33.44 | X50: 2437.027 | Y50: 576.99 | Z50: 142.789 | AA50: 3156.806 | AB50: 7012.356 | AW50: 7 | AX50: 63.302 | AY50: 540 | AZ50: 610.302 | BA50: 1.3 | BB50: 5.3 | BC50: 0.331 | BD50: No Data Reported | BE50: 75.668 | BF50: 53.028 | BG50: 0.144 | BH50: 128.84 | BI50: 135.771 | BJ50: 80.661 | BK50: Not Available | BL50: Not Available | BM50: Not Available | BN50: 80.661 | BO50: 3527.582 | BP50: 148.159 | BQ50: 5.389 | BR50: 33.44 | BS50: 137.86 | BT50: 300.413 | BU50: 438.273 | BV50: 4152.843 | BW50: 1213563 | BX50: 84234 | BY50: 1231679 | BZ50: 126729 | CA50: =BW50*42/1000 -> 50969.646 | CB50: =BX50*42/1000 -> 3537.828 | CC50: =BY50*42/1000 -> 51730.518 | CD50: =BZ50*42/1000 -> 5322.618
A51: 1997 | P51: 2370.991 | Q51: 186.315 | R51: 3107.908 | S51: 7016.768 | T51: 3640.458 | U51: 166.698 | V51: 68.124 | W51: 33.581 | X51: 2370.991 | Y51: 550.602 | Z51: 183.627 | AA51: 3105.22 | AB51: 7014.08 | AW51: 7.5 | AX51: 62.456 | AY51: 430 | AZ51: 499.956 | BA51: 1.228 | BB51: 5.7 | BC51: 0.366 | BD51: No Data Reported | BE51: 73.386 | BF51: 57.607 | BG51: 0.29 | BH51: 131.283 | BI51: 138.577 | BJ51: 101.966 | BK51: Not Available | BL51: Not Available | BM51: Not Available | BN51: 101.966 | BO51: 3581.168 | BP51: 150.398 | BQ51: 5.221 | BR51: 33.581 | BS51: 136.992 | BT51: 308.981 | BU51: 445.973 | BV51: 4216.34 | BW51: 1238041 | BX51: 83102 | BY51: 1253938 | BZ51: 138427 | CA51: =BW51*42/1000 -> 51997.722 | CB51: =BX51*42/1000 -> 3490.284 | CC51: =BY51*42/1000 -> 52665.396 | CD51: =BZ51*42/1000 -> 5813.934
A52: 1998 | P52: 2184.161 | Q52: 202.474 | R52: 2928.93 | S52: 6492.687 | T52: 3297.054 | U52: 168.45 | V52: 67.401 | W52: 30.853 | X52: 2184.161 | Y52: 542.295 | Z52: 201.034 | AA52: 2927.49 | AB52: 6491.248 | AW52: 7.7 | AX52: 61.772 | AY52: 380 | AZ52: 449.472 | BA52: 1.228 | BB52: 7.1 | BC52: 0.413 | BD52: No Data Reported | BE52: 64.014 | BF52: 54.162 | BG52: 0.284 | BH52: 118.46 | BI52: 127.202 | BJ52: 112.843 | BK52: Not Available | BL52: Not Available | BM52: Not Available | BN52: 112.843 | BO52: 3241.286 | BP52: 150.65 | BQ52: 5.124 | BR52: 30.853 | BS52: 136.707 | BT52: 307.789 | BU52: 444.496 | BV52: 3872.408 | BW52: 1249881 | BX52: 76618 | BY52: 1263427 | BZ52: 156075 | CA52: =BW52*42/1000 -> 52495.002 | CB52: =BX52*42/1000 -> 3217.956 | CC52: =BY52*42/1000 -> 53063.934 | CD52: =BZ52*42/1000 -> 6555.15
A53: 1999 | P53: 2214.167 | Q53: 210.809 | R53: 2965.132 | S53: 6515.532 | T53: 3267.575 | U53: 170.921 | V53: 66.01 | W53: 45.894 | X53: 2214.167 | Y53: 540.156 | Z53: 208.967 | AA53: 2963.29 | AB53: 6513.691 | AW53: 8.5 | AX53: 60.358 | AY53: 390 | AZ53: 458.858 | BA53: 1.173 | BB53: 6.7 | BC53: 0.482 | BD53: No Data Reported | BE53: 66.621 | BF53: 53.916 | BG53: 0.211 | BH53: 120.748 | BI53: 129.103 | BJ53: 117.795 | BK53: Not Available | BL53: Not Available | BM53: Not Available | BN53: 117.795 | BO53: 3217.744 | BP53: 151.621 | BQ53: 5.063 | BR53: 45.894 | BS53: 138.026 | BT53: 315.198 | BU53: 453.224 | BV53: 3873.546 | BW53: 1240783 | BX53: 91428 | BY53: 1303779 | BZ53: 125463 | CA53: =BW53*42/1000 -> 52112.886 | CB53: =BX53*42/1000 -> 3839.976 | CC53: =BY53*42/1000 -> 54758.718 | CD53: =BZ53*42/1000 -> 5269.446
A54: 2000 | P54: 2261.715 | Q54: 233.146 | R54: 3005.661 | S54: 6101.604 | T54: 2811.116 | U54: 164.364 | V54: 63.406 | W54: 57.057 | X54: 2261.715 | Y54: 510.8 | Z54: 235.712 | AA54: 3008.227 | AB54: 6104.171 | AW54: 8.6 | AX54: 57.707 | AY54: 420 | AZ54: 486.307 | BA54: 1.018 | BB54: 7.6 | BC54: 0.546 | BD54: No Data Reported | BE54: 71.469 | BF54: 47.256 | BG54: 0.376 | BH54: 119.101 | BI54: 128.265 | BJ54: 134.887 | BK54: Not Available | BL54: Not Available | BM54: Not Available | BN54: 134.887 | BO54: 2767.916 | BP54: 143.764 | BQ54: 5.033 | BR54: 57.057 | BS54: 134.321 | BT54: 318.433 | BU54: 452.754 | BV54: 3426.524 | BW54: 1310158 | BX54: 107919 | BY54: 1362315 | BZ54: 118027 | CA54: =BW54*42/1000 -> 55026.636 | CB54: =BX54*42/1000 -> 4532.598 | CC54: =BY54*42/1000 -> 57217.23 | CD54: =BZ54*42/1000 -> 4957.134
A55: 2001 | B55: 1.109 | C55: 0.015 | D55: =(G55/F55)*C55/1000 -> 1.9132564e-06 | E55: 204.203 | F55: 8.577 | G55: 1.094 | H55: 80.922 | I55: 40.646 | J55: 40.276 | K55: Not Available | L55: Not Available | M55: 244.479 | N55: 10.268 | O55: 1.31 | P55: 2005.834 | Q55: 254.453 | R55: 2624.162 | S55: 5161.695 | T55: 2241.858 | U55: 164.461 | V55: 61.597 | W55: 69.617 | X55: 2005.834 | Y55: 363.875 | Z55: 252.647 | AA55: 2622.356 | AB55: 5159.889 | AW55: 9.45 | AX55: 55.172 | AY55: 370 | AZ55: 434.622 | BA55: 0.687 | BB55: 8.27 | BC55: 0.668 | BD55: No Data Reported | BE55: 66.788 | BF55: 24.545 | BG55: 0.329 | BH55: 91.661 | BI55: 101.286 | BJ55: 140.822 | BK55: 1.31 | BL55: Not Available | BM55: Not Available | BN55: 142.132 | BO55: 2208.671 | BP55: 141.981 | BQ55: 5.608 | BR55: 69.617 | BS55: 126.402 | BT55: 210.736 | BU55: 337.138 | BV55: 2763.015 | BW55: 1348525 | BX55: 125586 | BY55: 1404082 | BZ55: 144513 | CA55: =BW55*42/1000 -> 56638.05 | CB55: =BX55*42/1000 -> 5274.612 | CC55: =BY55*42/1000 -> 58971.444 | CD55: =BZ55*42/1000 -> 6069.546 | CF55: 42
A56: 2002 | B56: 1.356 | C56: 0.018 | D56: =(G56/F56)*C56/1000 -> 2.2972148e-06 | E56: 249.62 | F56: 10.484 | G56: 1.338 | H56: 197.342 | I56: 57.426 | J56: 139.916 | K56: Not Available | L56: Not Available | M56: 389.536 | N56: 16.361 | O56: 2.088 | P56: 1995.284 | Q56: 308.118 | R56: 2705.406 | S56: 5730.811 | T56: 2689.017 | U56: 171.164 | V56: 59.89 | W56: 105.334 | X56: 1995.284 | Y56: 402.004 | Z56: 303.333 | AA56: 2700.621 | AB56: 5726.026 | AW56: 10.204 | AX56: 53.293 | AY56: 380 | AZ56: 443.497 | BA56: 0.13 | BB56: 8.753 | BC56: 0.78 | BD56: No Data Reported | BE56: 68.658 | BF56: 25.877 | BG56: 0.459 | BH56: 94.994 | BI56: 104.657 | BJ56: 167.587 | BK56: 2.088 | BL56: Not Available | BM56: Not Available | BN56: 169.675 | BO56: 2649.979 | BP56: 147.42 | BQ56: 5.644 | BR56: 105.334 | BS56: 150.192 | BT56: 229.782 | BU56: 379.974 | BV56: 3288.351 | BW56: 1311151 | BX56: 97603 | BY56: 1378206 | BZ56: 134085 | CA56: =BW56*42/1000 -> 55068.342 | CB56: =BX56*42/1000 -> 4099.326 | CC56: =BY56*42/1000 -> 57884.652 | CD56: =BZ56*42/1000 -> 5631.57
A57: 2003 | B57: 1.838 | C57: 0.025 | D57: =(G57/F57)*C57/1000 -> 3.1896552e-06 | E57: 338.322 | F57: 14.21 | G57: 1.813 | H57: 96.804 | I57: 113.467 | J57: -16.662 | K57: Not Available | L57: Not Available | M57: 321.66 | N57: 13.51 | O57: 1.724 | P57: 2002.037 | Q57: 401.394 | R57: 2804.778 | S57: 5942.362 | T57: 2792.539 | U57: 173.445 | V57: 58.327 | W57: 113.273 | X57: 2002.037 | Y57: 401.347 | Z57: 403.087 | AA57: 2806.471 | AB57: 5944.055 | AW57: 13 | AX57: 51.813 | AY57: 400 | AZ57: 464.813 | BA57: 0.731 | BB57: 11 | BC57: 0.906 | BD57: No Data Reported | BE57: 71.435 | BF57: 29.026 | BG57: 0.823 | BH57: 101.284 | BI57: 113.922 | BJ57: 228.086 | BK57: 1.724 | BL57: Not Available | BM57: Not Available | BN57: 229.81 | BO57: 2749.056 | BP57: 146.045 | BQ57: 5.407 | BR57: 113.273 | BS57: 167.287 | BT57: 229.882 | BU57: 397.169 | BV57: 3410.95 | BW57: 1353138 | BX57: 121672 | BY57: 1433373 | BZ57: 136542 | CA57: =BW57*42/1000 -> 56831.796 | CB57: =BX57*42/1000 -> 5110.224 | CC57: =BY57*42/1000 -> 60201.666 | CD57: =BZ57*42/1000 -> 5734.764
A58: 2004 | B58: 3.62 | C58: 0.049 | D58: =(G58/F58)*C58/1000 -> 6.2515188e-06 | E58: 666.237 | F58: 27.982 | G58: 3.57 | H58: 100.541 | I58: 127.716 | J58: -27.175 | K58: Not Available | L58: Not Available | M58: 639.062 | N58: 26.841 | O58: 3.425 | P58: 2121.252 | Q58: 485.722 | R58: 2996.017 | S58: 6062.542 | T58: 2688.468 | U58: 178.147 | V58: 58.247 | W58: 141.664 | X58: 2121.252 | Y58: 389.043 | Z58: 497.777 | AA58: 3008.073 | AB58: 6074.598 | AW58: 14 | AX58: 51.13 | AY58: 410 | AZ58: 475.13 | BA58: 1.051 | BB58: 12 | BC58: 1.111 | BD58: No Data Reported | BE58: 70.328 | BF58: 34.237 | BG58: 0.755 | BH58: 105.319 | BI58: 119.481 | BJ58: 286.29 | BK58: 3.425 | BL58: Not Available | BM58: Not Available | BN58: 289.715 | BO58: 2654.88 | BP58: 148.347 | BQ58: 5.761 | BR58: 141.664 | BS58: 165.189 | BT58: 222.877 | BU58: 388.066 | BV58: 3338.717 | BW58: 1396037 | BX58: 119118 | BY58: 1485324 | BZ58: 126272 | CA58: =BW58*42/1000 -> 58633.554 | CB58: =BX58*42/1000 -> 5002.956 | CC58: =BY58*42/1000 -> 62383.608 | CD58: =BZ58*42/1000 -> 5303.424
A59: 2005 | B59: 11.744 | C59: 0.16 | D59: =(G59/F59)*C59/1000 -> 2.0415258e-05 | E59: 2161.586 | F59: 90.787 | G59: 11.584 | H59: 213.69 | I59: 212.708 | J59: 0.982 | K59: Not Available | L59: Not Available | M59: 2162.568 | N59: 90.828 | O59: 11.589 | P59: 2136.697 | Q59: 561.27 | R59: 3101.186 | S59: 6220.62 | T59: 2702.942 | U59: 180.703 | V59: 57.701 | W59: 178.088 | X59: 2136.697 | Y59: 403.219 | Z59: 574.014 | AA59: 3113.93 | AB59: 6233.364 | AW59: 15.9 | AX59: 50.167 | AY59: 430 | AZ59: 496.067 | BA59: 0.86 | BB59: 13.6 | BC59: 1.664 | BD59: No Data Reported | BE59: 69.995 | BF59: 34.249 | BG59: 0.879 | BH59: 105.122 | BI59: 121.246 | BJ59: 327.426 | BK59: 11.589 | BL59: Not Available | BM59: Not Available | BN59: 339.016 | BO59: 2670.131 | BP59: 146.903 | BQ59: 5.502 | BR59: 178.088 | BS59: 184.973 | BT59: 220.722 | BU59: 405.695 | BV59: 3406.319 | BW59: 1443348 | BX59: 120009 | BY59: 1503074 | BZ59: 136022 | CA59: =BW59*42/1000 -> 60620.616 | CB59: =BX59*42/1000 -> 5040.378 | CC59: =BY59*42/1000 -> 63129.108 | CD59: =BZ59*42/1000 -> 5712.924
A60: 2006 | B60: 32.396 | C60: 0.441 | D60: =(G60/F60)*C60/1000 -> 5.626981e-05 | E60: 5962.838 | F60: 250.439 | G60: 31.955 | H60: 1105.315 | I60: 855.62 | J60: 249.695 | K60: Not Available | L60: Not Available | M60: 6212.534 | N60: 260.926 | O60: 33.293 | P60: 2099.319 | Q60: 715.635 | R60: 3211.515 | S60: 6585.965 | T60: 2869.035 | U60: 181.2 | V60: 60.477 | W60: 263.738 | X60: 2099.319 | Y60: 396.561 | Z60: 766.26 | AA60: 3262.14 | AB60: 6636.59 | AW60: 18.3 | AX60: 52.501 | AY60: 380 | AZ60: 450.801 | BA60: 0.927 | BB60: 14 | BC60: 2.407 | BD60: No Data Reported | BE60: 65.106 | BF60: 36.309 | BG60: 1.251 | BH60: 102.666 | BI60: 120 | BJ60: 441.702 | BK60: 33.293 | BL60: Not Available | BM60: Not Available | BN60: 474.995 | BO60: 2839.353 | BP60: 144.5 | BQ60: 5.036 | BR60: 263.738 | BS60: 181.815 | BT60: 230.667 | BU60: 412.482 | BV60: 3665.109 | BW60: 1474741 | BX60: 133126 | BY60: 1521731 | BZ60: 143651 | CA60: =BW60*42/1000 -> 61939.122 | CB60: =BX60*42/1000 -> 5591.292 | CC60: =BY60*42/1000 -> 63912.702 | CD60: =BZ60*42/1000 -> 6033.342
A61: 2007 | B61: 63.362 | C61: 0.863 | D61: =(G61/F61)*C61/1000 -> 0.0001101141 | E61: 11662.499 | F61: 489.825 | G61: 62.499 | H61: 3454.964 | I61: 6695.843 | J61: -3240.879 | K61: Not Available | L61: Not Available | M61: 8421.62 | N61: 353.708 | O61: 45.131 | P61: 2088.775 | Q61: 970.07 | R61: 3472.08 | S61: 6509.975 | T61: 2446.389 | U61: 185.774 | V61: 65.229 | W61: 340.503 | X61: 2088.775 | Y61: 413.235 | Z61: 982.814 | AA61: 3484.824 | AB61: 6522.719 | AW61: 22 | AX61: 55.046 | AY61: 420 | AZ61: 497.046 | BA61: 0.764 | BB61: 14.4 | BC61: 3.386 | BD61: No Data Reported | BE61: 69.796 | BF61: 30.96 | BG61: 1.966 | BH61: 102.723 | BI61: 121.273 | BJ61: 556.791 | BK61: 45.131 | BL61: Not Available | BM61: Not Available | BN61: 601.922 | BO61: 2429.909 | BP61: 144.674 | BQ61: 6.047 | BR61: 340.503 | BS61: 185.956 | BT61: 237.492 | BU61: 423.447 | BV61: 3344.581 | BW61: 1508530 | BX61: 110997 | BY61: 1531508 | BZ61: 133944 | CA61: =BW61*42/1000 -> 63358.26 | CB61: =BX61*42/1000 -> 4661.874 | CC61: =BY61*42/1000 -> 64323.336 | CD61: =BZ61*42/1000 -> 5625.648
A62: 2008 | B62: 87.718 | C62: 1.195 | D62: =(G62/F62)*C62/1000 -> 0.00015247614 | E62: 16145.382 | F62: 678.106 | G62: 86.523 | H62: 7755.03 | I62: 16672.9 | J62: -8917.869 | K62: Not Available | L62: Not Available | M62: 7227.513 | N62: 303.556 | O62: 38.732 | P62: 2058.985 | Q62: 1374.001 | R62: 3868.25 | S62: 7190.918 | T62: 2511.108 | U62: 192.433 | V62: 73.579 | W62: 545.548 | X62: 2058.985 | Y62: 435.263 | Z62: 1357.144 | AA62: 3851.392 | AB62: 7174.061 | AW62: 26.4 | AX62: 58.435 | AY62: 470 | AZ62: 554.835 | BA62: 0.591 | BB62: 14.8 | BC62: 5.426 | BD62: No Data Reported | BE62: 72.903 | BF62: 34.214 | BG62: 2.13 | BH62: 109.247 | BI62: 130.064 | BJ62: 785.844 | BK62: 38.732 | BL62: Not Available | BM62: Not Available | BN62: 824.576 | BO62: 2494.003 | BP62: 146.233 | BQ62: 8.516 | BR62: 545.548 | BS62: 177.348 | BT62: 257.926 | BU62: 435.274 | BV62: 3629.575 | BW62: 1571539 | BX62: 77930 | BY62: 1444024 | BZ62: 146013 | CA62: =BW62*42/1000 -> 66004.638 | CB62: =BX62*42/1000 -> 3273.06 | CC62: =BY62*42/1000 -> 60649.008 | CD62: =BZ62*42/1000 -> 6132.546
A63: 2009 | B63: 66.723 | C63: 0.909 | D63: =(G63/F63)*C63/1000 -> 0.00011598361 | E63: 12281.071 | F63: 515.805 | G63: 65.814 | H63: 1905.877 | I63: 6546.089 | J63: -4640.212 | K63: 711 | L63: 711 | M63: 7662.667 | N63: 321.832 | O63: 41.064 | P63: 1935.01 | Q63: 1569.92 | R63: 3956.617 | S63: 7624.096 | T63: 2668.824 | U63: 200.185 | V63: 77.341 | W63: 721.129 | X63: 1935.01 | Y63: 451.687 | Z63: 1553.312 | AA63: 3940.009 | AB63: 7607.488 | AW63: 32.8 | AX63: 59.822 | AY63: 504 | AZ63: 596.622 | BA63: 0.692 | BB63: 16.7 | BC63: 7.223 | BD63: 0.002 | BE63: 72.595 | BF63: 36.355 | BG63: 2.821 | BH63: 111.771 | BI63: 136.387 | BJ63: 893.9 | BK63: 41.064 | BL63: Not Available | BM63: Not Available | BN63: 934.964 | BO63: 2649.898 | BP63: 146.485 | BQ63: 8.697 | BR63: 721.127 | BS63: 180.046 | BT63: 260.966 | BU63: 441.012 | BV63: 3967.218 | BW63: 1477534 | BX63: 82172 | BY63: 1325344 | BZ63: 165964 | CA63: =BW63*42/1000 -> 62056.428 | CB63: =BX63*42/1000 -> 3451.224 | CC63: =BY63*42/1000 -> 55664.448 | CD63: =BZ63*42/1000 -> 6970.488
A64: 2010 | B64: 44.427 | C64: 0.605 | D64: =(G64/F64)*C64/1000 -> 7.7195213e-05 | E64: 8177.264 | F64: 343.445 | G64: 43.822 | H64: 563.956 | I64: 2587.966 | J64: -2024.009 | K64: 672 | L64: -39 | M64: 6192.255 | N64: 260.075 | O64: 33.184 | P64: 2216.74 | Q64: 1867.88 | R64: 4552.532 | S64: 8312.486 | T64: 2538.541 | U64: 207.979 | V64: 90.007 | W64: 923.427 | X64: 2216.74 | Y64: 467.912 | Z64: 1820.977 | AA64: 4505.629 | AB64: 8265.583 | AW64: 36.8 | AX64: 64.713 | AY64: 540.526 | AZ64: 642.039 | BA64: 0.785 | BB64: 18.5 | BC64: 11.073 | BD64: 0.157 | BE64: 71.617 | BF64: 35.959 | BG64: 3.307 | BH64: 110.883 | BI64: 141.397 | BJ64: 1041.351 | BK64: 33.184 | BL64: Not Available | BM64: Not Available | BN64: 1074.536 | BO64: 2521.486 | BP64: 148.479 | BQ64: 11.762 | BR64: 923.271 | BS64: 195.597 | BT64: 263.775 | BU64: 459.372 | BV64: 4064.369 | BW64: 1541503 | BX64: 83379 | BY64: 1387115 | BZ64: 164306 | CA64: =BW64*42/1000 -> 64743.126 | CB64: =BX64*42/1000 -> 3501.918 | CC64: =BY64*42/1000 -> 58258.83 | CD64: =BZ64*42/1000 -> 6900.852
A65: 2011 | B65: 125.151 | C65: 1.705 | D65: =(G65/F65)*C65/1000 -> 0.00021754994 | E65: 23035.269 | F65: 967.481 | G65: 123.446 | H65: 890.373 | I65: 1798.618 | J65: -908.245 | K65: 2004.622 | L65: 1027.721 | M65: 21099.303 | N65: 886.171 | O65: 113.071 | P65: 2213.22 | Q65: 2037.424 | R65: 4712.436 | S65: 9305.589 | T65: 3102.852 | U65: 212.311 | V65: 110.354 | W65: 1167.636 | X65: 2213.22 | Y65: 461.793 | Z65: 1941.48 | AA65: 4616.493 | AB65: 9209.646 | AC65: 1477.174 | AD65: 62.041 | AE65: 8.116 | AG65: 7 | AH65: 7 | AI65: 1470.174 | AJ65: 61.747 | AK65: 8.077 | AW65: 39.6 | AX65: 70.793 | AY65: 524.264 | AZ65: 634.657 | BA65: 0.249 | BB65: 19.7 | BC65: 18.743 | BD65: 0.494 | BE65: 69.159 | BF65: 42.543 | BG65: 2.899 | BH65: 114.601 | BI65: 153.787 | BJ65: 1044.999 | BK65: 113.071 | BL65: 8.077 | BM65: Not Available | BN65: 1166.147 | BO65: 3085.127 | BP65: 148.811 | BQ65: 16.782 | BR65: 1167.094 | BS65: 182.159 | BT65: 254.568 | BU65: 436.727 | BV65: 4854.541 | BW65: 1639606 | BX65: 65234 | BY65: 1423082 | BZ65: 149212 | CA65: =BW65*42/1000 -> 68863.452 | CB65: =BX65*42/1000 -> 2739.828 | CC65: =BY65*42/1000 -> 59769.444 | CD65: =BZ65*42/1000 -> 6266.904
A66: 2012 | B66: 128.156 | C66: 1.746 | D66: =(G66/F66)*C66/1000 -> 0.00022278128 | E66: 23588.36 | F66: 990.711 | G66: 126.41 | H66: 853 | I66: 3055.762 | J66: -2202.762 | K66: 1984.356 | L66: -20.266 | M66: 21405.864 | N66: 899.046 | O66: 114.714 | P66: 2151.213 | Q66: 1935.741 | R66: 4553.559 | S66: 8889.502 | T66: 2628.702 | U66: 211.592 | V66: 155.59 | W66: 1340.059 | X66: 2151.213 | Y66: 466.604 | Z66: 1899.134 | AA66: 4516.951 | AB66: 8852.895 | AC66: 1247.645 | AD66: 52.401 | AE66: 6.855 | AF66: 605 | AG66: 94 | AH66: 87 | AI66: 1765.645 | AJ66: 74.157 | AK66: 9.7 | AW66: 39.6 | AX66: 78.839 | AY66: 438.095 | AZ66: 556.533 | BA66: 0.262 | BB66: 19.7 | BC66: 30.541 | BD66: 0.513 | BE66: 60.683 | BF66: 45.247 | BG66: 2.553 | BH66: 108.483 | BI66: 159.499 | BJ66: 1044.606 | BK66: 114.714 | BL66: 9.7 | BM66: Not Available | BN66: 1169.02 | BO66: 2606.047 | BP66: 148.092 | BQ66: 39.625 | BR66: 1339.365 | BS66: 190.191 | BT66: 262.453 | BU66: 452.644 | BV66: 4585.773 | BW66: 1665256 | BX66: 46179 | BY66: 1369358 | BZ66: 134809 | CA66: =BW66*42/1000 -> 69940.752 | CB66: =BX66*42/1000 -> 1939.518 | CC66: =BY66*42/1000 -> 57513.036 | CD66: =BZ66*42/1000 -> 5661.978
A67: 2013 | B67: 175.855 | C67: 2.395 | D67: =(G67/F67)*C67/1000 -> 0.0003055904 | E67: 32368.005 | F67: 1359.456 | G67: 173.46 | H67: 8152 | I67: 4674.657 | J67: 3477.343 | K67: 3809.709 | L67: 1825.354 | M67: 34019.994 | N67: 1428.84 | O67: 182.313 | P67: 2338.256 | Q67: 2000.104 | R67: 4834.795 | S67: 9438.028 | T67: 2562.382 | U67: 214.006 | V67: 225.486 | W67: 1601.359 | X67: 2338.256 | Y67: 496.436 | Z67: 2026.344 | AA67: 4861.035 | AB67: 9464.269 | AC67: 2697.282 | AD67: 113.286 | AE67: 14.819 | AF67: 4921 | AG67: 691 | AH67: 597 | AI67: 7021.282 | AJ67: 294.894 | AK67: 38.575 | AW67: 39.6 | AX67: 91.422 | AY67: 571.655 | AZ67: 702.677 | BA67: 0.419 | BB67: 19.7 | BC67: 41.983 | BD67: 0.58 | BE67: 70.164 | BF67: 47.076 | BG67: 2.666 | BH67: 119.906 | BI67: 182.588 | BJ67: 1071.607 | BK67: 182.313 | BL67: 38.575 | BM67: Not Available | BN67: 1292.495 | BO67: 2528.923 | BP67: 150.506 | BQ67: 83.24 | BR67: 1600.424 | BS67: 207.426 | BT67: 262.185 | BU67: 469.611 | BV67: 4832.704 | BW67: 1727493 | BX67: 56465 | BY67: 1397025 | BZ67: 127543 | CA67: =BW67*42/1000 -> 72554.706 | CB67: =BX67*42/1000 -> 2371.53 | CC67: =BY67*42/1000 -> 58675.05 | CD67: =BZ67*42/1000 -> 5356.806
A68: 2014 | B68: 165.445 | C68: 2.253 | D68: =(G68/F68)*C68/1000 -> 0.00028747272 | E68: 30451.874 | F68: 1278.979 | G68: 163.192 | H68: 4578 | I68: 1974.269 | J68: 2603.731 | K68: 3130.619 | L68: -679.091 | M68: 33734.696 | N68: 1416.857 | O68: 180.784 | P68: 2401.078 | Q68: 2135.145 | R68: 5052.1 | S68: 9797.649 | T68: 2466.317 | U68: 214.474 | V68: 337.397 | W68: 1727.36 | X68: 2401.078 | Y68: 515.877 | Z68: 2098.567 | AA68: 5015.522 | AB68: 9761.071 | AC68: 3789.076 | AD68: 159.141 | AE68: 20.817 | AF68: 2873 | AG68: 350 | AH68: -341 | AI68: 7003.076 | AJ68: 294.129 | AK68: 38.475 | AN68: 290.47 | AO68: 12.2 | AP68: 1.557 | AR68: 7 | AS68: 2 | AT68: 288.47 | AU68: 12.116 | AV68: 1.546 | AW68: 39.6 | AX68: 109.408 | AY68: 578.535 | AZ68: 727.543 | BA68: 0.365 | BB68: 19.7 | BC68: 52.454 | BD68: 1.013 | BE68: 76.289 | BF68: 46.963 | BG68: 3.631 | BH68: 126.883 | BI68: 200.415 | BJ68: 1093.489 | BK68: 180.784 | BL68: 38.475 | BM68: 1.546 | BN68: 1314.294 | BO68: 2453.761 | BP68: 150.974 | BQ68: 164.545 | BR68: 1725.845 | BS68: 251.253 | BT68: 278.89 | BU68: 530.143 | BV68: 5025.268 | BW68: 1794433 | BX68: 71050 | BY68: 1473595 | BZ68: 136286 | CA68: =BW68*42/1000 -> 75366.186 | CB68: =BX68*42/1000 -> 2984.1 | CC68: =BY68*42/1000 -> 61890.99 | CD68: =BZ68*42/1000 -> 5724.012
A69: 2015 | B69: 163.423 | C69: 2.226 | D69: =(G69/F69)*C69/1000 -> 0.00028402689 | E69: 30079.688 | F69: 1263.347 | G69: 161.197 | H69: 8399 | I69: 2090.757 | J69: 6308.243 | K69: 3943.299 | L69: 812.681 | M69: 35575.25 | N69: 1494.161 | O69: 190.648 | P69: 2311.768 | Q69: 2201.209 | R69: 5031.349 | S69: 6845.927 | T69: 849.861 | U69: 117.811 | V69: 196.175 | W69: 650.732 | X69: 2311.768 | Y69: 518.371 | Z69: 2184.748 | AA69: 5014.887 | AB69: 6829.465 | AC69: 4210.658 | AD69: 176.848 | AE69: 23.133 | AF69: 4874 | AG69: 634 | AH69: 284 | AI69: 8800.658 | AJ69: 369.628 | AK69: 48.351 | AN69: 393.374 | AO69: 16.522 | AP69: 2.108 | AR69: 4 | AS69: -3 | AT69: 396.374 | AU69: 16.648 | AV69: 2.124 | AW69: 39.6 | AX69: 128.181 | AY69: 512.736 | AZ69: 680.517 | BA69: 0.325 | BB69: 19.7 | BC69: 56.868 | BD69: 1.103 | BE69: 79.288 | BF69: 47.029 | BG69: 25.588 | BH69: 151.905 | BI69: 229.901 | BJ69: 1109.915 | BK69: 190.648 | BL69: 48.351 | BM69: 2.124 | BN69: 1351.038 | BO69: 2306.479 | BP69: 148.256 | BQ69: 227.779 | BR69: 1774.753 | BS69: 243.857 | BT69: 281.022 | BU69: 524.879 | BV69: 4982.145 | BW69: 1818780 | BX69: 73178 | BY69: 1458262 | BZ69: 161326 | CA69: =BW69*42/1000 -> 76388.76 | CB69: =BX69*42/1000 -> 3073.476 | CC69: =BY69*42/1000 -> 61247.004 | CD69: =BZ69*42/1000 -> 6775.692
A70: 2016 | B70: 202.797 | C70: 2.762 | D70: =(G70/F70)*C70/1000 -> 0.00035241825 | E70: 37326.894 | F70: 1567.73 | G70: 200.035 | H70: 16879 | I70: 2098.187 | J70: 14780.813 | K70: 6397.74 | L70: 2454.44 | M70: 49653.267 | N70: 2085.437 | O70: 266.092 | P70: 2299.14 | Q70: 2329.398 | R70: 5131.757 | S70: 7188.417 | T70: 913.775 | U70: 117.498 | V70: 250.888 | W70: 774.499 | X70: 2226.565 | Y70: 503.219 | Z70: 2333.27 | AA70: 5063.054 | AB70: 7119.713 | AC70: 5749.701 | AD70: 241.487 | AE70: 31.589 | AF70: 5304 | AG70: 1315 | AH70: 681 | AI70: 10372.701 | AJ70: 435.653 | AK70: 56.988 | AN70: 503.469 | AO70: 21.146 | AP70: 2.698 | AR70: 43 | AS70: 39 | AT70: 464.469 | AU70: 19.508 | AV70: 2.489 | AW70: 39.6 | AX70: 161.454 | AY70: 444.642 | AZ70: 645.695 | BA70: 2.003 | BB70: 19.7 | BC70: 61.708 | BD70: 1.213 | BE70: 83.74 | BF70: 48.131 | BG70: 25.798 | BH70: 157.67 | BI70: 242.294 | BJ70: 1143.043 | BK70: 266.092 | BL70: 56.988 | BM70: 2.489 | BN70: 1468.612 | BO70: 2457.656 | BP70: 146.041 | BQ70: 327.57 | BR70: 2092.821 | BS70: 224.407 | BT70: 280.662 | BU70: 505.069 | BV70: 5529.156 | BW70: 1769335 | BX70: 53642 | BY70: 1419074 | BZ70: 166095 | CA70: =BW70*42/1000 -> 74312.07 | CB70: =BX70*42/1000 -> 2252.964 | CC70: =BY70*42/1000 -> 59601.108 | CD70: =BZ70*42/1000 -> 6975.99
A71: 2017 | B71: 206.416 | C71: 2.811 | D71: =(G71/F71)*C71/1000 -> 0.00035867044 | E71: 37993.065 | F71: 1595.709 | G71: 203.605 | H71: 9374 | I71: 2228.249 | J71: 7145.751 | K71: 4267.949 | L71: -2129.793 | M71: 47268.609 | N71: 1985.282 | O71: 253.312 | P71: 2263.583 | Q71: 2406.87 | R71: 5165.713 | S71: 7504.595 | T71: 1024.736 | U71: 117.842 | V71: 328.623 | W71: 867.681 | X71: 2184.957 | Y71: 495.26 | Z71: 2364.382 | AA71: 5044.598 | AB71: 7383.48 | AC71: 6151.003 | AD71: 258.342 | AE71: 33.794 | AF71: 4509 | AG71: 753 | AH71: -562 | AI71: 11222.003 | AJ71: 471.324 | AK71: 61.654 | AN71: 570.324 | AO71: 23.954 | AP71: 3.056 | AR71: 28 | AS71: -15 | AT71: 585.324 | AU71: 24.584 | AV71: 3.137 | AW71: 39.6 | AX71: 193.328 | AY71: 429.579 | AZ71: 662.506 | BA71: 2.207 | BB71: 19.7 | BC71: 75.559 | BD71: 1.328 | BE71: 83.73 | BF71: 47.506 | BG71: 25.15 | BH71: 156.386 | BI71: 255.18 | BJ71: 1155.55 | BK71: 253.312 | BL71: 61.654 | BM71: 3.137 | BN71: 1473.653 | BO71: 2750.53 | BP71: 146.654 | BQ71: 485.478 | BR71: 2339.514 | BS71: 229.324 | BT71: 280.217 | BU71: 509.541 | BV71: 6231.717 | BW71: 1833879 | BX71: 54975 | BY71: 1435249 | BZ71: 145638 | CA71: =BW71*42/1000 -> 77022.918 | CB71: =BX71*42/1000 -> 2308.95 | CC71: =BY71*42/1000 -> 60280.458 | CD71: =BZ71*42/1000 -> 6116.796
A72: 2018 | B72: 240.257 | C72: 3.272 | D72: =(G72/F72)*C72/1000 -> 0.00041749151 | E72: 44221.87 | F72: 1857.319 | G72: 236.985 | H72: 3969 | I72: 2470.295 | J72: 1498.705 | K72: 4662.217 | L72: 394.266 | M72: 45326.309 | N72: 1903.705 | O72: 242.904 | P72: 2356.054 | Q72: 2470.746 | R72: 5314.147 | S72: 7744.195 | T72: 998.092 | U72: 117.98 | V72: 383.634 | W72: 930.341 | X72: 2261.996 | Y72: 487.347 | Z72: 2355.17 | AA72: 5104.513 | AB72: 7534.561 | AC72: 7273.439 | AD72: 305.484 | AE72: 39.96 | AF72: 4124 | AG72: 1727 | AH72: 974 | AI72: 10423.439 | AJ72: 437.784 | AK72: 57.266 | AN72: 610.959 | AO72: 25.66 | AP72: 3.274 | AR72: 54 | AS72: 26 | AT72: 584.959 | AU72: 24.568 | AV72: 3.135 | AW72: 39.6 | AX72: 220.694 | AY72: 524.859 | AZ72: 785.154 | BA72: 2.068 | BB72: 20.004 | BC72: 93.924 | BD72: 1.584 | BE72: 84.073 | BF72: 46.924 | BG72: 25.477 | BH72: 156.474 | BI72: 274.054 | BJ72: 1152.42 | BK72: 242.904 | BL72: 57.266 | BM72: 3.135 | BN72: 1455.725 | BO72: 2648.861 | BP72: 144.965 | BQ72: 575.474 | BR72: 2478.263 | BS72: 221.063 | BT72: 275.021 | BU72: 496.085 | BV72: 6343.648 | BW72: 1886341 | BX72: 63769 | BY72: 1513227 | BZ72: 140162 | CA72: =BW72*42/1000 -> 79226.322 | CB72: =BX72*42/1000 -> 2678.298 | CC72: =BY72*42/1000 -> 63555.534 | CD72: =BZ72*42/1000 -> 5886.804
A73: 2019 | B73: 223.077 | C73: 3.038 | D73: =(G73/F73)*C73/1000 -> 0.00038763454 | E73: 41059.68 | F73: 1724.507 | G73: 220.039 | H73: 4078 | I73: 2730.357 | J73: 1347.643 | K73: 3906.621 | L73: -755.596 | M73: 43162.919 | N73: 1812.843 | O73: 231.31 | P73: 2340.959 | Q73: 2431.597 | R73: 5215.002 | S73: 7752.818 | T73: 982.225 | U73: 116.293 | V73: 429.747 | W73: 1009.551 | X73: 2237.315 | Y73: 442.447 | Z73: 2376.238 | AA73: 5056 | AB73: 7593.816 | AC73: 11714.559 | AD73: 492.011 | AE73: 64.36 | AF73: 6143 | AG73: 1491 | AH73: -236 | AI73: 18093.559 | AJ73: 759.929 | AK73: 99.406 | AN73: 791.153 | AO73: 33.228 | AP73: 4.24 | AR73: 50 | AS73: -4 | AT73: 795.153 | AU73: 33.396 | AV73: 4.261 | AW73: 39.6 | AX73: 251.141 | AY73: 545.509 | AZ73: 836.25 | BA73: 1.675 | BB73: 23.631 | BC73: 103.126 | BD73: 1.591 | BE73: 84.299 | BF73: 39.04 | BG73: 25.934 | BH73: 149.273 | BI73: 279.296 | BJ73: 1161.614 | BK73: 231.31 | BL73: 99.406 | BM73: 4.261 | BN73: 1496.591 | BO73: 2550.917 | BP73: 133.761 | BQ73: 634.185 | BR73: 2630.58 | BS73: 200.524 | BT73: 247.613 | BU73: 448.137 | BV73: 6397.579 | BW73: 1875015 | BX73: 73886 | BY73: 1497761 | BZ73: 140083 | CA73: =BW73*42/1000 -> 78750.63 | CB73: =BX73*42/1000 -> 3103.212 | CC73: =BY73*42/1000 -> 62905.962 | CD73: =BZ73*42/1000 -> 5883.486
A74: 2020 | B74: 234.744 | C74: 3.197 | D74: =(G74/F74)*C74/1000 -> 0.00040792229 | E74: 43207.097 | F74: 1814.698 | G74: 231.547 | H74: 4684 | I74: 3457.503 | J74: 1226.497 | K74: 3665.385 | L74: -241.235 | M74: 44674.829 | N74: 1876.343 | O74: 239.412 | P74: 2075.638 | Q74: 2194.401 | R74: 4709.773 | S74: 7465.203 | T74: 973.355 | U74: 117.716 | V74: 511.315 | W74: 1153.045 | X74: 1969.603 | Y74: 439.734 | Z74: 2135.793 | AA74: 4545.13 | AB74: 7300.56 | AC74: 12702.251 | AD74: 533.495 | AE74: 69.786 | AF74: 6658 | AG74: 1287 | AH74: -204 | AI74: 19564.251 | AJ74: 821.699 | AK74: 107.486 | AN74: 761.175 | AO74: 31.969 | AP74: 4.079 | AR74: 27 | AS74: -23 | AT74: 784.175 | AU74: 32.935 | AV74: 4.202 | AW74: 39.6 | AX74: 286.037 | AY74: 440.208 | AZ74: 765.845 | BA74: 1.873 | BB74: 23.636 | BC74: 117.875 | BD74: 1.472 | BE74: 82.95 | BF74: 37.854 | BG74: 26.182 | BH74: 146.986 | BI74: 291.842 | BJ74: 1004.386 | BK74: 239.412 | BL74: 107.486 | BM74: 4.202 | BN74: 1355.487 | BO74: 2490.348 | BP74: 135.369 | BQ74: 775.98 | BR74: 2955.82 | BS74: 185.374 | BT74: 242.199 | BU74: 427.573 | BV74: 6785.09 | BW74: 1733958 | BX74: 79789 | BY74: 1385590 | BZ74: 161188 | CA74: =BW74*42/1000 -> 72826.236 | CB74: =BX74*42/1000 -> 3351.138 | CC74: =BY74*42/1000 -> 58194.78 | CD74: =BZ74*42/1000 -> 6769.896
A75: 2021 | B75: 221.049 | C75: 3.011 | D75: =(G75/F75)*C75/1000 -> 0.00038418916 | E75: 40686.325 | F75: 1708.826 | G75: 218.038 | H75: 5005 | I75: 4452.456 | J75: 552.544 | K75: 4187.499 | L75: 522.113 | M75: 40716.756 | N75: 1710.104 | O75: 218.201 | P75: 2109.229 | Q75: 2374.119 | R75: 4913.616 | S75: 7807.3 | T75: 858.407 | U75: 118.007 | V75: 626.863 | W75: 1290.407 | X75: 1989.427 | Y75: 430.267 | Z75: 2330.855 | AA75: 4750.55 | AB75: 7644.234 | AC75: 20502.879 | AD75: 861.121 | AE75: 112.643 | AF75: 9340 | AG75: 2352.752 | AH75: 1065.753 | AI75: 28777.126 | AJ75: 1208.639 | AK75: 158.102 | AN75: 1913.988 | AO75: 80.387 | AP75: 10.257 | AQ75: 27 | AR75: 82.546 | AS75: 55.545 | AT75: 1885.443 | AU75: 79.189 | AV75: 10.104 | AW75: 39.6 | AX75: 332.785 | AY75: 438.968 | AZ75: 811.353 | BA75: 2.279 | BB75: 24.137 | BC75: 139.049 | BD75: 1.484 | BE75: 82.704 | BF75: 39.306 | BG75: 26.623 | BH75: 148.633 | BI75: 315.582 | BJ75: 1109.548 | BK75: 218.201 | BL75: 158.102 | BM75: 10.104 | BN75: 1495.955 | BO75: 2214.458 | BP75: 136.847 | BQ75: 1012.844 | BR75: 3342.301 | BS75: 196.746 | BT75: 229.465 | BU75: 426.211 | BV75: 7132.661 | BW75: 1703688 | BX75: 105262 | BY75: 1449807 | BZ75: 130039 | CA75: =BW75*42/1000 -> 71554.896 | CB75: =BX75*42/1000 -> 4421.004 | CC75: =BY75*42/1000 -> 60891.894 | CD75: =BZ75*42/1000 -> 5461.638
A76: 2022 | B76: 209.821 | C76: 2.858 | D76: =(G76/F76)*C76/1000 -> 0.0003646671 | E76: 38619.726 | F76: 1622.028 | G76: 206.963 | H76: 5950 | I76: 5671.095 | J76: 278.905 | K76: 3607.851 | L76: -579.648 | M76: 39478.279 | N76: 1658.088 | O76: 211.564 | P76: 2150.105 | Q76: 2510.778 | R76: 5073.211 | S76: 8307.341 | T76: 869.339 | U76: 118.389 | V76: 764.58 | W76: 1481.823 | X76: 2011.712 | Y76: 412.329 | Z76: 2432.624 | AA76: 4856.665 | AB76: 8090.795 | AC76: 35691.785 | AD76: 1499.055 | AE76: 196.091 | AF76: 6254 | AG76: 3405.459 | AH76: 1052.708 | AI76: 40893.077 | AJ76: 1717.509 | AK76: 224.667 | AN76: 4841.307 | AO76: 203.335 | AP76: 25.945 | AQ76: 114 | AR76: 282.253 | AS76: 199.707 | AT76: 4755.6 | AU76: 199.735 | AV76: 25.485 | AW76: 39.6 | AX76: 199.659 | AY76: 422.484 | AZ76: 661.743 | BA76: 0.898 | BB76: 19.7 | BC76: 62.756 | BD76: 0.59 | BE76: 83.045 | BF76: 75.059 | BG76: 31.507 | BH76: 189.611 | BI76: 273.556 | BJ76: 1111.38 | BK76: 211.564 | BL76: 224.667 | BM76: 25.485 | BN76: 1573.096 | BO76: 865.374 | BP76: 54.889 | BQ76: 487.411 | BR76: 1480.788 | BS76: 197.691 | BT76: 176.49 | BU76: 374.181 | BV76: 3262.642 | BW76: 1828961 | BX76: 68628 | BY76: 1469334 | BZ76: 118899 | CA76: =BW76*42/1000 -> 76816.362 | CB76: =BX76*42/1000 -> 2882.376 | CC76: =BY76*42/1000 -> 61712.028 | CD76: =BZ76*42/1000 -> 4993.758
A77: 2023 | B77: 219.751 | C77: 2.993 | D77: =(G77/F77)*C77/1000 -> 0.00038189273 | E77: 40447.452 | F77: 1698.793 | G77: 216.758 | H77: 11929 | I77: 5980.332 | J77: 5948.668 | K77: 3827.474 | L77: 228.025 | M77: 46168.095 | N77: 1939.06 | O77: 247.415 | P77: 2053.426 | Q77: 2708.294 | R77: 5159.841 | S77: 8426.336 | T77: 818.384 | U77: 119.668 | V77: 877.54 | W77: 1450.903 | X77: 1918.132 | Y77: 398.121 | Z77: 2661.826 | AA77: 4978.079 | AB77: 8244.574 | AC77: 61743.843 | AD77: 2593.241 | AE77: 339.221 | AF77: 8622 | AG77: 5477.77 | AH77: 2072.312 | AI77: 68293.531 | AJ77: 2868.328 | AK77: 375.205 | AN77: 6888.263 | AO77: 289.307 | AP77: 36.914 | AQ77: 112 | AR77: 304.726 | AS77: 22.473 | AT77: 6977.79 | AU77: 293.067 | AV77: 37.394 | AW77: 39.6 | AX77: 234.767 | AY77: 450.322 | AZ77: 724.69 | BA77: 0.813 | BB77: 19.7 | BC77: 68.788 | BD77: 0.505 | BE77: 81.822 | BF77: 71.039 | BG77: 31.99 | BH77: 184.851 | BI77: 274.657 | BJ77: 1128.392 | BK77: 247.415 | BL77: 375.205 | BM77: 37.394 | BN77: 1788.405 | BO77: 814.485 | BP77: 56.168 | BQ77: 557.811 | BR77: 1449.973 | BS77: 161.556 | BT77: 167.49 | BU77: 329.045 | BV77: 3207.481 | BW77: 1790989 | BX77: 61271 | BY77: 1435530 | BZ77: 130713 | CA77: =BW77*42/1000 -> 75221.538 | CB77: =BX77*42/1000 -> 2573.382 | CC77: =BY77*42/1000 -> 60292.26 | CD77: =BZ77*42/1000 -> 5489.946

Sheet monthly_data
C1: Biodiesel Feedstock | D1: Biodiesel Losses and Co-products | E1: Biodiesel Production | F1: Biodiesel Production | G1: Biodiesel Production | H1: Biodiesel Imports | I1: Biodiesel Exports | J1: Biodiesel Net Imports | K1: Biodiesel Stocks | L1: Biodiesel Stock Change | M1: Biodiesel Consumption | N1: Biodiesel Consumption | O1: Biodiesel Consumption | P1: Wood Energy Production | Q1: Biofuels Production | R1: Total Biomass Energy Production | S1: Total Renewable Energy Production | T1: Hydroelectric Power Consumption | U1: Geothermal Energy Consumption | V1: Solar Energy Consumption | W1: Wind Energy Consumption | X1: Wood Energy Consumption | Y1: Waste Energy Consumption | Z1: Biofuels Consumption | AA1: Total Biomass Energy Consumption | AB1: Total Renewable Energy Consumption | AC1: Renewable Diesel Fuel Production | AD1: Renewable Diesel Fuel Production | AE1: Renewable Diesel Fuel Production | AF1: Renewable Diesel Fuel Imports | AG1: Renewable Diesel Fuel Stocks | AH1: Renewable Diesel Fuel Stock Change | AI1: Renewable Diesel Fuel Consumption | AJ1: Renewable Diesel Fuel Consumption | AK1: Renewable Diesel Fuel Consumption | AL1: Renewable Diesel Fuel Consumption - Repeat from AJ - Delete if not linked | AM1: Renewable Diesel Fuel Consumption | AN1: Other Biofuels Feedstock | AO1: Other Biofuels Losses and Co-products | AP1: Other Biofuels Production | AQ1: Other Biofuels Production | AR1: Other Biofuels Production | AS1: Other Biofuels Imports | AT1: Other Biofuels Stocks | AU1: Other Biofuels Stock Change | AV1: Other Biofuels Consumption | AW1: Other Biofuels Consumption | AX1: Other Biofuels Consumption | AY1: Geothermal Energy Consumed by the Residential Sector | AZ1: Solar Energy Consumed by the Residential Sector | BA1: Wood Energy Consumed by the Residential Sector | BB1: Total Renewable Energy Consumed by the Residential Sector | BC1: Hydroelectric Power Consumed by the Commercial Sector | BD1: Geothermal Energy Consumed by the Commercial Sector | BE1: Solar Energy Consumed by the Commercial Sector | BF1: Wind Energy Consumed by the Commercial Sector | BG1: Wood Energy Consumed by the Commercial Sector | BH1: Waste Energy Consumed by the Commercial Sector | BI1: Fuel Ethanol, Excluding Denaturant, Consumed by the Commercial Sector | BJ1: Biomass Energy Consumed by the Commercial Sector | BK1: Total Renewable Energy Consumed by the Commercial Sector | BL1: Fuel Ethanol, Excluding Denaturant, Consumed by the Transportation Sector | BM1: Biodiesel Consumed by the Transportation Sector | BN1: Renewable Diesel Fuel Consumed by the Transportation Sector | BO1: Other Biofuels Consumed by the Transportation Sector | BP1: Biomass Energy Consumed by the Transportation Sector | BQ1: Conventional Hydroelectric Power Consumed by the Electric Power Sector | BR1: Geothermal Energy Consumed by the Electric Power Sector | BS1: Solar Energy Consumed by the Electric Power Sector | BT1: Wind Energy Consumed by the Electric Power Sector | BU1: Wood Energy Consumed by the Electric Power Sector | BV1: Waste Energy Consumed by the Electric Power Sector | BW1: Biomass Energy Consumed by the Electric Power Sector | BX1: Total Renewable Energy Consumed by the Electric Power Sector | BY1: U.S. Refinery and Blender Net Production of Distillate Fuel Oil (Th Bbls) | BZ1: U.S. Product Supplied of Distillate Fuel Oil (Th Bbls) | CA1: U.S. Imports of Distillate Fuel Oil (Th Bbls) | CB1: U.S. Ending Stocks of Distillate Fuel Oil (Th Bbls) | CC1: U.S. Exports of Distillate Fuel Oil Thousand Barrels | CD1: U.S. Refinery Net Production of Distillate Fuel Oil 0 to 15 ppm Sulfur Thousand Barrels | CE1: Diesel Consumption | CF1: Distillate Fuel Refinery Output | CG1: Distillate Fuel Oil Stocks | CH1: Distillate Fuel Imports | CI1: Distillate Fuel Exports | CJ1: Distillate Fuel U.S. Refinery and Blender Net Production | CK1: Distillate Fuel Oil Product Supplied | CL1: U.S. Refinery Net Production of Distillate Fuel Oil 0 to 15 ppm Sulfur Thousand Barrels
C2: (Trillion Btu) | D2: (Trillion Btu) | E2: (Thousand Barrels) | F2: (Million Gallons) | G2: (Trillion Btu) | H2: (Thousand Barrels) | I2: (Thousand Barrels) | J2: (Thousand Barrels) | K2: (Thousand Barrels) | L2: (Thousand Barrels) | M2: (Thousand Barrels) | N2: (Million Gallons) | O2: (Trillion Btu) | P2: (Trillion Btu) | Q2: (Trillion Btu) | R2: (Trillion Btu) | S2: (Trillion Btu) | T2: (Trillion Btu) | U2: (Trillion Btu) | V2: (Trillion Btu) | W2: (Trillion Btu) | X2: (Trillion Btu) | Y2: (Trillion Btu) | Z2: (Trillion Btu) | AA2: (Trillion Btu) | AB2: (Trillion Btu) | AC2: (Thousand Barrels) | AD2: (Million Gallons) | AE2: (Trillion Btu) | AF2: (Thousand Barrels) | AG2: (Thousand Barrels) | AH2: (Thousand Barrels) | AI2: (Thousand Barrels) | AJ2: (Million Gallons) | AK2: (Trillion Btu) | AL2: (Million Gallons) | AM2: (Trillion Btu) | AN2: (Trillion Btu) | AO2: (Trillion Btu) | AP2: (Thousand Barrels) | AQ2: (Million Gallons) | AR2: (Trillion Btu) | AS2: (Thousand Barrels) | AT2: (Thousand Barrels) | AU2: (Thousand Barrels) | AV2: (Thousand Barrels) | AW2: (Million Gallons) | AX2: (Trillion Btu) | AY2: (Trillion Btu) | AZ2: (Trillion Btu) | BA2: (Trillion Btu) | BB2: (Trillion Btu) | BC2: (Trillion Btu) | BD2: (Trillion Btu) | BE2: (Trillion Btu) | BF2: (Trillion Btu) | BG2: (Trillion Btu) | BH2: (Trillion Btu) | BI2: (Trillion Btu) | BJ2: (Trillion Btu) | BK2: (Trillion Btu) | BL2: (Trillion Btu) | BM2: (Trillion Btu) | BN2: (Trillion Btu) | BO2: (Trillion Btu) | BP2: (Trillion Btu) | BQ2: (Trillion Btu) | BR2: (Trillion Btu) | BS2: (Trillion Btu) | BT2: (Trillion Btu) | BU2: (Trillion Btu) | BV2: (Trillion Btu) | BW2: (Trillion Btu) | BX2: (Trillion Btu) | BY2: https://www.eia.gov/dnav/pet/hist/LeafHandler.ashx?n=PET&s=MDIRPUS1&f=M | BZ2: https://www.eia.gov/dnav/pet/hist/LeafHandler.ashx?n=PET&s=MDIUPUS1&f=M | CA2: https://www.eia.gov/dnav/pet/hist/LeafHandler.ashx?n=PET&s=MDIIMUS1&f=M | CB2: https://www.eia.gov/dnav/pet/hist/LeafHandler.ashx?n=pet&s=mdistus1&f=m | CC2: https://www.eia.gov/dnav/pet/hist/LeafHandler.ashx?n=PET&s=MDIEXUS1&f=M | CD2: https://www.eia.gov/dnav/pet/hist/LeafHandler.ashx?n=PET&s=MD0RX_NUS_1&f=M | CE2: (million gallons) | CF2: (million gallons) | CG2: (million gallons) | CH2: (million gallons) | CI2: (million gallons) | CJ2: (million gallons) | CK2: (Million Gallons) | CL2: (Million Gallons)
A3: 26665 | P3: 129.63 | Q3: Not Available | R3: 129.787 | S3: 403.981 | T3: 272.703 | U3: 1.491 | V3: Not Available | W3: Not Available | X3: 129.63 | Y3: 0.157 | Z3: Not Available | AA3: 129.787 | AB3: 403.981 | AN3: #N/A | AO3: #N/A | AP3: #N/A | AQ3: #N/A | AR3: #N/A | AS3: #N/A | AT3: #N/A | AU3: #N/A | AV3: #N/A | AW3: #N/A | AX3: #N/A | AY3: Not Available | AZ3: Not Available | BA3: 30.074 | BB3: 30.074 | BC3: Not Available | BD3: Not Available | BE3: Not Available | BF3: Not Available | BG3: 0.57 | BH3: Not Available | BI3: Not Available | BJ3: 0.57 | BK3: 0.57 | BL3: Not Available | BM3: Not Available | BN3: Not Available | BO3: Not Available | BP3: Not Available | BQ3: 269.536 | BR3: 1.491 | BS3: Not Available | BT3: Not Available | BU3: 0.054 | BV3: 0.157 | BW3: 0.211 | BX3: 271.238 | BY3: 93862 | BZ3: 128286 | CA3: 11289 | CB3: 130993 | CC3: 332 | CG3: =CB3*42/1000 -> 5501.706 | CH3: =CA3*42/1000 -> 474.138 | CI3: =CC3*42/1000 -> 13.944 | CJ3: =BY3*42/1000 -> 3942.204 | CK3: =BZ3*42/1000 -> 5388.012 | CL3: =CC3*42/1000 -> 13.944
A4: 26696 | P4: 117.194 | Q4: Not Available | R4: 117.338 | S4: 360.9 | T4: 242.199 | U4: 1.363 | V4: Not Available | W4: Not Available | X4: 117.194 | Y4: 0.144 | Z4: Not Available | AA4: 117.338 | AB4: 360.9 | AN4: #N/A | AO4: #N/A | AP4: #N/A | AQ4: #N/A | AR4: #N/A | AS4: #N/A | AT4: #N/A | AU4: #N/A | AV4: #N/A | AW4: #N/A | AX4: #N/A | AY4: Not Available | AZ4: Not Available | BA4: 27.164 | BB4: 27.164 | BC4: Not Available | BD4: Not Available | BE4: Not Available | BF4: Not Available | BG4: 0.515 | BH4: Not Available | BI4: Not Available | BJ4: 0.515 | BK4: 0.515 | BL4: Not Available | BM4: Not Available | BN4: Not Available | BO4: Not Available | BP4: Not Available | BQ4: 239.271 | BR4: 1.363 | BS4: Not Available | BT4: Not Available | BU4: 0.157 | BV4: 0.144 | BW4: 0.301 | BX4: 240.935 | BY4: 82242 | BZ4: 120447 | CA4: 20474 | CB4: 113310 | CC4: 67 | CG4: =CB4*42/1000 -> 4759.02 | CH4: =CA4*42/1000 -> 859.908 | CI4: =CC4*42/1000 -> 2.814 | CJ4: =BY4*42/1000 -> 3454.164 | CK4: =BZ4*42/1000 -> 5058.774 | CL4: =CC4*42/1000 -> 2.814
A5: 26724 | P5: 129.763 | Q5: Not Available | R5: 129.938 | S5: 400.161 | T5: 268.81 | U5: 1.412 | V5: Not Available | W5: Not Available | X5: 129.763 | Y5: 0.176 | Z5: Not Available | AA5: 129.938 | AB5: 400.161 | AN5: #N/A | AO5: #N/A | AP5: #N/A | AQ5: #N/A | AR5: #N/A | AS5: #N/A | AT5: #N/A | AU5: #N/A | AV5: #N/A | AW5: #N/A | AX5: #N/A | AY5: Not Available | AZ5: Not Available | BA5: 30.074 | BB5: 30.074 | BC5: Not Available | BD5: Not Available | BE5: Not Available | BF5: Not Available | BG5: 0.57 | BH5: Not Available | BI5: Not Available | BJ5: 0.57 | BK5: 0.57 | BL5: Not Available | BM5: Not Available | BN5: Not Available | BO5: Not Available | BP5: Not Available | BQ5: 265.57 | BR5: 1.412 | BS5: Not Available | BT5: Not Available | BU5: 0.186 | BV5: 0.176 | BW5: 0.362 | BX5: 267.345 | BY5: 82679 | BZ5: 103451 | CA5: 18672 | CB5: 111299 | CC5: 72 | CG5: =CB5*42/1000 -> 4674.558 | CH5: =CA5*42/1000 -> 784.224 | CI5: =CC5*42/1000 -> 3.024 | CJ5: =BY5*42/1000 -> 3472.518 | CK5: =BZ5*42/1000 -> 4344.942 | CL5: =CC5*42/1000 -> 3.024
A6: 26755 | P6: 125.462 | Q6: Not Available | R6: 125.636 | S6: 380.47 | T6: 253.185 | U6: 1.649 | V6: Not Available | W6: Not Available | X6: 125.462 | Y6: 0.174 | Z6: Not Available | AA6: 125.636 | AB6: 380.47 | AN6: #N/A | AO6: #N/A | AP6: #N/A | AQ6: #N/A | AR6: #N/A | AS6: #N/A | AT6: #N/A | AU6: #N/A | AV6: #N/A | AW6: #N/A | AX6: #N/A | AY6: Not Available | AZ6: Not Available | BA6: 29.104 | BB6: 29.104 | BC6: Not Available | BD6: Not Available | BE6: Not Available | BF6: Not Available | BG6: 0.551 | BH6: Not Available | BI6: Not Available | BJ6: 0.551 | BK6: 0.551 | BL6: Not Available | BM6: Not Available | BN6: Not Available | BO6: Not Available | BP6: Not Available | BQ6: 250.09 | BR6: 1.649 | BS6: Not Available | BT6: Not Available | BU6: 0.066 | BV6: 0.174 | BW6: 0.24 | BX6: 251.979 | BY6: 75306 | BZ6: 79037 | CA6: 7207 | CB6: 114723 | CC6: 197 | CG6: =CB6*42/1000 -> 4818.366 | CH6: =CA6*42/1000 -> 302.694 | CI6: =CC6*42/1000 -> 8.274 | CJ6: =BY6*42/1000 -> 3162.852 | CK6: =BZ6*42/1000 -> 3319.554 | CL6: =CC6*42/1000 -> 8.274
A7: 26785 | P7: 129.624 | Q7: Not Available | R7: 129.834 | S7: 392.141 | T7: 260.77 | U7: 1.537 | V7: Not Available | W7: Not Available | X7: 129.624 | Y7: 0.21 | Z7: Not Available | AA7: 129.834 | AB7: 392.141 | AN7: #N/A | AO7: #N/A | AP7: #N/A | AQ7: #N/A | AR7: #N/A | AS7: #N/A | AT7: #N/A | AU7: #N/A | AV7: #N/A | AW7: #N/A | AX7: #N/A | AY7: Not Available | AZ7: Not Available | BA7: 30.074 | BB7: 30.074 | BC7: Not Available | BD7: Not Available | BE7: Not Available | BF7: Not Available | BG7: 0.57 | BH7: Not Available | BI7: Not Available | BJ7: 0.57 | BK7: 0.57 | BL7: Not Available | BM7: Not Available | BN7: Not Available | BO7: Not Available | BP7: Not Available | BQ7: 257.577 | BR7: 1.537 | BS7: Not Available | BT7: Not Available | BU7: 0.048 | BV7: 0.21 | BW7: 0.258 | BX7: 259.372 | BY7: 78860 | BZ7: 82851 | CA7: 8301 | CB7: 119131 | CC7: 54 | CG7: =CB7*42/1000 -> 5003.502 | CH7: =CA7*42/1000 -> 348.642 | CI7: =CC7*42/1000 -> 2.268 | CJ7: =BY7*42/1000 -> 3312.12 | CK7: =BZ7*42/1000 -> 3479.742 | CL7: =CC7*42/1000 -> 2.268
A8: 26816 | P8: 125.435 | Q8: Not Available | R8: 125.611 | S8: 377.232 | T8: 249.859 | U8: 1.763 | V8: Not Available | W8: Not Available | X8: 125.435 | Y8: 0.176 | Z8: Not Available | AA8: 125.611 | AB8: 377.232 | AN8: #N/A | AO8: #N/A | AP8: #N/A | AQ8: #N/A | AR8: #N/A | AS8: #N/A | AT8: #N/A | AU8: #N/A | AV8: #N/A | AW8: #N/A | AX8: #N/A | AY8: Not Available | AZ8: Not Available | BA8: 29.104 | BB8: 29.104 | BC8: Not Available | BD8: Not Available | BE8: Not Available | BF8: Not Available | BG8: 0.551 | BH8: Not Available | BI8: Not Available | BJ8: 0.551 | BK8: 0.551 | BL8: Not Available | BM8: Not Available | BN8: Not Available | BO8: Not Available | BP8: Not Available | BQ8: 246.76 | BR8: 1.763 | BS8: Not Available | BT8: Not Available | BU8: 0.039 | BV8: 0.176 | BW8: 0.214 | BX8: 248.737 | BY8: 84759 | BZ8: 72560 | CA8: 6660 | CB8: 137869 | CC8: 253 | CG8: =CB8*42/1000 -> 5790.498 | CH8: =CA8*42/1000 -> 279.72 | CI8: =CC8*42/1000 -> 10.626 | CJ8: =BY8*42/1000 -> 3559.878 | CK8: =BZ8*42/1000 -> 3047.52 | CL8: =CC8*42/1000 -> 10.626
A9: 26846 | P9: 129.616 | Q9: Not Available | R9: 129.787 | S9: 367.325 | T9: 235.67 | U9: 1.869 | V9: Not Available | W9: Not Available | X9: 129.616 | Y9: 0.17 | Z9: Not Available | AA9: 129.787 | AB9: 367.325 | AN9: #N/A | AO9: #N/A | AP9: #N/A | AQ9: #N/A | AR9: #N/A | AS9: #N/A | AT9: #N/A | AU9: #N/A | AV9: #N/A | AW9: #N/A | AX9: #N/A | AY9: Not Available | AZ9: Not Available | BA9: 30.074 | BB9: 30.074 | BC9: Not Available | BD9: Not Available | BE9: Not Available | BF9: Not Available | BG9: 0.57 | BH9: Not Available | BI9: Not Available | BJ9: 0.57 | BK9: 0.57 | BL9: Not Available | BM9: Not Available | BN9: Not Available | BO9: Not Available | BP9: Not Available | BQ9: 232.91 | BR9: 1.869 | BS9: Not Available | BT9: Not Available | BU9: 0.04 | BV9: 0.17 | BW9: 0.21 | BX9: 234.989 | BY9: 85299 | BZ9: 72175 | CA9: 9870 | CB9: 160901 | CC9: 105 | CG9: =CB9*42/1000 -> 6757.842 | CH9: =CA9*42/1000 -> 414.54 | CI9: =CC9*42/1000 -> 4.41 | CJ9: =BY9*42/1000 -> 3582.558 | CK9: =BZ9*42/1000 -> 3031.35 | CL9: =CC9*42/1000 -> 4.41
A10: 26877 | P10: 129.734 | Q10: Not Available | R10: 129.918 | S10: 353.757 | T10: 222.077 | U10: 1.762 | V10: Not Available | W10: Not Available | X10: 129.734 | Y10: 0.184 | Z10: Not Available | AA10: 129.918 | AB10: 353.757 | AN10: #N/A | AO10: #N/A | AP10: #N/A | AQ10: #N/A | AR10: #N/A | AS10: #N/A | AT10: #N/A | AU10: #N/A | AV10: #N/A | AW10: #N/A | AX10: #N/A | AY10: Not Available | AZ10: Not Available | BA10: 30.074 | BB10: 30.074 | BC10: Not Available | BD10: Not Available | BE10: Not Available | BF10: Not Available | BG10: 0.57 | BH10: Not Available | BI10: Not Available | BJ10: 0.57 | BK10: 0.57 | BL10: Not Available | BM10: Not Available | BN10: Not Available | BO10: Not Available | BP10: Not Available | BQ10: 219.412 | BR10: 1.762 | BS10: Not Available | BT10: Not Available | BU10: 0.157 | BV10: 0.184 | BW10: 0.341 | BX10: 221.516 | BY10: 86840 | BZ10: 79208 | CA10: 8915 | CB10: 177304 | CC10: 264 | CG10: =CB10*42/1000 -> 7446.768 | CH10: =CA10*42/1000 -> 374.43 | CI10: =CC10*42/1000 -> 11.088 | CJ10: =BY10*42/1000 -> 3647.28 | CK10: =BZ10*42/1000 -> 3326.736 | CL10: =CC10*42/1000 -> 11.088
A11: 26908 | P11: 125.603 | Q11: Not Available | R11: 125.782 | S11: 307.006 | T11: 179.733 | U11: 1.492 | V11: Not Available | W11: Not Available | X11: 125.603 | Y11: 0.178 | Z11: Not Available | AA11: 125.782 | AB11: 307.006 | AN11: #N/A | AO11: #N/A | AP11: #N/A | AQ11: #N/A | AR11: #N/A | AS11: #N/A | AT11: #N/A | AU11: #N/A | AV11: #N/A | AW11: #N/A | AX11: #N/A | AY11: Not Available | AZ11: Not Available | BA11: 29.104 | BB11: 29.104 | BC11: Not Available | BD11: Not Available | BE11: Not Available | BF11: Not Available | BG11: 0.551 | BH11: Not Available | BI11: Not Available | BJ11: 0.551 | BK11: 0.551 | BL11: Not Available | BM11: Not Available | BN11: Not Available | BO11: Not Available | BP11: Not Available | BQ11: 177.407 | BR11: 1.492 | BS11: Not Available | BT11: Not Available | BU11: 0.207 | BV11: 0.178 | BW11: 0.385 | BX11: 179.284 | BY11: 84379 | BZ11: 80241 | CA11: 9399 | CB11: 190209 | CC11: 761 | CG11: =CB11*42/1000 -> 7988.778 | CH11: =CA11*42/1000 -> 394.758 | CI11: =CC11*42/1000 -> 31.962 | CJ11: =BY11*42/1000 -> 3543.918 | CK11: =BZ11*42/1000 -> 3370.122 | CL11: =CC11*42/1000 -> 31.962
A12: 26938 | P12: 129.769 | Q12: Not Available | R12: 129.97 | S12: 323.453 | T12: 191.723 | U12: 1.76 | V12: Not Available | W12: Not Available | X12: 129.769 | Y12: 0.2 | Z12: Not Available | AA12: 129.97 | AB12: 323.453 | AN12: #N/A | AO12: #N/A | AP12: #N/A | AQ12: #N/A | AR12: #N/A | AS12: #N/A | AT12: #N/A | AU12: #N/A | AV12: #N/A | AW12: #N/A | AX12: #N/A | AY12: Not Available | AZ12: Not Available | BA12: 30.074 | BB12: 30.074 | BC12: Not Available | BD12: Not Available | BE12: Not Available | BF12: Not Available | BG12: 0.57 | BH12: Not Available | BI12: Not Available | BJ12: 0.57 | BK12: 0.57 | BL12: Not Available | BM12: Not Available | BN12: Not Available | BO12: Not Available | BP12: Not Available | BQ12: 189.189 | BR12: 1.76 | BS12: Not Available | BT12: Not Available | BU12: 0.193 | BV12: 0.2 | BW12: 0.393 | BX12: 191.343 | BY12: 90230 | BZ12: 90834 | CA12: 13978 | CB12: 203000 | CC12: 721 | CG12: =CB12*42/1000 -> 8526 | CH12: =CA12*42/1000 -> 587.076 | CI12: =CC12*42/1000 -> 30.282 | CJ12: =BY12*42/1000 -> 3789.66 | CK12: =BZ12*42/1000 -> 3815.028 | CL12: =CC12*42/1000 -> 30.282
A13: 26969 | P13: 125.492 | Q13: Not Available | R13: 125.643 | S13: 337.817 | T13: 210.285 | U13: 1.889 | V13: Not Available | W13: Not Available | X13: 125.492 | Y13: 0.151 | Z13: Not Available | AA13: 125.643 | AB13: 337.817 | AN13: #N/A | AO13: #N/A | AP13: #N/A | AQ13: #N/A | AR13: #N/A | AS13: #N/A | AT13: #N/A | AU13: #N/A | AV13: #N/A | AW13: #N/A | AX13: #N/A | AY13: Not Available | AZ13: Not Available | BA13: 29.104 | BB13: 29.104 | BC13: Not Available | BD13: Not Available | BE13: Not Available | BF13: Not Available | BG13: 0.551 | BH13: Not Available | BI13: Not Available | BJ13: 0.551 | BK13: 0.551 | BL13: Not Available | BM13: Not Available | BN13: Not Available | BO13: Not Available | BP13: Not Available | BQ13: 207.617 | BR13: 1.889 | BS13: Not Available | BT13: Not Available | BU13: 0.095 | BV13: 0.151 | BW13: 0.246 | BX13: 209.752 | BY13: 87672 | BZ13: 105230 | CA13: 14769 | CB13: 200218 | CC13: 97 | CG13: =CB13*42/1000 -> 8409.156 | CH13: =CA13*42/1000 -> 620.298 | CI13: =CC13*42/1000 -> 4.074 | CJ13: =BY13*42/1000 -> 3682.224 | CK13: =BZ13*42/1000 -> 4419.66 | CL13: =CC13*42/1000 -> 4.074
A14: 26999 | P14: 129.69 | Q14: Not Available | R14: 129.824 | S14: 406.694 | T14: 274.435 | U14: 2.435 | V14: Not Available | W14: Not Available | X14: 129.69 | Y14: 0.135 | Z14: Not Available | AA14: 129.824 | AB14: 406.694 | AN14: #N/A | AO14: #N/A | AP14: #N/A | AQ14: #N/A | AR14: #N/A | AS14: #N/A | AT14: #N/A | AU14: #N/A | AV14: #N/A | AW14: #N/A | AX14: #N/A | AY14: Not Available | AZ14: Not Available | BA14: 30.074 | BB14: 30.074 | BC14: Not Available | BD14: Not Available | BE14: Not Available | BF14: Not Available | BG14: 0.57 | BH14: Not Available | BI14: Not Available | BJ14: 0.57 | BK14: 0.57 | BL14: Not Available | BM14: Not Available | BN14: Not Available | BO14: Not Available | BP14: Not Available | BQ14: 271.335 | BR14: 2.435 | BS14: Not Available | BT14: Not Available | BU14: 0.113 | BV14: 0.135 | BW14: 0.248 | BX14: 274.019 | BY14: 97215 | BZ14: 114394 | CA14: 13615 | CB14: 196461 | CC14: 308 | CG14: =CB14*42/1000 -> 8251.362 | CH14: =CA14*42/1000 -> 571.83 | CI14: =CC14*42/1000 -> 12.936 | CJ14: =BY14*42/1000 -> 4083.03 | CK14: =BZ14*42/1000 -> 4804.548 | CL14: =CC14*42/1000 -> 12.936
... A98: 29556 | P98: 209.546 | Q98: Not Available | R98: 209.671 | S98: 448.546 | T98: 233.998 | U98: 4.877 | V98: Not Available | W98: Not Available | X98: 209.546 | Y98: 0.125 | Z98: Not Available | AA98: 209.671 | AB98: 448.546 | AN98: #N/A | AO98: #N/A | AP98: #N/A | AQ98: #N/A | AR98: #N/A | AS98: #N/A | AT98: #N/A | AU98: #N/A | AV98: #N/A | AW98: #N/A | AX98: #N/A | AY98: Not Available | AZ98: Not Available | BA98: 71.995 | BB98: 71.995 | BC98: Not Available | BD98: Not Available | BE98: Not Available | BF98: Not Available | BG98: 1.779 | BH98: Not Available | BI98: Not Available | BJ98: 1.779 | BK98: 1.779 | BL98: Not Available | BM98: Not Available | BN98: Not Available | BO98: Not Available | BP98: Not Available | BQ98: 231.548 | BR98: 4.877 | BS98: Not Available | BT98: Not Available | BU98: 0.254 | BV98: 0.125 | BW98: 0.379 | BX98: 236.803 | BY98: 89615 | BZ98: 112067 | CA98: 5159 | CB98: 205113 | CC98: 2 | CG98: =CB98*42/1000 -> 8614.746 | CH98: =CA98*42/1000 -> 216.678 | CI98: =CC98*42/1000 -> 0.084 | CJ98: =BY98*42/1000 -> 3763.83 | CK98: =BZ98*42/1000 -> 4706.814 | CL98: =CC98*42/1000 -> 0.084
A99: 29587 | P99: 211.988 | Q99: 1.08 | R99: 220.544 | S99: 462.381 | T99: 236.553 | U99: 5.284 | V99: Not Available | W99: Not Available | X99: 211.988 | Y99: 7.476 | Z99: 1.08 | AA99: 220.544 | AB99: 462.381 | AN99: #N/A | AO99: #N/A | AP99: #N/A | AQ99: #N/A | AR99: #N/A | AS99: #N/A | AT99: #N/A | AU99: #N/A | AV99: #N/A | AW99: #N/A | AX99: #N/A | AY99: Not Available | AZ99: Not Available | BA99: 73.89 | BB99: 73.89 | BC99: Not Available | BD99: Not Available | BE99: Not Available | BF99: Not Available | BG99: 1.784 | BH99: Not Available | BI99: 0.004 | BJ99: 1.788 | BK99: 1.788 | BL99: 0.571 | BM99: Not Available | BN99: Not Available | BO99: Not Available | BP99: 0.571 | BQ99: 233.504 | BR99: 5.284 | BS99: Not Available | BT99: Not Available | BU99: 0.254 | BV99: 0.11 | BW99: 0.365 | BX99: 239.153 | BY99: 92634 | BZ99: 127383 | CA99: 8475 | CB99: 179439 | CC99: 5 | CG99: =CB99*42/1000 -> 7536.438 | CH99: =CA99*42/1000 -> 355.95 | CI99: =CC99*42/1000 -> 0.21 | CJ99: =BY99*42/1000 -> 3890.628 | CK99: =BZ99*42/1000 -> 5350.086 | CL99: =CC99*42/1000 -> 0.21
A100: 29618 | P100: 191.528 | Q100: 0.976 | R100: 199.248 | S100: 427.043 | T100: 223.123 | U100: 4.671 | V100: Not Available | W100: Not Available | X100: 191.528 | Y100: 6.744 | Z100: 0.976 | AA100: 199.248 | AB100: 427.043 | AN100: #N/A | AO100: #N/A | AP100: #N/A | AQ100: #N/A | AR100: #N/A | AS100: #N/A | AT100: #N/A | AU100: #N/A | AV100: #N/A | AW100: #N/A | AX100: #N/A | AY100: Not Available | AZ100: Not Available | BA100: 66.74 | BB100: 66.74 | BC100: Not Available | BD100: Not Available | BE100: Not Available | BF100: Not Available | BG100: 1.611 | BH100: Not Available | BI100: 0.004 | BJ100: 1.615 | BK100: 1.615 | BL100: 0.516 | BM100: Not Available | BN100: Not Available | BO100: Not Available | BP100: 0.516 | BQ100: 220.547 | BR100: 4.671 | BS100: Not Available | BT100: Not Available | BU100: 0.284 | BV100: 0.092 | BW100: 0.376 | BX100: 225.595 | BY100: 78635 | BZ100: 94456 | CA100: 9090 | CB100: 172562 | CC100: 465 | CG100: =CB100*42/1000 -> 7247.604 | CH100: =CA100*42/1000 -> 381.78 | CI100: =CC100*42/1000 -> 19.53 | CJ100: =BY100*42/1000 -> 3302.67 | CK100: =BZ100*42/1000 -> 3967.152 | CL100: =CC100*42/1000 -> 19.53
A101: 29646 | P101: 212.042 | Q101: 1.08 | R101: 220.595 | S101: 443.808 | T101: 217.976 | U101: 5.237 | V101: Not Available | W101: Not Available | X101: 212.042 | Y101: 7.472 | Z101: 1.08 | AA101: 220.595 | AB101: 443.808 | AN101: #N/A | AO101: #N/A | AP101: #N/A | AQ101: #N/A | AR101: #N/A | AS101: #N/A | AT101: #N/A | AU101: #N/A | AV101: #N/A | AW101: #N/A | AX101: #N/A | AY101: Not Available | AZ101: Not Available | BA101: 73.89 | BB101: 73.89 | BC101: Not Available | BD101: Not Available | BE101: Not Available | BF101: Not Available | BG101: 1.784 | BH101: Not Available | BI101: 0.004 | BJ101: 1.788 | BK101: 1.788 | BL101: 0.571 | BM101: Not Available | BN101: Not Available | BO101: Not Available | BP101: 0.571 | BQ101: 215.044 | BR101: 5.237 | BS101: Not Available | BT101: Not Available | BU101: 0.308 | BV101: 0.107 | BW101: 0.415 | BX101: 220.696 | BY101: 76981 | BZ101: 90027 | CA101: 4567 | CB101: 164372 | CC101: 6 | CG101: =CB101*42/1000 -> 6903.624 | CH101: =CA101*42/1000 -> 191.814 | CI101: =CC101*42/1000 -> 0.252 | CJ101: =BY101*42/1000 -> 3233.202 | CK101: =BZ101*42/1000 -> 3781.134 | CL101: =CC101*42/1000 -> 0.252
A102: 29677 | P102: 205.195 | Q102: 1.045 | R102: 213.467 | S102: 438.02 | T102: 219.717 | U102: 4.836 | V102: Not Available | W102: Not Available | X102: 205.195 | Y102: 7.226 | Z102: 1.045 | AA102: 213.467 | AB102: 438.02 | AN102: #N/A | AO102: #N/A | AP102: #N/A | AQ102: #N/A | AR102: #N/A | AS102: #N/A | AT102: #N/A | AU102: #N/A | AV102: #N/A | AW102: #N/A | AX102: #N/A | AY102: Not Available | AZ102: Not Available | BA102: 71.507 | BB102: 71.507 | BC102: Not Available | BD102: Not Available | BE102: Not Available | BF102: Not Available | BG102: 1.726 | BH102: Not Available | BI102: 0.004 | BJ102: 1.73 | BK102: 1.73 | BL102: 0.553 | BM102: Not Available | BN102: Not Available | BO102: Not Available | BP102: 0.553 | BQ102: 216.614 | BR102: 4.836 | BS102: Not Available | BT102: Not Available | BU102: 0.291 | BV102: 0.099 | BW102: 0.39 | BX102: 221.84 | BY102: 72535 | BZ102: 75951 | CA102: 3483 | CB102: 164647 | CC102: 101 | CG102: =CB102*42/1000 -> 6915.174 | CH102: =CA102*42/1000 -> 146.286 | CI102: =CC102*42/1000 -> 4.242 | CJ102: =BY102*42/1000 -> 3046.47 | CK102: =BZ102*42/1000 -> 3189.942 | CL102: =CC102*42/1000 -> 4.242
A103: 29707 | P103: 211.883 | Q103: 1.08 | R103: 220.433 | S103: 480.423 | T103: 255.2 | U103: 4.791 | V103: Not Available | W103: Not Available | X103: 211.883 | Y103: 7.469 | Z103: 1.08 | AA103: 220.433 | AB103: 480.423 | AN103: #N/A | AO103: #N/A | AP103: #N/A | AQ103: #N/A | AR103: #N/A | AS103: #N/A | AT103: #N/A | AU103: #N/A | AV103: #N/A | AW103: #N/A | AX103: #N/A | AY103: Not Available | AZ103: Not Available | BA103: 73.89 | BB103: 73.89 | BC103: Not Available | BD103: Not Available | BE103: Not Available | BF103: Not Available | BG103: 1.784 | BH103: Not Available | BI103: 0.004 | BJ103: 1.788 | BK103: 1.788 | BL103: 0.571 | BM103: Not Available | BN103: Not Available | BO103: Not Available | BP103: 0.571 | BQ103: 251.721 | BR103: 4.791 | BS103: Not Available | BT103: Not Available | BU103: 0.149 | BV103: 0.104 | BW103: 0.253 | BX103: 256.765 | BY103: 76053 | BZ103: 74733 | CA103: 5542 | CB103: 171837 | CC103: 3 | CG103: =CB103*42/1000 -> 7217.154 | CH103: =CA103*42/1000 -> 232.764 | CI103: =CC103*42/1000 -> 0.126 | CJ103: =BY103*42/1000 -> 3194.226 | CK103: =BZ103*42/1000 -> 3138.786 | CL103: =CC103*42/1000 -> 0.126
A104: 29738 | P104: 204.976 | Q104: 1.045 | R104: 213.237 | S104: 496.995 | T104: 278.976 | U104: 4.782 | V104: Not Available | W104: Not Available | X104: 204.976 | Y104: 7.216 | Z104: 1.045 | AA104: 213.237 | AB104: 496.995 | AN104: #N/A | AO104: #N/A | AP104: #N/A | AQ104: #N/A | AR104: #N/A | AS104: #N/A | AT104: #N/A | AU104: #N/A | AV104: #N/A | AW104: #N/A | AX104: #N/A | AY104: Not Available | AZ104: Not Available | BA104: 71.507 | BB104: 71.507 | BC104: Not Available | BD104: Not Available | BE104: Not Available | BF104: Not Available | BG104: 1.726 | BH104: Not Available | BI104: 0.004 | BJ104: 1.73 | BK104: 1.73 | BL104: 0.553 | BM104: Not Available | BN104: Not Available | BO104: Not Available | BP104: 0.553 | BQ104: 275.643 | BR104: 4.782 | BS104: Not Available | BT104: Not Available | BU104: 0.072 | BV104: 0.089 | BW104: 0.16 | BX104: 280.585 | BY104: 75014 | BZ104: 73930 | CA104: 6746 | CB104: 179945 | CC104: 15 | CG104: =CB104*42/1000 -> 7557.69 | CH104: =CA104*42/1000 -> 283.332 | CI104: =CC104*42/1000 -> 0.63 | CJ104: =BY104*42/1000 -> 3150.588 | CK104: =BZ104*42/1000 -> 3105.06 | CL104: =CC104*42/1000 -> 0.63
A105: 29768 | P105: 211.838 | Q105: 1.08 | R105: 220.392 | S105: 491.304 | T105: 265.656 | U105: 5.256 | V105: Not Available | W105: Not Available | X105: 211.838 | Y105: 7.473 | Z105: 1.08 | AA105: 220.392 | AB105: 491.304 | AN105: #N/A | AO105: #N/A | AP105: #N/A | AQ105: #N/A | AR105: #N/A | AS105: #N/A | AT105: #N/A | AU105: #N/A | AV105: #N/A | AW105: #N/A | AX105: #N/A | AY105: Not Available | AZ105: Not Available | BA105: 73.89 | BB105: 73.89 | BC105: Not Available | BD105: Not Available | BE105: Not Available | BF105: Not Available | BG105: 1.784 | BH105: Not Available | BI105: 0.004 | BJ105: 1.788 | BK105: 1.788 | BL105: 0.571 | BM105: Not Available | BN105: Not Available | BO105: Not Available | BP105: 0.571 | BQ105: 262.714 | BR105: 5.256 | BS105: Not Available | BT105: Not Available | BU105: 0.104 | BV105: 0.108 | BW105: 0.212 | BX105: 268.182 | BY105: 74227 | BZ105: 73708 | CA105: 5539 | CB105: 186264 | CC105: 72 | CG105: =CB105*42/1000 -> 7823.088 | CH105: =CA105*42/1000 -> 232.638 | CI105: =CC105*42/1000 -> 3.024 | CJ105: =BY105*42/1000 -> 3117.534 | CK105: =BZ105*42/1000 -> 3095.736 | CL105: =CC105*42/1000 -> 3.024
A106: 29799 | P106: 211.846 | Q106: 1.08 | R106: 220.428 | S106: 454.028 | T106: 228.409 | U106: 5.191 | V106: Not Available | W106: Not Available | X106: 211.846 | Y106: 7.501 | Z106: 1.08 | AA106: 220.428 | AB106: 454.028 | AN106: #N/A | AO106: #N/A | AP106: #N/A | AQ106: #N/A | AR106: #N/A | AS106: #N/A | AT106: #N/A | AU106: #N/A | AV106: #N/A | AW106: #N/A | AX106: #N/A | AY106: Not Available | AZ106: Not Available | BA106: 73.89 | BB106: 73.89 | BC106: Not Available | BD106: Not Available | BE106: Not Available | BF106: Not Available | BG106: 1.784 | BH106: Not Available | BI106: 0.004 | BJ106: 1.788 | BK106: 1.788 | BL106: 0.571 | BM106: Not Available | BN106: Not Available | BO106: Not Available | BP106: 0.571 | BQ106: 225.941 | BR106: 5.191 | BS106: Not Available | BT106: Not Available | BU106: 0.112 | BV106: 0.136 | BW106: 0.248 | BX106: 231.381 | BY106: 82316 | BZ106: 74019 | CA106: 5400 | CB106: 200224 | CC106: 7 | CG106: =CB106*42/1000 -> 8409.408 | CH106: =CA106*42/1000 -> 226.8 | CI106: =CC106*42/1000 -> 0.294 | CJ106: =BY106*42/1000 -> 3457.272 | CK106: =BZ106*42/1000 -> 3108.798 | CL106: =CC106*42/1000 -> 0.294
A107: 29830 | P107: 205.148 | Q107: 1.045 | R107: 213.48 | S107: 407.22 | T107: 188.516 | U107: 5.224 | V107: Not Available | W107: Not Available | X107: 205.148 | Y107: 7.287 | Z107: 1.045 | AA107: 213.48 | AB107: 407.22 | AN107: #N/A | AO107: #N/A | AP107: #N/A | AQ107: #N/A | AR107: #N/A | AS107: #N/A | AT107: #N/A | AU107: #N/A | AV107: #N/A | AW107: #N/A | AX107: #N/A | AY107: Not Available | AZ107: Not Available | BA107: 71.507 | BB107: 71.507 | BC107: Not Available | BD107: Not Available | BE107: Not Available | BF107: Not Available | BG107: 1.726 | BH107: Not Available | BI107: 0.004 | BJ107: 1.73 | BK107: 1.73 | BL107: 0.553 | BM107: Not Available | BN107: Not Available | BO107: Not Available | BP107: 0.553 | BQ107: 186.288 | BR107: 5.224 | BS107: Not Available | BT107: Not Available | BU107: 0.244 | BV107: 0.159 | BW107: 0.403 | BX107: 191.915 | BY107: 78306 | BZ107: 75378 | CA107: 3872 | CB107: 207287 | CC107: 32 | CG107: =CB107*42/1000 -> 8706.054 | CH107: =CA107*42/1000 -> 162.624 | CI107: =CC107*42/1000 -> 1.344 | CJ107: =BY107*42/1000 -> 3288.852 | CK107: =BZ107*42/1000 -> 3165.876 | CL107: =CC107*42/1000 -> 1.344
A108: 29860 | P108: 212.004 | Q108: 1.08 | R108: 220.581 | S108: 416.966 | T108: 191.231 | U108: 5.153 | V108: Not Available | W108: Not Available | X108: 212.004 | Y108: 7.497 | Z108: 1.08 | AA108: 220.581 | AB108: 416.966 | AN108: #N/A | AO108: #N/A | AP108: #N/A | AQ108: #N/A | AR108: #N/A | AS108: #N/A | AT108: #N/A | AU108: #N/A | AV108: #N/A | AW108: #N/A | AX108: #N/A | AY108: Not Available | AZ108: Not Available | BA108: 73.89 | BB108: 73.89 | BC108: Not Available | BD108: Not Available | BE108: Not Available | BF108: Not Available | BG108: 1.784 | BH108: Not Available | BI108: 0.004 | BJ108: 1.788 | BK108: 1.788 | BL108: 0.571 | BM108: Not Available | BN108: Not Available | BO108: Not Available | BP108: 0.571 | BQ108: 189.078 | BR108: 5.153 | BS108: Not Available | BT108: Not Available | BU108: 0.27 | BV108: 0.132 | BW108: 0.402 | BX108: 194.633 | BY108: 77020 | BZ108: 86900 | CA108: 3678 | CB108: 201189 | CC108: 167 | CG108: =CB108*42/1000 -> 8449.938 | CH108: =CA108*42/1000 -> 154.476 | CI108: =CC108*42/1000 -> 7.014 | CJ108: =BY108*42/1000 -> 3234.84 | CK108: =BZ108*42/1000 -> 3649.8 | CL108: =CC108*42/1000 -> 7.014
A109: 29891 | P109: 205.166 | Q109: 1.045 | R109: 213.437 | S109: 418.476 | T109: 200.541 | U109: 4.498 | V109: Not Available | W109: Not Available | X109: 205.166 | Y109: 7.226 | Z109: 1.045 | AA109: 213.437 | AB109: 418.476 | AN109: #N/A | AO109: #N/A | AP109: #N/A | AQ109: #N/A | AR109: #N/A | AS109: #N/A | AT109: #N/A | AU109: #N/A | AV109: #N/A | AW109: #N/A | AX109: #N/A | AY109: Not Available | AZ109: Not Available | BA109: 71.507 | BB109: 71.507 | BC109: Not Available | BD109: Not Available | BE109: Not Available | BF109: Not Available | BG109: 1.726 | BH109: Not Available | BI109: 0.004 | BJ109: 1.73 | BK109: 1.73 | BL109: 0.553 | BM109: Not Available | BN109: Not Available | BO109: Not Available | BP109: 0.553 | BQ109: 198.225 | BR109: 4.498 | BS109: Not Available | BT109: Not Available | BU109: 0.262 | BV109: 0.098 | BW109: 0.36 | BX109: 203.083 | BY109: 81463 | BZ109: 86413 | CA109: 3734 | CB109: 200115 | CC109: 193 | CG109: =CB109*42/1000 -> 8404.83 | CH109: =CA109*42/1000 -> 156.828 | CI109: =CC109*42/1000 -> 8.106 | CJ109: =BY109*42/1000 -> 3421.446 | CK109: =BZ109*42/1000 -> 3629.346 | CL109: =CC109*42/1000 -> 8.106
A110: 29921 | P110: 211.948 | Q110: 1.08 | R110: 220.44 | S110: 477.024 | T110: 252.071 | U110: 4.513 | V110: Not Available | W110: Not Available | X110: 211.948 | Y110: 7.412 | Z110: 1.08 | AA110: 220.44 | AB110: 477.024 | AN110: #N/A | AO110: #N/A | AP110: #N/A | AQ110: #N/A | AR110: #N/A | AS110: #N/A | AT110: #N/A | AU110: #N/A | AV110: #N/A | AW110: #N/A | AX110: #N/A | AY110: Not Available | AZ110: Not Available | BA110: 73.89 | BB110: 73.89 | BC110: Not Available | BD110: Not Available | BE110: Not Available | BF110: Not Available | BG110: 1.784 | BH110: Not Available | BI110: 0.004 | BJ110: 1.788 | BK110: 1.788 | BL110: 0.571 | BM110: Not Available | BN110: Not Available | BO110: Not Available | BP110: 0.571 | BQ110: 249.605 | BR110: 4.513 | BS110: Not Available | BT110: Not Available | BU110: 0.214 | BV110: 0.047 | BW110: 0.261 | BX110: 254.379 | BY110: 88548 | BZ110: 99578 | CA110: 2944 | CB110: 191541 | CC110: 820 | CG110: =CB110*42/1000 -> 8044.722 | CH110: =CA110*42/1000 -> 123.648 | CI110: =CC110*42/1000 -> 34.44 | CJ110: =BY110*42/1000 -> 3719.016 | CK110: =BZ110*42/1000 -> 4182.276 | CL110: =CC110*42/1000 -> 34.44
... A122: 30286 | P122: 213.17 | Q122: 2.922 | R122: 226.21 | S122: 522.93 | T122: 292.668 | U122: 4.053 | V122: Not Available | W122: Not Available | X122: 213.17 | Y122: 10.118 | Z122: 2.922 | AA122: 226.21 | AB122: 522.93 | AN122: #N/A | AO122: #N/A | AP122: #N/A | AQ122: #N/A | AR122: #N/A | AS122: #N/A | AT122: #N/A | AU122: #N/A | AV122: #N/A | AW122: #N/A | AX122: #N/A | AY122: Not Available | AZ122: Not Available | BA122: 82.384 | BB122: 82.384 | BC122: Not Available | BD122: Not Available | BE122: Not Available | BF122: Not Available | BG122: 1.868 | BH122: Not Available | BI122: 0.011 | BJ122: 1.88 | BK122: 1.88 | BL122: 1.553 | BM122: Not Available | BN122: Not Available | BO122: Not Available | BP122: 1.553 | BQ122: 290.202 | BR122: 4.053 | BS122: Not Available | BT122: Not Available | BU122: 0.161 | BV122: 0.122 | BW122: 0.283 | BX122: 294.538 | BY122: 82295 | BZ122: 88518 | CA122: 3370 | CB122: 178592 | CC122: 4436 | CG122: =CB122*42/1000 -> 7500.864 | CH122: =CA122*42/1000 -> 141.54 | CI122: =CC122*42/1000 -> 186.312 | CJ122: =BY122*42/1000 -> 3456.39 | CK122: =BZ122*42/1000 -> 3717.756 | CL122: =CC122*42/1000 -> 186.312
A123: 30317 | P123: 227.926 | Q123: 5.363 | R123: 246.575 | S123: 562.279 | T123: 310.615 | U123: 5.087 | V123: Not Available | W123: 0.002 | X123: 227.926 | Y123: 13.286 | Z123: 5.363 | AA123: 246.575 | AB123: 562.279 | AN123: #N/A | AO123: #N/A | AP123: #N/A | AQ123: #N/A | AR123: #N/A | AS123: #N/A | AT123: #N/A | AU123: #N/A | AV123: #N/A | AW123: #N/A | AX123: #N/A | AY123: Not Available | AZ123: Not Available | BA123: 82.384 | BB123: 82.384 | BC123: Not Available | BD123: Not Available | BE123: Not Available | BF123: Not Available | BG123: 1.868 | BH123: Not Available | BI123: 0.023 | BJ123: 1.892 | BK123: 1.892 | BL123: 2.864 | BM123: Not Available | BN123: Not Available | BO123: Not Available | BP123: 2.864 | BQ123: 307.547 | BR123: 5.087 | BS123: Not Available | BT123: 0.002 | BU123: 0.14 | BV123: 0.097 | BW123: 0.237 | BX123: 312.873 | BY123: 71963 | BZ123: 86692 | CA123: 2115 | CB123: 167555 | CC123: 5361 | CG123: =CB123*42/1000 -> 7037.31 | CH123: =CA123*42/1000 -> 88.83 | CI123: =CC123*42/1000 -> 225.162 | CJ123: =BY123*42/1000 -> 3022.446 | CK123: =BZ123*42/1000 -> 3641.064 | CL123: =CC123*42/1000 -> 225.162
A124: 30348 | P124: 205.87 | Q124: 4.844 | R124: 222.738 | S124: 523.276 | T124: 296.625 | U124: 3.913 | V124: Not Available | W124: 0 | X124: 205.87 | Y124: 12.023 | Z124: 4.844 | AA124: 222.738 | AB124: 523.276 | AN124: #N/A | AO124: #N/A | AP124: #N/A | AQ124: #N/A | AR124: #N/A | AS124: #N/A | AT124: #N/A | AU124: #N/A | AV124: #N/A | AW124: #N/A | AX124: #N/A | AY124: Not Available | AZ124: Not Available | BA124: 74.411 | BB124: 74.411 | BC124: Not Available | BD124: Not Available | BE124: Not Available | BF124: Not Available | BG124: 1.688 | BH124: Not Available | BI124: 0.021 | BJ124: 1.709 | BK124: 1.709 | BL124: 2.587 | BM124: Not Available | BN124: Not Available | BO124: Not Available | BP124: 2.587 | BQ124: 294.033 | BR124: 3.913 | BS124: Not Available | BT124: 0 | BU124: 0.128 | BV124: 0.111 | BW124: 0.239 | BX124: 298.185 | BY124: 59782 | BZ124: 77827 | CA124: 1638 | CB124: 148221 | CC124: 2931 | CG124: =CB124*42/1000 -> 6225.282 | CH124: =CA124*42/1000 -> 68.796 | CI124: =CC124*42/1000 -> 123.102 | CJ124: =BY124*42/1000 -> 2510.844 | CK124: =BZ124*42/1000 -> 3268.734 | CL124: =CC124*42/1000 -> 123.102
A125: 30376 | P125: 227.938 | Q125: 5.363 | R125: 246.61 | S125: 572.853 | T125: 321.73 | U125: 4.51 | V125: Not Available | W125: 0.003 | X125: 227.938 | Y125: 13.309 | Z125: 5.363 | AA125: 246.61 | AB125: 572.853 | AN125: #N/A | AO125: #N/A | AP125: #N/A | AQ125: #N/A | AR125: #N/A | AS125: #N/A | AT125: #N/A | AU125: #N/A | AV125: #N/A | AW125: #N/A | AX125: #N/A | AY125: Not Available | AZ125: Not Available | BA125: 82.384 | BB125: 82.384 | BC125: Not Available | BD125: Not Available | BE125: Not Available | BF125: Not Available | BG125: 1.868 | BH125: Not Available | BI125: 0.023 | BJ125: 1.892 | BK125: 1.892 | BL125: 2.864 | BM125: Not Available | BN125: Not Available | BO125: Not Available | BP125: 2.864 | BQ125: 318.779 | BR125: 4.51 | BS125: Not Available | BT125: 0.003 | BU125: 0.152 | BV125: 0.12 | BW125: 0.272 | BX125: 323.564 | BY125: 61787 | BZ125: 91369 | CA125: 1314 | CB125: 118122 | CC125: 1832 | CG125: =CB125*42/1000 -> 4961.124 | CH125: =CA125*42/1000 -> 55.188 | CI125: =CC125*42/1000 -> 76.944 | CJ125: =BY125*42/1000 -> 2595.054 | CK125: =BZ125*42/1000 -> 3837.498 | CL125: =CC125*42/1000 -> 76.944
A126: 30407 | P126: 220.561 | Q126: 5.19 | R126: 238.625 | S126: 561.458 | T126: 318.603 | U126: 4.227 | V126: Not Available | W126: 0.002 | X126: 220.561 | Y126: 12.875 | Z126: 5.19 | AA126: 238.625 | AB126: 561.458 | AN126: #N/A | AO126: #N/A | AP126: #N/A | AQ126: #N/A | AR126: #N/A | AS126: #N/A | AT126: #N/A | AU126: #N/A | AV126: #N/A | AW126: #N/A | AX126: #N/A | AY126: Not Available | AZ126: Not Available | BA126: 79.726 | BB126: 79.726 | BC126: Not Available | BD126: Not Available | BE126: Not Available | BF126: Not Available | BG126: 1.808 | BH126: Not Available | BI126: 0.023 | BJ126: 1.831 | BK126: 1.831 | BL126: 2.772 | BM126: Not Available | BN126: Not Available | BO126: Not Available | BP126: 2.772 | BQ126: 315.481 | BR126: 4.227 | BS126: Not Available | BT126: 0.002 | BU126: 0.122 | BV126: 0.112 | BW126: 0.234 | BX126: 319.944 | BY126: 65141 | BZ126: 80921 | CA126: 2197 | CB126: 103132 | CC126: 1408 | CG126: =CB126*42/1000 -> 4331.544 | CH126: =CA126*42/1000 -> 92.274 | CI126: =CC126*42/1000 -> 59.136 | CJ126: =BY126*42/1000 -> 2735.922 | CK126: =BZ126*42/1000 -> 3398.682 | CL126: =CC126*42/1000 -> 59.136
A127: 30437 | P127: 227.897 | Q127: 5.363 | R127: 246.647 | S127: 581.741 | T127: 331.656 | U127: 3.434 | V127: Not Available | W127: 0.003 | X127: 227.897 | Y127: 13.387 | Z127: 5.363 | AA127: 246.647 | AB127: 581.741 | AN127: #N/A | AO127: #N/A | AP127: #N/A | AQ127: #N/A | AR127: #N/A | AS127: #N/A | AT127: #N/A | AU127: #N/A | AV127: #N/A | AW127: #N/A | AX127: #N/A | AY127: Not Available | AZ127: Not Available | BA127: 82.384 | BB127: 82.384 | BC127: Not Available | BD127: Not Available | BE127: Not Available | BF127: Not Available | BG127: 1.868 | BH127: Not Available | BI127: 0.023 | BJ127: 1.892 | BK127: 1.892 | BL127: 2.864 | BM127: Not Available | BN127: Not Available | BO127: Not Available | BP127: 2.864 | BQ127: 328.156 | BR127: 3.434 | BS127: Not Available | BT127: 0.003 | BU127: 0.111 | BV127: 0.198 | BW127: 0.309 | BX127: 331.902 | BY127: 75762 | BZ127: 72980 | CA127: 4547 | CB127: 108904 | CC127: 1559 | CG127: =CB127*42/1000 -> 4573.968 | CH127: =CA127*42/1000 -> 190.974 | CI127: =CC127*42/1000 -> 65.478 | CJ127: =BY127*42/1000 -> 3182.004 | CK127: =BZ127*42/1000 -> 3065.16 | CL127: =CC127*42/1000 -> 65.478
A128: 30468 | P128: 220.582 | Q128: 5.19 | R128: 238.736 | S128: 569.493 | T128: 326.237 | U128: 4.518 | V128: Not Available | W128: 0.002 | X128: 220.582 | Y128: 12.964 | Z128: 5.19 | AA128: 238.736 | AB128: 569.493 | AN128: #N/A | AO128: #N/A | AP128: #N/A | AQ128: #N/A | AR128: #N/A | AS128: #N/A | AT128: #N/A | AU128: #N/A | AV128: #N/A | AW128: #N/A | AX128: #N/A | AY128: Not Available | AZ128: Not Available | BA128: 79.726 | BB128: 79.726 | BC128: Not Available | BD128: Not Available | BE128: Not Available | BF128: Not Available | BG128: 1.808 | BH128: Not Available | BI128: 0.023 | BJ128: 1.831 | BK128: 1.831 | BL128: 2.772 | BM128: Not Available | BN128: Not Available | BO128: Not Available | BP128: 2.772 | BQ128: 322.883 | BR128: 4.518 | BS128: Not Available | BT128: 0.002 | BU128: 0.144 | BV128: 0.2 | BW128: 0.344 | BX128: 327.747 | BY128: 76376 | BZ128: 75715 | CA128: 5362 | CB128: 113723 | CC128: 1203 | CG128: =CB128*42/1000 -> 4776.366 | CH128: =CA128*42/1000 -> 225.204 | CI128: =CC128*42/1000 -> 50.526 | CJ128: =BY128*42/1000 -> 3207.792 | CK128: =BZ128*42/1000 -> 3180.03 | CL128: =CC128*42/1000 -> 50.526
A129: 30498 | P129: 227.933 | Q129: 5.363 | R129: 246.651 | S129: 550.993 | T129: 298.715 | U129: 5.627 | V129: Not Available | W129: 0.001 | X129: 227.933 | Y129: 13.354 | Z129: 5.363 | AA129: 246.651 | AB129: 550.993 | AN129: #N/A | AO129: #N/A | AP129: #N/A | AQ129: #N/A | AR129: #N/A | AS129: #N/A | AT129: #N/A | AU129: #N/A | AV129: #N/A | AW129: #N/A | AX129: #N/A | AY129: Not Available | AZ129: Not Available | BA129: 82.384 | BB129: 82.384 | BC129: Not Available | BD129: Not Available | BE129: Not Available | BF129: Not Available | BG129: 1.868 | BH129: Not Available | BI129: 0.023 | BJ129: 1.892 | BK129: 1.892 | BL129: 2.864 | BM129: Not Available | BN129: Not Available | BO129: Not Available | BP129: 2.864 | BQ129: 295.753 | BR129: 5.627 | BS129: Not Available | BT129: 0.001 | BU129: 0.147 | BV129: 0.165 | BW129: 0.313 | BX129: 301.694 | BY129: 80723 | BZ129: 70362 | CA129: 8265 | CB129: 130655 | CC129: 1695 | CG129: =CB129*42/1000 -> 5487.51 | CH129: =CA129*42/1000 -> 347.13 | CI129: =CC129*42/1000 -> 71.19 | CJ129: =BY129*42/1000 -> 3390.366 | CK129: =BZ129*42/1000 -> 2955.204 | CL129: =CC129*42/1000 -> 71.19
A130: 30529 | P130: 227.978 | Q130: 5.363 | R130: 246.695 | S130: 528.288 | T130: 274.189 | U130: 7.404 | V130: Not Available | W130: 0 | X130: 227.978 | Y130: 13.354 | Z130: 5.363 | AA130: 246.695 | AB130: 528.288 | AN130: #N/A | AO130: #N/A | AP130: #N/A | AQ130: #N/A | AR130: #N/A | AS130: #N/A | AT130: #N/A | AU130: #N/A | AV130: #N/A | AW130: #N/A | AX130: #N/A | AY130: Not Available | AZ130: Not Available | BA130: 82.384 | BB130: 82.384 | BC130: Not Available | BD130: Not Available | BE130: Not Available | BF130: Not Available | BG130: 1.868 | BH130: Not Available | BI130: 0.023 | BJ130: 1.892 | BK130: 1.892 | BL130: 2.864 | BM130: Not Available | BN130: Not Available | BO130: Not Available | BP130: 2.864 | BQ130: 271.706 | BR130: 7.404 | BS130: Not Available | BT130: 0 | BU130: 0.191 | BV130: 0.165 | BW130: 0.357 | BX130: 279.467 | BY130: 81077 | BZ130: 77348 | CA130: 9346 | CB130: 142406 | CC130: 1324 | CG130: =CB130*42/1000 -> 5981.052 | CH130: =CA130*42/1000 -> 392.532 | CI130: =CC130*42/1000 -> 55.608 | CJ130: =BY130*42/1000 -> 3405.234 | CK130: =BZ130*42/1000 -> 3248.616 | CL130: =CC130*42/1000 -> 55.608
A131: 30560 | P131: 220.641 | Q131: 5.19 | R131: 238.755 | S131: 476.173 | T131: 230.65 | U131: 6.764 | V131: Not Available | W131: 0.004 | X131: 220.641 | Y131: 12.924 | Z131: 5.19 | AA131: 238.755 | AB131: 476.173 | AN131: #N/A | AO131: #N/A | AP131: #N/A | AQ131: #N/A | AR131: #N/A | AS131: #N/A | AT131: #N/A | AU131: #N/A | AV131: #N/A | AW131: #N/A | AX131: #N/A | AY131: Not Available | AZ131: Not Available | BA131: 79.726 | BB131: 79.726 | BC131: Not Available | BD131: Not Available | BE131: Not Available | BF131: Not Available | BG131: 1.808 | BH131: Not Available | BI131: 0.023 | BJ131: 1.831 | BK131: 1.831 | BL131: 2.772 | BM131: Not Available | BN131: Not Available | BO131: Not Available | BP131: 2.772 | BQ131: 228.407 | BR131: 6.764 | BS131: Not Available | BT131: 0.004 | BU131: 0.203 | BV131: 0.161 | BW131: 0.364 | BX131: 235.539 | BY131: 82183 | BZ131: 77262 | CA131: 7766 | CB131: 153996 | CC131: 1097 | CG131: =CB131*42/1000 -> 6467.832 | CH131: =CA131*42/1000 -> 326.172 | CI131: =CC131*42/1000 -> 46.074 | CJ131: =BY131*42/1000 -> 3451.686 | CK131: =BZ131*42/1000 -> 3245.004 | CL131: =CC131*42/1000 -> 46.074
A132: 30590 | P132: 228.031 | Q132: 5.363 | R132: 246.732 | S132: 474.251 | T132: 220.423 | U132: 7.091 | V132: Not Available | W132: 0.005 | X132: 228.031 | Y132: 13.338 | Z132: 5.363 | AA132: 246.732 | AB132: 474.251 | AN132: #N/A | AO132: #N/A | AP132: #N/A | AQ132: #N/A | AR132: #N/A | AS132: #N/A | AT132: #N/A | AU132: #N/A | AV132: #N/A | AW132: #N/A | AX132: #N/A | AY132: Not Available | AZ132: Not Available | BA132: 82.384 | BB132: 82.384 | BC132: Not Available | BD132: Not Available | BE132: Not Available | BF132: Not Available | BG132: 1.868 | BH132: Not Available | BI132: 0.023 | BJ132: 1.892 | BK132: 1.892 | BL132: 2.864 | BM132: Not Available | BN132: Not Available | BO132: Not Available | BP132: 2.864 | BQ132: 218.256 | BR132: 7.091 | BS132: Not Available | BT132: 0.005 | BU132: 0.245 | BV132: 0.149 | BW132: 0.394 | BX132: 225.746 | BY132: 83122 | BZ132: 80931 | CA132: 8066 | CB132: 162551 | CC132: 1701 | CG132: =CB132*42/1000 -> 6827.142 | CH132: =CA132*42/1000 -> 338.772 | CI132: =CC132*42/1000 -> 71.442 | CJ132: =BY132*42/1000 -> 3491.124 | CK132: =BZ132*42/1000 -> 3399.102 | CL132: =CC132*42/1000 -> 71.442
A133: 30621 | P133: 220.719 | Q133: 5.19 | R133: 238.78 | S133: 507.035 | T133: 261.94 | U133: 6.311 | V133: Not Available | W133: 0.004 | X133: 220.719 | Y133: 12.872 | Z133: 5.19 | AA133: 238.78 | AB133: 507.035 | AN133: #N/A | AO133: #N/A | AP133: #N/A | AQ133: #N/A | AR133: #N/A | AS133: #N/A | AT133: #N/A | AU133: #N/A | AV133: #N/A | AW133: #N/A | AX133: #N/A | AY133: Not Available | AZ133: Not Available | BA133: 79.726 | BB133: 79.726 | BC133: Not Available | BD133: Not Available | BE133: Not Available | BF133: Not Available | BG133: 1.808 | BH133: Not Available | BI133: 0.023 | BJ133: 1.831 | BK133: 1.831 | BL133: 2.772 | BM133: Not Available | BN133: Not Available | BO133: Not Available | BP133: 2.772 | BQ133: 259.609 | BR133: 6.311 | BS133: Not Available | BT133: 0.004 | BU133: 0.28 | BV133: 0.108 | BW133: 0.389 | BX133: 266.313 | BY133: 80393 | BZ133: 86209 | CA133: 6090 | CB133: 161211 | CC133: 1614 | CG133: =CB133*42/1000 -> 6770.862 | CH133: =CA133*42/1000 -> 255.78 | CI133: =CC133*42/1000 -> 67.788 | CJ133: =BY133*42/1000 -> 3376.506 | CK133: =BZ133*42/1000 -> 3620.778 | CL133: =CC133*42/1000 -> 67.788
A134: 30651 | P134: 228.194 | Q134: 5.363 | R134: 246.871 | S134: 587.773 | T134: 335.876 | U134: 5.025 | V134: Not Available | W134: 0.001 | X134: 228.194 | Y134: 13.314 | Z134: 5.363 | AA134: 246.871 | AB134: 587.773 | AN134: #N/A | AO134: #N/A | AP134: #N/A | AQ134: #N/A | AR134: #N/A | AS134: #N/A | AT134: #N/A | AU134: #N/A | AV134: #N/A | AW134: #N/A | AX134: #N/A | AY134: Not Available | AZ134: Not Available | BA134: 82.384 | BB134: 82.384 | BC134: Not Available | BD134: Not Available | BE134: Not Available | BF134: Not Available | BG134: 1.868 | BH134: Not Available | BI134: 0.023 | BJ134: 1.892 | BK134: 1.892 | BL134: 2.864 | BM134: Not Available | BN134: Not Available | BO134: Not Available | BP134: 2.864 | BQ134: 333.394 | BR134: 5.025 | BS134: Not Available | BT134: 0.001 | BU134: 0.408 | BV134: 0.125 | BW134: 0.533 | BX134: 338.953 | BY134: 78195 | BZ134: 104310 | CA134: 6836 | CB134: 140263 | CC134: 1669 | CG134: =CB134*42/1000 -> 5891.046 | CH134: =CA134*42/1000 -> 287.112 | CI134: =CC134*42/1000 -> 70.098 | CJ134: =BY134*42/1000 -> 3284.19 | CK134: =BZ134*42/1000 -> 4381.02 | CL134: =CC134*42/1000 -> 70.098
A135: 30682 | P135: 227.551 | Q135: 6.547 | R135: 251.483 | S135: 570.081 | T135: 313.504 | U135: 5.094 | V135: -0.001 | W135: 0 | X135: 227.551 | Y135: 17.385 | Z135: 6.547 | AA135: 251.483 | AB135: 570.081 | AN135: #N/A | AO135: #N/A | AP135: #N/A | AQ135: #N/A | AR135: #N/A | AS135: #N/A | AT135: #N/A | AU135: #N/A | AV135: #N/A | AW135: #N/A | AX135: #N/A | AY135: Not Available | AZ135: Not Available | BA135: 83.005 | BB135: 83.005 | BC135: Not Available | BD135: Not Available | BE135: Not Available | BF135: Not Available | BG135: 1.863 | BH135: Not Available | BI135: 0.03 | BJ135: 1.893 | BK135: 1.893 | BL135: 3.495 | BM135: Not Available | BN135: Not Available | BO135: Not Available | BP135: 3.495 | BQ135: 310.459 | BR135: 5.094 | BS135: -0.001 | BT135: 0 | BU135: 0.471 | BV135: 0.143 | BW135: 0.614 | BX135: 316.168 | BY135: 80281 | BZ135: 109271 | CA135: 9257 | CB135: 119317 | CC135: 1248 | CG135: =CB135*42/1000 -> 5011.314 | CH135: =CA135*42/1000 -> 388.794 | CI135: =CC135*42/1000 -> 52.416 | CJ135: =BY135*42/1000 -> 3371.802 | CK135: =BZ135*42/1000 -> 4589.382 | CL135: =CC135*42/1000 -> 52.416
A136: 30713 | P136: 212.673 | Q136: 6.125 | R136: 235.169 | S136: 535.239 | T136: 293.845 | U136: 6.222 | V136: 0.001 | W136: 0.002 | X136: 212.673 | Y136: 16.371 | Z136: 6.125 | AA136: 235.169 | AB136: 535.239 | AN136: #N/A | AO136: #N/A | AP136: #N/A | AQ136: #N/A | AR136: #N/A | AS136: #N/A | AT136: #N/A | AU136: #N/A | AV136: #N/A | AW136: #N/A | AX136: #N/A | AY136: Not Available | AZ136: Not Available | BA136: 77.65 | BB136: 77.65 | BC136: Not Available | BD136: Not Available | BE136: Not Available | BF136: Not Available | BG136: 1.743 | BH136: Not Available | BI136: 0.028 | BJ136: 1.771 | BK136: 1.771 | BL136: 3.27 | BM136: Not Available | BN136: Not Available | BO136: Not Available | BP136: 3.27 | BQ136: 291.272 | BR136: 6.222 | BS136: 0.001 | BT136: 0.002 | BU136: 0.244 | BV136: 0.241 | BW136: 0.485 | BX136: 297.983 | BY136: 83106 | BZ136: 82185 | CA136: 13167 | CB136: 132242 | CC136: 1203 | CG136: =CB136*42/1000 -> 5554.164 | CH136: =CA136*42/1000 -> 553.014 | CI136: =CC136*42/1000 -> 50.526 | CJ136: =BY136*42/1000 -> 3490.452 | CK136: =BZ136*42/1000 -> 3451.77 | CL136: =CC136*42/1000 -> 50.526
A137: 30742 | P137: 227.378 | Q137: 6.547 | R137: 251.529 | S137: 579.04 | T137: 320.67 | U137: 6.838 | V137: 0.002 | W137: 0.002 | X137: 227.378 | Y137: 17.603 | Z137: 6.547 | AA137: 251.529 | AB137: 579.04 | AN137: #N/A | AO137: #N/A | AP137: #N/A | AQ137: #N/A | AR137: #N/A | AS137: #N/A | AT137: #N/A | AU137: #N/A | AV137: #N/A | AW137: #N/A | AX137: #N/A | AY137: Not Available | AZ137: Not Available | BA137: 83.005 | BB137: 83.005 | BC137: Not Available | BD137: Not Available | BE137: Not Available | BF137: Not Available | BG137: 1.863 | BH137: Not Available | BI137: 0.03 | BJ137: 1.893 | BK137: 1.893 | BL137: 3.495 | BM137: Not Available | BN137: Not Available | BO137: Not Available | BP137: 3.495 | BQ137: 317.741 | BR137: 6.838 | BS137: 0.002 | BT137: 0.002 | BU137: 0.299 | BV137: 0.361 | BW137: 0.66 | BX137: 325.243 | BY137: 76800 | BZ137: 101043 | CA137: 3568 | CB137: 109572 | CC137: 2036 | CG137: =CB137*42/1000 -> 4602.024 | CH137: =CA137*42/1000 -> 149.856 | CI137: =CC137*42/1000 -> 85.512 | CJ137: =BY137*42/1000 -> 3225.6 | CK137: =BZ137*42/1000 -> 4243.806 | CL137: =CC137*42/1000 -> 85.512
A138: 30773 | P138: 219.904 | Q138: 6.336 | R138: 243.277 | S138: 566.019 | T138: 315.985 | U138: 6.748 | V138: 0.003 | W138: 0.006 | X138: 219.904 | Y138: 17.037 | Z138: 6.336 | AA138: 243.277 | AB138: 566.019 | AN138: #N/A | AO138: #N/A | AP138: #N/A | AQ138: #N/A | AR138: #N/A | AS138: #N/A | AT138: #N/A | AU138: #N/A | AV138: #N/A | AW138: #N/A | AX138: #N/A | AY138: Not Available | AZ138: Not Available | BA138: 80.328 | BB138: 80.328 | BC138: Not Available | BD138: Not Available | BE138: Not Available | BF138: Not Available | BG138: 1.803 | BH138: Not Available | BI138: 0.029 | BJ138: 1.832 | BK138: 1.832 | BL138: 3.382 | BM138: Not Available | BN138: Not Available | BO138: Not Available | BP138: 3.382 | BQ138: 312.886 | BR138: 6.748 | BS138: 0.003 | BT138: 0.006 | BU138: 0.15 | BV138: 0.351 | BW138: 0.501 | BX138: 320.144 | BY138: 70218 | BZ138: 87790 | CA138: 6608 | CB138: 97690 | CC138: 959 | CG138: =CB138*42/1000 -> 4102.98 | CH138: =CA138*42/1000 -> 277.536 | CI138: =CC138*42/1000 -> 40.278 | CJ138: =BY138*42/1000 -> 2949.156 | CK138: =BZ138*42/1000 -> 3687.18 | CL138: =CC138*42/1000 -> 40.278
A139: 30803 | P139: 227.242 | Q139: 6.547 | R139: 251.408 | S139: 593.504 | T139: 335.607 | U139: 6.473 | V139: 0.007 | W139: 0.008 | X139: 227.242 | Y139: 17.619 | Z139: 6.547 | AA139: 251.408 | AB139: 593.504 | AN139: #N/A | AO139: #N/A | AP139: #N/A | AQ139: #N/A | AR139: #N/A | AS139: #N/A | AT139: #N/A | AU139: #N/A | AV139: #N/A | AW139: #N/A | AX139: #N/A | AY139: Not Available | AZ139: Not Available | BA139: 83.005 | BB139: 83.005 | BC139: Not Available | BD139: Not Available | BE139: Not Available | BF139: Not Available | BG139: 1.863 | BH139: Not Available | BI139: 0.03 | BJ139: 1.893 | BK139: 1.893 | BL139: 3.495 | BM139: Not Available | BN139: Not Available | BO139: Not Available | BP139: 3.495 | BQ139: 332.133 | BR139: 6.473 | BS139: 0.007 | BT139: 0.008 | BU139: 0.163 | BV139: 0.377 | BW139: 0.54 | BX139: 339.161 | BY139: 81298 | BZ139: 87223 | CA139: 7836 | CB139: 98144 | CC139: 1498 | CG139: =CB139*42/1000 -> 4122.048 | CH139: =CA139*42/1000 -> 329.112 | CI139: =CC139*42/1000 -> 62.916 | CJ139: =BY139*42/1000 -> 3414.516 | CK139: =BZ139*42/1000 -> 3663.366 | CL139: =CC139*42/1000 -> 62.916
A140: 30834 | P140: 219.914 | Q140: 6.336 | R140: 243.303 | S140: 553.321 | T140: 303.719 | U140: 6.283 | V140: 0.01 | W140: 0.006 | X140: 219.914 | Y140: 17.053 | Z140: 6.336 | AA140: 243.303 | AB140: 553.321 | AN140: #N/A | AO140: #N/A | AP140: #N/A | AQ140: #N/A | AR140: #N/A | AS140: #N/A | AT140: #N/A | AU140: #N/A | AV140: #N/A | AW140: #N/A | AX140: #N/A | AY140: Not Available | AZ140: Not Available | BA140: 80.328 | BB140: 80.328 | BC140: Not Available | BD140: Not Available | BE140: Not Available | BF140: Not Available | BG140: 1.803 | BH140: Not Available | BI140: 0.029 | BJ140: 1.832 | BK140: 1.832 | BL140: 3.382 | BM140: Not Available | BN140: Not Available | BO140: Not Available | BP140: 3.382 | BQ140: 300.39 | BR140: 6.283 | BS140: 0.01 | BT140: 0.006 | BU140: 0.159 | BV140: 0.367 | BW140: 0.526 | BX140: 307.216 | BY140: 86366 | BZ140: 77803 | CA140: 7691 | CB140: 112849 | CC140: 1589 | CG140: =CB140*42/1000 -> 4739.658 | CH140: =CA140*42/1000 -> 323.022 | CI140: =CC140*42/1000 -> 66.738 | CJ140: =BY140*42/1000 -> 3627.372 | CK140: =BZ140*42/1000 -> 3267.726 | CL140: =CC140*42/1000 -> 66.738
A141: 30864 | P141: 227.458 | Q141: 6.547 | R141: 251.632 | S141: 547.618 | T141: 289.982 | U141: 5.997 | V141: 0.003 | W141: 0.005 | X141: 227.458 | Y141: 17.627 | Z141: 6.547 | AA141: 251.632 | AB141: 547.618 | AN141: #N/A | AO141: #N/A | AP141: #N/A | AQ141: #N/A | AR141: #N/A | AS141: #N/A | AT141: #N/A | AU141: #N/A | AV141: #N/A | AW141: #N/A | AX141: #N/A | AY141: Not Available | AZ141: Not Available | BA141: 83.005 | BB141: 83.005 | BC141: Not Available | BD141: Not Available | BE141: Not Available | BF141: Not Available | BG141: 1.863 | BH141: Not Available | BI141: 0.03 | BJ141: 1.893 | BK141: 1.893 | BL141: 3.495 | BM141: Not Available | BN141: Not Available | BO141: Not Available | BP141: 3.495 | BQ141: 287.043 | BR141: 5.997 | BS141: 0.003 | BT141: 0.005 | BU141: 0.379 | BV141: 0.384 | BW141: 0.763 | BX141: 293.811 | BY141: 84245 | BZ141: 77622 | CA141: 6156 | CB141: 124421 | CC141: 1245 | CG141: =CB141*42/1000 -> 5225.682 | CH141: =CA141*42/1000 -> 258.552 | CI141: =CC141*42/1000 -> 52.29 | CJ141: =BY141*42/1000 -> 3538.29 | CK141: =BZ141*42/1000 -> 3260.124 | CL141: =CC141*42/1000 -> 52.29
A142: 30895 | P142: 227.481 | Q142: 6.547 | R142: 251.638 | S142: 524.053 | T142: 264.894 | U142: 7.509 | V142: 0.009 | W142: 0.003 | X142: 227.481 | Y142: 17.61 | Z142: 6.547 | AA142: 251.638 | AB142: 524.053 | AN142: #N/A | AO142: #N/A | AP142: #N/A | AQ142: #N/A | AR142: #N/A | AS142: #N/A | AT142: #N/A | AU142: #N/A | AV142: #N/A | AW142: #N/A | AX142: #N/A | AY142: Not Available | AZ142: Not Available | BA142: 83.005 | BB142: 83.005 | BC142: Not Available | BD142: Not Available | BE142: Not Available | BF142: Not Available | BG142: 1.863 | BH142: Not Available | BI142: 0.03 | BJ142: 1.893 | BK142: 1.893 | BL142: 3.495 | BM142: Not Available | BN142: Not Available | BO142: Not Available | BP142: 3.495 | BQ142: 262.43 | BR142: 7.509 | BS142: 0.009 | BT142: 0.003 | BU142: 0.402 | BV142: 0.368 | BW142: 0.769 | BX142: 270.72 | BY142: 82447 | BZ142: 79322 | CA142: 8034 | CB142: 133317 | CC142: 2305 | CG142: =CB142*42/1000 -> 5599.314 | CH142: =CA142*42/1000 -> 337.428 | CI142: =CC142*42/1000 -> 96.81 | CJ142: =BY142*42/1000 -> 3462.774 | CK142: =BZ142*42/1000 -> 3331.524 | CL142: =CC142*42/1000 -> 96.81
A143: 30926 | P143: 220.21 | Q143: 6.336 | R143: 243.596 | S143: 470.91 | T143: 220.536 | U143: 6.763 | V143: 0.01 | W143: 0.005 | X143: 220.21 | Y143: 17.049 | Z143: 6.336 | AA143: 243.596 | AB143: 470.91 | AN143: #N/A | AO143: #N/A | AP143: #N/A | AQ143: #N/A | AR143: #N/A | AS143: #N/A | AT143: #N/A | AU143: #N/A | AV143: #N/A | AW143: #N/A | AX143: #N/A | AY143: Not Available | AZ143: Not Available | BA143: 80.328 | BB143: 80.328 | BC143: Not Available | BD143: Not Available | BE143: Not Available | BF143: Not Available | BG143: 1.803 | BH143: Not Available | BI143: 0.029 | BJ143: 1.832 | BK143: 1.832 | BL143: 3.382 | BM143: Not Available | BN143: Not Available | BO143: Not Available | BP143: 3.382 | BQ143: 218.311 | BR143: 6.763 | BS143: 0.01 | BT143: 0.005 | BU143: 0.456 | BV143: 0.364 | BW143: 0.819 | BX143: 225.909 | BY143: 81148 | BZ143: 79634 | CA143: 8720 | CB143: 142943 | CC143: 655 | CG143: =CB143*42/1000 -> 6003.606 | CH143: =CA143*42/1000 -> 366.24 | CI143: =CC143*42/1000 -> 27.51 | CJ143: =BY143*42/1000 -> 3408.216 | CK143: =BZ143*42/1000 -> 3344.628 | CL143: =CC143*42/1000 -> 27.51
A144: 30956 | P144: 227.64 | Q144: 6.547 | R144: 251.974 | S144: 479.62 | T144: 220.205 | U144: 7.424 | V144: 0.007 | W144: 0.009 | X144: 227.64 | Y144: 17.786 | Z144: 6.547 | AA144: 251.974 | AB144: 479.62 | AN144: #N/A | AO144: #N/A | AP144: #N/A | AQ144: #N/A | AR144: #N/A | AS144: #N/A | AT144: #N/A | AU144: #N/A | AV144: #N/A | AW144: #N/A | AX144: #N/A | AY144: Not Available | AZ144: Not Available | BA144: 83.005 | BB144: 83.005 | BC144: Not Available | BD144: Not Available | BE144: Not Available | BF144: Not Available | BG144: 1.863 | BH144: Not Available | BI144: 0.03 | BJ144: 1.893 | BK144: 1.893 | BL144: 3.495 | BM144: Not Available | BN144: Not Available | BO144: Not Available | BP144: 3.495 | BQ144: 218.055 | BR144: 7.424 | BS144: 0.007 | BT144: 0.009 | BU144: 0.561 | BV144: 0.544 | BW144: 1.105 | BX144: 226.601 | BY144: 83388 | BZ144: 85719 | CA144: 13037 | CB144: 152236 | CC144: 1460 | CG144: =CB144*42/1000 -> 6393.912 | CH144: =CA144*42/1000 -> 547.554 | CI144: =CC144*42/1000 -> 61.32 | CJ144: =BY144*42/1000 -> 3502.296 | CK144: =BZ144*42/1000 -> 3600.198 | CL144: =CC144*42/1000 -> 61.32
A145: 30987 | P145: 220.555 | Q145: 6.336 | R145: 244.068 | S145: 486.11 | T145: 234.699 | U145: 7.331 | V145: 0.004 | W145: 0.009 | X145: 220.555 | Y145: 17.177 | Z145: 6.336 | AA145: 244.068 | AB145: 486.11 | AN145: #N/A | AO145: #N/A | AP145: #N/A | AQ145: #N/A | AR145: #N/A | AS145: #N/A | AT145: #N/A | AU145: #N/A | AV145: #N/A | AW145: #N/A | AX145: #N/A | AY145: Not Available | AZ145: Not Available | BA145: 80.328 | BB145: 80.328 | BC145: Not Available | BD145: Not Available | BE145: Not Available | BF145: Not Available | BG145: 1.803 | BH145: Not Available | BI145: 0.029 | BJ145: 1.832 | BK145: 1.832 | BL145: 3.382 | BM145: Not Available | BN145: Not Available | BO145: Not Available | BP145: 3.382 | BQ145: 232.386 | BR145: 7.331 | BS145: 0.004 | BT145: 0.009 | BU145: 0.8 | BV145: 0.491 | BW145: 1.291 | BX145: 241.021 | BY145: 84743 | BZ145: 84799 | CA145: 9465 | CB145: 160970 | CC145: 715 | CG145: =CB145*42/1000 -> 6760.74 | CH145: =CA145*42/1000 -> 397.53 | CI145: =CC145*42/1000 -> 30.03 | CJ145: =BY145*42/1000 -> 3559.206 | CK145: =BZ145*42/1000 -> 3561.558 | CL145: =CC145*42/1000 -> 30.03
A146: 31017 | P146: 227.811 | Q146: 6.547 | R146: 252.042 | S146: 532.347 | T146: 272.166 | U146: 8.127 | V146: 0 | W146: 0.013 | X146: 227.811 | Y146: 17.684 | Z146: 6.547 | AA146: 252.042 | AB146: 532.347 | AN146: #N/A | AO146: #N/A | AP146: #N/A | AQ146: #N/A | AR146: #N/A | AS146: #N/A | AT146: #N/A | AU146: #N/A | AV146: #N/A | AW146: #N/A | AX146: #N/A | AY146: Not Available | AZ146: Not Available | BA146: 83.005 | BB146: 83.005 | BC146: Not Available | BD146: Not Available | BE146: Not Available | BF146: Not Available | BG146: 1.863 | BH146: Not Available | BI146: 0.03 | BJ146: 1.893 | BK146: 1.893 | BL146: 3.495 | BM146: Not Available | BN146: Not Available | BO146: Not Available | BP146: 3.495 | BQ146: 269.703 | BR146: 8.127 | BS146: 0 | BT146: 0.013 | BU146: 0.732 | BV146: 0.442 | BW146: 1.174 | BX146: 279.015 | BY146: 86687 | BZ146: 88806 | CA146: 5900 | CB146: 161072 | CC146: 3724 | CG146: =CB146*42/1000 -> 6765.024 | CH146: =CA146*42/1000 -> 247.8 | CI146: =CC146*42/1000 -> 156.408 | CJ146: =BY146*42/1000 -> 3640.854 | CK146: =BZ146*42/1000 -> 3729.852 | CL146: =CC146*42/1000 -> 156.408
... A194: 32478 | P194: 218.215 | Q194: 10.508 | R194: 255.345 | S194: 472.132 | T194: 208.016 | U194: 8.77 | V194: 0.001 | W194: 0.001 | X194: 218.215 | Y194: 26.623 | Z194: 10.508 | AA194: 255.345 | AB194: 472.132 | AN194: #N/A | AO194: #N/A | AP194: #N/A | AQ194: #N/A | AR194: #N/A | AS194: #N/A | AT194: #N/A | AU194: #N/A | AV194: #N/A | AW194: #N/A | AX194: #N/A | AY194: Not Available | AZ194: Not Available | BA194: 77.077 | BB194: 77.077 | BC194: Not Available | BD194: Not Available | BE194: Not Available | BF194: Not Available | BG194: 2.71 | BH194: Not Available | BI194: 0.045 | BJ194: 2.756 | BK194: 2.756 | BL194: 5.685 | BM194: Not Available | BN194: Not Available | BO194: Not Available | BP194: 5.685 | BQ194: 205.58 | BR194: 8.77 | BS194: 0.001 | BT194: 0.001 | BU194: 0.791 | BV194: 0.56 | BW194: 1.352 | BX194: 215.703 | BY194: 95063 | BZ194: 110375 | CA194: 12681 | CB194: 123517 | CC194: 2694 | CG194: =CB194*42/1000 -> 5187.714 | CH194: =CA194*42/1000 -> 532.602 | CI194: =CC194*42/1000 -> 113.148 | CJ194: =BY194*42/1000 -> 3992.646 | CK194: =BZ194*42/1000 -> 4635.75 | CL194: =CC194*42/1000 -> 113.148
A195: 32509 | P195: 231.17 | Q195: 10.649 | R195: 266.572 | S195: 509.146 | T195: 224.04 | U195: 14.134 | V195: 2.881 | W195: 1.521 | X195: 231.17 | Y195: 24.753 | Z195: 10.649 | AA195: 266.572 | AB195: 509.146 | AN195: #N/A | AO195: #N/A | AP195: #N/A | AQ195: #N/A | AR195: #N/A | AS195: #N/A | AT195: #N/A | AU195: #N/A | AV195: #N/A | AW195: #N/A | AX195: #N/A | AY195: 0.425 | AZ195: 2.798 | BA195: 78.137 | BB195: 81.36 | BC195: 0.054 | BD195: 0.212 | BE195: 0.008 | BF195: No Data Reported | BG195: 6.503 | BH195: 1.245 | BI195: 0.043 | BJ195: 7.791 | BK195: 8.065 | BL195: 5.783 | BM195: Not Available | BN195: Not Available | BO195: Not Available | BP195: 5.783 | BQ195: 221.743 | BR195: 13.344 | BS195: 0.073 | BT195: 1.521 | BU195: 8.805 | BV195: 7.468 | BW195: 16.273 | BX195: 252.952 | BY195: 92184 | BZ195: 102405 | CA195: 10734 | CB195: 120620 | CC195: 3410 | CG195: =CB195*42/1000 -> 5066.04 | CH195: =CA195*42/1000 -> 450.828 | CI195: =CC195*42/1000 -> 143.22 | CJ195: =BY195*42/1000 -> 3871.728 | CK195: =BZ195*42/1000 -> 4301.01 | CL195: =CC195*42/1000 -> 143.22
A196: 32540 | P196: 211.272 | Q196: 9.618 | R196: 243.927 | S196: 461.434 | T196: 199.31 | U196: 12.761 | V196: 3.104 | W196: 2.331 | X196: 211.272 | Y196: 23.037 | Z196: 9.618 | AA196: 243.927 | AB196: 461.434 | AN196: #N/A | AO196: #N/A | AP196: #N/A | AQ196: #N/A | AR196: #N/A | AS196: #N/A | AT196: #N/A | AU196: #N/A | AV196: #N/A | AW196: #N/A | AX196: #N/A | AY196: 0.384 | AZ196: 3.016 | BA196: 70.575 | BB196: 73.975 | BC196: 0.048 | BD196: 0.192 | BE196: 0.009 | BF196: No Data Reported | BG196: 5.878 | BH196: 1.204 | BI196: 0.039 | BJ196: 7.121 | BK196: 7.369 | BL196: 5.223 | BM196: Not Available | BN196: Not Available | BO196: Not Available | BP196: 5.223 | BQ196: 197.267 | BR196: 12.048 | BS196: 0.077 | BT196: 2.331 | BU196: 8.192 | BV196: 7.221 | BW196: 15.413 | BX196: 227.136 | BY196: 78318 | BZ196: 95966 | CA196: 9257 | CB196: 107648 | CC196: 4581 | CG196: =CB196*42/1000 -> 4521.216 | CH196: =CA196*42/1000 -> 388.794 | CI196: =CC196*42/1000 -> 192.402 | CJ196: =BY196*42/1000 -> 3289.356 | CK196: =BZ196*42/1000 -> 4030.572 | CL196: =CC196*42/1000 -> 192.402
A197: 32568 | P197: 236.6 | Q197: 10.649 | R197: 268.315 | S197: 532.714 | T197: 242.358 | U197: 15.001 | V197: 4.37 | W197: 2.671 | X197: 236.6 | Y197: 21.067 | Z197: 10.649 | AA197: 268.315 | AB197: 532.714 | AN197: #N/A | AO197: #N/A | AP197: #N/A | AQ197: #N/A | AR197: #N/A | AS197: #N/A | AT197: #N/A | AU197: #N/A | AV197: #N/A | AW197: #N/A | AX197: #N/A | AY197: 0.425 | AZ197: 4.156 | BA197: 78.137 | BB197: 82.718 | BC197: 0.059 | BD197: 0.212 | BE197: 0.012 | BF197: No Data Reported | BG197: 6.513 | BH197: 0.815 | BI197: 0.043 | BJ197: 7.371 | BK197: 7.654 | BL197: 5.783 | BM197: Not Available | BN197: Not Available | BO197: Not Available | BP197: 5.783 | BQ197: 239.874 | BR197: 14.211 | BS197: 0.199 | BT197: 2.671 | BU197: 9.331 | BV197: 4.888 | BW197: 14.219 | BX197: 271.173 | BY197: 84107 | BZ197: 106268 | CA197: 13606 | CB197: 96736 | CC197: 2357 | CG197: =CB197*42/1000 -> 4062.912 | CH197: =CA197*42/1000 -> 571.452 | CI197: =CC197*42/1000 -> 98.994 | CJ197: =BY197*42/1000 -> 3532.494 | CK197: =BZ197*42/1000 -> 4463.256 | CL197: =CC197*42/1000 -> 98.994
A198: 32599 | P198: 218.29 | Q198: 10.305 | R198: 251.946 | S198: 530.096 | T198: 257.728 | U198: 13.095 | V198: 4.843 | W198: 2.484 | X198: 218.29 | Y198: 23.351 | Z198: 10.305 | AA198: 251.946 | AB198: 530.096 | AN198: #N/A | AO198: #N/A | AP198: #N/A | AQ198: #N/A | AR198: #N/A | AS198: #N/A | AT198: #N/A | AU198: #N/A | AV198: #N/A | AW198: #N/A | AX198: #N/A | AY198: 0.411 | AZ198: 4.581 | BA198: 75.616 | BB198: 80.608 | BC198: 0.062 | BD198: 0.205 | BE198: 0.013 | BF198: No Data Reported | BG198: 6.283 | BH198: 1.134 | BI198: 0.041 | BJ198: 7.458 | BK198: 7.739 | BL198: 5.597 | BM198: Not Available | BN198: Not Available | BO198: Not Available | BP198: 5.597 | BQ198: 255.086 | BR198: 12.33 | BS198: 0.247 | BT198: 2.484 | BU198: 7.995 | BV198: 6.805 | BW198: 14.8 | BX198: 284.947 | BY198: 83679 | BZ198: 89242 | CA198: 9039 | CB198: 98541 | CC198: 1671 | CG198: =CB198*42/1000 -> 4138.722 | CH198: =CA198*42/1000 -> 379.638 | CI198: =CC198*42/1000 -> 70.182 | CJ198: =BY198*42/1000 -> 3514.518 | CK198: =BZ198*42/1000 -> 3748.164 | CL198: =CC198*42/1000 -> 70.182
A199: 32629 | P199: 200.711 | Q199: 10.649 | R199: 241.235 | S199: 562.699 | T199: 300.24 | U199: 13.857 | V199: 5.237 | W199: 2.131 | X199: 200.711 | Y199: 29.876 | Z199: 10.649 | AA199: 241.235 | AB199: 562.699 | AN199: #N/A | AO199: #N/A | AP199: #N/A | AQ199: #N/A | AR199: #N/A | AS199: #N/A | AT199: #N/A | AU199: #N/A | AV199: #N/A | AW199: #N/A | AX199: #N/A | AY199: 0.425 | AZ199: 5.057 | BA199: 78.137 | BB199: 83.618 | BC199: 0.073 | BD199: 0.212 | BE199: 0.014 | BF199: No Data Reported | BG199: 6.445 | BH199: 1.842 | BI199: 0.043 | BJ199: 8.33 | BK199: 8.629 | BL199: 5.783 | BM199: Not Available | BN199: Not Available | BO199: Not Available | BP199: 5.783 | BQ199: 297.162 | BR199: 13.067 | BS199: 0.162 | BT199: 2.131 | BU199: 5.853 | BV199: 11.053 | BW199: 16.906 | BX199: 329.428 | BY199: 85239 | BZ199: 91561 | CA199: 8975 | CB199: 99618 | CC199: 1576 | CG199: =CB199*42/1000 -> 4183.956 | CH199: =CA199*42/1000 -> 376.95 | CI199: =CC199*42/1000 -> 66.192 | CJ199: =BY199*42/1000 -> 3580.038 | CK199: =BZ199*42/1000 -> 3845.562 | CL199: =CC199*42/1000 -> 66.192
A200: 32660 | P200: 208.439 | Q200: 10.305 | R200: 248.447 | S200: 546.135 | T200: 277.046 | U200: 13.664 | V200: 5.346 | W200: 1.631 | X200: 208.439 | Y200: 29.704 | Z200: 10.305 | AA200: 248.447 | AB200: 546.135 | AN200: #N/A | AO200: #N/A | AP200: #N/A | AQ200: #N/A | AR200: #N/A | AS200: #N/A | AT200: #N/A | AU200: #N/A | AV200: #N/A | AW200: #N/A | AX200: #N/A | AY200: 0.411 | AZ200: 5.102 | BA200: 75.616 | BB200: 81.13 | BC200: 0.067 | BD200: 0.205 | BE200: 0.015 | BF200: No Data Reported | BG200: 6.264 | BH200: 1.875 | BI200: 0.041 | BJ200: 8.181 | BK200: 8.468 | BL200: 5.597 | BM200: Not Available | BN200: Not Available | BO200: Not Available | BP200: 5.597 | BQ200: 274.206 | BR200: 12.9 | BS200: 0.226 | BT200: 1.631 | BU200: 7.04 | BV200: 11.25 | BW200: 18.291 | BX200: 307.254 | BY200: 84265 | BZ200: 90068 | CA200: 6981 | CB200: 99613 | CC200: 1183 | CG200: =CB200*42/1000 -> 4183.746 | CH200: =CA200*42/1000 -> 293.202 | CI200: =CC200*42/1000 -> 49.686 | CJ200: =BY200*42/1000 -> 3539.13 | CK200: =BZ200*42/1000 -> 3782.856 | CL200: =CC200*42/1000 -> 49.686
A201: 32690 | P201: 217.404 | Q201: 10.649 | R201: 261.318 | S201: 525.096 | T201: 242.678 | U201: 13.872 | V201: 5.746 | W201: 1.482 | X201: 217.404 | Y201: 33.265 | Z201: 10.649 | AA201: 261.318 | AB201: 525.096 | AN201: #N/A | AO201: #N/A | AP201: #N/A | AQ201: #N/A | AR201: #N/A | AS201: #N/A | AT201: #N/A | AU201: #N/A | AV201: #N/A | AW201: #N/A | AX201: #N/A | AY201: 0.425 | AZ201: 5.356 | BA201: 78.137 | BB201: 83.918 | BC201: 0.059 | BD201: 0.212 | BE201: 0.015 | BF201: No Data Reported | BG201: 6.477 | BH201: 2.238 | BI201: 0.043 | BJ201: 8.757 | BK201: 9.043 | BL201: 5.783 | BM201: Not Available | BN201: Not Available | BO201: Not Available | BP201: 5.783 | BQ201: 240.19 | BR201: 13.082 | BS201: 0.371 | BT201: 1.482 | BU201: 7.471 | BV201: 13.425 | BW201: 20.895 | BX201: 276.021 | BY201: 88285 | BZ201: 80484 | CA201: 10366 | CB201: 115036 | CC201: 2744 | CG201: =CB201*42/1000 -> 4831.512 | CH201: =CA201*42/1000 -> 435.372 | CI201: =CC201*42/1000 -> 115.248 | CJ201: =BY201*42/1000 -> 3707.97 | CK201: =BZ201*42/1000 -> 3380.328 | CL201: =CC201*42/1000 -> 115.248
A202: 32721 | P202: 234.088 | Q202: 10.649 | R202: 276.985 | S202: 513.153 | T202: 216.086 | U202: 13.414 | V202: 5.593 | W202: 1.075 | X202: 234.088 | Y202: 32.249 | Z202: 10.649 | AA202: 276.985 | AB202: 513.153 | AN202: #N/A | AO202: #N/A | AP202: #N/A | AQ202: #N/A | AR202: #N/A | AS202: #N/A | AT202: #N/A | AU202: #N/A | AV202: #N/A | AW202: #N/A | AX202: #N/A | AY202: 0.425 | AZ202: 5.301 | BA202: 78.137 | BB202: 83.862 | BC202: 0.052 | BD202: 0.212 | BE202: 0.015 | BF202: No Data Reported | BG202: 6.508 | BH202: 2.119 | BI202: 0.043 | BJ202: 8.67 | BK202: 8.95 | BL202: 5.783 | BM202: Not Available | BN202: Not Available | BO202: Not Available | BP202: 5.783 | BQ202: 213.871 | BR202: 12.624 | BS202: 0.274 | BT202: 1.075 | BU202: 9.087 | BV202: 12.714 | BW202: 21.801 | BX202: 249.645 | BY202: 90103 | BZ202: 91933 | CA202: 7888 | CB202: 116306 | CC202: 4788 | CG202: =CB202*42/1000 -> 4884.852 | CH202: =CA202*42/1000 -> 331.296 | CI202: =CC202*42/1000 -> 201.096 | CJ202: =BY202*42/1000 -> 3784.326 | CK202: =BZ202*42/1000 -> 3861.186 | CL202: =CC202*42/1000 -> 201.096
A203: 32752 | P203: 220.479 | Q203: 10.305 | R203: 264.811 | S203: 487.948 | T203: 202.515 | U203: 12.52 | V203: 5.18 | W203: 2.923 | X203: 220.479 | Y203: 34.027 | Z203: 10.305 | AA203: 264.811 | AB203: 487.948 | AN203: #N/A | AO203: #N/A | AP203: #N/A | AQ203: #N/A | AR203: #N/A | AS203: #N/A | AT203: #N/A | AU203: #N/A | AV203: #N/A | AW203: #N/A | AX203: #N/A | AY203: 0.411 | AZ203: 4.835 | BA203: 75.616 | BB203: 80.862 | BC203: 0.049 | BD203: 0.205 | BE203: 0.014 | BF203: No Data Reported | BG203: 6.287 | BH203: 2.38 | BI203: 0.041 | BJ203: 8.708 | BK203: 8.976 | BL203: 5.597 | BM203: Not Available | BN203: Not Available | BO203: Not Available | BP203: 5.597 | BQ203: 200.439 | BR203: 11.756 | BS203: 0.328 | BT203: 2.923 | BU203: 8.207 | BV203: 14.276 | BW203: 22.483 | BX203: 237.928 | BY203: 88551 | BZ203: 86681 | CA203: 7475 | CB203: 123226 | CC203: 2425 | CG203: =CB203*42/1000 -> 5175.492 | CH203: =CA203*42/1000 -> 313.95 | CI203: =CC203*42/1000 -> 101.85 | CJ203: =BY203*42/1000 -> 3719.142 | CK203: =BZ203*42/1000 -> 3640.602 | CL203: =CC203*42/1000 -> 101.85
A204: 32782 | P204: 230.492 | Q204: 10.649 | R204: 276.462 | S204: 511.058 | T204: 214.892 | U204: 13.157 | V204: 4.715 | W204: 1.832 | X204: 230.492 | Y204: 35.321 | Z204: 10.649 | AA204: 276.462 | AB204: 511.058 | AN204: #N/A | AO204: #N/A | AP204: #N/A | AQ204: #N/A | AR204: #N/A | AS204: #N/A | AT204: #N/A | AU204: #N/A | AV204: #N/A | AW204: #N/A | AX204: #N/A | AY204: 0.425 | AZ204: 4.406 | BA204: 78.137 | BB204: 82.968 | BC204: 0.052 | BD204: 0.212 | BE204: 0.013 | BF204: No Data Reported | BG204: 6.502 | BH204: 2.478 | BI204: 0.043 | BJ204: 9.022 | BK204: 9.299 | BL204: 5.783 | BM204: Not Available | BN204: Not Available | BO204: Not Available | BP204: 5.783 | BQ204: 212.689 | BR204: 12.367 | BS204: 0.294 | BT204: 1.832 | BU204: 8.739 | BV204: 14.864 | BW204: 23.603 | BX204: 250.785 | BY204: 90092 | BZ204: 96930 | CA204: 8088 | CB204: 121691 | CC204: 2785 | CG204: =CB204*42/1000 -> 5111.022 | CH204: =CA204*42/1000 -> 339.696 | CI204: =CC204*42/1000 -> 116.97 | CJ204: =BY204*42/1000 -> 3783.864 | CK204: =BZ204*42/1000 -> 4071.06 | CL204: =CC204*42/1000 -> 116.97
A205: 32813 | P205: 231.613 | Q205: 10.305 | R205: 276.819 | S205: 521.323 | T205: 226.777 | U205: 12.562 | V205: 3.884 | W205: 1.281 | X205: 231.613 | Y205: 34.901 | Z205: 10.305 | AA205: 276.819 | AB205: 521.323 | AN205: #N/A | AO205: #N/A | AP205: #N/A | AQ205: #N/A | AR205: #N/A | AS205: #N/A | AT205: #N/A | AU205: #N/A | AV205: #N/A | AW205: #N/A | AX205: #N/A | AY205: 0.411 | AZ205: 3.614 | BA205: 75.616 | BB205: 79.642 | BC205: 0.055 | BD205: 0.205 | BE205: 0.01 | BF205: No Data Reported | BG205: 6.308 | BH205: 2.482 | BI205: 0.041 | BJ205: 8.831 | BK205: 9.102 | BL205: 5.597 | BM205: Not Available | BN205: Not Available | BO205: Not Available | BP205: 5.597 | BQ205: 224.453 | BR205: 11.797 | BS205: 0.257 | BT205: 1.281 | BU205: 9.286 | BV205: 14.888 | BW205: 24.174 | BX205: 261.962 | BY205: 91896 | BZ205: 99338 | CA205: 9207 | CB205: 119764 | CC205: 3692 | CG205: =CB205*42/1000 -> 5030.088 | CH205: =CA205*42/1000 -> 386.694 | CI205: =CC205*42/1000 -> 155.064 | CJ205: =BY205*42/1000 -> 3859.632 | CK205: =BZ205*42/1000 -> 4172.196 | CL205: =CC205*42/1000 -> 155.064
A206: 32843 | P206: 239.066 | Q206: 10.649 | R206: 282.52 | S206: 533.84 | T206: 233.595 | U206: 13.504 | V206: 3.55 | W206: 0.671 | X206: 239.066 | Y206: 32.806 | Z206: 10.649 | AA206: 282.52 | AB206: 533.84 | AN206: #N/A | AO206: #N/A | AP206: #N/A | AQ206: #N/A | AR206: #N/A | AS206: #N/A | AT206: #N/A | AU206: #N/A | AV206: #N/A | AW206: #N/A | AX206: #N/A | AY206: 0.425 | AZ206: 3.431 | BA206: 78.137 | BB206: 81.992 | BC206: 0.056 | BD206: 0.212 | BE206: 0.01 | BF206: No Data Reported | BG206: 6.518 | BH206: 2.184 | BI206: 0.043 | BJ206: 8.745 | BK206: 9.024 | BL206: 5.783 | BM206: Not Available | BN206: Not Available | BO206: Not Available | BP206: 5.783 | BQ206: 231.201 | BR206: 12.714 | BS206: 0.107 | BT206: 0.671 | BU206: 9.57 | BV206: 13.104 | BW206: 22.673 | BX206: 267.366 | BY206: 101256 | BZ206: 121348 | CA206: 10058 | CB206: 105700 | CC206: 4030 | CG206: =CB206*42/1000 -> 4439.4 | CH206: =CA206*42/1000 -> 422.436 | CI206: =CC206*42/1000 -> 169.26 | CJ206: =BY206*42/1000 -> 4252.752 | CK206: =BZ206*42/1000 -> 5096.616 | CL206: =CC206*42/1000 -> 169.26
... A315: 36161 | P315: 210.996 | Q315: 19.158 | R315: 272.26 | S315: 596.135 | T315: 301.877 | U315: 15.171 | V315: 3.38 | W315: 3.446 | X315: 210.996 | Y315: 42.105 | Z315: 18.586 | AA315: 271.688 | AB315: 595.563 | AN315: #N/A | AO315: #N/A | AP315: #N/A | AQ315: #N/A | AR315: #N/A | AS315: #N/A | AT315: #N/A | AU315: #N/A | AV315: #N/A | AW315: #N/A | AX315: #N/A | AY315: 0.722 | AZ315: 3.27 | BA315: 33.123 | BB315: 37.115 | BC315: 0.108 | BD315: 0.569 | BE315: 0.026 | BF315: No Data Reported | BG315: 5.675 | BH315: 4.071 | BI315: 0.018 | BJ315: 9.765 | BK315: 10.468 | BL315: 10.305 | BM315: Not Available | BN315: Not Available | BO315: Not Available | BP315: 10.305 | BQ315: 297.274 | BR315: 13.532 | BS315: 0.078 | BT315: 3.446 | BU315: 14.064 | BV315: 23.801 | BW315: 37.865 | BX315: 352.195 | BY315: 98453 | BZ315: 117434 | CA315: 9409 | CB315: 142861 | CC315: 3642 | CG315: =CB315*42/1000 -> 6000.162 | CH315: =CA315*42/1000 -> 395.178 | CI315: =CC315*42/1000 -> 152.964 | CJ315: =BY315*42/1000 -> 4135.026 | CK315: =BZ315*42/1000 -> 4932.228 | CL315: =CC315*42/1000 -> 152.964
A316: 36192 | P316: 162.352 | Q316: 15.417 | R316: 220.539 | S316: 533.202 | T316: 293.419 | U316: 12.383 | V316: 3.703 | W316: 3.159 | X316: 162.352 | Y316: 42.77 | Z316: 15.313 | AA316: 220.435 | AB316: 533.098 | AN316: #N/A | AO316: #N/A | AP316: #N/A | AQ316: #N/A | AR316: #N/A | AS316: #N/A | AT316: #N/A | AU316: #N/A | AV316: #N/A | AW316: #N/A | AX316: #N/A | AY316: 0.652 | AZ316: 3.525 | BA316: 29.918 | BB316: 34.095 | BC316: 0.105 | BD316: 0.514 | BE316: 0.028 | BF316: No Data Reported | BG316: 5.105 | BH316: 4.316 | BI316: 0.015 | BJ316: 9.436 | BK316: 10.084 | BL316: 8.645 | BM316: Not Available | BN316: Not Available | BO316: Not Available | BP316: 8.645 | BQ316: 288.945 | BR316: 10.902 | BS316: 0.143 | BT316: 3.159 | BU316: 9.823 | BV316: 25.229 | BW316: 35.052 | BX316: 338.201 | BY316: 91086 | BZ316: 99189 | CA316: 9022 | CB316: 140524 | CC316: 3256 | CG316: =CB316*42/1000 -> 5902.008 | CH316: =CA316*42/1000 -> 378.924 | CI316: =CC316*42/1000 -> 136.752 | CJ316: =BY316*42/1000 -> 3825.612 | CK316: =BZ316*42/1000 -> 4165.938 | CL316: =CD316*42/1000 -> 0
A317: 36220 | P317: 149.912 | Q317: 17.696 | R317: 212.177 | S317: 564.559 | T317: 328.047 | U317: 14.471 | V317: 5.296 | W317: 4.568 | X317: 149.912 | Y317: 44.57 | Z317: 16.867 | AA317: 211.349 | AB317: 563.73 | AN317: #N/A | AO317: #N/A | AP317: #N/A | AQ317: #N/A | AR317: #N/A | AS317: #N/A | AT317: #N/A | AU317: #N/A | AV317: #N/A | AW317: #N/A | AX317: #N/A | AY317: 0.722 | AZ317: 4.856 | BA317: 33.123 | BB317: 38.702 | BC317: 0.118 | BD317: 0.569 | BE317: 0.039 | BF317: No Data Reported | BG317: 5.63 | BH317: 4.403 | BI317: 0.017 | BJ317: 10.05 | BK317: 10.775 | BL317: 9.221 | BM317: Not Available | BN317: Not Available | BO317: Not Available | BP317: 9.221 | BQ317: 323.044 | BR317: 12.832 | BS317: 0.392 | BT317: 4.568 | BU317: 7.83 | BV317: 25.741 | BW317: 33.571 | BX317: 374.407 | BY317: 98667 | BZ317: 117349 | CA317: 7693 | CB317: 124621 | CC317: 4914 | CG317: =CB317*42/1000 -> 5234.082 | CH317: =CA317*42/1000 -> 323.106 | CI317: =CC317*42/1000 -> 206.388 | CJ317: =BY317*42/1000 -> 4144.014 | CK317: =BZ317*42/1000 -> 4928.658 | CL317: =CD317*42/1000 -> 0
A318: 36251 | P318: 183.534 | Q318: 19.152 | R318: 249.92 | S318: 551.65 | T318: 279.566 | U318: 12.382 | V318: 5.965 | W318: 3.818 | X318: 183.534 | Y318: 47.234 | Z318: 16.77 | AA318: 247.537 | AB318: 549.268 | AN318: #N/A | AO318: #N/A | AP318: #N/A | AQ318: #N/A | AR318: #N/A | AS318: #N/A | AT318: #N/A | AU318: #N/A | AV318: #N/A | AW318: #N/A | AX318: #N/A | AY318: 0.699 | AZ318: 5.353 | BA318: 32.055 | BB318: 38.106 | BC318: 0.1 | BD318: 0.551 | BE318: 0.043 | BF318: No Data Reported | BG318: 5.477 | BH318: 4.814 | BI318: 0.015 | BJ318: 10.306 | BK318: 11 | BL318: 8.511 | BM318: Not Available | BN318: Not Available | BO318: Not Available | BP318: 8.511 | BQ318: 275.302 | BR318: 10.796 | BS318: 0.56 | BT318: 3.818 | BU318: 11.503 | BV318: 28.141 | BW318: 39.644 | BX318: 330.12 | BY318: 102209 | BZ318: 102443 | CA318: 6376 | CB318: 125028 | CC318: 5735 | CG318: =CB318*42/1000 -> 5251.176 | CH318: =CA318*42/1000 -> 267.792 | CI318: =CC318*42/1000 -> 240.87 | CJ318: =BY318*42/1000 -> 4292.778 | CK318: =BZ318*42/1000 -> 4302.606 | CL318: =CD318*42/1000 -> 0
A319: 36281 | P319: 222.166 | Q319: 17.388 | R319: 289.264 | S319: 610.248 | T319: 296.517 | U319: 15.035 | V319: 6.614 | W319: 2.818 | X319: 222.166 | Y319: 49.711 | Z319: 16.077 | AA319: 287.953 | AB319: 608.937 | AN319: #N/A | AO319: #N/A | AP319: #N/A | AQ319: #N/A | AR319: #N/A | AS319: #N/A | AT319: #N/A | AU319: #N/A | AV319: #N/A | AW319: #N/A | AX319: #N/A | AY319: 0.722 | AZ319: 5.909 | BA319: 33.123 | BB319: 39.754 | BC319: 0.106 | BD319: 0.569 | BE319: 0.047 | BF319: No Data Reported | BG319: 5.684 | BH319: 5.096 | BI319: 0.015 | BJ319: 10.795 | BK319: 11.517 | BL319: 8.57 | BM319: Not Available | BN319: Not Available | BO319: Not Available | BP319: 8.57 | BQ319: 291.995 | BR319: 13.396 | BS319: 0.647 | BT319: 2.818 | BU319: 15.205 | BV319: 29.79 | BW319: 44.994 | BX319: 353.851 | BY319: 107194 | BZ319: 102735 | CA319: 8105 | CB319: 131803 | CC319: 5789 | CG319: =CB319*42/1000 -> 5535.726 | CH319: =CA319*42/1000 -> 340.41 | CI319: =CC319*42/1000 -> 243.138 | CJ319: =BY319*42/1000 -> 4502.148 | CK319: =BZ319*42/1000 -> 4314.87 | CL319: =CD319*42/1000 -> 0
A320: 36312 | P320: 173.903 | Q320: 14.336 | R320: 236.09 | S320: 571.946 | T320: 312.577 | U320: 13.986 | V320: 6.696 | W320: 2.596 | X320: 173.903 | Y320: 47.851 | Z320: 15.636 | AA320: 237.39 | AB320: 573.246 | AN320: #N/A | AO320: #N/A | AP320: #N/A | AQ320: #N/A | AR320: #N/A | AS320: #N/A | AT320: #N/A | AU320: #N/A | AV320: #N/A | AW320: #N/A | AX320: #N/A | AY320: 0.699 | AZ320: 5.962 | BA320: 32.055 | BB320: 38.716 | BC320: 0.112 | BD320: 0.551 | BE320: 0.048 | BF320: No Data Reported | BG320: 5.47 | BH320: 4.897 | BI320: 0.017 | BJ320: 10.383 | BK320: 11.094 | BL320: 9.42 | BM320: Not Available | BN320: Not Available | BO320: Not Available | BP320: 9.42 | BQ320: 307.811 | BR320: 12.4 | BS320: 0.676 | BT320: 2.596 | BU320: 10.52 | BV320: 28.627 | BW320: 39.147 | BX320: 362.629 | BY320: 101210 | BZ320: 102224 | CA320: 7150 | CB320: 132545 | CC320: 5394 | CG320: =CB320*42/1000 -> 5566.89 | CH320: =CA320*42/1000 -> 300.3 | CI320: =CC320*42/1000 -> 226.548 | CJ320: =BY320*42/1000 -> 4250.82 | CK320: =BZ320*42/1000 -> 4293.408 | CL320: =CD320*42/1000 -> 0
A321: 36342 | P321: 203.953 | Q321: 14.275 | R321: 264.292 | S321: 593.676 | T321: 303.567 | U321: 14.153 | V321: 7.001 | W321: 4.664 | X321: 203.953 | Y321: 46.064 | Z321: 14.23 | AA321: 264.247 | AB321: 593.631 | AN321: #N/A | AO321: #N/A | AP321: #N/A | AQ321: #N/A | AR321: #N/A | AS321: #N/A | AT321: #N/A | AU321: #N/A | AV321: #N/A | AW321: #N/A | AX321: #N/A | AY321: 0.722 | AZ321: 6.259 | BA321: 33.123 | BB321: 40.104 | BC321: 0.109 | BD321: 0.569 | BE321: 0.05 | BF321: No Data Reported | BG321: 5.67 | BH321: 4.604 | BI321: 0.014 | BJ321: 10.289 | BK321: 11.017 | BL321: 8.055 | BM321: Not Available | BN321: Not Available | BO321: Not Available | BP321: 8.055 | BQ321: 298.938 | BR321: 12.514 | BS321: 0.681 | BT321: 4.664 | BU321: 13.346 | BV321: 26.918 | BW321: 40.263 | BX321: 357.059 | BY321: 109146 | BZ321: 107838 | CA321: 7251 | CB321: 137295 | CC321: 3809 | CG321: =CB321*42/1000 -> 5766.39 | CH321: =CA321*42/1000 -> 304.542 | CI321: =CC321*42/1000 -> 159.978 | CJ321: =BY321*42/1000 -> 4584.132 | CK321: =BZ321*42/1000 -> 4529.196 | CL321: =CD321*42/1000 -> 0
A322: 36373 | P322: 197.764 | Q322: 17.11 | R322: 258.854 | S322: 547.07 | T322: 263.077 | U322: 14.417 | V322: 6.813 | W322: 3.909 | X322: 197.764 | Y322: 43.98 | Z322: 16.624 | AA322: 258.368 | AB322: 546.585 | AN322: #N/A | AO322: #N/A | AP322: #N/A | AQ322: #N/A | AR322: #N/A | AS322: #N/A | AT322: #N/A | AU322: #N/A | AV322: #N/A | AW322: #N/A | AX322: #N/A | AY322: 0.722 | AZ322: 6.194 | BA322: 33.123 | BB322: 40.039 | BC322: 0.094 | BD322: 0.569 | BE322: 0.049 | BF322: No Data Reported | BG322: 5.665 | BH322: 4.324 | BI322: 0.017 | BJ322: 10.006 | BK322: 10.719 | BL322: 9.228 | BM322: Not Available | BN322: Not Available | BO322: Not Available | BP322: 9.228 | BQ322: 259.065 | BR322: 12.777 | BS322: 0.559 | BT322: 3.909 | BU322: 12.714 | BV322: 25.277 | BW322: 37.991 | BX322: 314.301 | BY322: 106003 | BZ322: 106547 | CA322: 8463 | CB322: 141191 | CC322: 4023 | CG322: =CB322*42/1000 -> 5930.022 | CH322: =CA322*42/1000 -> 355.446 | CI322: =CC322*42/1000 -> 168.966 | CJ322: =BY322*42/1000 -> 4452.126 | CK322: =BZ322*42/1000 -> 4474.974 | CL322: =CD322*42/1000 -> 0
A323: 36404 | P323: 181.899 | Q323: 17.877 | R323: 244.14 | S323: 482.158 | T323: 213.64 | U323: 14.426 | V323: 6.093 | W323: 3.859 | X323: 181.899 | Y323: 44.364 | Z323: 16.972 | AA323: 243.235 | AB323: 481.253 | AN323: #N/A | AO323: #N/A | AP323: #N/A | AQ323: #N/A | AR323: #N/A | AS323: #N/A | AT323: #N/A | AU323: #N/A | AV323: #N/A | AW323: #N/A | AX323: #N/A | AY323: 0.699 | AZ323: 5.649 | BA323: 32.055 | BB323: 38.403 | BC323: 0.077 | BD323: 0.551 | BE323: 0.045 | BF323: No Data Reported | BG323: 5.476 | BH323: 4.427 | BI323: 0.017 | BJ323: 9.919 | BK323: 10.592 | BL323: 9.249 | BM323: Not Available | BN323: Not Available | BO323: Not Available | BP323: 9.249 | BQ323: 210.382 | BR323: 12.84 | BS323: 0.389 | BT323: 3.859 | BU323: 11.336 | BV323: 25.881 | BW323: 37.217 | BX323: 264.686 | BY323: 104450 | BZ323: 102926 | CA323: 7483 | CB323: 145347 | CC323: 4851 | CG323: =CB323*42/1000 -> 6104.574 | CH323: =CA323*42/1000 -> 314.286 | CI323: =CC323*42/1000 -> 203.742 | CJ323: =BY323*42/1000 -> 4386.9 | CK323: =BZ323*42/1000 -> 4322.892 | CL323: =CD323*42/1000 -> 0
A324: 36434 | P324: 164.413 | Q324: 19.309 | R324: 228.256 | S324: 456.712 | T324: 203.526 | U324: 14.953 | V324: 5.696 | W324: 4.281 | X324: 164.413 | Y324: 44.534 | Z324: 19.844 | AA324: 228.79 | AB324: 457.246 | AN324: #N/A | AO324: #N/A | AP324: #N/A | AQ324: #N/A | AR324: #N/A | AS324: #N/A | AT324: #N/A | AU324: #N/A | AV324: #N/A | AW324: #N/A | AX324: #N/A | AY324: 0.722 | AZ324: 5.149 | BA324: 33.123 | BB324: 38.994 | BC324: 0.073 | BD324: 0.569 | BE324: 0.041 | BF324: No Data Reported | BG324: 5.641 | BH324: 4.398 | BI324: 0.021 | BJ324: 10.06 | BK324: 10.743 | BL324: 11.485 | BM324: Not Available | BN324: Not Available | BO324: Not Available | BP324: 11.485 | BQ324: 200.422 | BR324: 13.314 | BS324: 0.497 | BT324: 4.281 | BU324: 9.31 | BV324: 25.713 | BW324: 35.023 | BX324: 253.537 | BY324: 108682 | BZ324: 116211 | CA324: 6697 | CB324: 138571 | CC324: 5944 | CG324: =CB324*42/1000 -> 5819.982 | CH324: =CA324*42/1000 -> 281.274 | CI324: =CC324*42/1000 -> 249.648 | CJ324: =BY324*42/1000 -> 4564.644 | CK324: =BZ324*42/1000 -> 4880.862 | CL324: =CD324*42/1000 -> 0
A325: 36465 | P325: 192.219 | Q325: 18.101 | R325: 254.125 | S325: 492.902 | T325: 216.417 | U325: 14.216 | V325: 4.522 | W325: 3.622 | X325: 192.219 | Y325: 43.805 | Z325: 19.651 | AA325: 255.675 | AB325: 494.452 | AN325: #N/A | AO325: #N/A | AP325: #N/A | AQ325: #N/A | AR325: #N/A | AS325: #N/A | AT325: #N/A | AU325: #N/A | AV325: #N/A | AW325: #N/A | AX325: #N/A | AY325: 0.699 | AZ325: 4.223 | BA325: 32.055 | BB325: 36.977 | BC325: 0.078 | BD325: 0.551 | BE325: 0.034 | BF325: No Data Reported | BG325: 5.483 | BH325: 4.352 | BI325: 0.021 | BJ325: 9.856 | BK325: 10.518 | BL325: 11.804 | BM325: Not Available | BN325: Not Available | BO325: Not Available | BP325: 11.804 | BQ325: 213.117 | BR325: 12.63 | BS325: 0.257 | BT325: 3.622 | BU325: 12.389 | BV325: 25.441 | BW325: 37.83 | BX325: 267.456 | BY325: 108241 | BZ325: 108243 | CA325: 7939 | CB325: 141405 | CC325: 5103 | CG325: =CB325*42/1000 -> 5939.01 | CH325: =CA325*42/1000 -> 333.438 | CI325: =CC325*42/1000 -> 214.326 | CJ325: =BY325*42/1000 -> 4546.122 | CK325: =BZ325*42/1000 -> 4546.206 | CL325: =CD325*42/1000 -> 0
A326: 36495 | P326: 171.056 | Q326: 20.99 | R326: 235.215 | S326: 515.274 | T326: 255.344 | U326: 15.328 | V326: 4.232 | W326: 5.155 | X326: 171.056 | Y326: 43.17 | Z326: 22.398 | AA326: 236.623 | AB326: 516.682 | AN326: #N/A | AO326: #N/A | AP326: #N/A | AQ326: #N/A | AR326: #N/A | AS326: #N/A | AT326: #N/A | AU326: #N/A | AV326: #N/A | AW326: #N/A | AX326: #N/A | AY326: 0.722 | AZ326: 4.009 | BA326: 33.123 | BB326: 37.854 | BC326: 0.092 | BD326: 0.569 | BE326: 0.032 | BF326: No Data Reported | BG326: 5.646 | BH326: 4.215 | BI326: 0.024 | BJ326: 9.884 | BK326: 10.577 | BL326: 13.302 | BM326: Not Available | BN326: Not Available | BO326: Not Available | BP326: 13.302 | BQ326: 251.45 | BR326: 13.689 | BS326: 0.183 | BT326: 5.155 | BU326: 9.988 | BV326: 24.639 | BW326: 34.627 | BX326: 305.104 | BY326: 105442 | BZ326: 120641 | CA326: 5840 | CB326: 125463 | CC326: 6583 | CG326: =CB326*42/1000 -> 5269.446 | CH326: =CA326*42/1000 -> 245.28 | CI326: =CC326*42/1000 -> 276.486 | CJ326: =BY326*42/1000 -> 4428.564 | CK326: =BZ326*42/1000 -> 5066.922 | CL326: =CD326*42/1000 -> 0
A327: 36526 | P327: 160.708 | Q327: 19.339 | R327: 222.067 | S327: 505.147 | T327: 258.518 | U327: 14.724 | V327: 3.255 | W327: 6.583 | X327: 160.708 | Y327: 42.021 | Z327: 19.713 | AA327: 222.442 | AB327: 505.522 | AN327: #N/A | AO327: #N/A | AP327: #N/A | AQ327: #N/A | AR327: #N/A | AS327: #N/A | AT327: #N/A | AU327: #N/A | AV327: #N/A | AW327: #N/A | AX327: #N/A | AY327: 0.728 | AZ327: 3.126 | BA327: 35.574 | BB327: 39.428 | BC327: 0.094 | BD327: 0.644 | BE327: 0.03 | BF327: No Data Reported | BG327: 6.025 | BH327: 3.856 | BI327: 0.032 | BJ327: 9.913 | BK327: 10.68 | BL327: 11.348 | BM327: Not Available | BN327: Not Available | BO327: Not Available | BP327: 11.348 | BQ327: 254.545 | BR327: 12.979 | BS327: 0.093 | BT327: 6.583 | BU327: 8.373 | BV327: 25.983 | BW327: 34.356 | BX327: 308.555 | BY327: 96816 | BZ327: 118350 | CA327: 6746 | CB327: 106577 | CC327: 4098 | CG327: =CB327*42/1000 -> 4476.234 | CH327: =CA327*42/1000 -> 283.332 | CI327: =CC327*42/1000 -> 172.116 | CJ327: =BY327*42/1000 -> 4066.272 | CK327: =BZ327*42/1000 -> 4970.7 | CL327: =CD327*42/1000 -> 0
... A338: 36861 | P338: 207.582 | Q338: 21.518 | R338: 254.788 | S338: 477.781 | T338: 200.852 | U338: 14.194 | V338: 4.034 | W338: 3.914 | X338: 207.582 | Y338: 25.688 | Z338: 22.801 | AA338: 256.071 | AB338: 479.064 | AN338: #N/A | AO338: #N/A | AP338: #N/A | AQ338: #N/A | AR338: #N/A | AS338: #N/A | AT338: #N/A | AU338: #N/A | AV338: #N/A | AW338: #N/A | AX338: #N/A | AY338: 0.728 | AZ338: 3.833 | BA338: 35.574 | BB338: 40.135 | BC338: 0.073 | BD338: 0.644 | BE338: 0.036 | BF338: No Data Reported | BG338: 6.068 | BH338: 1.93 | BI338: 0.038 | BJ338: 8.035 | BK338: 8.788 | BL338: 13.483 | BM338: Not Available | BN338: Not Available | BO338: Not Available | BP338: 13.483 | BQ338: 197.766 | BR338: 12.449 | BS338: 0.156 | BT338: 3.914 | BU338: 12.936 | BV338: 13.004 | BW338: 25.94 | BX338: 240.224 | BY338: 120042 | BZ338: 131735 | CA338: 13861 | CB338: 118027 | CC338: 4183 | CG338: =CB338*42/1000 -> 4957.134 | CH338: =CA338*42/1000 -> 582.162 | CI338: =CC338*42/1000 -> 175.686 | CJ338: =BY338*42/1000 -> 5041.764 | CK338: =BZ338*42/1000 -> 5532.87 | CL338: =CD338*42/1000 -> 0
A339: 36892 | B339: 2001 | C339: 0.094 | D339: 0.001 | E339: 17.343 | F339: 0.728 | G339: 0.093 | H339: 2.984 | I339: 3.219 | J339: -0.235 | M339: 17.108 | N339: 0.719 | O339: 0.092 | P339: 175.982 | Q339: 21.638 | R339: 228.434 | S339: 444.966 | T339: 194.798 | U339: 14.612 | V339: 3.1 | W339: 4.022 | X339: 175.982 | Y339: 30.814 | Z339: 23.739 | AA339: 230.534 | AB339: 447.067 | AN339: #N/A | AO339: #N/A | AP339: #N/A | AQ339: #N/A | AR339: #N/A | AS339: #N/A | AT339: #N/A | AU339: #N/A | AV339: #N/A | AW339: #N/A | AX339: #N/A | AY339: 0.803 | AZ339: 2.989 | BA339: 31.425 | BB339: 35.216 | BC339: 0.063 | BD339: 0.702 | BE339: 0.036 | BF339: No Data Reported | BG339: 5.684 | BH339: 2.006 | BI339: 0.033 | BJ339: 7.722 | BK339: 8.524 | BL339: 14.203 | BM339: 0.092 | BN339: Not Available | BO339: Not Available | BP339: 14.294 | BQ339: 192.312 | BR339: 12.703 | BS339: 0.067 | BT339: 4.022 | BU339: 11.569 | BV339: 17.303 | BW339: 28.872 | BX339: 237.976 | BY339: 111869 | BZ339: 134088 | CA339: 24474 | CB339: 118205 | CC339: 2077 | CG339: =CB339*42/1000 -> 4964.61 | CH339: =CA339*42/1000 -> 1027.908 | CI339: =CC339*42/1000 -> 87.234 | CJ339: =BY339*42/1000 -> 4698.498 | CK339: =BZ339*42/1000 -> 5631.696 | CL339: =CD339*42/1000 -> 0
A340: 36923 | B340: 2001 | C340: 0.085 | D340: 0.001 | E340: 15.665 | F340: 0.658 | G340: 0.084 | H340: 1.413 | I340: 5.119 | J340: -3.706 | M340: 11.959 | N340: 0.502 | O340: 0.064 | P340: 155.969 | Q340: 19.67 | R340: 202.849 | S340: 404.064 | T340: 180.547 | U340: 12.812 | V340: 3.399 | W340: 4.456 | X340: 155.969 | Y340: 27.21 | Z340: 20.084 | AA340: 203.263 | AB340: 404.478 | AN340: #N/A | AO340: #N/A | AP340: #N/A | AQ340: #N/A | AR340: #N/A | AS340: #N/A | AT340: #N/A | AU340: #N/A | AV340: #N/A | AW340: #N/A | AX340: #N/A | AY340: 0.725 | AZ340: 3.222 | BA340: 28.384 | BB340: 32.33 | BC340: 0.062 | BD340: 0.634 | BE340: 0.039 | BF340: No Data Reported | BG340: 5.125 | BH340: 1.872 | BI340: 0.027 | BJ340: 7.024 | BK340: 7.759 | BL340: 11.464 | BM340: 0.064 | BN340: Not Available | BO340: Not Available | BP340: 11.528 | BQ340: 178.054 | BR340: 11.088 | BS340: 0.13 | BT340: 4.456 | BU340: 9.491 | BV340: 15.702 | BW340: 25.193 | BX340: 218.921 | BY340: 101146 | BZ340: 117950 | CA340: 17771 | CB340: 117023 | CC340: 2149 | CG340: =CB340*42/1000 -> 4914.966 | CH340: =CA340*42/1000 -> 746.382 | CI340: =CC340*42/1000 -> 90.258 | CJ340: =BY340*42/1000 -> 4248.132 | CK340: =BZ340*42/1000 -> 4953.9 | CL340: =CD340*42/1000 -> 0
A341: 36951 | B341: 2001 | C341: 0.094 | D341: 0.001 | E341: 17.343 | F341: 0.728 | G341: 0.093 | H341: 6.948 | I341: 4.956 | J341: 1.992 | M341: 19.335 | N341: 0.812 | O341: 0.104 | P341: 168.14 | Q341: 21.192 | R341: 219.649 | S341: 455.774 | T341: 211.591 | U341: 14.206 | V341: 4.83 | W341: 5.498 | X341: 168.14 | Y341: 30.317 | Z341: 21.55 | AA341: 220.006 | AB341: 456.131 | AN341: #N/A | AO341: #N/A | AP341: #N/A | AQ341: #N/A | AR341: #N/A | AS341: #N/A | AT341: #N/A | AU341: #N/A | AV341: #N/A | AW341: #N/A | AX341: #N/A | AY341: 0.803 | AZ341: 4.439 | BA341: 31.425 | BB341: 36.666 | BC341: 0.067 | BD341: 0.702 | BE341: 0.054 | BF341: No Data Reported | BG341: 5.691 | BH341: 1.928 | BI341: 0.029 | BJ341: 7.647 | BK341: 8.47 | BL341: 12.232 | BM341: 0.104 | BN341: Not Available | BO341: Not Available | BP341: 12.336 | BQ341: 208.031 | BR341: 12.297 | BS341: 0.325 | BT341: 5.498 | BU341: 10.434 | BV341: 17.563 | BW341: 27.997 | BX341: 254.148 | BY341: 107982 | BZ341: 128438 | CA341: 10787 | CB341: 105021 | CC341: 2333 | CG341: =CB341*42/1000 -> 4410.882 | CH341: =CA341*42/1000 -> 453.054 | CI341: =CC341*42/1000 -> 97.986 | CJ341: =BY341*42/1000 -> 4535.244 | CK341: =BZ341*42/1000 -> 5394.396 | CL341: =CD341*42/1000 -> 0
A342: 36982 | B342: 2001 | C342: 0.091 | D342: 0.001 | E342: 16.784 | F342: 0.705 | G342: 0.09 | H342: 2.156 | I342: 3.893 | J342: -1.736 | M342: 15.047 | N342: 0.632 | O342: 0.081 | P342: 163.973 | Q342: 19.537 | R342: 213.628 | S342: 425.359 | T342: 186.128 | U342: 13.162 | V342: 5.366 | W342: 7.075 | X342: 163.973 | Y342: 30.118 | Z342: 18.71 | AA342: 212.8 | AB342: 424.531 | AN342: #N/A | AO342: #N/A | AP342: #N/A | AQ342: #N/A | AR342: #N/A | AS342: #N/A | AT342: #N/A | AU342: #N/A | AV342: #N/A | AW342: #N/A | AX342: #N/A | AY342: 0.777 | AZ342: 4.893 | BA342: 30.411 | BB342: 36.08 | BC342: 0.075 | BD342: 0.68 | BE342: 0.059 | BF342: No Data Reported | BG342: 5.462 | BH342: 1.955 | BI342: 0.024 | BJ342: 7.441 | BK342: 8.255 | BL342: 10.159 | BM342: 0.081 | BN342: Not Available | BO342: Not Available | BP342: 10.24 | BQ342: 183.129 | BR342: 11.315 | BS342: 0.4 | BT342: 7.075 | BU342: 9.402 | BV342: 17.144 | BW342: 26.546 | BX342: 228.466 | BY342: 109490 | BZ342: 115012 | CA342: 8642 | CB342: 104945 | CC342: 3196 | CG342: =CB342*42/1000 -> 4407.69 | CH342: =CA342*42/1000 -> 362.964 | CI342: =CC342*42/1000 -> 134.232 | CJ342: =BY342*42/1000 -> 4598.58 | CK342: =BZ342*42/1000 -> 4830.504 | CL342: =CD342*42/1000 -> 0
A343: 37012 | B343: 2001 | C343: 0.094 | D343: 0.001 | E343: 17.343 | F343: 0.728 | G343: 0.093 | H343: 1.933 | I343: 2.016 | J343: -0.083 | M343: 17.26 | N343: 0.725 | O343: 0.092 | P343: 161.457 | Q343: 20.222 | R343: 211.506 | S343: 435.509 | T343: 198.142 | U343: 12.98 | V343: 6.319 | W343: 6.562 | X343: 161.457 | Y343: 29.828 | Z343: 19.576 | AA343: 210.861 | AB343: 434.863 | AN343: #N/A | AO343: #N/A | AP343: #N/A | AQ343: #N/A | AR343: #N/A | AS343: #N/A | AT343: #N/A | AU343: #N/A | AV343: #N/A | AW343: #N/A | AX343: #N/A | AY343: 0.803 | AZ343: 5.401 | BA343: 31.425 | BB343: 37.629 | BC343: 0.072 | BD343: 0.702 | BE343: 0.065 | BF343: No Data Reported | BG343: 5.667 | BH343: 2.022 | BI343: 0.025 | BJ343: 7.713 | BK343: 8.554 | BL343: 10.713 | BM343: 0.092 | BN343: Not Available | BO343: Not Available | BP343: 10.806 | BQ343: 195.037 | BR343: 11.071 | BS343: 0.838 | BT343: 6.562 | BU343: 10.083 | BV343: 17.612 | BW343: 27.695 | BX343: 241.202 | BY343: 113219 | BZ343: 116132 | CA343: 9625 | CB343: 107142 | CC343: 4515 | CG343: =CB343*42/1000 -> 4499.964 | CH343: =CA343*42/1000 -> 404.25 | CI343: =CC343*42/1000 -> 189.63 | CJ343: =BY343*42/1000 -> 4755.198 | CK343: =BZ343*42/1000 -> 4877.544 | CL343: =CD343*42/1000 -> 0
A344: 37043 | B344: 2001 | C344: 0.091 | D344: 0.001 | E344: 16.784 | F344: 0.705 | G344: 0.09 | H344: 2.864 | I344: 1.932 | J344: 0.931 | M344: 17.715 | N344: 0.744 | O344: 0.095 | P344: 163.772 | Q344: 20.044 | R344: 213.95 | S344: 454.608 | T344: 214.179 | U344: 13.088 | V344: 6.472 | W344: 6.919 | X344: 163.772 | Y344: 30.134 | Z344: 16.692 | AA344: 210.598 | AB344: 451.256 | AN344: #N/A | AO344: #N/A | AP344: #N/A | AQ344: #N/A | AR344: #N/A | AS344: #N/A | AT344: #N/A | AU344: #N/A | AV344: #N/A | AW344: #N/A | AX344: #N/A | AY344: 0.777 | AZ344: 5.45 | BA344: 30.411 | BB344: 36.638 | BC344: 0.072 | BD344: 0.68 | BE344: 0.066 | BF344: No Data Reported | BG344: 5.493 | BH344: 2.147 | BI344: 0.019 | BJ344: 7.658 | BK344: 8.476 | BL344: 7.958 | BM344: 0.095 | BN344: Not Available | BO344: Not Available | BP344: 8.053 | BQ344: 211.099 | BR344: 11.241 | BS344: 0.942 | BT344: 6.919 | BU344: 11.607 | BV344: 18.076 | BW344: 29.683 | BX344: 259.884 | BY344: 111053 | BZ344: 109764 | CA344: 9059 | CB344: 113877 | CC344: 3613 | CG344: =CB344*42/1000 -> 4782.834 | CH344: =CA344*42/1000 -> 380.478 | CI344: =CC344*42/1000 -> 151.746 | CJ344: =BY344*42/1000 -> 4664.226 | CK344: =BZ344*42/1000 -> 4610.088 | CL344: =CD344*42/1000 -> 0
A345: 37073 | B345: 2001 | C345: 0.094 | D345: 0.001 | E345: 17.343 | F345: 0.728 | G345: 0.093 | H345: 13.066 | I345: 2.204 | J345: 10.862 | M345: 28.205 | N345: 1.185 | O345: 0.151 | P345: 169.421 | Q345: 21.023 | R345: 221.842 | S345: 436.058 | T345: 186.812 | U345: 14.087 | V345: 6.756 | W345: 6.561 | X345: 169.421 | Y345: 31.398 | Z345: 23.398 | AA345: 224.217 | AB345: 438.433 | AN345: #N/A | AO345: #N/A | AP345: #N/A | AQ345: #N/A | AR345: #N/A | AS345: #N/A | AT345: #N/A | AU345: #N/A | AV345: #N/A | AW345: #N/A | AX345: #N/A | AY345: 0.803 | AZ345: 5.721 | BA345: 31.425 | BB345: 37.948 | BC345: 0.055 | BD345: 0.702 | BE345: 0.069 | BF345: No Data Reported | BG345: 5.678 | BH345: 2.272 | BI345: 0.033 | BJ345: 7.982 | BK345: 8.809 | BL345: 14.067 | BM345: 0.151 | BN345: Not Available | BO345: Not Available | BP345: 14.218 | BQ345: 184.258 | BR345: 12.178 | BS345: 0.951 | BT345: 6.561 | BU345: 11.414 | BV345: 18.851 | BW345: 30.265 | BX345: 234.213 | BY345: 118949 | BZ345: 110645 | CA345: 6494 | CB345: 125176 | CC345: 3499 | CG345: =CB345*42/1000 -> 5257.392 | CH345: =CA345*42/1000 -> 272.748 | CI345: =CC345*42/1000 -> 146.958 | CJ345: =BY345*42/1000 -> 4995.858 | CK345: =BZ345*42/1000 -> 4647.09 | CL345: =CD345*42/1000 -> 0
A346: 37104 | B346: 2001 | C346: 0.094 | D346: 0.001 | E346: 17.343 | F346: 0.728 | G346: 0.093 | H346: 2.409 | I346: 3.021 | J346: -0.612 | M346: 16.731 | N346: 0.703 | O346: 0.09 | P346: 173.357 | Q346: 21.283 | R346: 225.897 | S346: 447.894 | T346: 195.436 | U346: 13.97 | V346: 6.627 | W346: 5.964 | X346: 173.357 | Y346: 31.258 | Z346: 18.938 | AA346: 223.552 | AB346: 445.55 | AN346: #N/A | AO346: #N/A | AP346: #N/A | AQ346: #N/A | AR346: #N/A | AS346: #N/A | AT346: #N/A | AU346: #N/A | AV346: #N/A | AW346: #N/A | AX346: #N/A | AY346: 0.803 | AZ346: 5.662 | BA346: 31.425 | BB346: 37.889 | BC346: 0.046 | BD346: 0.702 | BE346: 0.069 | BF346: No Data Reported | BG346: 5.673 | BH346: 2.265 | BI346: 0.023 | BJ346: 7.96 | BK346: 8.777 | BL346: 9.65 | BM346: 0.09 | BN346: Not Available | BO346: Not Available | BP346: 9.739 | BQ346: 192.12 | BR346: 12.061 | BS346: 0.881 | BT346: 5.964 | BU346: 11.432 | BV346: 18.851 | BW346: 30.283 | BX346: 241.31 | BY346: 113289 | BZ346: 118701 | CA346: 6565 | CB346: 122004 | CC346: 4325 | CG346: =CB346*42/1000 -> 5124.168 | CH346: =CA346*42/1000 -> 275.73 | CI346: =CC346*42/1000 -> 181.65 | CJ346: =BY346*42/1000 -> 4758.138 | CK346: =BZ346*42/1000 -> 4985.442 | CL346: =CD346*42/1000 -> 0
A347: 37135 | B347: 2001 | C347: 0.091 | D347: 0.001 | E347: 16.784 | F347: 0.705 | G347: 0.09 | H347: 12.564 | I347: 5.102 | J347: 7.462 | M347: 24.246 | N347: 1.018 | O347: 0.13 | P347: 163.666 | Q347: 21.008 | R347: 214.229 | S347: 396.462 | T347: 157.641 | U347: 13.617 | V347: 5.91 | W347: 5.066 | X347: 163.666 | Y347: 29.555 | Z347: 20.372 | AA347: 213.593 | AB347: 395.826 | AN347: #N/A | AO347: #N/A | AP347: #N/A | AQ347: #N/A | AR347: #N/A | AS347: #N/A | AT347: #N/A | AU347: #N/A | AV347: #N/A | AW347: #N/A | AX347: #N/A | AY347: 0.777 | AZ347: 5.164 | BA347: 30.411 | BB347: 36.352 | BC347: 0.039 | BD347: 0.68 | BE347: 0.063 | BF347: No Data Reported | BG347: 5.486 | BH347: 2.096 | BI347: 0.026 | BJ347: 7.608 | BK347: 8.389 | BL347: 11.128 | BM347: 0.13 | BN347: Not Available | BO347: Not Available | BP347: 11.258 | BQ347: 155.092 | BR347: 11.769 | BS347: 0.67 | BT347: 5.066 | BU347: 10.316 | BV347: 17.445 | BW347: 27.761 | BX347: 200.357 | BY347: 108743 | BZ347: 108720 | CA347: 9511 | CB347: 126991 | CC347: 4547 | CG347: =CB347*42/1000 -> 5333.622 | CH347: =CA347*42/1000 -> 399.462 | CI347: =CC347*42/1000 -> 190.974 | CJ347: =BY347*42/1000 -> 4567.206 | CK347: =BZ347*42/1000 -> 4566.24 | CL347: =CD347*42/1000 -> 0
A348: 37165 | B348: 2001 | C348: 0.094 | D348: 0.001 | E348: 17.343 | F348: 0.728 | G348: 0.093 | H348: 13.315 | I348: 3.283 | J348: 10.031 | M348: 27.375 | N348: 1.15 | O348: 0.147 | P348: 174.181 | Q348: 22.657 | R348: 227.319 | S348: 409.912 | T348: 157.418 | U348: 13.913 | V348: 4.991 | W348: 6.27 | X348: 174.181 | Y348: 30.481 | Z348: 25.014 | AA348: 229.675 | AB348: 412.268 | AN348: #N/A | AO348: #N/A | AP348: #N/A | AQ348: #N/A | AR348: #N/A | AS348: #N/A | AT348: #N/A | AU348: #N/A | AV348: #N/A | AW348: #N/A | AX348: #N/A | AY348: 0.803 | AZ348: 4.706 | BA348: 31.425 | BB348: 36.934 | BC348: 0.039 | BD348: 0.702 | BE348: 0.057 | BF348: No Data Reported | BG348: 5.663 | BH348: 1.97 | BI348: 0.035 | BJ348: 7.668 | BK348: 8.466 | BL348: 14.974 | BM348: 0.147 | BN348: Not Available | BO348: Not Available | BP348: 15.121 | BQ348: 155.248 | BR348: 12.004 | BS348: 0.215 | BT348: 6.27 | BU348: 9.952 | BV348: 17.501 | BW348: 27.453 | BX348: 201.19 | BY348: 117685 | BZ348: 120533 | CA348: 7856 | CB348: 128919 | CC348: 3080 | CG348: =CB348*42/1000 -> 5414.598 | CH348: =CA348*42/1000 -> 329.952 | CI348: =CC348*42/1000 -> 129.36 | CJ348: =BY348*42/1000 -> 4942.77 | CK348: =BZ348*42/1000 -> 5062.386 | CL348: =CD348*42/1000 -> 0
A349: 37196 | B349: 2001 | C349: 0.091 | D349: 0.001 | E349: 16.784 | F349: 0.705 | G349: 0.09 | H349: 19.273 | I349: 3.513 | J349: 15.759 | M349: 32.543 | N349: 1.367 | O349: 0.174 | P349: 166.005 | Q349: 22.961 | R349: 219.773 | S349: 401.766 | T349: 159.262 | U349: 13.805 | V349: 4.065 | W349: 4.861 | X349: 166.005 | Y349: 30.807 | Z349: 22.206 | AA349: 219.018 | AB349: 401.011 | AN349: #N/A | AO349: #N/A | AP349: #N/A | AQ349: #N/A | AR349: #N/A | AS349: #N/A | AT349: #N/A | AU349: #N/A | AV349: #N/A | AW349: #N/A | AX349: #N/A | AY349: 0.777 | AZ349: 3.861 | BA349: 30.411 | BB349: 35.048 | BC349: 0.041 | BD349: 0.68 | BE349: 0.047 | BF349: No Data Reported | BG349: 5.483 | BH349: 1.839 | BI349: 0.028 | BJ349: 7.351 | BK349: 8.118 | BL349: 12.069 | BM349: 0.174 | BN349: Not Available | BO349: Not Available | BP349: 12.243 | BQ349: 157.179 | BR349: 11.957 | BS349: 0.148 | BT349: 4.861 | BU349: 9.901 | BV349: 16.924 | BW349: 26.825 | BX349: 200.97 | BY349: 119039 | BZ349: 112376 | CA349: 7318 | CB349: 138943 | CC349: 3957 | CG349: =CB349*42/1000 -> 5835.606 | CH349: =CA349*42/1000 -> 307.356 | CI349: =CC349*42/1000 -> 166.194 | CJ349: =BY349*42/1000 -> 4999.638 | CK349: =BZ349*42/1000 -> 4719.792 | CL349: =CD349*42/1000 -> 0
A350: 37226 | B350: 2001 | C350: 0.094 | D350: 0.001 | E350: 17.343 | F350: 0.728 | G350: 0.093 | H350: 1.998 | I350: 2.388 | J350: -0.389 | M350: 16.954 | N350: 0.712 | O350: 0.091 | P350: 169.916 | Q350: 23.218 | R350: 225.088 | S350: 449.323 | T350: 199.905 | U350: 14.208 | V350: 3.76 | W350: 6.362 | X350: 169.916 | Y350: 31.954 | Z350: 22.369 | AA350: 224.239 | AB350: 448.475 | AN350: #N/A | AO350: #N/A | AP350: #N/A | AQ350: #N/A | AR350: #N/A | AS350: #N/A | AT350: #N/A | AU350: #N/A | AV350: #N/A | AW350: #N/A | AX350: #N/A | AY350: 0.803 | AZ350: 3.665 | BA350: 31.425 | BB350: 35.892 | BC350: 0.055 | BD350: 0.702 | BE350: 0.044 | BF350: No Data Reported | BG350: 5.686 | BH350: 2.172 | BI350: 0.028 | BJ350: 7.886 | BK350: 8.688 | BL350: 12.205 | BM350: 0.091 | BN350: Not Available | BO350: Not Available | BP350: 12.296 | BQ350: 197.112 | BR350: 12.299 | BS350: 0.042 | BT350: 6.362 | BU350: 10.801 | BV350: 17.764 | BW350: 28.565 | BX350: 244.379 | BY350: 116061 | BZ350: 111724 | CA350: 7484 | CB350: 144513 | CC350: 6251 | CG350: =CB350*42/1000 -> 6069.546 | CH350: =CA350*42/1000 -> 314.328 | CI350: =CC350*42/1000 -> 262.542 | CJ350: =BY350*42/1000 -> 4874.562 | CK350: =BZ350*42/1000 -> 4692.408 | CL350: =CD350*42/1000 -> 0
... A386: 38322 | B386: 2004 | C386: 0.307 | D386: 0.004 | E386: 56.43 | F386: 2.37 | G386: 0.302 | H386: 4.623 | I386: 6.752 | J386: -2.129 | M386: 54.3 | N386: 2.281 | O386: 0.291 | P386: 187.914 | Q386: 43.302 | R386: 264.199 | S386: 557.132 | T386: 262.527 | U386: 15.104 | V386: 3.564 | W386: 11.739 | X386: 187.914 | Y386: 32.983 | Z386: 45 | AA386: 265.897 | AB386: 558.831 | AN386: #N/A | AO386: #N/A | AP386: #N/A | AQ386: #N/A | AR386: #N/A | AS386: #N/A | AT386: #N/A | AU386: #N/A | AV386: #N/A | AW386: #N/A | AX386: #N/A | AY386: 1.186 | AZ386: 3.396 | BA386: 34.727 | BB386: 39.309 | BC386: 0.124 | BD386: 1.016 | BE386: 0.074 | BF386: No Data Reported | BG386: 5.984 | BH386: 2.962 | BI386: 0.069 | BJ386: 9.015 | BK386: 10.229 | BL386: 26.139 | BM386: 0.291 | BN386: Not Available | BO386: Not Available | BP386: 26.43 | BQ386: 258.387 | BR386: 12.58 | BS386: 0.078 | BT386: 11.739 | BU386: 15.679 | BV386: 18.968 | BW386: 34.646 | BX386: 317.43 | BY386: 128929 | BZ386: 129441 | CA386: 9048 | CB386: 126272 | CC386: 5468 | CG386: =CB386*42/1000 -> 5303.424 | CH386: =CA386*42/1000 -> 380.016 | CI386: =CC386*42/1000 -> 229.656 | CJ386: =BY386*42/1000 -> 5415.018 | CK386: =BZ386*42/1000 -> 5436.522 | CL386: =CD386*42/1000 -> 0
A387: 38353 | B387: 2005 | C387: 0.997 | D387: 0.014 | E387: 183.587 | F387: 7.711 | G387: 0.984 | H387: 14.89 | I387: 7.86 | J387: 7.029 | M387: 190.616 | N387: 8.006 | O387: 1.022 | P387: 185.551 | Q387: 45.102 | R387: 264.707 | S387: 537.024 | T387: 242.697 | U387: 15.391 | V387: 2.914 | W387: 11.315 | X387: 185.551 | Y387: 34.054 | Z387: 46.014 | AA387: 265.619 | AB387: 537.936 | AN387: #N/A | AO387: #N/A | AP387: #N/A | AQ387: #N/A | AR387: #N/A | AS387: #N/A | AT387: #N/A | AU387: #N/A | AV387: #N/A | AW387: #N/A | AX387: #N/A | AY387: 1.35 | AZ387: 2.718 | BA387: 36.521 | BB387: 40.589 | BC387: 0.111 | BD387: 1.155 | BE387: 0.09 | BF387: No Data Reported | BG387: 5.945 | BH387: 2.876 | BI387: 0.07 | BJ387: 8.891 | BK387: 10.247 | BL387: 26.134 | BM387: 1.022 | BN387: Not Available | BO387: Not Available | BP387: 27.156 | BQ387: 239.198 | BR387: 12.52 | BS387: 0.087 | BT387: 11.315 | BU387: 15.951 | BV387: 18.358 | BW387: 34.309 | BX387: 297.429 | BY387: 117090 | BZ387: 130904 | CA387: 10958 | CB387: 121895 | CC387: 1521 | CD387: 1299 | CG387: =CB387*42/1000 -> 5119.59 | CH387: =CA387*42/1000 -> 460.236 | CI387: =CC387*42/1000 -> 63.882 | CJ387: =BY387*42/1000 -> 4917.78 | CK387: =BZ387*42/1000 -> 5497.968 | CL387: =CD387*42/1000 -> 54.558
A388: 38384 | B388: 2005 | C388: 0.901 | D388: 0.012 | E388: 165.82 | F388: 6.964 | G388: 0.889 | H388: 33.766 | I388: 7.996 | J388: 25.77 | M388: 191.59 | N388: 8.047 | O388: 1.027 | P388: 175.761 | Q388: 41.376 | R388: 247.271 | S388: 489.382 | T388: 216.046 | U388: 13.222 | V388: 3.179 | W388: 9.664 | X388: 175.761 | Y388: 30.134 | Z388: 41.146 | AA388: 247.041 | AB388: 489.152 | AN388: #N/A | AO388: #N/A | AP388: #N/A | AQ388: #N/A | AR388: #N/A | AS388: #N/A | AT388: #N/A | AU388: #N/A | AV388: #N/A | AW388: #N/A | AX388: #N/A | AY388: 1.22 | AZ388: 2.93 | BA388: 32.986 | BB388: 37.136 | BC388: 0.109 | BD388: 1.043 | BE388: 0.097 | BF388: No Data Reported | BG388: 5.468 | BH388: 2.616 | BI388: 0.061 | BJ388: 8.145 | BK388: 9.394 | BL388: 22.841 | BM388: 1.027 | BN388: Not Available | BO388: Not Available | BP388: 23.867 | BQ388: 213.292 | BR388: 10.629 | BS388: 0.131 | BT388: 9.664 | BU388: 15.149 | BV388: 16.133 | BW388: 31.283 | BX388: 264.998 | BY388: 106324 | BZ388: 117655 | CA388: 9628 | CB388: 117326 | CC388: 2866 | CD388: 657 | CG388: =CB388*42/1000 -> 4927.692 | CH388: =CA388*42/1000 -> 404.376 | CI388: =CC388*42/1000 -> 120.372 | CJ388: =BY388*42/1000 -> 4465.608 | CK388: =BZ388*42/1000 -> 4941.51 | CL388: =CD388*42/1000 -> 27.594
A389: 38412 | B389: 2005 | C389: 0.997 | D389: 0.014 | E389: 183.587 | F389: 7.711 | G389: 0.984 | H389: 12.91 | I389: 25.098 | J389: -12.188 | M389: 171.398 | N389: 7.199 | O389: 0.919 | P389: 180.584 | Q389: 45.51 | R389: 260.043 | S389: 524.478 | T389: 229.338 | U389: 14.912 | V389: 4.581 | W389: 15.605 | X389: 180.584 | Y389: 33.949 | Z389: 44.966 | AA389: 259.499 | AB389: 523.935 | AN389: #N/A | AO389: #N/A | AP389: #N/A | AQ389: #N/A | AR389: #N/A | AS389: #N/A | AT389: #N/A | AU389: #N/A | AV389: #N/A | AW389: #N/A | AX389: #N/A | AY389: 1.35 | AZ389: 4.036 | BA389: 36.521 | BB389: 41.907 | BC389: 0.082 | BD389: 1.155 | BE389: 0.134 | BF389: No Data Reported | BG389: 5.938 | BH389: 2.885 | BI389: 0.067 | BJ389: 8.89 | BK389: 10.261 | BL389: 25.046 | BM389: 0.919 | BN389: Not Available | BO389: Not Available | BP389: 25.965 | BQ389: 226.301 | BR389: 12.041 | BS389: 0.382 | BT389: 15.605 | BU389: 16.045 | BV389: 18.436 | BW389: 34.481 | BX389: 288.81 | BY389: 120087 | BZ389: 134824 | CA389: 7976 | CB389: 105443 | CC389: 5122 | CD389: 385 | CG389: =CB389*42/1000 -> 4428.606 | CH389: =CA389*42/1000 -> 334.992 | CI389: =CC389*42/1000 -> 215.124 | CJ389: =BY389*42/1000 -> 5043.654 | CK389: =BZ389*42/1000 -> 5662.608 | CL389: =CD389*42/1000 -> 16.17
A390: 38443 | B390: 2005 | C390: 0.965 | D390: 0.013 | E390: 177.665 | F390: 7.462 | G390: 0.952 | H390: 17.762 | I390: 17.555 | J390: 0.207 | M390: 177.872 | N390: 7.471 | O390: 0.953 | P390: 171.578 | Q390: 43.143 | R390: 246.929 | S390: 514.322 | T390: 230.561 | U390: 14.648 | V390: 5.212 | W390: 16.973 | X390: 171.578 | Y390: 32.208 | Z390: 42.537 | AA390: 246.323 | AB390: 513.716 | AN390: #N/A | AO390: #N/A | AP390: #N/A | AQ390: #N/A | AR390: #N/A | AS390: #N/A | AT390: #N/A | AU390: #N/A | AV390: #N/A | AW390: #N/A | AX390: #N/A | AY390: 1.307 | AZ390: 4.449 | BA390: 35.342 | BB390: 41.098 | BC390: 0.123 | BD390: 1.118 | BE390: 0.148 | BF390: No Data Reported | BG390: 5.719 | BH390: 2.668 | BI390: 0.063 | BJ390: 8.45 | BK390: 9.839 | BL390: 23.583 | BM390: 0.953 | BN390: Not Available | BO390: Not Available | BP390: 24.536 | BQ390: 227.689 | BR390: 11.87 | BS390: 0.583 | BT390: 16.973 | BU390: 12.713 | BV390: 17.4 | BW390: 30.113 | BX390: 287.228 | BY390: 120841 | BZ390: 123044 | CA390: 7913 | CB390: 105402 | CC390: 5751 | CD390: 371 | CG390: =CB390*42/1000 -> 4426.884 | CH390: =CA390*42/1000 -> 332.346 | CI390: =CC390*42/1000 -> 241.542 | CJ390: =BY390*42/1000 -> 5075.322 | CK390: =BZ390*42/1000 -> 5167.848 | CL390: =CD390*42/1000 -> 15.582
A391: 38473 | B391: 2005 | C391: 0.997 | D391: 0.014 | E391: 183.587 | F391: 7.711 | G391: 0.984 | H391: 7.625 | I391: 10.018 | J391: -2.393 | M391: 181.194 | N391: 7.61 | O391: 0.971 | P391: 176.617 | Q391: 44.487 | R391: 255.79 | S391: 567.445 | T391: 272.758 | U391: 15.513 | V391: 5.922 | W391: 17.463 | X391: 176.617 | Y391: 34.686 | Z391: 45.383 | AA391: 256.686 | AB391: 568.341 | AN391: #N/A | AO391: #N/A | AP391: #N/A | AQ391: #N/A | AR391: #N/A | AS391: #N/A | AT391: #N/A | AU391: #N/A | AV391: #N/A | AW391: #N/A | AX391: #N/A | AY391: 1.35 | AZ391: 4.911 | BA391: 36.521 | BB391: 42.782 | BC391: 0.127 | BD391: 1.155 | BE391: 0.163 | BF391: No Data Reported | BG391: 5.947 | BH391: 2.958 | BI391: 0.069 | BJ391: 8.974 | BK391: 10.419 | BL391: 25.816 | BM391: 0.971 | BN391: Not Available | BO391: Not Available | BP391: 26.787 | BQ391: 270.008 | BR391: 12.642 | BS391: 0.811 | BT391: 17.463 | BU391: 14.158 | BV391: 19.122 | BW391: 33.279 | BX391: 334.203 | BY391: 129555 | BZ391: 125149 | CA391: 8722 | CB391: 112369 | CC391: 6161 | CD391: 538 | CG391: =CB391*42/1000 -> 4719.498 | CH391: =CA391*42/1000 -> 366.324 | CI391: =CC391*42/1000 -> 258.762 | CJ391: =BY391*42/1000 -> 5441.31 | CK391: =BZ391*42/1000 -> 5256.258 | CL391: =CD391*42/1000 -> 22.596
A392: 38504 | B392: 2005 | C392: 0.965 | D392: 0.013 | E392: 177.665 | F392: 7.462 | G392: 0.952 | H392: 21.987 | I392: 10.641 | J392: 11.346 | M392: 189.01 | N392: 7.938 | O392: 1.013 | P392: 173.219 | Q392: 45.082 | R392: 252.466 | S392: 559.535 | T392: 267.803 | U392: 15.257 | V392: 6.041 | W392: 17.967 | X392: 173.219 | Y392: 34.165 | Z392: 47.73 | AA392: 255.114 | AB392: 562.183 | AN392: #N/A | AO392: #N/A | AP392: #N/A | AQ392: #N/A | AR392: #N/A | AS392: #N/A | AT392: #N/A | AU392: #N/A | AV392: #N/A | AW392: #N/A | AX392: #N/A | AY392: 1.307 | AZ392: 4.955 | BA392: 35.342 | BB392: 41.605 | BC392: 0.069 | BD392: 1.118 | BE392: 0.164 | BF392: No Data Reported | BG392: 5.734 | BH392: 3.056 | BI392: 0.075 | BJ392: 8.865 | BK392: 10.216 | BL392: 27.815 | BM392: 1.013 | BN392: Not Available | BO392: Not Available | BP392: 28.828 | BQ392: 264.774 | BR392: 12.479 | BS392: 0.885 | BT392: 17.967 | BU392: 14.99 | BV392: 18.856 | BW392: 33.846 | BX392: 329.952 | BY392: 128228 | BZ392: 121148 | CA392: 7085 | CB392: 119721 | CC392: 6813 | CD392: 889 | CG392: =CB392*42/1000 -> 5028.282 | CH392: =CA392*42/1000 -> 297.57 | CI392: =CC392*42/1000 -> 286.146 | CJ392: =BY392*42/1000 -> 5385.576 | CK392: =BZ392*42/1000 -> 5088.216 | CL392: =CD392*42/1000 -> 37.338
A393: 38534 | B393: 2005 | C393: 0.997 | D393: 0.014 | E393: 183.587 | F393: 7.711 | G393: 0.984 | H393: 10.252 | I393: 25.403 | J393: -15.151 | M393: 168.435 | N393: 7.074 | O393: 0.903 | P393: 182.702 | Q393: 48.33 | R393: 266.332 | S393: 561.815 | T393: 259.542 | U393: 15.596 | V393: 6.136 | W393: 14.208 | X393: 182.702 | Y393: 35.3 | Z393: 49.025 | AA393: 267.028 | AB393: 562.511 | AN393: #N/A | AO393: #N/A | AP393: #N/A | AQ393: #N/A | AR393: #N/A | AS393: #N/A | AT393: #N/A | AU393: #N/A | AV393: #N/A | AW393: #N/A | AX393: #N/A | AY393: 1.35 | AZ393: 5.202 | BA393: 36.521 | BB393: 43.073 | BC393: 0.034 | BD393: 1.155 | BE393: 0.173 | BF393: No Data Reported | BG393: 5.92 | BH393: 3.097 | BI393: 0.075 | BJ393: 9.093 | BK393: 10.455 | BL393: 27.889 | BM393: 0.903 | BN393: Not Available | BO393: Not Available | BP393: 28.792 | BQ393: 256.595 | BR393: 12.726 | BS393: 0.723 | BT393: 14.208 | BU393: 17.093 | BV393: 19.635 | BW393: 36.728 | BX393: 320.98 | BY393: 131329 | BZ393: 119477 | CA393: 7542 | CB393: 133255 | CC393: 5860 | CD393: 670 | CG393: =CB393*42/1000 -> 5596.71 | CH393: =CA393*42/1000 -> 316.764 | CI393: =CC393*42/1000 -> 246.12 | CJ393: =BY393*42/1000 -> 5515.818 | CK393: =BZ393*42/1000 -> 5018.034 | CL393: =CD393*42/1000 -> 28.14
