Workbook

Sheet Forecasts
A1: Corn
A2: CME | B2: Forecast | C2: Low | D2: High | E2: Midpoint | F2: Current | G2: Spread | H2: Full Carry (₵/bu.) | I2: Spread % of Full Carry | J2: Range | K2: Implied Corn Futures | U2: CME Bean/Corn Ratio | V2: Forecast | W2: Low | X2: High | Y2: Midpoint | Z2: Current
A3: 46082 | B3: =AVERAGE(Prices!D666:D668) -> 4.3099657 | C3: =MIN(Prices!C666:C668) -> 3.9885698 | D3: =MAX(Prices!B666:B668) -> 4.6887302 | E3: =AVERAGE(C3:D3) -> 4.33865 | F3: 4.2475 | J3: =D3-C3 -> 0.7001604 | K3: =F3-SUM($H$3:H3) -> 4.2475 | U3: =#REF! -> #REF! | V3: =[1]Forecasts!B3/#REF! -> #REF! | W3: =[1]Forecasts!C3/#REF! -> #REF! | X3: =[1]Forecasts!D3/#REF! -> #REF! | Y3: =[1]Forecasts!E3/#REF! -> #REF! | Z3: =[1]Forecasts!F3/#REF! -> #REF! | AD3: Storage Cost Per Day
A4: 46143 | B4: =AVERAGE(Prices!D669:D670) -> 4.4780109 | C4: =MIN(Prices!C669:C670) -> 4.2073146 | D4: =MAX(Prices!B669:B670) -> 4.9794552 | E4: =AVERAGE(C4:D4) -> 4.5933849 | F4: 4.3225 | G4: =F4-F3 -> 0.075 | H4: =(B4*AE$11/365)+(AE$4*(A4-A3)) -> 0.20212935 | I4: =G4/H4 -> 0.37104952 | J4: =D4-C4 -> 0.77214058 | K4: =F4-SUM($H$3:H4) -> 4.1203706 | U4: =A3 -> 46082 | V4: =[1]Forecasts!B4/B3 -> 2.3260046 | W4: =[1]Forecasts!C4/C3 -> 2.3400977 | X4: =[1]Forecasts!D4/D3 -> 2.2718781 | Y4: =[1]Forecasts!E4/E3 -> 2.3032356 | Z4: =[1]Forecasts!F4/F3 -> 2.4914656 | AD4: Corn | AE4: =0.00165*2 -> 0.0033
A5: 46204 | B5: =AVERAGE(Prices!D671:D672) -> 4.5760431 | C5: =MIN(Prices!C671:C672) -> 4.1672659 | D5: =MAX(Prices!B671:B672) -> 4.9002659 | E5: =AVERAGE(C5:D5) -> 4.5337659 | F5: 4.3825 | G5: =F5-F4 -> 0.06 | H5: =(B5*AE$11/365)+(AE$4*(A5-A4)) -> 0.20214751 | I5: =G5/H5 -> 0.29681296 | J5: =D5-C5 -> 0.733 | K5: =F5-SUM($H$3:H5) -> 3.9782231 | U5: =A4 -> 46143 | V5: =[1]Forecasts!B5/B4 -> 2.2554657 | W5: =[1]Forecasts!C5/C4 -> 2.1561099 | X5: =[1]Forecasts!D5/D4 -> 2.2057255 | Y5: =[1]Forecasts!E5/E4 -> 2.1830028 | Z5: =[1]Forecasts!F5/F4 -> 2.4788895
A6: 46266 | B6: =AVERAGE(Prices!D673:D674) -> 3.7192406 | C6: =MIN(Prices!C673:C674) -> 3.44813 | D6: =MAX(Prices!B673:B674) -> 4.074254 | E6: =AVERAGE(C6:D6) -> 3.761192 | F6: 4.365 | G6: =F6-F5 -> -0.0175 | H6: =(B6*AE$11/365)+(AE$4*(A6-A5)) -> 0.20528882 | I6: =G6/H6 -> -0.085245751 | J6: =D6-C6 -> 0.62612397 | K6: =F6-SUM($H$3:H6) -> 3.7554343 | U6: =A5 -> 46204 | V6: =[1]Forecasts!B6/B5 -> 2.1088088 | W6: =[1]Forecasts!C6/C5 -> 2.0743975 | X6: =[1]Forecasts!D6/D5 -> 2.1829857 | Y6: =[1]Forecasts!E6/E5 -> 2.1330806 | Z6: =[1]Forecasts!F6/F5 -> 2.4386766
A7: 46357 | B7: =AVERAGE(Prices!D675:D677) -> 3.9740538 | C7: =MIN(Prices!C675:C677) -> 3.7284935 | D7: =MAX(Prices!B675:B677) -> 4.2250285 | E7: =AVERAGE(C7:D7) -> 3.976761 | F7: 4.495 | G7: =F7-F6 -> 0.13 | H7: =(B7*AE$11/365)+(AE$4*(A7-A6)) -> 0.30103602 | I7: =G7/H7 -> 0.43184202 | J7: =D7-C7 -> 0.496535 | K7: =F7-SUM($H$3:H7) -> 3.5843983 | U7: =A6 -> 46266 | V7: =[1]Forecasts!B7/B6 -> 2.4332924 | W7: =[1]Forecasts!C7/C6 -> 2.2661202 | X7: =[1]Forecasts!D7/D6 -> 2.4101004 | Y7: =[1]Forecasts!E7/E6 -> 2.3441023 | Z7: =[1]Forecasts!F7/F6 -> 2.4180985
AD9: Interest Rate | AG9: http://www.federalreserve.gov/releases/h15/update/
A10: Matiff | B10: Forecast | C10: Low | D10: High | E10: Midpoint | F10: Current | G10: Spread | H10: Full Carry (₵/bu.) | I10: Spread % of Full Carry | J10: Range | K10: Implied Corn Futures | AB10: =TODAY()-1 -> 46036 | AD10: 12-Month T-Bill | AE10: 0.0476 | AF10: =_xll.RHistory("USD1YFSR=X","NDA_RAW.Nda_last","START:"&$AB10&" INTERVAL:1D") -> #NAME?
A11: 45809 | B11: =MROUND(AVERAGE(Prices!P657:P659),0.25) -> 206.75 | C11: =MROUND(MIN(Prices!O657:O659),0.25) -> 181.75 | D11: =MROUND(MAX(Prices!N657:N659),0.25) -> 216.75 | E11: =AVERAGE(C11:D11) -> 199.25 | F11: {=[2]!cam5?Last} -> #REF! | J11: =D11-C11 -> 35 | K11: =F11-SUM($H$11:H11) -> #VALUE! | AD11: T-Bill + 200 bps | AE11: =AE10+0.02 -> 0.0676
A12: 45870 | B12: =MROUND(AVERAGE(Prices!P660:P661),0.25) -> 204.25 | C12: =MROUND(MIN(Prices!O660:O661),0.25) -> 189.25 | D12: =MROUND(MAX(Prices!N660:N661),0.25) -> 215 | E12: =AVERAGE(C12:D12) -> 202.125 | F12: {=[2]!caq5?Settle} -> #REF! | G12: =F12-F11 -> #VALUE! | H12: =(B12*AE$11/365)+(AE$4*(A12-A11)) -> 0.23912822 | I12: =G12/H12 -> #VALUE! | J12: =D12-C12 -> 25.75 | K12: =F12-SUM($H$12:H12) -> #VALUE!
A13: 45962 | B13: =MROUND(AVERAGE(Prices!P662:P664),0.25) -> 197 | C13: =MROUND(MIN(Prices!O662:O664),0.25) -> 188 | D13: =MROUND(MAX(Prices!N662:N664),0.25) -> 215.25 | E13: =AVERAGE(C13:D13) -> 201.625 | F13: {=[2]!cax5?Settle} -> #REF! | G13: =F13-F12 -> #VALUE! | H13: =(B13*AE$11/365)+(AE$4*(A13-A12)) -> 0.34008548 | I13: =G13/H13 -> #VALUE! | J13: =D13-C13 -> 27.25 | K13: =F13-SUM($H$12:H13) -> #VALUE!
A14: 46082 | B14: =MROUND(AVERAGE(Prices!P666:P668),0.25) -> 196.5 | C14: =MROUND(MIN(Prices!O666:O668),0.25) -> 191 | D14: =MROUND(MAX(Prices!N666:N668),0.25) -> 202.75 | E14: =AVERAGE(C14:D14) -> 196.875 | F14: {=[2]!cah6?Settle} -> #REF! | G14: =F14-F13 -> #VALUE! | H14: =(B14*AE$11/365)+(AE$4*(A14-A13)) -> 0.43239288 | I14: =G14/H14 -> #VALUE! | J14: =D14-C14 -> 11.75 | K14: =F14-SUM($H$12:H14) -> #VALUE!
A15: (€/tonne)
A21: Month | B21: 4
A22: Days | B22: 5
A24: Nearby CME Corn Futures | G24: Nearby Matiff Corn Futures
A25: {=[3]!'@CK5[INTERVAL:DAILY,COMPRESSION:1,SORT:ASC,SPAN:25]?DATE,CLOSE'} -> #REF! | B25: #REF! | C25: =IF(IF(ISNUMBER(A25),MONTH(A25),MONTH(DATEVALUE(A25)))=$B$21,B25/100,"-- ") -> #VALUE! | G25: {=[3]!'CAm25[INTERVAL:DAILY,COMPRESSION:1,SORT:ASC,SPAN:25]?DATE,CLOSE'} -> #REF! | H25: #REF! | I25: =IF(IF(ISNUMBER(G25),MONTH(G25),MONTH(DATEVALUE(G25)))=$B$21,H25,"-- ") -> #VALUE!
A26: #REF! | B26: #REF! | C26: {=IF(IF(ISNUMBER(A26),MONTH(A26),MONTH(DATEVALUE(A26)))=$B$21,B26/100,"-- ")} -> #VALUE! | G26: #REF! | H26: #REF! | I26: =IF(IF(ISNUMBER(G26),MONTH(G26),MONTH(DATEVALUE(G26)))=$B$21,H26,"-- ") -> #VALUE!
A27: #REF! | B27: #REF! | C27: =IF(IF(ISNUMBER(A27),MONTH(A27),MONTH(DATEVALUE(A27)))=$B$21,B27/100,"-- ") -> #VALUE! | G27: #REF! | H27: #REF! | I27: =IF(IF(ISNUMBER(G27),MONTH(G27),MONTH(DATEVALUE(G27)))=$B$21,H27,"-- ") -> #VALUE!
A28: #REF! | B28: #REF! | C28: =IF(IF(ISNUMBER(A28),MONTH(A28),MONTH(DATEVALUE(A28)))=$B$21,B28/100,"-- ") -> #VALUE! | G28: #REF! | H28: #REF! | I28: =IF(IF(ISNUMBER(G28),MONTH(G28),MONTH(DATEVALUE(G28)))=$B$21,H28,"-- ") -> #VALUE!
A29: #REF! | B29: #REF! | C29: {=IF(IF(ISNUMBER(A29),MONTH(A29),MONTH(DATEVALUE(A29)))=$B$21,B29/100,"-- ")} -> #VALUE! | G29: #REF! | H29: #REF! | I29: =IF(IF(ISNUMBER(G29),MONTH(G29),MONTH(DATEVALUE(G29)))=$B$21,H29,"-- ") -> #VALUE!
A30: #REF! | B30: #REF! | C30: {=IF(IF(ISNUMBER(A30),MONTH(A30),MONTH(DATEVALUE(A30)))=$B$21,B30/100,"-- ")} -> #VALUE! | G30: #REF! | H30: #REF! | I30: =IF(IF(ISNUMBER(G30),MONTH(G30),MONTH(DATEVALUE(G30)))=$B$21,H30,"-- ") -> #VALUE!
A31: #REF! | B31: #REF! | C31: {=IF(IF(ISNUMBER(A31),MONTH(A31),MONTH(DATEVALUE(A31)))=$B$21,B31/100,"-- ")} -> #VALUE! | G31: #REF! | H31: #REF! | I31: =IF(IF(ISNUMBER(G31),MONTH(G31),MONTH(DATEVALUE(G31)))=$B$21,H31,"-- ") -> #VALUE!
A32: #REF! | B32: #REF! | C32: =IF(IF(ISNUMBER(A32),MONTH(A32),MONTH(DATEVALUE(A32)))=$B$21,B32/100,"-- ") -> #VALUE! | G32: #REF! | H32: #REF! | I32: =IF(IF(ISNUMBER(G32),MONTH(G32),MONTH(DATEVALUE(G32)))=$B$21,H32,"-- ") -> #VALUE!
A33: #REF! | B33: #REF! | C33: {=IF(IF(ISNUMBER(A33),MONTH(A33),MONTH(DATEVALUE(A33)))=$B$21,B33/100,"-- ")} -> #VALUE! | G33: #REF! | H33: #REF! | I33: =IF(IF(ISNUMBER(G33),MONTH(G33),MONTH(DATEVALUE(G33)))=$B$21,H33,"-- ") -> #VALUE!
A34: #REF! | B34: #REF! | C34: {=IF(IF(ISNUMBER(A34),MONTH(A34),MONTH(DATEVALUE(A34)))=$B$21,B34/100,"-- ")} -> #VALUE! | G34: #REF! | H34: #REF! | I34: =IF(IF(ISNUMBER(G34),MONTH(G34),MONTH(DATEVALUE(G34)))=$B$21,H34,"-- ") -> #VALUE!
A35: #REF! | B35: #REF! | C35: {=IF(IF(ISNUMBER(A35),MONTH(A35),MONTH(DATEVALUE(A35)))=$B$21,B35/100,"-- ")} -> #VALUE! | G35: #REF! | H35: #REF! | I35: =IF(IF(ISNUMBER(G35),MONTH(G35),MONTH(DATEVALUE(G35)))=$B$21,H35,"-- ") -> #VALUE!
A36: #REF! | B36: #REF! | C36: {=IF(IF(ISNUMBER(A36),MONTH(A36),MONTH(DATEVALUE(A36)))=$B$21,B36/100,"-- ")} -> #VALUE! | G36: #REF! | H36: #REF! | I36: =IF(IF(ISNUMBER(G36),MONTH(G36),MONTH(DATEVALUE(G36)))=$B$21,H36,"-- ") -> #VALUE!
A37: #REF! | B37: #REF! | C37: {=IF(IF(ISNUMBER(A37),MONTH(A37),MONTH(DATEVALUE(A37)))=$B$21,B37/100,"-- ")} -> #VALUE! | G37: #REF! | H37: #REF! | I37: =IF(IF(ISNUMBER(G37),MONTH(G37),MONTH(DATEVALUE(G37)))=$B$21,H37,"-- ") -> #VALUE!
A38: #REF! | B38: #REF! | C38: {=IF(IF(ISNUMBER(A38),MONTH(A38),MONTH(DATEVALUE(A38)))=$B$21,B38/100,"-- ")} -> #VALUE! | G38: #REF! | H38: #REF! | I38: =IF(IF(ISNUMBER(G38),MONTH(G38),MONTH(DATEVALUE(G38)))=$B$21,H38,"-- ") -> #VALUE!
A39: #REF! | B39: #REF! | C39: =IF(IF(ISNUMBER(A39),MONTH(A39),MONTH(DATEVALUE(A39)))=$B$21,B39/100,"-- ") -> #VALUE! | G39: #REF! | H39: #REF! | I39: =IF(IF(ISNUMBER(G39),MONTH(G39),MONTH(DATEVALUE(G39)))=$B$21,H39,"-- ") -> #VALUE!
A40: #REF! | B40: #REF! | C40: {=IF(IF(ISNUMBER(A40),MONTH(A40),MONTH(DATEVALUE(A40)))=$B$21,B40/100,"-- ")} -> #VALUE! | G40: #REF! | H40: #REF! | I40: =IF(IF(ISNUMBER(G40),MONTH(G40),MONTH(DATEVALUE(G40)))=$B$21,H40,"-- ") -> #VALUE!
A41: #REF! | B41: #REF! | C41: {=IF(IF(ISNUMBER(A41),MONTH(A41),MONTH(DATEVALUE(A41)))=$B$21,B41/100,"-- ")} -> #VALUE! | G41: #REF! | H41: #REF! | I41: =IF(IF(ISNUMBER(G41),MONTH(G41),MONTH(DATEVALUE(G41)))=$B$21,H41,"-- ") -> #VALUE!
A42: #REF! | B42: #REF! | C42: {=IF(IF(ISNUMBER(A42),MONTH(A42),MONTH(DATEVALUE(A42)))=$B$21,B42/100,"-- ")} -> #VALUE! | G42: #REF! | H42: #REF! | I42: =IF(IF(ISNUMBER(G42),MONTH(G42),MONTH(DATEVALUE(G42)))=$B$21,H42,"-- ") -> #VALUE!
A43: #REF! | B43: #REF! | C43: {=IF(IF(ISNUMBER(A43),MONTH(A43),MONTH(DATEVALUE(A43)))=$B$21,B43/100,"-- ")} -> #VALUE! | G43: #REF! | H43: #REF! | I43: =IF(IF(ISNUMBER(G43),MONTH(G43),MONTH(DATEVALUE(G43)))=$B$21,H43,"-- ") -> #VALUE!
A44: #REF! | B44: #REF! | C44: =IF(IF(ISNUMBER(A44),MONTH(A44),MONTH(DATEVALUE(A44)))=$B$21,B44/100,"-- ") -> #VALUE! | G44: #REF! | H44: #REF! | I44: =IF(IF(ISNUMBER(G44),MONTH(G44),MONTH(DATEVALUE(G44)))=$B$21,H44,"-- ") -> #VALUE!
A45: #REF! | B45: #REF! | C45: {=IF(IF(ISNUMBER(A45),MONTH(A45),MONTH(DATEVALUE(A45)))=$B$21,B45/100,"-- ")} -> #VALUE! | G45: #REF! | H45: #REF! | I45: =IF(IF(ISNUMBER(G45),MONTH(G45),MONTH(DATEVALUE(G45)))=$B$21,H45,"-- ") -> #VALUE!
A46: #REF! | B46: #REF! | C46: {=IF(IF(ISNUMBER(A46),MONTH(A46),MONTH(DATEVALUE(A46)))=$B$21,B46/100,"-- ")} -> #VALUE! | G46: #REF! | H46: #REF! | I46: =IF(IF(ISNUMBER(G46),MONTH(G46),MONTH(DATEVALUE(G46)))=$B$21,H46,"-- ") -> #VALUE!
A47: #REF! | B47: #REF! | C47: =IF(IF(ISNUMBER(A47),MONTH(A47),MONTH(DATEVALUE(A47)))=$B$21,B47/100,"-- ") -> #VALUE! | G47: #REF! | H47: #REF! | I47: =IF(IF(ISNUMBER(G47),MONTH(G47),MONTH(DATEVALUE(G47)))=$B$21,H47,"-- ") -> #VALUE!
A48: #REF! | B48: #REF! | C48: =B48/100 -> #VALUE! | G48: #REF! | H48: #REF! | I48: =IF(IF(ISNUMBER(G48),MONTH(G48),MONTH(DATEVALUE(G48)))=$B$21,H48,"-- ") -> #VALUE!
A49: #REF! | B49: #REF! | C49: =B49/100 -> #VALUE! | G49: #REF! | H49: #REF! | I49: =IF(IF(ISNUMBER(G49),MONTH(G49),MONTH(DATEVALUE(G49)))=$B$21,H49,"-- ") -> #VALUE!
A50: 45782 | B50: 454.25 | C50: =B50/100 -> 4.5425
A51: 45783 | B51: 455.5 | C51: =B51/100 -> 4.555
A52: 45784 | B52: 449.25 | C52: =B52/100 -> 4.4925
A53: 45785 | B53: 447.5 | C53: =B53/100 -> 4.475
A54: 45786 | B54: 449.75 | C54: =B54/100 -> 4.4975
A55: 45789 | B55: 440.25 | C55: =B55/100 -> 4.4025
A56: 45790 | B56: 436 | C56: =B56/100 -> 4.36
A57: 45791 | B57: 438.5 | C57: =B57/100 -> 4.385
A58: 45792 | B58: 448.5 | C58: =B58/100 -> 4.485
A59: 45793 | B59: 443.5 | C59: =B59/100 -> 4.435
A60: 45796 | B60: 447.5 | C60: =B60/100 -> 4.475
A61: 45797 | B61: 454.5 | C61: =B61/100 -> 4.545
... A117: 45876 | B117: 405.88 | C117: =B117/100 -> 4.0588
A164: Average | B164: 402 | C164: =IF(ISNUMBER(C49),(($B$22-COUNT(C25:C48))*C49+SUM(C25:C48))/$B$22,2.25) -> 2.25 | G164: Average | I164: =IF(ISNUMBER(I49),(($B$22-COUNT(I25:I48))*I49+SUM(I25:I48))/$B$22,2.25) -> 2.25
B165: 401.5 | C165: =AVERAGE(C25:C49) -> #VALUE! | I165: =AVERAGE(I25:I49) -> #VALUE!
B166: 405.38 | C166: =COUNTIF(C25:C49,">0") -> 0 | D166: Calculated days so far | I166: 5 | J166: Calculated days so far
C167: 4.59 | D167: Avg price for rest of mth | I167: 215 | J167: Avg price for rest of mth
C168: =AVERAGE(C25:C49) -> #VALUE! | D168: Average to date | I168: =AVERAGE(I25:I49) -> #VALUE! | J168: Average to date
C169: =C166*C168 -> #VALUE! | D169: Sum to date | I169: =I166*I168 -> #VALUE! | J169: Sum to date
C170: =C167*(B22-C166) -> 22.95 | D170: Potential Sum | I170: =I167*(B22-I166) -> 0 | J170: Potential Sum
C171: =(C169+C170)/B22 -> #VALUE! | D171: Projected Average | I171: =(I169+I170)/B22 -> #VALUE! | J171: Projected Average

Sheet Prices
B1: Average Nearby CME Futures | G1: US Average | H1: Central Illinois Basis | I1: Feed Outlook - Central Illinois | J1: Difference | K1: cents per pound | N1: Average Nearby Matiff Futures | T1: Matiff Premium
A2: Month | B2: High | C2: Low | D2: Average | E2: High-Avg | F2: Low-Avg | M2: Month | N2: High | O2: Low | P2: Average | Q2: High-Avg | R2: Low-Avg | S2: $/bu | U2: Month | V2: Year | W2: Euro
A3: 25812 | B3: 1.597 | C3: 1.48 | D3: 1.5245714 | E3: =B3-D3 -> 0.072428571 | F3: =C3-D3 -> -0.044571429 | M3: =A3 -> 25812 | U3: =MONTH(M3) -> 9 | V3: =YEAR(M3) -> 1970
A4: 25842 | B4: 1.555 | C4: 1.435 | D4: 1.4909545 | E4: =B4-D4 -> 0.064045455 | F4: =C4-D4 -> -0.055954545 | M4: =A4 -> 25842 | U4: =MONTH(M4) -> 10 | V4: =YEAR(M4) -> 1970
A5: 25873 | B5: 1.527 | C5: 1.427 | D5: 1.4684211 | E5: =B5-D5 -> 0.058578947 | F5: =C5-D5 -> -0.041421053 | M5: =A5 -> 25873 | U5: =MONTH(M5) -> 11 | V5: =YEAR(M5) -> 1970
A6: 25903 | B6: 1.57 | C6: 1.517 | D6: 1.5455 | E6: =B6-D6 -> 0.0245 | F6: =C6-D6 -> -0.0285 | M6: =A6 -> 25903 | U6: =MONTH(M6) -> 12 | V6: =YEAR(M6) -> 1970
A7: 25934 | B7: 1.577 | C7: 1.525 | D7: 1.56235 | E7: =B7-D7 -> 0.01465 | F7: =C7-D7 -> -0.03735 | M7: =A7 -> 25934 | U7: =MONTH(M7) -> 1 | V7: =YEAR(M7) -> 1971
A8: 25965 | B8: 1.547 | C8: 1.49 | D8: 1.5208947 | E8: =B8-D8 -> 0.026105263 | F8: =C8-D8 -> -0.030894737 | M8: =A8 -> 25965 | U8: =MONTH(M8) -> 2 | V8: =YEAR(M8) -> 1971
A9: 25993 | B9: 1.552 | C9: 1.455 | D9: 1.5127391 | E9: =B9-D9 -> 0.03926087 | F9: =C9-D9 -> -0.05773913 | M9: =A9 -> 25993 | U9: =MONTH(M9) -> 3 | V9: =YEAR(M9) -> 1971
A10: 26024 | B10: 1.5 | C10: 1.402 | D10: 1.4585238 | E10: =B10-D10 -> 0.04147619 | F10: =C10-D10 -> -0.05652381 | M10: =A10 -> 26024 | U10: =MONTH(M10) -> 4 | V10: =YEAR(M10) -> 1971
A11: 26054 | B11: 1.502 | C11: 1.422 | D11: 1.45245 | E11: =B11-D11 -> 0.04955 | F11: =C11-D11 -> -0.03045 | M11: =A11 -> 26054 | U11: =MONTH(M11) -> 5 | V11: =YEAR(M11) -> 1971
A12: 26085 | B12: 1.607 | C12: 1.482 | D12: 1.5495 | E12: =B12-D12 -> 0.0575 | F12: =C12-D12 -> -0.0675 | M12: =A12 -> 26085 | U12: =MONTH(M12) -> 6 | V12: =YEAR(M12) -> 1971
A13: 26115 | B13: 1.53 | C13: 1.317 | D13: 1.4282857 | E13: =B13-D13 -> 0.10171429 | F13: =C13-D13 -> -0.11128571 | M13: =A13 -> 26115 | U13: =MONTH(M13) -> 7 | V13: =YEAR(M13) -> 1971
A14: 26146 | B14: 1.33 | C14: 1.172 | D14: 1.2385455 | E14: =B14-D14 -> 0.091454545 | F14: =C14-D14 -> -0.066545455 | M14: =A14 -> 26146 | U14: =MONTH(M14) -> 8 | V14: =YEAR(M14) -> 1971
... A62: 27607 | B62: 3.307 | C62: 2.865 | D62: 3.1157619 | E62: =B62-D62 -> 0.1912381 | F62: =C62-D62 -> -0.2507619 | M62: =A62 -> 27607 | U62: =MONTH(M62) -> 8 | V62: =YEAR(M62) -> 1975
A63: 27638 | B63: 3.195 | C63: 2.87 | D63: 3.0145714 | E63: =B63-D63 -> 0.18042857 | F63: =C63-D63 -> -0.14457143 | G63: 3 | K63: =G63/56*100 -> 5.3571429 | M63: =A63 -> 27638 | U63: =MONTH(M63) -> 9 | V63: =YEAR(M63) -> 1975
A64: 27668 | B64: 3.077 | C64: 2.735 | D64: 2.9046522 | E64: =B64-D64 -> 0.17234783 | F64: =C64-D64 -> -0.16965217 | G64: 2.52 | K64: =G64/56*100 -> 4.5 | M64: =A64 -> 27668 | U64: =MONTH(M64) -> 10 | V64: =YEAR(M64) -> 1975
A65: 27699 | B65: 2.785 | C65: 2.572 | D65: 2.6895263 | E65: =B65-D65 -> 0.095473684 | F65: =C65-D65 -> -0.11752632 | G65: 2.4 | K65: =G65/56*100 -> 4.2857143 | M65: =A65 -> 27699 | U65: =MONTH(M65) -> 11 | V65: =YEAR(M65) -> 1975
A66: 27729 | B66: 2.84 | C66: 2.565 | D66: 2.6787619 | E66: =B66-D66 -> 0.1612381 | F66: =C66-D66 -> -0.1137619 | G66: 2.46 | K66: =G66/56*100 -> 4.3928571 | M66: =A66 -> 27729 | U66: =MONTH(M66) -> 12 | V66: =YEAR(M66) -> 1975
A67: 27760 | B67: 2.74 | C67: 2.585 | D67: 2.6748095 | E67: =B67-D67 -> 0.065190476 | F67: =C67-D67 -> -0.089809524 | G67: 2.46 | K67: =G67/56*100 -> 4.3928571 | M67: =A67 -> 27760 | U67: =MONTH(M67) -> 1 | V67: =YEAR(M67) -> 1976
A68: 27791 | B68: 2.74 | C68: 2.652 | D68: 2.6859474 | E68: =B68-D68 -> 0.054052632 | F68: =C68-D68 -> -0.033947368 | G68: 2.53 | K68: =G68/56*100 -> 4.5178571 | M68: =A68 -> 27791 | U68: =MONTH(M68) -> 2 | V68: =YEAR(M68) -> 1976
A69: 27820 | B69: 2.785 | C69: 2.65 | D69: 2.7155652 | E69: =B69-D69 -> 0.069434783 | F69: =C69-D69 -> -0.065565217 | G69: 2.54 | K69: =G69/56*100 -> 4.5357143 | M69: =A69 -> 27820 | U69: =MONTH(M69) -> 3 | V69: =YEAR(M69) -> 1976
A70: 27851 | B70: 2.727 | C70: 2.637 | D70: 2.6705714 | E70: =B70-D70 -> 0.056428571 | F70: =C70-D70 -> -0.033571429 | G70: 2.52 | K70: =G70/56*100 -> 4.5 | M70: =A70 -> 27851 | U70: =MONTH(M70) -> 4 | V70: =YEAR(M70) -> 1976
A71: 27881 | B71: 2.97 | C71: 2.74 | D71: 2.8352 | E71: =B71-D71 -> 0.1348 | F71: =C71-D71 -> -0.0952 | G71: 2.65 | K71: =G71/56*100 -> 4.7321429 | M71: =A71 -> 27881 | U71: =MONTH(M71) -> 5 | V71: =YEAR(M71) -> 1976
A72: 27912 | B72: 3.145 | C72: 2.865 | D72: 2.9794545 | E72: =B72-D72 -> 0.16554545 | F72: =C72-D72 -> -0.11445455 | G72: 2.78 | K72: =G72/56*100 -> 4.9642857 | M72: =A72 -> 27912 | U72: =MONTH(M72) -> 6 | V72: =YEAR(M72) -> 1976
A73: 27942 | B73: 3.067 | C73: 2.78 | D73: 2.9162857 | E73: =B73-D73 -> 0.15071429 | F73: =C73-D73 -> -0.13628571 | G73: 2.81 | K73: =G73/56*100 -> 5.0178571 | M73: =A73 -> 27942 | U73: =MONTH(M73) -> 7 | V73: =YEAR(M73) -> 1976
A74: 27973 | B74: 2.85 | C74: 2.722 | D74: 2.7855909 | E74: =B74-D74 -> 0.064409091 | F74: =C74-D74 -> -0.063590909 | G74: 2.67 | K74: =G74/56*100 -> 4.7678571 | M74: =A74 -> 27973 | U74: =MONTH(M74) -> 8 | V74: =YEAR(M74) -> 1976
... A305: 35004 | B305: 3.39 | C305: 3.195 | D305: 3.2796667 | E305: =B305-D305 -> 0.11033333 | F305: =C305-D305 -> -0.084666667 | G305: 3.22 | K305: =G305/56*100 -> 5.75 | M305: =A305 -> 35004 | U305: =MONTH(M305) -> 11 | V305: =YEAR(M305) -> 1995
A306: 35034 | B306: 3.705 | C306: 3.355 | D306: 3.5035 | E306: =B306-D306 -> 0.2015 | F306: =C306-D306 -> -0.1485 | G306: 3.36 | H306: =G306-D306 -> -0.1435 | K306: =G306/56*100 -> 6 | M306: =A306 -> 35034 | U306: =MONTH(M306) -> 12 | V306: =YEAR(M306) -> 1995
A307: 35065 | B307: 3.752 | C307: 3.475 | D307: 3.6224545 | E307: =B307-D307 -> 0.12954545 | F307: =C307-D307 -> -0.14745455 | G307: 3.53 | H307: =G307-D307 -> -0.092454545 | K307: =G307/56*100 -> 6.3035714 | M307: =A307 -> 35065 | U307: =MONTH(M307) -> 1 | V307: =YEAR(M307) -> 1996
A308: 35096 | B308: 3.955 | C308: 3.585 | D308: 3.74335 | E308: =B308-D308 -> 0.21165 | F308: =C308-D308 -> -0.15835 | G308: 3.71 | H308: =G308-D308 -> -0.03335 | K308: =G308/56*100 -> 6.625 | M308: =A308 -> 35096 | U308: =MONTH(M308) -> 2 | V308: =YEAR(M308) -> 1996
A309: 35125 | B309: 4.105 | C309: 3.775 | D309: 3.8947619 | E309: =B309-D309 -> 0.2102381 | F309: =C309-D309 -> -0.1197619 | G309: 3.92 | H309: =G309-D309 -> 0.025238095 | K309: =G309/56*100 -> 7 | M309: =A309 -> 35125 | U309: =MONTH(M309) -> 3 | V309: =YEAR(M309) -> 1996
A310: 35156 | B310: 5.09 | C310: 4.09 | D310: 4.5415714 | E310: =B310-D310 -> 0.54842857 | F310: =C310-D310 -> -0.45157143 | G310: 4.47 | H310: =G310-D310 -> -0.071571429 | K310: =G310/56*100 -> 7.9821429 | M310: =A310 -> 35156 | U310: =MONTH(M310) -> 4 | V310: =YEAR(M310) -> 1996
A311: 35186 | B311: 5.135 | C311: 4.46 | D311: 4.8061818 | E311: =B311-D311 -> 0.32881818 | F311: =C311-D311 -> -0.34618182 | G311: 4.86 | H311: =G311-D311 -> 0.053818182 | K311: =G311/56*100 -> 8.6785714 | M311: =A311 -> 35186 | U311: =MONTH(M311) -> 5 | V311: =YEAR(M311) -> 1996
A312: 35217 | B312: 5.185 | C312: 4.292 | D312: 4.6872 | E312: =B312-D312 -> 0.4978 | F312: =C312-D312 -> -0.3952 | G312: 4.74 | H312: =G312-D312 -> 0.0528 | K312: =G312/56*100 -> 8.4642857 | M312: =A312 -> 35217 | U312: =MONTH(M312) -> 6 | V312: =YEAR(M312) -> 1996
A313: 35247 | B313: 4.38 | C313: 3.472 | D313: 3.8617273 | E313: =B313-D313 -> 0.51827273 | F313: =C313-D313 -> -0.38972727 | G313: 4.7 | H313: =G313-D313 -> 0.83827273 | K313: =G313/56*100 -> 8.3928571 | M313: =A313 -> 35247 | U313: =MONTH(M313) -> 7 | V313: =YEAR(M313) -> 1996
A314: 35278 | B314: 3.89 | C314: 3.412 | D314: 3.6434545 | E314: =B314-D314 -> 0.24654545 | F314: =C314-D314 -> -0.23145455 | G314: 4.48 | H314: =G314-D314 -> 0.83654545 | K314: =G314/56*100 -> 8 | M314: =A314 -> 35278 | U314: =MONTH(M314) -> 8 | V314: =YEAR(M314) -> 1996
A315: 35309 | B315: 3.46 | C315: 2.94 | D315: 3.19965 | E315: =B315-D315 -> 0.26035 | F315: =C315-D315 -> -0.25965 | G315: 3.39 | H315: =G315-D315 -> 0.19035 | K315: =G315/56*100 -> 6.0535714 | M315: =A315 -> 35309 | U315: =MONTH(M315) -> 9 | V315: =YEAR(M315) -> 1996
A316: 35339 | B316: 3.005 | C316: 2.655 | D316: 2.8376957 | E316: =B316-D316 -> 0.16730435 | F316: =C316-D316 -> -0.18269565 | G316: 2.81 | H316: =G316-D316 -> -0.027695652 | K316: =G316/56*100 -> 5.0178571 | M316: =A316 -> 35339 | U316: =MONTH(M316) -> 10 | V316: =YEAR(M316) -> 1996
A317: 35370 | B317: 2.775 | C317: 2.577 | D317: 2.6803 | E317: =B317-D317 -> 0.0947 | F317: =C317-D317 -> -0.1033 | G317: 2.63 | H317: =G317-D317 -> -0.0503 | K317: =G317/56*100 -> 4.6964286 | M317: =A317 -> 35370 | U317: =MONTH(M317) -> 11 | V317: =YEAR(M317) -> 1996
... A354: 36495 | B354: 2.067 | C354: 1.952 | D354: 2.0166667 | E354: =B354-D354 -> 0.050333333 | F354: =C354-D354 -> -0.064666667 | G354: 1.84 | H354: =G354-D354 -> -0.17666667 | K354: =G354/56*100 -> 3.2857143 | M354: =A354 -> 36495 | U354: =MONTH(M354) -> 12 | V354: =YEAR(M354) -> 1999
A355: 36526 | B355: 2.282 | C355: 2.005 | D355: 2.15965 | E355: =B355-D355 -> 0.12235 | F355: =C355-D355 -> -0.15465 | G355: 1.95 | H355: =G355-D355 -> -0.20965 | K355: =G355/56*100 -> 3.4821429 | M355: =A355 -> 36526 | N355: =_xlfn.MAXIFS(Sheet1!$B$2:$B$6350,Sheet1!$E$2:$E$6350,Prices!$U355,Sheet1!$F$2:$F$6350,Prices!$V355) -> 133 | O355: =_xlfn.MINIFS(Sheet1!$B$2:$B$6350,Sheet1!$E$2:$E$6350,Prices!$U355,Sheet1!$F$2:$F$6350,Prices!$V355) -> 132 | P355: =AVERAGEIFS(Sheet1!$B$2:$B$6350,Sheet1!$E$2:$E$6350,Prices!$U355,Sheet1!$F$2:$F$6350,Prices!$V355) -> 132.425 | Q355: =N355-P355 -> 0.575 | R355: =O355-P355 -> -0.425 | S355: =P355/39.3679/W355 -> 3.3215451 | T355: =S355-D355 -> 1.1618951 | U355: =MONTH(M355) -> 1 | V355: =YEAR(M355) -> 2000 | W355: 1.0127158
A356: 36557 | B356: 2.265 | C356: 2.115 | D356: 2.19635 | E356: =B356-D356 -> 0.06865 | F356: =C356-D356 -> -0.08135 | G356: 2.03 | H356: =G356-D356 -> -0.16635 | K356: =G356/56*100 -> 3.625 | M356: =A356 -> 36557 | N356: =_xlfn.MAXIFS(Sheet1!$B$2:$B$6350,Sheet1!$E$2:$E$6350,Prices!$U356,Sheet1!$F$2:$F$6350,Prices!$V356) -> 135.75 | O356: =_xlfn.MINIFS(Sheet1!$B$2:$B$6350,Sheet1!$E$2:$E$6350,Prices!$U356,Sheet1!$F$2:$F$6350,Prices!$V356) -> 135 | P356: =AVERAGEIFS(Sheet1!$B$2:$B$6350,Sheet1!$E$2:$E$6350,Prices!$U356,Sheet1!$F$2:$F$6350,Prices!$V356) -> 135.5625 | Q356: =N356-P356 -> 0.1875 | R356: =O356-P356 -> -0.5625 | S356: =P356/39.3679/W356 -> 3.4990429 | T356: =S356-D356 -> 1.3026929 | U356: =MONTH(M356) -> 2 | V356: =YEAR(M356) -> 2000 | W356: 0.98412
A357: 36586 | B357: 2.417 | C357: 2.22 | D357: 2.3066087 | E357: =B357-D357 -> 0.1103913 | F357: =C357-D357 -> -0.086608696 | G357: 2.08 | H357: =G357-D357 -> -0.2266087 | K357: =G357/56*100 -> 3.7142857 | M357: =A357 -> 36586 | N357: =_xlfn.MAXIFS(Sheet1!$B$2:$B$6350,Sheet1!$E$2:$E$6350,Prices!$U357,Sheet1!$F$2:$F$6350,Prices!$V357) -> 138 | O357: =_xlfn.MINIFS(Sheet1!$B$2:$B$6350,Sheet1!$E$2:$E$6350,Prices!$U357,Sheet1!$F$2:$F$6350,Prices!$V357) -> 136.25 | P357: =AVERAGEIFS(Sheet1!$B$2:$B$6350,Sheet1!$E$2:$E$6350,Prices!$U357,Sheet1!$F$2:$F$6350,Prices!$V357) -> 136.90217 | Q357: =N357-P357 -> 1.0978261 | R357: =O357-P357 -> -0.65217391 | S357: =P357/39.3679/W357 -> 3.6044306 | T357: =S357-D357 -> 1.2978219 | U357: =MONTH(M357) -> 3 | V357: =YEAR(M357) -> 2000 | W357: 0.96478696
A358: 36617 | B358: 2.395 | C358: 2.225 | D358: 2.2745263 | E358: =B358-D358 -> 0.12047368 | F358: =C358-D358 -> -0.049526316 | G358: 2.09 | H358: =G358-D358 -> -0.18452632 | K358: =G358/56*100 -> 3.7321429 | M358: =A358 -> 36617 | N358: =_xlfn.MAXIFS(Sheet1!$B$2:$B$6350,Sheet1!$E$2:$E$6350,Prices!$U358,Sheet1!$F$2:$F$6350,Prices!$V358) -> 139 | O358: =_xlfn.MINIFS(Sheet1!$B$2:$B$6350,Sheet1!$E$2:$E$6350,Prices!$U358,Sheet1!$F$2:$F$6350,Prices!$V358) -> 137.75 | P358: =AVERAGEIFS(Sheet1!$B$2:$B$6350,Sheet1!$E$2:$E$6350,Prices!$U358,Sheet1!$F$2:$F$6350,Prices!$V358) -> 138.13889 | Q358: =N358-P358 -> 0.86111111 | R358: =O358-P358 -> -0.38888889 | S358: =P358/39.3679/W358 -> 3.7113053 | T358: =S358-D358 -> 1.436779 | U358: =MONTH(M358) -> 4 | V358: =YEAR(M358) -> 2000 | W358: 0.94546842
A359: 36647 | B359: 2.582 | C359: 2.225 | D359: 2.3948636 | E359: =B359-D359 -> 0.18713636 | F359: =C359-D359 -> -0.16986364 | G359: 2.15 | H359: =G359-D359 -> -0.24486364 | K359: =G359/56*100 -> 3.8392857 | M359: =A359 -> 36647 | N359: =_xlfn.MAXIFS(Sheet1!$B$2:$B$6350,Sheet1!$E$2:$E$6350,Prices!$U359,Sheet1!$F$2:$F$6350,Prices!$V359) -> 141.75 | O359: =_xlfn.MINIFS(Sheet1!$B$2:$B$6350,Sheet1!$E$2:$E$6350,Prices!$U359,Sheet1!$F$2:$F$6350,Prices!$V359) -> 138 | P359: =AVERAGEIFS(Sheet1!$B$2:$B$6350,Sheet1!$E$2:$E$6350,Prices!$U359,Sheet1!$F$2:$F$6350,Prices!$V359) -> 140.34524 | Q359: =N359-P359 -> 1.4047619 | R359: =O359-P359 -> -2.3452381 | S359: =P359/39.3679/W359 -> 3.9287114 | T359: =S359-D359 -> 1.5338478 | U359: =MONTH(M359) -> 5 | V359: =YEAR(M359) -> 2000 | W359: 0.90741364
A360: 36678 | B360: 2.327 | C360: 1.865 | D360: 2.0788636 | E360: =B360-D360 -> 0.24813636 | F360: =C360-D360 -> -0.21386364 | G360: 1.83 | H360: =G360-D360 -> -0.24886364 | K360: =G360/56*100 -> 3.2678571 | M360: =A360 -> 36678 | N360: =_xlfn.MAXIFS(Sheet1!$B$2:$B$6350,Sheet1!$E$2:$E$6350,Prices!$U360,Sheet1!$F$2:$F$6350,Prices!$V360) -> 141.75 | O360: =_xlfn.MINIFS(Sheet1!$B$2:$B$6350,Sheet1!$E$2:$E$6350,Prices!$U360,Sheet1!$F$2:$F$6350,Prices!$V360) -> 138 | P360: =AVERAGEIFS(Sheet1!$B$2:$B$6350,Sheet1!$E$2:$E$6350,Prices!$U360,Sheet1!$F$2:$F$6350,Prices!$V360) -> 139.60714 | Q360: =N360-P360 -> 2.1428571 | R360: =O360-P360 -> -1.6071429 | S360: =P360/39.3679/W360 -> 3.7341829 | T360: =S360-D360 -> 1.6553192 | U360: =MONTH(M360) -> 6 | V360: =YEAR(M360) -> 2000 | W360: 0.94966364
A361: 36708 | B361: 1.97 | C361: 1.77 | D361: 1.8465 | E361: =B361-D361 -> 0.1235 | F361: =C361-D361 -> -0.0765 | G361: 1.53 | H361: =G361-D361 -> -0.3165 | K361: =G361/56*100 -> 2.7321429 | M361: =A361 -> 36708 | N361: =_xlfn.MAXIFS(Sheet1!$B$2:$B$6350,Sheet1!$E$2:$E$6350,Prices!$U361,Sheet1!$F$2:$F$6350,Prices!$V361) -> 164.5 | O361: =_xlfn.MINIFS(Sheet1!$B$2:$B$6350,Sheet1!$E$2:$E$6350,Prices!$U361,Sheet1!$F$2:$F$6350,Prices!$V361) -> 143 | P361: =AVERAGEIFS(Sheet1!$B$2:$B$6350,Sheet1!$E$2:$E$6350,Prices!$U361,Sheet1!$F$2:$F$6350,Prices!$V361) -> 150.8125 | Q361: =N361-P361 -> 13.6875 | R361: =O361-P361 -> -7.8125 | S361: =P361/39.3679/W361 -> 4.0806028 | T361: =S361-D361 -> 2.2341028 | U361: =MONTH(M361) -> 7 | V361: =YEAR(M361) -> 2000 | W361: 0.938795
A362: 36739 | B362: 1.85 | C362: 1.74 | D362: 1.7826522 | E362: =B362-D362 -> 0.067347826 | F362: =C362-D362 -> -0.042652174 | G362: 1.49 | H362: =G362-D362 -> -0.29265217 | K362: =G362/56*100 -> 2.6607143 | M362: =A362 -> 36739 | N362: =_xlfn.MAXIFS(Sheet1!$B$2:$B$6350,Sheet1!$E$2:$E$6350,Prices!$U362,Sheet1!$F$2:$F$6350,Prices!$V362) -> 166 | O362: =_xlfn.MINIFS(Sheet1!$B$2:$B$6350,Sheet1!$E$2:$E$6350,Prices!$U362,Sheet1!$F$2:$F$6350,Prices!$V362) -> 121.75 | P362: =AVERAGEIFS(Sheet1!$B$2:$B$6350,Sheet1!$E$2:$E$6350,Prices!$U362,Sheet1!$F$2:$F$6350,Prices!$V362) -> 131.9 | Q362: =N362-P362 -> 34.1 | R362: =O362-P362 -> -10.15 | S362: =P362/39.3679/W362 -> 3.7054964 | T362: =S362-D362 -> 1.9228442 | U362: =MONTH(M362) -> 8 | V362: =YEAR(M362) -> 2000 | W362: 0.90418261
A363: 36770 | B363: 1.997 | C363: 1.867 | D363: 1.92925 | E363: =B363-D363 -> 0.06775 | F363: =C363-D363 -> -0.06225 | G363: 1.58 | H363: =G363-D363 -> -0.34925 | K363: =G363/56*100 -> 2.8214286 | M363: =A363 -> 36770 | N363: =_xlfn.MAXIFS(Sheet1!$B$2:$B$6350,Sheet1!$E$2:$E$6350,Prices!$U363,Sheet1!$F$2:$F$6350,Prices!$V363) -> 123.25 | O363: =_xlfn.MINIFS(Sheet1!$B$2:$B$6350,Sheet1!$E$2:$E$6350,Prices!$U363,Sheet1!$F$2:$F$6350,Prices!$V363) -> 121.75 | P363: =AVERAGEIFS(Sheet1!$B$2:$B$6350,Sheet1!$E$2:$E$6350,Prices!$U363,Sheet1!$F$2:$F$6350,Prices!$V363) -> 122.625 | Q363: =N363-P363 -> 0.625 | R363: =O363-P363 -> -0.875 | S363: =P363/39.3679/W363 -> 3.582817 | T363: =S363-D363 -> 1.653567 | U363: =MONTH(M363) -> 9 | V363: =YEAR(M363) -> 2000 | W363: 0.869385
A364: 36800 | B364: 2.11 | C364: 1.967 | D364: 2.0414545 | E364: =B364-D364 -> 0.068545455 | F364: =C364-D364 -> -0.074454545 | G364: 1.81 | H364: =G364-D364 -> -0.23145455 | K364: =G364/56*100 -> 3.2321429 | M364: =A364 -> 36800 | N364: =_xlfn.MAXIFS(Sheet1!$B$2:$B$6350,Sheet1!$E$2:$E$6350,Prices!$U364,Sheet1!$F$2:$F$6350,Prices!$V364) -> 125.25 | O364: =_xlfn.MINIFS(Sheet1!$B$2:$B$6350,Sheet1!$E$2:$E$6350,Prices!$U364,Sheet1!$F$2:$F$6350,Prices!$V364) -> 123.25 | P364: =AVERAGEIFS(Sheet1!$B$2:$B$6350,Sheet1!$E$2:$E$6350,Prices!$U364,Sheet1!$F$2:$F$6350,Prices!$V364) -> 124.07955 | Q364: =N364-P364 -> 1.1704545 | R364: =O364-P364 -> -0.82954545 | S364: =P364/39.3679/W364 -> 3.6939884 | T364: =S364-D364 -> 1.6525339 | U364: =MONTH(M364) -> 10 | V364: =YEAR(M364) -> 2000 | W364: 0.85322273
A365: 36831 | B365: 2.165 | C365: 2.042 | D365: 2.106381 | E365: =B365-D365 -> 0.058619048 | F365: =C365-D365 -> -0.064380952 | G365: 1.96 | H365: =G365-D365 -> -0.14638095 | K365: =G365/56*100 -> 3.5 | M365: =A365 -> 36831 | N365: =_xlfn.MAXIFS(Sheet1!$B$2:$B$6350,Sheet1!$E$2:$E$6350,Prices!$U365,Sheet1!$F$2:$F$6350,Prices!$V365) -> 134.5 | O365: =_xlfn.MINIFS(Sheet1!$B$2:$B$6350,Sheet1!$E$2:$E$6350,Prices!$U365,Sheet1!$F$2:$F$6350,Prices!$V365) -> 124 | P365: =AVERAGEIFS(Sheet1!$B$2:$B$6350,Sheet1!$E$2:$E$6350,Prices!$U365,Sheet1!$F$2:$F$6350,Prices!$V365) -> 130.34091 | Q365: =N365-P365 -> 4.1590909 | R365: =O365-P365 -> -6.3409091 | S365: =P365/39.3679/W365 -> 3.8672686 | T365: =S365-D365 -> 1.7608877 | U365: =MONTH(M365) -> 11 | V365: =YEAR(M365) -> 2000 | W365: 0.85611905
A366: 36861 | B366: 2.32 | C366: 2.142 | D366: 2.22265 | E366: =B366-D366 -> 0.09735 | F366: =C366-D366 -> -0.08065 | G366: 2.01 | H366: =G366-D366 -> -0.21265 | K366: =G366/56*100 -> 3.5892857 | M366: =A366 -> 36861 | N366: =_xlfn.MAXIFS(Sheet1!$B$2:$B$6350,Sheet1!$E$2:$E$6350,Prices!$U366,Sheet1!$F$2:$F$6350,Prices!$V366) -> 134.75 | O366: =_xlfn.MINIFS(Sheet1!$B$2:$B$6350,Sheet1!$E$2:$E$6350,Prices!$U366,Sheet1!$F$2:$F$6350,Prices!$V366) -> 132 | P366: =AVERAGEIFS(Sheet1!$B$2:$B$6350,Sheet1!$E$2:$E$6350,Prices!$U366,Sheet1!$F$2:$F$6350,Prices!$V366) -> 133.52632 | Q366: =N366-P366 -> 1.2236842 | R366: =O366-P366 -> -1.5263158 | S366: =P366/39.3679/W366 -> 3.7685551 | T366: =S366-D366 -> 1.5459051 | U366: =MONTH(M366) -> 12 | V366: =YEAR(M366) -> 2000 | W366: 0.900015
... A578: 43313 | B578: 3.7125 | C578: 3.41 | D578: 3.5833696 | E578: =B578-D578 -> 0.12913043 | F578: =C578-D578 -> -0.17336957 | G578: 3.36 | H578: =G578-D578 -> -0.22336957 | K578: =G578/56*100 -> 6 | M578: =A578 -> 43313 | N578: =_xlfn.MAXIFS(Sheet1!$B$2:$B$6350,Sheet1!$E$2:$E$6350,Prices!$U578,Sheet1!$F$2:$F$6350,Prices!$V578) -> 200 | O578: =_xlfn.MINIFS(Sheet1!$B$2:$B$6350,Sheet1!$E$2:$E$6350,Prices!$U578,Sheet1!$F$2:$F$6350,Prices!$V578) -> 179.75 | P578: =AVERAGEIFS(Sheet1!$B$2:$B$6350,Sheet1!$E$2:$E$6350,Prices!$U578,Sheet1!$F$2:$F$6350,Prices!$V578) -> 188.45652 | Q578: =N578-P578 -> 11.543478 | R578: =O578-P578 -> -8.7065217 | S578: =P578/39.3679/W578 -> 4.1461239 | T578: =S578-D578 -> 0.56275433 | U578: =MONTH(M578) -> 8 | V578: =YEAR(M578) -> 2018 | W578: 1.154587
A579: 43344 | B579: 3.6825 | C579: 3.4325 | D579: 3.5844737 | E579: =B579-D579 -> 0.098026316 | F579: =C579-D579 -> -0.15197368 | G579: 3.4 | H579: =G579-D579 -> -0.18447368 | I579: 3.12 | J579: =G579-I579 -> 0.28 | K579: =G579/56*100 -> 6.0714286 | M579: =A579 -> 43344 | N579: =_xlfn.MAXIFS(Sheet1!$B$2:$B$6350,Sheet1!$E$2:$E$6350,Prices!$U579,Sheet1!$F$2:$F$6350,Prices!$V579) -> 181.5 | O579: =_xlfn.MINIFS(Sheet1!$B$2:$B$6350,Sheet1!$E$2:$E$6350,Prices!$U579,Sheet1!$F$2:$F$6350,Prices!$V579) -> 174.5 | P579: =AVERAGEIFS(Sheet1!$B$2:$B$6350,Sheet1!$E$2:$E$6350,Prices!$U579,Sheet1!$F$2:$F$6350,Prices!$V579) -> 177.5125 | Q579: =N579-P579 -> 3.9875 | R579: =O579-P579 -> -3.0125 | S579: =P579/39.3679/W579 -> 3.866688 | T579: =S579-D579 -> 0.28221436 | U579: =MONTH(M579) -> 9 | V579: =YEAR(M579) -> 2018 | W579: 1.1661316
A580: 43374 | B580: 3.7825 | C580: 3.61 | D580: 3.6815217 | E580: =B580-D580 -> 0.10097826 | F580: =C580-D580 -> -0.071521739 | G580: 3.42 | H580: =G580-D580 -> -0.26152174 | I580: 3.28 | J580: =G580-I580 -> 0.14 | K580: =G580/56*100 -> 6.1071429 | M580: =A580 -> 43374 | N580: =_xlfn.MAXIFS(Sheet1!$B$2:$B$6350,Sheet1!$E$2:$E$6350,Prices!$U580,Sheet1!$F$2:$F$6350,Prices!$V580) -> 174.75 | O580: =_xlfn.MINIFS(Sheet1!$B$2:$B$6350,Sheet1!$E$2:$E$6350,Prices!$U580,Sheet1!$F$2:$F$6350,Prices!$V580) -> 166 | P580: =AVERAGEIFS(Sheet1!$B$2:$B$6350,Sheet1!$E$2:$E$6350,Prices!$U580,Sheet1!$F$2:$F$6350,Prices!$V580) -> 170.86957 | Q580: =N580-P580 -> 3.8804348 | R580: =O580-P580 -> -4.8695652 | S580: =P580/39.3679/W580 -> 3.7810162 | T580: =S580-D580 -> 0.099494477 | U580: =MONTH(M580) -> 10 | V580: =YEAR(M580) -> 2018 | W580: 1.1479261
A581: 43405 | B581: 3.74 | C581: 3.3625 | D581: 3.6160714 | E581: =B581-D581 -> 0.12392857 | F581: =C581-D581 -> -0.25357143 | G581: 3.41 | H581: =G581-D581 -> -0.20607143 | I581: 3.36 | J581: =G581-I581 -> 0.05 | K581: =G581/56*100 -> 6.0892857 | M581: =A581 -> 43405 | N581: =_xlfn.MAXIFS(Sheet1!$B$2:$B$6350,Sheet1!$E$2:$E$6350,Prices!$U581,Sheet1!$F$2:$F$6350,Prices!$V581) -> 177.25 | O581: =_xlfn.MINIFS(Sheet1!$B$2:$B$6350,Sheet1!$E$2:$E$6350,Prices!$U581,Sheet1!$F$2:$F$6350,Prices!$V581) -> 167.25 | P581: =AVERAGEIFS(Sheet1!$B$2:$B$6350,Sheet1!$E$2:$E$6350,Prices!$U581,Sheet1!$F$2:$F$6350,Prices!$V581) -> 174.69318 | Q581: =N581-P581 -> 2.5568182 | R581: =O581-P581 -> -7.4431818 | S581: =P581/39.3679/W581 -> 3.9066666 | T581: =S581-D581 -> 0.29059519 | U581: =MONTH(M581) -> 11 | V581: =YEAR(M581) -> 2018 | W581: 1.1358667
A582: 43435 | B582: 3.855 | C582: 3.7325 | D582: 3.811625 | E582: =B582-D582 -> 0.043375 | F582: =C582-D582 -> -0.079125 | G582: 3.54 | H582: =G582-D582 -> -0.271625 | I582: 3.53 | J582: =G582-I582 -> 0.01 | K582: =G582/56*100 -> 6.3214286 | M582: =A582 -> 43435 | N582: =_xlfn.MAXIFS(Sheet1!$B$2:$B$6350,Sheet1!$E$2:$E$6350,Prices!$U582,Sheet1!$F$2:$F$6350,Prices!$V582) -> 180.25 | O582: =_xlfn.MINIFS(Sheet1!$B$2:$B$6350,Sheet1!$E$2:$E$6350,Prices!$U582,Sheet1!$F$2:$F$6350,Prices!$V582) -> 175.5 | P582: =AVERAGEIFS(Sheet1!$B$2:$B$6350,Sheet1!$E$2:$E$6350,Prices!$U582,Sheet1!$F$2:$F$6350,Prices!$V582) -> 178.02632 | Q582: =N582-P582 -> 2.2236842 | R582: =O582-P582 -> -2.5263158 | S582: =P582/39.3679/W582 -> 3.9759783 | T582: =S582-D582 -> 0.1643533 | U582: =MONTH(M582) -> 12 | V582: =YEAR(M582) -> 2018 | W582: 1.13736
A583: 43466 | B583: 3.83 | C583: 3.7125 | D583: 3.7869048 | E583: =B583-D583 -> 0.043095238 | F583: =C583-D583 -> -0.074404762 | G583: 3.56 | H583: =G583-D583 -> -0.22690476 | I583: 3.53 | J583: =G583-I583 -> 0.03 | K583: =G583/56*100 -> 6.3571429 | M583: =A583 -> 43466 | N583: =_xlfn.MAXIFS(Sheet1!$B$2:$B$6350,Sheet1!$E$2:$E$6350,Prices!$U583,Sheet1!$F$2:$F$6350,Prices!$V583) -> 182.75 | O583: =_xlfn.MINIFS(Sheet1!$B$2:$B$6350,Sheet1!$E$2:$E$6350,Prices!$U583,Sheet1!$F$2:$F$6350,Prices!$V583) -> 177.75 | P583: =AVERAGEIFS(Sheet1!$B$2:$B$6350,Sheet1!$E$2:$E$6350,Prices!$U583,Sheet1!$F$2:$F$6350,Prices!$V583) -> 180.65909 | Q583: =N583-P583 -> 2.0909091 | R583: =O583-P583 -> -2.9090909 | S583: =P583/39.3679/W583 -> 4.018267 | T583: =S583-D583 -> 0.23136224 | U583: =MONTH(M583) -> 1 | V583: =YEAR(M583) -> 2019 | W583: 1.1420333
A584: 43497 | B584: 3.8075 | C584: 3.6375 | D584: 3.7444444 | E584: =B584-D584 -> 0.063055556 | F584: =C584-D584 -> -0.10694444 | G584: 3.6 | H584: =G584-D584 -> -0.14444444 | I584: 3.5 | J584: =G584-I584 -> 0.1 | K584: =G584/56*100 -> 6.4285714 | M584: =A584 -> 43497 | N584: =_xlfn.MAXIFS(Sheet1!$B$2:$B$6350,Sheet1!$E$2:$E$6350,Prices!$U584,Sheet1!$F$2:$F$6350,Prices!$V584) -> 177 | O584: =_xlfn.MINIFS(Sheet1!$B$2:$B$6350,Sheet1!$E$2:$E$6350,Prices!$U584,Sheet1!$F$2:$F$6350,Prices!$V584) -> 164.25 | P584: =AVERAGEIFS(Sheet1!$B$2:$B$6350,Sheet1!$E$2:$E$6350,Prices!$U584,Sheet1!$F$2:$F$6350,Prices!$V584) -> 173.85 | Q584: =N584-P584 -> 3.15 | R584: =O584-P584 -> -9.6 | S584: =P584/39.3679/W584 -> 3.8920746 | T584: =S584-D584 -> 0.1476302 | U584: =MONTH(M584) -> 2 | V584: =YEAR(M584) -> 2019 | W584: 1.1346222
A585: 43525 | B585: 3.7975 | C585: 3.565 | D585: 3.7110714 | E585: =B585-D585 -> 0.086428571 | F585: =C585-D585 -> -0.14607143 | G585: 3.61 | H585: =G585-D585 -> -0.10107143 | I585: 3.43 | J585: =G585-I585 -> 0.18 | K585: =G585/56*100 -> 6.4464286 | M585: =A585 -> 43525 | N585: =_xlfn.MAXIFS(Sheet1!$B$2:$B$6350,Sheet1!$E$2:$E$6350,Prices!$U585,Sheet1!$F$2:$F$6350,Prices!$V585) -> 171 | O585: =_xlfn.MINIFS(Sheet1!$B$2:$B$6350,Sheet1!$E$2:$E$6350,Prices!$U585,Sheet1!$F$2:$F$6350,Prices!$V585) -> 157.75 | P585: =AVERAGEIFS(Sheet1!$B$2:$B$6350,Sheet1!$E$2:$E$6350,Prices!$U585,Sheet1!$F$2:$F$6350,Prices!$V585) -> 168.2619 | Q585: =N585-P585 -> 2.7380952 | R585: =O585-P585 -> -10.511905 | S585: =P585/39.3679/W585 -> 3.7827303 | T585: =S585-D585 -> 0.071658833 | U585: =MONTH(M585) -> 3 | V585: =YEAR(M585) -> 2019 | W585: 1.1298952
A586: 43556 | B586: 3.6525 | C586: 3.4675 | D586: 3.5770238 | E586: =B586-D586 -> 0.07547619 | F586: =C586-D586 -> -0.10952381 | G586: 3.53 | H586: =G586-D586 -> -0.04702381 | I586: 3.37 | J586: =G586-I586 -> 0.16 | K586: =G586/56*100 -> 6.3035714 | M586: =A586 -> 43556 | N586: =_xlfn.MAXIFS(Sheet1!$B$2:$B$6350,Sheet1!$E$2:$E$6350,Prices!$U586,Sheet1!$F$2:$F$6350,Prices!$V586) -> 170.5 | O586: =_xlfn.MINIFS(Sheet1!$B$2:$B$6350,Sheet1!$E$2:$E$6350,Prices!$U586,Sheet1!$F$2:$F$6350,Prices!$V586) -> 164 | P586: =AVERAGEIFS(Sheet1!$B$2:$B$6350,Sheet1!$E$2:$E$6350,Prices!$U586,Sheet1!$F$2:$F$6350,Prices!$V586) -> 167.2875 | Q586: =N586-P586 -> 3.2125 | R586: =O586-P586 -> -3.2875 | S586: =P586/39.3679/W586 -> 3.7836753 | T586: =S586-D586 -> 0.20665152 | U586: =MONTH(M586) -> 4 | V586: =YEAR(M586) -> 2019 | W586: 1.1230714
A587: 43586 | B587: 4.3625 | C587: 3.5175 | D587: 3.8367045 | E587: =B587-D587 -> 0.52579545 | F587: =C587-D587 -> -0.31920455 | G587: 3.63 | H587: =G587-D587 -> -0.20670455 | I587: 3.59 | J587: =G587-I587 -> 0.04 | K587: =G587/56*100 -> 6.4821429 | M587: =A587 -> 43586 | N587: =_xlfn.MAXIFS(Sheet1!$B$2:$B$6350,Sheet1!$E$2:$E$6350,Prices!$U587,Sheet1!$F$2:$F$6350,Prices!$V587) -> 166.75 | O587: =_xlfn.MINIFS(Sheet1!$B$2:$B$6350,Sheet1!$E$2:$E$6350,Prices!$U587,Sheet1!$F$2:$F$6350,Prices!$V587) -> 161.75 | P587: =AVERAGEIFS(Sheet1!$B$2:$B$6350,Sheet1!$E$2:$E$6350,Prices!$U587,Sheet1!$F$2:$F$6350,Prices!$V587) -> 164.09091 | Q587: =N587-P587 -> 2.6590909 | R587: =O587-P587 -> -2.3409091 | S587: =P587/39.3679/W587 -> 3.7275592 | T587: =S587-D587 -> -0.10914534 | U587: =MONTH(M587) -> 5 | V587: =YEAR(M587) -> 2019 | W587: 1.1181955
A588: 43617 | B588: 4.5475 | C588: 4.1475 | D588: 4.35225 | E588: =B588-D588 -> 0.19525 | F588: =C588-D588 -> -0.20475 | G588: 3.98 | H588: =G588-D588 -> -0.37225 | I588: 4.21 | J588: =G588-I588 -> -0.23 | K588: =G588/56*100 -> 7.1071429 | M588: =A588 -> 43617 | N588: =_xlfn.MAXIFS(Sheet1!$B$2:$B$6350,Sheet1!$E$2:$E$6350,Prices!$U588,Sheet1!$F$2:$F$6350,Prices!$V588) -> 178.5 | O588: =_xlfn.MINIFS(Sheet1!$B$2:$B$6350,Sheet1!$E$2:$E$6350,Prices!$U588,Sheet1!$F$2:$F$6350,Prices!$V588) -> 165 | P588: =AVERAGEIFS(Sheet1!$B$2:$B$6350,Sheet1!$E$2:$E$6350,Prices!$U588,Sheet1!$F$2:$F$6350,Prices!$V588) -> 175.0125 | Q588: =N588-P588 -> 3.4875 | R588: =O588-P588 -> -10.0125 | S588: =P588/39.3679/W588 -> 3.9362345 | T588: =S588-D588 -> -0.41601554 | U588: =MONTH(M588) -> 6 | V588: =YEAR(M588) -> 2019 | W588: 1.129395
A589: 43647 | B589: 4.5425 | C589: 4.0025 | D589: 4.2801136 | E589: =B589-D589 -> 0.26238636 | F589: =C589-D589 -> -0.27761364 | G589: 4.16 | H589: =G589-D589 -> -0.12011364 | I589: 4.29 | J589: =G589-I589 -> -0.13 | K589: =G589/56*100 -> 7.4285714 | M589: =A589 -> 43647 | N589: =_xlfn.MAXIFS(Sheet1!$B$2:$B$6350,Sheet1!$E$2:$E$6350,Prices!$U589,Sheet1!$F$2:$F$6350,Prices!$V589) -> 180.75 | O589: =_xlfn.MINIFS(Sheet1!$B$2:$B$6350,Sheet1!$E$2:$E$6350,Prices!$U589,Sheet1!$F$2:$F$6350,Prices!$V589) -> 170 | P589: =AVERAGEIFS(Sheet1!$B$2:$B$6350,Sheet1!$E$2:$E$6350,Prices!$U589,Sheet1!$F$2:$F$6350,Prices!$V589) -> 177.56522 | Q589: =N589-P589 -> 3.1847826 | R589: =O589-P589 -> -7.5652174 | S589: =P589/39.3679/W589 -> 4.0241759 | T589: =S589-D589 -> -0.25593771 | U589: =MONTH(M589) -> 7 | V589: =YEAR(M589) -> 2019 | W589: 1.1208273
A590: 43678 | B590: 4.2425 | C590: 3.6425 | D590: 3.7710714 | E590: =B590-D590 -> 0.47142857 | F590: =C590-D590 -> -0.12857143 | G590: 3.93 | H590: =G590-D590 -> 0.15892857 | I590: 3.945 | J590: =G590-I590 -> -0.015 | K590: =G590/56*100 -> 7.0178571 | M590: =A590 -> 43678 | N590: =_xlfn.MAXIFS(Sheet1!$B$2:$B$6350,Sheet1!$E$2:$E$6350,Prices!$U590,Sheet1!$F$2:$F$6350,Prices!$V590) -> 172.75 | O590: =_xlfn.MINIFS(Sheet1!$B$2:$B$6350,Sheet1!$E$2:$E$6350,Prices!$U590,Sheet1!$F$2:$F$6350,Prices!$V590) -> 158 | P590: =AVERAGEIFS(Sheet1!$B$2:$B$6350,Sheet1!$E$2:$E$6350,Prices!$U590,Sheet1!$F$2:$F$6350,Prices!$V590) -> 166.31818 | Q590: =N590-P590 -> 6.4318182 | R590: =O590-P590 -> -8.3181818 | S590: =P590/39.3679/W590 -> 3.7987699 | T590: =S590-D590 -> 0.027698476 | U590: =MONTH(M590) -> 8 | V590: =YEAR(M590) -> 2019 | W590: 1.1121273
... A651: 45536 | B651: 4.2475 | C651: 4.0175 | D651: 4.10725 | E651: =B651-D651 -> 0.14025 | F651: =C651-D651 -> -0.08975 | G651: 3.97 | H651: =G651-D651 -> -0.13725 | I651: 3.8634 | J651: =G651-I651 -> 0.1066 | K651: =G651/56*100 -> 7.0892857 | M651: =A651 -> 45536 | N651: =_xlfn.MAXIFS(Sheet1!$B$2:$B$6350,Sheet1!$E$2:$E$6350,Prices!$U651,Sheet1!$F$2:$F$6350,Prices!$V651) -> 202.25 | O651: =_xlfn.MINIFS(Sheet1!$B$2:$B$6350,Sheet1!$E$2:$E$6350,Prices!$U651,Sheet1!$F$2:$F$6350,Prices!$V651) -> 200.75 | P651: =AVERAGEIFS(Sheet1!$B$2:$B$6350,Sheet1!$E$2:$E$6350,Prices!$U651,Sheet1!$F$2:$F$6350,Prices!$V651) -> 201.5 | Q651: =N651-P651 -> 0.75 | R651: =O651-P651 -> -0.75 | S651: =P651/39.3679/W651 -> 4.7392438 | T651: =S651-D651 -> 0.63199375 | U651: =MONTH(M651) -> 9 | V651: =YEAR(M651) -> 2024 | W651: 1.08
A652: 45566 | B652: 4.325 | C652: 4.0125 | D652: 4.1611957 | E652: =B652-D652 -> 0.16380435 | F652: =C652-D652 -> -0.14869565 | G652: 3.99 | H652: =G652-D652 -> -0.17119565 | I652: 3.9015 | J652: =G652-I652 -> 0.0885 | K652: =G652/56*100 -> 7.125 | M652: =A652 -> 45566 | N652: 216.25 | O652: 198.25 | P652: 211.58696 | Q652: =N652-P652 -> 4.6630435 | R652: =O652-P652 -> -13.336957 | S652: =P652/39.3679/W652 -> 4.9764872 | T652: =S652-D652 -> 0.8152915 | U652: =MONTH(M652) -> 10 | V652: =YEAR(M652) -> 2024 | W652: 1.08
A653: 45597 | B653: 4.31 | C653: 4.145 | D653: 4.242375 | E653: =B653-D653 -> 0.067625 | F653: =C653-D653 -> -0.097375 | G653: 4.07 | H653: =G653-D653 -> -0.172375 | I653: 4.1895 | J653: =G653-I653 -> -0.1195 | K653: =G653/56*100 -> 7.2678571 | M653: =A653 -> 45597 | N653: 212.25 | O653: 195 | P653: 207.99 | Q653: =N653-P653 -> 4.26 | R653: =O653-P653 -> -12.99 | S653: =P653/39.3679/W653 -> 4.8918874 | T653: =S653-D653 -> 0.64951238 | U653: =MONTH(M653) -> 11 | V653: =YEAR(M653) -> 2024 | W653: 1.08
A654: 45627 | B654: 4.585 | C654: 4.22 | D654: 4.39 | E654: =B654-D654 -> 0.195 | F654: =C654-D654 -> -0.17 | G654: 4.23 | H654: =G654-D654 -> -0.16 | I654: 4.3974 | J654: =G654-I654 -> -0.1674 | K654: =G654/56*100 -> 7.5535714 | M654: =A654 -> 45627 | N654: 209.75 | O654: 203 | P654: 206.65 | Q654: =N654-P654 -> 3.1 | R654: =O654-P654 -> -3.65 | S654: =P654/39.3679/W654 -> 4.8603708 | T654: =S654-D654 -> 0.47037082 | U654: =MONTH(M654) -> 12 | V654: =YEAR(M654) -> 2024 | W654: 1.08
A655: 45658 | B655: 4.97 | C655: 4.5075 | D655: 4.7533333 | E655: =B655-D655 -> 0.21666667 | F655: =C655-D655 -> -0.24583333 | G655: 4.29 | H655: =G655-D655 -> -0.46333333 | I655: 4.6788 | J655: =G655-I655 -> -0.3888 | K655: =G655/56*100 -> 7.6607143 | M655: =A655 -> 45658 | N655: 217 | O655: 209.75 | P655: 213.75 | Q655: =N655-P655 -> 3.25 | R655: =O655-P655 -> -4 | S655: =P655/39.3679/W655 -> 5.0273615 | T655: =S655-D655 -> 0.27402821 | U655: =MONTH(M655) -> 1 | V655: =YEAR(M655) -> 2025 | W655: 1.08
A656: 45689 | B656: 5.02 | C656: 4.535 | D656: 4.8748684 | E656: =B656-D656 -> 0.14513158 | F656: =C656-D656 -> -0.33986842 | G656: 4.58 | H656: =G656-D656 -> -0.29486842 | I656: 4.7888 | J656: =G656-I656 -> -0.2088 | K656: =G656/56*100 -> 8.1785714 | M656: =A656 -> 45689 | N656: 230.98 | O656: 221.66 | P656: 225.1555 | Q656: =AVERAGE(Q644,Q632,Q620,Q608,Q596,Q584,Q572,Q560,Q548,Q536)+5 -> 14.205417 | R656: =AVERAGE(R644,R632,R620,R608,R596,R584,R572,R560,R548,R536) -> -6.1945833 | S656: =P656/39.3679/W656 -> 5.2956169 | T656: =S656-D656 -> 0.42074843 | U656: =MONTH(M656) -> 2 | V656: =YEAR(M656) -> 2025 | W656: 1.08 | Z656: Month | AA656: Year | AD656: Average | AE656: Month | AF656: Year
A657: 45717 | B657: 4.69 | C657: 4.36 | D657: 4.5458333 | E657: =B657-D657 -> 0.14416667 | F657: =C657-D657 -> -0.18583333 | G657: 4.57 | H657: =G657-D657 -> 0.024166667 | I657: 4.4503 | J657: =G657-I657 -> 0.1197 | K657: =G657/56*100 -> 8.1607143 | M657: =A657 -> 45717 | N657: 216.75 | O657: 181.75 | P657: 211.04762 | Q657: =AVERAGE(Q645,Q633,Q621,Q609,Q597,Q585,Q573,Q561,Q549,Q537)+5 -> 16.062072 | R657: =AVERAGE(R645,R633,R621,R609,R597,R585,R573,R561,R549,R537) -> -12.362928 | S657: =P657/39.3679/W657 -> 4.963802 | T657: =S657-D657 -> 0.4179687 | U657: =MONTH(M657) -> 3 | V657: =YEAR(M657) -> 2025 | W657: 1.08 | X657: {=[3]!'@ch5[INTERVAL:DAILY,COMPRESSION:1,SORT:ASC,NDATE:1/10/2024,FDATE:1/11/2025,VERSION:1]?DATE,CLOSE'} -> #REF! | Y657: #REF! | Z657: =MONTH(X657) -> #VALUE! | AA657: =YEAR(X657) -> #VALUE! | AC657: 45536 | AD657: =AVERAGEIFS(Y657:Y737,Z657:Z737,AE657,AA657:AA737,AF657)/100 -> #DIV/0! | AE657: 10 | AF657: =YEAR(AC657) -> 2024
A658: 45748 | B658: 4.9025 | C658: 4.575 | D658: 4.728875 | E658: =B658-D658 -> 0.173625 | F658: =C658-D658 -> -0.153875 | G658: 4.62 | H658: =G658-D658 -> -0.108875 | I658: 4.6839 | J658: =G658-I658 -> -0.0639 | K658: =G658/56*100 -> 8.25 | M658: =A658 -> 45748 | N658: 213 | O658: 199.5 | P658: 206.45 | Q658: =AVERAGE(Q646,Q634,Q622,Q610,Q598,Q586,Q574,Q562,Q550,Q538)+5 -> 12.953575 | R658: =AVERAGE(R646,R634,R622,R610,R598,R586,R574,R562,R550,R538) -> -6.7964254 | S658: =P658/39.3679/W658 -> 4.8556669 | T658: =S658-D658 -> 0.12679186 | U658: =MONTH(M658) -> 4 | V658: =YEAR(M658) -> 2025 | W658: 1.08 | X658: #REF! | Y658: #REF! | Z658: =MONTH(X658) -> #VALUE! | AA658: =YEAR(X658) -> #VALUE! | AC658: 45444 | AD658: =AVERAGEIFS(Y657:Y737,Z657:Z737,AE658,AA657:AA737,AF658)/100 -> #DIV/0! | AE658: =MONTH(AC658) -> 6 | AF658: =YEAR(AC658) -> 2024
A659: 45778 | B659: 5 | C659: 5 | D659: 4.6 | E659: =B659-D659 -> 0.4 | F659: =C659-D659 -> 0.4 | G659: 4.64 | H659: =G659-D659 -> 0.04 | I659: 4.5018 | J659: =G659-I659 -> 0.1382 | K659: =G659/56*100 -> 8.2857143 | M659: =A659 -> 45778 | N659: =P659+Q659 -> 201.80357 | O659: =P659+R659 -> 205.20357 | P659: =P658+AVERAGE(P647-P646,P635-P634,P623-P622,P611-P610,P599-P598,P587-P586,P575-P574,P563-P562,P551-P550,P539-P538)-9 -> 202.56521 | Q659: =AVERAGE(Q647,Q635,Q623,Q611,Q599,Q587,Q575,Q563,Q551,Q539)-8 -> -0.76163961 | R659: =AVERAGE(R647,R635,R623,R611,R599,R587,R575,R563,R551,R539)+10 -> 2.6383604 | S659: =P659/39.3679/W659 -> 4.7642974 | T659: =S659-D659 -> 0.1642974 | U659: =MONTH(M659) -> 5 | V659: =YEAR(M659) -> 2025 | W659: 1.08 | X659: #REF! | Y659: #REF! | Z659: =MONTH(X659) -> #VALUE! | AA659: =YEAR(X659) -> #VALUE! | AC659: 45474 | AD659: =AVERAGEIFS(Y657:Y737,Z657:Z737,AE659,AA657:AA737,AF659)/100 -> #DIV/0! | AE659: =MONTH(AC659) -> 7 | AF659: =YEAR(AC659) -> 2024
A660: 45809 | B660: =MAX(Forecasts!C70:C90) -> 4.445 | C660: =MIN(Forecasts!C70:C90) -> 4.04 | D660: =AVERAGE(Forecasts!C70:C90) -> 4.2986905 | E660: =B660-D660 -> 0.14630952 | F660: =C660-D660 -> -0.25869048 | G660: 4.47 | H660: =G660-D660 -> 0.17130952 | I660: 4.3349 | J660: =G660-I660 -> 0.1351 | K660: =G660/56*100 -> 7.9821429 | M660: =A660 -> 45809 | N660: =P660+Q660 -> 208.15357 | O660: =P660+R660 -> 189.25357 | P660: =P659+AVERAGE(P648-P647,P636-P635,P624-P623,P612-P611,P600-P599,P588-P587,P576-P575,P564-P563,P552-P551,P540-P539) -> 203.37035 | Q660: =AVERAGE(Q648,Q636,Q624,Q612,Q600,Q588,Q576,Q564,Q552,Q540)-6 -> 4.7832197 | R660: =AVERAGE(R648,R636,R624,R612,R600,R588,R576,R564,R552,R540) -> -14.11678 | S660: =P660/39.3679/W660 -> 4.7832342 | T660: =S660-D660 -> 0.48454368 | U660: =MONTH(M660) -> 6 | V660: =YEAR(M660) -> 2025 | W660: 1.08 | X660: #REF! | Y660: #REF! | Z660: =MONTH(X660) -> #VALUE! | AA660: =YEAR(X660) -> #VALUE!
A661: 45839 | B661: =MAX(Forecasts!C91:C112) -> 4.37 | C661: =MIN(Forecasts!C91:C112) -> 4 | D661: =AVERAGE(Forecasts!C91:C112) -> 4.1876136 | E661: =B661-D661 -> 0.18238636 | F661: =C661-D661 -> -0.18761364 | G661: 4.29 | H661: =G661-D661 -> 0.10238636 | I661: 4.1433 | J661: =G661-I661 -> 0.1467 | K661: =G661/56*100 -> 7.6607143 | M661: =A661 -> 45839 | N661: =P661+Q661 -> 214.97857 | O661: =P661+R661 -> 193.87857 | P661: =P660+AVERAGE(P649-P648,P637-P636,P625-P624,P613-P612,P601-P600,P589-P588,P577-P576,P565-P564,P553-P552,P541-P540) -> 205.08589 | Q661: =AVERAGE(Q649,Q637,Q625,Q613,Q601,Q589,Q577,Q565,Q553,Q541)-4 -> 9.8926812 | R661: =AVERAGE(R649,R637,R625,R613,R601,R589,R577,R565,R553,R541) -> -11.207319 | S661: =P661/39.3679/W661 -> 4.8235833 | T661: =S661-D661 -> 0.63596968 | U661: =MONTH(M661) -> 7 | V661: =YEAR(M661) -> 2025 | W661: 1.08 | X661: #REF! | Y661: #REF! | Z661: =MONTH(X661) -> #VALUE! | AA661: =YEAR(X661) -> #VALUE! | AD661: Max
A662: 45870 | B662: =D662+AVERAGE(E650,E638,E626,E614,E602) -> 4.3213325 | C662: =D662+AVERAGE(F650,F638,F626,F614,F602) -> 3.8603325 | D662: 4.05 | E662: =B662-D662 -> 0.27133255 | F662: =C662-D662 -> -0.18966745 | G662: 3.96 | H662: =AVERAGE(H650,H638,H626,H614,H602,H590,H578,H566,H554,H542)-0.15 -> 0.048344775 | I662: 3.9547 | J662: =G662-I662 -> 0.0053 | K662: =G662/56*100 -> 7.0714286 | M662: =A662 -> 45870 | N662: =P662+Q662 -> 215.20357 | O662: =P662+R662 -> 188.10357 | P662: =P661+AVERAGE(P650-P649,P638-P637,P626-P625,P614-P613,P602-P601,P590-P589,P578-P577,P566-P565,P554-P553,P542-P541) -> 198.97699 | Q662: =AVERAGE(Q650,Q638,Q626,Q614,Q602,Q590,Q578,Q566,Q554,Q542)-2 -> 16.226581 | R662: =AVERAGE(R650,R638,R626,R614,R602,R590,R578,R566,R554,R542) -> -10.873419 | S662: =P662/39.3679/W662 -> 4.6799031 | T662: =S662-D662 -> 0.62990309 | U662: =MONTH(M662) -> 8 | V662: =YEAR(M662) -> 2025 | W662: 1.08 | X662: #REF! | Y662: #REF! | Z662: =MONTH(X662) -> #VALUE! | AA662: =YEAR(X662) -> #VALUE! | AC662: =AC657 -> 45536 | AD662: =_xlfn.MAXIFS(Y657:Y737,Z657:Z737,AE662,AA657:AA737,AF662)/100 -> 0 | AE662: 10 | AF662: =YEAR(AC662) -> 2024
A663: 45901 | B663: =D663+AVERAGE(E651,E639,E627,E615,E603) -> 4.3564595 | C663: =D663+AVERAGE(F651,F639,F627,F615,F603) -> 4.0909595 | D663: 4.22 | E663: =B663-D663 -> 0.13645952 | F663: =C663-D663 -> -0.12904048 | G663: 4 | H663: =AVERAGE(H651,H639,H627,H615,H603,H591,H579,H567,H555,H543) -> -0.038881907 | I663: 4.0549 | J663: =G663-I663 -> -0.0549 | K663: =G663/56*100 -> 7.1428571 | M663: =A663 -> 45901 | N663: =P663+Q663 -> 197.50357 | O663: =P663+R663 -> 190.17857 | P663: =P662+AVERAGE(P651-P650,P639-P638,P627-P626,P615-P614,P603-P602,P591-P590,P579-P578,P567-P566,P555-P554,P543-P542) -> 193.97441 | Q663: =AVERAGE(Q651,Q639,Q627,Q615,Q603,Q591,Q579,Q567,Q555,Q543)-1 -> 3.5291613 | R663: =AVERAGE(R651,R639,R627,R615,R603,R591,R579,R567,R555,R543) -> -3.7958387 | S663: =P663/39.3679/W663 -> 4.5622433 | T663: =S663-D663 -> 0.34224331 | U663: =MONTH(M663) -> 9 | V663: =YEAR(M663) -> 2025 | W663: 1.08 | X663: #REF! | Y663: #REF! | Z663: =MONTH(X663) -> #VALUE! | AA663: =YEAR(X663) -> #VALUE! | AC663: =AC658 -> 45444 | AD663: =_xlfn.MAXIFS(Y656:Y737,Z656:Z737,AE663,AA656:AA737,AF663)/100 -> 0 | AE663: =MONTH(AC663) -> 6 | AF663: =YEAR(AC663) -> 2024
A664: 45931 | B664: =D664+AVERAGE(E652,E640,E628,E616,E604) -> 4.5805639 | C664: =D664+AVERAGE(F652,F640,F628,F616,F604) -> 4.2275639 | D664: =D663+AVERAGE(D640-D639,D628-D627,D616-D615,D604-D603,D592-D591) -> 4.3852954 | E664: =B664-D664 -> 0.19526845 | F664: =C664-D664 -> -0.15773155 | G664: 3.93 | H664: =AVERAGE(H652,H640,H628,H616,H604,H592,H580,H568,H556,H544) -> -0.22447095 | I664: 4.0987 | J664: =G664-I664 -> -0.1687 | K664: =G664/56*100 -> 7.0178571 | M664: =A664 -> 45931 | N664: =P664+Q664 -> 200.72857 | O664: =P664+R664 -> 190.70357 | P664: =P663+AVERAGE(P652-P651,P640-P639,P628-P627,P616-P615,P604-P603,P592-P591,P580-P579,P568-P567,P556-P555,P544-P543) -> 197.81563 | Q664: =AVERAGE(Q652,Q640,Q628,Q616,Q604,Q592,Q580,Q568,Q556,Q544)-3 -> 2.9129447 | R664: =AVERAGE(R652,R640,R628,R616,R604,R592,R580,R568,R556,R544) -> -7.1120553 | S664: =P664/39.3679/W664 -> 4.652588 | T664: =S664-D664 -> 0.2672926 | U664: =MONTH(M664) -> 10 | V664: =YEAR(M664) -> 2025 | W664: 1.08 | X664: #REF! | Y664: #REF! | Z664: =MONTH(X664) -> #VALUE! | AA664: =YEAR(X664) -> #VALUE! | AC664: =AC659 -> 45474 | AD664: =_xlfn.MAXIFS(Y656:Y737,Z656:Z737,AE664,AA656:AA737,AF664)/100 -> 0 | AE664: =MONTH(AC664) -> 7 | AF664: =YEAR(AC664) -> 2024
A665: 45962 | B665: =D665+AVERAGE(E653,E641,E629,E617,E605) -> 4.5528726 | C665: =D665+AVERAGE(F653,F641,F629,F617,F605) -> 4.2463726 | D665: 4.4 | E665: =B665-D665 -> 0.15287262 | F665: =C665-D665 -> -0.15362738 | G665: 3.98 | H665: =AVERAGE(H653,H641,H629,H617,H605,H593,H581,H569,H557,H545) -> -0.2173256 | I665: 4.2883 | J665: =G665-I665 -> -0.3083 | K665: =G665/56*100 -> 7.1071429 | M665: =A665 -> 45962 | N665: =P665+Q665 -> 203.40357 | O665: =P665+R665 -> 187.80357 | P665: =P664+AVERAGE(P653-P652,P641-P640,P629-P628,P617-P616,P605-P604,P593-P592,P581-P580,P569-P568,P557-P556,P545-P544) -> 198.72038 | Q665: =AVERAGE(Q653,Q641,Q629,Q617,Q605,Q593,Q581,Q569,Q557,Q545)-3 -> 4.683197 | R665: =AVERAGE(R653,R641,R629,R617,R605,R593,R581,R569,R557,R545) -> -10.916803 | S665: =P665/39.3679/W665 -> 4.6738675 | T665: =S665-D665 -> 0.27386753 | U665: =MONTH(M665) -> 11 | V665: =YEAR(M665) -> 2025 | W665: 1.08 | X665: #REF! | Y665: #REF! | Z665: =MONTH(X665) -> #VALUE! | AA665: =YEAR(X665) -> #VALUE!
A666: 45992 | B666: =D666+AVERAGE(E654,E642,E630,E618,E606) -> 4.6887302 | C666: =D666+AVERAGE(F654,F642,F630,F618,F606) -> 4.2682302 | D666: 4.44 | E666: =B666-D666 -> 0.24873016 | F666: =C666-D666 -> -0.17176984 | G666: =D666+H666 -> 4.240842 | H666: =AVERAGE(H654,H642,H630,H618,H606,H594,H582,H570,H558,H546) -> -0.19915801 | I666: 4.3769 | K666: =G666/56*100 -> 7.5729321 | M666: =A666 -> 45992 | N666: =P666+Q666 -> 194.47857 | O666: =P666+R666 -> 192.50357 | P666: =P665+AVERAGE(P654-P653,P642-P641,P630-P629,P618-P617,P606-P605,P594-P593,P582-P581,P570-P569,P558-P557,P546-P545) -> 195.95396 | Q666: =AVERAGE(Q654,Q642,Q630,Q618,Q606,Q594,Q582,Q570,Q558,Q546)-5 -> -1.4753901 | R666: =AVERAGE(R654,R642,R630,R618,R606,R594,R582,R570,R558,R546) -> -3.4503901 | S666: =P666/39.3679/W666 -> 4.608802 | T666: =S666-D666 -> 0.168802 | U666: =MONTH(M666) -> 12 | V666: =YEAR(M666) -> 2025 | W666: 1.08 | X666: #REF! | Y666: #REF! | Z666: =MONTH(X666) -> #VALUE! | AA666: =YEAR(X666) -> #VALUE!
A667: 46023 | B667: =D667+AVERAGE(E655,E643,E631,E619,E607) -> 4.4235635 | C667: =D667+AVERAGE(F655,F643,F631,F619,F607) -> 3.9900635 | D667: =D666+AVERAGE(D643-D642,D631-D630,D619-D618,D607-D606,D595-D594)-0.4 -> 4.2047351 | E667: =B667-D667 -> 0.21882838 | F667: =C667-D667 -> -0.21467162 | G667: =D667+H667 -> 3.9535899 | H667: =AVERAGE(H655,H643,H631,H619,H607,H595,H583,H571,H559,H547) -> -0.25114517 | K667: =G667/56*100 -> 7.059982 | M667: =A667 -> 46023 | N667: =P667+Q667 -> 197.22857 | O667: =P667+R667 -> 190.90357 | P667: =P666+AVERAGE(P655-P654,P643-P642,P631-P630,P619-P618,P607-P606,P595-P594,P583-P582,P571-P570,P559-P558,P547-P546) -> 196.32309 | Q667: =AVERAGE(Q655,Q643,Q631,Q619,Q607,Q595,Q583,Q571,Q559,Q547)-5 -> 0.90548701 | R667: =AVERAGE(R655,R643,R631,R619,R607,R595,R583,R571,R559,R547) -> -5.419513 | S667: =P667/39.3679/W667 -> 4.6174837 | T667: =S667-D667 -> 0.41274859 | U667: =MONTH(M667) -> 1 | V667: =YEAR(M667) -> 2026 | W667: 1.08 | X667: #REF! | Y667: #REF! | Z667: =MONTH(X667) -> #VALUE! | AA667: =YEAR(X667) -> #VALUE! | AD667: Min
A668: 46054 | B668: =D668+AVERAGE(E656,E644,E632,E620,E608) -> 4.5115698 | C668: =D668+AVERAGE(F656,F644,F632,F620,F608) -> 3.9885698 | D668: =D667+AVERAGE(D644-D643,D632-D631,D620-D619,D608-D607,D596-D595) -> 4.2851619 | E668: =B668-D668 -> 0.22640789 | F668: =C668-D668 -> -0.29659211 | G668: =D668+H668 -> 4.0991661 | H668: =AVERAGE(H656,H644,H632,H620,H608,H596,H584,H572,H560,H548) -> -0.18599573 | K668: =G668/56*100 -> 7.3199395 | M668: =A668 -> 46054 | N668: =P668+Q668 -> 202.76467 | O668: =P668+R668 -> 191.04967 | P668: =P667+AVERAGE(P656-P655,P644-P643,P632-P631,P620-P619,P608-P607,P596-P595,P584-P583,P572-P571,P560-P559,P548-P547) -> 197.47246 | Q668: =AVERAGE(Q656,Q644,Q632,Q620,Q608,Q596,Q584,Q572,Q560,Q548)-5 -> 5.2922083 | R668: =AVERAGE(R656,R644,R632,R620,R608,R596,R584,R572,R560,R548) -> -6.4227917 | S668: =P668/39.3679/W668 -> 4.6445167 | T668: =S668-D668 -> 0.35935482 | U668: =MONTH(M668) -> 2 | V668: =YEAR(M668) -> 2026 | W668: 1.08 | X668: #REF! | Y668: #REF! | Z668: =MONTH(X668) -> #VALUE! | AA668: =YEAR(X668) -> #VALUE! | AC668: =AC657 -> 45536 | AD668: =_xlfn.MINIFS(Y657:Y737,Z657:Z737,AE668,AA657:AA737,AF668)/100 -> 0 | AE668: 10 | AF668: =YEAR(AC668) -> 2024
A669: 46082 | B669: =D669+AVERAGE(E657,E645,E633,E621,E609) -> 4.5443146 | C669: =D669+AVERAGE(F657,F645,F633,F621,F609) -> 4.2073146 | D669: =D668+AVERAGE(D645-D644,D633-D632,D621-D620,D609-D608,D597-D596) -> 4.3855106 | E669: =B669-D669 -> 0.15880399 | F669: =C669-D669 -> -0.17819601 | G669: =D669+H669 -> 4.2025686 | H669: =AVERAGE(H657,H645,H633,H621,H609,H597,H585,H573,H561,H549) -> -0.18294194 | K669: =G669/56*100 -> 7.5045869 | M669: =A669 -> 46082 | N669: =P669+Q669 -> 204.41454 | O669: =P669+R669 -> 190.04704 | P669: =P668+AVERAGE(P657-P656,P645-P644,P633-P632,P621-P620,P609-P608,P597-P596,P585-P584,P573-P572,P561-P560,P549-P548) -> 202.2224 | Q669: =AVERAGE(Q657,Q645,Q633,Q621,Q609,Q597,Q585,Q573,Q561,Q549)-10 -> 2.1921431 | R669: =AVERAGE(R657,R645,R633,R621,R609,R597,R585,R573,R561,R549) -> -12.175357 | S669: =P669/39.3679/W669 -> 4.7562345 | T669: =S669-D669 -> 0.37072389 | U669: =MONTH(M669) -> 3 | V669: =YEAR(M669) -> 2026 | W669: 1.08 | X669: #REF! | Y669: #REF! | Z669: =MONTH(X669) -> #VALUE! | AA669: =YEAR(X669) -> #VALUE! | AC669: =AC658 -> 45444 | AD669: =_xlfn.MINIFS(Y656:Y737,Z656:Z737,AE669,AA656:AA737,AF669)/100 -> 0 | AE669: =MONTH(AC669) -> 6 | AF669: =YEAR(AC669) -> 2024
A670: 46113 | B670: =D670+AVERAGE(E658,E646,E634,E622,E610) -> 4.9794552 | C670: =D670+AVERAGE(F658,F646,F634,F622,F610) -> 4.2399552 | D670: =D669+AVERAGE(D646-D645,D634-D633,D622-D621,D610-D609,D598-D597) -> 4.5705112 | E670: =B670-D670 -> 0.40894398 | F670: =C670-D670 -> -0.33055602 | G670: =D670+H670 -> 4.3554634 | H670: =AVERAGE(H658,H646,H634,H622,H610,H598,H586,H574,H562,H550) -> -0.21504778 | K670: =G670/56*100 -> 7.7776132 | M670: =A670 -> 46113 | N670: =P670+Q670 -> 210.79393 | O670: =P670+R670 -> 194.91893 | P670: =P669+AVERAGE(P658-P657,P646-P645,P634-P633,P622-P621,P610-P609,P598-P597,P586-P585,P574-P573,P562-P561,P550-P549) -> 201.85 | Q670: =AVERAGE(Q658,Q646,Q634,Q622,Q610,Q598,Q586,Q574,Q562,Q550) -> 8.943932 | R670: =AVERAGE(R658,R646,R634,R622,R610,R598,R586,R574,R562,R550) -> -6.931068 | S670: =P670/39.3679/W670 -> 4.7474757 | T670: =S670-D670 -> 0.17696451 | U670: =MONTH(M670) -> 4 | V670: =YEAR(M670) -> 2026 | W670: 1.08 | X670: #REF! | Y670: #REF! | Z670: =MONTH(X670) -> #VALUE! | AA670: =YEAR(X670) -> #VALUE! | AC670: =AC659 -> 45474 | AD670: =_xlfn.MINIFS(Y656:Y737,Z656:Z737,AE670,AA656:AA737,AF670)/100 -> 0 | AE670: =MONTH(AC670) -> 7 | AF670: =YEAR(AC670) -> 2024
A671: 46143 | B671: =D671+AVERAGE(E659,E647,E635,E623,E611) -> 4.894579 | C671: =D671+AVERAGE(F659,F647,F635,F623,F611) -> 4.407079 | D671: =D670+AVERAGE(D647-D646,D635-D634,D623-D622,D611-D610,D599-D598) -> 4.5858318 | E671: =B671-D671 -> 0.30874719 | F671: =C671-D671 -> -0.17875281 | G671: =D671+H671 -> 4.4136868 | H671: =AVERAGE(H659,H647,H635,H623,H611,H599,H587,H575,H563,H551) -> -0.17214498 | K671: =G671/56*100 -> 7.8815836 | M671: =A671 -> 46143 | N671: =P671+Q671 -> 214.35893 | O671: =P671+R671 -> 200.57393 | P671: =P670+AVERAGE(P659-P658,P647-P646,P635-P634,P623-P622,P611-P610,P599-P598,P587-P586,P575-P574,P563-P562,P551-P550) -> 207.38799 | Q671: =AVERAGE(Q659,Q647,Q635,Q623,Q611,Q599,Q587,Q575,Q563,Q551) -> 6.9709464 | R671: =AVERAGE(R659,R647,R635,R623,R611,R599,R587,R575,R563,R551) -> -6.8140536 | S671: =P671/39.3679/W671 -> 4.8777281 | T671: =S671-D671 -> 0.29189633 | U671: =MONTH(M671) -> 5 | V671: =YEAR(M671) -> 2026 | W671: 1.08 | X671: #REF! | Y671: #REF! | Z671: =MONTH(X671) -> #VALUE! | AA671: =YEAR(X671) -> #VALUE!
A672: 46174 | B672: =D672+AVERAGE(E660,E648,E636,E624,E612) -> 4.9002659 | C672: =D672+AVERAGE(F660,F648,F636,F624,F612) -> 4.1672659 | D672: =D671+AVERAGE(D648-D647,D636-D635,D624-D623,D612-D611,D600-D599) -> 4.5662545 | E672: =B672-D672 -> 0.33401139 | F672: =C672-D672 -> -0.39898861 | G672: =D672+H672 -> 4.4332456 | H672: =AVERAGE(H660,H648,H636,H624,H612,H600,H588,H576,H564,H552) -> -0.13300885 | K672: =G672/56*100 -> 7.9165101 | M672: =A672 -> 46174 | N672: =P672+Q672 -> 216.29393 | O672: =P672+R672 -> 192.77893 | P672: =P671+AVERAGE(P660-P659,P648-P647,P636-P635,P624-P623,P612-P611,P600-P599,P588-P587,P576-P575,P564-P563,P552-P551) -> 207.26421 | Q672: =AVERAGE(Q660,Q648,Q636,Q624,Q612,Q600,Q588,Q576,Q564,Q552) -> 9.0297235 | R672: =AVERAGE(R660,R648,R636,R624,R612,R600,R588,R576,R564,R552) -> -14.485277 | S672: =P672/39.3679/W672 -> 4.8748169 | T672: =S672-D672 -> 0.30856242 | U672: =MONTH(M672) -> 6 | V672: =YEAR(M672) -> 2026 | W672: 1.08 | X672: #REF! | Y672: #REF! | Z672: =MONTH(X672) -> #VALUE! | AA672: =YEAR(X672) -> #VALUE!
A673: 46204 | B673: =D673+AVERAGE(E661,E649,E637,E625,E613) -> 4.074254 | C673: =D673+AVERAGE(F661,F649,F637,F625,F613) -> 3.501754 | D673: =D672+AVERAGE(D649-D648,D637-D636,D625-D624,D613-D612,D601-D600) -> 3.7725598 | E673: =B673-D673 -> 0.30169422 | F673: =C673-D673 -> -0.27080578 | G673: =D673+H673 -> 4.0042228 | H673: =AVERAGE(H661,H649,H637,H625,H613,H601,H589,H577,H565,H553) -> 0.23166307 | K673: =G673/56*100 -> 7.1503979 | M673: =A673 -> 46204 | N673: =P673+Q673 -> 221.10143 | O673: =P673+R673 -> 195.89143 | P673: =P672+AVERAGE(P661-P660,P649-P648,P637-P636,P625-P624,P613-P612,P601-P600,P589-P588,P577-P576,P565-P564,P553-P552) -> 207.38253 | Q673: =AVERAGE(Q661,Q649,Q637,Q625,Q613,Q601,Q589,Q577,Q565,Q553) -> 13.718906 | R673: =AVERAGE(R661,R649,R637,R625,R613,R601,R589,R577,R565,R553) -> -11.491094 | S673: =P673/39.3679/W673 -> 4.8775997 | T673: =S673-D673 -> 1.10504 | U673: =MONTH(M673) -> 7 | V673: =YEAR(M673) -> 2026 | W673: 1.08 | X673: #REF! | Y673: #REF! | Z673: =MONTH(X673) -> #VALUE! | AA673: =YEAR(X673) -> #VALUE!
A674: 46235 | B674: =D674+AVERAGE(E662,E650,E638,E626,E614) -> 3.92333 | C674: =D674+AVERAGE(F662,F650,F638,F626,F614) -> 3.44813 | D674: =D673+AVERAGE(D650-D649,D638-D637,D626-D625,D614-D613,D602-D601) -> 3.6659214 | E674: =B674-D674 -> 0.25740858 | F674: =C674-D674 -> -0.21779142 | G674: =D674+H674 -> 3.885815 | H674: =AVERAGE(H662,H650,H638,H626,H614,H602,H590,H578,H566,H554) -> 0.21989355 | K674: =G674/56*100 -> 6.9389553 | M674: =A674 -> 46235 | N674: =P674+Q674 -> 219.89893 | O674: =P674+R674 -> 190.06393 | P674: =P673+AVERAGE(P662-P661,P650-P649,P638-P637,P626-P625,P614-P613,P602-P601,P590-P589,P578-P577,P566-P565,P554-P553) -> 201.23184 | Q674: =AVERAGE(Q662,Q650,Q638,Q626,Q614,Q602,Q590,Q578,Q566,Q554) -> 18.667097 | R674: =AVERAGE(R662,R650,R638,R626,R614,R602,R590,R578,R566,R554) -> -11.167903 | S674: =P674/39.3679/W674 -> 4.7329366 | T674: =S674-D674 -> 1.0670151 | U674: =MONTH(M674) -> 8 | V674: =YEAR(M674) -> 2026 | W674: 1.08 | X674: #REF! | Y674: #REF! | Z674: =MONTH(X674) -> #VALUE! | AA674: =YEAR(X674) -> #VALUE!
A675: 46266 | B675: =D675+AVERAGE(E663,E651,E639,E627,E615) -> 3.9965935 | C675: =D675+AVERAGE(F663,F651,F639,F627,F615) -> 3.7284935 | D675: =D674+AVERAGE(D651-D650,D639-D638,D627-D626,D615-D614,D603-D602) -> 3.8582944 | E675: =B675-D675 -> 0.13829905 | F675: =C675-D675 -> -0.12980095 | G675: =D675+H675 -> 3.8399886 | H675: =AVERAGE(H663,H651,H639,H627,H615,H603,H591,H579,H567,H555) -> -0.018305797 | K675: =G675/56*100 -> 6.8571226 | M675: =A675 -> 46266 | N675: =P675+Q675 -> 201.47893 | O675: =P675+R675 -> 193.07143 | P675: =P674+AVERAGE(P663-P662,P651-P650,P639-P638,P627-P626,P615-P614,P603-P602,P591-P590,P579-P578,P567-P566,P555-P554) -> 197.00254 | Q675: =AVERAGE(Q663,Q651,Q639,Q627,Q615,Q603,Q591,Q579,Q567,Q555) -> 4.4763956 | R675: =AVERAGE(R663,R651,R639,R627,R615,R603,R591,R579,R567,R555) -> -3.9311044 | S675: =P675/39.3679/W675 -> 4.6334642 | T675: =S675-D675 -> 0.77516977 | U675: =MONTH(M675) -> 9 | V675: =YEAR(M675) -> 2026 | W675: 1.08 | X675: #REF! | Y675: #REF! | Z675: =MONTH(X675) -> #VALUE! | AA675: =YEAR(X675) -> #VALUE! | AH675: AMS_3192
A676: 46296 | B676: =D676+AVERAGE(E664,E652,E640,E628,E616) -> 4.1841031 | C676: =D676+AVERAGE(F664,F652,F640,F628,F616) -> 3.8400031 | D676: =D675+AVERAGE(D652-D651,D640-D639,D628-D627,D616-D615,D604-D603) -> 3.9904855 | E676: =B676-D676 -> 0.19361759 | F676: =C676-D676 -> -0.15048241 | G676: =D676+H676 -> 3.7596243 | H676: =AVERAGE(H664,H652,H640,H628,H616,H604,H592,H580,H568,H556) -> -0.23086125 | K676: =G676/56*100 -> 6.7136148 | M676: =A676 -> 46296 | N676: =P676+Q676 -> 207.12643 | O676: =P676+R676 -> 193.92393 | P676: =P675+AVERAGE(P664-P663,P652-P651,P640-P639,P628-P627,P616-P615,P604-P603,P592-P591,P580-P579,P568-P567,P556-P555) -> 201.20287 | Q676: =AVERAGE(Q664,Q652,Q640,Q628,Q616,Q604,Q592,Q580,Q568,Q556) -> 5.9235573 | R676: =AVERAGE(R664,R652,R640,R628,R616,R604,R592,R580,R568,R556) -> -7.2789427 | S676: =P676/39.3679/W676 -> 4.7322554 | T676: =S676-D676 -> 0.74176989 | U676: =MONTH(M676) -> 10 | V676: =YEAR(M676) -> 2026 | W676: 1.08 | X676: #REF! | Y676: #REF! | Z676: =MONTH(X676) -> #VALUE! | AA676: =YEAR(X676) -> #VALUE!
A677: 46327 | B677: =D677+AVERAGE(E665,E653,E641,E629,E617) -> 4.2250285 | C677: =D677+AVERAGE(F665,F653,F641,F629,F617) -> 3.9297285 | D677: =D676+AVERAGE(D653-D652,D641-D640,D629-D628,D617-D616,D605-D604) -> 4.0733814 | E677: =B677-D677 -> 0.15164714 | F677: =C677-D677 -> -0.14365286 | G677: =D677+H677 -> 3.8386357 | H677: =AVERAGE(H665,H653,H641,H629,H617,H605,H593,H581,H569,H557) -> -0.23474567 | K677: =G677/56*100 -> 6.8547066 | M677: =A677 -> 46327 | N677: =P677+Q677 -> 209.16893 | O677: =P677+R677 -> 190.50893 | P677: =P676+AVERAGE(P665-P664,P653-P652,P641-P640,P629-P628,P617-P616,P605-P604,P593-P592,P581-P580,P569-P568,P557-P556) -> 201.55075 | Q677: =AVERAGE(Q665,Q653,Q641,Q629,Q617,Q605,Q593,Q581,Q569,Q557) -> 7.6181833 | R677: =AVERAGE(R665,R653,R641,R629,R617,R605,R593,R581,R569,R557) -> -11.041817 | S677: =P677/39.3679/W677 -> 4.7404374 | T677: =S677-D677 -> 0.667056 | U677: =MONTH(M677) -> 11 | V677: =YEAR(M677) -> 2026 | W677: 1.08 | X677: #REF! | Y677: #REF! | Z677: =MONTH(X677) -> #VALUE! | AA677: =YEAR(X677) -> #VALUE!
A678: 46357 | B678: =D678+AVERAGE(E666,E654,E642,E630,E618) -> 4.3600526 | C678: =D678+AVERAGE(F666,F654,F642,F630,F618) -> 3.9839526 | D678: =D677+AVERAGE(D654-D653,D642-D641,D630-D629,D618-D617,D606-D605) -> 4.1515238 | E678: =B678-D678 -> 0.20852882 | F678: =C678-D678 -> -0.16757118 | G678: =D678+H678 -> 3.9414273 | H678: =AVERAGE(H666,H654,H642,H630,H618,H606,H594,H582,H570,H558) -> -0.21009652 | K678: =G678/56*100 -> 7.038263 | M678: =A678 -> 46357 | N678: =P678+Q678 -> 201.90143 | O678: =P678+R678 -> 195.40393 | P678: =P677+AVERAGE(P666-P665,P654-P653,P642-P641,P630-P629,P618-P617,P606-P605,P594-P593,P582-P581,P570-P569,P558-P557) -> 198.81641 | Q678: =AVERAGE(Q666,Q654,Q642,Q630,Q618,Q606,Q594,Q582,Q570,Q558) -> 3.0850255 | R678: =AVERAGE(R666,R654,R642,R630,R618,R606,R594,R582,R570,R558) -> -3.4124745 | S678: =P678/39.3679/W678 -> 4.6761261 | T678: =S678-D678 -> 0.52460231 | U678: =MONTH(M678) -> 12 | V678: =YEAR(M678) -> 2026 | W678: 1.08 | X678: #REF! | Y678: #REF! | Z678: =MONTH(X678) -> #VALUE! | AA678: =YEAR(X678) -> #VALUE! | AC678: https://www.ers.usda.gov/publications/pub-details/?pubid=99831
X679: #REF! | Y679: #REF! | Z679: =MONTH(X679) -> #VALUE! | AA679: =YEAR(X679) -> #VALUE!
X680: #REF! | Y680: #REF! | Z680: =MONTH(X680) -> #VALUE! | AA680: =YEAR(X680) -> #VALUE!
X681: #REF! | Y681: #REF! | Z681: =MONTH(X681) -> #VALUE! | AA681: =YEAR(X681) -> #VALUE! | AC681: Central Illinois Prices
X682: #REF! | Y682: #REF! | Z682: =MONTH(X682) -> #VALUE! | AA682: =YEAR(X682) -> #VALUE!
X683: #REF! | Y683: #REF! | Z683: =MONTH(X683) -> #VALUE! | AA683: =YEAR(X683) -> #VALUE!
X684: #REF! | Y684: #REF! | Z684: =MONTH(X684) -> #VALUE! | AA684: =YEAR(X684) -> #VALUE!
...

Sheet Sheet1
A2: 36529 | B2: 132 | E2: =MONTH(A2) -> 1 | F2: =YEAR(A2) -> 2000
A3: 36530 | B3: 132 | E3: =MONTH(A3) -> 1 | F3: =YEAR(A3) -> 2000
A4: 36531 | B4: 132 | E4: =MONTH(A4) -> 1 | F4: =YEAR(A4) -> 2000
A5: 36532 | B5: 132 | E5: =MONTH(A5) -> 1 | F5: =YEAR(A5) -> 2000
A6: 36535 | B6: 132 | E6: =MONTH(A6) -> 1 | F6: =YEAR(A6) -> 2000
A7: 36536 | B7: 132 | E7: =MONTH(A7) -> 1 | F7: =YEAR(A7) -> 2000
A8: 36537 | B8: 132 | E8: =MONTH(A8) -> 1 | F8: =YEAR(A8) -> 2000
A9: 36538 | B9: 132 | E9: =MONTH(A9) -> 1 | F9: =YEAR(A9) -> 2000
A10: 36539 | B10: 132 | E10: =MONTH(A10) -> 1 | F10: =YEAR(A10) -> 2000
A11: 36542 | B11: 132.25 | E11: =MONTH(A11) -> 1 | F11: =YEAR(A11) -> 2000
A12: 36543 | B12: 132.75 | E12: =MONTH(A12) -> 1 | F12: =YEAR(A12) -> 2000
A13: 36544 | B13: 132.75 | E13: =MONTH(A13) -> 1 | F13: =YEAR(A13) -> 2000
... A41: 36584 | B41: 135.75 | E41: =MONTH(A41) -> 2 | F41: =YEAR(A41) -> 2000
A42: 36585 | B42: --- | E42: =MONTH(A42) -> 2 | F42: =YEAR(A42) -> 2000
A43: 36586 | B43: 136.25 | E43: =MONTH(A43) -> 3 | F43: =YEAR(A43) -> 2000
A44: 36587 | B44: 136.25 | E44: =MONTH(A44) -> 3 | F44: =YEAR(A44) -> 2000
A45: 36588 | B45: 136.5 | E45: =MONTH(A45) -> 3 | F45: =YEAR(A45) -> 2000
A46: 36591 | B46: 136.5 | E46: =MONTH(A46) -> 3 | F46: =YEAR(A46) -> 2000
A47: 36592 | B47: 136.5 | E47: =MONTH(A47) -> 3 | F47: =YEAR(A47) -> 2000
A48: 36593 | B48: 136.5 | E48: =MONTH(A48) -> 3 | F48: =YEAR(A48) -> 2000
A49: 36594 | B49: 136.5 | E49: =MONTH(A49) -> 3 | F49: =YEAR(A49) -> 2000
A50: 36595 | B50: 137 | E50: =MONTH(A50) -> 3 | F50: =YEAR(A50) -> 2000
A51: 36598 | B51: 137 | E51: =MONTH(A51) -> 3 | F51: =YEAR(A51) -> 2000
A52: 36599 | B52: 137 | E52: =MONTH(A52) -> 3 | F52: =YEAR(A52) -> 2000
A53: 36600 | B53: 137 | E53: =MONTH(A53) -> 3 | F53: =YEAR(A53) -> 2000
A54: 36601 | B54: 136.75 | E54: =MONTH(A54) -> 3 | F54: =YEAR(A54) -> 2000
... A79: 36636 | B79: 138 | E79: =MONTH(A79) -> 4 | F79: =YEAR(A79) -> 2000
A80: 36637 | B80: --- | E80: =MONTH(A80) -> 4 | F80: =YEAR(A80) -> 2000
A81: 36640 | B81: --- | E81: =MONTH(A81) -> 4 | F81: =YEAR(A81) -> 2000
A82: 36641 | B82: 138.75 | E82: =MONTH(A82) -> 4 | F82: =YEAR(A82) -> 2000
A83: 36642 | B83: 139 | E83: =MONTH(A83) -> 4 | F83: =YEAR(A83) -> 2000
A84: 36643 | B84: 139 | E84: =MONTH(A84) -> 4 | F84: =YEAR(A84) -> 2000
A85: 36644 | B85: 139 | E85: =MONTH(A85) -> 4 | F85: =YEAR(A85) -> 2000
A86: 36647 | B86: --- | E86: =MONTH(A86) -> 5 | F86: =YEAR(A86) -> 2000
A87: 36648 | B87: 139.25 | E87: =MONTH(A87) -> 5 | F87: =YEAR(A87) -> 2000
A88: 36649 | B88: 140 | E88: =MONTH(A88) -> 5 | F88: =YEAR(A88) -> 2000
A89: 36650 | B89: 140.75 | E89: =MONTH(A89) -> 5 | F89: =YEAR(A89) -> 2000
A90: 36651 | B90: 141 | E90: =MONTH(A90) -> 5 | F90: =YEAR(A90) -> 2000
A91: 36654 | B91: --- | E91: =MONTH(A91) -> 5 | F91: =YEAR(A91) -> 2000
A92: 36655 | B92: 141.5 | E92: =MONTH(A92) -> 5 | F92: =YEAR(A92) -> 2000
A93: 36656 | B93: 141.5 | E93: =MONTH(A93) -> 5 | F93: =YEAR(A93) -> 2000
A94: 36657 | B94: 141.75 | E94: =MONTH(A94) -> 5 | F94: =YEAR(A94) -> 2000
A95: 36658 | B95: 141.75 | E95: =MONTH(A95) -> 5 | F95: =YEAR(A95) -> 2000
A96: 36661 | B96: 141.75 | E96: =MONTH(A96) -> 5 | F96: =YEAR(A96) -> 2000
A97: 36662 | B97: 141.5 | E97: =MONTH(A97) -> 5 | F97: =YEAR(A97) -> 2000
A98: 36663 | B98: 141 | E98: =MONTH(A98) -> 5 | F98: =YEAR(A98) -> 2000
A99: 36664 | B99: 141.25 | E99: =MONTH(A99) -> 5 | F99: =YEAR(A99) -> 2000
A100: 36665 | B100: 141.25 | E100: =MONTH(A100) -> 5 | F100: =YEAR(A100) -> 2000
A101: 36668 | B101: 141.25 | E101: =MONTH(A101) -> 5 | F101: =YEAR(A101) -> 2000
A102: 36669 | B102: 140.25 | E102: =MONTH(A102) -> 5 | F102: =YEAR(A102) -> 2000
A103: 36670 | B103: 138 | E103: =MONTH(A103) -> 5 | F103: =YEAR(A103) -> 2000
... A115: 36686 | B115: 139 | E115: =MONTH(A115) -> 6 | F115: =YEAR(A115) -> 2000
A116: 36689 | B116: --- | E116: =MONTH(A116) -> 6 | F116: =YEAR(A116) -> 2000
A117: 36690 | B117: 138 | E117: =MONTH(A117) -> 6 | F117: =YEAR(A117) -> 2000
A118: 36691 | B118: 138 | E118: =MONTH(A118) -> 6 | F118: =YEAR(A118) -> 2000
A119: 36692 | B119: 139.25 | E119: =MONTH(A119) -> 6 | F119: =YEAR(A119) -> 2000
A120: 36693 | B120: 139.5 | E120: =MONTH(A120) -> 6 | F120: =YEAR(A120) -> 2000
A121: 36696 | B121: 139.5 | E121: =MONTH(A121) -> 6 | F121: =YEAR(A121) -> 2000
A122: 36697 | B122: 139.75 | E122: =MONTH(A122) -> 6 | F122: =YEAR(A122) -> 2000
A123: 36698 | B123: 141.5 | E123: =MONTH(A123) -> 6 | F123: =YEAR(A123) -> 2000
A124: 36699 | B124: 140 | E124: =MONTH(A124) -> 6 | F124: =YEAR(A124) -> 2000
A125: 36700 | B125: 141 | E125: =MONTH(A125) -> 6 | F125: =YEAR(A125) -> 2000
A126: 36703 | B126: 141 | E126: =MONTH(A126) -> 6 | F126: =YEAR(A126) -> 2000
A127: 36704 | B127: 139 | E127: =MONTH(A127) -> 6 | F127: =YEAR(A127) -> 2000
A128: 36705 | B128: 139 | E128: =MONTH(A128) -> 6 | F128: =YEAR(A128) -> 2000
... A139: 36720 | B139: 148.25 | E139: =MONTH(A139) -> 7 | F139: =YEAR(A139) -> 2000
A140: 36721 | B140: --- | E140: =MONTH(A140) -> 7 | F140: =YEAR(A140) -> 2000
A141: 36724 | B141: 148.25 | E141: =MONTH(A141) -> 7 | F141: =YEAR(A141) -> 2000
A142: 36725 | B142: 152 | E142: =MONTH(A142) -> 7 | F142: =YEAR(A142) -> 2000
A143: 36726 | B143: 152 | E143: =MONTH(A143) -> 7 | F143: =YEAR(A143) -> 2000
A144: 36727 | B144: 152.5 | E144: =MONTH(A144) -> 7 | F144: =YEAR(A144) -> 2000
A145: 36728 | B145: 153 | E145: =MONTH(A145) -> 7 | F145: =YEAR(A145) -> 2000
A146: 36731 | B146: 153 | E146: =MONTH(A146) -> 7 | F146: =YEAR(A146) -> 2000
A147: 36732 | B147: 153 | E147: =MONTH(A147) -> 7 | F147: =YEAR(A147) -> 2000
A148: 36733 | B148: 153 | E148: =MONTH(A148) -> 7 | F148: =YEAR(A148) -> 2000
A149: 36734 | B149: 153 | E149: =MONTH(A149) -> 7 | F149: =YEAR(A149) -> 2000
A150: 36735 | B150: 162.5 | E150: =MONTH(A150) -> 7 | F150: =YEAR(A150) -> 2000
A151: 36738 | B151: 164.5 | E151: =MONTH(A151) -> 7 | F151: =YEAR(A151) -> 2000
A152: 36739 | B152: 166 | E152: =MONTH(A152) -> 8 | F152: =YEAR(A152) -> 2000
... A155: 36742 | B155: 165.5 | E155: =MONTH(A155) -> 8 | F155: =YEAR(A155) -> 2000
A156: 36745 | B156: --- | E156: =MONTH(A156) -> 8 | F156: =YEAR(A156) -> 2000
A157: 36746 | B157: --- | E157: =MONTH(A157) -> 8 | F157: =YEAR(A157) -> 2000
A158: 36747 | B158: --- | E158: =MONTH(A158) -> 8 | F158: =YEAR(A158) -> 2000
A159: 36748 | B159: 123.75 | E159: =MONTH(A159) -> 8 | F159: =YEAR(A159) -> 2000
A160: 36749 | B160: 123.75 | E160: =MONTH(A160) -> 8 | F160: =YEAR(A160) -> 2000
A161: 36752 | B161: 123.75 | E161: =MONTH(A161) -> 8 | F161: =YEAR(A161) -> 2000
A162: 36753 | B162: 123.75 | E162: =MONTH(A162) -> 8 | F162: =YEAR(A162) -> 2000
A163: 36754 | B163: 123.75 | E163: =MONTH(A163) -> 8 | F163: =YEAR(A163) -> 2000
A164: 36755 | B164: 123.75 | E164: =MONTH(A164) -> 8 | F164: =YEAR(A164) -> 2000
A165: 36756 | B165: 124.25 | E165: =MONTH(A165) -> 8 | F165: =YEAR(A165) -> 2000
A166: 36759 | B166: 124.25 | E166: =MONTH(A166) -> 8 | F166: =YEAR(A166) -> 2000
A167: 36760 | B167: 124.25 | E167: =MONTH(A167) -> 8 | F167: =YEAR(A167) -> 2000
A168: 36761 | B168: 124.25 | E168: =MONTH(A168) -> 8 | F168: =YEAR(A168) -> 2000
A169: 36762 | B169: 123.5 | E169: =MONTH(A169) -> 8 | F169: =YEAR(A169) -> 2000
A170: 36763 | B170: 123.5 | E170: =MONTH(A170) -> 8 | F170: =YEAR(A170) -> 2000
... A190: 36791 | B190: 123.25 | E190: =MONTH(A190) -> 9 | F190: =YEAR(A190) -> 2000
A191: 36794 | B191: --- | E191: =MONTH(A191) -> 9 | F191: =YEAR(A191) -> 2000
A192: 36795 | B192: 123.25 | E192: =MONTH(A192) -> 9 | F192: =YEAR(A192) -> 2000
A193: 36796 | B193: 123.25 | E193: =MONTH(A193) -> 9 | F193: =YEAR(A193) -> 2000
A194: 36797 | B194: 123.25 | E194: =MONTH(A194) -> 9 | F194: =YEAR(A194) -> 2000
...

Sheet Barley
B1: Average Nearby ICE Canadian Feed Barley Futures | G1: Corn - Barley | L1: FOB Russia | R1: FOB Ukraine | X1: FOB Argentina | AD1: FOB Australia | AJ1: FOB France | AP1: Canadian Dollars / US Dollar
A2: Month | B2: High | C2: Low | D2: Average | E2: High-Avg | F2: Low-Avg | G2: C$/tonne | H2: C¢/bu | I2: $/mt | J2: ¢/bu | L2: High | M2: Low | N2: Average | O2: High-Avg | P2: Low-Avg | R2: High | S2: Low | T2: Average | U2: High-Avg | V2: Low-Avg | X2: High | Y2: Low | Z2: Average | AA2: High-Avg | AB2: Low-Avg | AD2: High | AE2: Low | AF2: Average | AG2: High-Avg | AH2: Low-Avg | AJ2: High | AK2: Low | AL2: Average | AM2: High-Avg | AN2: Low-Avg | BA2: Month | BB2: Year | BC2: {=[3]!'AFB@C[INTERVAL:DAILY,COMPRESSION:1,FILTER:USA,SORT:ASC,NDATE:10/11/2026,FDATE:1/1/2000,VERSION:1]?DATE,CLOSE'} -> #REF! | BD2: #REF! | BF2: =MONTH(BC2) -> #VALUE! | BG2: =YEAR(BC2) -> #VALUE!
BC3: #REF! | BD3: #REF! | BF3: =MONTH(BC3) -> #VALUE! | BG3: =YEAR(BC3) -> #VALUE! | BJ3: {=[3]!'@CD@C[INTERVAL:DAILY,COMPRESSION:1,FILTER:USA,SORT:ASC,NDATE:10/11/2024,FDATE:1/1/2016,VERSION:1]?DATE,CLOSE'} -> #REF! | BK3: #REF! | BM3: =MONTH(BJ3) -> #VALUE! | BN3: =YEAR(BJ3) -> #VALUE! | BR3: CAD Avg
A4: =Prices!A3 -> 25812 | BC4: #REF! | BD4: #REF! | BF4: =MONTH(BC4) -> #VALUE! | BG4: =YEAR(BC4) -> #VALUE! | BJ4: #REF! | BK4: #REF! | BM4: =MONTH(BJ4) -> #VALUE! | BN4: =YEAR(BJ4) -> #VALUE!
A5: =Prices!A4 -> 25842 | BC5: #REF! | BD5: #REF! | BF5: =MONTH(BC5) -> #VALUE! | BG5: =YEAR(BC5) -> #VALUE! | BJ5: #REF! | BK5: #REF! | BM5: =MONTH(BJ5) -> #VALUE! | BN5: =YEAR(BJ5) -> #VALUE!
A6: =Prices!A5 -> 25873 | BC6: #REF! | BD6: #REF! | BF6: =MONTH(BC6) -> #VALUE! | BG6: =YEAR(BC6) -> #VALUE! | BJ6: #REF! | BK6: #REF! | BM6: =MONTH(BJ6) -> #VALUE! | BN6: =YEAR(BJ6) -> #VALUE!
A7: =Prices!A6 -> 25903 | BC7: #REF! | BD7: #REF! | BF7: =MONTH(BC7) -> #VALUE! | BG7: =YEAR(BC7) -> #VALUE! | BJ7: #REF! | BK7: #REF! | BM7: =MONTH(BJ7) -> #VALUE! | BN7: =YEAR(BJ7) -> #VALUE!
A8: =Prices!A7 -> 25934 | BC8: #REF! | BD8: #REF! | BF8: =MONTH(BC8) -> #VALUE! | BG8: =YEAR(BC8) -> #VALUE! | BJ8: #REF! | BK8: #REF! | BM8: =MONTH(BJ8) -> #VALUE! | BN8: =YEAR(BJ8) -> #VALUE!
A9: =Prices!A8 -> 25965 | BC9: #REF! | BD9: #REF! | BF9: =MONTH(BC9) -> #VALUE! | BG9: =YEAR(BC9) -> #VALUE! | BJ9: #REF! | BK9: #REF! | BM9: =MONTH(BJ9) -> #VALUE! | BN9: =YEAR(BJ9) -> #VALUE!
A10: =Prices!A9 -> 25993 | BC10: #REF! | BD10: #REF! | BF10: =MONTH(BC10) -> #VALUE! | BG10: =YEAR(BC10) -> #VALUE! | BJ10: #REF! | BK10: #REF! | BM10: =MONTH(BJ10) -> #VALUE! | BN10: =YEAR(BJ10) -> #VALUE!
A11: =Prices!A10 -> 26024 | BC11: #REF! | BD11: #REF! | BF11: =MONTH(BC11) -> #VALUE! | BG11: =YEAR(BC11) -> #VALUE! | BJ11: #REF! | BK11: #REF! | BM11: =MONTH(BJ11) -> #VALUE! | BN11: =YEAR(BJ11) -> #VALUE!
A12: =Prices!A11 -> 26054 | BC12: #REF! | BD12: #REF! | BF12: =MONTH(BC12) -> #VALUE! | BG12: =YEAR(BC12) -> #VALUE! | BJ12: #REF! | BK12: #REF! | BM12: =MONTH(BJ12) -> #VALUE! | BN12: =YEAR(BJ12) -> #VALUE!
A13: =Prices!A12 -> 26085 | BC13: #REF! | BD13: #REF! | BF13: =MONTH(BC13) -> #VALUE! | BG13: =YEAR(BC13) -> #VALUE! | BJ13: #REF! | BK13: #REF! | BM13: =MONTH(BJ13) -> #VALUE! | BN13: =YEAR(BJ13) -> #VALUE!
A14: =Prices!A13 -> 26115 | BC14: #REF! | BD14: #REF! | BF14: =MONTH(BC14) -> #VALUE! | BG14: =YEAR(BC14) -> #VALUE! | BJ14: #REF! | BK14: #REF! | BM14: =MONTH(BJ14) -> #VALUE! | BN14: =YEAR(BJ14) -> #VALUE!
A15: =Prices!A14 -> 26146 | BC15: #REF! | BD15: #REF! | BF15: =MONTH(BC15) -> #VALUE! | BG15: =YEAR(BC15) -> #VALUE! | BJ15: #REF! | BK15: #REF! | BM15: =MONTH(BJ15) -> #VALUE! | BN15: =YEAR(BJ15) -> #VALUE!
... A391: =Prices!A390 -> 37591 | BC391: #REF! | BD391: #REF! | BF391: =MONTH(BC391) -> #VALUE! | BG391: =YEAR(BC391) -> #VALUE! | BJ391: #REF! | BK391: #REF! | BM391: =MONTH(BJ391) -> #VALUE! | BN391: =YEAR(BJ391) -> #VALUE!
A392: =Prices!A391 -> 37622 | BC392: #REF! | BD392: #REF! | BF392: =MONTH(BC392) -> #VALUE! | BG392: =YEAR(BC392) -> #VALUE! | BJ392: #REF! | BK392: #REF! | BM392: =MONTH(BJ392) -> #VALUE! | BN392: =YEAR(BJ392) -> #VALUE! | BR392: 36526 | BS392: =MONTH(BR392) -> 1 | BT392: =YEAR(BR392) -> 2000 | BU392: =AVERAGEIFS($BK$3:$BK$5500,$BM$3:$BM$5500,BS392,$BN$3:$BN$5500,BT392) -> #DIV/0!
A393: =Prices!A392 -> 37653 | BC393: #REF! | BD393: #REF! | BF393: =MONTH(BC393) -> #VALUE! | BG393: =YEAR(BC393) -> #VALUE! | BJ393: #REF! | BK393: #REF! | BM393: =MONTH(BJ393) -> #VALUE! | BN393: =YEAR(BJ393) -> #VALUE! | BR393: 36557 | BS393: =MONTH(BR393) -> 2 | BT393: =YEAR(BR393) -> 2000 | BU393: =AVERAGEIFS($BK$3:$BK$5500,$BM$3:$BM$5500,BS393,$BN$3:$BN$5500,BT393) -> #DIV/0!
A394: =Prices!A393 -> 37681 | BC394: #REF! | BD394: #REF! | BF394: =MONTH(BC394) -> #VALUE! | BG394: =YEAR(BC394) -> #VALUE! | BJ394: #REF! | BK394: #REF! | BM394: =MONTH(BJ394) -> #VALUE! | BN394: =YEAR(BJ394) -> #VALUE! | BR394: 36586 | BS394: =MONTH(BR394) -> 3 | BT394: =YEAR(BR394) -> 2000 | BU394: =AVERAGEIFS($BK$3:$BK$5500,$BM$3:$BM$5500,BS394,$BN$3:$BN$5500,BT394) -> #DIV/0!
A395: =Prices!A394 -> 37712 | BC395: #REF! | BD395: #REF! | BF395: =MONTH(BC395) -> #VALUE! | BG395: =YEAR(BC395) -> #VALUE! | BJ395: #REF! | BK395: #REF! | BM395: =MONTH(BJ395) -> #VALUE! | BN395: =YEAR(BJ395) -> #VALUE! | BR395: 36617 | BS395: =MONTH(BR395) -> 4 | BT395: =YEAR(BR395) -> 2000 | BU395: =AVERAGEIFS($BK$3:$BK$5500,$BM$3:$BM$5500,BS395,$BN$3:$BN$5500,BT395) -> #DIV/0!
A396: =Prices!A395 -> 37742 | BC396: #REF! | BD396: #REF! | BF396: =MONTH(BC396) -> #VALUE! | BG396: =YEAR(BC396) -> #VALUE! | BJ396: #REF! | BK396: #REF! | BM396: =MONTH(BJ396) -> #VALUE! | BN396: =YEAR(BJ396) -> #VALUE! | BR396: 36647 | BS396: =MONTH(BR396) -> 5 | BT396: =YEAR(BR396) -> 2000 | BU396: =AVERAGEIFS($BK$3:$BK$5500,$BM$3:$BM$5500,BS396,$BN$3:$BN$5500,BT396) -> #DIV/0!
A397: =Prices!A396 -> 37773 | BC397: #REF! | BD397: #REF! | BF397: =MONTH(BC397) -> #VALUE! | BG397: =YEAR(BC397) -> #VALUE! | BJ397: #REF! | BK397: #REF! | BM397: =MONTH(BJ397) -> #VALUE! | BN397: =YEAR(BJ397) -> #VALUE! | BR397: 36678 | BS397: =MONTH(BR397) -> 6 | BT397: =YEAR(BR397) -> 2000 | BU397: =AVERAGEIFS($BK$3:$BK$5500,$BM$3:$BM$5500,BS397,$BN$3:$BN$5500,BT397) -> #DIV/0!
A398: =Prices!A397 -> 37803 | AQ398: Canadian Dollars per US Dollar | BC398: #REF! | BD398: #REF! | BF398: =MONTH(BC398) -> #VALUE! | BG398: =YEAR(BC398) -> #VALUE! | BJ398: #REF! | BK398: #REF! | BM398: =MONTH(BJ398) -> #VALUE! | BN398: =YEAR(BJ398) -> #VALUE! | BR398: 36708 | BS398: =MONTH(BR398) -> 7 | BT398: =YEAR(BR398) -> 2000 | BU398: =AVERAGEIFS($BK$3:$BK$5500,$BM$3:$BM$5500,BS398,$BN$3:$BN$5500,BT398) -> #DIV/0!
A399: =Prices!A398 -> 37834 | BC399: #REF! | BD399: #REF! | BF399: =MONTH(BC399) -> #VALUE! | BG399: =YEAR(BC399) -> #VALUE! | BJ399: #REF! | BK399: #REF! | BM399: =MONTH(BJ399) -> #VALUE! | BN399: =YEAR(BJ399) -> #VALUE! | BR399: 36739 | BS399: =MONTH(BR399) -> 8 | BT399: =YEAR(BR399) -> 2000 | BU399: =AVERAGEIFS($BK$3:$BK$5500,$BM$3:$BM$5500,BS399,$BN$3:$BN$5500,BT399) -> #DIV/0!
A400: =Prices!A399 -> 37865 | BC400: #REF! | BD400: #REF! | BF400: =MONTH(BC400) -> #VALUE! | BG400: =YEAR(BC400) -> #VALUE! | BJ400: #REF! | BK400: #REF! | BM400: =MONTH(BJ400) -> #VALUE! | BN400: =YEAR(BJ400) -> #VALUE! | BR400: 36770 | BS400: =MONTH(BR400) -> 9 | BT400: =YEAR(BR400) -> 2000 | BU400: =AVERAGEIFS($BK$3:$BK$5500,$BM$3:$BM$5500,BS400,$BN$3:$BN$5500,BT400) -> #DIV/0!
A401: =Prices!A400 -> 37895 | BC401: #REF! | BD401: #REF! | BF401: =MONTH(BC401) -> #VALUE! | BG401: =YEAR(BC401) -> #VALUE! | BJ401: #REF! | BK401: #REF! | BM401: =MONTH(BJ401) -> #VALUE! | BN401: =YEAR(BJ401) -> #VALUE! | BR401: 36800 | BS401: =MONTH(BR401) -> 10 | BT401: =YEAR(BR401) -> 2000 | BU401: =AVERAGEIFS($BK$3:$BK$5500,$BM$3:$BM$5500,BS401,$BN$3:$BN$5500,BT401) -> #DIV/0!
A402: =Prices!A401 -> 37926 | B402: =_xlfn.MAXIFS($BD$2:$BD$5500,$BF$2:$BF$5500,$BA402,$BG$2:$BG$5500,$BB402) -> 0 | C402: =_xlfn.MINIFS($BD$2:$BD$5500,$BF$2:$BF$5500,$BA402,$BG$2:$BG$5500,$BB402) -> 0 | D402: =AVERAGEIFS($BD$2:$BD$5500,$BF$2:$BF$5500,$BA402,$BG$2:$BG$5500,$BB402) -> #DIV/0! | E402: =B402-D402 -> #DIV/0! | F402: =C402-D402 -> #DIV/0! | G402: =Prices!P401-D402 -> #DIV/0! | H402: =(G402/45.9296)*100 -> #DIV/0! | I402: =D402*AQ402 -> #DIV/0! | J402: =(I402/45.9296)*100 -> #DIV/0! | AP402: 37926 | AQ402: 0.76066842 | BA402: =MONTH(A402) -> 11 | BB402: =YEAR(A402) -> 2003 | BC402: #REF! | BD402: #REF! | BF402: =MONTH(BC402) -> #VALUE! | BG402: =YEAR(BC402) -> #VALUE! | BJ402: #REF! | BK402: #REF! | BM402: =MONTH(BJ402) -> #VALUE! | BN402: =YEAR(BJ402) -> #VALUE! | BR402: 36831 | BS402: =MONTH(BR402) -> 11 | BT402: =YEAR(BR402) -> 2000 | BU402: =AVERAGEIFS($BK$3:$BK$5500,$BM$3:$BM$5500,BS402,$BN$3:$BN$5500,BT402) -> #DIV/0!
A403: =Prices!A402 -> 37956 | B403: =_xlfn.MAXIFS($BD$2:$BD$5500,$BF$2:$BF$5500,$BA403,$BG$2:$BG$5500,$BB403) -> 0 | C403: =_xlfn.MINIFS($BD$2:$BD$5500,$BF$2:$BF$5500,$BA403,$BG$2:$BG$5500,$BB403) -> 0 | D403: =AVERAGEIFS($BD$2:$BD$5500,$BF$2:$BF$5500,$BA403,$BG$2:$BG$5500,$BB403) -> #DIV/0! | E403: =B403-D403 -> #DIV/0! | F403: =C403-D403 -> #DIV/0! | G403: =Prices!P402-D403 -> #DIV/0! | H403: =(G403/45.9296)*100 -> #DIV/0! | I403: =D403*AQ403 -> #DIV/0! | J403: =(I403/45.9296)*100 -> #DIV/0! | AP403: 37956 | AQ403: 0.76079091 | BA403: =MONTH(A403) -> 12 | BB403: =YEAR(A403) -> 2003 | BC403: #REF! | BD403: #REF! | BF403: =MONTH(BC403) -> #VALUE! | BG403: =YEAR(BC403) -> #VALUE! | BJ403: #REF! | BK403: #REF! | BM403: =MONTH(BJ403) -> #VALUE! | BN403: =YEAR(BJ403) -> #VALUE! | BR403: 36861 | BS403: =MONTH(BR403) -> 12 | BT403: =YEAR(BR403) -> 2000 | BU403: =AVERAGEIFS($BK$3:$BK$5500,$BM$3:$BM$5500,BS403,$BN$3:$BN$5500,BT403) -> #DIV/0!
A404: =Prices!A403 -> 37987 | B404: =_xlfn.MAXIFS($BD$2:$BD$5500,$BF$2:$BF$5500,$BA404,$BG$2:$BG$5500,$BB404) -> 0 | C404: =_xlfn.MINIFS($BD$2:$BD$5500,$BF$2:$BF$5500,$BA404,$BG$2:$BG$5500,$BB404) -> 0 | D404: =AVERAGEIFS($BD$2:$BD$5500,$BF$2:$BF$5500,$BA404,$BG$2:$BG$5500,$BB404) -> #DIV/0! | E404: =B404-D404 -> #DIV/0! | F404: =C404-D404 -> #DIV/0! | G404: =Prices!P403-D404 -> #DIV/0! | H404: =(G404/45.9296)*100 -> #DIV/0! | I404: =D404*AQ404 -> #DIV/0! | J404: =(I404/45.9296)*100 -> #DIV/0! | AP404: 37987 | AQ404: 0.769575 | BA404: =MONTH(A404) -> 1 | BB404: =YEAR(A404) -> 2004 | BC404: #REF! | BD404: #REF! | BF404: =MONTH(BC404) -> #VALUE! | BG404: =YEAR(BC404) -> #VALUE! | BJ404: #REF! | BK404: #REF! | BM404: =MONTH(BJ404) -> #VALUE! | BN404: =YEAR(BJ404) -> #VALUE! | BR404: 36892 | BS404: =MONTH(BR404) -> 1 | BT404: =YEAR(BR404) -> 2001 | BU404: =AVERAGEIFS($BK$3:$BK$5500,$BM$3:$BM$5500,BS404,$BN$3:$BN$5500,BT404) -> #DIV/0!
A405: =Prices!A404 -> 38018 | B405: =_xlfn.MAXIFS($BD$2:$BD$5500,$BF$2:$BF$5500,$BA405,$BG$2:$BG$5500,$BB405) -> 0 | C405: =_xlfn.MINIFS($BD$2:$BD$5500,$BF$2:$BF$5500,$BA405,$BG$2:$BG$5500,$BB405) -> 0 | D405: =AVERAGEIFS($BD$2:$BD$5500,$BF$2:$BF$5500,$BA405,$BG$2:$BG$5500,$BB405) -> #DIV/0! | E405: =B405-D405 -> #DIV/0! | F405: =C405-D405 -> #DIV/0! | G405: =Prices!P404-D405 -> #DIV/0! | H405: =(G405/45.9296)*100 -> #DIV/0! | I405: =D405*AQ405 -> #DIV/0! | J405: =(I405/45.9296)*100 -> #DIV/0! | AP405: 38018 | AQ405: 0.75115263 | BA405: =MONTH(A405) -> 2 | BB405: =YEAR(A405) -> 2004 | BC405: #REF! | BD405: #REF! | BF405: =MONTH(BC405) -> #VALUE! | BG405: =YEAR(BC405) -> #VALUE! | BJ405: #REF! | BK405: #REF! | BM405: =MONTH(BJ405) -> #VALUE! | BN405: =YEAR(BJ405) -> #VALUE! | BR405: 36923 | BS405: =MONTH(BR405) -> 2 | BT405: =YEAR(BR405) -> 2001 | BU405: =AVERAGEIFS($BK$3:$BK$5500,$BM$3:$BM$5500,BS405,$BN$3:$BN$5500,BT405) -> #DIV/0!
A406: =Prices!A405 -> 38047 | B406: =_xlfn.MAXIFS($BD$2:$BD$5500,$BF$2:$BF$5500,$BA406,$BG$2:$BG$5500,$BB406) -> 0 | C406: =_xlfn.MINIFS($BD$2:$BD$5500,$BF$2:$BF$5500,$BA406,$BG$2:$BG$5500,$BB406) -> 0 | D406: =AVERAGEIFS($BD$2:$BD$5500,$BF$2:$BF$5500,$BA406,$BG$2:$BG$5500,$BB406) -> #DIV/0! | E406: =B406-D406 -> #DIV/0! | F406: =C406-D406 -> #DIV/0! | G406: =Prices!P405-D406 -> #DIV/0! | H406: =(G406/45.9296)*100 -> #DIV/0! | I406: =D406*AQ406 -> #DIV/0! | J406: =(I406/45.9296)*100 -> #DIV/0! | AP406: 38047 | AQ406: 0.75211739 | BA406: =MONTH(A406) -> 3 | BB406: =YEAR(A406) -> 2004 | BC406: #REF! | BD406: #REF! | BF406: =MONTH(BC406) -> #VALUE! | BG406: =YEAR(BC406) -> #VALUE! | BJ406: #REF! | BK406: #REF! | BM406: =MONTH(BJ406) -> #VALUE! | BN406: =YEAR(BJ406) -> #VALUE! | BR406: 36951 | BS406: =MONTH(BR406) -> 3 | BT406: =YEAR(BR406) -> 2001 | BU406: =AVERAGEIFS($BK$3:$BK$5500,$BM$3:$BM$5500,BS406,$BN$3:$BN$5500,BT406) -> #DIV/0!
A407: =Prices!A406 -> 38078 | B407: =_xlfn.MAXIFS($BD$2:$BD$5500,$BF$2:$BF$5500,$BA407,$BG$2:$BG$5500,$BB407) -> 0 | C407: =_xlfn.MINIFS($BD$2:$BD$5500,$BF$2:$BF$5500,$BA407,$BG$2:$BG$5500,$BB407) -> 0 | D407: =AVERAGEIFS($BD$2:$BD$5500,$BF$2:$BF$5500,$BA407,$BG$2:$BG$5500,$BB407) -> #DIV/0! | E407: =B407-D407 -> #DIV/0! | F407: =C407-D407 -> #DIV/0! | G407: =Prices!P406-D407 -> #DIV/0! | H407: =(G407/45.9296)*100 -> #DIV/0! | I407: =D407*AQ407 -> #DIV/0! | J407: =(I407/45.9296)*100 -> #DIV/0! | AP407: 38078 | AQ407: 0.74424286 | BA407: =MONTH(A407) -> 4 | BB407: =YEAR(A407) -> 2004 | BC407: #REF! | BD407: #REF! | BF407: =MONTH(BC407) -> #VALUE! | BG407: =YEAR(BC407) -> #VALUE! | BJ407: #REF! | BK407: #REF! | BM407: =MONTH(BJ407) -> #VALUE! | BN407: =YEAR(BJ407) -> #VALUE! | BR407: 36982 | BS407: =MONTH(BR407) -> 4 | BT407: =YEAR(BR407) -> 2001 | BU407: =AVERAGEIFS($BK$3:$BK$5500,$BM$3:$BM$5500,BS407,$BN$3:$BN$5500,BT407) -> #DIV/0!
A408: =Prices!A407 -> 38108 | B408: =_xlfn.MAXIFS($BD$2:$BD$5500,$BF$2:$BF$5500,$BA408,$BG$2:$BG$5500,$BB408) -> 0 | C408: =_xlfn.MINIFS($BD$2:$BD$5500,$BF$2:$BF$5500,$BA408,$BG$2:$BG$5500,$BB408) -> 0 | D408: =AVERAGEIFS($BD$2:$BD$5500,$BF$2:$BF$5500,$BA408,$BG$2:$BG$5500,$BB408) -> #DIV/0! | E408: =B408-D408 -> #DIV/0! | F408: =C408-D408 -> #DIV/0! | G408: =Prices!P407-D408 -> #DIV/0! | H408: =(G408/45.9296)*100 -> #DIV/0! | I408: =D408*AQ408 -> #DIV/0! | J408: =(I408/45.9296)*100 -> #DIV/0! | AP408: 38108 | AQ408: 0.724725 | BA408: =MONTH(A408) -> 5 | BB408: =YEAR(A408) -> 2004 | BC408: #REF! | BD408: #REF! | BF408: =MONTH(BC408) -> #VALUE! | BG408: =YEAR(BC408) -> #VALUE! | BJ408: #REF! | BK408: #REF! | BM408: =MONTH(BJ408) -> #VALUE! | BN408: =YEAR(BJ408) -> #VALUE! | BR408: 37012 | BS408: =MONTH(BR408) -> 5 | BT408: =YEAR(BR408) -> 2001 | BU408: =AVERAGEIFS($BK$3:$BK$5500,$BM$3:$BM$5500,BS408,$BN$3:$BN$5500,BT408) -> #DIV/0!
A409: =Prices!A408 -> 38139 | B409: =_xlfn.MAXIFS($BD$2:$BD$5500,$BF$2:$BF$5500,$BA409,$BG$2:$BG$5500,$BB409) -> 0 | C409: =_xlfn.MINIFS($BD$2:$BD$5500,$BF$2:$BF$5500,$BA409,$BG$2:$BG$5500,$BB409) -> 0 | D409: =AVERAGEIFS($BD$2:$BD$5500,$BF$2:$BF$5500,$BA409,$BG$2:$BG$5500,$BB409) -> #DIV/0! | E409: =B409-D409 -> #DIV/0! | F409: =C409-D409 -> #DIV/0! | G409: =Prices!P408-D409 -> #DIV/0! | H409: =(G409/45.9296)*100 -> #DIV/0! | I409: =D409*AQ409 -> #DIV/0! | J409: =(I409/45.9296)*100 -> #DIV/0! | AP409: 38139 | AQ409: 0.73584545 | BA409: =MONTH(A409) -> 6 | BB409: =YEAR(A409) -> 2004 | BC409: #REF! | BD409: #REF! | BF409: =MONTH(BC409) -> #VALUE! | BG409: =YEAR(BC409) -> #VALUE! | BJ409: #REF! | BK409: #REF! | BM409: =MONTH(BJ409) -> #VALUE! | BN409: =YEAR(BJ409) -> #VALUE! | BR409: 37043 | BS409: =MONTH(BR409) -> 6 | BT409: =YEAR(BR409) -> 2001 | BU409: =AVERAGEIFS($BK$3:$BK$5500,$BM$3:$BM$5500,BS409,$BN$3:$BN$5500,BT409) -> #DIV/0!
A410: =Prices!A409 -> 38169 | B410: =_xlfn.MAXIFS($BD$2:$BD$5500,$BF$2:$BF$5500,$BA410,$BG$2:$BG$5500,$BB410) -> 0 | C410: =_xlfn.MINIFS($BD$2:$BD$5500,$BF$2:$BF$5500,$BA410,$BG$2:$BG$5500,$BB410) -> 0 | D410: =AVERAGEIFS($BD$2:$BD$5500,$BF$2:$BF$5500,$BA410,$BG$2:$BG$5500,$BB410) -> #DIV/0! | E410: =B410-D410 -> #DIV/0! | F410: =C410-D410 -> #DIV/0! | G410: =Prices!P409-D410 -> #DIV/0! | H410: =(G410/45.9296)*100 -> #DIV/0! | I410: =D410*AQ410 -> #DIV/0! | J410: =(I410/45.9296)*100 -> #DIV/0! | AP410: 38169 | AQ410: 0.75573333 | BA410: =MONTH(A410) -> 7 | BB410: =YEAR(A410) -> 2004 | BC410: #REF! | BD410: #REF! | BF410: =MONTH(BC410) -> #VALUE! | BG410: =YEAR(BC410) -> #VALUE! | BJ410: #REF! | BK410: #REF! | BM410: =MONTH(BJ410) -> #VALUE! | BN410: =YEAR(BJ410) -> #VALUE! | BR410: 37073 | BS410: =MONTH(BR410) -> 7 | BT410: =YEAR(BR410) -> 2001 | BU410: =AVERAGEIFS($BK$3:$BK$5500,$BM$3:$BM$5500,BS410,$BN$3:$BN$5500,BT410) -> #DIV/0!
A411: =Prices!A410 -> 38200 | B411: =_xlfn.MAXIFS($BD$2:$BD$5500,$BF$2:$BF$5500,$BA411,$BG$2:$BG$5500,$BB411) -> 0 | C411: =_xlfn.MINIFS($BD$2:$BD$5500,$BF$2:$BF$5500,$BA411,$BG$2:$BG$5500,$BB411) -> 0 | D411: =AVERAGEIFS($BD$2:$BD$5500,$BF$2:$BF$5500,$BA411,$BG$2:$BG$5500,$BB411) -> #DIV/0! | E411: =B411-D411 -> #DIV/0! | F411: =C411-D411 -> #DIV/0! | G411: =Prices!P410-D411 -> #DIV/0! | H411: =(G411/45.9296)*100 -> #DIV/0! | I411: =D411*AQ411 -> #DIV/0! | J411: =(I411/45.9296)*100 -> #DIV/0! | AP411: 38200 | AQ411: 0.76149091 | BA411: =MONTH(A411) -> 8 | BB411: =YEAR(A411) -> 2004 | BC411: #REF! | BD411: #REF! | BF411: =MONTH(BC411) -> #VALUE! | BG411: =YEAR(BC411) -> #VALUE! | BJ411: #REF! | BK411: #REF! | BM411: =MONTH(BJ411) -> #VALUE! | BN411: =YEAR(BJ411) -> #VALUE! | BR411: 37104 | BS411: =MONTH(BR411) -> 8 | BT411: =YEAR(BR411) -> 2001 | BU411: =AVERAGEIFS($BK$3:$BK$5500,$BM$3:$BM$5500,BS411,$BN$3:$BN$5500,BT411) -> #DIV/0!
A412: =Prices!A411 -> 38231 | B412: =_xlfn.MAXIFS($BD$2:$BD$5500,$BF$2:$BF$5500,$BA412,$BG$2:$BG$5500,$BB412) -> 0 | C412: =_xlfn.MINIFS($BD$2:$BD$5500,$BF$2:$BF$5500,$BA412,$BG$2:$BG$5500,$BB412) -> 0 | D412: =AVERAGEIFS($BD$2:$BD$5500,$BF$2:$BF$5500,$BA412,$BG$2:$BG$5500,$BB412) -> #DIV/0! | E412: =B412-D412 -> #DIV/0! | F412: =C412-D412 -> #DIV/0! | G412: =Prices!P411-D412 -> #DIV/0! | H412: =(G412/45.9296)*100 -> #DIV/0! | I412: =D412*AQ412 -> #DIV/0! | J412: =(I412/45.9296)*100 -> #DIV/0! | AP412: 38231 | AQ412: 0.7760619 | BA412: =MONTH(A412) -> 9 | BB412: =YEAR(A412) -> 2004 | BC412: #REF! | BD412: #REF! | BF412: =MONTH(BC412) -> #VALUE! | BG412: =YEAR(BC412) -> #VALUE! | BJ412: #REF! | BK412: #REF! | BM412: =MONTH(BJ412) -> #VALUE! | BN412: =YEAR(BJ412) -> #VALUE! | BR412: 37135 | BS412: =MONTH(BR412) -> 9 | BT412: =YEAR(BR412) -> 2001 | BU412: =AVERAGEIFS($BK$3:$BK$5500,$BM$3:$BM$5500,BS412,$BN$3:$BN$5500,BT412) -> #DIV/0!
A413: =Prices!A412 -> 38261 | B413: =_xlfn.MAXIFS($BD$2:$BD$5500,$BF$2:$BF$5500,$BA413,$BG$2:$BG$5500,$BB413) -> 0 | C413: =_xlfn.MINIFS($BD$2:$BD$5500,$BF$2:$BF$5500,$BA413,$BG$2:$BG$5500,$BB413) -> 0 | D413: =AVERAGEIFS($BD$2:$BD$5500,$BF$2:$BF$5500,$BA413,$BG$2:$BG$5500,$BB413) -> #DIV/0! | E413: =B413-D413 -> #DIV/0! | F413: =C413-D413 -> #DIV/0! | G413: =Prices!P412-D413 -> #DIV/0! | H413: =(G413/45.9296)*100 -> #DIV/0! | I413: =D413*AQ413 -> #DIV/0! | J413: =(I413/45.9296)*100 -> #DIV/0! | AP413: 38261 | AQ413: 0.80117619 | BA413: =MONTH(A413) -> 10 | BB413: =YEAR(A413) -> 2004 | BC413: #REF! | BD413: #REF! | BF413: =MONTH(BC413) -> #VALUE! | BG413: =YEAR(BC413) -> #VALUE! | BJ413: #REF! | BK413: #REF! | BM413: =MONTH(BJ413) -> #VALUE! | BN413: =YEAR(BJ413) -> #VALUE! | BR413: 37165 | BS413: =MONTH(BR413) -> 10 | BT413: =YEAR(BR413) -> 2001 | BU413: =AVERAGEIFS($BK$3:$BK$5500,$BM$3:$BM$5500,BS413,$BN$3:$BN$5500,BT413) -> #DIV/0!
... A416: =Prices!A415 -> 38353 | B416: =_xlfn.MAXIFS($BD$2:$BD$5500,$BF$2:$BF$5500,$BA416,$BG$2:$BG$5500,$BB416) -> 0 | C416: =_xlfn.MINIFS($BD$2:$BD$5500,$BF$2:$BF$5500,$BA416,$BG$2:$BG$5500,$BB416) -> 0 | D416: =AVERAGEIFS($BD$2:$BD$5500,$BF$2:$BF$5500,$BA416,$BG$2:$BG$5500,$BB416) -> #DIV/0! | E416: =B416-D416 -> #DIV/0! | F416: =C416-D416 -> #DIV/0! | G416: =Prices!P415-D416 -> #DIV/0! | H416: =(G416/45.9296)*100 -> #DIV/0! | I416: =D416*AQ416 -> #DIV/0! | J416: =(I416/45.9296)*100 -> #DIV/0! | AP416: 38353 | AQ416: 0.81633333 | BA416: =MONTH(A416) -> 1 | BB416: =YEAR(A416) -> 2005 | BC416: #REF! | BD416: #REF! | BF416: =MONTH(BC416) -> #VALUE! | BG416: =YEAR(BC416) -> #VALUE! | BJ416: #REF! | BK416: #REF! | BM416: =MONTH(BJ416) -> #VALUE! | BN416: =YEAR(BJ416) -> #VALUE! | BR416: 37257 | BS416: =MONTH(BR416) -> 1 | BT416: =YEAR(BR416) -> 2002 | BU416: =AVERAGEIFS($BK$3:$BK$5500,$BM$3:$BM$5500,BS416,$BN$3:$BN$5500,BT416) -> #DIV/0!
A417: =Prices!A416 -> 38384 | AP417: 38384 | AQ417: 0.80727895 | BA417: =MONTH(A417) -> 2 | BB417: =YEAR(A417) -> 2005 | BC417: #REF! | BD417: #REF! | BF417: =MONTH(BC417) -> #VALUE! | BG417: =YEAR(BC417) -> #VALUE! | BJ417: #REF! | BK417: #REF! | BM417: =MONTH(BJ417) -> #VALUE! | BN417: =YEAR(BJ417) -> #VALUE! | BR417: 37288 | BS417: =MONTH(BR417) -> 2 | BT417: =YEAR(BR417) -> 2002 | BU417: =AVERAGEIFS($BK$3:$BK$5500,$BM$3:$BM$5500,BS417,$BN$3:$BN$5500,BT417) -> #DIV/0!
A418: =Prices!A417 -> 38412 | AP418: 38412 | AQ418: 0.82319091 | BA418: =MONTH(A418) -> 3 | BB418: =YEAR(A418) -> 2005 | BC418: #REF! | BD418: #REF! | BF418: =MONTH(BC418) -> #VALUE! | BG418: =YEAR(BC418) -> #VALUE! | BJ418: #REF! | BK418: #REF! | BM418: =MONTH(BJ418) -> #VALUE! | BN418: =YEAR(BJ418) -> #VALUE! | BR418: 37316 | BS418: =MONTH(BR418) -> 3 | BT418: =YEAR(BR418) -> 2002 | BU418: =AVERAGEIFS($BK$3:$BK$5500,$BM$3:$BM$5500,BS418,$BN$3:$BN$5500,BT418) -> #DIV/0!
A419: =Prices!A418 -> 38443 | B419: =_xlfn.MAXIFS($BD$2:$BD$5500,$BF$2:$BF$5500,$BA419,$BG$2:$BG$5500,$BB419) -> 0 | C419: =_xlfn.MINIFS($BD$2:$BD$5500,$BF$2:$BF$5500,$BA419,$BG$2:$BG$5500,$BB419) -> 0 | D419: =AVERAGEIFS($BD$2:$BD$5500,$BF$2:$BF$5500,$BA419,$BG$2:$BG$5500,$BB419) -> #DIV/0! | E419: =B419-D419 -> #DIV/0! | F419: =C419-D419 -> #DIV/0! | G419: =Prices!P418-D419 -> #DIV/0! | H419: =(G419/45.9296)*100 -> #DIV/0! | I419: =D419*AQ419 -> #DIV/0! | J419: =(I419/45.9296)*100 -> #DIV/0! | AP419: 38443 | AQ419: 0.80915714 | BA419: =MONTH(A419) -> 4 | BB419: =YEAR(A419) -> 2005 | BC419: #REF! | BD419: #REF! | BF419: =MONTH(BC419) -> #VALUE! | BG419: =YEAR(BC419) -> #VALUE! | BJ419: #REF! | BK419: #REF! | BM419: =MONTH(BJ419) -> #VALUE! | BN419: =YEAR(BJ419) -> #VALUE! | BR419: 37347 | BS419: =MONTH(BR419) -> 4 | BT419: =YEAR(BR419) -> 2002 | BU419: =AVERAGEIFS($BK$3:$BK$5500,$BM$3:$BM$5500,BS419,$BN$3:$BN$5500,BT419) -> #DIV/0!
A420: =Prices!A419 -> 38473 | AP420: 38473 | AQ420: 0.79704286 | BA420: =MONTH(A420) -> 5 | BB420: =YEAR(A420) -> 2005 | BC420: #REF! | BD420: #REF! | BF420: =MONTH(BC420) -> #VALUE! | BG420: =YEAR(BC420) -> #VALUE! | BJ420: #REF! | BK420: #REF! | BM420: =MONTH(BJ420) -> #VALUE! | BN420: =YEAR(BJ420) -> #VALUE! | BR420: 37377 | BS420: =MONTH(BR420) -> 5 | BT420: =YEAR(BR420) -> 2002 | BU420: =AVERAGEIFS($BK$3:$BK$5500,$BM$3:$BM$5500,BS420,$BN$3:$BN$5500,BT420) -> #DIV/0!
A421: =Prices!A420 -> 38504 | AP421: 38504 | AQ421: 0.80715909 | BA421: =MONTH(A421) -> 6 | BB421: =YEAR(A421) -> 2005 | BC421: #REF! | BD421: #REF! | BF421: =MONTH(BC421) -> #VALUE! | BG421: =YEAR(BC421) -> #VALUE! | BJ421: #REF! | BK421: #REF! | BM421: =MONTH(BJ421) -> #VALUE! | BN421: =YEAR(BJ421) -> #VALUE! | BR421: 37408 | BS421: =MONTH(BR421) -> 6 | BT421: =YEAR(BR421) -> 2002 | BU421: =AVERAGEIFS($BK$3:$BK$5500,$BM$3:$BM$5500,BS421,$BN$3:$BN$5500,BT421) -> #DIV/0!
A422: =Prices!A421 -> 38534 | AP422: 38534 | AQ422: 0.819015 | BA422: =MONTH(A422) -> 7 | BB422: =YEAR(A422) -> 2005 | BC422: #REF! | BD422: #REF! | BF422: =MONTH(BC422) -> #VALUE! | BG422: =YEAR(BC422) -> #VALUE! | BJ422: #REF! | BK422: #REF! | BM422: =MONTH(BJ422) -> #VALUE! | BN422: =YEAR(BJ422) -> #VALUE! | BR422: 37438 | BS422: =MONTH(BR422) -> 7 | BT422: =YEAR(BR422) -> 2002 | BU422: =AVERAGEIFS($BK$3:$BK$5500,$BM$3:$BM$5500,BS422,$BN$3:$BN$5500,BT422) -> #DIV/0!
A423: =Prices!A422 -> 38565 | AP423: 38565 | AQ423: 0.83083043 | BA423: =MONTH(A423) -> 8 | BB423: =YEAR(A423) -> 2005 | BC423: #REF! | BD423: #REF! | BF423: =MONTH(BC423) -> #VALUE! | BG423: =YEAR(BC423) -> #VALUE! | BJ423: #REF! | BK423: #REF! | BM423: =MONTH(BJ423) -> #VALUE! | BN423: =YEAR(BJ423) -> #VALUE! | BR423: 37469 | BS423: =MONTH(BR423) -> 8 | BT423: =YEAR(BR423) -> 2002 | BU423: =AVERAGEIFS($BK$3:$BK$5500,$BM$3:$BM$5500,BS423,$BN$3:$BN$5500,BT423) -> #DIV/0!
A424: =Prices!A423 -> 38596 | AP424: 38596 | AQ424: 0.85014286 | BA424: =MONTH(A424) -> 9 | BB424: =YEAR(A424) -> 2005 | BC424: #REF! | BD424: #REF! | BF424: =MONTH(BC424) -> #VALUE! | BG424: =YEAR(BC424) -> #VALUE! | BJ424: #REF! | BK424: #REF! | BM424: =MONTH(BJ424) -> #VALUE! | BN424: =YEAR(BJ424) -> #VALUE! | BR424: 37500 | BS424: =MONTH(BR424) -> 9 | BT424: =YEAR(BR424) -> 2002 | BU424: =AVERAGEIFS($BK$3:$BK$5500,$BM$3:$BM$5500,BS424,$BN$3:$BN$5500,BT424) -> #DIV/0!
A425: =Prices!A424 -> 38626 | AP425: 38626 | AQ425: 0.85059048 | BA425: =MONTH(A425) -> 10 | BB425: =YEAR(A425) -> 2005 | BC425: #REF! | BD425: #REF! | BF425: =MONTH(BC425) -> #VALUE! | BG425: =YEAR(BC425) -> #VALUE! | BJ425: #REF! | BK425: #REF! | BM425: =MONTH(BJ425) -> #VALUE! | BN425: =YEAR(BJ425) -> #VALUE! | BR425: 37530 | BS425: =MONTH(BR425) -> 10 | BT425: =YEAR(BR425) -> 2002 | BU425: =AVERAGEIFS($BK$3:$BK$5500,$BM$3:$BM$5500,BS425,$BN$3:$BN$5500,BT425) -> #DIV/0!
A426: =Prices!A425 -> 38657 | AP426: 38657 | AQ426: 0.84729524 | BA426: =MONTH(A426) -> 11 | BB426: =YEAR(A426) -> 2005 | BC426: #REF! | BD426: #REF! | BF426: =MONTH(BC426) -> #VALUE! | BG426: =YEAR(BC426) -> #VALUE! | BJ426: #REF! | BK426: #REF! | BM426: =MONTH(BJ426) -> #VALUE! | BN426: =YEAR(BJ426) -> #VALUE! | BR426: 37561 | BS426: =MONTH(BR426) -> 11 | BT426: =YEAR(BR426) -> 2002 | BU426: =AVERAGEIFS($BK$3:$BK$5500,$BM$3:$BM$5500,BS426,$BN$3:$BN$5500,BT426) -> #DIV/0!
A427: =Prices!A426 -> 38687 | AP427: 38687 | AQ427: 0.86190476 | BA427: =MONTH(A427) -> 12 | BB427: =YEAR(A427) -> 2005 | BC427: #REF! | BD427: #REF! | BF427: =MONTH(BC427) -> #VALUE! | BG427: =YEAR(BC427) -> #VALUE! | BJ427: #REF! | BK427: #REF! | BM427: =MONTH(BJ427) -> #VALUE! | BN427: =YEAR(BJ427) -> #VALUE! | BR427: 37591 | BS427: =MONTH(BR427) -> 12 | BT427: =YEAR(BR427) -> 2002 | BU427: =AVERAGEIFS($BK$3:$BK$5500,$BM$3:$BM$5500,BS427,$BN$3:$BN$5500,BT427) -> #DIV/0!
A428: =Prices!A427 -> 38718 | AP428: 38718 | AQ428: 0.865915 | BA428: =MONTH(A428) -> 1 | BB428: =YEAR(A428) -> 2006 | BC428: #REF! | BD428: #REF! | BF428: =MONTH(BC428) -> #VALUE! | BG428: =YEAR(BC428) -> #VALUE! | BJ428: #REF! | BK428: #REF! | BM428: =MONTH(BJ428) -> #VALUE! | BN428: =YEAR(BJ428) -> #VALUE! | BR428: 37622 | BS428: =MONTH(BR428) -> 1 | BT428: =YEAR(BR428) -> 2003 | BU428: =AVERAGEIFS($BK$3:$BK$5500,$BM$3:$BM$5500,BS428,$BN$3:$BN$5500,BT428) -> #DIV/0!
A429: =Prices!A428 -> 38749 | AP429: 38749 | AQ429: 0.8711 | BA429: =MONTH(A429) -> 2 | BB429: =YEAR(A429) -> 2006 | BC429: #REF! | BD429: #REF! | BF429: =MONTH(BC429) -> #VALUE! | BG429: =YEAR(BC429) -> #VALUE! | BJ429: #REF! | BK429: #REF! | BM429: =MONTH(BJ429) -> #VALUE! | BN429: =YEAR(BJ429) -> #VALUE! | BR429: 37653 | BS429: =MONTH(BR429) -> 2 | BT429: =YEAR(BR429) -> 2003 | BU429: =AVERAGEIFS($BK$3:$BK$5500,$BM$3:$BM$5500,BS429,$BN$3:$BN$5500,BT429) -> #DIV/0!
A430: =Prices!A429 -> 38777 | AP430: 38777 | AQ430: 0.87065 | BA430: =MONTH(A430) -> 3 | BB430: =YEAR(A430) -> 2006 | BC430: #REF! | BD430: #REF! | BF430: =MONTH(BC430) -> #VALUE! | BG430: =YEAR(BC430) -> #VALUE! | BJ430: #REF! | BK430: #REF! | BM430: =MONTH(BJ430) -> #VALUE! | BN430: =YEAR(BJ430) -> #VALUE! | BR430: 37681 | BS430: =MONTH(BR430) -> 3 | BT430: =YEAR(BR430) -> 2003 | BU430: =AVERAGEIFS($BK$3:$BK$5500,$BM$3:$BM$5500,BS430,$BN$3:$BN$5500,BT430) -> #DIV/0!
A431: =Prices!A430 -> 38808 | AP431: 38808 | AQ431: =AQ430 -> 0.87065 | BA431: =MONTH(A431) -> 4 | BB431: =YEAR(A431) -> 2006 | BC431: #REF! | BD431: #REF! | BF431: =MONTH(BC431) -> #VALUE! | BG431: =YEAR(BC431) -> #VALUE! | BJ431: #REF! | BK431: #REF! | BM431: =MONTH(BJ431) -> #VALUE! | BN431: =YEAR(BJ431) -> #VALUE! | BR431: 37712 | BS431: =MONTH(BR431) -> 4 | BT431: =YEAR(BR431) -> 2003 | BU431: =AVERAGEIFS($BK$3:$BK$5500,$BM$3:$BM$5500,BS431,$BN$3:$BN$5500,BT431) -> #DIV/0!
A432: =Prices!A431 -> 38838 | AP432: 38838 | AQ432: 0.90085 | BA432: =MONTH(A432) -> 5 | BB432: =YEAR(A432) -> 2006 | BC432: #REF! | BD432: #REF! | BF432: =MONTH(BC432) -> #VALUE! | BG432: =YEAR(BC432) -> #VALUE! | BJ432: #REF! | BK432: #REF! | BM432: =MONTH(BJ432) -> #VALUE! | BN432: =YEAR(BJ432) -> #VALUE! | BR432: 37742 | BS432: =MONTH(BR432) -> 5 | BT432: =YEAR(BR432) -> 2003 | BU432: =AVERAGEIFS($BK$3:$BK$5500,$BM$3:$BM$5500,BS432,$BN$3:$BN$5500,BT432) -> #DIV/0!
A433: =Prices!A432 -> 38869 | AP433: 38869 | AQ433: 0.89871364 | BA433: =MONTH(A433) -> 6 | BB433: =YEAR(A433) -> 2006 | BC433: #REF! | BD433: #REF! | BF433: =MONTH(BC433) -> #VALUE! | BG433: =YEAR(BC433) -> #VALUE! | BJ433: #REF! | BK433: #REF! | BM433: =MONTH(BJ433) -> #VALUE! | BN433: =YEAR(BJ433) -> #VALUE! | BR433: 37773 | BS433: =MONTH(BR433) -> 6 | BT433: =YEAR(BR433) -> 2003 | BU433: =AVERAGEIFS($BK$3:$BK$5500,$BM$3:$BM$5500,BS433,$BN$3:$BN$5500,BT433) -> #DIV/0!
A434: =Prices!A433 -> 38899 | AP434: 38899 | AQ434: 0.887005 | BA434: =MONTH(A434) -> 7 | BB434: =YEAR(A434) -> 2006 | BC434: #REF! | BD434: #REF! | BF434: =MONTH(BC434) -> #VALUE! | BG434: =YEAR(BC434) -> #VALUE! | BJ434: #REF! | BK434: #REF! | BM434: =MONTH(BJ434) -> #VALUE! | BN434: =YEAR(BJ434) -> #VALUE! | BR434: 37803 | BS434: =MONTH(BR434) -> 7 | BT434: =YEAR(BR434) -> 2003 | BU434: =AVERAGEIFS($BK$3:$BK$5500,$BM$3:$BM$5500,BS434,$BN$3:$BN$5500,BT434) -> #DIV/0!
A435: =Prices!A434 -> 38930 | AP435: 38930 | AQ435: 0.89472609 | BA435: =MONTH(A435) -> 8 | BB435: =YEAR(A435) -> 2006 | BC435: #REF! | BD435: #REF! | BF435: =MONTH(BC435) -> #VALUE! | BG435: =YEAR(BC435) -> #VALUE! | BJ435: #REF! | BK435: #REF! | BM435: =MONTH(BJ435) -> #VALUE! | BN435: =YEAR(BJ435) -> #VALUE! | BR435: 37834 | BS435: =MONTH(BR435) -> 8 | BT435: =YEAR(BR435) -> 2003 | BU435: =AVERAGEIFS($BK$3:$BK$5500,$BM$3:$BM$5500,BS435,$BN$3:$BN$5500,BT435) -> #DIV/0!
A436: =Prices!A435 -> 38961 | AP436: 38961 | AQ436: 0.896975 | BA436: =MONTH(A436) -> 9 | BB436: =YEAR(A436) -> 2006 | BC436: #REF! | BD436: #REF! | BF436: =MONTH(BC436) -> #VALUE! | BG436: =YEAR(BC436) -> #VALUE! | BJ436: #REF! | BK436: #REF! | BM436: =MONTH(BJ436) -> #VALUE! | BN436: =YEAR(BJ436) -> #VALUE! | BR436: 37865 | BS436: =MONTH(BR436) -> 9 | BT436: =YEAR(BR436) -> 2003 | BU436: =AVERAGEIFS($BK$3:$BK$5500,$BM$3:$BM$5500,BS436,$BN$3:$BN$5500,BT436) -> #DIV/0!
A437: =Prices!A436 -> 38991 | B437: =_xlfn.MAXIFS($BD$2:$BD$5500,$BF$2:$BF$5500,$BA437,$BG$2:$BG$5500,$BB437) -> 0 | C437: =_xlfn.MINIFS($BD$2:$BD$5500,$BF$2:$BF$5500,$BA437,$BG$2:$BG$5500,$BB437) -> 0 | D437: =AVERAGEIFS($BD$2:$BD$5500,$BF$2:$BF$5500,$BA437,$BG$2:$BG$5500,$BB437) -> #DIV/0! | E437: =B437-D437 -> #DIV/0! | F437: =C437-D437 -> #DIV/0! | G437: =Prices!P436-D437 -> #DIV/0! | H437: =(G437/45.9296)*100 -> #DIV/0! | I437: =D437*AQ437 -> #DIV/0! | J437: =(I437/45.9296)*100 -> #DIV/0! | AP437: 38991 | AQ437: 0.88808636 | BA437: =MONTH(A437) -> 10 | BB437: =YEAR(A437) -> 2006 | BC437: #REF! | BD437: #REF! | BF437: =MONTH(BC437) -> #VALUE! | BG437: =YEAR(BC437) -> #VALUE! | BJ437: #REF! | BK437: #REF! | BM437: =MONTH(BJ437) -> #VALUE! | BN437: =YEAR(BJ437) -> #VALUE! | BR437: 37895 | BS437: =MONTH(BR437) -> 10 | BT437: =YEAR(BR437) -> 2003 | BU437: =AVERAGEIFS($BK$3:$BK$5500,$BM$3:$BM$5500,BS437,$BN$3:$BN$5500,BT437) -> #DIV/0!
A438: =Prices!A437 -> 39022 | B438: =_xlfn.MAXIFS($BD$2:$BD$5500,$BF$2:$BF$5500,$BA438,$BG$2:$BG$5500,$BB438) -> 0 | C438: =_xlfn.MINIFS($BD$2:$BD$5500,$BF$2:$BF$5500,$BA438,$BG$2:$BG$5500,$BB438) -> 0 | D438: =AVERAGEIFS($BD$2:$BD$5500,$BF$2:$BF$5500,$BA438,$BG$2:$BG$5500,$BB438) -> #DIV/0! | E438: =B438-D438 -> #DIV/0! | F438: =C438-D438 -> #DIV/0! | G438: =Prices!P437-D438 -> #DIV/0! | H438: =(G438/45.9296)*100 -> #DIV/0! | I438: =D438*AQ438 -> #DIV/0! | J438: =(I438/45.9296)*100 -> #DIV/0! | AP438: 39022 | AQ438: 0.88090952 | BA438: =MONTH(A438) -> 11 | BB438: =YEAR(A438) -> 2006 | BC438: #REF! | BD438: #REF! | BF438: =MONTH(BC438) -> #VALUE! | BG438: =YEAR(BC438) -> #VALUE! | BJ438: #REF! | BK438: #REF! | BM438: =MONTH(BJ438) -> #VALUE! | BN438: =YEAR(BJ438) -> #VALUE! | BR438: 37926 | BS438: =MONTH(BR438) -> 11 | BT438: =YEAR(BR438) -> 2003 | BU438: =AVERAGEIFS($BK$3:$BK$5500,$BM$3:$BM$5500,BS438,$BN$3:$BN$5500,BT438) -> #DIV/0!
A439: =Prices!A438 -> 39052 | B439: =_xlfn.MAXIFS($BD$2:$BD$5500,$BF$2:$BF$5500,$BA439,$BG$2:$BG$5500,$BB439) -> 0 | C439: =_xlfn.MINIFS($BD$2:$BD$5500,$BF$2:$BF$5500,$BA439,$BG$2:$BG$5500,$BB439) -> 0 | D439: =AVERAGEIFS($BD$2:$BD$5500,$BF$2:$BF$5500,$BA439,$BG$2:$BG$5500,$BB439) -> #DIV/0! | E439: =B439-D439 -> #DIV/0! | F439: =C439-D439 -> #DIV/0! | G439: =Prices!P438-D439 -> #DIV/0! | H439: =(G439/45.9296)*100 -> #DIV/0! | I439: =D439*AQ439 -> #DIV/0! | J439: =(I439/45.9296)*100 -> #DIV/0! | AP439: 39052 | AQ439: 0.867885 | BA439: =MONTH(A439) -> 12 | BB439: =YEAR(A439) -> 2006 | BC439: #REF! | BD439: #REF! | BF439: =MONTH(BC439) -> #VALUE! | BG439: =YEAR(BC439) -> #VALUE! | BJ439: #REF! | BK439: #REF! | BM439: =MONTH(BJ439) -> #VALUE! | BN439: =YEAR(BJ439) -> #VALUE! | BR439: 37956 | BS439: =MONTH(BR439) -> 12 | BT439: =YEAR(BR439) -> 2003 | BU439: =AVERAGEIFS($BK$3:$BK$5500,$BM$3:$BM$5500,BS439,$BN$3:$BN$5500,BT439) -> #DIV/0!
A440: =Prices!A439 -> 39083 | B440: =_xlfn.MAXIFS($BD$2:$BD$5500,$BF$2:$BF$5500,$BA440,$BG$2:$BG$5500,$BB440) -> 0 | C440: =_xlfn.MINIFS($BD$2:$BD$5500,$BF$2:$BF$5500,$BA440,$BG$2:$BG$5500,$BB440) -> 0 | D440: =AVERAGEIFS($BD$2:$BD$5500,$BF$2:$BF$5500,$BA440,$BG$2:$BG$5500,$BB440) -> #DIV/0! | E440: =B440-D440 -> #DIV/0! | F440: =C440-D440 -> #DIV/0! | G440: =Prices!P439-D440 -> #DIV/0! | H440: =(G440/45.9296)*100 -> #DIV/0! | I440: =D440*AQ440 -> #DIV/0! | J440: =(I440/45.9296)*100 -> #DIV/0! | AP440: 39083 | AQ440: 0.85184286 | BA440: =MONTH(A440) -> 1 | BB440: =YEAR(A440) -> 2007 | BC440: #REF! | BD440: #REF! | BF440: =MONTH(BC440) -> #VALUE! | BG440: =YEAR(BC440) -> #VALUE! | BJ440: #REF! | BK440: #REF! | BM440: =MONTH(BJ440) -> #VALUE! | BN440: =YEAR(BJ440) -> #VALUE! | BR440: 37987 | BS440: =MONTH(BR440) -> 1 | BT440: =YEAR(BR440) -> 2004 | BU440: =AVERAGEIFS($BK$3:$BK$5500,$BM$3:$BM$5500,BS440,$BN$3:$BN$5500,BT440) -> #DIV/0!
A441: =Prices!A440 -> 39114 | B441: =_xlfn.MAXIFS($BD$2:$BD$5500,$BF$2:$BF$5500,$BA441,$BG$2:$BG$5500,$BB441) -> 0 | C441: =_xlfn.MINIFS($BD$2:$BD$5500,$BF$2:$BF$5500,$BA441,$BG$2:$BG$5500,$BB441) -> 0 | D441: =AVERAGEIFS($BD$2:$BD$5500,$BF$2:$BF$5500,$BA441,$BG$2:$BG$5500,$BB441) -> #DIV/0! | E441: =B441-D441 -> #DIV/0! | F441: =C441-D441 -> #DIV/0! | G441: =Prices!P440-D441 -> #DIV/0! | H441: =(G441/45.9296)*100 -> #DIV/0! | I441: =D441*AQ441 -> #DIV/0! | J441: =(I441/45.9296)*100 -> #DIV/0! | AP441: 39114 | AQ441: 0.85481579 | BA441: =MONTH(A441) -> 2 | BB441: =YEAR(A441) -> 2007 | BC441: #REF! | BD441: #REF! | BF441: =MONTH(BC441) -> #VALUE! | BG441: =YEAR(BC441) -> #VALUE! | BJ441: #REF! | BK441: #REF! | BM441: =MONTH(BJ441) -> #VALUE! | BN441: =YEAR(BJ441) -> #VALUE! | BR441: 38018 | BS441: =MONTH(BR441) -> 2 | BT441: =YEAR(BR441) -> 2004 | BU441: =AVERAGEIFS($BK$3:$BK$5500,$BM$3:$BM$5500,BS441,$BN$3:$BN$5500,BT441) -> #DIV/0!
A442: =Prices!A441 -> 39142 | B442: =_xlfn.MAXIFS($BD$2:$BD$5500,$BF$2:$BF$5500,$BA442,$BG$2:$BG$5500,$BB442) -> 0 | C442: =_xlfn.MINIFS($BD$2:$BD$5500,$BF$2:$BF$5500,$BA442,$BG$2:$BG$5500,$BB442) -> 0 | D442: =AVERAGEIFS($BD$2:$BD$5500,$BF$2:$BF$5500,$BA442,$BG$2:$BG$5500,$BB442) -> #DIV/0! | E442: =B442-D442 -> #DIV/0! | F442: =C442-D442 -> #DIV/0! | G442: =Prices!P441-D442 -> #DIV/0! | H442: =(G442/45.9296)*100 -> #DIV/0! | I442: =D442*AQ442 -> #DIV/0! | J442: =(I442/45.9296)*100 -> #DIV/0! | AP442: 39142 | AQ442: 0.85651818 | BA442: =MONTH(A442) -> 3 | BB442: =YEAR(A442) -> 2007 | BC442: #REF! | BD442: #REF! | BF442: =MONTH(BC442) -> #VALUE! | BG442: =YEAR(BC442) -> #VALUE! | BJ442: #REF! | BK442: #REF! | BM442: =MONTH(BJ442) -> #VALUE! | BN442: =YEAR(BJ442) -> #VALUE! | BR442: 38047 | BS442: =MONTH(BR442) -> 3 | BT442: =YEAR(BR442) -> 2004 | BU442: =AVERAGEIFS($BK$3:$BK$5500,$BM$3:$BM$5500,BS442,$BN$3:$BN$5500,BT442) -> #DIV/0!
A443: =Prices!A442 -> 39173 | B443: =_xlfn.MAXIFS($BD$2:$BD$5500,$BF$2:$BF$5500,$BA443,$BG$2:$BG$5500,$BB443) -> 0 | C443: =_xlfn.MINIFS($BD$2:$BD$5500,$BF$2:$BF$5500,$BA443,$BG$2:$BG$5500,$BB443) -> 0 | D443: =AVERAGEIFS($BD$2:$BD$5500,$BF$2:$BF$5500,$BA443,$BG$2:$BG$5500,$BB443) -> #DIV/0! | E443: =B443-D443 -> #DIV/0! | F443: =C443-D443 -> #DIV/0! | G443: =Prices!P442-D443 -> #DIV/0! | H443: =(G443/45.9296)*100 -> #DIV/0! | I443: =D443*AQ443 -> #DIV/0! | J443: =(I443/45.9296)*100 -> #DIV/0! | AP443: 39173 | AQ443: 0.88289524 | BA443: =MONTH(A443) -> 4 | BB443: =YEAR(A443) -> 2007 | BC443: #REF! | BD443: #REF! | BF443: =MONTH(BC443) -> #VALUE! | BG443: =YEAR(BC443) -> #VALUE! | BJ443: #REF! | BK443: #REF! | BM443: =MONTH(BJ443) -> #VALUE! | BN443: =YEAR(BJ443) -> #VALUE! | BR443: 38078 | BS443: =MONTH(BR443) -> 4 | BT443: =YEAR(BR443) -> 2004 | BU443: =AVERAGEIFS($BK$3:$BK$5500,$BM$3:$BM$5500,BS443,$BN$3:$BN$5500,BT443) -> #DIV/0!
A444: =Prices!A443 -> 39203 | B444: =_xlfn.MAXIFS($BD$2:$BD$5500,$BF$2:$BF$5500,$BA444,$BG$2:$BG$5500,$BB444) -> 0 | C444: =_xlfn.MINIFS($BD$2:$BD$5500,$BF$2:$BF$5500,$BA444,$BG$2:$BG$5500,$BB444) -> 0 | D444: =AVERAGEIFS($BD$2:$BD$5500,$BF$2:$BF$5500,$BA444,$BG$2:$BG$5500,$BB444) -> #DIV/0! | E444: =B444-D444 -> #DIV/0! | F444: =C444-D444 -> #DIV/0! | G444: =Prices!P443-D444 -> #DIV/0! | H444: =(G444/45.9296)*100 -> #DIV/0! | I444: =D444*AQ444 -> #DIV/0! | J444: =(I444/45.9296)*100 -> #DIV/0! | AP444: 39203 | AQ444: 0.91392727 | BA444: =MONTH(A444) -> 5 | BB444: =YEAR(A444) -> 2007 | BC444: #REF! | BD444: #REF! | BF444: =MONTH(BC444) -> #VALUE! | BG444: =YEAR(BC444) -> #VALUE! | BJ444: #REF! | BK444: #REF! | BM444: =MONTH(BJ444) -> #VALUE! | BN444: =YEAR(BJ444) -> #VALUE! | BR444: 38108 | BS444: =MONTH(BR444) -> 5 | BT444: =YEAR(BR444) -> 2004 | BU444: =AVERAGEIFS($BK$3:$BK$5500,$BM$3:$BM$5500,BS444,$BN$3:$BN$5500,BT444) -> #DIV/0!
A445: =Prices!A444 -> 39234 | B445: =_xlfn.MAXIFS($BD$2:$BD$5500,$BF$2:$BF$5500,$BA445,$BG$2:$BG$5500,$BB445) -> 0 | C445: =_xlfn.MINIFS($BD$2:$BD$5500,$BF$2:$BF$5500,$BA445,$BG$2:$BG$5500,$BB445) -> 0 | D445: =AVERAGEIFS($BD$2:$BD$5500,$BF$2:$BF$5500,$BA445,$BG$2:$BG$5500,$BB445) -> #DIV/0! | E445: =B445-D445 -> #DIV/0! | F445: =C445-D445 -> #DIV/0! | G445: =Prices!P444-D445 -> #DIV/0! | H445: =(G445/45.9296)*100 -> #DIV/0! | I445: =D445*AQ445 -> #DIV/0! | J445: =(I445/45.9296)*100 -> #DIV/0! | AP445: 39234 | AQ445: 0.93921429 | BA445: =MONTH(A445) -> 6 | BB445: =YEAR(A445) -> 2007 | BC445: #REF! | BD445: #REF! | BF445: =MONTH(BC445) -> #VALUE! | BG445: =YEAR(BC445) -> #VALUE! | BJ445: #REF! | BK445: #REF! | BM445: =MONTH(BJ445) -> #VALUE! | BN445: =YEAR(BJ445) -> #VALUE! | BR445: 38139 | BS445: =MONTH(BR445) -> 6 | BT445: =YEAR(BR445) -> 2004 | BU445: =AVERAGEIFS($BK$3:$BK$5500,$BM$3:$BM$5500,BS445,$BN$3:$BN$5500,BT445) -> #DIV/0!
A446: =Prices!A445 -> 39264 | B446: =_xlfn.MAXIFS($BD$2:$BD$5500,$BF$2:$BF$5500,$BA446,$BG$2:$BG$5500,$BB446) -> 0 | C446: =_xlfn.MINIFS($BD$2:$BD$5500,$BF$2:$BF$5500,$BA446,$BG$2:$BG$5500,$BB446) -> 0 | D446: =AVERAGEIFS($BD$2:$BD$5500,$BF$2:$BF$5500,$BA446,$BG$2:$BG$5500,$BB446) -> #DIV/0! | E446: =B446-D446 -> #DIV/0! | F446: =C446-D446 -> #DIV/0! | G446: =Prices!P445-D446 -> #DIV/0! | H446: =(G446/45.9296)*100 -> #DIV/0! | I446: =D446*AQ446 -> #DIV/0! | J446: =(I446/45.9296)*100 -> #DIV/0! | AP446: 39264 | AQ446: 0.95298095 | BA446: =MONTH(A446) -> 7 | BB446: =YEAR(A446) -> 2007 | BC446: #REF! | BD446: #REF! | BF446: =MONTH(BC446) -> #VALUE! | BG446: =YEAR(BC446) -> #VALUE! | BJ446: #REF! | BK446: #REF! | BM446: =MONTH(BJ446) -> #VALUE! | BN446: =YEAR(BJ446) -> #VALUE! | BR446: 38169 | BS446: =MONTH(BR446) -> 7 | BT446: =YEAR(BR446) -> 2004 | BU446: =AVERAGEIFS($BK$3:$BK$5500,$BM$3:$BM$5500,BS446,$BN$3:$BN$5500,BT446) -> #DIV/0!
A447: =Prices!A446 -> 39295 | B447: =_xlfn.MAXIFS($BD$2:$BD$5500,$BF$2:$BF$5500,$BA447,$BG$2:$BG$5500,$BB447) -> 0 | C447: =_xlfn.MINIFS($BD$2:$BD$5500,$BF$2:$BF$5500,$BA447,$BG$2:$BG$5500,$BB447) -> 0 | D447: =AVERAGEIFS($BD$2:$BD$5500,$BF$2:$BF$5500,$BA447,$BG$2:$BG$5500,$BB447) -> #DIV/0! | E447: =B447-D447 -> #DIV/0! | F447: =C447-D447 -> #DIV/0! | G447: =Prices!P446-D447 -> #DIV/0! | H447: =(G447/45.9296)*100 -> #DIV/0! | I447: =D447*AQ447 -> #DIV/0! | J447: =(I447/45.9296)*100 -> #DIV/0! | AP447: 39295 | AQ447: 0.94521739 | BA447: =MONTH(A447) -> 8 | BB447: =YEAR(A447) -> 2007 | BC447: #REF! | BD447: #REF! | BF447: =MONTH(BC447) -> #VALUE! | BG447: =YEAR(BC447) -> #VALUE! | BJ447: #REF! | BK447: #REF! | BM447: =MONTH(BJ447) -> #VALUE! | BN447: =YEAR(BJ447) -> #VALUE! | BR447: 38200 | BS447: =MONTH(BR447) -> 8 | BT447: =YEAR(BR447) -> 2004 | BU447: =AVERAGEIFS($BK$3:$BK$5500,$BM$3:$BM$5500,BS447,$BN$3:$BN$5500,BT447) -> #DIV/0!
A448: =Prices!A447 -> 39326 | B448: =_xlfn.MAXIFS($BD$2:$BD$5500,$BF$2:$BF$5500,$BA448,$BG$2:$BG$5500,$BB448) -> 0 | C448: =_xlfn.MINIFS($BD$2:$BD$5500,$BF$2:$BF$5500,$BA448,$BG$2:$BG$5500,$BB448) -> 0 | D448: =AVERAGEIFS($BD$2:$BD$5500,$BF$2:$BF$5500,$BA448,$BG$2:$BG$5500,$BB448) -> #DIV/0! | E448: =B448-D448 -> #DIV/0! | F448: =C448-D448 -> #DIV/0! | G448: =Prices!P447-D448 -> #DIV/0! | H448: =(G448/45.9296)*100 -> #DIV/0! | I448: =D448*AQ448 -> #DIV/0! | J448: =(I448/45.9296)*100 -> #DIV/0! | AP448: 39326 | AQ448: 0.97664737 | BA448: =MONTH(A448) -> 9 | BB448: =YEAR(A448) -> 2007 | BC448: #REF! | BD448: #REF! | BF448: =MONTH(BC448) -> #VALUE! | BG448: =YEAR(BC448) -> #VALUE! | BJ448: #REF! | BK448: #REF! | BM448: =MONTH(BJ448) -> #VALUE! | BN448: =YEAR(BJ448) -> #VALUE! | BR448: 38231 | BS448: =MONTH(BR448) -> 9 | BT448: =YEAR(BR448) -> 2004 | BU448: =AVERAGEIFS($BK$3:$BK$5500,$BM$3:$BM$5500,BS448,$BN$3:$BN$5500,BT448) -> #DIV/0!
... A505: =Prices!A504 -> 41061 | B505: =_xlfn.MAXIFS($BD$2:$BD$5500,$BF$2:$BF$5500,$BA505,$BG$2:$BG$5500,$BB505) -> 0 | C505: =_xlfn.MINIFS($BD$2:$BD$5500,$BF$2:$BF$5500,$BA505,$BG$2:$BG$5500,$BB505) -> 0 | D505: =AVERAGEIFS($BD$2:$BD$5500,$BF$2:$BF$5500,$BA505,$BG$2:$BG$5500,$BB505) -> #DIV/0! | E505: =B505-D505 -> #DIV/0! | F505: =C505-D505 -> #DIV/0! | G505: =Prices!P504-D505 -> #DIV/0! | H505: =(G505/45.9296)*100 -> #DIV/0! | I505: =D505*AQ505 -> #DIV/0! | J505: =(I505/45.9296)*100 -> #DIV/0! | AP505: 41061 | AQ505: 0.97158462 | BA505: =MONTH(A505) -> 6 | BB505: =YEAR(A505) -> 2012 | BC505: #REF! | BD505: #REF! | BF505: =MONTH(BC505) -> #VALUE! | BG505: =YEAR(BC505) -> #VALUE! | BJ505: #REF! | BK505: #REF! | BM505: =MONTH(BJ505) -> #VALUE! | BN505: =YEAR(BJ505) -> #VALUE! | BR505: 39965 | BS505: =MONTH(BR505) -> 6 | BT505: =YEAR(BR505) -> 2009 | BU505: =AVERAGEIFS($BK$3:$BK$5500,$BM$3:$BM$5500,BS505,$BN$3:$BN$5500,BT505) -> #DIV/0!
A506: =Prices!A505 -> 41091 | B506: =_xlfn.MAXIFS($BD$2:$BD$5500,$BF$2:$BF$5500,$BA506,$BG$2:$BG$5500,$BB506) -> 0 | C506: =_xlfn.MINIFS($BD$2:$BD$5500,$BF$2:$BF$5500,$BA506,$BG$2:$BG$5500,$BB506) -> 0 | D506: =AVERAGEIFS($BD$2:$BD$5500,$BF$2:$BF$5500,$BA506,$BG$2:$BG$5500,$BB506) -> #DIV/0! | E506: =B506-D506 -> #DIV/0! | F506: =C506-D506 -> #DIV/0! | G506: =Prices!P505-D506 -> #DIV/0! | H506: =(G506/45.9296)*100 -> #DIV/0! | I506: =D506*AQ506 -> #DIV/0! | J506: =(I506/45.9296)*100 -> #DIV/0! | AP506: 41091 | AQ506: =AQ505 -> 0.97158462 | BA506: =MONTH(A506) -> 7 | BB506: =YEAR(A506) -> 2012 | BC506: #REF! | BD506: #REF! | BF506: =MONTH(BC506) -> #VALUE! | BG506: =YEAR(BC506) -> #VALUE! | BJ506: #REF! | BK506: #REF! | BM506: =MONTH(BJ506) -> #VALUE! | BN506: =YEAR(BJ506) -> #VALUE! | BR506: 39995 | BS506: =MONTH(BR506) -> 7 | BT506: =YEAR(BR506) -> 2009 | BU506: =AVERAGEIFS($BK$3:$BK$5500,$BM$3:$BM$5500,BS506,$BN$3:$BN$5500,BT506) -> #DIV/0!
A507: =Prices!A506 -> 41122 | B507: =_xlfn.MAXIFS($BD$2:$BD$5500,$BF$2:$BF$5500,$BA507,$BG$2:$BG$5500,$BB507) -> 0 | C507: =_xlfn.MINIFS($BD$2:$BD$5500,$BF$2:$BF$5500,$BA507,$BG$2:$BG$5500,$BB507) -> 0 | D507: =AVERAGEIFS($BD$2:$BD$5500,$BF$2:$BF$5500,$BA507,$BG$2:$BG$5500,$BB507) -> #DIV/0! | E507: =B507-D507 -> #DIV/0! | F507: =C507-D507 -> #DIV/0! | G507: =Prices!P506-D507 -> #DIV/0! | H507: =(G507/45.9296)*100 -> #DIV/0! | I507: =D507*AQ507 -> #DIV/0! | J507: =(I507/45.9296)*100 -> #DIV/0! | AP507: 41122 | AQ507: 1.0098933 | BA507: =MONTH(A507) -> 8 | BB507: =YEAR(A507) -> 2012 | BC507: #REF! | BD507: #REF! | BF507: =MONTH(BC507) -> #VALUE! | BG507: =YEAR(BC507) -> #VALUE! | BJ507: #REF! | BK507: #REF! | BM507: =MONTH(BJ507) -> #VALUE! | BN507: =YEAR(BJ507) -> #VALUE! | BR507: 40026 | BS507: =MONTH(BR507) -> 8 | BT507: =YEAR(BR507) -> 2009 | BU507: =AVERAGEIFS($BK$3:$BK$5500,$BM$3:$BM$5500,BS507,$BN$3:$BN$5500,BT507) -> #DIV/0!
A508: =Prices!A507 -> 41153 | B508: =_xlfn.MAXIFS($BD$2:$BD$5500,$BF$2:$BF$5500,$BA508,$BG$2:$BG$5500,$BB508) -> 0 | C508: =_xlfn.MINIFS($BD$2:$BD$5500,$BF$2:$BF$5500,$BA508,$BG$2:$BG$5500,$BB508) -> 0 | D508: =AVERAGEIFS($BD$2:$BD$5500,$BF$2:$BF$5500,$BA508,$BG$2:$BG$5500,$BB508) -> #DIV/0! | E508: =B508-D508 -> #DIV/0! | F508: =C508-D508 -> #DIV/0! | G508: =Prices!P507-D508 -> #DIV/0! | H508: =(G508/45.9296)*100 -> #DIV/0! | I508: =D508*AQ508 -> #DIV/0! | J508: =(I508/45.9296)*100 -> #DIV/0! | AP508: 41153 | AQ508: 1.0212211 | BA508: =MONTH(A508) -> 9 | BB508: =YEAR(A508) -> 2012 | BC508: #REF! | BD508: #REF! | BF508: =MONTH(BC508) -> #VALUE! | BG508: =YEAR(BC508) -> #VALUE! | BJ508: #REF! | BK508: #REF! | BM508: =MONTH(BJ508) -> #VALUE! | BN508: =YEAR(BJ508) -> #VALUE! | BR508: 40057 | BS508: =MONTH(BR508) -> 9 | BT508: =YEAR(BR508) -> 2009 | BU508: =AVERAGEIFS($BK$3:$BK$5500,$BM$3:$BM$5500,BS508,$BN$3:$BN$5500,BT508) -> #DIV/0!
A509: =Prices!A508 -> 41183 | B509: =_xlfn.MAXIFS($BD$2:$BD$5500,$BF$2:$BF$5500,$BA509,$BG$2:$BG$5500,$BB509) -> 0 | C509: =_xlfn.MINIFS($BD$2:$BD$5500,$BF$2:$BF$5500,$BA509,$BG$2:$BG$5500,$BB509) -> 0 | D509: =AVERAGEIFS($BD$2:$BD$5500,$BF$2:$BF$5500,$BA509,$BG$2:$BG$5500,$BB509) -> #DIV/0! | E509: =B509-D509 -> #DIV/0! | F509: =C509-D509 -> #DIV/0! | G509: =Prices!P508-D509 -> #DIV/0! | H509: =(G509/45.9296)*100 -> #DIV/0! | I509: =D509*AQ509 -> #DIV/0! | J509: =(I509/45.9296)*100 -> #DIV/0! | AP509: 41183 | AQ509: 1.0117043 | BA509: =MONTH(A509) -> 10 | BB509: =YEAR(A509) -> 2012 | BC509: #REF! | BD509: #REF! | BF509: =MONTH(BC509) -> #VALUE! | BG509: =YEAR(BC509) -> #VALUE! | BJ509: #REF! | BK509: #REF! | BM509: =MONTH(BJ509) -> #VALUE! | BN509: =YEAR(BJ509) -> #VALUE! | BR509: 40087 | BS509: =MONTH(BR509) -> 10 | BT509: =YEAR(BR509) -> 2009 | BU509: =AVERAGEIFS($BK$3:$BK$5500,$BM$3:$BM$5500,BS509,$BN$3:$BN$5500,BT509) -> #DIV/0!
A510: =Prices!A509 -> 41214 | B510: =_xlfn.MAXIFS($BD$2:$BD$5500,$BF$2:$BF$5500,$BA510,$BG$2:$BG$5500,$BB510) -> 0 | C510: =_xlfn.MINIFS($BD$2:$BD$5500,$BF$2:$BF$5500,$BA510,$BG$2:$BG$5500,$BB510) -> 0 | D510: =AVERAGEIFS($BD$2:$BD$5500,$BF$2:$BF$5500,$BA510,$BG$2:$BG$5500,$BB510) -> #DIV/0! | E510: =B510-D510 -> #DIV/0! | F510: =C510-D510 -> #DIV/0! | G510: =Prices!P509-D510 -> #DIV/0! | H510: =(G510/45.9296)*100 -> #DIV/0! | I510: =D510*AQ510 -> #DIV/0! | J510: =(I510/45.9296)*100 -> #DIV/0! | AP510: 41214 | AQ510: 1.0025095 | BA510: =MONTH(A510) -> 11 | BB510: =YEAR(A510) -> 2012 | BC510: #REF! | BD510: #REF! | BF510: =MONTH(BC510) -> #VALUE! | BG510: =YEAR(BC510) -> #VALUE! | BJ510: #REF! | BK510: #REF! | BM510: =MONTH(BJ510) -> #VALUE! | BN510: =YEAR(BJ510) -> #VALUE! | BR510: 40118 | BS510: =MONTH(BR510) -> 11 | BT510: =YEAR(BR510) -> 2009 | BU510: =AVERAGEIFS($BK$3:$BK$5500,$BM$3:$BM$5500,BS510,$BN$3:$BN$5500,BT510) -> #DIV/0!
A511: =Prices!A510 -> 41244 | B511: =_xlfn.MAXIFS($BD$2:$BD$5500,$BF$2:$BF$5500,$BA511,$BG$2:$BG$5500,$BB511) -> 0 | C511: =_xlfn.MINIFS($BD$2:$BD$5500,$BF$2:$BF$5500,$BA511,$BG$2:$BG$5500,$BB511) -> 0 | D511: =AVERAGEIFS($BD$2:$BD$5500,$BF$2:$BF$5500,$BA511,$BG$2:$BG$5500,$BB511) -> #DIV/0! | E511: =B511-D511 -> #DIV/0! | F511: =C511-D511 -> #DIV/0! | G511: =Prices!P510-D511 -> #DIV/0! | H511: =(G511/45.9296)*100 -> #DIV/0! | I511: =D511*AQ511 -> #DIV/0! | J511: =(I511/45.9296)*100 -> #DIV/0! | AP511: 41244 | AQ511: 1.009325 | BA511: =MONTH(A511) -> 12 | BB511: =YEAR(A511) -> 2012 | BC511: #REF! | BD511: #REF! | BF511: =MONTH(BC511) -> #VALUE! | BG511: =YEAR(BC511) -> #VALUE! | BJ511: #REF! | BK511: #REF! | BM511: =MONTH(BJ511) -> #VALUE! | BN511: =YEAR(BJ511) -> #VALUE! | BR511: 40148 | BS511: =MONTH(BR511) -> 12 | BT511: =YEAR(BR511) -> 2009 | BU511: =AVERAGEIFS($BK$3:$BK$5500,$BM$3:$BM$5500,BS511,$BN$3:$BN$5500,BT511) -> #DIV/0!
A512: =Prices!A511 -> 41275 | B512: =_xlfn.MAXIFS($BD$2:$BD$5500,$BF$2:$BF$5500,$BA512,$BG$2:$BG$5500,$BB512) -> 0 | C512: =_xlfn.MINIFS($BD$2:$BD$5500,$BF$2:$BF$5500,$BA512,$BG$2:$BG$5500,$BB512) -> 0 | D512: =AVERAGEIFS($BD$2:$BD$5500,$BF$2:$BF$5500,$BA512,$BG$2:$BG$5500,$BB512) -> #DIV/0! | E512: =B512-D512 -> #DIV/0! | F512: =C512-D512 -> #DIV/0! | G512: =Prices!P511-D512 -> #DIV/0! | H512: =(G512/45.9296)*100 -> #DIV/0! | I512: =D512*AQ512 -> #DIV/0! | J512: =(I512/45.9296)*100 -> #DIV/0! | AP512: 41275 | AQ512: 1.0068238 | BA512: =MONTH(A512) -> 1 | BB512: =YEAR(A512) -> 2013 | BC512: #REF! | BD512: #REF! | BF512: =MONTH(BC512) -> #VALUE! | BG512: =YEAR(BC512) -> #VALUE! | BJ512: #REF! | BK512: #REF! | BM512: =MONTH(BJ512) -> #VALUE! | BN512: =YEAR(BJ512) -> #VALUE! | BR512: 40179 | BS512: =MONTH(BR512) -> 1 | BT512: =YEAR(BR512) -> 2010 | BU512: =AVERAGEIFS($BK$3:$BK$5500,$BM$3:$BM$5500,BS512,$BN$3:$BN$5500,BT512) -> #DIV/0!
A513: =Prices!A512 -> 41306 | B513: =_xlfn.MAXIFS($BD$2:$BD$5500,$BF$2:$BF$5500,$BA513,$BG$2:$BG$5500,$BB513) -> 0 | C513: =_xlfn.MINIFS($BD$2:$BD$5500,$BF$2:$BF$5500,$BA513,$BG$2:$BG$5500,$BB513) -> 0 | D513: =AVERAGEIFS($BD$2:$BD$5500,$BF$2:$BF$5500,$BA513,$BG$2:$BG$5500,$BB513) -> #DIV/0! | E513: =B513-D513 -> #DIV/0! | F513: =C513-D513 -> #DIV/0! | G513: =Prices!P512-D513 -> #DIV/0! | H513: =(G513/45.9296)*100 -> #DIV/0! | I513: =D513*AQ513 -> #DIV/0! | J513: =(I513/45.9296)*100 -> #DIV/0! | AP513: 41306 | AQ513: 0.98975263 | BA513: =MONTH(A513) -> 2 | BB513: =YEAR(A513) -> 2013 | BC513: #REF! | BD513: #REF! | BF513: =MONTH(BC513) -> #VALUE! | BG513: =YEAR(BC513) -> #VALUE! | BJ513: #REF! | BK513: #REF! | BM513: =MONTH(BJ513) -> #VALUE! | BN513: =YEAR(BJ513) -> #VALUE! | BR513: 40210 | BS513: =MONTH(BR513) -> 2 | BT513: =YEAR(BR513) -> 2010 | BU513: =AVERAGEIFS($BK$3:$BK$5500,$BM$3:$BM$5500,BS513,$BN$3:$BN$5500,BT513) -> #DIV/0!
A514: =Prices!A513 -> 41334 | B514: =_xlfn.MAXIFS($BD$2:$BD$5500,$BF$2:$BF$5500,$BA514,$BG$2:$BG$5500,$BB514) -> 0 | C514: =_xlfn.MINIFS($BD$2:$BD$5500,$BF$2:$BF$5500,$BA514,$BG$2:$BG$5500,$BB514) -> 0 | D514: =AVERAGEIFS($BD$2:$BD$5500,$BF$2:$BF$5500,$BA514,$BG$2:$BG$5500,$BB514) -> #DIV/0! | E514: =B514-D514 -> #DIV/0! | F514: =C514-D514 -> #DIV/0! | G514: =Prices!P513-D514 -> #DIV/0! | H514: =(G514/45.9296)*100 -> #DIV/0! | I514: =D514*AQ514 -> #DIV/0! | J514: =(I514/45.9296)*100 -> #DIV/0! | AP514: 41334 | AQ514: 0.97562 | BA514: =MONTH(A514) -> 3 | BB514: =YEAR(A514) -> 2013 | BC514: #REF! | BD514: #REF! | BF514: =MONTH(BC514) -> #VALUE! | BG514: =YEAR(BC514) -> #VALUE! | BJ514: #REF! | BK514: #REF! | BM514: =MONTH(BJ514) -> #VALUE! | BN514: =YEAR(BJ514) -> #VALUE! | BR514: 40238 | BS514: =MONTH(BR514) -> 3 | BT514: =YEAR(BR514) -> 2010 | BU514: =AVERAGEIFS($BK$3:$BK$5500,$BM$3:$BM$5500,BS514,$BN$3:$BN$5500,BT514) -> #DIV/0!
A515: =Prices!A514 -> 41365 | B515: =_xlfn.MAXIFS($BD$2:$BD$5500,$BF$2:$BF$5500,$BA515,$BG$2:$BG$5500,$BB515) -> 0 | C515: =_xlfn.MINIFS($BD$2:$BD$5500,$BF$2:$BF$5500,$BA515,$BG$2:$BG$5500,$BB515) -> 0 | D515: =AVERAGEIFS($BD$2:$BD$5500,$BF$2:$BF$5500,$BA515,$BG$2:$BG$5500,$BB515) -> #DIV/0! | E515: =B515-D515 -> #DIV/0! | F515: =C515-D515 -> #DIV/0! | G515: =Prices!P514-D515 -> #DIV/0! | H515: =(G515/45.9296)*100 -> #DIV/0! | I515: =D515*AQ515 -> #DIV/0! | J515: =(I515/45.9296)*100 -> #DIV/0! | AP515: 41365 | AQ515: 0.98044545 | BA515: =MONTH(A515) -> 4 | BB515: =YEAR(A515) -> 2013 | BC515: #REF! | BD515: #REF! | BF515: =MONTH(BC515) -> #VALUE! | BG515: =YEAR(BC515) -> #VALUE! | BJ515: #REF! | BK515: #REF! | BM515: =MONTH(BJ515) -> #VALUE! | BN515: =YEAR(BJ515) -> #VALUE! | BR515: 40269 | BS515: =MONTH(BR515) -> 4 | BT515: =YEAR(BR515) -> 2010 | BU515: =AVERAGEIFS($BK$3:$BK$5500,$BM$3:$BM$5500,BS515,$BN$3:$BN$5500,BT515) -> #DIV/0!
A516: =Prices!A515 -> 41395 | B516: =_xlfn.MAXIFS($BD$2:$BD$5500,$BF$2:$BF$5500,$BA516,$BG$2:$BG$5500,$BB516) -> 0 | C516: =_xlfn.MINIFS($BD$2:$BD$5500,$BF$2:$BF$5500,$BA516,$BG$2:$BG$5500,$BB516) -> 0 | D516: =AVERAGEIFS($BD$2:$BD$5500,$BF$2:$BF$5500,$BA516,$BG$2:$BG$5500,$BB516) -> #DIV/0! | E516: =B516-D516 -> #DIV/0! | F516: =C516-D516 -> #DIV/0! | G516: =Prices!P515-D516 -> #DIV/0! | H516: =(G516/45.9296)*100 -> #DIV/0! | I516: =D516*AQ516 -> #DIV/0! | J516: =(I516/45.9296)*100 -> #DIV/0! | AP516: 41395 | AQ516: 0.97979545 | BA516: =MONTH(A516) -> 5 | BB516: =YEAR(A516) -> 2013 | BC516: #REF! | BD516: #REF! | BF516: =MONTH(BC516) -> #VALUE! | BG516: =YEAR(BC516) -> #VALUE! | BJ516: #REF! | BK516: #REF! | BM516: =MONTH(BJ516) -> #VALUE! | BN516: =YEAR(BJ516) -> #VALUE! | BR516: 40299 | BS516: =MONTH(BR516) -> 5 | BT516: =YEAR(BR516) -> 2010 | BU516: =AVERAGEIFS($BK$3:$BK$5500,$BM$3:$BM$5500,BS516,$BN$3:$BN$5500,BT516) -> #DIV/0!
A517: =Prices!A516 -> 41426 | B517: =_xlfn.MAXIFS($BD$2:$BD$5500,$BF$2:$BF$5500,$BA517,$BG$2:$BG$5500,$BB517) -> 0 | C517: =_xlfn.MINIFS($BD$2:$BD$5500,$BF$2:$BF$5500,$BA517,$BG$2:$BG$5500,$BB517) -> 0 | D517: =AVERAGEIFS($BD$2:$BD$5500,$BF$2:$BF$5500,$BA517,$BG$2:$BG$5500,$BB517) -> #DIV/0! | E517: =B517-D517 -> #DIV/0! | F517: =C517-D517 -> #DIV/0! | G517: =Prices!P516-D517 -> #DIV/0! | H517: =(G517/45.9296)*100 -> #DIV/0! | I517: =D517*AQ517 -> #DIV/0! | J517: =(I517/45.9296)*100 -> #DIV/0! | AP517: 41426 | AQ517: 0.968165 | BA517: =MONTH(A517) -> 6 | BB517: =YEAR(A517) -> 2013 | BC517: #REF! | BD517: #REF! | BF517: =MONTH(BC517) -> #VALUE! | BG517: =YEAR(BC517) -> #VALUE! | BJ517: #REF! | BK517: #REF! | BM517: =MONTH(BJ517) -> #VALUE! | BN517: =YEAR(BJ517) -> #VALUE! | BR517: 40330 | BS517: =MONTH(BR517) -> 6 | BT517: =YEAR(BR517) -> 2010 | BU517: =AVERAGEIFS($BK$3:$BK$5500,$BM$3:$BM$5500,BS517,$BN$3:$BN$5500,BT517) -> #DIV/0!
A518: =Prices!A517 -> 41456 | B518: =_xlfn.MAXIFS($BD$2:$BD$5500,$BF$2:$BF$5500,$BA518,$BG$2:$BG$5500,$BB518) -> 0 | C518: =_xlfn.MINIFS($BD$2:$BD$5500,$BF$2:$BF$5500,$BA518,$BG$2:$BG$5500,$BB518) -> 0 | D518: =AVERAGEIFS($BD$2:$BD$5500,$BF$2:$BF$5500,$BA518,$BG$2:$BG$5500,$BB518) -> #DIV/0! | E518: =B518-D518 -> #DIV/0! | F518: =C518-D518 -> #DIV/0! | G518: =Prices!P517-D518 -> #DIV/0! | H518: =(G518/45.9296)*100 -> #DIV/0! | I518: =D518*AQ518 -> #DIV/0! | J518: =(I518/45.9296)*100 -> #DIV/0! | AP518: 41456 | AQ518: 0.96025909 | BA518: =MONTH(A518) -> 7 | BB518: =YEAR(A518) -> 2013 | BC518: #REF! | BD518: #REF! | BF518: =MONTH(BC518) -> #VALUE! | BG518: =YEAR(BC518) -> #VALUE! | BJ518: #REF! | BK518: #REF! | BM518: =MONTH(BJ518) -> #VALUE! | BN518: =YEAR(BJ518) -> #VALUE! | BR518: 40360 | BS518: =MONTH(BR518) -> 7 | BT518: =YEAR(BR518) -> 2010 | BU518: =AVERAGEIFS($BK$3:$BK$5500,$BM$3:$BM$5500,BS518,$BN$3:$BN$5500,BT518) -> #DIV/0!
... A569: =Prices!A568 -> 43009 | B569: =_xlfn.MAXIFS($BD$2:$BD$5500,$BF$2:$BF$5500,$BA569,$BG$2:$BG$5500,$BB569) -> 0 | C569: =_xlfn.MINIFS($BD$2:$BD$5500,$BF$2:$BF$5500,$BA569,$BG$2:$BG$5500,$BB569) -> 0 | D569: =AVERAGEIFS($BD$2:$BD$5500,$BF$2:$BF$5500,$BA569,$BG$2:$BG$5500,$BB569) -> #DIV/0! | E569: =B569-D569 -> #DIV/0! | F569: =C569-D569 -> #DIV/0! | G569: =Prices!P568-D569 -> #DIV/0! | H569: =(G569/45.9296)*100 -> #DIV/0! | I569: =D569*AQ569 -> #DIV/0! | J569: =(I569/45.9296)*100 -> #DIV/0! | AP569: 43009 | AQ569: 0.79365 | BA569: =MONTH(A569) -> 10 | BB569: =YEAR(A569) -> 2017 | BC569: #REF! | BD569: #REF! | BF569: =MONTH(BC569) -> #VALUE! | BG569: =YEAR(BC569) -> #VALUE! | BJ569: #REF! | BK569: #REF! | BM569: =MONTH(BJ569) -> #VALUE! | BN569: =YEAR(BJ569) -> #VALUE! | BR569: 41913 | BS569: =MONTH(BR569) -> 10 | BT569: =YEAR(BR569) -> 2014 | BU569: =AVERAGEIFS($BK$3:$BK$5500,$BM$3:$BM$5500,BS569,$BN$3:$BN$5500,BT569) -> #DIV/0!
A570: =Prices!A569 -> 43040 | B570: =_xlfn.MAXIFS($BD$2:$BD$5500,$BF$2:$BF$5500,$BA570,$BG$2:$BG$5500,$BB570) -> 0 | C570: =_xlfn.MINIFS($BD$2:$BD$5500,$BF$2:$BF$5500,$BA570,$BG$2:$BG$5500,$BB570) -> 0 | D570: =AVERAGEIFS($BD$2:$BD$5500,$BF$2:$BF$5500,$BA570,$BG$2:$BG$5500,$BB570) -> #DIV/0! | E570: =B570-D570 -> #DIV/0! | F570: =C570-D570 -> #DIV/0! | G570: =Prices!P569-D570 -> #DIV/0! | H570: =(G570/45.9296)*100 -> #DIV/0! | I570: =D570*AQ570 -> #DIV/0! | J570: =(I570/45.9296)*100 -> #DIV/0! | L570: ='[4]Brazil Corn Price'!$DR217 -> 0 | M570: ='[4]Brazil Corn Price'!$DS217 -> 0 | N570: ='[4]Brazil Corn Price'!$DQ217 -> 0 | O570: =L570-N570 -> 0 | P570: =M570-N570 -> 0 | AP570: 43040 | AQ570: 0.78330952 | BA570: =MONTH(A570) -> 11 | BB570: =YEAR(A570) -> 2017 | BC570: #REF! | BD570: #REF! | BF570: =MONTH(BC570) -> #VALUE! | BG570: =YEAR(BC570) -> #VALUE! | BJ570: #REF! | BK570: #REF! | BM570: =MONTH(BJ570) -> #VALUE! | BN570: =YEAR(BJ570) -> #VALUE! | BR570: 41944 | BS570: =MONTH(BR570) -> 11 | BT570: =YEAR(BR570) -> 2014 | BU570: =AVERAGEIFS($BK$3:$BK$5500,$BM$3:$BM$5500,BS570,$BN$3:$BN$5500,BT570) -> #DIV/0!
A571: =Prices!A570 -> 43070 | B571: =_xlfn.MAXIFS($BD$2:$BD$5500,$BF$2:$BF$5500,$BA571,$BG$2:$BG$5500,$BB571) -> 0 | C571: =_xlfn.MINIFS($BD$2:$BD$5500,$BF$2:$BF$5500,$BA571,$BG$2:$BG$5500,$BB571) -> 0 | D571: =AVERAGEIFS($BD$2:$BD$5500,$BF$2:$BF$5500,$BA571,$BG$2:$BG$5500,$BB571) -> #DIV/0! | E571: =B571-D571 -> #DIV/0! | F571: =C571-D571 -> #DIV/0! | G571: =Prices!P570-D571 -> #DIV/0! | H571: =(G571/45.9296)*100 -> #DIV/0! | I571: =D571*AQ571 -> #DIV/0! | J571: =(I571/45.9296)*100 -> #DIV/0! | L571: ='[4]Brazil Corn Price'!$DR218 -> 0 | M571: ='[4]Brazil Corn Price'!$DS218 -> 0 | N571: ='[4]Brazil Corn Price'!$DQ218 -> 0 | O571: =L571-N571 -> 0 | P571: =M571-N571 -> 0 | AP571: 43070 | AQ571: 0.783825 | BA571: =MONTH(A571) -> 12 | BB571: =YEAR(A571) -> 2017 | BC571: #REF! | BD571: #REF! | BF571: =MONTH(BC571) -> #VALUE! | BG571: =YEAR(BC571) -> #VALUE! | BJ571: #REF! | BK571: #REF! | BM571: =MONTH(BJ571) -> #VALUE! | BN571: =YEAR(BJ571) -> #VALUE! | BR571: 41974 | BS571: =MONTH(BR571) -> 12 | BT571: =YEAR(BR571) -> 2014 | BU571: =AVERAGEIFS($BK$3:$BK$5500,$BM$3:$BM$5500,BS571,$BN$3:$BN$5500,BT571) -> #DIV/0!
A572: =Prices!A571 -> 43101 | B572: =_xlfn.MAXIFS($BD$2:$BD$5500,$BF$2:$BF$5500,$BA572,$BG$2:$BG$5500,$BB572) -> 0 | C572: =_xlfn.MINIFS($BD$2:$BD$5500,$BF$2:$BF$5500,$BA572,$BG$2:$BG$5500,$BB572) -> 0 | D572: =AVERAGEIFS($BD$2:$BD$5500,$BF$2:$BF$5500,$BA572,$BG$2:$BG$5500,$BB572) -> #DIV/0! | E572: =B572-D572 -> #DIV/0! | F572: =C572-D572 -> #DIV/0! | G572: =Prices!P571-D572 -> #DIV/0! | H572: =(G572/45.9296)*100 -> #DIV/0! | I572: =D572*AQ572 -> #DIV/0! | J572: =(I572/45.9296)*100 -> #DIV/0! | L572: ='[4]Brazil Corn Price'!$DR219 -> 0 | M572: ='[4]Brazil Corn Price'!$DS219 -> 0 | N572: ='[4]Brazil Corn Price'!$DQ219 -> 0 | O572: =L572-N572 -> 0 | P572: =M572-N572 -> 0 | AP572: 43101 | AQ572: 0.80482381 | BA572: =MONTH(A572) -> 1 | BB572: =YEAR(A572) -> 2018 | BC572: #REF! | BD572: #REF! | BF572: =MONTH(BC572) -> #VALUE! | BG572: =YEAR(BC572) -> #VALUE! | BJ572: #REF! | BK572: #REF! | BM572: =MONTH(BJ572) -> #VALUE! | BN572: =YEAR(BJ572) -> #VALUE! | BR572: 42005 | BS572: =MONTH(BR572) -> 1 | BT572: =YEAR(BR572) -> 2015 | BU572: =AVERAGEIFS($BK$3:$BK$5500,$BM$3:$BM$5500,BS572,$BN$3:$BN$5500,BT572) -> #DIV/0!
A573: =Prices!A572 -> 43132 | B573: =_xlfn.MAXIFS($BD$2:$BD$5500,$BF$2:$BF$5500,$BA573,$BG$2:$BG$5500,$BB573) -> 0 | C573: =_xlfn.MINIFS($BD$2:$BD$5500,$BF$2:$BF$5500,$BA573,$BG$2:$BG$5500,$BB573) -> 0 | D573: =AVERAGEIFS($BD$2:$BD$5500,$BF$2:$BF$5500,$BA573,$BG$2:$BG$5500,$BB573) -> #DIV/0! | E573: =B573-D573 -> #DIV/0! | F573: =C573-D573 -> #DIV/0! | G573: =Prices!P572-D573 -> #DIV/0! | H573: =(G573/45.9296)*100 -> #DIV/0! | I573: =D573*AQ573 -> #DIV/0! | J573: =(I573/45.9296)*100 -> #DIV/0! | L573: ='[4]Brazil Corn Price'!$DR220 -> 0 | M573: ='[4]Brazil Corn Price'!$DS220 -> 0 | N573: ='[4]Brazil Corn Price'!$DQ220 -> 0 | O573: =L573-N573 -> 0 | P573: =M573-N573 -> 0 | AP573: 43132 | AQ573: 0.79462368 | BA573: =MONTH(A573) -> 2 | BB573: =YEAR(A573) -> 2018 | BC573: #REF! | BD573: #REF! | BF573: =MONTH(BC573) -> #VALUE! | BG573: =YEAR(BC573) -> #VALUE! | BJ573: #REF! | BK573: #REF! | BM573: =MONTH(BJ573) -> #VALUE! | BN573: =YEAR(BJ573) -> #VALUE! | BR573: 42036 | BS573: =MONTH(BR573) -> 2 | BT573: =YEAR(BR573) -> 2015 | BU573: =AVERAGEIFS($BK$3:$BK$5500,$BM$3:$BM$5500,BS573,$BN$3:$BN$5500,BT573) -> #DIV/0!
A574: =Prices!A573 -> 43160 | B574: =_xlfn.MAXIFS($BD$2:$BD$5500,$BF$2:$BF$5500,$BA574,$BG$2:$BG$5500,$BB574) -> 0 | C574: =_xlfn.MINIFS($BD$2:$BD$5500,$BF$2:$BF$5500,$BA574,$BG$2:$BG$5500,$BB574) -> 0 | D574: =AVERAGEIFS($BD$2:$BD$5500,$BF$2:$BF$5500,$BA574,$BG$2:$BG$5500,$BB574) -> #DIV/0! | E574: =B574-D574 -> #DIV/0! | F574: =C574-D574 -> #DIV/0! | G574: =Prices!P573-D574 -> #DIV/0! | H574: =(G574/45.9296)*100 -> #DIV/0! | I574: =D574*AQ574 -> #DIV/0! | J574: =(I574/45.9296)*100 -> #DIV/0! | L574: ='[4]Brazil Corn Price'!$DR221 -> 0 | M574: ='[4]Brazil Corn Price'!$DS221 -> 0 | N574: ='[4]Brazil Corn Price'!$DQ221 -> 0 | O574: =L574-N574 -> 0 | P574: =M574-N574 -> 0 | AP574: 43160 | AQ574: 0.77349286 | BA574: =MONTH(A574) -> 3 | BB574: =YEAR(A574) -> 2018 | BC574: #REF! | BD574: #REF! | BF574: =MONTH(BC574) -> #VALUE! | BG574: =YEAR(BC574) -> #VALUE! | BJ574: #REF! | BK574: #REF! | BM574: =MONTH(BJ574) -> #VALUE! | BN574: =YEAR(BJ574) -> #VALUE! | BR574: 42064 | BS574: =MONTH(BR574) -> 3 | BT574: =YEAR(BR574) -> 2015 | BU574: =AVERAGEIFS($BK$3:$BK$5500,$BM$3:$BM$5500,BS574,$BN$3:$BN$5500,BT574) -> #DIV/0!
A575: =Prices!A574 -> 43191 | B575: =_xlfn.MAXIFS($BD$2:$BD$5500,$BF$2:$BF$5500,$BA575,$BG$2:$BG$5500,$BB575) -> 0 | C575: =_xlfn.MINIFS($BD$2:$BD$5500,$BF$2:$BF$5500,$BA575,$BG$2:$BG$5500,$BB575) -> 0 | D575: =AVERAGEIFS($BD$2:$BD$5500,$BF$2:$BF$5500,$BA575,$BG$2:$BG$5500,$BB575) -> #DIV/0! | E575: =B575-D575 -> #DIV/0! | F575: =C575-D575 -> #DIV/0! | G575: =Prices!P574-D575 -> #DIV/0! | H575: =(G575/45.9296)*100 -> #DIV/0! | I575: =D575*AQ575 -> #DIV/0! | J575: =(I575/45.9296)*100 -> #DIV/0! | L575: ='[4]Brazil Corn Price'!$DR222 -> 0 | M575: ='[4]Brazil Corn Price'!$DS222 -> 0 | N575: ='[4]Brazil Corn Price'!$DQ222 -> 0 | O575: =L575-N575 -> 0 | P575: =M575-N575 -> 0 | AP575: 43191 | AQ575: 0.78561429 | BA575: =MONTH(A575) -> 4 | BB575: =YEAR(A575) -> 2018 | BC575: #REF! | BD575: #REF! | BF575: =MONTH(BC575) -> #VALUE! | BG575: =YEAR(BC575) -> #VALUE! | BJ575: #REF! | BK575: #REF! | BM575: =MONTH(BJ575) -> #VALUE! | BN575: =YEAR(BJ575) -> #VALUE! | BR575: 42095 | BS575: =MONTH(BR575) -> 4 | BT575: =YEAR(BR575) -> 2015 | BU575: =AVERAGEIFS($BK$3:$BK$5500,$BM$3:$BM$5500,BS575,$BN$3:$BN$5500,BT575) -> #DIV/0!
A576: =Prices!A575 -> 43221 | B576: =_xlfn.MAXIFS($BD$2:$BD$5500,$BF$2:$BF$5500,$BA576,$BG$2:$BG$5500,$BB576) -> 0 | C576: =_xlfn.MINIFS($BD$2:$BD$5500,$BF$2:$BF$5500,$BA576,$BG$2:$BG$5500,$BB576) -> 0 | D576: =AVERAGEIFS($BD$2:$BD$5500,$BF$2:$BF$5500,$BA576,$BG$2:$BG$5500,$BB576) -> #DIV/0! | E576: =B576-D576 -> #DIV/0! | F576: =C576-D576 -> #DIV/0! | G576: =Prices!P575-D576 -> #DIV/0! | H576: =(G576/45.9296)*100 -> #DIV/0! | I576: =D576*AQ576 -> #DIV/0! | J576: =(I576/45.9296)*100 -> #DIV/0! | L576: ='[4]Brazil Corn Price'!$DR223 -> 0 | M576: ='[4]Brazil Corn Price'!$DS223 -> 0 | N576: ='[4]Brazil Corn Price'!$DQ223 -> 0 | O576: =L576-N576 -> 0 | P576: =M576-N576 -> 0 | AP576: 43221 | AQ576: 0.77769318 | BA576: =MONTH(A576) -> 5 | BB576: =YEAR(A576) -> 2018 | BC576: #REF! | BD576: #REF! | BF576: =MONTH(BC576) -> #VALUE! | BG576: =YEAR(BC576) -> #VALUE! | BJ576: #REF! | BK576: #REF! | BM576: =MONTH(BJ576) -> #VALUE! | BN576: =YEAR(BJ576) -> #VALUE! | BR576: 42125 | BS576: =MONTH(BR576) -> 5 | BT576: =YEAR(BR576) -> 2015 | BU576: =AVERAGEIFS($BK$3:$BK$5500,$BM$3:$BM$5500,BS576,$BN$3:$BN$5500,BT576) -> #DIV/0!
A577: =Prices!A576 -> 43252 | B577: =_xlfn.MAXIFS($BD$2:$BD$5500,$BF$2:$BF$5500,$BA577,$BG$2:$BG$5500,$BB577) -> 0 | C577: =_xlfn.MINIFS($BD$2:$BD$5500,$BF$2:$BF$5500,$BA577,$BG$2:$BG$5500,$BB577) -> 0 | D577: =AVERAGEIFS($BD$2:$BD$5500,$BF$2:$BF$5500,$BA577,$BG$2:$BG$5500,$BB577) -> #DIV/0! | E577: =B577-D577 -> #DIV/0! | F577: =C577-D577 -> #DIV/0! | G577: =Prices!P576-D577 -> #DIV/0! | H577: =(G577/45.9296)*100 -> #DIV/0! | I577: =D577*AQ577 -> #DIV/0! | J577: =(I577/45.9296)*100 -> #DIV/0! | L577: ='[4]Brazil Corn Price'!$DR224 -> 0 | M577: ='[4]Brazil Corn Price'!$DS224 -> 0 | N577: ='[4]Brazil Corn Price'!$DQ224 -> 0 | O577: =L577-N577 -> 0 | P577: =M577-N577 -> 0 | AP577: 43252 | AQ577: 0.76184048 | BA577: =MONTH(A577) -> 6 | BB577: =YEAR(A577) -> 2018 | BC577: #REF! | BD577: #REF! | BF577: =MONTH(BC577) -> #VALUE! | BG577: =YEAR(BC577) -> #VALUE! | BJ577: #REF! | BK577: #REF! | BM577: =MONTH(BJ577) -> #VALUE! | BN577: =YEAR(BJ577) -> #VALUE! | BR577: 42156 | BS577: =MONTH(BR577) -> 6 | BT577: =YEAR(BR577) -> 2015 | BU577: =AVERAGEIFS($BK$3:$BK$5500,$BM$3:$BM$5500,BS577,$BN$3:$BN$5500,BT577) -> #DIV/0!
A578: =Prices!A577 -> 43282 | B578: =_xlfn.MAXIFS($BD$2:$BD$5500,$BF$2:$BF$5500,$BA578,$BG$2:$BG$5500,$BB578) -> 0 | C578: =_xlfn.MINIFS($BD$2:$BD$5500,$BF$2:$BF$5500,$BA578,$BG$2:$BG$5500,$BB578) -> 0 | D578: =AVERAGEIFS($BD$2:$BD$5500,$BF$2:$BF$5500,$BA578,$BG$2:$BG$5500,$BB578) -> #DIV/0! | E578: =B578-D578 -> #DIV/0! | F578: =C578-D578 -> #DIV/0! | G578: =Prices!P577-D578 -> #DIV/0! | H578: =(G578/45.9296)*100 -> #DIV/0! | I578: =D578*AQ578 -> #DIV/0! | J578: =(I578/45.9296)*100 -> #DIV/0! | L578: ='[4]Brazil Corn Price'!$DR225 -> 0 | M578: ='[4]Brazil Corn Price'!$DS225 -> 0 | N578: ='[4]Brazil Corn Price'!$DQ225 -> 0 | O578: =L578-N578 -> 0 | P578: =M578-N578 -> 0 | AP578: 43282 | AQ578: 0.76159286 | BA578: =MONTH(A578) -> 7 | BB578: =YEAR(A578) -> 2018 | BC578: #REF! | BD578: #REF! | BF578: =MONTH(BC578) -> #VALUE! | BG578: =YEAR(BC578) -> #VALUE! | BJ578: #REF! | BK578: #REF! | BM578: =MONTH(BJ578) -> #VALUE! | BN578: =YEAR(BJ578) -> #VALUE! | BR578: 42186 | BS578: =MONTH(BR578) -> 7 | BT578: =YEAR(BR578) -> 2015 | BU578: =AVERAGEIFS($BK$3:$BK$5500,$BM$3:$BM$5500,BS578,$BN$3:$BN$5500,BT578) -> #DIV/0!
A579: =Prices!A578 -> 43313 | B579: =_xlfn.MAXIFS($BD$2:$BD$5500,$BF$2:$BF$5500,$BA579,$BG$2:$BG$5500,$BB579) -> 0 | C579: =_xlfn.MINIFS($BD$2:$BD$5500,$BF$2:$BF$5500,$BA579,$BG$2:$BG$5500,$BB579) -> 0 | D579: =AVERAGEIFS($BD$2:$BD$5500,$BF$2:$BF$5500,$BA579,$BG$2:$BG$5500,$BB579) -> #DIV/0! | E579: =B579-D579 -> #DIV/0! | F579: =C579-D579 -> #DIV/0! | G579: =Prices!P578-D579 -> #DIV/0! | H579: =(G579/45.9296)*100 -> #DIV/0! | I579: =D579*AQ579 -> #DIV/0! | J579: =(I579/45.9296)*100 -> #DIV/0! | L579: ='[4]Brazil Corn Price'!$DR226 -> 0 | M579: ='[4]Brazil Corn Price'!$DS226 -> 0 | N579: ='[4]Brazil Corn Price'!$DQ226 -> 0 | O579: =L579-N579 -> 0 | P579: =M579-N579 -> 0 | AP579: 43313 | AQ579: 0.76712174 | BA579: =MONTH(A579) -> 8 | BB579: =YEAR(A579) -> 2018 | BC579: #REF! | BD579: #REF! | BF579: =MONTH(BC579) -> #VALUE! | BG579: =YEAR(BC579) -> #VALUE! | BJ579: #REF! | BK579: #REF! | BM579: =MONTH(BJ579) -> #VALUE! | BN579: =YEAR(BJ579) -> #VALUE! | BR579: 42217 | BS579: =MONTH(BR579) -> 8 | BT579: =YEAR(BR579) -> 2015 | BU579: =AVERAGEIFS($BK$3:$BK$5500,$BM$3:$BM$5500,BS579,$BN$3:$BN$5500,BT579) -> #DIV/0!
A580: =Prices!A579 -> 43344 | B580: =_xlfn.MAXIFS($BD$2:$BD$5500,$BF$2:$BF$5500,$BA580,$BG$2:$BG$5500,$BB580) -> 0 | C580: =_xlfn.MINIFS($BD$2:$BD$5500,$BF$2:$BF$5500,$BA580,$BG$2:$BG$5500,$BB580) -> 0 | D580: =AVERAGEIFS($BD$2:$BD$5500,$BF$2:$BF$5500,$BA580,$BG$2:$BG$5500,$BB580) -> #DIV/0! | E580: =B580-D580 -> #DIV/0! | F580: =C580-D580 -> #DIV/0! | G580: =Prices!P579-D580 -> #DIV/0! | H580: =(G580/45.9296)*100 -> #DIV/0! | I580: =D580*AQ580 -> #DIV/0! | J580: =(I580/45.9296)*100 -> #DIV/0! | L580: ='[4]Brazil Corn Price'!$DR227 -> 0 | M580: ='[4]Brazil Corn Price'!$DS227 -> 0 | N580: ='[4]Brazil Corn Price'!$DQ227 -> 0 | O580: =L580-N580 -> 0 | P580: =M580-N580 -> 0 | AP580: 43344 | AQ580: 0.76763158 | BA580: =MONTH(A580) -> 9 | BB580: =YEAR(A580) -> 2018 | BC580: #REF! | BD580: #REF! | BF580: =MONTH(BC580) -> #VALUE! | BG580: =YEAR(BC580) -> #VALUE! | BJ580: #REF! | BK580: #REF! | BM580: =MONTH(BJ580) -> #VALUE! | BN580: =YEAR(BJ580) -> #VALUE! | BR580: 42248 | BS580: =MONTH(BR580) -> 9 | BT580: =YEAR(BR580) -> 2015 | BU580: =AVERAGEIFS($BK$3:$BK$5500,$BM$3:$BM$5500,BS580,$BN$3:$BN$5500,BT580) -> #DIV/0!
A581: =Prices!A580 -> 43374 | B581: =_xlfn.MAXIFS($BD$2:$BD$5500,$BF$2:$BF$5500,$BA581,$BG$2:$BG$5500,$BB581) -> 0 | C581: =_xlfn.MINIFS($BD$2:$BD$5500,$BF$2:$BF$5500,$BA581,$BG$2:$BG$5500,$BB581) -> 0 | D581: =AVERAGEIFS($BD$2:$BD$5500,$BF$2:$BF$5500,$BA581,$BG$2:$BG$5500,$BB581) -> #DIV/0! | E581: =B581-D581 -> #DIV/0! | F581: =C581-D581 -> #DIV/0! | G581: =Prices!P580-D581 -> #DIV/0! | H581: =(G581/45.9296)*100 -> #DIV/0! | I581: =D581*AQ581 -> #DIV/0! | J581: =(I581/45.9296)*100 -> #DIV/0! | L581: ='[4]Brazil Corn Price'!$DR228 -> 0 | M581: ='[4]Brazil Corn Price'!$DS228 -> 0 | N581: ='[4]Brazil Corn Price'!$DQ228 -> 0 | O581: =L581-N581 -> 0 | P581: =M581-N581 -> 0 | AP581: 43374 | AQ581: 0.7688 | BA581: =MONTH(A581) -> 10 | BB581: =YEAR(A581) -> 2018 | BC581: #REF! | BD581: #REF! | BF581: =MONTH(BC581) -> #VALUE! | BG581: =YEAR(BC581) -> #VALUE! | BJ581: #REF! | BK581: #REF! | BM581: =MONTH(BJ581) -> #VALUE! | BN581: =YEAR(BJ581) -> #VALUE! | BR581: 42278 | BS581: =MONTH(BR581) -> 10 | BT581: =YEAR(BR581) -> 2015 | BU581: =AVERAGEIFS($BK$3:$BK$5500,$BM$3:$BM$5500,BS581,$BN$3:$BN$5500,BT581) -> #DIV/0!
... A633: =Prices!A632 -> 44958 | B633: =_xlfn.MAXIFS($BD$2:$BD$5500,$BF$2:$BF$5500,$BA633,$BG$2:$BG$5500,$BB633) -> 0 | C633: =_xlfn.MINIFS($BD$2:$BD$5500,$BF$2:$BF$5500,$BA633,$BG$2:$BG$5500,$BB633) -> 0 | D633: =AVERAGEIFS($BD$2:$BD$5500,$BF$2:$BF$5500,$BA633,$BG$2:$BG$5500,$BB633) -> #DIV/0! | E633: =B633-D633 -> #DIV/0! | F633: =C633-D633 -> #DIV/0! | G633: =Prices!P632-D633 -> #DIV/0! | H633: =(G633/45.9296)*100 -> #DIV/0! | I633: =D633*AQ633 -> #DIV/0! | J633: =(I633/45.9296)*100 -> #DIV/0! | L633: ='[4]Brazil Corn Price'!$DR280 -> 0 | M633: ='[4]Brazil Corn Price'!$DS280 -> 0 | N633: ='[4]Brazil Corn Price'!$DQ280 -> 0 | O633: =L633-N633 -> 0 | P633: =M633-N633 -> 0 | AP633: 44958 | AQ633: 0.74366842 | BA633: =MONTH(A633) -> 2 | BB633: =YEAR(A633) -> 2023 | BC633: #REF! | BD633: #REF! | BF633: =MONTH(BC633) -> #VALUE! | BG633: =YEAR(BC633) -> #VALUE! | BJ633: #REF! | BK633: #REF! | BM633: =MONTH(BJ633) -> #VALUE! | BN633: =YEAR(BJ633) -> #VALUE! | BR633: 43862 | BS633: =MONTH(BR633) -> 2 | BT633: =YEAR(BR633) -> 2020 | BU633: =AVERAGEIFS($BK$3:$BK$5500,$BM$3:$BM$5500,BS633,$BN$3:$BN$5500,BT633) -> #DIV/0!
A634: =Prices!A633 -> 44986 | B634: =_xlfn.MAXIFS($BD$2:$BD$5500,$BF$2:$BF$5500,$BA634,$BG$2:$BG$5500,$BB634) -> 0 | C634: =_xlfn.MINIFS($BD$2:$BD$5500,$BF$2:$BF$5500,$BA634,$BG$2:$BG$5500,$BB634) -> 0 | D634: =AVERAGEIFS($BD$2:$BD$5500,$BF$2:$BF$5500,$BA634,$BG$2:$BG$5500,$BB634) -> #DIV/0! | E634: =B634-D634 -> #DIV/0! | F634: =C634-D634 -> #DIV/0! | G634: =Prices!P633-D634 -> #DIV/0! | H634: =(G634/45.9296)*100 -> #DIV/0! | I634: =D634*AQ634 -> #DIV/0! | J634: =(I634/45.9296)*100 -> #DIV/0! | L634: ='[4]Brazil Corn Price'!$DR281 -> 0 | M634: ='[4]Brazil Corn Price'!$DS281 -> 0 | N634: ='[4]Brazil Corn Price'!$DQ281 -> 0 | O634: =L634-N634 -> 0 | P634: =M634-N634 -> 0 | R634: ='[4]Brazil Corn Price'!DW281 -> 0 | S634: ='[4]Brazil Corn Price'!DX281 -> 0 | T634: ='[4]Brazil Corn Price'!DV281 -> 0 | U634: =R634-T634 -> 0 | V634: =S634-T634 -> 0 | X634: ='[4]Brazil Corn Price'!$EB281 -> 0 | Y634: ='[4]Brazil Corn Price'!$EC281 -> 0 | Z634: ='[4]Brazil Corn Price'!$EA281 -> 0 | AA634: =X634-Z634 -> 0 | AB634: =Y634-Z634 -> 0 | AP634: 44986 | AQ634: 0.73123478 | BA634: =MONTH(A634) -> 3 | BB634: =YEAR(A634) -> 2023 | BC634: #REF! | BD634: #REF! | BF634: =MONTH(BC634) -> #VALUE! | BG634: =YEAR(BC634) -> #VALUE! | BJ634: #REF! | BK634: #REF! | BM634: =MONTH(BJ634) -> #VALUE! | BN634: =YEAR(BJ634) -> #VALUE! | BR634: 43891 | BS634: =MONTH(BR634) -> 3 | BT634: =YEAR(BR634) -> 2020 | BU634: =AVERAGEIFS($BK$3:$BK$5500,$BM$3:$BM$5500,BS634,$BN$3:$BN$5500,BT634) -> #DIV/0!
...

Sheet Corn and Barley Monthly
B1: Corn Futures
B2: 2000 | C2: 2001 | D2: 2002
A3: Jan
A4: Feb
A5: Mar
A6: Apr
A7: May
A8: Jun
A9: Jul
A10: Aug
A11: Sep
A12: Oct
A13: Nov
A14: Dec
