Workbook
Name BoxPlot: "BoxPlot"
Name Bubble: "Bubble"
Name Candlestick: "Candlestick"
Name Chart: "Chart"
Name ChartImage: "ChartImage"
Name ColumnRange: "ColumnRange"
Name Dumbbell: "Dumbbell"
Name Heatmap: "Heatmap"
Name Histogram: "Histogram"
Name Map: "Map"
Name OHLC: "OHLC"
Name PieChart: "PieChart"
Name Scatter: "Scatter"
Name Series: "Series"
Name Stripe: "Stripe"
Name Table: "Table"
Name TreeMap: "TreeMap"

Sheet Pivot
A3: Sum of Total nominal food sales | B3: Column Labels
A4: Row Labels | B4: January | C4: February | D4: March | E4: April | F4: May | G4: June | H4: July | I4: August | J4: September | K4: October | L4: November | M4: December | N4: Grand Total
A5: 1997 | B5: 51791.734 | C5: 49467.801 | D5: 55223.973 | E5: 53426.945 | F5: 57597.059 | G5: 55299.637 | H5: 57529.117 | I5: 58038.105 | J5: 54138.422 | K5: 56265.242 | L5: 54857.508 | M5: 59152.891 | N5: 662788.43
A6: 1998 | B6: 53119.102 | C6: 50502.051 | D6: 55420.773 | E6: 55948.324 | F6: 59232.855 | G6: 57700.625 | H6: 59749.93 | I6: 59152.469 | J6: 56246.848 | K6: 59056.469 | L6: 57011.508 | M6: 62902.012 | N6: 686042.96
A7: 1999 | B7: 55364.867 | C7: 53421.977 | D7: 58956.375 | E7: 58938.195 | F7: 61849.113 | G7: 60494.328 | H7: 63070.48 | I7: 61502.031 | J7: 59479.578 | K7: 61601.992 | L7: 60213.07 | M7: 67874.055 | N7: 722766.06
A8: 2000 | B8: 57592.348 | C8: 58163.207 | D8: 63381.527 | E8: 62566.543 | F8: 64887.078 | G8: 65159.629 | H8: 65925.391 | I8: 65717.812 | J8: 63611.871 | K8: 64172.723 | L8: 64049.32 | M8: 70350.617 | N8: 765578.07
A9: 2001 | B9: 61691.086 | C9: 59736.535 | D9: 66446.633 | E9: 64587.418 | F9: 68576.602 | G9: 68081.188 | H9: 68069.594 | I9: 69569.695 | J9: 64831.812 | K9: 66381.18 | L9: 66540.57 | M9: 72924.656 | N9: 797436.97
A10: 2002 | B10: 63725.898 | C10: 61657.77 | D10: 69157.648 | E10: 66150.172 | F10: 71037.867 | G10: 69383.305 | H10: 70394.312 | I10: 71776.156 | J10: 65996.227 | K10: 68579.789 | L10: 69367.828 | M10: 74159.828 | N10: 821386.8
A11: 2003 | B11: 66886.43 | C11: 64168.629 | D11: 70964.023 | E11: 69492.188 | F11: 74557.203 | G11: 71838.633 | H11: 74345.609 | I11: 75744.078 | J11: 69691.273 | K11: 73094.023 | L11: 72400.008 | M11: 78148.781 | N11: 861330.88
A12: 2004 | B12: 71715.82 | C12: 69945.367 | D12: 74750.297 | E12: 74637.305 | F12: 78090.844 | G12: 76025.32 | H12: 79448.289 | I12: 77283.141 | J12: 74517.43 | K12: 77758.031 | L12: 76259.133 | M12: 84929.922 | N12: 915360.9
A13: 2005 | B13: 74461.18 | C13: 72180.844 | D13: 79833.266 | E13: 79291.195 | F13: 81988.383 | G13: 81320.18 | H13: 83692.93 | I13: 82916.141 | J13: 80021.445 | K13: 82304.953 | L13: 81132.18 | M13: 90396.328 | N13: 969539.02
A14: 2006 | B14: 79003.742 | C14: 76540.695 | D14: 84708.961 | E14: 83677.438 | F14: 87232.992 | G14: 86234.516 | H14: 87356.438 | I14: 88014.922 | J14: 84077.711 | K14: 85437.914 | L14: 85171.711 | M14: 95646.555 | N14: 1023103.6
A15: 2007 | B15: 83123.086 | C15: 80506.766 | D15: 90249.914 | E15: 86883.266 | F15: 92313.141 | G15: 91678.086 | H15: 91702.602 | I15: 92894.742 | J15: 87761.617 | K15: 90146.477 | L15: 91007.477 | M15: 99819.977 | N15: 1078087.1
A16: 2008 | B16: 87701.305 | C16: 87070.547 | D16: 93210.883 | E16: 90680.141 | F16: 98401.57 | G16: 94458.742 | H16: 96671.695 | I16: 97533.258 | J16: 90209.922 | K16: 93257.008 | L16: 91265.992 | M16: 97036.484 | N16: 1117497.5
... A28: 2020 | B28: 133692.33 | C28: 132031.67 | D28: 134513.44 | E28: 105668.13 | F28: 124103.21 | G28: 130129.25 | H28: 136811.16 | I28: 137190.47 | J28: 132381.06 | K28: 138456.81 | L28: 132662.34 | M28: 139924.3 | N28: 1577564.2
A29: 2021 | B29: 133532.31 | C29: 124852.26 | D29: 150403.23 | E29: 150439.47 | F29: 160099.48 | G29: 158437.2 | N29: 877763.96
A30: Grand Total | B30: 2240942.3 | C30: 2176296.4 | D30: 2407094.7 | E30: 2331017.6 | F30: 2473998.5 | G30: 2425677.4 | H30: 2313090.4 | I30: 2320620.2 | J30: 2198559.8 | K30: 2276270 | L30: 2253310.3 | M30: 2448915.9 | N30: 27865793

Sheet Food Expenditure Series
A1: Monthly sales of food, with taxes and tips, for all purchasers | B1: Monthly Sales Of Food For All Purchasers With Taxes And Tips | C1: Monthly Sales Of Food For All Purchasers With Taxes And Tips | D1: Monthly Sales Of Food For All Purchasers With Taxes And Tips | E1: Monthly Sales Of Food For All Purchasers With Taxes And Tips | F1: Monthly Sales Of Food For All Purchasers With Taxes And Tips | G1: Monthly Sales Of Food For All Purchasers With Taxes And Tips
A2: [$ Million] | B2: [Millions of Dollars] | C2: [Millions of Dollars] | D2: [Millions of Dollars] | E2: [Millions of Dollars] | F2: [Millions of Dollars] | G2: [Millions of Dollars] | I2: Monthly Change Constant Dollars | J2: Year-over-Year Change - Real | N2: UCO Production (million pounds)
A3: USDA Site | R3: FAH Percent | S3: FAFH Percent | U3: Real GDP Forecast
A4: Monthly sales of food, with taxes and tips, for all purchasers | G4: Total constant dollar food sales | V4: Use GDP Now from Atlanta Fed for current quarter forecast
A5: Year | B5: FAH - Nominal | C5: FAFH - Nominal | D5: Total nominal food sales | E5: FAH - Constant $ | F5: FAFH - Constant $
A6: 35431 | B6: 30199.9 | C6: 21463.37 | D6: 51663.27 | E6: 22308.67 | F6: 16836.39 | G6: 39145.07 | L6: =G6/D6 -> 0.75769633 | M6: 60.071951 | N6: =G6*$O$6/'[2]Used Cooking Oil Complex'!$AZ$26 -> 0.035146751 | O6: =0.0007/AVERAGE(L6:L366) -> 0.0013053203 | P6: pounds per $ | R6: =B6/D6 -> 0.58455262 | S6: =C6/D6 -> 0.41544738
A7: 35462 | B7: 28029.09 | C7: 21319.07 | D7: 49348.16 | E7: 20731.36 | F7: 16690.96 | G7: 37422.31 | I7: =G7-G6 -> -1722.76 | L7: =G7/D7 -> 0.75833243 | M7: 57.428207 | N7: =G7*$O$6/'[2]Used Cooking Oil Complex'!$AZ$26 -> 0.033599955 | O7: 0.00175 | P7: 20/21 | R7: =B7/D7 -> 0.56798653 | S7: =C7/D7 -> 0.43201347
A8: 35490 | B8: 31442.48 | C8: 23645.48 | D8: 55087.97 | E8: 23256.03 | F8: 18464.87 | G8: 41720.9 | I8: =G8-G7 -> 4298.59 | L8: =G8/D8 -> 0.75735047 | M8: 64.024815 | N8: =G8*$O$6/'[2]Used Cooking Oil Complex'!$AZ$26 -> 0.037459483 | O8: 0.002 | P8: 21/22 | R8: =B8/D8 -> 0.57076854 | S8: =C8/D8 -> 0.42923128
A9: 35521 | B9: 29875.14 | C9: 23420.26 | D9: 53295.39 | E9: 22124.82 | F9: 18265.57 | G9: 40390.39 | I9: =G9-G8 -> -1330.51 | L9: =G9/D9 -> 0.75785898 | M9: 61.983017 | N9: =G9*$O$6/'[2]Used Cooking Oil Complex'!$AZ$26 -> 0.036264872 | O9: 0.0025 | P9: 22/23 | R9: =B9/D9 -> 0.56055768 | S9: =C9/D9 -> 0.43944251
A10: 35551 | B10: 32327.06 | C10: 25123.9 | D10: 57450.97 | E10: 23940.66 | F10: 19581.71 | G10: 43522.38 | I10: =G10-G9 -> 3131.99 | L10: =G10/D10 -> 0.75755692 | M10: 66.789363 | N10: =G10*$O$6/'[2]Used Cooking Oil Complex'!$AZ$26 -> 0.039076958 | O10: 0.00275 | P10: 23/24 | R10: =B10/D10 -> 0.56268954 | S10: =C10/D10 -> 0.43731028
A11: 35582 | B11: 30735.56 | C11: 24420.77 | D11: 55156.33 | E11: 22790.96 | F11: 18997.23 | G11: 41788.2 | I11: =G11-G10 -> -1734.18 | L11: =G11/D11 -> 0.75763199 | M11: 64.128094 | N11: =G11*$O$6/'[2]Used Cooking Oil Complex'!$AZ$26 -> 0.037519909 | O11: 0.003 | P11: 24/25 | R11: =B11/D11 -> 0.55724447 | S11: =C11/D11 -> 0.44275553
A12: 35612 | B12: 32142.13 | C12: 25231.44 | D12: 57373.57 | E12: 23773.51 | F12: 19565.39 | G12: 43338.9 | I12: =G12-G11 -> 1550.7 | L12: =G12/D12 -> 0.75538092 | M12: 66.507795 | N12: =G12*$O$6/'[2]Used Cooking Oil Complex'!$AZ$26 -> 0.038912219 | R12: =B12/D12 -> 0.56022538 | S12: =C12/D12 -> 0.43977462
A13: 35643 | B13: 32064.1 | C13: 25812.17 | D13: 57876.27 | E13: 23596.09 | F13: 19977.56 | G13: 43573.66 | I13: =G13-G12 -> 234.76 | L13: =G13/D13 -> 0.75287609 | M13: 66.868057 | N13: =G13*$O$6/'[2]Used Cooking Oil Complex'!$AZ$26 -> 0.039123 | R13: =B13/D13 -> 0.55401117 | S13: =C13/D13 -> 0.44598883
A14: 35674 | B14: 30239.88 | C14: 23738.73 | D14: 53978.61 | E14: 22239.61 | F14: 18326.23 | G14: 40565.84 | I14: =G14-G13 -> -3007.82 | L14: =G14/D14 -> 0.75151694 | M14: 62.252262 | N14: =G14*$O$6/'[2]Used Cooking Oil Complex'!$AZ$26 -> 0.036422402 | R14: =B14/D14 -> 0.56021969 | S14: =C14/D14 -> 0.43978031
A15: 35704 | B15: 31674.05 | C15: 24415.42 | D15: 56089.48 | E15: 23235.76 | F15: 18800.98 | G15: 42036.73 | I15: =G15-G14 -> 1470.89 | L15: =G15/D15 -> 0.74945837 | M15: 64.509487 | N15: =G15*$O$6/'[2]Used Cooking Oil Complex'!$AZ$26 -> 0.037743054 | R15: =B15/D15 -> 0.56470572 | S15: =C15/D15 -> 0.43529411
A16: 35735 | B16: 31623.79 | C16: 23049.3 | D16: 54673.09 | E16: 23184.31 | F16: 17704.23 | G16: 40888.54 | I16: =G16-G15 -> -1148.19 | L16: =G16/D16 -> 0.74787322 | M16: 62.747477 | N16: =G16*$O$6/'[2]Used Cooking Oil Complex'!$AZ$26 -> 0.036712141 | R16: =B16/D16 -> 0.578416 | S16: =C16/D16 -> 0.421584
A17: 35765 | B17: 34847.12 | C17: 24091.97 | D17: 58939.09 | E17: 25531.38 | F17: 18458.56 | G17: 43989.94 | I17: =G17-G16 -> 3101.4 | L17: =G17/D17 -> 0.74636273 | M17: 67.50688 | N17: =G17*$O$6/'[2]Used Cooking Oil Complex'!$AZ$26 -> 0.039496761 | R17: =B17/D17 -> 0.59123953 | S17: =C17/D17 -> 0.40876047
A18: 35796 | B18: 30342.99 | C18: 22686.14 | D18: 53029.13 | E18: 21984.26 | F18: 17356 | G18: 39340.26 | I18: =G18-G17 -> -4649.68 | J18: =G18/G6-1 -> 0.0049863239 | L18: =G18/D18 -> 0.74186131 | M18: 60.37149 | N18: =G18*$O$6/'[2]Used Cooking Oil Complex'!$AZ$26 -> 0.035322004 | R18: =B18/D18 -> 0.57219475 | S18: =C18/D18 -> 0.42780525
A19: 35827 | B19: 28064.53 | C19: 22345.57 | D19: 50410.09 | E19: 20460.54 | F19: 17052.6 | G19: 37513.14 | I19: =G19-G18 -> -1827.12 | J19: =G19/G7-1 -> 0.0024271618 | L19: =G19/D19 -> 0.74415935 | M19: 57.567595 | N19: =G19*$O$6/'[2]Used Cooking Oil Complex'!$AZ$26 -> 0.033681508 | R19: =B19/D19 -> 0.55672446 | S19: =C19/D19 -> 0.44327574
A20: 35855 | B20: 30671.49 | C20: 24639.52 | D20: 55311 | E20: 22333.23 | F20: 18767.91 | G20: 41101.14 | I20: =G20-G19 -> 3588 | J20: =G20/G8-1 -> -0.014854905 | L20: =G20/D20 -> 0.74309161 | M20: 63.073733 | N20: =G20*$O$6/'[2]Used Cooking Oil Complex'!$AZ$26 -> 0.036903026 | R20: =B20/D20 -> 0.55452785 | S20: =C20/D20 -> 0.44547233
A21: 35886 | B21: 31116.51 | C21: 24711.92 | D21: 55828.43 | E21: 22657.27 | F21: 18787.81 | G21: 41445.09 | I21: =G21-G20 -> 343.95 | J21: =G21/G9-1 -> 0.026112647 | L21: =G21/D21 -> 0.74236531 | M21: 63.601558 | N21: =G21*$O$6/'[2]Used Cooking Oil Complex'!$AZ$26 -> 0.037211844 | R21: =B21/D21 -> 0.55735957 | S21: =C21/D21 -> 0.44264043
A22: 35916 | B22: 32653.27 | C22: 26445.89 | D22: 59099.16 | E22: 23702.28 | F22: 20056.03 | G22: 43758.31 | I22: =G22-G21 -> 2313.22 | J22: =G22/G10-1 -> 0.0054208892 | L22: =G22/D22 -> 0.74042186 | M22: 67.151421 | N22: =G22*$O$6/'[2]Used Cooking Oil Complex'!$AZ$26 -> 0.03928879 | R22: =B22/D22 -> 0.55251665 | S22: =C22/D22 -> 0.44748335
A23: 35947 | B23: 31684.14 | C23: 25880.12 | D23: 57564.26 | E23: 23027.47 | F23: 19614.74 | G23: 42642.2 | I23: =G23-G22 -> -1116.11 | J23: =G23/G11-1 -> 0.020436391 | L23: =G23/D23 -> 0.74077561 | M23: 65.43864 | N23: =G23*$O$6/'[2]Used Cooking Oil Complex'!$AZ$26 -> 0.03828668 | R23: =B23/D23 -> 0.5504134 | S23: =C23/D23 -> 0.4495866
A24: 35977 | B24: 33131.73 | C24: 26469.79 | D24: 59601.52 | E24: 24034.63 | F24: 20011.84 | G24: 44046.47 | I24: =G24-G23 -> 1404.27 | J24: =G24/G12-1 -> 0.016326441 | L24: =G24/D24 -> 0.73901588 | M24: 67.593631 | N24: =G24*$O$6/'[2]Used Cooking Oil Complex'!$AZ$26 -> 0.039547517 | R24: =B24/D24 -> 0.55588733 | S24: =C24/D24 -> 0.44411267
A25: 36008 | B25: 32453.15 | C25: 26549.22 | D25: 59002.37 | E25: 23454.85 | F25: 20022.18 | G25: 43477.03 | I25: =G25-G24 -> -569.44 | J25: =G25/G13-1 -> -0.0022176241 | L25: =G25/D25 -> 0.73686921 | M25: 66.719769 | N25: =G25*$O$6/'[2]Used Cooking Oil Complex'!$AZ$26 -> 0.03903624 | R25: =B25/D25 -> 0.5500313 | S25: =C25/D25 -> 0.4499687
A26: 36039 | B26: 31238.89 | C26: 24860.14 | D26: 56099.03 | E26: 22605.28 | F26: 18678.96 | G26: 41284.23 | I26: =G26-G25 -> -2192.8 | J26: =G26/G14-1 -> 0.017709235 | L26: =G26/D26 -> 0.735917 | M26: 63.354702 | N26: =G26*$O$6/'[2]Used Cooking Oil Complex'!$AZ$26 -> 0.037067415 | R26: =B26/D26 -> 0.55685259 | S26: =C26/D26 -> 0.44314741
A27: 36069 | B27: 32726.56 | C27: 26172.46 | D27: 58899.02 | E27: 23492.34 | F27: 19640.75 | G27: 43133.09 | I27: =G27-G26 -> 1848.86 | J27: =G27/G15-1 -> 0.026081001 | L27: =G27/D27 -> 0.73232271 | M27: 66.191959 | N27: =G27*$O$6/'[2]Used Cooking Oil Complex'!$AZ$26 -> 0.03872743 | R27: =B27/D27 -> 0.55563845 | S27: =C27/D27 -> 0.44436155
A28: 36100 | B28: 32376.12 | C28: 24478.38 | D28: 56854.5 | E28: 23240.78 | F28: 18335.56 | G28: 41576.34 | I28: =G28-G27 -> -1556.75 | J28: =G28/G16-1 -> 0.016821339 | L28: =G28/D28 -> 0.73127615 | M28: 63.802974 | N28: =G28*$O$6/'[2]Used Cooking Oil Complex'!$AZ$26 -> 0.037329688 | R28: =B28/D28 -> 0.56945572 | S28: =C28/D28 -> 0.43054428
A29: 36130 | B29: 36784.93 | C29: 25938.42 | D29: 62723.35 | E29: 26389.35 | F29: 19381.53 | G29: 45770.88 | I29: =G29-G28 -> 4194.54 | J29: =G29/G17-1 -> 0.040485165 | L29: =G29/D29 -> 0.72972633 | M29: 70.239907 | N29: =G29*$O$6/'[2]Used Cooking Oil Complex'!$AZ$26 -> 0.041095793 | R29: =B29/D29 -> 0.5864631 | S29: =C29/D29 -> 0.4135369
... A281: 43800 | B281: 76391.16 | C281: 80137.73 | D281: 156528.91 | E281: 36844.08 | F281: 33887.36 | G281: 70731.45 | I281: =G281-G280 -> 3763.36 | J281: =G281/G269-1 -> 0.012199234 | L281: =G281/D281 -> 0.45187467 | M281: 108.54435 | N281: =G281*$O$6/'[2]Used Cooking Oil Complex'!$AZ$26 -> 0.063506864 | R281: =B281/D281 -> 0.48803227 | S281: =C281/D281 -> 0.5119676
A282: 43831 | B282: 66694.53 | C282: 78630 | D282: 145324.53 | E282: 31993.04 | F282: 33131 | G282: 65124.04 | I282: =G282-G281 -> -5607.41 | J282: =G282/G270-1 -> 0.046503694 | L282: =G282/D282 -> 0.44812834 | M282: 108.54435 | N282: =G282*$O$6/'[2]Used Cooking Oil Complex'!$AZ$26 -> 0.058472201 | R282: =B282/D282 -> 0.45893512 | S282: =C282/D282 -> 0.54106488 | U282: -0.046
A283: 43862 | B283: 64407.57 | C283: 79336.55 | D283: 143744.13 | E283: 30776.5 | F283: 33354.41 | G283: 64130.91 | I283: =G283-G282 -> -993.13 | J283: =G283/G271-1 -> 0.080265648 | L283: =G283/D283 -> 0.44614629 | M283: 108.54435 | N283: =G283*$O$6/'[2]Used Cooking Oil Complex'!$AZ$26 -> 0.05758051 | R283: =B283/D283 -> 0.44807096 | S283: =C283/D283 -> 0.55192897
A284: 43891 | B284: 81128.83 | C284: 63041.38 | D284: 144170.22 | E284: 38591.22 | F284: 26463.93 | G284: 65055.16 | I284: =G284-G283 -> 924.25 | J284: =G284/G272-1 -> -0.035483247 | L284: =G284/D284 -> 0.45123854 | M284: 108.54435 | N284: =G284*$O$6/'[2]Used Cooking Oil Complex'!$AZ$26 -> 0.058410357 | R284: =B284/D284 -> 0.56272946 | S284: =C284/D284 -> 0.43727047
A285: 43922 | B285: 70762.89 | C285: 41459.1 | D285: 112221.98 | E285: 32783.95 | F285: 17378.64 | G285: 50162.59 | I285: =G285-G284 -> -14892.57 | J285: =G285/G273-1 -> -0.23552763 | L285: =G285/D285 -> 0.44699434 | M285: 108.54435 | N285: =G285*$O$6/'[2]Used Cooking Oil Complex'!$AZ$26 -> 0.04503893 | R285: =B285/D285 -> 0.63056177 | S285: =C285/D285 -> 0.36943832 | U285: -0.299
A286: 43952 | B286: 76341.51 | C286: 56462.11 | D286: 132803.63 | E286: 35074.47 | F286: 23580.72 | G286: 58655.2 | I286: =G286-G285 -> 8492.61 | J286: =G286/G274-1 -> -0.15894767 | L286: =G286/D286 -> 0.44166865 | M286: 90.01216 | N286: =G286*$O$6/'[2]Used Cooking Oil Complex'!$AZ$26 -> 0.052664095 | R286: =B286/D286 -> 0.57484506 | S286: =C286/D286 -> 0.42515487
A287: 43983 | B287: 72909.72 | C287: 67401.96 | D287: 140311.69 | E287: 33338.18 | F287: 28004.66 | G287: 61342.84 | I287: =G287-G286 -> 2687.64 | J287: =G287/G275-1 -> -0.098930474 | L287: =G287/D287 -> 0.4371898 | M287: 94.136608 | N287: =G287*$O$6/'[2]Used Cooking Oil Complex'!$AZ$26 -> 0.055077217 | R287: =B287/D287 -> 0.51962684 | S287: =C287/D287 -> 0.48037309
A288: 44013 | B288: 75781.51 | C288: 71869.09 | D288: 147650.59 | E288: 34991.43 | F288: 29720.82 | G288: 64712.25 | I288: =G288-G287 -> 3369.41 | J288: =G288/G276-1 -> -0.05970239 | L288: =G288/D288 -> 0.43827966 | M288: 99.307298 | N288: =G288*$O$6/'[2]Used Cooking Oil Complex'!$AZ$26 -> 0.058102472 | R288: =B288/D288 -> 0.51324895 | S288: =C288/D288 -> 0.48675112 | U288: 0.353
A289: 44044 | B289: 74259.73 | C289: 74060.9 | D289: 148320.63 | E289: 34317.43 | F289: 30540.35 | G289: 64857.78 | I289: =G289-G288 -> 145.53 | J289: =G289/G277-1 -> -0.072552712 | L289: =G289/D289 -> 0.43728091 | M289: 99.530628 | N289: =G289*$O$6/'[2]Used Cooking Oil Complex'!$AZ$26 -> 0.058233137 | R289: =B289/D289 -> 0.50067027 | S289: =C289/D289 -> 0.49932973
A290: 44075 | B290: 71205.23 | C290: 71986.12 | D290: 143191.34 | E290: 33034.55 | F290: 29520.61 | G290: 62555.16 | I290: =G290-G289 -> -2302.62 | J290: =G290/G278-1 -> -0.03032274 | L290: =G290/D290 -> 0.43686413 | M290: 95.997032 | N290: =G290*$O$6/'[2]Used Cooking Oil Complex'!$AZ$26 -> 0.056165709 | R290: =B290/D290 -> 0.4972733 | S290: =C290/D290 -> 0.50272677
A291: 44105 | B291: 74573.17 | C291: 75178.05 | D291: 149751.22 | E291: 34519.05 | F291: 30745.44 | G291: 65264.5 | I291: =G291-G290 -> 2709.34 | J291: =G291/G279-1 -> -0.02498822 | L291: =G291/D291 -> 0.43581949 | M291: 134.36809 | N291: =G291*$O$7/'[2]Used Cooking Oil Complex'!$AZ$26 -> 0.078560836 | R291: =B291/D291 -> 0.49798038 | S291: =C291/D291 -> 0.50201962 | U291: 0.039
A292: 44136 | B292: 75228.64 | C292: 67697.91 | D292: 142926.56 | E292: 35035.23 | F292: 27652.88 | G292: 62688.11 | I292: =G292-G291 -> -2576.39 | J292: =G292/G280-1 -> -0.063910737 | L292: =G292/D292 -> 0.43860364 | M292: 129.06376 | N292: =G292*$O$7/'[2]Used Cooking Oil Complex'!$AZ$26 -> 0.075459558 | R292: =B292/D292 -> 0.52634472 | S292: =C292/D292 -> 0.47365521
A293: 44166 | B293: 81375.17 | C293: 69075.59 | D293: 150450.77 | E293: 37770.16 | F293: 28110.44 | G293: 65880.6 | I293: =G293-G292 -> 3192.49 | J293: =G293/G281-1 -> -0.068581232 | L293: =G293/D293 -> 0.43788809 | M293: 135.63653 | N293: =G293*$O$7/'[2]Used Cooking Oil Complex'!$AZ$26 -> 0.079302454 | R293: =B293/D293 -> 0.54087573 | S293: =C293/D293 -> 0.4591242
A294: 44197 | B294: 73674.02 | C294: 67843.37 | D294: 141517.39 | E294: 34100.54 | F294: 27539.94 | G294: 61640.47 | I294: =G294-G293 -> -4240.13 | J294: =G294/G282-1 -> -0.053491307 | L294: =G294/D294 -> 0.43556817 | M294: 126.90685 | N294: =G294*$O$7/'[2]Used Cooking Oil Complex'!$AZ$26 -> 0.074198482 | R294: =B294/D294 -> 0.52060047 | S294: =C294/D294 -> 0.47939953 | U294: 0.063 | Z294: 70487.296 | AA294: =B294-Z294 -> 3186.7241 | AB294: 69012.704 | AC294: =C294-AB294 -> -1169.3341 | AD294: 139500 | AE294: =D294-AD294 -> 2017.39
A295: 44228 | B295: 67539.78 | C295: 64905.6 | D295: 132445.38 | E295: 31185.93 | F295: 26333.55 | G295: 57519.48 | I295: =G295-G294 -> -4120.99 | J295: =G295/G283-1 -> -0.10309272 | L295: =G295/D295 -> 0.43428831 | M295: 118.42246 | N295: =G295*$O$7/'[2]Used Cooking Oil Complex'!$AZ$26 -> 0.069237923 | R295: =B295/D295 -> 0.5099444 | S295: =C295/D295 -> 0.4900556 | Z295: 69817.827 | AA295: =B295-Z295 -> -2278.047 | AB295: 70932.173 | AC295: =C295-AB295 -> -6026.573 | AD295: 140750 | AE295: =D295-AD295 -> -8304.62
A296: 44256 | B296: 78380.17 | C296: 81722.2 | D296: 160102.38 | E296: 36117.78 | F296: 33117.05 | G296: 69234.83 | I296: =G296-G295 -> 11715.35 | J296: =G296/G284-1 -> 0.064248093 | L296: =G296/D296 -> 0.43244098 | M296: 142.5423 | N296: =G296*$O$7/'[2]Used Cooking Oil Complex'!$AZ$26 -> 0.083340041 | R296: =B296/D296 -> 0.4895628 | S296: =C296/D296 -> 0.51043713 | Z296: 71816.488 | AA296: =B296-Z296 -> 6563.6818 | AB296: 70183.512 | AC296: =C296-AB296 -> 11538.688 | AD296: 142000 | AE296: =D296-AD296 -> 18102.38
A297: 44287 | B297: 76150.92 | C297: 84285.16 | D297: 160436.09 | E297: 34879.93 | F297: 34051.33 | G297: 68931.27 | I297: =G297-G296 -> -303.56 | J297: =G297/G285-1 -> 0.37415692 | L297: =G297/D297 -> 0.4296494 | M297: 141.91732 | N297: =G297*$O$7/'[2]Used Cooking Oil Complex'!$AZ$26 -> 0.082974637 | R297: =B297/D297 -> 0.47464956 | S297: =C297/D297 -> 0.52535037 | U297: 0.07 | Z297: 73649.055 | AA297: =B297-Z297 -> 2501.865 | AB297: 70350.945 | AC297: =C297-AB297 -> 13934.215 | AD297: 144000 | AE297: =D297-AD297 -> 16436.09
A298: 44317 | B298: 80074.32 | C298: 90803.3 | D298: 170877.63 | E298: 36568.48 | F298: 36483.76 | G298: 73052.23 | I298: =G298-G297 -> 4120.96 | J298: =G298/G286-1 -> 0.2454519 | L298: =G298/D298 -> 0.42751196 | M298: 150.40165 | N298: =G298*$O$7/'[2]Used Cooking Oil Complex'!$AZ$26 -> 0.08793516 | R298: =B298/D298 -> 0.46860622 | S298: =C298/D298 -> 0.53139372 | Z298: 74033.168 | AA298: =B298-Z298 -> 6041.1521 | AB298: 71966.832 | AC298: =C298-AB298 -> 18836.468 | AD298: 146000 | AE298: =D298-AD298 -> 24877.63
A299: 44348 | B299: 78684.92 | C299: 91389.16 | D299: 170074.09 | E299: 35669.29 | F299: 36460.49 | G299: 72129.78 | I299: =G299-G298 -> -922.45 | J299: =G299/G287-1 -> 0.17584677 | L299: =G299/D299 -> 0.42410799 | M299: 148.50249 | N299: =G299*$O$7/'[2]Used Cooking Oil Complex'!$AZ$26 -> 0.086824779 | R299: =B299/D299 -> 0.46265084 | S299: =C299/D299 -> 0.5373491 | Z299: 74715.785 | AA299: =B299-Z299 -> 3969.1347 | AB299: 73284.215 | AC299: =C299-AB299 -> 18104.945 | AD299: 148000 | AE299: =D299-AD299 -> 22074.09
A300: 44378 | B300: 80514.59 | C300: 96014.84 | D300: 176529.42 | E300: 36271.85 | F300: 38008.84 | G300: 74280.69 | I300: =G300-G299 -> 2150.91 | J300: =G300/G288-1 -> 0.14786134 | L300: =G300/D300 -> 0.42078363 | M300: 152.93083 | N300: =G300*$O$7/'[2]Used Cooking Oil Complex'!$AZ$26 -> 0.089413894 | R300: =B300/D300 -> 0.45609729 | S300: =C300/D300 -> 0.54390277 | U300: 0.027
A301: 44409 | B301: 80682.88 | C301: 93558.08 | D301: 174240.97 | E301: 36235.32 | F301: 36879.09 | G301: 73114.42 | I301: =G301-G300 -> -1166.27 | J301: =G301/G289-1 -> 0.12730377 | L301: =G301/D301 -> 0.4196167 | M301: 150.52969 | N301: =G301*$O$7/'[2]Used Cooking Oil Complex'!$AZ$26 -> 0.08801002 | R301: =B301/D301 -> 0.46305344 | S301: =C301/D301 -> 0.53694651
A302: 44440 | B302: 77963.79 | C302: 89692.89 | D302: 167656.69 | E302: 34631.62 | F302: 35166.79 | G302: 69798.41 | I302: =G302-G301 -> -3316.01 | J302: =G302/G290-1 -> 0.11578981 | L302: =G302/D302 -> 0.41631748 | M302: 143.70261 | N302: =G302*$O$7/'[2]Used Cooking Oil Complex'!$AZ$26 -> 0.084018439 | R302: =B302/D302 -> 0.46502045 | S302: =C302/D302 -> 0.53497949
A303: 44470 | B303: 82538.63 | C303: 93755.59 | D303: 176294.22 | E303: 36279.43 | F303: 36455.38 | G303: 72734.81 | I303: =G303-G302 -> 2936.4 | J303: =G303/G291-1 -> 0.11446207 | L303: =G303/D303 -> 0.41257626 | M303: 171.14073 | N303: =G303*$O$8/'[2]Used Cooking Oil Complex'!$AZ$26 -> 0.10006065 | R303: =B303/D303 -> 0.46818682 | S303: =C303/D303 -> 0.53181318 | U303: 0.07
A304: 44501 | B304: 84605.19 | C304: 88694.48 | D304: 173299.66 | E304: 37061.29 | F304: 34280.95 | G304: 71342.23 | I304: =G304-G303 -> -1392.58 | J304: =G304/G292-1 -> 0.13805042 | L304: =G304/D304 -> 0.41166976 | M304: 167.86407 | N304: =G304*$O$8/'[2]Used Cooking Oil Complex'!$AZ$26 -> 0.098144893 | R304: =B304/D304 -> 0.48820171 | S304: =C304/D304 -> 0.51179835
A305: 44531 | B305: 91905.23 | C305: 93937.6 | D305: 185842.84 | E305: 40082.89 | F305: 36091.12 | G305: 76174 | I305: =G305-G304 -> 4831.77 | J305: =G305/G293-1 -> 0.15624326 | L305: =G305/D305 -> 0.40988396 | M305: 179.23294 | N305: =G305*$O$8/'[2]Used Cooking Oil Complex'!$AZ$26 -> 0.10479192 | R305: =B305/D305 -> 0.49453199 | S305: =C305/D305 -> 0.50546795
A306: 44562 | B306: 80653.91 | C306: 83571.13 | D306: 164225.03 | E306: 34762.48 | F306: 31875.3 | G306: 66637.79 | I306: =G306-G305 -> -9536.21 | J306: =G306/G294-1 -> 0.081072062 | L306: =G306/D306 -> 0.40577122 | M306: 156.7948 | N306: =G306*$O$8/'[2]Used Cooking Oil Complex'!$AZ$26 -> 0.091673036 | R306: =B306/D306 -> 0.49111825 | S306: =C306/D306 -> 0.50888181 | U306: -0.02
A307: 44593 | B307: 74657.76 | C307: 85803.3 | D307: 160461.06 | E307: 31726.07 | F307: 32582.98 | G307: 64309.05 | I307: =G307-G306 -> -2328.74 | J307: =G307/G295-1 -> 0.11803949 | L307: =G307/D307 -> 0.40077667 | M307: 151.31541 | N307: =G307*$O$8/'[2]Used Cooking Oil Complex'!$AZ$26 -> 0.088469408 | R307: =B307/D307 -> 0.46527027 | S307: =C307/D307 -> 0.53472973
A308: 44621 | B308: 84560.6 | C308: 99254.84 | D308: 183815.44 | E308: 35412.73 | F308: 37596.29 | G308: 73009.03 | I308: =G308-G307 -> 8699.98 | J308: =G308/G296-1 -> 0.054513025 | L308: =G308/D308 -> 0.3971866 | M308: 171.78595 | N308: =G308*$O$8/'[2]Used Cooking Oil Complex'!$AZ$26 -> 0.1004379 | R308: =B308/D308 -> 0.46002991 | S308: =C308/D308 -> 0.53997009
A309: 44652 | B309: 83614.06 | C309: 101353.27 | D309: 184967.34 | E309: 34575.91 | F309: 38169.27 | G309: 72745.18 | I309: =G309-G308 -> -263.85 | J309: =G309/G297-1 -> 0.055329171 | L309: =G309/D309 -> 0.39328662 | M309: 171.16513 | N309: =G309*$O$8/'[2]Used Cooking Oil Complex'!$AZ$26 -> 0.10007492 | R309: =B309/D309 -> 0.4520477 | S309: =C309/D309 -> 0.54795225 | U309: -0.01
A310: 44682 | B310: 87698.59 | C310: 105795.77 | D310: 193494.36 | E310: 35784.02 | F310: 39549.79 | G310: 75333.81 | I310: =G310-G309 -> 2588.63 | J310: =G310/G298-1 -> 0.031232175 | L310: =G310/D310 -> 0.38933336 | M310: 177.25602 | N310: =G310*$O$8/'[2]Used Cooking Oil Complex'!$AZ$26 -> 0.10363608 | R310: =B310/D310 -> 0.4532359 | S310: =C310/D310 -> 0.5467641
A311: 44713 | B311: 87669.95 | C311: 103862.52 | D311: 191532.47 | E311: 35409.39 | F311: 38463.51 | G311: 73872.91 | I311: =G311-G310 -> -1460.9 | J311: =G311/G299-1 -> 0.024166579 | L311: =G311/D311 -> 0.38569392 | M311: 173.81861 | N311: =G311*$O$8/'[2]Used Cooking Oil Complex'!$AZ$26 -> 0.10162633 | R311: =B311/D311 -> 0.45772892 | S311: =C311/D311 -> 0.54227108
A312: 44743 | B312: 88896.27 | C312: 105655.08 | D312: 194551.34 | E312: 35403.7 | F312: 38854.68 | G312: 74258.39 | I312: =G312-G311 -> 385.48 | J312: =G312/G300-1 -> -0.00030021261 | L312: =G312/D312 -> 0.38169046 | M312: 174.72562 | N312: =G312*$O$8/'[2]Used Cooking Oil Complex'!$AZ$26 -> 0.10215663 | R312: =B312/D312 -> 0.45692962 | S312: =C312/D312 -> 0.54307043 | U312: 0.003
A313: 44774 | B313: 88245.3 | C313: 104805.67 | D313: 193050.97 | E313: 34902.02 | F313: 38211.34 | G313: 73113.36 | I313: =G313-G312 -> -1145.03 | J313: =G313/G301-1 -> -1.4497824e-05 | L313: =G313/D313 -> 0.37872568 | M313: 172.03144 | N313: =G313*$O$8/'[2]Used Cooking Oil Complex'!$AZ$26 -> 0.10058142 | R313: =B313/D313 -> 0.45710881 | S313: =C313/D313 -> 0.54289119
A314: 44805 | B314: 85113.6 | C314: 101175.04 | D314: 186288.64 | E314: 33463.3 | F314: 36542.46 | G314: 70005.76 | I314: =G314-G313 -> -3107.6 | J314: =G314/G302-1 -> 0.002970698 | L314: =G314/D314 -> 0.37579189 | M314: 164.71944 | N314: =G314*$O$8/'[2]Used Cooking Oil Complex'!$AZ$26 -> 0.096306323 | R314: =B314/D314 -> 0.45689098 | S314: =C314/D314 -> 0.54310902
A315: 44835 | B315: 89017.04 | C315: 104701.08 | D315: 193718.13 | E315: 34806.8 | F315: 37464.74 | G315: 72271.55 | I315: =G315-G314 -> 2265.79 | J315: =G315/G303-1 -> -0.0063691649 | L315: =G315/D315 -> 0.37307582 | M315: 212.56338 | N315: =G315*$O$9/'[2]Used Cooking Oil Complex'!$AZ$26 -> 0.12427919 | R315: =B315/D315 -> 0.45951837 | S315: =C315/D315 -> 0.54048157 | U315: 0.027
A316: 44866 | B316: 92002.51 | C316: 98143.88 | D316: 190146.38 | E316: 35988.27 | F316: 34940.49 | G316: 70928.77 | I316: =G316-G315 -> -1342.78 | J316: =G316/G304-1 -> -0.0057954454 | L316: =G316/D316 -> 0.37302193 | M316: 208.61403 | N316: =G316*$O$9/'[2]Used Cooking Oil Complex'!$AZ$26 -> 0.12197013 | R316: =B316/D316 -> 0.48385097 | S316: =C316/D316 -> 0.51614908
A317: 44896 | B317: 99145.64 | C317: 105474.91 | D317: 204620.55 | E317: 38678.04 | F317: 37409.11 | G317: 76087.15 | I317: =G317-G316 -> 5158.38 | J317: =G317/G305-1 -> -0.0011401528 | L317: =G317/D317 -> 0.37184511 | M317: 223.78574 | N317: =G317*$O$9/'[2]Used Cooking Oil Complex'!$AZ$26 -> 0.13084055 | R317: =B317/D317 -> 0.48453413 | S317: =C317/D317 -> 0.51546587
A318: 44927 | B318: 84500.28 | C318: 100769.74 | D318: 185270.03 | E318: 32687.5 | F318: 35514.73 | G318: 68202.23 | I318: =G318-G317 -> -7884.92 | J318: =G318/G306-1 -> 0.023476769 | L318: =G318/D318 -> 0.36812338 | M318: 200.59479 | N318: =G318*$O$9/'[2]Used Cooking Oil Complex'!$AZ$26 -> 0.11728153 | R318: =B318/D318 -> 0.45609255 | S318: =C318/D318 -> 0.5439074 | U318: 0.034
A319: 44958 | B319: 79632.28 | C319: 98558.15 | D319: 178190.44 | E319: 30697.67 | F319: 34516.41 | G319: 65214.09 | I319: =G319-G318 -> -2988.14 | J319: =G319/G307-1 -> 0.014073291 | L319: =G319/D319 -> 0.36597973 | M319: 191.80615 | N319: =G319*$O$9/'[2]Used Cooking Oil Complex'!$AZ$26 -> 0.11214308 | R319: =B319/D319 -> 0.44689423 | S319: =C319/D319 -> 0.55310571
A320: 44986 | B320: 87007.13 | C320: 111494.99 | D320: 198502.13 | E320: 33603.39 | F320: 38815.55 | G320: 72418.94 | I320: =G320-G319 -> 7204.85 | J320: =G320/G308-1 -> -0.0080824249 | L320: =G320/D320 -> 0.36482702 | M320: 212.99688 | N320: =G320*$O$9/'[2]Used Cooking Oil Complex'!$AZ$26 -> 0.12453264 | R320: =B320/D320 -> 0.43831837 | S320: =C320/D320 -> 0.56168158
A321: 45017 | B321: 86381.06 | C321: 108851.66 | D321: 195232.72 | E321: 33316.35 | F321: 37755.8 | G321: 71072.16 | I321: =G321-G320 -> -1346.78 | J321: =G321/G309-1 -> -0.022998362 | L321: =G321/D321 -> 0.36403816 | M321: 209.03576 | N321: =G321*$O$9/'[2]Used Cooking Oil Complex'!$AZ$26 -> 0.1222167 | R321: =B321/D321 -> 0.44245176 | S321: =C321/D321 -> 0.55754824 | U321: 0.028
A322: 45047 | B322: 90478.08 | C322: 114286.88 | D322: 204764.95 | E322: 34872.65 | F322: 39455.13 | G322: 74327.78 | I322: =G322-G321 -> 3255.62 | J322: =G322/G310-1 -> -0.013354296 | L322: =G322/D322 -> 0.36299074 | M322: 218.61112 | N322: =G322*$O$9/'[2]Used Cooking Oil Complex'!$AZ$26 -> 0.12781511 | R322: =B322/D322 -> 0.44186312 | S322: =C322/D322 -> 0.55813693
A323: 45078 | B323: 88124.33 | C323: 113449.48 | D323: 201573.81 | E323: 33987.92 | F323: 39016.45 | G323: 73004.37 | I323: =G323-G322 -> -1323.41 | J323: =G323/G311-1 -> -0.011757219 | L323: =G323/D323 -> 0.3621719 | M323: 214.71874 | N323: =G323*$O$9/'[2]Used Cooking Oil Complex'!$AZ$26 -> 0.12553936 | R323: =B323/D323 -> 0.43718145 | S323: =C323/D323 -> 0.56281855
A324: 45108 | B324: 89600.3 | C324: 114571.88 | D324: 204172.19 | E324: 34429.64 | F324: 39333.93 | G324: 73763.58 | I324: =G324-G323 -> 759.21 | J324: =G324/G312-1 -> -0.0066633548 | L324: =G324/D324 -> 0.36128123 | M324: 216.95171 | N324: =G324*$O$9/'[2]Used Cooking Oil Complex'!$AZ$26 -> 0.1268449 | R324: =B324/D324 -> 0.43884674 | S324: =C324/D324 -> 0.56115321 | U324: 0.024
A325: 45139 | B325: 90775.52 | C325: 113539.74 | D325: 204315.27 | E325: 34851.25 | F325: 38845.93 | G325: 73697.17 | I325: =G325-G324 -> -66.41 | J325: =G325/G313-1 -> 0.0079849975 | L325: =G325/D325 -> 0.36070319 | M325: 216.75638 | N325: =G325*$O$9/'[2]Used Cooking Oil Complex'!$AZ$26 -> 0.12673071 | R325: =B325/D325 -> 0.44429141 | S325: =C325/D325 -> 0.55570854
A326: 45170 | B326: 87172.37 | C326: 110354.03 | D326: 197526.41 | E326: 33444.88 | F326: 37607.6 | G326: 71052.48 | I326: =G326-G325 -> -2644.69 | J326: =G326/G314-1 -> 0.014951913 | L326: =G326/D326 -> 0.35971129 | M326: 208.97788 | N326: =G326*$O$9/'[2]Used Cooking Oil Complex'!$AZ$26 -> 0.12218286 | R326: =B326/D326 -> 0.44132007 | S326: =C326/D326 -> 0.55867987
A327: 45200 | B327: 89396.82 | C327: 111500.33 | D327: 200897.16 | E327: 34201.21 | F327: 37856.77 | G327: 72057.98 | I327: =G327-G326 -> 1005.5 | J327: =G327/G315-1 -> -0.0029551047 | L327: =G327/D327 -> 0.35868093 | M327: 233.12876 | N327: =G327*$O$10/'[2]Used Cooking Oil Complex'!$AZ$26 -> 0.13630312 | R327: =B327/D327 -> 0.44498797 | S327: =C327/D327 -> 0.55501198 | U327: 0.044
A328: 45231 | B328: 92102.15 | C328: 107247.69 | D328: 199349.84 | E328: 35417.95 | F328: 36255.38 | G328: 71673.33 | I328: =G328-G327 -> -384.65 | J328: =G328/G316-1 -> 0.010497292 | L328: =G328/D328 -> 0.35953543 | M328: 231.8843 | N328: =G328*$O$10/'[2]Used Cooking Oil Complex'!$AZ$26 -> 0.13557553 | R328: =B328/D328 -> 0.46201266 | S328: =C328/D328 -> 0.53798734
A329: 45261 | B329: 99928.52 | C329: 116537.31 | D329: 216465.83 | E329: 38455.36 | F329: 39267.09 | G329: 77722.45 | I329: =G329-G328 -> 6049.12 | J329: =G329/G317-1 -> 0.02149246 | L329: =G329/D329 -> 0.35905182 | M329: 251.45499 | N329: =G329*$O$10/'[2]Used Cooking Oil Complex'!$AZ$26 -> 0.1470179 | R329: =B329/D329 -> 0.46163646 | S329: =C329/D329 -> 0.53836354
A330: 45292 | B330: 86141.12 | C330: 103609.29 | D330: 189750.41 | E330: 32928.76 | F330: 34749.07 | G330: 67677.83 | I330: =G330-G329 -> -10044.62 | J330: =G330/G318-1 -> -0.0076888981 | L330: =G330/D330 -> 0.35666764 | M330: 218.93459 | N330: =G330*$O$10/'[2]Used Cooking Oil Complex'!$AZ$26 -> 0.12801774 | R330: =AVERAGE(R327:R329,R318,R306,R294,R282,R270) -> 0.47233334 | S330: =1-R330 -> 0.52766666 | U330: 0.032
A331: 45323 | B331: 83675.88 | C331: 107880.95 | D331: 191556.83 | E331: 31941.15 | F331: 36147.18 | G331: 68088.33 | I331: =G331-G330 -> 410.5 | J331: =G331/G319-1 -> 0.044073911 | L331: =G331/D331 -> 0.35544715 | M331: 220.28176 | N331: =G331*$O$10/'[2]Used Cooking Oil Complex'!$AZ$26 -> 0.12879423 | R331: =AVERAGE(R328:R330,R319,R307,R295,R283,R271) -> 0.46617854 | S331: =1-R331 -> 0.53382146
A332: 45352 | B332: 91163.12 | C332: 118016.26 | D332: 209179.38 | E332: 34804.11 | F332: 39440.14 | G332: 74244.25 | I332: =G332-G331 -> 6155.92 | J332: =G332/G320-1 -> 0.02520487 | L332: =G332/D332 -> 0.35493102 | M332: 240.26326 | N332: =G332*$O$10/'[2]Used Cooking Oil Complex'!$AZ$26 -> 0.14043862 | R332: =AVERAGE(R329:R331,R320,R308,R296,R284,R272) -> 0.47599025 | S332: =1-R332 -> 0.52400975
A333: 45383 | B333: 86846.89 | C333: 114105.16 | D333: 200952.05 | E333: 33125.79 | F333: 38001 | G333: 71126.8 | I333: =G333-G332 -> -3117.45 | J333: =G333/G321-1 -> 0.00076879611 | L333: =G333/D333 -> 0.35394911 | M333: 230.27914 | N333: =G333*$O$10/'[2]Used Cooking Oil Complex'!$AZ$26 -> 0.13454173 | R333: =AVERAGE(R330:R332,R321,R309,R297,R285,R273) -> 0.48435983 | S333: =1-R333 -> 0.51564017 | U333: 0.016
A334: 45413 | B334: 93801 | C334: 121211.6 | D334: 215012.59 | E334: 35781.56 | F334: 40226.29 | G334: 76007.84 | I334: =G334-G333 -> 4881.04 | J334: =G334/G322-1 -> 0.022603393 | L334: =G334/D334 -> 0.35350414 | M334: 246.22607 | N334: =G334*$O$10/'[2]Used Cooking Oil Complex'!$AZ$26 -> 0.14377458 | R334: =AVERAGE(R331:R333,R322,R310,R298,R286,R274) -> 0.47808046 | S334: =1-R334 -> 0.52191954
A335: 45444 | B335: 90289.73 | C335: 117619.86 | D335: 207909.59 | E335: 34433.91 | F335: 38873.66 | G335: 73307.56 | I335: =G335-G334 -> -2700.28 | J335: =G335/G323-1 -> 0.0041530391 | L335: =G335/D335 -> 0.35259345 | M335: 237.72142 | N335: =G335*$O$10/'[2]Used Cooking Oil Complex'!$AZ$26 -> 0.1386668 | R335: =AVERAGE(R332:R334,R323,R311,R299,R287,R275) -> 0.47132453 | S335: =1-R335 -> 0.52867547
A336: 45474 | B336: 92691.59 | C336: 117653.91 | D336: 210345.5 | E336: 35247.2 | F336: 38804.17 | G336: 74051.38 | I336: =G336-G335 -> 743.82 | J336: =G336/G324-1 -> 0.0039016544 | L336: =G336/D336 -> 0.35204642 | M336: 240.39054 | N336: =G336*$O$10/'[2]Used Cooking Oil Complex'!$AZ$26 -> 0.14007379 | R336: =AVERAGE(R333:R335,R324,R312,R300,R288,R276) -> 0.46976535 | S336: =1-R336 -> 0.53023465 | U336: 0.03
A337: 45505 | B337: 93538.24 | C337: 120076.09 | D337: 213614.34 | E337: 35597.13 | F337: 39499.86 | G337: 75096.98 | I337: =G337-G336 -> 1045.6 | J337: =G337/G325-1 -> 0.018994081 | L337: =G337/D337 -> 0.35155402 | M337: 243.93289 | N337: =G337*$O$10/'[2]Used Cooking Oil Complex'!$AZ$26 -> 0.14205162 | R337: =AVERAGE(R334:R336,R325,R313,R301,R289,R277) -> 0.46796281 | S337: =1-R337 -> 0.53203719
A338: 45536 | B338: 88314.86 | C338: 112263.64 | D338: 200578.5 | E338: 33460.24 | F338: 36805.07 | G338: 70265.31 | I338: =G338-G337 -> -4831.67 | J338: =G338/G326-1 -> -0.011078713 | L338: =G338/D338 -> 0.35031327 | M338: 228.34389 | N338: =G338*$O$10/'[2]Used Cooking Oil Complex'!$AZ$26 -> 0.13291215 | R338: =AVERAGE(R335:R337,R326,R314,R302,R290,R278) -> 0.46623253 | S338: =1-R338 -> 0.53376747
A339: 45566 | B339: 93233.73 | C339: 116677.03 | D339: 209910.75 | E339: 35274.24 | F339: 38161.4 | G339: 73435.64 | I339: =G339-G338 -> 3170.33 | J339: =G339/G327-1 -> 0.019118771 | L339: =G339/D339 -> 0.34984221 | M339: 260.30509 | N339: =G339*$O$11/'[2]Used Cooking Oil Complex'!$AZ$26 -> 0.15153717 | R339: =AVERAGE(R336:R338,R327,R315,R303,R291,R279) -> 0.46747512 | S339: =1-R339 -> 0.53252488 | U339: 0.031
A340: 45597 | B340: 95478.53 | C340: 113558.88 | D340: 209037.41 | E340: 36150.29 | F340: 37037.75 | G340: 73188.03 | I340: =G340-G339 -> -247.61 | J340: =G340/G328-1 -> 0.021133384 | L340: =G340/D340 -> 0.35011929 | M340: 259.55742 | N340: =G340*$O$11/'[2]Used Cooking Oil Complex'!$AZ$26 -> 0.15102622 | R340: =AVERAGE(R337:R339,R328,R316,R304,R292,R280) -> 0.4805529 | S340: =1-R340 -> 0.5194471
A341: 45627 | B341: 102300.77 | C341: 117329.59 | D341: 219630.34 | E341: 38682.09 | F341: 38153.78 | G341: 76835.88 | I341: =G341-G340 -> 3647.85 | J341: =G341/G329-1 -> -0.011406872 | L341: =G341/D341 -> 0.34984183 | M341: 259.55742 | N341: =G341*$O$11/'[2]Used Cooking Oil Complex'!$AZ$26 -> 0.15855369 | O341: =AVERAGE(B317-B316,B305-B304,B293-B292,B281-B280,B269-B268) -> 6162.842 | P341: =AVERAGE(C317-C316,C305-C304,C293-C292,C281-C280,C269-C268) -> 4442.904 | Q341: =AVERAGE(D317-D316,D305-D304,D293-D292,D281-D280,D269-D268) -> 10605.754 | R341: =AVERAGE(R338:R340,R329,R317,R305,R293,R281) -> 0.48548389 | S341: =1-R341 -> 0.51451611
A342: 45658 | B342: =D342*R342 -> 105755.58 | C342: =D342*S342 -> 114994.42 | D342: =MROUND((($D$338*$U$339)/3*0.5)+D341,250) -> 220750 | E342: =FORECAST(B342,E$6:E$299,B$6:B$299) -> 41933.454 | F342: =FORECAST(C342,F$6:F$299,C$6:C$299) -> 43095.209 | G342: =FORECAST(D342,G$6:G$299,D$6:D$299) -> 84624.502 | I342: =G342-G341 -> 7788.6219 | J342: =G342/G330-1 -> 0.25040212 | L342: =G342/D342 -> 0.38334995 | M342: 259.55742 | N342: =G342*$O$11/'[2]Used Cooking Oil Complex'!$AZ$26 -> 0.1746258 | O342: =AVERAGE(B318-B317,B306-B305,B294-B293,B282-B281,B270-B269) -> -10421.004 | P342: =AVERAGE(C318-C317,C306-C305,C294-C293,C282-C281,C270-C269) -> -4974.702 | Q342: =AVERAGE(D318-D317,D306-D305,D294-D293,D282-D281,D270-D269) -> -15395.712 | R342: =AVERAGE(R339:R341,R330,R318,R306,R294,R282) -> 0.47907396 | S342: =1-R342 -> 0.52092604 | U342: 0.023
A343: 45689 | B343: =D343*R343 -> 104699.43 | C343: =D343*S343 -> 116800.57 | D343: =MROUND((($D$342*$U$342)/3*0.5)+D342,250) -> 221500 | E343: =FORECAST(B343,E$6:E$299,B$6:B$299) -> 41663.948 | F343: =FORECAST(C343,F$6:F$299,C$6:C$299) -> 43573.23 | G343: =FORECAST(D343,G$6:G$299,D$6:D$299) -> 84817.368 | I343: =G343-G342 -> 192.86577 | J343: =G343/G331-1 -> 0.24569611 | L343: =G343/D343 -> 0.38292265 | N343: =G343*$O$11/'[2]Used Cooking Oil Complex'!$AZ$26 -> 0.17502379 | O343: =AVERAGE(B319-B318,B307-B306,B295-B294,B283-B282,B271-B270) -> -4916.78 | P343: =AVERAGE(C319-C318,C307-C306,C295-C294,C283-C282,C271-C270) -> -495.57 | Q343: =AVERAGE(D319-D318,D307-D306,D295-D294,D283-D282,D271-D270) -> -5412.346 | R343: =AVERAGE(R340:R342,R331,R319,R307,R295,R283) -> 0.47268364 | S343: =1-R343 -> 0.52731636
A344: 45717 | B344: =D344*R344 -> 107343.2 | C344: =D344*S344 -> 114906.8 | D344: =MROUND((($D$342*$U$342)/3*0.5)+D343,250) -> 222250 | E344: =FORECAST(B344,E$6:E$299,B$6:B$299) -> 42338.581 | F344: =FORECAST(C344,F$6:F$299,C$6:C$299) -> 43072.018 | G344: =FORECAST(D344,G$6:G$299,D$6:D$299) -> 85010.233 | I344: =G344-G343 -> 192.86577 | J344: =G344/G332-1 -> 0.14500764 | L344: =G344/D344 -> 0.38249824 | N344: =G344*$O$11/'[2]Used Cooking Oil Complex'!$AZ$26 -> 0.17542177 | O344: =AVERAGE(B320-B319,B308-B307,B296-B295,B284-B283,B272-B271) -> 10465.376 | P344: =AVERAGE(C320-C319,C308-C307,C296-C295,C284-C283,C272-C271) -> 7510.006 | Q344: =AVERAGE(D320-D319,D308-D307,D296-D295,D284-D283,D272-D271) -> 17975.384 | R344: =AVERAGE(R341:R343,R332,R320,R308,R296,R284) -> 0.48298404 | S344: =1-R344 -> 0.51701596
A345: 45748 | B345: =D345*R345 -> 109236.89 | C345: =D345*S345 -> 113763.11 | D345: =MROUND((($D$344*$U$345)/3*0.5)+D344,250) -> 223000 | E345: =FORECAST(B345,E$6:E$299,B$6:B$299) -> 42821.808 | F345: =FORECAST(C345,F$6:F$299,C$6:C$299) -> 42769.325 | G345: =FORECAST(D345,G$6:G$299,D$6:D$299) -> 85203.099 | I345: =G345-G344 -> 192.86577 | J345: =G345/G333-1 -> 0.1979043 | L345: =G345/D345 -> 0.38207668 | N345: =G345*$O$11/'[2]Used Cooking Oil Complex'!$AZ$26 -> 0.17581976 | O345: =AVERAGE(B321-B320,B309-B308,B297-B296,B285-B284,B273-B272) -> -3101.19 | P345: =AVERAGE(C321-C320,C309-C308,C297-C296,C285-C284,C273-C272) -> -4453.856 | Q345: =AVERAGE(D321-D320,D309-D308,D297-D296,D285-D284,D273-D272) -> -7555.05 | R345: =AVERAGE(R342:R344,R333,R321,R309,R297,R285) -> 0.48985153 | S345: =1-R345 -> 0.51014847 | U345: 0.018
A346: 45778 | B346: =D346*R346 -> 108019.51 | C346: =D346*S346 -> 115730.49 | D346: =MROUND((($D$344*$U$345)/3*0.5)+D345,250) -> 223750 | E346: =FORECAST(B346,E$6:E$299,B$6:B$299) -> 42511.159 | F346: =FORECAST(C346,F$6:F$299,C$6:C$299) -> 43290.019 | G346: =FORECAST(D346,G$6:G$299,D$6:D$299) -> 85395.965 | I346: =G346-G345 -> 192.86577 | J346: =G346/G334-1 -> 0.12351522 | L346: =G346/D346 -> 0.38165794 | N346: =G346*$O$11/'[2]Used Cooking Oil Complex'!$AZ$26 -> 0.17621774 | O346: =AVERAGE(B322-B321,B310-B309,B298-B297,B286-B285,B274-B273) -> 4363.488 | P346: =AVERAGE(C322-C321,C310-C309,C298-C297,C286-C285,C274-C273) -> 7321.228 | Q346: =AVERAGE(D322-D321,D310-D309,D298-D297,D286-D285,D274-D273) -> 11684.716 | R346: =AVERAGE(R343:R345,R334,R322,R310,R298,R286) -> 0.48276875 | S346: =1-R346 -> 0.51723125
A347: 45809 | B347: =D347*R347 -> 106753.03 | C347: =D347*S347 -> 117746.97 | D347: =MROUND((($D$344*$U$345)/3*0.5)+D346,250) -> 224500 | E347: =FORECAST(B347,E$6:E$299,B$6:B$299) -> 42187.982 | F347: =FORECAST(C347,F$6:F$299,C$6:C$299) -> 43823.706 | G347: =FORECAST(D347,G$6:G$299,D$6:D$299) -> 85588.831 | I347: =G347-G346 -> 192.86577 | J347: =G347/G335-1 -> 0.16753075 | L347: =G347/D347 -> 0.38124201 | N347: =G347*$O$11/'[2]Used Cooking Oil Complex'!$AZ$26 -> 0.17661573 | O347: =AVERAGE(B323-B322,B311-B310,B299-B298,B287-B286,B275-B274) -> -1905.416 | P347: =AVERAGE(C323-C322,C311-C310,C299-C298,C287-C286,C275-C274) -> 1504.36 | Q347: =AVERAGE(D323-D322,D311-D310,D299-D298,D287-D286,D275-D274) -> -401.052 | R347: =AVERAGE(R344:R346,R335,R323,R311,R299,R287) -> 0.47551461 | S347: =1-R347 -> 0.52448539
A348: 45839 | B348: =D348*R348 -> 106397.52 | C348: =D348*S348 -> 118602.48 | D348: =MROUND((($D$347*$U$348)/3*0.5)+D347,250) -> 225000 | E348: =FORECAST(B348,E$6:E$299,B$6:B$299) -> 42097.263 | F348: =FORECAST(C348,F$6:F$299,C$6:C$299) -> 44050.129 | G348: =FORECAST(D348,G$6:G$299,D$6:D$299) -> 85717.408 | L348: =G348/D348 -> 0.38096626 | N348: =G348*$O$11/'[2]Used Cooking Oil Complex'!$AZ$26 -> 0.17688105 | O348: =AVERAGE(B324-B323,B312-B311,B300-B299,B288-B287,B276-B275) -> 1765.134 | P348: =AVERAGE(C324-C323,C312-C311,C300-C299,C288-C287,C276-C275) -> 2457.934 | Q348: =AVERAGE(D324-D323,D312-D311,D300-D299,D288-D287,D276-D275) -> 4223.058 | R348: =AVERAGE(R345:R347,R336,R324,R312,R300,R288) -> 0.47287785 | S348: =1-R348 -> 0.52712215 | U348: 0.015
A349: 45870 | B349: =D349*R349 -> 106104.74 | C349: =D349*S349 -> 119395.26 | D349: =MROUND((($D$347*$U$348)/3*0.5)+D348,250) -> 225500 | E349: =FORECAST(B349,E$6:E$299,B$6:B$299) -> 42022.553 | F349: =FORECAST(C349,F$6:F$299,C$6:C$299) -> 44259.948 | G349: =FORECAST(D349,G$6:G$299,D$6:D$299) -> 85845.985 | L349: =G349/D349 -> 0.38069173 | N349: =G349*$O$11/'[2]Used Cooking Oil Complex'!$AZ$26 -> 0.17714638 | O349: =AVERAGE(B325-B324,B313-B312,B301-B300,B289-B288,B277-B276) -> 73.982 | P349: =AVERAGE(C325-C324,C313-C312,C301-C300,C289-C288,C277-C276) -> -158.524 | Q349: =AVERAGE(D325-D324,D313-D312,D301-D300,D289-D288,D277-D276) -> -84.53 | R349: =AVERAGE(R346:R348,R337,R325,R313,R301,R289) -> 0.47053099 | S349: =1-R349 -> 0.52946901
A350: 45901 | B350: =D350*R350 -> 105931.97 | C350: =D350*S350 -> 120318.03 | D350: =MROUND((($D$344*$U$345)/3*0.5)+D349,250) -> 226250 | E350: =FORECAST(B350,E$6:E$299,B$6:B$299) -> 41978.466 | F350: =FORECAST(C350,F$6:F$299,C$6:C$299) -> 44504.171 | G350: =FORECAST(D350,G$6:G$299,D$6:D$299) -> 86038.851 | L350: =G350/D350 -> 0.38028221 | N350: =G350*$O$11/'[2]Used Cooking Oil Complex'!$AZ$26 -> 0.17754436 | O350: =AVERAGE(B326-B325,B314-B313,B302-B301,B290-B289,B278-B277) -> -3549.892 | P350: =AVERAGE(C326-C325,C314-C313,C302-C301,C290-C289,C278-C277) -> -3840.29 | Q350: =AVERAGE(D326-D325,D314-D313,D302-D301,D290-D289,D278-D277) -> -7390.188 | R350: =AVERAGE(R347:R349,R338,R326,R314,R302,R290) -> 0.4682076 | S350: =1-R350 -> 0.5317924
A351: 45931 | B351: =D351*R351 -> 106516.77 | C351: =D351*S351 -> 120733.23 | D351: =MROUND((($D$338*$U$339)/3*0.5)+D350,250) -> 227250 | E351: =FORECAST(B351,E$6:E$299,B$6:B$299) -> 42127.693 | F351: =FORECAST(C351,F$6:F$299,C$6:C$299) -> 44614.06 | G351: =FORECAST(D351,G$6:G$299,D$6:D$299) -> 86296.005 | L351: =G351/D351 -> 0.3797404 | N351: =G351*$O$11/'[2]Used Cooking Oil Complex'!$AZ$26 -> 0.17807501 | O351: =AVERAGE(B327-B326,B315-B314,B303-B302,B291-B290,B279-B278) -> 3479.734 | P351: =AVERAGE(C327-C326,C315-C314,C303-C302,C291-C290,C279-C278) -> 2852.12 | Q351: =AVERAGE(D327-D326,D315-D314,D303-D302,D291-D290,D279-D278) -> 6331.856 | R351: =AVERAGE(R348:R350,R339,R327,R315,R303,R291) -> 0.46872064 | S351: =1-R351 -> 0.53127936 | U351: 0.013
...

Sheet Chart Data
A1: Food at Home - Constant $
B2: Jan | C2: Feb | D2: Mar | E2: Apr | F2: May | G2: Jun | H2: Jul | I2: Aug | J2: Sep | K2: Oct | L2: Nov | M2: Dec
A3: 1997 | B3: 22407.044 | C3: 20823.225 | D3: 23360.066 | E3: 22225.236 | F3: 24051.395 | G3: 22898.897 | H3: 23889.25 | I3: 23714.65 | J3: 22355.336 | K3: 23361.335 | L3: 23314.793 | M3: 25681.366
A4: 1998 | B4: 22056.769 | C4: 20533.077 | D4: 22417.435 | E4: 22747.234 | F4: 23800.559 | G4: 23126.401 | H4: 24140.89 | I4: 23560.868 | J4: 22709.112 | K4: 23601.398 | L4: 23349.212 | M4: 26512.421
A5: 1999 | B5: 22389.009 | C5: 21182.697 | D5: 23626.46 | E5: 23264.541 | F5: 24476.836 | G5: 23860.386 | H5: 24956.359 | I5: 24110.756 | J5: 23707.904 | K5: 24071.901 | L5: 24211.883 | M5: 28464.018
A6: 2000 | B6: 22494.397 | C6: 22325.656 | D6: 24322.169 | E6: 23938.016 | F6: 24796.488 | G6: 24814.534 | H6: 24862.126 | I6: 24808.309 | J6: 24099.806 | K6: 24309.184 | L6: 25202.428 | M6: 28325.761
A7: 2001 | B7: 23663.861 | C7: 22424.296 | D7: 24756.646 | E7: 24121.097 | F7: 25597.627 | G7: 24978.552 | H7: 24829.759 | I7: 25358.776 | J7: 24086.171 | K7: 24559.617 | L7: 25342.369 | M7: 28200.011
A8: 2002 | B8: 23593.558 | C8: 22340.642 | D8: 25101.694 | E8: 23516.051 | F8: 25846.664 | G8: 24907.686 | H8: 25362.399 | I8: 25751.155 | J8: 23846.498 | K8: 25089.866 | L8: 25989.792 | M8: 28147.276
A9: 2003 | B9: 24789.864 | C9: 23230.79 | D9: 25271.693 | E9: 24890.966 | F9: 26326.461 | G9: 24996.652 | H9: 26028.592 | I9: 26122.375 | J9: 24471.973 | K9: 25453.577 | L9: 25751.32 | M9: 28273.706
A10: 2004 | B10: 25088.937 | C10: 23857.366 | D10: 25258.692 | E10: 25343.68 | F10: 26273.771 | G10: 25337.626 | H10: 26301.911 | I10: 25644.558 | J10: 25206.219 | K10: 25948.934 | L10: 26323.597 | M10: 29901.646
A11: 2005 | B11: 25306.859 | C11: 24056.212 | D11: 26798.783 | E11: 25756.687 | F11: 26894.728 | G11: 26768.96 | H11: 27280.006 | I11: 27237.495 | J11: 26532.971 | K11: 27160.903 | L11: 27515.958 | M11: 31229.531
A12: 2006 | B12: 25717.198 | C12: 24860.255 | D12: 27221.805 | E12: 27086.981 | F12: 28418.298 | G12: 27873.328 | H12: 28136.698 | I12: 28283.171 | J12: 26797.21 | K12: 27271.675 | L12: 28332.908 | M12: 32125.349
A13: 2007 | B13: 26834.401 | C13: 25428.988 | D13: 27982.701 | E13: 26932.787 | F13: 28703.294 | G13: 28077.346 | H13: 28006.418 | I13: 28341.083 | J13: 26757.483 | K13: 27447.837 | L13: 28732.712 | M13: 32048.264
A14: 2008 | B14: 26954.829 | C14: 26253.075 | D14: 28072.502 | E14: 26662.683 | F14: 29068.69 | G14: 27689.999 | H14: 28083.625 | I14: 27937.575 | J14: 25842.35 | K14: 26643.408 | L14: 26852.565 | M14: 29207.606
... A29: 2023 | B29: 38080.767 | C29: 37720.272 | D29: 38144.427 | E29: 38314.022 | F29: 37965.513 | G29: 37568.56 | H29: 37453.553 | I29: 37329.538 | J29: 37283.931 | K29: 37384.734 | L29: 38062.741 | M29: 38419.984
A30: 5-Year Average | B30: =AVERAGE(B24:B28) -> 32676.654 | C30: =AVERAGE(C24:C28) -> 30386.378 | D30: =AVERAGE(D24:D28) -> 35141.988 | E30: =AVERAGE(E24:E28) -> 32939.848 | F30: =AVERAGE(F24:F28) -> 34876.329 | G30: =AVERAGE(G24:G28) -> 33881.227 | H30: =AVERAGE(H24:H28) -> 34460.953 | I30: =AVERAGE(I24:I28) -> 34419.26 | ... M30: =AVERAGE(M24:M28) -> 37764.573
A31: 5-Year Maximum | B31: =MAX(B24:B28) -> 34525.217 | C31: =MAX(C24:C28) -> 31476.53 | D31: =MAX(D24:D28) -> 38893.415 | E31: =MAX(E24:E28) -> 35013.506 | F31: =MAX(F24:F28) -> 36623.522 | G31: =MAX(G24:G28) -> 35650.433 | H31: =MAX(H24:H28) -> 36189.165 | I31: =MAX(I24:I28) -> 36099.719 | ... M31: =MAX(M24:M28) -> 39812.382
A32: 5-Year Minimum | B32: =MIN(B24:B28) -> 30671.076 | C32: =MIN(C24:C28) -> 29077.776 | D32: =MIN(D24:D28) -> 32634.074 | E32: =MIN(E24:E28) -> 30569.385 | F32: =MIN(F24:F28) -> 33223.503 | G32: =MIN(G24:G28) -> 32395.957 | H32: =MIN(H24:H28) -> 32462.294 | I32: =MIN(I24:I28) -> 32970.321 | ... M32: =MIN(M24:M28) -> 36225.457
A33: Percent Change from 5-Year Average | B33: =(B29-B30)/B30 -> 0.16538146 | C33: =(C29-C30)/C30 -> 0.24135467 | D33: =(D29-D30)/D30 -> 0.085437351 | E33: =(E29-E30)/E30 -> 0.16315114 | F33: =(F29-F30)/F30 -> 0.088575387 | G33: =(G29-G30)/G30 -> 0.10883116 | H33: =(H29-H30)/H30 -> 0.086840321 | I33: =(I29-I30)/I30 -> 0.084553786 | ... M33: =(M29-M30)/M30 -> 0.017355174
A35: Food Away from Home - Constant $
B36: =B2 -> Jan | C36: =C2 -> Feb | D36: =D2 -> Mar | E36: =E2 -> Apr | F36: =F2 -> May | G36: =G2 -> Jun | H36: =H2 -> Jul | I36: =I2 -> Aug | ... M36: =M2 -> Dec
A37: 1997 | B37: 16833.029 | C37: 16687.749 | D37: 18461.604 | E37: 18262.775 | F37: 19579.349 | G37: 18995.715 | H37: 19564.803 | I37: 19978.139 | J37: 18328.005 | K37: 18804.233 | L37: 17708.805 | M37: 18465.044
A38: 1998 | B38: 17349.567 | C38: 17047.883 | D38: 18764.336 | E38: 18785.7 | F38: 20055.175 | G38: 19615.106 | H38: 20013.269 | I38: 20024.483 | J38: 18681.762 | K38: 19644.222 | L38: 18339.136 | M38: 19385.502
A39: 1999 | B39: 17750.248 | C39: 17603.995 | D39: 19180.641 | E39: 19492.808 | F39: 20315.232 | G39: 19983.958 | H39: 20689.083 | I39: 20285.118 | J39: 19131.384 | K39: 20173.924 | L39: 18976.399 | M39: 20087.586
A40: 2000 | B40: 18590.579 | C40: 19136.004 | D40: 20807.108 | E40: 20573.873 | F40: 21187.727 | G40: 21358.505 | H40: 21643.636 | I40: 21406.812 | J40: 20554.566 | K40: 20686.67 | L40: 19705.955 | M40: 20685.722
A41: 2001 | B41: 19134.882 | C41: 18926.327 | D41: 21154.409 | E41: 20425.431 | F41: 21557.323 | G41: 21715.633 | H41: 21710.143 | I41: 22085.647 | J41: 20048.037 | K41: 20443.331 | L41: 19791.326 | M41: 21224.134
A42: 2002 | B42: 19381.39 | C42: 19222.497 | D42: 21459.609 | E42: 21015.188 | F42: 22039.508 | G42: 21874.284 | H42: 22032.994 | I42: 22585.62 | J42: 20507.433 | K42: 20962.634 | L42: 20498.38 | M42: 21412.572
A43: 2003 | B43: 19858.907 | C43: 19411.259 | D43: 21847.216 | E43: 21293.37 | F43: 23106.223 | G43: 22434.852 | H43: 23003.465 | I43: 23683.267 | J43: 21262.152 | K43: 22255.107 | L43: 21295.5 | M43: 22157.479
A44: 2004 | B44: 21172.744 | C44: 21217.012 | D44: 22840.624 | E44: 22657.875 | F44: 23524.899 | G44: 23088.831 | H44: 24165.009 | I44: 23426.797 | J44: 22117.369 | K44: 23123.527 | L44: 21719.25 | M44: 23479.564
A45: 2005 | B45: 21371.237 | C45: 21260.516 | D45: 23266.218 | E45: 23701.852 | F45: 24101.74 | G45: 23864.962 | H45: 24727.279 | I45: 24250.46 | J45: 23033.328 | K45: 23632.258 | L45: 22461.534 | M45: 24275.898
A46: 2006 | B46: 22524.395 | C46: 21917.017 | D46: 24546.312 | E46: 24112.978 | F46: 24807.664 | G46: 24639.607 | H46: 24939.077 | I46: 25057.198 | J46: 23983.89 | K46: 24117.46 | L46: 22943.031 | M46: 25381.092
A47: 2007 | B47: 22710.497 | C47: 22284.185 | D47: 25410.326 | E47: 24357.687 | F47: 25536.09 | G47: 25621.784 | H47: 25520.674 | I47: 25675.616 | J47: 24008.941 | K47: 24485.737 | L47: 23550.863 | M47: 25166.411
A48: 2008 | B48: 22871.836 | C48: 23094.33 | D48: 24694.167 | E48: 24274.919 | F48: 25947.841 | G48: 24829.176 | H48: 25157.473 | I48: 25513.177 | J48: 23298.519 | K48: 23911.259 | L48: 22581.42 | M48: 23312.382
... A63: 2023 | B63: 38568.83 | C63: 38876.631 | D63: 38370.012 | E63: 38061.24 | F63: 38290.23 | G63: 38569.502 | H63: 38622.502 | I63: 38684.851 | J63: 38665.818 | K63: 38627.561 | L63: 37990.2 | M63: 37685.774
A64: 5-Year Average | B64: =AVERAGE(B58:B62) -> 31071.437 | C64: =AVERAGE(C58:C62) -> 30837.921 | D64: =AVERAGE(D58:D62) -> 33581.656 | E64: =AVERAGE(E58:E62) -> 31375.028 | F64: =AVERAGE(F58:F62) -> 34144.967 | G64: =AVERAGE(G58:G62) -> 34565.68 | H64: =AVERAGE(H58:H62) -> 35216.737 | I64: =AVERAGE(I58:I62) -> 35086.167 | ... M64: =AVERAGE(M58:M62) -> 33629.237
A65: 5-Year Maximum | B65: =MAX(B58:B62) -> 32835.51 | C65: =MAX(C58:C62) -> 33357.153 | D65: =MAX(D58:D62) -> 37027.839 | E65: =MAX(E58:E62) -> 37540.811 | F65: =MAX(F58:F62) -> 38887.626 | G65: =MAX(G58:G62) -> 37849.847 | H65: =MAX(H58:H62) -> 38310.099 | I65: =MAX(I58:I62) -> 37734.172 | ... M65: =MAX(M58:M62) -> 38170.453
A66: 5-Year Minimum | B66: =MIN(B58:B62) -> 30034.351 | C66: =MIN(C58:C62) -> 28777.659 | D66: =MIN(D58:D62) -> 26619.217 | E66: =MIN(E58:E62) -> 17536.834 | F66: =MIN(F58:F62) -> 23832.145 | G66: =MIN(G58:G62) -> 28283.266 | H66: =MIN(H58:H62) -> 29915.058 | I66: =MIN(I58:I62) -> 30548.208 | ... M66: =MIN(M58:M62) -> 26599.193
A67: Percent Change from 5-Year Average | B67: =(B63-B64)/B64 -> 0.24129531 | C67: =(C63-C64)/C64 -> 0.26067614 | D67: =(D63-D64)/D64 -> 0.14258843 | E67: =(E63-E64)/E64 -> 0.21310618 | F67: =(F63-F64)/F64 -> 0.12140189 | G67: =(G63-G64)/G64 -> 0.11583231 | H67: =(H63-H64)/H64 -> 0.096708704 | I67: =(I63-I64)/I64 -> 0.10256703 | ... M67: =(M63-M64)/M64 -> 0.1206253
A69: Food Expendatures at Home - Nominal $
B70: =B2 -> Jan | C70: =C2 -> Feb | D70: =D2 -> Mar | E70: =E2 -> Apr | F70: =F2 -> May | G70: =G2 -> Jun | H70: =H2 -> Jul | I70: =I2 -> Aug | ... M70: =M2 -> Dec
A71: 1997 | B71: 30334.111 | C71: 28154.23 | D71: 31584.1 | E71: 30011.506 | F71: 32477.244 | G71: 30881.499 | H71: 32298.722 | I71: 32224.972 | J71: 30396.65 | K71: 31844.197 | L71: 31800.275 | M71: 35049.619
A72: 1998 | B72: 30442.638 | C72: 28163.253 | D72: 30786.005 | E72: 31238.784 | F72: 32787.337 | G72: 31819.138 | H72: 33277.357 | I72: 32599.474 | J72: 31382.628 | K72: 32879.518 | L72: 32529.107 | M72: 36959.886
A73: 1999 | B73: 31539.112 | C73: 29749.964 | D73: 33102.007 | E73: 32615.658 | F73: 34399.825 | G73: 33493 | H73: 35031.731 | I73: 33927.561 | J73: 33441.948 | K73: 34079.02 | L73: 34276.789 | M73: 40369.073
A74: 2000 | B74: 32075.51 | C74: 31834.288 | D74: 34701.465 | E74: 34173.549 | F74: 35611.489 | G74: 35594.819 | H74: 35876.392 | I74: 35926.671 | J74: 34921.78 | K74: 35246.676 | L74: 36477.849 | M74: 41339.761
A75: 2001 | B75: 34760.399 | C75: 33036.753 | D75: 36516.397 | E75: 35621.211 | F75: 37934.238 | G75: 37124.591 | H75: 37031.768 | I75: 37886.449 | J75: 36006.12 | K75: 36903.633 | L75: 37971.215 | M75: 42252.853
A76: 2002 | B76: 35654.235 | C76: 33722.286 | D76: 37954.217 | E76: 35576.447 | F76: 38902.29 | G76: 37381.601 | H76: 38106.824 | I76: 38623.86 | J76: 35827.599 | K76: 37673.188 | L76: 39112.512 | M76: 42502.877
A77: 2003 | B77: 37559.421 | C77: 35375.481 | D77: 38503.999 | E77: 37837.715 | F77: 40131.982 | G77: 38340.008 | H77: 39922.375 | I77: 40245.121 | J77: 37786.279 | K77: 39607.507 | L77: 40269.744 | M77: 44626.775
A78: 2004 | B78: 39579.078 | C78: 37636.777 | D78: 39913.028 | E78: 40004.434 | F78: 42036.328 | G78: 40582.548 | H78: 42195.206 | I78: 41053.176 | J78: 40222.244 | K78: 41808.371 | L78: 42457.597 | M78: 48331.682
A79: 2005 | B79: 40992.021 | C79: 38780.89 | D79: 43225.494 | E79: 41920.408 | F79: 43888.255 | G79: 43476.719 | H79: 44400.597 | I79: 44261.606 | J79: 43230.756 | K79: 44440.443 | L79: 45068.813 | M79: 51339.061
A80: 2006 | B80: 42652.314 | C80: 41060.543 | D80: 44890.832 | E80: 44482.327 | F80: 46765.539 | G80: 45939.681 | H80: 46469.296 | I80: 46831.277 | J80: 44599.266 | K80: 45621.204 | L80: 47200.295 | M80: 53515.863
A81: 2007 | B81: 45245.25 | C81: 43205.648 | D81: 47680.49 | E81: 45949.048 | F81: 49292.17 | G81: 48365.139 | H81: 48351.291 | I81: 49105.679 | J81: 46607.401 | K81: 48079.376 | L81: 50433.253 | M81: 56382.506
A82: 2008 | B82: 48065.408 | C82: 46894.372 | D82: 50116.591 | E82: 48207.597 | F82: 52812.803 | G82: 50621.196 | H82: 51973.091 | I82: 52058.733 | J82: 48460.74 | K82: 50201.244 | L82: 50465.876 | M82: 54793.913
... A94: 2020 | B94: 65927.395 | C94: 63667.664 | D94: 80197.887 | E94: 69951.719 | F94: 75467.184 | G94: 72075.356 | H94: 74914.883 | I94: 73410.99 | J94: 70391.774 | K94: 73721.54 | L94: 74369.724 | M94: 80446.196
A95: 2021 | B95: 73214.926 | C95: 67069.075 | D95: 77283.232 | E95: 75021.359 | F95: 79189.626 | G95: 77442.997
A96: Food Expendatures Away From Home - Nominal $
B97: =B2 -> Jan | C97: =C2 -> Feb | D97: =D2 -> Mar | E97: =E2 -> Apr | F97: =F2 -> May | G97: =G2 -> Jun | H97: =H2 -> Jul | I97: =I2 -> Aug | ... M97: =M2 -> Dec
A98: 1997 | B98: 21457.621 | C98: 21313.572 | D98: 23639.873 | E98: 23415.44 | F98: 25119.815 | G98: 24418.138 | H98: 25230.396 | I98: 25813.133 | J98: 23741.773 | K98: 24421.047 | L98: 23057.232 | M98: 24103.272
A99: 1998 | B99: 22676.464 | C99: 22338.796 | D99: 24634.769 | E99: 24709.54 | F99: 26445.52 | G99: 25881.486 | H99: 26472.573 | I99: 26552.996 | J99: 24864.221 | K99: 26176.95 | L99: 24482.403 | M99: 25942.126
A100: 1999 | B100: 23825.754 | C100: 23672.014 | D100: 25854.369 | E100: 26322.537 | F100: 27449.288 | G100: 27001.328 | H100: 28038.751 | I100: 27574.471 | J100: 26037.631 | K100: 27522.973 | L100: 25936.281 | M100: 27504.98
A101: 2000 | B101: 25516.838 | C101: 26328.918 | D101: 28680.06 | E101: 28392.995 | F101: 29275.588 | G101: 29564.811 | H101: 30048.995 | I101: 29791.143 | J101: 28690.092 | K101: 28926.046 | L101: 27571.472 | M101: 29010.853
A102: 2001 | B102: 26930.687 | C102: 26699.783 | D102: 29930.24 | E102: 28966.207 | F102: 30642.368 | G102: 30956.596 | H102: 31037.823 | I102: 31683.249 | J102: 28825.693 | K102: 29477.544 | L102: 28569.356 | M102: 30671.799
A103: 2002 | B103: 28071.665 | C103: 27935.483 | D103: 31203.434 | E103: 30573.727 | F103: 32135.579 | G103: 32001.707 | H103: 32287.489 | I103: 33152.298 | J103: 30168.625 | K103: 30906.6 | L103: 30255.315 | M103: 31656.952
A104: 2003 | B104: 29327.01 | C104: 28793.146 | D104: 32460.028 | E104: 31654.472 | F104: 34425.219 | G104: 33498.622 | H104: 34423.234 | I104: 35498.954 | J104: 31904.993 | K104: 33486.52 | L104: 32130.266 | M104: 33522.005
A105: 2004 | B105: 32136.745 | C105: 32308.589 | D105: 34837.273 | E105: 34632.872 | F105: 36054.514 | G105: 35442.775 | H105: 37253.082 | I105: 36229.966 | J105: 34295.185 | K105: 35949.662 | L105: 33801.534 | M105: 36598.239
A106: 2005 | B106: 33469.158 | C106: 33399.954 | D106: 36607.769 | E106: 37370.787 | F106: 38100.131 | G106: 37843.461 | H106: 39292.335 | I106: 38654.538 | J106: 36790.69 | K106: 37864.509 | L106: 36063.37 | M106: 39057.267
A107: 2006 | B107: 36351.426 | C107: 35480.152 | D107: 39818.125 | E107: 39195.113 | F107: 40467.456 | G107: 40294.837 | H107: 40887.142 | I107: 41183.646 | J107: 39478.441 | K107: 39816.712 | L107: 37971.414 | M107: 42130.693
A108: 2007 | B108: 37877.836 | C108: 37301.115 | D108: 42569.425 | E108: 40934.217 | F108: 43020.974 | G108: 43312.947 | H108: 43351.31 | I108: 43789.066 | J108: 41154.22 | K108: 42067.101 | L108: 40574.221 | M108: 43437.473
A109: 2008 | B109: 39635.893 | C109: 40176.172 | D109: 43094.295 | E109: 42472.545 | F109: 45588.77 | G109: 43837.544 | H109: 44698.6 | I109: 45474.523 | J109: 41749.182 | K109: 43055.765 | L109: 40800.113 | M109: 42242.567
... A124: 2023 | B124: 97701.013 | C124: 98860.41 | D124: 96952.126 | E124: 95789.073 | F124: 96651.611 | G124: 97703.547 | H124: 97903.181 | I124: 98138.032 | J124: 98066.341 | K124: 97922.239 | L124: 95521.487 | M124: 94374.803
A125: Total Food Expendatures - Nominal $
B126: =B97 -> Jan | C126: =C97 -> Feb | D126: =D97 -> Mar | E126: =E97 -> Apr | F126: =F97 -> May | G126: =G97 -> Jun | H126: =H97 -> Jul | I126: =I97 -> Aug | ... M126: =M97 -> Dec
A127: 1997 | B127: 51791.734 | C127: 49467.801 | D127: 55223.973 | E127: 53426.945 | F127: 57597.059 | G127: 55299.637 | H127: 57529.117 | I127: 58038.105 | J127: 54138.422 | K127: 56265.242 | L127: 54857.508 | M127: 59152.891
A128: 1998 | B128: 53119.102 | C128: 50502.051 | D128: 55420.773 | E128: 55948.324 | F128: 59232.855 | G128: 57700.625 | H128: 59749.93 | I128: 59152.469 | J128: 56246.848 | K128: 59056.469 | L128: 57011.508 | M128: 62902.012
A129: 1999 | B129: 55364.867 | C129: 53421.977 | D129: 58956.375 | E129: 58938.195 | F129: 61849.113 | G129: 60494.328 | H129: 63070.48 | I129: 61502.031 | J129: 59479.578 | K129: 61601.992 | L129: 60213.07 | M129: 67874.055
A130: 2000 | B130: 57592.348 | C130: 58163.207 | D130: 63381.527 | E130: 62566.543 | F130: 64887.078 | G130: 65159.629 | H130: 65925.391 | I130: 65717.812 | J130: 63611.871 | K130: 64172.723 | L130: 64049.32 | M130: 70350.617
A131: 2001 | B131: 61691.086 | C131: 59736.535 | D131: 66446.633 | E131: 64587.418 | F131: 68576.602 | G131: 68081.188 | H131: 68069.594 | I131: 69569.695 | J131: 64831.812 | K131: 66381.18 | L131: 66540.57 | M131: 72924.656
A132: 2002 | B132: 63725.898 | C132: 61657.77 | D132: 69157.648 | E132: 66150.172 | F132: 71037.867 | G132: 69383.305 | H132: 70394.312 | I132: 71776.156 | J132: 65996.227 | K132: 68579.789 | L132: 69367.828 | M132: 74159.828
A133: 2003 | B133: 66886.43 | C133: 64168.629 | D133: 70964.023 | E133: 69492.188 | F133: 74557.203 | G133: 71838.633 | H133: 74345.609 | I133: 75744.078 | J133: 69691.273 | K133: 73094.023 | L133: 72400.008 | M133: 78148.781
A134: 2004 | B134: 71715.82 | C134: 69945.367 | D134: 74750.297 | E134: 74637.305 | F134: 78090.844 | G134: 76025.32 | H134: 79448.289 | I134: 77283.141 | J134: 74517.43 | K134: 77758.031 | L134: 76259.133 | M134: 84929.922
A135: 2005 | B135: 74461.18 | C135: 72180.844 | D135: 79833.266 | E135: 79291.195 | F135: 81988.383 | G135: 81320.18 | H135: 83692.93 | I135: 82916.141 | J135: 80021.445 | K135: 82304.953 | L135: 81132.18 | M135: 90396.328 | P135: {=- Need to update} -> #NAME?
A136: 2006 | B136: 79003.742 | C136: 76540.695 | D136: 84708.961 | E136: 83677.438 | F136: 87232.992 | G136: 86234.516 | H136: 87356.438 | I136: 88014.922 | J136: 84077.711 | K136: 85437.914 | L136: 85171.711 | M136: 95646.555
A137: 2007 | B137: 83123.086 | C137: 80506.766 | D137: 90249.914 | E137: 86883.266 | F137: 92313.141 | G137: 91678.086 | H137: 91702.602 | I137: 92894.742 | J137: 87761.617 | K137: 90146.477 | L137: 91007.477 | M137: 99819.977
A138: 2008 | B138: 87701.305 | C138: 87070.547 | D138: 93210.883 | E138: 90680.141 | F138: 98401.57 | G138: 94458.742 | H138: 96671.695 | I138: 97533.258 | J138: 90209.922 | K138: 93257.008 | L138: 91265.992 | M138: 97036.484
A139: 2009 | B139: 88710.516 | C139: 83671.609 | D139: 90271.047 | E139: 89992.93 | F139: 95557.016 | G139: 91994.117 | H139: 94254.336 | I139: 93584.906 | J139: 88415.164 | K139: 92410.711 | L139: 90191.961 | M139: 98844.562
A140: 2010 | B140: 88656.359 | C140: 86082.359 | D140: 94158.695 | E140: 92923.602 | F140: 97043.508 | G140: 94019.008 | H140: 97089.812 | I140: 95537.531 | J140: 91442.516 | K140: 95043.25 | L140: 93805.203 | M140: 102870.45
A141: 2011 | B141: 91798.633 | C141: 89895.797 | D141: 99160.727 | E141: 99461.375 | F141: 101971.79 | G141: 100626.76 | H141: 102970.35 | I141: 101767.65 | J141: 97919.328 | K141: 100440.99 | L141: 99220.758 | M141: 108961.84
A142: 2012 | B142: 96381.898 | C142: 97672.688 | D142: 106142.39 | E142: 102282.8 | F142: 107113.21 | G142: 105304.62 | H142: 105047.37 | I142: 106829.02 | J142: 101381.71 | K142: 103847.56 | L142: 104409.47 | M142: 112709.21
A143: 2013 | B143: 100803.12 | C143: 98448.414 | D143: 110489.34 | E143: 104259.84 | F143: 111156.62 | G143: 107636.8 | H143: 108624.83 | I143: 110966.94 | J143: 103249.06 | K143: 107999.45 | L143: 109287.27 | M143: 115910.76
A144: 2014 | B144: 104767.27 | C144: 101465.4 | D144: 112867.71 | E144: 110637.09 | F144: 117836.19 | G144: 112386.2 | H144: 114978.9 | I144: 117006.81 | J144: 109571.27 | K144: 115502.98 | L144: 114309.23 | M144: 122902.74
A145: 2015 | B145: 116161.38 | C145: 110913.72 | D145: 123260.2 | E145: 120837.02 | F145: 128504.48 | G145: 122964.58 | H145: 126271.11 | I145: 125580.41 | J145: 119180.13 | K145: 125216.43 | L145: 121815.88 | M145: 133300.3
A146: 2016 | B146: 119363.48 | C146: 118936.55 | D146: 128330.71 | E146: 126738.62 | F146: 131117.95 | G146: 128271.87 | H146: 130838.43 | I146: 129300.7 | J146: 125251.2 | K146: 129226.42 | L146: 128184.52 | M146: 140604.38
A147: 2017 | B147: 125097.76 | C147: 122034.98 | D147: 136352.03 | E147: 134031.03 | F147: 138668.92 | G147: 136197.41 | H147: 136826.27 | I147: 137430.97 | J147: 133144.05 | K147: 135463.98 | L147: 135624.84 | M147: 149525.12
... A153: 2023 | B153: 188250 | C153: 188000 | D153: 187750 | E153: 187250 | F153: 186750 | G153: 186250 | H153: 186000 | I153: 185750 | J153: 185500 | K153: 185750 | L153: 186000 | M153: 186250
A154: Five-Year Average | B154: =AVERAGE(B148:B152) -> 144620.7 | C154: =AVERAGE(C148:C152) -> 139613.83 | D154: =AVERAGE(D148:D152) -> 157006.18 | E154: =AVERAGE(E148:E152) -> 148120.76 | F154: =AVERAGE(F148:F152) -> 159668.44 | G154: =AVERAGE(G148:G152) -> 159252.62 | H154: =AVERAGE(H148:H152) -> 162759.01 | I154: =AVERAGE(I148:I152) -> 162728.53 | ... M154: =AVERAGE(M148:M152) -> 165434.18
A155: Change from 5-Year Average | B155: =B153-B154 -> 43629.298 | C155: =C153-C154 -> 48386.173 | D155: =D153-D154 -> 30743.822 | E155: =E153-E154 -> 39129.239 | F155: =F153-F154 -> 27081.556 | G155: =G153-G154 -> 26997.384 | H155: =H153-H154 -> 23240.994 | I155: =I153-I154 -> 23021.472 | ... M155: =M153-M154 -> 20815.822

Sheet quarterly series
A1: 2005:1 | B1: release: | C1: 2023_3
A2: 2038:4
B4: GDPR | C4: CR | D4: CPIU | E4: IRFF | F4: IRG10Y | G4: UR | H4: IND | I4: INDM | J4: INDMD | K4: INDMN | L4: PPI | M4: PWTI | N4: PBRENT | O4: PNGAS | P4: HSTARTS | Q4: NETEXM | R4: IRPRIME | S4: CNR | T4: IRG3M | U4: IRG30Y | V4: ZAR | W4: ECI | X4: YDR | Y4: KFRB | Z4: UKFRB | AA4: JQZMHNF | AB4: JQZMHM | AC4: PMOIL | AD4: PGDP | AE4: PICNR | AF4: PICR | AG4: POP | AH4: HH | AI4: PPIIG | AJ4: PPIIND | AK4: GDP | AM4: PPI051 | AN4: PPI053 | AO4: PPI054 | AP4: PPI057 | AQ4: PPI06 | AR4: PPI07 | AS4: PPIENERGY | AT4: PPI05 | AU4: PPIFOOD | AV4: GDPR_CA | AW4: CR_CA | AX4: IND_CA | AY4: CPI_CA | AZ4: HSTARTS_CA | BA4: XRUSCA | BB4: YPR_CA | BC4: AHEM_CA | BD4: UR_CA | BE4: PPI_CA | BF4: IRG3M_CA | BG4: IRBANK_CA | BH4: IRG10Y_CA | BI4: PICNRR_CA | BJ4: PGDPR_CA | BK4: POIL_CA | BL4: PWTI_CA | BM4: INDMD_CA | BN4: INDMN_CA | BO4: N_CA | BP4: XRCAUS | BQ4: YP_CA | BR4: TRANSP_CA | BS4: GDPR_EMU | BT4: CR_EMU | BU4: IND_EMU | BV4: CPI_EMU | BW4: PPI_EMU | BX4: XRUSEU | BY4: IRG10Y_DE | BZ4: IRG10Y_FI | CA4: IRG10Y_SE | CB4: XRGBUS | CC4: XRSEUS | CD4: IND_DE | CE4: IND_FR | CF4: IND_IT | CG4: IND_GB | CH4: INDCN_DE | CI4: INDCN_FR | CJ4: INDCN_IT | CK4: INDCN_GB | CL4: CPI_GY | CM4: PPI_DE | CN4: CPI_PT | CO4: PPI_ES | CP4: XREUUS | CQ4: INDCN_EMU | CR4: IRECR_DE | CS4: PBRENT_EUR | CT4: XRRUUS | CU4: XRCZUS | CV4: XRCZEU | CW4: PPIIND_FI | CX4: PPIIND_PT | CY4: PPIIND_SE | CZ4: PPIIND_AT | DA4: PPIIND_CZ | DB4: PPI_RU | DC4: AHEM_RU_YY | DD4: AHEM_DE | DE4: AHEM_FI | DF4: AHEM_SP | DG4: AHEM_PT | DH4: AHEM_SE | DI4: AHEM_AT | DJ4: AHEM_CZ | DK4: PELEC_FN | DL4: PPICHEM_FN | DM4: PELEC_GY | DN4: PPICHEM_GY | DO4: PELEC_SP | DP4: PPICHEM_SP | DQ4: PELEC_SW | DR4: PPICHEM_SW | DS4: PELEC_PT | DT4: PPICHEM_PT | DU4: GDPR_JP | DV4: CR_JP | DW4: IND_JP | DX4: CPI_JP | DY4: PPI_JP | DZ4: PGDP_JP | EA4: HSTARTS_JP | EB4: XRJPUS | EC4: PPI_DE_OLD | ED4: PPI_ES_OLD | EE4: PPIIND_PT_OLD | EF4: PPIIND_FI_OLD | EG4: PPIIND_SE_OLD | EH4: PELEC_FN_OLD | EI4: PELEC_GY_OLD | EJ4: PELEC_PT_OLD | EK4: PELEC_SP_OLD | EL4: PELEC_SW_OLD | EM4: PHFO_FN_OLD | EN4: PHFO_GY_OLD | EO4: PHFO_PT_OLD | EP4: PHFO_SP_OLD | EQ4: PHFO_SW_OLD | ER4: PPICHEM_FN_OLD | ES4: PPICHEM_SP_OLD | ET4: PPICHEM_SW_OLD | EU4: PPINS_BR | EV4: PPINS_CL | EW4: PPINS_ID | EX4: PPI_BR | EY4: PPI_CL | EZ4: PPI_ID | FA4: PPICHEM_BR | FB4: PPIELECT_BR | FC4: WAGES_BR | FD4: WAGES_CL | FE4: WAGES_ID | FF4: PPI_CN | FG4: XRBRUS | FH4: XRCLUS | FI4: XRIDUS | FJ4: XRCNUS | FK4: XRMXUS | FL4: EXCH | FM4: EXCHR
B5: =B$4&$C$1 -> GDPR2023_3 | C5: =C$4&$C$1 -> CR2023_3 | D5: =D$4&$C$1 -> CPIU2023_3 | E5: =E$4&$C$1 -> IRFF2023_3 | F5: =F$4&$C$1 -> IRG10Y2023_3 | G5: =G$4&$C$1 -> UR2023_3 | H5: =H$4&$C$1 -> IND2023_3 | I5: =I$4&$C$1 -> INDM2023_3 | ... AK5: =AK$4&$C$1 -> GDP2023_3 | AM5: =AM$4&$C$1 -> PPI0512023_3 | AN5: =AN$4&$C$1 -> PPI0532023_3 | AO5: =AO$4&$C$1 -> PPI0542023_3 | AP5: =AP$4&$C$1 -> PPI0572023_3 | AQ5: =AQ$4&$C$1 -> PPI062023_3 | AR5: =AR$4&$C$1 -> PPI072023_3 | AS5: =AS$4&$C$1 -> PPIENERGY2023_3 | AT5: =AT$4&$C$1 -> PPI052023_3 | ... FM5: =FM$4&$C$1 -> EXCHR2023_3
A6: 2005:1 | B6: #NAME? | C6: #NAME? | D6: #NAME? | E6: #NAME? | F6: #NAME? | G6: #NAME? | H6: #NAME? | I6: #NAME? | J6: #NAME? | K6: #NAME? | L6: #NAME? | M6: #NAME? | N6: #NAME? | O6: #NAME? | P6: #NAME? | Q6: #NAME? | R6: #NAME? | S6: #NAME? | T6: #NAME? | U6: #NAME? | V6: #NAME? | W6: #NAME? | X6: #NAME? | Y6: #NAME? | Z6: #NAME? | AA6: #NAME? | AB6: #NAME? | AC6: #NAME? | AD6: #NAME? | AE6: #NAME? | AF6: #NAME? | AG6: #NAME? | AH6: #NAME? | AI6: #NAME? | AJ6: #NAME? | AK6: #NAME? | AM6: #NAME? | AN6: #NAME? | AO6: #NAME? | AP6: #NAME? | AQ6: #NAME? | AR6: #NAME? | AS6: #NAME? | AT6: #NAME? | AU6: #NAME? | AV6: #NAME? | AW6: #NAME? | AX6: #NAME? | AY6: #NAME? | AZ6: #NAME? | BA6: #NAME? | BB6: #NAME? | BC6: #NAME? | BD6: #NAME? | BE6: #NAME? | BF6: #NAME? | BG6: #NAME? | BH6: #NAME? | BI6: #NAME? | BJ6: #NAME? | BK6: #NAME? | BL6: #NAME? | BM6: #NAME? | BN6: #NAME? | BO6: #NAME? | BP6: #NAME? | BQ6: #NAME? | BR6: #NAME? | BS6: #NAME? | BT6: #NAME? | BU6: #NAME? | BV6: #NAME? | BW6: #NAME? | BX6: #NAME? | BY6: #NAME? | BZ6: #NAME? | CA6: #NAME? | CB6: #NAME? | CC6: #NAME? | CD6: #NAME? | CE6: #NAME? | CF6: #NAME? | CG6: #NAME? | CH6: #NAME? | CI6: #NAME? | CJ6: #NAME? | CK6: #NAME? | CL6: #NAME? | CM6: #NAME? | CN6: #NAME? | CO6: #NAME? | CP6: #NAME? | CQ6: #NAME? | CR6: #NAME? | CS6: #NAME? | CT6: #NAME? | CU6: #NAME? | CV6: #NAME? | CW6: #NAME? | CX6: #NAME? | CY6: #NAME? | CZ6: #NAME? | DA6: #NAME? | DB6: #NAME? | DC6: #NAME? | DD6: #NAME? | DE6: #NAME? | DF6: #NAME? | DG6: #NAME? | DH6: #NAME? | DI6: #NAME? | DJ6: #NAME? | DK6: #NAME? | DL6: #NAME? | DM6: #NAME? | DN6: #NAME? | DO6: #NAME? | DP6: #NAME? | DQ6: #NAME? | DR6: #NAME? | DS6: #NAME? | DT6: #NAME? | DU6: #NAME? | DV6: #NAME? | DW6: #NAME? | DX6: #NAME? | DY6: #NAME? | DZ6: #NAME? | EA6: #NAME? | EB6: #NAME? | EC6: #NAME? | ED6: #NAME? | EE6: #NAME? | EF6: #NAME? | EG6: #NAME? | EH6: #NAME? | EI6: #NAME? | EJ6: #NAME? | EK6: #NAME? | EL6: #NAME? | EM6: #NAME? | EN6: #NAME? | EO6: #NAME? | EP6: #NAME? | EQ6: #NAME? | ER6: #NAME? | ES6: #NAME? | ET6: #NAME? | EU6: #NAME? | EV6: #NAME? | EW6: #NAME? | EX6: #NAME? | EY6: #NAME? | EZ6: #NAME? | FA6: #NAME? | FB6: #NAME? | FC6: #NAME? | FD6: #NAME? | FE6: #NAME? | FF6: #NAME? | FG6: #NAME? | FH6: #NAME? | FI6: #NAME? | FJ6: #NAME? | FK6: #NAME? | FL6: #NAME? | FM6: #NAME?
A7: 2005:2 | B7: 14839.71 | C7: 10074.53 | D7: 1.936659 | E7: 2.943956 | F7: 4.15978 | G7: 5.099999 | H7: 0.9683464 | I7: 1.017963 | J7: 0.8908383 | K7: 1.112999 | L7: 1.539989 | M7: 53.01791 | N7: 51.593956 | O7: 6.9315385 | P7: 2.051333 | Q7: -686.4388 | R7: 5.914066 | S7: 2375.192 | T7: 2.863077 | U7: 4.480879 | V7: 1845.046 | W7: 0.988 | X7: 11344.23 | Y7: 1.202783 | Z7: 0.8050877 | AA7: 0.84417 | AB7: 0.91604 | AC7: 44.06901 | AD7: 0.81137 | AE7: 0.67374 | AF7: 0.77263 | AG7: 295.5883 | AH7: 113.2006 | AI7: 1.509956 | AJ7: 1.567 | AK7: 12922.66 | AM7: 1.1463187 | AN7: 2.603813 | AO7: 1.4773297 | AP7: 1.4877912 | AQ7: 1.882022 | AR7: 1.419989 | AS7: 1.245528 | AT7: 1.453813 | AU7: 1.561363 | AV7: 1632.938 | AW7: 820.058 | AX7: 1.07028 | AY7: 1.06733 | AZ7: 232.6333 | BA7: 0.803899 | BB7: 78.7 | BC7: 20.50451 | BD7: 6.801099 | BE7: 0.8016667 | BF7: 2.45989 | BG7: 2.5 | BH7: 3.99033 | BI7: 0.735 | BJ7: 0.857 | BK7: 54.82161 | BL7: 65.95399 | BM7: 1.059488 | BN7: 1.269527 | BO7: 32.1412 | BP7: 1.2439945 | BQ7: 1374.26 | BR7: 312.02615 | BS7: 9488.281 | BT7: 5320.689 | BU7: 0.9882528 | BV7: 0.8475033 | BW7: 0.8656374 | BX7: 1.259942 | BY7: 3.348176 | BZ7: 3.328264 | CA7: 3.353011 | CB7: 0.5387891 | CC7: 7.313332 | CD7: 0.8689011 | CE7: 1.102286 | CF7: 1.21656 | CG7: 1.007667 | CH7: 0.9383626 | CI7: 0.9939671 | CJ7: 1.037143 | CK7: 0.9346666 | CL7: 0.8513333 | CM7: 0.8809999 | CN7: 0.8543667 | CO7: 0.808 | CP7: 0.7942305 | CQ7: 0.939945 | CR7: 2.108352 | CS7: 41.007987 | CT7: 28.08553 | CU7: 23.95646 | CV7: 30.183744 | CW7: 0.8816667 | CX7: 0.8693333 | CY7: 0.8736666 | CZ7: 0.903 | DA7: 0.942 | DB7: 0.611101 | DC7: 1.077 | DD7: 0.715 | DE7: 0.734 | DF7: 0.735 | DG7: 0.805 | DH7: 0.202 | DI7: 0 | DJ7: 0.486 | DK7: 0.681 | DL7: 0.7943333 | DM7: 0.79 | DN7: 0.83966667 | DO7: 0.6076667 | DP7: 0.7573333 | DQ7: 0.8636667 | DR7: 0.7366667 | DS7: 0.608 | DT7: 0.82966667 | DU7: 510.3484 | DV7: 285.0205 | DW7: 120.1626 | DX7: 0.9533517 | DY7: 0.941 | DZ7: 1.041 | EA7: 1200.789 | EB7: 107.5033 | EC7: 0.8809999 | ED7: 0.808 | EE7: 0.8693333 | EF7: 0.8736666 | EG7: 0.8816667 | EH7: 0.331 | EI7: 0.123 | EJ7: 15.597 | EK7: 8.219 | EL7: 0.318 | EM7: 1797 | EN7: 429.4 | EO7: 55565 | EP7: 44298 | EQ7: 3257.6 | ER7: 1.104 | ES7: 1.155 | ET7: 1.084 | EU7: 0.4823048 | EV7: 0.5396463 | EW7: 0.5040135 | EX7: 0.4842594 | EY7: 0.5379742 | EZ7: 0.5049503 | FA7: 3.546 | FB7: 3.578 | FC7: 15.237 | FD7: 6268.771 | FE7: 30841.27 | FF7: 0.996125 | FG7: 2.481774 | FH7: 581.3792 | FI7: 9553.555 | FJ7: 8.2765 | FK7: 10.96941 | FL7: 1.005089 | FM7: 0.9962757
A8: 2005:3 | B8: 14956.29 | C8: 10158.95 | D8: 1.965761 | E8: 3.458261 | F8: 4.213478 | G8: 4.966304 | H8: 0.9643635 | I8: 1.016608 | J8: 0.8973345 | K8: 1.101608 | L8: 1.566772 | M8: 63.16728 | N8: 61.454348 | O8: 9.6136957 | P8: 2.1 | Q8: -724.9175 | R8: 6.424891 | S8: 2384.244 | T8: 3.359348 | U8: 4.445478 | V8: 1862.914 | W8: 0.995 | X8: 11386.09 | Y8: 1.207529 | Z8: 0.7986323 | AA8: 0.8494 | AB8: 0.91547 | AC8: 52.95304 | AD8: 0.81905 | AE8: 0.69786 | AF8: 0.79294 | AG8: 296.3374 | AH8: 113.4981 | AI8: 1.542011 | AJ8: 1.6196667 | AK8: 13142.64 | AM8: 1.1649565 | AN8: 3.184206 | AO8: 1.5002717 | AP8: 1.7635978 | AQ8: 1.913283 | AR8: 1.428239 | AS8: 1.361152 | AT8: 1.642228 | AU8: 1.544544 | AV8: 1652.719 | AW8: 825.517 | AX8: 1.078371 | AY8: 1.076587 | AZ8: 229.4333 | BA8: 0.832218 | BB8: 78.9 | BC8: 20.74544 | BD8: 6.666304 | BE8: 0.802 | BF8: 2.715652 | BG8: 2.568182 | BH8: 3.875978 | BI8: 0.748 | BJ8: 0.869 | BK8: 63.64392 | BL8: 75.92034 | BM8: 1.058957 | BN8: 1.269297 | BO8: 32.24236 | BP8: 1.2018935 | BQ8: 1411.38 | BR8: 312.47895 | BS8: 9560.738 | BT8: 5347.576 | BU8: 0.9926087 | BV8: 0.8505608 | BW8: 0.8769565 | BX8: 1.218952 | BY8: 3.192011 | BZ8: 3.144011 | CA8: 3.063511 | CB8: 0.5607694 | CC8: 7.684385 | CD8: 0.8799348 | CE8: 1.098467 | CF8: 1.218989 | CG8: 0.983 | CH8: 0.9559999 | CI8: 1.00025 | CJ8: 1.062837 | CK8: 0.941 | CL8: 0.8593333 | CM8: 0.8889999 | CN8: 0.8612667 | CO8: 0.819 | CP8: 0.8204424 | CQ8: 0.9492391 | CR8: 2.113152 | CS8: 50.398929 | CT8: 28.51751 | CU8: 24.38355 | CV8: 29.722381 | CW8: 0.8973333 | CX8: 0.9156666 | CY8: 0.8883333 | CZ8: 0.89833333 | DA8: 0.93533333 | DB8: 0.63403094 | DC8: 1.1023333 | DD8: 0.712 | DE8: 0.738 | DF8: 0.739 | DG8: 0.836 | DH8: 0.211 | DI8: 0 | DJ8: 0.493 | DK8: 0.6896667 | DL8: 0.772 | DM8: 0.8216667 | DN8: 0.83933333 | DO8: 0.613 | DP8: 0.7576666 | DQ8: 0.847 | DR8: 0.743 | DS8: 0.61 | DT8: 0.88766667 | DU8: 515.4854 | DV8: 287.6931 | DW8: 119.625 | DX8: 0.9516413 | DY8: 0.9466522 | DZ8: 1.037 | EA8: 1290.593 | EB8: 111.267 | EC8: 0.8889999 | ED8: 0.819 | EE8: 0.9156666 | EF8: 0.8883333 | EG8: 0.8973333 | EH8: 0.336 | EI8: 0.123 | EJ8: 16.019 | EK8: 8.219 | EL8: 0.323 | EM8: 2064.3 | EN8: 517.4 | EO8: 63610 | EP8: 50250 | EQ8: 3875.7 | ER8: 1.121 | ES8: 1.16 | ET8: 1.104 | EU8: 0.47117 | EV8: 0.5515963 | EW8: 0.5096012 | EX8: 0.4726344 | EY8: 0.5368508 | EZ8: 0.5096853 | FA8: 3.596 | FB8: 3.618 | FC8: 14.882 | FD8: 6407.78 | FE8: 31910.03 | FF8: 1.003875 | FG8: 2.342512 | FH8: 553.093 | FI8: 10009.68 | FJ8: 8.140523 | FK8: 10.71389 | FL8: 0.9716222 | FM8: 1.007078
A9: 2005:4 | B9: 15041.23 | C9: 10177.27 | D9: 1.98437 | E9: 3.979782 | F9: 4.489457 | G9: 4.966304 | H9: 0.97302 | I9: 1.031745 | J9: 0.926078 | K9: 1.099138 | L9: 1.596098 | M9: 60.01489 | N9: 56.897826 | O9: 12.277935 | P9: 2.068667 | Q9: -782.5286 | R9: 6.966304 | S9: 2417.524 | T9: 3.826087 | U9: 4.679022 | V9: 1958.866 | W9: 1.002 | X9: 11487.87 | Y9: 1.212658 | Z9: 0.8023812 | AA9: 0.84983 | AB9: 0.91601 | AC9: 52.74294 | AD9: 0.82557 | AE9: 0.72546 | AF9: 0.8076 | AG9: 297.0856 | AH9: 113.7769 | AI9: 1.609402 | AJ9: 1.6823333 | AK9: 13324.2 | AM9: 1.2192065 | AN9: 4.222598 | AO9: 1.5589348 | AP9: 1.9060652 | AQ9: 2.016695 | AR9: 1.498881 | AS9: 1.473076 | AT9: 1.800957 | AU9: 1.567685 | AV9: 1669.06 | AW9: 833.352 | AX9: 1.091687 | AY9: 1.077337 | AZ9: 224.7 | BA9: 0.8522856 | BB9: 80.2 | BC9: 20.53707 | BD9: 6.53587 | BE9: 0.8033333 | BF9: 3.242718 | BG9: 3.030769 | BH9: 4.049891 | BI9: 0.762 | BJ9: 0.88 | BK9: 61.88747 | BL9: 70.42023 | BM9: 1.065179 | BN9: 1.272521 | BO9: 32.35223 | BP9: 1.1733793 | BQ9: 1433.624 | BR9: 311.08111 | BS9: 9617.77 | BT9: 5371.408 | BU9: 1.006902 | BV9: 0.8561174 | BW9: 0.8853478 | BX9: 1.187661 | BY9: 3.34637 | BZ9: 3.280391 | CA9: 3.296717 | CB9: 0.5718664 | CC9: 7.968686 | CD9: 0.8966957 | CE9: 1.107457 | CF9: 1.224554 | CG9: 1.034667 | CH9: 0.9606631 | CI9: 1.003587 | CJ9: 1.073098 | CK9: 1.037 | CL9: 0.8616667 | CM9: 0.896 | CN9: 0.867 | CO9: 0.826 | CP9: 0.8420556 | CQ9: 0.9585543 | CR9: 2.336522 | CS9: 47.902065 | CT9: 28.70743 | CU9: 24.68422 | CV9: 29.316482 | CW9: 0.9003333 | CX9: 0.93 | CY9: 0.9006667 | CZ9: 0.90033333 | DA9: 0.93233333 | DB9: 0.64758872 | DC9: 1.1326667 | DD9: 0.712 | DE9: 0.745 | DF9: 0.749 | DG9: 0.815 | DH9: 0.217 | DI9: 0 | DJ9: 0.5 | DK9: 0.705 | DL9: 0.813 | DM9: 0.8446667 | DN9: 0.85433333 | DO9: 0.624 | DP9: 0.7783333 | DQ9: 0.94 | DR9: 0.7746667 | DS9: 0.6026667 | DT9: 0.90333333 | DU9: 516.4283 | DV9: 287.8076 | DW9: 121.1272 | DX9: 0.9516848 | DY9: 0.9506739 | DZ9: 1.036 | EA9: 1245.681 | EB9: 116.2362 | EC9: 0.896 | ED9: 0.826 | EE9: 0.93 | EF9: 0.9006667 | EG9: 0.9003333 | EH9: 0.342 | EI9: 0.123 | EJ9: 16.019 | EK9: 8.275 | EL9: 0.339 | EM9: 2147.2 | EN9: 587.1 | EO9: 71315 | EP9: 54654 | EQ9: 3975.8 | ER9: 1.128 | ES9: 1.172 | ET9: 1.135 | EU9: 0.4728911 | EV9: 0.5426998 | EW9: 0.6224735 | EX9: 0.4705722 | EY9: 0.5449548 | EZ9: 0.6257214 | FA9: 3.601 | FB9: 3.649 | FC9: 14.841 | FD9: 6304.31 | FE9: 35354.86 | FF9: 1.011625 | FG9: 2.248875 | FH9: 526.4667 | FI9: 9995.068 | FJ9: 8.082955 | FK9: 10.71176 | FL9: 0.9657034 | FM9: 1.017431
A10: 2006:1 | B10: 15244.09 | C10: 10288.2 | D10: 1.994689 | E10: 4.455555 | F10: 4.57 | G10: 4.731111 | H10: 0.9823456 | I10: 1.041711 | J10: 0.9343671 | K10: 1.110733 | L10: 1.595267 | M10: 63.32467 | N10: 61.804778 | O10: 7.7122222 | P10: 2.120333 | Q10: -768.8895 | R10: 7.427667 | S10: 2441.937 | T10: 4.392111 | U10: 4.617156 | V10: 2015.785 | W10: 1.008 | X10: 11700.63 | Y10: 1.217915 | Z10: 0.80658 | AA10: 0.85653 | AB10: 0.91491 | AC10: 52.60056 | AD10: 0.83135 | AE10: 0.74437 | AF10: 0.82051 | AG10: 297.7368 | AH10: 113.8978 | AI10: 1.618411 | AJ10: 1.6676667 | AK10: 13599.16 | AM10: 1.2359667 | AN10: 3.125233 | AO10: 1.6125222 | AP10: 1.8604667 | AQ10: 2.035033 | AR10: 1.530622 | AS10: 1.4519 | AT10: 1.677711 | AU10: 1.554089 | AV10: 1682.596 | AW10: 845.036 | AX10: 1.093648 | AY10: 1.082756 | AZ10: 244.1 | BA10: 0.8660714 | BB10: 82.3 | BC10: 20.41622 | BD10: 6.434444 | BE10: 0.806 | BF10: 3.661777 | BG10: 3.511539 | BH10: 4.148222 | BI10: 0.776 | BJ10: 0.877 | BK10: 60.73535 | BL10: 73.11797 | BM10: 1.085545 | BN10: 1.273182 | BO10: 32.39455 | BP10: 1.1546522 | BQ10: 1446.988 | BR10: 312.76266 | BS10: 9698.821 | BT10: 5397.979 | BU10: 1.015411 | BV10: 0.8567955 | BW10: 0.899 | BX10: 1.203438 | BY10: 3.488789 | BZ10: 3.439033 | CA10: 3.427567 | CB10: 0.5702165 | CC10: 7.765904 | CD10: 0.9015555 | CE10: 1.107989 | CF10: 1.238456 | CG10: 1.051667 | CH10: 0.9509333 | CI10: 0.9885445 | CJ10: 1.0599 | CK10: 0.964 | CL10: 0.8633333 | CM10: 0.91 | CN10: 0.8697 | CO10: 0.8429999 | CP10: 0.8309854 | CQ10: 0.9492 | CR10: 2.593444 | CS10: 51.353083 | CT10: 28.1584 | CU10: 23.82358 | CV10: 28.670196 | CW10: 0.9103333 | CX10: 0.9096667 | CY10: 0.9133334 | CZ10: 0.90533333 | DA10: 0.93 | DB10: 0.65841674 | DC10: 1.1026667 | DD10: 0.719 | DE10: 0.746 | DF10: 0.751 | DG10: 0.818 | DH10: 0.232 | DI10: 0 | DJ10: 0.508 | DK10: 0.7573333 | DL10: 0.808 | DM10: 0.9173333 | DN10: 0.86266667 | DO10: 0.66 | DP10: 0.7883334 | DQ10: 1.045 | DR10: 0.7766666 | DS10: 0.633 | DT10: 0.90833333 | DU10: 517.2199 | DV10: 288.8 | DW10: 122.6411 | DX10: 0.9507222 | DY10: 0.9549667 | DZ10: 1.033 | EA10: 1257.078 | EB10: 116.8404 | EC10: 0.91 | ED10: 0.8429999 | EE10: 0.9096667 | EF10: 0.9133334 | EG10: 0.9103333 | EH10: 0.384 | EI10: 0.129 | EJ10: 16.74 | EK10: 8.441 | EL10: 0.401 | EM10: 2250 | EN10: 621 | EO10: 74800 | EP10: 55034 | EQ10: 4220 | ER10: 1.146 | ES10: 1.197 | ET10: 1.131 | EU10: 0.4749691 | EV10: 0.5470996 | EW10: 0.6347665 | EX10: 0.4740576 | EY10: 0.5612028 | EZ10: 0.6305201 | FA10: 3.617 | FB10: 3.644 | FC10: 14.968 | FD10: 6500.86 | FE10: 37088.42 | FF10: 1.0192188 | FG10: 2.193833 | FH10: 526.3378 | FI10: 9212.645 | FJ10: 8.050511 | FK10: 10.59525 | FL10: 1.005066 | FM10: 1.002679
A11: 2006:2 | B11: 15281.53 | C11: 10341.58 | D11: 2.01267 | E11: 4.907033 | F11: 5.070439 | G11: 4.632967 | H11: 0.9880714 | I11: 1.043539 | J11: 0.9402003 | K11: 1.10725 | L11: 1.608637 | M11: 70.41473 | N11: 69.536044 | O11: 6.5368132 | P11: 1.855 | Q11: -764.8199 | R11: 7.90033 | S11: 2447.219 | T11: 4.703516 | U11: 5.137362 | V11: 2016.463 | W11: 1.016 | X11: 11744.28 | Y11: 1.223659 | Z11: 0.8074728 | AA11: 0.85486 | AB11: 0.91136 | AC11: 60.21692 | AD11: 0.83871 | AE11: 0.763 | AF11: 0.82804 | AG11: 298.4079 | AH11: 114.1947 | AI11: 1.642022 | AJ11: 1.7 | AK11: 13753.42 | AM11: 1.254011 | AN11: 2.589956 | AO11: 1.6213187 | AP11: 2.0661319 | AQ11: 2.055681 | AR11: 1.531341 | AS11: 1.492615 | AT11: 1.716473 | AU11: 1.55055 | AV11: 1683.465 | AW11: 852.667 | AX11: 1.082398 | AY11: 1.094692 | AZ11: 227.7333 | BA11: 0.8910621 | BB11: 82.1 | BC11: 20.29769 | BD11: 6.131868 | BE11: 0.821 | BF11: 4.15033 | BG11: 4.046154 | BH11: 4.532417 | BI11: 0.79 | BJ11: 0.886 | BK11: 67.59118 | BL11: 79.03782 | BM11: 1.054917 | BN11: 1.240555 | BO11: 32.47046 | BP11: 1.1224615 | BQ11: 1470.084 | BR11: 323.68764 | BS11: 9805.709 | BT11: 5425.973 | BU11: 1.032725 | BV11: 0.8683725 | BW11: 0.9126703 | BX11: 1.25692 | BY11: 3.946813 | BZ11: 3.941429 | CA11: 3.873407 | CB11: 0.5475911 | CC11: 7.399088 | CD11: 0.9200439 | CE11: 1.124077 | CF11: 1.261758 | CG11: 1.039333 | CH11: 0.9676923 | CI11: 0.997077 | CJ11: 1.10211 | CK11: 1.007667 | CL11: 0.8696667 | CM11: 0.9209999 | CN11: 0.8852667 | CO11: 0.854 | CP11: 0.7958249 | CQ11: 0.9707583 | CR11: 2.86989 | CS11: 55.343927 | CT11: 27.21629 | CU11: 22.64622 | CV11: 28.464482 | CW11: 0.9253333 | CX11: 0.9496667 | CY11: 0.921 | CZ11: 0.916 | DA11: 0.93333333 | DB11: 0.68835305 | DC11: 1.1426667 | DD11: 0.717 | DE11: 0.752 | DF11: 0.758 | DG11: 0.829 | DH11: 0.239 | DI11: 0 | DJ11: 0.515 | DK11: 0.7523333 | DL11: 0.8276666 | DM11: 0.9423333 | DN11: 0.871 | DO11: 0.658 | DP11: 0.798 | DQ11: 1.003 | DR11: 0.777 | DS11: 0.642 | DT11: 0.87666667 | DU11: 518.0319 | DV11: 288.4658 | DW11: 124.7879 | DX11: 0.955011 | DY11: 0.9623517 | DZ11: 1.031 | EA11: 1312.157 | EB11: 114.4465 | EC11: 0.9209999 | ED11: 0.854 | EE11: 0.9496667 | EF11: 0.921 | EG11: 0.9253333 | EH11: 0.35 | EI11: 0.125 | EJ11: 17.32 | EK11: 8.815 | EL11: 0.416 | EM11: 2161 | EN11: 594.8 | EO11: 72268 | EP11: 54980 | EQ11: 4473 | ER11: 1.17 | ES11: 1.224 | ET11: 1.128 | EU11: 0.4745657 | EV11: 0.5790884 | EW11: 0.6437069 | EX11: 0.4763435 | EY11: 0.57842 | EZ11: 0.6447929 | FA11: 3.666 | FB11: 3.654 | FC11: 15.054 | FD11: 6716.831 | FE11: 37995.29 | FF11: 1.0270313 | FG11: 2.182228 | FH11: 526.7935 | FI11: 9018.105 | FJ11: 8.010562 | FK11: 11.17671 | FL11: 0.97159 | FM11: 0.9902611
A12: 2006:3 | B12: 15304.52 | C12: 10407.63 | D12: 2.031707 | E12: 5.24663 | F12: 4.898587 | G12: 4.634783 | H12: 0.9920372 | I12: 1.046439 | J12: 0.9440553 | K12: 1.112801 | L12: 1.611098 | M12: 70.48859 | N12: 69.703261 | O12: 6.0827174 | P12: 1.702333 | Q12: -797.3226 | R12: 8.25 | S12: 2461.17 | T12: 4.907717 | U12: 4.994892 | V12: 2058.765 | W12: 1.025 | X12: 11760.91 | Y12: 1.230641 | Z12: 0.8061154 | AA12: 0.85289 | AB12: 0.91896 | AC12: 64.51479 | AD12: 0.84486 | AE12: 0.777 | AF12: 0.83101 | AG12: 299.177 | AH12: 114.5284 | AI12: 1.655761 | AJ12: 1.7096667 | AK12: 13870.19 | AM12: 1.2729239 | AN12: 2.604489 | AO12: 1.6229348 | AP12: 2.0102174 | AQ12: 2.085772 | AR12: 1.540641 | AS12: 1.484359 | AT12: 1.713478 | AU12: 1.57687 | AV12: 1688.166 | AW12: 862.048 | AX12: 1.066809 | AY12: 1.09537 | AZ12: 219.5337 | BA12: 0.8918548 | BB12: 84.2 | BC12: 20.65511 | BD12: 6.366304 | BE12: 0.8266667 | BF12: 4.153152 | BG12: 4.25 | BH12: 4.161957 | BI12: 0.804 | BJ12: 0.891 | BK12: 72.33972 | BL12: 79.03809 | BM12: 1.033756 | BN12: 1.231203 | BO12: 32.5705 | BP12: 1.1212891 | BQ12: 1485.1 | BR12: 328.85609 | BS12: 9864.713 | BT12: 5442.976 | BU12: 1.037315 | BV12: 0.8690304 | BW12: 0.9200435 | BX12: 1.273784 | BY12: 3.898152 | BZ12: 3.941522 | CA12: 3.838152 | CB12: 0.5336909 | CC12: 7.245852 | CD12: 0.938337 | CE12: 1.113902 | CF12: 1.264956 | CG12: 1.019667 | CH12: 0.9690543 | CI12: 1.000011 | CJ12: 1.097196 | CK12: 1.049333 | CL12: 0.873 | CM12: 0.926 | CN12: 0.8860334 | CO12: 0.8610001 | CP12: 0.7850768 | CQ12: 0.9672717 | CR12: 3.201739 | CS12: 54.719391 | CT12: 26.80877 | CU12: 22.26966 | CV12: 28.36673 | CW12: 0.933 | CX12: 0.96 | CY12: 0.93 | CZ12: 0.922 | DA12: 0.94166667 | DB12: 0.72183803 | DC12: 1.1436667 | DD12: 0.721 | DE12: 0.763 | DF12: 0.762 | DG12: 0.816 | DH12: 0.252 | DI12: 0 | DJ12: 0.525 | DK12: 0.803 | DL12: 0.8426667 | DM12: 0.9516667 | DN12: 0.879 | DO12: 0.6683334 | DP12: 0.8093333 | DQ12: 1.069333 | DR12: 0.778 | DS12: 0.635 | DT12: 0.96433333 | DU12: 516.9734 | DV12: 286.2234 | DW12: 125.9652 | DX12: 0.9576413 | DY12: 0.9716413 | DZ12: 1.03 | EA12: 1283.287 | EB12: 116.2901 | EC12: 0.926 | ED12: 0.8610001 | EE12: 0.96 | EF12: 0.93 | EG12: 0.933 | EH12: 0.356 | EI12: 0.126 | EJ12: 17.64 | EK12: 8.981 | EL12: 0.419 | EM12: 2175 | EN12: 589.4 | EO12: 73433 | EP12: 54559 | EQ12: 4436 | ER12: 1.189 | ES12: 1.24 | ET12: 1.121 | EU12: 0.481572 | EV12: 0.6031176 | EW12: 0.6627051 | EX12: 0.4829333 | EY12: 0.5880141 | EZ12: 0.6623282 | FA12: 3.654 | FB12: 3.667 | FC12: 15.275 | FD12: 6898.331 | FE12: 39258.39 | FF12: 1.0349062 | FG12: 2.170528 | FH12: 539.2735 | FI12: 9139.204 | FJ12: 7.965445 | FK12: 10.94789 | FL12: 0.965646 | FM12: 0.989291
A13: 2006:4 | B13: 15433.64 | C13: 10507.44 | D13: 2.02337 | E13: 5.25 | F13: 4.630326 | G13: 4.432609 | H13: 0.9944859 | I13: 1.050808 | J13: 0.948884 | K13: 1.117663 | L13: 1.599326 | M13: 59.98641 | N13: 59.69 | O13: 6.6552174 | P13: 1.57 | Q13: -716.7772 | R13: 8.25 | S13: 2495.64 | T13: 4.902935 | U13: 4.740543 | V13: 1978.632 | W13: 1.033 | X13: 11904.76 | Y13: 1.238984 | Z13: 0.8026587 | AA13: 0.85883 | AB13: 0.93303 | AC13: 53.87076 | AD13: 0.84806 | AE13: 0.79711 | AF13: 0.83701 | AG13: 299.946 | AH13: 114.8991 | AI13: 1.638337 | AJ13: 1.6743333 | AK13: 14039.56 | AM13: 1.2890978 | AN13: 2.495783 | AO13: 1.6200435 | AP13: 1.7747391 | AQ13: 2.055783 | AR13: 1.548663 | AS13: 1.397011 | AT13: 1.562098 | AU13: 1.590413 | AV13: 1694.895 | AW13: 870.951 | AX13: 1.053188 | AY13: 1.092 | AZ13: 222.2 | BA13: 0.8778543 | BB13: 85.8 | BC13: 20.66413 | BD13: 6.198913 | BE13: 0.8193333 | BF13: 4.169891 | BG13: 4.25 | BH13: 4.054565 | BI13: 0.813 | BJ13: 0.894 | BK13: 61.3715 | BL13: 68.33868 | BM13: 1.024607 | BN13: 1.208147 | BO13: 32.67899 | BP13: 1.1392359 | BQ13: 1488.98 | BR13: 324.78981 | BS13: 9975.932 | BT13: 5487.223 | BU13: 1.048359 | BV13: 0.8713446 | BW13: 0.916 | BX13: 1.29035 | BY13: 3.770326 | BZ13: 3.800435 | CA13: 3.673696 | CB13: 0.5217321 | CC13: 7.078452 | CD13: 0.9479674 | CE13: 1.116424 | CF13: 1.27975 | CG13: 1.070333 | CH13: 0.9809456 | CI13: 0.9990218 | CJ13: 1.115098 | CK13: 1.109667 | CL13: 0.873 | CM13: 0.926 | CN13: 0.8889334 | CO13: 0.8569999 | CP13: 0.7752548 | CQ13: 0.9780434 | CR13: 3.573261 | CS13: 46.246957 | CT13: 26.59589 | CU13: 21.7878 | CV13: 28.113888 | CW13: 0.9286667 | CX13: 0.9316667 | CY13: 0.937 | CZ13: 0.92433333 | DA13: 0.93966667 | DB13: 0.70391265 | DC13: 1.1486667 | DD13: 0.721 | DE13: 0.768 | DF13: 0.771 | DG13: 0.827 | DH13: 0.27 | DI13: 0 | DJ13: 0.532 | DK13: 0.7726667 | DL13: 0.85 | DM13: 0.943 | DN13: 0.88766667 | DO13: 0.668 | DP13: 0.814 | DQ13: 1.088667 | DR13: 0.7883334 | DS13: 0.627 | DT13: 0.937 | DU13: 524.0022 | DV13: 290.6019 | DW13: 127.5326 | DX13: 0.9550217 | DY13: 0.9683369 | DZ13: 1.03 | EA13: 1310.495 | EB13: 117.7547 | EC13: 0.926 | ED13: 0.8569999 | EE13: 0.9316667 | EF13: 0.937 | EG13: 0.9286667 | EH13: 0.358 | EI13: 0.176 | EJ13: 18.043 | EK13: 9.2 | EL13: 0.42 | EM13: 1931 | EN13: 525.4 | EO13: 82328 | EP13: 49534 | EQ13: 3875 | ER13: 1.196 | ES13: 1.251 | ET13: 1.127 | EU13: 0.4915648 | EV13: 0.575017 | EW13: 0.6705279 | EX13: 0.4892541 | EY13: 0.5758278 | EZ13: 0.6737586 | FA13: 3.708 | FB13: 3.708 | FC13: 15.496 | FD13: 6683.34 | FE13: 40305.01 | FF13: 1.0428438 | FG13: 2.14957 | FH13: 528.6713 | FI13: 9070.799 | FJ13: 7.861964 | FK13: 10.88402 | FL13: 0.9657758 | FM13: 0.9750478
A14: 2007:1 | B14: 16611.69 | C14: 11183.47 | D14: 2.0432 | E14: 5.25 | F14: 4.830222 | G14: 4.5 | H14: 1.004535 | I14: 1.063069 | J14: 0.9641865 | K14: 1.126807 | L14: 1.625622 | M14: 58.03656 | N14: 57.770111 | O14: 7.194 | P14: 1.461333 | Q14: -712.0449 | R14: 8.25 | S14: 2435.163 | T14: 4.981778 | U14: 4.795889 | V14: 1853.234 | W14: 1.039 | X14: 11995.9 | Y14: 1.247637 | Z14: 0.805145 | AA14: 0.86024 | AB14: 0.94528 | AC14: 52.035 | AD14: 0.85655 | AE14: 0.80695 | AF14: 0.84136 | AG14: 300.6097 | AH14: 115.5331 | AI14: 1.653689 | AJ14: 1.6916667 | AK14: 14215.65 | AM14: 1.2787222 | AN14: 2.670522 | AO14: 1.6417333 | AP14: 1.8661667 | AQ14: 2.071822 | AR14: 1.54 | AS14: 1.436478 | AT14: 1.601655 | AU14: 1.639244 | AV14: 1705.736 | AW14: 878.693 | AX14: 1.063271 | AY14: 1.102344 | AZ14: 223.5333 | BA14: 0.8533506 | BB14: 86.8 | BC14: 20.93822 | BD14: 6.165555 | BE14: 0.8383333 | BF14: 4.169666 | BG14: 4.25 | BH14: 4.102334 | BI14: 0.82 | BJ14: 0.907 | BK14: 60.97779 | BL14: 68.01078 | BM14: 1.041888 | BN14: 1.189826 | BO14: 32.71656 | BP14: 1.1718611 | BQ14: 1516.436 | BR14: 334.88957 | BS14: 10070.24 | BT14: 5500.071 | BU14: 1.062656 | BV14: 0.8728366 | BW14: 0.9193444 | BX14: 1.310721 | BY14: 4.005222 | BZ14: 4.035222 | CA14: 3.868333 | CB14: 0.5115469 | CC14: 7.008702 | CD14: 0.9639667 | CE14: 1.124 | CF14: 1.288656 | CG14: 1.058 | CH14: 0.9943445 | CI14: 1.008278 | CJ14: 1.115411 | CK14: 1.008667 | CL14: 0.8793333 | CM14: 0.927 | CN14: 0.8909 | CO14: 0.867 | CP14: 0.7629891 | CQ14: 0.9880667 | CR14: 3.803111 | CS14: 44.05663 | CT14: 26.31396 | CU14: 21.42842 | CV14: 28.086682 | CW14: 0.9226667 | CX14: 0.923 | CY14: 0.947 | CZ14: 0.93266667 | DA14: 0.95066667 | DB14: 0.71510464 | DC14: 1.1823333 | DD14: 0.719 | DE14: 0.793 | DF14: 0.781 | DG14: 0.855 | DH14: 0.276 | DI14: 0 | DJ14: 0.548 | DK14: 0.7493333 | DL14: 0.8603333 | DM14: 0.936 | DN14: 0.89033333 | DO14: 0.6933333 | DP14: 0.8173333 | DQ14: 1.068667 | DR14: 0.7983333 | DS14: 0.668 | DT14: 0.94933333 | DU14: 527.4114 | DV14: 290.7974 | DW14: 126.9244 | DX14: 0.9497555 | DY14: 0.9680001 | DZ14: 1.027 | EA14: 1223.613 | EB14: 119.3668 | EC14: 0.927 | ED14: 0.867 | EE14: 0.923 | EF14: 0.947 | EG14: 0.9226667 | EH14: 0.338 | EI14: 0.14 | EJ14: 18.043 | EK14: 9.5 | EL14: 0.425 | EM14: 1776.1 | EN14: 474.7 | EO14: 72782 | EP14: 47256 | EQ14: 3390 | ER14: 1.204 | ES14: 1.274 | ET14: 1.189 | EU14: 0.4955434 | EV14: 0.5743385 | EW14: 0.6939964 | EX14: 0.4948937 | EY14: 0.5869996 | EZ14: 0.6906581 | FA14: 3.752 | FB14: 3.752 | FC14: 15.694 | FD14: 6831.515 | FE14: 41802.69 | FF14: 1.0445937 | FG14: 2.107023 | FH14: 540.3599 | FI14: 9138.21 | FJ14: 7.758501 | FK14: 11.02256 | FL14: 0.9690918 | FM14: 0.9764724
A15: 2007:2 | B15: 16713.31 | C15: 11212.73 | D15: 2.066324 | E15: 5.25 | F15: 4.845604 | G15: 4.498901 | H15: 1.016219 | I15: 1.07726 | J15: 0.9889973 | K15: 1.128574 | L15: 1.658022 | M15: 64.96 | N15: 68.568242 | O15: 7.5312088 | P15: 1.451 | Q15: -717.2159 | R15: 8.25 | S15: 2429.857 | T15: 4.736593 | U15: 4.989011 | V15: 1920.197 | W15: 1.048 | X15: 12055.38 | Y15: 1.25528 | Z15: 0.8095576 | AA15: 0.86223 | AB15: 0.95676 | AC15: 59.20187 | AD15: 0.86201 | AE15: 0.81079 | AF15: 0.83916 | AG15: 301.2836 | AH15: 115.8869 | AI15: 1.694692 | AJ15: 1.7543333 | AK15: 14402.08 | AM15: 1.2889451 | AN15: 2.934308 | AO15: 1.6683626 | AP15: 2.0802418 | AQ15: 2.131396 | AR15: 1.54167 | AS15: 1.541451 | AT15: 1.794868 | AU15: 1.663967 | AV15: 1722.263 | AW15: 891.981 | AX15: 1.066086 | AY15: 1.118692 | AZ15: 231.2667 | BA15: 0.911055 | BB15: 86.2 | BC15: 21.60692 | BD15: 6.032967 | BE15: 0.8456666 | BF15: 4.293297 | BG15: 4.25 | BH15: 4.417363 | BI15: 0.839 | BJ15: 0.915 | BK15: 65.02518 | BL15: 71.34971 | BM15: 1.034603 | BN15: 1.199378 | BO15: 32.78514 | BP15: 1.0983637 | BQ15: 1551.308 | BR15: 339.32481 | BS15: 10141.6 | BT15: 5546.822 | BU15: 1.067396 | BV15: 0.8848044 | BW15: 0.9286703 | BX15: 1.348437 | BY15: 4.326044 | BZ15: 4.362747 | CA15: 4.19945 | CB15: 0.5034631 | CC15: 6.864389 | CD15: 0.9747254 | CE15: 1.13044 | CF15: 1.288791 | CG15: 1.017333 | CH15: 1.008187 | CI15: 1.012747 | CJ15: 1.084176 | CK15: 1.009333 | CL15: 0.887 | CM15: 0.931 | CN15: 0.9074667 | CO15: 0.879 | CP15: 0.7416072 | CQ15: 0.9844396 | CR15: 4.036814 | CS15: 50.854982 | CT15: 25.86114 | CU15: 20.99371 | CV15: 28.308703 | CW15: 0.9486667 | CX15: 0.962 | CY15: 0.9576667 | CZ15: 0.93966667 | DA15: 0.96333333 | DB15: 0.77861692 | DC15: 1.167 | DD15: 0.722 | DE15: 0.801 | DF15: 0.793 | DG15: 0.861 | DH15: 0.289 | DI15: 0 | DJ15: 0.558 | DK15: 0.7336667 | DL15: 0.882 | DM15: 0.9163333 | DN15: 0.89833333 | DO15: 0.6893333 | DP15: 0.8223333 | DQ15: 0.9823334 | DR15: 0.805 | DS15: 0.676 | DT15: 0.91433333 | DU15: 527.6331 | DV15: 292.4069 | DW15: 127.6714 | DX15: 0.9543517 | DY15: 0.9786704 | DZ15: 1.027 | EA15: 1282.3 | EB15: 120.7964 | EC15: 0.931 | ED15: 0.879 | EE15: 0.962 | EF15: 0.9576667 | EG15: 0.9486667 | EH15: 0.346 | EI15: 0.145 | EJ15: 18.805 | EK15: 9.8 | EL15: 0.42 | EM15: 2056.7 | EN15: 513.6 | EO15: 80597 | EP15: 54326 | EQ15: 3735 | ER15: 1.229 | ES15: 1.298 | ET15: 1.204 | EU15: 0.4963494 | EV15: 0.602466 | EW15: 0.7163473 | EX15: 0.4979301 | EY15: 0.6043059 | EZ15: 0.7170881 | FA15: 3.774 | FB15: 3.774 | FC15: 15.805 | FD15: 7045.085 | FE15: 43472.08 | FF15: 1.0551563 | FG15: 1.982051 | FH15: 526.9572 | FI15: 8979.259 | FJ15: 7.678421 | FK15: 10.87771 | FL15: 0.9378414 | FM15: 0.9555408
A16: 2007:3 | B16: 16809.59 | C16: 11287.19 | D16: 2.079324 | E16: 5.184783 | F16: 4.732283 | G16: 4.666305 | H16: 1.01704 | I16: 1.077547 | J16: 0.9949392 | K16: 1.126246 | L16: 1.669261 | M16: 75.41826 | N16: 74.929239 | O16: 6.1743478 | P16: 1.289 | Q16: -698.9097 | R16: 8.178261 | S16: 2437.523 | T16: 4.307826 | U16: 4.945 | V16: 1836.398 | W16: 1.056 | X16: 12075.48 | Y16: 1.259917 | Z16: 0.8072277 | AA16: 0.87083 | AB16: 0.96349 | AC16: 67.38185 | AD16: 0.86568 | AE16: 0.81787 | AF16: 0.83949 | AG16: 302.0597 | AH16: 116.1869 | AI16: 1.710967 | AJ16: 1.7613333 | AK16: 14564.12 | AM16: 1.3146196 | AN16: 2.582706 | AO16: 1.6819348 | AP16: 2.1636087 | AQ16: 2.16262 | AR16: 1.553641 | AS16: 1.563478 | AT16: 1.806522 | AU16: 1.66987 | AV16: 1729.494 | AW16: 900.362 | AX16: 1.060003 | AY16: 1.118663 | AZ16: 245.5 | BA16: 0.9569712 | BB16: 86.5 | BC16: 21.76033 | BD16: 6.001087 | BE16: 0.8253334 | BF16: 4.227935 | BG16: 4.476923 | BH16: 4.457174 | BI16: 0.858 | BJ16: 0.915 | BK16: 70.42289 | BL16: 78.822 | BM16: 1.010639 | BN16: 1.200142 | BO16: 32.88793 | BP16: 1.0451315 | BQ16: 1563.328 | BR16: 328.82201 | BS16: 10184.25 | BT16: 5569.262 | BU16: 1.079674 | BV16: 0.8853739 | BW16: 0.9343153 | BX16: 1.37523 | BY16: 4.341413 | BZ16: 4.427935 | CA16: 4.297826 | CB16: 0.4946538 | CC16: 6.736534 | CD16: 0.9922608 | CE16: 1.135489 | CF16: 1.305728 | CG16: 0.9903333 | CH16: 1.016196 | CI16: 1.003076 | CJ16: 1.095261 | CK16: 1.013333 | CL16: 0.8923333 | CM16: 0.932 | CN16: 0.9043667 | CO16: 0.884 | CP16: 0.7272034 | CQ16: 0.9887065 | CR16: 4.4775 | CS16: 54.474248 | CT16: 25.50754 | CU16: 20.3716 | CV16: 28.015644 | CW16: 0.951 | CX16: 0.957 | CY16: 0.962 | CZ16: 0.94566667 | DA16: 0.967 | DB16: 0.82010919 | DC16: 1.1393333 | DD16: 0.725 | DE16: 0.812 | DF16: 0.804 | DG16: 0.859 | DH16: 0.304 | DI16: 0 | DJ16: 0.563 | DK16: 0.746 | DL16: 0.8886667 | DM16: 0.907 | DN16: 0.90133333 | DO16: 0.6946667 | DP16: 0.829 | DQ16: 0.9716667 | DR16: 0.812 | DS16: 0.6713333 | DT16: 0.97866667 | DU16: 524.7734 | DV16: 289.5295 | DW16: 129.8033 | DX16: 0.9563152 | DY16: 0.986337 | DZ16: 1.022 | EA16: 809.2329 | EB16: 117.7559 | EC16: 0.932 | ED16: 0.884 | EE16: 0.957 | EF16: 0.962 | EG16: 0.951 | EH16: 0.345 | EI16: 0.15 | EJ16: 18.805 | EK16: 9.97 | EL16: 0.421 | EM16: 2232.6 | EN16: 591.5 | EO16: 91021 | EP16: 60148 | EQ16: 3963 | ER16: 1.234 | ES16: 1.306 | ET16: 1.214 | EU16: 0.5079733 | EV16: 0.6319398 | EW16: 0.7409334 | EX16: 0.5092505 | EY16: 0.6188014 | EZ16: 0.7397653 | FA16: 3.859 | FB16: 3.859 | FC16: 16.179 | FD16: 7281.881 | FE16: 44993.7 | FF16: 1.0682813 | FG16: 1.915307 | FH16: 519.9113 | FI16: 9242.516 | FJ16: 7.557088 | FK16: 10.96292 | FL16: 0.9104183 | FM16: 0.9356268
A17: 2007:4 | B17: 16915.19 | C17: 11331.86 | D17: 2.104859 | E17: 4.496739 | F17: 4.261196 | G17: 4.801087 | H17: 1.02032 | I17: 1.080957 | J17: 1.008241 | K17: 1.119742 | L17: 1.711196 | M17: 90.70967 | N17: 88.518152 | O17: 6.9820652 | P17: 1.166 | Q17: -693.3904 | R17: 7.523586 | S17: 2435.461 | T17: 3.391304 | U17: 4.607609 | V17: 1782.974 | W17: 1.065 | X17: 12090.55 | Y17: 1.260725 | Z17: 0.8093125 | AA17: 0.87836 | AB17: 0.97598 | AC17: 78.41098 | AD17: 0.86982 | AE17: 0.82763 | AF17: 0.84039 | AG17: 302.8286 | AH17: 116.4331 | AI17: 1.754196 | AJ17: 1.798 | AK17: 14715.06 | AM17: 1.3386848 | AN17: 2.984989 | AO17: 1.6973261 | AP17: 2.4645109 | AQ17: 2.226804 | AR17: 1.566685 | AS17: 1.681696 | AT17: 1.900598 | AU17: 1.712076 | AV17: 1731.459 | AW17: 916.872 | AX17: 1.042142 | AY17: 1.118326 | AZ17: 214.5 | BA17: 1.01885 | BB17: 87.9 | BC17: 22.13348 | BD17: 5.966305 | BE17: 0.8146667 | BF17: 3.916631 | BG17: 4.424242 | BH17: 4.157609 | BI17: 0.865 | BJ17: 0.927 | BK17: 76.97784 | BL17: 89.05176 | BM17: 0.9930496 | BN17: 1.191451 | BO17: 33.00108 | BP17: 0.98172283 | BQ17: 1586.68 | BR17: 325.75607 | BS17: 10234.34 | BT17: 5586.609 | BU17: 1.08437 | BV17: 0.8964956 | BW17: 0.9473043 | BX17: 1.448959 | BY17: 4.214565 | BZ17: 4.297826 | CA17: 4.287282 | CB17: 0.4894342 | CC17: 6.415819 | CD17: 1.001707 | CE17: 1.132424 | CF17: 1.27775 | CG17: 1.047667 | CH17: 1.008076 | CI17: 1.001435 | CJ17: 1.102598 | CK17: 1.094333 | CL17: 0.8993334 | CM17: 0.939 | CN17: 0.9127 | CO17: 0.895 | CP17: 0.6902699 | CQ17: 0.9953805 | CR17: 4.704239 | CS17: 61.061306 | CT17: 24.65414 | CU17: 18.55147 | CV17: 26.880314 | CW17: 0.9606667 | CX17: 0.9923334 | CY17: 0.967 | CZ17: 0.951 | DA17: 0.95566667 | DB17: 0.84922657 | DC17: 1.1603333 | DD17: 0.73 | DE17: 0.832 | DF17: 0.811 | DG17: 0.88 | DH17: 0.325 | DI17: 0 | DJ17: 0.57 | DK17: 0.8036667 | DL17: 0.8956667 | DM17: 0.9276667 | DN17: 0.904 | DO17: 0.6993333 | DP17: 0.8313333 | DQ17: 1.109667 | DR17: 0.8246667 | DS17: 0.653 | DT17: 0.94733333 | DU17: 527.0786 | DV17: 290.0263 | DW17: 131.0435 | DX17: 0.9596739 | DY17: 0.9913369 | DZ17: 1.018 | EA17: 947.6356 | EB17: 113.1524 | EC17: 0.939 | ED17: 0.895 | EE17: 0.9923334 | EF17: 0.967 | EG17: 0.9606667 | EH17: 0.357 | EI17: 0.16 | EJ17: 18.645 | EK17: 10.4 | EL17: 0.45 | EM17: 2427.9 | EN17: 615.7 | EO17: 91504 | EP17: 62035 | EQ17: 4413 | ER17: 1.24 | ES17: 1.316 | ET17: 1.215 | EU17: 0.5304558 | EV17: 0.6491836 | EW17: 0.7755773 | EX17: 0.5281417 | EY17: 0.647458 | EZ17: 0.7791815 | FA17: 4.003 | FB17: 4.003 | FC17: 16.797 | FD17: 7541.61 | FE17: 47978.18 | FF17: 1.0839687 | FG17: 1.783782 | FH17: 502.5092 | FI17: 9377.514 | FJ17: 7.430468 | FK17: 10.84899 | FL17: 0.8668792 | FM17: 0.9032093
A18: 2008:1 | B18: 16843 | C18: 11316.89 | D18: 2.127715 | E18: 3.180989 | F18: 3.661649 | G18: 5.002198 | H18: 1.017812 | I18: 1.075499 | J18: 1.011754 | K18: 1.102151 | L18: 1.742066 | M18: 97.99264 | N18: 96.979451 | O18: 8.649011 | P18: 1.064 | Q18: -741.5455 | R18: 6.218022 | S18: 2416.966 | T18: 2.041648 | U18: 4.410989 | V18: 1664.662 | W18: 1.072 | X18: 12141.6 | Y18: 1.258921 | Z18: 0.8084787 | AA18: 0.87236 | AB18: 0.97798 | AC18: 86.26572 | AD18: 0.87359 | AE18: 0.83873 | AF18: 0.83723 | AG18: 303.4937 | AH18: 116.5491 | AI18: 1.815495 | AJ18: 1.8586667 | AK18: 14706.54 | AM18: 1.3863846 | AN18: 3.416121 | AO18: 1.7072198 | AP18: 2.7103407 | AQ18: 2.320494 | AR18: 1.599 | AS18: 1.744538 | AT18: 2.042692 | AU18: 1.752176 | AV18: 1732.786 | AW18: 924.095 | AX18: 1.023767 | AY18: 1.122 | AZ18: 228.8667 | BA18: 0.9961223 | BB18: 89.2 | BC18: 22.31769 | BD18: 5.968132 | BE18: 0.8376667 | BF18: 2.966813 | BG18: 3.903846 | BH18: 3.751429 | BI18: 0.868 | BJ18: 0.945 | BK18: 86.60339 | BL18: 98.37621 | BM18: 0.9675229 | BN18: 1.163761 | BO18: 33.04976 | BP18: 1.0039143 | BQ18: 1619.932 | BR18: 342.66706 | BS18: 10315.06 | BT18: 5599.939 | BU18: 1.091978 | BV18: 0.9021077 | BW18: 0.961 | BX18: 1.500768 | BY18: 3.94956 | BZ18: 4.08044 | CA18: 4.013846 | CB18: 0.5053198 | CC18: 6.266342 | CD18: 1.012681 | CE18: 1.138824 | CF18: 1.302769 | CG18: 1.027667 | CH18: 1.013429 | CI18: 0.9968461 | CJ18: 1.121253 | CK18: 1.015667 | CL18: 0.9063333 | CM18: 0.951 | CN18: 0.9176 | CO18: 0.9139999 | CP18: 0.6667209 | CQ18: 0.9948902 | CR18: 4.452637 | CS18: 64.580509 | CT18: 24.25338 | CU18: 17.11929 | CV18: 25.692085 | CW18: 0.9783334 | CX18: 0.9573333 | CY18: 0.9843333 | CZ18: 0.963 | DA18: 0.955 | DB18: 0.8989081 | DC18: 1.134 | DD18: 0.737 | DE18: 0.839 | DF18: 0.819 | DG18: 0.878 | DH18: 0.716 | DI18: 0 | DJ18: 0.578 | DK18: 0.8316666 | DL18: 1.005 | DM18: 0.9593334 | DN18: 0.91933333 | DO18: 0.7256666 | DP18: 0.857 | DQ18: 1.170333 | DR18: 0.855 | DS18: 0.691 | DT18: 0.98166667 | DU18: 528.8763 | DV18: 291.2867 | DW18: 131.455 | DX18: 0.959044 | DY18: 1.002 | DZ18: 1.016 | EA18: 1105.082 | EB18: 105.1632 | EC18: 0.951 | ED18: 0.9139999 | EE18: 0.9573333 | EF18: 0.9843333 | EG18: 0.9783334 | EH18: 0.361 | EI18: 0.16451718 | EJ18: 18.845308 | EK18: 10.693617 | EL18: 0.471 | EM18: 2596 | EN18: 677.37709 | EO18: 100670.32 | EP18: 68249.29 | EQ18: 4855.0676 | ER18: 1.248 | ES18: 1.3350261 | ET18: 1.2321638 | EU18: 0.5488732 | EV18: 0.642522 | EW18: 0.8359249 | EX18: 0.5483897 | EY18: 0.6523488 | EZ18: 0.8331662 | FA18: 4.158 | FB18: 4.158 | FC18: 17.466 | FD18: 7644.815 | FE18: 51900.8 | FF18: 1.1295625 | FG18: 1.736495 | FH18: 463.6046 | FI18: 9192.916 | FJ18: 7.158916 | FK18: 10.80309 | FL18: 0.853489 | FM18: 0.8873507
... A81: 2023:4 | B81: 22672.9 | C81: 15569.92 | D81: 3.08131 | E81: 5.33 | F81: 4.439348 | G81: 3.733696 | H81: 1.024581 | I81: 0.9897586 | J81: 1.007522 | K81: 0.9828809 | L81: 2.542582 | M81: 78.41782 | N81: 83.731848 | O81: 2.7369565 | P81: 1.371099 | Q81: -752.1831 | R81: 8.499999 | S81: 3395.502 | T81: 5.283478 | U81: 4.642424 | V81: 2680.842 | W81: 1.619 | X81: 16914.36 | Y81: 1.303087 | Z81: 0.786272 | AA81: 1.11758 | AB81: 0.98531 | AC81: 81.5788 | AD81: 1.240023 | AE81: 1.360458 | AF81: 1.484715 | AG81: 335.9226 | AH81: 133.2269 | AI81: 2.561808 | AJ81: 2.6103583 | AK81: 27957 | AM81: 2.795297 | AN81: 1.179634 | AO81: 2.7109321 | AP81: 2.8963028 | AQ81: 3.454125 | AR81: 2.512412 | AS81: 2.204206 | AT81: 2.292649 | AU81: 2.65104 | AV81: 2210.889 | AW81: 1255.621 | AX81: 1.085454 | AY81: 1.585641 | AZ81: 226.8934 | BA81: 0.7348283 | BB81: 135.946 | BC81: 30.21 | BD81: 5.766304 | BE81: 1.2555 | BF81: 5.001821 | BG81: 5 | BH81: 3.660152 | BI81: 1.358252 | BJ81: 1.291805 | BK81: 111.0175 | BL81: 106.7159 | BM81: 1.057208 | BN81: 1.252141 | BO81: 39.29513 | BP81: 1.3610086 | BQ81: 2847.999 | BR81: 585.08293 | BS81: 11796.54 | BT81: 6199.585 | BU81: 1.024525 | BV81: 1.241499 | BW81: 1.359315 | BX81: 1.076116 | BY81: 2.464413 | BZ81: 2.959131 | CA81: 1.149848 | CB81: 0.8056434 | CC81: 10.65813 | CD81: 0.9146304 | CE81: 0.9893587 | CF81: 1.016087 | CG81: 0.973837 | CH81: 0.9203044 | CI81: 1.065359 | CJ81: 0.9675217 | CK81: 1.1215758 | CL81: 1.267 | CM81: 1.204108 | CN81: 1.195333 | CO81: 1.256949 | CP81: 0.9294446 | CQ81: 1.144377 | CR81: 3.914467 | CS81: 77.840622 | CT81: 92.97024 | CU81: 22.78703 | CV81: 24.350646 | CW81: 1.336333 | CX81: 1.251 | CY81: 1.467 | CZ81: 1.305 | DA81: 1.2751569 | DB81: 2.4337632 | DC81: 1.0742371 | DD81: 1.1193673 | DE81: 1.2234004 | DF81: 1.1169309 | DG81: 1.1349415 | DH81: 1.1339481 | DI81: 1.3082991 | DJ81: 1.1356541 | DK81: 1.497333 | DL81: 1.526333 | DM81: 2.057333 | DN81: 1.3046667 | DO81: 1.808333 | DP81: 1.293 | DQ81: 1.473333 | DR81: 1.545 | DS81: 1.011667 | DT81: 1.2253333 | DU81: 560.9283 | DV81: 299.2498 | DW81: 104.9435 | DX81: 1.069337 | DY81: 1.196 | DZ81: 1.072372 | EA81: 803.1036 | EB81: 147.7352 | EC81: 1.204108 | ED81: 1.256949 | EE81: 1.251 | EF81: 1.467 | EG81: 1.336333 | EH81: 0.59693274 | EI81: 0.24657938 | EJ81: 28.245465 | EK81: 16.02766 | EL81: 0.70593772 | EM81: 2572.6717 | EN81: 640.57446 | EO81: 95200.788 | EP81: 64541.232 | EQ81: 4591.2865 | ER81: 1.7677324 | ES81: 1.8883674 | ET81: 1.743055 | EU81: 1.721924 | EV81: 1.656975 | EW81: 1.891892 | EX81: 1.594818 | EY81: 1.685663 | EZ81: 1.823915 | FA81: 13.149016 | FB81: 11.901263 | FC81: 51.797504 | FD81: 14130.807 | FE81: 117436.1 | FF81: 1.295 | FG81: 4.957346 | FH81: 896.491 | FI81: 15631.02 | FJ81: 7.208384 | FK81: 17.55085 | FL81: 1.165692 | FM81: 1.155808
A82: 2024:1 | B82: 22718.11 | C82: 15627.98 | D82: 3.101901 | E82: 5.33 | F82: 4.469597 | G82: 3.733696 | H82: 1.028577 | I82: 0.9938503 | J82: 1.010846 | K82: 0.9879254 | L82: 2.556452 | M82: 77.74998 | N82: 83.018744 | O82: 2.8093034 | P82: 1.383663 | Q82: -748.8593 | R82: 8.33 | S82: 3404.148 | T82: 5.110256 | U82: 4.636482 | V82: 2681.569 | W82: 1.631474 | X82: 17221.33 | Y82: 1.303489 | Z82: 0.7891536 | AA82: 1.129615 | AB82: 0.9911295 | AC82: 75.84804 | AD82: 1.246742 | AE82: 1.375492 | AF82: 1.499585 | AG82: 336.5386 | AH82: 133.4712 | AI82: 2.583216 | AJ82: 2.6259174 | AK82: =(AK81*AL82)+AK81 -> 28164.538 | AL82: 0.0074234606 | AM82: 2.7851565 | AN82: 1.0668805 | AO82: 2.7198353 | AP82: 2.4495666 | AQ82: 3.6180602 | AR82: 2.4860063 | AS82: 2.1625286 | AT82: 2.2258682 | AU82: 2.6539677 | AV82: 2219.68 | AW82: 1261.544 | AX82: 1.088157 | AY82: 1.593511 | AZ82: 230.0815 | BA82: 0.7374051 | BB82: 140.4348 | BC82: 30.258 | BD82: 5.786524 | BE82: 1.260858 | BF82: 4.767876 | BG82: 4.856792 | BH82: 3.649781 | BI82: 1.364037 | BJ82: 1.296514 | BK82: 102.858 | BL82: 105.4373 | BM82: 1.062252 | BN82: 1.254637 | BO82: 39.39926 | BP82: 1.3561068 | BQ82: 2873.263 | BR82: 587.8058 | BS82: 11802.43 | BT82: 6194.309 | BU82: 1.029114 | BV82: 1.244899 | BW82: 1.369397 | BX82: 1.099791 | BY82: 2.51649 | BZ82: 2.970473 | CA82: 1.260481 | CB82: 0.8016152 | CC82: 9.288661 | CD82: 0.9201653 | CE82: 0.9942089 | CF82: 1.025356 | CG82: 1.007973 | CH82: 0.94684645 | CI82: 1.0595924 | CJ82: 0.97810139 | CK82: 1.0961926 | CL82: 1.262694 | CM82: 1.206728 | CN82: 1.200154 | CO82: 1.364745 | CP82: 0.90926373 | CQ82: 1.137529 | CR82: 4.106013 | CS82: 75.485933 | CT82: 93.528061 | CU82: 22.074736 | CV82: 24.277594 | CW82: 1.33358 | CX82: 1.257724 | CY82: 1.436381 | CZ82: 1.3085143 | DA82: 1.2637704 | DB82: 2.4371921 | DC82: 1.0634601 | DD82: 1.1281887 | DE82: 1.3150267 | DF82: 1.1425701 | DG82: 1.1627837 | DH82: 1.1396745 | DI82: 1.4456288 | DJ82: 1.1303167 | DK82: 1.511887 | DL82: 1.61739 | DM82: 2.067375 | DN82: 1.3576714 | DO82: 1.878053 | DP82: 1.326365 | DQ82: 1.453001 | DR82: 1.59276 | DS82: 1.011117 | DT82: 1.3365034 | DU82: 563.228 | DV82: 300.13 | DW82: 104.733 | DX82: 1.070804 | DY82: 1.197289 | DZ82: 1.072674 | EA82: 816.3241 | EB82: 144.04182 | EC82: 1.213039 | ED82: 1.2672042 | EE82: 1.2607022 | EF82: 1.4800284 | EG82: 1.3468325 | EH82: 0.59948019 | EI82: 0.24763167 | EJ82: 28.366004 | EK82: 16.096059 | EL82: 0.70895036 | EM82: 2391.946 | EN82: 595.57524 | EO82: 88513.101 | EP82: 60007.325 | EQ82: 4268.7567 | ER82: 1.7808438 | ES82: 1.9023735 | ET82: 1.7559833 | EU82: 1.741513 | EV82: 1.666974 | EW82: 1.919885 | EX82: 1.736297 | EY82: 1.666908 | EZ82: 1.922962 | FA82: 13.299473 | FB82: 13.069426 | FC82: 56.392552 | FD82: 13973.584 | FE82: 123813.4 | FF82: 1.2983437 | FG82: 5.0069195 | FH82: 892.00855 | FI82: 15521.603 | FJ82: 7.2804678 | FK82: 17.726358 | FL82: 1.158449 | FM82: 1.147916
A83: 2024:2 | B83: 22763.41 | C83: 15697.06 | D83: 3.120347 | E83: 4.481978 | F83: 4.066222 | G83: 3.788484 | H83: 1.028126 | I83: 0.9937073 | J83: 1.011543 | K83: 0.9887071 | L83: 2.568573 | M83: 77.1814 | N83: 82.411643 | O83: 2.5224756 | P83: 1.409296 | Q83: -747.191 | R83: 7.481978 | S83: 3418.725 | T83: 4.307192 | U83: 4.399261 | V83: 2681.003 | W83: 1.646726 | X83: 17502.64 | Y83: 1.304401 | Z83: 0.7882749 | AA83: 1.142299 | AB83: 0.9949349 | AC83: 75.29175 | AD83: 1.252824 | AE83: 1.388382 | AF83: 1.50738 | AG83: 337.1545 | AH83: 133.7155 | AI83: 2.597218 | AJ83: 2.6343806 | AK83: =(AK82*AL83)+AK82 -> 28358.353 | AL83: 0.0068815332 | AM83: 2.7774499 | AN83: 0.96073252 | AO83: 2.7292799 | AP83: 2.3878562 | AQ83: 3.7378302 | AR83: 2.4731954 | AS83: 2.1512637 | AT83: 2.1932785 | AU83: 2.6681463 | AV83: 2226.309 | AW83: 1266.248 | AX83: 1.092215 | AY83: 1.601027 | AZ83: 232.1379 | BA83: 0.7410285 | BB83: 143.3247 | BC83: 30.41821 | BD83: 5.757371 | BE83: 1.265176 | BF83: 4.046683 | BG83: 4.191284 | BH83: 3.338722 | BI83: 1.369371 | BJ83: 1.300819 | BK83: 101.6044 | BL83: 104.1544 | BM83: 1.06262 | BN83: 1.255767 | BO83: 39.50367 | BP83: 1.3494758 | BQ83: 2895.487 | BR83: 589.7533 | BS83: 11823.03 | BT83: 6205.428 | BU83: 1.03394 | BV83: 1.25398 | BW83: 1.381058 | BX83: 1.10529 | BY83: 2.37365 | BZ83: 2.853573 | CA83: 1.210617 | CB83: 0.8008136 | CC83: 9.1500242 | CD83: 0.9241801 | CE83: 0.9994817 | CF83: 1.03484 | CG83: 1.030367 | CH83: 0.96656526 | CI83: 1.0561011 | CJ83: 0.98850161 | CK83: 1.0804994 | CL83: 1.266609 | CM83: 1.209221 | CN83: 1.211792 | CO83: 1.443813 | CP83: 0.90474003 | CQ83: 1.133182 | CR83: 3.669382 | CS83: 74.561112 | CT83: 92.966893 | CU83: 21.899017 | CV83: 24.204761 | CW83: 1.334034 | CX83: 1.265621 | CY83: 1.412388 | CZ83: 1.3132979 | DA83: 1.2550095 | DB83: 2.4454183 | DC83: 1.0547699 | DD83: 1.1387289 | DE83: 1.3881365 | DF83: 1.1693013 | DG83: 1.1919103 | DH83: 1.1458763 | DI83: 1.5600762 | DJ83: 1.1299086 | DK83: 1.535722 | DL83: 1.685918 | DM83: 2.083912 | DN83: 1.3984702 | DO83: 1.945651 | DP83: 1.360034 | DQ83: 1.445121 | DR83: 1.63557 | DS83: 1.014985 | DT83: 1.348134 | DU83: 564.281 | DV83: 300.7084 | DW83: 104.7592 | DX83: 1.07234 | DY83: 1.196791 | DZ83: 1.073477 | EA83: 824.8589 | EB83: 139.72057 | EC83: 1.2233687 | ED83: 1.2790743 | EE83: 1.2719287 | EF83: 1.4951145 | EG83: 1.3589805 | EH83: 0.6015331 | EI83: 0.24847968 | EJ83: 28.463143 | EK83: 16.151179 | EL83: 0.71137815 | EM83: 2374.4029 | EN83: 591.20713 | EO83: 87863.923 | EP83: 59567.215 | EQ83: 4237.4485 | ER83: 1.7960088 | ES83: 1.9185734 | ET83: 1.7709366 | EU83: 1.755581 | EV83: 1.675678 | EW83: 1.944427 | EX83: 1.746021 | EY83: 1.678084 | EZ83: 1.947882 | FA83: 13.407532 | FB83: 13.174166 | FC83: 56.708362 | FD83: 14067.276 | FE83: 125417.9 | FF83: 1.3019063 | FG83: 5.0119264 | FH83: 887.5485 | FI83: 15366.387 | FJ83: 7.3023092 | FK83: 17.744085 | FL83: 1.152597 | FM83: 1.146511
A84: 2024:3 | B84: 22831.4 | C84: 15758.95 | D84: 3.135834 | E84: 4.365463 | F84: 4.086235 | G84: 3.871709 | H84: 1.032705 | I84: 0.9982697 | J84: 1.015455 | K84: 0.9934149 | L84: 2.582083 | M84: 76.72114 | N84: 81.920179 | O84: 2.3474281 | P84: 1.42732 | Q84: -745.2227 | R84: 7.365463 | S84: 3428.603 | T84: 4.127323 | U84: 4.361763 | V84: 2687.129 | W84: 1.656841 | X84: 17704.55 | Y84: 1.304986 | Z84: 0.7915273 | AA84: 1.152897 | AB84: 0.9982123 | AC84: 74.84142 | AD84: 1.257556 | AE84: 1.399187 | AF84: 1.517451 | AG84: 337.7706 | AH84: 133.9598 | AI84: 2.617832 | AJ84: 2.647355 | AK84: =(AK83*AL84)+AK83 -> 28550.488 | AL84: 0.0067752416 | AM84: 2.7674179 | AN84: 0.89908963 | AO84: 2.7386649 | AP84: 2.3746389 | AQ84: 3.831395 | AR84: 2.472235 | AS84: 2.1503831 | AT84: 2.1843265 | AU84: 2.6755819 | AV84: 2233.51 | AW84: 1273.536 | AX84: 1.094121 | AY84: 1.61041 | AZ84: 233.9008 | BA84: 0.7447973 | BB84: 145.6667 | BC84: 30.45771 | BD84: 5.728366 | BE84: 1.270075 | BF84: 3.83428 | BG84: 3.999032 | BH84: 3.331465 | BI84: 1.376084 | BJ84: 1.30642 | BK84: 100.4856 | BL84: 103.0094 | BM84: 1.067957 | BN84: 1.25815 | BO84: 39.60836 | BP84: 1.3426471 | BQ84: 2921.494 | BR84: 592.31139 | BS84: 11858.34 | BT84: 6228.569 | BU84: 1.038333 | BV84: 1.261099 | BW84: 1.387061 | BX84: 1.113027 | BY84: 2.341402 | BZ84: 2.811207 | CA84: 1.246587 | CB84: 0.7960087 | CC84: 8.9955551 | CD84: 0.928475 | CE84: 1.004182 | CF84: 1.043345 | CG84: 1.043902 | CH84: 0.98158766 | CI84: 1.0540681 | CJ84: 0.99811941 | CK84: 1.0707876 | CL84: 1.270256 | CM84: 1.21245 | CN84: 1.221067 | CO84: 1.493725 | CP84: 0.89845088 | CQ84: 1.130736 | CR84: 3.4687217 | CS84: 73.601257 | CT84: 92.409092 | CU84: 21.681549 | CV84: 24.132147 | CW84: 1.331691 | CX84: 1.269568 | CY84: 1.389892 | CZ84: 1.3144084 | DA84: 1.2454771 | DB84: 2.4466343 | DC84: 1.0474666 | DD84: 1.1453442 | DE84: 1.4376616 | DF84: 1.1907438 | DG84: 1.2154658 | DH84: 1.1489469 | DI84: 1.6412197 | DJ84: 1.1319036 | DK84: 1.544353 | DL84: 1.727386 | DM84: 2.080058 | DN84: 1.4255104 | DO84: 1.97836 | DP84: 1.383952 | DQ84: 1.422042 | DR84: 1.668063 | DS84: 1.000246 | DT84: 1.3496641 | DU84: 564.8445 | DV84: 301.0276 | DW84: 104.8183 | DX84: 1.073617 | DY84: 1.195423 | DZ84: 1.074232 | EA84: 831.6854 | EB84: 138.74252 | EC84: 1.2286862 | ED84: 1.2851898 | EE84: 1.2777081 | EF84: 1.5029028 | EG84: 1.3652394 | EH84: 0.60386263 | EI84: 0.24944196 | EJ84: 28.573371 | EK84: 16.213727 | EL84: 0.71413307 | EM84: 2360.2013 | EN84: 587.67105 | EO84: 87338.398 | EP84: 59210.936 | EQ84: 4212.1038 | ER84: 1.8038153 | ES84: 1.9269126 | ET84: 1.7786341 | EU84: 1.771833 | EV84: 1.685054 | EW84: 1.971221 | EX84: 1.777248 | EY84: 1.684658 | EZ84: 1.972078 | FA84: 13.532361 | FB84: 13.295262 | FC84: 57.722582 | FD84: 14122.385 | FE84: 126975.8 | FF84: 1.3067813 | FG84: 5.0269622 | FH84: 891.0987 | FI84: 15289.555 | FJ84: 7.2804023 | FK84: 17.815061 | FL84: 1.148033 | FM84: 1.144791
A85: 2024:4 | B85: 22922.18 | C85: 15833.21 | D85: 3.153711 | E85: 3.919753 | F85: 3.980008 | G85: 3.852204 | H85: 1.034775 | I85: 1.000525 | J85: 1.017842 | K85: 0.9957771 | L85: 2.593183 | M85: 75.66521 | N85: 80.792705 | O85: 2.4324798 | P85: 1.434333 | Q85: -742.6611 | R85: 6.919753 | S85: 3442.247 | T85: 3.724205 | U85: 4.271781 | V85: 2694.609 | W85: 1.670427 | X85: 17904.96 | Y85: 1.306189 | Z85: 0.7924889 | AA85: 1.165413 | AB85: 1.001095 | AC85: 73.80831 | AD85: 1.263682 | AE85: 1.412315 | AF85: 1.526977 | AG85: 338.3865 | AH85: 134.2041 | AI85: 2.631799 | AJ85: 2.6573331 | AK85: =(AK84*AL85)+AK84 -> 28803.638 | AL85: 0.0088667501 | AM85: 2.7577779 | AN85: 0.90764327 | AO85: 2.7478511 | AP85: 2.3503606 | AQ85: 3.8998361 | AR85: 2.4729071 | AS85: 2.148875 | AT85: 2.1782506 | AU85: 2.687524 | AV85: 2242.942 | AW85: 1281.031 | AX85: 1.097389 | AY85: 1.61843 | AZ85: 235.3704 | BA85: 0.7522453 | BB85: 147.1832 | BC85: 30.63415 | BD85: 5.750294 | BE85: 1.272131 | BF85: 3.456259 | BG85: 3.631438 | BH85: 3.24863 | BI85: 1.381505 | BJ85: 1.310676 | BK85: 98.11734 | BL85: 100.5858 | BM85: 1.070726 | BN85: 1.259996 | BO85: 39.71332 | BP85: 1.3293536 | BQ85: 2948.319 | BR85: 592.86841 | BS85: 11902.57 | BT85: 6259.328 | BU85: 1.040113 | BV85: 1.267357 | BW85: 1.387854 | BX85: 1.120818 | BY85: 2.313356 | BZ85: 2.772685 | CA85: 1.282833 | CB85: 0.7904366 | CC85: 8.8436937 | CD85: 0.9308013 | CE85: 1.006099 | CF85: 1.048059 | CG85: 1.050293 | CH85: 0.99264582 | CI85: 1.0523588 | CJ85: 1.0055801 | CK85: 1.064085 | CL85: 1.274184 | CM85: 1.215406 | CN85: 1.229303 | CO85: 1.522087 | CP85: 0.89220544 | CQ85: 1.129576 | CR85: 3.5497937 | CS85: 72.083691 | CT85: 92.59391 | CU85: 21.46624 | CV85: 24.059751 | CW85: 1.326602 | CX85: 1.269875 | CY85: 1.368404 | CZ85: 1.3121408 | DA85: 1.2351604 | DB85: 2.441365 | DC85: 1.0404912 | DD85: 1.1484641 | DE85: 1.4699859 | DF85: 1.2086237 | DG85: 1.2343143 | DH85: 1.1490608 | DI85: 1.6980877 | DJ85: 1.1371445 | DK85: 1.551279 | DL85: 1.748722 | DM85: 2.065479 | DN85: 1.4403097 | DO85: 1.99134 | DP85: 1.39901 | DQ85: 1.400638 | DR85: 1.688165 | DS85: 0.9854854 | DT85: 1.3468299 | DU85: 565.8725 | DV85: 301.6481 | DW85: 104.9046 | DX85: 1.075241 | DY85: 1.196497 | DZ85: 1.074653 | EA85: 837.7048 | EB85: 137.3551 | EC85: 1.2293885 | ED85: 1.2859979 | EE85: 1.2784713 | EF85: 1.5039335 | EG85: 1.3660666 | EH85: 0.60483992 | EI85: 0.24984566 | EJ85: 28.619614 | EK85: 16.239968 | EL85: 0.71528882 | EM85: 2327.6211 | EN85: 579.55885 | EO85: 86132.781 | EP85: 58393.59 | EQ85: 4153.9601 | ER85: 1.8048463 | ES85: 1.9280141 | ET85: 1.7796508 | EU85: 1.786844 | EV85: 1.693007 | EW85: 1.995109 | EX85: 1.795243 | EY85: 1.691368 | EZ85: 1.989268 | FA85: 13.647659 | FB85: 13.406793 | FC85: 58.30703 | FD85: 14178.634 | FE85: 128082.7 | FF85: 1.3129688 | FG85: 5.052097 | FH85: 893.77199 | FI85: 15304.844 | FJ85: 7.2949631 | FK85: 17.868506 | FL85: 1.143037 | FM85: 1.142814
A86: 2025:1 | B86: 23027.47 | C86: 15905.55 | D86: 3.174786 | E86: 3.752567 | F86: 3.97002 | G86: 3.832797 | H86: 1.038859 | I86: 1.004648 | J86: 1.021527 | K86: 0.9995806 | L86: 2.604135 | M86: 74.53709 | N86: 79.588138 | O86: 2.4097994 | P86: 1.515683 | Q86: -739.624 | R86: 6.752567 | S86: 3454.274 | T86: 3.548106 | U86: 4.219971 | V86: 2705.513 | W86: 1.684689 | X86: 18113.56 | Y86: 1.307336 | Z86: 0.7950682 | AA86: 1.177861 | AB86: 1.005313 | AC86: 72.70456 | AD86: 1.27119 | AE86: 1.428512 | AF86: 1.540294 | AG86: 338.9888 | AH86: 134.443 | AI86: 2.645355 | AJ86: 2.6664992 | AK86: =(AK85*AL86)+AK85 -> 29107.859 | AL86: 0.010561914 | AM86: 2.7470537 | AN86: 0.88348985 | AO86: 2.7570249 | AP86: 2.3261957 | AQ86: 3.9534428 | AR86: 2.477982 | AS86: 2.1460656 | AT86: 2.166698 | AU86: 2.6976937 | AV86: 2252.968 | AW86: 1287.388 | AX86: 1.100015 | AY86: 1.626861 | AZ86: 228.0092 | BA86: 0.757511 | BB86: 148.5331 | BC86: 30.85101 | BD86: 5.774579 | BE86: 1.274677 | BF86: 3.268694 | BG86: 3.461597 | BH86: 3.234126 | BI86: 1.387301 | BJ86: 1.315439 | BK86: 95.97823 | BL86: 98.39738 | BM86: 1.075714 | BN86: 1.262482 | BO86: 39.81856 | BP86: 1.3201128 | BQ86: 2976.179 | BR86: 593.81957 | BS86: 11946.95 | BT86: 6283.488 | BU86: 1.041085 | BV86: 1.272741 | BW86: 1.388402 | BX86: 1.126422 | BY86: 2.306738 | BZ86: 2.749391 | CA86: 1.333391 | CB86: 0.7880653 | CC86: 8.7732961 | CD86: 0.9322567 | CE86: 1.007187 | CF86: 1.051569 | CG86: 1.053261 | CH86: 1.0009736 | CI86: 1.0513645 | CJ86: 1.0121366 | CK86: 1.0599725 | CL86: 1.278003 | CM86: 1.218393 | CN86: 1.236483 | CO86: 1.540962 | CP86: 0.88776661 | CQ86: 1.12957 | CR86: 3.6036091 | CS86: 70.655691 | CT86: 92.316128 | CU86: 21.295365 | CV86: 23.987571 | CW86: 1.322387 | CX86: 1.270045 | CY86: 1.3502 | CZ86: 1.3098684 | DA86: 1.2260447 | DB86: 2.4350163 | DC86: 1.034551 | DD86: 1.1512956 | DE86: 1.4932505 | DF86: 1.2233818 | DG86: 1.25121 | DH86: 1.1491001 | DI86: 1.740552 | DJ86: 1.1416331 | DK86: 1.557979 | DL86: 1.762919 | DM86: 2.053191 | DN86: 1.4503667 | DO86: 2.002155 | DP86: 1.412418 | DQ86: 1.385851 | DR86: 1.704276 | DS86: 0.9751964 | DT86: 1.3448742 | DU86: 567.4924 | DV86: 303.0836 | DW86: 105.4631 | DX86: 1.076869 | DY86: 1.198467 | DZ86: 1.074867 | EA86: 842.98 | EB86: 135.98155 | EC86: 1.2298743 | ED86: 1.2865569 | EE86: 1.2789992 | EF86: 1.5046465 | EG86: 1.3666387 | EH86: 0.60605072 | EI86: 0.25034581 | EJ86: 28.676906 | EK86: 16.272478 | EL86: 0.71672072 | EM86: 2292.8133 | EN86: 570.89198 | EO86: 84844.729 | EP86: 57520.357 | EQ86: 4091.8407 | ER86: 1.8055595 | ES86: 1.9287759 | ET86: 1.780354 | EU86: 1.800951 | EV86: 1.70104 | EW86: 2.018926 | EX86: 1.795828 | EY86: 1.701242 | EZ86: 2.020392 | FA86: 13.756007 | FB86: 13.511533 | FC86: 58.326038 | FD86: 14261.406 | FE86: 130086.6 | FF86: 1.324375 | FG86: 5.0672533 | FH86: 891.98445 | FI86: 15228.32 | FJ86: 7.2876682 | FK86: 17.904243 | FL86: 1.13855 | FM86: 1.143455
A87: 2025:2 | B87: 23138.91 | C87: 15974.29 | D87: 3.194445 | E87: 3.752567 | F87: 3.979397 | G87: 3.795105 | H87: 1.040414 | I87: 1.006891 | J87: 1.023465 | K87: 1.002074 | L87: 2.613992 | M87: 73.5624 | N87: 78.547392 | O87: 2.2917604 | P87: 1.534047 | Q87: -736.6548 | R87: 6.752567 | S87: 3464.904 | T87: 3.501195 | U87: 4.214375 | V87: 2717.421 | W87: 1.697325 | X87: 18287.87 | Y87: 1.308827 | Z87: 0.7955048 | AA87: 1.190878 | AB87: 1.007963 | AC87: 71.75092 | AD87: 1.278287 | AE87: 1.443681 | AF87: 1.553483 | AG87: 339.5912 | AH87: 134.6819 | AI87: 2.658141 | AJ87: 2.674302 | AK87: =(AK86*AL87)+AK86 -> 29412.021 | AL87: 0.010449476 | AM87: 2.7378801 | AN87: 0.83264897 | AO87: 2.7662935 | AP87: 2.3041819 | AQ87: 3.9952244 | AR87: 2.4843498 | AS87: 2.1431912 | AT87: 2.1532117 | AU87: 2.7053119 | AV87: 2264.038 | AW87: 1293.46 | AX87: 1.101362 | AY87: 1.633949 | AZ87: 229.045 | BA87: 0.7650861 | BB87: 149.4494 | BC87: 31.06897 | BD87: 5.614884 | BE87: 1.27599 | BF87: 3.198864 | BG87: 3.418463 | BH87: 3.23592 | BI87: 1.39203 | BJ87: 1.319297 | BK87: 93.78149 | BL87: 96.14918 | BM87: 1.077086 | BN87: 1.263221 | BO87: 39.92408 | BP87: 1.3070424 | BQ87: 3003.303 | BR87: 594.17708 | BS87: 11991.5 | BT87: 6316.465 | BU87: 1.042579 | BV87: 1.278053 | BW87: 1.37751 | BX87: 1.126422 | BY87: 2.302799 | BZ87: 2.728825 | CA87: 1.383301 | CB87: 0.7857011 | CC87: 8.7469763 | CD87: 0.9341082 | CE87: 1.008766 | CF87: 1.055376 | CG87: 1.055419 | CH87: 1.0073568 | CI87: 1.0509754 | CJ87: 1.0183319 | CK87: 1.0573063 | CL87: 1.282267 | CM87: 1.222076 | CN87: 1.243571 | CO87: 1.536602 | CP87: 0.88776661 | CQ87: 1.129857 | CR87: 3.6398105 | CS87: 69.731752 | CT87: 93.054657 | CU87: 21.231479 | CV87: 23.915609 | CW87: 1.310132 | CX87: 1.262162 | CY87: 1.328184 | CZ87: 1.2999536 | DA87: 1.2130816 | DB87: 2.4194982 | DC87: 1.0294723 | DD87: 1.1467057 | DE87: 1.5002249 | DF87: 1.2364294 | DG87: 1.2607341 | DH87: 1.1425071 | DI87: 1.7621744 | DJ87: 1.1552218 | DK87: 1.537362 | DL87: 1.749677 | DM87: 1.990103 | DN87: 1.4497348 | DO87: 1.941603 | DP87: 1.407996 | DQ87: 1.313693 | DR87: 1.707735 | DS87: 0.9091858 | DT87: 1.3195601 | DU87: 569.4683 | DV87: 304.0667 | DW87: 105.719 | DX87: 1.077595 | DY87: 1.200797 | DZ87: 1.074382 | EA87: 851.0405 | EB87: 134.62173 | EC87: 1.2202259 | ED87: 1.2754545 | EE87: 1.2685208 | EF87: 1.4904477 | EG87: 1.355266 | EH87: 0.60667474 | EI87: 0.25060358 | EJ87: 28.706433 | EK87: 16.289233 | EL87: 0.7174587 | EM87: 2262.7393 | EN87: 563.4038 | EO87: 83731.852 | EP87: 56765.884 | EQ87: 4038.1695 | ER87: 1.7913948 | ES87: 1.9136445 | ET87: 1.766387 | EU87: 1.813377 | EV87: 1.708132 | EW87: 2.040348 | EX87: 1.806578 | EY87: 1.709509 | EZ87: 2.043448 | FA87: 13.851452 | FB87: 13.603809 | FC87: 58.675168 | FD87: 14330.709 | FE87: 131571.2 | FF87: 1.331625 | FG87: 5.0773878 | FH87: 892.87643 | FI87: 15152.179 | FJ87: 7.2803805 | FK87: 17.922148 | FL87: 1.134365 | FM87: 1.146665
A88: 2025:3 | B88: 23265.71 | C88: 16056.57 | D88: 3.211086 | E88: 3.752567 | F88: 3.983059 | G88: 3.775985 | H88: 1.04223 | I88: 1.00931 | J88: 1.025606 | K88: 1.004746 | L88: 2.623494 | M88: 72.61478 | N88: 77.535556 | O88: 2.2587062 | P88: 1.546512 | Q88: -731.7093 | R88: 6.752567 | S88: 3477.741 | T88: 3.46499 | U88: 4.20878 | V88: 2731.588 | W88: 1.708303 | X88: 18417.8 | Y88: 1.310477 | Z88: 0.7960328 | AA88: 1.203049 | AB88: 1.009535 | AC88: 70.82378 | AD88: 1.284234 | AE88: 1.456118 | AF88: 1.56476 | AG88: 340.1935 | AH88: 134.9207 | AI88: 2.671084 | AJ88: 2.682423 | AK88: =(AK87*AL88)+AK87 -> 29710.803 | AL88: 0.010158509 | AM88: 2.7286574 | AN88: 0.80563242 | AO88: 2.7754761 | AP88: 2.2830368 | AQ88: 4.0293829 | AR88: 2.4910408 | AS88: 2.1413179 | AT88: 2.1447578 | AU88: 2.7126444 | AV88: 2278.613 | AW88: 1303.689 | AX88: 1.105714 | AY88: 1.640712 | AZ88: 230.1687 | BA88: 0.772737 | BB88: 150.0564 | BC88: 31.25346 | BD88: 5.614884 | BE88: 1.27691 | BF88: 3.144301 | BG88: 3.379631 | BH88: 3.232777 | BI88: 1.396576 | BJ88: 1.323114 | BK88: 91.65314 | BL88: 93.97089 | BM88: 1.080023 | BN88: 1.265468 | BO88: 40.02988 | BP88: 1.2941013 | BQ88: 3033.981 | BR88: 593.96283 | BS88: 12036.22 | BT88: 6332.01 | BU88: 1.048875 | BV88: 1.284427 | BW88: 1.378435 | BX88: 1.132054 | BY88: 2.312315 | BZ88: 2.718095 | CA88: 1.44139 | CB88: 0.783344 | CC88: 8.6338313 | CD88: 0.9409291 | CE88: 1.015224 | CF88: 1.065347 | CG88: 1.059842 | CH88: 1.0137157 | CI88: 1.0530186 | CJ88: 1.0272934 | CK88: 1.0581053 | CL88: 1.287943 | CM88: 1.224646 | CN88: 1.251929 | CO88: 1.545959 | CP88: 0.88334986 | CQ88: 1.131672 | CR88: 3.6667164 | CS88: 68.491023 | CT88: 93.612985 | CU88: 21.062472 | CV88: 23.843862 | CW88: 1.30778 | CX88: 1.262656 | CY88: 1.315532 | CZ88: 1.2982341 | DA88: 1.2062842 | DB88: 2.4163259 | DC88: 1.0245535 | DD88: 1.1498672 | DE88: 1.5149429 | DF88: 1.2487961 | DG88: 1.2757264 | DH88: 1.142687 | DI88: 1.7908059 | DJ88: 1.1604978 | DK88: 1.546221 | DL88: 1.757492 | DM88: 1.980763 | DN88: 1.4557051 | DO88: 1.948319 | DP88: 1.419704 | DQ88: 1.3033 | DR88: 1.720654 | DS88: 0.90065 | DT88: 1.3183362 | DU88: 570.4623 | DV88: 304.6533 | DW88: 105.8857 | DX88: 1.078921 | DY88: 1.203191 | DZ88: 1.074294 | EA88: 855.1895 | EB88: 133.41013 | EC88: 1.2210453 | ED88: 1.2763966 | EE88: 1.269411 | EF88: 1.4916486 | EG88: 1.3562306 | EH88: 0.60711213 | EI88: 0.25078425 | EJ88: 28.72713 | EK88: 16.300977 | EL88: 0.71797596 | EM88: 2233.5007 | EN88: 556.12363 | EO88: 82649.889 | EP88: 56032.368 | EQ88: 3985.9892 | ER88: 1.7925978 | ES88: 1.9149296 | ET88: 1.7675732 | EU88: 1.825408 | EV88: 1.715111 | EW88: 2.061046 | EX88: 1.829525 | EY88: 1.714854 | EZ88: 2.060838 | FA88: 13.943858 | FB88: 13.693144 | FC88: 59.420447 | FD88: 14375.514 | FE88: 132690.8 | FF88: 1.338625 | FG88: 5.0875425 | FH88: 889.30493 | FI88: 15076.418 | FJ88: 7.2876609 | FK88: 17.957992 | FL88: 1.12966 | FM88: 1.145679
A89: 2025:4 | B89: 23401.21 | C89: 16140.21 | D89: 3.229392 | E89: 3.752567 | F89: 4.002827 | G89: 3.756962 | H89: 1.044567 | I89: 1.012256 | J89: 1.028219 | K89: 1.00755 | L89: 2.635223 | M89: 72.39818 | N89: 77.304279 | O89: 2.2697243 | P89: 1.563078 | Q89: -727.246 | R89: 6.752567 | S89: 3490.706 | T89: 3.442641 | U89: 4.260432 | V89: 2749.221 | W89: 1.719891 | X89: 18546.75 | Y89: 1.312105 | Z89: 0.7969772 | AA89: 1.21509 | AB89: 1.011264 | AC89: 70.61185 | AD89: 1.290581 | AE89: 1.469358 | AF89: 1.576427 | AG89: 340.7959 | AH89: 135.1596 | AI89: 2.687087 | AJ89: 2.6944602 | AK89: =(AK88*AL89)+AK88 -> 30031.502 | AL89: 0.010794002 | AM89: 2.720334 | AN89: 0.79710271 | AO89: 2.7855601 | AP89: 2.2797558 | AQ89: 4.0638096 | AR89: 2.5001927 | AS89: 2.1463709 | AT89: 2.146356 | AU89: 2.7223584 | AV89: 2289.361 | AW89: 1311.822 | AX89: 1.110331 | AY89: 1.648617 | AZ89: 234.5104 | BA89: 0.7770643 | BB89: 151.0428 | BC89: 31.43292 | BD89: 5.510904 | BE89: 1.280561 | BF89: 3.101018 | BG89: 3.343411 | BH89: 3.241115 | BI89: 1.402212 | BJ89: 1.328275 | BK89: 90.87003 | BL89: 93.16884 | BM89: 1.08388 | BN89: 1.268123 | BO89: 40.13596 | BP89: 1.2868947 | BQ89: 3061.557 | BR89: 595.5064 | BS89: 12099.65 | BT89: 6360.82 | BU89: 1.054081 | BV89: 1.289181 | BW89: 1.380722 | BX89: 1.13545 | BY89: 2.316569 | BZ89: 2.704729 | CA89: 1.492708 | CB89: 0.7825606 | CC89: 8.5907913 | CD89: 0.9465927 | CE89: 1.020568 | CF89: 1.07377 | CG89: 1.062991 | CH89: 1.0191082 | CI89: 1.0556067 | CJ89: 1.0354857 | CK89: 1.0596858 | CL89: 1.292228 | CM89: 1.22778 | CN89: 1.258335 | CO89: 1.554686 | CP89: 0.88070773 | CQ89: 1.134971 | CR89: 3.6851 | CS89: 68.082477 | CT89: 94.08105 | CU89: 20.978474 | CV89: 23.820018 | CW89: 1.307061 | CX89: 1.264134 | CY89: 1.305738 | CZ89: 1.297578 | DA89: 1.2009645 | DB89: 2.4177349 | DC89: 1.0207481 | DD89: 1.1536847 | DE89: 1.5269393 | DF89: 1.2583777 | DG89: 1.289663 | DH89: 1.1437819 | DI89: 1.8133637 | DJ89: 1.1629212 | DK89: 1.553477 | DL89: 1.765584 | DM89: 1.9771 | DN89: 1.4614732 | DO89: 1.9595 | DP89: 1.43228 | DQ89: 1.298448 | DR89: 1.73233 | DS89: 0.8965735 | DT89: 1.3192713 | DU89: 572.5895 | DV89: 305.8647 | DW89: 106.3642 | DX89: 1.079608 | DY89: 1.205291 | DZ89: 1.073815 | EA89: 862.0509 | EB89: 133.41013 | EC89: 1.2230711 | ED89: 1.278726 | EE89: 1.2716121 | EF89: 1.4946168 | EG89: 1.3586153 | EH89: 0.60884793 | EI89: 0.25150127 | EJ89: 28.809263 | EK89: 16.347583 | EL89: 0.72002872 | EM89: 2226.8176 | EN89: 554.45959 | EO89: 82402.583 | EP89: 55864.708 | EQ89: 3974.0623 | ER89: 1.7955718 | ES89: 1.9181066 | ET89: 1.7705057 | EU89: 1.838782 | EV89: 1.723262 | EW89: 2.083946 | EX89: 1.844905 | EY89: 1.722153 | EZ89: 2.081514 | FA89: 14.046589 | FB89: 13.792885 | FC89: 59.919968 | FD89: 14436.699 | FE89: 134022.1 | FF89: 1.345375 | FG89: 5.0926301 | FH89: 888.41562 | FI89: 15031.188 | FJ89: 7.2730855 | FK89: 17.97595 | FL89: 1.127046 | FM89: 1.145101
A90: 2026:1 | B90: 23532.32 | C90: 16228.25 | D90: 3.24939 | E90: 3.592513 | F90: 3.843453 | G90: 3.738034 | H90: 1.050009 | I90: 1.01755 | J90: 1.032968 | K90: 1.009927 | L90: 2.648767 | M90: 72.42525 | N90: 77.333189 | O90: 2.2917604 | P90: 1.582932 | Q90: -724.7025 | R90: 6.592513 | S90: 3505.119 | T90: 3.274368 | U90: 4.210426 | V90: 2767.68 | W90: 1.733026 | X90: 18703.8 | Y90: 1.313307 | Z90: 0.8005563 | AA90: 1.22529 | AB90: 1.0147 | AC90: 70.63834 | AD90: 1.297355 | AE90: 1.483404 | AF90: 1.5882 | AG90: 342.1491 | AH90: 135.393 | AI90: 2.704375 | AJ90: 2.7084559 | AK90: =(AK89*AL90)+AK89 -> 30358.276 | AL90: 0.010881046 | AM90: 2.7108612 | AN90: 0.79414391 | AO90: 2.7958012 | AP90: 2.2842598 | AQ90: 4.0983641 | AR90: 2.511867 | AS90: 2.153978 | AT90: 2.1518738 | AU90: 2.7366093 | AV90: 2301.286 | AW90: 1318.978 | AX90: 1.113372 | AY90: 1.656253 | AZ90: 236 | BA90: 0.7817267 | BB90: 151.9139 | BC90: 31.67192 | BD90: 5.510904 | BE90: 1.285023 | BF90: 2.951464 | BG90: 3.217902 | BH90: 3.119768 | BI90: 1.407822 | BJ90: 1.333684 | BK90: 90.36194 | BL90: 92.6478 | BM90: 1.090688 | BN90: 1.271436 | BO90: 40.24231 | BP90: 1.2792194 | BQ90: 3090.079 | BR90: 597.74779 | BS90: 12180.51 | BT90: 6410.95 | BU90: 1.058792 | BV90: 1.295579 | BW90: 1.389272 | BX90: 1.139992 | BY90: 2.237498 | BZ90: 2.636856 | CA90: 1.474485 | CB90: 0.7817781 | CC90: 8.5480084 | CD90: 0.9504295 | CE90: 1.025725 | CF90: 1.082426 | CG90: 1.06651 | CH90: 1.0234857 | CI90: 1.0586442 | CJ90: 1.0435991 | CK90: 1.0623481 | CL90: 1.298319 | CM90: 1.230913 | CN90: 1.266711 | CO90: 1.57104 | CP90: 0.87719894 | CQ90: 1.13905 | CR90: 3.107412 | CS90: 67.836591 | CT90: 94.175131 | CU90: 20.853105 | CV90: 23.772378 | CW90: 1.311683 | CX90: 1.270057 | CY90: 1.301351 | CZ90: 1.3013167 | DA90: 1.1991539 | DB90: 2.4263014 | DC90: 1.0175004 | DD90: 1.1617384 | DE90: 1.5440385 | DF90: 1.2684549 | DG90: 1.3066011 | DH90: 1.1483821 | DI90: 1.841459 | DJ90: 1.1621197 | DK90: 1.561896 | DL90: 1.784881 | DM90: 1.987616 | DN90: 1.4743741 | DO90: 1.985552 | DP90: 1.453039 | DQ90: 1.295713 | DR90: 1.756052 | DS90: 0.8921202 | DT90: 1.3254039 | DU90: 573.4465 | DV90: 306.6265 | DW90: 106.6634 | DX90: 1.080747 | DY90: 1.207635 | DZ90: 1.073575 | EA90: 864.6373 | EB90: 134.07718 | EC90: 1.2306446 | ED90: 1.287436 | EE90: 1.2798447 | EF90: 1.5057024 | EG90: 1.3675281 | EH90: 0.61096944 | EI90: 0.25237762 | EJ90: 28.909649 | EK90: 16.404545 | EL90: 0.72253765 | EM90: 2227.653 | EN90: 554.66759 | EO90: 82433.496 | EP90: 55885.665 | EQ90: 3975.5532 | ER90: 1.8066904 | ES90: 1.929984 | ET90: 1.7814691 | EU90: 1.854281 | EV90: 1.732543 | EW90: 2.109549 | EX90: 1.850262 | EY90: 1.733154 | EZ90: 2.109549 | FA90: 14.165631 | FB90: 13.908603 | FC90: 60.093971 | FD90: 14528.918 | FE90: 135827.2 | FF90: 1.3534375 | FG90: 5.1028153 | FH90: 889.30404 | FI90: 14956.033 | FJ90: 7.2439932 | FK90: 17.993926 | FL90: 1.12427 | FM90: 1.14274
A91: 2026:2 | B91: 23629.38 | C91: 16339.09 | D91: 3.270308 | E91: 3.592513 | F91: 3.733095 | G91: 3.76696 | H91: 1.054443 | I91: 1.021731 | J91: 1.036559 | K91: 1.012851 | L91: 2.662495 | M91: 72.26281 | N91: 77.159731 | O91: 2.3027785 | P91: 1.592026 | Q91: -721.1714 | R91: 6.592513 | S91: 3522.33 | T91: 3.227863 | U91: 4.205821 | V91: 2778.526 | W91: 1.745794 | X91: 18971.5 | Y91: 1.314261 | Z91: 0.8033891 | AA91: 1.232237 | AB91: 1.020478 | AC91: 70.4794 | AD91: 1.304381 | AE91: 1.496827 | AF91: 1.603228 | AG91: 342.7387 | AH91: 135.6263 | AI91: 2.722205 | AJ91: 2.7226659 | AK91: =(AK90*AL91)+AK90 -> 30648.576 | AL91: 0.0095624728 | AM91: 2.7016451 | AN91: 0.78870482 | AO91: 2.8060108 | AP91: 2.2834805 | AQ91: 4.1307329 | AR91: 2.5232299 | AS91: 2.160088 | AT91: 2.1548991 | AU91: 2.7493302 | AV91: 2315.536 | AW91: 1325.524 | AX91: 1.115592 | AY91: 1.664392 | AZ91: 238 | BA91: 0.7864171 | BB91: 152.7735 | BC91: 31.9213 | BD91: 5.484539 | BE91: 1.289292 | BF91: 2.905773 | BG91: 3.20088 | BH91: 3.031683 | BI91: 1.413813 | BJ91: 1.33943 | BK91: 89.6209 | BL91: 91.88866 | BM91: 1.095982 | BN91: 1.273926 | BO91: 40.34896 | BP91: 1.2715899 | BQ91: 3122.153 | BR91: 599.94053 | BS91: 12247.25 | BT91: 6448.246 | BU91: 1.063264 | BV91: 1.301584 | BW91: 1.396851 | BX91: 1.144552 | BY91: 2.244632 | BZ91: 2.626989 | CA91: 1.523438 | CB91: 0.7809963 | CC91: 8.5309805 | CD91: 0.9553667 | CE91: 1.030338 | CF91: 1.089833 | CG91: 1.068623 | CH91: 1.0273539 | CI91: 1.0614143 | CJ91: 1.050661 | CK91: 1.0645227 | CL91: 1.304121 | CM91: 1.234162 | CN91: 1.274608 | CO91: 1.584756 | CP91: 0.87370412 | CQ91: 1.142685 | CR91: 3.1227871 | CS91: 67.414775 | CT91: 94.269306 | CU91: 20.686944 | CV91: 23.677288 | CW91: 1.315928 | CX91: 1.275311 | CY91: 1.297862 | CZ91: 1.3045141 | DA91: 1.1975992 | DB91: 2.4330442 | DC91: 1.0145354 | DD91: 1.1690963 | DE91: 1.5586128 | DF91: 1.2773865 | DG91: 1.3219651 | DH91: 1.1524489 | DI91: 1.8654302 | DJ91: 1.1616733 | DK91: 1.573178 | DL91: 1.801652 | DM91: 1.999437 | DN91: 1.4848685 | DO91: 2.011864 | DP91: 1.471641 | DQ91: 1.299211 | DR91: 1.775744 | DS91: 0.8939664 | DT91: 1.3322735 | DU91: 575.0597 | DV91: 307.3772 | DW91: 106.9902 | DX91: 1.082466 | DY91: 1.20902 | DZ91: 1.07398 | EA91: 868.1333 | EB91: 134.34534 | EC91: 1.237358 | ED91: 1.2951615 | EE91: 1.287144 | EF91: 1.5155432 | EG91: 1.375432 | EH91: 0.61299911 | EI91: 0.25321603 | EJ91: 29.005688 | EK91: 16.459042 | EL91: 0.72493795 | EM91: 2222.6407 | EN91: 553.41956 | EO91: 82248.016 | EP91: 55759.92 | EQ91: 3966.608 | ER91: 1.8165462 | ES91: 1.9405124 | ET91: 1.7911874 | EU91: 1.871362 | EV91: 1.742042 | EW91: 2.135969 | EX91: 1.867203 | EY91: 1.742293 | EZ91: 2.137489 | FA91: 14.296833 | FB91: 14.036044 | FC91: 60.644187 | FD91: 14605.534 | FE91: 137626.2 | FF91: 1.3590625 | FG91: 5.1283294 | FH91: 890.19334 | FI91: 14903.686 | FJ91: 7.2439932 | FK91: 18.01192 | FL91: 1.122275 | FM91: 1.139579
A92: 2026:3 | B92: 23752.46 | C92: 16403.65 | D92: 3.285732 | E92: 3.592513 | F92: 3.729817 | G92: 3.614401 | H92: 1.059416 | I92: 1.026827 | J92: 1.040911 | K92: 1.014982 | L92: 2.672356 | M92: 72.28086 | N92: 77.179004 | O92: 2.3137966 | P92: 1.599547 | Q92: -718.1285 | R92: 6.592513 | S92: 3532.205 | T92: 3.215887 | U92: 4.201008 | V92: 2796.972 | W92: 1.755549 | X92: 19052.18 | Y92: 1.315403 | Z92: 0.8066835 | AA92: 1.241676 | AB92: 1.02246 | AC92: 70.49706 | AD92: 1.309764 | AE92: 1.508465 | AF92: 1.613019 | AG92: 343.3284 | AH92: 135.8597 | AI92: 2.735633 | AJ92: 2.7329663 | AK92: =(AK91*AL92)+AK91 -> 30935.386 | AL92: 0.0093580172 | AM92: 2.6924744 | AN92: 0.78315066 | AO92: 2.8134996 | AP92: 2.287447 | AQ92: 4.1538793 | AR92: 2.5322416 | AS92: 2.1655704 | AT92: 2.1580864 | AU92: 2.7584455 | AV92: 2332.144 | AW92: 1334.707 | AX92: 1.120303 | AY92: 1.670669 | AZ92: 240 | BA92: 0.7903492 | BB92: 153.1583 | BC92: 32.11948 | BD92: 5.551847 | BE92: 1.291966 | BF92: 2.883506 | BG92: 3.184337 | BH92: 3.024173 | BI92: 1.418364 | BJ92: 1.3439 | BK92: 89.19736 | BL92: 91.45433 | BM92: 1.102998 | BN92: 1.277822 | BO92: 40.45588 | BP92: 1.2652635 | BQ92: 3153.738 | BR92: 600.93638 | BS92: 12290.12 | BT92: 6470.539 | BU92: 1.066433 | BV92: 1.308044 | BW92: 1.397927 | BX92: 1.14913 | BY92: 2.251865 | BZ92: 2.617923 | CA92: 1.570301 | CB92: 0.7802153 | CC92: 8.5139865 | CD92: 0.9589841 | CE92: 1.03364 | CF92: 1.095545 | CG92: 1.069709 | CH92: 1.0300753 | CI92: 1.0632218 | CJ92: 1.0562537 | CK92: 1.0659016 | CL92: 1.31045 | CM92: 1.236855 | CN92: 1.283047 | CO92: 1.587925 | CP92: 0.87022323 | CQ92: 1.144943 | CR92: 3.1303536 | CS92: 67.162962 | CT92: 94.269306 | CU92: 20.522108 | CV92: 23.582579 | CW92: 1.315421 | CX92: 1.275985 | CY92: 1.291801 | CZ92: 1.3033946 | DA92: 1.1938022 | DB92: 2.432379 | DC92: 1.0123604 | DD92: 1.1722915 | DE92: 1.5666076 | DF92: 1.2862366 | DG92: 1.3332846 | DH92: 1.1527077 | DI92: 1.8817826 | DJ92: 1.1669407 | DK92: 1.58675 | DL92: 1.80486 | DM92: 1.996673 | DN92: 1.4869407 | DO92: 2.018718 | DP92: 1.480082 | DQ92: 1.299386 | DR92: 1.781093 | DS92: 0.8943785 | DT92: 1.3332691 | DU92: 576.9799 | DV92: 308.3351 | DW92: 107.294 | DX92: 1.082677 | DY92: 1.210408 | DZ92: 1.073382 | EA92: 874.3412 | EB92: 133.67361 | EC92: 1.2383116 | ED92: 1.2962595 | EE92: 1.2881806 | EF92: 1.5169444 | EG92: 1.3765554 | EH92: 0.61427075 | EI92: 0.25374132 | EJ92: 29.065859 | EK92: 16.493186 | EL92: 0.7264418 | EM92: 2223.1976 | EN92: 553.55823 | EO92: 82268.625 | EP92: 55773.891 | EQ92: 3967.6019 | ER92: 1.8179461 | ES92: 1.9420079 | ET92: 1.7925677 | EU92: 1.884242 | EV92: 1.748695 | EW92: 2.154848 | EX92: 1.886612 | EY92: 1.748562 | EZ92: 2.154752 | FA92: 14.39576 | FB92: 14.132206 | FC92: 61.274553 | FD92: 14658.084 | FE92: 138737.7 | FF92: 1.3638125 | FG92: 5.1539711 | FH92: 891.08354 | FI92: 14844.072 | FJ92: 7.2295052 | FK92: 18.065956 | FL92: 1.119429 | FM92: 1.139361
A93: 2026:4 | B93: 23846.91 | C93: 16472.96 | D93: 3.300419 | E93: 3.592513 | F93: 3.728277 | G93: 3.546352 | H93: 1.064733 | I93: 1.031989 | J93: 1.045256 | K93: 1.017563 | L93: 2.681774 | M93: 72.36208 | N93: 77.265733 | O93: 2.3248146 | P93: 1.605495 | Q93: -715.7226 | R93: 6.592513 | S93: 3542.76 | T93: 3.206729 | U93: 4.259835 | V93: 2810.693 | W93: 1.764659 | X93: 19182.57 | Y93: 1.316168 | Z93: 0.8104071 | AA93: 1.248472 | AB93: 1.025886 | AC93: 70.57654 | AD93: 1.314821 | AE93: 1.519014 | AF93: 1.623275 | AG93: 343.9181 | AH93: 136.093 | AI93: 2.748521 | AJ93: 2.7429657 | AK93: =(AK92*AL93)+AK92 -> 31178.304 | AL93: 0.0078524262 | AM93: 2.6832673 | AN93: 0.78016137 | AO93: 2.8198664 | AP93: 2.2930529 | AQ93: 4.1749839 | AR93: 2.540569 | AS93: 2.1710606 | AT93: 2.161753 | AU93: 2.7671634 | AV93: 2348.301 | AW93: 1344.28 | AX93: 1.12724 | AY93: 1.67736 | AZ93: 242 | BA93: 0.7824457 | BB93: 153.6942 | BC93: 32.28556 | BD93: 5.685722 | BE93: 1.298204 | BF93: 2.851449 | BG93: 3.154301 | BH93: 3.004359 | BI93: 1.423724 | BJ93: 1.349753 | BK93: 90.19991 | BL93: 92.48193 | BM93: 1.112046 | BN93: 1.283073 | BO93: 40.56309 | BP93: 1.278044 | BQ93: 3183.773 | BR93: 603.96908 | BS93: 12350.51 | BT93: 6503.405 | BU93: 1.07059 | BV93: 1.312312 | BW93: 1.400857 | BX93: 1.153727 | BY93: 2.259195 | BZ93: 2.609618 | CA93: 1.615182 | CB93: 0.7794351 | CC93: 8.4546261 | CD93: 0.963594 | CE93: 1.037938 | CF93: 1.10242 | CG93: 1.071503 | CH93: 1.0330644 | CI93: 1.0660128 | CJ93: 1.0624713 | CK93: 1.0682294 | CL93: 1.31463 | CM93: 1.23929 | CN93: 1.288847 | CO93: 1.593354 | CP93: 0.8667562 | CQ93: 1.148526 | CR93: 3.1359633 | CS93: 66.970554 | CT93: 95.211999 | CU93: 20.358585 | CV93: 23.488249 | CW93: 1.316606 | CX93: 1.27798 | CY93: 1.287871 | CZ93: 1.3036443 | DA93: 1.1913374 | DB93: 2.4365127 | DC93: 1.0099758 | DD93: 1.1763886 | DE93: 1.5740096 | DF93: 1.2924356 | DG93: 1.3439146 | DH93: 1.1542106 | DI93: 1.8951124 | DJ93: 1.1683392 | DK93: 1.595252 | DL93: 1.811406 | DM93: 1.998602 | DN93: 1.4910613 | DO93: 2.029998 | DP93: 1.490555 | DQ93: 1.300701 | DR93: 1.789631 | DS93: 0.8951911 | DT93: 1.3359275 | DU93: 579.2029 | DV93: 309.256 | DW93: 107.8318 | DX93: 1.083309 | DY93: 1.211043 | DZ93: 1.073229 | EA93: 880.4962 | EB93: 134.20831 | EC93: 1.2409066 | ED93: 1.2992476 | EE93: 1.2910021 | EF93: 1.5207567 | EG93: 1.3796127 | EH93: 0.61723643 | EI93: 0.25496637 | EJ93: 29.206188 | EK93: 16.572814 | EL93: 0.72994904 | EM93: 2225.7037 | EN93: 554.18225 | EO93: 82361.365 | EP93: 55836.764 | EQ93: 3972.0745 | ER93: 1.8217559 | ES93: 1.9460776 | ET93: 1.7963243 | EU93: 1.895365 | EV93: 1.755066 | EW93: 2.172754 | EX93: 1.899103 | EY93: 1.754846 | EZ93: 2.172693 | FA93: 14.481194 | FB93: 14.215286 | FC93: 61.68026 | FD93: 14710.764 | FE93: 139892.8 | FF93: 1.3676875 | FG93: 5.164279 | FH93: 890.19245 | FI93: 14777.273 | FJ93: 7.2150462 | FK93: 18.084022 | FL93: 1.121091 | FM93: 1.139967
... A141: 2038:4 | B141: 29713.28 | C141: 20704.2 | D141: 4.3094 | E141: 3.490907 | F141: 2.96697 | G141: 3.77304 | H141: 1.369279 | I141: 1.296088 | J141: 1.288241 | K141: 1.202093 | L141: 3.377792 | M141: 87.12691 | N141: 93.031104 | O141: 2.9528451 | P141: 1.245799 | Q141: -420.1026 | R141: 6.46444 | S141: 4204.763 | T141: 3.110346 | U141: 4.266419 | V141: 3638.919 | W141: 2.376636 | X141: 26850.04 | Y141: 1.362051 | Z141: 1.005641 | AA141: 1.483912 | AB141: 1.208002 | AC141: 85.0224 | AD141: 1.6522 | AE141: 2.179687 | AF141: 2.220108 | AG141: 371.3216 | AH141: 226.0922 | AI141: 3.524657 | AJ141: 3.4771281 | AK141: =(AK140*AL141)+AK140 -> 48816.541 | AL141: 0.011195132 | AM141: 2.2755052 | AN141: 0.65944557 | AO141: 3.3396674 | AP141: 2.8577825 | AQ141: 5.5492183 | AR141: 3.1910497 | AS141: 2.6553781 | AT141: 2.562153 | AU141: 3.5308633 | AV141: 3022.338 | AW141: 1798.8 | AX141: 1.44286 | AY141: 2.134407 | AZ141: 216.0564 | BA141: 0.7839263 | BB141: 203.4402 | BC141: 42.55571 | BD141: 5.524924 | BE141: 1.598324 | BF141: 2.632354 | BG141: 2.98086 | BH141: 2.1535 | BI141: 1.77508 | BJ141: 1.695765 | BK141: 110.2852 | BL141: 111.1417 | BM141: 1.580733 | BN141: 1.548784 | BO141: 46.05748 | BP141: 1.2756301 | BQ141: 4765.104 | BR141: 748.31365 | BS141: 15399.22 | BT141: 8029.32 | BU141: 1.31043 | BV141: 1.62174 | BW141: 1.730952 | BX141: 1.139256 | BY141: 1.950486 | BZ141: 2.176812 | CA141: 2.041778 | CB141: 0.7416308 | CC141: 8.9612055 | CD141: 1.212828 | CE141: 1.284432 | CF141: 1.431023 | CG141: 1.230038 | CH141: 1.1551395 | CI141: 1.2443819 | CJ141: 1.2907307 | CK141: 1.2199246 | CL141: 1.624582 | CM141: 1.412867 | CN141: 1.68725 | CO141: 2.035334 | CP141: 0.87232492 | CQ141: 1.37121 | CR141: 0.67206389 | CS141: 78.539025 | CT141: 100.13757 | CU141: 18.576273 | CV141: 21.163138 | CW141: 1.568763 | CX141: 1.51077 | CY141: 1.450762 | CZ141: 1.5016589 | DA141: 1.3087183 | DB141: 2.8616568 | DC141: 0.99562305 | DD141: 1.4906975 | DE141: 2.1156281 | DF141: 1.5928663 | DG141: 1.7193296 | DH141: 1.3275328 | DI141: 2.7427351 | DJ141: 1.2027278 | DK141: 2.190194 | DL141: 2.460646 | DM141: 2.708966 | DN141: 1.8953847 | DO141: 2.980261 | DP141: 2.025968 | DQ141: 1.486016 | DR141: 2.449708 | DS141: 0.9784943 | DT141: 1.6337601 | DU141: 674.921 | DV141: 347.9037 | DW141: 127.0891 | DX141: 1.181816 | DY141: 1.348577 | DZ141: 1.119444 | EA141: 942.7303 | EB141: 122.29588 | EC141: 1.533311 | ED141: 1.6396052 | EE141: 1.6106095 | EF141: 1.9590465 | EG141: 1.7261807 | EH141: 0.75992971 | EI141: 0.31390973 | EJ141: 35.958101 | EK141: 20.404132 | EL141: 0.89869932 | EM141: 2681.2689 | EN141: 667.61429 | EO141: 99219.389 | EP141: 67265.636 | EQ141: 4785.0931 | ER141: 2.2510303 | ES141: 2.4046468 | ET141: 2.219606 | EU141: 2.717498 | EV141: 2.229051 | EW141: 3.449711 | EX141: 2.717404 | EY141: 2.228408 | EZ141: 3.448542 | FA141: 20.795903 | FB141: 20.36041 | FC141: 88.257529 | FD141: 18680.602 | FE141: 222040.7 | FF141: 1.6932813 | FG141: 6.1715626 | FH141: 932.4821 | FI141: 14354.058 | FJ141: 6.9529101 | FK141: 20.07054 | FL141: 1.119124 | FM141: 1.151446

Sheet World Macro Links
A2: OECD GDP Projections
A3: OECD Population Projections
A5: Stats Canada Population Projections

Sheet Canadian GDP
A1: CANADA ECONOMIC GROWTH (million USD)
B2: Value | C2: GDP Growth | D2: Per Cap GDP M2 Medium Growth 5 Scenario | E2: Per Cap GDP Med Growth Scenario
A3: 2020 | B3: 1610008 | H3: OECD - 2024
A4: 2021 | B4: 1683116 | C4: =B4/B3-1 -> 0.04540847 | D4: 38246.1 | H4: GDP - in USD constant 2015 exchange
A5: 2022 | B5: 1737807 | C5: =B5/B4-1 -> 0.032493898 | D5: 38882.1 | E5: =D5/D4-1 -> 0.016629147
A6: 2023 | B6: 1755761 | C6: =B6/B5-1 -> 0.010331412 | D6: 39426.2 | E6: =D6/D5-1 -> 0.013993586
A7: 2024 | B7: 1779192 | C7: =B7/B6-1 -> 0.01334521 | D7: 39953.6 | E7: =D7/D6-1 -> 0.013376892
A8: 2025 | B8: =B7*1.015 -> 1805879.9 | C8: =B8/B7-1 -> 0.015 | D8: 40465.6 | E8: =D8/D7-1 -> 0.012814865
A9: 2026 | B9: =B8*(1+G10) -> 1833886.9 | C9: =B9/B8-1 -> 0.015508792 | D9: 40965.9 | E9: =D9/D8-1 -> 0.012363588
A10: 2027 | B10: =B9*(1+G11) -> 1861994.4 | C10: =B10/B9-1 -> 0.015326734 | D10: 41454.4 | E10: =D10/D9-1 -> 0.011924552 | G10: 0.015508792
A11: 2028 | B11: =B10*(1+G12) -> 1890198.6 | C11: =B11/B10-1 -> 0.015147336 | D11: 41930.6 | E11: =D11/D10-1 -> 0.011487321 | G11: 0.015326734
A12: 2029 | B12: =B11*(1+G13) -> 1918477.3 | C12: =B12/B11-1 -> 0.014960695 | D12: 42394 | E12: =D12/D11-1 -> 0.011051595 | G12: 0.015147336
A13: 2030 | B13: =B12*(1+G14) -> 1946823 | C13: =B13/B12-1 -> 0.014775088 | D13: 42844 | E13: =D13/D12-1 -> 0.01061471 | G13: 0.014960695
A14: 2031 | B14: =B13*(1+G15) -> 1975250.5 | C14: =B14/B13-1 -> 0.014602018 | D14: 43280 | E14: =D14/D13-1 -> 0.010176454 | G14: 0.014775088
A15: 2032 | B15: =B14*(1+G16) -> 2003756.2 | C15: =B15/B14-1 -> 0.014431433 | D15: 43701.6 | E15: =D15/D14-1 -> 0.00974122 | G15: 0.014602018
A16: 2033 | B16: =B15*(1+G17) -> 2032311.2 | C16: =B16/B15-1 -> 0.014250738 | D16: 44113.5 | E16: =D16/D15-1 -> 0.0094252842 | G16: 0.014431433
A17: 2034 | B17: =B16*(1+G18) -> 2060888.6 | C17: =B17/B16-1 -> 0.014061495 | D17: 44515.2 | E17: =D17/D16-1 -> 0.009106056 | G17: 0.014250738
A18: 2035 | B18: =B17*(1+G19) -> 2089488.2 | C18: =B18/B17-1 -> 0.013877346 | D18: 44906.8 | E18: =D18/D17-1 -> 0.0087969952 | G18: 0.014061495
A19: 2036 | B19: =B18*(1+G20) -> 2118152.1 | C19: =B19/B18-1 -> 0.013718124 | D19: 45288.7 | E19: =D19/D18-1 -> 0.00850428 | G19: 0.013877346
A20: 2037 | B20: =B19*(1+G21) -> 2146929.5 | C20: =B20/B19-1 -> 0.013586071 | D20: 45661.2 | E20: =D20/D19-1 -> 0.0082250098 | G20: 0.013718124
A21: 2038 | B21: =B20*(1+G22) -> 2175859.4 | C21: =B21/B20-1 -> 0.013475033 | D21: 46025.3 | E21: =D21/D20-1 -> 0.0079739472 | G21: 0.013586071
... A23: 2040 | B23: =B22*(1+G24) -> 2234290.6 | C23: =B23/B22-1 -> 0.013296697 | D23: 46733 | E23: =D23/D22-1 -> 0.0075632462 | G23: 0.013379678
A24: 2041 | B24: =B23*(1+G25) -> 2263841.1 | C24: =B24/B23-1 -> 0.0132259 | G24: 0.013296697
A25: 2042 | B25: =B24*(1+G26) -> 2293610.2 | C25: =B25/B24-1 -> 0.013149838 | G25: 0.0132259
A26: 2043 | B26: =B25*(1+G27) -> 2323551.5 | C26: =B26/B25-1 -> 0.013054206 | G26: 0.013149838
A27: 2044 | B27: =B26*(1+G28) -> 2353612.7 | C27: =B27/B26-1 -> 0.012937643 | G27: 0.013054206
A28: 2045 | B28: =B27*(1+G29) -> 2383773.6 | C28: =B28/B27-1 -> 0.012814695 | G28: 0.012937643
A29: 2046 | B29: =B28*(1+G30) -> 2414079.5 | C29: =B29/B28-1 -> 0.012713442 | G29: 0.012814695
A30: 2047 | B30: =B29*(1+G31) -> 2444551.1 | C30: =B30/B29-1 -> 0.01262244 | G30: 0.012713442
A31: 2048 | B31: =B30*(1+G32) -> 2475204.1 | C31: =B31/B30-1 -> 0.012539315 | G31: 0.01262244
A32: 2049 | B32: =B31*(1+G33) -> 2506060.9 | C32: =B32/B31-1 -> 0.012466345 | G32: 0.012539315
A33: 2050 | B33: =B32*(1+G34) -> 2537163.2 | C33: =B33/B32-1 -> 0.012410858 | G33: 0.012466345
A34: 2051 | B34: =B33*(1+G35) -> 2568550.3 | C34: =B34/B33-1 -> 0.012370927 | G34: 0.012410858
A35: 2052 | B35: =B34*(1+G36) -> 2600264.8 | C35: =B35/B34-1 -> 0.012347258 | G35: 0.012370927
... A42: 2059 | B42: =B41*(1+G43) -> 2834246.2 | C42: =B42/B41-1 -> 0.012525132 | G42: 0.01246181
A43: 2060 | B43: =B42*(1+G43) -> 2869745.5 | C43: =B43/B42-1 -> 0.012525132 | G43: 0.012525132

Sheet Canada Population
A1: Projected population, by projection scenario, age and sex, as of July 1 (x 1,000) 1
A2: Frequency: Annual
A3: Table: 17-10-0057-01 (formerly CANSIM 052-0005)
A4: Release date: 2022-08-22
A5: Geography: Canada, Province or territory
A9: Geography 2 | B9: Canada
A10: Sex | B10: Both sexes
A11: Age group | B11: All ages
A12: Projection scenario 1 | B12: Projection scenario LG: low-growth 3 | C12: Projection scenario M1: medium-growth 4 | D12: Projection scenario M2: medium-growth 5 | E12: Projection scenario M3: medium-growth 6 | F12: Projection scenario M4: medium-growth 7 | G12: Projection scenario M5: medium-growth 8 | H12: Projection scenario M6: medium-growth 9 | I12: Projection scenario HG: high-growth 10 | J12: Projection scenario SA: slow-aging 11 | K12: Projection scenario FA: fast-aging 12
A13: Reference period
B14: Persons
A15: 2021 | B15: 38246.1 | C15: 38246.1 | D15: 38246.1 | E15: 38246.1 | F15: 38246.1 | G15: 38246.1 | H15: 38246.1 | I15: 38246.1 | J15: 38246.1 | K15: 38246.1
A16: 2022 | B16: 38763.3 | C16: 38882 | D16: 38882.1 | E16: 38882.1 | F16: 38882.1 | G16: 38882 | H16: 38882 | I16: 38957.4 | J16: 38935.4 | K16: 38785.3
A17: 2023 | B17: 39147 | C17: 39426 | D17: 39426.2 | E17: 39426.2 | F17: 39426.3 | G17: 39426.1 | H17: 39426 | I17: 39633.9 | J17: 39582.2 | K17: 39198.6
A18: 2024 | B18: 39512.2 | C18: 39953.1 | D18: 39953.6 | E18: 39953.6 | F18: 39953.7 | G18: 39953.2 | H18: 39953.1 | I18: 40318.5 | J18: 40233.1 | K18: 39597.2
A19: 2025 | B19: 39861.1 | C19: 40464.7 | D19: 40465.6 | E19: 40465.5 | F19: 40465.7 | G19: 40464.9 | H19: 40464.7 | I19: 40992.8 | J19: 40876 | K19: 39977.3
A20: 2026 | B20: 40163.9 | C20: 40964.6 | D20: 40965.9 | E20: 40965.7 | F20: 40966 | G20: 40964.8 | H20: 40964.4 | I20: 41653.6 | J20: 41505.6 | K20: 40310.7
A21: 2027 | B21: 40431 | C21: 41452.7 | D21: 41454.4 | E21: 41454.2 | F21: 41454.6 | G21: 41452.9 | H21: 41452.3 | I21: 42299.2 | J21: 42118.4 | K21: 40609.7
A22: 2028 | B22: 40676.1 | C22: 41928.3 | D22: 41930.6 | E22: 41930.3 | F22: 41930.8 | G22: 41928.5 | H22: 41927.7 | I22: 42929.5 | J22: 42714.7 | K22: 40887.7
A23: 2029 | B23: 40902.4 | C23: 42391.3 | D23: 42394 | E23: 42393.7 | F23: 42394.4 | G23: 42391.4 | H23: 42390.4 | I23: 43545.4 | J23: 43295.8 | K23: 41147.5
A24: 2030 | B24: 41111.9 | C24: 42840.8 | D24: 42844 | E24: 42843.6 | F24: 42844.5 | G24: 42840.8 | H24: 42839.5 | I24: 44150 | J24: 43864.5 | K24: 41391.2
A25: 2031 | B25: 41306.3 | C25: 43276.3 | D25: 43280 | E25: 43279.5 | F25: 43280.6 | G25: 43276.1 | H25: 43274.5 | I25: 44748.1 | J25: 44425.7 | K25: 41620.5
A26: 2032 | B26: 41487.2 | C26: 43697.3 | D26: 43701.6 | E26: 43701 | F26: 43702.4 | G26: 43696.9 | H26: 43695 | I26: 45346 | J26: 44985.8 | K26: 41836.8
... A34: 2040 | B34: 42584 | C34: 46724.2 | D34: 46733 | E34: 46731.6 | F34: 46734.6 | G34: 46719 | H34: 46713.5 | I34: 50433.7 | J34: 49745.9 | K34: 43225.5
A39: Footnotes:
A40: 1 | B40: The base population for these projections is derived from the official preliminary postcensal estimates of the population for Canada, provinces and territories as of July 1, 2018. In all scenarios, the population is projected until 2043 for the provinces and territories, and until 2068 for Canada as a whole. For more detail on the assumptions and scenarios, please refer to the projection report (catalogue 91-520) and the technical report (catalogue 91-620). Because of rounding, counts within tables may differ from the totals.
A41: 2 | B41: The population is projected until 2043 for the provinces and territories, and until 2068 for Canada as a whole.
A42: 3 | B42: The low-growth scenario contains the following assumptions at the Canada level: the total fertility rate reaches 1.40 children per woman in 2042/2043 and remains constant thereafter; life expectancy at birth reaches 85.6 years for males and 88.8 years for females in 2067/2068; interprovincial migration is based on the trends observed between 1991/1992 and 2016/2017; the immigration rate reaches 0.65% in 2042/2043 and remains constant thereafter; the annual number of non-permanent residents reaches 1,080,910 in 2043 and remains constant thereafter; the net emigration rate reaches 0.18% in 2042/2043 and remains constant thereafter.
A43: 4 | B43: The medium-growth (M1) scenario contains the following assumptions at the Canada level: the total fertility rate reaches 1.59 children per woman in 2042/2043 and remains constant thereafter; life expectancy at birth reaches 87.0 years for males and 89.0 years for females in 2067/2068; interprovincial migration is based on the trends observed between 1991/1992 and 2016/2017; the immigration rate reaches 0.83% in 2042/2043 and remains constant thereafter; the annual number of non-permanent residents reaches 1,397,060 in 2043 and remains constant thereafter; the net emigration rate reaches 0.15% in 2042/2043 and remains constant thereafter.
A44: 5 | B44: The medium-growth (M2) scenario contains the following assumptions at the Canada level: the total fertility rate reaches 1.59 children per woman in 2042/2043 and remains constant thereafter; life expectancy at birth reaches 87.0 years for males and 89.0 years for females in 2067/2068; interprovincial migration is based on the trends observed between 1995/1996 and 2010/2011; the immigration rate reaches 0.83% in 2042/2043 and remains constant thereafter; the annual number of non-permanent residents reaches 1,397,060 in 2043 and remains constant thereafter; the net emigration rate reaches 0.15% in 2042/2043 and remains constant thereafter.
A45: 6 | B45: The medium-growth (M3) scenario contains the following assumptions at the Canada level: the total fertility rate reaches 1.59 children per woman in 2042/2043 and remains constant thereafter; life expectancy at birth reaches 87.0 years for males and 89.0 years for females in 2067/2068; interprovincial migration is based on the trends observed between 2003/2004 and 2008/2009; the immigration rate reaches 0.83% in 2042/2043 and remains constant thereafter; the annual number of non-permanent residents reaches 1,397,060 in 2043 and remains constant thereafter; the net emigration rate reaches 0.15% in 2042/2043 and remains constant thereafter.
A46: 7 | B46: The medium-growth (M4) scenario contains the following assumptions at the Canada level: the total fertility rate reaches 1.59 children per woman in 2042/2043 and remains constant thereafter; life expectancy at birth reaches 87.0 years for males and 89.0 years for females in 2067/2068; interprovincial migration is based on the trends observed between 2009/2010 and 2016/2017; the immigration rate reaches 0.83% in 2042/2043 and remains constant thereafter; the annual number of non-permanent residents reaches 1,397,060 in 2043 and remains constant thereafter; the net emigration rate reaches 0.15% in 2042/2043 and remains constant thereafter.
A47: 8 | B47: The medium-growth (M5) scenario contains the following assumptions at the Canada level: the total fertility rate reaches 1.59 children per woman in 2042/2043 and remains constant thereafter; life expectancy at birth reaches 87.0 years for males and 89.0 years for females in 2067/2068; interprovincial migration is based on the trends observed between 2014/2015 and 2016/2017; the immigration rate reaches 0.83% in 2042/2043 and remains constant thereafter; the annual number of non-permanent residents reaches 1,397,060 in 2043 and remains constant thereafter; the net emigration rate reaches 0.15% in 2042/2043 and remains constant thereafter.
A48: 9 | B48: The medium-growth (M6) scenario contains the following assumptions at the Canada level: the total fertility rate reaches 1.59 children per woman in 2042/2043 and remains constant thereafter; life expectancy at birth reaches 83.7 years for males and 87.4 years for females in 2042/2043; interprovincial migration is based on the trends observed between 2018/2019 and 2020/2021; the immigration rate reaches 0.83% in 2042/2043 and remains constant thereafter; the annual number of non-permanent residents reaches 1,795,809 in 2043 and remains constant thereafter; the net emigration rate reaches 0.15% in 2042/2043 and remains constant thereafter.
A49: 10 | B49: The high-growth scenario contains the following assumptions at the Canada level: the total fertility rate reaches 1.79 children per woman in 2042/2043 and remains constant thereafter; life expectancy at birth reaches 88.0 years for males and 91.3 years for females in 2067/2068; interprovincial migration is based on the trends observed between 1991/1992 and 2016/2017; the immigration rate reaches 1.08% in 2042/2043 and remains constant thereafter; the annual number of non-permanent residents reaches 1,944,400 in 2043 and remains constant thereafter; the net emigration rate reaches 0.13% in 2042/2043 and remains constant thereafter.
A50: 11 | B50: The slow-aging scenario contains the following assumptions at the Canada level: the total fertility rate reaches 1.79 children per woman in 2042/2043 and remains constant thereafter; life expectancy at birth reaches 85.6 years for males and 88.8 years for females in 2067/2068; interprovincial migration is based on the trends observed between 1991/1992 and 2016/2017; the immigration rate reaches 1.08% in 2042/2043 and remains constant thereafter; the annual number of non-permanent residents reaches 1,944,400 in 2043 and remains constant thereafter; the net emigration rate reaches 0.13% in 2042/2043 and remains constant thereafter.
A51: 12 | B51: The fast-aging scenario contains the following assumptions at the Canada level: the total fertility rate reaches 1.40 children per woman in 2042/2043 and remains constant thereafter; life expectancy at birth reaches 88.0 years for males and 91.3 years for females in 2067/2068; interprovincial migration is based on the trends observed between 1991/1992 and 2016/2017; the immigration rate reaches 0.65% in 2042/2043 and remains constant thereafter; the annual number of non-permanent residents reaches 1,080,910 in 2043 and remains constant thereafter; the net emigration rate reaches 0.18% in 2042/2043 and remains constant thereafter.
A55: How to cite: Statistics Canada. Table 17-10-0057-01 Projected population, by projection scenario, age and sex, as of July 1 (x 1,000)
A56: https://www150.statcan.gc.ca/t1/tbl1/en/tv.action?pid=1710005701

Sheet Mexico GDP
A1: MEXICO ECONOMIC GROWTH (million USD)
B2: Value | C2: GDP Growth | D2: OECD Population | E2: Per Capita GDP
A3: 2020 | B3: 2190301.4
A4: 2021 | B4: 2299481 | C4: =B4/B3-1 -> 0.049846849 | D4: ='Mexico Population'!C$7 -> 128972439 | E4: =B4/D4*1000000 -> 17829.244
A5: 2022 | B5: 2372532.9 | C5: =B5/B4-1 -> 0.031768844 | D5: ='Mexico Population'!D$7 -> 130118356 | E5: =B5/D5*1000000 -> 18233.653 | F5: =E5/E4-1 -> 0.022682336
A6: 2023 | B6: 2485282 | C6: =B6/B5-1 -> 0.047522673 | D6: ='Mexico Population'!E$7 -> 131230255 | E6: =B6/D6*1000000 -> 18938.331 | F6: =E6/E5-1 -> 0.038647132
A7: 2024 | B7: 2592371 | C7: =B7/B6-1 -> 0.043089275 | D7: ='Mexico Population'!F$7 -> 132308276 | E7: =B7/D7*1000000 -> 19593.415 | F7: =E7/E6-1 -> 0.034590395
A8: 2025 | B8: 2687380 | C8: =B8/B7-1 -> 0.036649461 | D8: ='Mexico Population'!G$7 -> 133352387 | E8: =B8/D8*1000000 -> 20152.47 | F8: =E8/E7-1 -> 0.028532793
A9: 2026 | B9: 2772470 | C9: =B9/B8-1 -> 0.031662809 | D9: ='Mexico Population'!H$7 -> 134362934 | E9: =B9/D9*1000000 -> 20634.188 | F9: =E9/E8-1 -> 0.023903647
A10: 2027 | B10: 2850996 | C10: =B10/B9-1 -> 0.028323481 | D10: ='Mexico Population'!I$7 -> 135339973 | E10: =B10/D10*1000000 -> 21065.439 | F10: =E10/E9-1 -> 0.020899863
A11: 2028 | B11: 2926182 | C11: =B11/B10-1 -> 0.026371836 | D11: ='Mexico Population'!J$7 -> 136283592 | E11: =B11/D11*1000000 -> 21471.271 | F11: =E11/E10-1 -> 0.019265302
A12: 2029 | B12: 2999927 | C12: =B12/B11-1 -> 0.025201782 | D12: ='Mexico Population'!K$7 -> 137193751 | E12: =B12/D12*1000000 -> 21866.353 | F12: =E12/E11-1 -> 0.018400476
A13: 2030 | B13: 3073297 | C13: =B13/B12-1 -> 0.024457262 | D13: ='Mexico Population'!L$7 -> 138070271 | E13: =B13/D13*1000000 -> 22258.934 | F13: =E13/E12-1 -> 0.017953637
A14: 2031 | B14: 3146855 | C14: =B14/B13-1 -> 0.023934556
A15: 2032 | B15: 3220864 | C15: =B15/B14-1 -> 0.023518402
A16: 2033 | B16: 3295445 | C16: =B16/B15-1 -> 0.023155588
A17: 2034 | B17: 3370625 | C17: =B17/B16-1 -> 0.022813307
A18: 2035 | B18: 3446378 | C18: =B18/B17-1 -> 0.022474467
A19: 2036 | B19: 3522672 | C19: =B19/B18-1 -> 0.022137444
A20: 2037 | B20: 3599450 | C20: =B20/B19-1 -> 0.021795387
A21: 2038 | B21: 3676677 | C21: =B21/B20-1 -> 0.021455222
A22: 2039 | B22: 3754303 | C22: =B22/B21-1 -> 0.021113087
A23: 2040 | B23: 3832268 | C23: =B23/B22-1 -> 0.020766837
A24: 2041 | B24: 3910525 | C24: =B24/B23-1 -> 0.020420545
A25: 2042 | B25: 3989020 | C25: =B25/B24-1 -> 0.020072752
... A43: 2060 | B43: 5406676 | C43: =B43/B42-1 -> 0.014923098

Sheet Mexico Population
A1: =DotStatQuery(B1) -> #NAME? | B1: <?xml version="1.0" encoding="utf-16"?><WebTableParameter xmlns:xsd="http://www.w3.org/2001/XMLSchema" xmlns:xsi="http://www.w3.org/2001/XMLSchema-instance" xmlns="http://stats.oecd.org/OECDStatWS/2004/03/01/"><DataTable Code="POPPROJ" HasMetadata="true"><Name LocaleIsoCode="en">Population projections</Name><Name LocaleIsoCode="fr">Projections de la population</Name><Dimension Code="LOCATION" HasMetadata="false" CommonCode="LOCATION" Display="labels"><Name LocaleIsoCode="en">Country</Name><Name LocaleIsoCode="fr">Pays</Name><Member Code="AUS" HasMetadata="false" HasOnlyUnitMetadata="false" HasChild="0"><Name LocaleIsoCode="en">Australia</Name><Name LocaleIsoCode="fr">Australie</Name></Member><Member Code="AUT" HasMetadata="false" HasOnlyUnitMetadata="false" HasChild="0"><Name LocaleIsoCode="en">Austria</Name><Name LocaleIsoCode="fr">Autriche</Name></Member><Member Code="BEL" HasMetadata="false" HasOnlyUnitMetadata="false" HasChild="0"><Name LocaleIsoCode="en">Belgium</Name><Name LocaleIsoCode="fr">Belgique</Name></Member><Member Code="CAN" HasMetadata="false" HasOnlyUnitMetadata="false" HasChild="0"><Name LocaleIsoCode="en">Canada</Name><Name LocaleIsoCode="fr">Canada</Name></Member><Member Code="CHL" HasMetadata="false" HasOnlyUnitMetadata="false" HasChild="0"><Name LocaleIsoCode="en">Chile</Name><Name LocaleIsoCode="fr">Chili</Name></Member><Member Code="COL" HasMetadata="false" HasOnlyUnitMetadata="false" HasChild="0"><Name LocaleIsoCode="en">Colombia</Name><Name LocaleIsoCode="fr">Colombie</Name></Member><Member Code="CRI" HasMetadata="false" HasOnlyUnitMetadata="false" HasChild="0"><Name LocaleIsoCode="en">Costa Rica</Name><Name LocaleIsoCode="fr">Costa Rica</Name></Member><Member Code="CZE" HasMetadata="false" HasOnlyUnitMetadata="false" HasChild="0"><Name LocaleIsoCode="en">Czech Republic</Name><Name LocaleIsoCode="fr">République tchèque</Name></Member><Member Code="DNK" HasMetadata="false" HasOnlyUnitMetadata="false" HasChild="0"><Name LocaleIsoCode="en">Denmark</Name><Name LocaleIsoCode="fr">Danemark</Name></Member><Member Code="EST" HasMetadata="false" HasOnlyUnitMetadata="false" HasChild="0"><Name LocaleIsoCode="en">Estonia</Name><Name LocaleIsoCode="fr">Estonie</Name></Member><Member Code="FIN" HasMetadata="false" HasOnlyUnitMetadata="false" HasChild="0"><Name LocaleIsoCode="en">Finland</Name><Name LocaleIsoCode="fr">Finlande</Name></Member><Member Code="FRA" HasMetadata="false" HasOnlyUnitMetadata="false" HasChild="0"><Name LocaleIsoCode="en">France</Name><Name LocaleIsoCode="fr">France</Name></Member><Member Code="DEU" HasMetadata="true" HasOnlyUnitMetadata="false" HasChild="0"><Name LocaleIsoCode="en">Germany</Name><Name LocaleIsoCode="fr">Allemagne</Name></Member><Member Code="GRC" HasMetadata="false" HasOnlyUnitMetadata="false" HasChild="0"><Name LocaleIsoCode="en">Greece</Name><Name LocaleIsoCode="fr">Grèce</Name></Member><Member Code="HUN" HasMetadata="false" HasOnlyUnitMetadata="false" HasChild="0"><Name LocaleIsoCode="en">Hungary</Name><Name LocaleIsoCode="fr">Hongrie</Name></Member><Member Code="ISL" HasMetadata="false" HasOnlyUnitMetadata="false" HasChild="0"><Name LocaleIsoCode="en">Iceland</Name><Name LocaleIsoCode="fr">Islande</Name></Member><Member Code="IRL" HasMetadata="false" HasOnlyUnitMetadata="false" HasChild="0"><Name LocaleIsoCode="en">Ireland</Name><Name LocaleIsoCode="fr">Irlande</Name></Member><Member Code="ISR" HasMetadata="true" HasOnlyUnitMetadata="false" HasChild="0"><Name LocaleIsoCode="en">Israel</Name><Name LocaleIsoCode="fr">Israël</Name></Member><Member Code="ITA" HasMetadata="false" HasOnlyUnitMetadata="false" HasChild="0"><Name LocaleIsoCode="en">Italy</Name><Name LocaleIsoCode="fr">Italie</Name></Member><Member Code="JPN" HasMetadata="false" HasOnlyUnitMetadata="false" HasChild="0"><Name LocaleIsoCode="en">Japan</Name><Name LocaleIsoCode="fr">Japon</Name></Member><Member Code="KOR" HasMetadata="false" HasOnlyUnitMetadata="false" HasChild="0"><Name LocaleIsoCode="en">Korea</Name><Name LocaleIsoCode="fr">Corée</Name></Member><Member Code="LTU" HasMetadata="false" HasOnlyUnitMetadata="false" HasChild="0"><Name LocaleIsoCode="en">Lithuania</Name><Name LocaleIsoCode="fr">Lituanie</Name></Member><Member Code="LVA" HasMetadata="false" HasOnlyUnitMetadata="false" HasChild="0"><Name LocaleIsoCode="en">Latvia</Name><Name LocaleIsoCode="fr">Lettonie</Name></Member><Member Code="LUX" HasMetadata="false" HasOnlyUnitMetadata="false" HasChild="0"><Name LocaleIsoCode="en">Luxembourg</Name><Name LocaleIsoCode="fr">Luxembourg</Name></Member><Member Code="MEX" HasMetadata="false" HasOnlyUnitMetadata="false" HasChild="0" IsDisplayed="true"><Name LocaleIsoCode="en">Mexico</Name><Name LocaleIsoCode="fr">Mexique</Name></Member><Member Code="NLD" HasMetadata="false" HasOnlyUnitMetadata="false" HasChild="0"><Name LocaleIsoCode="en">Netherlands</Name><Name LocaleIsoCode="fr">Pays-Bas</Name></Member><Member Code="NZL" HasMetadata="false" HasOnlyUnitMetadata="false" HasChild="0"><Name LocaleIsoCode="en">New Zealand</Name><Name LocaleIsoCode="fr">Nouvelle-Zélande</Name></Member><Member Code="NOR" HasMetadata="false" HasOnlyUnitMetadata="false" HasChild="0"><Name LocaleIsoCode="en">Norway</Name><Name LocaleIsoCode="fr">Norvège</Name></Member><Member Code="POL" HasMetadata="false" HasOnlyUnitMetadata="false" HasChild="0"><Name LocaleIsoCode="en">Poland</Name><Name LocaleIsoCode="fr">Pologne</Name></Member><Member Code="PRT" HasMetadata="false" HasOnlyUnitMetadata="false" HasChild="0"><Name LocaleIsoCode="en">Portugal</Name><Name LocaleIsoCode="fr">Portugal</Name></Member><Member Code="SVK" HasMetadata="false" HasOnlyUnitMetadata="false" HasChild="0"><Name LocaleIsoCode="en">Slovak Republic</Name><Name LocaleIsoCode="fr">République slovaque</Name></Member><Member Code="SVN" HasMetadata="false" HasOnlyUnitMetadata="false" HasChild="0"><Name LocaleIsoCode="en">Slovenia</Name><Name LocaleIsoCode="fr">Slovénie</Name></Member><Member Code="ESP" HasMetadata="false" HasOnlyUnitMetadata="false" HasChild="0"><Name LocaleIsoCode="en">Spain</Name><Name LocaleIsoCode="fr">Espagne</Name></Member><Member Code="SWE" HasMetadata="false" HasOnlyUnitMetadata="false" HasChild="0"><Name LocaleIsoCode="en">Sweden</Name><Name LocaleIsoCode="fr">Suède</Name></Member><Member Code="CHE" HasMetadata="false" HasOnlyUnitMetadata="false" HasChild="0"><Name LocaleIsoCode="en">Switzerland</Name><Name LocaleIsoCode="fr">Suisse</Name></Member><Member Code="TUR" HasMetadata="false" HasOnlyUnitMetadata="false" HasChild="0"><Name LocaleIsoCode="en">Türkiye</Name><Name LocaleIsoCode="fr">Türkiye</Name></Member><Member Code="GBR" HasMetadata="false" HasOnlyUnitMetadata="false" HasChild="0"><Name LocaleIsoCode="en">United Kingdom</Name><Name LocaleIsoCode="fr">Royaume-Uni</Name></Member><Member Code="USA" HasMetadata="false" HasOnlyUnitMetadata="false" HasChild="0"><Name LocaleIsoCode="en">United States</Name><Name LocaleIsoCode="fr">États-Unis</Name></Member><Member Code="OECD" HasMetadata="false" HasOnlyUnitMetadata="false" HasChild="0"><Name LocaleIsoCode="en">OECD - Total</Name><Name LocaleIsoCode="fr">OCDE - Total</Name></Member><Member Code="NMEC" HasMetadata="false" HasOnlyUnitMetadata="false" HasChild="1"><Name LocaleIsoCode="en">Non-OECD Economies</Name><Name LocaleIsoCode="fr">Économies non-OCDE</Name><ChildMember Code="ARG" HasMetadata="false" HasOnlyUnitMetadata="false" HasChild="0"><Name LocaleIsoCode="en">Argentina</Name><Name LocaleIsoCode="fr">Argentine</Name></ChildMember><ChildMember Code="BRA" HasMetadata="false" HasOnlyUnitMetadata="false" HasChild="0"><Name LocaleIsoCode="en">Brazil</Name><Name LocaleIsoCode="fr">Brésil</Name></ChildMember><ChildMember Code="BGR" HasMetadata="false" HasOnlyUnitMetadata="false" HasChild="0"><Name LocaleIsoCode="en">Bulgaria</Name><Name LocaleIsoCode="fr">Bulgarie</Name></ChildMember><ChildMember Code="CHN" HasMetadata="false" HasOnlyUnitMetadata="false" HasChild="0"><Name LocaleIsoCode="en">China (People's Republic of)</Name><Name LocaleIsoCode="fr">Chine (République populaire de)</Name></ChildMember><ChildMember Code="HRV" HasMetadata="false" HasOnlyUnitMetadata="false" HasChild="0"><Name LocaleIsoCode="en">Croatia</Name><Name LocaleIsoCode="fr">Croatie</Name></ChildMember><ChildMember Code="CYP" HasMetadata="true" HasOnlyUnitMetadata="false" HasChild="0"><Name LocaleIsoCode="en">Cyprus</Name><Name LocaleIsoCode="fr">Chypre</Name></ChildMember><ChildMember Code="IND" HasMetadata="false" HasOnlyUnitMetadata="false" HasChild="0"><Name LocaleIsoCode="en">India</Name><Name LocaleIsoCode="fr">Inde</Name></ChildMember><ChildMember Code="IDN" HasMetadata="false" HasOnlyUnitMetadata="false" HasChild="0"><Name LocaleIsoCode="en">Indonesia</Name><Name LocaleIsoCode="fr">Indonésie</Name></ChildMember><ChildMember Code="MLT" HasMetadata="false" HasOnlyUnitMetadata="false" HasChild="0"><Name LocaleIsoCode="en">Malta</Name><Name LocaleIsoCode="fr">Malte</Name></ChildMember><ChildMember Code="ROU" HasMetadata="false" HasOnlyUnitMetadata="false" HasChild="0"><Name LocaleIsoCode="en">Romania</Name><Name LocaleIsoCode="fr">Roumanie</Name></ChildMember><ChildMember Code="RUS" HasMetadata="false" HasOnlyUnitMetadata="false" HasChild="0"><Name LocaleIsoCode="en">Russia</Name><Name LocaleIsoCode="fr">Russie</Name></ChildMember><ChildMember Code="SAU" HasMetadata="false" HasOnlyUnitMetadata="false" HasChild="0"><Name LocaleIsoCode="en">Saudi Arabia</Name><Name LocaleIsoCode="fr">Arabie saoudite</Name></ChildMember><ChildMember Code="SGP" HasMetadata="false" HasOnlyUnitMetadata="false" HasChild="0"><Name LocaleIsoCode="en">Singapore</Name><Name LocaleIsoCode="fr">Singapour</Name></ChildMember><ChildMember Code="ZAF" HasMetadata="false" HasOnlyUnitMetadata="false" HasChild="0"><Name LocaleIsoCode="en">South Africa</Name><Name LocaleIsoCode="fr">Afrique du Sud</Name></ChildMember></Member></Dimension><Dimension Code="TIME" HasMetadata="false" CommonCode="TIME" Display="labels"><Name LocaleIsoCode="en">Time</Name><Name LocaleIsoCode="fr">Temps</Name><Member Code="2021" HasMetadata="false"><Name LocaleIsoCode="en">2021</Name><Name LocaleIsoCode="fr">2021</Name></Member><Member Code="2022" HasMetadata="false"><Name LocaleIsoCode="en">2022</Name><Name LocaleIsoCode="fr">2022</Name></Member><Member Code="2023" HasMetadata="false"><Name LocaleIsoCode="en">2023</Name><Name LocaleIsoCode="fr">2023</Name></Member><Member Code="2024" HasMetadata="false"><Name LocaleIsoCode="en">2024</Name><Name LocaleIsoCode="fr">2024</Name></Member><Member Code="2025" HasMetadata="false"><Name LocaleIsoCode="en">2025</Name><Name LocaleIsoCode="fr">2025</Name></Member><Member Code="2026" HasMetadata="false"><Name LocaleIsoCode="en">2026</Name><Name LocaleIsoCode="fr">2026</Name></Member><Member Code="2027" HasMetadata="false"><Name LocaleIsoCode="en">2027</Name><Name LocaleIsoCode="fr">2027</Name></Member><Member Code="2028" HasMetadata="false"><Name LocaleIsoCode="en">2028</Name><Name LocaleIsoCode="fr">2028</Name></Member><Member Code="2029" HasMetadata="false"><Name LocaleIsoCode="en">2029</Name><Name LocaleIsoCode="fr">2029</Name></Member><Member Code="2030" HasMetadata="false"><Name LocaleIsoCode="en">2030</Name><Name LocaleIsoCode="fr">2030</Name></Member></Dimension><Dimension Code="SEX" HasMetadata="false" CommonCode="SEX" Display="labels"><Name LocaleIsoCode="en">Sex</Name><Name LocaleIsoCode="fr">Sexe</Name><Member Code="W" HasMetadata="false" HasOnlyUnitMetadata="false" HasChild="0"><Name LocaleIsoCode="en">Women</Name><Name LocaleIsoCode="fr">Femmes</Name></Member><Member Code="M" HasMetadata="false" HasOnlyUnitMetadata="false" HasChild="0"><Name LocaleIsoCode="en">Men</Name><Name LocaleIsoCode="fr">Hommes</Name></Member><Member Code="T" HasMetadata="false" HasOnlyUnitMetadata="false" HasChild="0" IsDisplayed="true"><Name LocaleIsoCode="en">Total</Name><Name LocaleIsoCode="fr">Total</Name></Member></Dimension><Dimension Code="AGE" HasMetadata="false" Display="labels"><Name LocaleIsoCode="en">Age</Name><Name LocaleIsoCode="fr">Âge</Name><Member Code="TOTAL" HasMetadata="false" HasOnlyUnitMetadata="false" HasChild="0"><Name LocaleIsoCode="en">Total</Name><Name LocaleIsoCode="fr">Total</Name></Member><Member Code="0_4" HasMetadata="false" HasOnlyUnitMetadata="false" HasChild="0"><Name LocaleIsoCode="en">0 to 4</Name><Name LocaleIsoCode="fr">0 à 4 ans</Name></Member><Member Code="05_9" HasMetadata="false" HasOnlyUnitMetadata="false" HasChild="0"><Name LocaleIsoCode="en">5 to 9</Name><Name LocaleIsoCode="fr">5 à 9 ans</Name></Member><Member Code="10_14" HasMetadata="false" HasOnlyUnitMetadata="false" HasChild="0"><Name LocaleIsoCode="en">10 to 14</Name><Name LocaleIsoCode="fr">10 a 14 ans</Name></Member><Member Code="15_19" HasMetadata="false" HasOnlyUnitMetadata="false" HasChild="0"><Name LocaleIsoCode="en">15 to 19</Name><Name LocaleIsoCode="fr">15 à 19 ans</Name></Member><Member Code="20_24" HasMetadata="false" HasOnlyUnitMetadata="false" HasChild="0"><Name LocaleIsoCode="en">20 to 24</Name><Name LocaleIsoCode="fr">20 à 24 ans</Name></Member><Member Code="25_29" HasMetadata="false" HasOnlyUnitMetadata="false" HasChild="0"><Name LocaleIsoCode="en">25 to 29</Name><Name LocaleIsoCode="fr">25 à 29 ans</Name></Member><Member Code="30_34" HasMetadata="false" HasOnlyUnitMetadata="false" HasChild="0"><Name LocaleIsoCode="en">30 to 34</Name><Name LocaleIsoCode="fr">30 à 34 ans</Name></Member><Member Code="35_39" HasMetadata="false" HasOnlyUnitMetadata="false" HasChild="0"><Name LocaleIsoCode="en">35 to 39</Name><Name LocaleIsoCode="fr">35 à 39 ans</Name></Member><Member Code="40_44" HasMetadata="false" HasOnlyUnitMetadata="false" HasChild="0"><Name LocaleIsoCode="en">40 to 44</Name><Name LocaleIsoCode="fr">40 à 44 ans</Name></Member><Member Code="45_49" HasMetadata="false" HasOnlyUnitMetadata="false" HasChild="0"><Name LocaleIsoCode="en">45 to 49</Name><Name LocaleIsoCode="fr">45 à 49 ans</Name></Member><Member Code="50_54" HasMetadata="false" HasOnlyUnitMetadata="false" HasChild="0"><Name LocaleIsoCode="en">50 to 54</Name><Name LocaleIsoCode="fr">50 à 54 ans</Name></Member><Member Code="55_59" HasMetadata="false" HasOnlyUnitMetadata="false" HasChild="0"><Name LocaleIsoCode="en">55 to 59</Name><Name LocaleIsoCode="fr">55 à 59 ans</Name></Member><Member Code="60_64" HasMetadata="false" HasOnlyUnitMetadata="false" HasChild="0"><Name LocaleIsoCode="en">60 to 64</Name><Name LocaleIsoCode="fr">60 à 64 ans</Name></Member><Member Code="65_69" HasMetadata="false" HasOnlyUnitMetadata="false" HasChild="0"><Name LocaleIsoCode="en">65 to 69</Name><Name LocaleIsoCode="fr">65 à 69 ans</Name></Member><Member Code="70_74" HasMetadata="false" HasOnlyUnitMetadata="false" HasChild="0"><Name LocaleIsoCode="en">70 to 74</Name><Name LocaleIsoCode="fr">70 à 74 ans</Name></Member><Member Code="75_79" HasMetadata="false" HasOnlyUnitMetadata="false" HasChild="0"><Name LocaleIsoCode="en">75 to 79</Name><Name LocaleIsoCode="fr">75 à 79 ans</Name></Member><Member Code="80_84" HasMetadata="false" HasOnlyUnitMetadata="false" HasChild="0"><Name LocaleIsoCode="en">80 to 84</Name><Name LocaleIsoCode="fr">80 à 84 ans</Name></Member><Member Code="85_OVER" HasMetadata="false" HasOnlyUnitMetadata="false" HasChild="0"><Name LocaleIsoCode="en">85 and over</Name><Name LocaleIsoCode="fr">85 ans et plus</Name></Member><Member Code="50_OVER" HasMetadata="false" HasOnlyUnitMetadata="false" HasChild="0"><Name LocaleIsoCode="en">50 and over</Name><Name LocaleIsoCode="fr">50 ans et plus</Name></Member><Member Code="LESS_20" HasMetadata="false" HasOnlyUnitMetadata="false" HasChild="0"><Name LocaleIsoCode="en">Under 20</Name><Name LocaleIsoCode="fr">Moins de 20 ans</Name></Member><Member Code="15-64" HasMetadata="false" HasOnlyUnitMetadata="false" HasChild="0"><Name LocaleIsoCode="en">15 to 64</Name><Name LocaleIsoCode="fr">15 à 64 ans</Name></Member><Member Code="20-64" HasMetadata="false" HasOnlyUnitMetadata="false" HasChild="0"><Name LocaleIsoCode="en">20 to 64</Name><Name LocaleIsoCode="fr">20 à 64 ans</Name></Member><Member Code="65_OVER" HasMetadata="false" HasOnlyUnitMetadata="false" HasChild="0"><Name LocaleIsoCode="en">65 and over</Name><Name LocaleIsoCode="fr">65 ans et plus</Name></Member><Member Code="65_OVER_SHARE" HasMetadata="false" HasOnlyUnitMetadata="false" HasChild="0"><Name LocaleIsoCode="en">Share of 65 and over - elderly</Name><Name LocaleIsoCode="fr">Part des 65 ans et plus - personnes âgées</Name></Member><Member Code="LESS_15_SHARE" HasMetadata="false" HasOnlyUnitMetadata="false" HasChild="0"><Name LocaleIsoCode="en">Share of under 15 - children</Name><Name LocaleIsoCode="fr">Part des moins de 20 ans - enfants</Name></Member><Member Code="15-24_SHARE" HasMetadata="false" HasOnlyUnitMetadata="false" HasChild="0"><Name LocaleIsoCode="en">Share of 15 to 24 - youth</Name><Name LocaleIsoCode="fr">Part des 15 à 24 ans - jeunes</Name></Member><Member Code="OAD15-64" HasMetadata="false" HasOnlyUnitMetadata="false" HasChild="0"><Name LocaleIsoCode="en">Old age dependency ratio (65 and over/15-64)</Name><Name LocaleIsoCode="fr">Ratio de dépendance des personnes âgés (65 et plus/15-64)</Name></Member><Member Code="TOTD20-64" HasMetadata="false" HasOnlyUnitMetadata="false" HasChild="0"><Name LocaleIsoCode="en">Total dependency ratio ((&lt;20 &amp; 65+) / 20-64)</Name><Name LocaleIsoCode="fr">Ratio de dépendance total ((&lt;20 &amp; 65+) / 20-64)</Name></Member><Member Code="15-64_SHARE" HasMetadata="false" HasOnlyUnitMetadata="false" HasChild="0"><Name LocaleIsoCode="en">Share of 15 to 64 - working age</Name><Name LocaleIsoCode="fr">Part des 15 à 64 ans - âge de travailler</Name></Member><Member Code="POP_GR" HasMetadata="false" HasOnlyUnitMetadata="false" HasChild="0"><Name LocaleIsoCode="en">Annual growth rate of total population</Name><Name LocaleIsoCode="fr">Taux de croissance annuel de la population totale</Name></Member></Dimension><WBOSInformations><TimeDimension WebTreeWasUsed="false"><StartCodes Annual="2018" /><EndCodes Annual="2030" /></TimeDimension></WBOSInformations><Tabulation Axis="horizontal"><Dimension Code="TIME" CommonCode="TIME" /></Tabulation><Tabulation Axis="vertical"><Dimension Code="AGE" /></Tabulation><Tabulation Axis="page"><Dimension Code="SEX" CommonCode="SEX" /><Dimension Code="LOCATION" CommonCode="LOCATION" /></Tabulation><Formatting><Labels LocaleIsoCode="en" /><Power>0</Power><Decimals>-1</Decimals><SkipEmptyLines>true</SkipEmptyLines><SkipEmptyCols>false</SkipEmptyCols><SkipLineHierarchy>false</SkipLineHierarchy><SkipColHierarchy>false</SkipColHierarchy><Page>1</Page></Formatting></DataTable><Format><ShowEmptyAxes>true</ShowEmptyAxes><Page>1</Page><EnableSort>true</EnableSort><IncludeFlagColumn>false</IncludeFlagColumn><IncludeTimeSeriesId>false</IncludeTimeSeriesId><DoBarChart>false</DoBarChart><FreezePanes>true</FreezePanes><MaxBarChartLen>65</MaxBarChartLen></Format><Query><AbsoluteUri>http://stats.oecd.org//View.aspx?QueryId=&amp;QueryType=Public&amp;Lang=en</AbsoluteUri></Query></WebTableParameter>
A2: Dataset: Population projections
A3: Sex | C3: Total
A4: Country | C4: Mexico
A5: Time | C5: 2021 | D5: 2022 | E5: 2023 | F5: 2024 | G5: 2025 | H5: 2026 | I5: 2027 | J5: 2028 | K5: 2029 | L5: 2030
A6: Age
A7: Total | C7: 128972439 | D7: 130118356 | E7: 131230255 | F7: 132308276 | G7: 133352387 | H7: 134362934 | I7: 135339973 | J7: 136283592 | K7: 137193751 | L7: 138070271
A8: 0 to 4 | C8: 10732197 | D8: 10648820 | E8: 10566280 | F8: 10484458 | G8: 10403493 | H8: 10323414 | I8: 10244333 | J8: 10166279 | K8: 10089192 | L8: 10013011
A9: 5 to 9 | C9: 11000967 | D9: 10956105 | E9: 10898742 | F9: 10830177 | G9: 10753689 | H9: 10672757 | I9: 10590324 | J9: 10508779 | K9: 10428096 | L9: 10348393
A10: 10 to 14 | C10: 11083131 | D10: 11056598 | E10: 11031201 | F10: 11006223 | G10: 10979061 | H10: 10945386 | I10: 10901218 | J10: 10844652 | K10: 10776999 | L10: 10701451
A11: 15 to 19 | C11: 11076419 | D11: 11070858 | E11: 11056608 | F11: 11032621 | G11: 11003061 | H11: 10974505 | I11: 10948538 | J11: 10923411 | K11: 10898583 | L11: 10871670
A12: 20 to 24 | C12: 10823411 | D12: 10821598 | E12: 10829306 | F12: 10843815 | G12: 10857219 | H12: 10861941 | I12: 10857176 | J12: 10843561 | K12: 10820163 | L12: 10791224
A13: 25 to 29 | C13: 10670774 | D13: 10669257 | E13: 10650213 | F13: 10623759 | G13: 10600276 | H13: 10587616 | I13: 10586399 | J13: 10594768 | K13: 10609979 | L13: 10624205
A14: 30 to 34 | C14: 10041442 | D14: 10173243 | E14: 10286731 | F14: 10377617 | G14: 10439274 | H14: 10466522 | I14: 10465661 | J14: 10448199 | K14: 10423912 | L14: 10402732
A15: 35 to 39 | C15: 9143294 | D15: 9292518 | E15: 9442782 | F15: 9590133 | G15: 9733656 | H15: 9873688 | I15: 10004165 | J15: 10117153 | K15: 10208334 | L15: 10270981
A16: 40 to 44 | C16: 8405040 | D16: 8487556 | E16: 8590173 | F16: 8710640 | G16: 8845112 | H16: 8988461 | I16: 9136457 | J16: 9285712 | K16: 9432291 | L16: 9575213
A17: 45 to 49 | C17: 7951363 | D17: 8021724 | E17: 8075078 | F17: 8121299 | G17: 8170078 | H17: 8232476 | I17: 8315146 | J17: 8417511 | K17: 8537364 | L17: 8670919
A18: 50 to 54 | C18: 7056428 | D18: 7220969 | E18: 7376302 | F18: 7516203 | G18: 7636165 | H18: 7731404 | I18: 7802087 | J18: 7856270 | K18: 7903494 | L18: 7953241
... A37: Annual growth rate of total population | C37: 0.92349314 | D37: 0.88849758 | E37: 0.85452893 | F37: 0.82147291 | G37: 0.78915018 | H37: 0.75780196 | I37: 0.72716409 | J37: 0.69722121 | K37: 0.66784195 | L37: 0.63889207
A38: Data extracted on 19 Nov 2022 19:46 UTC (GMT) from OECD.Stat
