Workbook

Sheet Spreads
A2: Day | B2: RBD - central Illinois | C2: Crude-degummed - central Illinois | D2: Crude-degummed - Gulf | E2: Brazil - SBO FOB | F2: Argentina UpRiver | G2: Canola Oil - Los Angeles | H2: SBO Futures | I2: RBD Palm Oil - West Coast | J2: Palm Oil Futures | K2: RBD SBO - RBD PO | L2: Palm Oil Basis | M2: RBD Basis | N2: Refining Margin | O2: Central Illinois Basis | P2: Gulf Basis | Q2: Paranagua Basis | R2: Argentina Up River | S2: Canola Oil Basis | T2: RBD Canola Oil - RBD SBO | V2: Argentina UpRiver ($/mt) | W2: Gulf - Up River | X2: Brazil - FOB SOB | Y2: Gulf - Brazil | Z2: Brazl - Argentina | AA2: Month | AB2: Year | AC2: Week | AD2: 4-Yr Avg SBO Futures | AF2: Argentine Peso/$ | AG2: Argentina local price in peso per pound | AI2: Crude Oil | AJ2: Heating Oil | AM2: Brazil SBO FOB | AN2: Brazil Real/$ | AO2: Brazil SBO in real per pound | AT2: Central Illinois Soybean Meal ($/ton) | AU2: Central Illinois Soybeans ($/bu) | AV2: Central Illinois Crush Margin (crude degummed, $/bu) | AW2: Central Illinois Crush Margin (RBD, $/bu) | AX2: Refining Margin ($/bu) | AY2: Oil Share | BB2: Crude-deguumed central Illinois $/ton
A3: 43437 | B3: 32.12 | C3: 28.37 | D3: 30.82 | E3: =IF(AM3="","",AM3/2206.622)*100 -> 29.366153 | F3: 28.893842 | G3: 41.57 | H3: 28.57 | I3: 27.22 | J3: 21.780721 | K3: =B3-I3 -> 4.9 | L3: =IF(I3="","",IF(J3="","",I3-J3)) -> 5.4392793 | M3: =B3-H3 -> 3.55 | N3: =B3-C3 -> 3.75 | O3: =C3-H3 -> -0.2 | P3: =D3-H3 -> 2.25 | Q3: =IF(E3="","",E3-H3) -> 0.79615333 | R3: =IF(F3="","",F3-H3) -> 0.32384212 | S3: =G3-H3 -> 13 | T3: =G3-B3 -> 9.45 | U3: =IF(P3=N3,"EQUAL",IF(N3<P3,"LOWER","HIGHER")) -> HIGHER | V3: 637 | W3: =IF(V3="","",IF(D3="","",D3-F3)) -> 1.9261579 | X3: =IF(AM3="","",AM3/22.04622) -> 29.392794 | Y3: =IF(X3="","",IF(D3="","",D3-X3)) -> 1.4272061 | Z3: =IF(X3="","",IF(F3="","",X3-F3)) -> 0.49895175 | AA3: =MONTH(A3) -> 12 | AB3: =YEAR(A3) -> 2018 | AF3: 36.475 | AG3: =IF(V3="","",V3*AF3/2204.622*100) -> 1053.9029 | AL3: =A3 -> 43437 | AM3: 648 | AN3: 3.8408 | AO3: =IF(AM3="","",AM3*AN3/2204.622*100) -> 112.89184 | AT3: 314 | AU3: 8.76 | AV3: =(((C3/100*11.7)+(AT3/2000*47))-(AU3)) -> 1.93829 | AW3: =(((B3/100*11.7*0.98)+(AT3/2000*47))-(AU3)) -> 2.3018792 | AX3: =AW3-AV3 -> 0.3635892 | AY3: =(B3*11.7/100)/((AT3/2000*47)+(B3*11.7/100)) -> 0.33743616 | AZ3: =C3/100*11.7 -> 3.31929 | BB3: =C3*22.0462 -> 625.45069
A4: 43438 | B4: 32.45 | C4: 28.7 | D4: 31.15 | E4: =IF(AM4="","",AM4/2206.622)*100 -> 29.479449 | F4: 29.00724 | G4: 41.9 | H4: 28.9 | I4: 27.1 | J4: 22.072282 | K4: =B4-I4 -> 5.35 | L4: =IF(I4="","",IF(J4="","",I4-J4)) -> 5.0277185 | M4: =B4-H4 -> 3.55 | N4: =B4-C4 -> 3.75 | O4: =C4-H4 -> -0.2 | P4: =D4-H4 -> 2.25 | Q4: =IF(E4="","",E4-H4) -> 0.57944868 | R4: =IF(F4="","",F4-H4) -> 0.10724024 | S4: =G4-H4 -> 13 | T4: =G4-B4 -> 9.45 | U4: =IF(P4=N4,"EQUAL",IF(N4<P4,"LOWER","HIGHER")) -> HIGHER | V4: 639.5 | W4: =IF(V4="","",IF(D4="","",D4-F4)) -> 2.1427598 | X4: =IF(AM4="","",AM4/22.04622) -> 29.506192 | Y4: =IF(X4="","",IF(D4="","",D4-X4)) -> 1.643808 | Z4: =IF(X4="","",IF(F4="","",X4-F4)) -> 0.49895175 | AA4: =MONTH(A4) -> 12 | AB4: =YEAR(A4) -> 2018 | AF4: 37.331 | AG4: =IF(V4="","",V4*AF4/2204.622*100) -> 1082.8693 | AL4: =A4 -> 43438 | AM4: 650.5 | AN4: 3.8524 | AO4: =IF(AM4="","",AM4*AN4/2204.622*100) -> 113.66965 | AT4: 315 | AU4: 8.82 | AV4: =(((C4/100*11.7)+(AT4/2000*47))-(AU4)) -> 1.9404 | AW4: =(((B4/100*11.7*0.98)+(AT4/2000*47))-(AU4)) -> 2.303217 | AX4: =AW4-AV4 -> 0.362817 | AY4: =(B4*11.7/100)/((AT4/2000*47)+(B4*11.7/100)) -> 0.33901234 | BB4: =C4*22.0462 -> 632.72594
A5: 43439 | B5: 32.39 | C5: 28.64 | D5: 31.09 | E5: =IF(AM5="","",AM5/2206.622)*100 -> 29.400142 | F5: 28.927862 | G5: 41.84 | H5: 28.84 | I5: 27.1 | J5: 21.781179 | K5: =B5-I5 -> 5.29 | L5: =IF(I5="","",IF(J5="","",I5-J5)) -> 5.3188214 | M5: =B5-H5 -> 3.55 | N5: =B5-C5 -> 3.75 | O5: =C5-H5 -> -0.2 | P5: =D5-H5 -> 2.25 | Q5: =IF(E5="","",E5-H5) -> 0.56014194 | R5: =IF(F5="","",F5-H5) -> 0.087861556 | S5: =G5-H5 -> 13 | T5: =G5-B5 -> 9.45 | U5: =IF(P5=N5,"EQUAL",IF(N5<P5,"LOWER","HIGHER")) -> HIGHER | V5: 637.75 | W5: =IF(V5="","",IF(D5="","",D5-F5)) -> 2.1621384 | X5: =IF(AM5="","",AM5/22.04622) -> 29.426813 | Y5: =IF(X5="","",IF(D5="","",D5-X5)) -> 1.6631867 | Z5: =IF(X5="","",IF(F5="","",X5-F5)) -> 0.49895175 | AA5: =MONTH(A5) -> 12 | AB5: =YEAR(A5) -> 2018 | AF5: 37.446 | AG5: =IF(V5="","",V5*AF5/2204.622*100) -> 1083.2327 | AL5: =A5 -> 43439 | AM5: 648.75 | AN5: 3.8682 | AO5: =IF(AM5="","",AM5*AN5/2204.622*100) -> 113.8288 | AT5: 314 | AU5: 8.84 | AV5: =(((C5/100*11.7)+(AT5/2000*47))-(AU5)) -> 1.88988 | AW5: =(((B5/100*11.7*0.98)+(AT5/2000*47))-(AU5)) -> 2.2528374 | AX5: =AW5-AV5 -> 0.3629574 | AY5: =(B5*11.7/100)/((AT5/2000*47)+(B5*11.7/100)) -> 0.33931019 | BB5: =C5*22.0462 -> 631.40317
A6: 43440 | B6: 32.26 | C6: 28.51 | D6: 30.96 | E6: =IF(AM6="","",AM6/2206.622)*100 -> 29.071585 | F6: 28.701065 | G6: 41.71 | H6: 28.71 | I6: 27.1 | J6: 21.840446 | K6: =B6-I6 -> 5.16 | L6: =IF(I6="","",IF(J6="","",I6-J6)) -> 5.2595539 | M6: =B6-H6 -> 3.55 | N6: =B6-C6 -> 3.75 | O6: =C6-H6 -> -0.2 | P6: =D6-H6 -> 2.25 | Q6: =IF(E6="","",E6-H6) -> 0.36158544 | R6: =IF(F6="","",F6-H6) -> -0.0089346927 | S6: =G6-H6 -> 13 | T6: =G6-B6 -> 9.45 | U6: =IF(P6=N6,"EQUAL",IF(N6<P6,"LOWER","HIGHER")) -> HIGHER | V6: 632.75 | W6: =IF(V6="","",IF(D6="","",D6-F6)) -> 2.2589347 | X6: =IF(AM6="","",AM6/22.04622) -> 29.097959 | Y6: =IF(X6="","",IF(D6="","",D6-X6)) -> 1.8620413 | Z6: =IF(X6="","",IF(F6="","",X6-F6)) -> 0.39689344 | AA6: =MONTH(A6) -> 12 | AB6: =YEAR(A6) -> 2018 | AF6: 37.69 | AG6: =IF(V6="","",V6*AF6/2204.622*100) -> 1081.7432 | AL6: =A6 -> 43440 | AM6: 641.5 | AN6: 3.8779 | AO6: =IF(AM6="","",AM6*AN6/2204.622*100) -> 112.83897 | AT6: 312 | AU6: 8.8 | AV6: =(((C6/100*11.7)+(AT6/2000*47))-(AU6)) -> 1.86767 | AW6: =(((B6/100*11.7*0.98)+(AT6/2000*47))-(AU6)) -> 2.2309316 | AX6: =AW6-AV6 -> 0.3632616 | AY6: =(B6*11.7/100)/((AT6/2000*47)+(B6*11.7/100)) -> 0.33984128 | BB6: =C6*22.0462 -> 628.53716
A7: 43441 | B7: 32.29 | C7: 28.54 | D7: 30.99 | E7: =IF(AM7="","",AM7/2206.622)*100 -> 29.094245 | F7: 28.723745 | G7: 41.74 | H7: 28.74 | I7: 27.1 | J7: 21.764597 | K7: =B7-I7 -> 5.19 | L7: =IF(I7="","",IF(J7="","",I7-J7)) -> 5.3354032 | M7: =B7-H7 -> 3.55 | N7: =B7-C7 -> 3.75 | O7: =C7-H7 -> -0.2 | P7: =D7-H7 -> 2.25 | Q7: =IF(E7="","",E7-H7) -> 0.35424451 | R7: =IF(F7="","",F7-H7) -> -0.016255068 | S7: =G7-H7 -> 13 | T7: =G7-B7 -> 9.45 | U7: =IF(P7=N7,"EQUAL",IF(N7<P7,"LOWER","HIGHER")) -> HIGHER | V7: 633.25 | W7: =IF(V7="","",IF(D7="","",D7-F7)) -> 2.2662551 | X7: =IF(AM7="","",AM7/22.04622) -> 29.120638 | Y7: =IF(X7="","",IF(D7="","",D7-X7)) -> 1.8693616 | Z7: =IF(X7="","",IF(F7="","",X7-F7)) -> 0.39689344 | AA7: =MONTH(A7) -> 12 | AB7: =YEAR(A7) -> 2018 | AF7: 37.326 | AG7: =IF(V7="","",V7*AF7/2204.622*100) -> 1072.1425 | AL7: =A7 -> 43441 | AM7: 642 | AN7: 3.9074 | AO7: =IF(AM7="","",AM7*AN7/2204.622*100) -> 113.78598 | AT7: 311 | AU7: 8.87 | AV7: =(((C7/100*11.7)+(AT7/2000*47))-(AU7)) -> 1.77768 | AW7: =(((B7/100*11.7*0.98)+(AT7/2000*47))-(AU7)) -> 2.1408714 | AX7: =AW7-AV7 -> 0.3631914 | AY7: =(B7*11.7/100)/((AT7/2000*47)+(B7*11.7/100)) -> 0.34077065 | BB7: =C7*22.0462 -> 629.19855
A8: 43444 | B8: 32.31 | C8: 28.56 | D8: 31.01 | E8: =IF(AM8="","",AM8/2206.622)*100 -> 29.536096 | F8: 28.859823 | G8: 41.76 | H8: 28.76 | I8: 27.33 | J8: 22.211892 | K8: =B8-I8 -> 4.98 | L8: =IF(I8="","",IF(J8="","",I8-J8)) -> 5.1181084 | M8: =B8-H8 -> 3.55 | N8: =B8-C8 -> 3.75 | O8: =C8-H8 -> -0.2 | P8: =D8-H8 -> 2.25 | Q8: =IF(E8="","",E8-H8) -> 0.77609635 | R8: =IF(F8="","",F8-H8) -> 0.099822682 | S8: =G8-H8 -> 13 | T8: =G8-B8 -> 9.45 | U8: =IF(P8=N8,"EQUAL",IF(N8<P8,"LOWER","HIGHER")) -> HIGHER | V8: 636.25 | W8: =IF(V8="","",IF(D8="","",D8-F8)) -> 2.1501773 | X8: =IF(AM8="","",AM8/22.04622) -> 29.562891 | Y8: =IF(X8="","",IF(D8="","",D8-X8)) -> 1.4471089 | Z8: =IF(X8="","",IF(F8="","",X8-F8)) -> 0.70306837 | AA8: =MONTH(A8) -> 12 | AB8: =YEAR(A8) -> 2018 | AF8: 37.65 | AG8: =IF(V8="","",V8*AF8/2204.622*100) -> 1086.5723 | AL8: =A8 -> 43444 | AM8: 651.75 | AN8: 3.9178 | AO8: =IF(AM8="","",AM8*AN8/2204.622*100) -> 115.82149 | AT8: 310 | AU8: 8.8 | AV8: =(((C8/100*11.7)+(AT8/2000*47))-(AU8)) -> 1.82652 | AW8: =(((B8/100*11.7*0.98)+(AT8/2000*47))-(AU8)) -> 2.1896646 | AX8: =AW8-AV8 -> 0.3631446 | AY8: =(B8*11.7/100)/((AT8/2000*47)+(B8*11.7/100)) -> 0.34163378 | BB8: =C8*22.0462 -> 629.63947
A9: 43445 | B9: 32.51 | C9: 28.76 | D9: 31.21 | E9: =IF(AM9="","",AM9/2206.622)*100 -> 29.592744 | F9: 28.723745 | G9: 41.96 | H9: 28.96 | I9: 27.33 | J9: 21.860925 | K9: =B9-I9 -> 5.18 | L9: =IF(I9="","",IF(J9="","",I9-J9)) -> 5.4690754 | M9: =B9-H9 -> 3.55 | N9: =B9-C9 -> 3.75 | O9: =C9-H9 -> -0.2 | P9: =D9-H9 -> 2.25 | Q9: =IF(E9="","",E9-H9) -> 0.63274402 | R9: =IF(F9="","",F9-H9) -> -0.23625507 | S9: =G9-H9 -> 13 | T9: =G9-B9 -> 9.45 | U9: =IF(P9=N9,"EQUAL",IF(N9<P9,"LOWER","HIGHER")) -> HIGHER | V9: 633.25 | W9: =IF(V9="","",IF(D9="","",D9-F9)) -> 2.4862551 | X9: =IF(AM9="","",AM9/22.04622) -> 29.61959 | Y9: =IF(X9="","",IF(D9="","",D9-X9)) -> 1.5904099 | Z9: =IF(X9="","",IF(F9="","",X9-F9)) -> 0.89584518 | AA9: =MONTH(A9) -> 12 | AB9: =YEAR(A9) -> 2018 | AF9: 37.79 | AG9: =IF(V9="","",V9*AF9/2204.622*100) -> 1085.4703 | AL9: =A9 -> 43445 | AM9: 653 | AN9: 3.9039 | AO9: =IF(AM9="","",AM9*AN9/2204.622*100) -> 115.63192 | AT9: 311 | AU9: 8.85 | AV9: =(((C9/100*11.7)+(AT9/2000*47))-(AU9)) -> 1.82342 | AW9: =(((B9/100*11.7*0.98)+(AT9/2000*47))-(AU9)) -> 2.1860966 | AX9: =AW9-AV9 -> 0.3626766 | AY9: =(B9*11.7/100)/((AT9/2000*47)+(B9*11.7/100)) -> 0.34229768 | BB9: =C9*22.0462 -> 634.04871
A10: 43446 | B10: 32.59 | C10: 28.84 | D10: 31.29 | E10: =IF(AM10="","",AM10/2206.622)*100 -> 29.581414 | F10: 28.814463 | G10: 42.04 | H10: 29.04 | I10: 27.33 | J10: 22.034424 | K10: =B10-I10 -> 5.26 | L10: =IF(I10="","",IF(J10="","",I10-J10)) -> 5.295576 | M10: =B10-H10 -> 3.55 | N10: =B10-C10 -> 3.75 | O10: =C10-H10 -> -0.2 | P10: =D10-H10 -> 2.25 | Q10: =IF(E10="","",E10-H10) -> 0.54141449 | R10: =IF(F10="","",F10-H10) -> -0.22553657 | S10: =G10-H10 -> 13 | T10: =G10-B10 -> 9.45 | U10: =IF(P10=N10,"EQUAL",IF(N10<P10,"LOWER","HIGHER")) -> HIGHER | V10: 635.25 | W10: =IF(V10="","",IF(D10="","",D10-F10)) -> 2.4755366 | X10: =IF(AM10="","",AM10/22.04622) -> 29.60825 | Y10: =IF(X10="","",IF(D10="","",D10-X10)) -> 1.6817497 | Z10: =IF(X10="","",IF(F10="","",X10-F10)) -> 0.79378687 | AA10: =MONTH(A10) -> 12 | AB10: =YEAR(A10) -> 2018 | AF10: 37.545 | AG10: =IF(V10="","",V10*AF10/2204.622*100) -> 1081.839 | AL10: =A10 -> 43446 | AM10: 652.75 | AN10: 3.8554 | AO10: =IF(AM10="","",AM10*AN10/2204.622*100) -> 114.15165 | AT10: 313 | AU10: 8.9 | AV10: =(((C10/100*11.7)+(AT10/2000*47))-(AU10)) -> 1.82978 | AW10: =(((B10/100*11.7*0.98)+(AT10/2000*47))-(AU10)) -> 2.1922694 | AX10: =AW10-AV10 -> 0.3624894 | AY10: =(B10*11.7/100)/((AT10/2000*47)+(B10*11.7/100)) -> 0.3414084 | BB10: =C10*22.0462 -> 635.81241
A11: 43447 | B11: 32.38 | C11: 28.63 | D11: 31.08 | E11: =IF(AM11="","",AM11/2206.622)*100 -> 29.354824 | F11: 28.485609 | G11: 41.83 | H11: 28.83 | I11: 27.33 | J11: 22.191074 | K11: =B11-I11 -> 5.05 | L11: =IF(I11="","",IF(J11="","",I11-J11)) -> 5.1389261 | M11: =B11-H11 -> 3.55 | N11: =B11-C11 -> 3.75 | O11: =C11-H11 -> -0.2 | P11: =D11-H11 -> 2.25 | Q11: =IF(E11="","",E11-H11) -> 0.5248238 | R11: =IF(F11="","",F11-H11) -> -0.34439113 | S11: =G11-H11 -> 13 | T11: =G11-B11 -> 9.45 | U11: =IF(P11=N11,"EQUAL",IF(N11<P11,"LOWER","HIGHER")) -> HIGHER | V11: 628 | W11: =IF(V11="","",IF(D11="","",D11-F11)) -> 2.5943911 | X11: =IF(AM11="","",AM11/22.04622) -> 29.381454 | Y11: =IF(X11="","",IF(D11="","",D11-X11)) -> 1.6985459 | Z11: =IF(X11="","",IF(F11="","",X11-F11)) -> 0.89584518 | AA11: =MONTH(A11) -> 12 | AB11: =YEAR(A11) -> 2018 | AF11: 37.8 | AG11: =IF(V11="","",V11*AF11/2204.622*100) -> 1076.756 | AL11: =A11 -> 43447 | AM11: 647.75 | AN11: 3.891 | AO11: =IF(AM11="","",AM11*AN11/2204.622*100) -> 114.32324 | AT11: 309 | AU11: 8.77 | AV11: =(((C11/100*11.7)+(AT11/2000*47))-(AU11)) -> 1.84121 | AW11: =(((B11/100*11.7*0.98)+(AT11/2000*47))-(AU11)) -> 2.2041908 | AX11: =AW11-AV11 -> 0.3629808 | AY11: =(B11*11.7/100)/((AT11/2000*47)+(B11*11.7/100)) -> 0.3428483 | BB11: =C11*22.0462 -> 631.18271
A12: 43448 | B12: 32.04 | C12: 28.29 | D12: 30.74 | E12: =IF(AM12="","",AM12/2206.622)*100 -> 29.286847 | F12: 28.315512 | G12: 41.49 | H12: 28.49 | I12: 27.33 | J12: 22.424798 | K12: =B12-I12 -> 4.71 | L12: =IF(I12="","",IF(J12="","",I12-J12)) -> 4.9052023 | M12: =B12-H12 -> 3.55 | N12: =B12-C12 -> 3.75 | O12: =C12-H12 -> -0.2 | P12: =D12-H12 -> 2.25 | Q12: =IF(E12="","",E12-H12) -> 0.79684659 | R12: =IF(F12="","",F12-H12) -> -0.17448832 | S12: =G12-H12 -> 13 | T12: =G12-B12 -> 9.45 | U12: =IF(P12=N12,"EQUAL",IF(N12<P12,"LOWER","HIGHER")) -> HIGHER | V12: 624.25 | W12: =IF(V12="","",IF(D12="","",D12-F12)) -> 2.4244883 | X12: =IF(AM12="","",AM12/22.04622) -> 29.313415 | Y12: =IF(X12="","",IF(D12="","",D12-X12)) -> 1.4265848 | Z12: =IF(X12="","",IF(F12="","",X12-F12)) -> 0.9979035 | AA12: =MONTH(A12) -> 12 | AB12: =YEAR(A12) -> 2018 | AF12: 38.116 | AG12: =IF(V12="","",V12*AF12/2204.622*100) -> 1079.274 | AL12: =A12 -> 43448 | AM12: 646.25 | AN12: 3.917 | AO12: =IF(AM12="","",AM12*AN12/2204.622*100) -> 114.82065 | AT12: 307 | AU12: 8.71 | AV12: =(((C12/100*11.7)+(AT12/2000*47))-(AU12)) -> 1.81443 | AW12: =(((B12/100*11.7*0.98)+(AT12/2000*47))-(AU12)) -> 2.1782064 | AX12: =AW12-AV12 -> 0.3637764 | AY12: =(B12*11.7/100)/((AT12/2000*47)+(B12*11.7/100)) -> 0.34193364 | BB12: =C12*22.0462 -> 623.687
A13: 43451 | B13: 31.72 | C13: 27.97 | D13: 30.42 | E13: =IF(AM13="","",AM13/2206.622)*100 -> 28.856324 | F13: 27.975317 | G13: 41.17 | H13: 28.17 | I13: 27.67 | J13: 23.032383 | K13: =B13-I13 -> 4.05 | L13: =IF(I13="","",IF(J13="","",I13-J13)) -> 4.6376171 | M13: =B13-H13 -> 3.55 | N13: =B13-C13 -> 3.75 | O13: =C13-H13 -> -0.2 | P13: =D13-H13 -> 2.25 | Q13: =IF(E13="","",E13-H13) -> 0.68632428 | R13: =IF(F13="","",F13-H13) -> -0.19468269 | S13: =G13-H13 -> 13 | T13: =G13-B13 -> 9.45 | U13: =IF(P13=N13,"EQUAL",IF(N13<P13,"LOWER","HIGHER")) -> HIGHER | V13: 616.75 | W13: =IF(V13="","",IF(D13="","",D13-F13)) -> 2.4446827 | X13: =IF(AM13="","",AM13/22.04622) -> 28.882502 | Y13: =IF(X13="","",IF(D13="","",D13-X13)) -> 1.5374977 | Z13: =IF(X13="","",IF(F13="","",X13-F13)) -> 0.907185 | AA13: =MONTH(A13) -> 12 | AB13: =YEAR(A13) -> 2018 | AF13: 38.252 | AG13: =IF(V13="","",V13*AF13/2204.622*100) -> 1070.1118 | AL13: =A13 -> 43451 | AM13: 636.75 | AN13: 3.8994 | AO13: =IF(AM13="","",AM13*AN13/2204.622*100) -> 112.62443 | AT13: 309 | AU13: 8.75 | AV13: =(((C13/100*11.7)+(AT13/2000*47))-(AU13)) -> 1.78399 | AW13: =(((B13/100*11.7*0.98)+(AT13/2000*47))-(AU13)) -> 2.1485152 | AX13: =AW13-AV13 -> 0.3645252 | AY13: =(B13*11.7/100)/((AT13/2000*47)+(B13*11.7/100)) -> 0.33822363 | BB13: =C13*22.0462 -> 616.63221
A14: 43452 | B14: 31.96 | C14: 28.21 | D14: 30.66 | E14: =IF(AM14="","",AM14/2206.622)*100 -> 28.878983 | F14: 28.009337 | G14: 41.41 | H14: 28.41 | I14: 27.67 | J14: 23.391249 | K14: =B14-I14 -> 4.29 | L14: =IF(I14="","",IF(J14="","",I14-J14)) -> 4.2787509 | M14: =B14-H14 -> 3.55 | N14: =B14-C14 -> 3.75 | O14: =C14-H14 -> -0.2 | P14: =D14-H14 -> 2.25 | Q14: =IF(E14="","",E14-H14) -> 0.46898335 | R14: =IF(F14="","",F14-H14) -> -0.40066325 | S14: =G14-H14 -> 13 | T14: =G14-B14 -> 9.45 | U14: =IF(P14=N14,"EQUAL",IF(N14<P14,"LOWER","HIGHER")) -> HIGHER | V14: 617.5 | W14: =IF(V14="","",IF(D14="","",D14-F14)) -> 2.6506633 | X14: =IF(AM14="","",AM14/22.04622) -> 28.905182 | Y14: =IF(X14="","",IF(D14="","",D14-X14)) -> 1.7548181 | Z14: =IF(X14="","",IF(F14="","",X14-F14)) -> 0.89584518 | AA14: =MONTH(A14) -> 12 | AB14: =YEAR(A14) -> 2018 | AF14: 38.221 | AG14: =IF(V14="","",V14*AF14/2204.622*100) -> 1070.5449 | AL14: =A14 -> 43452 | AM14: 637.25 | AN14: 3.9123 | AO14: =IF(AM14="","",AM14*AN14/2204.622*100) -> 113.08574 | AT14: 310 | AU14: 8.78 | AV14: =(((C14/100*11.7)+(AT14/2000*47))-(AU14)) -> 1.80557 | AW14: =(((B14/100*11.7*0.98)+(AT14/2000*47))-(AU14)) -> 2.1695336 | AX14: =AW14-AV14 -> 0.3639636 | AY14: =(B14*11.7/100)/((AT14/2000*47)+(B14*11.7/100)) -> 0.33918827 | BB14: =C14*22.0462 -> 621.9233
A15: 43453 | B15: 32.01 | C15: 28.26 | D15: 30.71 | E15: =IF(AM15="","",AM15/2206.622)*100 -> 28.901642 | F15: 28.134075 | G15: 41.46 | H15: 28.46 | I15: 28 | J15: 23.868717 | K15: =B15-I15 -> 4.01 | L15: =IF(I15="","",IF(J15="","",I15-J15)) -> 4.131283 | M15: =B15-H15 -> 3.55 | N15: =B15-C15 -> 3.75 | O15: =C15-H15 -> -0.2 | P15: =D15-H15 -> 2.25 | Q15: =IF(E15="","",E15-H15) -> 0.44164242 | R15: =IF(F15="","",F15-H15) -> -0.32592532 | S15: =G15-H15 -> 13 | T15: =G15-B15 -> 9.45 | U15: =IF(P15=N15,"EQUAL",IF(N15<P15,"LOWER","HIGHER")) -> HIGHER | V15: 620.25 | W15: =IF(V15="","",IF(D15="","",D15-F15)) -> 2.5759253 | X15: =IF(AM15="","",AM15/22.04622) -> 28.927862 | Y15: =IF(X15="","",IF(D15="","",D15-X15)) -> 1.7821384 | Z15: =IF(X15="","",IF(F15="","",X15-F15)) -> 0.79378687 | AA15: =MONTH(A15) -> 12 | AB15: =YEAR(A15) -> 2018 | AF15: 38.35 | AG15: =IF(V15="","",V15*AF15/2204.622*100) -> 1078.9418 | AL15: =A15 -> 43453 | AM15: 637.75 | AN15: 3.8976 | AO15: =IF(AM15="","",AM15*AN15/2204.622*100) -> 112.74923 | AT15: 308 | AU15: 8.7 | AV15: =(((C15/100*11.7)+(AT15/2000*47))-(AU15)) -> 1.84442 | AW15: =(((B15/100*11.7*0.98)+(AT15/2000*47))-(AU15)) -> 2.2082666 | AX15: =AW15-AV15 -> 0.3638466 | AY15: =(B15*11.7/100)/((AT15/2000*47)+(B15*11.7/100)) -> 0.34099172 | BB15: =C15*22.0462 -> 623.02561
... A17: 43455 | B17: 31.44 | C17: 27.69 | D17: 30.14 | E17: =IF(AM17="","",AM17/2206.622)*100 -> 27.904643 | F17: 27.124831 | G17: 40.89 | H17: 28.17 | I17: 28 | J17: 23.401422 | K17: =B17-I17 -> 3.44 | L17: =IF(I17="","",IF(J17="","",I17-J17)) -> 4.598578 | M17: =B17-H17 -> 3.27 | N17: =B17-C17 -> 3.75 | O17: =C17-H17 -> -0.48 | P17: =D17-H17 -> 1.97 | Q17: =IF(E17="","",E17-H17) -> -0.26535661 | R17: =IF(F17="","",F17-H17) -> -1.0451686 | S17: =G17-H17 -> 12.72 | T17: =G17-B17 -> 9.45 | U17: =IF(P17=N17,"EQUAL",IF(N17<P17,"LOWER","HIGHER")) -> HIGHER | V17: 598 | W17: =IF(V17="","",IF(D17="","",D17-F17)) -> 3.0151686 | X17: =IF(AM17="","",AM17/22.04622) -> 27.929958 | Y17: =IF(X17="","",IF(D17="","",D17-X17)) -> 2.2100419 | Z17: =IF(X17="","",IF(F17="","",X17-F17)) -> 0.80512668 | AA17: =MONTH(A17) -> 12 | AB17: =YEAR(A17) -> 2018 | AF17: 37.965 | AG17: =IF(V17="","",V17*AF17/2204.622*100) -> 1029.7942 | AL17: =A17 -> 43455 | AM17: 615.75 | AN17: 3.9039 | AO17: =IF(AM17="","",AM17*AN17/2204.622*100) -> 109.03576 | AT17: 306 | AU17: 8.55 | AV17: =(((C17/100*11.7)+(AT17/2000*47))-(AU17)) -> 1.88073 | AW17: =(((B17/100*11.7*0.98)+(AT17/2000*47))-(AU17)) -> 2.2459104 | AX17: =AW17-AV17 -> 0.3651804 | AY17: =(B17*11.7/100)/((AT17/2000*47)+(B17*11.7/100)) -> 0.33842281 | BB17: =C17*22.0462 -> 610.45928
A18: 43458 | B18: 31.29 | C18: 27.54 | D18: 29.99 | E18: =IF(AM18="","",AM18/2206.622)*100 -> #VALUE! | G18: 40.74 | H18: 28.03 | I18: 28 | J18: 23.042889 | K18: =B18-I18 -> 3.29 | L18: =IF(I18="","",IF(J18="","",I18-J18)) -> 4.9571107 | M18: =B18-H18 -> 3.26 | N18: =B18-C18 -> 3.75 | O18: =C18-H18 -> -0.49 | P18: =D18-H18 -> 1.96 | Q18: =IF(E18="","",E18-H18) -> #VALUE! | R18: =IF(F18="","",F18-H18) | S18: =G18-H18 -> 12.71 | T18: =G18-B18 -> 9.45 | U18: =IF(P18=N18,"EQUAL",IF(N18<P18,"LOWER","HIGHER")) -> HIGHER | X18: =IF(AM18="","",AM18/22.04622) | Y18: =IF(X18="","",IF(D18="","",D18-X18)) | Z18: =IF(X18="","",IF(F18="","",X18-F18)) | AA18: =MONTH(A18) -> 12 | AB18: =YEAR(A18) -> 2018 | AF18: 37.939 | AG18: =IF(V18="","",V18*AF18/2204.622*100) | AL18: =A18 -> 43458 | AN18: 3.9035 | AO18: =IF(AM18="","",AM18*AN18/2204.622*100) | AT18: 308 | AU18: 8.54 | AV18: =(((C18/100*11.7)+(AT18/2000*47))-(AU18)) -> 1.92018 | AW18: =(((B18/100*11.7*0.98)+(AT18/2000*47))-(AU18)) -> 2.2857114 | AX18: =AW18-AV18 -> 0.3655314 | AY18: =(B18*11.7/100)/((AT18/2000*47)+(B18*11.7/100)) -> 0.33589811 | BB18: =C18*22.0462 -> 607.15235
A19: 43460 | B19: 30.91 | C19: 27.16 | D19: 29.61 | E19: =IF(AM19="","",AM19/2206.622)*100 -> #VALUE! | G19: 40.36 | H19: 27.65 | I19: 28 | J19: 22.750244 | K19: =B19-I19 -> 2.91 | L19: =IF(I19="","",IF(J19="","",I19-J19)) -> 5.2497559 | M19: =B19-H19 -> 3.26 | N19: =B19-C19 -> 3.75 | O19: =C19-H19 -> -0.49 | P19: =D19-H19 -> 1.96 | Q19: =IF(E19="","",E19-H19) -> #VALUE! | R19: =IF(F19="","",F19-H19) | S19: =G19-H19 -> 12.71 | T19: =G19-B19 -> 9.45 | U19: =IF(P19=N19,"EQUAL",IF(N19<P19,"LOWER","HIGHER")) -> HIGHER | X19: =IF(AM19="","",AM19/22.04622) | Y19: =IF(X19="","",IF(D19="","",D19-X19)) | Z19: =IF(X19="","",IF(F19="","",X19-F19)) | AA19: =MONTH(A19) -> 12 | AB19: =YEAR(A19) -> 2018 | AF19: 38.513 | AG19: =IF(V19="","",V19*AF19/2204.622*100) | AL19: =A19 -> 43460 | AN19: 3.9219 | AO19: =IF(AM19="","",AM19*AN19/2204.622*100) | AT19: 303 | AU19: 8.4 | AV19: =(((C19/100*11.7)+(AT19/2000*47))-(AU19)) -> 1.89822 | AW19: =(((B19/100*11.7*0.98)+(AT19/2000*47))-(AU19)) -> 2.2646406 | AX19: =AW19-AV19 -> 0.3664206 | AY19: =(B19*11.7/100)/((AT19/2000*47)+(B19*11.7/100)) -> 0.33682408 | BB19: =C19*22.0462 -> 598.77479
A20: 43461 | B20: 30.86 | C20: 27.11 | D20: 29.56 | E20: =IF(AM20="","",AM20/2206.622)*100 -> 27.428803 | F20: 27.056793 | G20: 40.31 | H20: 27.63 | I20: 28 | J20: 22.908272 | K20: =B20-I20 -> 2.86 | L20: =IF(I20="","",IF(J20="","",I20-J20)) -> 5.0917279 | M20: =B20-H20 -> 3.23 | N20: =B20-C20 -> 3.75 | O20: =C20-H20 -> -0.52 | P20: =D20-H20 -> 1.93 | Q20: =IF(E20="","",E20-H20) -> -0.20119706 | R20: =IF(F20="","",F20-H20) -> -0.5732075 | S20: =G20-H20 -> 12.68 | T20: =G20-B20 -> 9.45 | U20: =IF(P20=N20,"EQUAL",IF(N20<P20,"LOWER","HIGHER")) -> HIGHER | V20: 596.5 | W20: =IF(V20="","",IF(D20="","",D20-F20)) -> 2.5032075 | X20: =IF(AM20="","",AM20/22.04622) -> 27.453686 | Y20: =IF(X20="","",IF(D20="","",D20-X20)) -> 2.1063141 | Z20: =IF(X20="","",IF(F20="","",X20-F20)) -> 0.39689344 | AA20: =MONTH(A20) -> 12 | AB20: =YEAR(A20) -> 2018 | AF20: 38.257 | AG20: =IF(V20="","",V20*AF20/2204.622*100) -> 1035.1117 | AL20: =A20 -> 43461 | AM20: 605.25 | AN20: 3.8732 | AO20: =IF(AM20="","",AM20*AN20/2204.622*100) -> 106.33362 | AT20: 304 | AU20: 8.39 | AV20: =(((C20/100*11.7)+(AT20/2000*47))-(AU20)) -> 1.92587 | AW20: =(((B20/100*11.7*0.98)+(AT20/2000*47))-(AU20)) -> 2.2924076 | AX20: =AW20-AV20 -> 0.3665376 | AY20: =(B20*11.7/100)/((AT20/2000*47)+(B20*11.7/100)) -> 0.33572734 | BB20: =C20*22.0462 -> 597.67248
A21: 43462 | B21: 31.07 | C21: 27.32 | D21: 29.77 | E21: =IF(AM21="","",AM21/2206.622)*100 -> 27.757359 | F21: 27.18153 | G21: 40.52 | H21: 27.84 | I21: 28 | J21: 23.149612 | K21: =B21-I21 -> 3.07 | L21: =IF(I21="","",IF(J21="","",I21-J21)) -> 4.8503877 | M21: =B21-H21 -> 3.23 | N21: =B21-C21 -> 3.75 | O21: =C21-H21 -> -0.52 | P21: =D21-H21 -> 1.93 | Q21: =IF(E21="","",E21-H21) -> -0.082640561 | R21: =IF(F21="","",F21-H21) -> -0.65846956 | S21: =G21-H21 -> 12.68 | T21: =G21-B21 -> 9.45 | U21: =IF(P21=N21,"EQUAL",IF(N21<P21,"LOWER","HIGHER")) -> HIGHER | V21: 599.25 | W21: =IF(V21="","",IF(D21="","",D21-F21)) -> 2.5884696 | X21: =IF(AM21="","",AM21/22.04622) -> 27.78254 | Y21: =IF(X21="","",IF(D21="","",D21-X21)) -> 1.9874595 | Z21: =IF(X21="","",IF(F21="","",X21-F21)) -> 0.60101006 | AA21: =MONTH(A21) -> 12 | AB21: =YEAR(A21) -> 2018 | AF21: 37.68 | AG21: =IF(V21="","",V21*AF21/2204.622*100) -> 1024.2001 | AL21: =A21 -> 43462 | AM21: 612.5 | AN21: 3.8804 | AO21: =IF(AM21="","",AM21*AN21/2204.622*100) -> 107.80737 | AT21: 309 | AU21: 8.53 | AV21: =(((C21/100*11.7)+(AT21/2000*47))-(AU21)) -> 1.92794 | AW21: =(((B21/100*11.7*0.98)+(AT21/2000*47))-(AU21)) -> 2.2939862 | AX21: =AW21-AV21 -> 0.3660462 | AY21: =(B21*11.7/100)/((AT21/2000*47)+(B21*11.7/100)) -> 0.33360498 | BB21: =C21*22.0462 -> 602.30218
A22: 43465 | B22: 31.1 | C22: 27.35 | D22: 29.8 | E22: =IF(AM22="","",AM22/2206.622)*100 -> #VALUE! | G22: 40.55 | H22: 27.85 | I22: 28 | J22: 23.2727 | K22: =B22-I22 -> 3.1 | L22: =IF(I22="","",IF(J22="","",I22-J22)) -> 4.7273002 | M22: =B22-H22 -> 3.25 | N22: =B22-C22 -> 3.75 | O22: =C22-H22 -> -0.5 | P22: =D22-H22 -> 1.95 | Q22: =IF(E22="","",E22-H22) -> #VALUE! | R22: =IF(F22="","",F22-H22) | S22: =G22-H22 -> 12.7 | T22: =G22-B22 -> 9.45 | U22: =IF(P22=N22,"EQUAL",IF(N22<P22,"LOWER","HIGHER")) -> HIGHER | X22: =IF(AM22="","",AM22/22.04622) | Y22: =IF(X22="","",IF(D22="","",D22-X22)) | Z22: =IF(X22="","",IF(F22="","",X22-F22)) | AA22: =MONTH(A22) -> 12 | AB22: =YEAR(A22) -> 2018 | AF22: 37.619 | AG22: =IF(V22="","",V22*AF22/2204.622*100) | AL22: =A22 -> 43465 | AN22: 3.8804 | AO22: =IF(AM22="","",AM22*AN22/2204.622*100) | AT22: 306 | AU22: 8.53 | AV22: =(((C22/100*11.7)+(AT22/2000*47))-(AU22)) -> 1.86095 | AW22: =(((B22/100*11.7*0.98)+(AT22/2000*47))-(AU22)) -> 2.226926 | AX22: =AW22-AV22 -> 0.365976 | AY22: =(B22*11.7/100)/((AT22/2000*47)+(B22*11.7/100)) -> 0.33599269 | BB22: =C22*22.0462 -> 602.96357
A23: 43467 | B23: 31.73 | C23: 27.98 | D23: 30.43 | E23: =IF(AM23="","",AM23/2206.622)*100 -> 28.176552 | F23: 27.703162 | G23: 41.18 | H23: 28.18 | I23: 28 | J23: 23.73819 | K23: =B23-I23 -> 3.73 | L23: =IF(I23="","",IF(J23="","",I23-J23)) -> 4.2618098 | M23: =B23-H23 -> 3.55 | N23: =B23-C23 -> 3.75 | O23: =C23-H23 -> -0.2 | P23: =D23-H23 -> 2.25 | Q23: =IF(E23="","",E23-H23) -> -0.0034477858 | R23: =IF(F23="","",F23-H23) -> -0.47683819 | S23: =G23-H23 -> 13 | T23: =G23-B23 -> 9.45 | U23: =IF(P23=N23,"EQUAL",IF(N23<P23,"LOWER","HIGHER")) -> HIGHER | V23: 610.75 | W23: =IF(V23="","",IF(D23="","",D23-F23)) -> 2.7268382 | X23: =IF(AM23="","",AM23/22.04622) -> 28.202114 | Y23: =IF(X23="","",IF(D23="","",D23-X23)) -> 2.2278864 | Z23: =IF(X23="","",IF(F23="","",X23-F23)) -> 0.49895175 | AA23: =MONTH(A23) -> 1 | AB23: =YEAR(A23) -> 2019 | AC23: =WEEKNUM(A23) -> 1 | AF23: 37.696 | AG23: =IF(V23="","",V23*AF23/2204.622*100) -> 1044.2984 | AL23: =A23 -> 43467 | AM23: 621.75 | AN23: 3.7897 | AO23: =IF(AM23="","",AM23*AN23/2204.622*100) -> 106.87755 | AT23: 315 | AU23: 8.77 | AV23: =(((C23/100*11.7)+(AT23/2000*47))-(AU23)) -> 1.90616 | AW23: =(((B23/100*11.7*0.98)+(AT23/2000*47))-(AU23)) -> 2.2706618 | AX23: =AW23-AV23 -> 0.3645018 | AY23: =(B23*11.7/100)/((AT23/2000*47)+(B23*11.7/100)) -> 0.3340027 | BB23: =C23*22.0462 -> 616.85268
A24: 43468 | B24: 31.98 | C24: 28.23 | D24: 30.68 | E24: =IF(AM24="","",AM24/2206.622)*100 -> 28.22187 | F24: 27.646463 | G24: 41.43 | H24: 28.43 | I24: 28 | J24: 23.561397 | K24: =B24-I24 -> 3.98 | L24: =IF(I24="","",IF(J24="","",I24-J24)) -> 4.4386027 | M24: =B24-H24 -> 3.55 | N24: =B24-C24 -> 3.75 | O24: =C24-H24 -> -0.2 | P24: =D24-H24 -> 2.25 | Q24: =IF(E24="","",E24-H24) -> -0.20812965 | R24: =IF(F24="","",F24-H24) -> -0.78353725 | S24: =G24-H24 -> 13 | T24: =G24-B24 -> 9.45 | U24: =IF(P24=N24,"EQUAL",IF(N24<P24,"LOWER","HIGHER")) -> HIGHER | V24: 609.5 | W24: =IF(V24="","",IF(D24="","",D24-F24)) -> 3.0335373 | X24: =IF(AM24="","",AM24/22.04622) -> 28.247473 | Y24: =IF(X24="","",IF(D24="","",D24-X24)) -> 2.4325272 | Z24: =IF(X24="","",IF(F24="","",X24-F24)) -> 0.60101006 | AA24: =MONTH(A24) -> 1 | AB24: =YEAR(A24) -> 2019 | AC24: =WEEKNUM(A24) -> 1 | AF24: 37.411 | AG24: =IF(V24="","",V24*AF24/2204.622*100) -> 1034.2818 | AL24: =A24 -> 43468 | AM24: 622.75 | AN24: 3.7564 | AO24: =IF(AM24="","",AM24*AN24/2204.622*100) -> 106.10881 | AT24: 317 | AU24: 8.83 | AV24: =(((C24/100*11.7)+(AT24/2000*47))-(AU24)) -> 1.92241 | AW24: =(((B24/100*11.7*0.98)+(AT24/2000*47))-(AU24)) -> 2.2863268 | AX24: =AW24-AV24 -> 0.3639168 | AY24: =(B24*11.7/100)/((AT24/2000*47)+(B24*11.7/100)) -> 0.33434068 | BB24: =C24*22.0462 -> 622.36423
A25: 43469 | B25: 32.19 | C25: 28.44 | D25: 30.89 | E25: =IF(AM25="","",AM25/2206.622)*100 -> 28.72037 | F25: 28.054696 | G25: 41.64 | H25: 28.64 | I25: 28 | J25: 23.820738 | K25: =B25-I25 -> 4.19 | L25: =IF(I25="","",IF(J25="","",I25-J25)) -> 4.1792619 | M25: =B25-H25 -> 3.55 | N25: =B25-C25 -> 3.75 | O25: =C25-H25 -> -0.2 | P25: =D25-H25 -> 2.25 | Q25: =IF(E25="","",E25-H25) -> 0.080369869 | R25: =IF(F25="","",F25-H25) -> -0.585304 | S25: =G25-H25 -> 13 | T25: =G25-B25 -> 9.45 | U25: =IF(P25=N25,"EQUAL",IF(N25<P25,"LOWER","HIGHER")) -> HIGHER | V25: 618.5 | W25: =IF(V25="","",IF(D25="","",D25-F25)) -> 2.835304 | X25: =IF(AM25="","",AM25/22.04622) -> 28.746425 | Y25: =IF(X25="","",IF(D25="","",D25-X25)) -> 2.1435754 | Z25: =IF(X25="","",IF(F25="","",X25-F25)) -> 0.69172856 | AA25: =MONTH(A25) -> 1 | AB25: =YEAR(A25) -> 2019 | AC25: =WEEKNUM(A25) -> 1 | AF25: 37.34 | AG25: =IF(V25="","",V25*AF25/2204.622*100) -> 1047.5623 | AL25: =A25 -> 43469 | AM25: 633.75 | AN25: 3.7154 | AO25: =IF(AM25="","",AM25*AN25/2204.622*100) -> 106.80447 | AT25: 319 | AU25: 8.92 | AV25: =(((C25/100*11.7)+(AT25/2000*47))-(AU25)) -> 1.90398 | AW25: =(((B25/100*11.7*0.98)+(AT25/2000*47))-(AU25)) -> 2.2674054 | AX25: =AW25-AV25 -> 0.3634254 | AY25: =(B25*11.7/100)/((AT25/2000*47)+(B25*11.7/100)) -> 0.33439761 | BB25: =C25*22.0462 -> 626.99393
A26: 43472 | B26: 32.06 | C26: 28.31 | D26: 30.76 | E26: =IF(AM26="","",AM26/2206.622)*100 -> 28.267188 | F26: 27.884599 | G26: 41.51 | H26: 28.51 | I26: 28 | J26: 23.810022 | K26: =B26-I26 -> 4.06 | L26: =IF(I26="","",IF(J26="","",I26-J26)) -> 4.189978 | M26: =B26-H26 -> 3.55 | N26: =B26-C26 -> 3.75 | O26: =C26-H26 -> -0.2 | P26: =D26-H26 -> 2.25 | Q26: =IF(E26="","",E26-H26) -> -0.24281151 | R26: =IF(F26="","",F26-H26) -> -0.62540119 | S26: =G26-H26 -> 13 | T26: =G26-B26 -> 9.45 | U26: =IF(P26=N26,"EQUAL",IF(N26<P26,"LOWER","HIGHER")) -> HIGHER | V26: 614.75 | W26: =IF(V26="","",IF(D26="","",D26-F26)) -> 2.8754012 | X26: =IF(AM26="","",AM26/22.04622) -> 28.292832 | Y26: =IF(X26="","",IF(D26="","",D26-X26)) -> 2.4671679 | Z26: =IF(X26="","",IF(F26="","",X26-F26)) -> 0.40823325 | AA26: =MONTH(A26) -> 1 | AB26: =YEAR(A26) -> 2019 | AC26: =WEEKNUM(A26) -> 2 | AF26: 37.269 | AG26: =IF(V26="","",V26*AF26/2204.622*100) -> 1039.2311 | AL26: =A26 -> 43472 | AM26: 623.75 | AN26: 3.7351 | AO26: =IF(AM26="","",AM26*AN26/2204.622*100) -> 105.67656 | AT26: 322 | AU26: 8.86 | AV26: =(((C26/100*11.7)+(AT26/2000*47))-(AU26)) -> 2.01927 | AW26: =(((B26/100*11.7*0.98)+(AT26/2000*47))-(AU26)) -> 2.3829996 | AX26: =AW26-AV26 -> 0.3637296 | AY26: =(B26*11.7/100)/((AT26/2000*47)+(B26*11.7/100)) -> 0.33142016 | BB26: =C26*22.0462 -> 624.12792
A27: 43473 | B27: 31.98 | C27: 28.23 | D27: 30.68 | E27: =IF(AM27="","",AM27/2206.622)*100 -> 28.414472 | F27: 28.043356 | G27: 41.43 | H27: 28.43 | I27: 28 | J27: 24.002052 | K27: =B27-I27 -> 3.98 | L27: =IF(I27="","",IF(J27="","",I27-J27)) -> 3.997948 | M27: =B27-H27 -> 3.55 | N27: =B27-C27 -> 3.75 | O27: =C27-H27 -> -0.2 | P27: =D27-H27 -> 2.25 | Q27: =IF(E27="","",E27-H27) -> -0.015527562 | R27: =IF(F27="","",F27-H27) -> -0.38664381 | S27: =G27-H27 -> 13 | T27: =G27-B27 -> 9.45 | U27: =IF(P27=N27,"EQUAL",IF(N27<P27,"LOWER","HIGHER")) -> HIGHER | V27: 618.25 | W27: =IF(V27="","",IF(D27="","",D27-F27)) -> 2.6366438 | X27: =IF(AM27="","",AM27/22.04622) -> 28.44025 | Y27: =IF(X27="","",IF(D27="","",D27-X27)) -> 2.2397504 | Z27: =IF(X27="","",IF(F27="","",X27-F27)) -> 0.39689344 | AA27: =MONTH(A27) -> 1 | AB27: =YEAR(A27) -> 2019 | AC27: =WEEKNUM(A27) -> 2 | AF27: 37.512 | AG27: =IF(V27="","",V27*AF27/2204.622*100) -> 1051.9624 | AL27: =A27 -> 43473 | AM27: 627 | AN27: 3.7132 | AO27: =IF(AM27="","",AM27*AN27/2204.622*100) -> 105.60433 | AT27: 322 | AU27: 8.81 | AV27: =(((C27/100*11.7)+(AT27/2000*47))-(AU27)) -> 2.05991 | AW27: =(((B27/100*11.7*0.98)+(AT27/2000*47))-(AU27)) -> 2.4238268 | AX27: =AW27-AV27 -> 0.3639168 | AY27: =(B27*11.7/100)/((AT27/2000*47)+(B27*11.7/100)) -> 0.33086679 | BB27: =C27*22.0462 -> 622.36423
A28: 43474 | B28: 32.15 | C28: 28.4 | D28: 30.6 | E28: =IF(AM28="","",AM28/2206.622)*100 -> 28.765688 | F28: 28.190774 | G28: 41.6 | H28: 28.6 | I28: 29.26 | J28: 24.0747 | K28: =B28-I28 -> 2.89 | L28: =IF(I28="","",IF(J28="","",I28-J28)) -> 5.1852997 | M28: =B28-H28 -> 3.55 | N28: =B28-C28 -> 3.75 | O28: =C28-H28 -> -0.2 | P28: =D28-H28 -> 2 | Q28: =IF(E28="","",E28-H28) -> 0.16568801 | R28: =IF(F28="","",F28-H28) -> -0.40922625 | S28: =G28-H28 -> 13 | T28: =G28-B28 -> 9.45 | U28: =IF(P28=N28,"EQUAL",IF(N28<P28,"LOWER","HIGHER")) -> HIGHER | V28: 621.5 | W28: =IF(V28="","",IF(D28="","",D28-F28)) -> 2.4092263 | X28: =IF(AM28="","",AM28/22.04622) -> 28.791784 | Y28: =IF(X28="","",IF(D28="","",D28-X28)) -> 1.8082162 | Z28: =IF(X28="","",IF(F28="","",X28-F28)) -> 0.60101006 | AA28: =MONTH(A28) -> 1 | AB28: =YEAR(A28) -> 2019 | AC28: =WEEKNUM(A28) -> 2 | AF28: 37.318 | AG28: =IF(V28="","",V28*AF28/2204.622*100) -> 1052.0233 | AL28: =A28 -> 43474 | AM28: 634.75 | AN28: 3.6806 | AO28: =IF(AM28="","",AM28*AN28/2204.622*100) -> 105.97104 | AT28: 323 | AU28: 8.86 | AV28: =(((C28/100*11.7)+(AT28/2000*47))-(AU28)) -> 2.0533 | AW28: =(((B28/100*11.7*0.98)+(AT28/2000*47))-(AU28)) -> 2.416819 | AX28: =AW28-AV28 -> 0.363519 | AY28: =(B28*11.7/100)/((AT28/2000*47)+(B28*11.7/100)) -> 0.33135425 | BB28: =C28*22.0462 -> 626.11208
A29: 43475 | B29: 31.74 | C29: 27.99 | D29: 30.19 | E29: =IF(AM29="","",AM29/2206.622)*100 -> 28.584415 | F29: 28.111395 | G29: 41.19 | H29: 28.19 | I29: 29.26 | J29: 23.970065 | K29: =B29-I29 -> 2.48 | L29: =IF(I29="","",IF(J29="","",I29-J29)) -> 5.2899349 | M29: =B29-H29 -> 3.55 | N29: =B29-C29 -> 3.75 | O29: =C29-H29 -> -0.2 | P29: =D29-H29 -> 2 | Q29: =IF(E29="","",E29-H29) -> 0.39441545 | R29: =IF(F29="","",F29-H29) -> -0.07860494 | S29: =G29-H29 -> 13 | T29: =G29-B29 -> 9.45 | U29: =IF(P29=N29,"EQUAL",IF(N29<P29,"LOWER","HIGHER")) -> HIGHER | V29: 619.75 | W29: =IF(V29="","",IF(D29="","",D29-F29)) -> 2.0786049 | X29: =IF(AM29="","",AM29/22.04622) -> 28.610347 | Y29: =IF(X29="","",IF(D29="","",D29-X29)) -> 1.5796532 | Z29: =IF(X29="","",IF(F29="","",X29-F29)) -> 0.49895175 | AA29: =MONTH(A29) -> 1 | AB29: =YEAR(A29) -> 2019 | AC29: =WEEKNUM(A29) -> 2 | AF29: 36.85 | AG29: =IF(V29="","",V29*AF29/2204.622*100) -> 1035.9049 | AL29: =A29 -> 43475 | AM29: 630.75 | AN29: 3.7104 | AO29: =IF(AM29="","",AM29*AN29/2204.622*100) -> 106.15583 | AT29: 317 | AU29: 8.69 | AV29: =(((C29/100*11.7)+(AT29/2000*47))-(AU29)) -> 2.03433 | AW29: =(((B29/100*11.7*0.98)+(AT29/2000*47))-(AU29)) -> 2.3988084 | AX29: =AW29-AV29 -> 0.3644784 | AY29: =(B29*11.7/100)/((AT29/2000*47)+(B29*11.7/100)) -> 0.33266625 | BB29: =C29*22.0462 -> 617.07314
A30: 43476 | B30: 31.96 | C30: 28.21 | D30: 30.41 | E30: =IF(AM30="","",AM30/2206.622)*100 -> 28.96962 | F30: 28.803124 | G30: 41.41 | H30: 28.41 | I30: 29.26 | J30: 24.075635 | K30: =B30-I30 -> 2.7 | L30: =IF(I30="","",IF(J30="","",I30-J30)) -> 5.184365 | M30: =B30-H30 -> 3.55 | N30: =B30-C30 -> 3.75 | O30: =C30-H30 -> -0.2 | P30: =D30-H30 -> 2 | Q30: =IF(E30="","",E30-H30) -> 0.55961963 | R30: =IF(F30="","",F30-H30) -> 0.39312362 | S30: =G30-H30 -> 13 | T30: =G30-B30 -> 9.45 | U30: =IF(P30=N30,"EQUAL",IF(N30<P30,"LOWER","HIGHER")) -> HIGHER | V30: 635 | W30: =IF(V30="","",IF(D30="","",D30-F30)) -> 1.6068764 | X30: =IF(AM30="","",AM30/22.04622) -> 28.9959 | Y30: =IF(X30="","",IF(D30="","",D30-X30)) -> 1.4140996 | Z30: =IF(X30="","",IF(F30="","",X30-F30)) -> 0.19277681 | AA30: =MONTH(A30) -> 1 | AB30: =YEAR(A30) -> 2019 | AC30: =WEEKNUM(A30) -> 2 | AF30: 36.862 | AG30: =IF(V30="","",V30*AF30/2204.622*100) -> 1061.7407 | AL30: =A30 -> 43476 | AM30: 639.25 | AN30: 3.7108 | AO30: =IF(AM30="","",AM30*AN30/2204.622*100) -> 107.59799 | AT30: 315 | AU30: 8.72 | AV30: =(((C30/100*11.7)+(AT30/2000*47))-(AU30)) -> 1.98307 | AW30: =(((B30/100*11.7*0.98)+(AT30/2000*47))-(AU30)) -> 2.3470336 | AX30: =AW30-AV30 -> 0.3639636 | AY30: =(B30*11.7/100)/((AT30/2000*47)+(B30*11.7/100)) -> 0.33561124 | BB30: =C30*22.0462 -> 621.9233
A31: 43479 | B31: 31.95 | C31: 28.2 | D31: 30.4 | E31: =IF(AM31="","",AM31/2206.622)*100 -> 28.95829 | F31: 28.678386 | G31: 41.4 | H31: 28.4 | I31: 29.26 | J31: 23.626224 | K31: =B31-I31 -> 2.69 | L31: =IF(I31="","",IF(J31="","",I31-J31)) -> 5.6337762 | M31: =B31-H31 -> 3.55 | N31: =B31-C31 -> 3.75 | O31: =C31-H31 -> -0.2 | P31: =D31-H31 -> 2 | Q31: =IF(E31="","",E31-H31) -> 0.55829009 | R31: =IF(F31="","",F31-H31) -> 0.27838568 | S31: =G31-H31 -> 13 | T31: =G31-B31 -> 9.45 | U31: =IF(P31=N31,"EQUAL",IF(N31<P31,"LOWER","HIGHER")) -> HIGHER | V31: 632.25 | W31: =IF(V31="","",IF(D31="","",D31-F31)) -> 1.7216143 | X31: =IF(AM31="","",AM31/22.04622) -> 28.984561 | Y31: =IF(X31="","",IF(D31="","",D31-X31)) -> 1.4154394 | Z31: =IF(X31="","",IF(F31="","",X31-F31)) -> 0.30617494 | AA31: =MONTH(A31) -> 1 | AB31: =YEAR(A31) -> 2019 | AC31: =WEEKNUM(A31) -> 3 | AF31: 36.942 | AG31: =IF(V31="","",V31*AF31/2204.622*100) -> 1059.4369 | AL31: =A31 -> 43479 | AM31: 639 | AN31: 3.6978 | AO31: =IF(AM31="","",AM31*AN31/2204.622*100) -> 107.17911 | AT31: 312 | AU31: 8.64 | AV31: =(((C31/100*11.7)+(AT31/2000*47))-(AU31)) -> 1.9914 | AW31: =(((B31/100*11.7*0.98)+(AT31/2000*47))-(AU31)) -> 2.355387 | AX31: =AW31-AV31 -> 0.363987 | AY31: =(B31*11.7/100)/((AT31/2000*47)+(B31*11.7/100)) -> 0.33767835 | BB31: =C31*22.0462 -> 621.70284
A32: 43480 | B32: 31.59 | C32: 27.84 | D32: 30.24 | E32: =IF(AM32="","",AM32/2206.622)*100 -> 29.094245 | F32: 28.621687 | G32: 41.24 | H32: 28.24 | I32: 29.26 | J32: 23.735391 | K32: =B32-I32 -> 2.33 | L32: =IF(I32="","",IF(J32="","",I32-J32)) -> 5.524609 | M32: =B32-H32 -> 3.35 | N32: =B32-C32 -> 3.75 | O32: =C32-H32 -> -0.4 | P32: =D32-H32 -> 2 | Q32: =IF(E32="","",E32-H32) -> 0.85424451 | R32: =IF(F32="","",F32-H32) -> 0.38168662 | S32: =G32-H32 -> 13 | T32: =G32-B32 -> 9.65 | U32: =IF(P32=N32,"EQUAL",IF(N32<P32,"LOWER","HIGHER")) -> HIGHER | V32: 631 | W32: =IF(V32="","",IF(D32="","",D32-F32)) -> 1.6183134 | X32: =IF(AM32="","",AM32/22.04622) -> 29.120638 | Y32: =IF(X32="","",IF(D32="","",D32-X32)) -> 1.1193616 | Z32: =IF(X32="","",IF(F32="","",X32-F32)) -> 0.49895175 | AA32: =MONTH(A32) -> 1 | AB32: =YEAR(A32) -> 2019 | AC32: =WEEKNUM(A32) -> 3 | AF32: 37.073 | AG32: =IF(V32="","",V32*AF32/2204.622*100) -> 1061.0918 | AL32: =A32 -> 43480 | AM32: 642 | AN32: 3.7167 | AO32: =IF(AM32="","",AM32*AN32/2204.622*100) -> 108.23268 | AT32: 309 | AU32: 8.53 | AV32: =(((C32/100*11.7)+(AT32/2000*47))-(AU32)) -> 1.98878 | AW32: =(((B32/100*11.7*0.98)+(AT32/2000*47))-(AU32)) -> 2.3536094 | AX32: =AW32-AV32 -> 0.3648294 | AY32: =(B32*11.7/100)/((AT32/2000*47)+(B32*11.7/100)) -> 0.33730503 | BB32: =C32*22.0462 -> 613.76621
A33: 43481 | B33: 31.58 | C33: 27.83 | D33: 30.23 | E33: =IF(AM33="","",AM33/2206.622)*100 -> 28.833665 | F33: 28.564988 | G33: 41.23 | H33: 28.23 | I33: 29.26 | J33: 24.004627 | K33: =B33-I33 -> 2.32 | L33: =IF(I33="","",IF(J33="","",I33-J33)) -> 5.2553727 | M33: =B33-H33 -> 3.35 | N33: =B33-C33 -> 3.75 | O33: =C33-H33 -> -0.4 | P33: =D33-H33 -> 2 | Q33: =IF(E33="","",E33-H33) -> 0.60366521 | R33: =IF(F33="","",F33-H33) -> 0.33498756 | S33: =G33-H33 -> 13 | T33: =G33-B33 -> 9.65 | U33: =IF(P33=N33,"EQUAL",IF(N33<P33,"LOWER","HIGHER")) -> HIGHER | V33: 629.75 | W33: =IF(V33="","",IF(D33="","",D33-F33)) -> 1.6650124 | X33: =IF(AM33="","",AM33/22.04622) -> 28.859823 | Y33: =IF(X33="","",IF(D33="","",D33-X33)) -> 1.3701773 | Z33: =IF(X33="","",IF(F33="","",X33-F33)) -> 0.29483512 | AA33: =MONTH(A33) -> 1 | AB33: =YEAR(A33) -> 2019 | AC33: =WEEKNUM(A33) -> 3 | AF33: 37.445 | AG33: =IF(V33="","",V33*AF33/2204.622*100) -> 1069.616 | AL33: =A33 -> 43481 | AM33: 636.25 | AN33: 3.7361 | AO33: =IF(AM33="","",AM33*AN33/2204.622*100) -> 107.82318 | AT33: 310 | AU33: 8.55 | AV33: =(((C33/100*11.7)+(AT33/2000*47))-(AU33)) -> 1.99111 | AW33: =(((B33/100*11.7*0.98)+(AT33/2000*47))-(AU33)) -> 2.3559628 | AX33: =AW33-AV33 -> 0.3648528 | AY33: =(B33*11.7/100)/((AT33/2000*47)+(B33*11.7/100)) -> 0.33651249 | BB33: =C33*22.0462 -> 613.54575
A34: 43482 | B34: 31.87 | C34: 28.12 | D34: 30.77 | E34: =IF(AM34="","",AM34/2206.622)*100 -> 28.95829 | F34: 29.177337 | G34: 41.77 | H34: 28.77 | I34: 29.26 | J34: 24.234988 | K34: =B34-I34 -> 2.61 | L34: =IF(I34="","",IF(J34="","",I34-J34)) -> 5.0250117 | M34: =B34-H34 -> 3.1 | N34: =B34-C34 -> 3.75 | O34: =C34-H34 -> -0.65 | P34: =D34-H34 -> 2 | Q34: =IF(E34="","",E34-H34) -> 0.18829009 | R34: =IF(F34="","",F34-H34) -> 0.40733743 | S34: =G34-H34 -> 13 | T34: =G34-B34 -> 9.9 | U34: =IF(P34=N34,"EQUAL",IF(N34<P34,"LOWER","HIGHER")) -> HIGHER | V34: 643.25 | W34: =IF(V34="","",IF(D34="","",D34-F34)) -> 1.5926626 | X34: =IF(AM34="","",AM34/22.04622) -> 28.984561 | Y34: =IF(X34="","",IF(D34="","",D34-X34)) -> 1.7854394 | Z34: =IF(X34="","",IF(F34="","",X34-F34)) -> -0.19277681 | AA34: =MONTH(A34) -> 1 | AB34: =YEAR(A34) -> 2019 | AC34: =WEEKNUM(A34) -> 3 | AF34: 37.654 | AG34: =IF(V34="","",V34*AF34/2204.622*100) -> 1098.6435 | AL34: =A34 -> 43482 | AM34: 639 | AN34: 3.7502 | AO34: =IF(AM34="","",AM34*AN34/2204.622*100) -> 108.6979 | AT34: 312 | AU34: 8.68 | AV34: =(((C34/100*11.7)+(AT34/2000*47))-(AU34)) -> 1.94204 | AW34: =(((B34/100*11.7*0.98)+(AT34/2000*47))-(AU34)) -> 2.3062142 | AX34: =AW34-AV34 -> 0.3641742 | AY34: =(B34*11.7/100)/((AT34/2000*47)+(B34*11.7/100)) -> 0.33711787 | BB34: =C34*22.0462 -> 619.93914
... A45: 43500 | B45: 33.23 | C45: 29.48 | D45: 32.13 | E45: =IF(AM45="","",AM45/2206.622)*100 -> 30.974947 | F45: 30.696872 | G45: 41.13 | H45: 30.13 | I45: 30.8 | J45: 25.574188 | K45: =B45-I45 -> 2.43 | L45: =IF(I45="","",IF(J45="","",I45-J45)) -> 5.2258117 | M45: =B45-H45 -> 3.1 | N45: =B45-C45 -> 3.75 | O45: =C45-H45 -> -0.65 | P45: =D45-H45 -> 2 | Q45: =IF(E45="","",E45-H45) -> 0.84494723 | R45: =IF(F45="","",F45-H45) -> 0.5668723 | S45: =G45-H45 -> 11 | T45: =G45-B45 -> 7.9 | U45: =IF(P45=N45,"EQUAL",IF(N45<P45,"LOWER","HIGHER")) -> HIGHER | V45: 676.75 | W45: =IF(V45="","",IF(D45="","",D45-F45)) -> 1.4331277 | X45: =IF(AM45="","",AM45/22.04622) -> 31.003047 | Y45: =IF(X45="","",IF(D45="","",D45-X45)) -> 1.1269528 | Z45: =IF(X45="","",IF(F45="","",X45-F45)) -> 0.30617494 | AA45: =MONTH(A45) -> 2 | AB45: =YEAR(A45) -> 2019 | AC45: =WEEKNUM(A45) -> 6 | AF45: 37.118 | AG45: =IF(V45="","",V45*AF45/2204.622*100) -> 1139.4065 | AL45: =A45 -> 43500 | AM45: 683.5 | AN45: 3.6686 | AO45: =IF(AM45="","",AM45*AN45/2204.622*100) -> 113.73778 | AT45: 306 | AU45: 8.86 | AV45: =(((C45/100*11.7)+(AT45/2000*47))-(AU45)) -> 1.78016 | AW45: =(((B45/100*11.7*0.98)+(AT45/2000*47))-(AU45)) -> 2.1411518 | AX45: =AW45-AV45 -> 0.3609918 | AY45: =(B45*11.7/100)/((AT45/2000*47)+(B45*11.7/100)) -> 0.35092893 | BB45: =C45*22.0462 -> 649.92198
A46: 43501 | B46: 33.48 | C46: 29.73 | D46: 32.38 | E46: =IF(AM46="","",AM46/2206.622)*100 -> 31.15622 | F46: 31.093766 | G46: 41.38 | H46: 30.38 | I46: 30.8 | K46: =B46-I46 -> 2.68 | L46: =IF(I46="","",IF(J46="","",I46-J46)) | M46: =B46-H46 -> 3.1 | N46: =B46-C46 -> 3.75 | O46: =C46-H46 -> -0.65 | P46: =D46-H46 -> 2 | Q46: =IF(E46="","",E46-H46) -> 0.77621978 | R46: =IF(F46="","",F46-H46) -> 0.71376573 | S46: =G46-H46 -> 11 | T46: =G46-B46 -> 7.9 | U46: =IF(P46=N46,"EQUAL",IF(N46<P46,"LOWER","HIGHER")) -> HIGHER | V46: 685.5 | W46: =IF(V46="","",IF(D46="","",D46-F46)) -> 1.2862343 | X46: =IF(AM46="","",AM46/22.04622) -> 31.184484 | Y46: =IF(X46="","",IF(D46="","",D46-X46)) -> 1.1955158 | Z46: =IF(X46="","",IF(F46="","",X46-F46)) -> 0.0907185 | AA46: =MONTH(A46) -> 2 | AB46: =YEAR(A46) -> 2019 | AC46: =WEEKNUM(A46) -> 6 | AF46: 37.205 | AG46: =IF(V46="","",V46*AF46/2204.622*100) -> 1156.8436 | AL46: =A46 -> 43501 | AM46: 687.5 | AN46: 3.6695 | AO46: =IF(AM46="","",AM46*AN46/2204.622*100) -> 114.43146 | AT46: 305 | AU46: 8.87 | AV46: =(((C46/100*11.7)+(AT46/2000*47))-(AU46)) -> 1.77591 | AW46: =(((B46/100*11.7*0.98)+(AT46/2000*47))-(AU46)) -> 2.1363168 | AX46: =AW46-AV46 -> 0.3604068 | AY46: =(B46*11.7/100)/((AT46/2000*47)+(B46*11.7/100)) -> 0.35338567 | BB46: =C46*22.0462 -> 655.43353
A47: 43502 | B47: 34 | C47: 30.25 | D47: 32.9 | E47: =IF(AM47="","",AM47/2206.622)*100 -> 31.280845 | F47: 31.309222 | G47: 41.9 | H47: 30.9 | I47: 30.8 | K47: =B47-I47 -> 3.2 | L47: =IF(I47="","",IF(J47="","",I47-J47)) | M47: =B47-H47 -> 3.1 | N47: =B47-C47 -> 3.75 | O47: =C47-H47 -> -0.65 | P47: =D47-H47 -> 2 | Q47: =IF(E47="","",E47-H47) -> 0.38084466 | R47: =IF(F47="","",F47-H47) -> 0.40922217 | S47: =G47-H47 -> 11 | T47: =G47-B47 -> 7.9 | U47: =IF(P47=N47,"EQUAL",IF(N47<P47,"LOWER","HIGHER")) -> HIGHER | V47: 690.25 | W47: =IF(V47="","",IF(D47="","",D47-F47)) -> 1.5907778 | X47: =IF(AM47="","",AM47/22.04622) -> 31.309222 | Y47: =IF(X47="","",IF(D47="","",D47-X47)) -> 1.5907778 | Z47: =IF(X47="","",IF(F47="","",X47-F47)) -> -3.5527137e-15 | AA47: =MONTH(A47) -> 2 | AB47: =YEAR(A47) -> 2019 | AC47: =WEEKNUM(A47) -> 6 | AF47: 37.492 | AG47: =IF(V47="","",V47*AF47/2204.622*100) -> 1173.8454 | AL47: =A47 -> 43502 | AM47: 690.25 | AN47: 3.6982 | AO47: =IF(AM47="","",AM47*AN47/2204.622*100) -> 115.78777 | AT47: 304 | AU47: 8.89 | AV47: =(((C47/100*11.7)+(AT47/2000*47))-(AU47)) -> 1.79325 | AW47: =(((B47/100*11.7*0.98)+(AT47/2000*47))-(AU47)) -> 2.15244 | AX47: =AW47-AV47 -> 0.35919 | AY47: =(B47*11.7/100)/((AT47/2000*47)+(B47*11.7/100)) -> 0.35766948 | BB47: =C47*22.0462 -> 666.89755
A48: 43503 | B48: 33.31 | C48: 30.16 | D48: 32.81 | E48: =IF(AM48="","",AM48/2206.622)*100 -> 31.15622 | F48: 30.980368 | G48: 41.81 | H48: 30.81 | I48: 30.8 | J48: 25.82408 | K48: =B48-I48 -> 2.51 | L48: =IF(I48="","",IF(J48="","",I48-J48)) -> 4.9759202 | M48: =B48-H48 -> 2.5 | N48: =B48-C48 -> 3.15 | O48: =C48-H48 -> -0.65 | P48: =D48-H48 -> 2 | Q48: =IF(E48="","",E48-H48) -> 0.34621978 | R48: =IF(F48="","",F48-H48) -> 0.17036761 | S48: =G48-H48 -> 11 | T48: =G48-B48 -> 8.5 | U48: =IF(P48=N48,"EQUAL",IF(N48<P48,"LOWER","HIGHER")) -> HIGHER | V48: 683 | W48: =IF(V48="","",IF(D48="","",D48-F48)) -> 1.8296324 | X48: =IF(AM48="","",AM48/22.04622) -> 31.184484 | Y48: =IF(X48="","",IF(D48="","",D48-X48)) -> 1.6255158 | Z48: =IF(X48="","",IF(F48="","",X48-F48)) -> 0.20411662 | AA48: =MONTH(A48) -> 2 | AB48: =YEAR(A48) -> 2019 | AC48: =WEEKNUM(A48) -> 6 | AF48: 37.762 | AG48: =IF(V48="","",V48*AF48/2204.622*100) -> 1169.8806 | AL48: =A48 -> 43503 | AM48: 687.5 | AN48: 3.7166 | AO48: =IF(AM48="","",AM48*AN48/2204.622*100) -> 115.90025 | AT48: 301 | AU48: 8.8 | AV48: =(((C48/100*11.7)+(AT48/2000*47))-(AU48)) -> 1.80222 | AW48: =(((B48/100*11.7*0.98)+(AT48/2000*47))-(AU48)) -> 2.0928246 | AX48: =AW48-AV48 -> 0.2906046 | AY48: =(B48*11.7/100)/((AT48/2000*47)+(B48*11.7/100)) -> 0.35524125 | BB48: =C48*22.0462 -> 664.91339
A49: 43504 | B49: 33.37 | C49: 30.22 | D49: 32.87 | E49: =IF(AM49="","",AM49/2206.622)*100 -> 30.884311 | F49: 30.606154 | G49: 41.87 | H49: 30.87 | I49: 30.8 | J49: 25.529216 | K49: =B49-I49 -> 2.57 | L49: =IF(I49="","",IF(J49="","",I49-J49)) -> 5.2707837 | M49: =B49-H49 -> 2.5 | N49: =B49-C49 -> 3.15 | O49: =C49-H49 -> -0.65 | P49: =D49-H49 -> 2 | Q49: =IF(E49="","",E49-H49) -> 0.014310951 | R49: =IF(F49="","",F49-H49) -> -0.2638462 | S49: =G49-H49 -> 11 | T49: =G49-B49 -> 8.5 | U49: =IF(P49=N49,"EQUAL",IF(N49<P49,"LOWER","HIGHER")) -> HIGHER | V49: 674.75 | W49: =IF(V49="","",IF(D49="","",D49-F49)) -> 2.2638462 | X49: =IF(AM49="","",AM49/22.04622) -> 30.912329 | Y49: =IF(X49="","",IF(D49="","",D49-X49)) -> 1.9576713 | Z49: =IF(X49="","",IF(F49="","",X49-F49)) -> 0.30617494 | AA49: =MONTH(A49) -> 2 | AB49: =YEAR(A49) -> 2019 | AC49: =WEEKNUM(A49) -> 6 | AF49: 37.82 | AG49: =IF(V49="","",V49*AF49/2204.622*100) -> 1157.5247 | AL49: =A49 -> 43504 | AM49: 681.5 | AN49: 3.729 | AO49: =IF(AM49="","",AM49*AN49/2204.622*100) -> 115.27207 | AT49: 301 | AU49: 8.82 | AV49: =(((C49/100*11.7)+(AT49/2000*47))-(AU49)) -> 1.78924 | AW49: =(((B49/100*11.7*0.98)+(AT49/2000*47))-(AU49)) -> 2.0797042 | AX49: =AW49-AV49 -> 0.2904642 | AY49: =(B49*11.7/100)/((AT49/2000*47)+(B49*11.7/100)) -> 0.35565355 | BB49: =C49*22.0462 -> 666.23616
A50: 43507 | B50: 32.74 | C50: 29.59 | D50: 32.24 | E50: =IF(AM50="","",AM50/2206.622)*100 -> 31.235527 | F50: 30.957688 | G50: 41.24 | H50: 30.24 | I50: 30.8 | J50: 25.242924 | K50: =B50-I50 -> 1.94 | L50: =IF(I50="","",IF(J50="","",I50-J50)) -> 5.557076 | M50: =B50-H50 -> 2.5 | N50: =B50-C50 -> 3.15 | O50: =C50-H50 -> -0.65 | P50: =D50-H50 -> 2 | Q50: =IF(E50="","",E50-H50) -> 0.99552652 | R50: =IF(F50="","",F50-H50) -> 0.71768798 | S50: =G50-H50 -> 11 | T50: =G50-B50 -> 8.5 | U50: =IF(P50=N50,"EQUAL",IF(N50<P50,"LOWER","HIGHER")) -> HIGHER | V50: 682.5 | W50: =IF(V50="","",IF(D50="","",D50-F50)) -> 1.282312 | X50: =IF(AM50="","",AM50/22.04622) -> 31.263863 | Y50: =IF(X50="","",IF(D50="","",D50-X50)) -> 0.97613708 | Z50: =IF(X50="","",IF(F50="","",X50-F50)) -> 0.30617494 | AA50: =MONTH(A50) -> 2 | AB50: =YEAR(A50) -> 2019 | AC50: =WEEKNUM(A50) -> 7 | AF50: 37.89 | AG50: =IF(V50="","",V50*AF50/2204.622*100) -> 1172.9868 | AL50: =A50 -> 43507 | AM50: 689.25 | AN50: 3.7576 | AO50: =IF(AM50="","",AM50*AN50/2204.622*100) -> 117.47709 | AT50: 304 | AU50: 8.8 | AV50: =(((C50/100*11.7)+(AT50/2000*47))-(AU50)) -> 1.80603 | AW50: =(((B50/100*11.7*0.98)+(AT50/2000*47))-(AU50)) -> 2.0979684 | AX50: =AW50-AV50 -> 0.2919384 | AY50: =(B50*11.7/100)/((AT50/2000*47)+(B50*11.7/100)) -> 0.34904115 | BB50: =C50*22.0462 -> 652.34706
A51: 43508 | B51: 32.83 | C51: 29.68 | D51: 32.33 | E51: =IF(AM51="","",AM51/2206.622)*100 -> 31.439458 | F51: 31.173144 | G51: 41.33 | H51: 30.33 | I51: 30.8 | J51: 25.088327 | K51: =B51-I51 -> 2.03 | L51: =IF(I51="","",IF(J51="","",I51-J51)) -> 5.7116732 | M51: =B51-H51 -> 2.5 | N51: =B51-C51 -> 3.15 | O51: =C51-H51 -> -0.65 | P51: =D51-H51 -> 2 | Q51: =IF(E51="","",E51-H51) -> 1.1094581 | R51: =IF(F51="","",F51-H51) -> 0.84314442 | S51: =G51-H51 -> 11 | T51: =G51-B51 -> 8.5 | U51: =IF(P51=N51,"EQUAL",IF(N51<P51,"LOWER","HIGHER")) -> HIGHER | V51: 687.25 | W51: =IF(V51="","",IF(D51="","",D51-F51)) -> 1.1568556 | X51: =IF(AM51="","",AM51/22.04622) -> 31.46798 | Y51: =IF(X51="","",IF(D51="","",D51-X51)) -> 0.86202046 | Z51: =IF(X51="","",IF(F51="","",X51-F51)) -> 0.29483512 | AA51: =MONTH(A51) -> 2 | AB51: =YEAR(A51) -> 2019 | AC51: =WEEKNUM(A51) -> 7 | AF51: 37.929 | AG51: =IF(V51="","",V51*AF51/2204.622*100) -> 1182.3662 | AL51: =A51 -> 43508 | AM51: 693.75 | AN51: 3.7097 | AO51: =IF(AM51="","",AM51*AN51/2204.622*100) -> 116.73676 | AT51: 308 | AU51: 8.93 | AV51: =(((C51/100*11.7)+(AT51/2000*47))-(AU51)) -> 1.78056 | AW51: =(((B51/100*11.7*0.98)+(AT51/2000*47))-(AU51)) -> 2.0722878 | AX51: =AW51-AV51 -> 0.2917278 | AY51: =(B51*11.7/100)/((AT51/2000*47)+(B51*11.7/100)) -> 0.34669843 | BB51: =C51*22.0462 -> 654.33122
A52: 43509 | B52: 32.49 | C52: 29.34 | D52: 31.99 | E52: =IF(AM52="","",AM52/2206.622)*100 -> 31.088243 | F52: 30.923669 | G52: 40.99 | H52: 29.99 | I52: 30.8 | J52: 25.128913 | K52: =B52-I52 -> 1.69 | L52: =IF(I52="","",IF(J52="","",I52-J52)) -> 5.6710872 | M52: =B52-H52 -> 2.5 | N52: =B52-C52 -> 3.15 | O52: =C52-H52 -> -0.65 | P52: =D52-H52 -> 2 | Q52: =IF(E52="","",E52-H52) -> 1.0982426 | R52: =IF(F52="","",F52-H52) -> 0.93366855 | S52: =G52-H52 -> 11 | T52: =G52-B52 -> 8.5 | U52: =IF(P52=N52,"EQUAL",IF(N52<P52,"LOWER","HIGHER")) -> HIGHER | V52: 681.75 | W52: =IF(V52="","",IF(D52="","",D52-F52)) -> 1.0663315 | X52: =IF(AM52="","",AM52/22.04622) -> 31.116445 | Y52: =IF(X52="","",IF(D52="","",D52-X52)) -> 0.87355464 | Z52: =IF(X52="","",IF(F52="","",X52-F52)) -> 0.19277681 | AA52: =MONTH(A52) -> 2 | AB52: =YEAR(A52) -> 2019 | AC52: =WEEKNUM(A52) -> 7 | AF52: 38.18 | AG52: =IF(V52="","",V52*AF52/2204.622*100) -> 1180.6657 | AL52: =A52 -> 43509 | AM52: 686 | AN52: 3.7543 | AO52: =IF(AM52="","",AM52*AN52/2204.622*100) -> 116.82047 | AT52: 309 | AU52: 8.92 | AV52: =(((C52/100*11.7)+(AT52/2000*47))-(AU52)) -> 1.77428 | AW52: =(((B52/100*11.7*0.98)+(AT52/2000*47))-(AU52)) -> 2.0668034 | AX52: =AW52-AV52 -> 0.2925234 | AY52: =(B52*11.7/100)/((AT52/2000*47)+(B52*11.7/100)) -> 0.3436128 | BB52: =C52*22.0462 -> 646.83551
A53: 43510 | B53: 33.39 | C53: 29.24 | D53: 31.89 | E53: =IF(AM53="","",AM53/2206.622)*100 -> 30.714368 | F53: 30.436057 | G53: 40.89 | H53: 30.23 | I53: 30.8 | J53: 25.296076 | K53: =B53-I53 -> 2.59 | L53: =IF(I53="","",IF(J53="","",I53-J53)) -> 5.5039235 | M53: =B53-H53 -> 3.16 | N53: =B53-C53 -> 4.15 | O53: =C53-H53 -> -0.99 | P53: =D53-H53 -> 1.66 | Q53: =IF(E53="","",E53-H53) -> 0.48436793 | R53: =IF(F53="","",F53-H53) -> 0.20605661 | S53: =G53-H53 -> 10.66 | T53: =G53-B53 -> 7.5 | U53: =IF(P53=N53,"EQUAL",IF(N53<P53,"LOWER","HIGHER")) -> HIGHER | V53: 671 | W53: =IF(V53="","",IF(D53="","",D53-F53)) -> 1.4539434 | X53: =IF(AM53="","",AM53/22.04622) -> 30.742232 | Y53: =IF(X53="","",IF(D53="","",D53-X53)) -> 1.1477685 | Z53: =IF(X53="","",IF(F53="","",X53-F53)) -> 0.30617494 | AA53: =MONTH(A53) -> 2 | AB53: =YEAR(A53) -> 2019 | AC53: =WEEKNUM(A53) -> 7 | AF53: 38.162 | AG53: =IF(V53="","",V53*AF53/2204.622*100) -> 1161.5008 | AL53: =A53 -> 43510 | AM53: 677.75 | AN53: 3.7232 | AO53: =IF(AM53="","",AM53*AN53/2204.622*100) -> 114.45948 | AT53: 305 | AU53: 8.79 | AV53: =(((C53/100*11.7)+(AT53/2000*47))-(AU53)) -> 1.79858 | AW53: =(((B53/100*11.7*0.98)+(AT53/2000*47))-(AU53)) -> 2.2059974 | AX53: =AW53-AV53 -> 0.4074174 | AY53: =(B53*11.7/100)/((AT53/2000*47)+(B53*11.7/100)) -> 0.35277083 | BB53: =C53*22.0462 -> 644.63089
A54: 43511 | B54: 32.45 | C54: 29.3 | D54: 31.95 | E54: =IF(AM54="","",AM54/2206.622)*100 -> 30.759686 | F54: 30.492756 | G54: 40.95 | H54: 29.95 | I54: 30.8 | J54: 25.029241 | K54: =B54-I54 -> 1.65 | L54: =IF(I54="","",IF(J54="","",I54-J54)) -> 5.7707593 | M54: =B54-H54 -> 2.5 | N54: =B54-C54 -> 3.15 | O54: =C54-H54 -> -0.65 | P54: =D54-H54 -> 2 | Q54: =IF(E54="","",E54-H54) -> 0.80968607 | R54: =IF(F54="","",F54-H54) -> 0.54275567 | S54: =G54-H54 -> 11 | T54: =G54-B54 -> 8.5 | U54: =IF(P54=N54,"EQUAL",IF(N54<P54,"LOWER","HIGHER")) -> HIGHER | V54: 672.25 | W54: =IF(V54="","",IF(D54="","",D54-F54)) -> 1.4572443 | X54: =IF(AM54="","",AM54/22.04622) -> 30.787591 | Y54: =IF(X54="","",IF(D54="","",D54-X54)) -> 1.1624092 | Z54: =IF(X54="","",IF(F54="","",X54-F54)) -> 0.29483512 | AA54: =MONTH(A54) -> 2 | AB54: =YEAR(A54) -> 2019 | AC54: =WEEKNUM(A54) -> 7 | AF54: 38.58 | AG54: =IF(V54="","",V54*AF54/2204.622*100) -> 1176.4105 | AL54: =A54 -> 43511 | AM54: 678.75 | AN54: 3.7007 | AO54: =IF(AM54="","",AM54*AN54/2204.622*100) -> 113.93564 | AT54: 306 | AU54: 8.83 | AV54: =(((C54/100*11.7)+(AT54/2000*47))-(AU54)) -> 1.7891 | AW54: =(((B54/100*11.7*0.98)+(AT54/2000*47))-(AU54)) -> 2.081717 | AX54: =AW54-AV54 -> 0.292617 | AY54: =(B54*11.7/100)/((AT54/2000*47)+(B54*11.7/100)) -> 0.34553794 | BB54: =C54*22.0462 -> 645.95366
A55: 43515 | B55: 32.24 | C55: 29.09 | D55: 31.74 | E55: =IF(AM55="","",AM55/2206.622)*100 -> 30.635061 | F55: 30.356678 | G55: 40.74 | H55: 29.74 | I55: 30.6 | J55: 25.114349 | K55: =B55-I55 -> 1.64 | L55: =IF(I55="","",IF(J55="","",I55-J55)) -> 5.4856507 | M55: =B55-H55 -> 2.5 | N55: =B55-C55 -> 3.15 | O55: =C55-H55 -> -0.65 | P55: =D55-H55 -> 2 | Q55: =IF(E55="","",E55-H55) -> 0.89506119 | R55: =IF(F55="","",F55-H55) -> 0.61667792 | S55: =G55-H55 -> 11 | T55: =G55-B55 -> 8.5 | U55: =IF(P55=N55,"EQUAL",IF(N55<P55,"LOWER","HIGHER")) -> HIGHER | V55: 669.25 | W55: =IF(V55="","",IF(D55="","",D55-F55)) -> 1.3833221 | X55: =IF(AM55="","",AM55/22.04622) -> 30.662853 | Y55: =IF(X55="","",IF(D55="","",D55-X55)) -> 1.0771471 | Z55: =IF(X55="","",IF(F55="","",X55-F55)) -> 0.30617494 | AA55: =MONTH(A55) -> 2 | AB55: =YEAR(A55) -> 2019 | AC55: =WEEKNUM(A55) -> 8 | AF55: 39.27 | AG55: =IF(V55="","",V55*AF55/2204.622*100) -> 1192.1067 | AL55: =A55 -> 43515 | AM55: 676 | AN55: 3.7227 | AO55: =IF(AM55="","",AM55*AN55/2204.622*100) -> 114.1486 | AT55: 305 | AU55: 8.76 | AV55: =(((C55/100*11.7)+(AT55/2000*47))-(AU55)) -> 1.81103 | AW55: =(((B55/100*11.7*0.98)+(AT55/2000*47))-(AU55)) -> 2.1041384 | AX55: =AW55-AV55 -> 0.2931084 | AY55: =(B55*11.7/100)/((AT55/2000*47)+(B55*11.7/100)) -> 0.34481031 | BB55: =C55*22.0462 -> 641.32396
A56: 43516 | B56: 32.46 | C56: 29.31 | D56: 31.96 | E56: =IF(AM56="","",AM56/2206.622)*100 -> 30.782345 | F56: 30.515435 | G56: 40.96 | H56: 29.96 | I56: 30.6 | J56: 25.012323 | K56: =B56-I56 -> 1.86 | L56: =IF(I56="","",IF(J56="","",I56-J56)) -> 5.5876775 | M56: =B56-H56 -> 2.5 | N56: =B56-C56 -> 3.15 | O56: =C56-H56 -> -0.65 | P56: =D56-H56 -> 2 | Q56: =IF(E56="","",E56-H56) -> 0.82234514 | R56: =IF(F56="","",F56-H56) -> 0.5554353 | S56: =G56-H56 -> 11 | T56: =G56-B56 -> 8.5 | U56: =IF(P56=N56,"EQUAL",IF(N56<P56,"LOWER","HIGHER")) -> HIGHER | V56: 672.75 | W56: =IF(V56="","",IF(D56="","",D56-F56)) -> 1.4445647 | X56: =IF(AM56="","",AM56/22.04622) -> 30.81027 | Y56: =IF(X56="","",IF(D56="","",D56-X56)) -> 1.1497296 | Z56: =IF(X56="","",IF(F56="","",X56-F56)) -> 0.29483512 | AA56: =MONTH(A56) -> 2 | AB56: =YEAR(A56) -> 2019 | AC56: =WEEKNUM(A56) -> 8 | AF56: 39.66 | AG56: =IF(V56="","",V56*AF56/2204.622*100) -> 1210.2422 | AL56: =A56 -> 43516 | AM56: 679.25 | AN56: 3.7273 | AO56: =IF(AM56="","",AM56*AN56/2204.622*100) -> 114.83912 | AT56: 304 | AU56: 8.78 | AV56: =(((C56/100*11.7)+(AT56/2000*47))-(AU56)) -> 1.79327 | AW56: =(((B56/100*11.7*0.98)+(AT56/2000*47))-(AU56)) -> 2.0858636 | AX56: =AW56-AV56 -> 0.2925936 | AY56: =(B56*11.7/100)/((AT56/2000*47)+(B56*11.7/100)) -> 0.34709217 | BB56: =C56*22.0462 -> 646.17412
A57: 43517 | B57: 32.99 | C57: 29.84 | D57: 32.49 | E57: =IF(AM57="","",AM57/2206.622)*100 -> 31.190208 | F57: 30.923669 | G57: 41.49 | H57: 30.82 | I57: 30.6 | J57: 25.183509 | K57: =B57-I57 -> 2.39 | L57: =IF(I57="","",IF(J57="","",I57-J57)) -> 5.4164911 | M57: =B57-H57 -> 2.17 | N57: =B57-C57 -> 3.15 | O57: =C57-H57 -> -0.98 | P57: =D57-H57 -> 1.67 | Q57: =IF(E57="","",E57-H57) -> 0.37020838 | R57: =IF(F57="","",F57-H57) -> 0.10366855 | S57: =G57-H57 -> 10.67 | T57: =G57-B57 -> 8.5 | U57: =IF(P57=N57,"EQUAL",IF(N57<P57,"LOWER","HIGHER")) -> HIGHER | V57: 681.75 | W57: =IF(V57="","",IF(D57="","",D57-F57)) -> 1.5663315 | X57: =IF(AM57="","",AM57/22.04622) -> 31.218504 | Y57: =IF(X57="","",IF(D57="","",D57-X57)) -> 1.2714963 | Z57: =IF(X57="","",IF(F57="","",X57-F57)) -> 0.29483512 | AA57: =MONTH(A57) -> 2 | AB57: =YEAR(A57) -> 2019 | AC57: =WEEKNUM(A57) -> 8 | AF57: 39.48 | AG57: =IF(V57="","",V57*AF57/2204.622*100) -> 1220.8664 | AL57: =A57 -> 43517 | AM57: 688.25 | AN57: 3.7693 | AO57: =IF(AM57="","",AM57*AN57/2204.622*100) -> 117.67191 | AT57: 305 | AU57: 8.86 | AV57: =(((C57/100*11.7)+(AT57/2000*47))-(AU57)) -> 1.79878 | AW57: =(((B57/100*11.7*0.98)+(AT57/2000*47))-(AU57)) -> 2.0901334 | AX57: =AW57-AV57 -> 0.2913534 | AY57: =(B57*11.7/100)/((AT57/2000*47)+(B57*11.7/100)) -> 0.35002399 | BB57: =C57*22.0462 -> 657.85861
A58: 43518 | B58: 33.01 | C58: 29.86 | D58: 32.51 | E58: =IF(AM58="","",AM58/2206.622)*100 -> 31.326163 | F58: 31.161805 | G58: 41.51 | H58: 30.85 | I58: 30.6 | J58: 25.061097 | K58: =B58-I58 -> 2.41 | L58: =IF(I58="","",IF(J58="","",I58-J58)) -> 5.5389032 | M58: =B58-H58 -> 2.16 | N58: =B58-C58 -> 3.15 | O58: =C58-H58 -> -0.99 | P58: =D58-H58 -> 1.66 | Q58: =IF(E58="","",E58-H58) -> 0.4761628 | R58: =IF(F58="","",F58-H58) -> 0.31180461 | S58: =G58-H58 -> 10.66 | T58: =G58-B58 -> 8.5 | U58: =IF(P58=N58,"EQUAL",IF(N58<P58,"LOWER","HIGHER")) -> HIGHER | V58: 687 | W58: =IF(V58="","",IF(D58="","",D58-F58)) -> 1.3481954 | X58: =IF(AM58="","",AM58/22.04622) -> 31.354581 | Y58: =IF(X58="","",IF(D58="","",D58-X58)) -> 1.1554186 | Z58: =IF(X58="","",IF(F58="","",X58-F58)) -> 0.19277681 | AA58: =MONTH(A58) -> 2 | AB58: =YEAR(A58) -> 2019 | AC58: =WEEKNUM(A58) -> 8 | AF58: 39.17 | AG58: =IF(V58="","",V58*AF58/2204.622*100) -> 1220.6079 | AL58: =A58 -> 43518 | AM58: 691.25 | AN58: 3.7482 | AO58: =IF(AM58="","",AM58*AN58/2204.622*100) -> 117.52324 | AT58: 304 | AU58: 8.85 | AV58: =(((C58/100*11.7)+(AT58/2000*47))-(AU58)) -> 1.78762 | AW58: =(((B58/100*11.7*0.98)+(AT58/2000*47))-(AU58)) -> 2.0789266 | AX58: =AW58-AV58 -> 0.2913066 | AY58: =(B58*11.7/100)/((AT58/2000*47)+(B58*11.7/100)) -> 0.35090954 | BB58: =C58*22.0462 -> 658.29953
A59: 43521 | B59: 32.86 | C59: 29.71 | D59: 32.36 | E59: =IF(AM59="","",AM59/2206.622)*100 -> 31.054254 | F59: 30.980368 | G59: 40.36 | H59: 30.68 | I59: 30.6 | J59: 24.682573 | K59: =B59-I59 -> 2.26 | L59: =IF(I59="","",IF(J59="","",I59-J59)) -> 5.9174267 | M59: =B59-H59 -> 2.18 | N59: =B59-C59 -> 3.15 | O59: =C59-H59 -> -0.97 | P59: =D59-H59 -> 1.68 | Q59: =IF(E59="","",E59-H59) -> 0.37425397 | R59: =IF(F59="","",F59-H59) -> 0.30036761 | S59: =G59-H59 -> 9.68 | T59: =G59-B59 -> 7.5 | U59: =IF(P59=N59,"EQUAL",IF(N59<P59,"LOWER","HIGHER")) -> HIGHER | V59: 683 | W59: =IF(V59="","",IF(D59="","",D59-F59)) -> 1.3796324 | X59: =IF(AM59="","",AM59/22.04622) -> 31.082426 | Y59: =IF(X59="","",IF(D59="","",D59-X59)) -> 1.2775741 | Z59: =IF(X59="","",IF(F59="","",X59-F59)) -> 0.10205831 | AA59: =MONTH(A59) -> 2 | AB59: =YEAR(A59) -> 2019 | AC59: =WEEKNUM(A59) -> 9 | AF59: 38.989 | AG59: =IF(V59="","",V59*AF59/2204.622*100) -> 1207.8936 | AL59: =A59 -> 43521 | AM59: 685.25 | AN59: 3.7519 | AO59: =IF(AM59="","",AM59*AN59/2204.622*100) -> 116.61815 | AT59: 304 | AU59: 8.87 | AV59: =(((C59/100*11.7)+(AT59/2000*47))-(AU59)) -> 1.75007 | AW59: =(((B59/100*11.7*0.98)+(AT59/2000*47))-(AU59)) -> 2.0417276 | AX59: =AW59-AV59 -> 0.2916576 | AY59: =(B59*11.7/100)/((AT59/2000*47)+(B59*11.7/100)) -> 0.34987287 | BB59: =C59*22.0462 -> 654.9926
A60: 43522 | B60: 32.59 | C60: 29.44 | D60: 31.99 | E60: =IF(AM60="","",AM60/2206.622)*100 -> 30.65772 | F60: 30.583474 | G60: 40.09 | H60: 30.4 | I60: 29.7 | K60: =B60-I60 -> 2.89 | L60: =IF(I60="","",IF(J60="","",I60-J60)) | M60: =B60-H60 -> 2.19 | N60: =B60-C60 -> 3.15 | O60: =C60-H60 -> -0.96 | P60: =D60-H60 -> 1.59 | Q60: =IF(E60="","",E60-H60) -> 0.25772026 | R60: =IF(F60="","",F60-H60) -> 0.18347417 | S60: =G60-H60 -> 9.69 | T60: =G60-B60 -> 7.5 | U60: =IF(P60=N60,"EQUAL",IF(N60<P60,"LOWER","HIGHER")) -> HIGHER | V60: 674.25 | W60: =IF(V60="","",IF(D60="","",D60-F60)) -> 1.4065258 | X60: =IF(AM60="","",AM60/22.04622) -> 30.685532 | Y60: =IF(X60="","",IF(D60="","",D60-X60)) -> 1.3044675 | Z60: =IF(X60="","",IF(F60="","",X60-F60)) -> 0.10205831 | AA60: =MONTH(A60) -> 2 | AB60: =YEAR(A60) -> 2019 | AC60: =WEEKNUM(A60) -> 9 | AF60: 38.87 | AG60: =IF(V60="","",V60*AF60/2204.622*100) -> 1188.7796 | AL60: =A60 -> 43522 | AM60: 676.5 | AN60: 3.7487 | AO60: =IF(AM60="","",AM60*AN60/2204.622*100) -> 115.03086 | AT60: 302 | AU60: 8.79 | AV60: =(((C60/100*11.7)+(AT60/2000*47))-(AU60)) -> 1.75148 | AW60: =(((B60/100*11.7*0.98)+(AT60/2000*47))-(AU60)) -> 2.0437694 | AX60: =AW60-AV60 -> 0.2922894 | AY60: =(B60*11.7/100)/((AT60/2000*47)+(B60*11.7/100)) -> 0.34949766 | BB60: =C60*22.0462 -> 649.04013
A61: 43523 | B61: 32.3 | C61: 29.15 | D61: 31.7 | E61: =IF(AM61="","",AM61/2206.622)*100 -> 30.510436 | F61: 30.436057 | G61: 39.8 | H61: 30.12 | I61: 29.7 | J61: 23.795748 | K61: =B61-I61 -> 2.6 | L61: =IF(I61="","",IF(J61="","",I61-J61)) -> 5.9042518 | M61: =B61-H61 -> 2.18 | N61: =B61-C61 -> 3.15 | O61: =C61-H61 -> -0.97 | P61: =D61-H61 -> 1.58 | Q61: =IF(E61="","",E61-H61) -> 0.39043631 | R61: =IF(F61="","",F61-H61) -> 0.31605661 | S61: =G61-H61 -> 9.68 | T61: =G61-B61 -> 7.5 | U61: =IF(P61=N61,"EQUAL",IF(N61<P61,"LOWER","HIGHER")) -> HIGHER | V61: 671 | W61: =IF(V61="","",IF(D61="","",D61-F61)) -> 1.2639434 | X61: =IF(AM61="","",AM61/22.04622) -> 30.538115 | Y61: =IF(X61="","",IF(D61="","",D61-X61)) -> 1.1618851 | Z61: =IF(X61="","",IF(F61="","",X61-F61)) -> 0.10205831 | AA61: =MONTH(A61) -> 2 | AB61: =YEAR(A61) -> 2019 | AC61: =WEEKNUM(A61) -> 9 | AF61: 38.741 | AG61: =IF(V61="","",V61*AF61/2204.622*100) -> 1179.1233 | AL61: =A61 -> 43523 | AM61: 673.25 | AN61: 3.7285 | AO61: =IF(AM61="","",AM61*AN61/2204.622*100) -> 113.86136 | AT61: 304 | AU61: 8.79 | AV61: =(((C61/100*11.7)+(AT61/2000*47))-(AU61)) -> 1.76455 | AW61: =(((B61/100*11.7*0.98)+(AT61/2000*47))-(AU61)) -> 2.057518 | AX61: =AW61-AV61 -> 0.292968 | AY61: =(B61*11.7/100)/((AT61/2000*47)+(B61*11.7/100)) -> 0.34597321 | BB61: =C61*22.0462 -> 642.64673
A62: 43524 | B62: 32.46 | C62: 29.31 | D62: 31.86 | E62: =IF(AM62="","",AM62/2206.622)*100 -> 30.340493 | F62: 30.265959 | G62: 39.96 | H62: 30.25 | I62: 29.7 | J62: 23.678309 | K62: =B62-I62 -> 2.76 | L62: =IF(I62="","",IF(J62="","",I62-J62)) -> 6.0216905 | M62: =B62-H62 -> 2.21 | N62: =B62-C62 -> 3.15 | O62: =C62-H62 -> -0.94 | P62: =D62-H62 -> 1.61 | Q62: =IF(E62="","",E62-H62) -> 0.090493297 | R62: =IF(F62="","",F62-H62) -> 0.015959425 | S62: =G62-H62 -> 9.71 | T62: =G62-B62 -> 7.5 | U62: =IF(P62=N62,"EQUAL",IF(N62<P62,"LOWER","HIGHER")) -> HIGHER | V62: 667.25 | W62: =IF(V62="","",IF(D62="","",D62-F62)) -> 1.5940406 | X62: =IF(AM62="","",AM62/22.04622) -> 30.368018 | Y62: =IF(X62="","",IF(D62="","",D62-X62)) -> 1.4919823 | Z62: =IF(X62="","",IF(F62="","",X62-F62)) -> 0.10205831 | AA62: =MONTH(A62) -> 2 | AB62: =YEAR(A62) -> 2019 | AC62: =WEEKNUM(A62) -> 9 | AF62: 39.091 | AG62: =IF(V62="","",V62*AF62/2204.622*100) -> 1183.1266 | AL62: =A62 -> 43524 | AM62: 669.5 | AN62: 3.7511 | AO62: =IF(AM62="","",AM62*AN62/2204.622*100) -> 113.91347 | AT62: 301 | AU62: 8.73 | AV62: =(((C62/100*11.7)+(AT62/2000*47))-(AU62)) -> 1.77277 | AW62: =(((B62/100*11.7*0.98)+(AT62/2000*47))-(AU62)) -> 2.0653636 | AX62: =AW62-AV62 -> 0.2925936 | AY62: =(B62*11.7/100)/((AT62/2000*47)+(B62*11.7/100)) -> 0.34934304 | BB62: =C62*22.0462 -> 646.17412
A63: 43525 | B63: 32.74 | C63: 29.59 | D63: 32.14 | E63: =IF(AM63="","",AM63/2206.622)*100 -> 29.388812 | F63: 29.222697 | G63: 40.24 | H63: 30.24 | I63: 29.7 | J63: 24.383939 | K63: =B63-I63 -> 3.04 | L63: =IF(I63="","",IF(J63="","",I63-J63)) -> 5.3160614 | M63: =B63-H63 -> 2.5 | N63: =B63-C63 -> 3.15 | O63: =C63-H63 -> -0.65 | P63: =D63-H63 -> 1.9 | Q63: =IF(E63="","",E63-H63) -> -0.8511876 | R63: =IF(F63="","",F63-H63) -> -1.0173033 | S63: =G63-H63 -> 10 | T63: =G63-B63 -> 7.5 | U63: =IF(P63=N63,"EQUAL",IF(N63<P63,"LOWER","HIGHER")) -> HIGHER | V63: 644.25 | W63: =IF(V63="","",IF(D63="","",D63-F63)) -> 2.9173033 | X63: =IF(AM63="","",AM63/22.04622) -> 29.415473 | Y63: =IF(X63="","",IF(D63="","",D63-X63)) -> 2.7245265 | Z63: =IF(X63="","",IF(F63="","",X63-F63)) -> 0.19277681 | AA63: =MONTH(A63) -> 3 | AB63: =YEAR(A63) -> 2019 | AC63: =WEEKNUM(A63) -> 9 | AF63: 39.787 | AG63: =IF(V63="","",V63*AF63/2204.622*100) -> 1162.6834 | AL63: =A63 -> 43525 | AM63: 648.5 | AN63: 3.7749 | AO63: =IF(AM63="","",AM63*AN63/2204.622*100) -> 111.04047 | AT63: 302 | AU63: 8.87 | AV63: =(((C63/100*11.7)+(AT63/2000*47))-(AU63)) -> 1.68903 | AW63: =(((B63/100*11.7*0.98)+(AT63/2000*47))-(AU63)) -> 1.9809684 | AX63: =AW63-AV63 -> 0.2919384 | AY63: =(B63*11.7/100)/((AT63/2000*47)+(B63*11.7/100)) -> 0.35054239 | BB63: =C63*22.0462 -> 652.34706
A64: 43528 | B64: 32.58 | C64: 29.43 | D64: 31.98 | E64: =IF(AM64="","",AM64/2206.622)*100 -> #VALUE! | G64: 40.08 | H64: 30.08 | I64: 29.7 | J64: 23.926615 | K64: =B64-I64 -> 2.88 | L64: =IF(I64="","",IF(J64="","",I64-J64)) -> 5.7733854 | M64: =B64-H64 -> 2.5 | N64: =B64-C64 -> 3.15 | O64: =C64-H64 -> -0.65 | P64: =D64-H64 -> 1.9 | Q64: =IF(E64="","",E64-H64) -> #VALUE! | R64: =IF(F64="","",F64-H64) | S64: =G64-H64 -> 10 | T64: =G64-B64 -> 7.5 | U64: =IF(P64=N64,"EQUAL",IF(N64<P64,"LOWER","HIGHER")) -> HIGHER | X64: =IF(AM64="","",AM64/22.04622) | Y64: =IF(X64="","",IF(D64="","",D64-X64)) | Z64: =IF(X64="","",IF(F64="","",X64-F64)) | AA64: =MONTH(A64) -> 3 | AB64: =YEAR(A64) -> 2019 | AC64: =WEEKNUM(A64) -> 10 | AF64: 39.82 | AG64: =IF(V64="","",V64*AF64/2204.622*100) | AL64: =A64 -> 43528 | AN64: 3.775 | AO64: =IF(AM64="","",AM64*AN64/2204.622*100) | AT64: 306 | AU64: 8.91 | AV64: =(((C64/100*11.7)+(AT64/2000*47))-(AU64)) -> 1.72431 | AW64: =(((B64/100*11.7*0.98)+(AT64/2000*47))-(AU64)) -> 2.0166228 | AX64: =AW64-AV64 -> 0.2923128 | AY64: =(B64*11.7/100)/((AT64/2000*47)+(B64*11.7/100)) -> 0.34644265 | BB64: =C64*22.0462 -> 648.81967
A65: 43529 | B65: 32.42 | C65: 29.27 | D65: 31.92 | E65: =IF(AM65="","",AM65/2206.622)*100 -> #VALUE! | G65: 40.02 | H65: 30.02 | I65: 29.7 | J65: 24.049087 | K65: =B65-I65 -> 2.72 | L65: =IF(I65="","",IF(J65="","",I65-J65)) -> 5.6509132 | M65: =B65-H65 -> 2.4 | N65: =B65-C65 -> 3.15 | O65: =C65-H65 -> -0.75 | P65: =D65-H65 -> 1.9 | Q65: =IF(E65="","",E65-H65) -> #VALUE! | R65: =IF(F65="","",F65-H65) | S65: =G65-H65 -> 10 | T65: =G65-B65 -> 7.6 | U65: =IF(P65=N65,"EQUAL",IF(N65<P65,"LOWER","HIGHER")) -> HIGHER | X65: =IF(AM65="","",AM65/22.04622) | Y65: =IF(X65="","",IF(D65="","",D65-X65)) | Z65: =IF(X65="","",IF(F65="","",X65-F65)) | AA65: =MONTH(A65) -> 3 | AB65: =YEAR(A65) -> 2019 | AC65: =WEEKNUM(A65) -> 10 | AF65: 39.82 | AG65: =IF(V65="","",V65*AF65/2204.622*100) | AL65: =A65 -> 43529 | AN65: 3.775 | AO65: =IF(AM65="","",AM65*AN65/2204.622*100) | AT65: 305 | AU65: 8.82 | AV65: =(((C65/100*11.7)+(AT65/2000*47))-(AU65)) -> 1.77209 | AW65: =(((B65/100*11.7*0.98)+(AT65/2000*47))-(AU65)) -> 2.0647772 | AX65: =AW65-AV65 -> 0.2926872 | AY65: =(B65*11.7/100)/((AT65/2000*47)+(B65*11.7/100)) -> 0.34606921 | BB65: =C65*22.0462 -> 645.29227
A66: 43530 | B66: 32.18 | C66: 29.03 | D66: 31.68 | E66: =IF(AM66="","",AM66/2206.622)*100 -> 29.298176 | F66: 29.01858 | G66: 39.78 | H66: 29.78 | I66: 29.7 | J66: 23.939296 | K66: =B66-I66 -> 2.48 | L66: =IF(I66="","",IF(J66="","",I66-J66)) -> 5.7607042 | M66: =B66-H66 -> 2.4 | N66: =B66-C66 -> 3.15 | O66: =C66-H66 -> -0.75 | P66: =D66-H66 -> 1.9 | Q66: =IF(E66="","",E66-H66) -> -0.48182387 | R66: =IF(F66="","",F66-H66) -> -0.76141994 | S66: =G66-H66 -> 10 | T66: =G66-B66 -> 7.6 | U66: =IF(P66=N66,"EQUAL",IF(N66<P66,"LOWER","HIGHER")) -> HIGHER | V66: 639.75 | W66: =IF(V66="","",IF(D66="","",D66-F66)) -> 2.6614199 | X66: =IF(AM66="","",AM66/22.04622) -> 29.324755 | Y66: =IF(X66="","",IF(D66="","",D66-X66)) -> 2.355245 | Z66: =IF(X66="","",IF(F66="","",X66-F66)) -> 0.30617494 | AA66: =MONTH(A66) -> 3 | AB66: =YEAR(A66) -> 2019 | AC66: =WEEKNUM(A66) -> 10 | AF66: 40.72 | AG66: =IF(V66="","",V66*AF66/2204.622*100) -> 1181.6366 | AL66: =A66 -> 43530 | AM66: 646.5 | AN66: 3.8397 | AO66: =IF(AM66="","",AM66*AN66/2204.622*100) -> 112.59826 | AT66: 301 | AU66: 8.7 | AV66: =(((C66/100*11.7)+(AT66/2000*47))-(AU66)) -> 1.77001 | AW66: =(((B66/100*11.7*0.98)+(AT66/2000*47))-(AU66)) -> 2.0632588 | AX66: =AW66-AV66 -> 0.2932488 | AY66: =(B66*11.7/100)/((AT66/2000*47)+(B66*11.7/100)) -> 0.3473764 | BB66: =C66*22.0462 -> 640.00119
A67: 43531 | B67: 32.07 | C67: 28.92 | D67: 31.57 | E67: =IF(AM67="","",AM67/2206.622)*100 -> 29.422801 | F67: 29.154658 | G67: 39.67 | H67: 29.67 | I67: 29.7 | J67: 23.689828 | K67: =B67-I67 -> 2.37 | L67: =IF(I67="","",IF(J67="","",I67-J67)) -> 6.0101715 | M67: =B67-H67 -> 2.4 | N67: =B67-C67 -> 3.15 | O67: =C67-H67 -> -0.75 | P67: =D67-H67 -> 1.9 | Q67: =IF(E67="","",E67-H67) -> -0.24719899 | R67: =IF(F67="","",F67-H67) -> -0.51534219 | S67: =G67-H67 -> 10 | T67: =G67-B67 -> 7.6 | U67: =IF(P67=N67,"EQUAL",IF(N67<P67,"LOWER","HIGHER")) -> HIGHER | V67: 642.75 | W67: =IF(V67="","",IF(D67="","",D67-F67)) -> 2.4153422 | X67: =IF(AM67="","",AM67/22.04622) -> 29.449493 | Y67: =IF(X67="","",IF(D67="","",D67-X67)) -> 2.1205071 | Z67: =IF(X67="","",IF(F67="","",X67-F67)) -> 0.29483512 | AA67: =MONTH(A67) -> 3 | AB67: =YEAR(A67) -> 2019 | AC67: =WEEKNUM(A67) -> 10 | AF67: 42.332 | AG67: =IF(V67="","",V67*AF67/2204.622*100) -> 1234.175 | AL67: =A67 -> 43531 | AM67: 649.25 | AN67: 3.8701 | AO67: =IF(AM67="","",AM67*AN67/2204.622*100) -> 113.97248 | AT67: 301 | AU67: 8.71 | AV67: =(((C67/100*11.7)+(AT67/2000*47))-(AU67)) -> 1.74714 | AW67: =(((B67/100*11.7*0.98)+(AT67/2000*47))-(AU67)) -> 2.0406462 | AX67: =AW67-AV67 -> 0.2935062 | AY67: =(B67*11.7/100)/((AT67/2000*47)+(B67*11.7/100)) -> 0.34660054 | BB67: =C67*22.0462 -> 637.5761
A68: 43532 | B68: 32.05 | C68: 28.9 | D68: 31.55 | E68: =IF(AM68="","",AM68/2206.622)*100 -> 29.275517 | F68: 28.9959 | G68: 39.65 | H68: 29.65 | I68: 29.7 | J68: 23.583704 | K68: =B68-I68 -> 2.35 | L68: =IF(I68="","",IF(J68="","",I68-J68)) -> 6.1162961 | M68: =B68-H68 -> 2.4 | N68: =B68-C68 -> 3.15 | O68: =C68-H68 -> -0.75 | P68: =D68-H68 -> 1.9 | Q68: =IF(E68="","",E68-H68) -> -0.37448294 | R68: =IF(F68="","",F68-H68) -> -0.65409957 | S68: =G68-H68 -> 10 | T68: =G68-B68 -> 7.6 | U68: =IF(P68=N68,"EQUAL",IF(N68<P68,"LOWER","HIGHER")) -> HIGHER | V68: 639.25 | W68: =IF(V68="","",IF(D68="","",D68-F68)) -> 2.5540996 | X68: =IF(AM68="","",AM68/22.04622) -> 29.302075 | Y68: =IF(X68="","",IF(D68="","",D68-X68)) -> 2.2479246 | Z68: =IF(X68="","",IF(F68="","",X68-F68)) -> 0.30617494 | AA68: =MONTH(A68) -> 3 | AB68: =YEAR(A68) -> 2019 | AC68: =WEEKNUM(A68) -> 10 | AF68: 41.117 | AG68: =IF(V68="","",V68*AF68/2204.622*100) -> 1192.2244 | AL68: =A68 -> 43532 | AM68: 646 | AN68: 3.8666 | AO68: =IF(AM68="","",AM68*AN68/2204.622*100) -> 113.2994 | AT68: 299 | AU68: 8.64 | AV68: =(((C68/100*11.7)+(AT68/2000*47))-(AU68)) -> 1.7678 | AW68: =(((B68/100*11.7*0.98)+(AT68/2000*47))-(AU68)) -> 2.061353 | AX68: =AW68-AV68 -> 0.293553 | AY68: =(B68*11.7/100)/((AT68/2000*47)+(B68*11.7/100)) -> 0.34797032 | BB68: =C68*22.0462 -> 637.13518
A69: 43535 | B69: 32.04 | C69: 28.89 | D69: 31.54 | E69: =IF(AM69="","",AM69/2206.622)*100 -> 29.638062 | F69: 29.358774 | G69: 39.64 | H69: 29.64 | I69: 29.7 | J69: 23.550851 | K69: =B69-I69 -> 2.34 | L69: =IF(I69="","",IF(J69="","",I69-J69)) -> 6.149149 | M69: =B69-H69 -> 2.4 | N69: =B69-C69 -> 3.15 | O69: =C69-H69 -> -0.75 | P69: =D69-H69 -> 1.9 | Q69: =IF(E69="","",E69-H69) -> -0.0019378398 | R69: =IF(F69="","",F69-H69) -> -0.28122557 | S69: =G69-H69 -> 10 | T69: =G69-B69 -> 7.6 | U69: =IF(P69=N69,"EQUAL",IF(N69<P69,"LOWER","HIGHER")) -> HIGHER | V69: 647.25 | W69: =IF(V69="","",IF(D69="","",D69-F69)) -> 2.1812256 | X69: =IF(AM69="","",AM69/22.04622) -> 29.664949 | Y69: =IF(X69="","",IF(D69="","",D69-X69)) -> 1.8750506 | Z69: =IF(X69="","",IF(F69="","",X69-F69)) -> 0.30617494 | AA69: =MONTH(A69) -> 3 | AB69: =YEAR(A69) -> 2019 | AC69: =WEEKNUM(A69) -> 11 | AF69: 41.208 | AG69: =IF(V69="","",V69*AF69/2204.622*100) -> 1209.8164 | AL69: =A69 -> 43535 | AM69: 654 | AN69: 3.8392 | AO69: =IF(AM69="","",AM69*AN69/2204.622*100) -> 113.88967 | AT69: 296 | AU69: 8.58 | AV69: =(((C69/100*11.7)+(AT69/2000*47))-(AU69)) -> 1.75613 | AW69: =(((B69/100*11.7*0.98)+(AT69/2000*47))-(AU69)) -> 2.0497064 | AX69: =AW69-AV69 -> 0.2935764 | AY69: =(B69*11.7/100)/((AT69/2000*47)+(B69*11.7/100)) -> 0.35019076 | BB69: =C69*22.0462 -> 636.91472
A70: 43536 | B70: 32.39 | C70: 29.24 | D70: 31.89 | E70: =IF(AM70="","",AM70/2206.622)*100 -> 29.502108 | F70: 29.234036 | G70: 40.49 | H70: 29.99 | I70: 29.7 | J70: 23.501914 | K70: =B70-I70 -> 2.69 | L70: =IF(I70="","",IF(J70="","",I70-J70)) -> 6.1980859 | M70: =B70-H70 -> 2.4 | N70: =B70-C70 -> 3.15 | O70: =C70-H70 -> -0.75 | P70: =D70-H70 -> 1.9 | Q70: =IF(E70="","",E70-H70) -> -0.48789225 | R70: =IF(F70="","",F70-H70) -> -0.75596351 | S70: =G70-H70 -> 10.5 | T70: =G70-B70 -> 8.1 | U70: =IF(P70=N70,"EQUAL",IF(N70<P70,"LOWER","HIGHER")) -> HIGHER | V70: 644.5 | W70: =IF(V70="","",IF(D70="","",D70-F70)) -> 2.6559635 | X70: =IF(AM70="","",AM70/22.04622) -> 29.528872 | Y70: =IF(X70="","",IF(D70="","",D70-X70)) -> 2.3611284 | Z70: =IF(X70="","",IF(F70="","",X70-F70)) -> 0.29483512 | AA70: =MONTH(A70) -> 3 | AB70: =YEAR(A70) -> 2019 | AC70: =WEEKNUM(A70) -> 11 | AF70: 41.459 | AG70: =IF(V70="","",V70*AF70/2204.622*100) -> 1212.0139 | AL70: =A70 -> 43536 | AM70: 651 | AN70: 3.8111 | AO70: =IF(AM70="","",AM70*AN70/2204.622*100) -> 112.53748 | AT70: 298 | AU70: 8.65 | AV70: =(((C70/100*11.7)+(AT70/2000*47))-(AU70)) -> 1.77408 | AW70: =(((B70/100*11.7*0.98)+(AT70/2000*47))-(AU70)) -> 2.0668374 | AX70: =AW70-AV70 -> 0.2927574 | AY70: =(B70*11.7/100)/((AT70/2000*47)+(B70*11.7/100)) -> 0.35113128 | BB70: =C70*22.0462 -> 644.63089
A71: 43537 | B71: 32.33 | C71: 29.18 | D71: 31.83 | E71: =IF(AM71="","",AM71/2206.622)*100 -> 29.309506 | F71: 29.04126 | G71: 40.43 | H71: 29.93 | I71: 29.7 | J71: 23.18744 | K71: =B71-I71 -> 2.63 | L71: =IF(I71="","",IF(J71="","",I71-J71)) -> 6.5125602 | M71: =B71-H71 -> 2.4 | N71: =B71-C71 -> 3.15 | O71: =C71-H71 -> -0.75 | P71: =D71-H71 -> 1.9 | Q71: =IF(E71="","",E71-H71) -> -0.62049434 | R71: =IF(F71="","",F71-H71) -> -0.88874032 | S71: =G71-H71 -> 10.5 | T71: =G71-B71 -> 8.1 | U71: =IF(P71=N71,"EQUAL",IF(N71<P71,"LOWER","HIGHER")) -> HIGHER | V71: 640.25 | W71: =IF(V71="","",IF(D71="","",D71-F71)) -> 2.7887403 | X71: =IF(AM71="","",AM71/22.04622) -> 29.336095 | Y71: =IF(X71="","",IF(D71="","",D71-X71)) -> 2.4939052 | Z71: =IF(X71="","",IF(F71="","",X71-F71)) -> 0.29483512 | AA71: =MONTH(A71) -> 3 | AB71: =YEAR(A71) -> 2019 | AC71: =WEEKNUM(A71) -> 11 | AF71: 41.179 | AG71: =IF(V71="","",V71*AF71/2204.622*100) -> 1195.89 | AL71: =A71 -> 43537 | AM71: 646.75 | AN71: 3.8142 | AO71: =IF(AM71="","",AM71*AN71/2204.622*100) -> 111.89373 | AT71: 300 | AU71: 8.69 | AV71: =(((C71/100*11.7)+(AT71/2000*47))-(AU71)) -> 1.77406 | AW71: =(((B71/100*11.7*0.98)+(AT71/2000*47))-(AU71)) -> 2.0669578 | AX71: =AW71-AV71 -> 0.2928978 | AY71: =(B71*11.7/100)/((AT71/2000*47)+(B71*11.7/100)) -> 0.34918731 | BB71: =C71*22.0462 -> 643.30812
A72: 43538 | B72: 31.97 | C72: 28.82 | D72: 31.47 | E72: =IF(AM72="","",AM72/2206.622)*100 -> 29.309506 | F72: 29.04126 | G72: 40.07 | H72: 29.57 | I72: 29.7 | J72: 22.873752 | K72: =B72-I72 -> 2.27 | L72: =IF(I72="","",IF(J72="","",I72-J72)) -> 6.8262477 | M72: =B72-H72 -> 2.4 | N72: =B72-C72 -> 3.15 | O72: =C72-H72 -> -0.75 | P72: =D72-H72 -> 1.9 | Q72: =IF(E72="","",E72-H72) -> -0.26049434 | R72: =IF(F72="","",F72-H72) -> -0.52874032 | S72: =G72-H72 -> 10.5 | T72: =G72-B72 -> 8.1 | U72: =IF(P72=N72,"EQUAL",IF(N72<P72,"LOWER","HIGHER")) -> HIGHER | V72: 640.25 | W72: =IF(V72="","",IF(D72="","",D72-F72)) -> 2.4287403 | X72: =IF(AM72="","",AM72/22.04622) -> 29.336095 | Y72: =IF(X72="","",IF(D72="","",D72-X72)) -> 2.1339052 | Z72: =IF(X72="","",IF(F72="","",X72-F72)) -> 0.29483512 | AA72: =MONTH(A72) -> 3 | AB72: =YEAR(A72) -> 2019 | AC72: =WEEKNUM(A72) -> 11 | AF72: 40.698 | AG72: =IF(V72="","",V72*AF72/2204.622*100) -> 1181.9212 | AL72: =A72 -> 43538 | AM72: 646.75 | AN72: 3.843 | AO72: =IF(AM72="","",AM72*AN72/2204.622*100) -> 112.73861 | AT72: 301 | AU72: 8.67 | AV72: =(((C72/100*11.7)+(AT72/2000*47))-(AU72)) -> 1.77544 | AW72: =(((B72/100*11.7*0.98)+(AT72/2000*47))-(AU72)) -> 2.0691802 | AX72: =AW72-AV72 -> 0.2937402 | AY72: =(B72*11.7/100)/((AT72/2000*47)+(B72*11.7/100)) -> 0.34589361 | BB72: =C72*22.0462 -> 635.37148
A73: 43539 | B73: 31.83 | C73: 28.68 | D73: 31.33 | E73: =IF(AM73="","",AM73/2206.622)*100 -> 29.218869 | F73: 28.848483 | G73: 39.93 | H73: 29.43 | I73: 29.7 | J73: 22.918124 | K73: =B73-I73 -> 2.13 | L73: =IF(I73="","",IF(J73="","",I73-J73)) -> 6.7818757 | M73: =B73-H73 -> 2.4 | N73: =B73-C73 -> 3.15 | O73: =C73-H73 -> -0.75 | P73: =D73-H73 -> 1.9 | Q73: =IF(E73="","",E73-H73) -> -0.21113062 | R73: =IF(F73="","",F73-H73) -> -0.58151713 | S73: =G73-H73 -> 10.5 | T73: =G73-B73 -> 8.1 | U73: =IF(P73=N73,"EQUAL",IF(N73<P73,"LOWER","HIGHER")) -> HIGHER | V73: 636 | W73: =IF(V73="","",IF(D73="","",D73-F73)) -> 2.4815171 | X73: =IF(AM73="","",AM73/22.04622) -> 29.245376 | Y73: =IF(X73="","",IF(D73="","",D73-X73)) -> 2.0846237 | Z73: =IF(X73="","",IF(F73="","",X73-F73)) -> 0.39689344 | AA73: =MONTH(A73) -> 3 | AB73: =YEAR(A73) -> 2019 | AC73: =WEEKNUM(A73) -> 11 | AF73: 39.98 | AG73: =IF(V73="","",V73*AF73/2204.622*100) -> 1153.3623 | AL73: =A73 -> 43539 | AM73: 644.75 | AN73: 3.8131 | AO73: =IF(AM73="","",AM73*AN73/2204.622*100) -> 111.51554 | AT73: 306 | AU73: 8.77 | AV73: =(((C73/100*11.7)+(AT73/2000*47))-(AU73)) -> 1.77656 | AW73: =(((B73/100*11.7*0.98)+(AT73/2000*47))-(AU73)) -> 2.0706278 | AX73: =AW73-AV73 -> 0.2940678 | AY73: =(B73*11.7/100)/((AT73/2000*47)+(B73*11.7/100)) -> 0.3411885 | BB73: =C73*22.0462 -> 632.28502
A74: 43542 | B74: 31.84 | C74: 28.69 | D74: 31.34 | E74: =IF(AM74="","",AM74/2206.622)*100 -> 29.230199 | F74: 28.859823 | G74: 39.94 | H74: 29.44 | I74: 29.7 | J74: 23.414098 | K74: =B74-I74 -> 2.14 | L74: =IF(I74="","",IF(J74="","",I74-J74)) -> 6.2859025 | M74: =B74-H74 -> 2.4 | N74: =B74-C74 -> 3.15 | O74: =C74-H74 -> -0.75 | P74: =D74-H74 -> 1.9 | Q74: =IF(E74="","",E74-H74) -> -0.20980108 | R74: =IF(F74="","",F74-H74) -> -0.58017732 | S74: =G74-H74 -> 10.5 | T74: =G74-B74 -> 8.1 | U74: =IF(P74=N74,"EQUAL",IF(N74<P74,"LOWER","HIGHER")) -> HIGHER | V74: 636.25 | W74: =IF(V74="","",IF(D74="","",D74-F74)) -> 2.4801773 | X74: =IF(AM74="","",AM74/22.04622) -> 29.256716 | Y74: =IF(X74="","",IF(D74="","",D74-X74)) -> 2.0832839 | Z74: =IF(X74="","",IF(F74="","",X74-F74)) -> 0.39689344 | AA74: =MONTH(A74) -> 3 | AB74: =YEAR(A74) -> 2019 | AC74: =WEEKNUM(A74) -> 12 | AF74: 39.977 | AG74: =IF(V74="","",V74*AF74/2204.622*100) -> 1153.7291 | AL74: =A74 -> 43542 | AM74: 645 | AN74: 3.7913 | AO74: =IF(AM74="","",AM74*AN74/2204.622*100) -> 110.92099 | AT74: 305 | AU74: 8.74 | AV74: =(((C74/100*11.7)+(AT74/2000*47))-(AU74)) -> 1.78423 | AW74: =(((B74/100*11.7*0.98)+(AT74/2000*47))-(AU74)) -> 2.0782744 | AX74: =AW74-AV74 -> 0.2940444 | AY74: =(B74*11.7/100)/((AT74/2000*47)+(B74*11.7/100)) -> 0.34199534 | BB74: =C74*22.0462 -> 632.50548
A75: 43543 | B75: 31.64 | C75: 28.49 | D75: 31.14 | E75: =IF(AM75="","",AM75/2206.622)*100 -> 29.173551 | F75: 28.803124 | G75: 39.74 | H75: 29.24 | I75: 29.7 | J75: 23.698121 | K75: =B75-I75 -> 1.94 | L75: =IF(I75="","",IF(J75="","",I75-J75)) -> 6.0018791 | M75: =B75-H75 -> 2.4 | N75: =B75-C75 -> 3.15 | O75: =C75-H75 -> -0.75 | P75: =D75-H75 -> 1.9 | Q75: =IF(E75="","",E75-H75) -> -0.066448753 | R75: =IF(F75="","",F75-H75) -> -0.43687638 | S75: =G75-H75 -> 10.5 | T75: =G75-B75 -> 8.1 | U75: =IF(P75=N75,"EQUAL",IF(N75<P75,"LOWER","HIGHER")) -> HIGHER | V75: 635 | W75: =IF(V75="","",IF(D75="","",D75-F75)) -> 2.3368764 | X75: =IF(AM75="","",AM75/22.04622) -> 29.200017 | Y75: =IF(X75="","",IF(D75="","",D75-X75)) -> 1.9399829 | Z75: =IF(X75="","",IF(F75="","",X75-F75)) -> 0.39689344 | AA75: =MONTH(A75) -> 3 | AB75: =YEAR(A75) -> 2019 | AC75: =WEEKNUM(A75) -> 12 | AF75: 40.479 | AG75: =IF(V75="","",V75*AF75/2204.622*100) -> 1165.9216 | AL75: =A75 -> 43543 | AM75: 643.75 | AN75: 3.7885 | AO75: =IF(AM75="","",AM75*AN75/2204.622*100) -> 110.62426 | AT75: 306 | AU75: 8.72 | AV75: =(((C75/100*11.7)+(AT75/2000*47))-(AU75)) -> 1.80433 | AW75: =(((B75/100*11.7*0.98)+(AT75/2000*47))-(AU75)) -> 2.0988424 | AX75: =AW75-AV75 -> 0.2945124 | AY75: =(B75*11.7/100)/((AT75/2000*47)+(B75*11.7/100)) -> 0.33984401 | BB75: =C75*22.0462 -> 628.09624
A76: 43544 | B76: 31.67 | C76: 28.52 | D76: 31.17 | E76: =IF(AM76="","",AM76/2206.622)*100 -> 29.116904 | F76: 28.837143 | G76: 39.77 | H76: 29.27 | I76: 29.7 | J76: 24.124649 | K76: =B76-I76 -> 1.97 | L76: =IF(I76="","",IF(J76="","",I76-J76)) -> 5.575351 | M76: =B76-H76 -> 2.4 | N76: =B76-C76 -> 3.15 | O76: =C76-H76 -> -0.75 | P76: =D76-H76 -> 1.9 | Q76: =IF(E76="","",E76-H76) -> -0.15309643 | R76: =IF(F76="","",F76-H76) -> -0.43285694 | S76: =G76-H76 -> 10.5 | T76: =G76-B76 -> 8.1 | U76: =IF(P76=N76,"EQUAL",IF(N76<P76,"LOWER","HIGHER")) -> HIGHER | V76: 635.75 | W76: =IF(V76="","",IF(D76="","",D76-F76)) -> 2.3328569 | X76: =IF(AM76="","",AM76/22.04622) -> 29.143318 | Y76: =IF(X76="","",IF(D76="","",D76-X76)) -> 2.026682 | Z76: =IF(X76="","",IF(F76="","",X76-F76)) -> 0.30617494 | AA76: =MONTH(A76) -> 3 | AB76: =YEAR(A76) -> 2019 | AC76: =WEEKNUM(A76) -> 12 | AF76: 40.802 | AG76: =IF(V76="","",V76*AF76/2204.622*100) -> 1176.6131 | AL76: =A76 -> 43544 | AM76: 642.5 | AN76: 3.7756 | AO76: =IF(AM76="","",AM76*AN76/2204.622*100) -> 110.03351 | AT76: 307 | AU76: 8.74 | AV76: =(((C76/100*11.7)+(AT76/2000*47))-(AU76)) -> 1.81134 | AW76: =(((B76/100*11.7*0.98)+(AT76/2000*47))-(AU76)) -> 2.1057822 | AX76: =AW76-AV76 -> 0.2944422 | AY76: =(B76*11.7/100)/((AT76/2000*47)+(B76*11.7/100)) -> 0.33932485 | BB76: =C76*22.0462 -> 628.75762
A77: 43545 | B77: 31.5 | C77: 28.35 | D77: 31 | E77: =IF(AM77="","",AM77/2206.622)*100 -> 29.218869 | F77: 28.939201 | G77: 39.6 | H77: 29.1 | I77: 29.7 | J77: 24.266081 | K77: =B77-I77 -> 1.8 | L77: =IF(I77="","",IF(J77="","",I77-J77)) -> 5.4339186 | M77: =B77-H77 -> 2.4 | N77: =B77-C77 -> 3.15 | O77: =C77-H77 -> -0.75 | P77: =D77-H77 -> 1.9 | Q77: =IF(E77="","",E77-H77) -> 0.11886938 | R77: =IF(F77="","",F77-H77) -> -0.16079863 | S77: =G77-H77 -> 10.5 | T77: =G77-B77 -> 8.1 | U77: =IF(P77=N77,"EQUAL",IF(N77<P77,"LOWER","HIGHER")) -> HIGHER | V77: 638 | W77: =IF(V77="","",IF(D77="","",D77-F77)) -> 2.0607986 | X77: =IF(AM77="","",AM77/22.04622) -> 29.245376 | Y77: =IF(X77="","",IF(D77="","",D77-X77)) -> 1.7546237 | Z77: =IF(X77="","",IF(F77="","",X77-F77)) -> 0.30617494 | AA77: =MONTH(A77) -> 3 | AB77: =YEAR(A77) -> 2019 | AC77: =WEEKNUM(A77) -> 12 | AF77: 41.02 | AG77: =IF(V77="","",V77*AF77/2204.622*100) -> 1187.086 | AL77: =A77 -> 43545 | AM77: 644.75 | AN77: 3.7921 | AO77: =IF(AM77="","",AM77*AN77/2204.622*100) -> 110.90139 | AT77: 310 | AU77: 8.79 | AV77: =(((C77/100*11.7)+(AT77/2000*47))-(AU77)) -> 1.81195 | AW77: =(((B77/100*11.7*0.98)+(AT77/2000*47))-(AU77)) -> 2.10679 | AX77: =AW77-AV77 -> 0.29484 | AY77: =(B77*11.7/100)/((AT77/2000*47)+(B77*11.7/100)) -> 0.3359464 | BB77: =C77*22.0462 -> 625.00977
... A84: 43556 | B84: 30.97 | C84: 27.82 | D84: 30.47 | E84: =IF(AM84="","",AM84/2206.622)*100 -> 27.961291 | F84: 27.589764 | G84: 37.57 | H84: 28.57 | I84: 28.24 | J84: 23.496959 | K84: =B84-I84 -> 2.73 | L84: =IF(I84="","",IF(J84="","",I84-J84)) -> 4.7430412 | M84: =B84-H84 -> 2.4 | N84: =B84-C84 -> 3.15 | O84: =C84-H84 -> -0.75 | P84: =D84-H84 -> 1.9 | Q84: =IF(E84="","",E84-H84) -> -0.60870894 | R84: =IF(F84="","",F84-H84) -> -0.98023631 | S84: =G84-H84 -> 9 | T84: =G84-B84 -> 6.6 | U84: =IF(P84=N84,"EQUAL",IF(N84<P84,"LOWER","HIGHER")) -> HIGHER | V84: 608.25 | W84: =IF(V84="","",IF(D84="","",D84-F84)) -> 2.8802363 | X84: =IF(AM84="","",AM84/22.04622) -> 27.986657 | Y84: =IF(X84="","",IF(D84="","",D84-X84)) -> 2.4833429 | Z84: =IF(X84="","",IF(F84="","",X84-F84)) -> 0.39689344 | AA84: =MONTH(A84) -> 4 | AB84: =YEAR(A84) -> 2019 | AC84: =WEEKNUM(A84) -> 14 | AF84: 42.682 | AG84: =IF(V84="","",V84*AF84/2204.622*100) -> 1177.5863 | AL84: =A84 -> 43556 | AM84: 617 | AN84: 3.8508 | AO84: =IF(AM84="","",AM84*AN84/2204.622*100) -> 107.77102 | AT84: 304 | AU84: 8.64 | AV84: =(((C84/100*11.7)+(AT84/2000*47))-(AU84)) -> 1.75894 | AW84: =(((B84/100*11.7*0.98)+(AT84/2000*47))-(AU84)) -> 2.0550202 | AX84: =AW84-AV84 -> 0.2960802 | AY84: =(B84*11.7/100)/((AT84/2000*47)+(B84*11.7/100)) -> 0.33652132 | BB84: =C84*22.0462 -> 613.32528
A85: 43557 | B85: 31.36 | C85: 28.21 | D85: 30.86 | E85: =IF(AM85="","",AM85/2206.622)*100 -> 28.380484 | G85: 37.96 | H85: 28.96 | I85: 28.24 | J85: 23.918311 | K85: =B85-I85 -> 3.12 | L85: =IF(I85="","",IF(J85="","",I85-J85)) -> 4.3216888 | M85: =B85-H85 -> 2.4 | N85: =B85-C85 -> 3.15 | O85: =C85-H85 -> -0.75 | P85: =D85-H85 -> 1.9 | Q85: =IF(E85="","",E85-H85) -> -0.57951617 | R85: =IF(F85="","",F85-H85) | S85: =G85-H85 -> 9 | T85: =G85-B85 -> 6.6 | U85: =IF(P85=N85,"EQUAL",IF(N85<P85,"LOWER","HIGHER")) -> HIGHER | X85: =IF(AM85="","",AM85/22.04622) -> 28.40623 | Y85: =IF(X85="","",IF(D85="","",D85-X85)) -> 2.4537698 | Z85: =IF(X85="","",IF(F85="","",X85-F85)) | AA85: =MONTH(A85) -> 4 | AB85: =YEAR(A85) -> 2019 | AC85: =WEEKNUM(A85) -> 14 | AF85: 42.682 | AG85: =IF(V85="","",V85*AF85/2204.622*100) | AL85: =A85 -> 43557 | AM85: 626.25 | AN85: 3.8525 | AO85: =IF(AM85="","",AM85*AN85/2204.622*100) -> 109.435 | AT85: 306 | AU85: 8.68 | AV85: =(((C85/100*11.7)+(AT85/2000*47))-(AU85)) -> 1.81157 | AW85: =(((B85/100*11.7*0.98)+(AT85/2000*47))-(AU85)) -> 2.1067376 | AX85: =AW85-AV85 -> 0.2951676 | AY85: =(B85*11.7/100)/((AT85/2000*47)+(B85*11.7/100)) -> 0.33785262 | BB85: =C85*22.0462 -> 621.9233
A86: 43558 | B86: 31.35 | C86: 28.2 | D86: 30.7 | E86: =IF(AM86="","",AM86/2206.622)*100 -> 28.357825 | F86: 27.975317 | G86: 37.8 | H86: 28.8 | I86: 28.24 | J86: 24.209401 | K86: =B86-I86 -> 3.11 | L86: =IF(I86="","",IF(J86="","",I86-J86)) -> 4.0305991 | M86: =B86-H86 -> 2.55 | N86: =B86-C86 -> 3.15 | O86: =C86-H86 -> -0.6 | P86: =D86-H86 -> 1.9 | Q86: =IF(E86="","",E86-H86) -> -0.44217523 | R86: =IF(F86="","",F86-H86) -> -0.82468269 | S86: =G86-H86 -> 9 | T86: =G86-B86 -> 6.45 | U86: =IF(P86=N86,"EQUAL",IF(N86<P86,"LOWER","HIGHER")) -> HIGHER | V86: 616.75 | W86: =IF(V86="","",IF(D86="","",D86-F86)) -> 2.7246827 | X86: =IF(AM86="","",AM86/22.04622) -> 28.383551 | Y86: =IF(X86="","",IF(D86="","",D86-X86)) -> 2.3164494 | Z86: =IF(X86="","",IF(F86="","",X86-F86)) -> 0.40823325 | AA86: =MONTH(A86) -> 4 | AB86: =YEAR(A86) -> 2019 | AC86: =WEEKNUM(A86) -> 14 | AF86: 42.817 | AG86: =IF(V86="","",V86*AF86/2204.622*100) -> 1197.8192 | AL86: =A86 -> 43558 | AM86: 625.75 | AN86: 3.8694 | AO86: =IF(AM86="","",AM86*AN86/2204.622*100) -> 109.82731 | AT86: 306 | AU86: 8.67 | AV86: =(((C86/100*11.7)+(AT86/2000*47))-(AU86)) -> 1.8204 | AW86: =(((B86/100*11.7*0.98)+(AT86/2000*47))-(AU86)) -> 2.115591 | AX86: =AW86-AV86 -> 0.295191 | AY86: =(B86*11.7/100)/((AT86/2000*47)+(B86*11.7/100)) -> 0.33778128 | BB86: =C86*22.0462 -> 621.70284
A87: 43559 | B87: 31.75 | C87: 28.6 | D87: 31.1 | E87: =IF(AM87="","",AM87/2206.622)*100 -> 28.878983 | F87: 28.701065 | G87: 38.2 | H87: 29.2 | I87: 28.24 | J87: 24.507999 | K87: =B87-I87 -> 3.51 | L87: =IF(I87="","",IF(J87="","",I87-J87)) -> 3.7320005 | M87: =B87-H87 -> 2.55 | N87: =B87-C87 -> 3.15 | O87: =C87-H87 -> -0.6 | P87: =D87-H87 -> 1.9 | Q87: =IF(E87="","",E87-H87) -> -0.32101665 | R87: =IF(F87="","",F87-H87) -> -0.49893469 | S87: =G87-H87 -> 9 | T87: =G87-B87 -> 6.45 | U87: =IF(P87=N87,"EQUAL",IF(N87<P87,"LOWER","HIGHER")) -> HIGHER | V87: 632.75 | W87: =IF(V87="","",IF(D87="","",D87-F87)) -> 2.3989347 | X87: =IF(AM87="","",AM87/22.04622) -> 28.905182 | Y87: =IF(X87="","",IF(D87="","",D87-X87)) -> 2.1948181 | Z87: =IF(X87="","",IF(F87="","",X87-F87)) -> 0.20411662 | AA87: =MONTH(A87) -> 4 | AB87: =YEAR(A87) -> 2019 | AC87: =WEEKNUM(A87) -> 14 | AF87: 43.355 | AG87: =IF(V87="","",V87*AF87/2204.622*100) -> 1244.3347 | AL87: =A87 -> 43559 | AM87: 637.25 | AN87: 3.8587 | AO87: =IF(AM87="","",AM87*AN87/2204.622*100) -> 111.53643 | AT87: 307 | AU87: 8.75 | AV87: =(((C87/100*11.7)+(AT87/2000*47))-(AU87)) -> 1.8107 | AW87: =(((B87/100*11.7*0.98)+(AT87/2000*47))-(AU87)) -> 2.104955 | AX87: =AW87-AV87 -> 0.294255 | AY87: =(B87*11.7/100)/((AT87/2000*47)+(B87*11.7/100)) -> 0.33989066 | BB87: =C87*22.0462 -> 630.52132
A88: 43560 | B88: 31.7 | C88: 28.55 | D88: 31.05 | E88: =IF(AM88="","",AM88/2206.622)*100 -> 28.811006 | F88: 28.644366 | G88: 38.15 | H88: 29.15 | I88: 28.24 | J88: 24.649595 | K88: =B88-I88 -> 3.46 | L88: =IF(I88="","",IF(J88="","",I88-J88)) -> 3.5904052 | M88: =B88-H88 -> 2.55 | N88: =B88-C88 -> 3.15 | O88: =C88-H88 -> -0.6 | P88: =D88-H88 -> 1.9 | Q88: =IF(E88="","",E88-H88) -> -0.33899386 | R88: =IF(F88="","",F88-H88) -> -0.50563375 | S88: =G88-H88 -> 9 | T88: =G88-B88 -> 6.45 | U88: =IF(P88=N88,"EQUAL",IF(N88<P88,"LOWER","HIGHER")) -> HIGHER | V88: 631.5 | W88: =IF(V88="","",IF(D88="","",D88-F88)) -> 2.4056338 | X88: =IF(AM88="","",AM88/22.04622) -> 28.837143 | Y88: =IF(X88="","",IF(D88="","",D88-X88)) -> 2.2128569 | Z88: =IF(X88="","",IF(F88="","",X88-F88)) -> 0.19277681 | AA88: =MONTH(A88) -> 4 | AB88: =YEAR(A88) -> 2019 | AC88: =WEEKNUM(A88) -> 14 | AF88: 43.871 | AG88: =IF(V88="","",V88*AF88/2204.622*100) -> 1256.657 | AL88: =A88 -> 43560 | AM88: 635.75 | AN88: 3.873 | AO88: =IF(AM88="","",AM88*AN88/2204.622*100) -> 111.68626 | AT88: 303 | AU88: 8.67 | AV88: =(((C88/100*11.7)+(AT88/2000*47))-(AU88)) -> 1.79085 | AW88: =(((B88/100*11.7*0.98)+(AT88/2000*47))-(AU88)) -> 2.085222 | AX88: =AW88-AV88 -> 0.294372 | AY88: =(B88*11.7/100)/((AT88/2000*47)+(B88*11.7/100)) -> 0.34248435 | BB88: =C88*22.0462 -> 629.41901
A89: 43563 | B89: 31.43 | C89: 28.28 | D89: 30.38 | E89: =IF(AM89="","",AM89/2206.622)*100 -> 28.561756 | F89: 28.587667 | G89: 37.88 | H89: 28.88 | I89: 30.15 | J89: 24.379904 | K89: =B89-I89 -> 1.28 | L89: =IF(I89="","",IF(J89="","",I89-J89)) -> 5.7700955 | M89: =B89-H89 -> 2.55 | N89: =B89-C89 -> 3.15 | O89: =C89-H89 -> -0.6 | P89: =D89-H89 -> 1.5 | Q89: =IF(E89="","",E89-H89) -> -0.31824361 | R89: =IF(F89="","",F89-H89) -> -0.29233282 | S89: =G89-H89 -> 9 | T89: =G89-B89 -> 6.45 | U89: =IF(P89=N89,"EQUAL",IF(N89<P89,"LOWER","HIGHER")) -> HIGHER | V89: 630.25 | W89: =IF(V89="","",IF(D89="","",D89-F89)) -> 1.7923328 | X89: =IF(AM89="","",AM89/22.04622) -> 28.587667 | Y89: =IF(X89="","",IF(D89="","",D89-X89)) -> 1.7923328 | Z89: =IF(X89="","",IF(F89="","",X89-F89)) -> -7.1054274e-15 | AA89: =MONTH(A89) -> 4 | AB89: =YEAR(A89) -> 2019 | AC89: =WEEKNUM(A89) -> 15 | AF89: 43.68 | AG89: =IF(V89="","",V89*AF89/2204.622*100) -> 1248.7093 | AL89: =A89 -> 43563 | AM89: 630.25 | AN89: 3.849 | AO89: =IF(AM89="","",AM89*AN89/2204.622*100) -> 110.03393 | AT89: 304 | AU89: 8.7 | AV89: =(((C89/100*11.7)+(AT89/2000*47))-(AU89)) -> 1.75276 | AW89: =(((B89/100*11.7*0.98)+(AT89/2000*47))-(AU89)) -> 2.0477638 | AX89: =AW89-AV89 -> 0.2950038 | AY89: =(B89*11.7/100)/((AT89/2000*47)+(B89*11.7/100)) -> 0.33982115 | BB89: =C89*22.0462 -> 623.46654
A90: 43564 | B90: 31.59 | C90: 28.44 | D90: 30.54 | E90: =IF(AM90="","",AM90/2206.622)*100 -> 28.70904 | F90: 28.633026 | G90: 38.04 | H90: 29.04 | I90: 30.15 | J90: 24.508627 | K90: =B90-I90 -> 1.44 | L90: =IF(I90="","",IF(J90="","",I90-J90)) -> 5.6413731 | M90: =B90-H90 -> 2.55 | N90: =B90-C90 -> 3.15 | O90: =C90-H90 -> -0.6 | P90: =D90-H90 -> 1.5 | Q90: =IF(E90="","",E90-H90) -> -0.33095967 | R90: =IF(F90="","",F90-H90) -> -0.40697357 | S90: =G90-H90 -> 9 | T90: =G90-B90 -> 6.45 | U90: =IF(P90=N90,"EQUAL",IF(N90<P90,"LOWER","HIGHER")) -> HIGHER | V90: 631.25 | W90: =IF(V90="","",IF(D90="","",D90-F90)) -> 1.9069736 | X90: =IF(AM90="","",AM90/22.04622) -> 28.735085 | Y90: =IF(X90="","",IF(D90="","",D90-X90)) -> 1.8049153 | Z90: =IF(X90="","",IF(F90="","",X90-F90)) -> 0.10205831 | AA90: =MONTH(A90) -> 4 | AB90: =YEAR(A90) -> 2019 | AC90: =WEEKNUM(A90) -> 15 | AF90: 43.319 | AG90: =IF(V90="","",V90*AF90/2204.622*100) -> 1240.3541 | AL90: =A90 -> 43564 | AM90: 633.5 | AN90: 3.8502 | AO90: =IF(AM90="","",AM90*AN90/2204.622*100) -> 110.63582 | AT90: 304 | AU90: 8.7 | AV90: =(((C90/100*11.7)+(AT90/2000*47))-(AU90)) -> 1.77148 | AW90: =(((B90/100*11.7*0.98)+(AT90/2000*47))-(AU90)) -> 2.0661094 | AX90: =AW90-AV90 -> 0.2946294 | AY90: =(B90*11.7/100)/((AT90/2000*47)+(B90*11.7/100)) -> 0.34096123 | BB90: =C90*22.0462 -> 626.99393
A91: 43565 | B91: 31.62 | C91: 28.47 | D91: 30.57 | E91: =IF(AM91="","",AM91/2206.622)*100 -> 28.70904 | F91: 28.644366 | G91: 38.07 | H91: 29.07 | I91: 30.15 | J91: 23.977971 | K91: =B91-I91 -> 1.47 | L91: =IF(I91="","",IF(J91="","",I91-J91)) -> 6.1720287 | M91: =B91-H91 -> 2.55 | N91: =B91-C91 -> 3.15 | O91: =C91-H91 -> -0.6 | P91: =D91-H91 -> 1.5 | Q91: =IF(E91="","",E91-H91) -> -0.36095967 | R91: =IF(F91="","",F91-H91) -> -0.42563375 | S91: =G91-H91 -> 9 | T91: =G91-B91 -> 6.45 | U91: =IF(P91=N91,"EQUAL",IF(N91<P91,"LOWER","HIGHER")) -> HIGHER | V91: 631.5 | W91: =IF(V91="","",IF(D91="","",D91-F91)) -> 1.9256338 | X91: =IF(AM91="","",AM91/22.04622) -> 28.735085 | Y91: =IF(X91="","",IF(D91="","",D91-X91)) -> 1.8349153 | Z91: =IF(X91="","",IF(F91="","",X91-F91)) -> 0.0907185 | AA91: =MONTH(A91) -> 4 | AB91: =YEAR(A91) -> 2019 | AC91: =WEEKNUM(A91) -> 15 | AF91: 42.944 | AG91: =IF(V91="","",V91*AF91/2204.622*100) -> 1230.1037 | AL91: =A91 -> 43565 | AM91: 633.5 | AN91: 3.8247 | AO91: =IF(AM91="","",AM91*AN91/2204.622*100) -> 109.90308 | AT91: 305 | AU91: 8.73 | AV91: =(((C91/100*11.7)+(AT91/2000*47))-(AU91)) -> 1.76849 | AW91: =(((B91/100*11.7*0.98)+(AT91/2000*47))-(AU91)) -> 2.0630492 | AX91: =AW91-AV91 -> 0.2945592 | AY91: =(B91*11.7/100)/((AT91/2000*47)+(B91*11.7/100)) -> 0.34043677 | BB91: =C91*22.0462 -> 627.65531
A92: 43566 | B92: 31.53 | C92: 28.38 | D92: 30.48 | E92: =IF(AM92="","",AM92/2206.622)*100 -> 28.595745 | F92: 28.519628 | G92: 37.98 | H92: 28.98 | I92: 30.15 | J92: 23.771689 | K92: =B92-I92 -> 1.38 | L92: =IF(I92="","",IF(J92="","",I92-J92)) -> 6.3783115 | M92: =B92-H92 -> 2.55 | N92: =B92-C92 -> 3.15 | O92: =C92-H92 -> -0.6 | P92: =D92-H92 -> 1.5 | Q92: =IF(E92="","",E92-H92) -> -0.38425501 | R92: =IF(F92="","",F92-H92) -> -0.46037169 | S92: =G92-H92 -> 9 | T92: =G92-B92 -> 6.45 | U92: =IF(P92=N92,"EQUAL",IF(N92<P92,"LOWER","HIGHER")) -> HIGHER | V92: 628.75 | W92: =IF(V92="","",IF(D92="","",D92-F92)) -> 1.9603717 | X92: =IF(AM92="","",AM92/22.04622) -> 28.621687 | Y92: =IF(X92="","",IF(D92="","",D92-X92)) -> 1.8583134 | Z92: =IF(X92="","",IF(F92="","",X92-F92)) -> 0.10205831 | AA92: =MONTH(A92) -> 4 | AB92: =YEAR(A92) -> 2019 | AC92: =WEEKNUM(A92) -> 15 | AF92: 42.677 | AG92: =IF(V92="","",V92*AF92/2204.622*100) -> 1217.1322 | AL92: =A92 -> 43566 | AM92: 631 | AN92: 3.857 | AO92: =IF(AM92="","",AM92*AN92/2204.622*100) -> 110.39385 | AT92: 302 | AU92: 8.66 | AV92: =(((C92/100*11.7)+(AT92/2000*47))-(AU92)) -> 1.75746 | AW92: =(((B92/100*11.7*0.98)+(AT92/2000*47))-(AU92)) -> 2.0522298 | AX92: =AW92-AV92 -> 0.2947698 | AY92: =(B92*11.7/100)/((AT92/2000*47)+(B92*11.7/100)) -> 0.34201804 | BB92: =C92*22.0462 -> 625.67116
A93: 43567 | B93: 31.5 | C93: 28.35 | D93: 30.45 | E93: =IF(AM93="","",AM93/2206.622)*100 -> 28.618404 | F93: 28.451589 | G93: 37.95 | H93: 28.95 | I93: 30.15 | J93: 23.893029 | K93: =B93-I93 -> 1.35 | L93: =IF(I93="","",IF(J93="","",I93-J93)) -> 6.256971 | M93: =B93-H93 -> 2.55 | N93: =B93-C93 -> 3.15 | O93: =C93-H93 -> -0.6 | P93: =D93-H93 -> 1.5 | Q93: =IF(E93="","",E93-H93) -> -0.33159594 | R93: =IF(F93="","",F93-H93) -> -0.49841057 | S93: =G93-H93 -> 9 | T93: =G93-B93 -> 6.45 | U93: =IF(P93=N93,"EQUAL",IF(N93<P93,"LOWER","HIGHER")) -> HIGHER | V93: 627.25 | W93: =IF(V93="","",IF(D93="","",D93-F93)) -> 1.9984106 | X93: =IF(AM93="","",AM93/22.04622) -> 28.644366 | Y93: =IF(X93="","",IF(D93="","",D93-X93)) -> 1.8056338 | Z93: =IF(X93="","",IF(F93="","",X93-F93)) -> 0.19277681 | AA93: =MONTH(A93) -> 4 | AB93: =YEAR(A93) -> 2019 | AC93: =WEEKNUM(A93) -> 15 | AF93: 42.139 | AG93: =IF(V93="","",V93*AF93/2204.622*100) -> 1198.9215 | AL93: =A93 -> 43567 | AM93: 631.5 | AN93: 3.8812 | AO93: =IF(AM93="","",AM93*AN93/2204.622*100) -> 111.17451 | AT93: 303 | AU93: 8.66 | AV93: =(((C93/100*11.7)+(AT93/2000*47))-(AU93)) -> 1.77745 | AW93: =(((B93/100*11.7*0.98)+(AT93/2000*47))-(AU93)) -> 2.07229 | AX93: =AW93-AV93 -> 0.29484 | AY93: =(B93*11.7/100)/((AT93/2000*47)+(B93*11.7/100)) -> 0.34106052 | BB93: =C93*22.0462 -> 625.00977
A94: 43570 | B94: 31.36 | C94: 28.21 | D94: 30.31 | E94: =IF(AM94="","",AM94/2206.622)*100 -> 28.539097 | F94: 28.270152 | G94: 37.81 | H94: 28.81 | I94: 30.15 | J94: 23.640252 | K94: =B94-I94 -> 1.21 | L94: =IF(I94="","",IF(J94="","",I94-J94)) -> 6.5097483 | M94: =B94-H94 -> 2.55 | N94: =B94-C94 -> 3.15 | O94: =C94-H94 -> -0.6 | P94: =D94-H94 -> 1.5 | Q94: =IF(E94="","",E94-H94) -> -0.27090268 | R94: =IF(F94="","",F94-H94) -> -0.53984757 | S94: =G94-H94 -> 9 | T94: =G94-B94 -> 6.45 | U94: =IF(P94=N94,"EQUAL",IF(N94<P94,"LOWER","HIGHER")) -> HIGHER | V94: 623.25 | W94: =IF(V94="","",IF(D94="","",D94-F94)) -> 2.0398476 | X94: =IF(AM94="","",AM94/22.04622) -> 28.564988 | Y94: =IF(X94="","",IF(D94="","",D94-X94)) -> 1.7450124 | Z94: =IF(X94="","",IF(F94="","",X94-F94)) -> 0.29483512 | AA94: =MONTH(A94) -> 4 | AB94: =YEAR(A94) -> 2019 | AC94: =WEEKNUM(A94) -> 16 | AF94: 41.576 | AG94: =IF(V94="","",V94*AF94/2204.622*100) -> 1175.3599 | AL94: =A94 -> 43570 | AM94: 629.75 | AN94: 3.872 | AO94: =IF(AM94="","",AM94*AN94/2204.622*100) -> 110.60363 | AT94: 306 | AU94: 8.7 | AV94: =(((C94/100*11.7)+(AT94/2000*47))-(AU94)) -> 1.79157 | AW94: =(((B94/100*11.7*0.98)+(AT94/2000*47))-(AU94)) -> 2.0867376 | AX94: =AW94-AV94 -> 0.2951676 | AY94: =(B94*11.7/100)/((AT94/2000*47)+(B94*11.7/100)) -> 0.33785262 | BB94: =C94*22.0462 -> 621.9233
A95: 43571 | B95: 31.27 | C95: 28.12 | D95: 30.22 | E95: =IF(AM95="","",AM95/2206.622)*100 -> 28.2332 | F95: 28.054696 | G95: 38.22 | H95: 28.72 | I95: 29.5 | J95: 23.859998 | K95: =B95-I95 -> 1.77 | L95: =IF(I95="","",IF(J95="","",I95-J95)) -> 5.6400025 | M95: =B95-H95 -> 2.55 | N95: =B95-C95 -> 3.15 | O95: =C95-H95 -> -0.6 | P95: =D95-H95 -> 1.5 | Q95: =IF(E95="","",E95-H95) -> -0.48680011 | R95: =IF(F95="","",F95-H95) -> -0.665304 | S95: =G95-H95 -> 9.5 | T95: =G95-B95 -> 6.95 | U95: =IF(P95=N95,"EQUAL",IF(N95<P95,"LOWER","HIGHER")) -> HIGHER | V95: 618.5 | W95: =IF(V95="","",IF(D95="","",D95-F95)) -> 2.165304 | X95: =IF(AM95="","",AM95/22.04622) -> 28.258813 | Y95: =IF(X95="","",IF(D95="","",D95-X95)) -> 1.9611874 | Z95: =IF(X95="","",IF(F95="","",X95-F95)) -> 0.20411662 | AA95: =MONTH(A95) -> 4 | AB95: =YEAR(A95) -> 2019 | AC95: =WEEKNUM(A95) -> 16 | AF95: 42.258 | AG95: =IF(V95="","",V95*AF95/2204.622*100) -> 1185.5353 | AL95: =A95 -> 43571 | AM95: 623 | AN95: 3.9031 | AO95: =IF(AM95="","",AM95*AN95/2204.622*100) -> 110.29697 | AS95: =AV95/AU95 -> 0.2092014 | AT95: 302 | AU95: 8.59 | AV95: =(((C95/100*11.7)+(AT95/2000*47))-(AU95)) -> 1.79704 | AW95: =(((B95/100*11.7*0.98)+(AT95/2000*47))-(AU95)) -> 2.0924182 | AX95: =AW95-AV95 -> 0.2953782 | AY95: =(B95*11.7/100)/((AT95/2000*47)+(B95*11.7/100)) -> 0.34015707 | BB95: =C95*22.0462 -> 619.93914
A96: 43572 | B96: 31.01 | C96: 27.86 | D96: 29.96 | E96: =IF(AM96="","",AM96/2206.622)*100 -> 28.278518 | F96: 27.997997 | G96: 37.96 | H96: 28.46 | I96: 29.5 | J96: 24.221598 | K96: =B96-I96 -> 1.51 | L96: =IF(I96="","",IF(J96="","",I96-J96)) -> 5.2784021 | M96: =B96-H96 -> 2.55 | N96: =B96-C96 -> 3.15 | O96: =C96-H96 -> -0.6 | P96: =D96-H96 -> 1.5 | Q96: =IF(E96="","",E96-H96) -> -0.18148198 | R96: =IF(F96="","",F96-H96) -> -0.46200306 | S96: =G96-H96 -> 9.5 | T96: =G96-B96 -> 6.95 | U96: =IF(P96=N96,"EQUAL",IF(N96<P96,"LOWER","HIGHER")) -> HIGHER | V96: 617.25 | W96: =IF(V96="","",IF(D96="","",D96-F96)) -> 1.9620031 | X96: =IF(AM96="","",AM96/22.04622) -> 28.304172 | Y96: =IF(X96="","",IF(D96="","",D96-X96)) -> 1.6558281 | Z96: =IF(X96="","",IF(F96="","",X96-F96)) -> 0.30617494 | AA96: =MONTH(A96) -> 4 | AB96: =YEAR(A96) -> 2019 | AC96: =WEEKNUM(A96) -> 16 | AF96: 41.62 | AG96: =IF(V96="","",V96*AF96/2204.622*100) -> 1165.2766 | AL96: =A96 -> 43572 | AM96: 624 | AN96: 3.9373 | AO96: =IF(AM96="","",AM96*AN96/2204.622*100) -> 111.44202 | AS96: =AV96/AU96 -> 0.21013176 | AT96: 299 | AU96: 8.5 | AV96: =(((C96/100*11.7)+(AT96/2000*47))-(AU96)) -> 1.78612 | AW96: =(((B96/100*11.7*0.98)+(AT96/2000*47))-(AU96)) -> 2.0821066 | AX96: =AW96-AV96 -> 0.2959866 | AY96: =(B96*11.7/100)/((AT96/2000*47)+(B96*11.7/100)) -> 0.34052392 | BB96: =C96*22.0462 -> 614.20713
A97: 43573 | B97: 31.35 | C97: 28.2 | D97: 30.3 | E97: =IF(AM97="","",AM97/2206.622)*100 -> 28.199211 | F97: 28.326851 | G97: 38.3 | H97: 28.8 | I97: 29.5 | J97: 23.911916 | K97: =B97-I97 -> 1.85 | L97: =IF(I97="","",IF(J97="","",I97-J97)) -> 5.5880844 | M97: =B97-H97 -> 2.55 | N97: =B97-C97 -> 3.15 | O97: =C97-H97 -> -0.6 | P97: =D97-H97 -> 1.5 | Q97: =IF(E97="","",E97-H97) -> -0.60078872 | R97: =IF(F97="","",F97-H97) -> -0.4731485 | S97: =G97-H97 -> 9.5 | T97: =G97-B97 -> 6.95 | U97: =IF(P97=N97,"EQUAL",IF(N97<P97,"LOWER","HIGHER")) -> HIGHER | V97: 624.5 | W97: =IF(V97="","",IF(D97="","",D97-F97)) -> 1.9731485 | X97: =IF(AM97="","",AM97/22.04622) -> 28.224793 | Y97: =IF(X97="","",IF(D97="","",D97-X97)) -> 2.0752068 | Z97: =IF(X97="","",IF(F97="","",X97-F97)) -> -0.10205831 | AA97: =MONTH(A97) -> 4 | AB97: =YEAR(A97) -> 2019 | AC97: =WEEKNUM(A97) -> 16 | AF97: 41.791 | AG97: =IF(V97="","",V97*AF97/2204.622*100) -> 1183.8075 | AL97: =A97 -> 43573 | AM97: 622.25 | AN97: 3.9261 | AO97: =IF(AM97="","",AM97*AN97/2204.622*100) -> 110.81336 | AS97: =AV97/AU97 -> 0.20920188 | AT97: 298 | AU97: 8.52 | AV97: =(((C97/100*11.7)+(AT97/2000*47))-(AU97)) -> 1.7824 | AW97: =(((B97/100*11.7*0.98)+(AT97/2000*47))-(AU97)) -> 2.077591 | AX97: =AW97-AV97 -> 0.295191 | AY97: =(B97*11.7/100)/((AT97/2000*47)+(B97*11.7/100)) -> 0.34373228 | BB97: =C97*22.0462 -> 621.70284
A98: 43577 | B98: 31.25 | C98: 28.1 | D98: 30.2 | E98: =IF(AM98="","",AM98/2206.622)*100 -> #VALUE! | G98: 38.2 | H98: 28.7 | I98: 29.5 | J98: 23.843809 | K98: =B98-I98 -> 1.75 | L98: =IF(I98="","",IF(J98="","",I98-J98)) -> 5.656191 | M98: =B98-H98 -> 2.55 | N98: =B98-C98 -> 3.15 | O98: =C98-H98 -> -0.6 | P98: =D98-H98 -> 1.5 | Q98: =IF(E98="","",E98-H98) -> #VALUE! | R98: =IF(F98="","",F98-H98) | S98: =G98-H98 -> 9.5 | T98: =G98-B98 -> 6.95 | U98: =IF(P98=N98,"EQUAL",IF(N98<P98,"LOWER","HIGHER")) -> HIGHER | X98: =IF(AM98="","",AM98/22.04622) | Y98: =IF(X98="","",IF(D98="","",D98-X98)) | Z98: =IF(X98="","",IF(F98="","",X98-F98)) | AA98: =MONTH(A98) -> 4 | AB98: =YEAR(A98) -> 2019 | AC98: =WEEKNUM(A98) -> 17 | AF98: 42.416 | AG98: =IF(V98="","",V98*AF98/2204.622*100) | AL98: =A98 -> 43577 | AN98: 3.9358 | AO98: =IF(AM98="","",AM98*AN98/2204.622*100) | AS98: =AV98/AU98 -> 0.21352594 | AT98: 298 | AU98: 8.48 | AV98: =(((C98/100*11.7)+(AT98/2000*47))-(AU98)) -> 1.8107 | AW98: =(((B98/100*11.7*0.98)+(AT98/2000*47))-(AU98)) -> 2.106125 | AX98: =AW98-AV98 -> 0.295425 | AY98: =(B98*11.7/100)/((AT98/2000*47)+(B98*11.7/100)) -> 0.34301194 | BB98: =C98*22.0462 -> 619.49822
A99: 43578 | B99: 30.61 | C99: 27.46 | D99: 29.56 | E99: =IF(AM99="","",AM99/2206.622)*100 -> 28.097245 | F99: 28.315512 | G99: 37.56 | H99: 28.37 | I99: 29.5 | J99: 23.861714 | K99: =B99-I99 -> 1.11 | L99: =IF(I99="","",IF(J99="","",I99-J99)) -> 5.6382856 | M99: =B99-H99 -> 2.24 | N99: =B99-C99 -> 3.15 | O99: =C99-H99 -> -0.91 | P99: =D99-H99 -> 1.19 | Q99: =IF(E99="","",E99-H99) -> -0.27275453 | R99: =IF(F99="","",F99-H99) -> -0.054488316 | S99: =G99-H99 -> 9.19 | T99: =G99-B99 -> 6.95 | U99: =IF(P99=N99,"EQUAL",IF(N99<P99,"LOWER","HIGHER")) -> HIGHER | V99: 624.25 | W99: =IF(V99="","",IF(D99="","",D99-F99)) -> 1.2444883 | X99: =IF(AM99="","",AM99/22.04622) -> 28.122735 | Y99: =IF(X99="","",IF(D99="","",D99-X99)) -> 1.4372651 | Z99: =IF(X99="","",IF(F99="","",X99-F99)) -> -0.19277681 | AA99: =MONTH(A99) -> 4 | AB99: =YEAR(A99) -> 2019 | AC99: =WEEKNUM(A99) -> 17 | AF99: 42.4 | AG99: =IF(V99="","",V99*AF99/2204.622*100) -> 1200.5777 | AL99: =A99 -> 43578 | AM99: 620 | AN99: 3.9197 | AO99: =IF(AM99="","",AM99*AN99/2204.622*100) -> 110.23268 | AS99: =AV99/AU99 -> 0.2207467 | AT99: 296 | AU99: 8.33 | AV99: =(((C99/100*11.7)+(AT99/2000*47))-(AU99)) -> 1.83882 | AW99: =(((B99/100*11.7*0.98)+(AT99/2000*47))-(AU99)) -> 2.1357426 | AX99: =AW99-AV99 -> 0.2969226 | AY99: =(B99*11.7/100)/((AT99/2000*47)+(B99*11.7/100)) -> 0.33987323 | BB99: =C99*22.0462 -> 605.38865
A100: 43579 | B100: 30.2 | C100: 27.05 | D100: 29.42 | E100: =IF(AM100="","",AM100/2206.622)*100 -> 28.108575 | F100: 28.326851 | G100: 37.42 | H100: 28.22 | I100: 29.25 | J100: 23.894703 | K100: =B100-I100 -> 0.95 | L100: =IF(I100="","",IF(J100="","",I100-J100)) -> 5.355297 | M100: =B100-H100 -> 1.98 | N100: =B100-C100 -> 3.15 | O100: =C100-H100 -> -1.17 | P100: =D100-H100 -> 1.2 | Q100: =IF(E100="","",E100-H100) -> -0.11142499 | R100: =IF(F100="","",F100-H100) -> 0.1068515 | S100: =G100-H100 -> 9.2 | T100: =G100-B100 -> 7.22 | U100: =IF(P100=N100,"EQUAL",IF(N100<P100,"LOWER","HIGHER")) -> HIGHER | V100: 624.5 | W100: =IF(V100="","",IF(D100="","",D100-F100)) -> 1.0931485 | X100: =IF(AM100="","",AM100/22.04622) -> 28.134075 | Y100: =IF(X100="","",IF(D100="","",D100-X100)) -> 1.2859253 | Z100: =IF(X100="","",IF(F100="","",X100-F100)) -> -0.19277681 | AA100: =MONTH(A100) -> 4 | AB100: =YEAR(A100) -> 2019 | AC100: =WEEKNUM(A100) -> 17 | AF100: 43.853 | AG100: =IF(V100="","",V100*AF100/2204.622*100) -> 1242.2174 | AL100: =A100 -> 43579 | AM100: 620.25 | AN100: 3.9922 | AO100: =IF(AM100="","",AM100*AN100/2204.622*100) -> 112.31685 | AS100: =AV100/AU100 -> 0.22243947 | AT100: 295 | AU100: 8.26 | AV100: =(((C100/100*11.7)+(AT100/2000*47))-(AU100)) -> 1.83735 | AW100: =(((B100/100*11.7*0.98)+(AT100/2000*47))-(AU100)) -> 2.135232 | AX100: =AW100-AV100 -> 0.297882 | AY100: =(B100*11.7/100)/((AT100/2000*47)+(B100*11.7/100)) -> 0.33761072 | BB100: =C100*22.0462 -> 596.34971
A101: 43580 | B101: 29.92 | C101: 26.77 | D101: 29.14 | E101: =IF(AM101="","",AM101/2206.622)*100 -> 27.949962 | F101: 28.281492 | G101: 37.14 | H101: 27.94 | I101: 29.25 | J101: 23.667127 | K101: =B101-I101 -> 0.67 | L101: =IF(I101="","",IF(J101="","",I101-J101)) -> 5.5828733 | M101: =B101-H101 -> 1.98 | N101: =B101-C101 -> 3.15 | O101: =C101-H101 -> -1.17 | P101: =D101-H101 -> 1.2 | Q101: =IF(E101="","",E101-H101) -> 0.0099615249 | R101: =IF(F101="","",F101-H101) -> 0.34149225 | S101: =G101-H101 -> 9.2 | T101: =G101-B101 -> 7.22 | U101: =IF(P101=N101,"EQUAL",IF(N101<P101,"LOWER","HIGHER")) -> HIGHER | V101: 623.5 | W101: =IF(V101="","",IF(D101="","",D101-F101)) -> 0.85850775 | X101: =IF(AM101="","",AM101/22.04622) -> 27.975317 | Y101: =IF(X101="","",IF(D101="","",D101-X101)) -> 1.1646827 | Z101: =IF(X101="","",IF(F101="","",X101-F101)) -> -0.30617494 | AA101: =MONTH(A101) -> 4 | AB101: =YEAR(A101) -> 2019 | AC101: =WEEKNUM(A101) -> 17 | AF101: 44.92 | AG101: =IF(V101="","",V101*AF101/2204.622*100) -> 1270.4046 | AL101: =A101 -> 43580 | AM101: 616.75 | AN101: 3.953 | AO101: =IF(AM101="","",AM101*AN101/2204.622*100) -> 110.58643 | AS101: =AV101/AU101 -> 0.22958916 | AT101: 301 | AU101: 8.3 | AV101: =(((C101/100*11.7)+(AT101/2000*47))-(AU101)) -> 1.90559 | AW101: =(((B101/100*11.7*0.98)+(AT101/2000*47))-(AU101)) -> 2.2041272 | AX101: =AW101-AV101 -> 0.2985372 | AY101: =(B101*11.7/100)/((AT101/2000*47)+(B101*11.7/100)) -> 0.33105671 | BB101: =C101*22.0462 -> 590.17677
A102: 43581 | B102: 29.8 | C102: 26.65 | D102: 29.27 | E102: =IF(AM102="","",AM102/2206.622)*100 -> 28.176552 | F102: 28.202114 | G102: 37.02 | H102: 27.84 | I102: 29 | J102: 23.267066 | K102: =B102-I102 -> 0.8 | L102: =IF(I102="","",IF(J102="","",I102-J102)) -> 5.7329338 | M102: =B102-H102 -> 1.96 | N102: =B102-C102 -> 3.15 | O102: =C102-H102 -> -1.19 | P102: =D102-H102 -> 1.43 | Q102: =IF(E102="","",E102-H102) -> 0.33655221 | R102: =IF(F102="","",F102-H102) -> 0.36211356 | S102: =G102-H102 -> 9.18 | T102: =G102-B102 -> 7.22 | U102: =IF(P102=N102,"EQUAL",IF(N102<P102,"LOWER","HIGHER")) -> HIGHER | V102: 621.75 | W102: =IF(V102="","",IF(D102="","",D102-F102)) -> 1.0678864 | X102: =IF(AM102="","",AM102/22.04622) -> 28.202114 | Y102: =IF(X102="","",IF(D102="","",D102-X102)) -> 1.0678864 | Z102: =IF(X102="","",IF(F102="","",X102-F102)) -> -3.5527137e-15 | AA102: =MONTH(A102) -> 4 | AB102: =YEAR(A102) -> 2019 | AC102: =WEEKNUM(A102) -> 17 | AF102: 45.809 | AG102: =IF(V102="","",V102*AF102/2204.622*100) -> 1291.9106 | AL102: =A102 -> 43581 | AM102: 621.75 | AN102: 3.9288 | AO102: =IF(AM102="","",AM102*AN102/2204.622*100) -> 110.80046 | AS102: =AV102/AU102 -> 0.21824848 | AT102: 295 | AU102: 8.25 | AV102: =(((C102/100*11.7)+(AT102/2000*47))-(AU102)) -> 1.80055 | AW102: =(((B102/100*11.7*0.98)+(AT102/2000*47))-(AU102)) -> 2.099368 | AX102: =AW102-AV102 -> 0.298818 | AY102: =(B102*11.7/100)/((AT102/2000*47)+(B102*11.7/100)) -> 0.33463543 | BB102: =C102*22.0462 -> 587.53123
A103: 43584 | B103: 30.16 | C103: 27.01 | D103: 29.63 | E103: =IF(AM103="","",AM103/2206.622)*100 -> 28.448461 | F103: 28.474269 | G103: 37.88 | H103: 28.19 | I103: 29 | J103: 23.15166 | K103: =B103-I103 -> 1.16 | L103: =IF(I103="","",IF(J103="","",I103-J103)) -> 5.8483403 | M103: =B103-H103 -> 1.97 | N103: =B103-C103 -> 3.15 | O103: =C103-H103 -> -1.18 | P103: =D103-H103 -> 1.44 | Q103: =IF(E103="","",E103-H103) -> 0.25846104 | R103: =IF(F103="","",F103-H103) -> 0.28426906 | S103: =G103-H103 -> 9.69 | T103: =G103-B103 -> 7.72 | U103: =IF(P103=N103,"EQUAL",IF(N103<P103,"LOWER","HIGHER")) -> HIGHER | V103: 627.75 | W103: =IF(V103="","",IF(D103="","",D103-F103)) -> 1.1557309 | X103: =IF(AM103="","",AM103/22.04622) -> 28.474269 | Y103: =IF(X103="","",IF(D103="","",D103-X103)) -> 1.1557309 | Z103: =IF(X103="","",IF(F103="","",X103-F103)) -> 0 | AA103: =MONTH(A103) -> 4 | AB103: =YEAR(A103) -> 2019 | AC103: =WEEKNUM(A103) -> 18 | AF103: 44.35 | AG103: =IF(V103="","",V103*AF103/2204.622*100) -> 1262.8338 | AL103: =A103 -> 43584 | AM103: 627.75 | AN103: 3.9442 | AO103: =IF(AM103="","",AM103*AN103/2204.622*100) -> 112.30821 | AS103: =AV103/AU103 -> 0.23774848 | AT103: 299 | AU103: 8.23 | AV103: =(((C103/100*11.7)+(AT103/2000*47))-(AU103)) -> 1.95667 | AW103: =(((B103/100*11.7*0.98)+(AT103/2000*47))-(AU103)) -> 2.2546456 | AX103: =AW103-AV103 -> 0.2979756 | AY103: =(B103*11.7/100)/((AT103/2000*47)+(B103*11.7/100)) -> 0.33431042 | BB103: =C103*22.0462 -> 595.46786
A104: 43585 | B104: 29.86 | C104: 26.71 | D104: 29.33 | E104: =IF(AM104="","",AM104/2206.622)*100 -> 28.119905 | F104: 27.997997 | G104: 37.58 | H104: 27.88 | I104: 29 | J104: 22.986996 | K104: =B104-I104 -> 0.86 | L104: =IF(I104="","",IF(J104="","",I104-J104)) -> 6.0130036 | M104: =B104-H104 -> 1.98 | N104: =B104-C104 -> 3.15 | O104: =C104-H104 -> -1.17 | P104: =D104-H104 -> 1.45 | Q104: =IF(E104="","",E104-H104) -> 0.23990454 | R104: =IF(F104="","",F104-H104) -> 0.11799694 | S104: =G104-H104 -> 9.7 | T104: =G104-B104 -> 7.72 | U104: =IF(P104=N104,"EQUAL",IF(N104<P104,"LOWER","HIGHER")) -> HIGHER | V104: 617.25 | W104: =IF(V104="","",IF(D104="","",D104-F104)) -> 1.3320031 | X104: =IF(AM104="","",AM104/22.04622) -> 28.145414 | Y104: =IF(X104="","",IF(D104="","",D104-X104)) -> 1.1845855 | Z104: =IF(X104="","",IF(F104="","",X104-F104)) -> 0.14741756 | AA104: =MONTH(A104) -> 4 | AB104: =YEAR(A104) -> 2019 | AC104: =WEEKNUM(A104) -> 18 | AF104: 44.242 | AG104: =IF(V104="","",V104*AF104/2204.622*100) -> 1238.6874 | AL104: =A104 -> 43585 | AM104: 620.5 | AN104: 3.9207 | AO104: =IF(AM104="","",AM104*AN104/2204.622*100) -> 110.34973 | AS104: =AV104/AU104 -> 0.24406495 | AT104: 299 | AU104: 8.16 | AV104: =(((C104/100*11.7)+(AT104/2000*47))-(AU104)) -> 1.99157 | AW104: =(((B104/100*11.7*0.98)+(AT104/2000*47))-(AU104)) -> 2.2902476 | AX104: =AW104-AV104 -> 0.2986776 | AY104: =(B104*11.7/100)/((AT104/2000*47)+(B104*11.7/100)) -> 0.33208937 | BB104: =C104*22.0462 -> 588.854
A105: 43586 | B105: 29.93 | C105: 26.78 | D105: 29.4 | E105: =IF(AM105="","",AM105/2206.622)*100 -> #VALUE! | G105: 37.65 | H105: 27.65 | I105: 29 | K105: =B105-I105 -> 0.93 | L105: =IF(I105="","",IF(J105="","",I105-J105)) | M105: =B105-H105 -> 2.28 | N105: =B105-C105 -> 3.15 | O105: =C105-H105 -> -0.87 | P105: =D105-H105 -> 1.75 | Q105: =IF(E105="","",E105-H105) -> #VALUE! | R105: =IF(F105="","",F105-H105) | S105: =G105-H105 -> 10 | T105: =G105-B105 -> 7.72 | U105: =IF(P105=N105,"EQUAL",IF(N105<P105,"LOWER","HIGHER")) -> HIGHER | X105: =IF(AM105="","",AM105/22.04622) | Y105: =IF(X105="","",IF(D105="","",D105-X105)) | Z105: =IF(X105="","",IF(F105="","",X105-F105)) | AA105: =MONTH(A105) -> 5 | AB105: =YEAR(A105) -> 2019 | AC105: =WEEKNUM(A105) -> 18 | AF105: 44.11 | AG105: =IF(V105="","",V105*AF105/2204.622*100) | AL105: =A105 -> 43586 | AN105: 3.9195 | AO105: =IF(AM105="","",AM105*AN105/2204.622*100) | AS105: =AV105/AU105 -> 0.21714148 | AT105: 295 | AU105: 8.27 | AV105: =(((C105/100*11.7)+(AT105/2000*47))-(AU105)) -> 1.79576 | AW105: =(((B105/100*11.7*0.98)+(AT105/2000*47))-(AU105)) -> 2.0942738 | AX105: =AW105-AV105 -> 0.2985138 | AY105: =(B105*11.7/100)/((AT105/2000*47)+(B105*11.7/100)) -> 0.33560533 | BB105: =C105*22.0462 -> 590.39724
A106: 43587 | B106: 29.78 | C106: 26.63 | D106: 29.25 | E106: =IF(AM106="","",AM106/2206.622)*100 -> 27.972621 | F106: 27.895939 | G106: 37.5 | H106: 27.5 | I106: 29 | J106: 22.243636 | K106: =B106-I106 -> 0.78 | L106: =IF(I106="","",IF(J106="","",I106-J106)) -> 6.7563635 | M106: =B106-H106 -> 2.28 | N106: =B106-C106 -> 3.15 | O106: =C106-H106 -> -0.87 | P106: =D106-H106 -> 1.75 | Q106: =IF(E106="","",E106-H106) -> 0.47262059 | R106: =IF(F106="","",F106-H106) -> 0.39593862 | S106: =G106-H106 -> 10 | T106: =G106-B106 -> 7.72 | U106: =IF(P106=N106,"EQUAL",IF(N106<P106,"LOWER","HIGHER")) -> HIGHER | V106: 615 | W106: =IF(V106="","",IF(D106="","",D106-F106)) -> 1.3540614 | X106: =IF(AM106="","",AM106/22.04622) -> 27.997997 | Y106: =IF(X106="","",IF(D106="","",D106-X106)) -> 1.2520031 | Z106: =IF(X106="","",IF(F106="","",X106-F106)) -> 0.10205831 | AA106: =MONTH(A106) -> 5 | AB106: =YEAR(A106) -> 2019 | AC106: =WEEKNUM(A106) -> 18 | AF106: 44.725 | AG106: =IF(V106="","",V106*AF106/2204.622*100) -> 1247.6459 | AL106: =A106 -> 43587 | AM106: 617.25 | AN106: 3.9654 | AO106: =IF(AM106="","",AM106*AN106/2204.622*100) -> 111.02326 | AS106: =AV106/AU106 -> 0.21976895 | AT106: 292 | AU106: 8.18 | AV106: =(((C106/100*11.7)+(AT106/2000*47))-(AU106)) -> 1.79771 | AW106: =(((B106/100*11.7*0.98)+(AT106/2000*47))-(AU106)) -> 2.0965748 | AX106: =AW106-AV106 -> 0.2988648 | AY106: =(B106*11.7/100)/((AT106/2000*47)+(B106*11.7/100)) -> 0.33676517 | BB106: =C106*22.0462 -> 587.09031
A107: 43588 | B107: 29.63 | C107: 26.48 | D107: 29.1 | E107: =IF(AM107="","",AM107/2206.622)*100 -> 27.949962 | F107: 27.884599 | G107: 37.35 | H107: 27.35 | I107: 29 | J107: 21.984065 | K107: =B107-I107 -> 0.63 | L107: =IF(I107="","",IF(J107="","",I107-J107)) -> 7.0159347 | M107: =B107-H107 -> 2.28 | N107: =B107-C107 -> 3.15 | O107: =C107-H107 -> -0.87 | P107: =D107-H107 -> 1.75 | Q107: =IF(E107="","",E107-H107) -> 0.59996152 | R107: =IF(F107="","",F107-H107) -> 0.53459881 | S107: =G107-H107 -> 10 | T107: =G107-B107 -> 7.72 | U107: =IF(P107=N107,"EQUAL",IF(N107<P107,"LOWER","HIGHER")) -> HIGHER | V107: 614.75 | W107: =IF(V107="","",IF(D107="","",D107-F107)) -> 1.2154012 | X107: =IF(AM107="","",AM107/22.04622) -> 27.975317 | Y107: =IF(X107="","",IF(D107="","",D107-X107)) -> 1.1246827 | Z107: =IF(X107="","",IF(F107="","",X107-F107)) -> 0.0907185 | AA107: =MONTH(A107) -> 5 | AB107: =YEAR(A107) -> 2019 | AC107: =WEEKNUM(A107) -> 18 | AF107: 44.44 | AG107: =IF(V107="","",V107*AF107/2204.622*100) -> 1239.1916 | AL107: =A107 -> 43588 | AM107: 616.75 | AN107: 3.9378 | AO107: =IF(AM107="","",AM107*AN107/2204.622*100) -> 110.1612 | AS107: =AV107/AU107 -> 0.22199021 | AT107: 293 | AU107: 8.17 | AV107: =(((C107/100*11.7)+(AT107/2000*47))-(AU107)) -> 1.81366 | AW107: =(((B107/100*11.7*0.98)+(AT107/2000*47))-(AU107)) -> 2.1128758 | AX107: =AW107-AV107 -> 0.2992158 | AY107: =(B107*11.7/100)/((AT107/2000*47)+(B107*11.7/100)) -> 0.33487632 | BB107: =C107*22.0462 -> 583.78338
A108: 43591 | B108: 29.41 | C108: 26.26 | D108: 28.88 | E108: =IF(AM108="","",AM108/2206.622)*100 -> #VALUE! | G108: 37.13 | H108: 27.13 | I108: 29 | J108: 21.727803 | K108: =B108-I108 -> 0.41 | L108: =IF(I108="","",IF(J108="","",I108-J108)) -> 7.2721973 | M108: =B108-H108 -> 2.28 | N108: =B108-C108 -> 3.15 | O108: =C108-H108 -> -0.87 | P108: =D108-H108 -> 1.75 | Q108: =IF(E108="","",E108-H108) -> #VALUE! | R108: =IF(F108="","",F108-H108) | S108: =G108-H108 -> 10 | T108: =G108-B108 -> 7.72 | U108: =IF(P108=N108,"EQUAL",IF(N108<P108,"LOWER","HIGHER")) -> HIGHER | X108: =IF(AM108="","",AM108/22.04622) | Y108: =IF(X108="","",IF(D108="","",D108-X108)) | Z108: =IF(X108="","",IF(F108="","",X108-F108)) | AA108: =MONTH(A108) -> 5 | AB108: =YEAR(A108) -> 2019 | AC108: =WEEKNUM(A108) -> 19 | AF108: 44.64 | AG108: =IF(V108="","",V108*AF108/2204.622*100) | AL108: =A108 -> 43591 | AN108: 3.9683 | AO108: =IF(AM108="","",AM108*AN108/2204.622*100) | AS108: =AV108/AU108 -> 0.24961258 | AT108: 292 | AU108: 7.95 | AV108: =(((C108/100*11.7)+(AT108/2000*47))-(AU108)) -> 1.98442 | AW108: =(((B108/100*11.7*0.98)+(AT108/2000*47))-(AU108)) -> 2.2841506 | AX108: =AW108-AV108 -> 0.2997306 | AY108: =(B108*11.7/100)/((AT108/2000*47)+(B108*11.7/100)) -> 0.33397845 | BB108: =C108*22.0462 -> 578.93321
A109: 43592 | B109: 29.75 | C109: 26.6 | D109: 28.85 | E109: =IF(AM109="","",AM109/2206.622)*100 -> 28.017939 | F109: 27.941298 | G109: 37.1 | H109: 27.1 | I109: 29 | J109: 22.302269 | K109: =B109-I109 -> 0.75 | L109: =IF(I109="","",IF(J109="","",I109-J109)) -> 6.6977308 | M109: =B109-H109 -> 2.65 | N109: =B109-C109 -> 3.15 | O109: =C109-H109 -> -0.5 | P109: =D109-H109 -> 1.75 | Q109: =IF(E109="","",E109-H109) -> 0.91793873 | R109: =IF(F109="","",F109-H109) -> 0.84129787 | S109: =G109-H109 -> 10 | T109: =G109-B109 -> 7.35 | U109: =IF(P109=N109,"EQUAL",IF(N109<P109,"LOWER","HIGHER")) -> HIGHER | V109: 616 | W109: =IF(V109="","",IF(D109="","",D109-F109)) -> 0.90870213 | X109: =IF(AM109="","",AM109/22.04622) -> 28.043356 | Y109: =IF(X109="","",IF(D109="","",D109-X109)) -> 0.80664381 | Z109: =IF(X109="","",IF(F109="","",X109-F109)) -> 0.10205831 | AA109: =MONTH(A109) -> 5 | AB109: =YEAR(A109) -> 2019 | AC109: =WEEKNUM(A109) -> 19 | AF109: 45.26 | AG109: =IF(V109="","",V109*AF109/2204.622*100) -> 1264.6231 | AL109: =A109 -> 43592 | AM109: 618.25 | AN109: 3.97 | AO109: =IF(AM109="","",AM109*AN109/2204.622*100) -> 111.33212 | AS109: =AV109/AU109 -> 0.24123116 | AT109: 288 | AU109: 7.96 | AV109: =(((C109/100*11.7)+(AT109/2000*47))-(AU109)) -> 1.9202 | AW109: =(((B109/100*11.7*0.98)+(AT109/2000*47))-(AU109)) -> 2.219135 | AX109: =AW109-AV109 -> 0.298935 | AY109: =(B109*11.7/100)/((AT109/2000*47)+(B109*11.7/100)) -> 0.33962678 | BB109: =C109*22.0462 -> 586.42892
A110: 43593 | B110: 29.65 | C110: 26.5 | D110: 28.75 | E110: =IF(AM110="","",AM110/2206.622)*100 -> 28.244529 | F110: 28.224793 | G110: 37 | H110: 27 | I110: 29 | J110: 22.269456 | K110: =B110-I110 -> 0.65 | L110: =IF(I110="","",IF(J110="","",I110-J110)) -> 6.7305443 | M110: =B110-H110 -> 2.65 | N110: =B110-C110 -> 3.15 | O110: =C110-H110 -> -0.5 | P110: =D110-H110 -> 1.75 | Q110: =IF(E110="","",E110-H110) -> 1.2445294 | R110: =IF(F110="","",F110-H110) -> 1.2247932 | S110: =G110-H110 -> 10 | T110: =G110-B110 -> 7.35 | U110: =IF(P110=N110,"EQUAL",IF(N110<P110,"LOWER","HIGHER")) -> HIGHER | V110: 622.25 | W110: =IF(V110="","",IF(D110="","",D110-F110)) -> 0.52520682 | X110: =IF(AM110="","",AM110/22.04622) -> 28.270152 | Y110: =IF(X110="","",IF(D110="","",D110-X110)) -> 0.47984757 | Z110: =IF(X110="","",IF(F110="","",X110-F110)) -> 0.04535925 | AA110: =MONTH(A110) -> 5 | AB110: =YEAR(A110) -> 2019 | AC110: =WEEKNUM(A110) -> 19 | AF110: 44.97 | AG110: =IF(V110="","",V110*AF110/2204.622*100) -> 1269.2689 | AL110: =A110 -> 43593 | AM110: 623.25 | AN110: 3.9279 | AO110: =IF(AM110="","",AM110*AN110/2204.622*100) -> 111.04233 | AS110: =AV110/AU110 -> 0.24602273 | AT110: 288 | AU110: 7.92 | AV110: =(((C110/100*11.7)+(AT110/2000*47))-(AU110)) -> 1.9485 | AW110: =(((B110/100*11.7*0.98)+(AT110/2000*47))-(AU110)) -> 2.247669 | AX110: =AW110-AV110 -> 0.299169 | AY110: =(B110*11.7/100)/((AT110/2000*47)+(B110*11.7/100)) -> 0.33887204 | BB110: =C110*22.0462 -> 584.2243
A111: 43594 | B111: 29.28 | C111: 26.13 | D111: 28.38 | E111: =IF(AM111="","",AM111/2206.622)*100 -> 28.323836 | F111: 28.247473 | G111: 36.63 | H111: 26.63 | I111: 29 | J111: 21.893048 | K111: =B111-I111 -> 0.28 | L111: =IF(I111="","",IF(J111="","",I111-J111)) -> 7.1069517 | M111: =B111-H111 -> 2.65 | N111: =B111-C111 -> 3.15 | O111: =C111-H111 -> -0.5 | P111: =D111-H111 -> 1.75 | Q111: =IF(E111="","",E111-H111) -> 1.6938362 | R111: =IF(F111="","",F111-H111) -> 1.6174728 | S111: =G111-H111 -> 10 | T111: =G111-B111 -> 7.35 | U111: =IF(P111=N111,"EQUAL",IF(N111<P111,"LOWER","HIGHER")) -> HIGHER | V111: 622.75 | W111: =IF(V111="","",IF(D111="","",D111-F111)) -> 0.13252719 | X111: =IF(AM111="","",AM111/22.04622) -> 28.349531 | Y111: =IF(X111="","",IF(D111="","",D111-X111)) -> 0.030468879 | Z111: =IF(X111="","",IF(F111="","",X111-F111)) -> 0.10205831 | AA111: =MONTH(A111) -> 5 | AB111: =YEAR(A111) -> 2019 | AC111: =WEEKNUM(A111) -> 19 | AF111: 45.22 | AG111: =IF(V111="","",V111*AF111/2204.622*100) -> 1277.3507 | AL111: =A111 -> 43594 | AM111: 625 | AN111: 3.9456 | AO111: =IF(AM111="","",AM111*AN111/2204.622*100) -> 111.85591 | AS111: =AV111/AU111 -> 0.2507982 | AT111: 284 | AU111: 7.78 | AV111: =(((C111/100*11.7)+(AT111/2000*47))-(AU111)) -> 1.95121 | AW111: =(((B111/100*11.7*0.98)+(AT111/2000*47))-(AU111)) -> 2.2512448 | AX111: =AW111-AV111 -> 0.3000348 | AY111: =(B111*11.7/100)/((AT111/2000*47)+(B111*11.7/100)) -> 0.33919222 | BB111: =C111*22.0462 -> 576.06721
A112: 43595 | B112: 29.44 | C112: 26.29 | D112: 28.54 | E112: =IF(AM112="","",AM112/2206.622)*100 -> 28.301177 | F112: 28.42891 | G112: 36.79 | H112: 26.79 | I112: 29 | J112: 21.648485 | K112: =B112-I112 -> 0.44 | L112: =IF(I112="","",IF(J112="","",I112-J112)) -> 7.3515151 | M112: =B112-H112 -> 2.65 | N112: =B112-C112 -> 3.15 | O112: =C112-H112 -> -0.5 | P112: =D112-H112 -> 1.75 | Q112: =IF(E112="","",E112-H112) -> 1.5111771 | R112: =IF(F112="","",F112-H112) -> 1.6389098 | S112: =G112-H112 -> 10 | T112: =G112-B112 -> 7.35 | U112: =IF(P112=N112,"EQUAL",IF(N112<P112,"LOWER","HIGHER")) -> HIGHER | V112: 626.75 | W112: =IF(V112="","",IF(D112="","",D112-F112)) -> 0.11109019 | X112: =IF(AM112="","",AM112/22.04622) -> 28.326851 | Y112: =IF(X112="","",IF(D112="","",D112-X112)) -> 0.2131485 | Z112: =IF(X112="","",IF(F112="","",X112-F112)) -> -0.10205831 | AA112: =MONTH(A112) -> 5 | AB112: =YEAR(A112) -> 2019 | AC112: =WEEKNUM(A112) -> 19 | AF112: 44.715 | AG112: =IF(V112="","",V112*AF112/2204.622*100) -> 1271.1987 | AL112: =A112 -> 43595 | AM112: 624.5 | AN112: 3.9566 | AO112: =IF(AM112="","",AM112*AN112/2204.622*100) -> 112.07802 | AS112: =AV112/AU112 -> 0.25360853 | AT112: 282 | AU112: 7.74 | AV112: =(((C112/100*11.7)+(AT112/2000*47))-(AU112)) -> 1.96293 | AW112: =(((B112/100*11.7*0.98)+(AT112/2000*47))-(AU112)) -> 2.2625904 | AX112: =AW112-AV112 -> 0.2996604 | AY112: =(B112*11.7/100)/((AT112/2000*47)+(B112*11.7/100)) -> 0.34200336 | BB112: =C112*22.0462 -> 579.5946
A113: 43598 | B113: 29.26 | C113: 26.11 | D113: 28.36 | E113: =IF(AM113="","",AM113/2206.622)*100 -> 28.289848 | F113: 28.41757 | G113: 36.61 | H113: 26.61 | I113: 29 | J113: 21.622478 | K113: =B113-I113 -> 0.26 | L113: =IF(I113="","",IF(J113="","",I113-J113)) -> 7.3775224 | M113: =B113-H113 -> 2.65 | N113: =B113-C113 -> 3.15 | O113: =C113-H113 -> -0.5 | P113: =D113-H113 -> 1.75 | Q113: =IF(E113="","",E113-H113) -> 1.6798476 | R113: =IF(F113="","",F113-H113) -> 1.80757 | S113: =G113-H113 -> 10 | T113: =G113-B113 -> 7.35 | U113: =IF(P113=N113,"EQUAL",IF(N113<P113,"LOWER","HIGHER")) -> HIGHER | V113: 626.5 | W113: =IF(V113="","",IF(D113="","",D113-F113)) -> -0.057569996 | X113: =IF(AM113="","",AM113/22.04622) -> 28.315512 | Y113: =IF(X113="","",IF(D113="","",D113-X113)) -> 0.044488316 | Z113: =IF(X113="","",IF(F113="","",X113-F113)) -> -0.10205831 | AA113: =MONTH(A113) -> 5 | AB113: =YEAR(A113) -> 2019 | AC113: =WEEKNUM(A113) -> 20 | AF113: 45.085 | AG113: =IF(V113="","",V113*AF113/2204.622*100) -> 1281.2061 | AL113: =A113 -> 43598 | AM113: 624.25 | AN113: 3.9925 | AO113: =IF(AM113="","",AM113*AN113/2204.622*100) -> 113.04968 | AS113: =AV113/AU113 -> 0.25575486 | AT113: 282 | AU113: 7.71 | AV113: =(((C113/100*11.7)+(AT113/2000*47))-(AU113)) -> 1.97187 | AW113: =(((B113/100*11.7*0.98)+(AT113/2000*47))-(AU113)) -> 2.2719516 | AX113: =AW113-AV113 -> 0.3000816 | AY113: =(B113*11.7/100)/((AT113/2000*47)+(B113*11.7/100)) -> 0.34062457 | BB113: =C113*22.0462 -> 575.62628
A114: 43599 | B114: 29.65 | C114: 26.5 | D114: 28.75 | E114: =IF(AM114="","",AM114/2206.622)*100 -> 29.264188 | F114: 29.188677 | G114: 37 | H114: 27 | I114: 29 | J114: 21.890816 | K114: =B114-I114 -> 0.65 | L114: =IF(I114="","",IF(J114="","",I114-J114)) -> 7.1091843 | M114: =B114-H114 -> 2.65 | N114: =B114-C114 -> 3.15 | O114: =C114-H114 -> -0.5 | P114: =D114-H114 -> 1.75 | Q114: =IF(E114="","",E114-H114) -> 2.2641875 | R114: =IF(F114="","",F114-H114) -> 2.1886772 | S114: =G114-H114 -> 10 | T114: =G114-B114 -> 7.35 | U114: =IF(P114=N114,"EQUAL",IF(N114<P114,"LOWER","HIGHER")) -> HIGHER | V114: 643.5 | W114: =IF(V114="","",IF(D114="","",D114-F114)) -> -0.43867724 | X114: =IF(AM114="","",AM114/22.04622) -> 29.290736 | Y114: =IF(X114="","",IF(D114="","",D114-X114)) -> -0.54073555 | Z114: =IF(X114="","",IF(F114="","",X114-F114)) -> 0.10205831 | AA114: =MONTH(A114) -> 5 | AB114: =YEAR(A114) -> 2019 | AC114: =WEEKNUM(A114) -> 20 | AF114: 44.93 | AG114: =IF(V114="","",V114*AF114/2204.622*100) -> 1311.4473 | AL114: =A114 -> 43599 | AM114: 645.75 | AN114: 3.9745 | AO114: =IF(AM114="","",AM114*AN114/2204.622*100) -> 116.41603 | AS114: =AV114/AU114 -> 0.24825 | AT114: 293 | AU114: 8 | AV114: =(((C114/100*11.7)+(AT114/2000*47))-(AU114)) -> 1.986 | AW114: =(((B114/100*11.7*0.98)+(AT114/2000*47))-(AU114)) -> 2.285169 | AX114: =AW114-AV114 -> 0.299169 | AY114: =(B114*11.7/100)/((AT114/2000*47)+(B114*11.7/100)) -> 0.33502663 | BB114: =C114*22.0462 -> 584.2243
A115: 43600 | B115: 29.89 | C115: 26.74 | D115: 28.99 | E115: =IF(AM115="","",AM115/2206.622)*100 -> 29.128233 | F115: 29.245376 | G115: 37.24 | H115: 27.24 | I115: 29 | J115: 22.043748 | K115: =B115-I115 -> 0.89 | L115: =IF(I115="","",IF(J115="","",I115-J115)) -> 6.9562524 | M115: =B115-H115 -> 2.65 | N115: =B115-C115 -> 3.15 | O115: =C115-H115 -> -0.5 | P115: =D115-H115 -> 1.75 | Q115: =IF(E115="","",E115-H115) -> 1.8882331 | R115: =IF(F115="","",F115-H115) -> 2.0053763 | S115: =G115-H115 -> 10 | T115: =G115-B115 -> 7.35 | U115: =IF(P115=N115,"EQUAL",IF(N115<P115,"LOWER","HIGHER")) -> HIGHER | V115: 644.75 | W115: =IF(V115="","",IF(D115="","",D115-F115)) -> -0.2553763 | X115: =IF(AM115="","",AM115/22.04622) -> 29.154658 | Y115: =IF(X115="","",IF(D115="","",D115-X115)) -> -0.16465781 | Z115: =IF(X115="","",IF(F115="","",X115-F115)) -> -0.0907185 | AA115: =MONTH(A115) -> 5 | AB115: =YEAR(A115) -> 2019 | AC115: =WEEKNUM(A115) -> 20 | AF115: 44.912 | AG115: =IF(V115="","",V115*AF115/2204.622*100) -> 1313.4683 | AL115: =A115 -> 43600 | AM115: 642.75 | AN115: 4.0012 | AO115: =IF(AM115="","",AM115*AN115/2204.622*100) -> 116.65362 | AS115: =AV115/AU115 -> 0.25137811 | AT115: 295 | AU115: 8.04 | AV115: =(((C115/100*11.7)+(AT115/2000*47))-(AU115)) -> 2.02108 | AW115: =(((B115/100*11.7*0.98)+(AT115/2000*47))-(AU115)) -> 2.3196874 | AX115: =AW115-AV115 -> 0.2986074 | AY115: =(B115*11.7/100)/((AT115/2000*47)+(B115*11.7/100)) -> 0.3353072 | BB115: =C115*22.0462 -> 589.51539
A116: 43601 | B116: 30.37 | C116: 27.22 | D116: 29.47 | E116: =IF(AM116="","",AM116/2206.622)*100 -> 28.675052 | F116: 28.803124 | G116: 37.72 | H116: 27.72 | I116: 29 | J116: 22.826718 | K116: =B116-I116 -> 1.37 | L116: =IF(I116="","",IF(J116="","",I116-J116)) -> 6.1732817 | M116: =B116-H116 -> 2.65 | N116: =B116-C116 -> 3.15 | O116: =C116-H116 -> -0.5 | P116: =D116-H116 -> 1.75 | Q116: =IF(E116="","",E116-H116) -> 0.95505173 | R116: =IF(F116="","",F116-H116) -> 1.0831236 | S116: =G116-H116 -> 10 | T116: =G116-B116 -> 7.35 | U116: =IF(P116=N116,"EQUAL",IF(N116<P116,"LOWER","HIGHER")) -> HIGHER | V116: 635 | W116: =IF(V116="","",IF(D116="","",D116-F116)) -> 0.66687638 | X116: =IF(AM116="","",AM116/22.04622) -> 28.701065 | Y116: =IF(X116="","",IF(D116="","",D116-X116)) -> 0.76893469 | Z116: =IF(X116="","",IF(F116="","",X116-F116)) -> -0.10205831 | AA116: =MONTH(A116) -> 5 | AB116: =YEAR(A116) -> 2019 | AC116: =WEEKNUM(A116) -> 20 | AF116: 44.681 | AG116: =IF(V116="","",V116*AF116/2204.622*100) -> 1286.9524 | AL116: =A116 -> 43601 | AM116: 632.75 | AN116: 4.0467 | AO116: =IF(AM116="","",AM116*AN116/2204.622*100) -> 116.1446 | AS116: =AV116/AU116 -> 0.2579505 | AT116: 297 | AU116: 8.08 | AV116: =(((C116/100*11.7)+(AT116/2000*47))-(AU116)) -> 2.08424 | AW116: =(((B116/100*11.7*0.98)+(AT116/2000*47))-(AU116)) -> 2.3817242 | AX116: =AW116-AV116 -> 0.2974842 | AY116: =(B116*11.7/100)/((AT116/2000*47)+(B116*11.7/100)) -> 0.33735506 | BB116: =C116*22.0462 -> 600.09756
A117: 43602 | B117: 29.87 | C117: 26.72 | D117: 29.72 | E117: =IF(AM117="","",AM117/2206.622)*100 -> 28.346495 | F117: 28.270152 | G117: 37.22 | H117: 27.22 | I117: 28.8 | J117: 22.771973 | K117: =B117-I117 -> 1.07 | L117: =IF(I117="","",IF(J117="","",I117-J117)) -> 6.0280269 | M117: =B117-H117 -> 2.65 | N117: =B117-C117 -> 3.15 | O117: =C117-H117 -> -0.5 | P117: =D117-H117 -> 2.5 | Q117: =IF(E117="","",E117-H117) -> 1.1264952 | R117: =IF(F117="","",F117-H117) -> 1.0501524 | S117: =G117-H117 -> 10 | T117: =G117-B117 -> 7.35 | U117: =IF(P117=N117,"EQUAL",IF(N117<P117,"LOWER","HIGHER")) -> HIGHER | V117: 623.25 | W117: =IF(V117="","",IF(D117="","",D117-F117)) -> 1.4498476 | X117: =IF(AM117="","",AM117/22.04622) -> 28.372211 | Y117: =IF(X117="","",IF(D117="","",D117-X117)) -> 1.3477893 | Z117: =IF(X117="","",IF(F117="","",X117-F117)) -> 0.10205831 | AA117: =MONTH(A117) -> 5 | AB117: =YEAR(A117) -> 2019 | AC117: =WEEKNUM(A117) -> 20 | AF117: 44.945 | AG117: =IF(V117="","",V117*AF117/2204.622*100) -> 1270.602 | AL117: =A117 -> 43602 | AM117: 625.5 | AN117: 4.0997 | AO117: =IF(AM117="","",AM117*AN117/2204.622*100) -> 116.31755 | AS117: =AV117/AU117 -> 0.25541013 | AT117: 289 | AU117: 7.9 | AV117: =(((C117/100*11.7)+(AT117/2000*47))-(AU117)) -> 2.01774 | AW117: =(((B117/100*11.7*0.98)+(AT117/2000*47))-(AU117)) -> 2.3163942 | AX117: =AW117-AV117 -> 0.2986542 | AY117: =(B117*11.7/100)/((AT117/2000*47)+(B117*11.7/100)) -> 0.33975223 | BB117: =C117*22.0462 -> 589.07446
A118: 43605 | B118: 30.15 | C118: 27 | D118: 30 | E118: =IF(AM118="","",AM118/2206.622)*100 -> 28.47112 | F118: 28.39489 | G118: 37.5 | H118: 27.5 | I118: 28.8 | K118: =B118-I118 -> 1.35 | L118: =IF(I118="","",IF(J118="","",I118-J118)) | M118: =B118-H118 -> 2.65 | N118: =B118-C118 -> 3.15 | O118: =C118-H118 -> -0.5 | P118: =D118-H118 -> 2.5 | Q118: =IF(E118="","",E118-H118) -> 0.97112011 | R118: =IF(F118="","",F118-H118) -> 0.89489037 | S118: =G118-H118 -> 10 | T118: =G118-B118 -> 7.35 | U118: =IF(P118=N118,"EQUAL",IF(N118<P118,"LOWER","HIGHER")) -> HIGHER | V118: 626 | W118: =IF(V118="","",IF(D118="","",D118-F118)) -> 1.6051096 | X118: =IF(AM118="","",AM118/22.04622) -> 28.496949 | Y118: =IF(X118="","",IF(D118="","",D118-X118)) -> 1.5030513 | Z118: =IF(X118="","",IF(F118="","",X118-F118)) -> 0.10205831 | AA118: =MONTH(A118) -> 5 | AB118: =YEAR(A118) -> 2019 | AC118: =WEEKNUM(A118) -> 21 | AF118: 45.145 | AG118: =IF(V118="","",V118*AF118/2204.622*100) -> 1281.8873 | AL118: =A118 -> 43605 | AM118: 628.25 | AN118: 4.0963 | AO118: =IF(AM118="","",AM118*AN118/2204.622*100) -> 116.73205 | AS118: =AV118/AU118 -> 0.252625 | AT118: 292 | AU118: 8 | AV118: =(((C118/100*11.7)+(AT118/2000*47))-(AU118)) -> 2.021 | AW118: =(((B118/100*11.7*0.98)+(AT118/2000*47))-(AU118)) -> 2.318999 | AX118: =AW118-AV118 -> 0.297999 | AY118: =(B118*11.7/100)/((AT118/2000*47)+(B118*11.7/100)) -> 0.33952866 | BB118: =C118*22.0462 -> 595.2474
...

Sheet Monthly Data
A1: Copy AI - AK to CE - CL to set basis levels. | D1: RBD - Central Illinois | I1: Crude-degummed - Central Illinois | N1: Crude-degummed - Gulf | S1: Crude-degummed Argentina - UpRiver | X1: Canola Oil - Los Angeles | AC1: SBO Futures | AI1: RBD Basis | AJ1: Crude Basis | AK1: Ref Margin | AM1: Crude-degummed Argentina - UpRiver ($/mt) | AQ1: Crush Margin | AT1: RBD Basis | AY1: Refining Margin | BD1: Central Illinois Basis | BI1: Gulf Basis | BN1: Argentina Up River | BS1: Canola Oil Basis | BX1: RBD Canola Oil - RBD SBO | CE1: Argentina Up River Basis Prediction | CG1: RBD - Central Illinois Refining Margin Prediction | CI1: Gulf Basis Prediction | CK1: Crude Basis | CM1: RBD - Central Illinois | CP1: Crude-degummed - Central Illinois | CS1: Crude-degummed - Gulf | CV1: Crude-degummed Argentina - UpRiver | CY1: Canola Oil - Los Angeles | DB1: SBO Futures | DF1: Gulf - central Illinois | DJ1: Canola Oil - RBD SBO | DM1: Canola Oil - RBD Spread Forecast | DW1: Brazil (cents per pound) | DZ1: Brazil ($/tonne) | EC1: US SBM - C. IL ($/ton) | EF1: US Soy - C. IL ($/bu) | EI1: C. IL Cash Crush - crude degummed ($/bu) | EL1: C. IL Cash Crush - RBD ($/bu) | EO1: C. IL SBO Refining Margin - RBD ($/bu) | ER1: C. IL SBO Oil Share - RBD
B2: Month | C2: Year | D2: Low | E2: High | F2: Average | G2: Low-Avg | H2: High-Avg | I2: Low | J2: High | K2: Average | L2: Low-Avg | M2: High-Avg | N2: Low | O2: High | P2: Average | Q2: Low-Avg | R2: High-Avg | S2: Low | T2: High | U2: Average | V2: Low-Avg | W2: High-Avg | X2: Low | Y2: High | Z2: Average | AA2: Low-Avg | AB2: High-Avg | AC2: Low | AD2: High | AE2: Average | AF2: Low-Avg | AG2: High-Avg | AI2: Copy refining margin to cells to the right | AM2: Low | AN2: High | AO2: Average | AT2: Low | AU2: High | AV2: Average | AW2: Low-Avg | AX2: High-Avg | AY2: Low | AZ2: High | BA2: Average | BB2: Low-Avg | BC2: High-Avg | BD2: Low | BE2: High | BF2: Average | BG2: Low-Avg | BH2: High-Avg | BI2: Low | BJ2: High | BK2: Average | BL2: Low-Avg | BM2: High-Avg | BN2: Low | BO2: High | BP2: Average | BQ2: Low-Avg | BR2: High-Avg | BS2: Low | BT2: High | BU2: Average | BV2: Low-Avg | BW2: High-Avg | BX2: Low | BY2: High | BZ2: Average | CA2: Low-Avg | CB2: High-Avg | CE2: Prediction | CF2: Difference | CG2: Prediction | CH2: Difference | CI2: Prediction | CJ2: Difference | CK2: Prediction | CL2: Difference | CM2: Low | CN2: High | CO2: Average | CP2: Low | CQ2: High | CR2: Average | CS2: Low | CT2: High | CU2: Average | CV2: Low | CW2: High | CX2: Average | CY2: Low | CZ2: High | DA2: Average | DB2: Low | DC2: High | DD2: Average | DF2: Low | DG2: High | DH2: Average | DJ2: Low | DK2: High | DL2: Average | DM2: Low | DN2: High | DO2: Average | DS2: Low | DT2: High | DU2: Average | DW2: Low | DX2: High | DY2: Average | DZ2: Low | EA2: High | EB2: Average | EC2: Low | ED2: High | EE2: Average | EF2: Low | EG2: High | EH2: Average | EI2: Low | EJ2: High | EK2: Average | EL2: Low | EM2: High | EN2: Average | EO2: Low | EP2: High | EQ2: Average | ER2: Low | ES2: High | ET2: Average
A3: 43435 | B3: =MONTH(A3) -> 12 | C3: =YEAR(A3) -> 2018 | D3: =_xlfn.MINIFS(Spreads!B$3:B$1616,Spreads!$AA$3:$AA$1616,'Monthly Data'!$B3,Spreads!$AB$3:$AB$1616,'Monthly Data'!$C3) -> 30.86 | E3: =_xlfn.MAXIFS(Spreads!B$3:B$1616,Spreads!$AA$3:$AA$1616,'Monthly Data'!$B3,Spreads!$AB$3:$AB$1616,'Monthly Data'!$C3) -> 32.59 | F3: =AVERAGEIFS(Spreads!B$3:B$1616,Spreads!$AA$3:$AA$1616,'Monthly Data'!$B3,Spreads!$AB$3:$AB$1616,'Monthly Data'!$C3) -> 31.8725 | G3: =D3-F3 -> -1.0125 | H3: =E3-F3 -> 0.7175 | I3: =_xlfn.MINIFS(Spreads!C$3:C$1616,Spreads!$AA$3:$AA$1616,'Monthly Data'!$B3,Spreads!$AB$3:$AB$1616,'Monthly Data'!$C3) -> 27.11 | J3: =_xlfn.MAXIFS(Spreads!C$3:C$1616,Spreads!$AA$3:$AA$1616,'Monthly Data'!$B3,Spreads!$AB$3:$AB$1616,'Monthly Data'!$C3) -> 28.84 | K3: =AVERAGEIFS(Spreads!C$3:C$1616,Spreads!$AA$3:$AA$1616,'Monthly Data'!$B3,Spreads!$AB$3:$AB$1616,'Monthly Data'!$C3) -> 28.1225 | L3: =I3-K3 -> -1.0125 | M3: =J3-K3 -> 0.7175 | N3: =_xlfn.MINIFS(Spreads!D$3:D$1616,Spreads!$AA$3:$AA$1616,'Monthly Data'!$B3,Spreads!$AB$3:$AB$1616,'Monthly Data'!$C3) -> 29.56 | O3: =_xlfn.MAXIFS(Spreads!D$3:D$1616,Spreads!$AA$3:$AA$1616,'Monthly Data'!$B3,Spreads!$AB$3:$AB$1616,'Monthly Data'!$C3) -> 31.29 | P3: =AVERAGEIFS(Spreads!D$3:D$1616,Spreads!$AA$3:$AA$1616,'Monthly Data'!$B3,Spreads!$AB$3:$AB$1616,'Monthly Data'!$C3) -> 30.5725 | Q3: =N3-P3 -> -1.0125 | R3: =O3-P3 -> 0.7175 | S3: =_xlfn.MINIFS(Spreads!F$3:F$1616,Spreads!$AA$3:$AA$1616,'Monthly Data'!$B3,Spreads!$AB$3:$AB$1616,'Monthly Data'!$C3) -> 27.056793 | T3: =_xlfn.MAXIFS(Spreads!F$3:F$1616,Spreads!$AA$3:$AA$1616,'Monthly Data'!$B3,Spreads!$AB$3:$AB$1616,'Monthly Data'!$C3) -> 29.00724 | U3: =AVERAGEIFS(Spreads!F$3:F$1616,Spreads!$AA$3:$AA$1616,'Monthly Data'!$B3,Spreads!$AB$3:$AB$1616,'Monthly Data'!$C3) -> 28.278157 | V3: =S3-U3 -> -1.2213645 | W3: =T3-U3 -> 0.72908324 | X3: =_xlfn.MINIFS(Spreads!G$3:G$1616,Spreads!$AA$3:$AA$1616,'Monthly Data'!$B3,Spreads!$AB$3:$AB$1616,'Monthly Data'!$C3) -> 40.31 | Y3: =_xlfn.MAXIFS(Spreads!G$3:G$1616,Spreads!$AA$3:$AA$1616,'Monthly Data'!$B3,Spreads!$AB$3:$AB$1616,'Monthly Data'!$C3) -> 42.04 | Z3: =AVERAGEIFS(Spreads!G$3:G$1616,Spreads!$AA$3:$AA$1616,'Monthly Data'!$B3,Spreads!$AB$3:$AB$1616,'Monthly Data'!$C3) -> 41.3225 | AA3: =X3-Z3 -> -1.0125 | AB3: =Y3-Z3 -> 0.7175 | AC3: =_xlfn.MINIFS(Spreads!H$3:H$1616,Spreads!$AA$3:$AA$1616,'Monthly Data'!$B3,Spreads!$AB$3:$AB$1616,'Monthly Data'!$C3) -> 27.63 | AD3: =_xlfn.MAXIFS(Spreads!H$3:H$1616,Spreads!$AA$3:$AA$1616,'Monthly Data'!$B3,Spreads!$AB$3:$AB$1616,'Monthly Data'!$C3) -> 29.04 | AE3: =AVERAGEIFS(Spreads!H$3:H$1616,Spreads!$AA$3:$AA$1616,'Monthly Data'!$B3,Spreads!$AB$3:$AB$1616,'Monthly Data'!$C3) -> 28.4265 | AF3: =AC3-AE3 -> -0.7965 | AG3: =AD3-AE3 -> 0.6135 | AQ3: =AVERAGEIFS(Spreads!AV$3:AV$1616,Spreads!$AA$3:$AA$1616,'Monthly Data'!$B3,Spreads!$AB$3:$AB$1616,'Monthly Data'!$C3) -> 1.8635575 | AS3: =A3 -> 43435 | AT3: =_xlfn.MINIFS(Spreads!M$3:M$1616,Spreads!$AA$3:$AA$1616,'Monthly Data'!$B3,Spreads!$AB$3:$AB$1616,'Monthly Data'!$C3) -> 3.23 | AU3: =_xlfn.MAXIFS(Spreads!M$3:M$1616,Spreads!$AA$3:$AA$1616,'Monthly Data'!$B3,Spreads!$AB$3:$AB$1616,'Monthly Data'!$C3) -> 3.55 | AV3: =AVERAGEIFS(Spreads!M$3:M$1616,Spreads!$AA$3:$AA$1616,'Monthly Data'!$B3,Spreads!$AB$3:$AB$1616,'Monthly Data'!$C3) -> 3.446 | AW3: =AT3-AV3 -> -0.216 | AX3: =AU3-AV3 -> 0.104 | AY3: =_xlfn.MINIFS(Spreads!N$3:N$1616,Spreads!$AA$3:$AA$1616,'Monthly Data'!$B3,Spreads!$AB$3:$AB$1616,'Monthly Data'!$C3) -> 3.75 | AZ3: =_xlfn.MAXIFS(Spreads!N$3:N$1616,Spreads!$AA$3:$AA$1616,'Monthly Data'!$B3,Spreads!$AB$3:$AB$1616,'Monthly Data'!$C3) -> 3.75 | BA3: =AVERAGEIFS(Spreads!N$3:N$1616,Spreads!$AA$3:$AA$1616,'Monthly Data'!$B3,Spreads!$AB$3:$AB$1616,'Monthly Data'!$C3) -> 3.75 | BB3: =AY3-BA3 -> -3.5527137e-15 | BC3: =AZ3-BA3 -> 3.5527137e-15 | BD3: =_xlfn.MINIFS(Spreads!O$3:O$1616,Spreads!$AA$3:$AA$1616,'Monthly Data'!$B3,Spreads!$AB$3:$AB$1616,'Monthly Data'!$C3) -> -0.52 | BE3: =_xlfn.MAXIFS(Spreads!O$3:O$1616,Spreads!$AA$3:$AA$1616,'Monthly Data'!$B3,Spreads!$AB$3:$AB$1616,'Monthly Data'!$C3) -> -0.2 | BF3: =AVERAGEIFS(Spreads!O$3:O$1616,Spreads!$AA$3:$AA$1616,'Monthly Data'!$B3,Spreads!$AB$3:$AB$1616,'Monthly Data'!$C3) -> -0.304 | BG3: =BD3-BF3 -> -0.216 | BH3: =BE3-BF3 -> 0.104 | BI3: =_xlfn.MINIFS(Spreads!P$3:P$1616,Spreads!$AA$3:$AA$1616,'Monthly Data'!$B3,Spreads!$AB$3:$AB$1616,'Monthly Data'!$C3) -> 1.93 | BJ3: =_xlfn.MAXIFS(Spreads!P$3:P$1616,Spreads!$AA$3:$AA$1616,'Monthly Data'!$B3,Spreads!$AB$3:$AB$1616,'Monthly Data'!$C3) -> 2.25 | BK3: =AVERAGEIFS(Spreads!P$3:P$1616,Spreads!$AA$3:$AA$1616,'Monthly Data'!$B3,Spreads!$AB$3:$AB$1616,'Monthly Data'!$C3) -> 2.146 | BL3: =BI3-BK3 -> -0.216 | BM3: =BJ3-BK3 -> 0.104 | BN3: =_xlfn.MINIFS(Spreads!R$3:R$1616,Spreads!$AA$3:$AA$1616,'Monthly Data'!$B3,Spreads!$AB$3:$AB$1616,'Monthly Data'!$C3) -> -1.0451686 | BO3: =_xlfn.MAXIFS(Spreads!R$3:R$1616,Spreads!$AA$3:$AA$1616,'Monthly Data'!$B3,Spreads!$AB$3:$AB$1616,'Monthly Data'!$C3) -> 0.32384212 | BP3: =AVERAGEIFS(Spreads!R$3:R$1616,Spreads!$AA$3:$AA$1616,'Monthly Data'!$B3,Spreads!$AB$3:$AB$1616,'Monthly Data'!$C3) -> -0.25125476 | BQ3: =BN3-BP3 -> -0.79391387 | BR3: =BO3-BP3 -> 0.57509688 | BS3: =_xlfn.MINIFS(Spreads!S$3:S$1616,Spreads!$AA$3:$AA$1616,'Monthly Data'!$B3,Spreads!$AB$3:$AB$1616,'Monthly Data'!$C3) -> 12.68 | BT3: =_xlfn.MAXIFS(Spreads!S$3:S$1616,Spreads!$AA$3:$AA$1616,'Monthly Data'!$B3,Spreads!$AB$3:$AB$1616,'Monthly Data'!$C3) -> 13 | BU3: =AVERAGEIFS(Spreads!S$3:S$1616,Spreads!$AA$3:$AA$1616,'Monthly Data'!$B3,Spreads!$AB$3:$AB$1616,'Monthly Data'!$C3) -> 12.896 | BV3: =BS3-BU3 -> -0.216 | BW3: =BT3-BU3 -> 0.104 | BX3: =_xlfn.MINIFS(Spreads!T$3:T$1616,Spreads!$AA$3:$AA$1616,'Monthly Data'!$B3,Spreads!$AB$3:$AB$1616,'Monthly Data'!$C3) -> 9.45 | BY3: =_xlfn.MAXIFS(Spreads!T$3:T$1616,Spreads!$AA$3:$AA$1616,'Monthly Data'!$B3,Spreads!$AB$3:$AB$1616,'Monthly Data'!$C3) -> 9.45 | BZ3: =AVERAGEIFS(Spreads!T$3:T$1616,Spreads!$AA$3:$AA$1616,'Monthly Data'!$B3,Spreads!$AB$3:$AB$1616,'Monthly Data'!$C3) -> 9.45 | CA3: =BX3-BZ3 -> 0 | CB3: =BY3-BZ3 -> 0 | DJ3: =X3-D3 -> 9.45 | DK3: =Y3-E3 -> 9.45 | DL3: =Z3-F3 -> 9.45 | DV3: =A3 -> 43435 | DW3: =_xlfn.MINIFS(Spreads!X$3:X$1616,Spreads!$AA$3:$AA$1616,'Monthly Data'!$B3,Spreads!$AB$3:$AB$1616,'Monthly Data'!$C3) -> 27.453686 | DX3: =_xlfn.MAXIFS(Spreads!X$3:X$1616,Spreads!$AA$3:$AA$1616,'Monthly Data'!$B3,Spreads!$AB$3:$AB$1616,'Monthly Data'!$C3) -> 29.61959 | DY3: =AVERAGEIFS(Spreads!X$3:X$1616,Spreads!$AA$3:$AA$1616,'Monthly Data'!$B3,Spreads!$AB$3:$AB$1616,'Monthly Data'!$C3) -> 28.970553 | DZ3: =_xlfn.MINIFS(Spreads!AM$3:AM$1616,Spreads!$AA$3:$AA$1616,'Monthly Data'!$B3,Spreads!$AB$3:$AB$1616,'Monthly Data'!$C3) -> 605.25 | EA3: =_xlfn.MAXIFS(Spreads!AM$3:AM$1616,Spreads!$AA$3:$AA$1616,'Monthly Data'!$B3,Spreads!$AB$3:$AB$1616,'Monthly Data'!$C3) -> 653 | EB3: =AVERAGEIFS(Spreads!AM$3:AM$1616,Spreads!$AA$3:$AA$1616,'Monthly Data'!$B3,Spreads!$AB$3:$AB$1616,'Monthly Data'!$C3) -> 638.69118 | EC3: =_xlfn.MINIFS(Spreads!AT$3:AT$1616,Spreads!$AA$3:$AA$1616,'Monthly Data'!$B3,Spreads!$AB$3:$AB$1616,'Monthly Data'!$C3) -> 303 | ED3: =_xlfn.MAXIFS(Spreads!AT$3:AT$1616,Spreads!$AA$3:$AA$1616,'Monthly Data'!$B3,Spreads!$AB$3:$AB$1616,'Monthly Data'!$C3) -> 315 | EE3: =AVERAGEIFS(Spreads!AT$3:AT$1616,Spreads!$AA$3:$AA$1616,'Monthly Data'!$B3,Spreads!$AB$3:$AB$1616,'Monthly Data'!$C3) -> 309.35 | EF3: =_xlfn.MINIFS(Spreads!AU$3:AU$1616,Spreads!$AA$3:$AA$1616,'Monthly Data'!$B3,Spreads!$AB$3:$AB$1616,'Monthly Data'!$C3) -> 8.39 | EG3: =_xlfn.MAXIFS(Spreads!AU$3:AU$1616,Spreads!$AA$3:$AA$1616,'Monthly Data'!$B3,Spreads!$AB$3:$AB$1616,'Monthly Data'!$C3) -> 8.9 | EH3: =AVERAGEIFS(Spreads!AU$3:AU$1616,Spreads!$AA$3:$AA$1616,'Monthly Data'!$B3,Spreads!$AB$3:$AB$1616,'Monthly Data'!$C3) -> 8.6965 | EI3: =_xlfn.MINIFS(Spreads!AV$3:AV$1616,Spreads!$AA$3:$AA$1616,'Monthly Data'!$B3,Spreads!$AB$3:$AB$1616,'Monthly Data'!$C3) -> 1.77768 | EJ3: =_xlfn.MAXIFS(Spreads!AV$3:AV$1616,Spreads!$AA$3:$AA$1616,'Monthly Data'!$B3,Spreads!$AB$3:$AB$1616,'Monthly Data'!$C3) -> 1.9404 | EK3: =AVERAGEIFS(Spreads!AV$3:AV$1616,Spreads!$AA$3:$AA$1616,'Monthly Data'!$B3,Spreads!$AB$3:$AB$1616,'Monthly Data'!$C3) -> 1.8635575 | EL3: =_xlfn.MINIFS(Spreads!AW$3:AW$1616,Spreads!$AA$3:$AA$1616,'Monthly Data'!$B3,Spreads!$AB$3:$AB$1616,'Monthly Data'!$C3) -> 2.1408714 | EM3: =_xlfn.MAXIFS(Spreads!AW$3:AW$1616,Spreads!$AA$3:$AA$1616,'Monthly Data'!$B3,Spreads!$AB$3:$AB$1616,'Monthly Data'!$C3) -> 2.303217 | EN3: =AVERAGEIFS(Spreads!AW$3:AW$1616,Spreads!$AA$3:$AA$1616,'Monthly Data'!$B3,Spreads!$AB$3:$AB$1616,'Monthly Data'!$C3) -> 2.2277258 | EO3: =_xlfn.MINIFS(Spreads!AX$3:AX$1616,Spreads!$AA$3:$AA$1616,'Monthly Data'!$B3,Spreads!$AB$3:$AB$1616,'Monthly Data'!$C3) -> 0.3624894 | EP3: =_xlfn.MAXIFS(Spreads!AX$3:AX$1616,Spreads!$AA$3:$AA$1616,'Monthly Data'!$B3,Spreads!$AB$3:$AB$1616,'Monthly Data'!$C3) -> 0.3665376 | EQ3: =AVERAGEIFS(Spreads!AX$3:AX$1616,Spreads!$AA$3:$AA$1616,'Monthly Data'!$B3,Spreads!$AB$3:$AB$1616,'Monthly Data'!$C3) -> 0.36416835 | ER3: =_xlfn.MINIFS(Spreads!AY$3:AY$1616,Spreads!$AA$3:$AA$1616,'Monthly Data'!$B3,Spreads!$AB$3:$AB$1616,'Monthly Data'!$C3) -> 0.33360498 | ES3: =_xlfn.MAXIFS(Spreads!AY$3:AY$1616,Spreads!$AA$3:$AA$1616,'Monthly Data'!$B3,Spreads!$AB$3:$AB$1616,'Monthly Data'!$C3) -> 0.3428483 | ET3: =AVERAGEIFS(Spreads!AY$3:AY$1616,Spreads!$AA$3:$AA$1616,'Monthly Data'!$B3,Spreads!$AB$3:$AB$1616,'Monthly Data'!$C3) -> 0.33902637
A4: 43466 | B4: =MONTH(A4) -> 1 | C4: =YEAR(A4) -> 2019 | D4: =_xlfn.MINIFS(Spreads!B$3:B$1616,Spreads!$AA$3:$AA$1616,'Monthly Data'!$B4,Spreads!$AB$3:$AB$1616,'Monthly Data'!$C4) -> 31.58 | E4: =_xlfn.MAXIFS(Spreads!B$3:B$1616,Spreads!$AA$3:$AA$1616,'Monthly Data'!$B4,Spreads!$AB$3:$AB$1616,'Monthly Data'!$C4) -> 33.52 | F4: =AVERAGEIFS(Spreads!B$3:B$1616,Spreads!$AA$3:$AA$1616,'Monthly Data'!$B4,Spreads!$AB$3:$AB$1616,'Monthly Data'!$C4) -> 32.317619 | G4: =D4-F4 -> -0.73761905 | H4: =E4-F4 -> 1.202381 | I4: =_xlfn.MINIFS(Spreads!C$3:C$1616,Spreads!$AA$3:$AA$1616,'Monthly Data'!$B4,Spreads!$AB$3:$AB$1616,'Monthly Data'!$C4) -> 27.83 | J4: =_xlfn.MAXIFS(Spreads!C$3:C$1616,Spreads!$AA$3:$AA$1616,'Monthly Data'!$B4,Spreads!$AB$3:$AB$1616,'Monthly Data'!$C4) -> 29.77 | K4: =AVERAGEIFS(Spreads!C$3:C$1616,Spreads!$AA$3:$AA$1616,'Monthly Data'!$B4,Spreads!$AB$3:$AB$1616,'Monthly Data'!$C4) -> 28.567619 | L4: =I4-K4 -> -0.73761905 | M4: =J4-K4 -> 1.202381 | N4: =_xlfn.MINIFS(Spreads!D$3:D$1616,Spreads!$AA$3:$AA$1616,'Monthly Data'!$B4,Spreads!$AB$3:$AB$1616,'Monthly Data'!$C4) -> 30.19 | O4: =_xlfn.MAXIFS(Spreads!D$3:D$1616,Spreads!$AA$3:$AA$1616,'Monthly Data'!$B4,Spreads!$AB$3:$AB$1616,'Monthly Data'!$C4) -> 32.42 | P4: =AVERAGEIFS(Spreads!D$3:D$1616,Spreads!$AA$3:$AA$1616,'Monthly Data'!$B4,Spreads!$AB$3:$AB$1616,'Monthly Data'!$C4) -> 31.06 | Q4: =N4-P4 -> -0.87 | R4: =O4-P4 -> 1.36 | S4: =_xlfn.MINIFS(Spreads!F$3:F$1616,Spreads!$AA$3:$AA$1616,'Monthly Data'!$B4,Spreads!$AB$3:$AB$1616,'Monthly Data'!$C4) -> 27.646463 | T4: =_xlfn.MAXIFS(Spreads!F$3:F$1616,Spreads!$AA$3:$AA$1616,'Monthly Data'!$B4,Spreads!$AB$3:$AB$1616,'Monthly Data'!$C4) -> 31.762815 | U4: =AVERAGEIFS(Spreads!F$3:F$1616,Spreads!$AA$3:$AA$1616,'Monthly Data'!$B4,Spreads!$AB$3:$AB$1616,'Monthly Data'!$C4) -> 29.455433 | V4: =S4-U4 -> -1.8089701 | W4: =T4-U4 -> 2.3073818 | X4: =_xlfn.MINIFS(Spreads!G$3:G$1616,Spreads!$AA$3:$AA$1616,'Monthly Data'!$B4,Spreads!$AB$3:$AB$1616,'Monthly Data'!$C4) -> 40.06 | Y4: =_xlfn.MAXIFS(Spreads!G$3:G$1616,Spreads!$AA$3:$AA$1616,'Monthly Data'!$B4,Spreads!$AB$3:$AB$1616,'Monthly Data'!$C4) -> 42.01 | Z4: =AVERAGEIFS(Spreads!G$3:G$1616,Spreads!$AA$3:$AA$1616,'Monthly Data'!$B4,Spreads!$AB$3:$AB$1616,'Monthly Data'!$C4) -> 41.239048 | AA4: =X4-Z4 -> -1.1790476 | AB4: =Y4-Z4 -> 0.77095238 | AC4: =_xlfn.MINIFS(Spreads!H$3:H$1616,Spreads!$AA$3:$AA$1616,'Monthly Data'!$B4,Spreads!$AB$3:$AB$1616,'Monthly Data'!$C4) -> 28.18 | AD4: =_xlfn.MAXIFS(Spreads!H$3:H$1616,Spreads!$AA$3:$AA$1616,'Monthly Data'!$B4,Spreads!$AB$3:$AB$1616,'Monthly Data'!$C4) -> 30.42 | AE4: =AVERAGEIFS(Spreads!H$3:H$1616,Spreads!$AA$3:$AA$1616,'Monthly Data'!$B4,Spreads!$AB$3:$AB$1616,'Monthly Data'!$C4) -> 29.000952 | AF4: =AC4-AE4 -> -0.82095238 | AG4: =AD4-AE4 -> 1.4190476 | AH4: =AE4/AE3-1 -> 0.02020834 | AI4: =F4-AE4 -> 3.3166667 | AJ4: =K4-AE4 -> -0.43333333 | AK4: =AI4-AJ4 -> 3.75 | AQ4: =AVERAGEIFS(Spreads!AV$3:AV$1616,Spreads!$AA$3:$AA$1616,'Monthly Data'!$B4,Spreads!$AB$3:$AB$1616,'Monthly Data'!$C4) -> 1.9561019 | AS4: =A4 -> 43466 | AT4: =_xlfn.MINIFS(Spreads!M$3:M$1616,Spreads!$AA$3:$AA$1616,'Monthly Data'!$B4,Spreads!$AB$3:$AB$1616,'Monthly Data'!$C4) -> 3.1 | AU4: =_xlfn.MAXIFS(Spreads!M$3:M$1616,Spreads!$AA$3:$AA$1616,'Monthly Data'!$B4,Spreads!$AB$3:$AB$1616,'Monthly Data'!$C4) -> 3.55 | AV4: =AVERAGEIFS(Spreads!M$3:M$1616,Spreads!$AA$3:$AA$1616,'Monthly Data'!$B4,Spreads!$AB$3:$AB$1616,'Monthly Data'!$C4) -> 3.3166667 | AW4: =AT4-AV4 -> -0.21666667 | AX4: =AU4-AV4 -> 0.23333333 | AY4: =_xlfn.MINIFS(Spreads!N$3:N$1616,Spreads!$AA$3:$AA$1616,'Monthly Data'!$B4,Spreads!$AB$3:$AB$1616,'Monthly Data'!$C4) -> 3.75 | AZ4: =_xlfn.MAXIFS(Spreads!N$3:N$1616,Spreads!$AA$3:$AA$1616,'Monthly Data'!$B4,Spreads!$AB$3:$AB$1616,'Monthly Data'!$C4) -> 3.75 | BA4: =AVERAGEIFS(Spreads!N$3:N$1616,Spreads!$AA$3:$AA$1616,'Monthly Data'!$B4,Spreads!$AB$3:$AB$1616,'Monthly Data'!$C4) -> 3.75 | BB4: =AY4-BA4 -> -3.5527137e-15 | BC4: =AZ4-BA4 -> 3.5527137e-15 | BD4: =_xlfn.MINIFS(Spreads!O$3:O$1616,Spreads!$AA$3:$AA$1616,'Monthly Data'!$B4,Spreads!$AB$3:$AB$1616,'Monthly Data'!$C4) -> -0.65 | BE4: =_xlfn.MAXIFS(Spreads!O$3:O$1616,Spreads!$AA$3:$AA$1616,'Monthly Data'!$B4,Spreads!$AB$3:$AB$1616,'Monthly Data'!$C4) -> -0.2 | BF4: =AVERAGEIFS(Spreads!O$3:O$1616,Spreads!$AA$3:$AA$1616,'Monthly Data'!$B4,Spreads!$AB$3:$AB$1616,'Monthly Data'!$C4) -> -0.43333333 | BG4: =BD4-BF4 -> -0.21666667 | BH4: =BE4-BF4 -> 0.23333333 | BI4: =_xlfn.MINIFS(Spreads!P$3:P$1616,Spreads!$AA$3:$AA$1616,'Monthly Data'!$B4,Spreads!$AB$3:$AB$1616,'Monthly Data'!$C4) -> 1.99 | BJ4: =_xlfn.MAXIFS(Spreads!P$3:P$1616,Spreads!$AA$3:$AA$1616,'Monthly Data'!$B4,Spreads!$AB$3:$AB$1616,'Monthly Data'!$C4) -> 2.25 | BK4: =AVERAGEIFS(Spreads!P$3:P$1616,Spreads!$AA$3:$AA$1616,'Monthly Data'!$B4,Spreads!$AB$3:$AB$1616,'Monthly Data'!$C4) -> 2.0590476 | BL4: =BI4-BK4 -> -0.069047619 | BM4: =BJ4-BK4 -> 0.19095238 | BN4: =_xlfn.MINIFS(Spreads!R$3:R$1616,Spreads!$AA$3:$AA$1616,'Monthly Data'!$B4,Spreads!$AB$3:$AB$1616,'Monthly Data'!$C4) -> -0.78353725 | BO4: =_xlfn.MAXIFS(Spreads!R$3:R$1616,Spreads!$AA$3:$AA$1616,'Monthly Data'!$B4,Spreads!$AB$3:$AB$1616,'Monthly Data'!$C4) -> 1.5928147 | BP4: =AVERAGEIFS(Spreads!R$3:R$1616,Spreads!$AA$3:$AA$1616,'Monthly Data'!$B4,Spreads!$AB$3:$AB$1616,'Monthly Data'!$C4) -> 0.45448045 | BQ4: =BN4-BP4 -> -1.2380177 | BR4: =BO4-BP4 -> 1.1383342 | BS4: =_xlfn.MINIFS(Spreads!S$3:S$1616,Spreads!$AA$3:$AA$1616,'Monthly Data'!$B4,Spreads!$AB$3:$AB$1616,'Monthly Data'!$C4) -> 11 | BT4: =_xlfn.MAXIFS(Spreads!S$3:S$1616,Spreads!$AA$3:$AA$1616,'Monthly Data'!$B4,Spreads!$AB$3:$AB$1616,'Monthly Data'!$C4) -> 13 | BU4: =AVERAGEIFS(Spreads!S$3:S$1616,Spreads!$AA$3:$AA$1616,'Monthly Data'!$B4,Spreads!$AB$3:$AB$1616,'Monthly Data'!$C4) -> 12.238095 | BV4: =BS4-BU4 -> -1.2380952 | BW4: =BT4-BU4 -> 0.76190476 | BX4: =_xlfn.MINIFS(Spreads!T$3:T$1616,Spreads!$AA$3:$AA$1616,'Monthly Data'!$B4,Spreads!$AB$3:$AB$1616,'Monthly Data'!$C4) -> 7.9 | BY4: =_xlfn.MAXIFS(Spreads!T$3:T$1616,Spreads!$AA$3:$AA$1616,'Monthly Data'!$B4,Spreads!$AB$3:$AB$1616,'Monthly Data'!$C4) -> 9.9 | BZ4: =AVERAGEIFS(Spreads!T$3:T$1616,Spreads!$AA$3:$AA$1616,'Monthly Data'!$B4,Spreads!$AB$3:$AB$1616,'Monthly Data'!$C4) -> 8.9214286 | CA4: =BX4-BZ4 -> -1.0214286 | CB4: =BY4-BZ4 -> 0.97857143 | DJ4: =X4-D4 -> 8.48 | DK4: =Y4-E4 -> 8.49 | DL4: =Z4-F4 -> 8.9214286 | DV4: =A4 -> 43466 | DW4: =_xlfn.MINIFS(Spreads!X$3:X$1616,Spreads!$AA$3:$AA$1616,'Monthly Data'!$B4,Spreads!$AB$3:$AB$1616,'Monthly Data'!$C4) -> 28.202114 | DX4: =_xlfn.MAXIFS(Spreads!X$3:X$1616,Spreads!$AA$3:$AA$1616,'Monthly Data'!$B4,Spreads!$AB$3:$AB$1616,'Monthly Data'!$C4) -> 31.638077 | DY4: =AVERAGEIFS(Spreads!X$3:X$1616,Spreads!$AA$3:$AA$1616,'Monthly Data'!$B4,Spreads!$AB$3:$AB$1616,'Monthly Data'!$C4) -> 29.661709 | DZ4: =_xlfn.MINIFS(Spreads!AM$3:AM$1616,Spreads!$AA$3:$AA$1616,'Monthly Data'!$B4,Spreads!$AB$3:$AB$1616,'Monthly Data'!$C4) -> 621.75 | EA4: =_xlfn.MAXIFS(Spreads!AM$3:AM$1616,Spreads!$AA$3:$AA$1616,'Monthly Data'!$B4,Spreads!$AB$3:$AB$1616,'Monthly Data'!$C4) -> 697.5 | EB4: =AVERAGEIFS(Spreads!AM$3:AM$1616,Spreads!$AA$3:$AA$1616,'Monthly Data'!$B4,Spreads!$AB$3:$AB$1616,'Monthly Data'!$C4) -> 653.92857 | EC4: =_xlfn.MINIFS(Spreads!AT$3:AT$1616,Spreads!$AA$3:$AA$1616,'Monthly Data'!$B4,Spreads!$AB$3:$AB$1616,'Monthly Data'!$C4) -> 305 | ED4: =_xlfn.MAXIFS(Spreads!AT$3:AT$1616,Spreads!$AA$3:$AA$1616,'Monthly Data'!$B4,Spreads!$AB$3:$AB$1616,'Monthly Data'!$C4) -> 323 | EE4: =AVERAGEIFS(Spreads!AT$3:AT$1616,Spreads!$AA$3:$AA$1616,'Monthly Data'!$B4,Spreads!$AB$3:$AB$1616,'Monthly Data'!$C4) -> 313.57143 | EF4: =_xlfn.MINIFS(Spreads!AU$3:AU$1616,Spreads!$AA$3:$AA$1616,'Monthly Data'!$B4,Spreads!$AB$3:$AB$1616,'Monthly Data'!$C4) -> 8.53 | EG4: =_xlfn.MAXIFS(Spreads!AU$3:AU$1616,Spreads!$AA$3:$AA$1616,'Monthly Data'!$B4,Spreads!$AB$3:$AB$1616,'Monthly Data'!$C4) -> 8.92 | EH4: =AVERAGEIFS(Spreads!AU$3:AU$1616,Spreads!$AA$3:$AA$1616,'Monthly Data'!$B4,Spreads!$AB$3:$AB$1616,'Monthly Data'!$C4) -> 8.7552381 | EI4: =_xlfn.MINIFS(Spreads!AV$3:AV$1616,Spreads!$AA$3:$AA$1616,'Monthly Data'!$B4,Spreads!$AB$3:$AB$1616,'Monthly Data'!$C4) -> 1.85355 | EJ4: =_xlfn.MAXIFS(Spreads!AV$3:AV$1616,Spreads!$AA$3:$AA$1616,'Monthly Data'!$B4,Spreads!$AB$3:$AB$1616,'Monthly Data'!$C4) -> 2.05991 | EK4: =AVERAGEIFS(Spreads!AV$3:AV$1616,Spreads!$AA$3:$AA$1616,'Monthly Data'!$B4,Spreads!$AB$3:$AB$1616,'Monthly Data'!$C4) -> 1.9561019 | EL4: =_xlfn.MINIFS(Spreads!AW$3:AW$1616,Spreads!$AA$3:$AA$1616,'Monthly Data'!$B4,Spreads!$AB$3:$AB$1616,'Monthly Data'!$C4) -> 2.214144 | EM4: =_xlfn.MAXIFS(Spreads!AW$3:AW$1616,Spreads!$AA$3:$AA$1616,'Monthly Data'!$B4,Spreads!$AB$3:$AB$1616,'Monthly Data'!$C4) -> 2.4238268 | EN4: =AVERAGEIFS(Spreads!AW$3:AW$1616,Spreads!$AA$3:$AA$1616,'Monthly Data'!$B4,Spreads!$AB$3:$AB$1616,'Monthly Data'!$C4) -> 2.3192287 | EO4: =_xlfn.MINIFS(Spreads!AX$3:AX$1616,Spreads!$AA$3:$AA$1616,'Monthly Data'!$B4,Spreads!$AB$3:$AB$1616,'Monthly Data'!$C4) -> 0.3603132 | EP4: =_xlfn.MAXIFS(Spreads!AX$3:AX$1616,Spreads!$AA$3:$AA$1616,'Monthly Data'!$B4,Spreads!$AB$3:$AB$1616,'Monthly Data'!$C4) -> 0.3648528 | EQ4: =AVERAGEIFS(Spreads!AX$3:AX$1616,Spreads!$AA$3:$AA$1616,'Monthly Data'!$B4,Spreads!$AB$3:$AB$1616,'Monthly Data'!$C4) -> 0.36312677 | ER4: =_xlfn.MINIFS(Spreads!AY$3:AY$1616,Spreads!$AA$3:$AA$1616,'Monthly Data'!$B4,Spreads!$AB$3:$AB$1616,'Monthly Data'!$C4) -> 0.33086679 | ES4: =_xlfn.MAXIFS(Spreads!AY$3:AY$1616,Spreads!$AA$3:$AA$1616,'Monthly Data'!$B4,Spreads!$AB$3:$AB$1616,'Monthly Data'!$C4) -> 0.35291069 | ET4: =AVERAGEIFS(Spreads!AY$3:AY$1616,Spreads!$AA$3:$AA$1616,'Monthly Data'!$B4,Spreads!$AB$3:$AB$1616,'Monthly Data'!$C4) -> 0.33913917
A5: 43497 | B5: =MONTH(A5) -> 2 | C5: =YEAR(A5) -> 2019 | D5: =_xlfn.MINIFS(Spreads!B$3:B$1616,Spreads!$AA$3:$AA$1616,'Monthly Data'!$B5,Spreads!$AB$3:$AB$1616,'Monthly Data'!$C5) -> 32.24 | E5: =_xlfn.MAXIFS(Spreads!B$3:B$1616,Spreads!$AA$3:$AA$1616,'Monthly Data'!$B5,Spreads!$AB$3:$AB$1616,'Monthly Data'!$C5) -> 34 | F5: =AVERAGEIFS(Spreads!B$3:B$1616,Spreads!$AA$3:$AA$1616,'Monthly Data'!$B5,Spreads!$AB$3:$AB$1616,'Monthly Data'!$C5) -> 32.904737 | G5: =D5-F5 -> -0.66473684 | H5: =E5-F5 -> 1.0952632 | I5: =_xlfn.MINIFS(Spreads!C$3:C$1616,Spreads!$AA$3:$AA$1616,'Monthly Data'!$B5,Spreads!$AB$3:$AB$1616,'Monthly Data'!$C5) -> 29.09 | J5: =_xlfn.MAXIFS(Spreads!C$3:C$1616,Spreads!$AA$3:$AA$1616,'Monthly Data'!$B5,Spreads!$AB$3:$AB$1616,'Monthly Data'!$C5) -> 30.25 | K5: =AVERAGEIFS(Spreads!C$3:C$1616,Spreads!$AA$3:$AA$1616,'Monthly Data'!$B5,Spreads!$AB$3:$AB$1616,'Monthly Data'!$C5) -> 29.575789 | L5: =I5-K5 -> -0.48578947 | M5: =J5-K5 -> 0.67421053 | N5: =_xlfn.MINIFS(Spreads!D$3:D$1616,Spreads!$AA$3:$AA$1616,'Monthly Data'!$B5,Spreads!$AB$3:$AB$1616,'Monthly Data'!$C5) -> 31.7 | O5: =_xlfn.MAXIFS(Spreads!D$3:D$1616,Spreads!$AA$3:$AA$1616,'Monthly Data'!$B5,Spreads!$AB$3:$AB$1616,'Monthly Data'!$C5) -> 32.9 | P5: =AVERAGEIFS(Spreads!D$3:D$1616,Spreads!$AA$3:$AA$1616,'Monthly Data'!$B5,Spreads!$AB$3:$AB$1616,'Monthly Data'!$C5) -> 32.21 | Q5: =N5-P5 -> -0.51 | R5: =O5-P5 -> 0.69 | S5: =_xlfn.MINIFS(Spreads!F$3:F$1616,Spreads!$AA$3:$AA$1616,'Monthly Data'!$B5,Spreads!$AB$3:$AB$1616,'Monthly Data'!$C5) -> 30.265959 | T5: =_xlfn.MAXIFS(Spreads!F$3:F$1616,Spreads!$AA$3:$AA$1616,'Monthly Data'!$B5,Spreads!$AB$3:$AB$1616,'Monthly Data'!$C5) -> 31.309222 | U5: =AVERAGEIFS(Spreads!F$3:F$1616,Spreads!$AA$3:$AA$1616,'Monthly Data'!$B5,Spreads!$AB$3:$AB$1616,'Monthly Data'!$C5) -> 30.761927 | V5: =S5-U5 -> -0.49596759 | W5: =T5-U5 -> 0.54729516 | X5: =_xlfn.MINIFS(Spreads!G$3:G$1616,Spreads!$AA$3:$AA$1616,'Monthly Data'!$B5,Spreads!$AB$3:$AB$1616,'Monthly Data'!$C5) -> 39.8 | Y5: =_xlfn.MAXIFS(Spreads!G$3:G$1616,Spreads!$AA$3:$AA$1616,'Monthly Data'!$B5,Spreads!$AB$3:$AB$1616,'Monthly Data'!$C5) -> 41.9 | Z5: =AVERAGEIFS(Spreads!G$3:G$1616,Spreads!$AA$3:$AA$1616,'Monthly Data'!$B5,Spreads!$AB$3:$AB$1616,'Monthly Data'!$C5) -> 41.015263 | AA5: =X5-Z5 -> -1.2152632 | AB5: =Y5-Z5 -> 0.88473684 | AC5: =_xlfn.MINIFS(Spreads!H$3:H$1616,Spreads!$AA$3:$AA$1616,'Monthly Data'!$B5,Spreads!$AB$3:$AB$1616,'Monthly Data'!$C5) -> 29.74 | AD5: =_xlfn.MAXIFS(Spreads!H$3:H$1616,Spreads!$AA$3:$AA$1616,'Monthly Data'!$B5,Spreads!$AB$3:$AB$1616,'Monthly Data'!$C5) -> 30.9 | AE5: =AVERAGEIFS(Spreads!H$3:H$1616,Spreads!$AA$3:$AA$1616,'Monthly Data'!$B5,Spreads!$AB$3:$AB$1616,'Monthly Data'!$C5) -> 30.344211 | AF5: =AC5-AE5 -> -0.60421053 | AG5: =AD5-AE5 -> 0.55578947 | AH5: =AE5/AE4-1 -> 0.046317725 | AI5: =F5-AE5 -> 2.5605263 | AJ5: =K5-AE5 -> -0.76842105 | AK5: =AI5-AJ5 -> 3.3289474 | AQ5: =AVERAGEIFS(Spreads!AV$3:AV$1616,Spreads!$AA$3:$AA$1616,'Monthly Data'!$B5,Spreads!$AB$3:$AB$1616,'Monthly Data'!$C5) -> 1.7881305 | AS5: =A5 -> 43497 | AT5: =_xlfn.MINIFS(Spreads!M$3:M$1616,Spreads!$AA$3:$AA$1616,'Monthly Data'!$B5,Spreads!$AB$3:$AB$1616,'Monthly Data'!$C5) -> 2.16 | AU5: =_xlfn.MAXIFS(Spreads!M$3:M$1616,Spreads!$AA$3:$AA$1616,'Monthly Data'!$B5,Spreads!$AB$3:$AB$1616,'Monthly Data'!$C5) -> 3.16 | AV5: =AVERAGEIFS(Spreads!M$3:M$1616,Spreads!$AA$3:$AA$1616,'Monthly Data'!$B5,Spreads!$AB$3:$AB$1616,'Monthly Data'!$C5) -> 2.5605263 | AW5: =AT5-AV5 -> -0.40052632 | AX5: =AU5-AV5 -> 0.59947368 | AY5: =_xlfn.MINIFS(Spreads!N$3:N$1616,Spreads!$AA$3:$AA$1616,'Monthly Data'!$B5,Spreads!$AB$3:$AB$1616,'Monthly Data'!$C5) -> 3.15 | AZ5: =_xlfn.MAXIFS(Spreads!N$3:N$1616,Spreads!$AA$3:$AA$1616,'Monthly Data'!$B5,Spreads!$AB$3:$AB$1616,'Monthly Data'!$C5) -> 4.15 | BA5: =AVERAGEIFS(Spreads!N$3:N$1616,Spreads!$AA$3:$AA$1616,'Monthly Data'!$B5,Spreads!$AB$3:$AB$1616,'Monthly Data'!$C5) -> 3.3289474 | BB5: =AY5-BA5 -> -0.17894737 | BC5: =AZ5-BA5 -> 0.82105263 | BD5: =_xlfn.MINIFS(Spreads!O$3:O$1616,Spreads!$AA$3:$AA$1616,'Monthly Data'!$B5,Spreads!$AB$3:$AB$1616,'Monthly Data'!$C5) -> -0.99 | BE5: =_xlfn.MAXIFS(Spreads!O$3:O$1616,Spreads!$AA$3:$AA$1616,'Monthly Data'!$B5,Spreads!$AB$3:$AB$1616,'Monthly Data'!$C5) -> -0.65 | BF5: =AVERAGEIFS(Spreads!O$3:O$1616,Spreads!$AA$3:$AA$1616,'Monthly Data'!$B5,Spreads!$AB$3:$AB$1616,'Monthly Data'!$C5) -> -0.76842105 | BG5: =BD5-BF5 -> -0.22157895 | BH5: =BE5-BF5 -> 0.11842105 | BI5: =_xlfn.MINIFS(Spreads!P$3:P$1616,Spreads!$AA$3:$AA$1616,'Monthly Data'!$B5,Spreads!$AB$3:$AB$1616,'Monthly Data'!$C5) -> 1.58 | BJ5: =_xlfn.MAXIFS(Spreads!P$3:P$1616,Spreads!$AA$3:$AA$1616,'Monthly Data'!$B5,Spreads!$AB$3:$AB$1616,'Monthly Data'!$C5) -> 2 | BK5: =AVERAGEIFS(Spreads!P$3:P$1616,Spreads!$AA$3:$AA$1616,'Monthly Data'!$B5,Spreads!$AB$3:$AB$1616,'Monthly Data'!$C5) -> 1.8657895 | BL5: =BI5-BK5 -> -0.28578947 | BM5: =BJ5-BK5 -> 0.13421053 | BN5: =_xlfn.MINIFS(Spreads!R$3:R$1616,Spreads!$AA$3:$AA$1616,'Monthly Data'!$B5,Spreads!$AB$3:$AB$1616,'Monthly Data'!$C5) -> -0.2638462 | BO5: =_xlfn.MAXIFS(Spreads!R$3:R$1616,Spreads!$AA$3:$AA$1616,'Monthly Data'!$B5,Spreads!$AB$3:$AB$1616,'Monthly Data'!$C5) -> 0.93366855 | BP5: =AVERAGEIFS(Spreads!R$3:R$1616,Spreads!$AA$3:$AA$1616,'Monthly Data'!$B5,Spreads!$AB$3:$AB$1616,'Monthly Data'!$C5) -> 0.41771649 | BQ5: =BN5-BP5 -> -0.68156269 | BR5: =BO5-BP5 -> 0.51595206 | BS5: =_xlfn.MINIFS(Spreads!S$3:S$1616,Spreads!$AA$3:$AA$1616,'Monthly Data'!$B5,Spreads!$AB$3:$AB$1616,'Monthly Data'!$C5) -> 9.68 | BT5: =_xlfn.MAXIFS(Spreads!S$3:S$1616,Spreads!$AA$3:$AA$1616,'Monthly Data'!$B5,Spreads!$AB$3:$AB$1616,'Monthly Data'!$C5) -> 11 | BU5: =AVERAGEIFS(Spreads!S$3:S$1616,Spreads!$AA$3:$AA$1616,'Monthly Data'!$B5,Spreads!$AB$3:$AB$1616,'Monthly Data'!$C5) -> 10.671053 | BV5: =BS5-BU5 -> -0.99105263 | BW5: =BT5-BU5 -> 0.32894737 | BX5: =_xlfn.MINIFS(Spreads!T$3:T$1616,Spreads!$AA$3:$AA$1616,'Monthly Data'!$B5,Spreads!$AB$3:$AB$1616,'Monthly Data'!$C5) -> 7.5 | BY5: =_xlfn.MAXIFS(Spreads!T$3:T$1616,Spreads!$AA$3:$AA$1616,'Monthly Data'!$B5,Spreads!$AB$3:$AB$1616,'Monthly Data'!$C5) -> 8.5 | BZ5: =AVERAGEIFS(Spreads!T$3:T$1616,Spreads!$AA$3:$AA$1616,'Monthly Data'!$B5,Spreads!$AB$3:$AB$1616,'Monthly Data'!$C5) -> 8.1105263 | CA5: =BX5-BZ5 -> -0.61052632 | CB5: =BY5-BZ5 -> 0.38947368 | DJ5: =X5-D5 -> 7.56 | DK5: =Y5-E5 -> 7.9 | DL5: =Z5-F5 -> 8.1105263 | DV5: =A5 -> 43497 | DW5: =_xlfn.MINIFS(Spreads!X$3:X$1616,Spreads!$AA$3:$AA$1616,'Monthly Data'!$B5,Spreads!$AB$3:$AB$1616,'Monthly Data'!$C5) -> 30.368018 | DX5: =_xlfn.MAXIFS(Spreads!X$3:X$1616,Spreads!$AA$3:$AA$1616,'Monthly Data'!$B5,Spreads!$AB$3:$AB$1616,'Monthly Data'!$C5) -> 31.46798 | DY5: =AVERAGEIFS(Spreads!X$3:X$1616,Spreads!$AA$3:$AA$1616,'Monthly Data'!$B5,Spreads!$AB$3:$AB$1616,'Monthly Data'!$C5) -> 30.977383 | DZ5: =_xlfn.MINIFS(Spreads!AM$3:AM$1616,Spreads!$AA$3:$AA$1616,'Monthly Data'!$B5,Spreads!$AB$3:$AB$1616,'Monthly Data'!$C5) -> 669.5 | EA5: =_xlfn.MAXIFS(Spreads!AM$3:AM$1616,Spreads!$AA$3:$AA$1616,'Monthly Data'!$B5,Spreads!$AB$3:$AB$1616,'Monthly Data'!$C5) -> 693.75 | EB5: =AVERAGEIFS(Spreads!AM$3:AM$1616,Spreads!$AA$3:$AA$1616,'Monthly Data'!$B5,Spreads!$AB$3:$AB$1616,'Monthly Data'!$C5) -> 682.93421 | EC5: =_xlfn.MINIFS(Spreads!AT$3:AT$1616,Spreads!$AA$3:$AA$1616,'Monthly Data'!$B5,Spreads!$AB$3:$AB$1616,'Monthly Data'!$C5) -> 301 | ED5: =_xlfn.MAXIFS(Spreads!AT$3:AT$1616,Spreads!$AA$3:$AA$1616,'Monthly Data'!$B5,Spreads!$AB$3:$AB$1616,'Monthly Data'!$C5) -> 309 | EE5: =AVERAGEIFS(Spreads!AT$3:AT$1616,Spreads!$AA$3:$AA$1616,'Monthly Data'!$B5,Spreads!$AB$3:$AB$1616,'Monthly Data'!$C5) -> 304.47368 | EF5: =_xlfn.MINIFS(Spreads!AU$3:AU$1616,Spreads!$AA$3:$AA$1616,'Monthly Data'!$B5,Spreads!$AB$3:$AB$1616,'Monthly Data'!$C5) -> 8.73 | EG5: =_xlfn.MAXIFS(Spreads!AU$3:AU$1616,Spreads!$AA$3:$AA$1616,'Monthly Data'!$B5,Spreads!$AB$3:$AB$1616,'Monthly Data'!$C5) -> 8.93 | EH5: =AVERAGEIFS(Spreads!AU$3:AU$1616,Spreads!$AA$3:$AA$1616,'Monthly Data'!$B5,Spreads!$AB$3:$AB$1616,'Monthly Data'!$C5) -> 8.8273684 | EI5: =_xlfn.MINIFS(Spreads!AV$3:AV$1616,Spreads!$AA$3:$AA$1616,'Monthly Data'!$B5,Spreads!$AB$3:$AB$1616,'Monthly Data'!$C5) -> 1.75007 | EJ5: =_xlfn.MAXIFS(Spreads!AV$3:AV$1616,Spreads!$AA$3:$AA$1616,'Monthly Data'!$B5,Spreads!$AB$3:$AB$1616,'Monthly Data'!$C5) -> 1.85558 | EK5: =AVERAGEIFS(Spreads!AV$3:AV$1616,Spreads!$AA$3:$AA$1616,'Monthly Data'!$B5,Spreads!$AB$3:$AB$1616,'Monthly Data'!$C5) -> 1.7881305 | EL5: =_xlfn.MINIFS(Spreads!AW$3:AW$1616,Spreads!$AA$3:$AA$1616,'Monthly Data'!$B5,Spreads!$AB$3:$AB$1616,'Monthly Data'!$C5) -> 2.0417276 | EM5: =_xlfn.MAXIFS(Spreads!AW$3:AW$1616,Spreads!$AA$3:$AA$1616,'Monthly Data'!$B5,Spreads!$AB$3:$AB$1616,'Monthly Data'!$C5) -> 2.2171334 | EN5: =AVERAGEIFS(Spreads!AW$3:AW$1616,Spreads!$AA$3:$AA$1616,'Monthly Data'!$B5,Spreads!$AB$3:$AB$1616,'Monthly Data'!$C5) -> 2.1006203 | EO5: =_xlfn.MINIFS(Spreads!AX$3:AX$1616,Spreads!$AA$3:$AA$1616,'Monthly Data'!$B5,Spreads!$AB$3:$AB$1616,'Monthly Data'!$C5) -> 0.2904642 | EP5: =_xlfn.MAXIFS(Spreads!AX$3:AX$1616,Spreads!$AA$3:$AA$1616,'Monthly Data'!$B5,Spreads!$AB$3:$AB$1616,'Monthly Data'!$C5) -> 0.4074174 | EQ5: =AVERAGEIFS(Spreads!AX$3:AX$1616,Spreads!$AA$3:$AA$1616,'Monthly Data'!$B5,Spreads!$AB$3:$AB$1616,'Monthly Data'!$C5) -> 0.31248976 | ER5: =_xlfn.MINIFS(Spreads!AY$3:AY$1616,Spreads!$AA$3:$AA$1616,'Monthly Data'!$B5,Spreads!$AB$3:$AB$1616,'Monthly Data'!$C5) -> 0.3436128 | ES5: =_xlfn.MAXIFS(Spreads!AY$3:AY$1616,Spreads!$AA$3:$AA$1616,'Monthly Data'!$B5,Spreads!$AB$3:$AB$1616,'Monthly Data'!$C5) -> 0.35766948 | ET5: =AVERAGEIFS(Spreads!AY$3:AY$1616,Spreads!$AA$3:$AA$1616,'Monthly Data'!$B5,Spreads!$AB$3:$AB$1616,'Monthly Data'!$C5) -> 0.34982112
A6: 43525 | B6: =MONTH(A6) -> 3 | C6: =YEAR(A6) -> 2019 | D6: =_xlfn.MINIFS(Spreads!B$3:B$1616,Spreads!$AA$3:$AA$1616,'Monthly Data'!$B6,Spreads!$AB$3:$AB$1616,'Monthly Data'!$C6) -> 30.76 | E6: =_xlfn.MAXIFS(Spreads!B$3:B$1616,Spreads!$AA$3:$AA$1616,'Monthly Data'!$B6,Spreads!$AB$3:$AB$1616,'Monthly Data'!$C6) -> 32.74 | F6: =AVERAGEIFS(Spreads!B$3:B$1616,Spreads!$AA$3:$AA$1616,'Monthly Data'!$B6,Spreads!$AB$3:$AB$1616,'Monthly Data'!$C6) -> 31.79 | G6: =D6-F6 -> -1.03 | H6: =E6-F6 -> 0.95 | I6: =_xlfn.MINIFS(Spreads!C$3:C$1616,Spreads!$AA$3:$AA$1616,'Monthly Data'!$B6,Spreads!$AB$3:$AB$1616,'Monthly Data'!$C6) -> 27.61 | J6: =_xlfn.MAXIFS(Spreads!C$3:C$1616,Spreads!$AA$3:$AA$1616,'Monthly Data'!$B6,Spreads!$AB$3:$AB$1616,'Monthly Data'!$C6) -> 29.59 | K6: =AVERAGEIFS(Spreads!C$3:C$1616,Spreads!$AA$3:$AA$1616,'Monthly Data'!$B6,Spreads!$AB$3:$AB$1616,'Monthly Data'!$C6) -> 28.64 | L6: =I6-K6 -> -1.03 | M6: =J6-K6 -> 0.95 | N6: =_xlfn.MINIFS(Spreads!D$3:D$1616,Spreads!$AA$3:$AA$1616,'Monthly Data'!$B6,Spreads!$AB$3:$AB$1616,'Monthly Data'!$C6) -> 30.26 | O6: =_xlfn.MAXIFS(Spreads!D$3:D$1616,Spreads!$AA$3:$AA$1616,'Monthly Data'!$B6,Spreads!$AB$3:$AB$1616,'Monthly Data'!$C6) -> 32.14 | P6: =AVERAGEIFS(Spreads!D$3:D$1616,Spreads!$AA$3:$AA$1616,'Monthly Data'!$B6,Spreads!$AB$3:$AB$1616,'Monthly Data'!$C6) -> 31.280476 | Q6: =N6-P6 -> -1.0204762 | R6: =O6-P6 -> 0.85952381 | S6: =_xlfn.MINIFS(Spreads!F$3:F$1616,Spreads!$AA$3:$AA$1616,'Monthly Data'!$B6,Spreads!$AB$3:$AB$1616,'Monthly Data'!$C6) -> 27.80522 | T6: =_xlfn.MAXIFS(Spreads!F$3:F$1616,Spreads!$AA$3:$AA$1616,'Monthly Data'!$B6,Spreads!$AB$3:$AB$1616,'Monthly Data'!$C6) -> 29.358774 | U6: =AVERAGEIFS(Spreads!F$3:F$1616,Spreads!$AA$3:$AA$1616,'Monthly Data'!$B6,Spreads!$AB$3:$AB$1616,'Monthly Data'!$C6) -> 28.797752 | V6: =S6-U6 -> -0.99253201 | W6: =T6-U6 -> 0.5610223 | X6: =_xlfn.MINIFS(Spreads!G$3:G$1616,Spreads!$AA$3:$AA$1616,'Monthly Data'!$B6,Spreads!$AB$3:$AB$1616,'Monthly Data'!$C6) -> 38.86 | Y6: =_xlfn.MAXIFS(Spreads!G$3:G$1616,Spreads!$AA$3:$AA$1616,'Monthly Data'!$B6,Spreads!$AB$3:$AB$1616,'Monthly Data'!$C6) -> 40.49 | Z6: =AVERAGEIFS(Spreads!G$3:G$1616,Spreads!$AA$3:$AA$1616,'Monthly Data'!$B6,Spreads!$AB$3:$AB$1616,'Monthly Data'!$C6) -> 39.71381 | AA6: =X6-Z6 -> -0.85380952 | AB6: =Y6-Z6 -> 0.77619048 | AC6: =_xlfn.MINIFS(Spreads!H$3:H$1616,Spreads!$AA$3:$AA$1616,'Monthly Data'!$B6,Spreads!$AB$3:$AB$1616,'Monthly Data'!$C6) -> 28.36 | AD6: =_xlfn.MAXIFS(Spreads!H$3:H$1616,Spreads!$AA$3:$AA$1616,'Monthly Data'!$B6,Spreads!$AB$3:$AB$1616,'Monthly Data'!$C6) -> 30.24 | AE6: =AVERAGEIFS(Spreads!H$3:H$1616,Spreads!$AA$3:$AA$1616,'Monthly Data'!$B6,Spreads!$AB$3:$AB$1616,'Monthly Data'!$C6) -> 29.380476 | AF6: =AC6-AE6 -> -1.0204762 | AG6: =AD6-AE6 -> 0.85952381 | AH6: =AE6/AE5-1 -> -0.031760073 | AI6: =F6-AE6 -> 2.4095238 | AJ6: =K6-AE6 -> -0.74047619 | AK6: =AI6-AJ6 -> 3.15 | AQ6: =AVERAGEIFS(Spreads!AV$3:AV$1616,Spreads!$AA$3:$AA$1616,'Monthly Data'!$B6,Spreads!$AB$3:$AB$1616,'Monthly Data'!$C6) -> 1.7757371 | AS6: =A6 -> 43525 | AT6: =_xlfn.MINIFS(Spreads!M$3:M$1616,Spreads!$AA$3:$AA$1616,'Monthly Data'!$B6,Spreads!$AB$3:$AB$1616,'Monthly Data'!$C6) -> 2.4 | AU6: =_xlfn.MAXIFS(Spreads!M$3:M$1616,Spreads!$AA$3:$AA$1616,'Monthly Data'!$B6,Spreads!$AB$3:$AB$1616,'Monthly Data'!$C6) -> 2.5 | AV6: =AVERAGEIFS(Spreads!M$3:M$1616,Spreads!$AA$3:$AA$1616,'Monthly Data'!$B6,Spreads!$AB$3:$AB$1616,'Monthly Data'!$C6) -> 2.4095238 | AW6: =AT6-AV6 -> -0.0095238095 | AX6: =AU6-AV6 -> 0.09047619 | AY6: =_xlfn.MINIFS(Spreads!N$3:N$1616,Spreads!$AA$3:$AA$1616,'Monthly Data'!$B6,Spreads!$AB$3:$AB$1616,'Monthly Data'!$C6) -> 3.15 | AZ6: =_xlfn.MAXIFS(Spreads!N$3:N$1616,Spreads!$AA$3:$AA$1616,'Monthly Data'!$B6,Spreads!$AB$3:$AB$1616,'Monthly Data'!$C6) -> 3.15 | BA6: =AVERAGEIFS(Spreads!N$3:N$1616,Spreads!$AA$3:$AA$1616,'Monthly Data'!$B6,Spreads!$AB$3:$AB$1616,'Monthly Data'!$C6) -> 3.15 | BB6: =AY6-BA6 -> 0 | BC6: =AZ6-BA6 -> 0 | BD6: =_xlfn.MINIFS(Spreads!O$3:O$1616,Spreads!$AA$3:$AA$1616,'Monthly Data'!$B6,Spreads!$AB$3:$AB$1616,'Monthly Data'!$C6) -> -0.75 | BE6: =_xlfn.MAXIFS(Spreads!O$3:O$1616,Spreads!$AA$3:$AA$1616,'Monthly Data'!$B6,Spreads!$AB$3:$AB$1616,'Monthly Data'!$C6) -> -0.65 | BF6: =AVERAGEIFS(Spreads!O$3:O$1616,Spreads!$AA$3:$AA$1616,'Monthly Data'!$B6,Spreads!$AB$3:$AB$1616,'Monthly Data'!$C6) -> -0.74047619 | BG6: =BD6-BF6 -> -0.0095238095 | BH6: =BE6-BF6 -> 0.09047619 | BI6: =_xlfn.MINIFS(Spreads!P$3:P$1616,Spreads!$AA$3:$AA$1616,'Monthly Data'!$B6,Spreads!$AB$3:$AB$1616,'Monthly Data'!$C6) -> 1.9 | BJ6: =_xlfn.MAXIFS(Spreads!P$3:P$1616,Spreads!$AA$3:$AA$1616,'Monthly Data'!$B6,Spreads!$AB$3:$AB$1616,'Monthly Data'!$C6) -> 1.9 | BK6: =AVERAGEIFS(Spreads!P$3:P$1616,Spreads!$AA$3:$AA$1616,'Monthly Data'!$B6,Spreads!$AB$3:$AB$1616,'Monthly Data'!$C6) -> 1.9 | BL6: =BI6-BK6 -> -1.7763568e-15 | BM6: =BJ6-BK6 -> 1.7763568e-15 | BN6: =_xlfn.MINIFS(Spreads!R$3:R$1616,Spreads!$AA$3:$AA$1616,'Monthly Data'!$B6,Spreads!$AB$3:$AB$1616,'Monthly Data'!$C6) -> -1.0173033 | BO6: =_xlfn.MAXIFS(Spreads!R$3:R$1616,Spreads!$AA$3:$AA$1616,'Monthly Data'!$B6,Spreads!$AB$3:$AB$1616,'Monthly Data'!$C6) -> -0.049653192 | BP6: =AVERAGEIFS(Spreads!R$3:R$1616,Spreads!$AA$3:$AA$1616,'Monthly Data'!$B6,Spreads!$AB$3:$AB$1616,'Monthly Data'!$C6) -> -0.51224787 | BQ6: =BN6-BP6 -> -0.50505545 | BR6: =BO6-BP6 -> 0.46259468 | BS6: =_xlfn.MINIFS(Spreads!S$3:S$1616,Spreads!$AA$3:$AA$1616,'Monthly Data'!$B6,Spreads!$AB$3:$AB$1616,'Monthly Data'!$C6) -> 10 | BT6: =_xlfn.MAXIFS(Spreads!S$3:S$1616,Spreads!$AA$3:$AA$1616,'Monthly Data'!$B6,Spreads!$AB$3:$AB$1616,'Monthly Data'!$C6) -> 10.5 | BU6: =AVERAGEIFS(Spreads!S$3:S$1616,Spreads!$AA$3:$AA$1616,'Monthly Data'!$B6,Spreads!$AB$3:$AB$1616,'Monthly Data'!$C6) -> 10.333333 | BV6: =BS6-BU6 -> -0.33333333 | BW6: =BT6-BU6 -> 0.16666667 | BX6: =_xlfn.MINIFS(Spreads!T$3:T$1616,Spreads!$AA$3:$AA$1616,'Monthly Data'!$B6,Spreads!$AB$3:$AB$1616,'Monthly Data'!$C6) -> 7.5 | BY6: =_xlfn.MAXIFS(Spreads!T$3:T$1616,Spreads!$AA$3:$AA$1616,'Monthly Data'!$B6,Spreads!$AB$3:$AB$1616,'Monthly Data'!$C6) -> 8.1 | BZ6: =AVERAGEIFS(Spreads!T$3:T$1616,Spreads!$AA$3:$AA$1616,'Monthly Data'!$B6,Spreads!$AB$3:$AB$1616,'Monthly Data'!$C6) -> 7.9238095 | CA6: =BX6-BZ6 -> -0.42380952 | CB6: =BY6-BZ6 -> 0.17619048 | DJ6: =X6-D6 -> 8.1 | DK6: =Y6-E6 -> 7.75 | DL6: =Z6-F6 -> 7.9238095 | DV6: =A6 -> 43525 | DW6: =_xlfn.MINIFS(Spreads!X$3:X$1616,Spreads!$AA$3:$AA$1616,'Monthly Data'!$B6,Spreads!$AB$3:$AB$1616,'Monthly Data'!$C6) -> 28.100055 | DX6: =_xlfn.MAXIFS(Spreads!X$3:X$1616,Spreads!$AA$3:$AA$1616,'Monthly Data'!$B6,Spreads!$AB$3:$AB$1616,'Monthly Data'!$C6) -> 29.664949 | DY6: =AVERAGEIFS(Spreads!X$3:X$1616,Spreads!$AA$3:$AA$1616,'Monthly Data'!$B6,Spreads!$AB$3:$AB$1616,'Monthly Data'!$C6) -> 29.081247 | DZ6: =_xlfn.MINIFS(Spreads!AM$3:AM$1616,Spreads!$AA$3:$AA$1616,'Monthly Data'!$B6,Spreads!$AB$3:$AB$1616,'Monthly Data'!$C6) -> 619.5 | EA6: =_xlfn.MAXIFS(Spreads!AM$3:AM$1616,Spreads!$AA$3:$AA$1616,'Monthly Data'!$B6,Spreads!$AB$3:$AB$1616,'Monthly Data'!$C6) -> 654 | EB6: =AVERAGEIFS(Spreads!AM$3:AM$1616,Spreads!$AA$3:$AA$1616,'Monthly Data'!$B6,Spreads!$AB$3:$AB$1616,'Monthly Data'!$C6) -> 641.13158 | EC6: =_xlfn.MINIFS(Spreads!AT$3:AT$1616,Spreads!$AA$3:$AA$1616,'Monthly Data'!$B6,Spreads!$AB$3:$AB$1616,'Monthly Data'!$C6) -> 296 | ED6: =_xlfn.MAXIFS(Spreads!AT$3:AT$1616,Spreads!$AA$3:$AA$1616,'Monthly Data'!$B6,Spreads!$AB$3:$AB$1616,'Monthly Data'!$C6) -> 310 | EE6: =AVERAGEIFS(Spreads!AT$3:AT$1616,Spreads!$AA$3:$AA$1616,'Monthly Data'!$B6,Spreads!$AB$3:$AB$1616,'Monthly Data'!$C6) -> 303.42857 | EF6: =_xlfn.MINIFS(Spreads!AU$3:AU$1616,Spreads!$AA$3:$AA$1616,'Monthly Data'!$B6,Spreads!$AB$3:$AB$1616,'Monthly Data'!$C6) -> 8.52 | EG6: =_xlfn.MAXIFS(Spreads!AU$3:AU$1616,Spreads!$AA$3:$AA$1616,'Monthly Data'!$B6,Spreads!$AB$3:$AB$1616,'Monthly Data'!$C6) -> 8.91 | EH6: =AVERAGEIFS(Spreads!AU$3:AU$1616,Spreads!$AA$3:$AA$1616,'Monthly Data'!$B6,Spreads!$AB$3:$AB$1616,'Monthly Data'!$C6) -> 8.7057143 | EI6: =_xlfn.MINIFS(Spreads!AV$3:AV$1616,Spreads!$AA$3:$AA$1616,'Monthly Data'!$B6,Spreads!$AB$3:$AB$1616,'Monthly Data'!$C6) -> 1.68903 | EJ6: =_xlfn.MAXIFS(Spreads!AV$3:AV$1616,Spreads!$AA$3:$AA$1616,'Monthly Data'!$B6,Spreads!$AB$3:$AB$1616,'Monthly Data'!$C6) -> 1.83047 | EK6: =AVERAGEIFS(Spreads!AV$3:AV$1616,Spreads!$AA$3:$AA$1616,'Monthly Data'!$B6,Spreads!$AB$3:$AB$1616,'Monthly Data'!$C6) -> 1.7757371 | EL6: =_xlfn.MINIFS(Spreads!AW$3:AW$1616,Spreads!$AA$3:$AA$1616,'Monthly Data'!$B6,Spreads!$AB$3:$AB$1616,'Monthly Data'!$C6) -> 1.9809684 | EM6: =_xlfn.MAXIFS(Spreads!AW$3:AW$1616,Spreads!$AA$3:$AA$1616,'Monthly Data'!$B6,Spreads!$AB$3:$AB$1616,'Monthly Data'!$C6) -> 2.1263396 | EN6: =AVERAGEIFS(Spreads!AW$3:AW$1616,Spreads!$AA$3:$AA$1616,'Monthly Data'!$B6,Spreads!$AB$3:$AB$1616,'Monthly Data'!$C6) -> 2.0698985 | EO6: =_xlfn.MINIFS(Spreads!AX$3:AX$1616,Spreads!$AA$3:$AA$1616,'Monthly Data'!$B6,Spreads!$AB$3:$AB$1616,'Monthly Data'!$C6) -> 0.2919384 | EP6: =_xlfn.MAXIFS(Spreads!AX$3:AX$1616,Spreads!$AA$3:$AA$1616,'Monthly Data'!$B6,Spreads!$AB$3:$AB$1616,'Monthly Data'!$C6) -> 0.2965716 | EQ6: =AVERAGEIFS(Spreads!AX$3:AX$1616,Spreads!$AA$3:$AA$1616,'Monthly Data'!$B6,Spreads!$AB$3:$AB$1616,'Monthly Data'!$C6) -> 0.2941614 | ER6: =_xlfn.MINIFS(Spreads!AY$3:AY$1616,Spreads!$AA$3:$AA$1616,'Monthly Data'!$B6,Spreads!$AB$3:$AB$1616,'Monthly Data'!$C6) -> 0.33281558 | ES6: =_xlfn.MAXIFS(Spreads!AY$3:AY$1616,Spreads!$AA$3:$AA$1616,'Monthly Data'!$B6,Spreads!$AB$3:$AB$1616,'Monthly Data'!$C6) -> 0.35113128 | ET6: =AVERAGEIFS(Spreads!AY$3:AY$1616,Spreads!$AA$3:$AA$1616,'Monthly Data'!$B6,Spreads!$AB$3:$AB$1616,'Monthly Data'!$C6) -> 0.34281226
A7: 43556 | B7: =MONTH(A7) -> 4 | C7: =YEAR(A7) -> 2019 | D7: =_xlfn.MINIFS(Spreads!B$3:B$1616,Spreads!$AA$3:$AA$1616,'Monthly Data'!$B7,Spreads!$AB$3:$AB$1616,'Monthly Data'!$C7) -> 29.8 | E7: =_xlfn.MAXIFS(Spreads!B$3:B$1616,Spreads!$AA$3:$AA$1616,'Monthly Data'!$B7,Spreads!$AB$3:$AB$1616,'Monthly Data'!$C7) -> 31.75 | F7: =AVERAGEIFS(Spreads!B$3:B$1616,Spreads!$AA$3:$AA$1616,'Monthly Data'!$B7,Spreads!$AB$3:$AB$1616,'Monthly Data'!$C7) -> 31.028095 | G7: =D7-F7 -> -1.2280952 | H7: =E7-F7 -> 0.72190476 | I7: =_xlfn.MINIFS(Spreads!C$3:C$1616,Spreads!$AA$3:$AA$1616,'Monthly Data'!$B7,Spreads!$AB$3:$AB$1616,'Monthly Data'!$C7) -> 26.65 | J7: =_xlfn.MAXIFS(Spreads!C$3:C$1616,Spreads!$AA$3:$AA$1616,'Monthly Data'!$B7,Spreads!$AB$3:$AB$1616,'Monthly Data'!$C7) -> 28.6 | K7: =AVERAGEIFS(Spreads!C$3:C$1616,Spreads!$AA$3:$AA$1616,'Monthly Data'!$B7,Spreads!$AB$3:$AB$1616,'Monthly Data'!$C7) -> 27.878095 | L7: =I7-K7 -> -1.2280952 | M7: =J7-K7 -> 0.72190476 | N7: =_xlfn.MINIFS(Spreads!D$3:D$1616,Spreads!$AA$3:$AA$1616,'Monthly Data'!$B7,Spreads!$AB$3:$AB$1616,'Monthly Data'!$C7) -> 29.14 | O7: =_xlfn.MAXIFS(Spreads!D$3:D$1616,Spreads!$AA$3:$AA$1616,'Monthly Data'!$B7,Spreads!$AB$3:$AB$1616,'Monthly Data'!$C7) -> 31.1 | P7: =AVERAGEIFS(Spreads!D$3:D$1616,Spreads!$AA$3:$AA$1616,'Monthly Data'!$B7,Spreads!$AB$3:$AB$1616,'Monthly Data'!$C7) -> 30.187619 | Q7: =N7-P7 -> -1.047619 | R7: =O7-P7 -> 0.91238095 | S7: =_xlfn.MINIFS(Spreads!F$3:F$1616,Spreads!$AA$3:$AA$1616,'Monthly Data'!$B7,Spreads!$AB$3:$AB$1616,'Monthly Data'!$C7) -> 27.589764 | T7: =_xlfn.MAXIFS(Spreads!F$3:F$1616,Spreads!$AA$3:$AA$1616,'Monthly Data'!$B7,Spreads!$AB$3:$AB$1616,'Monthly Data'!$C7) -> 28.701065 | U7: =AVERAGEIFS(Spreads!F$3:F$1616,Spreads!$AA$3:$AA$1616,'Monthly Data'!$B7,Spreads!$AB$3:$AB$1616,'Monthly Data'!$C7) -> 28.315512 | V7: =S7-U7 -> -0.725748 | W7: =T7-U7 -> 0.38555362 | X7: =_xlfn.MINIFS(Spreads!G$3:G$1616,Spreads!$AA$3:$AA$1616,'Monthly Data'!$B7,Spreads!$AB$3:$AB$1616,'Monthly Data'!$C7) -> 37.02 | Y7: =_xlfn.MAXIFS(Spreads!G$3:G$1616,Spreads!$AA$3:$AA$1616,'Monthly Data'!$B7,Spreads!$AB$3:$AB$1616,'Monthly Data'!$C7) -> 38.3 | Z7: =AVERAGEIFS(Spreads!G$3:G$1616,Spreads!$AA$3:$AA$1616,'Monthly Data'!$B7,Spreads!$AB$3:$AB$1616,'Monthly Data'!$C7) -> 37.842381 | AA7: =X7-Z7 -> -0.82238095 | AB7: =Y7-Z7 -> 0.45761905 | AC7: =_xlfn.MINIFS(Spreads!H$3:H$1616,Spreads!$AA$3:$AA$1616,'Monthly Data'!$B7,Spreads!$AB$3:$AB$1616,'Monthly Data'!$C7) -> 27.84 | AD7: =_xlfn.MAXIFS(Spreads!H$3:H$1616,Spreads!$AA$3:$AA$1616,'Monthly Data'!$B7,Spreads!$AB$3:$AB$1616,'Monthly Data'!$C7) -> 29.2 | AE7: =AVERAGEIFS(Spreads!H$3:H$1616,Spreads!$AA$3:$AA$1616,'Monthly Data'!$B7,Spreads!$AB$3:$AB$1616,'Monthly Data'!$C7) -> 28.644286 | AF7: =AC7-AE7 -> -0.80428571 | AG7: =AD7-AE7 -> 0.55571429 | AH7: =AE7/AE6-1 -> -0.025057132 | AI7: =F7-AE7 -> 2.3838095 | AJ7: =K7-AE7 -> -0.76619048 | AK7: =AI7-AJ7 -> 3.15 | AQ7: =AVERAGEIFS(Spreads!AV$3:AV$1616,Spreads!$AA$3:$AA$1616,'Monthly Data'!$B7,Spreads!$AB$3:$AB$1616,'Monthly Data'!$C7) -> 1.8151657 | AS7: =A7 -> 43556 | AT7: =_xlfn.MINIFS(Spreads!M$3:M$1616,Spreads!$AA$3:$AA$1616,'Monthly Data'!$B7,Spreads!$AB$3:$AB$1616,'Monthly Data'!$C7) -> 1.96 | AU7: =_xlfn.MAXIFS(Spreads!M$3:M$1616,Spreads!$AA$3:$AA$1616,'Monthly Data'!$B7,Spreads!$AB$3:$AB$1616,'Monthly Data'!$C7) -> 2.55 | AV7: =AVERAGEIFS(Spreads!M$3:M$1616,Spreads!$AA$3:$AA$1616,'Monthly Data'!$B7,Spreads!$AB$3:$AB$1616,'Monthly Data'!$C7) -> 2.3838095 | AW7: =AT7-AV7 -> -0.42380952 | AX7: =AU7-AV7 -> 0.16619048 | AY7: =_xlfn.MINIFS(Spreads!N$3:N$1616,Spreads!$AA$3:$AA$1616,'Monthly Data'!$B7,Spreads!$AB$3:$AB$1616,'Monthly Data'!$C7) -> 3.15 | AZ7: =_xlfn.MAXIFS(Spreads!N$3:N$1616,Spreads!$AA$3:$AA$1616,'Monthly Data'!$B7,Spreads!$AB$3:$AB$1616,'Monthly Data'!$C7) -> 3.15 | BA7: =AVERAGEIFS(Spreads!N$3:N$1616,Spreads!$AA$3:$AA$1616,'Monthly Data'!$B7,Spreads!$AB$3:$AB$1616,'Monthly Data'!$C7) -> 3.15 | BB7: =AY7-BA7 -> 0 | BC7: =AZ7-BA7 -> 0 | BD7: =_xlfn.MINIFS(Spreads!O$3:O$1616,Spreads!$AA$3:$AA$1616,'Monthly Data'!$B7,Spreads!$AB$3:$AB$1616,'Monthly Data'!$C7) -> -1.19 | BE7: =_xlfn.MAXIFS(Spreads!O$3:O$1616,Spreads!$AA$3:$AA$1616,'Monthly Data'!$B7,Spreads!$AB$3:$AB$1616,'Monthly Data'!$C7) -> -0.6 | BF7: =AVERAGEIFS(Spreads!O$3:O$1616,Spreads!$AA$3:$AA$1616,'Monthly Data'!$B7,Spreads!$AB$3:$AB$1616,'Monthly Data'!$C7) -> -0.76619048 | BG7: =BD7-BF7 -> -0.42380952 | BH7: =BE7-BF7 -> 0.16619048 | BI7: =_xlfn.MINIFS(Spreads!P$3:P$1616,Spreads!$AA$3:$AA$1616,'Monthly Data'!$B7,Spreads!$AB$3:$AB$1616,'Monthly Data'!$C7) -> 1.19 | BJ7: =_xlfn.MAXIFS(Spreads!P$3:P$1616,Spreads!$AA$3:$AA$1616,'Monthly Data'!$B7,Spreads!$AB$3:$AB$1616,'Monthly Data'!$C7) -> 1.9 | BK7: =AVERAGEIFS(Spreads!P$3:P$1616,Spreads!$AA$3:$AA$1616,'Monthly Data'!$B7,Spreads!$AB$3:$AB$1616,'Monthly Data'!$C7) -> 1.5433333 | BL7: =BI7-BK7 -> -0.35333333 | BM7: =BJ7-BK7 -> 0.35666667 | BN7: =_xlfn.MINIFS(Spreads!R$3:R$1616,Spreads!$AA$3:$AA$1616,'Monthly Data'!$B7,Spreads!$AB$3:$AB$1616,'Monthly Data'!$C7) -> -0.98023631 | BO7: =_xlfn.MAXIFS(Spreads!R$3:R$1616,Spreads!$AA$3:$AA$1616,'Monthly Data'!$B7,Spreads!$AB$3:$AB$1616,'Monthly Data'!$C7) -> 0.36211356 | BP7: =AVERAGEIFS(Spreads!R$3:R$1616,Spreads!$AA$3:$AA$1616,'Monthly Data'!$B7,Spreads!$AB$3:$AB$1616,'Monthly Data'!$C7) -> -0.30922516 | BQ7: =BN7-BP7 -> -0.67101115 | BR7: =BO7-BP7 -> 0.67133872 | BS7: =_xlfn.MINIFS(Spreads!S$3:S$1616,Spreads!$AA$3:$AA$1616,'Monthly Data'!$B7,Spreads!$AB$3:$AB$1616,'Monthly Data'!$C7) -> 9 | BT7: =_xlfn.MAXIFS(Spreads!S$3:S$1616,Spreads!$AA$3:$AA$1616,'Monthly Data'!$B7,Spreads!$AB$3:$AB$1616,'Monthly Data'!$C7) -> 9.7 | BU7: =AVERAGEIFS(Spreads!S$3:S$1616,Spreads!$AA$3:$AA$1616,'Monthly Data'!$B7,Spreads!$AB$3:$AB$1616,'Monthly Data'!$C7) -> 9.1980952 | BV7: =BS7-BU7 -> -0.19809524 | BW7: =BT7-BU7 -> 0.50190476 | BX7: =_xlfn.MINIFS(Spreads!T$3:T$1616,Spreads!$AA$3:$AA$1616,'Monthly Data'!$B7,Spreads!$AB$3:$AB$1616,'Monthly Data'!$C7) -> 6.45 | BY7: =_xlfn.MAXIFS(Spreads!T$3:T$1616,Spreads!$AA$3:$AA$1616,'Monthly Data'!$B7,Spreads!$AB$3:$AB$1616,'Monthly Data'!$C7) -> 7.72 | BZ7: =AVERAGEIFS(Spreads!T$3:T$1616,Spreads!$AA$3:$AA$1616,'Monthly Data'!$B7,Spreads!$AB$3:$AB$1616,'Monthly Data'!$C7) -> 6.8142857 | CA7: =BX7-BZ7 -> -0.36428571 | CB7: =BY7-BZ7 -> 0.90571429 | DJ7: =X7-D7 -> 7.22 | DK7: =Y7-E7 -> 6.55 | DL7: =Z7-F7 -> 6.8142857 | DV7: =A7 -> 43556 | DW7: =_xlfn.MINIFS(Spreads!X$3:X$1616,Spreads!$AA$3:$AA$1616,'Monthly Data'!$B7,Spreads!$AB$3:$AB$1616,'Monthly Data'!$C7) -> 27.975317 | DX7: =_xlfn.MAXIFS(Spreads!X$3:X$1616,Spreads!$AA$3:$AA$1616,'Monthly Data'!$B7,Spreads!$AB$3:$AB$1616,'Monthly Data'!$C7) -> 28.905182 | DY7: =AVERAGEIFS(Spreads!X$3:X$1616,Spreads!$AA$3:$AA$1616,'Monthly Data'!$B7,Spreads!$AB$3:$AB$1616,'Monthly Data'!$C7) -> 28.412467 | DZ7: =_xlfn.MINIFS(Spreads!AM$3:AM$1616,Spreads!$AA$3:$AA$1616,'Monthly Data'!$B7,Spreads!$AB$3:$AB$1616,'Monthly Data'!$C7) -> 616.75 | EA7: =_xlfn.MAXIFS(Spreads!AM$3:AM$1616,Spreads!$AA$3:$AA$1616,'Monthly Data'!$B7,Spreads!$AB$3:$AB$1616,'Monthly Data'!$C7) -> 637.25 | EB7: =AVERAGEIFS(Spreads!AM$3:AM$1616,Spreads!$AA$3:$AA$1616,'Monthly Data'!$B7,Spreads!$AB$3:$AB$1616,'Monthly Data'!$C7) -> 626.3875 | EC7: =_xlfn.MINIFS(Spreads!AT$3:AT$1616,Spreads!$AA$3:$AA$1616,'Monthly Data'!$B7,Spreads!$AB$3:$AB$1616,'Monthly Data'!$C7) -> 295 | ED7: =_xlfn.MAXIFS(Spreads!AT$3:AT$1616,Spreads!$AA$3:$AA$1616,'Monthly Data'!$B7,Spreads!$AB$3:$AB$1616,'Monthly Data'!$C7) -> 307 | EE7: =AVERAGEIFS(Spreads!AT$3:AT$1616,Spreads!$AA$3:$AA$1616,'Monthly Data'!$B7,Spreads!$AB$3:$AB$1616,'Monthly Data'!$C7) -> 301.52381 | EF7: =_xlfn.MINIFS(Spreads!AU$3:AU$1616,Spreads!$AA$3:$AA$1616,'Monthly Data'!$B7,Spreads!$AB$3:$AB$1616,'Monthly Data'!$C7) -> 8.16 | EG7: =_xlfn.MAXIFS(Spreads!AU$3:AU$1616,Spreads!$AA$3:$AA$1616,'Monthly Data'!$B7,Spreads!$AB$3:$AB$1616,'Monthly Data'!$C7) -> 8.75 | EH7: =AVERAGEIFS(Spreads!AU$3:AU$1616,Spreads!$AA$3:$AA$1616,'Monthly Data'!$B7,Spreads!$AB$3:$AB$1616,'Monthly Data'!$C7) -> 8.532381 | EI7: =_xlfn.MINIFS(Spreads!AV$3:AV$1616,Spreads!$AA$3:$AA$1616,'Monthly Data'!$B7,Spreads!$AB$3:$AB$1616,'Monthly Data'!$C7) -> 1.75276 | EJ7: =_xlfn.MAXIFS(Spreads!AV$3:AV$1616,Spreads!$AA$3:$AA$1616,'Monthly Data'!$B7,Spreads!$AB$3:$AB$1616,'Monthly Data'!$C7) -> 1.99157 | EK7: =AVERAGEIFS(Spreads!AV$3:AV$1616,Spreads!$AA$3:$AA$1616,'Monthly Data'!$B7,Spreads!$AB$3:$AB$1616,'Monthly Data'!$C7) -> 1.8151657 | EL7: =_xlfn.MINIFS(Spreads!AW$3:AW$1616,Spreads!$AA$3:$AA$1616,'Monthly Data'!$B7,Spreads!$AB$3:$AB$1616,'Monthly Data'!$C7) -> 2.0477638 | EM7: =_xlfn.MAXIFS(Spreads!AW$3:AW$1616,Spreads!$AA$3:$AA$1616,'Monthly Data'!$B7,Spreads!$AB$3:$AB$1616,'Monthly Data'!$C7) -> 2.2902476 | EN7: =AVERAGEIFS(Spreads!AW$3:AW$1616,Spreads!$AA$3:$AA$1616,'Monthly Data'!$B7,Spreads!$AB$3:$AB$1616,'Monthly Data'!$C7) -> 2.11111 | EO7: =_xlfn.MINIFS(Spreads!AX$3:AX$1616,Spreads!$AA$3:$AA$1616,'Monthly Data'!$B7,Spreads!$AB$3:$AB$1616,'Monthly Data'!$C7) -> 0.294255 | EP7: =_xlfn.MAXIFS(Spreads!AX$3:AX$1616,Spreads!$AA$3:$AA$1616,'Monthly Data'!$B7,Spreads!$AB$3:$AB$1616,'Monthly Data'!$C7) -> 0.298818 | EQ7: =AVERAGEIFS(Spreads!AX$3:AX$1616,Spreads!$AA$3:$AA$1616,'Monthly Data'!$B7,Spreads!$AB$3:$AB$1616,'Monthly Data'!$C7) -> 0.29594426 | ER7: =_xlfn.MINIFS(Spreads!AY$3:AY$1616,Spreads!$AA$3:$AA$1616,'Monthly Data'!$B7,Spreads!$AB$3:$AB$1616,'Monthly Data'!$C7) -> 0.33105671 | ES7: =_xlfn.MAXIFS(Spreads!AY$3:AY$1616,Spreads!$AA$3:$AA$1616,'Monthly Data'!$B7,Spreads!$AB$3:$AB$1616,'Monthly Data'!$C7) -> 0.34373228 | ET7: =AVERAGEIFS(Spreads!AY$3:AY$1616,Spreads!$AA$3:$AA$1616,'Monthly Data'!$B7,Spreads!$AB$3:$AB$1616,'Monthly Data'!$C7) -> 0.33874675
A8: 43586 | B8: =MONTH(A8) -> 5 | C8: =YEAR(A8) -> 2019 | D8: =_xlfn.MINIFS(Spreads!B$3:B$1616,Spreads!$AA$3:$AA$1616,'Monthly Data'!$B8,Spreads!$AB$3:$AB$1616,'Monthly Data'!$C8) -> 29.26 | E8: =_xlfn.MAXIFS(Spreads!B$3:B$1616,Spreads!$AA$3:$AA$1616,'Monthly Data'!$B8,Spreads!$AB$3:$AB$1616,'Monthly Data'!$C8) -> 31.43 | F8: =AVERAGEIFS(Spreads!B$3:B$1616,Spreads!$AA$3:$AA$1616,'Monthly Data'!$B8,Spreads!$AB$3:$AB$1616,'Monthly Data'!$C8) -> 30.131364 | G8: =D8-F8 -> -0.87136364 | H8: =E8-F8 -> 1.2986364 | I8: =_xlfn.MINIFS(Spreads!C$3:C$1616,Spreads!$AA$3:$AA$1616,'Monthly Data'!$B8,Spreads!$AB$3:$AB$1616,'Monthly Data'!$C8) -> 26.11 | J8: =_xlfn.MAXIFS(Spreads!C$3:C$1616,Spreads!$AA$3:$AA$1616,'Monthly Data'!$B8,Spreads!$AB$3:$AB$1616,'Monthly Data'!$C8) -> 28.28 | K8: =AVERAGEIFS(Spreads!C$3:C$1616,Spreads!$AA$3:$AA$1616,'Monthly Data'!$B8,Spreads!$AB$3:$AB$1616,'Monthly Data'!$C8) -> 26.981364 | L8: =I8-K8 -> -0.87136364 | M8: =J8-K8 -> 1.2986364 | N8: =_xlfn.MINIFS(Spreads!D$3:D$1616,Spreads!$AA$3:$AA$1616,'Monthly Data'!$B8,Spreads!$AB$3:$AB$1616,'Monthly Data'!$C8) -> 28.36 | O8: =_xlfn.MAXIFS(Spreads!D$3:D$1616,Spreads!$AA$3:$AA$1616,'Monthly Data'!$B8,Spreads!$AB$3:$AB$1616,'Monthly Data'!$C8) -> 30.28 | P8: =AVERAGEIFS(Spreads!D$3:D$1616,Spreads!$AA$3:$AA$1616,'Monthly Data'!$B8,Spreads!$AB$3:$AB$1616,'Monthly Data'!$C8) -> 29.321364 | Q8: =N8-P8 -> -0.96136364 | R8: =O8-P8 -> 0.95863636 | S8: =_xlfn.MINIFS(Spreads!F$3:F$1616,Spreads!$AA$3:$AA$1616,'Monthly Data'!$B8,Spreads!$AB$3:$AB$1616,'Monthly Data'!$C8) -> 27.884599 | T8: =_xlfn.MAXIFS(Spreads!F$3:F$1616,Spreads!$AA$3:$AA$1616,'Monthly Data'!$B8,Spreads!$AB$3:$AB$1616,'Monthly Data'!$C8) -> 29.245376 | U8: =AVERAGEIFS(Spreads!F$3:F$1616,Spreads!$AA$3:$AA$1616,'Monthly Data'!$B8,Spreads!$AB$3:$AB$1616,'Monthly Data'!$C8) -> 28.430611 | V8: =S8-U8 -> -0.54601197 | W8: =T8-U8 -> 0.81476552 | X8: =_xlfn.MINIFS(Spreads!G$3:G$1616,Spreads!$AA$3:$AA$1616,'Monthly Data'!$B8,Spreads!$AB$3:$AB$1616,'Monthly Data'!$C8) -> 36.61 | Y8: =_xlfn.MAXIFS(Spreads!G$3:G$1616,Spreads!$AA$3:$AA$1616,'Monthly Data'!$B8,Spreads!$AB$3:$AB$1616,'Monthly Data'!$C8) -> 37.78 | Z8: =AVERAGEIFS(Spreads!G$3:G$1616,Spreads!$AA$3:$AA$1616,'Monthly Data'!$B8,Spreads!$AB$3:$AB$1616,'Monthly Data'!$C8) -> 37.230455 | AA8: =X8-Z8 -> -0.62045455 | AB8: =Y8-Z8 -> 0.54954545 | AC8: =_xlfn.MINIFS(Spreads!H$3:H$1616,Spreads!$AA$3:$AA$1616,'Monthly Data'!$B8,Spreads!$AB$3:$AB$1616,'Monthly Data'!$C8) -> 26.61 | AD8: =_xlfn.MAXIFS(Spreads!H$3:H$1616,Spreads!$AA$3:$AA$1616,'Monthly Data'!$B8,Spreads!$AB$3:$AB$1616,'Monthly Data'!$C8) -> 27.78 | AE8: =AVERAGEIFS(Spreads!H$3:H$1616,Spreads!$AA$3:$AA$1616,'Monthly Data'!$B8,Spreads!$AB$3:$AB$1616,'Monthly Data'!$C8) -> 27.230455 | AF8: =AC8-AE8 -> -0.62045455 | AG8: =AD8-AE8 -> 0.54954545 | AH8: =AE8/AE7-1 -> -0.049358227 | AI8: =F8-AE8 -> 2.9009091 | AJ8: =K8-AE8 -> -0.24909091 | AK8: =AI8-AJ8 -> 3.15 | AQ8: =AVERAGEIFS(Spreads!AV$3:AV$1616,Spreads!$AA$3:$AA$1616,'Monthly Data'!$B8,Spreads!$AB$3:$AB$1616,'Monthly Data'!$C8) -> 2.041615 | AS8: =A8 -> 43586 | AT8: =_xlfn.MINIFS(Spreads!M$3:M$1616,Spreads!$AA$3:$AA$1616,'Monthly Data'!$B8,Spreads!$AB$3:$AB$1616,'Monthly Data'!$C8) -> 2.28 | AU8: =_xlfn.MAXIFS(Spreads!M$3:M$1616,Spreads!$AA$3:$AA$1616,'Monthly Data'!$B8,Spreads!$AB$3:$AB$1616,'Monthly Data'!$C8) -> 3.65 | AV8: =AVERAGEIFS(Spreads!M$3:M$1616,Spreads!$AA$3:$AA$1616,'Monthly Data'!$B8,Spreads!$AB$3:$AB$1616,'Monthly Data'!$C8) -> 2.9009091 | AW8: =AT8-AV8 -> -0.62090909 | AX8: =AU8-AV8 -> 0.74909091 | AY8: =_xlfn.MINIFS(Spreads!N$3:N$1616,Spreads!$AA$3:$AA$1616,'Monthly Data'!$B8,Spreads!$AB$3:$AB$1616,'Monthly Data'!$C8) -> 3.15 | AZ8: =_xlfn.MAXIFS(Spreads!N$3:N$1616,Spreads!$AA$3:$AA$1616,'Monthly Data'!$B8,Spreads!$AB$3:$AB$1616,'Monthly Data'!$C8) -> 3.15 | BA8: =AVERAGEIFS(Spreads!N$3:N$1616,Spreads!$AA$3:$AA$1616,'Monthly Data'!$B8,Spreads!$AB$3:$AB$1616,'Monthly Data'!$C8) -> 3.15 | BB8: =AY8-BA8 -> 0 | BC8: =AZ8-BA8 -> 0 | BD8: =_xlfn.MINIFS(Spreads!O$3:O$1616,Spreads!$AA$3:$AA$1616,'Monthly Data'!$B8,Spreads!$AB$3:$AB$1616,'Monthly Data'!$C8) -> -0.87 | BE8: =_xlfn.MAXIFS(Spreads!O$3:O$1616,Spreads!$AA$3:$AA$1616,'Monthly Data'!$B8,Spreads!$AB$3:$AB$1616,'Monthly Data'!$C8) -> 0.5 | BF8: =AVERAGEIFS(Spreads!O$3:O$1616,Spreads!$AA$3:$AA$1616,'Monthly Data'!$B8,Spreads!$AB$3:$AB$1616,'Monthly Data'!$C8) -> -0.24909091 | BG8: =BD8-BF8 -> -0.62090909 | BH8: =BE8-BF8 -> 0.74909091 | BI8: =_xlfn.MINIFS(Spreads!P$3:P$1616,Spreads!$AA$3:$AA$1616,'Monthly Data'!$B8,Spreads!$AB$3:$AB$1616,'Monthly Data'!$C8) -> 1.75 | BJ8: =_xlfn.MAXIFS(Spreads!P$3:P$1616,Spreads!$AA$3:$AA$1616,'Monthly Data'!$B8,Spreads!$AB$3:$AB$1616,'Monthly Data'!$C8) -> 2.5 | BK8: =AVERAGEIFS(Spreads!P$3:P$1616,Spreads!$AA$3:$AA$1616,'Monthly Data'!$B8,Spreads!$AB$3:$AB$1616,'Monthly Data'!$C8) -> 2.0909091 | BL8: =BI8-BK8 -> -0.34090909 | BM8: =BJ8-BK8 -> 0.40909091 | BN8: =_xlfn.MINIFS(Spreads!R$3:R$1616,Spreads!$AA$3:$AA$1616,'Monthly Data'!$B8,Spreads!$AB$3:$AB$1616,'Monthly Data'!$C8) -> 0.39593862 | BO8: =_xlfn.MAXIFS(Spreads!R$3:R$1616,Spreads!$AA$3:$AA$1616,'Monthly Data'!$B8,Spreads!$AB$3:$AB$1616,'Monthly Data'!$C8) -> 2.1886772 | BP8: =AVERAGEIFS(Spreads!R$3:R$1616,Spreads!$AA$3:$AA$1616,'Monthly Data'!$B8,Spreads!$AB$3:$AB$1616,'Monthly Data'!$C8) -> 1.2161108 | BQ8: =BN8-BP8 -> -0.82017216 | BR8: =BO8-BP8 -> 0.97256646 | BS8: =_xlfn.MINIFS(Spreads!S$3:S$1616,Spreads!$AA$3:$AA$1616,'Monthly Data'!$B8,Spreads!$AB$3:$AB$1616,'Monthly Data'!$C8) -> 10 | BT8: =_xlfn.MAXIFS(Spreads!S$3:S$1616,Spreads!$AA$3:$AA$1616,'Monthly Data'!$B8,Spreads!$AB$3:$AB$1616,'Monthly Data'!$C8) -> 10 | BU8: =AVERAGEIFS(Spreads!S$3:S$1616,Spreads!$AA$3:$AA$1616,'Monthly Data'!$B8,Spreads!$AB$3:$AB$1616,'Monthly Data'!$C8) -> 10 | BV8: =BS8-BU8 -> 0 | BW8: =BT8-BU8 -> 0 | BX8: =_xlfn.MINIFS(Spreads!T$3:T$1616,Spreads!$AA$3:$AA$1616,'Monthly Data'!$B8,Spreads!$AB$3:$AB$1616,'Monthly Data'!$C8) -> 6.35 | BY8: =_xlfn.MAXIFS(Spreads!T$3:T$1616,Spreads!$AA$3:$AA$1616,'Monthly Data'!$B8,Spreads!$AB$3:$AB$1616,'Monthly Data'!$C8) -> 7.72 | BZ8: =AVERAGEIFS(Spreads!T$3:T$1616,Spreads!$AA$3:$AA$1616,'Monthly Data'!$B8,Spreads!$AB$3:$AB$1616,'Monthly Data'!$C8) -> 7.0990909 | CA8: =BX8-BZ8 -> -0.74909091 | CB8: =BY8-BZ8 -> 0.62090909 | DJ8: =X8-D8 -> 7.35 | DK8: =Y8-E8 -> 6.35 | DL8: =Z8-F8 -> 7.0990909 | DV8: =A8 -> 43586 | DW8: =_xlfn.MINIFS(Spreads!X$3:X$1616,Spreads!$AA$3:$AA$1616,'Monthly Data'!$B8,Spreads!$AB$3:$AB$1616,'Monthly Data'!$C8) -> 27.975317 | DX8: =_xlfn.MAXIFS(Spreads!X$3:X$1616,Spreads!$AA$3:$AA$1616,'Monthly Data'!$B8,Spreads!$AB$3:$AB$1616,'Monthly Data'!$C8) -> 29.290736 | DY8: =AVERAGEIFS(Spreads!X$3:X$1616,Spreads!$AA$3:$AA$1616,'Monthly Data'!$B8,Spreads!$AB$3:$AB$1616,'Monthly Data'!$C8) -> 28.508288 | DZ8: =_xlfn.MINIFS(Spreads!AM$3:AM$1616,Spreads!$AA$3:$AA$1616,'Monthly Data'!$B8,Spreads!$AB$3:$AB$1616,'Monthly Data'!$C8) -> 616.75 | EA8: =_xlfn.MAXIFS(Spreads!AM$3:AM$1616,Spreads!$AA$3:$AA$1616,'Monthly Data'!$B8,Spreads!$AB$3:$AB$1616,'Monthly Data'!$C8) -> 645.75 | EB8: =AVERAGEIFS(Spreads!AM$3:AM$1616,Spreads!$AA$3:$AA$1616,'Monthly Data'!$B8,Spreads!$AB$3:$AB$1616,'Monthly Data'!$C8) -> 628.5 | EC8: =_xlfn.MINIFS(Spreads!AT$3:AT$1616,Spreads!$AA$3:$AA$1616,'Monthly Data'!$B8,Spreads!$AB$3:$AB$1616,'Monthly Data'!$C8) -> 282 | ED8: =_xlfn.MAXIFS(Spreads!AT$3:AT$1616,Spreads!$AA$3:$AA$1616,'Monthly Data'!$B8,Spreads!$AB$3:$AB$1616,'Monthly Data'!$C8) -> 322 | EE8: =AVERAGEIFS(Spreads!AT$3:AT$1616,Spreads!$AA$3:$AA$1616,'Monthly Data'!$B8,Spreads!$AB$3:$AB$1616,'Monthly Data'!$C8) -> 295.13636 | EF8: =_xlfn.MINIFS(Spreads!AU$3:AU$1616,Spreads!$AA$3:$AA$1616,'Monthly Data'!$B8,Spreads!$AB$3:$AB$1616,'Monthly Data'!$C8) -> 7.71 | EG8: =_xlfn.MAXIFS(Spreads!AU$3:AU$1616,Spreads!$AA$3:$AA$1616,'Monthly Data'!$B8,Spreads!$AB$3:$AB$1616,'Monthly Data'!$C8) -> 8.57 | EH8: =AVERAGEIFS(Spreads!AU$3:AU$1616,Spreads!$AA$3:$AA$1616,'Monthly Data'!$B8,Spreads!$AB$3:$AB$1616,'Monthly Data'!$C8) -> 8.0509091 | EI8: =_xlfn.MINIFS(Spreads!AV$3:AV$1616,Spreads!$AA$3:$AA$1616,'Monthly Data'!$B8,Spreads!$AB$3:$AB$1616,'Monthly Data'!$C8) -> 1.79576 | EJ8: =_xlfn.MAXIFS(Spreads!AV$3:AV$1616,Spreads!$AA$3:$AA$1616,'Monthly Data'!$B8,Spreads!$AB$3:$AB$1616,'Monthly Data'!$C8) -> 2.30576 | EK8: =AVERAGEIFS(Spreads!AV$3:AV$1616,Spreads!$AA$3:$AA$1616,'Monthly Data'!$B8,Spreads!$AB$3:$AB$1616,'Monthly Data'!$C8) -> 2.041615 | EL8: =_xlfn.MINIFS(Spreads!AW$3:AW$1616,Spreads!$AA$3:$AA$1616,'Monthly Data'!$B8,Spreads!$AB$3:$AB$1616,'Monthly Data'!$C8) -> 2.0942738 | EM8: =_xlfn.MAXIFS(Spreads!AW$3:AW$1616,Spreads!$AA$3:$AA$1616,'Monthly Data'!$B8,Spreads!$AB$3:$AB$1616,'Monthly Data'!$C8) -> 2.6007638 | EN8: =AVERAGEIFS(Spreads!AW$3:AW$1616,Spreads!$AA$3:$AA$1616,'Monthly Data'!$B8,Spreads!$AB$3:$AB$1616,'Monthly Data'!$C8) -> 2.3396576 | EO8: =_xlfn.MINIFS(Spreads!AX$3:AX$1616,Spreads!$AA$3:$AA$1616,'Monthly Data'!$B8,Spreads!$AB$3:$AB$1616,'Monthly Data'!$C8) -> 0.2950038 | EP8: =_xlfn.MAXIFS(Spreads!AX$3:AX$1616,Spreads!$AA$3:$AA$1616,'Monthly Data'!$B8,Spreads!$AB$3:$AB$1616,'Monthly Data'!$C8) -> 0.3000816 | EQ8: =AVERAGEIFS(Spreads!AX$3:AX$1616,Spreads!$AA$3:$AA$1616,'Monthly Data'!$B8,Spreads!$AB$3:$AB$1616,'Monthly Data'!$C8) -> 0.29804261 | ER8: =_xlfn.MINIFS(Spreads!AY$3:AY$1616,Spreads!$AA$3:$AA$1616,'Monthly Data'!$B8,Spreads!$AB$3:$AB$1616,'Monthly Data'!$C8) -> 0.32703741 | ES8: =_xlfn.MAXIFS(Spreads!AY$3:AY$1616,Spreads!$AA$3:$AA$1616,'Monthly Data'!$B8,Spreads!$AB$3:$AB$1616,'Monthly Data'!$C8) -> 0.34472612 | ET8: =AVERAGEIFS(Spreads!AY$3:AY$1616,Spreads!$AA$3:$AA$1616,'Monthly Data'!$B8,Spreads!$AB$3:$AB$1616,'Monthly Data'!$C8) -> 0.33709028
