Workbook

Sheet Futures Price Forecasts
B1: Average Nearby Futures
B2: Beans | E2: Meal | I2: Oil | L2: Margin | M2: Oil Share | O2: Updated: | P2: 43751 | T2: Corn Futures
D3: High | E3: Average | F3: Low | H3: High | I3: Average | J3: Low | O3: Based on : | P3: Oct 11 Closes | S3: High | T3: Futures | U3: Low
A4: 43132 | B4: =Prices!B580 -> #DIV/0! | E4: =Prices!C580 -> 360.51 | I4: =Prices!D580 -> 32.18 | L4: =Prices!E581 -> #DIV/0! | M4: =Prices!F581 -> #DIV/0!
A5: 43160 | B5: =Prices!B581 -> #DIV/0! | E5: =Prices!C581 -> 375.15 | I5: =Prices!D581 -> 31.85 | L5: =Prices!E582 -> #DIV/0! | M5: =Prices!F582 -> #DIV/0!
A6: 43191 | B6: =Prices!B582 -> #DIV/0! | E6: =Prices!C582 -> 380.78 | I6: =Prices!D582 -> 31.35 | L6: =Prices!E583 -> #DIV/0! | M6: =Prices!F583 -> #DIV/0!
A7: 43221 | B7: =Prices!B583 -> #DIV/0! | E7: =Prices!C583 -> 384.5 | I7: =Prices!D583 -> 31 | L7: =Prices!E584 -> #DIV/0! | M7: =Prices!F584 -> #DIV/0!
A8: 43252 | B8: =Prices!B584 -> #DIV/0! | E8: =Prices!C584 -> 345.95 | I8: =Prices!D584 -> 29.82 | L8: =Prices!E585 -> #DIV/0! | M8: =Prices!F585 -> #DIV/0!
A9: 43282 | B9: =Prices!B585 -> #DIV/0! | E9: =Prices!C585 -> 330.37 | I9: =Prices!D585 -> 28.36 | L9: =Prices!E586 -> #DIV/0! | M9: =Prices!F586 -> #DIV/0!
A10: 43313 | B10: =Prices!B586 -> #DIV/0! | E10: =Prices!C586 -> 322.5 | I10: =Prices!D586 -> 28.33 | L10: =Prices!E587 -> #DIV/0! | M10: =Prices!F587 -> #DIV/0!
A11: 43344 | B11: =Prices!B587 -> #DIV/0! | E11: =Prices!C587 -> 311.51 | I11: =Prices!D587 -> 28.26 | L11: =Prices!E588 -> #DIV/0! | M11: =Prices!F588 -> #DIV/0!
A12: 43374 | B12: =Prices!B588 -> #DIV/0! | E12: =Prices!C588 -> 313.95217 | I12: =Prices!D588 -> 29.051739 | L12: =Prices!E589 -> #DIV/0! | M12: =Prices!F589 -> #DIV/0!
A13: 43405 | B13: =Prices!B589 -> #DIV/0! | E13: =Prices!C589 -> 307.31 | I13: =Prices!D589 -> 27.69 | L13: =Prices!E590 -> #DIV/0! | M13: =Prices!F590 -> #DIV/0!
A14: 43435 | B14: =Prices!B590 -> #DIV/0! | E14: =Prices!C590 -> 309.31 | I14: =Prices!D590 -> 28.32 | L14: =Prices!E591 -> #DIV/0! | M14: =Prices!F591 -> #DIV/0!
A15: 43466 | B15: =Prices!B591 -> #DIV/0! | E15: =Prices!C591 -> 314.51905 | I15: =Prices!D591 -> 29.000952 | L15: =Prices!E592 -> #DIV/0! | M15: =Prices!F592 -> #DIV/0!
... A18: 43556 | B18: =Prices!B594 -> #DIV/0! | E18: =Prices!C594 -> 305.80952 | I18: =Prices!D594 -> 28.556667 | L18: =Prices!E595 -> #DIV/0! | M18: =Prices!F595 -> #DIV/0!
A19: 43586 | B19: =Prices!B595 -> #DIV/0! | E19: =Prices!C595 -> 300.22273 | I19: =Prices!D595 -> 27.230455 | L19: =Prices!E596 -> #DIV/0! | M19: =Prices!F596 -> #DIV/0! | R19: 43586
A20: 43617 | B20: =Prices!B596 -> #DIV/0! | E20: =Prices!C596 -> 317.69 | I20: =Prices!D596 -> 27.85 | L20: =Prices!E597 -> #DIV/0! | M20: =Prices!F597 -> #DIV/0! | R20: 43617
A21: 43647 | B21: =Prices!B597 -> #DIV/0! | E21: =Prices!C597 -> 307.1 | I21: =Prices!D597 -> 28.055 | L21: =Prices!E598 -> #DIV/0! | M21: =Prices!F598 -> #DIV/0! | R21: 43647
A22: 43678 | B22: =Prices!B598 -> #DIV/0! | E22: =Prices!C598 -> 294.19091 | I22: =Prices!D598 -> 28.57 | L22: =Prices!E599 -> #DIV/0! | M22: =Prices!F599 -> #DIV/0! | R22: 43678
A23: 43709 | B23: =Prices!B599 -> #DIV/0! | E23: =Prices!C599 -> 293.005 | I23: =Prices!D599 -> 29.063 | L23: =Prices!E600 -> #DIV/0! | M23: =Prices!F600 -> #DIV/0! | R23: 43709
A24: 43739 | B24: =Prices!B600 -> #DIV/0! | E24: =Prices!C600 -> 306.21739 | I24: =Prices!D600 -> 30.28 | L24: =Prices!E601 -> #DIV/0! | M24: =Prices!F601 -> #DIV/0! | R24: 43739
A25: 43770 | B25: =Prices!B601 -> #DIV/0! | E25: =Prices!C601 -> 300.815 | I25: =Prices!D601 -> 30.958 | L25: =Prices!E602 -> #DIV/0! | M25: =Prices!F602 -> #DIV/0! | R25: 43770 | S25: =[3]Prices!$B593*100 -> 391.75 | T25: =[3]Prices!$D593*100 -> 375.1875 | U25: =[3]Prices!$C593*100 -> 365.75 | W25: =S25-U25 -> 26
A26: 43800 | B26: =Prices!B602 -> #DIV/0! | E26: =Prices!C602 -> 298.44286 | I26: =Prices!D602 -> 32.689524 | L26: =Prices!E603 -> #DIV/0! | M26: =Prices!F603 -> #DIV/0! | R26: 43800 | S26: =[3]Prices!$B594*100 -> 392 | T26: =[3]Prices!$D594*100 -> 383.2381 | U26: =[3]Prices!$C594*100 -> 370.84246 | W26: =S26-U26 -> 21.157545
A27: 43831 | B27: =Prices!B603 -> #DIV/0! | E27: =Prices!C603 -> 299.6381 | I27: =Prices!D603 -> 33.150952 | L27: =Prices!E604 -> #DIV/0! | M27: =Prices!F604 -> #DIV/0! | R27: 43831 | S27: =[3]Prices!$B595*100 -> 394 | T27: =[3]Prices!$D595*100 -> 385.7381 | U27: =[3]Prices!$C595*100 -> 375.25 | W27: =S27-U27 -> 18.75
A28: 43862 | B28: =Prices!B604 -> #DIV/0! | E28: =Prices!C604 -> 290.88421 | I28: =Prices!D604 -> 30.248421 | L28: =Prices!E605 -> #DIV/0! | M28: =Prices!F605 -> #DIV/0! | R28: 43862 | S28: =[3]Prices!$B596*100 -> 385 | T28: =[3]Prices!$D596*100 -> 378.14474 | U28: =[3]Prices!$C596*100 -> 365.75 | W28: =S28-U28 -> 19.25
A29: 43891 | B29: =Prices!B605 -> #DIV/0! | E29: =Prices!C605 -> 311.91364 | I29: =Prices!D605 -> 27.017727 | L29: =Prices!E606 -> #DIV/0! | M29: =Prices!F606 -> #DIV/0! | R29: 43891 | S29: =[3]Prices!$B597*100 -> 385 | T29: =[3]Prices!$D597*100 -> 358.86364 | U29: =[3]Prices!$C597*100 -> 335.25 | W29: =S29-U29 -> 49.75
A30: 43922 | B30: =Prices!B606 -> #DIV/0! | E30: =Prices!C606 -> 291.94762 | I30: =Prices!D606 -> 26.202857 | L30: =Prices!E607 -> #DIV/0! | M30: =Prices!F607 -> #DIV/0! | R30: 43922 | S30: =[3]Prices!$B598*100 -> 334.75 | T30: =[3]Prices!$D598*100 -> 323.9881 | U30: =[3]Prices!$C598*100 -> 312 | W30: =S30-U30 -> 22.75
A31: 43952 | B31: =Prices!B607 -> #DIV/0! | E31: =Prices!C607 -> 287.06 | I31: =Prices!D607 -> 26.709 | L31: =Prices!E608 -> #DIV/0! | M31: =Prices!F608 -> #DIV/0! | R31: 43952 | S31: =[3]Prices!$B599*100 -> 327.5 | T31: =[3]Prices!$D599*100 -> 319.4125 | U31: =[3]Prices!$C599*100 -> 314.25 | W31: =S31-U31 -> 13.25
A32: 43983 | B32: =Prices!B608 -> #DIV/0! | E32: =Prices!C608 -> 286.76364 | I32: =Prices!D608 -> 27.891364 | L32: =Prices!E609 -> #DIV/0! | M32: =Prices!F609 -> #DIV/0! | R32: 43983 | S32: =[3]Prices!$B600*100 -> 341.5 | T32: =[3]Prices!$D600*100 -> 328.125 | U32: =[3]Prices!$C600*100 -> 317.25 | W32: =S32-U32 -> 24.25
A33: 44013 | B33: =Prices!B609 -> #DIV/0! | E33: =Prices!C609 -> 290.32273 | I33: =Prices!D609 -> 29.206818 | L33: =Prices!E610 -> #DIV/0! | M33: =Prices!F610 -> #DIV/0! | R33: 44013 | S33: =[3]Prices!$B601*100 -> 360.5 | T33: =[3]Prices!$D601*100 -> 339.51136 | U33: =[3]Prices!$C601*100 -> 326.25 | W33: =S33-U33 -> 34.25
A34: 44044 | B34: =Prices!B610 -> #DIV/0! | E34: =Prices!C610 -> 290.90952 | I34: =Prices!D610 -> 31.592381 | L34: =Prices!E611 -> #DIV/0! | M34: =Prices!F611 -> #DIV/0! | R34: 44044 | S34: =[3]Prices!$B602*100 -> 359.25 | T34: =[3]Prices!$D602*100 -> 325.15476 | U34: =[3]Prices!$C602*100 -> 320.25 | W34: =S34-U34 -> 39
A35: 44075 | B35: =Prices!B611 -> #DIV/0! | E35: =Prices!C611 -> 323.22381 | I35: =Prices!D611 -> 33.510476 | L35: =Prices!E612 -> #DIV/0! | M35: =Prices!F612 -> #DIV/0! | R35: 44075 | S35: =[3]Prices!$B603*100 -> 379 | T35: =[3]Prices!$D603*100 -> 366.27381 | U35: =[3]Prices!$C603*100 -> 353.75 | W35: =S35-U35 -> 25.25
A36: 44105 | B36: =Prices!B612 -> #DIV/0! | E36: =Prices!C612 -> 368.10909 | I36: =Prices!D612 -> 33.276818 | L36: =Prices!E613 -> #DIV/0! | M36: =Prices!F613 -> #DIV/0! | R36: 44105 | S36: =[3]Prices!$B604*100 -> 419.25 | T36: =[3]Prices!$D604*100 -> 398.89773 | U36: =[3]Prices!$C604*100 -> 379.5
A37: 44136 | B37: =Prices!B613 -> #DIV/0! | E37: =Prices!C613 -> 390.305 | I37: =Prices!D613 -> 36.8625 | L37: =Prices!E614 -> #DIV/0! | M37: =Prices!F614 -> #DIV/0! | R37: 44136 | S37: =[3]Prices!$B605*100 -> 433.75 | T37: =[3]Prices!$D605*100 -> 417.85 | U37: =[3]Prices!$C605*100 -> 397.5
A38: 44166 | B38: =Prices!B614 -> #DIV/0! | E38: =Prices!C614 -> 399.46818 | I38: =Prices!D614 -> 39.571364 | L38: =Prices!E615 -> #DIV/0! | M38: =Prices!F615 -> #DIV/0! | R38: 44166 | S38: =[3]Prices!$B606*100 -> 484 | T38: =[3]Prices!$D606*100 -> 439.02632 | U38: =[3]Prices!$C606*100 -> 419.75
A39: 44197 | B39: =Prices!B615 -> #DIV/0! | D39: =E39+(Forecasts!J24/2) -> 440.86842 | E39: =Prices!C615 -> 440.86842 | I39: =Prices!D615 -> 43.154211 | L39: =Prices!E615 -> #DIV/0! | M39: =Prices!F615 -> #DIV/0! | R39: 44197 | S39: =[3]Prices!$B607*100 -> 547 | T39: =[3]Prices!$D607*100 -> 515.39474 | U39: =[3]Prices!$C607*100 -> 483.75
A40: 44228 | B40: =Prices!B616 -> #DIV/0! | D40: =E40+(Forecasts!J26/2) -> 428.77895 | E40: =Prices!C616 -> 428.77895 | F40: =E40-(Forecasts!J26/2) -> 428.77895 | H40: =I40+(Forecasts!J36/2) -> 46.946316 | I40: =Prices!D616 -> 46.946316 | J40: =I40-(Forecasts!J36/2) -> 46.946316 | L40: =Prices!E616 -> #DIV/0! | M40: =Prices!F616 -> #DIV/0! | R40: 44228 | S40: =[3]Prices!$B608*100 -> 563.75 | T40: =[3]Prices!$D608*100 -> 549.97368 | U40: =[3]Prices!$C608*100 -> 534.5
A41: 44256 | B41: =Prices!B617 -> #DIV/0! | D41: =E41+(Forecasts!J27/2) -> 408.16522 | E41: =Prices!C617 -> 408.16522 | F41: =E41-(Forecasts!J27/2) -> 408.16522 | H41: =I41+(Forecasts!J41/2) -> 53.37 | I41: =Prices!D617 -> 53.37 | J41: =I41-(Forecasts!J41/2) -> 53.37 | L41: =Prices!E617 -> #DIV/0! | M41: =Prices!F617 -> #DIV/0! | R41: 44256 | S41: =[3]Prices!$B609*100 -> 564.25 | T41: =[3]Prices!$D609*100 -> 547.55 | U41: =[3]Prices!$C609*100 -> 532.5
A42: 44287 | B42: =Prices!B618 -> #DIV/0! | D42: =E42+(Forecasts!J28/2) -> 411.33333 | E42: =Prices!C618 -> 411.33333 | F42: =E42-(Forecasts!J28/2) -> 411.33333 | H42: =I42+(Forecasts!J42/2) -> 58.235714 | I42: =Prices!D618 -> 58.235714 | J42: =I42-(Forecasts!J42/2) -> 58.235714 | L42: =Prices!E618 -> #DIV/0! | M42: =Prices!F618 -> #DIV/0! | R42: 44287 | S42: =[3]Prices!$B610*100 -> 740 | T42: =[3]Prices!$D610*100 -> 616.07143 | U42: =[3]Prices!$C610*100 -> 553.25
A43: 44317 | B43: =Prices!B619 -> #DIV/0! | E43: =Prices!C619 -> 414.655 | I43: =Prices!D619 -> 65.6395 | L43: =Prices!E619 -> #DIV/0! | M43: =Prices!F619 -> #DIV/0! | R43: 44317
A44: 44348 | B44: =Prices!B620 -> #DIV/0! | E44: =Prices!C620 -> 374 | I44: =Prices!D620 -> 65.243182 | L44: =Prices!E620 -> #DIV/0! | M44: =Prices!F620 -> #DIV/0! | R44: 44348
A45: 44378 | B45: =Prices!B621 -> #DIV/0! | E45: =Prices!C621 -> 361.36667 | I45: =Prices!D621 -> 64.93619 | L45: =Prices!E621 -> #DIV/0! | M45: =Prices!F621 -> #DIV/0! | R45: 44378
A46: 44409 | B46: =Prices!B622 -> #DIV/0! | E46: =Prices!C622 -> 354.02727 | I46: =Prices!D622 -> 61.464091 | L46: =Prices!E622 -> #DIV/0! | M46: =Prices!F622 -> #DIV/0! | R46: 44409
A47: 44440 | B47: =Prices!B623 -> #DIV/0! | E47: =Prices!C623 -> 337.04762 | I47: =Prices!D623 -> 57.204762 | L47: =Prices!E623 -> #DIV/0! | M47: =Prices!F623 -> #DIV/0! | R47: 44440
A48: 44470 | B48: =Prices!B624 -> #DIV/0! | E48: =Prices!C624 -> 322.55714 | I48: =Prices!D624 -> 61.24619 | L48: =Prices!E624 -> #DIV/0! | M48: =Prices!F624 -> #DIV/0! | R48: 44470
A49: 44501 | B49: =Prices!B625 -> #DIV/0! | E49: =Prices!C625 -> 352.2619 | I49: =Prices!D625 -> 59.234762 | L49: =Prices!E625 -> #DIV/0! | M49: =Prices!F625 -> #DIV/0! | R49: 44501
A50: 44531 | B50: =Prices!B626 -> #DIV/0! | E50: =Prices!C626 -> 380.27273 | I50: =Prices!D626 -> 55.209545 | L50: =Prices!E626 -> #DIV/0! | M50: =Prices!F626 -> #DIV/0! | R50: 44531

Sheet Forecasts
A1: Soybeans | L1: =" "&TEXT([1]!'@S@c[DTN:CBOT]?SETTLE DATE',"mmm d")&" Closes" -> #REF!
B2: Forecast | C2: Low | D2: High | E2: Midpoint | F2: Current | G2: Spread | H2: Full Carry (₵/bu.) | I2: Spread % of Full Carry | J2: Range | K2: Cell Ref | X2: Implied Futures
A3: 45778 | B3: =AVERAGE(Prices!B665:'Prices'!B666) -> 9.925 | C3: =MIN('[7]Futures Averages'!$K$697:$L$697) -> 9.2445566 | D3: =MAX('[7]Futures Averages'!$K$640:$L$640) -> 10.47504 | E3: =AVERAGE(C3:D3) -> 9.8597985 | F3: =[1]!'@sk5[DTN:cbot]?Last'/100 -> #REF! | J3: =D3-C3 -> 1.2304838 | K3: 665:666 | U3: Storage Cost Per Day | X3: =F3-H3 -> #VALUE!
A4: 45839 | B4: =AVERAGE(Prices!B668:'Prices'!B667) -> 10.125 | C4: =MIN('[7]Futures Averages'!$K$870:$L$870) -> 9.3222058 | D4: =MAX('[7]Futures Averages'!$K$812:$L$812) -> 10.992938 | E4: =AVERAGE(C4:D4) -> 10.157572 | F4: =[1]!'@sn5[DTN:cbot]?Last'/100 -> #REF! | G4: =F4-F3 -> #VALUE! | H4: =(B4*V$10/1200)+(V$4*(A4-A3)) -> 0.15231526 | I4: =G4/H4 -> #VALUE! | J4: =D4-C4 -> 1.670732 | K4: 667:668 | U4: Soybeans | V4: 0.00165 | X4: =F4-H4 -> #VALUE!
A5: 45870 | B5: =AVERAGE(Prices!B669:'Prices'!B669) -> 10.05 | C5: ='[7]Futures Averages'!$L$1047 -> 8.6724756 | D5: ='[7]Futures Averages'!$L$988 -> 10.448846 | E5: =AVERAGE(C5:D5) -> 9.5606608 | F5: =[1]!'@sq5[DTN:cbot]?Last'/100 -> #REF! | G5: =F5-F4 -> #VALUE! | H5: =(B5*V$10/1200)+(V$4*(A5-A4)) -> 0.10243255 | I5: =G5/H5 -> #VALUE! | J5: =D5-C5 -> 1.7763704 | K5: 669 | U5: Soybean Meal | V5: 0.07 | X5: =F5-H5 -> #VALUE! | Z5: 45597
A6: 45901 | B6: =AVERAGE(Prices!B670:'Prices'!B670) -> 9.55 | C6: ='[7]Futures Averages'!$L$1222 -> 8.421037 | D6: ='[7]Futures Averages'!$L$1164 -> 10.264774 | E6: =AVERAGE(C6:D6) -> 9.3429054 | F6: =[1]!'@su5[DTN:cbot]?Last'/100 -> #REF! | G6: =F6-F5 -> #VALUE! | H6: =(B6*V$10/1200)+(V$4*(A6-A5)) -> 0.099881183 | I6: =G6/H6 -> #VALUE! | J6: =D6-C6 -> 1.8437368 | K6: 670 | U6: Soybean Oil | V6: 0.003 | X6: =F6-H6 -> #VALUE! | Z6: 45962
A7: 45962 | B7: =AVERAGE(Prices!B671:'Prices'!B672) -> 8.825 | C7: =MIN('[7]Futures Averages'!$K$177:$L$177) -> 7.5095138 | D7: =MAX('[7]Futures Averages'!$K$118:$L$118) -> 10.098868 | E7: =AVERAGE(C7:D7) -> 8.8041908 | F7: =[1]!'@sx5[DTN:cbot]?Last'/100 -> #REF! | G7: =F7-F6 -> #VALUE! | H7: =(B7*V$10/1200)+(V$4*(A7-A6)) -> 0.1456817 | I7: =G7/H7 -> #VALUE! | J7: =D7-C7 -> 2.589354 | K7: 671:672 | X7: =F7-H7 -> #VALUE! | Z7: =V4*(Z6-Z5) -> 0.60225
A8: 46023 | B8: =AVERAGE(Prices!B674:'Prices'!B673) -> 9.075 | C8: =MIN('[7]Futures Averages'!$K$352:$L$352) -> 8.3936828 | D8: =MAX('[7]Futures Averages'!$K$294:$L$294) -> 9.9402485 | E8: =AVERAGE(C8:D8) -> 9.1669656 | F8: =[1]!'@sf6[DTN:cbot]?Last'/100 -> #REF! | G8: =F8-F7 -> #VALUE! | H8: =(B8*V$10/1200)+(V$4*(A8-A7)) -> 0.14695738 | I8: =G8/H8 -> #VALUE! | J8: =D8-C8 -> 1.5465657 | K8: 673-674 | U8: Interest Rate | X8: =F8-H8 -> #VALUE!
A9: 46082 | B9: =AVERAGE(Prices!B675:'Prices'!B676) -> 9.2 | C9: =MIN('[7]Futures Averages'!$K$526:$L$526) -> 8.5171326 | D9: =MAX('[7]Futures Averages'!$K$468:$L$468) -> 9.9879606 | E9: =AVERAGE(C9:D9) -> 9.2525466 | F9: =[1]!'@sh6[DTN:cbot]?Last'/100 -> #REF! | G9: =F9-F8 -> #VALUE! | H9: =(B9*V$10/1200)+(V$4*(A9-A8)) -> 0.14429522 | I9: =G9/H9 -> #VALUE! | J9: =D9-C9 -> 1.470828 | K9: 675-676 | U9: LIBOR - 12 Months | V9: 4.12329 | X9: =F9-H9 -> #VALUE!
B10: =B3/#REF!-1 -> #REF! | F10: =[1]!'@sf6[DTN:cbot]?Last'/100 -> #REF! | U10: LIBOR + 200 bps | V10: =V9+2 -> 6.12329
A14: Soybean Meal
B15: Forecast | C15: Low | D15: High | E15: Midpoint | F15: Current | G15: Spread | H15: Full Carry | I15: Spread % of Full Carry | J15: Range | K15: Cell Ref
A16: 45778 | B16: =AVERAGE(Prices!C665:'Prices'!C666) -> #VALUE! | C16: =B16-(J16/2) -> #VALUE! | D16: =B16+(J16/2) -> #VALUE! | E16: =AVERAGE(C16:D16) -> #VALUE! | F16: =[1]!'@smk5[DTN:cbot]?Last' -> #REF! | J16: =60*(J31/AVERAGE($J$31:$J$36)) -> #DIV/0! | K16: 665-666 | X16: =F16-H16 -> #VALUE!
A17: 45839 | B17: =AVERAGE(Prices!C668:'Prices'!C667) -> #VALUE! | C17: =B17-(J17/2) -> #VALUE! | D17: =B17+(J17/2) -> #VALUE! | E17: =AVERAGE(C17:D17) -> #VALUE! | F17: =[1]!'@smn5[DTN:cbot]?Last' -> #REF! | G17: =F17-F16 -> #VALUE! | H17: =(B17*V$10/1200)+(V$5*(A17-A16)) -> #VALUE! | I17: =G17/H17 -> #VALUE! | J17: =60*(J32/AVERAGE($J$31:$J$36)) -> #DIV/0! | K17: 667-668 | X17: =F17-H17 -> #VALUE!
A18: 45870 | B18: =AVERAGE(Prices!C669:'Prices'!C669) -> #VALUE! | C18: =B18-(J18/2) -> #VALUE! | D18: =B18+(J18/2) -> #VALUE! | E18: =AVERAGE(C18:D18) -> #VALUE! | F18: =[1]!'@smq5[DTN:cbot]?Last' -> #REF! | G18: =F18-F17 -> #VALUE! | H18: =(B18*V$10/1200)+(V$5*(A18-A17)) -> #VALUE! | I18: =G18/H18 -> #VALUE! | J18: =60*(J33/AVERAGE($J$31:$J$36)) -> #DIV/0! | K18: 669 | X18: =F18-H18 -> #VALUE!
A19: 45901 | B19: =AVERAGE(Prices!C670:'Prices'!C670) -> #VALUE! | C19: =B19-(J19/2) -> #VALUE! | D19: =B19+(J19/2) -> #VALUE! | E19: =AVERAGE(C19:D19) -> #VALUE! | F19: =[1]!'@smq5[DTN:cbot]?Last' -> #REF! | G19: =F19-F18 -> #VALUE! | H19: =(B19*V$10/1200)+(V$5*(A19-A18)) -> #VALUE! | I19: =G19/H19 -> #VALUE! | J19: =60*(J34/AVERAGE($J$31:$J$36)) -> #DIV/0! | K19: 670 | X19: =F19-H19 -> #VALUE!
A20: 45931 | B20: =AVERAGE(Prices!C671:'Prices'!C671) -> #VALUE! | C20: =B20-(J20/2) -> #VALUE! | D20: =B20+(J20/2) -> #VALUE! | E20: =AVERAGE(C20:D20) -> #VALUE! | F20: =[1]!'@smv5[DTN:cbot]?Last' -> #REF! | G20: =F20-F19 -> #VALUE! | H20: =(B20*V$10/1200)+(V$5*(A20-A19)) -> #VALUE! | I20: =G20/H20 -> #VALUE! | J20: =60*(J35/AVERAGE($J$31:$J$36)) -> #DIV/0! | K20: 671 | X20: =F20-H20 -> #VALUE!
A21: 45992 | B21: =AVERAGE(Prices!C673:'Prices'!C672) -> #VALUE! | C21: =B21-(J21/2) -> #VALUE! | D21: =B21+(J21/2) -> #VALUE! | E21: =AVERAGE(C21:D21) -> #VALUE! | F21: =[1]!'@smq5[DTN:cbot]?Last' -> #REF! | G21: =F21-F20 -> #VALUE! | H21: =(B21*V$10/1200)+(V$5*(A21-A20)) -> #VALUE! | I21: =G21/H21 -> #VALUE! | J21: =60*(J36/AVERAGE($J$31:$J$36)) -> #DIV/0! | K21: 672-673 | X21: =F21-H21 -> #VALUE!
A22: 46023 | B22: =AVERAGE(Prices!C674) -> #VALUE! | C22: =B22-(J22/2) -> #VALUE! | D22: =B22+(J22/2) -> #VALUE! | E22: =AVERAGE(C22:D22) -> #VALUE! | F22: =[1]!'@smv5[DTN:cbot]?Last' -> #REF! | G22: =F22-F21 -> #VALUE! | H22: =(B22*V$10/1200)+(V$5*(A22-A21)) -> #VALUE! | I22: =G22/H22 -> #VALUE! | J22: =60*(J37/AVERAGE($J$31:$J$36)) -> #DIV/0! | K22: 674 | X22: =F22-H22 -> #VALUE!
A23: 46082 | B23: =AVERAGE(Prices!C675:'Prices'!C676) -> #VALUE! | C23: =B23-(J23/2) -> #VALUE! | D23: =B23+(J23/2) -> #VALUE! | E23: =AVERAGE(C23:D23) -> #VALUE! | F23: =[1]!'@smq5[DTN:cbot]?Last' -> #REF! | G23: =F23-F22 -> #VALUE! | H23: =(B23*V$10/1200)+(V$5*(A23-A22)) -> #VALUE! | I23: =G23/H23 -> #VALUE! | J23: =60*(J38/AVERAGE($J$31:$J$36)) -> #DIV/0! | K23: 675-676 | X23: =F23-H23 -> #VALUE!
A29: Soybean Oil
B30: Forecast | C30: Low | D30: High | E30: Midpoint | F30: Current | G30: Spread | H30: Full Carry | I30: Spread % of Full Carry | J30: Range | Z30: Days of Coverage
A31: 45778 | B31: =MROUND(AVERAGE('[5]Monthly Prices'!$AR$305:$AR$306),0.25) -> #DIV/0! | C31: =MROUND(MIN('[5]Monthly Prices'!$AT$305:$AT$306),0.25) -> 0 | D31: =MROUND(MAX('[5]Monthly Prices'!$AS$305:$AS$306),0.25) -> 0 | E31: =AVERAGE(C31:D31) -> 0 | F31: =[1]!'@BOk5[DTN:cbot]?Last' -> #REF! | J31: =D31-C31 -> 0 | X31: =A31 -> 45778 | Y31: =F31-H31 -> #VALUE! | Z31: =AVERAGE('[8]Soy Complex'!$BN$504:$BN$505) -> 23.110272 | AA31: =B31 -> #DIV/0! | AB31: =F3 -> #VALUE!
A32: 45839 | B32: =MROUND(AVERAGE('[5]Monthly Prices'!$AR$307:$AR$308),0.25) -> #DIV/0! | C32: =MROUND(MIN('[5]Monthly Prices'!$AT$307:$AT$308),0.25) -> 0 | D32: =MROUND(MAX('[5]Monthly Prices'!$AS$307:$AS$308),0.25) -> 0 | E32: =AVERAGE(C32:D32) -> 0 | F32: =[1]!'@BOn5[DTN:cbot]?Last' -> #REF! | G32: =F32-F31 -> #VALUE! | H32: =(B32*V$10/1200)+(V$6*(A32-A31)) -> #DIV/0! | I32: =G32/H32 -> #VALUE! | J32: =D32-C32 -> 0 | X32: =A32 -> 45839 | Y32: =F32-H32 -> #VALUE! | Z32: =AVERAGE('[8]Soy Complex'!$BN$506:$BN$507) -> 28.628737 | AA32: =B32 -> #DIV/0! | AB32: =F4 -> #VALUE!
A33: 45870 | B33: =MROUND(AVERAGE('[5]Monthly Prices'!$AR$309),0.25) -> #DIV/0! | C33: =MROUND(MIN('[5]Monthly Prices'!$AT$309),0.25) -> 0 | D33: =MROUND(MAX('[5]Monthly Prices'!$AS$309),0.25) -> 0 | E33: =AVERAGE(C33:D33) -> 0 | F33: =[1]!'@BOq5[DTN:cbot]?Last' -> #REF! | G33: =F33-F32 -> #VALUE! | H33: =(B33*V$10/1200)+(V$6*(A33-A32)) -> #DIV/0! | I33: =G33/H33 -> #VALUE! | J33: =D33-C33 -> 0 | X33: =A33 -> 45870 | Y33: =F33-H33 -> #VALUE! | Z33: ='[8]Soy Complex'!$BN$508 -> 28.005825 | AA33: =B33 -> #DIV/0! | AB33: =F5 -> #VALUE!
A34: 45901 | B34: =MROUND(AVERAGE('[5]Monthly Prices'!$AR$310),0.25) -> #DIV/0! | C34: =MROUND(MIN('[5]Monthly Prices'!$AT$310),0.25) -> 0 | D34: =MROUND(MAX('[5]Monthly Prices'!$AS$310),0.25) -> 0 | E34: =AVERAGE(C34:D34) -> 0 | F34: =[1]!'@BOu5[DTN:cbot]?Last' -> #REF! | G34: =F34-F33 -> #VALUE! | H34: =(B34*V$10/1200)+(V$6*(A34-A33)) -> #DIV/0! | I34: =G34/H34 -> #VALUE! | J34: =D34-C34 -> 0 | X34: =A34 -> 45901 | Y34: =F34-H34 -> #VALUE! | Z34: ='[8]Soy Complex'!$BN$509 -> 34.175981 | AA34: =B34 -> #DIV/0! | AB34: =F6 -> #VALUE!
A35: 45931 | B35: =MROUND(AVERAGE('[5]Monthly Prices'!$AR$311),0.25) -> #DIV/0! | C35: =MROUND(MIN('[5]Monthly Prices'!$AT$311),0.25) -> 0 | D35: =MROUND(MAX('[5]Monthly Prices'!$AS$311),0.25) -> 0 | E35: =AVERAGE(C35:D35) -> 0 | F35: =[1]!'@BOv5[DTN:cbot]?Last' -> #REF! | G35: =F35-F34 -> #VALUE! | H35: =(B35*V$10/1200)+(V$6*(A35-A34)) -> #DIV/0! | I35: =G35/H35 -> #VALUE! | J35: =D35-C35 -> 0 | X35: =A35 -> 45931 | Y35: =F35-H35 -> #VALUE! | Z35: ='[8]Soy Complex'!$BN$510 -> 0 | AA35: =B35 -> #DIV/0! | AB35: =F7 -> #VALUE!
A36: 45992 | B36: =MROUND(AVERAGE('[5]Monthly Prices'!$AR$312:$AR$313),0.25) -> #DIV/0! | C36: =MROUND(MIN('[5]Monthly Prices'!$AT$312:$AT$313),0.25) -> 0 | D36: =MROUND(MAX('[5]Monthly Prices'!$AS$312:$AS$313),0.25) -> 0 | E36: =AVERAGE(C36:D36) -> 0 | F36: =[1]!'@BOz5[DTN:cbot]?Last' -> #REF! | G36: =F36-F35 -> #VALUE! | H36: =(B36*V$10/1200)+(V$6*(A36-A35)) -> #DIV/0! | I36: =G36/H36 -> #VALUE! | J36: =D36-C36 -> 0 | X36: =A36 -> 45992 | Y36: =F36-H36 -> #VALUE! | Z36: =AVERAGE('[8]Soy Complex'!$BO$499:$BO$500) -> 25.032821 | AA36: =B36 -> #DIV/0! | AB36: =F8 -> #VALUE!
A37: 46023 | B37: =MROUND(AVERAGE('[5]Monthly Prices'!$AR$314),0.25) -> #DIV/0! | C37: =MROUND(MIN('[5]Monthly Prices'!$AT$314),0.25) -> 0 | D37: =MROUND(MAX('[5]Monthly Prices'!$AS$314:$AS$314),0.25) -> 0 | E37: =AVERAGE(C37:D37) -> 0 | F37: =[1]!'@BOf6[DTN:cbot]?Last' -> #REF! | G37: =F37-F36 -> #VALUE! | H37: =(B37*V$10/1200)+(V$6*(A37-A36)) -> #DIV/0! | I37: =G37/H37 -> #VALUE! | J37: =D37-C37 -> 0 | X37: =A37 -> 46023 | Y37: =F37-H37 -> #VALUE! | Z37: ='[8]Soy Complex'!$BO$501 -> 33.226842 | AA37: =B37 -> #DIV/0! | AB37: =F9 -> #VALUE!
A38: 46082 | B38: =MROUND(AVERAGE('[5]Monthly Prices'!$AR$315:$AR$316),0.25) -> #DIV/0! | C38: =MROUND(MIN('[5]Monthly Prices'!$AT$315:$AT$316),0.25) -> 0 | D38: =MROUND(MAX('[5]Monthly Prices'!$AS$315:$AS$316),0.25) -> 0 | E38: =AVERAGE(C38:D38) -> 0 | F38: =[1]!'@BOh6[DTN:cbot]?Last' -> #REF! | G38: =F38-F37 -> #VALUE! | H38: =(B38*V$10/1200)+(V$6*(A38-A37)) -> #DIV/0! | I38: =G38/H38 -> #VALUE! | J38: =D38-C38 -> 0 | X38: 46082 | Y38: =F38-H38 -> #VALUE! | Z38: =AVERAGE('[8]Soy Complex'!$BO$502:$BO$503) -> 36.548428 | AA38: =B38 -> #DIV/0! | AB38: =F10 -> #VALUE!
A39: 46143 | B39: =MROUND(AVERAGE('[5]Monthly Prices'!$AR$317:$AR$318),0.25) -> #DIV/0! | C39: =MROUND(MIN('[5]Monthly Prices'!$AT$317:$AT$318),0.25) -> 0 | D39: =MROUND(MAX('[5]Monthly Prices'!$AS$317:$AS$318),0.25) -> 0 | E39: =AVERAGE(C39:D39) -> 0 | F39: =[1]!'@BOk6[DTN:cbot]?Last' -> #REF! | G39: =F39-F38 -> #VALUE! | H39: =(B39*V$10/1200)+(V$6*(A39-A38)) -> #DIV/0! | I39: =G39/H39 -> #VALUE! | J39: =D39-C39 -> 0
A42: Palm Oil
B43: Forecast | C43: Low | D43: High | E43: Midpoint | F43: Current | G43: Spread | H43: Full Carry | I43: Spread % of Full Carry | J43: Range | L43: PO Forecast in Cents per Pound | M43: SBO Forecast | N43: Forecast Spread | O43: PO Current in Cents per Pound | P43: SBO Current | Q43: Current Spread | R43: Forecast Spread - Current Spread
A44: 45748 | B44: 4750 | C44: =B44-(J44/2) -> #DIV/0! | D44: =B44+(J44/2) -> #DIV/0! | E44: =AVERAGE(C44:D44) -> #DIV/0! | F44: =[1]!'KPOj5[DTN:MDE]?Settle' -> #REF! | J44: =MROUND(450*(J31/AVERAGE($J$31:$J$38)),50)+100 -> #DIV/0! | L44: =B44/$A$63/2204.622*100 -> #N/A | M44: ='[5]Monthly Prices'!$AR306 -> 0 | N44: =M44-L44 -> #N/A | O44: =F44/$A$63/2204.622*100 -> #VALUE! | P44: =F31 -> #VALUE! | Q44: =P44-O44 -> #VALUE! | R44: =N44-Q44 -> #N/A
A45: 45778 | B45: 4650 | C45: =B45-(J45/2) -> #DIV/0! | D45: =B45+(J45/2) -> #DIV/0! | E45: =AVERAGE(C45:D45) -> #DIV/0! | F45: =[1]!'KPOk5[DTN:MDE]?Settle' -> #REF! | G45: =F45-F44 -> #VALUE! | J45: =MROUND(450*(J32/AVERAGE($J$31:$J$38)),50)+100 -> #DIV/0! | L45: =B45/$A$63/2204.622*100 -> #N/A | M45: ='[5]Monthly Prices'!$AR307 -> 0 | N45: =M45-L45 -> #N/A | O45: =F45/$A$63/2204.622*100 -> #VALUE! | P45: =F31 -> #VALUE! | Q45: =P45-O45 -> #VALUE! | R45: =N45-Q45 -> #N/A
A46: 45809 | B46: 5000 | C46: =B46-(J46/2) -> #DIV/0! | D46: =B46+(J46/2) -> #DIV/0! | E46: =AVERAGE(C46:D46) -> #DIV/0! | F46: =[1]!'KPOm5[DTN:MDE]?Settle' -> #REF! | G46: =F46-F45 -> #VALUE! | J46: =MROUND(450*(J32/AVERAGE($J$31:$J$38)),50)+100 -> #DIV/0! | L46: =B46/$A$63/2204.622*100 -> #N/A | M46: ='[5]Monthly Prices'!$AR308 -> 0 | N46: =M46-L46 -> #N/A | O46: =F46/$A$63/2204.622*100 -> #VALUE! | P46: =F32 -> #VALUE! | Q46: =P46-O46 -> #VALUE! | R46: =N46-Q46 -> #N/A
A47: 45839 | B47: 5000 | C47: =B47-(J47/2) -> #DIV/0! | D47: =B47+(J47/2) -> #DIV/0! | E47: =AVERAGE(C47:D47) -> #DIV/0! | F47: =[1]!'KPOn5[DTN:MDE]?Settle' -> #REF! | G47: =F47-F46 -> #VALUE! | J47: =MROUND(450*(J33/AVERAGE($J$31:$J$38)),50)+100 -> #DIV/0! | L47: =B47/$A$63/2204.622*100 -> #N/A | M47: ='[5]Monthly Prices'!$AR309 -> 0 | N47: =M47-L47 -> #N/A | O47: =F47/$A$63/2204.622*100 -> #VALUE! | P47: =F32 -> #VALUE! | Q47: =P47-O47 -> #VALUE! | R47: =N47-Q47 -> #N/A
A48: 45870 | B48: 5100 | C48: =B48-(J48/2) -> #DIV/0! | D48: =B48+(J48/2) -> #DIV/0! | E48: =AVERAGE(C48:D48) -> #DIV/0! | F48: =[1]!'KPOq5[DTN:MDE]?Settle' -> #REF! | G48: =F48-F47 -> #VALUE! | J48: =MROUND(450*(J34/AVERAGE($J$31:$J$38)),50)+100 -> #DIV/0! | L48: =B48/$A$63/2204.622*100 -> #N/A | M48: ='[5]Monthly Prices'!$AR310 -> 0 | N48: =M48-L48 -> #N/A | O48: =F48/$A$63/2204.622*100 -> #VALUE! | P48: =F33 -> #VALUE! | Q48: =P48-O48 -> #VALUE! | R48: =N48-Q48 -> #N/A
A49: 45901 | B49: 5200 | C49: =B49-(J49/2) -> #DIV/0! | D49: =B49+(J49/2) -> #DIV/0! | E49: =AVERAGE(C49:D49) -> #DIV/0! | F49: =[1]!'KPOu5[DTN:MDE]?Settle' -> #REF! | G49: =F49-F48 -> #VALUE! | J49: =MROUND(450*(J35/AVERAGE($J$31:$J$38)),50)+100 -> #DIV/0! | L49: =B49/$A$63/2204.622*100 -> #N/A | M49: ='[5]Monthly Prices'!$AR311 -> 0 | N49: =M49-L49 -> #N/A | O49: =F49/$A$63/2204.622*100 -> #VALUE! | P49: =F34 -> #VALUE! | Q49: =P49-O49 -> #VALUE! | R49: =N49-Q49 -> #N/A
A50: 45931 | B50: 5100 | C50: =B50-(J50/2) -> #DIV/0! | D50: =B50+(J50/2) -> #DIV/0! | E50: =AVERAGE(C50:D50) -> #DIV/0! | F50: =[1]!'KPOv5[DTN:MDE]?Settle' -> #REF! | G50: =F50-F49 -> #VALUE! | J50: =MROUND(450*(J36/AVERAGE($J$31:$J$38)),50)+100 -> #DIV/0! | L50: =B50/$A$63/2204.622*100 -> #N/A | M50: ='[5]Monthly Prices'!$AR312 -> 0 | N50: =M50-L50 -> #N/A | O50: =F50/$A$63/2204.622*100 -> #VALUE! | P50: =F35 -> #VALUE! | Q50: =P50-O50 -> #VALUE! | R50: =N50-Q50 -> #N/A
A51: 45962 | B51: 4900 | C51: =B51-(J51/2) -> #DIV/0! | D51: =B51+(J51/2) -> #DIV/0! | E51: =AVERAGE(C51:D51) -> #DIV/0! | F51: =[1]!'KPOx5[DTN:MDE]?Settle' -> #REF! | G51: =F51-F50 -> #VALUE! | J51: =MROUND(450*(J36/AVERAGE($J$31:$J$38)),50)+100 -> #DIV/0! | L51: =B51/$A$63/2204.622*100 -> #N/A | M51: ='[5]Monthly Prices'!$AR313 -> 0 | N51: =M51-L51 -> #N/A | O51: =F51/$A$63/2204.622*100 -> #VALUE! | P51: =F36 -> #VALUE! | Q51: =P51-O51 -> #VALUE! | R51: =N51-Q51 -> #N/A
A52: 45992 | B52: 4800 | C52: =B52-(J52/2) -> #DIV/0! | D52: =B52+(J52/2) -> #DIV/0! | E52: =AVERAGE(C52:D52) -> #DIV/0! | F52: =[1]!'KPOz5[DTN:MDE]?Settle' -> #REF! | G52: =F52-F51 -> #VALUE! | J52: =MROUND(450*(J37/AVERAGE($J$31:$J$38)),50)+100 -> #DIV/0! | L52: =B52/$A$63/2204.622*100 -> #N/A | M52: ='[5]Monthly Prices'!$AR314 -> 0 | N52: =M52-L52 -> #N/A | O52: =F52/$A$63/2204.622*100 -> #VALUE! | P52: =F36 -> #VALUE! | Q52: =P52-O52 -> #VALUE! | R52: =N52-Q52 -> #N/A
A53: 46023 | B53: 5200 | C53: =B53-(J53/2) -> #DIV/0! | D53: =B53+(J53/2) -> #DIV/0! | E53: =AVERAGE(C53:D53) -> #DIV/0! | F53: =[1]!'KPof6[DTN:MDE]?Settle' -> #REF! | G53: =F53-F52 -> #VALUE! | J53: =MROUND(450*(J38/AVERAGE($J$31:$J$38)),50)+100 -> #DIV/0! | L53: =B53/$A$63/2204.622*100 -> #N/A | M53: ='[5]Monthly Prices'!$AR315 -> 0 | N53: =M53-L53 -> #N/A | O53: =F53/$A$63/2204.622*100 -> #VALUE! | P53: =F37 -> #VALUE! | Q53: =P53-O53 -> #VALUE! | R53: =N53-Q53 -> #N/A
A54: 46054 | B54: 5100 | C54: =B54-(J54/2) -> #DIV/0! | D54: =B54+(J54/2) -> #DIV/0! | E54: =AVERAGE(C54:D54) -> #DIV/0! | F54: =[1]!'KPOg6[DTN:MDE]?Settle' -> #REF! | G54: =F54-F53 -> #VALUE! | J54: =MROUND(450*(J38/AVERAGE($J$31:$J$38)),50)+100 -> #DIV/0! | L54: =B54/$A$63/2204.622*100 -> #N/A | M54: ='[5]Monthly Prices'!$AR316 -> 0 | N54: =M54-L54 -> #N/A | O54: =F54/$A$63/2204.622*100 -> #VALUE! | P54: =F38 -> #VALUE! | Q54: =P54-O54 -> #VALUE! | R54: =N54-Q54 -> #N/A
A55: 46082 | B55: 4900 | C55: =B55-(J55/2) -> #DIV/0! | D55: =B55+(J55/2) -> #DIV/0! | E55: =AVERAGE(C55:D55) -> #DIV/0! | F55: =[1]!'KPOh6[DTN:MDE]?Settle' -> #REF! | G55: =F55-F54 -> #VALUE! | J55: =MROUND(450*(J39/AVERAGE($J$31:$J$39)),50)+100 -> #DIV/0! | L55: =B55/$A$63/2204.622*100 -> #N/A | M55: ='[5]Monthly Prices'!$AR317 -> 0 | N55: =M55-L55 -> #N/A | O55: =F55/$A$63/2204.622*100 -> #VALUE! | P55: =F38 -> #VALUE! | Q55: =P55-O55 -> #VALUE! | R55: =N55-Q55 -> #N/A
A56: 46113 | B56: 4900 | C56: =B56-(J56/2) -> #DIV/0! | D56: =B56+(J56/2) -> #DIV/0! | E56: =AVERAGE(C56:D56) -> #DIV/0! | F56: =AVERAGE(F55,F59) -> #VALUE! | G56: =F56-F55 -> #VALUE! | J56: =MROUND(450*(J39/AVERAGE($J$31:$J$39)),50)+100 -> #DIV/0! | L56: =B56/$A$63/2204.622*100 -> #N/A | M56: ='[5]Monthly Prices'!$AR318 -> 0 | N56: =M56-L56 -> #N/A | O56: =F56/$A$63/2204.622*100 -> #VALUE! | P56: =F39 -> #VALUE! | Q56: =P56-O56 -> #VALUE! | R56: =N56-Q56 -> #N/A
F59: =[1]!'KPOk6[DTN:MDE]?Settle' -> #REF!
A60: =RTD("prophetx.rtdserver", "", "QUOTE", "kpo@c1", "Last") -> #N/A
A61: =RTD("prophetx.rtdserver", "", "QUOTE", "kpo@c3", "Settle") -> #N/A | B61: Current 3rd Month Continuous Palm Oil in Ringgit per Tonne
A62: =RTD("prophetx.rtdserver", "", "QUOTE", "upo@c3", "Last") -> #N/A | B62: Current 3rd Month Continuous Palm Oil in Dollars per Tonne
A63: =A61/A62 -> #N/A | B63: Implied Ringgit per USD
A64: =_xll.TR("MYR=","CF_LAST") -> #NAME? | B64: Ringgit per USD
A65: =A61/A64 -> #N/A | B65: 3rd month continuous PO in $/tonne
A67: =RTD("prophetx.rtdserver", "", "QUOTE", "@bo@c3", "Last")*22.04622 -> #N/A | B67: 3rd Month SBO in $/tonne
A68: =A67-A62 -> #N/A | B68: Spread in $/tonne
A69: =A68/2204.622*100 -> #N/A | B69: Spread in cents per pound
A71: 20 | B71: Spread Assumption (cents per pound)
A73: PKO NOLA/NYC | D73: Palm Sterin - US Gulf
A74: =#REF! -> #REF! | B74: =MROUND((((#REF!/22.04622/$A$63)*1.0702)+3.3839)*1.475,0.25) -> #REF! | D74: =A74 -> #REF! | E74: =MROUND((B74*20.773+30.912)*0.755,5) -> #REF!
A75: =A44 -> 45748 | B75: =MROUND((((B44/22.04622/$A$63)*1.0702)+3.3839)*1.475,0.25) -> #N/A | D75: =A75 -> 45748 | E75: =MROUND((B75*20.773+30.912)*0.755,5) -> #N/A
A76: =A45 -> 45778 | B76: =MROUND((((B45/22.04622/$A$63)*1.0702)+3.3839)*1.475,0.25) -> #N/A | D76: =A76 -> 45778 | E76: =MROUND((B76*20.773+30.912)*0.755,5) -> #N/A
A77: =A46 -> 45809 | B77: =MROUND((((B46/22.04622/$A$63)*1.0702)+3.3839)*1.475,0.25) -> #N/A | D77: =A77 -> 45809 | E77: =MROUND((B77*20.773+30.912)*0.755,5) -> #N/A
A78: =A47 -> 45839 | B78: =MROUND((((B47/22.04622/$A$63)*1.0702)+3.3839)*1.475,0.25) -> #N/A | D78: =A78 -> 45839 | E78: =MROUND((B78*20.773+30.912)*0.755,5) -> #N/A
A79: =A48 -> 45870 | B79: =MROUND((((B48/22.04622/$A$63)*1.0702)+3.3839)*1.475,0.25) -> #N/A | D79: =A79 -> 45870 | E79: =MROUND((B79*20.773+30.912)*0.755,5) -> #N/A
A80: =A49 -> 45901 | B80: =MROUND((((B49/22.04622/$A$63)*1.0702)+3.3839)*1.475,0.25) -> #N/A | D80: =A80 -> 45901 | E80: =MROUND((B80*20.773+30.912)*0.755,5) -> #N/A
A81: =A50 -> 45931 | B81: =MROUND((((B50/22.04622/$A$63)*1.0702)+3.3839)*1.475,0.25) -> #N/A | D81: =A81 -> 45931 | E81: =MROUND((B81*20.773+30.912)*0.755,5) -> #N/A
A82: =A51 -> 45962 | B82: =MROUND((((B51/22.04622/$A$63)*1.0702)+3.3839)*1.475,0.25) -> #N/A | D82: =A82 -> 45962 | E82: =MROUND((B82*20.773+30.912)*0.755,5) -> #N/A
A83: =A52 -> 45992 | B83: =MROUND((((B52/22.04622/$A$63)*1.0702)+3.3839)*1.475,0.25) -> #N/A | D83: =A83 -> 45992 | E83: =MROUND((B83*20.773+30.912)*0.755,5) -> #N/A
A84: =A53 -> 46023 | B84: =MROUND((((B53/22.04622/$A$63)*1.0702)+3.3839)*1.475,0.25) -> #N/A | D84: =A84 -> 46023 | E84: =MROUND((B84*20.773+30.912)*0.755,5) -> #N/A
A85: =A54 -> 46054 | B85: =MROUND((((B54/22.04622/$A$63)*1.0702)+3.3839)*1.475,0.25) -> #N/A | D85: =A85 -> 46054 | E85: =MROUND((B85*20.773+30.912)*0.755,5) -> #N/A
M89: =K114/100*11.7/(C114+M114)
M90: Oilshare = SBO/100*11.7/(S+SBM)
M91: =(F100/2000*44.5)+(J100/100*11.7)-(B100/100)
M92: Crush Margin=(SBM/2000*44.5)+(SBO/100*11.7)-(S/100)
J93: =F114 -> #VALUE! | K93: =J114 -> #VALUE!
A96: Month | B96: 3
A97: Days | B97: 21
H98: SBM value per bu | L98: SBO value per bu | S98: Biodiesel Margin
A99: Nearby Soybean Futures | E99: Nearby Soybean Meal Futures | I99: Nearby Soybean Oil Futures | M99: Margin | N99: Oil Share | P99: Nearby Heating Oil Futures | S99: HO+$1.15 | X99: Nearby Palm Oil Futures
A100: {=([2]!'@Sk5[INTERVAL:DAILY,COMPRESSION:1,SORT:ASC,SPAN:25]?DATE,CLOSE')} -> #REF! | B100: #REF! | C100: {=IF(IF(ISNUMBER(A100),MONTH(A100),MONTH(DATEVALUE(A100)))=$B$96,B100/100,"-- ")} -> #VALUE! | E100: {=[2]!'@SMk5[INTERVAL:DAILY,COMPRESSION:1,SORT:ASC,SPAN:25]?DATE,CLOSE'} -> #REF! | F100: #REF! | G100: =IF(IF(ISNUMBER(E100),MONTH(E100),MONTH(DATEVALUE(E100)))=$B$96,F100,"-- ") -> #VALUE! | H100: =F100*44.5/2000 -> #VALUE! | I100: {=[2]!'@BOk5[INTERVAL:DAILY,COMPRESSION:1,SORT:ASC,SPAN:25]?DATE,CLOSE'} -> #REF! | J100: #REF! | K100: =IF(IF(ISNUMBER(I100),MONTH(I100),MONTH(DATEVALUE(I100)))=$B$96,J100,"-- ") -> #VALUE! | L100: =(J100/100)*11.7 -> #VALUE! | M100: =(F100/2000*44.5)+(J100/100*11.7)-(B100/100) -> #VALUE! | N100: =(J100*11.7/100)/((J100*11.7/100)+(F100*44.5/2000)) -> #VALUE! | P100: {=[2]!'qhok5[INTERVAL:DAILY,COMPRESSION:1,SORT:ASC,SPAN:25]?DATE,CLOSE'} -> #REF! | Q100: #REF! | R100: =IF(IF(ISNUMBER(P100),MONTH(P100),MONTH(DATEVALUE(P100)))=$B$96,Q100,"-- ") -> #VALUE! | S100: =Q100+0.2+0.1-0.29-0.08-0.08-(J100+AVERAGE('[6]Monthly SBO'!$M$259:$N$259)/100*7.5) -> #VALUE! | U100: =(F100/2000*44)+(J100/100*11)-B100/100 -> #VALUE! | V100: =J100/100*11/(B100/100+U100) -> #VALUE! | X100: {=[2]!'KPOk5[INTERVAL:DAILY,COMPRESSION:1,SORT:ASC,SPAN:25]?DATE,CLOSE'} -> #REF! | Y100: #REF! | Z100: =IF(IF(ISNUMBER(X100),MONTH(X100),MONTH(DATEVALUE(X100)))=$B$96,Y100,"-- ") -> #VALUE!
A101: #REF! | B101: #REF! | C101: {=IF(IF(ISNUMBER(A101),MONTH(A101),MONTH(DATEVALUE(A101)))=$B$96,B101/100,"-- ")} -> #VALUE! | E101: #REF! | F101: #REF! | G101: =IF(IF(ISNUMBER(E101),MONTH(E101),MONTH(DATEVALUE(E101)))=$B$96,F101,"-- ") -> #VALUE! | H101: =F101*44.5/2000 -> #VALUE! | I101: #REF! | J101: #REF! | K101: =IF(IF(ISNUMBER(I101),MONTH(I101),MONTH(DATEVALUE(I101)))=$B$96,J101,"-- ") -> #VALUE! | L101: =(J101/100)*11.7 -> #VALUE! | M101: =(F101/2000*44.5)+(J101/100*11.7)-(B101/100) -> #VALUE! | N101: =(J101*11.7/100)/((J101*11.7/100)+(F101*44.5/2000)) -> #VALUE! | P101: #REF! | Q101: #REF! | R101: =IF(IF(ISNUMBER(P101),MONTH(P101),MONTH(DATEVALUE(P101)))=$B$96,Q101,"-- ") -> #VALUE! | S101: =Q101+0.2+0.1-0.29-0.08-0.08-(J101+AVERAGE('[6]Monthly SBO'!$M$259:$N$259)/100*7.5) -> #VALUE! | U101: =(F101/2000*44)+(J101/100*11)-B101/100 -> #VALUE! | V101: =J101/100*11/(B101/100+U101) -> #VALUE! | X101: #REF! | Y101: #REF! | Z101: =IF(IF(ISNUMBER(X101),MONTH(X101),MONTH(DATEVALUE(X101)))=$B$96,Y101,"-- ") -> #VALUE!
A102: #REF! | B102: #REF! | C102: {=IF(IF(ISNUMBER(A102),MONTH(A102),MONTH(DATEVALUE(A102)))=$B$96,B102/100,"-- ")} -> #VALUE! | E102: #REF! | F102: #REF! | G102: =IF(IF(ISNUMBER(E102),MONTH(E102),MONTH(DATEVALUE(E102)))=$B$96,F102,"-- ") -> #VALUE! | H102: =F102*44.5/2000 -> #VALUE! | I102: #REF! | J102: #REF! | K102: =IF(IF(ISNUMBER(I102),MONTH(I102),MONTH(DATEVALUE(I102)))=$B$96,J102,"-- ") -> #VALUE! | L102: =(J102/100)*11.7 -> #VALUE! | M102: =(F102/2000*44.5)+(J102/100*11.7)-(B102/100) -> #VALUE! | N102: =(J102*11.7/100)/((J102*11.7/100)+(F102*44.5/2000)) -> #VALUE! | P102: #REF! | Q102: #REF! | R102: =IF(IF(ISNUMBER(P102),MONTH(P102),MONTH(DATEVALUE(P102)))=$B$96,Q102,"-- ") -> #VALUE! | S102: =Q102+0.2+0.1-0.29-0.08-0.08-(J102+AVERAGE('[6]Monthly SBO'!$M$259:$N$259)/100*7.5) -> #VALUE! | U102: =(F102/2000*44)+(J102/100*11)-B102/100 -> #VALUE! | V102: =J102/100*11/(B102/100+U102) -> #VALUE! | X102: #REF! | Y102: #REF! | Z102: =IF(IF(ISNUMBER(X102),MONTH(X102),MONTH(DATEVALUE(X102)))=$B$96,Y102,"-- ") -> #VALUE!
A103: #REF! | B103: #REF! | C103: {=IF(IF(ISNUMBER(A103),MONTH(A103),MONTH(DATEVALUE(A103)))=$B$96,B103/100,"-- ")} -> #VALUE! | E103: #REF! | F103: #REF! | G103: =IF(IF(ISNUMBER(E103),MONTH(E103),MONTH(DATEVALUE(E103)))=$B$96,F103,"-- ") -> #VALUE! | H103: =F103*44.5/2000 -> #VALUE! | I103: #REF! | J103: #REF! | K103: =IF(IF(ISNUMBER(I103),MONTH(I103),MONTH(DATEVALUE(I103)))=$B$96,J103,"-- ") -> #VALUE! | L103: =(J103/100)*11.7 -> #VALUE! | M103: =(F103/2000*44.5)+(J103/100*11.7)-(B103/100) -> #VALUE! | N103: =(J103*11.7/100)/((J103*11.7/100)+(F103*44.5/2000)) -> #VALUE! | P103: #REF! | Q103: #REF! | R103: =IF(IF(ISNUMBER(P103),MONTH(P103),MONTH(DATEVALUE(P103)))=$B$96,Q103,"-- ") -> #VALUE! | S103: =Q103+0.2+0.1-0.29-0.08-0.08-(J103+AVERAGE('[6]Monthly SBO'!$M$259:$N$259)/100*7.5) -> #VALUE! | U103: =(F103/2000*44)+(J103/100*11)-B103/100 -> #VALUE! | V103: =J103/100*11/(B103/100+U103) -> #VALUE! | X103: #REF! | Y103: #REF! | Z103: =IF(IF(ISNUMBER(X103),MONTH(X103),MONTH(DATEVALUE(X103)))=$B$96,Y103,"-- ") -> #VALUE!
A104: #REF! | B104: #REF! | C104: {=IF(IF(ISNUMBER(A104),MONTH(A104),MONTH(DATEVALUE(A104)))=$B$96,B104/100,"-- ")} -> #VALUE! | E104: #REF! | F104: #REF! | G104: =IF(IF(ISNUMBER(E104),MONTH(E104),MONTH(DATEVALUE(E104)))=$B$96,F104,"-- ") -> #VALUE! | H104: =F104*44.5/2000 -> #VALUE! | I104: #REF! | J104: #REF! | K104: =IF(IF(ISNUMBER(I104),MONTH(I104),MONTH(DATEVALUE(I104)))=$B$96,J104,"-- ") -> #VALUE! | L104: =(J104/100)*11.7 -> #VALUE! | M104: =(F104/2000*44.5)+(J104/100*11.7)-(B104/100) -> #VALUE! | N104: =(J104*11.7/100)/((J104*11.7/100)+(F104*44.5/2000)) -> #VALUE! | P104: #REF! | Q104: #REF! | R104: =IF(IF(ISNUMBER(P104),MONTH(P104),MONTH(DATEVALUE(P104)))=$B$96,Q104,"-- ") -> #VALUE! | S104: =Q104+0.2+0.1-0.29-0.08-0.08-(J104+AVERAGE('[6]Monthly SBO'!$M$259:$N$259)/100*7.5) -> #VALUE! | U104: =(F104/2000*44)+(J104/100*11)-B104/100 -> #VALUE! | V104: =J104/100*11/(B104/100+U104) -> #VALUE! | X104: #REF! | Y104: #REF! | Z104: =IF(IF(ISNUMBER(X104),MONTH(X104),MONTH(DATEVALUE(X104)))=$B$96,Y104,"-- ") -> #VALUE!
A105: #REF! | B105: #REF! | C105: {=IF(IF(ISNUMBER(A105),MONTH(A105),MONTH(DATEVALUE(A105)))=$B$96,B105/100,"-- ")} -> #VALUE! | E105: #REF! | F105: #REF! | G105: =IF(IF(ISNUMBER(E105),MONTH(E105),MONTH(DATEVALUE(E105)))=$B$96,F105,"-- ") -> #VALUE! | H105: =F105*44.5/2000 -> #VALUE! | I105: #REF! | J105: #REF! | K105: =IF(IF(ISNUMBER(I105),MONTH(I105),MONTH(DATEVALUE(I105)))=$B$96,J105,"-- ") -> #VALUE! | L105: =(J105/100)*11.7 -> #VALUE! | M105: =(F105/2000*44.5)+(J105/100*11.7)-(B105/100) -> #VALUE! | N105: =(J105*11.7/100)/((J105*11.7/100)+(F105*44.5/2000)) -> #VALUE! | P105: #REF! | Q105: #REF! | R105: =IF(IF(ISNUMBER(P105),MONTH(P105),MONTH(DATEVALUE(P105)))=$B$96,Q105,"-- ") -> #VALUE! | S105: =Q105+0.2+0.1-0.29-0.08-0.08-(J105+AVERAGE('[6]Monthly SBO'!$M$259:$N$259)/100*7.5) -> #VALUE! | U105: =(F105/2000*44)+(J105/100*11)-B105/100 -> #VALUE! | V105: =J105/100*11/(B105/100+U105) -> #VALUE! | X105: #REF! | Y105: #REF! | Z105: =IF(IF(ISNUMBER(X105),MONTH(X105),MONTH(DATEVALUE(X105)))=$B$96,Y105,"-- ") -> #VALUE!
A106: #REF! | B106: #REF! | C106: {=IF(IF(ISNUMBER(A106),MONTH(A106),MONTH(DATEVALUE(A106)))=$B$96,B106/100,"-- ")} -> #VALUE! | E106: #REF! | F106: #REF! | G106: =IF(IF(ISNUMBER(E106),MONTH(E106),MONTH(DATEVALUE(E106)))=$B$96,F106,"-- ") -> #VALUE! | H106: =F106*44.5/2000 -> #VALUE! | I106: #REF! | J106: #REF! | K106: =IF(IF(ISNUMBER(I106),MONTH(I106),MONTH(DATEVALUE(I106)))=$B$96,J106,"-- ") -> #VALUE! | L106: =(J106/100)*11.7 -> #VALUE! | M106: =(F106/2000*44.5)+(J106/100*11.7)-(B106/100) -> #VALUE! | N106: =(J106*11.7/100)/((J106*11.7/100)+(F106*44.5/2000)) -> #VALUE! | P106: #REF! | Q106: #REF! | R106: =IF(IF(ISNUMBER(P106),MONTH(P106),MONTH(DATEVALUE(P106)))=$B$96,Q106,"-- ") -> #VALUE! | S106: =Q106+0.2+0.1-0.29-0.08-0.08-(J106+AVERAGE('[6]Monthly SBO'!$M$259:$N$259)/100*7.5) -> #VALUE! | U106: =(F106/2000*44)+(J106/100*11)-B106/100 -> #VALUE! | V106: =J106/100*11/(B106/100+U106) -> #VALUE! | X106: #REF! | Y106: #REF! | Z106: =IF(IF(ISNUMBER(X106),MONTH(X106),MONTH(DATEVALUE(X106)))=$B$96,Y106,"-- ") -> #VALUE!
A107: #REF! | B107: #REF! | C107: {=IF(IF(ISNUMBER(A107),MONTH(A107),MONTH(DATEVALUE(A107)))=$B$96,B107/100,"-- ")} -> #VALUE! | E107: #REF! | F107: #REF! | G107: =IF(IF(ISNUMBER(E107),MONTH(E107),MONTH(DATEVALUE(E107)))=$B$96,F107,"-- ") -> #VALUE! | H107: =F107*44.5/2000 -> #VALUE! | I107: #REF! | J107: #REF! | K107: =IF(IF(ISNUMBER(I107),MONTH(I107),MONTH(DATEVALUE(I107)))=$B$96,J107,"-- ") -> #VALUE! | L107: =(J107/100)*11.7 -> #VALUE! | M107: =(F107/2000*44.5)+(J107/100*11.7)-(B107/100) -> #VALUE! | N107: =(J107*11.7/100)/((J107*11.7/100)+(F107*44.5/2000)) -> #VALUE! | P107: #REF! | Q107: #REF! | R107: =IF(IF(ISNUMBER(P107),MONTH(P107),MONTH(DATEVALUE(P107)))=$B$96,Q107,"-- ") -> #VALUE! | S107: =Q107+0.2+0.1-0.29-0.08-0.08-(J107+AVERAGE('[6]Monthly SBO'!$M$259:$N$259)/100*7.5) -> #VALUE! | U107: =(F107/2000*44)+(J107/100*11)-B107/100 -> #VALUE! | V107: =J107/100*11/(B107/100+U107) -> #VALUE! | X107: #REF! | Y107: #REF! | Z107: =IF(IF(ISNUMBER(X107),MONTH(X107),MONTH(DATEVALUE(X107)))=$B$96,Y107,"-- ") -> #VALUE!
A108: #REF! | B108: #REF! | C108: {=IF(IF(ISNUMBER(A108),MONTH(A108),MONTH(DATEVALUE(A108)))=$B$96,B108/100,"-- ")} -> #VALUE! | E108: #REF! | F108: #REF! | G108: =IF(IF(ISNUMBER(E108),MONTH(E108),MONTH(DATEVALUE(E108)))=$B$96,F108,"-- ") -> #VALUE! | H108: =F108*44.5/2000 -> #VALUE! | I108: #REF! | J108: #REF! | K108: =IF(IF(ISNUMBER(I108),MONTH(I108),MONTH(DATEVALUE(I108)))=$B$96,J108,"-- ") -> #VALUE! | L108: =(J108/100)*11.7 -> #VALUE! | M108: =(F108/2000*44.5)+(J108/100*11.7)-(B108/100) -> #VALUE! | N108: =(J108*11.7/100)/((J108*11.7/100)+(F108*44.5/2000)) -> #VALUE! | P108: #REF! | Q108: #REF! | R108: =IF(IF(ISNUMBER(P108),MONTH(P108),MONTH(DATEVALUE(P108)))=$B$96,Q108,"-- ") -> #VALUE! | S108: =Q108+0.2+0.1-0.29-0.08-0.08-(J108+AVERAGE('[6]Monthly SBO'!$M$259:$N$259)/100*7.5) -> #VALUE! | U108: =(F108/2000*44)+(J108/100*11)-B108/100 -> #VALUE! | V108: =J108/100*11/(B108/100+U108) -> #VALUE! | X108: #REF! | Y108: #REF! | Z108: =IF(IF(ISNUMBER(X108),MONTH(X108),MONTH(DATEVALUE(X108)))=$B$96,Y108,"-- ") -> #VALUE!
A109: #REF! | B109: #REF! | C109: {=IF(IF(ISNUMBER(A109),MONTH(A109),MONTH(DATEVALUE(A109)))=$B$96,B109/100,"-- ")} -> #VALUE! | E109: #REF! | F109: #REF! | G109: =IF(IF(ISNUMBER(E109),MONTH(E109),MONTH(DATEVALUE(E109)))=$B$96,F109,"-- ") -> #VALUE! | H109: =F109*44.5/2000 -> #VALUE! | I109: #REF! | J109: #REF! | K109: =IF(IF(ISNUMBER(I109),MONTH(I109),MONTH(DATEVALUE(I109)))=$B$96,J109,"-- ") -> #VALUE! | L109: =(J109/100)*11.7 -> #VALUE! | M109: =(F109/2000*44.5)+(J109/100*11.7)-(B109/100) -> #VALUE! | N109: =(J109*11.7/100)/((J109*11.7/100)+(F109*44.5/2000)) -> #VALUE! | P109: #REF! | Q109: #REF! | R109: =IF(IF(ISNUMBER(P109),MONTH(P109),MONTH(DATEVALUE(P109)))=$B$96,Q109,"-- ") -> #VALUE! | S109: =Q109+0.2+0.1-0.29-0.08-0.08-(J109+AVERAGE('[6]Monthly SBO'!$M$259:$N$259)/100*7.5) -> #VALUE! | U109: =(F109/2000*44)+(J109/100*11)-B109/100 -> #VALUE! | V109: =J109/100*11/(B109/100+U109) -> #VALUE! | X109: #REF! | Y109: #REF! | Z109: =IF(IF(ISNUMBER(X109),MONTH(X109),MONTH(DATEVALUE(X109)))=$B$96,Y109,"-- ") -> #VALUE!
A110: #REF! | B110: #REF! | C110: {=IF(IF(ISNUMBER(A110),MONTH(A110),MONTH(DATEVALUE(A110)))=$B$96,B110/100,"-- ")} -> #VALUE! | E110: #REF! | F110: #REF! | G110: =IF(IF(ISNUMBER(E110),MONTH(E110),MONTH(DATEVALUE(E110)))=$B$96,F110,"-- ") -> #VALUE! | H110: =F110*44.5/2000 -> #VALUE! | I110: #REF! | J110: #REF! | K110: =IF(IF(ISNUMBER(I110),MONTH(I110),MONTH(DATEVALUE(I110)))=$B$96,J110,"-- ") -> #VALUE! | L110: =(J110/100)*11.7 -> #VALUE! | M110: =(F110/2000*44.5)+(J110/100*11.7)-(B110/100) -> #VALUE! | N110: =(J110*11.7/100)/((J110*11.7/100)+(F110*44.5/2000)) -> #VALUE! | P110: #REF! | Q110: #REF! | R110: =IF(IF(ISNUMBER(P110),MONTH(P110),MONTH(DATEVALUE(P110)))=$B$96,Q110,"-- ") -> #VALUE! | S110: =Q110+0.2+0.1-0.29-0.08-0.08-(J110+AVERAGE('[6]Monthly SBO'!$M$259:$N$259)/100*7.5) -> #VALUE! | U110: =(F110/2000*44)+(J110/100*11)-B110/100 -> #VALUE! | V110: =J110/100*11/(B110/100+U110) -> #VALUE! | X110: #REF! | Y110: #REF! | Z110: =IF(IF(ISNUMBER(X110),MONTH(X110),MONTH(DATEVALUE(X110)))=$B$96,Y110,"-- ") -> #VALUE!
A111: #REF! | B111: #REF! | C111: {=IF(IF(ISNUMBER(A111),MONTH(A111),MONTH(DATEVALUE(A111)))=$B$96,B111/100,"-- ")} -> #VALUE! | E111: #REF! | F111: #REF! | G111: =IF(IF(ISNUMBER(E111),MONTH(E111),MONTH(DATEVALUE(E111)))=$B$96,F111,"-- ") -> #VALUE! | H111: =F111*44.5/2000 -> #VALUE! | I111: #REF! | J111: #REF! | K111: =IF(IF(ISNUMBER(I111),MONTH(I111),MONTH(DATEVALUE(I111)))=$B$96,J111,"-- ") -> #VALUE! | L111: =(J111/100)*11.7 -> #VALUE! | M111: =(F111/2000*44.5)+(J111/100*11.7)-(B111/100) -> #VALUE! | N111: =(J111*11.7/100)/((J111*11.7/100)+(F111*44.5/2000)) -> #VALUE! | P111: #REF! | Q111: #REF! | R111: =IF(IF(ISNUMBER(P111),MONTH(P111),MONTH(DATEVALUE(P111)))=$B$96,Q111,"-- ") -> #VALUE! | S111: =Q111+0.2+0.1-0.29-0.08-0.08-(J111+AVERAGE('[6]Monthly SBO'!$M$259:$N$259)/100*7.5) -> #VALUE! | U111: =(F111/2000*44)+(J111/100*11)-B111/100 -> #VALUE! | V111: =J111/100*11/(B111/100+U111) -> #VALUE! | X111: #REF! | Y111: #REF! | Z111: =IF(IF(ISNUMBER(X111),MONTH(X111),MONTH(DATEVALUE(X111)))=$B$96,Y111,"-- ") -> #VALUE!
A112: #REF! | B112: #REF! | C112: {=IF(IF(ISNUMBER(A112),MONTH(A112),MONTH(DATEVALUE(A112)))=$B$96,B112/100,"-- ")} -> #VALUE! | E112: #REF! | F112: #REF! | G112: =IF(IF(ISNUMBER(E112),MONTH(E112),MONTH(DATEVALUE(E112)))=$B$96,F112,"-- ") -> #VALUE! | H112: =F112*44.5/2000 -> #VALUE! | I112: #REF! | J112: #REF! | K112: =IF(IF(ISNUMBER(I112),MONTH(I112),MONTH(DATEVALUE(I112)))=$B$96,J112,"-- ") -> #VALUE! | L112: =(J112/100)*11.7 -> #VALUE! | M112: =(F112/2000*44.5)+(J112/100*11.7)-(B112/100) -> #VALUE! | N112: =(J112*11.7/100)/((J112*11.7/100)+(F112*44.5/2000)) -> #VALUE! | P112: #REF! | Q112: #REF! | R112: =IF(IF(ISNUMBER(P112),MONTH(P112),MONTH(DATEVALUE(P112)))=$B$96,Q112,"-- ") -> #VALUE! | S112: =Q112+0.2+0.1-0.29-0.08-0.08-(J112+AVERAGE('[6]Monthly SBO'!$M$259:$N$259)/100*7.5) -> #VALUE! | U112: =(F112/2000*44)+(J112/100*11)-B112/100 -> #VALUE! | V112: =J112/100*11/(B112/100+U112) -> #VALUE! | X112: #REF! | Y112: #REF! | Z112: =IF(IF(ISNUMBER(X112),MONTH(X112),MONTH(DATEVALUE(X112)))=$B$96,Y112,"-- ") -> #VALUE!
A113: #REF! | B113: #REF! | C113: {=IF(IF(ISNUMBER(A113),MONTH(A113),MONTH(DATEVALUE(A113)))=$B$96,B113/100,"-- ")} -> #VALUE! | E113: #REF! | F113: #REF! | G113: =IF(IF(ISNUMBER(E113),MONTH(E113),MONTH(DATEVALUE(E113)))=$B$96,F113,"-- ") -> #VALUE! | H113: =F113*44.5/2000 -> #VALUE! | I113: #REF! | J113: #REF! | K113: =IF(IF(ISNUMBER(I113),MONTH(I113),MONTH(DATEVALUE(I113)))=$B$96,J113,"-- ") -> #VALUE! | L113: =(J113/100)*11.7 -> #VALUE! | M113: =(F113/2000*44.5)+(J113/100*11.7)-(B113/100) -> #VALUE! | N113: =(J113*11.7/100)/((J113*11.7/100)+(F113*44.5/2000)) -> #VALUE! | P113: #REF! | Q113: #REF! | R113: =IF(IF(ISNUMBER(P113),MONTH(P113),MONTH(DATEVALUE(P113)))=$B$96,Q113,"-- ") -> #VALUE! | S113: =Q113+0.2+0.1-0.29-0.08-0.08-(J113+AVERAGE('[6]Monthly SBO'!$M$259:$N$259)/100*7.5) -> #VALUE! | U113: =(F113/2000*44)+(J113/100*11)-B113/100 -> #VALUE! | V113: =J113/100*11/(B113/100+U113) -> #VALUE! | X113: #REF! | Y113: #REF! | Z113: =IF(IF(ISNUMBER(X113),MONTH(X113),MONTH(DATEVALUE(X113)))=$B$96,Y113,"-- ") -> #VALUE!
A114: #REF! | B114: #REF! | C114: {=IF(IF(ISNUMBER(A114),MONTH(A114),MONTH(DATEVALUE(A114)))=$B$96,B114/100,"-- ")} -> #VALUE! | E114: #REF! | F114: #REF! | G114: =IF(IF(ISNUMBER(E114),MONTH(E114),MONTH(DATEVALUE(E114)))=$B$96,F114,"-- ") -> #VALUE! | H114: =F114*44.5/2000 -> #VALUE! | I114: #REF! | J114: #REF! | K114: =IF(IF(ISNUMBER(I114),MONTH(I114),MONTH(DATEVALUE(I114)))=$B$96,J114,"-- ") -> #VALUE! | L114: =(J114/100)*11.7 -> #VALUE! | M114: =(F114/2000*44.5)+(J114/100*11.7)-(B114/100) -> #VALUE! | N114: =(J114*11.7/100)/((J114*11.7/100)+(F114*44.5/2000)) -> #VALUE! | O114: =L114/(L114+H114) -> #VALUE! | P114: #REF! | Q114: #REF! | R114: =IF(IF(ISNUMBER(P114),MONTH(P114),MONTH(DATEVALUE(P114)))=$B$96,Q114,"-- ") -> #VALUE! | S114: =Q114+0.2+0.1-0.29-0.08-0.08-(J114+AVERAGE('[6]Monthly SBO'!$M$259:$N$259)/100*7.5) -> #VALUE! | U114: =(F114/2000*44)+(J114/100*11)-B114/100 -> #VALUE! | V114: =J114/100*11/(B114/100+U114) -> #VALUE! | X114: #REF! | Y114: #REF! | Z114: =IF(IF(ISNUMBER(X114),MONTH(X114),MONTH(DATEVALUE(X114)))=$B$96,Y114,"-- ") -> #VALUE!
A115: #REF! | B115: #REF! | C115: {=IF(IF(ISNUMBER(A115),MONTH(A115),MONTH(DATEVALUE(A115)))=$B$96,B115/100,"-- ")} -> #VALUE! | E115: #REF! | F115: #REF! | G115: =IF(IF(ISNUMBER(E115),MONTH(E115),MONTH(DATEVALUE(E115)))=$B$96,F115,"-- ") -> #VALUE! | H115: =F115*44.5/2000 -> #VALUE! | I115: #REF! | J115: #REF! | K115: =IF(IF(ISNUMBER(I115),MONTH(I115),MONTH(DATEVALUE(I115)))=$B$96,J115,"-- ") -> #VALUE! | L115: =(J115/100)*11.7 -> #VALUE! | M115: =(F115/2000*44.5)+(J115/100*11.7)-(B115/100) -> #VALUE! | N115: =(J115*11.7/100)/((J115*11.7/100)+(F115*44.5/2000)) -> #VALUE! | P115: #REF! | Q115: #REF! | R115: =IF(IF(ISNUMBER(P115),MONTH(P115),MONTH(DATEVALUE(P115)))=$B$96,Q115,"-- ") -> #VALUE! | S115: =Q115+0.2+0.1-0.29-0.08-0.08-(J115+AVERAGE('[6]Monthly SBO'!$M$259:$N$259)/100*7.5) -> #VALUE! | U115: =(F115/2000*44)+(J115/100*11)-B115/100 -> #VALUE! | V115: =J115/100*11/(B115/100+U115) -> #VALUE! | X115: #REF! | Y115: #REF! | Z115: =IF(IF(ISNUMBER(X115),MONTH(X115),MONTH(DATEVALUE(X115)))=$B$96,Y115,"-- ") -> #VALUE!
A116: #REF! | B116: #REF! | C116: {=IF(IF(ISNUMBER(A116),MONTH(A116),MONTH(DATEVALUE(A116)))=$B$96,B116/100,"-- ")} -> #VALUE! | E116: #REF! | F116: #REF! | G116: =IF(IF(ISNUMBER(E116),MONTH(E116),MONTH(DATEVALUE(E116)))=$B$96,F116,"-- ") -> #VALUE! | H116: =F116*44.5/2000 -> #VALUE! | I116: #REF! | J116: #REF! | K116: =IF(IF(ISNUMBER(I116),MONTH(I116),MONTH(DATEVALUE(I116)))=$B$96,J116,"-- ") -> #VALUE! | L116: =(J116/100)*11.7 -> #VALUE! | M116: =(F116/2000*44.5)+(J116/100*11.7)-(B116/100) -> #VALUE! | N116: =(J116*11.7/100)/((J116*11.7/100)+(F116*44.5/2000)) -> #VALUE! | P116: #REF! | Q116: #REF! | R116: =IF(IF(ISNUMBER(P116),MONTH(P116),MONTH(DATEVALUE(P116)))=$B$96,Q116,"-- ") -> #VALUE! | S116: =Q116+0.2+0.1-0.29-0.08-0.08-(J116+AVERAGE('[6]Monthly SBO'!$M$259:$N$259)/100*7.5) -> #VALUE! | U116: =(F116/2000*44)+(J116/100*11)-B116/100 -> #VALUE! | V116: =J116/100*11/(B116/100+U116) -> #VALUE! | X116: #REF! | Y116: #REF! | Z116: =IF(IF(ISNUMBER(X116),MONTH(X116),MONTH(DATEVALUE(X116)))=$B$96,Y116,"-- ") -> #VALUE!
A117: #REF! | B117: #REF! | C117: {=IF(IF(ISNUMBER(A117),MONTH(A117),MONTH(DATEVALUE(A117)))=$B$96,B117/100,"-- ")} -> #VALUE! | E117: #REF! | F117: #REF! | G117: =IF(IF(ISNUMBER(E117),MONTH(E117),MONTH(DATEVALUE(E117)))=$B$96,F117,"-- ") -> #VALUE! | H117: =F117*44.5/2000 -> #VALUE! | I117: #REF! | J117: #REF! | K117: =IF(IF(ISNUMBER(I117),MONTH(I117),MONTH(DATEVALUE(I117)))=$B$96,J117,"-- ") -> #VALUE! | L117: =(J117/100)*11.7 -> #VALUE! | M117: =(F117/2000*44.5)+(J117/100*11.7)-(B117/100) -> #VALUE! | N117: =(J117*11.7/100)/((J117*11.7/100)+(F117*44.5/2000)) -> #VALUE! | P117: #REF! | Q117: #REF! | R117: =IF(IF(ISNUMBER(P117),MONTH(P117),MONTH(DATEVALUE(P117)))=$B$96,Q117,"-- ") -> #VALUE! | S117: =Q117+0.2+0.1-0.29-0.08-0.08-(J117+AVERAGE('[6]Monthly SBO'!$M$259:$N$259)/100*7.5) -> #VALUE! | U117: =(F117/2000*44)+(J117/100*11)-B117/100 -> #VALUE! | V117: =J117/100*11/(B117/100+U117) -> #VALUE! | X117: #REF! | Y117: #REF! | Z117: =IF(IF(ISNUMBER(X117),MONTH(X117),MONTH(DATEVALUE(X117)))=$B$96,Y117,"-- ") -> #VALUE!
A118: #REF! | B118: #REF! | C118: {=IF(IF(ISNUMBER(A118),MONTH(A118),MONTH(DATEVALUE(A118)))=$B$96,B118/100,"-- ")} -> #VALUE! | E118: #REF! | F118: #REF! | G118: =IF(IF(ISNUMBER(E118),MONTH(E118),MONTH(DATEVALUE(E118)))=$B$96,F118,"-- ") -> #VALUE! | H118: =F118*44.5/2000 -> #VALUE! | I118: #REF! | J118: #REF! | K118: =IF(IF(ISNUMBER(I118),MONTH(I118),MONTH(DATEVALUE(I118)))=$B$96,J118,"-- ") -> #VALUE! | L118: =(J118/100)*11.7 -> #VALUE! | M118: =(F118/2000*44.5)+(J118/100*11.7)-(B118/100) -> #VALUE! | N118: =(J118*11.7/100)/((J118*11.7/100)+(F118*44.5/2000)) -> #VALUE! | P118: #REF! | Q118: #REF! | R118: =IF(IF(ISNUMBER(P118),MONTH(P118),MONTH(DATEVALUE(P118)))=$B$96,Q118,"-- ") -> #VALUE! | S118: =Q118+0.2+0.1-0.29-0.08-0.08-(J118+AVERAGE('[6]Monthly SBO'!$M$259:$N$259)/100*7.5) -> #VALUE! | U118: =(F118/2000*44)+(J118/100*11)-B118/100 -> #VALUE! | V118: =J118/100*11/(B118/100+U118) -> #VALUE! | X118: #REF! | Y118: #REF! | Z118: =IF(IF(ISNUMBER(X118),MONTH(X118),MONTH(DATEVALUE(X118)))=$B$96,Y118,"-- ") -> #VALUE!
A119: #REF! | B119: #REF! | C119: {=IF(IF(ISNUMBER(A119),MONTH(A119),MONTH(DATEVALUE(A119)))=$B$96,B119/100,"-- ")} -> #VALUE! | E119: #REF! | F119: #REF! | G119: =IF(IF(ISNUMBER(E119),MONTH(E119),MONTH(DATEVALUE(E119)))=$B$96,F119,"-- ") -> #VALUE! | H119: =F119*44.5/2000 -> #VALUE! | I119: #REF! | J119: #REF! | K119: =IF(IF(ISNUMBER(I119),MONTH(I119),MONTH(DATEVALUE(I119)))=$B$96,J119,"-- ") -> #VALUE! | L119: =(J119/100)*11.7 -> #VALUE! | M119: =(F119/2000*44.5)+(J119/100*11.7)-(B119/100) -> #VALUE! | N119: =(J119*11.7/100)/((J119*11.7/100)+(F119*44.5/2000)) -> #VALUE! | P119: #REF! | Q119: #REF! | R119: =IF(IF(ISNUMBER(P119),MONTH(P119),MONTH(DATEVALUE(P119)))=$B$96,Q119,"-- ") -> #VALUE! | S119: =Q119+0.2+0.1-0.29-0.08-0.08-(J119+AVERAGE('[6]Monthly SBO'!$M$259:$N$259)/100*7.5) -> #VALUE! | U119: =(F119/2000*44)+(J119/100*11)-B119/100 -> #VALUE! | V119: =J119/100*11/(B119/100+U119) -> #VALUE! | X119: #REF! | Y119: #REF! | Z119: =IF(IF(ISNUMBER(X119),MONTH(X119),MONTH(DATEVALUE(X119)))=$B$96,Y119,"-- ") -> #VALUE!
A120: #REF! | B120: #REF! | C120: {=IF(IF(ISNUMBER(A120),MONTH(A120),MONTH(DATEVALUE(A120)))=$B$96,B120/100,"-- ")} -> #VALUE! | E120: #REF! | F120: #REF! | G120: =IF(IF(ISNUMBER(E120),MONTH(E120),MONTH(DATEVALUE(E120)))=$B$96,F120,"-- ") -> #VALUE! | H120: =F120*44.5/2000 -> #VALUE! | I120: #REF! | J120: #REF! | K120: =IF(IF(ISNUMBER(I120),MONTH(I120),MONTH(DATEVALUE(I120)))=$B$96,J120,"-- ") -> #VALUE! | L120: =(J120/100)*11.7 -> #VALUE! | M120: =(F120/2000*44.5)+(J120/100*11.7)-(B120/100) -> #VALUE! | N120: =(J120*11.7/100)/((J120*11.7/100)+(F120*44.5/2000)) -> #VALUE! | P120: #REF! | Q120: #REF! | R120: =IF(IF(ISNUMBER(P120),MONTH(P120),MONTH(DATEVALUE(P120)))=$B$96,Q120,"-- ") -> #VALUE! | S120: =Q120+0.2+0.1-0.29-0.08-0.08-(J120+AVERAGE('[6]Monthly SBO'!$M$259:$N$259)/100*7.5) -> #VALUE! | U120: =(F120/2000*44)+(J120/100*11)-B120/100 -> #VALUE! | V120: =J120/100*11/(B120/100+U120) -> #VALUE! | X120: #REF! | Y120: #REF! | Z120: =IF(IF(ISNUMBER(X120),MONTH(X120),MONTH(DATEVALUE(X120)))=$B$96,Y120,"-- ") -> #VALUE!
...

Sheet Sheet1
B1: SF1 | C1: BOZ1 | D1: BOF2 | E1: SMZ1 | F1: SMF2
A2: 44501 | B2: 1248.5 | C2: 61.97 | E2: 329.1
A3: 44502 | B3: 1256.25 | C3: 61.99 | E3: 337.2
A4: 44503 | B4: 1244.25 | C4: 61.03 | E4: 340.8
A5: 44504 | B5: 1222.75 | C5: 59.58 | E5: 335.8
A6: 44505 | B6: 1205.5 | C6: 58.78 | E6: 332.7
A7: 44508 | B7: 1188.5 | C7: 58.05 | E7: 331.8
A8: 44509 | B8: 1212 | C8: 58.47 | E8: 342.5
A9: 44510 | B9: 1216.75 | C9: 59.14 | E9: 342.4
A10: 44511 | B10: 1221.5 | C10: 59.14 | E10: 344.5
A11: 44512 | B11: 1244.25 | C11: 58.97 | E11: 362.1
A12: 44515 | B12: 1257.25 | C12: 58.2 | E12: 371.7
A13: 44516 | B13: 1251.25 | C13: 59.17 | E13: 367.5
... A22: 44530 | B22: 1217.25 | C22: 55.11 | E22: 348.8
A23: 44531 | B23: 1228.25 | D23: 55.18 | F23: 349.1
A24: 44532 | B24: 1244.25 | D24: 56.34 | F24: 348.8
A25: 44533 | B25: 1267.25 | D25: 57.22 | F25: 358.6
A26: 44536 | B26: 1261.5 | D26: 57.86 | F26: 352.6
A27: 44537 | B27: 1250.25 | D27: 57.1 | F27: 349.7
A28: 44538 | B28: 1261 | D28: 55.55 | F28: 357.2
A29: 44539 | B29: 1264.5 | D29: 54.85 | F29: 359.7
A30: 44540 | B30: 1267.75 | D30: 53.69 | F30: 366.8
A31: 44543 | B31: 1244 | D31: 53.35 | F31: 362.1
A32: 44544 | B32: 1259.5 | D32: 52.24 | F32: 376.9
A33: 44545 | B33: 1262.5 | D33: 53.47 | F33: 372.2
A34: 44546 | B34: 1277.25 | D34: 54.65 | F34: 372.3
... A44: 44561 | B44: 1328.75 | D44: 56.3 | F44: 411.7

Sheet Prices
B1: Average Nearby Futures | G1: Quarterly | J1: Central Illinois Soy Processor | K1: http://www.ams.usda.gov/mnreports/gx_gr117.txt - discontinued Jul 2022 | M1: Cash prices in the columns J - L come from FM price reports through the vegoilspreads file | O1: Soybean Basis | P1: Basis estimates in columns O - Q are based on Fastmarkets price reports | R1: Quarterly | U1: Farm Price | Z1: Canola Oil - RBD - Chicago | AA1: Canola Oil - Soybean Oil Spread | AB1: Soybean Oil - RBD - Central Illinois | AC1: Refining Spread | AD1: Palm Oil - RBD - Gulf | AE1: Soybean Oil - Palm Oil | AF1: Soybean Oil - Crude Degummed - Gulf | AG1: Palm Oil Futures (3rd month, rolled on 1st) | AH1: Palm Oil Futures (cents per pound) | AI1: SBO - PO Futures (3rd month) | AJ1: Crude Soybean Oil - central Illinois - The Jacobsen | AK1: USDA - The Jake | AP1: OLD CASH PRICES (from AMS reports)
A2: Month | B2: Beans | C2: Meal | D2: Oil | E2: Margin | F2: Oil Share | G2: Beans | H2: Meal | I2: Oil | J2: Soybeans | K2: Meal (Rail) | L2: Crude Soybean Oil - Central Illinois | M2: Margin (AMS) | N2: Oil Share (Jake) | O2: Soybeans | P2: Meal (Rail) | Q2: Oil | R2: Soybeans | S2: Meal (Rail) | T2: Oil | U2: Price | V2: Basis | W2: Oly Avg | X2: Difference | AQ2: Soybeans | AR2: Soybean Meal | AS2: Soybean Oil
A3: 25569 | B3: 2.539125 | C3: 76.565 | D3: 9.2505 | E3: =(C3/2000*48)+(D3/100*11)-B3 -> 0.31599 | F3: =D3/100*11/(B3+E3) -> 0.3563972 | J3: 2.47 | K3: 97.25 | L3: 9.6 | M3: =(K3/2000*44)+(L3/100*11)-J3 -> 0.7255 | N3: =L3/100*11/(J3+M3) -> 0.33046472 | O3: =J3-B3 -> -0.069125 | P3: =K3-(C3+14) -> 6.685 | Q3: =L3-D3 -> 0.3495
A4: 25600 | B4: 2.555 | C4: 80.463158 | D4: 10.867895 | E4: =(C4/2000*48)+(D4/100*11)-B4 -> 0.57158421 | F4: =D4/100*11/(B4+E4) -> 0.38235606 | G4: =F4-F3 -> 0.025958857 | J4: 2.46 | K4: 95.6 | L4: 11.5 | M4: =(K4/2000*44)+(L4/100*11)-J4 -> 0.9082 | N4: =L4/100*11/(J4+M4) -> 0.37557152 | O4: =J4-B4 -> -0.095 | P4: =K4-(C4+14) -> 1.1368421 | Q4: =L4-D4 -> 0.63210526
A5: 25628 | B5: Mid | C5: 72.109524 | D5: Mid | E5: =(C5/2000*48)+(D5/100*11)-B5 -> #VALUE! | F5: Mid | G5: =F5-F4 -> #VALUE! | J5: 2.47 | K5: 80.1 | L5: 12.2 | M5: =(K5/2000*44)+(L5/100*11)-J5 -> 0.6342 | N5: Mid | O5: =J5-B5 -> #VALUE! | P5: Mid | Q5: =L5-D5 -> #VALUE! | R5: Mid | V5: Mid | Z5: Mid | AB5: Mid | AD5: Mid | AH5: Mid | AJ5: Mid | AL5: Mid
A6: 25659 | B6: 2.6313068 | C6: 73.9 | D6: 11.689091 | E6: =(C6/2000*48)+(D6/100*11)-B6 -> 0.42809318 | F6: =D6/100*11/(B6+E6) -> 0.42027849 | G6: =F6-F5 -> #VALUE! | J6: 2.58 | K6: 83.1 | L6: 12.2 | M6: =(K6/2000*44)+(L6/100*11)-J6 -> 0.5902 | N6: =L6/100*11/(J6+M6) -> 0.42331714 | O6: =J6-B6 -> -0.051306818 | P6: =K6-(C6+14) -> -4.8 | Q6: =L6-D6 -> 0.51090909 | Y6: 45138 | Z6: 0.1 | AA6: 45138 | AB6: 0.3 | AC6: 45138 | AD6: 0.18
A7: 25689 | B7: 2.690625 | C7: 73.44 | D7: 10.911 | E7: =(C7/2000*48)+(D7/100*11)-B7 -> 0.272145 | F7: =D7/100*11/(B7+E7) -> 0.40509726 | G7: =F7-F6 -> -0.015181229 | J7: 2.65 | K7: 78.9 | L7: 11.3 | M7: =(K7/2000*44)+(L7/100*11)-J7 -> 0.3288 | N7: =L7/100*11/(J7+M7) -> 0.41728213 | O7: =J7-B7 -> -0.040625 | P7: =K7-(C7+14) -> -8.54 | Q7: =L7-D7 -> 0.389 | Y7: 45139 | Z7: 0.05 | AA7: 45139 | AB7: 0.3 | AC7: 45139 | AD7: 0.18
A8: 25720 | B8: 2.7913068 | C8: 76.913636 | D8: 10.858182 | E8: =(C8/2000*48)+(D8/100*11)-B8 -> 0.24902045 | F8: =D8/100*11/(B8+E8) -> 0.39285244 | G8: =F8-F7 -> -0.012244813 | J8: 2.73 | K8: 82.7 | L8: 11.1 | M8: =(K8/2000*44)+(L8/100*11)-J8 -> 0.3104 | N8: =L8/100*11/(J8+M8) -> 0.4015919 | O8: =J8-B8 -> -0.061306818 | P8: =K8-(C8+14) -> -8.2136364 | Q8: =L8-D8 -> 0.24181818 | Y8: 45140 | Z8: 0.05 | AA8: 45140 | AB8: 0.3 | AC8: 45140 | AD8: -0.13
A9: 25750 | B9: 2.9084659 | C9: 82.590909 | D9: 11.053636 | E9: =(C9/2000*48)+(D9/100*11)-B9 -> 0.28961591 | F9: =D9/100*11/(B9+E9) -> 0.38019665 | G9: =F9-F8 -> -0.012655792 | J9: 2.8 | K9: 92.5 | L9: 11.5 | M9: =(K9/2000*44)+(L9/100*11)-J9 -> 0.5 | N9: =L9/100*11/(J9+M9) -> 0.38333333 | O9: =J9-B9 -> -0.10846591 | P9: =K9-(C9+14) -> -4.0909091 | Q9: =L9-D9 -> 0.44636364 | Y9: 45141 | Z9: 0.05 | AA9: 45141 | AB9: 0.28 | AC9: 45141 | AD9: -0.13
A10: 25781 | B10: 2.8142262 | C10: 82.114286 | D10: 10.855714 | E10: =(C10/2000*48)+(D10/100*11)-B10 -> 0.35064524 | F10: =D10/100*11/(B10+E10) -> 0.37730714 | G10: =F10-F9 -> -0.0028895169 | J10: 2.75 | K10: 92.5 | L10: 11.6 | M10: =(K10/2000*44)+(L10/100*11)-J10 -> 0.561 | N10: =L10/100*11/(J10+M10) -> 0.38538206 | O10: =J10-B10 -> -0.06422619 | P10: =K10-(C10+14) -> -3.6142857 | Q10: =L10-D10 -> 0.74428571 | Y10: 45142 | Z10: 0.05 | AA10: 45142 | AB10: 0.28 | AC10: 45142 | AD10: -0.13
A11: 25812 | B11: 2.8457143 | C11: 80.814286 | D11: 11.21 | E11: =(C11/2000*48)+(D11/100*11)-B11 -> 0.32692857 | F11: =D11/100*11/(B11+E11) -> 0.3886665 | G11: =F11-F10 -> 0.011359367 | J11: 2.75 | K11: 88.2 | L11: 12.1 | M11: =(K11/2000*44)+(L11/100*11)-J11 -> 0.5214 | N11: =L11/100*11/(J11+M11) -> 0.40685945 | O11: =J11-B11 -> -0.095714286 | P11: =K11-(C11+14) -> -6.6142857 | Q11: =L11-D11 -> 0.89 | Y11: 45145 | Z11: 0.05 | AA11: 45145 | AB11: 0.28 | AC11: 45145 | AD11: -0.13
A12: 25842 | B12: 2.9805682 | C12: 78.890909 | D12: 12.519091 | E12: =(C12/2000*48)+(D12/100*11)-B12 -> 0.28991364 | F12: =D12/100*11/(B12+E12) -> 0.42106946 | G12: =F12-F11 -> 0.032402954 | J12: 2.9 | K12: 83.75 | L12: 14 | M12: =(K12/2000*44)+(L12/100*11)-J12 -> 0.4825 | N12: =L12/100*11/(J12+M12) -> 0.45528455 | O12: =J12-B12 -> -0.080568182 | P12: =K12-(C12+14) -> -9.1409091 | Q12: =L12-D12 -> 1.4809091 | Y12: 45146 | Z12: 0.05 | AA12: 45146 | AB12: 0.38 | AC12: 45146 | AD12: -0.13
A13: 25873 | B13: 3.0588816 | C13: 80.473684 | D13: 13.129474 | E13: =(C13/2000*48)+(D13/100*11)-B13 -> 0.31672895 | F13: =D13/100*11/(B13+E13) -> 0.42784619 | G13: =F13-F12 -> 0.0067767348 | J13: 2.97 | K13: 82.5 | L13: 13.9 | M13: =(K13/2000*44)+(L13/100*11)-J13 -> 0.374 | N13: =L13/100*11/(J13+M13) -> 0.45723684 | O13: =J13-B13 -> -0.088881579 | P13: =K13-(C13+14) -> -11.973684 | Q13: =L13-D13 -> 0.77052632 | Y13: 45147 | Z13: 0.05 | AA13: 45147 | AB13: 0.28 | AC13: 45147 | AD13: -0.13
A14: 25903 | B14: 2.9548295 | C14: 81.404545 | D14: 11.907273 | E14: =(C14/2000*48)+(D14/100*11)-B14 -> 0.30867955 | F14: =D14/100*11/(B14+E14) -> 0.40134713 | G14: =F14-F13 -> -0.026499063 | J14: 2.88 | K14: 88.2 | L14: 12.4 | M14: =(K14/2000*44)+(L14/100*11)-J14 -> 0.4244 | N14: =L14/100*11/(J14+M14) -> 0.41278296 | O14: =J14-B14 -> -0.074829545 | P14: =K14-(C14+14) -> -7.2045455 | Q14: =L14-D14 -> 0.49272727 | Y14: 45148 | Z14: 0.05 | AA14: 45148 | AB14: 0.28 | AC14: 45148 | AD14: -0.13
A15: 25934 | B15: 3.058875 | C15: 79.855 | D15: 12.137 | E15: =(C15/2000*48)+(D15/100*11)-B15 -> 0.192715 | F15: =D15/100*11/(B15+E15) -> 0.4105899 | G15: =F15-F14 -> 0.0092427683 | J15: 2.99 | K15: 86.1 | L15: 12.3 | M15: =(K15/2000*44)+(L15/100*11)-J15 -> 0.2572 | N15: =L15/100*11/(J15+M15) -> 0.41666667 | O15: =J15-B15 -> -0.068875 | P15: =K15-(C15+14) -> -7.755 | Q15: =L15-D15 -> 0.163 | Y15: 45149 | Z15: 0.05 | AA15: 45149 | AB15: 0.1 | AC15: 45149 | AD15: -0.13
A16: 25965 | B16: 3.0553289 | C16: 78.205263 | D16: 11.954737 | E16: =(C16/2000*48)+(D16/100*11)-B16 -> 0.13661842 | F16: =D16/100*11/(B16+E16) -> 0.41198081 | G16: =F16-F15 -> 0.0013909109 | J16: 3.01 | K16: 82.4 | L16: 12.1 | M16: =(K16/2000*44)+(L16/100*11)-J16 -> 0.1338 | N16: =L16/100*11/(J16+M16) -> 0.42337299 | O16: =J16-B16 -> -0.045328947 | P16: =K16-(C16+14) -> -9.8052632 | Q16: =L16-D16 -> 0.14526316 | Y16: 45152 | Z16: -0.05 | AA16: 45152 | AB16: 0.15 | AC16: 45152 | AD16: -0.13
A17: 25993 | B17: 3.051413 | C17: 78.36087 | D17: 11.89 | E17: =(C17/2000*48)+(D17/100*11)-B17 -> 0.13714783 | F17: =D17/100*11/(B17+E17) -> 0.41018505 | G17: =F17-F16 -> -0.0017957569 | J17: 3 | K17: 82 | L17: 12.2 | M17: =(K17/2000*44)+(L17/100*11)-J17 -> 0.146 | N17: =L17/100*11/(J17+M17) -> 0.42657343 | O17: =J17-B17 -> -0.051413043 | P17: =K17-(C17+14) -> -10.36087 | Q17: =L17-D17 -> 0.31 | Y17: 45153 | Z17: -0.05 | AA17: 45153 | AB17: 0.18 | AC17: 45153 | AD17: -0.13
... A67: 27515 | B67: 5.1078571 | C67: 121.21905 | D67: 22.451429 | E67: =(C67/2000*48)+(D67/100*11)-B67 -> 0.27105714 | F67: =D67/100*11/(B67+E67) -> 0.45913673 | G67: =F67-F66 -> -0.038495259 | J67: 5.23 | K67: 120 | L67: 23.6 | M67: =(K67/2000*44)+(L67/100*11)-J67 -> 0.006 | N67: =L67/100*11/(J67+M67) -> 0.49579832 | O67: =J67-B67 -> 0.12214286 | P67: =K67-(C67+14) -> -15.219048 | Q67: =L67-D67 -> 1.1485714 | Y67: 45224 | Z67: -0.49 | AA67: 45224 | AB67: -0.39 | AC67: 45224 | AD67: -0.25
A68: 27546 | B68: 5.0881548 | C68: 123.25238 | D68: 21.897143 | E68: =(C68/2000*48)+(D68/100*11)-B68 -> 0.2785881 | F68: =D68/100*11/(B68+E68) -> 0.44881705 | G68: =F68-F67 -> -0.010319682 | J68: 5.16 | L68: 23.3 | O68: =J68-B68 -> 0.071845238 | Q68: =L68-D68 -> 1.4028571 | Y68: 45225 | Z68: -0.49 | AA68: 45225 | AB68: -0.39 | AC68: 45225 | AD68: -0.25
A69: 27576 | B69: 5.5544318 | C69: 129.39091 | D69: 24.909091 | E69: =(C69/2000*48)+(D69/100*11)-B69 -> 0.29095 | F69: =D69/100*11/(B69+E69) -> 0.46874611 | G69: =F69-F68 -> 0.019929059 | J69: 5.6 | K69: 147.1 | L69: 27.5 | M69: =(K69/2000*44)+(L69/100*11)-J69 -> 0.6612 | N69: =L69/100*11/(J69+M69) -> 0.48313422 | O69: =J69-B69 -> 0.045568182 | P69: =K69-(C69+14) -> 3.7090909 | Q69: =L69-D69 -> 2.5909091 | Y69: 45226 | Z69: -0.48 | AA69: 45226 | AB69: -0.28 | AC69: 45226 | AD69: -0.25
A70: 27607 | B70: 6.0555952 | C70: 143.01905 | D70: 26.691429 | E70: =(C70/2000*48)+(D70/100*11)-B70 -> 0.31291905 | F70: =D70/100*11/(B70+E70) -> 0.46102702 | G70: =F70-F69 -> -0.0077190951 | J70: 6.02 | K70: 165.9 | L70: 28.5 | M70: =(K70/2000*44)+(L70/100*11)-J70 -> 0.7648 | N70: =L70/100*11/(J70+M70) -> 0.46206226 | O70: =J70-B70 -> -0.035595238 | P70: =K70-(C70+14) -> 8.8809524 | Q70: =L70-D70 -> 1.8085714 | Y70: 45229 | Z70: -0.48 | AA70: 45229 | AB70: -0.28 | AC70: 45229 | AD70: -0.25
A71: 27638 | B71: 5.7344048 | C71: 140.5381 | D71: 23.538095 | E71: =(C71/2000*48)+(D71/100*11)-B71 -> 0.2277 | F71: =D71/100*11/(B71+E71) -> 0.43427457 | G71: =F71-F70 -> -0.026752448 | J71: 5.57 | K71: 147.25 | L71: 24.3 | M71: =(K71/2000*44)+(L71/100*11)-J71 -> 0.3425 | N71: =L71/100*11/(J71+M71) -> 0.45209302 | O71: =J71-B71 -> -0.16440476 | P71: =K71-(C71+14) -> -7.2880952 | Q71: =L71-D71 -> 0.76190476 | Y71: 45230 | Z71: -0.48 | AA71: 45230 | AB71: -0.28 | AC71: 45230 | AD71: -0.25
A72: 27668 | B72: 5.2458765 | C72: 135.72174 | D72: 20.787826 | E72: =(C72/2000*48)+(D72/100*11)-B72 -> 0.29810609 | F72: =D72/100*11/(B72+E72) -> 0.41245816 | G72: =F72-F71 -> -0.021816408 | J72: 5.01 | L72: 21.4 | O72: =J72-B72 -> -0.23587652 | Q72: =L72-D72 -> 0.61217391 | Y72: 45231 | Z72: -0.63 | AA72: 45231 | AB72: -0.45 | AC72: 45231 | AD72: -0.38
A73: 27699 | B73: 4.8606579 | C73: 129.96842 | D73: 18.520526 | E73: =(C73/2000*48)+(D73/100*11)-B73 -> 0.29584211 | F73: =D73/100*11/(B73+E73) -> 0.39508541 | G73: =F73-F72 -> -0.017372755 | J73: 4.71 | L73: 18.9 | O73: =J73-B73 -> -0.15065789 | Q73: =L73-D73 -> 0.37947368 | Y73: 45232 | Z73: -0.63 | AA73: 45232 | AB73: -0.43 | AC73: 45232 | AD73: -0.38
A74: 27729 | B74: 4.6353571 | C74: 130.59524 | D74: 16.58619 | E74: =(C74/2000*48)+(D74/100*11)-B74 -> 0.32340952 | F74: =D74/100*11/(B74+E74) -> 0.36793039 | G74: =F74-F73 -> -0.027155016 | J74: 4.58 | L74: 16.8 | O74: =J74-B74 -> -0.055357143 | Q74: =L74-D74 -> 0.21380952 | Y74: 45233 | Z74: -0.63 | AA74: 45233 | AB74: -0.4 | AC74: 45233 | AD74: -0.38
A75: 27760 | B75: 4.7532738 | C75: 135.4 | D75: 16.390476 | E75: =(C75/2000*48)+(D75/100*11)-B75 -> 0.29927857 | F75: =D75/100*11/(B75+E75) -> 0.35683992 | G75: =F75-F74 -> -0.011090471 | J75: 4.64 | K75: 136.25 | L75: 16.2 | M75: =(K75/2000*44)+(L75/100*11)-J75 -> 0.1395 | N75: =L75/100*11/(J75+M75) -> 0.37284235 | O75: =J75-B75 -> -0.11327381 | P75: =K75-(C75+14) -> -13.15 | Q75: =L75-D75 -> -0.19047619 | Y75: 45236 | Z75: -0.63 | AA75: 45236 | AB75: -0.4 | AC75: 45236 | AD75: -0.38
A76: 27791 | B76: 4.7967105 | C76: 137.56316 | D76: 16.511579 | E76: =(C76/2000*48)+(D76/100*11)-B76 -> 0.32107895 | F76: =D76/100*11/(B76+E76) -> 0.35489418 | G76: =F76-F75 -> -0.0019457415 | J76: 4.75 | K76: 139.25 | L76: 16.3 | M76: =(K76/2000*44)+(L76/100*11)-J76 -> 0.1065 | N76: =L76/100*11/(J76+M76) -> 0.36919592 | O76: =J76-B76 -> -0.046710526 | P76: =K76-(C76+14) -> -12.313158 | Q76: =L76-D76 -> -0.21157895 | Y76: 45237 | Z76: -0.6 | AA76: 45237 | AB76: -0.4 | AC76: 45237 | AD76: -0.38
A77: 27820 | B77: 4.80375 | C77: 133.4087 | D77: 16.737826 | E77: =(C77/2000*48)+(D77/100*11)-B77 -> 0.23921957 | F77: =D77/100*11/(B77+E77) -> 0.36509458 | G77: =F77-F76 -> 0.010200406 | J77: 4.72 | K77: 135.6 | L77: 16.6 | M77: =(K77/2000*44)+(L77/100*11)-J77 -> 0.0892 | N77: =L77/100*11/(J77+M77) -> 0.37968893 | O77: =J77-B77 -> -0.08375 | P77: =K77-(C77+14) -> -11.808696 | Q77: =L77-D77 -> -0.13782609 | Y77: 45238 | Z77: -0.55 | AA77: 45238 | AB77: -0.4 | AC77: 45238 | AD77: -0.38
A78: 27851 | B78: 4.8030952 | C78: 133.18095 | D78: 16.357619 | E78: =(C78/2000*48)+(D78/100*11)-B78 -> 0.19258571 | F78: =D78/100*11/(B78+E78) -> 0.36017874 | G78: =F78-F77 -> -0.0049158379 | J78: 4.75 | K78: 136.4 | L78: 16.3 | M78: =(K78/2000*44)+(L78/100*11)-J78 -> 0.0438 | N78: =L78/100*11/(J78+M78) -> 0.37402478 | O78: =J78-B78 -> -0.053095238 | P78: =K78-(C78+14) -> -10.780952 | Q78: =L78-D78 -> -0.057619048 | Y78: 45239 | Z78: -0.55 | AA78: 45239 | AB78: -0.38 | AC78: 45239 | AD78: -0.4
A79: 27881 | B79: 5.3135625 | C79: 158.105 | D79: 16.231 | E79: =(C79/2000*48)+(D79/100*11)-B79 -> 0.2663675 | F79: =D79/100*11/(B79+E79) -> 0.31996996 | G79: =F79-F78 -> -0.040208781 | J79: 5.23 | K79: 161.8 | L79: 15.8 | M79: =(K79/2000*44)+(L79/100*11)-J79 -> 0.0676 | N79: =L79/100*11/(J79+M79) -> 0.32807309 | O79: =J79-B79 -> -0.0835625 | P79: =K79-(C79+14) -> -10.305 | Q79: =L79-D79 -> -0.431 | Y79: 45240 | Z79: -0.55 | AA79: 45240 | AB79: -0.38 | AC79: 45240 | AD79: -0.4
A80: 27912 | B80: 6.3502273 | C80: 192.89545 | D80: 18.286818 | E80: =(C80/2000*48)+(D80/100*11)-B80 -> 0.29081364 | F80: =D80/100*11/(B80+E80) -> 0.30289679 | G80: =F80-F79 -> -0.01707317 | J80: 6.23 | K80: 200.3 | L80: 17.6 | M80: =(K80/2000*44)+(L80/100*11)-J80 -> 0.1126 | N80: =L80/100*11/(J80+M80) -> 0.3052376 | O80: =J80-B80 -> -0.12022727 | P80: =K80-(C80+14) -> -6.5954545 | Q80: =L80-D80 -> -0.68681818 | Y80: 45243 | Z80: -0.58 | AA80: 45243 | AB80: -0.38 | AC80: 45243 | AD80: -0.4
A81: 27942 | B81: 6.8269643 | C81: 199.40476 | D81: 20.984286 | E81: =(C81/2000*48)+(D81/100*11)-B81 -> 0.26702143 | F81: =D81/100*11/(B81+E81) -> 0.32538428 | G81: =F81-F80 -> 0.022487485 | J81: 6.66 | K81: 207.9 | L81: 20.9 | M81: =(K81/2000*44)+(L81/100*11)-J81 -> 0.2128 | N81: =L81/100*11/(J81+M81) -> 0.33450704 | O81: =J81-B81 -> -0.16696429 | P81: =K81-(C81+14) -> -5.5047619 | Q81: =L81-D81 -> -0.084285714 | Y81: 45244 | Z81: -0.58 | AA81: 45244 | AB81: -0.38 | AC81: 45244 | AD81: -0.4
A82: 27973 | B82: 6.4123864 | C82: 183.32273 | D82: 20.586818 | E82: =(C82/2000*48)+(D82/100*11)-B82 -> 0.25190909 | F82: =D82/100*11/(B82+E82) -> 0.33980336 | G82: =F82-F81 -> 0.014419083 | J82: 6.31 | K82: 187.1 | L82: 20.4 | M82: =(K82/2000*44)+(L82/100*11)-J82 -> 0.0502 | N82: =L82/100*11/(J82+M82) -> 0.35281909 | O82: =J82-B82 -> -0.10238636 | P82: =K82-(C82+14) -> -10.222727 | Q82: =L82-D82 -> -0.18681818 | Y82: 45245 | Z82: -0.6 | AA82: 45245 | AB82: -0.38 | AC82: 45245 | AD82: -0.4
A83: 28004 | B83: 6.8102381 | C83: 187.35238 | D83: 22.649048 | E83: =(C83/2000*48)+(D83/100*11)-B83 -> 0.17761429 | F83: =D83/100*11/(B83+E83) -> 0.35653232 | G83: =F83-F82 -> 0.016728961 | J83: 6.59 | K83: 192.5 | L83: 22.5 | M83: =(K83/2000*44)+(L83/100*11)-J83 -> 0.12 | N83: =L83/100*11/(J83+M83) -> 0.36885246 | O83: =J83-B83 -> -0.2202381 | P83: =K83-(C83+14) -> -8.852381 | Q83: =L83-D83 -> -0.14904762 | Y83: 45246 | Z83: -0.63 | AA83: 45246 | AB83: -0.38 | AC83: 45246 | AD83: -0.4
A84: 28034 | B84: 6.4125 | C84: 182.65714 | D84: 21.148095 | E84: =(C84/2000*48)+(D84/100*11)-B84 -> 0.2975619 | F84: =D84/100*11/(B84+E84) -> 0.34668689 | G84: =F84-F83 -> -0.009845435 | J84: 6.22 | L84: 20.7 | O84: =J84-B84 -> -0.1925 | Q84: =L84-D84 -> -0.44809524 | Y84: 45247 | Z84: -0.63 | AA84: 45247 | AB84: -0.4 | AC84: 45247 | AD84: -0.4
A85: 28065 | B85: 6.683125 | C85: 186.59 | D85: 21.9715 | E85: =(C85/2000*48)+(D85/100*11)-B85 -> 0.2119 | F85: =D85/100*11/(B85+E85) -> 0.35052302 | G85: =F85-F84 -> 0.0038361346 | J85: 6.55 | L85: 21.8 | O85: =J85-B85 -> -0.133125 | Q85: =L85-D85 -> -0.1715 | Y85: 45250 | Z85: -0.63 | AA85: 45250 | AB85: -0.4 | AC85: 45250 | AD85: -0.4
A86: 28095 | B86: 6.9278571 | C86: 199.85714 | D86: 21.270952 | E86: =(C86/2000*48)+(D86/100*11)-B86 -> 0.20851905 | F86: =D86/100*11/(B86+E86) -> 0.32787015 | G86: =F86-F85 -> -0.022652868 | J86: 6.86 | L86: 21 | O86: =J86-B86 -> -0.067857143 | Q86: =L86-D86 -> -0.27095238 | Y86: 45251 | Z86: -0.59 | AA86: 45251 | AB86: -0.43 | AC86: 45251 | AD86: -0.4
A87: 28126 | B87: 7.2075595 | C87: 212.41905 | D87: 21.43619 | E87: =(C87/2000*48)+(D87/100*11)-B87 -> 0.24847857 | F87: =D87/100*11/(B87+E87) -> 0.31625119 | G87: =F87-F86 -> -0.01161896 | J87: 7.06 | L87: 20.9 | O87: =J87-B87 -> -0.14755952 | Q87: =L87-D87 -> -0.53619048 | Y87: 45252 | Z87: -0.59 | AA87: 45252 | AB87: -0.43 | AC87: 45252 | AD87: -0.4
A88: 28157 | B88: 7.3990789 | C88: 212.81579 | D88: 22.888947 | E88: =(C88/2000*48)+(D88/100*11)-B88 -> 0.22628421 | F88: =D88/100*11/(B88+E88) -> 0.33018548 | G88: =F88-F87 -> 0.013934288 | J88: 7.26 | K88: 230.4 | L88: 22.4 | M88: =(K88/2000*44)+(L88/100*11)-J88 -> 0.2728 | N88: =L88/100*11/(J88+M88) -> 0.3271028 | O88: =J88-B88 -> -0.13907895 | P88: =K88-(C88+14) -> 3.5842105 | Q88: =L88-D88 -> -0.48894737 | Y88: 45254 | Z88: -0.59 | AA88: 45254 | AB88: -0.43 | AC88: 45254 | AD88: -0.45
A89: 28185 | B89: 8.4590217 | C89: 238.15217 | D89: 26.801739 | E89: =(C89/2000*48)+(D89/100*11)-B89 -> 0.20482174 | F89: =D89/100*11/(B89+E89) -> 0.34028677 | G89: =F89-F88 -> 0.010101287 | J89: 8.25 | K89: 246.6 | L89: 26.5 | M89: =(K89/2000*44)+(L89/100*11)-J89 -> 0.0902 | N89: =L89/100*11/(J89+M89) -> 0.349512 | O89: =J89-B89 -> -0.20902174 | P89: =K89-(C89+14) -> -5.5521739 | Q89: =L89-D89 -> -0.30173913 | Y89: 45257 | Z89: -0.59 | AA89: 45257 | AB89: -0.43 | AC89: 45257 | AD89: -0.45
A90: 28216 | B90: 9.8885 | C90: 282.4 | D90: 29.5395 | E90: =(C90/2000*48)+(D90/100*11)-B90 -> 0.138445 | F90: =D90/100*11/(B90+E90) -> 0.32406132 | G90: =F90-F89 -> -0.016225452 | J90: 9.6 | K90: 299 | L90: 29.6 | M90: =(K90/2000*44)+(L90/100*11)-J90 -> 0.234 | N90: =L90/100*11/(J90+M90) -> 0.3310962 | O90: =J90-B90 -> -0.2885 | P90: =K90-(C90+14) -> 2.6 | Q90: =L90-D90 -> 0.0605 | Y90: 45258 | Z90: -0.59 | AA90: 45258 | AB90: -0.43 | AC90: 45258 | AD90: -0.45
A91: 28246 | B91: 9.545 | C91: 264.07 | D91: 31.2385 | E91: =(C91/2000*48)+(D91/100*11)-B91 -> 0.228915 | F91: =D91/100*11/(B91+E91) -> 0.35157202 | G91: =F91-F90 -> 0.027510699 | J91: 9.42 | K91: 283.5 | L91: 31.3 | M91: =(K91/2000*44)+(L91/100*11)-J91 -> 0.26 | N91: =L91/100*11/(J91+M91) -> 0.35568182 | O91: =J91-B91 -> -0.125 | P91: =K91-(C91+14) -> 5.43 | Q91: =L91-D91 -> 0.0615 | Y91: 45259 | Z91: -0.59 | AA91: 45259 | AB91: -0.43 | AC91: 45259 | AD91: -0.45
A92: 28277 | B92: 8.2791477 | C92: 224.43182 | D92: 28.175 | E92: =(C92/2000*48)+(D92/100*11)-B92 -> 0.20646591 | F92: =D92/100*11/(B92+E92) -> 0.36523581 | G92: =F92-F91 -> 0.013663798 | J92: 8.25 | K92: 247.1 | L92: 28.3 | M92: =(K92/2000*44)+(L92/100*11)-J92 -> 0.2992 | N92: =L92/100*11/(J92+M92) -> 0.36412764 | O92: =J92-B92 -> -0.029147727 | P92: =K92-(C92+14) -> 8.6681818 | Q92: =L92-D92 -> 0.125 | Y92: 45260 | Z92: -0.59 | AA92: 45260 | AB92: -0.43 | AC92: 45260 | AD92: -0.45
A93: 28307 | B93: 6.35725 | C93: 166.775 | D93: 23.2385 | E93: =(C93/2000*48)+(D93/100*11)-B93 -> 0.201585 | F93: =D93/100*11/(B93+E93) -> 0.38973918 | G93: =F93-F92 -> 0.02450337 | J93: 6.4 | K93: 182.75 | L93: 23.8 | M93: =(K93/2000*44)+(L93/100*11)-J93 -> 0.2385 | N93: =L93/100*11/(J93+M93) -> 0.3943662 | O93: =J93-B93 -> 0.04275 | P93: =K93-(C93+14) -> 1.975 | Q93: =L93-D93 -> 0.5615 | Y93: 45261 | Z93: -0.58 | AA93: 45261 | AB93: -0.39 | AC93: 45261 | AD93: -0.45
A94: 28338 | B94: 5.3902174 | C94: 142.16522 | D94: 20.181739 | E94: =(C94/2000*48)+(D94/100*11)-B94 -> 0.24173913 | F94: =D94/100*11/(B94+E94) -> 0.39417764 | G94: =F94-F93 -> 0.0044384515 | J94: 5.49 | K94: 160.9 | L94: 21.1 | M94: =(K94/2000*44)+(L94/100*11)-J94 -> 0.3708 | N94: =L94/100*11/(J94+M94) -> 0.39602102 | O94: =J94-B94 -> 0.099782609 | P94: =K94-(C94+14) -> 4.7347826 | Q94: =L94-D94 -> 0.91826087 | Y94: 45264 | Z94: -0.58 | AA94: 45264 | AB94: -0.39 | AC94: 45264 | AD94: -0.45
A95: 28369 | B95: 5.2639286 | C95: 138.29048 | D95: 18.634286 | E95: =(C95/2000*48)+(D95/100*11)-B95 -> 0.10481429 | F95: =D95/100*11/(B95+E95) -> 0.38179728 | G95: =F95-F94 -> -0.012380354 | J95: 5.16 | K95: 162.4 | L95: 19.2 | M95: =(K95/2000*44)+(L95/100*11)-J95 -> 0.5248 | N95: =L95/100*11/(J95+M95) -> 0.37151703 | O95: =J95-B95 -> -0.10392857 | P95: =K95-(C95+14) -> 10.109524 | Q95: =L95-D95 -> 0.56571429 | Y95: 45265 | Z95: -0.58 | AA95: 45265 | AB95: -0.39 | AC95: 45265 | AD95: -0.45
A96: 28399 | B96: 5.3108333 | C96: 143.95714 | D96: 18.341429 | E96: =(C96/2000*48)+(D96/100*11)-B96 -> 0.16169524 | F96: =D96/100*11/(B96+E96) -> 0.36867001 | G96: =F96-F95 -> -0.013127275 | J96: 5.07 | K96: 150.75 | L96: 18.8 | M96: =(K96/2000*44)+(L96/100*11)-J96 -> 0.3145 | N96: =L96/100*11/(J96+M96) -> 0.38406537 | O96: =J96-B96 -> -0.24083333 | P96: =K96-(C96+14) -> -7.2071429 | Q96: =L96-D96 -> 0.45857143 | Y96: 45266 | Z96: -0.58 | AA96: 45266 | AB96: -0.39 | AC96: 45266 | AD96: -0.5
A97: 28430 | B97: 5.9813095 | C97: 164.14762 | D97: 20.322857 | E97: =(C97/2000*48)+(D97/100*11)-B97 -> 0.19374762 | F97: =D97/100*11/(B97+E97) -> 0.36202325 | G97: =F97-F96 -> -0.0066467514 | J97: 5.84 | K97: 177.9 | L97: 21 | M97: =(K97/2000*44)+(L97/100*11)-J97 -> 0.3838 | N97: =L97/100*11/(J97+M97) -> 0.37115589 | O97: =J97-B97 -> -0.14130952 | P97: =K97-(C97+14) -> -0.24761905 | Q97: =L97-D97 -> 0.67714286 | Y97: 45267 | Z97: -0.53 | AA97: 45267 | AB97: -0.39 | AC97: 45267 | AD97: -0.5
A98: 28460 | B98: 5.9583333 | C98: 159.21905 | D98: 21.892857 | E98: =(C98/2000*48)+(D98/100*11)-B98 -> 0.2711381 | F98: =D98/100*11/(B98+E98) -> 0.38658405 | G98: =F98-F97 -> 0.024560794 | J98: 5.94 | K98: 175.1 | L98: 22.6 | M98: =(K98/2000*44)+(L98/100*11)-J98 -> 0.3982 | N98: =L98/100*11/(J98+M98) -> 0.39222492 | O98: =J98-B98 -> -0.018333333 | P98: =K98-(C98+14) -> 1.8809524 | Q98: =L98-D98 -> 0.70714286 | Y98: 45268 | Z98: -0.53 | AA98: 45268 | AB98: -0.39 | AC98: 45268 | AD98: -0.5
A99: 28491 | B99: 5.8259524 | C99: 157.60952 | D99: 20.557619 | E99: =(C99/2000*48)+(D99/100*11)-B99 -> 0.21801429 | F99: =D99/100*11/(B99+E99) -> 0.37414801 | G99: =F99-F98 -> -0.01243604 | J99: 5.73 | K99: 175.4 | L99: 20.9 | M99: =(K99/2000*44)+(L99/100*11)-J99 -> 0.4278 | N99: =L99/100*11/(J99+M99) -> 0.37334762 | O99: =J99-B99 -> -0.095952381 | P99: =K99-(C99+14) -> 3.7904762 | Q99: =L99-D99 -> 0.34238095 | Y99: 45271 | Z99: -0.53 | AA99: 45271 | AB99: -0.39 | AC99: 45271 | AD99: -0.5
... A115: 28976 | B115: 7.3698864 | C115: 194.93636 | D115: 26.156364 | E115: =(C115/2000*48)+(D115/100*11)-B115 -> 0.18578636 | F115: =D115/100*11/(B115+E115) -> 0.38079998 | G115: =F115-F114 -> -0.002894961 | J115: 7.21 | K115: 205 | L115: 26.3 | M115: =(K115/2000*44)+(L115/100*11)-J115 -> 0.193 | N115: =L115/100*11/(J115+M115) -> 0.39078752 | O115: =J115-B115 -> -0.15988636 | P115: =K115-(C115+14) -> -3.9363636 | Q115: =L115-D115 -> 0.14363636 | Y115: 45295 | Z115: -0.45 | AA115: 45295 | AB115: -0.48 | AC115: 45295 | AD115: -0.6
A116: 29007 | B116: 7.8071429 | C116: 211.29048 | D116: 27.09619 | E116: =(C116/2000*48)+(D116/100*11)-B116 -> 0.24440952 | F116: =D116/100*11/(B116+E116) -> 0.37018712 | G116: =F116-F115 -> -0.010612861 | J116: 7.68 | L116: 27.6 | O116: =J116-B116 -> -0.12714286 | Q116: =L116-D116 -> 0.50380952 | Y116: 45296 | Z116: -0.45 | AA116: 45296 | AB116: -0.5 | AC116: 45296 | AD116: -0.6
A117: 29037 | B117: 7.6385714 | C117: 203.8 | D117: 28.241429 | E117: =(C117/2000*48)+(D117/100*11)-B117 -> 0.35918571 | F117: =D117/100*11/(B117+E117) -> 0.38842854 | G117: =F117-F116 -> 0.018241426 | J117: 7.64 | K117: 220.9 | L117: 29.1 | M117: =(K117/2000*44)+(L117/100*11)-J117 -> 0.4208 | N117: =L117/100*11/(J117+M117) -> 0.39710699 | O117: =J117-B117 -> 0.0014285714 | P117: =K117-(C117+14) -> 3.1 | Q117: =L117-D117 -> 0.85857143 | Y117: 45299 | Z117: -0.45 | AA117: 45299 | AB117: -0.5 | AC117: 45299 | AD117: -0.6
A118: 29068 | B118: 7.1752174 | C118: 191.48261 | D118: 27.756087 | E118: =(C118/2000*48)+(D118/100*11)-B118 -> 0.47353478 | F118: =D118/100*11/(B118+E118) -> 0.39917224 | G118: =F118-F117 -> 0.010743702 | J118: 7.28 | K118: 205.25 | L118: 29.2 | M118: =(K118/2000*44)+(L118/100*11)-J118 -> 0.4475 | N118: =L118/100*11/(J118+M118) -> 0.41565836 | O118: =J118-B118 -> 0.10478261 | P118: =K118-(C118+14) -> -0.2326087 | Q118: =L118-D118 -> 1.443913 | Y118: 45300 | Z118: -0.4 | AA118: 45300 | AB118: -0.5 | AC118: 45300 | AD118: -0.6
A119: 29099 | B119: 7.1318421 | C119: 189.96316 | D119: 27.928421 | E119: =(C119/2000*48)+(D119/100*11)-B119 -> 0.4994 | F119: =D119/100*11/(B119+E119) -> 0.40257225 | G119: =F119-F118 -> 0.003400008 | J119: 7.04 | K119: 204.9 | L119: 30 | M119: =(K119/2000*44)+(L119/100*11)-J119 -> 0.7678 | N119: =L119/100*11/(J119+M119) -> 0.42265427 | O119: =J119-B119 -> -0.091842105 | P119: =K119-(C119+14) -> 0.93684211 | Q119: =L119-D119 -> 2.0715789 | Y119: 45301 | Z119: -0.4 | AA119: 45301 | AB119: -0.48 | AC119: 45301 | AD119: -0.6
A120: 29129 | B120: 6.7183696 | C120: 187.50435 | D120: 26.104783 | E120: =(C120/2000*48)+(D120/100*11)-B120 -> 0.65326087 | F120: =D120/100*11/(B120+E120) -> 0.38953745 | G120: =F120-F119 -> -0.013034806 | J120: 6.56 | K120: 197.8 | L120: 27.9 | M120: =(K120/2000*44)+(L120/100*11)-J120 -> 0.8606 | N120: =L120/100*11/(J120+M120) -> 0.41357842 | O120: =J120-B120 -> -0.15836957 | P120: =K120-(C120+14) -> -3.7043478 | Q120: =L120-D120 -> 1.7952174 | Y120: 45302 | Z120: -0.4 | AA120: 45302 | AB120: -0.48 | AC120: 45302 | AD120: -0.6
A121: 29160 | B121: 6.7734524 | C121: 190.67143 | D121: 26.449524 | E121: =(C121/2000*48)+(D121/100*11)-B121 -> 0.71210952 | F121: =D121/100*11/(B121+E121) -> 0.38867458 | G121: =F121-F120 -> -0.00086286664 | J121: 6.52 | K121: 197.4 | L121: 27.8 | M121: =(K121/2000*44)+(L121/100*11)-J121 -> 0.8808 | N121: =L121/100*11/(J121+M121) -> 0.41319857 | O121: =J121-B121 -> -0.25345238 | P121: =K121-(C121+14) -> -7.2714286 | Q121: =L121-D121 -> 1.3504762 | Y121: 45303 | Z121: -0.4 | AA121: 45303 | AB121: -0.48 | AC121: 45303 | AD121: -0.6
A122: 29190 | B122: 6.6360526 | C122: 189.8 | D122: 25.121579 | E122: =(C122/2000*48)+(D122/100*11)-B122 -> 0.68252105 | F122: =D122/100*11/(B122+E122) -> 0.37758364 | G122: =F122-F121 -> -0.01109094 | J122: 6.53 | K122: 205.2 | L122: 26.2 | M122: =(K122/2000*44)+(L122/100*11)-J122 -> 0.8664 | N122: =L122/100*11/(J122+M122) -> 0.38964902 | O122: =J122-B122 -> -0.10605263 | P122: =K122-(C122+14) -> 1.4 | Q122: =L122-D122 -> 1.0784211 | Y122: 45307 | Z122: -0.4 | AA122: 45307 | AB122: -0.48 | AC122: 45307 | AD122: -0.6
A123: 29221 | B123: 6.6205 | C123: 185.14 | D123: 23.8005 | E123: =(C123/2000*48)+(D123/100*11)-B123 -> 0.440915 | F123: =D123/100*11/(B123+E123) -> 0.37075501 | G123: =F123-F122 -> -0.0068286275 | J123: 6.36 | K123: 194.8 | L123: 23.6 | M123: =(K123/2000*44)+(L123/100*11)-J123 -> 0.5216 | N123: =L123/100*11/(J123+M123) -> 0.37723785 | O123: =J123-B123 -> -0.2605 | P123: =K123-(C123+14) -> -4.34 | Q123: =L123-D123 -> -0.2005 | Y123: 45308 | Z123: -0.4 | AA123: 45308 | AB123: -0.48 | AC123: 45308 | AD123: -0.6
A124: 29252 | B124: 6.568375 | C124: 179.86 | D124: 23.5315 | E124: =(C124/2000*48)+(D124/100*11)-B124 -> 0.33673 | F124: =D124/100*11/(B124+E124) -> 0.37486251 | G124: =F124-F123 -> 0.0041074996 | J124: 6.42 | K124: 189.25 | L124: 23.4 | M124: =(K124/2000*44)+(L124/100*11)-J124 -> 0.3175 | N124: =L124/100*11/(J124+M124) -> 0.38204082 | O124: =J124-B124 -> -0.148375 | P124: =K124-(C124+14) -> -4.61 | Q124: =L124-D124 -> -0.1315 | Y124: 45309 | Z124: -0.4 | AA124: 45309 | AB124: -0.48 | AC124: 45309 | AD124: -0.6
A125: 29281 | B125: 6.3165476 | C125: 173.35238 | D125: 22.398095 | E125: =(C125/2000*48)+(D125/100*11)-B125 -> 0.3077 | F125: =D125/100*11/(B125+E125) -> 0.37193514 | G125: =F125-F124 -> -0.0029273695 | J125: 6.07 | K125: 180.4 | L125: 22.1 | M125: =(K125/2000*44)+(L125/100*11)-J125 -> 0.3298 | N125: =L125/100*11/(J125+M125) -> 0.37985562 | O125: =J125-B125 -> -0.24654762 | P125: =K125-(C125+14) -> -6.952381 | Q125: =L125-D125 -> -0.29809524 | Y125: 45310 | Z125: -0.38 | AA125: 45310 | AB125: -0.48 | AC125: 45310 | AD125: -0.6
A126: 29312 | B126: 5.9378571 | C126: 164.38095 | D126: 20.463333 | E126: =(C126/2000*48)+(D126/100*11)-B126 -> 0.25825238 | F126: =D126/100*11/(B126+E126) -> 0.3632871 | G126: =F126-F125 -> -0.0086480406 | J126: 5.8 | K126: 168 | L126: 20.3 | M126: =(K126/2000*44)+(L126/100*11)-J126 -> 0.129 | N126: =L126/100*11/(J126+M126) -> 0.37662338 | O126: =J126-B126 -> -0.13785714 | P126: =K126-(C126+14) -> -10.380952 | Q126: =L126-D126 -> -0.16333333 | Y126: 45313 | Z126: -0.35 | AA126: 45313 | AB126: -0.48 | AC126: 45313 | AD126: -0.6
A127: 29342 | B127: 6.2483333 | C127: 173.69524 | D127: 21.303333 | E127: =(C127/2000*48)+(D127/100*11)-B127 -> 0.26371905 | F127: =D127/100*11/(B127+E127) -> 0.35985071 | G127: =F127-F126 -> -0.003436392 | J127: 6.04 | K127: 180.75 | L127: 20.8 | M127: =(K127/2000*44)+(L127/100*11)-J127 -> 0.2245 | N127: =L127/100*11/(J127+M127) -> 0.36523266 | O127: =J127-B127 -> -0.20833333 | P127: =K127-(C127+14) -> -6.9452381 | Q127: =L127-D127 -> -0.50333333 | Y127: 45314 | Z127: -0.35 | AA127: 45314 | AB127: -0.48 | AC127: 45314 | AD127: -0.6
A128: 29373 | B128: 6.3308333 | C128: 172.42381 | D128: 21.997619 | E128: =(C128/2000*48)+(D128/100*11)-B128 -> 0.22707619 | F128: =D128/100*11/(B128+E128) -> 0.3689801 | G128: =F128-F127 -> 0.0091293884 | J128: 6.1 | K128: 175.1 | L128: 21.6 | M128: =(K128/2000*44)+(L128/100*11)-J128 -> 0.1282 | N128: =L128/100*11/(J128+M128) -> 0.38149064 | O128: =J128-B128 -> -0.23083333 | P128: =K128-(C128+14) -> -11.32381 | Q128: =L128-D128 -> -0.39761905 | Y128: 45315 | Z128: -0.35 | AA128: 45315 | AB128: -0.48 | AC128: 45315 | AD128: -0.6
... A154: 30164 | B154: 5.7127273 | C154: 166.19545 | D154: 17.531818 | E154: =(C154/2000*48)+(D154/100*11)-B154 -> 0.20446364 | F154: =D154/100*11/(B154+E154) -> 0.32591478 | G154: =F154-F153 -> 0.0032913505 | J154: 5.73 | K154: 181.4 | L154: 17.86 | M154: =(K154/2000*44)+(L154/100*11)-J154 -> 0.2254 | N154: =L154/100*11/(J154+M154) -> 0.32988548 | O154: =J154-B154 -> 0.017272727 | P154: =K154-(C154+14) -> 1.2045455 | Q154: =L154-D154 -> 0.32818182 | Y154: 45352 | Z154: -0.33 | AA154: 45352 | AB154: -0.28 | AC154: 45352 | AD154: -0.63
A155: 30195 | B155: 5.4840476 | C155: 156.89524 | D155: 17.21619 | E155: =(C155/2000*48)+(D155/100*11)-B155 -> 0.17521905 | F155: =D155/100*11/(B155+E155) -> 0.33463363 | G155: =F155-F154 -> 0.0087188463 | J155: 5.4 | K155: 173.2 | L155: 17.42 | M155: =(K155/2000*44)+(L155/100*11)-J155 -> 0.3266 | N155: =L155/100*11/(J155+M155) -> 0.33461391 | O155: =J155-B155 -> -0.084047619 | P155: =K155-(C155+14) -> 2.3047619 | Q155: =L155-D155 -> 0.20380952 | U155: 5.22 | V155: =U155-B155 -> -0.26404762 | Y155: 45355 | Z155: -0.33 | AA155: 45355 | AB155: -0.28 | AC155: 45355 | AD155: -0.63
A156: 30225 | B156: 5.3245238 | C156: 157.82857 | D156: 17.135238 | E156: =(C156/2000*48)+(D156/100*11)-B156 -> 0.3482381 | F156: =D156/100*11/(B156+E156) -> 0.33226781 | G156: =F156-F155 -> -0.002365818 | J156: 5.26 | K156: 168.5 | L156: 17.37 | M156: =(K156/2000*44)+(L156/100*11)-J156 -> 0.3577 | N156: =L156/100*11/(J156+M156) -> 0.3401214 | O156: =J156-B156 -> -0.06452381 | P156: =K156-(C156+14) -> -3.3285714 | Q156: =L156-D156 -> 0.2347619 | U156: 5.06 | V156: =U156-B156 -> -0.26452381 | Y156: 45356 | Z156: -0.33 | AA156: 45356 | AB156: -0.28 | AC156: 45356 | AD156: -0.63
A157: 30256 | B157: 5.730625 | C157: 172.375 | D157: 17.0785 | E157: =(C157/2000*48)+(D157/100*11)-B157 -> 0.28501 | F157: =D157/100*11/(B157+E157) -> 0.31229205 | G157: =F157-F156 -> -0.01997576 | J157: 5.7 | K157: 185.2 | L157: 17.55 | M157: =(K157/2000*44)+(L157/100*11)-J157 -> 0.3049 | N157: =L157/100*11/(J157+M157) -> 0.32148745 | O157: =J157-B157 -> -0.030625 | P157: =K157-(C157+14) -> -1.175 | Q157: =L157-D157 -> 0.4715 | U157: 5.34 | V157: =U157-B157 -> -0.390625 | Y157: 45357 | Z157: -0.33 | AA157: 45357 | AB157: -0.28 | AC157: 45357 | AD157: -0.63
A158: 30286 | B158: 5.6716667 | C158: 173.56667 | D158: 16.587476 | E158: =(C158/2000*48)+(D158/100*11)-B158 -> 0.31855571 | F158: =D158/100*11/(B158+E158) -> 0.30460011 | G158: =F158-F157 -> -0.0076919448 | J158: 5.73 | K158: 190 | L158: 16.6 | M158: =(K158/2000*44)+(L158/100*11)-J158 -> 0.276 | N158: =L158/100*11/(J158+M158) -> 0.3040293 | O158: =J158-B158 -> 0.058333333 | P158: =K158-(C158+14) -> 2.4333333 | Q158: =L158-D158 -> 0.01252381 | U158: 5.46 | V158: =U158-B158 -> -0.21166667 | Y158: 45358 | Z158: -0.33 | AA158: 45358 | AB158: -0.28 | AC158: 45358 | AD158: -0.63
A159: 30317 | B159: 5.8970238 | C159: 179.22381 | D159: 16.947143 | E159: =(C159/2000*48)+(D159/100*11)-B159 -> 0.26853333 | F159: =D159/100*11/(B159+E159) -> 0.30235479 | G159: =F159-F158 -> -0.0022453208 | J159: 5.81 | K159: 191.75 | L159: 16.4 | M159: =(K159/2000*44)+(L159/100*11)-J159 -> 0.2125 | N159: =L159/100*11/(J159+M159) -> 0.29954338 | O159: =J159-B159 -> -0.08702381 | P159: =K159-(C159+14) -> -1.4738095 | Q159: =L159-D159 -> -0.54714286 | U159: 5.56 | V159: =U159-B159 -> -0.33702381 | Y159: 45359 | Z159: -0.33 | AA159: 45359 | AB159: -0.28 | AC159: 45359 | AD159: -0.63
A160: 30348 | B160: 5.9036842 | C160: 176.98421 | D160: 17.211579 | E160: =(C160/2000*48)+(D160/100*11)-B160 -> 0.23721053 | F160: =D160/100*11/(B160+E160) -> 0.30830584 | G160: =F160-F159 -> 0.0059510492 | J160: 5.86 | K160: 189.25 | L160: 17.25 | M160: =(K160/2000*44)+(L160/100*11)-J160 -> 0.201 | N160: =L160/100*11/(J160+M160) -> 0.31306715 | O160: =J160-B160 -> -0.043684211 | P160: =K160-(C160+14) -> -1.7342105 | Q160: =L160-D160 -> 0.038421053 | U160: 5.66 | V160: =U160-B160 -> -0.24368421 | Y160: 45362 | Z160: -0.33 | AA160: 45362 | AB160: -0.32 | AC160: 45362 | AD160: -0.63
A161: 30376 | B161: 6.0533696 | C161: 180.62609 | D161: 17.532609 | E161: =(C161/2000*48)+(D161/100*11)-B161 -> 0.21024348 | F161: =D161/100*11/(B161+E161) -> 0.30790327 | G161: =F161-F160 -> -0.00040256283 | J161: 5.98 | K161: 192.7 | L161: 17.7 | M161: =(K161/2000*44)+(L161/100*11)-J161 -> 0.2064 | N161: =L161/100*11/(J161+M161) -> 0.31472262 | O161: =J161-B161 -> -0.073369565 | P161: =K161-(C161+14) -> -1.926087 | Q161: =L161-D161 -> 0.1673913 | U161: 5.82 | V161: =U161-B161 -> -0.23336957 | Y161: 45363 | Z161: -0.33 | AA161: 45363 | AB161: -0.3 | AC161: 45363 | AD161: -0.63
A162: 30407 | B162: 6.362125 | C162: 188.665 | D162: 19.0085 | E162: =(C162/2000*48)+(D162/100*11)-B162 -> 0.25677 | F162: =D162/100*11/(B162+E162) -> 0.31590394 | G162: =F162-F161 -> 0.0080006657 | J162: 6.35 | K162: 203.4 | L162: 19.35 | M162: =(K162/2000*44)+(L162/100*11)-J162 -> 0.2533 | N162: =L162/100*11/(J162+M162) -> 0.32233883 | O162: =J162-B162 -> -0.012125 | P162: =K162-(C162+14) -> 0.735 | Q162: =L162-D162 -> 0.3415 | U162: 6.09 | V162: =U162-B162 -> -0.272125 | Y162: 45364 | Z162: -0.38 | AA162: 45364 | AB162: -0.3 | AC162: 45364 | AD162: -0.63
A163: 30437 | B163: 6.3085714 | C163: 184.03333 | D163: 19.400952 | E163: =(C163/2000*48)+(D163/100*11)-B163 -> 0.24233333 | F163: =D163/100*11/(B163+E163) -> 0.32577252 | G163: =F163-F162 -> 0.0098685828 | J163: 6.27 | K163: 201.9 | L163: 19.75 | M163: =(K163/2000*44)+(L163/100*11)-J163 -> 0.3443 | N163: =L163/100*11/(J163+M163) -> 0.32845501 | O163: =J163-B163 -> -0.038571429 | P163: =K163-(C163+14) -> 3.8666667 | Q163: =L163-D163 -> 0.34904762 | U163: 6.06 | V163: =U163-B163 -> -0.24857143 | Y163: 45365 | Z163: -0.39 | AA163: 45365 | AB163: -0.3 | AC163: 45365 | AD163: -0.63
A164: 30468 | B164: 6.0225 | C164: 174.71364 | D164: 18.961818 | E164: =(C164/2000*48)+(D164/100*11)-B164 -> 0.25642727 | F164: =D164/100*11/(B164+E164) -> 0.3321905 | G164: =F164-F163 -> 0.0064179801 | J164: 6.06 | K164: 190.5 | L164: 19.4 | M164: =(K164/2000*44)+(L164/100*11)-J164 -> 0.265 | N164: =L164/100*11/(J164+M164) -> 0.3373913 | O164: =J164-B164 -> 0.0375 | P164: =K164-(C164+14) -> 1.7863636 | Q164: =L164-D164 -> 0.43818182 | U164: 5.9 | V164: =U164-B164 -> -0.1225 | Y164: 45366 | Z164: -0.39 | AA164: 45366 | AB164: -0.3 | AC164: 45366 | AD164: -0.63
A165: 30498 | B165: 6.619125 | C165: 189.905 | D165: 21.3135 | E165: =(C165/2000*48)+(D165/100*11)-B165 -> 0.28308 | F165: =D165/100*11/(B165+E165) -> 0.33967189 | G165: =F165-F164 -> 0.0074813859 | J165: 6.59 | K165: 204.6 | L165: 21.61 | M165: =(K165/2000*44)+(L165/100*11)-J165 -> 0.2883 | N165: =L165/100*11/(J165+M165) -> 0.34559411 | O165: =J165-B165 -> -0.029125 | P165: =K165-(C165+14) -> 0.695 | Q165: =L165-D165 -> 0.2965 | U165: 6.27 | V165: =U165-B165 -> -0.349125 | Y165: 45369 | Z165: -0.39 | AA165: 45369 | AB165: -0.3 | AC165: 45369 | AD165: -0.63
A166: 30529 | B166: 8.5006522 | C166: 236.58696 | D166: 29.816957 | E166: =(C166/2000*48)+(D166/100*11)-B166 -> 0.4573 | F166: =D166/100*11/(B166+E166) -> 0.36614007 | G166: =F166-F165 -> 0.02646818 | J166: 8.46 | K166: 246.2 | L166: 30.16 | M166: =(K166/2000*44)+(L166/100*11)-J166 -> 0.274 | N166: =L166/100*11/(J166+M166) -> 0.37984887 | O166: =J166-B166 -> -0.040652174 | P166: =K166-(C166+14) -> -4.3869565 | Q166: =L166-D166 -> 0.34304348 | U166: 7.57 | V166: =U166-B166 -> -0.93065217 | Y166: 45370 | Z166: -0.39 | AA166: 45370 | AB166: -0.28 | AC166: 45370 | AD166: -0.63
... A274: 33817 | B274: 5.500119 | C274: 173.04286 | D274: 18.424286 | E274: =(C274/2000*48)+(D274/100*11)-B274 -> 0.67958095 | F274: =D274/100*11/(B274+E274) -> 0.32795628 | G274: =F274-F273 -> -0.0078888536 | J274: 5.64 | K274: 186 | L274: 17.87 | M274: =(K274/2000*44)+(L274/100*11)-J274 -> 0.4177 | N274: =L274/100*11/(J274+M274) -> 0.3244961 | O274: =J274-B274 -> 0.13988095 | P274: =K274-(C274+14) -> -1.0428571 | Q274: =L274-D274 -> -0.55428571 | U274: 5.4 | V274: =U274-B274 -> -0.10011905 | Y274: 45526 | Z274: -0.2 | AA274: 45526 | AB274: -0.41 | AC274: 45526 | AD274: -0.08
A275: 33848 | B275: 5.474881 | C275: 188.68571 | D275: 18.820476 | E275: =(C275/2000*44)+(D275/100*11)-B275 -> 0.74645714 | F275: =D275/100*11/(B275+E275) -> 0.33276642 | G275: =F275-F274 -> 0.0048101352 | J275: 5.54 | K275: 187 | L275: 18.28 | M275: =(K275/2000*44)+(L275/100*11)-J275 -> 0.5848 | N275: =L275/100*11/(J275+M275) -> 0.3283046 | O275: =J275-B275 -> 0.065119048 | P275: =K275-C275 -> -1.6857143 | Q275: =L275-D275 -> -0.54047619 | U275: 5.36 | V275: =U275-B275 -> -0.11488095 | Y275: 45527 | Z275: -0.2 | AA275: 45527 | AB275: -0.48 | AC275: 45527 | AD275: -0.08
A276: 33878 | B276: 5.3793182 | C276: 182.38182 | D276: 18.887273 | E276: =(C276/2000*44)+(D276/100*11)-B276 -> 0.71068182 | F276: =D276/100*11/(B276+E276) -> 0.34114943 | G276: =F276-F275 -> 0.0083830092 | J276: 5.35 | K276: 180.6 | L276: 18.36 | M276: =(K276/2000*44)+(L276/100*11)-J276 -> 0.6428 | N276: =L276/100*11/(J276+M276) -> 0.33700441 | O276: =J276-B276 -> -0.029318182 | P276: =K276-C276 -> -1.7818182 | Q276: =L276-D276 -> -0.52727273 | U276: 5.26 | V276: =U276-B276 -> -0.11931818 | Y276: 45530 | Z276: -0.3 | AA276: 45530 | AB276: -0.43 | AC276: 45530 | AD276: -0.1
A277: 33909 | B277: 5.597 | C277: 180.645 | D277: 20.16 | E277: =(C277/2000*44)+(D277/100*11)-B277 -> 0.59479 | F277: =D277/100*11/(B277+E277) -> 0.35815168 | G277: =F277-F276 -> 0.017002256 | J277: 5.6 | K277: 181.9 | L277: 20.1 | M277: =(K277/2000*44)+(L277/100*11)-J277 -> 0.6128 | N277: =L277/100*11/(J277+M277) -> 0.35587819 | O277: =J277-B277 -> 0.003 | P277: =K277-C277 -> 1.255 | Q277: =L277-D277 -> -0.06 | U277: 5.36 | V277: =U277-B277 -> -0.237 | Y277: 45531 | Z277: -0.3 | AA277: 45531 | AB277: -0.43 | AC277: 45531 | AD277: -0.1
A278: 33939 | B278: 5.6848864 | C278: 184.95 | D278: 20.598636 | E278: =(C278/2000*44)+(D278/100*11)-B278 -> 0.64986364 | F278: =D278/100*11/(B278+E278) -> 0.35768578 | G278: =F278-F277 -> -0.00046590069 | J278: 5.72 | K278: 187.6 | L278: 20.52 | M278: =(K278/2000*44)+(L278/100*11)-J278 -> 0.6644 | N278: =L278/100*11/(J278+M278) -> 0.35354928 | O278: =J278-B278 -> 0.035113636 | P278: =K278-C278 -> 2.65 | Q278: =L278-D278 -> -0.078636364 | U278: 5.46 | V278: =U278-B278 -> -0.22488636 | Y278: 45532 | Z278: -0.45 | AA278: 45532 | AB278: -0.43 | AC278: 45532 | AD278: -0.1
A279: 33970 | B279: 5.7885 | C279: 183.46 | D279: 21.3475 | E279: =(C279/2000*44)+(D279/100*11)-B279 -> 0.595845 | F279: =D279/100*11/(B279+E279) -> 0.36780985 | G279: =F279-F278 -> 0.010124073 | J279: 5.82 | K279: 188.75 | L279: 21.23 | M279: =(K279/2000*44)+(L279/100*11)-J279 -> 0.6678 | N279: =L279/100*11/(J279+M279) -> 0.35995253 | O279: =J279-B279 -> 0.0315 | P279: =K279-C279 -> 5.29 | Q279: =L279-D279 -> -0.1175 | U279: 5.58 | V279: =U279-B279 -> -0.2085 | Y279: 45533 | Z279: -0.45 | AA279: 45533 | AB279: -0.43 | AC279: 45533 | AD279: -0.08
A280: 34001 | B280: 5.7153947 | C280: 177.78421 | D280: 20.723158 | E280: =(C280/2000*44)+(D280/100*11)-B280 -> 0.47540526 | F280: =D280/100*11/(B280+E280) -> 0.36821531 | G280: =F280-F279 -> 0.00040546077 | J280: 5.75 | K280: 179.9 | L280: 20.72 | M280: =(K280/2000*44)+(L280/100*11)-J280 -> 0.487 | N280: =L280/100*11/(J280+M280) -> 0.3654321 | O280: =J280-B280 -> 0.034605263 | P280: =K280-C280 -> 2.1157895 | Q280: =L280-D280 -> -0.0031578947 | U280: 5.56 | V280: =U280-B280 -> -0.15539474 | Y280: 45534 | Z280: -0.45 | AA280: 45534 | AB280: -0.48 | AC280: 45534 | AD280: -0.08
A281: 34029 | B281: 5.8428261 | C281: 181.99565 | D281: 21.138696 | E281: =(C281/2000*44)+(D281/100*11)-B281 -> 0.48633478 | F281: =D281/100*11/(B281+E281) -> 0.36738781 | G281: =F281-F280 -> -0.00082750903 | J281: 5.87 | K281: 183.6 | L281: 21 | M281: =(K281/2000*44)+(L281/100*11)-J281 -> 0.4792 | N281: =L281/100*11/(J281+M281) -> 0.36382536 | O281: =J281-B281 -> 0.027173913 | P281: =K281-C281 -> 1.6043478 | Q281: =L281-D281 -> -0.13869565 | U281: 5.65 | V281: =U281-B281 -> -0.19282609 | Y281: 45538 | Z281: -0.53 | AA281: 45538 | AB281: -0.53 | AC281: 45538 | AD281: -0.08
A282: 34060 | B282: 5.9240476 | C282: 185.30952 | D282: 21.24381 | E282: =(C282/2000*44)+(D282/100*11)-B282 -> 0.48958095 | F282: =D282/100*11/(B282+E282) -> 0.3643521 | G282: =F282-F281 -> -0.003035704 | J282: 5.97 | K282: 187.4 | L282: 21.24 | M282: =(K282/2000*44)+(L282/100*11)-J282 -> 0.4892 | N282: =L282/100*11/(J282+M282) -> 0.36171662 | O282: =J282-B282 -> 0.045952381 | P282: =K282-C282 -> 2.0904762 | Q282: =L282-D282 -> -0.0038095238 | U282: 5.73 | V282: =U282-B282 -> -0.19404762 | Y282: 45539 | Z282: -0.53 | AA282: 45539 | AB282: -0.53 | AC282: 45539 | AD282: -0.08
A283: 34090 | B283: 6.028375 | C283: 191.17 | D283: 21.3165 | E283: =(C283/2000*44)+(D283/100*11)-B283 -> 0.52218 | F283: =D283/100*11/(B283+E283) -> 0.35795669 | G283: =F283-F282 -> -0.0063954092 | J283: 6.07 | K283: 193.25 | L283: 21.15 | M283: =(K283/2000*44)+(L283/100*11)-J283 -> 0.508 | N283: =L283/100*11/(J283+M283) -> 0.35367893 | O283: =J283-B283 -> 0.041625 | P283: =K283-C283 -> 2.08 | Q283: =L283-D283 -> -0.1665 | U283: 5.81 | V283: =U283-B283 -> -0.218375 | Y283: 45540 | Z283: -0.53 | AA283: 45540 | AB283: -0.53 | AC283: 45540 | AD283: -0.08
A284: 34121 | B284: 6.0390909 | C284: 190.98636 | D284: 21.334545 | E284: =(C284/2000*44)+(D284/100*11)-B284 -> 0.50940909 | F284: =D284/100*11/(B284+E284) -> 0.35837215 | G284: =F284-F283 -> 0.00041545407 | J284: 6.06 | K284: 193.1 | L284: 21.3 | M284: =(K284/2000*44)+(L284/100*11)-J284 -> 0.5312 | N284: =L284/100*11/(J284+M284) -> 0.35547397 | O284: =J284-B284 -> 0.020909091 | P284: =K284-C284 -> 2.1136364 | Q284: =L284-D284 -> -0.034545455 | U284: 5.9 | V284: =U284-B284 -> -0.13909091 | Y284: 45541 | Z284: -0.53 | AA284: 45541 | AB284: -0.53 | AC284: 45541 | AD284: -0.08
A285: 34151 | B285: 7.0463095 | C285: 225.25714 | D285: 24.271905 | E285: =(C285/2000*44)+(D285/100*11)-B285 -> 0.57925714 | F285: =D285/100*11/(B285+E285) -> 0.35012605 | G285: =F285-F284 -> -0.0082460979 | J285: 6.89 | K285: 229.9 | L285: 24.13 | M285: =(K285/2000*44)+(L285/100*11)-J285 -> 0.8221 | N285: =L285/100*11/(J285+M285) -> 0.34417344 | O285: =J285-B285 -> -0.15630952 | P285: =K285-C285 -> 4.6428571 | Q285: =L285-D285 -> -0.14190476 | U285: 6.56 | V285: =U285-B285 -> -0.48630952 | Y285: 45544 | Z285: -0.63 | AA285: 45544 | AB285: -0.53 | AC285: 45544 | AD285: 0
A286: 34182 | B286: 6.7131818 | C286: 215.10909 | D286: 23.618636 | E286: =(C286/2000*44)+(D286/100*11)-B286 -> 0.61726818 | F286: =D286/100*11/(B286+E286) -> 0.3544189 | G286: =F286-F285 -> 0.0042928481 | J286: 6.79 | K286: 219.1 | L286: 23.47 | M286: =(K286/2000*44)+(L286/100*11)-J286 -> 0.6119 | N286: =L286/100*11/(J286+M286) -> 0.34878882 | O286: =J286-B286 -> 0.076818182 | P286: =K286-C286 -> 3.9909091 | Q286: =L286-D286 -> -0.14863636 | U286: 6.56 | V286: =U286-B286 -> -0.15318182 | Y286: 45545 | Z286: -0.7 | AA286: 45545 | AB286: -0.5 | AC286: 45545 | AD286: 0
... A370: 36739 | B370: 4.5770652 | C370: 154.7913 | D370: 15.328261 | E370: =(C370/2000*44)+(D370/100*11)-B370 -> 0.51445217 | F370: =D370/100*11/(B370+E370) -> 0.33116035 | G370: =F370-F369 -> -0.00028700718 | J370: 4.63 | K370: 157.45 | L370: 14.34 | M370: =(K370/2000*44)+(L370/100*11)-J370 -> 0.4113 | N370: =L370/100*11/(J370+M370) -> 0.31289548 | O370: =J370-B370 -> 0.052934783 | P370: =K370-C370 -> 2.6586957 | Q370: =L370-D370 -> -0.98826087 | U370: 4.45 | V370: =U370-B370 -> -0.12706522 | Y370: 45666 | Z370: -0.21 | AA370: 45666 | AB370: -0.38 | AC370: 45666 | AD370: -0.4
A371: 36770 | B371: ='[4]Monthly Prices'!$CF11 -> #DIV/0! | C371: 169.645 | D371: 15.497 | E371: =(C371/2000*44)+(D371/100*11)-B371 -> #DIV/0! | F371: =D371/100*11/(B371+E371) -> #DIV/0! | G371: =F371-F370 -> #DIV/0! | J371: 4.84 | K371: 174.6 | L371: 14.24 | M371: =(K371/2000*44)+(L371/100*11)-J371 -> 0.5676 | N371: =L371/100*11/(J371+M371) -> 0.2896664 | O371: =J371-B371 -> #DIV/0! | P371: =K371-C371 -> 4.955 | Q371: =L371-D371 -> -1.257 | U371: 4.59 | V371: =U371-B371 -> #DIV/0! | Y371: 45667 | Z371: -0.21 | AA371: 45667 | AB371: -0.38 | AC371: 45667 | AD371: -0.4
A372: 36800 | B372: ='[4]Monthly Prices'!$CF12 -> #DIV/0! | C372: 167.76818 | D372: 15.067727 | E372: =(C372/2000*44)+(D372/100*11)-B372 -> #DIV/0! | F372: =D372/100*11/(B372+E372) -> #DIV/0! | G372: =F372-F371 -> #DIV/0! | J372: 4.68 | K372: 171.52 | L372: 13.51 | M372: =(K372/2000*44)+(L372/100*11)-J372 -> 0.57954 | N372: =L372/100*11/(J372+M372) -> 0.28255323 | O372: =J372-B372 -> #DIV/0! | P372: =K372-C372 -> 3.7518182 | Q372: =L372-D372 -> -1.5577273 | U372: 4.45 | V372: =U372-B372 -> #DIV/0! | Y372: 45670 | Z372: -0.21 | AA372: 45670 | AB372: -0.38 | AC372: 45670 | AD372: -0.43
A373: 36831 | B373: ='[4]Monthly Prices'!$CF13 -> #DIV/0! | C373: 176.28571 | D373: 14.992381 | E373: =(C373/2000*44)+(D373/100*11)-B373 -> #DIV/0! | F373: =D373/100*11/(B373+E373) -> #DIV/0! | G373: =F373-F372 -> #DIV/0! | J373: 4.83 | K373: 179.95 | L373: 13.37 | M373: =(K373/2000*44)+(L373/100*11)-J373 -> 0.5996 | N373: =L373/100*11/(J373+M373) -> 0.2708671 | O373: =J373-B373 -> #DIV/0! | P373: =K373-C373 -> 3.6642857 | Q373: =L373-D373 -> -1.622381 | U373: 4.55 | V373: =U373-B373 -> #DIV/0! | Y373: 45671 | Z373: -0.23 | AA373: 45671 | AB373: -0.38 | AC373: 45671 | AD373: -0.45
A374: 36861 | B374: ='[4]Monthly Prices'!$CF14 -> #DIV/0! | C374: 191.065 | D374: 14.9915 | E374: =(C374/2000*44)+(D374/100*11)-B374 -> #DIV/0! | F374: =D374/100*11/(B374+E374) -> #DIV/0! | G374: =F374-F373 -> #DIV/0! | J374: 5.06 | K374: 195.65 | L374: 13.12 | M374: =(K374/2000*44)+(L374/100*11)-J374 -> 0.6875 | N374: =L374/100*11/(J374+M374) -> 0.25110048 | O374: =J374-B374 -> #DIV/0! | P374: =K374-C374 -> 4.585 | Q374: =L374-D374 -> -1.8715 | U374: 4.78 | V374: =U374-B374 -> #DIV/0! | Y374: 45672 | Z374: -0.23 | AA374: 45672 | AB374: -0.38 | AC374: 45672 | AD374: -0.45
A375: 36892 | B375: ='[4]Monthly Prices'!$CF15 -> #DIV/0! | C375: 177.41905 | D375: 14.708095 | E375: =(C375/2000*44)+(D375/100*11)-B375 -> #DIV/0! | F375: =D375/100*11/(B375+E375) -> #DIV/0! | G375: =F375-F374 -> #DIV/0! | J375: 4.78 | K375: 183.24 | L375: 12.54 | M375: =(K375/2000*44)+(L375/100*11)-J375 -> 0.63068 | N375: =L375/100*11/(J375+M375) -> 0.25494023 | O375: =J375-B375 -> #DIV/0! | P375: =K375-C375 -> 5.8209524 | Q375: =L375-D375 -> -2.1680952 | U375: 4.68 | V375: =U375-B375 -> #DIV/0! | Y375: 45673 | Z375: -0.23 | AA375: 45673 | AB375: -0.38 | AC375: 45673 | AD375: -0.45 | AG375: ='[6]Monthly Palm Oil'!$D2 -> 1142.1765 | AH375: ='[6]Monthly Palm Oil'!$X2 -> 13.634134 | AI375: =D377-AH375 -> 2.4613202
A376: 36923 | B376: ='[4]Monthly Prices'!$CF16 -> #DIV/0! | C376: 162.12105 | D376: 14.755263 | E376: =(C376/2000*44)+(D376/100*11)-B376 -> #DIV/0! | F376: =D376/100*11/(B376+E376) -> #DIV/0! | G376: =F376-F375 -> #DIV/0! | J376: 4.57 | K376: 166.08 | L376: 12.38 | M376: =(K376/2000*44)+(L376/100*11)-J376 -> 0.44556 | N376: =L376/100*11/(J376+M376) -> 0.27151505 | O376: =J376-B376 -> #DIV/0! | P376: =K376-C376 -> 3.9589474 | Q376: =L376-D376 -> -2.3752632 | U376: 4.46 | V376: =U376-B376 -> #DIV/0! | Y376: 45674 | Z376: -0.23 | AA376: 45674 | AB376: -0.38 | AC376: 45674 | AD376: -0.45 | AG376: ='[6]Monthly Palm Oil'!$D3 -> 1060.9412 | AH376: ='[6]Monthly Palm Oil'!$X3 -> 12.664508 | AI376: =D378-AH376 -> 2.4824922
A377: 36951 | B377: ='[4]Monthly Prices'!$CF17 -> #DIV/0! | C377: 153.43636 | D377: 16.095455 | E377: =(C377/2000*44)+(D377/100*11)-B377 -> #DIV/0! | F377: =D377/100*11/(B377+E377) -> #DIV/0! | G377: =F377-F376 -> #DIV/0! | J377: 4.51 | K377: 156.32 | L377: 13.91 | M377: =(K377/2000*44)+(L377/100*11)-J377 -> 0.45914 | N377: =L377/100*11/(J377+M377) -> 0.30792049 | O377: =J377-B377 -> #DIV/0! | P377: =K377-C377 -> 2.8836364 | Q377: =L377-D377 -> -2.1854545 | U377: 4.39 | V377: =U377-B377 -> #DIV/0! | Y377: 45678 | Z377: -0.23 | AA377: 45678 | AB377: -0.38 | AC377: 45678 | AD377: -0.45 | AG377: ='[6]Monthly Palm Oil'!$D4 -> 1124.0455 | AH377: ='[6]Monthly Palm Oil'!$X4 -> 13.417831 | AI377: =D379-AH377 -> 1.3665166
A378: 36982 | B378: ='[4]Monthly Prices'!$CF18 -> #DIV/0! | C378: 153.335 | D378: 15.147 | E378: =(C378/2000*44)+(D378/100*11)-B378 -> #DIV/0! | F378: =D378/100*11/(B378+E378) -> #DIV/0! | G378: =F378-F377 -> #DIV/0! | J378: 4.41 | K378: 158.47 | L378: 13.53 | M378: =(K378/2000*44)+(L378/100*11)-J378 -> 0.56464 | N378: =L378/100*11/(J378+M378) -> 0.29917743 | O378: =J378-B378 -> #DIV/0! | P378: =K378-C378 -> 5.135 | Q378: =L378-D378 -> -1.617 | U378: 4.22 | V378: =U378-B378 -> #DIV/0! | Y378: 45679 | Z378: -0.23 | AA378: 45679 | AB378: -0.38 | AC378: 45679 | AD378: -0.45 | AG378: ='[6]Monthly Palm Oil'!$D5 -> 1205.2222 | AH378: ='[6]Monthly Palm Oil'!$X5 -> 14.387125 | AI378: =D380-AH378 -> 0.69192222
A379: 37012 | B379: ='[4]Monthly Prices'!$CF19 -> #DIV/0! | C379: 159.81364 | D379: 14.784348 | E379: =(C379/2000*44)+(D379/100*11)-B379 -> #DIV/0! | F379: =D379/100*11/(B379+E379) -> #DIV/0! | G379: =F379-F378 -> #DIV/0! | J379: 4.57 | K379: 165.14 | L379: 13.53 | M379: =(K379/2000*44)+(L379/100*11)-J379 -> 0.55138 | N379: =L379/100*11/(J379+M379) -> 0.29060527 | O379: =J379-B379 -> #DIV/0! | P379: =K379-C379 -> 5.3263636 | Q379: =L379-D379 -> -1.2543478 | U379: 4.33 | V379: =U379-B379 -> #DIV/0! | Y379: 45680 | Z379: -0.21 | AA379: 45680 | AB379: -0.38 | AC379: 45680 | AD379: -0.45 | AG379: ='[6]Monthly Palm Oil'!$D6 -> 1085.4 | AH379: ='[6]Monthly Palm Oil'!$X6 -> 12.956564 | AI379: =D381-AH379 -> 4.4867694
...
