Workbook

Sheet Balance Sheet Data
A1: US SOYBEAN BALANCE SHEET (million bushels/million acres)
B2: ='[1]Soy Complex'!K$2 -> 0 | C2: ='[1]Soy Complex'!L$2 -> 0 | D2: ='[1]Soy Complex'!M$2 -> 0 | E2: ='[1]Soy Complex'!N$2 -> 0 | F2: ='[1]Soy Complex'!O$2 -> 0 | G2: ='[1]Soy Complex'!P$2 -> 0 | H2: ='[1]Soy Complex'!Q$2 -> 0 | I2: ='[1]Soy Complex'!R$2 -> 0 | ... BB2: ='[1]Soy Complex'!BK$2 -> 0
A3: Planted Acres | B3: 42.534 | C3: 43.082 | D3: 43.476 | E3: 46.866 | F3: 56.549 | G3: 52.479 | H3: 54.59 | I3: 50.269 | J3: 58.978 | K3: 64.708 | L3: 71.411 | M3: 69.93 | N3: 67.543 | O3: 70.884 | P3: 63.779 | Q3: 67.755 | R3: 63.145 | S3: 60.405 | T3: 58.18 | U3: 58.84 | V3: 60.82 | W3: 57.795 | X3: 59.18 | Y3: 59.18 | Z3: 60.085 | AA3: 61.62 | AB3: 62.495 | AC3: 64.195 | AD3: 70.005 | AE3: 72.025 | AF3: 73.73 | AG3: 74.266 | AH3: 74.075 | AI3: 73.963 | AJ3: 73.404 | AK3: 75.208 | AL3: 72.032 | AM3: 75.522 | AN3: 64.741 | AO3: ='[1]Soy Complex'!AX$4 -> 75.718 | AP3: ='[1]Soy Complex'!AY$4 -> 77.451 | AQ3: ='[1]Soy Complex'!AZ$4 -> 77.404 | AR3: ='[1]Soy Complex'!BA$4 -> 75.046 | AS3: ='[1]Soy Complex'!BB$4 -> 77.198 | AT3: ='[1]Soy Complex'!BC$4 -> 76.84 | AU3: ='[1]Soy Complex'!BD$4 -> 83.276 | AV3: ='[1]Soy Complex'!BE$4 -> 82.65 | ... BB3: ='[1]Soy Complex'!BK$4 -> 87.195
A4: Harvested Acres | B4: 41.337 | C4: 42.249 | D4: 42.705 | E4: 45.683 | F4: 55.667 | G4: 51.341 | H4: 53.617 | I4: 49.401 | J4: 57.83 | K4: 63.663 | L4: 70.343 | M4: 67.813 | N4: 66.163 | O4: 69.442 | P4: 62.525 | Q4: 66.113 | R4: 61.599 | S4: 58.312 | T4: 57.172 | U4: 57.373 | V4: 59.538 | W4: 56.512 | X4: 58.011 | Y4: 58.233 | Z4: 57.307 | AA4: 60.809 | AB4: 61.544 | AC4: 63.349 | AD4: 69.11 | AE4: 70.441 | AF4: 72.446 | AG4: 72.408 | AH4: 72.975 | AI4: 72.497 | AJ4: 72.476 | AK4: 73.958 | AL4: 71.251 | AM4: 74.602 | AN4: 64.146 | AO4: ='[1]Soy Complex'!AX$5 -> 74.681 | AP4: ='[1]Soy Complex'!AY$5 -> 76.372 | AQ4: ='[1]Soy Complex'!AZ$5 -> 76.61 | AR4: ='[1]Soy Complex'!BA$5 -> 73.776 | AS4: ='[1]Soy Complex'!BB$5 -> 76.144 | AT4: ='[1]Soy Complex'!BC$5 -> 76.253 | AU4: ='[1]Soy Complex'!BD$5 -> 82.591 | AV4: ='[1]Soy Complex'!BE$5 -> 81.732 | ... BB4: ='[1]Soy Complex'!BK$5 -> 86.292
A5: Yield | B5: 27.411762 | C5: 26.677554 | D5: 27.540124 | E5: 27.813585 | F5: 27.800007 | G5: 23.690364 | H5: 28.877856 | I5: 26.084654 | J5: 30.559692 | K5: 29.353848 | L5: 32.137739 | M5: 26.507351 | N5: 30.063782 | O5: 31.541387 | P5: 26.161887 | Q5: 28.146703 | R5: 34.076138 | S5: 33.313177 | T5: 33.89285 | U5: 26.995991 | V5: 32.309886 | W5: 34.080319 | X5: 34.244178 | Y5: 37.613621 | Z5: 32.626346 | AA5: 41.356855 | AB5: 35.328448 | AC5: 37.573979 | AD5: 38.905368 | AE5: 38.912196 | AF5: 36.630842 | AG5: 38.08709 | AH5: 39.611949 | AI5: 38.017394 | AJ5: 33.857346 | AK5: 42.237351 | AL5: 43.063845 | AM5: 42.850406 | AN5: 41.734746 | AO5: ='[1]Soy Complex'!AX$7 -> 39.729074 | AP5: ='[1]Soy Complex'!AY$7 -> 44.007372 | AQ5: ='[1]Soy Complex'!AZ$7 -> 43.483958 | AR5: ='[1]Soy Complex'!BA$7 -> 41.980847 | AS5: ='[1]Soy Complex'!BB$7 -> 39.951198 | AT5: ='[1]Soy Complex'!BC$7 -> 44.02455 | AU5: ='[1]Soy Complex'!BD$7 -> 47.560509 | AV5: ='[1]Soy Complex'!BE$7 -> 48.044573 | ... BB5: ='[1]Soy Complex'!BK$7 -> 51.737032
A6: Beginning Stocks (Sep. 1) | B6: 326.844 | C6: 229.836 | D6: 98.779 | E6: 71.962 | F6: 59.634 | G6: 170.751 | H6: 188.151 | I6: 244.94 | J6: 102.924 | K6: 161.176 | L6: 175.588 | M6: 358.476 | N6: 313.007 | O6: 254.481 | P6: 344.634 | Q6: 175.696 | R6: 316.057 | S6: 536.365 | T6: 436.447 | U6: 302.476 | V6: 182.029 | W6: 239.139 | X6: 329.042 | Y6: 278.437 | Z6: 292.284 | AA6: 209.117 | AB6: 334.814 | AC6: 183.458 | AD6: 131.833 | AE6: 199.799 | AF6: 348.482 | AG6: 290.162 | AH6: 247.747 | AI6: 208.061 | AJ6: 178.329 | AK6: 112.414 | AL6: 255.738 | AM6: 449.326 | AN6: 573.81 | AO6: ='[1]Soy Complex'!AX$8 -> 205.034 | AP6: ='[1]Soy Complex'!AY$8 -> 138.198 | AQ6: ='[1]Soy Complex'!AZ$8 -> 150.885 | AR6: ='[1]Soy Complex'!BA$8 -> 215.013 | AS6: ='[1]Soy Complex'!BB$8 -> 169.37 | AT6: ='[1]Soy Complex'!BC$8 -> 140.557 | AU6: ='[1]Soy Complex'!BD$8 -> 91.991 | AV6: ='[1]Soy Complex'!BE$8 -> 190.61 | ... BB6: ='[1]Soy Complex'!BK$8 -> 256.979
A7: Production | B7: 1133.12 | C7: 1127.1 | D7: 1176.101 | E7: 1270.608 | F7: 1547.543 | G7: 1216.287 | H7: 1548.344 | I7: 1288.608 | J7: 1767.267 | K7: 1868.754 | L7: 2260.665 | M7: 1797.543 | N7: 1989.11 | O7: 2190.297 | P7: 1635.772 | Q7: 1860.863 | R7: 2099.056 | S7: 1942.558 | T7: 1937.722 | U7: 1548.841 | V7: 1923.666 | W7: 1925.947 | X7: 1986.539 | Y7: 2190.354 | Z7: 1869.718 | AA7: 2514.869 | AB7: 2174.254 | AC7: 2380.274 | AD7: 2688.75 | AE7: 2741.014 | AF7: 2653.758 | AG7: 2757.81 | AH7: 2890.682 | AI7: 2756.147 | AJ7: 2453.845 | AK7: 3123.79 | AL7: 3068.342 | AM7: 3196.726 | AN7: 2677.117 | AO7: ='[1]Soy Complex'!AX$9 -> 2967.007 | AP7: ='[1]Soy Complex'!AY$9 -> 3360.931 | AQ7: ='[1]Soy Complex'!AZ$9 -> 3331.306 | AR7: ='[1]Soy Complex'!BA$9 -> 3097.179 | AS7: ='[1]Soy Complex'!BB$9 -> 3042.044 | AT7: ='[1]Soy Complex'!BC$9 -> 3357.004 | AU7: ='[1]Soy Complex'!BD$9 -> 3928.07 | AV7: ='[1]Soy Complex'!BE$9 -> 3926.779 | ... BB7: ='[1]Soy Complex'!BK$9 -> 4464.492
A8: Imports | B8: 0 | C8: 0 | D8: 0 | E8: 0 | F8: 0 | G8: 0 | H8: 0 | I8: 0 | J8: 0 | K8: 0.003 | L8: 0.006 | M8: 0.35 | N8: 0.247 | O8: 0.1415 | P8: 0.106 | Q8: 0.438 | R8: 0.696 | S8: 0.081 | T8: 1.266 | U8: 3.591 | V8: 2.494 | W8: 3.483 | X8: 3.444 | Y8: 2.0567176 | Z8: 6.4164678 | AA8: 5.4799444 | AB8: 4.4558019 | AC8: 8.9039355 | AD8: 5.0059507 | AE8: 3.5210716 | AF8: 4.1711522 | AG8: 3.5678243 | AH8: 2.3197731 | AI8: 4.6609751 | AJ8: 5.5615522 | AK8: 5.5775577 | AL8: 3.3712088 | AM8: 9.034552 | AN8: 9.8708018 | AO8: ='[1]Soy Complex'!AX$10 -> 13.272 | AP8: ='[1]Soy Complex'!AY$10 -> 14.591 | AQ8: ='[1]Soy Complex'!AZ$10 -> 14.45 | AR8: ='[1]Soy Complex'!BA$10 -> 16.132 | AS8: ='[1]Soy Complex'!BB$10 -> 40.518 | AT8: ='[1]Soy Complex'!BC$10 -> 71.775 | AU8: ='[1]Soy Complex'!BD$10 -> 33.205 | AV8: ='[1]Soy Complex'!BE$10 -> 21.376161 | ... BB8: ='[1]Soy Complex'!BK$10 -> 16.50854
A9: Total Supply | B9: 1459.964 | C9: 1356.936 | D9: 1274.88 | E9: 1342.57 | F9: 1607.177 | G9: 1387.038 | H9: 1736.495 | I9: 1533.548 | J9: 1870.191 | K9: 2029.933 | L9: 2436.259 | M9: 2156.369 | N9: 2302.364 | O9: 2444.9195 | P9: 1980.512 | Q9: 2036.997 | R9: 2415.809 | S9: 2479.004 | T9: 2375.435 | U9: 1854.908 | V9: 2108.189 | W9: 2168.569 | X9: 2319.025 | Y9: 2470.8477 | Z9: 2168.4185 | AA9: 2729.4659 | AB9: 2513.5238 | AC9: 2572.6359 | AD9: 2825.589 | AE9: 2944.3341 | AF9: 3006.4112 | AG9: 3051.5398 | AH9: 3140.7488 | AI9: 2968.869 | AJ9: 2637.7356 | AK9: 3241.7816 | AL9: 3327.4512 | AM9: 3655.0866 | AN9: 3260.7978 | AO9: ='[1]Soy Complex'!AX$11 -> 3185.313 | AP9: ='[1]Soy Complex'!AY$11 -> 3513.72 | AQ9: ='[1]Soy Complex'!AZ$11 -> 3496.641 | AR9: ='[1]Soy Complex'!BA$11 -> 3328.324 | AS9: ='[1]Soy Complex'!BB$11 -> 3251.932 | AT9: ='[1]Soy Complex'!BC$11 -> 3569.336 | AU9: ='[1]Soy Complex'!BD$11 -> 4053.266 | AV9: ='[1]Soy Complex'!BE$11 -> 4138.7652 | ... BB9: ='[1]Soy Complex'!BK$11 -> 4737.9795
A10: Crush | B10: 737.349 | C10: 760.129 | D10: 720.544 | E10: 721.8 | F10: 821.313 | G10: 701.262 | H10: 865.121 | I10: 790.204 | J10: 926.66967 | K10: 1017.8233 | L10: 1123.3967 | M10: 1020.5033 | N10: 1029.6767 | O10: 1107.9933 | P10: 982.74333 | Q10: 1030.49 | R10: 1052.8267 | S10: 1178.77 | T10: 1174.4833 | U10: 1057.6467 | V10: 1146.4467 | W10: 1187.2855 | X10: 1253.557 | Y10: 1278.95 | Z10: 1275.65 | AA10: 1405.16 | AB10: 1369.54 | AC10: 1435.9633 | AD10: 1596.98 | AE10: 1589.7867 | AF10: 1577.3167 | AG10: 1639.67 | AH10: 1699.7433 | AI10: 1614.7933 | AJ10: 1529.7033 | AK10: 1696.0833 | AL10: 1738.8533 | AM10: 1807.7076 | AN10: 1803.4041 | AO10: ='[1]Soy Complex'!AX$12 -> 1661.9176 | AP10: ='[1]Soy Complex'!AY$12 -> 1751.6824 | AQ10: ='[1]Soy Complex'!AZ$12 -> 1647.9917 | AR10: ='[1]Soy Complex'!BA$12 -> 1702.997 | AS10: ='[1]Soy Complex'!BB$12 -> 1688.9977 | AT10: ='[1]Soy Complex'!BC$12 -> 1734.0087 | AU10: ='[1]Soy Complex'!BD$12 -> 1873.0101 | AV10: ='[1]Soy Complex'!BE$12 -> 1886.2378 | ... BB10: ='[1]Soy Complex'!BK$12 -> 2203.8722
A11: Exports | B11: 432.6 | C11: 433.8 | D11: 416.829 | E11: 479.443 | F11: 538.859 | G11: 420.702 | H11: 554.825 | I11: 564.071 | J11: 700.452 | K11: 739.154 | L11: 875.173 | M11: 724.295 | N11: 929.08 | O11: 905.158 | P11: 740.309 | Q11: 598.174 | R11: 740.672 | S11: 756.909 | T11: 801.686 | U11: 526.501 | V11: 623.353 | W11: 558.004 | X11: 683.94272 | Y11: 770.59476 | Z11: 588.10541 | AA11: 840.21426 | AB11: 849.08441 | AC11: 885.88759 | AD11: 874.33398 | AE11: 804.65143 | AF11: 975.04857 | AG11: 995.87119 | AH11: 1063.6514 | AI11: 1044.3721 | AJ11: 886.55056 | AK11: 1097.1563 | AL11: 939.87875 | AM11: 1116.4959 | AN11: 1158.8291 | AO11: ='[1]Soy Complex'!AX$13 -> 1279.3054 | AP11: ='[1]Soy Complex'!AY$13 -> 1499.0695 | AQ11: ='[1]Soy Complex'!AZ$13 -> 1504.9852 | AR11: ='[1]Soy Complex'!BA$13 -> 1366.3512 | AS11: ='[1]Soy Complex'!BB$13 -> 1327.5131 | AT11: ='[1]Soy Complex'!BC$13 -> 1638.5486 | AU11: ='[1]Soy Complex'!BD$13 -> 1842.4393 | AV11: ='[1]Soy Complex'!BE$13 -> 1942.272 | ... BB11: ='[1]Soy Complex'!BK$13 -> 2156.8532
A12: Seed | B12: 48.533 | C12: 48.113 | D12: 50.693 | E12: 59.947 | F12: 54.901 | G12: 57.214 | H12: 53.32 | I12: 62.84 | J12: 68.91 | K12: 76.05 | L12: 68 | M12: 66 | N12: 70 | O12: 61 | P12: 64.5 | Q12: 61 | R12: 60 | S12: 56 | T12: 60 | U12: 62.85 | V12: 57.8 | W12: 61.15 | X12: 63.07 | Y12: 65.09 | Z12: 70.86 | AA12: 71.87 | AB12: 73.82 | AC12: 81.67 | AD12: 85.61 | AE12: 86.94 | AF12: 88.03 | AG12: 89.46 | AH12: 87.52 | AI12: 87 | AJ12: 89.27 | AK12: 85.78 | AL12: 88.74 | AM12: 75.91 | AN12: 88.72 | AO12: ='[1]Soy Complex'!AX$14 -> 90 | AP12: ='[1]Soy Complex'!AY$14 -> 90 | AQ12: ='[1]Soy Complex'!AZ$14 -> 87 | AR12: ='[1]Soy Complex'!BA$14 -> 90 | AS12: ='[1]Soy Complex'!BB$14 -> 89 | AT12: ='[1]Soy Complex'!BC$14 -> 97 | AU12: ='[1]Soy Complex'!BD$14 -> 96 | AV12: ='[1]Soy Complex'!BE$14 -> 97 | ... BB12: ='[1]Soy Complex'!BK$14 -> 75
A13: Residual | B13: 11.646 | C13: 16.115 | D13: 14.852 | E13: 21.746 | F13: 21.353 | G13: 19.709 | H13: 18.289 | I13: 13.509 | J13: 12.983333 | K13: 21.317667 | L13: 11.213333 | M13: 32.563667 | N13: 19.126333 | O13: 26.134167 | P13: 17.263667 | Q13: 31.276 | R13: 25.945333 | S13: 50.878 | T13: 36.789667 | U13: 25.881333 | V13: 41.450333 | W13: 33.087467 | X13: 40.018277 | Y13: 63.928962 | Z13: 24.686062 | AA13: 77.407688 | AB13: 37.621396 | AC13: 37.282008 | AD13: 68.865972 | AE13: 114.47398 | AF13: 75.853915 | AG13: 78.791636 | AH13: 81.772993 | AI13: 44.374541 | AJ13: 19.797658 | AK13: 107.02392 | AL13: 110.65313 | AM13: 81.163117 | AN13: 4.8106738 | AO13: ='[1]Soy Complex'!AX$15 -> 15.892046 | AP13: ='[1]Soy Complex'!AY$15 -> 22.083117 | AQ13: ='[1]Soy Complex'!AZ$15 -> 41.651103 | AR13: ='[1]Soy Complex'!BA$15 -> -0.394236 | AS13: ='[1]Soy Complex'!BB$15 -> 5.864205 | AT13: ='[1]Soy Complex'!BC$15 -> 7.787752 | AU13: ='[1]Soy Complex'!BD$15 -> 51.206543 | AV13: ='[1]Soy Complex'!BE$15 -> 16.526339 | ... BB13: ='[1]Soy Complex'!BK$15 -> 27.86022
A14: Total Use | B14: 1230.128 | C14: 1258.157 | D14: 1202.918 | E14: 1282.936 | F14: 1436.426 | G14: 1198.887 | H14: 1491.555 | I14: 1430.624 | J14: 1709.015 | K14: 1854.345 | L14: 2077.783 | M14: 1843.362 | N14: 2047.883 | O14: 2100.2855 | P14: 1804.816 | Q14: 1720.94 | R14: 1879.444 | S14: 2042.557 | T14: 2072.959 | U14: 1672.879 | V14: 1869.05 | W14: 1839.527 | X14: 2040.588 | Y14: 2178.5637 | Z14: 1959.3015 | AA14: 2394.6519 | AB14: 2330.0658 | AC14: 2440.8029 | AD14: 2625.79 | AE14: 2595.8521 | AF14: 2716.2492 | AG14: 2803.7928 | AH14: 2932.6878 | AI14: 2790.54 | AJ14: 2525.3216 | AK14: 2986.0436 | AL14: 2878.1252 | AM14: 3081.2766 | AN14: 3055.7638 | AO14: ='[1]Soy Complex'!AX$16 -> 3047.115 | AP14: ='[1]Soy Complex'!AY$16 -> 3362.835 | AQ14: ='[1]Soy Complex'!AZ$16 -> 3281.628 | AR14: ='[1]Soy Complex'!BA$16 -> 3158.954 | AS14: ='[1]Soy Complex'!BB$16 -> 3111.375 | AT14: ='[1]Soy Complex'!BC$16 -> 3477.345 | AU14: ='[1]Soy Complex'!BD$16 -> 3862.656 | AV14: ='[1]Soy Complex'!BE$16 -> 3942.0362 | ... BB14: ='[1]Soy Complex'!BK$16 -> 4463.5855
A15: Ending Stocks (Aug. 1) | B15: 229.836 | C15: 98.779 | D15: 71.962 | E15: 59.634 | F15: 170.751 | G15: 188.151 | H15: 244.94 | I15: 102.924 | J15: 161.176 | K15: 175.588 | L15: 358.476 | M15: 313.007 | N15: 254.481 | O15: 344.634 | P15: 175.696 | Q15: 316.057 | R15: 536.365 | S15: 436.447 | T15: 302.476 | U15: 182.029 | V15: 239.139 | W15: 329.042 | X15: 278.437 | Y15: 292.284 | Z15: 209.117 | AA15: 334.814 | AB15: 183.458 | AC15: 131.833 | AD15: 199.799 | AE15: 348.482 | AF15: 290.162 | AG15: 247.747 | AH15: 208.061 | AI15: 178.329 | AJ15: 112.414 | AK15: 255.738 | AL15: 449.326 | AM15: 573.81 | AN15: 205.034 | AO15: ='[1]Soy Complex'!AX$17 -> 138.198 | AP15: ='[1]Soy Complex'!AY$17 -> 150.885 | AQ15: ='[1]Soy Complex'!AZ$17 -> 215.013 | AR15: ='[1]Soy Complex'!BA$17 -> 169.37 | AS15: ='[1]Soy Complex'!BB$17 -> 140.557 | AT15: ='[1]Soy Complex'!BC$17 -> 91.991 | AU15: ='[1]Soy Complex'!BD$17 -> 190.61 | AV15: ='[1]Soy Complex'!BE$17 -> 196.729 | ... BB15: ='[1]Soy Complex'!BK$17 -> 274.394
A16: Stocks/Use | B16: =B15/B14 -> 0.18683909 | C16: =C15/C14 -> 0.078510869 | D16: =D15/D14 -> 0.059822864 | E16: =E15/E14 -> 0.046482443 | F16: =F15/F14 -> 0.11887212 | G16: =G15/G14 -> 0.15693806 | H16: =H15/H14 -> 0.16421788 | I16: =I15/I14 -> 0.071943432 | ... BB16: =BB15/BB14 -> 0.061473898
A17: On Farm Stocks | B17: 40.58 | C17: 20.554 | D17: 11.779 | E17: 9.412 | F17: 64.414 | G17: 78.229 | H17: 86.159 | I17: 32.756 | J17: 59.132 | K17: 61.509 | L17: 128.596 | M17: 153.571 | N17: 117.749 | O17: 118.574 | P17: 67.912 | Q17: 143.221 | R17: 167.09 | S17: 107.95 | T17: 105.05 | U17: 87.32 | V17: 86 | W17: 118.4 | X17: 105 | Y17: 124.97 | Z17: 59.08 | AA17: 105.13 | AB17: 59.523 | AC17: 43.6 | AD17: 84.3 | AE17: 145 | AF17: 112.5 | AG17: 83.5 | AH17: 62.7 | AI17: 58 | AJ17: 29.4 | AK17: 99.7 | AL17: 176.3 | AM17: 143 | AN17: 47 | AO17: ='[1]Soy Complex'!AX$110 -> 103.098 | AP17: ='[1]Soy Complex'!AY$110 -> 115.485 | AQ17: ='[1]Soy Complex'!AZ$110 -> 166.513 | AR17: ='[1]Soy Complex'!BA$110 -> 131.12 | AS17: ='[1]Soy Complex'!BB$110 -> 101.007 | AT17: ='[1]Soy Complex'!BC$110 -> 70.666 | AU17: ='[1]Soy Complex'!BD$110 -> 140.91 | AV17: ='[1]Soy Complex'!BE$110 -> 155.169 | ... BB17: ='[1]Soy Complex'!BK$110 -> 211.464
A18: Commercial Stocks | B18: 189.256 | C18: 78.225 | D18: 60.183 | E18: 50.222 | F18: 106.337 | G18: 109.922 | H18: 158.781 | I18: 70.168 | J18: 102.044 | K18: 114.079 | L18: 229.88 | M18: 159.436 | N18: 136.732 | O18: 226.06 | P18: 107.784 | Q18: 172.836 | R18: 369.275 | S18: 328.497 | T18: 197.426 | U18: 94.709 | V18: 153.139 | W18: 210.642 | X18: 173.437 | Y18: 167.314 | Z18: 150.037 | AA18: 229.684 | AB18: 123.935 | AC18: 88.233 | AD18: 115.499 | AE18: 203.482 | AF18: 177.662 | AG18: 164.247 | AH18: 145.361 | AI18: 120.329 | AJ18: 83.014 | AK18: 156.038 | AL18: 273.026 | AM18: 430.81 | AN18: 158.034 | AO18: ='[1]Soy Complex'!AX$111 -> #REF! | AP18: ='[1]Soy Complex'!AY$111 -> #REF! | AQ18: ='[1]Soy Complex'!AZ$111 -> #REF! | AR18: ='[1]Soy Complex'!BA$111 -> #REF! | AS18: ='[1]Soy Complex'!BB$111 -> #REF! | AT18: ='[1]Soy Complex'!BC$111 -> #REF! | AU18: ='[1]Soy Complex'!BD$111 -> #REF! | AV18: ='[1]Soy Complex'!BE$111 -> #REF! | ... BB18: ='[1]Soy Complex'!BK$111 -> #REF!
A19: Outstanding Loan | B19: 150.151 | C19: 2.5 | D19: 0 | E19: 0 | F19: 0 | G19: 0 | H19: 0 | I19: 3.5 | J19: 17.6 | K19: 12.5 | L19: 42 | M19: 56.4 | N19: 83.9 | O19: 119.4 | P19: 27.2 | Q19: 157 | R19: 323.5 | S19: 148 | T19: 42.5 | U19: 16.9 | V19: 26.7 | W19: 53.4 | X19: 39.8 | Y19: 56 | Z19: 10.3 | AA19: 51.7 | AB19: 18.2 | AC19: 15.7 | AD19: 45.7 | AE19: 58.129 | AF19: 48.114 | AG19: 28.576 | AH19: 25.719 | AI19: 43.015 | AJ19: 12.923 | AK19: 58.49 | AL19: 119.947 | AM19: 56.36 | AN19: 7.175 | AO19: 8.605
A20: Reserve
A21: CCC | B21: 46.711 | C21: 8.887 | D21: 1.494 | E21: 0.219 | F21: 0.806 | G21: 0.447 | H21: 0 | I21: 0 | J21: 0 | K21: 0 | L21: 0 | M21: 0 | N21: 0.5 | O21: 20.9 | P21: 0.7 | Q21: 4.4 | R21: 131.3 | S21: 249.2 | T21: 6.9 | U21: 0.3 | V21: 0 | W21: 0 | X21: 0 | Y21: 0 | Z21: 0 | AA21: 0.5 | AB21: 0 | AC21: 0 | AD21: 0.6 | AE21: 3.8 | AF21: 7 | AG21: 2 | AH21: 2.7 | AI21: 0.7 | AJ21: 0 | AK21: 0 | AL21: 0.1 | AM21: 1.051 | AN21: 0 | AO21: 0
A22: Government | B22: 196.862 | C22: 11.387 | D22: 1.494 | E22: 0.219 | F22: 0.806 | G22: 0.447 | H22: 0 | I22: 3.5 | J22: 17.6 | K22: 12.5 | L22: 42 | M22: 56.4 | N22: 84.4 | O22: 140.3 | P22: 27.9 | Q22: 161.4 | R22: 454.8 | S22: 397.2 | T22: 49.4 | U22: 17.2 | V22: 26.7 | W22: 53.4 | X22: 39.8 | Y22: 56 | Z22: 10.3 | AA22: 52.2 | AB22: 18.2 | AC22: 15.7 | AD22: 46.3 | AE22: 61.929 | AF22: 55.114 | AG22: 30.576 | AH22: 28.419 | AI22: 43.715 | AJ22: 12.923 | AK22: 58.49 | AL22: 120.047 | AM22: 57.411 | AN22: 7.175 | AO22: 8.605
A23: Non-Government | B23: 32.974 | C23: 87.392 | D23: 70.468 | E23: 59.415 | F23: 169.945 | G23: 187.704 | H23: 244.94 | I23: 99.424 | J23: 143.576 | K23: 163.088 | L23: 316.476 | M23: 256.607 | N23: 170.081 | O23: 204.334 | P23: 147.796 | Q23: 154.657 | R23: 81.565 | S23: 39.247 | T23: 253.076 | U23: 164.829 | V23: 212.439 | W23: 275.642 | X23: 238.637 | Y23: 236.284 | Z23: 198.817 | AA23: 282.614 | AB23: 165.258 | AC23: 116.133 | AD23: 153.499 | AE23: 286.553 | AF23: 235.048 | AG23: 217.171 | AH23: 179.642 | AI23: 134.614 | AJ23: 99.491 | AK23: 197.248 | AL23: 329.279 | AM23: 516.399 | AN23: 197.859 | AO23: 129.593
A24: Farm Price ($/bu) | B24: 2.35 | C24: 2.85 | D24: 3.03 | E24: 4.37 | F24: 5.68 | G24: 6.64 | H24: 4.92 | I24: 6.81 | J24: 5.88 | K24: 6.66 | L24: 6.28 | M24: 7.57 | N24: 6.07 | O24: 5.71 | P24: 7.83 | Q24: 5.84 | R24: 5.05 | S24: 4.78 | T24: 5.88 | U24: 7.42 | V24: 5.69 | W24: 5.74 | X24: 5.58 | Y24: 5.56 | Z24: ='[1]Soy Complex'!AI$20 -> 0 | AA24: ='[1]Soy Complex'!AJ$20 -> #REF! | AB24: ='[1]Soy Complex'!AK$20 -> #REF! | AC24: ='[1]Soy Complex'!AL$20 -> #REF! | AD24: ='[1]Soy Complex'!AM$20 -> #REF! | AE24: ='[1]Soy Complex'!AN$20 -> #REF! | AF24: ='[1]Soy Complex'!AO$20 -> #REF! | AG24: ='[1]Soy Complex'!AP$20 -> #REF! | ... BB24: ='[1]Soy Complex'!BK$20 -> #REF!
A25: MYA Futures ($/bu) | H25: 5.3780222 | I25: 7.4466246 | J25: 6.2255 | K25: 7.2062158 | L25: 6.6999634 | M25: 7.843934 | N25: 6.3629513 | O25: 6.1564929 | P25: 7.7970623 | Q25: 5.8539288 | R25: 5.1994852 | S25: 5.0859378 | T25: 6.8224232 | U25: 7.4673892 | V25: 5.8974499 | W25: 5.8150585 | X25: 5.7617815 | Y25: 5.9361509 | Z25: 6.5572333 | AA25: 5.7330986 | AB25: 7.3700806 | AC25: 7.6448684 | AD25: 6.4984716 | AE25: 5.0201248 | AF25: 4.9614747 | AG25: 4.7382265 | AH25: 4.7475565 | AI25: 5.7925 | AJ25: 8.0633333 | AK25: 5.9458333 | AL25: 5.8191667 | AM25: 7.2733333 | AN25: 12.571667 | AO25: ='[1]Soy Complex'!AX$19 -> 10.235777 | AP25: ='[1]Soy Complex'!AY$19 -> 9.7797765 | AQ25: ='[1]Soy Complex'!AZ$19 -> 13.123064 | AR25: ='[1]Soy Complex'!BA$19 -> 13.58603 | AS25: ='[1]Soy Complex'!BB$19 -> 14.772545 | AT25: ='[1]Soy Complex'!BC$19 -> 13.502862 | AU25: ='[1]Soy Complex'!BD$19 -> 9.8799525 | AV25: ='[1]Soy Complex'!BE$19 -> 9.4980072 | ... BB25: ='[1]Soy Complex'!BK$19 -> 14.893779
A27: Free Ending Stocks/Use
A28: Sep 1 Free Supply
A29: Supply/Use
A30: Free Supply/Use
A31: Supply/Use (t--1)
A32: Free Supply/Use(t-1)
A33: Stk/Use x Sup/Use(t-1)
A34: Ending Stock Change
A35: Feed Grain Stocks/Use
A36: Sep-Nov Use/Supply
A37: Dec-Feb Use/Supply
A38: Sep-Feb Use/Supply
... A44: Mar 1 Stocks/Sep-Feb Use
A45: Sep 1 US & SA Stocks' | Z45: ='[2]Major Exporting Quarterly S&D'!F$5 -> #REF! | AA45: ='[2]Major Exporting Quarterly S&D'!$K$5 -> 78.150855 | AB45: ='[2]Major Exporting Quarterly S&D'!$P$5 -> 71.288494 | AC45: ='[2]Major Exporting Quarterly S&D'!$U$5 -> 76.390169 | AD45: ='[2]Major Exporting Quarterly S&D'!$Z$5 -> 84.792022 | AE45: ='[2]Major Exporting Quarterly S&D'!$AE$5 -> 82.176136 | AF45: ='[2]Major Exporting Quarterly S&D'!$AJ$5 -> 86.174354 | AG45: ='[2]Major Exporting Quarterly S&D'!$AO$5 -> 87.61512 | AH45: ='[2]Major Exporting Quarterly S&D'!$AT$5 -> 90.11308 | AI45: ='[2]Major Exporting Quarterly S&D'!$AY$5 -> 96.249778 | AJ45: ='[2]Major Exporting Quarterly S&D'!$BD$5 -> 86.341783 | AK45: ='[2]Major Exporting Quarterly S&D'!$BI$5 -> 113.68924 | AL45: ='[2]Major Exporting Quarterly S&D'!$BN$5 -> 106.01002 | AM45: ='[2]Major Exporting Quarterly S&D'!$BS$5 -> 117.14005 | AN45: ='[2]Major Exporting Quarterly S&D'!$BX$5 -> 107.34095 | AO45: ='[2]Major Exporting Quarterly S&D'!$CC$5 -> 126.20671 | AP45: ='[2]Major Exporting Quarterly S&D'!$CH$5 -> 133.06663 | AQ45: ='[2]Major Exporting Quarterly S&D'!$CM$5 -> 104.2647 | AR45: ='[2]Major Exporting Quarterly S&D'!$CR$5 -> 129.36474 | AS45: ='[2]Major Exporting Quarterly S&D'!$CW$5 -> 125.71894 | AT45: ='[2]Major Exporting Quarterly S&D'!$DB$5 -> 130.80571 | AU45: ='[2]Major Exporting Quarterly S&D'!$DG$5 -> 147.73877 | AV45: ='[2]Major Exporting Quarterly S&D'!$DL$5 -> 152.48254 | AW45: ='[2]Major Exporting Quarterly S&D'!$DQ$5 -> 173.56293 | AX45: ='[2]Major Exporting Quarterly S&D'!$DV$5 -> 183.49971 | AY45: ='[2]Major Exporting Quarterly S&D'!$EA$5 -> 192.12442 | AZ45: ='[2]Major Exporting Quarterly S&D'!$EF$5 -> 142.47279 | BA45: ='[2]Major Exporting Quarterly S&D'!$EK$5 -> 155.83526 | BB45: ='[2]Major Exporting Quarterly S&D'!$EP$5 -> #REF!
A46: Sep 1 US & SA Supplies | Z46: ='[2]Major Exporting Quarterly S&D'!$F$8 -> #REF! | AA46: ='[2]Major Exporting Quarterly S&D'!$K$8 -> 147.06195 | AB46: ='[2]Major Exporting Quarterly S&D'!$P$8 -> 139.84469 | AC46: ='[2]Major Exporting Quarterly S&D'!$U$8 -> 146.34282 | AD46: ='[2]Major Exporting Quarterly S&D'!$Z$8 -> 162.04606 | AE46: ='[2]Major Exporting Quarterly S&D'!$AE$8 -> 162.37663 | AF46: ='[2]Major Exporting Quarterly S&D'!$AJ$8 -> 168.07553 | AG46: ='[2]Major Exporting Quarterly S&D'!$AO$8 -> 170.86272 | AH46: ='[2]Major Exporting Quarterly S&D'!$AT$8 -> 176.03952 | AI46: ='[2]Major Exporting Quarterly S&D'!$AY$8 -> 177.33894 | AJ46: ='[2]Major Exporting Quarterly S&D'!$BD$8 -> 158.3932 | AK46: ='[2]Major Exporting Quarterly S&D'!$BI$8 -> 202.03976 | AL46: ='[2]Major Exporting Quarterly S&D'!$BN$8 -> 196.67893 | AM46: ='[2]Major Exporting Quarterly S&D'!$BS$8 -> 216.67417 | AN46: ='[2]Major Exporting Quarterly S&D'!$BX$8 -> 196.40158 | AO46: ='[2]Major Exporting Quarterly S&D'!$CC$8 -> 213.17929 | AP46: ='[2]Major Exporting Quarterly S&D'!$CH$8 -> 228.51675 | AQ46: ='[2]Major Exporting Quarterly S&D'!$CM$8 -> 199.25226 | AR46: ='[2]Major Exporting Quarterly S&D'!$CR$8 -> 219.69632 | AS46: ='[2]Major Exporting Quarterly S&D'!$CW$8 -> 213.53321 | AT46: ='[2]Major Exporting Quarterly S&D'!$DB$8 -> 226.45819 | AU46: ='[2]Major Exporting Quarterly S&D'!$DG$8 -> 257.59029 | AV46: ='[2]Major Exporting Quarterly S&D'!$DL$8 -> 264.81568 | AW46: ='[2]Major Exporting Quarterly S&D'!$DQ$8 -> 296.32723 | AX46: ='[2]Major Exporting Quarterly S&D'!$DV$8 -> 312.52516 | AY46: ='[2]Major Exporting Quarterly S&D'!$EA$8 -> 326.48162 | AZ46: ='[2]Major Exporting Quarterly S&D'!$EF$8 -> 264.43649 | BA46: ='[2]Major Exporting Quarterly S&D'!$EK$8 -> 286.42746 | BB46: ='[2]Major Exporting Quarterly S&D'!$EP$8 -> #REF!
A47: Dec 1 US & SA Stocks
A48: Mar 1 US & SA Stocks
A49: Mar 1 US & SA Supplies
A50: Jun 1 US & SA Stocks
A51: Sep 1 US & SA Stocks
A53: SON Use
A54: DJF Use
A55: MAM Use
A56: JJA Use
A57: Sep/Aug US & SA Use
A59: Sep 1 US & SA Supplies/SON Use
A60: Sep 1 US & SA Supplies/Sep-Feb Use
... A74: US SOYBEAN QUARTERLY BALANCE (Million Bushels)
B75: =B2 -> 0 | C75: =C2 -> 0 | D75: =D2 -> 0 | E75: =E2 -> 0 | F75: =F2 -> 0 | G75: =G2 -> 0 | H75: =H2 -> 0 | I75: =I2 -> 0 | ... BB75: =BB2 -> 0
A76: SEP-NOV
A77: Carryin (Sep 1) | B77: 326.844 | C77: 229.836 | D77: 98.779 | E77: 71.962 | F77: 59.634 | G77: 170.751 | H77: 188.151 | I77: 244.94 | J77: 102.924 | K77: 161.176 | L77: 175.588 | M77: 358.476 | N77: 313.007 | O77: 254.481 | P77: 344.634 | Q77: 175.696 | R77: 316.057 | S77: 536.365 | T77: 436.447 | U77: 302.476 | V77: 182.029 | W77: 239.139 | X77: 329.042 | Y77: 278.437 | Z77: 292.284 | AA77: 209.117 | AB77: 334.814 | AC77: 183.458 | AD77: 131.833 | AE77: 199.799 | AF77: 348.482 | AG77: 290.162 | AH77: 247.747 | AI77: 208.061 | AJ77: 178.329 | AK77: 112.414 | AL77: 255.738 | AM77: 449.326 | AN77: 573.81 | AO77: =AN137 -> 205.034 | AP77: =AO137 -> 0.30036775 | AQ77: =AP137 -> 0.35681685 | AR77: =AQ137 -> 0.52806042 | AS77: =AR137 -> 0.33678061 | AT77: =AS137 -> 0.44230775 | AU77: =AT137 -> 0.26792975 | AV77: =AU137 -> 0.4282216 | ... BB77: =BA137 -> 0.49179901
A78: Production | B78: 1133.12 | C78: 1127.1 | D78: 1176.101 | E78: 1270.608 | F78: 1547.543 | G78: 1216.287 | H78: 1548.344 | I78: 1288.608 | J78: 1767.267 | K78: 1868.754 | L78: 2260.665 | M78: 1797.543 | N78: 1989.11 | O78: 2190.297 | P78: 1635.772 | Q78: 1860.863 | R78: 2099.056 | S78: 1942.558 | T78: 1937.722 | U78: 1548.841 | V78: 1923.666 | W78: 1925.947 | X78: 1986.539 | Y78: 2190.354 | Z78: 1869.718 | AA78: 2514.869 | AB78: 2174.254 | AC78: 2380.274 | AD78: 2688.75 | AE78: 2741.014 | AF78: 2653.758 | AG78: 2757.81 | AH78: 2890.682 | AI78: 2756.147 | AJ78: 2453.845 | AK78: 3123.79 | AL78: 3068.342 | AM78: 3196.726 | AN78: 2677.117 | AO78: ='[1]Soy Complex'!AX$54 -> 2.771 | AP78: ='[1]Soy Complex'!AY$54 -> 3.172 | AQ78: ='[1]Soy Complex'!AZ$54 -> 3.738 | AR78: ='[1]Soy Complex'!BA$54 -> 2.843 | AS78: ='[1]Soy Complex'!BB$54 -> 4.286 | AT78: ='[1]Soy Complex'!BC$54 -> 7.489 | AU78: ='[1]Soy Complex'!BD$54 -> 7.625 | AV78: ='[1]Soy Complex'!BE$54 -> 4.3373062 | ... BB78: ='[1]Soy Complex'!BK$54 -> 2.9653121
A79: Imports | H79: 0 | I79: 0 | J79: 0 | K79: 0 | L79: 0 | M79: 0.074 | N79: 0.059 | O79: 0.073 | P79: 0.026 | Q79: 0.223 | R79: 0.02 | S79: 0.002 | T79: 0.151 | U79: 1.176 | V79: 0.877 | W79: 0.775 | X79: 1.595 | Y79: 0.69392682 | Z79: 1.8361268 | AA79: 2.1045138 | AB79: 1.2501125 | AC79: 0.55531856 | AD79: 0.69279144 | AE79: 1.6202392 | AF79: 1.0094854 | AG79: 0.90103269 | AH79: 0.84574444 | AI79: 1.4126556 | AJ79: 2.2462967 | AK79: 0.97057014 | AL79: 0.58762362 | AM79: 1.5217624 | AN79: 1.5687429 | AO79: ='[1]Soy Complex'!AX$55 -> 3174.812 | AP79: ='[1]Soy Complex'!AY$55 -> 3502.301 | AQ79: ='[1]Soy Complex'!AZ$55 -> 3485.929 | AR79: ='[1]Soy Complex'!BA$55 -> 3315.035 | AS79: ='[1]Soy Complex'!BB$55 -> 3215.7 | AT79: ='[1]Soy Complex'!BC$55 -> 3505.05 | AU79: ='[1]Soy Complex'!BD$55 -> 4027.686 | AV79: ='[1]Soy Complex'!BE$55 -> 4121.7263 | ... BB79: ='[1]Soy Complex'!BK$55 -> 4724.4363
A80: Total Supply | B80: 1459.964 | C80: 1356.936 | D80: 1274.88 | E80: 1342.57 | F80: 1607.177 | G80: 1387.038 | H80: 1736.495 | I80: 1533.548 | J80: 1870.191 | K80: 2029.93 | L80: 2436.253 | M80: 2156.093 | N80: 2302.176 | O80: 2444.851 | P80: 1980.432 | Q80: 2036.782 | R80: 2415.133 | S80: 2478.925 | T80: 2374.32 | U80: 1852.493 | V80: 2106.572 | W80: 2165.861 | X80: 2317.176 | Y80: 2469.4849 | Z80: 2163.8381 | AA80: 2726.0905 | AB80: 2510.3181 | AC80: 2564.2873 | AD80: 2821.2758 | AE80: 2942.4332 | AF80: 3003.2495 | AG80: 3048.873 | AH80: 3139.2747 | AI80: 2965.6207 | AJ80: 2634.4203 | AK80: 3237.1746 | AL80: 3324.6676 | AM80: 3647.5738 | AN80: 3252.4957 | AO80: =SUM(AO77:AO79) -> 3382.617 | AP80: =SUM(AP77:AP79) -> 3505.7734 | AQ80: =SUM(AQ77:AQ79) -> 3490.0238 | AR80: =SUM(AR77:AR79) -> 3318.4061 | AS80: =SUM(AS77:AS79) -> 3220.3228 | AT80: =SUM(AT77:AT79) -> 3512.9813 | AU80: =SUM(AU77:AU79) -> 4035.5789 | AV80: =SUM(AV77:AV79) -> 4126.4918 | ... BB80: =SUM(BB77:BB79) -> 4727.8934
A81: Crush | B81: 171.373 | C81: 186.017 | D81: 173.502 | E81: 189.676 | F81: 175.96 | G81: 175.996 | H81: 198.952 | I81: 215.182 | J81: 212.973 | K81: 250.32 | L81: 273.09667 | M81: 277.85 | N81: 277.45 | O81: 284.25667 | P81: 269.61 | Q81: 253.71 | R81: 267.51 | S81: 295.81667 | T81: 293.36333 | U81: 275.37 | V81: 272.98333 | W81: 304.1274 | X81: 320.39533 | Y81: 328.22667 | Z81: 326.55333 | AA81: 347.71333 | AB81: 351.44667 | AC81: 361.02 | AD81: 395.81667 | AE81: 409.29667 | AF81: 426.74667 | AG81: 421.13667 | AH81: 427.54 | AI81: 417.50667 | AJ81: 419.40333 | AK81: 427.36333 | AL81: 442.35 | AM81: 459.20333 | AN81: 467.36481 | AO81: ='[1]Soy Complex'!AX$58 -> 386.93372 | AP81: ='[1]Soy Complex'!AY$58 -> 535.97826 | AQ81: ='[1]Soy Complex'!AZ$58 -> 622.06349 | AR81: ='[1]Soy Complex'!BA$58 -> 424.8315 | AS81: ='[1]Soy Complex'!BB$58 -> 626.17816 | AT81: ='[1]Soy Complex'!BC$58 -> 676.50579 | AU81: ='[1]Soy Complex'!BD$58 -> 812.56895 | AV81: ='[1]Soy Complex'!BE$58 -> 793.0918 | ... BB81: ='[1]Soy Complex'!BK$58 -> 863.69617
A82: Exports | B82: 119.583 | C82: 119.266 | D82: 106.039 | E82: 130.58 | F82: 128.536 | G82: 118.281 | H82: 148.478 | I82: 149.65 | J82: 180.335 | K82: 227.203 | L82: 247.839 | M82: 176.706 | N82: 255.389 | O82: 245.893 | P82: 190.593 | Q82: 153.358 | R82: 166.481 | S82: 216.499 | T82: 260.86 | U82: 138.138 | V82: 168.511 | W82: 120.405 | X82: 169.84463 | Y82: 233.40429 | Z82: 178.82479 | AA82: 221.35199 | AB82: 231.55318 | AC82: 289.86462 | AD82: 367.29535 | AE82: 269.76166 | AF82: 296.6668 | AG82: 315.7676 | AH82: 348.61938 | AI82: 320.40385 | AJ82: 383.50131 | AK82: 405.77626 | AL82: 312.63421 | AM82: 373.81479 | AN82: 328.06036 | AO82: ='[1]Soy Complex'!AX$59 -> 0 | AP82: ='[1]Soy Complex'!AY$59 -> 0 | AQ82: ='[1]Soy Complex'!AZ$59 -> 0 | AR82: ='[1]Soy Complex'!BA$59 -> 0 | AS82: ='[1]Soy Complex'!BB$59 -> 0 | AT82: ='[1]Soy Complex'!BC$59 -> 0 | AU82: ='[1]Soy Complex'!BD$59 -> 0 | AV82: ='[1]Soy Complex'!BE$59 -> 0 | ... BB82: ='[1]Soy Complex'!BK$59 -> 0
A83: Seed | H83: ='[1]Soy Complex'!Q$60 -> 0 | I83: ='[1]Soy Complex'!R$60 -> 0 | J83: ='[1]Soy Complex'!S$60 -> 0 | K83: ='[1]Soy Complex'!T$60 -> 0 | L83: ='[1]Soy Complex'!U$60 -> 0 | M83: ='[1]Soy Complex'!V$60 -> 0 | N83: ='[1]Soy Complex'!W$60 -> 0 | O83: ='[1]Soy Complex'!X$60 -> 0 | ... BB83: ='[1]Soy Complex'!BK$60 -> 172.52701
A84: Residual | B84: 5 | C84: 5 | D84: 5 | E84: 5 | F84: 5 | G84: 5 | H84: 3.665 | I84: 5.087 | J84: 4.583 | K84: -6.774 | L84: -26.184667 | M84: 5.666 | N84: -12.833 | O84: -36.159667 | P84: 48.5 | Q84: 14.999 | R84: 21.325 | S84: 9.9723333 | T84: 61.815667 | U84: 72.173 | V84: 54.361667 | W84: 57.3656 | X84: 54.204033 | Y84: 71.868974 | Z84: 84.840003 | AA84: 55.069195 | AB84: 93.88927 | AC84: 88.318699 | AD84: 58.746772 | AE84: 76.934909 | AF84: 97.170022 | AG84: 71.977761 | AH84: 87.497369 | AI84: 112.33714 | AJ84: 142.86265 | AK84: 99.394978 | AL84: 68.257411 | AM84: 113.18964 | AN84: 96.710575 | AO84: =AO85-AO83-AO82-AO81 -> 2903.1378 | AP84: =AP85-AP83-AP82-AP81 -> 2786.5599 | AQ84: =AQ85-AQ83-AQ82-AQ81 -> 2724.3339 | AR84: =AR85-AR83-AR82-AR81 -> 2784.6072 | AS84: =AS85-AS83-AS82-AS81 -> 2421.8257 | AT84: =AT85-AT83-AT82-AT81 -> 2607.5635 | AU84: =AU85-AU83-AU82-AU81 -> 2974.2736 | AV84: =AV85-AV83-AV82-AV81 -> 3188.8417 | ... BB84: =BB85-BB83-BB82-BB81 -> 3691.185
A85: Total Use | B85: 295.956 | C85: 310.283 | D85: 284.541 | E85: 325.256 | F85: 309.496 | G85: 299.277 | H85: 351.095 | I85: 369.919 | J85: 397.891 | K85: 470.749 | L85: 494.751 | M85: 460.222 | N85: 520.006 | O85: 493.99 | P85: 508.703 | Q85: 422.067 | R85: 455.316 | S85: 522.288 | T85: 616.039 | U85: 485.681 | V85: 495.856 | W85: 481.898 | X85: 544.444 | Y85: 633.49993 | Z85: 590.21813 | AA85: 624.13451 | AB85: 676.88911 | AC85: 739.20332 | AD85: 821.85879 | AE85: 755.99324 | AF85: 820.58349 | AG85: 808.88203 | AH85: 863.65674 | AI85: 850.24766 | AJ85: 945.7673 | AK85: 932.53457 | AL85: 823.24162 | AM85: 946.20776 | AN85: 892.13574 | AO85: =AO80-AO86 -> 3382.0945 | AP85: =AP80-AP86 -> 3505.2476 | AQ85: =AQ80-AQ86 -> 3489.5449 | AR85: =AR80-AR86 -> 3317.9254 | AS85: =AS80-AS86 -> 3219.8599 | AT85: =AT80-AT86 -> 3512.5379 | AU85: =AU80-AU86 -> 4035.0971 | AV85: =AV80-AV86 -> 4126.0097 | ... BB85: =BB80-BB86 -> 4727.4082
A86: Stocks (Dec 1) | B86: 1164.008 | C86: 1046.653 | D86: 990.339 | E86: 1017.314 | F86: 1297.681 | G86: 1087.761 | H86: 1385.4 | I86: 1163.629 | J86: 1472.3 | K86: 1559.181 | L86: 1941.502 | M86: 1695.871 | N86: 1782.17 | O86: 1950.861 | P86: 1471.729 | Q86: 1614.715 | R86: 1959.817 | S86: 1956.637 | T86: 1758.281 | U86: 1366.812 | V86: 1610.716 | W86: 1683.963 | X86: 1772.732 | Y86: 1835.985 | Z86: 1573.62 | AA86: 2101.956 | AB86: 1833.429 | AC86: 1825.084 | AD86: 1999.417 | AE86: 2186.44 | AF86: 2182.666 | AG86: 2239.991 | AH86: 2275.618 | AI86: 2115.373 | AJ86: 1688.653 | AK86: 2304.64 | AL86: 2501.426 | AM86: 2701.366 | AN86: 2360.36 | AO86: ='[1]Soy Complex'!AX$63 -> 0.52253814 | AP86: ='[1]Soy Complex'!AY$63 -> 0.52575314 | AQ86: ='[1]Soy Complex'!AZ$63 -> 0.47891123 | AR86: ='[1]Soy Complex'!BA$63 -> 0.48061404 | AS86: ='[1]Soy Complex'!BB$63 -> 0.46283087 | AT86: ='[1]Soy Complex'!BC$63 -> 0.44343921 | AU86: ='[1]Soy Complex'!BD$63 -> 0.48185259 | AV86: ='[1]Soy Complex'!BE$63 -> 0.48211602 | ... BB86: ='[1]Soy Complex'!BK$63 -> 0.48525055
A87: Stocks/Use | B87: 3.9330441 | C87: 3.3732206 | D87: 3.4804791 | E87: 3.1277332 | F87: 4.1928846 | G87: 3.6346295 | H87: 3.9459406 | I87: 3.1456319 | J87: 3.7002596 | K87: 3.3121281 | L87: 3.9242003 | M87: 3.6848977 | N87: 3.4272105 | O87: 3.9491913 | P87: 2.8931007 | Q87: 3.8257315 | R87: 4.3043007 | S87: 3.7462798 | T87: 2.8541716 | U87: 2.8142176 | V87: 3.2483544 | W87: 3.4944387 | X87: 3.256041 | Y87: 2.8981613 | Z87: 2.6661668 | AA87: 3.3677932 | AB87: 2.7086106 | AC87: 2.4689878 | AD87: 2.4327987 | AE87: 2.8921423 | AF87: 2.6598951 | AG87: 2.7692431 | AH87: 2.6348639 | AI87: 2.4879492 | AJ87: 1.7854847 | AK87: 2.4713722 | AL87: 3.0385077 | AM87: 2.8549396 | AN87: 2.6457409 | AO87: =AO86/AO85 -> 0.00015450134 | AP87: =AP86/AP85 -> 0.0001499903 | AQ87: =AQ86/AQ85 -> 0.00013724174 | AR87: =AR86/AR85 -> 0.00014485378 | AS87: =AS86/AS85 -> 0.00014374255 | AT87: =AT86/AT85 -> 0.00012624468 | AU87: =AU86/AU85 -> 0.00011941537 | AV87: =AV86/AV85 -> 0.00011684801 | ... BB87: =BB86/BB85 -> 0.00010264621
A88: Outstanding Loan | H88: 0 | I88: 8.4 | J88: 48.6 | K88: 33.5 | L88: 45.7 | M88: 35.5 | N88: 108 | O88: 262.8 | P88: 63.2 | Q88: 106.9 | R88: 327.3 | S88: 320.4 | T88: 227.6 | U88: 51.2 | V88: 120.6 | W88: 125.6 | X88: 125.8 | Y88: 121.4 | Z88: 87 | AA88: 261 | AB88: 118.4 | AC88: 107 | AD88: 145.8 | AE88: 172 | AF88: 170.315 | AG88: 194.628 | AH88: 221.413 | AI88: 230.935 | AJ88: 98.078 | AK88: 230.654 | AL88: 274.125 | AM88: 251.541 | AN88: 123.889
A89: CCC | H89: 0 | I89: 0 | J89: 0 | K89: 0 | L89: 0 | M89: 0 | N89: 0 | O89: 6.9 | P89: 23.1 | Q89: 1 | R89: 89.4 | S89: 247.8 | T89: 48.4 | U89: 1 | V89: 0.2 | W89: 0 | X89: 0 | Y89: 0.6 | Z89: 0 | AA89: 0.2 | AB89: 0 | AC89: 0 | AD89: 0 | AE89: 3.1 | AF89: 6.766 | AG89: 8.9 | AH89: 3 | AI89: 2.9 | AJ89: 0.3 | AK89: 0 | AL89: 0.1 | AM89: 1.2 | AN89: 0
A90: Government | H90: 0 | I90: 8.4 | J90: 48.6 | K90: 33.5 | L90: 45.7 | M90: 35.5 | N90: 108 | O90: 269.7 | P90: 86.3 | Q90: 107.9 | R90: 416.7 | S90: 568.2 | T90: 276 | U90: 52.2 | V90: 120.8 | W90: 125.6 | X90: 125.8 | Y90: 122 | Z90: 87 | AA90: 261.2 | AB90: 118.4 | AC90: 107 | AD90: 145.8 | AE90: 175.1 | AF90: 177.081 | AG90: 203.528 | AH90: 224.413 | AI90: 233.835 | AJ90: 98.378 | AK90: 230.654 | AL90: 274.225 | AM90: 252.741 | AN90: 123.889
A91: Non-Government | H91: 1385.4 | I91: 1155.229 | J91: 1423.7 | K91: 1525.681 | L91: 1895.802 | M91: 1660.371 | N91: 1674.17 | O91: 1681.161 | P91: 1385.429 | Q91: 1506.815 | R91: 1543.117 | S91: 1388.437 | T91: 1482.281 | U91: 1314.612 | V91: 1489.916 | W91: 1558.363 | X91: 1646.932 | Y91: 1713.985 | Z91: 1486.62 | AA91: 1840.756 | AB91: 1715.029 | AC91: 1718.084 | AD91: 1853.617 | AE91: 2011.34 | AF91: 2005.585 | AG91: 2036.463 | AH91: 2051.205 | AI91: 1881.538 | AJ91: 1590.275 | AK91: 2073.986 | AL91: 2227.201 | AM91: 2448.625 | AN91: 2236.471
A92: On Farms | H92: 0 | I92: 534.106 | J92: 747.928 | K92: 782.702 | L92: 976.576 | M92: 814.018 | N92: 976.629 | O92: 1115.892 | P92: 707.902 | Q92: 870.331 | R92: 1030.864 | S92: 1061 | T92: 868.3 | U92: 650 | V92: 793.4 | W92: 754 | X92: 810 | Y92: 876.1 | Z92: 697.4 | AA92: 985.8 | AB92: 861.5 | AC92: 935.1 | AD92: 1048 | AE92: 1187 | AF92: 1150 | AG92: 1217 | AH92: 1240 | AI92: 1172 | AJ92: 820 | AK92: 1300 | AL92: 1345 | AM92: 1461 | AN92: 1128.5 | AO92: ='[1]Soy Complex'!AX$65 -> 1086.432 | AP92: ='[1]Soy Complex'!AY$65 -> 1109.05 | AQ92: ='[1]Soy Complex'!AZ$65 -> 1187.084 | AR92: ='[1]Soy Complex'!BA$65 -> 1230.885 | AS92: ='[1]Soy Complex'!BB$65 -> 1056.161 | AT92: ='[1]Soy Complex'!BC$65 -> 1198.621 | AU92: ='[1]Soy Complex'!BD$65 -> 1309.744 | AV92: ='[1]Soy Complex'!BE$65 -> 1405.577 | ... BB92: ='[1]Soy Complex'!BK$65 -> 1614.524
A93: Off Farms | H93: 1385.4 | I93: 629.523 | J93: 724.372 | K93: 776.479 | L93: 964.926 | M93: 881.853 | N93: 805.541 | O93: 834.969 | P93: 763.827 | Q93: 744.384 | R93: 928.953 | S93: 895.637 | T93: 889.981 | U93: 716.812 | V93: 817.316 | W93: 929.963 | X93: 962.732 | Y93: 959.885 | Z93: 876.22 | AA93: 1116.156 | AB93: 971.929 | AC93: 889.984 | AD93: 951.417 | AE93: 999.44 | AF93: 1032.666 | AG93: 1022.991 | AH93: 1035.618 | AI93: 943.373 | AJ93: 868.653 | AK93: 1004.64 | AL93: 1156.426 | AM93: 1240.366 | AN93: 1231.86 | AO93: ='[1]Soy Complex'!AX$66 -> #REF! | AP93: ='[1]Soy Complex'!AY$66 -> #REF! | AQ93: ='[1]Soy Complex'!AZ$66 -> #REF! | AR93: ='[1]Soy Complex'!BA$66 -> #REF! | AS93: ='[1]Soy Complex'!BB$66 -> #REF! | AT93: ='[1]Soy Complex'!BC$66 -> #REF! | AU93: ='[1]Soy Complex'!BD$66 -> #REF! | AV93: ='[1]Soy Complex'!BE$66 -> #REF! | ... BB93: ='[1]Soy Complex'!BK$66 -> #REF!
A94: Farm Price ($/Bu) | O94: 5.1895442 | P94: 7.9796526 | Q94: 6.0410937 | R94: 4.8979348 | S94: 4.631374 | T94: 5.1045952 | U94: 7.5793151 | V94: 5.5990172 | W94: 5.8665789 | X94: 5.5262136 | Y94: 5.2979677 | Z94: 6.1165099 | AA94: 5.3476064 | AB94: 6.1733793 | AC94: 7.0221246 | AD94: 6.6147895 | AE94: 5.23985 | AF94: 4.497925 | AG94: 4.50095 | AH94: 4.1635389 | AI94: 5.3016129 | AJ94: 6.5890566 | AK94: 5.5599698 | AL94: 5.6828358 | AM94: 5.6345098 | AN94: 8.5770142 | AO94: ='[1]Soy Complex'!AX$67 -> 0 | AP94: ='[1]Soy Complex'!AY$67 -> 0 | AQ94: ='[1]Soy Complex'!AZ$67 -> 0 | AR94: ='[1]Soy Complex'!BA$67 -> 0 | AS94: ='[1]Soy Complex'!BB$67 -> 0 | AT94: ='[1]Soy Complex'!BC$67 -> 0 | AU94: ='[1]Soy Complex'!BD$67 -> 0 | AV94: ='[1]Soy Complex'!BE$67 -> 0 | ... BB94: ='[1]Soy Complex'!BK$67 -> 0
A95: DEC-FEB
A96: Imports | H96: 0 | I96: 0 | J96: 0 | K96: 0 | L96: 0.002 | M96: 0.147 | N96: 0.059 | O96: 0.0145 | P96: 0.012 | Q96: 0.144 | R96: 0.101 | S96: 0.015 | T96: 0.79 | U96: 0.597 | V96: 0.439 | W96: 0.282 | X96: 0.441 | Y96: 1.0014459 | Z96: 1.24987 | AA96: 1.1934684 | AB96: 1.6919702 | AC96: 0.44767789 | AD96: 0.83781148 | AE96: 0.82900769 | AF96: 0.86967194 | AG96: 0.80002058 | AH96: 0.63756198 | AI96: 1.0949476 | AJ96: 1.3831394 | AK96: 1.3773155 | AL96: 0.7777392 | AM96: 1.9104152 | AN96: 3.7267775 | AO96: ='[1]Soy Complex'!AX$70 -> 2280.028 | AP96: ='[1]Soy Complex'!AY$70 -> 2344.161 | AQ96: ='[1]Soy Complex'!AZ$70 -> 2282.958 | AR96: ='[1]Soy Complex'!BA$70 -> 2373.029 | AS96: ='[1]Soy Complex'!BB$70 -> 1970.879 | AT96: ='[1]Soy Complex'!BC$70 -> 2162.035 | AU96: ='[1]Soy Complex'!BD$70 -> 2536.443 | AV96: ='[1]Soy Complex'!BE$70 -> 2720.3267 | ... BB96: ='[1]Soy Complex'!BK$70 -> 3140.185
A97: Total Supply | H97: =H86+H96 -> 1385.4 | I97: =I86+I96 -> 1163.629 | J97: =J86+J96 -> 1472.3 | K97: =K86+K96 -> 1559.181 | L97: =L86+L96 -> 1941.504 | M97: =M86+M96 -> 1696.018 | N97: =N86+N96 -> 1782.229 | O97: =O86+O96 -> 1950.8755 | ... BB97: =BB86+BB96 -> 3140.6703
A98: Crush | B98: 184.901 | C98: 195.85 | D98: 188.049 | E98: 204.632 | F98: 217.945 | G98: 177.474 | H98: 221.993 | I98: 216.464 | J98: 247.28667 | K98: 268.45333 | L98: 311.03667 | M98: 265.88667 | N98: 284.11667 | O98: 314.85333 | P98: 262.47667 | Q98: 276.39667 | R98: 281.87333 | S98: 320.16667 | T98: 317.34667 | U98: 286.29667 | V98: 304.36 | W98: 299.29013 | X98: 324.61167 | Y98: 335.2 | Z98: 328.14667 | AA98: 372.32333 | AB98: 359.09 | AC98: 400.53333 | AD98: 443.07667 | AE98: 408.63 | AF98: 407.64667 | AG98: 417.93667 | AH98: 447.59667 | AI98: 422.03 | AJ98: 423.11667 | AK98: 436.18667 | AL98: 437.15667 | AM98: 449.81745 | AN98: 471.03593 | AO98: ='[1]Soy Complex'!AX$73 -> 482.87527 | AP98: ='[1]Soy Complex'!AY$73 -> 622.28715 | AQ98: ='[1]Soy Complex'!AZ$73 -> 550.53501 | AR98: ='[1]Soy Complex'!BA$73 -> 479.45793 | AS98: ='[1]Soy Complex'!BB$73 -> 522.18691 | AT98: ='[1]Soy Complex'!BC$73 -> 712.22905 | AU98: ='[1]Soy Complex'!BD$73 -> 725.40655 | AV98: ='[1]Soy Complex'!BE$73 -> 680.67421 | ... BB98: ='[1]Soy Complex'!BK$73 -> 673.56994
A99: Exports | B99: 100.163 | C99: 114.996 | D99: 128.182 | E99: 151.505 | F99: 162.772 | G99: 124.67 | H99: 153.59 | I99: 167.551 | J99: 164.084 | K99: 200.731 | L99: 237.073 | M99: 201.671 | N99: 247.311 | O99: 263.614 | P99: 234.584 | Q99: 227.684 | R99: 270.938 | S99: 234.442 | T99: 258.901 | U99: 191.658 | V99: 216.912 | W99: 180.286 | X99: 258.81642 | Y99: 266.28057 | Z99: 209.10968 | AA99: 284.36368 | AB99: 278.90258 | AC99: 333.80542 | AD99: 307.07941 | AE99: 241.53398 | AF99: 316.03128 | AG99: 336.29109 | AH99: 422.4493 | AI99: 425.47132 | AJ99: 333.88559 | AK99: 410.68419 | AL99: 305.21963 | AM99: 396.31736 | AN99: 431.28932 | AO99: ='[1]Soy Complex'!AX$74 -> 0 | AP99: ='[1]Soy Complex'!AY$74 -> 0 | AQ99: ='[1]Soy Complex'!AZ$74 -> 0 | AR99: ='[1]Soy Complex'!BA$74 -> 0 | AS99: ='[1]Soy Complex'!BB$74 -> 0 | AT99: ='[1]Soy Complex'!BC$74 -> 0 | AU99: ='[1]Soy Complex'!BD$74 -> 0 | AV99: ='[1]Soy Complex'!BE$74 -> 0 | ... BB99: ='[1]Soy Complex'!BK$74 -> 0
A100: Seed | B100: . | H100: ='[1]Soy Complex'!Q$75 -> 0 | I100: ='[1]Soy Complex'!R$75 -> 0 | J100: ='[1]Soy Complex'!S$75 -> 0 | K100: ='[1]Soy Complex'!T$75 -> 0 | L100: ='[1]Soy Complex'!U$75 -> 0 | M100: ='[1]Soy Complex'!V$75 -> 0 | N100: ='[1]Soy Complex'!W$75 -> 0 | O100: ='[1]Soy Complex'!X$75 -> 0 | ... BB100: ='[1]Soy Complex'!BK$75 -> -32.156867
A101: Residual | B101: 10 | C101: 10 | D101: 10 | E101: 10 | F101: 10 | G101: 10 | H101: 8.217 | I101: 19.594 | J101: 37.487333 | K101: 25.138667 | L101: 24.845333 | M101: 10.343333 | N101: 40.218333 | O101: 26.607167 | P101: 18.923333 | Q101: 49.720333 | R101: 35.806667 | S101: 63.085333 | T101: 35.103333 | U101: -0.79166667 | V101: 34.378 | W101: 14.549867 | X101: 12.401913 | Y101: 19.938881 | Z101: 15.996521 | AA101: 76.264452 | AB101: 6.772393 | AC101: 35.438927 | AD101: 47.176735 | AE101: 79.767031 | AF101: 63.871728 | AG101: 82.655261 | AH101: 70.222595 | AI101: 66.938625 | AJ101: 27.18688 | AK101: 77.782461 | AL101: 90.621445 | AM101: 70.254598 | AN101: 27.779531 | AO101: =AO102-AO100-AO99-AO98 -> 1722.9081 | AP101: =AP102-AP100-AP99-AP98 -> 1763.6186 | AQ101: =AQ102-AQ100-AQ99-AQ98 -> 1678.9997 | AR101: =AR102-AR100-AR99-AR98 -> 1818.782 | AS101: =AS102-AS100-AS99-AS98 -> 1473.9605 | AT101: =AT102-AT100-AT99-AT98 -> 1479.7638 | AU101: =AU102-AU100-AU99-AU98 -> 1823.6536 | AV101: =AV102-AV100-AV99-AV98 -> 2012.2354 | ... BB101: =BB102-BB100-BB99-BB98 -> 2497.6585
A102: Total Use | B102: 295.064 | C102: 320.846 | D102: 326.231 | E102: 366.137 | F102: 390.717 | G102: 312.144 | H102: 383.8 | I102: 403.609 | J102: 448.858 | K102: 494.323 | L102: 572.955 | M102: 477.901 | N102: 571.646 | O102: 605.0745 | P102: 515.984 | Q102: 553.801 | R102: 588.618 | S102: 617.694 | T102: 611.351 | U102: 477.163 | V102: 555.65 | W102: 494.126 | X102: 595.83 | Y102: 621.41945 | Z102: 553.25287 | AA102: 732.95147 | AB102: 644.76497 | AC102: 769.77768 | AD102: 797.33281 | AE102: 729.93101 | AF102: 787.54967 | AG102: 836.88302 | AH102: 940.26856 | AI102: 914.43995 | AJ102: 784.18914 | AK102: 924.65332 | AL102: 832.99774 | AM102: 916.38942 | AN102: 930.10478 | AO102: =AO97-AO103 -> 2279.2198 | AP102: =AP97-AP103 -> 2343.5043 | AQ102: =AQ97-AQ103 -> 2282.2294 | AR102: =AR97-AR103 -> 2372.1331 | AS102: =AS97-AS103 -> 1970.316 | AT102: =AT97-AT103 -> 2161.6277 | AU102: =AU97-AU103 -> 2535.8283 | AV102: =AV97-AV103 -> 2719.5217 | ... BB102: =BB97-BB103 -> 3139.0716
A103: Stocks (Mar 1) | B103: 868.944 | C103: 725.807 | D103: 664.108 | E103: 651.177 | F103: 906.964 | G103: 775.617 | H103: 1001.6 | I103: 760.02 | J103: 1023.442 | K103: 1064.858 | L103: 1368.549 | M103: 1218.117 | N103: 1210.583 | O103: 1345.801 | P103: 955.757 | Q103: 1061.058 | R103: 1371.3 | S103: 1338.958 | T103: 1147.72 | U103: 890.246 | V103: 1055.505 | W103: 1190.119 | X103: 1177.343 | Y103: 1215.567 | Z103: 1021.617 | AA103: 1370.198 | AB103: 1190.356 | AC103: 1055.754 | AD103: 1202.922 | AE103: 1457.338 | AF103: 1395.986 | AG103: 1403.908 | AH103: 1335.987 | AI103: 1202.028 | AJ103: 905.847 | AK103: 1381.364 | AL103: 1669.206 | AM103: 1786.887 | AN103: 1433.982 | AO103: ='[1]Soy Complex'!AX$78 -> 1.3307474 | AP103: ='[1]Soy Complex'!AY$78 -> 1.1824563 | AQ103: ='[1]Soy Complex'!AZ$78 -> 1.2075524 | AR103: ='[1]Soy Complex'!BA$78 -> 1.3764963 | AS103: ='[1]Soy Complex'!BB$78 -> 1.0258629 | AT103: ='[1]Soy Complex'!BC$78 -> 0.85072937 | AU103: ='[1]Soy Complex'!BD$78 -> 1.0965042 | AV103: ='[1]Soy Complex'!BE$78 -> 1.2871022 | ... BB103: ='[1]Soy Complex'!BK$78 -> 1.5986992
A104: Stocks/Use | B104: 2.944934 | C104: 2.2621663 | D104: 2.0356986 | E104: 1.7785064 | F104: 2.3212811 | G104: 2.4848051 | H104: 2.6096925 | I104: 1.8830601 | J104: 2.2801019 | K104: 2.1541745 | L104: 2.3885803 | M104: 2.5488898 | N104: 2.1177145 | O104: 2.2241906 | P104: 1.8522997 | Q104: 1.9159554 | R104: 2.3296943 | S104: 2.167672 | T104: 1.8773503 | U104: 1.8657063 | V104: 1.8995861 | W104: 2.4085335 | X104: 1.9759713 | Y104: 1.9561136 | Z104: 1.8465643 | AA104: 1.8694253 | AB104: 1.8461859 | AC104: 1.3715051 | AD104: 1.5086824 | AE104: 1.9965421 | AF104: 1.7725688 | AG104: 1.6775439 | AH104: 1.4208568 | AI104: 1.3144964 | AJ104: 1.1551384 | AK104: 1.4939264 | AL104: 2.0038542 | AM104: 1.949921 | AN104: 1.5417424 | AO104: =AO103/AO102 -> 0.00058386093 | AP104: =AP103/AP102 -> 0.00050456757 | AQ104: =AQ103/AQ102 -> 0.0005291109 | AR104: =AR103/AR102 -> 0.00058027785 | AS104: =AS103/AS102 -> 0.0005206591 | AT104: =AT103/AT102 -> 0.00039355961 | AU104: =AU103/AU102 -> 0.00043240473 | AV104: =AV103/AV102 -> 0.00047328257 | ... BB104: =BB103/BB102 -> 0.00050929045
A105: Outstanding Loan | H105: 0 | I105: 10 | J105: 82 | K105: 50.1 | L105: 100.4 | M105: 108.7 | N105: 206.8 | O105: 376 | P105: 90.1 | Q105: 243.7 | R105: 472.8 | S105: 356.6 | T105: 241.8 | U105: 96.8 | V105: 172.5 | W105: 208.4 | X105: 142.4 | Y105: 164.5 | Z105: 86.7 | AA105: 315.3 | AB105: 129.6 | AC105: 140.6 | AD105: 213 | AE105: 292.4 | AF105: 228.387 | AG105: 178.477 | AH105: 163.382 | AI105: 293.645 | AJ105: 98.358 | AK105: 343.136 | AL105: 369.656 | AM105: 307.536 | AN105: 115.038
A106: CCC | H106: 0 | I106: 0 | J106: 0 | K106: 0 | L106: 0 | M106: 0 | N106: 0 | O106: 18.2 | P106: 21.3 | Q106: 0.9 | R106: 133.3 | S106: 360.2 | T106: 27.5 | U106: 0.7 | V106: 0.1 | W106: 0 | X106: 0 | Y106: 0 | Z106: 0 | AA106: 0 | AB106: 0 | AC106: 0 | AD106: 0 | AE106: 3.3 | AF106: 6.7 | AG106: 8.7 | AH106: 3.112 | AI106: 2.6 | AJ106: 0.1 | AK106: 0 | AL106: 0.1 | AM106: 1.2 | AN106: 0
A107: Government | H107: 0 | I107: 10 | J107: 82 | K107: 50.1 | L107: 100.4 | M107: 108.7 | N107: 206.8 | O107: 394.2 | P107: 111.4 | Q107: 244.6 | R107: 606.1 | S107: 716.8 | T107: 269.3 | U107: 97.5 | V107: 172.6 | W107: 208.4 | X107: 142.4 | Y107: 164.5 | Z107: 86.7 | AA107: 315.3 | AB107: 129.6 | AC107: 140.6 | AD107: 213 | AE107: 295.7 | AF107: 235.087 | AG107: 187.177 | AH107: 166.494 | AI107: 296.245 | AJ107: 98.458 | AK107: 343.136 | AL107: 369.756 | AM107: 308.736 | AN107: 115.038
A108: Non-Government | H108: 1001.6 | I108: 750.02 | J108: 941.442 | K108: 1014.758 | L108: 1268.149 | M108: 1109.417 | N108: 1003.783 | O108: 951.601 | P108: 844.357 | Q108: 816.458 | R108: 765.2 | S108: 622.158 | T108: 878.42 | U108: 792.746 | V108: 882.905 | W108: 981.719 | X108: 1034.943 | Y108: 1051.067 | Z108: 934.917 | AA108: 1054.898 | AB108: 1060.756 | AC108: 915.154 | AD108: 989.922 | AE108: 1161.638 | AF108: 1160.899 | AG108: 1216.731 | AH108: 1169.493 | AI108: 905.783 | AJ108: 807.389 | AK108: 1038.228 | AL108: 1299.45 | AM108: 1478.151 | AN108: 1318.944
A109: On Farms | H109: 0 | I109: 280.447 | J109: 474.877 | K109: 497.289 | L109: 696.591 | M109: 628.548 | N109: 667.031 | O109: 753.649 | P109: 453.029 | Q109: 577.216 | R109: 699.339 | S109: 589 | T109: 553.1 | U109: 415 | V109: 535.8 | W109: 555.5 | X109: 505 | Y109: 576.9 | Z109: 425.7 | AA109: 635.3 | AB109: 512 | AC109: 514 | AD109: 637 | AE109: 815 | AF109: 730 | AG109: 780 | AH109: 687 | AI109: 636.5 | AJ109: 355.9 | AK109: 795 | AL109: 872 | AM109: 910 | AN109: 593 | AO109: ='[1]Soy Complex'!AX$80 -> 645.289 | AP109: ='[1]Soy Complex'!AY$80 -> 660.868 | AQ109: ='[1]Soy Complex'!AZ$80 -> 743.8 | AR109: ='[1]Soy Complex'!BA$80 -> 819.488 | AS109: ='[1]Soy Complex'!BB$80 -> 541.32 | AT109: ='[1]Soy Complex'!BC$80 -> 611.928 | AU109: ='[1]Soy Complex'!BD$80 -> 717.399 | AV109: ='[1]Soy Complex'!BE$80 -> 803.406 | ... BB109: ='[1]Soy Complex'!BK$80 -> 1181.817
A110: Off Farms | H110: 1001.6 | I110: 479.573 | J110: 548.565 | K110: 567.569 | L110: 671.958 | M110: 589.569 | N110: 543.552 | O110: 592.152 | P110: 502.728 | Q110: 483.842 | R110: 671.961 | S110: 749.958 | T110: 594.62 | U110: 475.246 | V110: 519.705 | W110: 634.619 | X110: 672.343 | Y110: 638.667 | Z110: 595.917 | AA110: 734.898 | AB110: 678.356 | AC110: 541.754 | AD110: 565.922 | AE110: 642.338 | AF110: 665.986 | AG110: 623.908 | AH110: 648.987 | AI110: 565.528 | AJ110: 549.947 | AK110: 586.364 | AL110: 797.206 | AM110: 876.887 | AN110: 840.982 | AO110: ='[1]Soy Complex'!AX$81 -> #REF! | AP110: ='[1]Soy Complex'!AY$81 -> #REF! | AQ110: ='[1]Soy Complex'!AZ$81 -> #REF! | AR110: ='[1]Soy Complex'!BA$81 -> #REF! | AS110: ='[1]Soy Complex'!BB$81 -> #REF! | AT110: ='[1]Soy Complex'!BC$81 -> #REF! | AU110: ='[1]Soy Complex'!BD$81 -> #REF! | AV110: ='[1]Soy Complex'!BE$81 -> #REF! | ... BB110: ='[1]Soy Complex'!BK$81 -> #REF!
A111: Farm Price ($/Bu) | O111: 5.5515751 | P111: 7.6924797 | Q111: 5.8441667 | R111: 5.1064127 | S111: 4.6889399 | T111: 5.7656299 | U111: 7.5938783 | V111: 5.6226692 | W111: 5.6932407 | X111: 5.5286063 | Y111: 5.5390485 | Z111: 6.6940138 | AA111: 5.4341343 | AB111: 6.8220351 | AC111: 7.1447447 | AD111: 6.6687986 | AE111: 5.1885398 | AF111: 4.6142545 | AG111: 4.653213 | AH111: 4.2124919 | AI111: 5.5058437 | AJ111: 7.5001911 | AK111: 5.4821176 | AL111: 5.8021379 | AM111: 6.4262866 | AN111: 10.351982 | AO111: ='[1]Soy Complex'!AX$82 -> 0 | AP111: ='[1]Soy Complex'!AY$82 -> 0 | AQ111: ='[1]Soy Complex'!AZ$82 -> 0 | AR111: ='[1]Soy Complex'!BA$82 -> 0 | AS111: ='[1]Soy Complex'!BB$82 -> 0 | AT111: ='[1]Soy Complex'!BC$82 -> 0 | AU111: ='[1]Soy Complex'!BD$82 -> 0 | AV111: ='[1]Soy Complex'!BE$82 -> 0 | ... BB111: ='[1]Soy Complex'!BK$82 -> 0
A112: MAR-MAY
A113: Imports | H113: 0 | I113: 0 | J113: 0 | K113: 0.003 | L113: 0.003 | M113: 0.087 | N113: 0.102 | O113: 0.044 | P113: 0.045 | Q113: 0.049 | R113: 0.543 | S113: 0.047 | T113: 0.281 | U113: 1.451 | V113: 0.414 | W113: 1.234 | X113: 1.094 | Y113: 0.2499086 | Z113: 1.9622679 | AA113: 1.4842801 | AB113: 1.1593482 | AC113: 0.49361487 | AD113: 1.946097 | AE113: 0.58752074 | AF113: 1.028515 | AG113: 0.81336589 | AH113: 0.46173603 | AI113: 1.2422347 | AJ113: 0.99409713 | AK113: 0.96965522 | AL113: 0.95618865 | AM113: 2.5686602 | AN113: 2.2371732 | AO113: ='[1]Soy Complex'!AX$85 -> 1305.559 | AP113: ='[1]Soy Complex'!AY$85 -> 1273.25 | AQ113: ='[1]Soy Complex'!AZ$85 -> 1251.733 | AR113: ='[1]Soy Complex'!BA$85 -> 1379.819 | AS113: ='[1]Soy Complex'!BB$85 -> 1005.86 | AT113: ='[1]Soy Complex'!BC$85 -> 1019.414 | AU113: ='[1]Soy Complex'!BD$85 -> 1334.818 | AV113: ='[1]Soy Complex'!BE$85 -> 1536.0599 | ... BB113: ='[1]Soy Complex'!BK$85 -> 1936.3749
A114: Total Supply | H114: =H113+H103 -> 1001.6 | I114: =I113+I103 -> 760.02 | J114: =J113+J103 -> 1023.442 | K114: =K113+K103 -> 1064.861 | L114: =L113+L103 -> 1368.552 | M114: =M113+M103 -> 1218.204 | N114: =N113+N103 -> 1210.685 | O114: =O113+O103 -> 1345.845 | ... BB114: =BB113+BB103 -> 1937.9736
A115: Crush | B115: 192.752 | C115: 191.191 | D115: 185.472 | E115: 184.269 | F115: 217.095 | G115: 171.421 | H115: 234.705 | I115: 202.592 | J115: 249.28667 | K115: 259.27 | L115: 288.05 | M115: 256.36333 | N115: 252.66333 | O115: 260.05333 | P115: 239.98667 | Q115: 258.20333 | R115: 262.32667 | S115: 297.22 | T115: 308.25667 | U115: 270.07333 | V115: 290.68 | W115: 291.651 | X115: 303.96 | Y115: 325.43333 | Z115: 321.84 | AA115: 361.66333 | AB115: 333.96 | AC115: 355.65 | AD115: 404.87 | AE115: 396.46 | AF115: 372.92667 | AG115: 405.48667 | AH115: 429.61667 | AI115: 399.52 | AJ115: 359.57333 | AK115: 430.72333 | AL115: 431.25333 | AM115: 453.228 | AN115: 456.01 | AO115: ='[1]Soy Complex'!AX$88 -> 243.68337 | AP115: ='[1]Soy Complex'!AY$88 -> 218.94072 | AQ115: ='[1]Soy Complex'!AZ$88 -> 226.85318 | AR115: ='[1]Soy Complex'!BA$88 -> 258.06295 | AS115: ='[1]Soy Complex'!BB$88 -> 128.66467 | AT115: ='[1]Soy Complex'!BC$88 -> 192.04427 | AU115: ='[1]Soy Complex'!BD$88 -> 187.76605 | AV115: ='[1]Soy Complex'!BE$88 -> 179.9444 | ... BB115: ='[1]Soy Complex'!BK$88 -> 332.61335
A116: Exports | B116: 117.479 | C116: 98.149 | D116: 100.352 | E116: 145.571 | F116: 163.445 | G116: 99.343 | H116: 152.337 | I116: 170.556 | J116: 218.597 | K116: 198.003 | L116: 224.823 | M116: 232.779 | N116: 255.339 | O116: 216.145 | P116: 204.181 | Q116: 153.362 | R116: 227.521 | S116: 159.23 | T116: 184.951 | U116: 130.843 | V116: 153.72 | W116: 146.952 | X116: 146.65609 | Y116: 163.31796 | Z116: 115.79656 | AA116: 209.23152 | AB116: 188.22717 | AC116: 170.04907 | AD116: 120.86396 | AE116: 162.75096 | AF116: 205.65504 | AG116: 227.73025 | AH116: 155.29813 | AI116: 194.41018 | AJ116: 123.36723 | AK116: 197.91318 | AL116: 184.31342 | AM116: 210.00531 | AN116: 243.75315 | AO116: ='[1]Soy Complex'!AX$89 -> 4.2428571 | AP116: ='[1]Soy Complex'!AY$89 -> 10.671429 | AQ116: ='[1]Soy Complex'!AZ$89 -> 2.3614286 | AR116: ='[1]Soy Complex'!BA$89 -> 12.342857 | AS116: ='[1]Soy Complex'!BB$89 -> 0.50857143 | AT116: ='[1]Soy Complex'!BC$89 -> 3.7414286 | AU116: ='[1]Soy Complex'!BD$89 -> 7.9542857 | AV116: ='[1]Soy Complex'!BE$89 -> 7.0671429 | ... BB116: ='[1]Soy Complex'!BK$89 -> 8.5714286
A117: Seed | B117: 25.23716 | C117: 25.01876 | D117: 26.36036 | E117: 31.17244 | F117: 28.54852 | G117: 29.75128 | H117: 27.62 | I117: 32.551 | J117: 35.695 | K117: 49.433 | L117: 44.2 | M117: 30.36 | N117: 35 | O117: 20.13 | P117: 32.895 | Q117: 46.36 | R117: 32.4 | S117: 42 | T117: 46.286 | U117: 38.069 | V117: 22.294 | W117: 31.798 | X117: 50.456 | Y117: 30.592 | Z117: 57.295 | AA117: 25.976 | AB117: 31.11 | AC117: 62.069 | AD117: 64.208 | AE117: 63.342 | AF117: 76.712 | AG117: 67.734 | AH117: 56.513 | AI117: 61.397 | AJ117: 69.758 | AK117: 71.688 | AL117: 71.372 | AM117: 64.198 | AN117: 59.062 | AO117: ='[1]Soy Complex'!AX$90 -> 30.617103 | AP117: ='[1]Soy Complex'!AY$90 -> 47.046316 | AQ117: ='[1]Soy Complex'!AZ$90 -> 6.941526 | AR117: ='[1]Soy Complex'!BA$90 -> 11.516452 | AS117: ='[1]Soy Complex'!BB$90 -> 43.73688 | AT117: ='[1]Soy Complex'!BC$90 -> -16.80448 | AU117: ='[1]Soy Complex'!BD$90 -> 27.839958 | AV117: ='[1]Soy Complex'!BE$90 -> -8.1509473 | ... BB117: ='[1]Soy Complex'!BK$90 -> 72.997385
A118: Residual | B118: 27.47584 | C118: 33.44824 | D118: 30.92364 | E118: 32.16456 | F118: 50.37548 | G118: 51.00172 | H118: 31.971 | I118: 18.586 | J118: 13.507333 | K118: 32.05 | L118: 37.295 | M118: 17.781667 | N118: 21.317667 | O118: 58.892667 | P118: 7.2263333 | Q118: -5.2353333 | R118: 0.66933333 | S118: 3.801 | T118: -47.774667 | U118: -11.799333 | V118: -6.689 | W118: -2.57 | X118: -18.306085 | Y118: 13.060618 | Z118: -26.61229 | AA118: -17.060578 | AB118: 15.417176 | AC118: -31.410457 | AD118: 21.272142 | AE118: -13.200444 | AF118: -32.704192 | AG118: -4.4095516 | AH118: 10.099939 | AI118: -54.418947 | AJ118: -56.461466 | AK118: -17.264857 | AL118: -7.4755619 | AM118: -30.160647 | AN118: 1.2510237 | AO118: =AO119-AO117-AO116-AO115 -> 1027.506 | AP118: =AP119-AP117-AP116-AP115 -> 996.96058 | AQ118: =AQ119-AQ117-AQ116-AQ115 -> 1015.8052 | AR118: =AR119-AR117-AR116-AR115 -> 1098.3363 | AS118: =AS119-AS117-AS116-AS115 -> 833.21477 | AT118: =AT119-AT117-AT116-AT115 -> 840.62423 | AU118: =AU119-AU117-AU116-AU115 -> 1111.4682 | AV118: =AV119-AV117-AV116-AV115 -> 1357.174 | ... BB118: =BB119-BB117-BB116-BB115 -> 1522.7928
A119: Total Use | B119: 362.944 | C119: 347.807 | D119: 343.108 | E119: 393.177 | F119: 459.464 | G119: 351.517 | H119: 446.633 | I119: 424.285 | J119: 517.086 | K119: 538.756 | L119: 594.368 | M119: 537.284 | N119: 564.32 | O119: 555.221 | P119: 484.289 | Q119: 452.69 | R119: 522.917 | S119: 502.251 | T119: 491.719 | U119: 427.186 | V119: 460.005 | W119: 467.831 | X119: 482.766 | Y119: 532.40391 | Z119: 468.31927 | AA119: 579.81028 | AB119: 568.71435 | AC119: 556.35761 | AD119: 611.2141 | AE119: 609.35252 | AF119: 622.58951 | AG119: 696.54137 | AH119: 651.52774 | AI119: 600.90823 | AJ119: 496.2371 | AK119: 683.05966 | AL119: 679.46319 | AM119: 697.27066 | AN119: 760.07617 | AO119: =AO114-AO120 -> 1306.0494 | AP119: =AP114-AP120 -> 1273.619 | AQ119: =AQ114-AQ120 -> 1251.9614 | AR119: =AR114-AR120 -> 1380.2585 | AS119: =AS114-AS120 -> 1006.1249 | AT119: =AT114-AT120 -> 1019.6054 | AU119: =AU114-AU120 -> 1335.0285 | AV119: =AV114-AV120 -> 1536.0346 | ... BB119: =BB114-BB120 -> 1936.9749
A120: Stocks (Jun 1) | B120: 506 | C120: 378 | D120: 321 | E120: 258 | F120: 447.5 | G120: 424.1 | H120: 554.967 | I120: 335.735 | J120: 506.356 | K120: 526.105 | L120: 774.184 | M120: 680.92 | N120: 646.365 | O120: 790.624 | P120: 471.513 | Q120: 608.417 | R120: 848.926 | S120: 836.754 | T120: 656.282 | U120: 464.511 | V120: 595.914 | W120: 723.522 | X120: 695.671 | Y120: 683.413 | Z120: 555.26 | AA120: 791.872 | AB120: 622.801 | AC120: 499.89 | AD120: 593.654 | AE120: 848.573 | AF120: 774.425 | AG120: 708.18 | AH120: 684.921 | AI120: 602.362 | AJ120: 410.604 | AK120: 699.274 | AL120: 990.699 | AM120: 1092.185 | AN120: 676.143 | AO120: ='[1]Soy Complex'!AX$93 -> 0.84037074 | AP120: ='[1]Soy Complex'!AY$93 -> 0.81341837 | AQ120: ='[1]Soy Complex'!AZ$93 -> 0.97918096 | AR120: ='[1]Soy Complex'!BA$93 -> 0.93698498 | AS120: ='[1]Soy Complex'!BB$93 -> 0.76097172 | AT120: ='[1]Soy Complex'!BC$93 -> 0.65928619 | AU120: ='[1]Soy Complex'!BD$93 -> 0.88600212 | AV120: ='[1]Soy Complex'!BE$93 -> 1.312372 | ... BB120: ='[1]Soy Complex'!BK$93 -> 0.99863254
A121: Stocks/Use | B121: 1.3941545 | C121: 1.0868096 | D121: 0.93556548 | E121: 0.65619301 | F121: 0.97396096 | G121: 1.206485 | H121: 1.2425571 | I121: 0.79129594 | J121: 0.9792491 | K121: 0.97651813 | L121: 1.3025331 | M121: 1.2673372 | N121: 1.1453874 | O121: 1.4239807 | P121: 0.97361906 | Q121: 1.3440036 | R121: 1.6234431 | S121: 1.6660076 | T121: 1.3346688 | U121: 1.0873741 | V121: 1.2954511 | W121: 1.5465457 | X121: 1.4410108 | Y121: 1.2836363 | Z121: 1.1856441 | AA121: 1.3657433 | AB121: 1.0951034 | AC121: 0.89850482 | AD121: 0.97127014 | AE121: 1.3925814 | AF121: 1.2438774 | AG121: 1.0167092 | AH121: 1.0512538 | AI121: 1.0024193 | AJ121: 0.82743512 | AK121: 1.0237378 | AL121: 1.4580613 | AM121: 1.5663717 | AN121: =AN120/AN119 -> 0.88957268 | AO121: =AO120/AO119 -> 0.00064344484 | AP121: =AP120/AP119 -> 0.00063866694 | AQ121: =AQ120/AQ119 -> 0.00078211755 | AR121: =AR120/AR119 -> 0.00067884746 | AS121: =AS120/AS119 -> 0.00075633922 | AT121: =AT120/AT119 -> 0.00064660914 | AU121: =AU120/AU119 -> 0.00066365783 | ... BB121: =BB120/BB119 -> 0.00051556297
...

Sheet Cash Prices
A1: Monthly Farm Price
B2: Sep | C2: Oct | D2: Nov | E2: Dec | F2: Jan | G2: Feb | H2: Mar | I2: Apr | J2: May | K2: Jun | L2: Jul | M2: Aug | N2: Average | O2: Wtd Avg
A3: 70/71 | B3: 2.66 | C3: 2.77 | D3: 2.86 | E3: 2.77 | F3: 2.86 | G3: 2.92 | H3: 2.91 | I3: 2.8 | J3: 2.85 | K3: 2.98 | L3: 3.18 | M3: 3.09 | N3: =AVERAGE(B3:M3) -> 2.8875 | O3: ='Balance Sheet Data'!C$24 -> 2.85
A4: 71/72 | B4: 2.95 | C4: 2.96 | D4: 2.84 | E4: 2.93 | F4: 2.92 | G4: 3 | H4: 3.2 | I4: 3.37 | J4: 3.35 | K4: 3.32 | L4: 3.34 | M4: 3.36 | N4: =AVERAGE(B4:M4) -> 3.1283333 | O4: ='Balance Sheet Data'!D$24 -> 3.03
A5: 72/73 | B5: 3.26 | C5: 3.13 | D5: 3.38 | E5: 3.95 | F5: 4.11 | G5: 5.49 | H5: 6.04 | I5: 6.14 | J5: 8.27 | K5: 10 | L5: 6.69 | M5: 8.99 | N5: =AVERAGE(B5:M5) -> 5.7875 | O5: ='Balance Sheet Data'!E$24 -> 4.37
A6: 73/74 | B6: 5.81 | C6: 5.63 | D6: 5.14 | E6: 5.65 | F6: 5.87 | G6: 6.07 | H6: 5.96 | I6: 5.15 | J6: 5.21 | K6: 5.13 | L6: 6.11 | M6: 7.55 | N6: =AVERAGE(B6:M6) -> 5.7733333 | O6: ='Balance Sheet Data'!F$24 -> 5.68
A7: 74/75 | B7: 7.32 | C7: 8.17 | D7: 7.44 | E7: 7.03 | F7: 6.3 | G7: 5.72 | H7: 5.31 | I7: 5.6 | J7: 5 | K7: 4.9 | L7: 5.28 | M7: 5.8 | N7: =AVERAGE(B7:M7) -> 6.1558333 | O7: ='Balance Sheet Data'!G$24 -> 6.64
A8: 75/76 | B8: 5.32 | C8: 4.92 | D8: 4.45 | E8: 4.28 | F8: 4.46 | G8: 4.5 | H8: 4.46 | I8: 4.52 | J8: 4.87 | K8: 6.16 | L8: 6.73 | M8: 6.07 | N8: =AVERAGE(B8:M8) -> 5.0616667 | O8: ='Balance Sheet Data'!H$24 -> 4.92
A9: 76/77 | B9: 6.65 | C9: 5.9 | D9: 6.11 | E9: 6.56 | F9: 6.81 | G9: 7.06 | H9: 7.83 | I9: 9.05 | J9: 9.24 | K9: 8.13 | L9: 6.52 | M9: 5.48 | N9: =AVERAGE(B9:M9) -> 7.1116667 | O9: ='Balance Sheet Data'!I$24 -> 6.81
A10: 77/78 | B10: 5.17 | C10: 5.28 | D10: 5.61 | E10: 5.68 | F10: 5.75 | G10: 5.53 | H10: 6.2 | I10: 6.49 | J10: 6.77 | K10: 6.69 | L10: 6.4 | M10: 6.21 | N10: =AVERAGE(B10:M10) -> 5.9816667 | O10: ='Balance Sheet Data'!J$24 -> 5.88
A11: 78/79 | B11: 6.2 | C11: 6.26 | D11: 6.41 | E11: 6.49 | F11: 6.58 | G11: 6.99 | H11: 7.16 | I11: 7.06 | J11: 7.06 | K11: 7.36 | L11: 7.36 | M11: 7.07 | N11: =AVERAGE(B11:M11) -> 6.8333333 | O11: ='Balance Sheet Data'!K$24 -> 6.66
A12: 79/80 | B12: 6.81 | C12: 6.35 | D12: 6.3 | E12: 6.27 | F12: 6.39 | G12: 6.2 | H12: 5.94 | I12: 5.63 | J12: 5.76 | K12: 5.91 | L12: 6.75 | M12: 7.18 | N12: =AVERAGE(B12:M12) -> 6.2908333 | O12: ='Balance Sheet Data'!L$24 -> 6.28
A13: 80/81 | B13: 7.59 | C13: 7.68 | D13: 8.18 | E13: 7.8 | F13: 7.8 | G13: 7.5 | H13: 7.59 | I13: 7.6 | J13: 7.4 | K13: 7.05 | L13: 7.13 | M13: 6.71 | N13: =AVERAGE(B13:M13) -> 7.5025 | O13: ='Balance Sheet Data'!M$24 -> 7.57
A14: 81/82 | B14: 6.21 | C14: 6.06 | D14: 6.04 | E14: 6 | F14: 6.13 | G14: 6.04 | H14: 5.99 | I14: 6.17 | J14: 6.27 | K14: 6.12 | L14: 5.99 | M14: 5.59 | N14: =AVERAGE(B14:M14) -> 6.0508333 | O14: ='Balance Sheet Data'!N$24 -> 6.07
A15: 82/83 | B15: 5.22 | C15: 5.06 | D15: 5.34 | E15: 5.46 | F15: 5.56 | G15: 5.66 | H15: 5.82 | I15: 6.09 | J15: 6.06 | K15: 5.9 | L15: 6.27 | M15: 7.57 | N15: =AVERAGE(B15:M15) -> 5.8341667 | O15: ='Balance Sheet Data'!O$24 -> 5.71
A16: 83/84 | B16: 8.28 | C16: 7.96 | D16: 7.81 | E16: 7.75 | F16: 7.85 | G16: 7.28 | H16: 7.68 | I16: 7.83 | J16: 8.12 | K16: 7.99 | L16: 6.95 | M16: 6.5 | N16: =AVERAGE(B16:M16) -> 7.6666667 | O16: ='Balance Sheet Data'!P$24 -> 7.83
A17: 84/85 | B17: 6.09 | C17: 6.07 | D17: 6.01 | E17: 5.82 | F17: 5.91 | G17: 5.77 | H17: 5.88 | I17: 5.88 | J17: 5.7 | K17: 5.62 | L17: 5.42 | M17: 5.1 | N17: =AVERAGE(B17:M17) -> 5.7725 | O17: ='Balance Sheet Data'!Q$24 -> 5.84
A18: 85/86 | B18: 4.99 | C18: 4.85 | D18: 4.92 | E18: 5.01 | F18: 5.16 | G18: 5.18 | H18: 5.23 | I18: 5.23 | J18: 5.25 | K18: 5.19 | L18: 5.11 | M18: 4.99 | N18: =AVERAGE(B18:M18) -> 5.0925 | O18: ='Balance Sheet Data'!R$24 -> 5.05
A19: 86/87 | B19: 4.85 | C19: 4.55 | D19: 4.64 | E19: 4.67 | F19: 4.7 | G19: 4.69 | H19: 4.73 | I19: 4.9 | J19: 5.2 | K19: 5.36 | L19: 5.25 | M19: 5.02 | N19: =AVERAGE(B19:M19) -> 4.88 | O19: ='Balance Sheet Data'!S$24 -> 4.78
A20: 87/88 | B20: 5.02 | C20: 5.04 | D20: 5.36 | E20: 5.63 | F20: 5.73 | G20: 5.96 | H20: 6.05 | I20: 6.39 | J20: 6.98 | K20: 8.18 | L20: 8.5 | M20: 8.33 | N20: =AVERAGE(B20:M20) -> 6.4308333 | O20: ='Balance Sheet Data'!T$24 -> 5.88
A21: 88/89 | B21: 7.93 | C21: 7.53 | D21: 7.43 | E21: 7.53 | F21: 7.69 | G21: 7.41 | H21: 7.51 | I21: 7.29 | J21: 7.2 | K21: 7.05 | L21: 6.83 | M21: 6.07 | N21: =AVERAGE(B21:M21) -> 7.2891667 | O21: ='Balance Sheet Data'!U$24 -> 7.42
A22: 89/90 | B22: 5.7 | C22: 5.55 | D22: 5.66 | E22: 5.64 | F22: 5.65 | G22: 5.56 | H22: 5.65 | I22: 5.82 | J22: 5.97 | K22: 5.88 | L22: 5.97 | M22: 6 | N22: =AVERAGE(B22:M22) -> 5.7541667 | O22: ='Balance Sheet Data'!V$24 -> 5.69
A23: 90/91 | B23: 5.99 | C23: 5.88 | D23: 5.78 | E23: 5.72 | F23: 5.71 | G23: 5.65 | H23: 5.76 | I23: 5.77 | J23: 5.67 | K23: 5.56 | L23: 5.36 | M23: 5.66 | N23: =AVERAGE(B23:M23) -> 5.7091667 | O23: ='Balance Sheet Data'!W$24 -> 5.74
A24: 91/92 | B24: 5.64 | C24: 5.48 | D24: 5.48 | E24: 5.45 | F24: 5.54 | G24: 5.59 | H24: 5.67 | I24: 5.66 | J24: 5.87 | K24: 5.94 | L24: 5.59 | M24: 5.4 | N24: =AVERAGE(B24:M24) -> 5.6091667 | O24: ='Balance Sheet Data'!X$24 -> 5.58
A25: 92/93 | B25: 5.36 | C25: 5.26 | D25: 5.36 | E25: 5.46 | F25: 5.58 | G25: 5.56 | H25: 5.65 | I25: 5.73 | J25: 5.81 | K25: 5.9 | L25: 6.56 | M25: 6.56 | N25: =AVERAGE(B25:M25) -> 5.7325 | O25: ='Balance Sheet Data'!Y$24 -> 5.56
A26: 93/94 | B26: 6.21 | C26: 6.01 | D26: 6.32 | E26: 6.64 | F26: 6.72 | G26: 6.71 | H26: 6.73 | I26: 6.57 | J26: 6.77 | K26: 6.72 | L26: 5.92 | M26: 5.58 | N26: =AVERAGE(B26:M26) -> 6.4083333 | O26: ='Balance Sheet Data'!Z$24 -> 0
A27: 94/95 | B27: 5.47 | C27: 5.3 | D27: 5.36 | E27: 5.41 | F27: 5.47 | G27: 5.4 | H27: 5.51 | I27: 5.55 | J27: 5.56 | K27: 5.68 | L27: 5.9 | M27: 5.83 | N27: =AVERAGE(B27:M27) -> 5.5366667 | O27: ='Balance Sheet Data'!AA$24 -> #REF!
A28: 95/96 | B28: 5.98 | C28: 6.16 | D28: 6.4 | E28: 6.76 | F28: 6.78 | G28: 7 | H28: 7 | I28: 7.43 | J28: 7.69 | K28: 7.41 | L28: 7.62 | M28: 7.82 | N28: =AVERAGE(B28:M28) -> 7.0041667 | O28: ='Balance Sheet Data'!AB$24 -> #REF!
A29: 96/97 | B29: 7.79 | C29: 6.94 | D29: 6.9 | E29: 6.91 | F29: 7.13 | G29: 7.38 | H29: 7.97 | I29: 8.23 | J29: 8.4 | K29: 8.16 | L29: 7.52 | M29: 7.25 | N29: =AVERAGE(B29:M29) -> 7.5483333 | O29: ='Balance Sheet Data'!AC$24 -> #REF!
A30: 97/98 | B30: 6.72 | C30: 6.49 | D30: 6.86 | E30: 6.72 | F30: 6.69 | G30: 6.57 | H30: 6.4 | I30: 6.26 | J30: 6.26 | K30: 6.16 | L30: 6.14 | M30: 5.43 | N30: =AVERAGE(B30:M30) -> 6.3916667 | O30: ='Balance Sheet Data'!AD$24 -> #REF!
A31: 98/99 | B31: 5.25 | C31: 5.18 | D31: 5.39 | E31: 5.37 | F31: 5.32 | G31: 4.8 | H31: 4.61 | I31: 4.63 | J31: 4.5 | K31: 4.44 | L31: 4.19 | M31: 4.39 | N31: =AVERAGE(B31:M31) -> 4.8391667 | O31: ='Balance Sheet Data'!AE$24 -> #REF!
A32: 99/00 | B32: 4.57 | C32: 4.48 | D32: 4.45 | E32: 4.43 | F32: 4.62 | G32: 4.79 | H32: 4.91 | I32: 5 | J32: 5.19 | K32: 4.93 | L32: 4.53 | M32: 4.45 | N32: =AVERAGE(B32:M32) -> 4.6958333 | O32: ='Balance Sheet Data'!AF$24 -> #REF!
A33: 00/01 | B33: 4.59 | C33: 4.45 | D33: 4.55 | E33: 4.78 | F33: 4.68 | G33: 4.46 | H33: 4.39 | I33: 4.22 | J33: 4.33 | K33: 4.46 | L33: 4.79 | M33: 4.85 | N33: =AVERAGE(B33:M33) -> 4.5458333 | O33: ='Balance Sheet Data'!AG$24 -> #REF!
A34: 01/02 | B34: 4.53 | C34: 4.09 | D34: 4.16 | E34: 4.2 | F34: 4.22 | G34: 4.22 | H34: 4.38 | I34: 4.47 | J34: 4.64 | K34: 4.88 | L34: 5.35 | M34: 5.53 | N34: =AVERAGE(B34:M34) -> 4.5558333 | O34: ='Balance Sheet Data'!AH$24 -> #REF!
A35: 02/03 | B35: 5.39 | C35: 5.2 | D35: 5.46 | E35: 5.46 | F35: 5.51 | G35: 5.55 | H35: 5.59 | I35: 5.82 | J35: 6.07 | K35: 6.09 | L35: 5.82 | M35: 5.68 | N35: =AVERAGE(B35:M35) -> 5.6366667 | O35: ='Balance Sheet Data'!AI$24 -> #REF!
A36: 03/04 | B36: 6.06 | C36: 6.6 | D36: 7.05 | E36: 7.17 | F36: 7.35 | G36: 8.28 | H36: 9.28 | I36: 9.62 | J36: 9.56 | K36: 9.08 | L36: 8.46 | M36: 6.83 | N36: =AVERAGE(B36:M36) -> 7.945 | O36: ='Balance Sheet Data'!AJ$24 -> #REF!
A37: 04/05 | B37: 5.83 | C37: 5.56 | D37: 5.36 | E37: 5.45 | F37: 5.57 | G37: 5.42 | H37: 5.95 | I37: 6.03 | J37: 6.21 | K37: 6.58 | L37: 6.65 | M37: 6.15 | N37: =AVERAGE(B37:M37) -> 5.8966667 | O37: ='Balance Sheet Data'!AK$24 -> #REF!
A38: 05/06 | B38: 5.77 | C38: 5.67 | D38: 5.62 | E38: 5.78 | F38: 5.87 | G38: 5.67 | H38: 5.57 | I38: 5.52 | J38: 5.68 | K38: 5.62 | L38: 5.61 | M38: 5.23 | N38: =AVERAGE(B38:M38) -> 5.6341667 | O38: ='Balance Sheet Data'!AL$24 -> #REF!
A39: 06/07 | B39: 5.23 | C39: 5.52 | D39: 6.08 | E39: 6.18 | F39: 6.37 | G39: 6.87 | H39: 6.95 | I39: 6.88 | J39: 7.12 | K39: 7.51 | L39: 7.56 | M39: 7.72 | N39: =AVERAGE(B39:M39) -> 6.6658333 | O39: ='Balance Sheet Data'!AM$24 -> #REF!
A40: 07/08 | B40: 8.15 | C40: 8.36 | D40: 9.42 | E40: 10 | F40: 9.95 | G40: 11.7 | H40: 11.4 | I40: 12 | J40: 12.1 | K40: 13.1 | L40: 13.3 | M40: 12.8 | N40: =AVERAGE(B40:M40) -> 11.023333 | O40: ='Balance Sheet Data'!AN$24 -> #REF!
A41: 08/09 | B41: 10.8 | C41: 9.95 | D41: 9.39 | E41: 9.24 | F41: 9.97 | G41: 9.54 | H41: 9.12 | I41: 9.79 | J41: 10.7 | K41: 11.4 | L41: 10.8 | M41: 10.8 | N41: =AVERAGE(B41:M41) -> 10.125 | O41: ='Balance Sheet Data'!AO$24 -> #REF!
A42: 09/10 | B42: 9.75 | C42: 9.43 | D42: 9.53 | E42: 9.8 | F42: 9.79 | G42: 9.41 | H42: 9.39 | I42: 9.47 | J42: 9.41 | K42: 9.45 | L42: 9.79 | M42: 10.1 | N42: =AVERAGE(B42:M42) -> 9.61 | O42: ='Balance Sheet Data'!AP$24 -> #REF!
A43: 10/11 | B43: 9.98 | C43: 10.2 | D43: 11.1 | E43: 11.6 | F43: 11.6 | G43: 12.7 | H43: 12.7 | I43: 13.1 | J43: 13.2 | K43: 13.2 | L43: 13.2 | M43: 13.4 | N43: =AVERAGE(B43:M43) -> 12.165 | O43: ='Balance Sheet Data'!AQ$24 -> #REF!
A44: 11/12 | B44: 12.2 | C44: 11.8 | D44: 11.7 | E44: 11.5 | F44: 11.9 | G44: 12.2 | H44: 13 | I44: 13.8 | J44: 14 | K44: 13.9 | L44: 15.4 | M44: 16.2 | N44: =AVERAGE(B44:M44) -> 13.133333 | O44: ='Balance Sheet Data'!AR$24 -> #REF!
A45: 12/13 | B45: 14.3 | C45: 14.2 | D45: 14.3 | E45: 14.3 | F45: 14.3 | G45: 14.6 | H45: 14.6 | I45: 14.4 | J45: 14.9 | K45: 15.1 | L45: 15.3 | M45: 14.1 | N45: =AVERAGE(B45:M45) -> 14.533333 | O45: ='Balance Sheet Data'!AS$24 -> #REF!
A46: 13/14 | B46: 13.3 | C46: 12.5 | D46: 12.7 | E46: 13 | F46: 12.9 | G46: 13.2 | H46: 13.7 | I46: 14.3 | J46: 14.4 | K46: 14.3 | L46: 13.1 | M46: 12.4 | N46: =AVERAGE(B46:M46) -> 13.316667 | O46: ='Balance Sheet Data'!AT$24 -> #REF!
A47: 14/15 | B47: 10.9 | C47: 9.97 | D47: 10.2 | E47: 10.3 | F47: 10.3 | G47: 9.91 | H47: 9.85 | I47: 9.69 | J47: 9.58 | K47: 9.58 | L47: 9.95 | M47: 9.71 | N47: =AVERAGE(B47:M47) -> 9.995 | O47: ='Balance Sheet Data'!AU$24 -> #REF!
A48: 15/16 | B48: 9.05 | C48: 8.81 | D48: 8.68 | E48: 8.76 | F48: 8.71 | G48: 8.51 | H48: 8.56 | I48: 9.04 | J48: 9.76 | K48: 10.2 | L48: 10.2 | M48: 9.93 | N48: =AVERAGE(B48:M48) -> 9.1841667 | O48: ='Balance Sheet Data'!AV$24 -> #REF!
A49: 16/17 | B49: ='[1]Soy Complex'!$BF$498 -> 28.768678 | C49: 9.3 | D49: 9.46 | E49: 9.64 | F49: 9.71 | G49: 9.86 | H49: 9.69 | I49: 9.32 | J49: 9.26 | K49: 8.9653407 | L49: 9.9608107 | M49: 10.127914 | N49: =AVERAGE(B49:M49) -> 11.171895 | O49: ='Balance Sheet Data'!AW$24 -> #REF!
A50: 17/18 | B50: ='[1]Soy Complex'!$BG$498 -> 23.625378 | C50: ='[1]Soy Complex'!$BG$499 -> 26.213908 | D50: ='[1]Soy Complex'!$BG$500 -> 33.851087 | E50: ='[1]Soy Complex'!$BG$501 -> 40.166308 | F50: ='[1]Soy Complex'!$BG$502 -> 38.909929 | G50: ='[1]Soy Complex'!$BG$503 -> 36.410938 | H50: ='[1]Soy Complex'!$BG$504 -> 46.11059 | I50: ='[1]Soy Complex'!$BG$505 -> 31.785997 | J50: ='[1]Soy Complex'!$BG$506 -> 33.927711 | K50: ='[1]Soy Complex'!$BG$507 -> 36.99772 | L50: ='[1]Soy Complex'!$BG$508 -> 32.119984 | M50: ='[1]Soy Complex'!$BG$509 -> 27.508832 | N50: =AVERAGE(B50:M50) -> 33.969032 | O50: ='Balance Sheet Data'!AX$24 -> #REF!
A51: 18/19 | B51: ='[1]Soy Complex'!$BH$498 -> 29.97869 | C51: ='[1]Soy Complex'!$BH$499 -> 25.423265 | D51: ='[1]Soy Complex'!$BH$500 -> 28.263058 | E51: ='[1]Soy Complex'!$BH$501 -> 29.767644 | F51: ='[1]Soy Complex'!$BH$502 -> 33.728207 | G51: ='[1]Soy Complex'!$BH$503 -> 33.914199 | H51: ='[1]Soy Complex'!$BH$504 -> 35.10722 | I51: ='[1]Soy Complex'!$BH$505 -> 28.587773 | J51: ='[1]Soy Complex'!$BH$506 -> 32.652987 | K51: ='[1]Soy Complex'!$BH$507 -> 30.08429 | L51: ='[1]Soy Complex'!$BH$508 -> 24.17272 | M51: ='[1]Soy Complex'!$BH$509 -> 27.218407 | N51: =AVERAGE(B51:M51) -> 29.908205 | O51: ='Balance Sheet Data'!AY$24 -> #REF!
A52: 19/20 | B52: ='[1]Soy Complex'!$BI$498 -> 26.442909 | C52: ='[1]Soy Complex'!$BI$499 -> 27.237047 | D52: ='[1]Soy Complex'!$BI$500 -> 34.95481 | E52: ='[1]Soy Complex'!$BI$501 -> 37.162529 | F52: ='[1]Soy Complex'!$BI$502 -> 34.348912 | G52: ='[1]Soy Complex'!$BI$503 -> 31.702404 | H52: ='[1]Soy Complex'!$BI$504 -> 42.172575 | I52: ='[1]Soy Complex'!$BI$505 -> 33.886028 | J52: ='[1]Soy Complex'!$BI$506 -> 30.479215 | K52: ='[1]Soy Complex'!$BI$507 -> 28.642271 | L52: ='[1]Soy Complex'!$BI$508 -> 27.237047 | M52: ='[1]Soy Complex'!$BI$509 -> 26.70986 | N52: =AVERAGE(B52:M52) -> 31.747967 | O52: ='Balance Sheet Data'!AZ$24 -> #REF!
A53: 20/21 | B53: ='[1]Soy Complex'!$BJ$498 -> 27.887987 | C53: ='[1]Soy Complex'!$BJ$499 -> 30.550978 | D53: ='[1]Soy Complex'!$BJ$500 -> 28.887551 | E53: ='[1]Soy Complex'!$BJ$501 -> 33.522343 | F53: ='[1]Soy Complex'!$BJ$502 -> 33.177956 | G53: ='[1]Soy Complex'!$BJ$503 -> 30.20627 | H53: ='[1]Soy Complex'!$BJ$504 -> 31.406253 | I53: ='[1]Soy Complex'!$BJ$505 -> 31.843452 | J53: ='[1]Soy Complex'!$BJ$506 -> 31.810049 | K53: ='[1]Soy Complex'!$BJ$507 -> 30.505349 | L53: ='[1]Soy Complex'!$BJ$508 -> 34.135298 | M53: ='[1]Soy Complex'!$BJ$509 -> 31.567407 | N53: =AVERAGE(B53:M53) -> 31.291741 | O53: ='Balance Sheet Data'!BA$24 -> #REF!
A54: 21/22 | B54: ='[1]Soy Complex'!$BK$498 -> 34.756941 | C54: ='[1]Soy Complex'!$BK$499 -> 32.080731 | D54: ='[1]Soy Complex'!$BK$500 -> 33.296657 | E54: ='[1]Soy Complex'!$BK$501 -> 34.296142 | F54: ='[1]Soy Complex'!$BK$502 -> 35.57962 | G54: ='[1]Soy Complex'!$BK$503 -> 31.020372 | H54: ='[1]Soy Complex'!$BK$504 -> 33.419469 | I54: ='[1]Soy Complex'!$BK$505 -> 33.240464 | J54: ='[1]Soy Complex'!$BK$506 -> 32.131989 | K54: ='[1]Soy Complex'!$BK$507 -> 30.309137 | L54: ='[1]Soy Complex'!$BK$508 -> 27.681605 | M54: ='[1]Soy Complex'!$BK$509 -> 28.253139 | N54: =AVERAGE(B54:M54) -> 32.172189 | O54: ='Balance Sheet Data'!BA$24 -> #REF!
A57: Central Illinois Processor
B58: Sep | C58: Oct | D58: Nov | E58: Dec | F58: Jan | G58: Feb | H58: Mar | I58: Apr | J58: May | K58: Jun | L58: Jul | M58: Aug | N58: Average
A59: =A3 -> 70/71 | B59: =[3]Prices!$J11 -> 2.75 | C59: =[3]Prices!$J12 -> 2.9 | D59: =[3]Prices!$J13 -> 2.97 | E59: =[3]Prices!$J14 -> 2.88 | F59: =[3]Prices!$J15 -> 2.99 | G59: =[3]Prices!$J16 -> 3.01 | H59: =[3]Prices!$J17 -> 3 | I59: =[3]Prices!$J18 -> 2.91 | J59: =[3]Prices!$J19 -> 2.99 | K59: =[3]Prices!$J20 -> 3.12 | L59: =[3]Prices!$J21 -> 3.3 | M59: =[3]Prices!$J22 -> 3.23 | N59: =AVERAGE(B59:M59) -> 3.0041667
A60: =A4 -> 71/72 | B60: =[3]Prices!$J23 -> 3.01 | C60: =[3]Prices!$J24 -> 3.01 | D60: =[3]Prices!$J25 -> 2.98 | E60: =[3]Prices!$J26 -> 3.06 | F60: =[3]Prices!$J27 -> 3.05 | G60: =[3]Prices!$J28 -> 3.14 | H60: =[3]Prices!$J29 -> 3.35 | I60: =[3]Prices!$J30 -> 3.47 | J60: =[3]Prices!$J31 -> 3.47 | K60: =[3]Prices!$J32 -> 3.44 | L60: =[3]Prices!$J33 -> 3.48 | M60: =[3]Prices!$J34 -> 3.45 | N60: =AVERAGE(B60:M60) -> 3.2425
A61: =A5 -> 72/73 | B61: =[3]Prices!$J35 -> 3.42 | C61: =[3]Prices!$J36 -> 3 | D61: =[3]Prices!$J37 -> 3.61 | E61: =[3]Prices!$J38 -> 4.07 | F61: =[3]Prices!$J39 -> 4.46 | G61: =[3]Prices!$J40 -> 5.8 | H61: =[3]Prices!$J41 -> 6.15 | I61: =[3]Prices!$J42 -> 6.52 | J61: =[3]Prices!$J43 -> 8.94 | K61: =[3]Prices!$J44 -> 10.84 | L61: =[3]Prices!$J45 -> 8.47 | M61: =[3]Prices!$J46 -> 9 | N61: =AVERAGE(B61:M61) -> 6.19
A62: =A6 -> 73/74 | B62: =[3]Prices!$J47 -> 6.1 | C62: =[3]Prices!$J48 -> 5.62 | D62: =[3]Prices!$J49 -> 5.57 | E62: =[3]Prices!$J50 -> 5.92 | F62: =[3]Prices!$J51 -> 6.19 | G62: =[3]Prices!$J52 -> 6.35 | H62: =[3]Prices!$J53 -> 6.29 | I62: =[3]Prices!$J54 -> 5.59 | J62: =[3]Prices!$J55 -> 5.47 | K62: =[3]Prices!$J56 -> 5.51 | L62: =[3]Prices!$J57 -> 7.11 | M62: =[3]Prices!$J58 -> 7.76 | N62: =AVERAGE(B62:M62) -> 6.1233333
A63: =A7 -> 74/75 | B63: =[3]Prices!$J59 -> 7.64 | C63: =[3]Prices!$J60 -> 8.3 | D63: =[3]Prices!$J61 -> 7.54 | E63: =[3]Prices!$J62 -> 7.23 | F63: =[3]Prices!$J63 -> 6.38 | G63: =[3]Prices!$J64 -> 5.69 | H63: =[3]Prices!$J65 -> 5.6 | I63: =[3]Prices!$J66 -> 5.55 | J63: =[3]Prices!$J67 -> 5.23 | K63: =[3]Prices!$J68 -> 5.16 | L63: =[3]Prices!$J69 -> 5.6 | M63: =[3]Prices!$J70 -> 6.02 | N63: =AVERAGE(B63:M63) -> 6.3283333
A64: =A8 -> 75/76 | B64: =[3]Prices!$J71 -> 5.57 | C64: =[3]Prices!$J72 -> 5.01 | D64: =[3]Prices!$J73 -> 4.71 | E64: =[3]Prices!$J74 -> 4.58 | F64: =[3]Prices!$J75 -> 4.64 | G64: =[3]Prices!$J76 -> 4.75 | H64: =[3]Prices!$J77 -> 4.72 | I64: =[3]Prices!$J78 -> 4.75 | J64: =[3]Prices!$J79 -> 5.23 | K64: =[3]Prices!$J80 -> 6.23 | L64: =[3]Prices!$J81 -> 6.66 | M64: =[3]Prices!$J82 -> 6.31 | N64: =AVERAGE(B64:M64) -> 5.2633333
A65: =A9 -> 76/77 | B65: =[3]Prices!$J83 -> 6.59 | C65: =[3]Prices!$J84 -> 6.22 | D65: =[3]Prices!$J85 -> 6.55 | E65: =[3]Prices!$J86 -> 6.86 | F65: =[3]Prices!$J87 -> 7.06 | G65: =[3]Prices!$J88 -> 7.26 | H65: =[3]Prices!$J89 -> 8.25 | I65: =[3]Prices!$J90 -> 9.6 | J65: =[3]Prices!$J91 -> 9.42 | K65: =[3]Prices!$J92 -> 8.25 | L65: =[3]Prices!$J93 -> 6.4 | M65: =[3]Prices!$J94 -> 5.49 | N65: =AVERAGE(B65:M65) -> 7.3291667
A66: =A10 -> 77/78 | B66: =[3]Prices!$J95 -> 5.16 | C66: =[3]Prices!$J96 -> 5.07 | D66: =[3]Prices!$J97 -> 5.84 | E66: =[3]Prices!$J98 -> 5.94 | F66: =[3]Prices!$J99 -> 5.73 | G66: =[3]Prices!$J100 -> 5.65 | H66: =[3]Prices!$J101 -> 6.58 | I66: =[3]Prices!$J102 -> 6.81 | J66: =[3]Prices!$J103 -> 7.01 | K66: =[3]Prices!$J104 -> 6.76 | L66: =[3]Prices!$J105 -> 6.62 | M66: =[3]Prices!$J106 -> 6.47 | N66: =AVERAGE(B66:M66) -> 6.1366667
A67: =A11 -> 78/79 | B67: =[3]Prices!$J107 -> 6.42 | C67: =[3]Prices!$J108 -> 6.72 | D67: =[3]Prices!$J109 -> 6.68 | E67: =[3]Prices!$J110 -> 6.81 | F67: =[3]Prices!$J111 -> 6.89 | G67: =[3]Prices!$J112 -> 7.28 | H67: =[3]Prices!$J113 -> 7.45 | I67: =[3]Prices!$J114 -> 7.27 | J67: =[3]Prices!$J115 -> 7.21 | K67: =[3]Prices!$J116 -> 7.68 | L67: =[3]Prices!$J117 -> 7.64 | M67: =[3]Prices!$J118 -> 7.28 | N67: =AVERAGE(B67:M67) -> 7.1108333
A68: =A12 -> 79/80 | B68: =[3]Prices!$J119 -> 7.04 | C68: =[3]Prices!$J120 -> 6.56 | D68: =[3]Prices!$J121 -> 6.52 | E68: =[3]Prices!$J122 -> 6.53 | F68: =[3]Prices!$J123 -> 6.36 | G68: =[3]Prices!$J124 -> 6.42 | H68: =[3]Prices!$J125 -> 6.07 | I68: =[3]Prices!$J126 -> 5.8 | J68: =[3]Prices!$J127 -> 6.04 | K68: =[3]Prices!$J128 -> 6.1 | L68: =[3]Prices!$J129 -> 7.22 | M68: =[3]Prices!$J130 -> 7.45 | N68: =AVERAGE(B68:M68) -> 6.5091667
A69: =A13 -> 80/81 | B69: =[3]Prices!$J131 -> 8.13 | C69: =[3]Prices!$J132 -> 8.27 | D69: =[3]Prices!$J133 -> 8.91 | E69: =[3]Prices!$J134 -> 7.73 | F69: =[3]Prices!$J135 -> 7.57 | G69: =[3]Prices!$J136 -> 7.34 | H69: =[3]Prices!$J137 -> 7.37 | I69: =[3]Prices!$J138 -> 7.72 | J69: =[3]Prices!$J139 -> 7.58 | K69: =[3]Prices!$J140 -> 7.13 | L69: =[3]Prices!$J141 -> 7.36 | M69: =[3]Prices!$J142 -> 6.94 | N69: =AVERAGE(B69:M69) -> 7.6708333
A70: =A14 -> 81/82 | B70: =[3]Prices!$J143 -> 6.44 | C70: =[3]Prices!$J144 -> 6.3 | D70: =[3]Prices!$J145 -> 6.28 | E70: =[3]Prices!$J146 -> 6.23 | F70: =[3]Prices!$J147 -> 6.3 | G70: =[3]Prices!$J148 -> 6.24 | H70: =[3]Prices!$J149 -> 6.16 | I70: =[3]Prices!$J150 -> 6.42 | J70: =[3]Prices!$J151 -> 6.56 | K70: =[3]Prices!$J152 -> 6.31 | L70: =[3]Prices!$J153 -> 6.2 | M70: =[3]Prices!$J154 -> 5.73 | N70: =AVERAGE(B70:M70) -> 6.2641667
A71: =A15 -> 82/83 | B71: =[3]Prices!$J155 -> 5.4 | C71: =[3]Prices!$J156 -> 5.26 | D71: =[3]Prices!$J157 -> 5.7 | E71: =[3]Prices!$J158 -> 5.73 | F71: =[3]Prices!$J159 -> 5.81 | G71: =[3]Prices!$J160 -> 5.86 | H71: =[3]Prices!$J161 -> 5.98 | I71: =[3]Prices!$J162 -> 6.35 | J71: =[3]Prices!$J163 -> 6.27 | K71: =[3]Prices!$J164 -> 6.06 | L71: =[3]Prices!$J165 -> 6.59 | M71: =[3]Prices!$J166 -> 8.46 | N71: =AVERAGE(B71:M71) -> 6.1225
A72: =A16 -> 83/84 | B72: =[3]Prices!$J167 -> 8.93 | C72: =[3]Prices!$J168 -> 8.46 | D72: =[3]Prices!$J169 -> 8.2 | E72: =[3]Prices!$J170 -> 7.77 | F72: =[3]Prices!$J171 -> 7.67 | G72: =[3]Prices!$J172 -> 7.37 | H72: =[3]Prices!$J173 -> 7.94 | I72: =[3]Prices!$J174 -> 7.98 | J72: =[3]Prices!$J175 -> 8.61 | K72: =[3]Prices!$J176 -> 7.91 | L72: =[3]Prices!$J177 -> 6.85 | M72: =[3]Prices!$J178 -> 6.63 | N72: =AVERAGE(B72:M72) -> 7.86
A73: =A17 -> 84/85 | B73: =[3]Prices!$J179 -> 6.21 | C73: =[3]Prices!$J180 -> 6.27 | D73: =[3]Prices!$J181 -> 6.25 | E73: =[3]Prices!$J182 -> 6.07 | F73: =[3]Prices!$J183 -> 6.04 | G73: =[3]Prices!$J184 -> 5.97 | H73: =[3]Prices!$J185 -> 6.08 | I73: =[3]Prices!$J186 -> 6.13 | J73: =[3]Prices!$J187 -> 5.95 | K73: =[3]Prices!$J188 -> 5.88 | L73: =[3]Prices!$J189 -> 5.65 | M73: =[3]Prices!$J190 -> 5.28 | N73: =AVERAGE(B73:M73) -> 5.9816667
A74: =A18 -> 85/86 | B74: =[3]Prices!$J191 -> 5.19 | C74: =[3]Prices!$J192 -> 5.05 | D74: =[3]Prices!$J193 -> 5.19 | E74: =[3]Prices!$J194 -> 5.32 | F74: =[3]Prices!$J195 -> 5.45 | G74: =[3]Prices!$J196 -> 5.38 | H74: =[3]Prices!$J197 -> 5.47 | I74: =[3]Prices!$J198 -> 5.4 | J74: =[3]Prices!$J199 -> 5.44 | K74: =[3]Prices!$J200 -> 5.43 | L74: =[3]Prices!$J201 -> 5.33 | M74: =[3]Prices!$J202 -> 5 | N74: =AVERAGE(B74:M74) -> 5.3041667
A75: =A19 -> 86/87 | B75: =[3]Prices!$J203 -> 4.96 | C75: =[3]Prices!$J204 -> 4.89 | D75: =[3]Prices!$J205 -> 5.08 | E75: =[3]Prices!$J206 -> 4.96 | F75: =[3]Prices!$J207 -> 4.98 | G75: =[3]Prices!$J208 -> 4.89 | H75: =[3]Prices!$J209 -> 4.92 | I75: =[3]Prices!$J210 -> 5.12 | J75: =[3]Prices!$J211 -> 5.52 | K75: =[3]Prices!$J212 -> 5.63 | L75: =[3]Prices!$J213 -> 5.47 | M75: =[3]Prices!$J214 -> 5.28 | N75: =AVERAGE(B75:M75) -> 5.1416667
A76: =A20 -> 87/88 | B76: =[3]Prices!$J215 -> 5.27 | C76: =[3]Prices!$J216 -> 5.32 | D76: =[3]Prices!$J217 -> 5.64 | E76: =[3]Prices!$J218 -> 5.94 | F76: =[3]Prices!$J219 -> 6.17 | G76: =[3]Prices!$J220 -> 6.21 | H76: =[3]Prices!$J221 -> 6.3 | I76: =[3]Prices!$J222 -> 6.71 | J76: =[3]Prices!$J223 -> 7.31 | K76: =[3]Prices!$J224 -> 9.13 | L76: =[3]Prices!$J225 -> 8.59 | M76: =[3]Prices!$J226 -> 8.52 | N76: =AVERAGE(B76:M76) -> 6.7591667
A77: =A21 -> 88/89 | B77: =[3]Prices!$J227 -> 8.52 | C77: =[3]Prices!$J228 -> 7.92 | D77: =[3]Prices!$J229 -> 7.67 | E77: =[3]Prices!$J230 -> 7.83 | F77: =[3]Prices!$J231 -> 7.83 | G77: =[3]Prices!$J232 -> 7.6 | H77: =[3]Prices!$J233 -> 7.78 | I77: =[3]Prices!$J234 -> 7.39 | J77: =[3]Prices!$J235 -> 7.4 | K77: =[3]Prices!$J236 -> 7.25 | L77: =[3]Prices!$J237 -> 7.08 | M77: =[3]Prices!$J238 -> 6.06 | N77: =AVERAGE(B77:M77) -> 7.5275
A78: =A22 -> 89/90 | B78: =[3]Prices!$J239 -> 6 | C78: =[3]Prices!$J240 -> 5.64 | D78: =[3]Prices!$J241 -> 5.7 | E78: =[3]Prices!$J242 -> 5.82 | F78: =[3]Prices!$J243 -> 5.72 | G78: =[3]Prices!$J244 -> 5.85 | H78: =[3]Prices!$J245 -> 5.89 | I78: =[3]Prices!$J246 -> 6 | J78: =[3]Prices!$J247 -> 6.2 | K78: =[3]Prices!$J248 -> 6.09 | L78: =[3]Prices!$J249 -> 6.19 | M78: =[3]Prices!$J250 -> 6.26 | N78: =AVERAGE(B78:M78) -> 5.9466667
A79: =A23 -> 90/91 | B79: =[3]Prices!$J251 -> 6.28 | C79: =[3]Prices!$J252 -> 6.14 | D79: =[3]Prices!$J253 -> 5.87 | E79: =[3]Prices!$J254 -> 5.91 | F79: =[3]Prices!$J255 -> 5.76 | G79: =[3]Prices!$J256 -> 5.85 | H79: =[3]Prices!$J257 -> 5.92 | I79: =[3]Prices!$J258 -> 6.01 | J79: =[3]Prices!$J259 -> 5.89 | K79: =[3]Prices!$J260 -> 5.83 | L79: =[3]Prices!$J261 -> 5.54 | M79: =[3]Prices!$J262 -> 5.78 | N79: =AVERAGE(B79:M79) -> 5.8983333
A80: =A24 -> 91/92 | B80: =[3]Prices!$J263 -> 5.98 | C80: =[3]Prices!$J264 -> 5.68 | D80: =[3]Prices!$J265 -> 5.71 | E80: =[3]Prices!$J266 -> 5.68 | F80: =[3]Prices!$J267 -> 5.77 | G80: =[3]Prices!$J268 -> 5.81 | H80: =[3]Prices!$J269 -> 5.93 | I80: =[3]Prices!$J270 -> 5.85 | J80: =[3]Prices!$J271 -> 6.09 | K80: =[3]Prices!$J272 -> 6.19 | L80: =[3]Prices!$J273 -> 5.8 | M80: =[3]Prices!$J274 -> 5.64 | N80: =AVERAGE(B80:M80) -> 5.8441667
A81: =A25 -> 92/93 | B81: =[3]Prices!$J275 -> 5.54 | C81: =[3]Prices!$J276 -> 5.35 | D81: =[3]Prices!$J277 -> 5.6 | E81: =[3]Prices!$J278 -> 5.72 | F81: =[3]Prices!$J279 -> 5.82 | G81: =[3]Prices!$J280 -> 5.75 | H81: =[3]Prices!$J281 -> 5.87 | I81: =[3]Prices!$J282 -> 5.97 | J81: =[3]Prices!$J283 -> 6.07 | K81: =[3]Prices!$J284 -> 6.06 | L81: =[3]Prices!$J285 -> 6.89 | M81: =[3]Prices!$J286 -> 6.79 | N81: =AVERAGE(B81:M81) -> 5.9525
A82: =A26 -> 93/94 | B82: =[3]Prices!$J287 -> 6.43 | C82: =[3]Prices!$J288 -> 6.06 | D82: =[3]Prices!$J289 -> 6.64 | E82: =[3]Prices!$J290 -> 6.94 | F82: =[3]Prices!$J291 -> 7.01 | G82: =[3]Prices!$J292 -> 6.86 | H82: =[3]Prices!$J293 -> 6.92 | I82: =[3]Prices!$J294 -> 6.7 | J82: =[3]Prices!$J295 -> 6.89 | K82: =[3]Prices!$J296 -> 6.85 | L82: =[3]Prices!$J297 -> 6.03 | M82: =[3]Prices!$J298 -> 5.76 | N82: =AVERAGE(B82:M82) -> 6.5908333
A83: =A27 -> 94/95 | B83: =[3]Prices!$J299 -> 5.57 | C83: =[3]Prices!$J300 -> 5.31 | D83: =[3]Prices!$J301 -> 5.66 | E83: =[3]Prices!$J302 -> 5.67 | F83: =[3]Prices!$J303 -> 5.58 | G83: =[3]Prices!$J304 -> 5.6 | H83: =[3]Prices!$J305 -> 5.74 | I83: =[3]Prices!$J306 -> 5.78 | J83: =[3]Prices!$J307 -> 5.8 | K83: =[3]Prices!$J308 -> 5.91 | L83: =[3]Prices!$J309 -> 6.23 | M83: =[3]Prices!$J310 -> 6.02 | N83: =AVERAGE(B83:M83) -> 5.7391667
A84: =A28 -> 95/96 | B84: =[3]Prices!$J311 -> 6.32 | C84: =[3]Prices!$J312 -> 6.56 | D84: =[3]Prices!$J313 -> 6.86 | E84: =[3]Prices!$J314 -> 7.19 | F84: =[3]Prices!$J315 -> 7.37 | G84: =[3]Prices!$J316 -> 7.3 | H84: =[3]Prices!$J317 -> 7.26 | I84: =[3]Prices!$J318 -> 7.91 | J84: =[3]Prices!$J319 -> 8.08 | K84: =[3]Prices!$J320 -> 7.78 | L84: =[3]Prices!$J321 -> 7.95 | M84: =[3]Prices!$J322 -> 8.16 | N84: =AVERAGE(B84:M84) -> 7.395
A85: =A29 -> 96/97 | B85: =[3]Prices!$J323 -> 8.2 | C85: =[3]Prices!$J324 -> 7.11 | D85: =[3]Prices!$J325 -> 7.03 | E85: =[3]Prices!$J326 -> 7.08 | F85: =[3]Prices!$J327 -> 7.37 | G85: =[3]Prices!$J328 -> 7.69 | H85: =[3]Prices!$J329 -> 8.33 | I85: =[3]Prices!$J330 -> 8.54 | J85: =[3]Prices!$J331 -> 8.78 | K85: =[3]Prices!$J332 -> 8.37 | L85: =[3]Prices!$J333 -> 7.69 | M85: =[3]Prices!$J334 -> 7.41 | N85: =AVERAGE(B85:M85) -> 7.8
A86: =A30 -> 97/98 | B86: =[3]Prices!$J335 -> 7.03 | C86: =[3]Prices!$J336 -> 6.84 | D86: =[3]Prices!$J337 -> 7.27 | E86: =[3]Prices!$J338 -> 6.99 | F86: =[3]Prices!$J339 -> 6.79 | G86: =[3]Prices!$J340 -> 6.8 | H86: =[3]Prices!$J341 -> 6.62 | I86: =[3]Prices!$J342 -> 6.49 | J86: =[3]Prices!$J343 -> 6.49 | K86: =[3]Prices!$J344 -> 6.4 | L86: =[3]Prices!$J345 -> 6.4 | M86: =[3]Prices!$J346 -> 5.57 | N86: =AVERAGE(B86:M86) -> 6.6408333
A87: =A31 -> 98/99 | B87: =[3]Prices!$J347 -> 5.33 | C87: =[3]Prices!$J348 -> 5.36 | D87: =[3]Prices!$J349 -> 5.72 | E87: =[3]Prices!$J350 -> 5.58 | F87: =[3]Prices!$J351 -> 5.32 | G87: =[3]Prices!$J352 -> 4.9 | H87: =[3]Prices!$J353 -> 4.75 | I87: =[3]Prices!$J354 -> 4.8 | J87: =[3]Prices!$J355 -> 4.68 | K87: =[3]Prices!$J356 -> 4.62 | L87: =[3]Prices!$J357 -> 4.25 | M87: =[3]Prices!$J358 -> 4.65 | N87: =AVERAGE(B87:M87) -> 4.9966667
A88: =A32 -> 99/00 | B88: =[3]Prices!$J359 -> 4.85 | C88: =[3]Prices!$J360 -> 4.7 | D88: =[3]Prices!$J361 -> 4.64 | E88: =[3]Prices!$J362 -> 4.6 | F88: =[3]Prices!$J363 -> 4.86 | G88: =[3]Prices!$J364 -> 5 | H88: =[3]Prices!$J365 -> 5.13 | I88: =[3]Prices!$J366 -> 5.29 | J88: =[3]Prices!$J367 -> 5.42 | K88: =[3]Prices!$J368 -> 5.1 | L88: =[3]Prices!$J369 -> 4.74 | M88: =[3]Prices!$J370 -> 4.63 | N88: =AVERAGE(B88:M88) -> 4.9133333
A89: =A33 -> 00/01 | B89: =[3]Prices!$J371 -> 4.84 | C89: =[3]Prices!$J372 -> 4.68 | D89: =[3]Prices!$J373 -> 4.83 | E89: =[3]Prices!$J374 -> 5.06 | F89: =[3]Prices!$J375 -> 4.78 | G89: =[3]Prices!$J376 -> 4.57 | H89: =[3]Prices!$J377 -> 4.51 | I89: =[3]Prices!$J378 -> 4.41 | J89: =[3]Prices!$J379 -> 4.57 | K89: =[3]Prices!$J380 -> 4.74 | L89: =[3]Prices!$J381 -> 5.17 | M89: =[3]Prices!$J382 -> 5.1 | N89: =AVERAGE(B89:M89) -> 4.7716667
A90: =A34 -> 01/02 | B90: =[3]Prices!$J383 -> 4.69 | C90: =[3]Prices!$J384 -> 4.3 | D90: =[3]Prices!$J385 -> 4.41 | E90: =[3]Prices!$J386 -> 4.38 | F90: =[3]Prices!$J387 -> 4.37 | G90: =[3]Prices!$J388 -> 4.4 | H90: =[3]Prices!$J389 -> 4.64 | I90: =[3]Prices!$J390 -> 4.71 | J90: =[3]Prices!$J391 -> 4.92 | K90: =[3]Prices!$J392 -> 5.19 | L90: =[3]Prices!$J393 -> 5.75 | M90: =[3]Prices!$J394 -> 5.8 | N90: =AVERAGE(B90:M90) -> 4.7966667
A91: =A35 -> 02/03 | B91: =[3]Prices!$J395 -> 5.79 | C91: =[3]Prices!$J396 -> 5.41 | D91: =[3]Prices!$J397 -> 5.75 | E91: =[3]Prices!$J398 -> 5.66 | F91: =[3]Prices!$J399 -> 5.7 | G91: =[3]Prices!$J400 -> 5.78 | H91: =[3]Prices!$J401 -> 5.8 | I91: =[3]Prices!$J402 -> 6.11 | J91: =[3]Prices!$J403 -> 6.4 | K91: =[3]Prices!$J404 -> 6.35 | L91: =[3]Prices!$J405 -> 6.01 | M91: =[3]Prices!$J406 -> 5.89 | N91: =AVERAGE(B91:M91) -> 5.8875
A92: =A36 -> 03/04 | B92: =[3]Prices!$J407 -> 6.39 | C92: =[3]Prices!$J408 -> 7.29 | D92: =[3]Prices!$J409 -> 7.63 | E92: =[3]Prices!$J410 -> 7.72 | F92: =[3]Prices!$J411 -> 8.23 | G92: =[3]Prices!$J412 -> 8.73 | H92: =[3]Prices!$J413 -> 9.89 | I92: =[3]Prices!$J414 -> 9.93 | J92: =[3]Prices!$J415 -> 9.58 | K92: =[3]Prices!$J416 -> 8.91 | L92: =[3]Prices!$J417 -> 8.1 | M92: =[3]Prices!$J418 -> 6.42 | N92: =AVERAGE(B92:M92) -> 8.235
A93: =A37 -> 04/05 | B93: =[3]Prices!$J419 -> 5.62 | C93: =[3]Prices!$J420 -> 5.19 | D93: =[3]Prices!$J421 -> 5.34 | E93: =[3]Prices!$J422 -> 5.45 | F93: =[3]Prices!$J423 -> 5.39 | G93: =[3]Prices!$J424 -> 5.45 | H93: =[3]Prices!$J425 -> 6.28 | I93: =[3]Prices!$J426 -> 6.22 | J93: =[3]Prices!$J427 -> 6.44 | K93: =[3]Prices!$J428 -> 7.01 | L93: =[3]Prices!$J429 -> 7.03 | M93: =[3]Prices!$J430 -> 6.39 | N93: =AVERAGE(B93:M93) -> 5.9841667
A94: =A38 -> 05/06 | B94: =[3]Prices!$J431 -> 5.66 | C94: =[3]Prices!$J432 -> 5.53 | D94: =[3]Prices!$J433 -> 5.75 | E94: =[3]Prices!$J434 -> 5.92 | F94: =[3]Prices!$J435 -> 5.79 | G94: =[3]Prices!$J436 -> 5.75 | H94: =[3]Prices!$J437 -> 5.68 | I94: =[3]Prices!$J438 -> 5.62 | J94: =[3]Prices!$J439 -> 5.81 | K94: =[3]Prices!$J440 -> 5.77 | L94: =[3]Prices!$J441 -> 5.77 | M94: =[3]Prices!$J442 -> 5.42 | N94: =AVERAGE(B94:M94) -> 5.7058333
A95: =A39 -> 06/07 | B95: =[3]Prices!$J443 -> 5.35 | C95: =[3]Prices!$J444 -> 5.83 | D95: =[3]Prices!$J445 -> 6.61 | E95: =[3]Prices!$J446 -> 6.58 | F95: =[3]Prices!$J447 -> 6.83 | G95: =[3]Prices!$J448 -> 7.35 | H95: =[3]Prices!$J449 -> 7.31 | I95: =[3]Prices!$J450 -> 7.19 | J95: =[3]Prices!$J451 -> 7.5 | K95: =[3]Prices!$J452 -> 7.94 | L95: =[3]Prices!$J453 -> 8 | M95: =[3]Prices!$J454 -> 8.06 | N95: =AVERAGE(B95:M95) -> 7.0458333
A96: =A40 -> 07/08 | B96: =[3]Prices!$J455 -> 9.08 | C96: =[3]Prices!$J456 -> 9.47 | D96: =[3]Prices!$J457 -> 10.34 | E96: =[3]Prices!$J458 -> 11.23 | F96: =[3]Prices!$J459 -> 12.18 | G96: =[3]Prices!$J460 -> 13.43 | H96: =[3]Prices!$J461 -> 13.13 | I96: =[3]Prices!$J462 -> 12.93 | J96: =[3]Prices!$J463 -> 13.25 | K96: =[3]Prices!$J464 -> 15 | L96: =[3]Prices!$J465 -> 15.16 | M96: =[3]Prices!$J466 -> 12.89 | N96: =AVERAGE(B96:M96) -> 12.340833
A97: =A41 -> 08/09 | B97: =[3]Prices!$J467 -> 11.74 | C97: =[3]Prices!$J468 -> 9.04 | D97: =[3]Prices!$J469 -> 8.93 | E97: =[3]Prices!$J470 -> 8.68 | F97: =[3]Prices!$J471 -> 9.91 | G97: =[3]Prices!$J472 -> 9.39 | H97: =[3]Prices!$J473 -> 9.17 | I97: =[3]Prices!$J474 -> 10.26 | J97: =[3]Prices!$J475 -> 11.67 | K97: =[3]Prices!$J476 -> 12.37 | L97: =[3]Prices!$J477 -> 10.96 | M97: =[3]Prices!$J478 -> 11.36 | N97: =AVERAGE(B97:M97) -> 10.29
A98: =A42 -> 09/10 | B98: =[3]Prices!$J479 -> 10.12 | C98: =[3]Prices!$J480 -> 9.79 | D98: =[3]Prices!$J481 -> 10.09 | E98: =[3]Prices!$J482 -> 10.34 | F98: =[3]Prices!$J483 -> 9.84 | G98: =[3]Prices!$J484 -> 9.44 | H98: =[3]Prices!$J485 -> 9.49 | I98: =[3]Prices!$J486 -> 9.75 | J98: =[3]Prices!$J487 -> 9.55 | K98: =[3]Prices!$J488 -> 9.72 | L98: =[3]Prices!$J489 -> 10.31 | M98: =[3]Prices!$J490 -> 10.66 | N98: =AVERAGE(B98:M98) -> 9.925
A99: =A43 -> 10/11 | B99: =[3]Prices!$J491 -> 10.65 | C99: =[3]Prices!$J492 -> 11.48 | D99: =[3]Prices!$J493 -> 12.52 | E99: =[3]Prices!$J494 -> 13.11 | F99: =[3]Prices!$J495 -> 13.78 | G99: =[3]Prices!$J496 -> 13.86 | H99: =[3]Prices!$J497 -> 13.5 | I99: =[3]Prices!$J498 -> 13.64 | J99: =[3]Prices!$J499 -> 13.68 | K99: =[3]Prices!$J500 -> 13.82 | L99: =[3]Prices!$J501 -> 13.84 | M99: =[3]Prices!$J502 -> 13.81 | N99: =AVERAGE(B99:M99) -> 13.140833
A100: =A44 -> 11/12 | B100: =[3]Prices!$J503 -> 13.33 | C100: =[3]Prices!$J504 -> 12.08 | D100: =[3]Prices!$J505 -> 11.79 | E100: =[3]Prices!$J506 -> 11.43 | F100: =[3]Prices!$J507 -> 12.02 | G100: =[3]Prices!$J508 -> 12.63 | H100: =[3]Prices!$J509 -> 13.58 | I100: =[3]Prices!$J510 -> 14.47 | J100: =[3]Prices!$J511 -> 14.29 | K100: =[3]Prices!$J512 -> 14.45 | L100: =[3]Prices!$J513 -> 16.86 | M100: =[3]Prices!$J514 -> 17.35 | N100: =AVERAGE(B100:M100) -> 13.69
A101: =A45 -> 12/13 | B101: =[3]Prices!$J515 -> 16.95 | C101: =[3]Prices!$J516 -> 15.49 | D101: =[3]Prices!$J517 -> 14.64 | E101: =[3]Prices!$J518 -> 14.74 | F101: =[3]Prices!$J519 -> 14.54 | G101: =[3]Prices!$J520 -> 14.91 | H101: =[3]Prices!$J521 -> 14.88 | I101: =[3]Prices!$J522 -> 14.58 | J101: =[3]Prices!$J523 -> 15.38 | K101: =[3]Prices!$J524 -> 15.76 | L101: =[3]Prices!$J525 -> 15.39 | M101: =[3]Prices!$J526 -> 14.25 | N101: =AVERAGE(B101:M101) -> 15.125833
A102: =A46 -> 13/14 | B102: =[3]Prices!$J527 -> 13.91 | C102: =[3]Prices!$J528 -> 12.94 | D102: =[3]Prices!$J529 -> 13.07 | E102: =[3]Prices!$J530 -> 13.4 | F102: =[3]Prices!$J531 -> 13.03 | G102: =[3]Prices!$J532 -> 13.6726 | H102: =[3]Prices!$J533 -> 14.4074 | I102: =[3]Prices!$J534 -> 15.1296 | J102: =[3]Prices!$J535 -> 15.2214 | K102: =[3]Prices!$J536 -> 14.6748 | L102: =[3]Prices!$J537 -> 13.1467 | M102: =[3]Prices!$J538 -> 12.868 | N102: =AVERAGE(B102:M102) -> 13.789208
...

Sheet Futures Averages
A2: November Futures Average
A3: Contract Year | B3: Dec | C3: Jan | D3: Feb | E3: Mar | F3: Apr | G3: May | H3: Jun | I3: Jul | J3: Aug | K3: Sep | L3: Oct | M3: Nov
A4: 1970 | B4: 2.4328571 | C4: 2.4685 | D4: 2.4965789 | E4: 2.5267857 | F4: 2.5775 | G4: 2.58375 | H4: 2.7217045 | I4: 2.9275 | J4: 2.8370238 | K4: 2.8459524 | L4: 2.9810227 | M4: 3.0452083
A5: 1971 | B5: 2.8092045 | C5: 2.877 | D5: 2.8740789 | E5: 2.8676087 | F5: 2.8367857 | G5: 2.919375 | H5: 3.1265909 | I5: 3.3028571 | J5: 3.2051136 | K5: 3.1425 | L5: 3.1842857 | M5: 3.10875
A6: 1972 | B6: 3.0830952 | C6: 3.0092857 | D6: 3.01325 | E6: 3.1294318 | F6: 3.213625 | G6: 3.1953409 | H6: 3.2178409 | I6: 3.219 | J6: 3.3138043 | K6: 3.394875 | L6: 3.4067045 | M6: 3.6551923
A7: 1973 | B7: 3.5030263 | C7: 3.5786905 | D7: 3.9457895 | E7: 4.0770454 | F7: 4.28325 | G7: 5.0545454 | H7: 6.3184211 | I7: 6.8666667 | J7: 7.8011957 | K7: 6.4431579 | L7: 5.8456818 | M7: 5.5053571
A8: 1974 | B8: 5.9880263 | C8: 6.2156818 | D8: 6.2973611 | E8: 6.1611905 | F8: 5.3802381 | G8: 5.3565909 | H8: 5.453375 | I8: 7.0825 | J8: 7.8106818 | K8: 7.6815 | L8: 8.5882609 | M8: 8
A9: 1975 | B9: 7.0635714 | C9: 6.3407954 | D9: 5.7601316 | E9: 5.571875 | F9: 5.5323864 | G9: 4.9863095 | H9: 4.9407143 | I9: 5.5492045 | J9: 6.1144048 | K9: 5.7344048 | L9: 5.2457609 | M9: 4.824375
A10: 1976 | B10: 5.0336905 | C10: 5.0466667 | D10: 5.0852632 | E10: 5.0226087 | F10: 5.0444048 | G10: 5.43875 | H10: 6.4846591 | I10: 6.9691667 | J10: 6.5064773 | K10: 6.8102381 | L10: 6.4125 | M10: 6.5851923
A11: 1977 | B11: 6.2532143 | C11: 6.6759524 | D11: 6.9648684 | E11: 7.158913 | F11: 7.289375 | G11: 7.315625 | H11: 7.2038636 | I11: 5.941625 | J11: 5.296413 | K11: 5.2639286 | L11: 5.3108333 | M11: 5.90875
A12: 1978 | B12: 5.9163095 | C12: 5.7627381 | D12: 5.7586842 | E12: 6.1177273 | F12: 6.18525 | G12: 6.3064773 | H12: 6.3368182 | I12: 6.08425 | J12: 6.2304348 | K12: 6.509625 | L12: 6.8381818 | M12: 6.7076923
A13: 1979 | B13: 6.65225 | C13: 6.7318182 | D13: 6.9719737 | E13: 7.0898864 | F13: 7.028 | G13: 7.1878409 | H13: 7.7755952 | I13: 7.5586905 | J13: 7.1441304 | K13: 7.1318421 | L13: 6.7183696 | M13: 6.5776786
A14: 1980 | B14: 7.428421 | C14: 7.288875 | D14: 7.288 | E14: 6.9055952 | F14: 6.524881 | G14: 6.5497619 | H14: 6.6429762 | I14: 7.7086364 | J14: 7.8285714 | K14: 8.3860714 | L14: 8.5722826 | M14: 8.9906818
A15: 1981 | B15: 8.2128571 | C15: 8.3467857 | D15: 8.2635526 | E15: 8.0913636 | F15: 8.4008333 | G15: 7.90725 | H15: 7.4860227 | I15: 7.6260227 | J15: 7.0309524 | K15: 6.639881 | L15: 6.5647727 | M15: 6.4359615
... A53: 2019 | B53: 9.483625 | C53: 9.532619 | D53: 9.5365789 | E53: 9.3605952 | F53: 9.1569048 | G53: 8.6139773 | H53: 9.148875 | I53: 9.0544318 | J53: 8.7132955 | K53: 8.83275 | L53: 9.2497826 | M53: 9.532875
A54: 2020 | B54: 9.5442857 | C54: 9.5454762 | D54: 9.1731579 | E54: 8.7918182 | F54: 8.56 | G54: 8.502875 | H54: 8.7281818 | I54: 8.9347727 | J54: 9.0378571 | K54: 9.9629762 | L54: 10.548068
A55: 2021 | B55: 10.665455 | C55: 11.565789 | D55: 11.866579 | E55: 12.295978 | F55: 12.944881 | G55: 13.86075 | H55: 13.671932 | I55: 13.620357 | J55: 13.305909 | K55: 12.81 | L55: 12.302024 | M55: 12.364762
A56: 2022 | B56: 12.489091 | C56: 13.13375 | D56: 14.326447 | G56: =MROUND(FORECAST(K56,G5:G55,K5:K55),0.1) -> 13.6 | H56: =MROUND(FORECAST(L56,H5:H55,L5:L55),0.1) -> 13.5 | K56: =[3]Prices!$B$635 -> 14.607143 | L56: =[3]Prices!$B$636 -> 13.813095
A57: 2023 | K57: =[3]Prices!$B$647 -> 13.242875 | L57: =[3]Prices!$B$648 -> 12.843864
A58: 2024 | K58: =[3]Prices!$B$659 -> 10.142125 | L58: =[3]Prices!$B$660 -> 10.028696
A59: 2025 | K59: =[3]Prices!$B$671 -> 10.25 | L59: =[3]Prices!$B$672 -> 10
A61: November Futures High
A62: Contract Year | B62: Dec | C62: Jan | D62: Feb | E62: Mar | F62: Apr | G62: May | H62: Jun | I62: Jul | J62: Aug | K62: Sep | L62: Oct | M62: Nov | O62: =_xlfn.CONCAT(K62," ","Error") -> Sep Error | P62: =_xlfn.CONCAT(L62," ","Error") -> Oct Error
A63: 1970 | B63: 2.4575 | C63: 2.5075 | D63: 2.5275 | E63: 2.54 | F63: 2.635 | G63: 2.6275 | H63: 2.96 | I63: 3.02 | J63: 2.975 | K63: 2.92 | L63: 3.1025 | M63: 3.085 | O63: =K63-K4 -> 0.07404762 | P63: =L63-L4 -> 0.12147728
A64: 1971 | B64: 2.87 | C64: 2.9575 | D64: 2.93 | E64: 2.915 | F64: 2.8825 | G64: 3.06 | H64: 3.2375 | I64: 3.4225 | J64: 3.3775 | K64: 3.275 | L64: 3.2975 | M64: 3.2125 | O64: =K64-K5 -> 0.1325 | P64: =L64-L5 -> 0.11321429
A65: 1972 | B65: 3.1325 | C65: 3.0725 | D65: 3.0975 | E65: 3.19 | F65: 3.285 | G65: 3.2525 | H65: 3.285 | I65: 3.31 | J65: 3.3925 | K65: 3.49 | L65: 3.585 | M65: 3.8675 | O65: =K65-K6 -> 0.095125 | P65: =L65-L6 -> 0.17829546
A66: 1973 | B66: 3.73 | C66: 3.7775 | D66: 4.285 | E66: 4.3575 | F66: 4.62 | G66: 6.56 | H66: 7.18 | I66: 8.26 | J66: 9.29 | K66: 6.95 | L66: 6.565 | M66: 5.78 | O66: =K66-K7 -> 0.50684211 | P66: =L66-L7 -> 0.71931819
A67: 1974 | B67: 6.33 | C67: 6.45 | D67: 6.66 | E67: 6.46 | F67: 5.79 | G67: 5.56 | H67: 5.8825 | I67: 8.865 | J67: 8.9 | K67: 8.78 | L67: 9.56 | M67: 8.61 | O67: =K67-K8 -> 1.0985 | P67: =L67-L8 -> 0.97173914
A68: 1975 | B68: 7.42 | C68: 6.99 | D68: 6.13 | E68: 6.035 | F68: 5.99 | G68: 5.21 | H68: 5.19 | I68: 6.38 | J68: 6.525 | K68: 6.17 | L68: 5.775 | M68: 5.03 | O68: =K68-K9 -> 0.43559524 | P68: =L68-L9 -> 0.52923914
A69: 1976 | B69: 5.39 | C69: 5.255 | D69: 5.18 | E69: 5.1425 | F69: 5.18 | G69: 5.975 | H69: 6.97 | I69: 7.7725 | J69: 6.99 | K69: 7.585 | L69: 6.79 | M69: 6.8 | O69: =K69-K10 -> 0.77476191 | P69: =L69-L10 -> 0.3775
A70: 1977 | B70: 6.41 | C70: 6.97 | D70: 7.2 | E70: 7.45 | F70: 7.76 | G70: 7.71 | H70: 7.975 | I70: 6.56 | J70: 5.75 | K70: 5.69 | L70: 5.58 | M70: 6.22 | O70: =K70-K11 -> 0.42607143 | P70: =L70-L11 -> 0.26916667
A71: 1978 | B71: 6.04 | C71: 5.96 | D71: 5.885 | E71: 6.3625 | F71: 6.455 | G71: 6.86 | H71: 6.79 | I71: 6.25 | J71: 6.58 | K71: 6.8 | L71: 7.31 | M71: 7.07 | O71: =K71-K12 -> 0.290375 | P71: =L71-L12 -> 0.47181819
A72: 1979 | B72: 6.8 | C72: 6.905 | D72: 7.2 | E72: 7.1975 | F72: 7.1875 | G72: 7.295 | H72: 8.33 | I72: 8.02 | J72: 7.37 | K72: 7.48 | L72: 7.37 | M72: 6.79 | O72: =K72-K13 -> 0.3481579 | P72: =L72-L13 -> 0.65163044
A73: 1980 | B73: 7.55 | C73: 7.49 | D73: 7.555 | E73: 7.245 | F73: 6.695 | G73: 6.715 | H73: 7.05 | I73: 8.4 | J73: 8.23 | K73: 8.8 | L73: 9.23 | M73: 9.305 | O73: =K73-K14 -> 0.41392858 | P73: =L73-L14 -> 0.6577174
A74: 1981 | B74: 8.97 | C74: 8.69 | D74: 8.48 | E74: 8.41 | F74: 8.71 | G74: 8.34 | H74: 7.8 | I74: 7.98 | J74: 7.45 | K74: 6.87 | L74: 6.76 | M74: 6.61 | O74: =K74-K15 -> 0.23011905 | P74: =L74-L15 -> 0.19522728
... A114: 2021 | B114: 11.18 | C114: 12.03 | D114: 12.5275 | E114: 12.6525 | F114: 13.8475 | G114: 14.61 | H114: 14.8 | I114: 14.23 | J114: 13.7975 | K114: 13.08 | L114: 12.625 | M114: 12.685 | O114: =K114-K55 -> 0.27 | P114: =L114-L55 -> 0.32297619
A115: 2022 | B115: 12.83 | C115: 13.6925 | D115: 15.55 | G115: =(SUM(G110:G114)-SUM(G51:G55))/5+G56 -> 14.001957 | H115: =(SUM(H110:H114)-SUM(H51:H55))/5+H56 -> 14.063573 | K115: =(SUM(K110:K114)-SUM(K51:K55))/5+K56+0.5 -> 15.390533 | L115: =(SUM(L110:L114)-SUM(L51:L55))/5+L56+0.5 -> 14.618267 | O115: =K115-K56 -> 0.78339029 | P115: =L115-L56 -> 0.80517133
A116: 2023 | K116: =(SUM(K111:K115)-SUM(K52:K56))/5+K57+0.5 -> 14.141118 | L116: =(SUM(L111:L115)-SUM(L52:L56))/5+L57+0.5 -> 13.753706 | O116: =K116-K57 -> 0.89824335 | P116: =L116-L57 -> 0.90984195
A117: 2024 | K117: =(SUM(K112:K116)-SUM(K53:K57))/5+K58+0.5 -> 11.180306 | L117: =(SUM(L112:L116)-SUM(L53:L57))/5+L58+0.5 -> 11.055723 | O117: =K117-K58 -> 1.0381815 | P117: =L117-L58 -> 1.0270277
A118: 2025 | K118: =(SUM(K113:K117)-SUM(K54:K58))/5+K59+0.5 -> 11.448868 | L118: =(SUM(L113:L117)-SUM(L54:L58))/5+L59+0.5 -> 11.19139
A120: November Futures Low
A121: Contract Year | B121: Dec | C121: Jan | D121: Feb | E121: Mar | F121: Apr | G121: May | H121: Jun | I121: Jul | J121: Aug | K121: Sep | L121: Oct | M121: Nov | O121: =_xlfn.CONCAT(K121," ","Error") -> Sep Error | P121: =_xlfn.CONCAT(L121," ","Error") -> Oct Error
A122: 1970 | B122: 2.4075 | C122: 2.425 | D122: 2.47 | E122: 2.5125 | F122: 2.5275 | G122: 2.5575 | H122: 2.5775 | I122: 2.8175 | J122: 2.76 | K122: 2.75 | L122: 2.8475 | M122: 3.01 | O122: =K4-K122 -> 0.09595238 | P122: =L4-L122 -> 0.13352272
A123: 1971 | B123: 2.7575 | C123: 2.78 | D123: 2.8325 | E123: 2.82 | F123: 2.8075 | G123: 2.825 | H123: 2.995 | I123: 3.2 | J123: 3.125 | K123: 3.0525 | L123: 3.07 | M123: 2.9775 | O123: =K5-K123 -> 0.09 | P123: =L5-L123 -> 0.11428571
A124: 1972 | B124: 3.045 | C124: 2.9575 | D124: 2.96 | E124: 3.06 | F124: 3.14 | G124: 3.1375 | H124: 3.1575 | I124: 3.1625 | J124: 3.17 | K124: 3.3125 | L124: 3.3125 | M124: 3.5125 | O124: =K6-K124 -> 0.082375 | P124: =L6-L124 -> 0.09420454
A125: 1973 | B125: 3.305 | C125: 3.4525 | D125: 3.55 | E125: 3.775 | F125: 3.985 | G125: 4.44 | H125: 5.62 | I125: 5.55 | J125: 6.81 | K125: 5.99 | L125: 5.18 | M125: 5.22 | O125: =K7-K125 -> 0.45315789 | P125: =L7-L125 -> 0.66568181
A126: 1974 | B126: 5.77 | C126: 5.785 | D126: 6.13 | E126: 5.68 | F126: 5.06 | G126: 5.08 | H126: 5.16 | I126: 5.75 | J126: 7.14 | K126: 6.925 | L126: 7.6 | M126: 7.25 | O126: =K8-K126 -> 0.7565 | P126: =L8-L126 -> 0.98826086
A127: 1975 | B127: 6.61 | C127: 5.67 | D127: 5.125 | E127: 4.96 | F127: 5.12 | G127: 4.82 | H127: 4.76 | I127: 4.88 | J127: 5.66 | K127: 5.445 | L127: 4.75 | M127: 4.64 | O127: =K9-K127 -> 0.28940476 | P127: =L9-L127 -> 0.49576086
A128: 1976 | B128: 4.84 | C128: 4.83 | D128: 4.965 | E128: 4.9025 | F128: 4.89 | G128: 5.0425 | H128: 5.855 | I128: 6.18 | J128: 5.9 | K128: 6.14 | L128: 6.04 | M128: 6.245 | O128: =K10-K128 -> 0.67023809 | P128: =L10-L128 -> 0.3725
A129: 1977 | B129: 6.05 | C129: 6.3 | D129: 6.795 | E129: 6.945 | F129: 6.86 | G129: 6.99 | H129: 6.53 | I129: 5.56 | J129: 4.97 | K129: 5.005 | L129: 5.08 | M129: 5.485 | O129: =K11-K129 -> 0.25892857 | P129: =L11-L129 -> 0.23083333
A130: 1978 | B130: 5.785 | C130: 5.54 | D130: 5.635 | E130: 5.85 | F130: 5.91 | G130: 6.01 | H130: 6.055 | I130: 5.88 | J130: 5.855 | K130: 6.28 | L130: 6.525 | M130: 6.3725 | O130: =K12-K130 -> 0.229625 | P130: =L12-L130 -> 0.31318181
A131: 1979 | B131: 6.47 | C131: 6.56 | D131: 6.795 | E131: 6.945 | F131: 6.92 | G131: 7.03 | H131: 7.19 | I131: 7.015 | J131: 6.84 | K131: 6.905 | L131: 6.25 | M131: 6.355 | O131: =K13-K131 -> 0.2268421 | P131: =L13-L131 -> 0.46836956
A132: 1980 | B132: 7.29 | C132: 7 | D132: 7.09 | E132: 6.46 | F132: 6.31 | G132: 6.43 | H132: 6.385 | I132: 6.985 | J132: 7.48 | K132: 7.84 | L132: 7.8625 | M132: 8.62 | O132: =K14-K132 -> 0.54607142 | P132: =L14-L132 -> 0.7097826
A133: 1981 | B133: 7.49 | C133: 7.8625 | D133: 8 | E133: 7.73 | F133: 8.165 | G133: 7.62 | H133: 7.14 | I133: 7.28 | J133: 6.62 | K133: 6.365 | L133: 6.415 | M133: 6.25 | O133: =K15-K133 -> 0.27488095 | P133: =L15-L133 -> 0.14977272
... A173: 2021 | B173: 10.2225 | C173: 10.97 | D173: 11.3575 | E173: 11.84 | F173: 12.4275 | G173: 13.2575 | H173: 12.405 | I173: 13.005 | J173: 12.7725 | K173: 12.49 | L173: 11.845 | M173: 11.9225 | O173: =K55-K173 -> 0.32 | P173: =L55-L173 -> 0.45702381
A174: 2022 | B174: 12.0475 | C174: 12.74 | D174: 13.6225 | G174: =(SUM(G169:G173)-SUM(G51:G55))/5+G56 -> 13.226457 | H174: =(SUM(H169:H173)-SUM(H51:H55))/5+H56 -> 12.899073 | K174: =(SUM(K169:K173)-SUM(K51:K55))/5+K56-0.5 -> 13.760033 | L174: =(SUM(L169:L173)-SUM(L51:L55))/5+L56-0.5 -> 12.993767 | O174: =K56-K174 -> 0.84710971 | P174: =L56-L174 -> 0.81932867
A175: 2023 | K175: =(SUM(K170:K174)-SUM(K52:K56))/5+K57-0.5 -> 12.283518 | L175: =(SUM(L170:L174)-SUM(L52:L56))/5+L57-0.5 -> 11.905806 | O175: =K57-K175 -> 0.95935665 | P175: =L57-L175 -> 0.93805805
A176: 2024 | K176: =(SUM(K171:K175)-SUM(K53:K57))/5+K58-0.5 -> 9.0451865 | L176: =(SUM(L171:L175)-SUM(L53:L57))/5+L58-0.5 -> 8.9587434 | O176: =K58-K176 -> 1.0969385 | P176: =L58-L176 -> 1.0699523
A177: 2025 | K177: =(SUM(K172:K176)-SUM(K54:K58))/5+K59-0.5 -> 8.9982238 | L177: =(SUM(L172:L176)-SUM(L54:L58))/5+L59-0.5 -> 8.7595138
A179: January Futures Average
A180: Contract Year | B180: Feb | C180: Mar | D180: Apr | E180: May | F180: Jun | G180: Jul | H180: Aug | I180: Sep | J180: Oct | K180: Nov | L180: Dec | M180: Jan
A181: 1971 | B181: 2.5418421 | C181: 2.5757143 | D181: 2.6253409 | E181: 2.628625 | F181: 2.7695454 | G181: 2.9794318 | H181: 2.8908333 | I181: 2.8985714 | J181: 3.0272727 | K181: 3.0590789 | L181: 2.9552273 | M181: 3.0038462
A182: 1972 | B182: 2.9181579 | C182: 2.9105435 | D182: 2.8789286 | E182: 2.962375 | F182: 3.1671591 | G182: 3.3369048 | H182: 3.2406818 | I182: 3.1815476 | J182: 3.2166667 | K182: 3.137619 | L182: 3.1333333 | M182: 3.0748214
A183: 1973 | B183: 3.053375 | C183: 3.1707954 | D183: 3.25375 | E183: 3.2329545 | F183: 3.2585227 | G183: 3.26 | H183: 3.3552174 | I183: 3.443 | J183: 3.4401136 | K183: 3.68275 | L183: 4.1739474 | M183: 4.4626667
A184: 1974 | B184: 3.9194737 | C184: 4.065 | D184: 4.291375 | E184: 5.0363636 | F184: 6.1581579 | G184: 6.7654762 | H184: 7.6966304 | I184: 6.4598684 | J184: 5.8625 | K184: 5.677619 | L184: 6.0081579 | M184: 6.1596667
A185: 1975 | B185: 6.3419444 | C185: 6.1890476 | D185: 5.4060714 | E185: 5.4 | F185: 5.494125 | G185: 7.10625 | H185: 7.8259091 | I185: 7.74825 | J185: 8.7323913 | K185: 7.9194737 | L185: 7.3689286 | M185: 6.5066667
A186: 1976 | B186: 5.8260526 | C186: 5.6335 | D186: 5.5865909 | E186: 5.0479762 | F186: 5.0079762 | G186: 5.6356818 | H186: 6.2014286 | I186: 5.8320238 | J186: 5.3534783 | K186: 4.8606579 | L186: 4.6353571 | M186: 4.7201786
A187: 1977 | B187: 5.1528947 | C187: 5.0913043 | D187: 5.1195238 | E187: 5.499125 | F187: 6.5315909 | G187: 7.0220238 | H187: 6.5805682 | I187: 6.8719048 | J187: 6.487619 | K187: 6.683125 | L187: 6.9278571 | M187: 7.1225
A188: 1978 | B188: 7.0153947 | C188: 7.208913 | D188: 7.324875 | E188: 7.358625 | F188: 7.2430682 | G188: 6.0055 | H188: 5.3663043 | I188: 5.34 | J188: 5.3813095 | K188: 5.9813095 | L188: 5.9583333 | M188: 5.80375
A189: 1979 | B189: 5.8256579 | C189: 6.18125 | D189: 6.234 | E189: 6.3554545 | F189: 6.3771591 | G189: 6.141875 | H189: 6.2947826 | I189: 6.578 | J189: 6.9152273 | K189: 6.79875 | L189: 6.83825 | M189: 6.8498333
A190: 1980 | B190: 7.0515789 | C190: 7.1770454 | D190: 7.119625 | E190: 7.2873864 | F190: 7.8780952 | G190: 7.6588095 | H190: 7.2776087 | I190: 7.2875 | J190: 6.9171739 | K190: 6.7734524 | L190: 6.6360526 | M190: 6.4228846
A191: 1981 | B191: 7.456375 | C191: 7.0796428 | D191: 6.6919048 | E191: 6.6991667 | F191: 6.7927381 | G191: 7.8239773 | H191: 7.9555952 | I191: 8.585 | J191: 8.8180435 | K191: 9.2543055 | L191: 7.9809524 | M191: 7.9128571
A192: 1982 | B192: 8.4459211 | C192: 8.2745454 | D192: 8.5894048 | E192: 8.09525 | F192: 7.6682954 | G192: 7.8139773 | H192: 7.2261905 | I192: 6.8507143 | J192: 6.77125 | K192: 6.544875 | L192: 6.2864773 | M192: 6.3051923
... A231: 2021 | B231: 9.2146053 | C231: 8.8019318 | D231: 8.5802381 | E231: 8.53025 | F231: 8.7659091 | G231: 8.9856818 | H231: 9.0978571 | I231: 10.007024 | J231: 10.547727 | K231: 11.4475 | L231: 12.022976 | M231: 11.513158
A232: 2022 | B232: #REF! | C232: 12.270217 | D232: 12.92869 | I232: 12.5 | J232: 12.6 | K232: 12.371548 | L232: 12.895
A233: 2023 | I233: =MROUND(FORECAST(K233,I182:I232,K182:K232),0.1) -> 14.5 | J233: =MROUND(FORECAST(L233,J182:J232,L182:L232),0.1) -> 14.3 | K233: =[3]Prices!$B$637 -> 14.420119 | L233: =[3]Prices!$B$638 -> 14.744167
A234: 2024 | K234: =[3]Prices!$B$649 -> 13.44869 | L234: =[3]Prices!$B$650 -> 13.10925
A235: 2025 | K235: =[3]Prices!$B$661 -> 9.95075 | L235: =[3]Prices!$B$662 -> 9.835
A236: 2026 | K236: =[3]Prices!$B$673 -> 11 | L236: =[3]Prices!$B$675 -> 11.75
A237: January Futures High
A238: Contract Year | B238: Feb | C238: Mar | D238: Apr | E238: May | F238: Jun | G238: Jul | H238: Aug | I238: Sep | J238: Oct | K238: Nov | L238: Dec | M238: Jan | O238: =_xlfn.CONCAT(K238," ","Error") -> Nov Error | P238: =_xlfn.CONCAT(L238," ","Error") -> Dec Error
A239: 1971 | B239: 2.5775 | C239: 2.59 | D239: 2.6825 | E239: 2.67 | F239: 3.0125 | G239: 3.07 | H239: 3.035 | I239: 2.9725 | J239: 3.15 | K239: 3.1125 | L239: 3.0075 | M239: 3.0825 | O239: =K239-K181 -> 0.05342106 | P239: =L239-L181 -> 0.05227273
A240: 1972 | B240: 2.975 | C240: 2.9575 | D240: 2.9225 | E240: 3.1 | F240: 3.2775 | G240: 3.46 | H240: 3.3625 | I240: 3.315 | J240: 3.32 | K240: 3.2575 | L240: 3.185 | M240: 3.1325 | O240: =K240-K182 -> 0.11988096 | P240: =L240-L182 -> 0.05166667
A241: 1973 | B241: 3.1375 | C241: 3.2325 | D241: 3.3225 | E241: 3.2875 | F241: 3.325 | G241: 3.3525 | H241: 3.4375 | I241: 3.53 | J241: 3.5975 | K241: 3.895 | L241: 4.44 | M241: 5 | O241: =K241-K183 -> 0.21225 | P241: =L241-L183 -> 0.26605264
A242: 1974 | B242: 4.26 | C242: 4.33 | D242: 4.6175 | E242: 6.42 | F242: 6.995 | G242: 8.08 | H242: 9.15 | I242: 6.93 | J242: 6.615 | K242: 6.37 | L242: 6.44 | M242: 6.43 | O242: =K242-K184 -> 0.69238096 | P242: =L242-L184 -> 0.43184211
A243: 1975 | B243: 6.73 | C243: 6.48 | D243: 5.81 | E243: 5.59 | F243: 5.945 | G243: 8.875 | H243: 8.84 | I243: 8.855 | J243: 9.61 | K243: 8.8 | L243: 7.87 | M243: 7.12 | O243: =K243-K185 -> 0.88052632 | P243: =L243-L185 -> 0.50107143
A244: 1976 | B244: 6.19 | C244: 6.09 | D244: 6.04 | E244: 5.27 | F244: 5.275 | G244: 6.455 | H244: 6.635 | I244: 6.2 | J244: 5.875 | K244: 5.12 | L244: 5.07 | M244: 4.89 | O244: =K244-K186 -> 0.25934211 | P244: =L244-L186 -> 0.43464286
A245: 1977 | B245: 5.245 | C245: 5.215 | D245: 5.26 | E245: 6.025 | F245: 7.06 | G245: 7.825 | H245: 7.05 | I245: 7.65 | J245: 6.875 | K245: 6.965 | L245: 7.12 | M245: 7.295 | O245: =K245-K187 -> 0.281875 | P245: =L245-L187 -> 0.19214286
A246: 1978 | B246: 7.235 | C246: 7.48 | D246: 7.79 | E246: 7.75 | F246: 7.99 | G246: 6.605 | H246: 5.865 | I246: 5.77 | J246: 5.655 | K246: 6.345 | L246: 6.165 | M246: 6.045 | O246: =K246-K188 -> 0.36369048 | P246: =L246-L188 -> 0.20666667
A247: 1979 | B247: 5.95 | C247: 6.41 | D247: 6.505 | E247: 6.89 | F247: 6.84 | G247: 6.295 | H247: 6.63 | I247: 6.8625 | J247: 7.385 | K247: 7.2 | L247: 7.06 | M247: 7.08 | O247: =K247-K189 -> 0.40125 | P247: =L247-L189 -> 0.22175
A248: 1980 | B248: 7.265 | C248: 7.275 | D248: 7.285 | E248: 7.4 | F248: 8.42 | G248: 8.1 | H248: 7.5 | I248: 7.65 | J248: 7.54 | K248: 6.97 | L248: 6.86 | M248: 6.665 | O248: =K248-K190 -> 0.19654762 | P248: =L248-L190 -> 0.22394737
A249: 1981 | B249: 7.71 | C249: 7.42 | D249: 6.85 | E249: 6.87 | F249: 7.19 | G249: 8.47 | H249: 8.36 | I249: 9.01 | J249: 9.51 | K249: 9.58 | L249: 9.38 | M249: 8.275 | O249: =K249-K191 -> 0.32569445 | P249: =L249-L191 -> 1.3990476
A250: 1982 | B250: 8.65 | C250: 8.585 | D250: 8.88 | E250: 8.5 | F250: 7.965 | G250: 8.18 | H250: 7.645 | I250: 7.05 | J250: 7.11 | K250: 6.79 | L250: 6.66 | M250: 6.46 | O250: =K250-K192 -> 0.245125 | P250: =L250-L192 -> 0.37352273
... A289: 2021 | B289: 9.325 | C289: 9.2625 | D289: 8.845 | E289: 8.66 | F289: 8.8975 | G289: 9.1625 | H289: 9.7225 | I289: 10.5025 | J289: 10.885 | K289: 12 | L289: 13.0825 | M289: 11.97 | O289: =K289-K231 -> 0.5525 | P289: =L289-L231 -> 1.0595238
A290: 2022 | B290: 12.435 | C290: 12.595 | D290: 13.815 | I290: 12.794123 | J290: 12.922865 | K290: 12.733126 | L290: 13.394625 | O290: =K290-K232 -> 0.36157857 | P290: =L290-L232 -> 0.499625
A291: 2023 | I291: 14.786115 | J291: 14.592986 | K291: 14.73818 | L291: 15.262955 | O291: =K291-K233 -> 0.31806095 | P291: =L291-L233 -> 0.5187881
A292: 2024 | K292: =(SUM(K287:K291)-SUM(K229:K233))/5+K234 -> 13.790554 | L292: =(SUM(L287:L291)-SUM(L229:L233))/5+L234 -> 13.645821
A293: 2025 | K293: =(SUM(K288:K292)-SUM(K230:K234))/5+K235 -> 10.325201 | L293: =(SUM(L288:L292)-SUM(L230:L234))/5+L235 -> 10.421735
K294: =(SUM(K289:K293)-SUM(K231:K235))/5+K236 -> 11.389691 | L294: =(SUM(L289:L293)-SUM(L231:L235))/5+L236 -> 12.390248
A295: January Futures Low
...

Sheet Spreads Averages
A2: Jul - Nov Spread Average
A3: Contract Year | B3: Aug | C3: Sep | D3: Oct | E3: Nov | F3: Dec | G3: Jan | H3: Feb | I3: Mar | J3: Apr | K3: May | L3: Jun | M3: Jul
A4: 1971 | D4: 38.75 | E4: 28.828947 | F4: 26.113636 | G4: 25.5125 | H4: 24.513157 | I4: 21.5 | J4: 11.738095 | K4: 10.25 | L4: 6.920454 | M4: 4.875
A5: 1972 | E5: 22.857142 | F5: 17.416666 | G5: 20.285714 | H5: 26.45 | I5: 32.727272 | J5: 35.575 | K5: 34.011363 | L5: 26.136363 | M5: 28.211538
A6: 1973 | C6: 27 | D6: 22.977272 | E6: 33.925 | F6: 59.592105 | G6: 65.357142 | H6: 134.64474 | I6: 157.59091 | J6: 172.5125 | K6: 332.73864 | L6: 466.44737 | M6: 242.28571
A7: 1974 | C7: 42.802631 | D7: 23.488636 | E7: 19.023809 | F7: 15 | G7: 14.113636 | H7: 26.041666 | I7: 19.369047 | J7: 18.797619 | K7: 11.613636 | L7: 6.925 | M7: 3.416666
A8: 1975 | C8: 64.833333 | D8: 104.58696 | E8: 89.421052 | F8: 65.642857 | G8: 33.579545 | H8: 10.763157 | I8: 8.3375 | J8: 13.443181 | K8: 12.154761 | L8: 14.75 | M8: 9.3
A9: 1976 | D9: 3.613636 | E9: -6.921052 | F9: -13.559523 | G9: -13.428571 | H9: -12.723684 | I9: -13.717391 | J9: -15.666666 | K9: -12.5125 | L9: -13.443181 | M9: -15.553571
A10: 1977 | D10: 37.966666 | E10: 58.7625 | F10: 60.023809 | G10: 52.5 | H10: 49.539473 | I10: 130.19565 | J10: 255.7 | K10: 222.9375 | L10: 107.53409 | M10: 35.673076
A11: 1978 | D11: 5.178571 | E11: 19.083333 | F11: 22.5 | G11: 19.5 | H11: 9.131578 | I11: 70.272727 | J11: 75.775 | K11: 83.352272 | L11: 53.261363 | M11: 56.75
A12: 1979 | D12: 39.772727 | E12: 41.8 | F12: 43.4875 | G12: 41.215909 | H12: 71.947368 | I12: 63.772727 | J12: 49.75 | K12: 18.215909 | L12: 3.154761 | M12: 3.982142
A13: 1980 | C13: 14.535714 | D13: -5.195652 | E13: -15.333333 | F13: -18.210526 | G13: -24.925 | H13: -26.6875 | I13: -34.761904 | J13: -34.166666 | K13: -30.142857 | L13: -31.214285 | M13: -26.65
A14: 1981 | C14: 67.357142 | D14: 110.29348 | E14: 138.52778 | F14: 59.333333 | G14: -1.607142 | H14: -25.710526 | I14: -30.363636 | J14: -30.869047 | K14: -20.2125 | L14: -27.522727 | M14: -35.583333
A15: 1982 | C15: -14.785714 | D15: -12.352272 | E15: -10.5 | F15: -4.079545 | G15: -8.2125 | H15: -14.5 | I15: -9.717391 | J15: -9.738095 | K15: -8.675 | L15: -11.920454 | M15: -2.071428
A16: 1983 | B16: -4.571428 | C16: -6.214285 | D16: -0.130952 | E16: 8.4875 | F16: 3.333333 | G16: -4.845238 | H16: -14.644736 | I16: -21.445652 | J16: -24.65 | K16: -21.869047 | L16: -19.78409 | M16: -28.942307
A17: 1984 | B17: 161.81522 | C17: 191.22619 | D17: 180.98809 | E17: 160.5119 | F17: 126.69048 | G17: 68.607142 | H17: 39.9875 | I17: 65.829545 | J17: 75.175 | K17: 120.68182 | L17: 55.595238 | M17: 37.196428
A18: 1985 | B18: 38.945652 | C18: 26.710526 | D18: 11.445652 | E18: 13.607142 | F18: 4.6 | G18: 3.340909 | H18: -1.026315 | I18: 2.20238 | J18: -4.178571 | K18: -6.53409 | L18: 9.3125 | M18: 0.1
A19: 1986 | B19: 10.625 | C19: 8.4375 | D19: 12.945652 | E19: 15.3 | F19: 20.773809 | G19: 26.306818 | H19: 24.342105 | I19: 20.475 | J19: 14.761363 | K19: 13.071428 | L19: 25.333333 | M19: 34.433333
A20: 1987 | B20: 9.333333 | C20: 1.654761 | D20: 5.706521 | E20: 9.486842 | F20: 6.988636 | G20: 13.571428 | H20: 15.618421 | I20: 11.386363 | J20: 5.059523 | K20: -6.9625 | L20: -14.068181 | M20: 11.65
A21: 1988 | B21: 9.357142 | C21: 13.285714 | D21: 15.602272 | E21: 15.1875 | F21: 27.818181 | G21: 5.45 | H21: -7.175 | I21: -11.956521 | J21: -13.8125 | K21: -16.214285 | L21: 8.375 | M21: 1.807692
A22: 1989 | B22: 129.29348 | C22: 111.25 | D22: 88.964285 | E22: 72.821428 | F22: 95.071428 | G22: 68.595238 | H22: 43.197368 | I22: 41.352272 | J22: 19.7125 | K22: 39.829545 | L22: 81.102272 | M22: 67.365384
A23: 1990 | B23: 27.163043 | C23: 26.675 | D23: 19.647727 | E23: 12.607142 | F23: -3.0625 | G23: -9.795454 | H23: -6.43421 | I23: -9.625 | J23: -11 | K23: -13.931818 | L23: -18.809523 | M23: -22
A24: 1991 | B24: 30.923913 | C24: 38.539473 | D24: 39.391304 | E24: 12.440476 | F24: 3.9125 | G24: -8.715909 | H24: -16.5 | I24: -18.3375 | J24: -18.022727 | K24: -13.477272 | L24: -10.3875 | M24: -1.95
A25: 1992 | B25: 20.170454 | C25: 36.125 | D25: 10.586956 | E25: 1.9875 | F25: -7.821428 | G25: -11.875 | H25: -15.18421 | I25: -15.829545 | J25: -14.565789 | K25: -14.8375 | L25: -15.340909 | M25: -10.116666
A26: 1993 | B26: 0.630952 | C26: -1.369047 | D26: -7.704545 | E26: -7.275 | F26: -5.875 | G26: -5.2625 | H26: -8.526315 | I26: -8.891304 | J26: -7.273809 | K26: -0.5125 | L26: 0.863636 | M26: -3.946428
A27: 1994 | B27: 61.613636 | C27: 33.404761 | D27: 18.238095 | E27: 43.845238 | F27: 56.321428 | G27: 52.571428 | H27: 39.697368 | I27: 35.673913 | J27: 41.197368 | K27: 41.761904 | L27: 25.363636 | M27: 39.096153
... A53: 2020 | B53: -12.613636 | C53: -12.025 | D53: -0.043478261 | E53: -3.725 | F53: -4.1309524 | G53: -6.0714286 | H53: -9.1315789 | I53: -0.96590909 | J53: -5.0357143 | K53: -7.2625 | L53: -5.9761905 | M53: 9.7954545
A54: 2021 | B54: 9.1428571 | C54: 42.928571 | D54: 65.5 | E54: 107.3125 | F54: 139.25 | G54: 198.03947 | H54: #REF! | I54: 172.16304 | J54: 154.89286 | K54: 171.1125 | L54: 95.842532
A55: 2022 | K55: =('Futures Averages'!K754-'Futures Averages'!G56)*100 -> 317.02381 | L55: =('Futures Averages'!L754-'Futures Averages'!H56)*100 -> 340.08333
A59: Jul - Nov Spread High
A60: Contract Year | B60: Aug | C60: Sep | D60: Oct | E60: Nov | F60: Dec | G60: Jan | H60: Feb | I60: Mar | J60: Apr | K60: May | L60: Jun | M60: Jul | O60: =_xlfn.CONCAT(K60," ","Error") -> May Error | P60: =_xlfn.CONCAT(L60," ","Error") -> Jun Error
A61: 1971 | D61: 42 | E61: 36.75 | F61: 30 | G61: 27.5 | H61: 28 | I61: 27 | J61: 13.5 | K61: 12.5 | L61: 11 | M61: 11.5 | O61: =K61-K4 -> 2.25 | P61: =L61-L4 -> 4.079546
A62: 1972 | E62: 30.25 | F62: 20.5 | G62: 23 | H62: 30.25 | I62: 36 | J62: 40 | K62: 37.75 | L62: 30 | M62: 32.25 | O62: =K62-K5 -> 3.738637 | P62: =L62-L5 -> 3.863637
A63: 1973 | C63: 27.5 | D63: 27 | E63: 45 | F63: 69.25 | G63: 87.5 | H63: 177.5 | I63: 199.25 | J63: 220 | K63: 427 | L63: 533 | M63: 429.25 | O63: =K63-K6 -> 94.261364 | P63: =L63-L6 -> 66.552632
A64: 1974 | C64: 62 | D64: 29.5 | E64: 22.5 | F64: 18.75 | G64: 21.75 | H64: 36.25 | I64: 29 | J64: 29.5 | K64: 15.25 | L64: 14 | M64: 14.5 | O64: =K64-K7 -> 3.636364 | P64: =L64-L7 -> 7.075
A65: 1975 | C65: 69.5 | D65: 128.5 | E65: 104.5 | F65: 78 | G65: 53 | H65: 17.5 | I65: 16 | J65: 18.75 | K65: 17.5 | L65: 21.75 | M65: 12.5 | O65: =K65-K8 -> 5.345239 | P65: =L65-L8 -> 7
A66: 1976 | D66: 14.75 | E66: -2.5 | F66: -8.25 | G66: -10.5 | H66: -11.25 | I66: -11.75 | J66: -13.75 | K66: -9 | L66: -9.5 | M66: -12.5 | O66: =K66-K9 -> 3.5125 | P66: =L66-L9 -> 3.943181
A67: 1977 | D67: 67.5 | E67: 69 | F67: 63.25 | G67: 62.5 | H67: 70 | I67: 174.5 | J67: 309.5 | K67: 290.25 | L67: 205.5 | M67: 75 | O67: =K67-K10 -> 67.3125 | P67: =L67-L10 -> 97.96591
A68: 1978 | D68: 7 | E68: 28.5 | F68: 28.75 | G68: 30.5 | H68: 12.75 | I68: 123.25 | J68: 92.5 | K68: 103 | L68: 64.5 | M68: 79 | O68: =K68-K11 -> 19.647728 | P68: =L68-L11 -> 11.238637
A69: 1979 | D69: 53.5 | E69: 50.25 | F69: 49.25 | G69: 45.5 | H69: 85 | I69: 74.25 | J69: 67.75 | K69: 31 | L69: 39 | M69: 16 | O69: =K69-K12 -> 12.784091 | P69: =L69-L12 -> 35.845239
A70: 1980 | C70: 21.5 | D70: 6.75 | E70: -12.5 | F70: -15 | G70: -22.25 | H70: -18 | I70: -27 | J70: -30.75 | K70: -26 | L70: -29 | M70: -7.5 | O70: =K70-K13 -> 4.142857 | P70: =L70-L13 -> 2.214285
A71: 1981 | C71: 88.5 | D71: 152.75 | E71: 164.5 | F71: 121.5 | G71: 45 | H71: -16 | I71: -24.25 | J71: -23.5 | K71: -10.25 | L71: -10.75 | M71: -23.25 | O71: =K71-K14 -> 9.9625 | P71: =L71-L14 -> 16.772727
A72: 1982 | C72: -4 | D72: -9.5 | E72: -5.5 | F72: 3.5 | G72: -4 | H72: -9 | I72: -5.5 | J72: -6.25 | K72: -5 | L72: -7.25 | M72: 4.5 | O72: =K72-K15 -> 3.675 | P72: =L72-L15 -> 4.670454
A73: 1983 | B73: -2 | C73: -4.5 | D73: 5.25 | E73: 14.75 | F73: 9 | G73: 1.5 | H73: -12 | I73: -18 | J73: -21.75 | K73: -16.25 | L73: -16.5 | M73: -26.5 | O73: =K73-K16 -> 5.619047 | P73: =L73-L16 -> 3.28409
A74: 1984 | B74: 194.5 | C74: 210.5 | D74: 196 | E74: 198.5 | F74: 140.25 | G74: 113.5 | H74: 52.25 | I74: 84.25 | J74: 90.75 | K74: 149 | L74: 99.5 | M74: 72 | O74: =K74-K17 -> 28.318182 | P74: =L74-L17 -> 43.904762
A75: 1985 | B75: 60 | C75: 49 | D75: 15.5 | E75: 19.5 | F75: 14.5 | G75: 10.5 | H75: 7.75 | I75: 6.25 | J75: 3.5 | K75: 6.25 | L75: 17 | M75: 9.25 | O75: =K75-K18 -> 12.78409 | P75: =L75-L18 -> 7.6875
A76: 1986 | B76: 22.75 | C76: 13.5 | D76: 20 | E76: 25.25 | F76: 29.25 | G76: 32.25 | H76: 30.5 | I76: 27.5 | J76: 18.25 | K76: 22 | L76: 29.75 | M76: 43.25 | O76: =K76-K19 -> 8.928572 | P76: =L76-L19 -> 4.416667
A77: 1987 | B77: 20.75 | C77: 3.75 | D77: 9 | E77: 12.5 | F77: 11 | G77: 16.75 | H77: 18.5 | I77: 13.25 | J77: 8.75 | K77: 3.5 | L77: -2 | M77: 28.75 | O77: =K77-K20 -> 10.4625 | P77: =L77-L20 -> 12.068181
A78: 1988 | B78: 13 | C78: 20.75 | D78: 23.5 | E78: 35.25 | F78: 39.75 | G78: 19 | H78: -1.5 | I78: -8.25 | J78: -9.75 | K78: -11.5 | L78: 44 | M78: 42.5 | O78: =K78-K21 -> 4.714285 | P78: =L78-L21 -> 35.625
A79: 1989 | B79: 151 | C79: 135.25 | D79: 110 | E79: 98.25 | F79: 104.75 | G79: 100.25 | H79: 50.75 | I79: 50.5 | J79: 31.5 | K79: 85.5 | L79: 97.5 | M79: 97.5 | O79: =K79-K22 -> 45.670455 | P79: =L79-L22 -> 16.397728
A80: 1990 | B80: 44 | C80: 35.75 | D80: 21.75 | E80: 19.75 | F80: 3.25 | G80: -7 | H80: -4 | I80: -6.5 | J80: -8.75 | K80: -10.5 | L80: -13.25 | M80: -4.25 | O80: =K80-K23 -> 3.431818 | P80: =L80-L23 -> 5.559523
A81: 1991 | B81: 45.25 | C81: 46.25 | D81: 56.75 | E81: 33.75 | F81: 13.75 | G81: -2 | H81: -12.5 | I81: -13.5 | J81: -14.5 | K81: -9.5 | L81: -6 | M81: 2 | O81: =K81-K24 -> 3.977272 | P81: =L81-L24 -> 4.3875
A82: 1992 | B82: 52.5 | C82: 48 | D82: 36 | E82: 10 | F82: -3.5 | G82: -6.5 | H82: -12.25 | I82: -14.25 | J82: -13 | K82: -13.25 | L82: -13.25 | M82: -4.75 | O82: =K82-K25 -> 1.5875 | P82: =L82-L25 -> 2.090909
A83: 1993 | B83: 6 | C83: 4.5 | D83: -6.25 | E83: -5.5 | F83: -4 | G83: -2.75 | H83: -7.25 | I83: -7.75 | J83: -4 | K83: 3.75 | L83: 6.25 | M83: 5.25 | O83: =K83-K26 -> 4.2625 | P83: =L83-L26 -> 5.386364
A84: 1994 | B84: 90.75 | C84: 48.5 | D84: 20.75 | E84: 58.75 | F84: 65.5 | G84: 62 | H84: 50 | I84: 41.75 | J84: 46 | K84: 52 | L84: 30.5 | M84: 45 | O84: =K84-K27 -> 10.238096 | P84: =L84-L27 -> 5.136364
... A104: 2014 | B104: 95.5 | C104: 136 | D104: 85.25 | E104: 141 | F104: 138.25 | G104: 163.25 | H104: 216 | I104: 242.25 | J104: 271.5 | K104: 264.75 | L104: 270.75 | M104: 254.25 | O104: =K104-K47 -> 16.202381 | P104: =L104-L47 -> 53.928572
A105: 2015 | B105: 28.5 | C105: 18.5 | D105: 48.5 | E105: 41.5 | F105: 46.25 | G105: 42.5 | H105: 37.25 | I105: 32.5 | J105: 26.25 | K105: 30.25 | L105: 35.75 | M105: 48 | O105: 7.325 | P105: =L105-L48 -> 9.261364
A106: 2016 | B106: 43.25 | C106: 21.5 | D106: 17.75 | E106: 10 | F106: -1.25 | G106: 0.75 | H106: -1.75 | I106: -4.25 | J106: 27.25 | K106: 33 | L106: 75 | M106: 94 | O106: 14.297619 | P106: =L106-L49 -> 49.761905
A107: 2017 | B107: 56.75 | C107: 49 | D107: 37.25 | E107: 43.75 | F107: 43.75 | G107: 60.5 | H107: 50.25 | I107: 27.5 | J107: 5.25 | K107: 9.25 | L107: -3 | M107: 34 | O107: 6.4886364 | P107: =L107-L50 -> 4.8068182
A108: 2018 | B108: 31 | C108: 20.5 | D108: 25.5 | E108: 20 | F108: 22.5 | G108: 8.5 | H108: 33 | I108: 47.5 | J108: 20 | K108: 4 | L108: -15.5 | M108: 12.75 | O108: 11.443182 | P108: =L108-L51 -> 5.452381
A109: 2019 | B109: 9.25 | C109: -5.5 | D109: -9.5 | E109: -6.5 | F109: -0.75 | G109: -10.5 | H109: -12 | I109: -19.25 | J109: -18.25 | K109: -20.75 | L109: -23.25 | M109: 5 | O109: 3.9772727 | P109: =L109-L52 -> 2.7375
A110: 2020 | B110: -8.25 | C110: -7.25 | D110: 7.5 | E110: 1.5 | F110: 1.25 | G110: 1.5 | H110: -4.5 | I110: 13.25 | J110: 11.75 | K110: -2.25 | L110: 4.5 | M110: 12.25 | O110: 5.0125 | P110: =L110-L53 -> 10.47619
A111: 2021 | B111: 25.5 | C111: 59.25 | D111: 78.25 | E111: 134.5 | F111: 191 | G111: 229 | H111: 205 | I111: 191.75 | J111: 196 | K111: 179.35634 | L111: 110.48949 | O111: 8.243842 | P111: =L111-L54 -> 14.646959
A112: 2022 | K112: =((SUM(K107:K111)-SUM(K50:K54))/5)+K55 -> 324.0569 | L112: =((SUM(L107:L111)-SUM(L50:L54))/5)+L55 -> 347.7073 | O112: =K112-K55 -> 7.0330866 | P112: =L112-L55 -> 7.6239697
A115: Jul - Nov Spread Low
A116: Contract Year | B116: Aug | C116: Sep | D116: Oct | E116: Nov | F116: Dec | G116: Jan | H116: Feb | I116: Mar | J116: Apr | K116: May | L116: Jun | M116: Jul | O116: =_xlfn.CONCAT(K116," ","Error") -> May Error | P116: =_xlfn.CONCAT(L116," ","Error") -> Jun Error
A117: 1971 | D117: 35.75 | E117: 21.75 | F117: 21.5 | G117: 23.75 | H117: 20.5 | I117: 14 | J117: 9.25 | K117: 6.25 | L117: 0.25 | M117: 1.5 | O117: =K4-K117 -> 4 | P117: =L4-L117 -> 6.670454
A118: 1972 | E118: 16.5 | F118: 15.5 | G118: 16 | H118: 22.75 | I118: 30 | J118: 31.25 | K118: 25 | L118: 23 | M118: 24.25 | O118: =K5-K118 -> 9.011363 | P118: =L5-L118 -> 3.136363
A119: 1973 | C119: 26.5 | D119: 19 | E119: 26.5 | F119: 44.5 | G119: 54.5 | H119: 94 | I119: 112.5 | J119: 118.5 | K119: 224.25 | L119: 372.5 | M119: 132.25 | O119: =K6-K119 -> 108.48864 | P119: =L6-L119 -> 93.947368
A120: 1974 | C120: 24.5 | D120: 15.5 | E120: 13 | F120: 9.75 | G120: 8.5 | H120: 14 | I120: 11.5 | J120: 10 | K120: 7 | L120: -2.25 | M120: -3.5 | O120: =K7-K120 -> 4.613636 | P120: =L7-L120 -> 9.175
A121: 1975 | C121: 55.5 | D121: 74.5 | E121: 71.5 | F121: 50 | G121: 16.5 | H121: 2 | I121: 1.5 | J121: 7.25 | K121: 7.75 | L121: 9.25 | M121: -4.5 | O121: =K8-K121 -> 4.404761 | P121: =L8-L121 -> 5.5
A122: 1976 | D122: -6.5 | E122: -9.5 | F122: -16.5 | G122: -15.25 | H122: -16 | I122: -15.75 | J122: -17.25 | K122: -17.25 | L122: -21 | M122: -20.25 | O122: =K9-K122 -> 4.7375 | P122: =L9-L122 -> 7.556819
A123: 1977 | D123: 8.5 | E123: 46.5 | F123: 55.75 | G123: 36 | H123: 40.25 | I123: 75.75 | J123: 196 | K123: 177 | L123: 49 | M123: 11 | O123: =K10-K123 -> 45.9375 | P123: =L10-L123 -> 58.53409
A124: 1978 | D124: 3 | E124: 9.5 | F124: 19 | G124: 12.75 | H124: 4.25 | I124: 21.25 | J124: 55.25 | K124: 58.5 | L124: 39.5 | M124: 33.25 | O124: =K11-K124 -> 24.852272 | P124: =L11-L124 -> 13.761363
A125: 1979 | D125: 28.5 | E125: 34 | F125: 39 | G125: 35 | H125: 45.25 | I125: 54.75 | J125: 25.25 | K125: 10.5 | L125: -16 | M125: -8.25 | O125: =K12-K125 -> 7.715909 | P125: =L12-L125 -> 19.154761
A126: 1980 | C126: 4 | D126: -17.5 | E126: -20.25 | F126: -22.25 | G126: -27.25 | H126: -31.75 | I126: -40 | J126: -37.5 | K126: -35 | L126: -33.5 | M126: -34.5 | O126: =K13-K126 -> 4.857143 | P126: =L13-L126 -> 2.285715
A127: 1981 | C127: 41.75 | D127: 76 | E127: 119 | F127: 30.5 | G127: -31.5 | H127: -33.5 | I127: -36 | J127: -34.25 | K127: -31.75 | L127: -45 | M127: -42 | O127: =K14-K127 -> 11.5375 | P127: =L14-L127 -> 17.477273
A128: 1982 | C128: -18 | D128: -16.25 | E128: -13.5 | F128: -10.5 | G128: -16 | H128: -19.5 | I128: -18.5 | J128: -13.5 | K128: -12.5 | L128: -16.5 | M128: -11.5 | O128: =K15-K128 -> 3.825 | P128: =L15-L128 -> 4.579546
A129: 1983 | B129: -8 | C129: -8 | D129: -5.5 | E129: 3.5 | F129: -3.5 | G129: -13.5 | H129: -19 | I129: -26.25 | J129: -26.75 | K129: -25.25 | L129: -22.25 | M129: -33 | O129: =K16-K129 -> 3.380953 | P129: =L16-L129 -> 2.46591
A130: 1984 | B130: 87 | C130: 171.5 | D130: 168.5 | E130: 114 | F130: 106.25 | G130: 39.75 | H130: 22.5 | I130: 48 | J130: 61.25 | K130: 77 | L130: 7.25 | M130: 12.25 | O130: =K17-K130 -> 43.681818 | P130: =L17-L130 -> 48.345238
A131: 1985 | B131: 14.5 | C131: 7.25 | D131: 7.5 | E131: 7.75 | F131: -8.25 | G131: -8.25 | H131: -6.25 | I131: -4.25 | J131: -14 | K131: -11.5 | L131: 3.25 | M131: -11.25 | O131: =K18-K131 -> 4.96591 | P131: =L18-L131 -> 6.0625
A132: 1986 | B132: 4 | C132: 2 | D132: 5 | E132: 1.25 | F132: 7 | G132: 20 | H132: 20.25 | I132: 16 | J132: 9.25 | K132: 1 | L132: 20.5 | M132: 22.75 | O132: =K19-K132 -> 12.071428 | P132: =L19-L132 -> 4.833333
A133: 1987 | B133: 2.25 | C133: -0.75 | D133: 2.5 | E133: 7.5 | F133: 3.75 | G133: 6.5 | H133: 12.75 | I133: 8.5 | J133: 0.75 | K133: -20 | L133: -21.75 | M133: -11.75 | O133: =K20-K133 -> 13.0375 | P133: =L20-L133 -> 7.681819
A134: 1988 | B134: 6.5 | C134: 6.75 | D134: 1 | E134: 8 | F134: 15 | G134: -6.25 | H134: -11 | I134: -14.25 | J134: -17 | K134: -20.5 | L134: -15.25 | M134: -42 | O134: =K21-K134 -> 4.285715 | P134: =L21-L134 -> 23.625
A135: 1989 | B135: 113 | C135: 88 | D135: 70.5 | E135: 56.5 | F135: 83 | G135: 39.25 | H135: 33 | I135: 32.25 | J135: 8 | K135: 21 | L135: 66.5 | M135: 45 | O135: =K22-K135 -> 18.829545 | P135: =L22-L135 -> 14.602272
A136: 1990 | B136: 12 | C136: 16.75 | D136: 14.75 | E136: 5.5 | F136: -9.75 | G136: -12.75 | H136: -9 | I136: -13.25 | J136: -13 | K136: -16.75 | L136: -27 | M136: -28 | O136: =K23-K136 -> 2.818182 | P136: =L23-L136 -> 8.190477
A137: 1991 | B137: 11.75 | C137: 31.25 | D137: 27.5 | E137: 0.25 | F137: -6.5 | G137: -15 | H137: -19.75 | I137: -21.75 | J137: -21.75 | K137: -16.25 | L137: -13 | M137: -10.5 | O137: =K24-K137 -> 2.772728 | P137: =L24-L137 -> 2.6125
A138: 1992 | B138: -2.5 | C138: 27.75 | D138: -0.25 | E138: -4 | F138: -11.25 | G138: -15 | H138: -17.5 | I138: -17.5 | J138: -16.5 | K138: -16.5 | L138: -18 | M138: -16.5 | O138: =K25-K138 -> 1.6625 | P138: =L25-L138 -> 2.659091
A139: 1993 | B139: -4.75 | C139: -7.25 | D139: -9.25 | E139: -9.25 | F139: -7.75 | G139: -7.25 | H139: -10 | I139: -9.75 | J139: -9.5 | K139: -3.25 | L139: -6.5 | M139: -8.25 | O139: =K26-K139 -> 2.7375 | P139: =L26-L139 -> 7.363636
A140: 1994 | B140: 46.5 | C140: 24 | D140: 14 | E140: 17.75 | F140: 47 | G140: 43.25 | H140: 33 | I140: 29.75 | J140: 35.25 | K140: 27.25 | L140: 16 | M140: 33.25 | O140: =K27-K140 -> 14.511904 | P140: =L27-L140 -> 9.363636
... A166: 2020 | B166: -18 | C166: -17 | D166: -7.25 | E166: -8.75 | F166: -12 | G166: -11.75 | H166: -13.75 | I166: -14 | J166: -12.5 | K166: -12.25 | L166: -14 | M166: 6.5 | O166: =K53-K166 -> 4.9875 | P166: =L53-L166 -> 8.0238095
A167: 2021 | B167: 3.25 | C167: 19 | D167: 51.5 | E167: 69.25 | F167: 111 | G167: 170.25 | H167: 159.25 | I167: 154.25 | J167: 129 | K167: 163.60634 | L167: 89.539491 | O167: =K54-K167 -> 7.506158 | P167: =L54-L167 -> 6.3030411
A168: 2022 | K168: =((SUM(K163:K167)-SUM(K50:K54))/5)+K55 -> 310.2569 | L168: =((SUM(L163:L167)-SUM(L50:L54))/5)+L55 -> 335.5173 | O168: =K55-K168 -> 6.7669134 | P168: =L55-L168 -> 4.5660303
A171: Nov - Jan Spread Average
A172: Contract Year | B172: Dec | C172: Jan | D172: Feb | E172: Mar | F172: Apr | G172: May | H172: Jun | I172: Jul | J172: Aug | K172: Sep | L172: Oct | M172: Nov
A173: 1970 | C173: -4.535714 | D173: -4.526315 | E173: -4.892857 | F173: -4.78409 | G173: -4.4875 | H173: -4.78409 | I173: -5.193181 | J173: -5.380952 | K173: -5.261904 | L173: -4.625 | M173: -3.270833
A174: 1971 | B174: -4.056818 | C174: -4.2875 | D174: -4.407894 | E174: -4.293478 | F174: -4.214285 | G174: -4.3 | H174: -4.056818 | I174: -3.404761 | J174: -3.556818 | K174: -3.904761 | L174: -3.238095 | M174: -4.428571
A175: 1972 | B175: -3.940476 | C175: -3.97619 | D175: -4.0125 | E175: -4.136363 | F175: -4.0125 | G175: -3.761363 | H175: -4.068181 | I175: -4.1 | J175: -4.141304 | K175: -4.8125 | L175: -3.340909 | M175: 3.25
A176: 1973 | C176: -2.05 | D176: 2.631578 | E176: 1.204545 | F176: -0.8125 | G176: 1.818181 | H176: 16.026315 | I176: 10.119047 | J176: 10.456521 | K176: -1.671052 | L176: -1.681818 | M176: 2.410714
A177: 1974 | B177: -2.25 | C177: -3.022727 | D177: -4.458333 | E177: -2.785714 | F177: -2.583333 | G177: -4.340909 | H177: -4.075 | I177: -2.375 | J177: -1.522727 | K177: -6.675 | L177: -14.413043 | M177: -16.083333
...
