Workbook

Sheet Refining Capacity and Demand
B1: ='Soy Crude'!Z2 -> 17/18 | C1: ='Soy Crude'!AA2 -> 18/19 | D1: ='Soy Crude'!AB2 -> 19/20 | E1: ='Soy Crude'!AC2 -> 20/21 | F1: ='Soy Crude'!AD2 -> 21/22 | G1: ='Soy Crude'!AE2 -> 22/23 | H1: ='Soy Crude'!AF2 -> 23/24 | I1: ='Soy Crude'!AG2 -> 24/25 | ... R1: ='Soy Crude'!AP2 -> 33/34
A2: Degumming Capacity | B2: ='[2]US Soy diff units'!$E153/1000000 -> #VALUE! | C2: ='[2]US Soy diff units'!$E154/1000000 -> 4997.929 | D2: ='[2]US Soy diff units'!$E155/1000000 -> 5035.6968 | E2: ='[2]US Soy diff units'!$E156/1000000 -> 5061.0018 | F2: ='[2]US Soy diff units'!$E157/1000000 -> 6447.19 | G2: ='[2]US Soy diff units'!$E158/1000000 -> 6374.7592 | H2: ='[2]US Soy diff units'!$E159/1000000 -> 6612.3208 | I2: ='[2]US Soy diff units'!$E160/1000000 -> 6914.9393 | J2: ='[2]US Soy diff units'!$E161/1000000 -> 7495.1767
A3: RBD Refining Capacity | B3: ='[2]US Soy diff units'!$F154/1000000 -> 19991.716 | C3: ='[2]US Soy diff units'!$F155/1000000 -> 20142.787 | D3: ='[2]US Soy diff units'!$F156/1000000 -> 20244.007 | E3: ='[2]US Soy diff units'!$F157/1000000 -> 20788.76 | F3: ='[2]US Soy diff units'!$F158/1000000 -> 21499.037 | G3: ='[2]US Soy diff units'!$F159/1000000 -> 22027.803 | H3: ='[2]US Soy diff units'!$F160/1000000 -> 22701.373 | I3: ='[2]US Soy diff units'!$F161/1000000 -> 23992.869 | J3: ='[2]US Soy diff units'!$F162/1000000 -> 24723.501 | K3: ='[2]US Soy diff units'!$F163/1000000 -> 26241.709 | L3: ='[2]US Soy diff units'!$F164/1000000 -> 27898.762 | M3: ='[2]US Soy diff units'!$F165/1000000 -> 27334.751 | N3: ='[2]US Soy diff units'!$F166/1000000 -> 27404.927 | O3: ='[2]US Soy diff units'!$F167/1000000 -> 28892.628 | P3: ='[2]US Soy diff units'!$F168/1000000 -> 29140.042 | Q3: ='[2]US Soy diff units'!$F169/1000000 -> 29940.387 | R3: ='[2]US Soy diff units'!$F170/1000000 -> 30297.537
A4: Pre-Treatment Capacity | B4: ='[2]US Soy diff units'!$G154/1000000 -> 27.506067 | C4: ='[2]US Soy diff units'!$G154/1000000 -> 27.506067 | D4: ='[2]US Soy diff units'!$G155/1000000 -> 41.501419 | E4: ='[2]US Soy diff units'!$G156/1000000 -> 50.34644 | F4: ='[2]US Soy diff units'!$G157/1000000 -> 78.399967 | G4: ='[2]US Soy diff units'!$G158/1000000 -> 153.01525 | H4: ='[2]US Soy diff units'!$G159/1000000 -> 655.36976 | I4: ='[2]US Soy diff units'!$G160/1000000 -> 1497.5648 | J4: ='[2]US Soy diff units'!$G161/1000000 -> 1851.2468 | K4: ='[2]US Soy diff units'!$G162/1000000 -> 2134.2276 | L4: ='[2]US Soy diff units'!$G163/1000000 -> 2408.1037 | M4: ='[2]US Soy diff units'!$G164/1000000 -> 2626.9226 | N4: ='[2]US Soy diff units'!$G165/1000000 -> 2777.4067 | O4: ='[2]US Soy diff units'!$G166/1000000 -> 2735.0661 | P4: ='[2]US Soy diff units'!$G167/1000000 -> 2722.8338 | Q4: ='[2]US Soy diff units'!$G168/1000000 -> 2733.7837 | R4: ='[2]US Soy diff units'!$G168/1000000 -> 2733.7837
A5: Soybean Oil Refining Capacity | B5: =B4+B3+B2 -> #VALUE! | C5: =C4+C3+C2 -> 25168.222 | D5: =D4+D3+D2 -> 25321.205 | E5: =E4+E3+E2 -> 25900.108 | F5: =F4+F3+F2 -> 28024.627 | G5: =G4+G3+G2 -> 28555.577 | H5: =H4+H3+H2 -> 29969.064 | I5: =I4+I3+I2 -> 32405.373 | J5: =J4+J3+J2 -> 34069.924
A7: Crude Demand | B7: =SUM(B8:B11) -> 6231.323 | C7: =SUM(C8:C11) -> 6409.786 | D7: =SUM(D8:D11) -> 6533.794 | E7: =SUM(E8:E11) -> 5197.563 | F7: =SUM(F8:F11) -> 5554.012 | G7: =SUM(G8:G11) -> 5140.846 | H7: =SUM(H8:H11) -> 5882.968 | I7: =SUM(I8:I11) -> 4859.0302 | ... R7: =SUM(R8:R11) -> 2585.3427
A8: Inedible Crude Demand | B8: ='Soy Crude'!Z10 -> 1376.9624 | C8: ='Soy Crude'!AA10 -> 1196.8618 | D8: ='Soy Crude'!AB10 -> 1396.0377 | E8: ='Soy Crude'!AC10 -> 1468.888 | F8: ='Soy Crude'!AD10 -> 1886.242 | G8: ='Soy Crude'!AE10 -> 2132.1206 | H8: ='Soy Crude'!AF10 -> 2094.9554 | I8: ='Soy Crude'!AG10 -> 2029 | ... R8: ='Soy Crude'!AP10 -> 2051
A9: Crude Residual | B9: ='Soy Crude'!Z11 -> 2702.9216 | C9: ='Soy Crude'!AA11 -> 3853.4074 | D9: ='Soy Crude'!AB11 -> 2641.7816 | E9: ='Soy Crude'!AC11 -> 2095.6613 | F9: ='Soy Crude'!AD11 -> 2420.2012 | G9: ='Soy Crude'!AE11 -> 3313.4996 | H9: ='Soy Crude'!AF11 -> 4149.2806 | I9: ='Soy Crude'!AG11 -> 3000 | ... R9: ='Soy Crude'!AP11 -> 500
A10: Net Crude Trade* | B10: ='Soy Crude'!Z12-'Soy Crude'!Z6 -> 1904.01 | C10: ='Soy Crude'!AA12-'Soy Crude'!AA6 -> 1607.2948 | D10: ='Soy Crude'!AB12-'Soy Crude'!AB6 -> 2389.0547 | E10: ='Soy Crude'!AC12-'Soy Crude'!AC6 -> 1398.9137 | F10: ='Soy Crude'!AD12-'Soy Crude'!AD6 -> 1399.1048 | G10: ='Soy Crude'!AE12-'Soy Crude'!AE6 -> 100.76382 | H10: ='Soy Crude'!AF12-'Soy Crude'!AF6 -> -246.85498 | I10: ='Soy Crude'!AG12-'Soy Crude'!AG6 -> -71.769314 | ... R10: ='Soy Crude'!AP12-'Soy Crude'!AP6 -> -133.84792
A11: Change in Crude Socks | B11: ='Soy Crude'!Z14-'Soy Crude'!Y14 -> 247.429 | C11: ='Soy Crude'!AA14-'Soy Crude'!Z14 -> -247.778 | D11: ='Soy Crude'!AB14-'Soy Crude'!AA14 -> 106.92 | E11: ='Soy Crude'!AC14-'Soy Crude'!AB14 -> 234.1 | F11: ='Soy Crude'!AD14-'Soy Crude'!AC14 -> -151.536 | G11: ='Soy Crude'!AE14-'Soy Crude'!AD14 -> -405.538 | H11: ='Soy Crude'!AF14-'Soy Crude'!AE14 -> -114.413 | I11: ='Soy Crude'!AG14-'Soy Crude'!AF14 -> -98.200458 | ... R11: ='Soy Crude'!AP14-'Soy Crude'!AO14 -> 168.19064
A13: Refined Demand | B13: =B31+B15+B16+B17+B18 -> 17099.033 | C13: =C31+C15+C16+C17+C18 -> 17384.932 | D13: =D31+D15+D16+D17+D18 -> 17934.801 | E13: =E31+E15+E16+E17+E18 -> 19367.987 | F13: =F31+F15+F16+F17+F18 -> 20143.847 | G13: =G31+G15+G16+G17+G18 -> 20633.113 | H13: =H31+H15+H16+H17+H18 -> 20794.489 | I13: =I31+I15+I16+I17+I18 -> 23464.997 | ... R13: =R31+R15+R16+R17+R18 -> 35515.344
A14: Inedible Refined Demand | B14: ='Soy Refined'!Z114 -> 4010.46 | C14: ='Soy Refined'!AA114 -> 5040.685 | D14: ='Soy Refined'!AB114 -> 4981.978 | E14: ='Soy Refined'!AC114 -> 5164.755 | F14: ='Soy Refined'!AD114 -> 5460.309 | G14: ='Soy Refined'!AE114 -> 6242.451 | H14: ='Soy Refined'!AF114 -> 6173.267 | I14: ='Soy Refined'!AG114 -> 5637.5534 | ... R14: ='Soy Refined'!AP114 -> 5712.5055
A15: Edible Refined Demand | B15: ='Soy Refined'!Z10 -> 13405.498 | C15: ='Soy Refined'!AA10 -> 13009.89 | D15: ='Soy Refined'!AB10 -> 13127.203 | E15: ='Soy Refined'!AC10 -> 14169.159 | F15: ='Soy Refined'!AD10 -> 14655.959 | G15: ='Soy Refined'!AE10 -> 14378.865 | H15: ='Soy Refined'!AF10 -> 14640.663 | I15: ='Soy Refined'!AG10 -> 17644.694 | ... R15: ='Soy Refined'!AP10 -> 24955.761
A16: Refined Residual | B16: ='Soy Refined'!Z12 -> -550.70714 | C16: ='Soy Refined'!AA12 -> -620.49268 | D16: ='Soy Refined'!AB12 -> -265.14168 | E16: ='Soy Refined'!AC12 -> -37.649977 | F16: ='Soy Refined'!AD12 -> -47.626659 | G16: ='Soy Refined'!AE12 -> 98.481593 | H16: ='Soy Refined'!AF12 -> -33.89253 | I16: ='Soy Refined'!AG12 -> -97.86003 | ... R16: ='Soy Refined'!AP12 -> 4798.3852
A17: Net Refined Trade* | B17: ='Soy Refined'!Z13-'Soy Refined'!Z6 -> 196.73114 | C17: ='Soy Refined'!AA13-'Soy Refined'!AA6 -> -72.810321 | D17: ='Soy Refined'!AB13-'Soy Refined'!AB6 -> 120.32268 | E17: ='Soy Refined'!AC13-'Soy Refined'!AC6 -> 27.264977 | F17: ='Soy Refined'!AD13-'Soy Refined'!AD6 -> 63.754659 | G17: ='Soy Refined'!AE13-'Soy Refined'!AE6 -> -103.31059 | H17: ='Soy Refined'!AF13-'Soy Refined'!AF6 -> 1.4165301 | I17: ='Soy Refined'!AG13-'Soy Refined'!AG6 -> -178.23069 | ... R17: ='Soy Refined'!AP13-'Soy Refined'!AP6 -> -116.15208
A18: Change in Refined Stocks | B18: ='Soy Refined'!Z15-'Soy Refined'!Y15 -> 37.051 | C18: ='Soy Refined'!AA15-'Soy Refined'!Z15 -> 27.66 | D18: ='Soy Refined'!AB15-'Soy Refined'!AA15 -> -29.561 | E18: ='Soy Refined'!AC15-'Soy Refined'!AB15 -> 44.458 | F18: ='Soy Refined'!AD15-'Soy Refined'!AC15 -> 11.451 | G18: ='Soy Refined'!AE15-'Soy Refined'!AD15 -> 16.626 | H18: ='Soy Refined'!AF15-'Soy Refined'!AE15 -> 13.035 | I18: ='Soy Refined'!AG15-'Soy Refined'!AF15 -> 458.84064 | ... R18: ='Soy Refined'!AP15-'Soy Refined'!AO15 -> 164.84506
A22: Total Demand | B22: =B13+B7 -> 23330.356 | C22: =C13+C7 -> 23794.718 | D22: =D13+D7 -> 24468.595 | E22: =E13+E7 -> 24565.55 | F22: =F13+F7 -> 25697.859 | G22: =G13+G7 -> 25773.959 | H22: =H13+H7 -> 26677.457 | I22: =I13+I7 -> 28324.027 | ... R22: =R13+R7 -> 38100.687
A23: *Positive numbers indicate net exports | B23: =B22-(B16+B9) -> 21178.142 | C23: =C22-(C16+C9) -> 20561.803 | D23: =D22-(D16+D9) -> 22091.955 | E23: =E22-(E16+E9) -> 22507.539 | F23: =F22-(F16+F9) -> 23325.284 | G23: =G22-(G16+G9) -> 22361.978 | H23: =H22-(H16+H9) -> 22562.069 | I23: =I22-(I16+I9) -> 25421.887 | ... R23: =R22-(R16+R9) -> 32802.302
A24: **Pre-treatment capacity assumes that soybean oil processing capacity is equal to the total multiplied by the average of soybean oil's portion of the feedstock mix for the year
A26: SBO Supply | B26: ='Soy Crude'!Z5+('Soy Crude'!Y6-'Soy Crude'!Y12)+('Soy Crude'!Y14-'Soy Crude'!X14) -> 21816.35 | C26: ='Soy Crude'!AA5+('Soy Crude'!Z6-'Soy Crude'!Z12)+('Soy Crude'!Z14-'Soy Crude'!Y14) -> 22540.618 | D26: ='Soy Crude'!AB5+('Soy Crude'!AA6-'Soy Crude'!AA12)+('Soy Crude'!AA14-'Soy Crude'!Z14) -> 23056.052 | E26: ='Soy Crude'!AC5+('Soy Crude'!AB6-'Soy Crude'!AB12)+('Soy Crude'!AB14-'Soy Crude'!AA14) -> 22740.532 | F26: ='Soy Crude'!AD5+('Soy Crude'!AC6-'Soy Crude'!AC12)+('Soy Crude'!AC14-'Soy Crude'!AB14) -> 24990.359 | G26: ='Soy Crude'!AE5+('Soy Crude'!AD6-'Soy Crude'!AD12)+('Soy Crude'!AD14-'Soy Crude'!AC14) -> 24676.668 | H26: ='Soy Crude'!AF5+('Soy Crude'!AE6-'Soy Crude'!AE12)+('Soy Crude'!AE14-'Soy Crude'!AD14) -> 26625.426 | I26: ='Soy Crude'!AG5+('Soy Crude'!AF6-'Soy Crude'!AF12)+('Soy Crude'!AF14-'Soy Crude'!AE14) -> 29019.292 | ... R26: ='Soy Crude'!AP5+('Soy Crude'!AO6-'Soy Crude'!AO12)+('Soy Crude'!AO14-'Soy Crude'!AN14) -> 39182.723
B27: =B26-B22 -> -1514.006 | C27: =C26-C22 -> -1254.1 | D27: =D26-D22 -> -1412.5428 | E27: =E26-E22 -> -1825.0177 | F27: =F26-F22 -> -707.4997 | G27: =G26-G22 -> -1097.2908 | H27: =H26-H22 -> -52.030817 | I27: =I26-I22 -> 695.26461 | ... R27: =R26-R22 -> 1082.036
B28: =B26-B23 -> 638.20841 | C28: =C26-C23 -> 1978.8147 | D28: =D26-D23 -> 964.09713 | E28: =E26-E23 -> 232.99364 | F28: =F26-F23 -> 1665.0749 | G28: =G26-G23 -> 2314.6904 | H28: =H26-H23 -> 4063.3572 | I28: =I26-I23 -> 3597.4046 | ... R28: =R26-R23 -> 6380.4212
A30: Biofuel Use | B30: ='Soy Refined'!Z146 -> 7658.8947 | C30: ='Soy Refined'!AA146 -> 8973.8277 | D30: ='Soy Refined'!AB146 -> 9332.7849 | E30: ='Soy Refined'!AC146 -> 9070.1698 | F30: ='Soy Refined'!AD146 -> 11495.128 | G30: ='Soy Refined'!AE146 -> 12613.444 | H30: ='Soy Refined'!AF146 -> 12997.373 | I30: ='Soy Refined'!AG146 -> 14851.941 | ... R30: ='Soy Refined'!AP146 -> 24928.157
A31: Non-Biofuel Use | B31: ='Soy Refined'!Z114 -> 4010.46 | C31: ='Soy Refined'!AA114 -> 5040.685 | D31: ='Soy Refined'!AB114 -> 4981.978 | E31: ='Soy Refined'!AC114 -> 5164.755 | F31: ='Soy Refined'!AD114 -> 5460.309 | G31: ='Soy Refined'!AE114 -> 6242.451 | H31: ='Soy Refined'!AF114 -> 6173.267 | I31: ='Soy Refined'!AG114 -> 5637.5534 | ... R31: ='Soy Refined'!AP114 -> 5712.5055
A35: SBO SUPPLY
A36: - CRUSH SUPPLY | B36: ='[3]Soy Complex'!BG$288 -> 23772.428 | C36: ='[3]Soy Complex'!BH$288 -> 24197.199 | D36: ='[3]Soy Complex'!BI$288 -> 24911.125 | E36: ='[3]Soy Complex'!BJ$288 -> 25022.667 | F36: ='[3]Soy Complex'!BK$288 -> 26141.24 | G36: ='[3]Soy Complex'!BL$288 -> 26227.309 | H36: ='[3]Soy Complex'!BM$288 -> 27262.999 | I36: ='[3]Soy Complex'!BN$288 -> 28886.85 | ... R36: ='[3]Soy Complex'!BW$288 -> 38951.4
A37: - DEGUMMED SUPPLY | B37: ='Soy Crude'!X5 -> 21950.231 | C37: ='Soy Crude'!Y5 -> 22123.409 | D37: ='Soy Crude'!Z5 -> 23772.428 | E37: ='Soy Crude'!AA5 -> 24197.199 | F37: ='Soy Crude'!AB5 -> 24911.125 | G37: ='Soy Crude'!AC5 -> 25022.667 | H37: ='Soy Crude'!AD5 -> 26155.173 | I37: ='Soy Crude'!AE5 -> 26227.309 | ... R37: ='Soy Crude'!AN5 -> 38278.05
A38: - RBD SUPPLY | B38: ='Soy Refined'!Z5 -> 17099.033 | C38: ='Soy Refined'!AA5 -> 17384.932 | D38: ='Soy Refined'!AB5 -> 17934.801 | E38: ='Soy Refined'!AC5 -> 19367.987 | F38: ='Soy Refined'!AD5 -> 20143.847 | G38: ='Soy Refined'!AE5 -> 20633.113 | H38: ='Soy Refined'!AF5 -> 20794.489 | I38: ='Soy Refined'!AG5 -> 23464.997 | ... R38: ='Soy Refined'!AP5 -> 35515.344
A39: - REFINING LOSS
A41: SBO DEMAND
A42: Crude Processing Use | B42: ='Soy Crude'!X9 -> 17168.813 | C42: ='Soy Crude'!Y9 -> 17337.342 | D42: ='Soy Crude'!Z9 -> 17541.105 | E42: ='Soy Crude'!AA9 -> 17787.413 | F42: ='Soy Crude'!AB9 -> 18377.331 | G42: ='Soy Crude'!AC9 -> 19825.104 | H42: ='Soy Crude'!AD9 -> 20601.161 | I42: ='Soy Crude'!AE9 -> 21086.463 | ... R42: ='Soy Crude'!AN9 -> 33146.046
A43: Crude Trade Use | B43: ='Soy Crude'!X12-'Soy Crude'!X6 -> 1829.3836 | C43: ='Soy Crude'!Y12-'Soy Crude'!Y6 -> 1939.596 | D43: ='Soy Crude'!Z12-'Soy Crude'!Z6 -> 1904.01 | E43: ='Soy Crude'!AA12-'Soy Crude'!AA6 -> 1607.2948 | F43: ='Soy Crude'!AB12-'Soy Crude'!AB6 -> 2389.0547 | G43: ='Soy Crude'!AC12-'Soy Crude'!AC6 -> 1398.9137 | H43: ='Soy Crude'!AD12-'Soy Crude'!AD6 -> 1399.1048 | I43: ='Soy Crude'!AE12-'Soy Crude'!AE6 -> 100.76382 | ... R43: ='Soy Crude'!AN12-'Soy Crude'!AN6 -> -123.44885
A44: Crude Inedible Use | B44: ='Soy Crude'!Z10 -> 1376.9624 | C44: ='Soy Crude'!AA10 -> 1196.8618 | D44: ='Soy Crude'!AB10 -> 1396.0377 | E44: ='Soy Crude'!AC10 -> 1468.888 | F44: ='Soy Crude'!AD10 -> 1886.242 | G44: ='Soy Crude'!AE10 -> 2132.1206 | H44: ='Soy Crude'!AF10 -> 2094.9554 | I44: ='Soy Crude'!AG10 -> 2029 | ... R44: ='Soy Crude'!AP10 -> 2051
A45: Crude Inventory Change | B45: ='Soy Crude'!Z14-'Soy Crude'!Y14 -> 247.429 | C45: ='Soy Crude'!AA14-'Soy Crude'!Z14 -> -247.778 | D45: ='Soy Crude'!AB14-'Soy Crude'!AA14 -> 106.92 | E45: ='Soy Crude'!AC14-'Soy Crude'!AB14 -> 234.1 | F45: ='Soy Crude'!AD14-'Soy Crude'!AC14 -> -151.536 | G45: ='Soy Crude'!AE14-'Soy Crude'!AD14 -> -405.538 | H45: ='Soy Crude'!AF14-'Soy Crude'!AE14 -> -114.413 | I45: ='Soy Crude'!AG14-'Soy Crude'!AF14 -> -98.200458 | ... R45: ='Soy Crude'!AP14-'Soy Crude'!AO14 -> 168.19064
A46: Total Crude Demand | B46: =SUM(B42:B45) -> 20622.588 | C46: =SUM(C42:C45) -> 20226.022 | D46: =SUM(D42:D45) -> 20948.073 | E46: =SUM(E42:E45) -> 21097.696 | F46: =SUM(F42:F45) -> 22501.092 | G46: =SUM(G42:G45) -> 22950.6 | H46: =SUM(H42:H45) -> 23980.808 | I46: =SUM(I42:I45) -> 23118.026 | ... R46: =SUM(R42:R45) -> 35241.788
A49: Refined Trade Use | B49: ='Soy Refined'!Z13-'Soy Refined'!Z6 -> 196.73114 | C49: ='Soy Refined'!AA13-'Soy Refined'!AA6 -> -72.810321 | D49: ='Soy Refined'!AB13-'Soy Refined'!AB6 -> 120.32268 | E49: ='Soy Refined'!AC13-'Soy Refined'!AC6 -> 27.264977 | F49: ='Soy Refined'!AD13-'Soy Refined'!AD6 -> 63.754659 | G49: ='Soy Refined'!AE13-'Soy Refined'!AE6 -> -103.31059 | H49: ='Soy Refined'!AF13-'Soy Refined'!AF6 -> 1.4165301 | I49: ='Soy Refined'!AG13-'Soy Refined'!AG6 -> -178.23069 | ... R49: ='Soy Refined'!AP13-'Soy Refined'!AP6 -> -116.15208
A50: Refined Edible Use | B50: ='Soy Refined'!Z10 -> 13405.498 | C50: ='Soy Refined'!AA10 -> 13009.89 | D50: ='Soy Refined'!AB10 -> 13127.203 | E50: ='Soy Refined'!AC10 -> 14169.159 | F50: ='Soy Refined'!AD10 -> 14655.959 | G50: ='Soy Refined'!AE10 -> 14378.865 | H50: ='Soy Refined'!AF10 -> 14640.663 | I50: ='Soy Refined'!AG10 -> 17644.694 | ... R50: ='Soy Refined'!AP10 -> 24955.761
A51: Refined Inedible Use | B51: ='Soy Refined'!Y11 -> 3455.56 | C51: ='Soy Refined'!Z11 -> 4010.46 | D51: ='Soy Refined'!AA11 -> 5040.685 | E51: ='Soy Refined'!AB11 -> 4981.978 | F51: ='Soy Refined'!AC11 -> 5164.755 | G51: ='Soy Refined'!AD11 -> 5460.309 | H51: ='Soy Refined'!AE11 -> 6242.451 | I51: ='Soy Refined'!AF11 -> 6173.267 | ... R51: ='Soy Refined'!AO11 -> 5722.0422
A52: Total Refined Demand | B52: =SUM(B49:B51) -> 17057.789 | C52: =SUM(C49:C51) -> 16947.54 | D52: =SUM(D49:D51) -> 18288.211 | E52: =SUM(E49:E51) -> 19178.402 | F52: =SUM(F49:F51) -> 19884.469 | G52: =SUM(G49:G51) -> 19735.863 | H52: =SUM(H49:H51) -> 20884.531 | I52: =SUM(I49:I51) -> 23639.73 | ... R52: =SUM(R49:R51) -> 30561.651
A53: Refining Capacity | B53: =B5 -> #VALUE! | C53: =C5 -> 25168.222 | D53: =D5 -> 25321.205 | E53: =E5 -> 25900.108 | F53: =F5 -> 28024.627 | G53: =G5 -> 28555.577 | H53: =H5 -> 29969.064 | I53: =I5 -> 32405.373 | ... R53: =R5 -> 0
A54: Excess/(Deficit)
A55: Crude | B55: =B37-B46 -> 1327.643 | C55: =C37-C46 -> 1897.3872 | D55: =D37-D46 -> 2824.3553 | E55: =E37-E46 -> 3099.5032 | F55: =F37-F46 -> 2410.0333 | G55: =G37-G46 -> 2072.0667 | H55: =H37-H46 -> 2174.3648 | I55: =I37-I46 -> 3109.2826 | ... R55: =R37-R46 -> 3036.2619
A56: Refined | B56: =B38-B52 -> 41.243864 | C56: =C38-C52 -> 437.39232 | D56: =D38-D52 -> -353.40968 | E56: =E38-E52 -> 189.58502 | F56: =F38-F52 -> 259.37834 | G56: =G38-G52 -> 897.24959 | H56: =H38-H52 -> -90.04153 | I56: =I38-I52 -> -174.73294 | ... R56: =R38-R52 -> 4953.6936

Sheet Sheet1
C1: 2017 | D1: 2018 | E1: 2019 | F1: 2020 | G1: 2021 | H1: 2022 | I1: 2023 | J1: 2024 | K1: 2025 | L1: 2026 | M1: 2027 | N1: 2028 | O1: 2029 | P1: 2030 | Q1: 2031 | R1: 2032 | S1: 2033
A2: REFINED USE
A3: REFINED EDIBLE USE | C3: =SUM('Soy Refined'!Y89:Y97,'Soy Refined'!Z86:Z88) -> 13317.826 | D3: =SUM('Soy Refined'!Z89:Z97,'Soy Refined'!AA86:AA88) -> 13370.83 | E3: =SUM('Soy Refined'!AA89:AA97,'Soy Refined'!AB86:AB88) -> 12841.846 | F3: =SUM('Soy Refined'!AB89:AB97,'Soy Refined'!AC86:AC88) -> 13309.302 | G3: =SUM('Soy Refined'!AC89:AC97,'Soy Refined'!AD86:AD88) -> 14520.783 | H3: =SUM('Soy Refined'!AD89:AD97,'Soy Refined'!AE86:AE88) -> 14458.518 | I3: =SUM('Soy Refined'!AE89:AE97,'Soy Refined'!AF86:AF88) -> 14496.66 | J3: =SUM('Soy Refined'!AF89:AF97,'Soy Refined'!AG86:AG88) -> 15512.911 | ... S3: =SUM('Soy Refined'!AO89:AO97,'Soy Refined'!AP86:AP88) -> 24792.075
A4: REFINED INEDIBLE USE | C4: =SUM('Soy Refined'!Y105:Y113,'Soy Refined'!Z102:Z104) -> 3476.508 | D4: =SUM('Soy Refined'!Z105:Z113,'Soy Refined'!AA102:AA104) -> 4380.385 | E4: =SUM('Soy Refined'!AA105:AA113,'Soy Refined'!AB102:AB104) -> 4963.221 | F4: =SUM('Soy Refined'!AB105:AB113,'Soy Refined'!AC102:AC104) -> 5124.095 | G4: =SUM('Soy Refined'!AC105:AC113,'Soy Refined'!AD102:AD104) -> 5045.908 | H4: =SUM('Soy Refined'!AD105:AD113,'Soy Refined'!AE102:AE104) -> 5677.746 | I4: =SUM('Soy Refined'!AE105:AE113,'Soy Refined'!AF102:AF104) -> 6326.362 | J4: =SUM('Soy Refined'!AF105:AF113,'Soy Refined'!AG102:AG104) -> 6003.0921 | ... S4: =SUM('Soy Refined'!AO105:AO113,'Soy Refined'!AP102:AP104) -> 5720.3434
B5: Total Domestic Use | C5: =SUM(C3:C4) -> 16794.334 | D5: =SUM(D3:D4) -> 17751.215 | E5: =SUM(E3:E4) -> 17805.067 | F5: =SUM(F3:F4) -> 18433.397 | G5: =SUM(G3:G4) -> 19566.691 | H5: =SUM(H3:H4) -> 20136.264 | I5: =SUM(I3:I4) -> 20823.022 | J5: =SUM(J3:J4) -> 21516.003 | ... S5: =SUM(S3:S4) -> 30512.418
A7: REFINED EXPORTS | C7: =SUM('Soy Refined'!Y57:Y65,'Soy Refined'!Z54:Z56) -> 534.91048 | D7: =SUM('Soy Refined'!Z57:Z65,'Soy Refined'!AA54:AA56) -> 426.81876 | E7: =SUM('Soy Refined'!AA57:AA65,'Soy Refined'!AB54:AB56) -> 347.54236 | F7: =SUM('Soy Refined'!AB57:AB65,'Soy Refined'!AC54:AC56) -> 375.27091 | G7: =SUM('Soy Refined'!AC57:AC65,'Soy Refined'!AD54:AD56) -> 248.63677 | H7: =SUM('Soy Refined'!AD57:AD65,'Soy Refined'!AE54:AE56) -> 277.9211 | I7: =SUM('Soy Refined'!AE57:AE65,'Soy Refined'!AF54:AF56) -> 162.56399 | J7: =SUM('Soy Refined'!AF57:AF65,'Soy Refined'!AG54:AG56) -> 268.62678 | ... S7: =SUM('Soy Refined'!AO57:AO65,'Soy Refined'!AP54:AP56) -> 249.38537
B8: Total Demand | C8: =C7+C5 -> 17329.244 | D8: =D7+D5 -> 18178.034 | E8: =E7+E5 -> 18152.609 | F8: =F7+F5 -> 18808.668 | G8: =G7+G5 -> 19815.328 | H8: =H7+H5 -> 20414.185 | I8: =I7+I5 -> 20985.586 | J8: =J7+J5 -> 21784.63 | ... S8: =S7+S5 -> 30761.803
A12: REFINED PRODUCTION | C12: =SUM('Soy Refined'!Y25:Y33,'Soy Refined'!Z22:Z24) -> 16943.425 | D12: =SUM('Soy Refined'!Z25:Z33,'Soy Refined'!AA22:AA24) -> 17146.988 | E12: =SUM('Soy Refined'!AA25:AA33,'Soy Refined'!AB22:AB24) -> 17200.398 | F12: =SUM('Soy Refined'!AB25:AB33,'Soy Refined'!AC22:AC24) -> 18450.364 | G12: =SUM('Soy Refined'!AC25:AC33,'Soy Refined'!AD22:AD24) -> 19595.492 | H12: =SUM('Soy Refined'!AD25:AD33,'Soy Refined'!AE22:AE24) -> 20112.678 | I12: =SUM('Soy Refined'!AE25:AE33,'Soy Refined'!AF22:AF24) -> 20918.585 | J12: =SUM('Soy Refined'!AF25:AF33,'Soy Refined'!AG22:AG24) -> 21202.221 | ... S12: =SUM('Soy Refined'!AO25:AO33,'Soy Refined'!AP22:AP24) -> 34705.816
A13: REFINED IMPORTS | C13: =SUM('Soy Refined'!Y41:Y49,'Soy Refined'!Z38:Z40) -> 283.11157 | D13: =SUM('Soy Refined'!Z41:Z49,'Soy Refined'!AA38:AA40) -> 301.22909 | E13: =SUM('Soy Refined'!AA41:AA49,'Soy Refined'!AB38:AB40) -> 351.53543 | F13: =SUM('Soy Refined'!AB41:AB49,'Soy Refined'!AC38:AC40) -> 243.02328 | G13: =SUM('Soy Refined'!AC41:AC49,'Soy Refined'!AD38:AD40) -> 273.98614 | H13: =SUM('Soy Refined'!AD41:AD49,'Soy Refined'!AE38:AE40) -> 207.64739 | I13: =SUM('Soy Refined'!AE41:AE49,'Soy Refined'!AF38:AF40) -> 281.39187 | J13: =SUM('Soy Refined'!AF41:AF49,'Soy Refined'!AG38:AG40) -> 302.87727 | ... S13: =SUM('Soy Refined'!AO41:AO49,'Soy Refined'!AP38:AP40) -> 368.181
B14: Total Supply | C14: =C12+C13 -> 17226.537 | D14: =D12+D13 -> 17448.217 | E14: =E12+E13 -> 17551.933 | F14: =F12+F13 -> 18693.387 | G14: =G12+G13 -> 19869.478 | H14: =H12+H13 -> 20320.325 | I14: =I12+I13 -> 21199.977 | J14: =J12+J13 -> 21505.098 | ... S14: =S12+S13 -> 35073.997
B15: Excess/(Deficit) | C15: =C14-C8 -> -102.70791 | D15: =D14-D8 -> -729.81667 | E15: =E14-E8 -> -600.67593 | F15: =F14-F8 -> -115.28063 | G15: =G14-G8 -> 54.150375 | H15: =H14-H8 -> -93.859707 | I15: =I14-I8 -> 214.39088 | J15: =J14-J8 -> -279.53162 | ... S15: =S14-S8 -> 4312.1939

Sheet Soy Crude
A1: US CRUDE SOYBEAN OIL SUPPLY AND DEMAND
B2: 93/94 | C2: 94/95 | D2: 95/96 | E2: 96/97 | F2: 97/98 | G2: 98/99 | H2: 99/00 | I2: 00/01 | J2: 01/02 | K2: 02/03 | L2: 03/04 | M2: 04/05 | N2: 05/06 | O2: 06/07 | P2: 07/08 | Q2: 08/09 | R2: 09/10 | S2: 10/11 | T2: 11/12 | U2: 12/13 | V2: 13/14 | W2: 14/15 | X2: 15/16 | Y2: 16/17 | Z2: 17/18 | AA2: 18/19 | AB2: 19/20 | AC2: 20/21 | AD2: 21/22 | AE2: 22/23 | AF2: ='[3]Soy Complex'!BM2 -> 23/24 | AG2: ='[3]Soy Complex'!BN2 -> 24/25 | AH2: ='[3]Soy Complex'!BO2 -> 25/26 | AI2: ='[3]Soy Complex'!BP2 -> 26/27 | AJ2: ='[3]Soy Complex'!BQ2 -> 27/28 | AK2: ='[3]Soy Complex'!BR2 -> 28/29 | AL2: ='[3]Soy Complex'!BS2 -> 29/30 | AM2: ='[3]Soy Complex'!BT2 -> 30/31 | ... AU2: ='[3]Soy Complex'!CB2 -> 38/39
A3: US CRUDE SOYBEAN OIL SUPPLY AND DEMAND (million pounds) | AW3: US Crude soybean oil supply and demand
A4: Beginning Stocks (October 1) | X4: =W14 -> 1516.385 | Y4: =X14 -> 1417.4 | Z4: =Y14 -> 1400.918 | AA4: =Z14 -> 1648.347 | AB4: =AA14 -> 1400.569 | AC4: =AB14 -> 1507.489 | AD4: =AC14 -> 1741.589 | AE4: =AD14 -> 1590.053 | ... AU4: =AT14 -> -3931.8741 | AW4: (million pounds) | AX4: 2021/22 | AY4: 2022/23
A5: Production | X5: =X33 -> 21950.231 | Y5: =Y33 -> 22123.409 | Z5: =Z33 -> 23772.428 | AA5: =AA33 -> 24197.199 | AB5: =AB33 -> 24911.125 | AC5: =AC33 -> 25022.667 | AD5: =AD33 -> 26155.173 | AE5: =AE33 -> 26227.309 | ... AU5: =AU33 -> 41308.85 | AW5: =A4 -> Beginning Stocks (October 1) | AX5: =AD4 -> 1741.589 | AY5: =AE4 -> 1590.053
A6: Imports | X6: =X49 -> 58.164191 | Y6: =Y49 -> 69.728614 | Z6: =Z49 -> 56.484749 | AA6: =AA49 -> 25.902655 | AB6: =AB49 -> 54.327069 | AC6: =AC49 -> 49.933508 | AD6: =AD49 -> 70.69392 | AE6: =AE49 -> 94.232713 | AF6: ='[3]Soy Complex'!$BK$36*(SUM(V6:AE6)/SUM('[3]Soy Complex'!$BA$36:$BJ$36))+200 -> 253.56933 | AG6: ='[3]Soy Complex'!$BK$36*(SUM(W6:AF6)/SUM('[3]Soy Complex'!$BA$36:$BJ$36)) -> 81.899809 | AH6: ='[3]Soy Complex'!$BK$36*(SUM(X6:AG6)/SUM('[3]Soy Complex'!$BA$36:$BJ$36)) -> 91.050208 | AI6: ='[3]Soy Complex'!$BK$36*(SUM(Y6:AH6)/SUM('[3]Soy Complex'!$BA$36:$BJ$36)) -> 94.724455 | AJ6: ='[3]Soy Complex'!$BK$36*(SUM(Z6:AI6)/SUM('[3]Soy Complex'!$BA$36:$BJ$36)) -> 97.517159 | AK6: ='[3]Soy Complex'!$BK$36*(SUM(AA6:AJ6)/SUM('[3]Soy Complex'!$BA$36:$BJ$36)) -> 102.10158 | AL6: ='[3]Soy Complex'!$BK$36*(SUM(AB6:AK6)/SUM('[3]Soy Complex'!$BA$36:$BJ$36)) -> 110.61503 | AM6: ='[3]Soy Complex'!$BK$36*(SUM(AC6:AL6)/SUM('[3]Soy Complex'!$BA$36:$BJ$36)) -> 116.90391 | AN6: ='[3]Soy Complex'!$BK$36*(SUM(AD6:AM6)/SUM('[3]Soy Complex'!$BA$36:$BJ$36)) -> 124.38629 | ... AU6: ='[3]Soy Complex'!$BK$36*(SUM(AK6:AT6)/SUM('[3]Soy Complex'!$BA$36:$BJ$36)) -> 137.19761 | AW6: =A5 -> Production | AX6: =AD5 -> 26155.173 | AY6: =AE5 -> 26227.309
A7: Total Supply | X7: =SUM(X4:X6) -> 23524.78 | Y7: =SUM(Y4:Y6) -> 23610.538 | Z7: =SUM(Z4:Z6) -> 25229.831 | AA7: =SUM(AA4:AA6) -> 25871.449 | AB7: =SUM(AB4:AB6) -> 26366.021 | AC7: =SUM(AC4:AC6) -> 26580.09 | AD7: =SUM(AD4:AD6) -> 27967.456 | AE7: =SUM(AE4:AE6) -> 27911.595 | ... AU7: =SUM(AU4:AU6) -> 37514.173 | AW7: =A6 -> Imports | AX7: =AD6 -> 70.69392 | AY7: =AE6 -> 94.232713
A8: Domestic Use | X8: =X13-X12 -> 20219.832 | Y8: =Y13-Y12 -> 20200.295 | Z8: =Z13-Z12 -> 21620.989 | AA8: =AA13-AA12 -> 22837.682 | AB8: =AB13-AB12 -> 22415.15 | AC8: =AC13-AC12 -> 23389.653 | AD8: =AD13-AD12 -> 24907.604 | AE8: =AE13-AE12 -> 26532.083 | ... AU8: =AU13-AU12 -> 64058.27 | AW8: =A7 -> Total Supply | AX8: =AD7 -> 27967.456 | AY8: =AE7 -> 27911.595
A9: Processing | X9: =X81 -> 17168.813 | Y9: =Y81 -> 17337.342 | Z9: =Z81 -> 17541.105 | AA9: =AA81 -> 17787.413 | AB9: =AB81 -> 18377.331 | AC9: =AC81 -> 19825.104 | AD9: =AD81 -> 20601.161 | AE9: =AE81 -> 21086.463 | ... AU9: =AU81 -> 55756.27 | AW9: =A8 -> Domestic Use | AX9: =AD8 -> 24907.604 | AY9: =AE8 -> 26532.083
A10: Inedible Use | X10: =X97 -> 1355.8973 | Y10: =Y97 -> 1155.7726 | Z10: =Z97 -> 1376.9624 | AA10: =AA97 -> 1196.8618 | AB10: =AB97 -> 1396.0377 | AC10: =AC97 -> 1468.888 | AD10: =AD97 -> 1886.242 | AE10: =AE97 -> 2132.1206 | AF10: =AF97 -> 2094.9554 | AG10: =MROUND(FORECAST(AG5,Z10:AF10,Z5:AF5),1)-650 -> 2029 | AH10: =MROUND(FORECAST(AH5,AA10:AG10,AA5:AG5),1)-650 -> 2035 | AI10: =MROUND(FORECAST(AI5,AB10:AH10,AB5:AH5),1)-350 -> 2058 | AJ10: =MROUND(FORECAST(AJ5,AC10:AI10,AC5:AI5),1)-100 -> 2069 | AK10: =MROUND(FORECAST(AK5,AD10:AJ10,AD5:AJ5),1) -> 2066 | AL10: =MROUND(FORECAST(AL5,AE10:AK10,AE5:AK5),1) -> 2040 | AM10: =MROUND(FORECAST(AM5,AF10:AL10,AF5:AL5),1) -> 2047 | AN10: =MROUND(FORECAST(AN5,AG10:AM10,AG5:AM5),1) -> 2060 | AO10: =MROUND(FORECAST(AO5,AH10:AN10,AH5:AN5),1) -> 2056 | AP10: =MROUND(FORECAST(AP5,AI10:AO10,AI5:AO5),1) -> 2051 | AQ10: =MROUND(FORECAST(AQ5,AJ10:AP10,AJ5:AP5),1) -> 2049 | AR10: =MROUND(FORECAST(AR5,AK10:AQ10,AK5:AQ5),1) -> 2050 | ... AU10: =MROUND(FORECAST(AU5,AN10:AT10,AN5:AT5),1) -> 2052 | AW10: =A9 -> Processing | AX10: =AD9 -> 20601.161 | AY10: =AE9 -> 21086.463
A11: Residual (balance) | X11: =X8-X9-X10 -> 1695.122 | Y11: =Y8-Y9-Y10 -> 1707.1804 | Z11: =Z8-Z9-Z10 -> 2702.9216 | AA11: =AA8-AA9-AA10 -> 3853.4074 | AB11: =AB8-AB9-AB10 -> 2641.7816 | AC11: =AC8-AC9-AC10 -> 2095.6613 | AD11: =AD8-AD9-AD10 -> 2420.2012 | AE11: =AE8-AE9-AE10 -> 3313.4996 | ... AU11: =AU8-AU9-AU10 -> 6250 | AW11: =A10 -> Inedible Use | AX11: =AD10 -> 1886.242 | AY11: =AE10 -> 2132.1206
A12: Exports | X12: =X65 -> 1887.5478 | Y12: =Y65 -> 2009.3246 | Z12: =Z65 -> 1960.4948 | AA12: =AA65 -> 1633.1975 | AB12: =AB65 -> 2443.3818 | AC12: =AC65 -> 1448.8472 | AD12: =AD65 -> 1469.7987 | AE12: =AE65 -> 194.99653 | AF12: ='[3]Soy Complex'!BM$44*(SUM(Z12:AE12)/SUM('[3]Soy Complex'!BG$44:BL$44))-200 -> 6.7143554 | AG12: ='[3]Soy Complex'!BN$44*(SUM(AA12:AF12)/SUM('[3]Soy Complex'!BH$44:BM$44))*0.05 -> 10.130494 | AH12: ='[3]Soy Complex'!BO$44*(SUM(AB12:AG12)/SUM('[3]Soy Complex'!BI$44:BN$44))*0.05 -> 9.6792611 | AI12: ='[3]Soy Complex'!BP$44*(SUM(AC12:AH12)/SUM('[3]Soy Complex'!BJ$44:BO$44))*0.05 -> 8.4986436 | AJ12: ='[3]Soy Complex'!BQ$44*(SUM(AD12:AI12)/SUM('[3]Soy Complex'!BK$44:BP$44))*0.05 -> 6.7678813 | AK12: ='[3]Soy Complex'!BR$44*(SUM(AE12:AJ12)/SUM('[3]Soy Complex'!BL$44:BQ$44))*0.05 -> 1.8233904 | AL12: ='[3]Soy Complex'!BS$44*(SUM(AF12:AK12)/SUM('[3]Soy Complex'!BM$44:BR$44))*0.1 -> 0.72690044 | AM12: ='[3]Soy Complex'!BT$44*(SUM(AG12:AL12)/SUM('[3]Soy Complex'!BN$44:BS$44))*0.1 -> 0.62710952 | AN12: ='[3]Soy Complex'!BU$44*(SUM(AH12:AM12)/SUM('[3]Soy Complex'!BO$44:BT$44))*0.2 -> 0.93743955 | AO12: ='[3]Soy Complex'!BV$44*(SUM(AI12:AN12)/SUM('[3]Soy Complex'!BP$44:BU$44))*0.2 -> 0.64604549 | AP12: ='[3]Soy Complex'!BW$44*(SUM(AJ12:AO12)/SUM('[3]Soy Complex'!BQ$44:BV$44))*0.3 -> 0.57643834 | AQ12: ='[3]Soy Complex'!BX$44*(SUM(AK12:AP12)/SUM('[3]Soy Complex'!BR$44:BW$44))*0.75 -> 0.66716547 | AR12: ='[3]Soy Complex'!BY$44*(SUM(AL12:AQ12)/SUM('[3]Soy Complex'!BS$44:BX$44))*0.75 -> 0.52263735 | AS12: ='[3]Soy Complex'!BZ$44*(SUM(AM12:AR12)/SUM('[3]Soy Complex'!BT$44:BY$44))*0.75 -> 0.49710447 | AT12: ='[3]Soy Complex'!CA$44*(SUM(AN12:AS12)/SUM('[3]Soy Complex'!BU$44:BZ$44))*0.75 -> 0.48085383 | AU12: ='[3]Soy Complex'!CB$44*(SUM(AO12:AT12)/SUM('[3]Soy Complex'!BV$44:CA$44))*0.75 -> 0.42378062 | AW12: Residual Use | AX12: =AD11 -> 2420.2012 | AY12: =AE11 -> 3313.4996
A13: Total Use | X13: =X7-X14 -> 22107.38 | Y13: =Y7-Y14 -> 22209.62 | Z13: =Z7-Z14 -> 23581.484 | AA13: =AA7-AA14 -> 24470.88 | AB13: =AB7-AB14 -> 24858.532 | AC13: =AC7-AC14 -> 24838.501 | AD13: =AD7-AD14 -> 26377.403 | AE13: =AE7-AE14 -> 26727.08 | ... AU13: =AU7-AU14 -> 64058.694 | AW13: =A12 -> Exports | AX13: =AD12 -> 1469.7987 | AY13: =AE12 -> 194.99653
A14: Ending Stocks (September 30) | W14: =W128 -> 1516.385 | X14: =X128 -> 1417.4 | Y14: =Y128 -> 1400.918 | Z14: =Z128 -> 1648.347 | AA14: =AA128 -> 1400.569 | AB14: =AB128 -> 1507.489 | AC14: =AC128 -> 1741.589 | AD14: =AD128 -> 1590.053 | ... AU14: =AU128 -> -26544.52 | AW14: =A13 -> Total Use | AX14: =AD13 -> 26377.403 | AY14: =AE13 -> 26727.08
A15: Days of Coverage | X15: =X14/X13 -> 0.064114336 | Y15: =Y14/(Y13/365) -> 23.023135 | Z15: =Z14/(Z13/365) -> 25.51352 | AA15: =AA14/(AA13/365) -> 20.89045 | AB15: =AB14/(AB13/365) -> 22.134593 | AC15: =AC14/(AC13/365) -> 25.592527 | AD15: =AD14/(AD13/365) -> 22.00252 | AE15: =AE14/(AE13/365) -> 16.176402 | AF15: =AF14/(AF13/365) -> 14.203322 | ... AU15: =AU14/(AU13/365) -> -151.24801 | AW15: =A14 -> Ending Stocks (September 30) | AX15: =AD14 -> 1590.053 | AY15: =AE14 -> 1184.515
A16: Average Price (Central Illinois - cents per pound) | W16: =W144 -> 31.780667 | X16: =X144 -> 29.989292 | Y16: =Y144 -> 32.526883 | Z16: =Z144 -> 30.031575 | AA16: =AA144 -> 28.324388 | AB16: =AB144 -> 29.621027 | AC16: =AC144 -> 57.913644 | AD16: =AD144 -> 72.145012 | ... AU16: =AU144 -> -1472.5519 | AW16: Source: USDA, Fastmarkets
A17: Bold Numbers are The Jacobsen Forecasts and Estimates | AD17: ='Soy Refined'!AD17-'Soy Crude'!AD16 -> 13.405256 | AO17: =AO18-AO6-50 -> 319.61484 | AP17: =AP18-AP6-50 -> 315.57564 | AQ17: =AQ18-AQ6-50 -> 228.88732 | AR17: =AR18-AR6-50 -> 224.50619 | AS17: =AS18-AS6-50 -> 220.65792 | AT17: =AT18-AT6-50 -> 216.79021 | AU17: =AU18-AU6-50 -> 212.80239
Z18: ='Soy Refined'!Z10+'Soy Refined'!Z13-'Soy Refined'!Z6 -> 13602.229 | AA18: ='Soy Refined'!AA10+'Soy Refined'!AA13-'Soy Refined'!AA6 -> 12937.08 | AB18: ='Soy Refined'!AB10+'Soy Refined'!AB13-'Soy Refined'!AB6 -> 13247.526 | AC18: ='Soy Refined'!AC10+'Soy Refined'!AC13-'Soy Refined'!AC6 -> 14196.424 | AD18: ='Soy Refined'!AD10+'Soy Refined'!AD13-'Soy Refined'!AD6 -> 14719.714 | AE18: ='Soy Refined'!AE10+'Soy Refined'!AE13-'Soy Refined'!AE6 -> 14275.554 | AF18: ='Soy Refined'!AF10+'Soy Refined'!AF13-'Soy Refined'!AF6 -> 14642.08 | AG18: ='Soy Refined'!AG10+'Soy Refined'!AG13-'Soy Refined'!AG6 -> 17466.463 | ... AK18: ='Soy Refined'!AK10+'Soy Refined'!AK13-'Soy Refined'!AK6 -> 20544.972 | AO18: =AO6+'Soy Refined'!AO6 -> 500 | AP18: =AP6+'Soy Refined'!AP6 -> 500 | AQ18: =AQ6+'Soy Refined'!AQ6 -> 400 | AR18: =AR6+'Soy Refined'!AR6 -> 400 | AS18: =AS6+'Soy Refined'!AS6 -> 400 | AT18: =AT6+'Soy Refined'!AT6 -> 400 | AU18: =AU6+'Soy Refined'!AU6 -> 400
A19: CRUDE SOYBEAN OIL PRODUCTION (Million Pounds) | Z19: ='Soy Refined'!Z11+Z12-Z6+Z10 -> 7291.4324 | AA19: ='Soy Refined'!AA11+AA12-AA6+AA10 -> 7844.8416 | AB19: ='Soy Refined'!AB11+AB12-AB6+AB10 -> 8767.0704 | AC19: ='Soy Refined'!AC11+AC12-AC6+AC10 -> 8032.5567 | AD19: ='Soy Refined'!AD11+AD12-AD6+AD10 -> 8745.6558 | AE19: ='Soy Refined'!AE11+AE12-AE6+AE10 -> 8475.3354 | AF19: ='Soy Refined'!AF11+AF12-AF6+AF10 -> 8021.3674 | AG19: ='Soy Refined'!AG11+AG12-AG6+AG10 -> 7594.7841 | ... AK19: ='Soy Refined'!AK11+AK12-AK6+AK10 -> 7784.6361
B20: =B$2 -> 93/94 | C20: =C$2 -> 94/95 | D20: =D$2 -> 95/96 | E20: =E$2 -> 96/97 | F20: =F$2 -> 97/98 | G20: =G$2 -> 98/99 | H20: =H$2 -> 99/00 | I20: =I$2 -> 00/01 | ... AU20: =AU$2 -> 38/39
A21: October | X21: ='[4]NASS Crush'!$O10 -> 1962.937 | Y21: ='[4]NASS Crush'!$O22 -> 2028.518 | Z21: ='[4]NASS Crush'!$O34 -> 2016.888 | AA21: ='[4]NASS Crush'!$O46 -> 2134.553 | AB21: ='[4]NASS Crush'!$O58 -> 2149.969 | AC21: ='[4]NASS Crush'!$O70 -> 2282.471 | AD21: ='[4]NASS Crush'!$O82 -> 2347.58 | AE21: ='[4]NASS Crush'!$O94 -> 2338.085 | AF21: ='[4]NASS Crush'!$O106 -> 2375.654 | AG21: ='[3]Soy Complex'!BN276 -> 2596.75 | AH21: ='[3]Soy Complex'!BO276 -> 2726 | AI21: ='[3]Soy Complex'!BP276 -> 2950 | AJ21: ='[3]Soy Complex'!BQ276 -> 3009 | AK21: ='[3]Soy Complex'!BR276 -> 3032.6 | AL21: ='[3]Soy Complex'!BS276 -> 3209.6 | AM21: ='[3]Soy Complex'!BT276 -> 3292.2 | AN21: ='[3]Soy Complex'!BU276 -> 3433.8 | ... AU21: ='[3]Soy Complex'!CB276 -> 3681.6
A22: November | X22: ='[4]NASS Crush'!$O11 -> 1901.853 | Y22: ='[4]NASS Crush'!$O23 -> 1961.256 | Z22: ='[4]NASS Crush'!$O35 -> 1977.005 | AA22: ='[4]NASS Crush'!$O47 -> 2060.563 | AB22: ='[4]NASS Crush'!$O59 -> 1999.648 | AC22: ='[4]NASS Crush'!$O71 -> 2206.792 | AD22: ='[4]NASS Crush'!$O83 -> 2235.37 | AE22: ='[4]NASS Crush'!$O95 -> 2199.962 | AF22: ='[4]NASS Crush'!$O107 -> 2324.668 | AG22: ='[3]Soy Complex'!BN277 -> 2493.1 | AH22: ='[3]Soy Complex'!BO277 -> 2644.8 | AI22: ='[3]Soy Complex'!BP277 -> 2818.8 | AJ22: ='[3]Soy Complex'!BQ277 -> 2888.4 | AK22: ='[3]Soy Complex'!BR277 -> 2911.6 | AL22: ='[3]Soy Complex'!BS277 -> 3074 | AM22: ='[3]Soy Complex'!BT277 -> 3143.6 | AN22: ='[3]Soy Complex'!BU277 -> 3294.4 | ... AU22: ='[3]Soy Complex'!CB277 -> 3526.4
A23: December | X23: ='[4]NASS Crush'!$O12 -> 1929.027 | Y23: ='[4]NASS Crush'!$O24 -> 1950.176 | Z23: ='[4]NASS Crush'!$O36 -> 2015.256 | AA23: ='[4]NASS Crush'!$O48 -> 2135.37 | AB23: ='[4]NASS Crush'!$O60 -> 2110.936 | AC23: ='[4]NASS Crush'!$O72 -> 2233.486 | AD23: ='[4]NASS Crush'!$O84 -> 2324.183 | AE23: ='[4]NASS Crush'!$O96 -> 2195.358 | AF23: ='[4]NASS Crush'!$O108 -> 2376.237 | AG23: ='[3]Soy Complex'!BN278 -> 2574 | AH23: ='[3]Soy Complex'!BO278 -> 2702.8 | AI23: ='[3]Soy Complex'!BP278 -> 2901.6 | AJ23: ='[3]Soy Complex'!BQ278 -> 2948.4 | AK23: ='[3]Soy Complex'!BR278 -> 3006.9 | AL23: ='[3]Soy Complex'!BS278 -> 3170.7 | AM23: ='[3]Soy Complex'!BT278 -> 3252.6 | AN23: ='[3]Soy Complex'!BU278 -> 3381.3 | ... AU23: ='[3]Soy Complex'!CB278 -> 3627
A24: January | X24: ='[4]NASS Crush'!$O13 -> 1864.887 | Y24: ='[4]NASS Crush'!$O25 -> 1982.893 | Z24: ='[4]NASS Crush'!$O37 -> 1995.589 | AA24: ='[4]NASS Crush'!$O49 -> 2115.799 | AB24: ='[4]NASS Crush'!$O61 -> 2154.427 | AC24: ='[4]NASS Crush'!$O73 -> 2308.752 | AD24: ='[4]NASS Crush'!$O85 -> 2277.355 | AE24: ='[4]NASS Crush'!$O97 -> 2252.312 | AF24: ='[4]NASS Crush'!$O109 -> 2288.572 | AG24: ='[3]Soy Complex'!BN279 -> 2573.25 | AH24: ='[3]Soy Complex'!BO279 -> 2702.5 | AI24: ='[3]Soy Complex'!BP279 -> 2855.25 | AJ24: ='[3]Soy Complex'!BQ279 -> 2937.5 | AK24: ='[3]Soy Complex'!BR279 -> 2961 | AL24: ='[3]Soy Complex'!BS279 -> 3149 | AM24: ='[3]Soy Complex'!BT279 -> 3231.25 | AN24: ='[3]Soy Complex'!BU279 -> 3360.5 | ... AU24: ='[3]Soy Complex'!CB279 -> 3607.25
A25: February | X25: ='[4]NASS Crush'!$O14 -> 1795.866 | Y25: ='[4]NASS Crush'!$O26 -> 1757.03 | Z25: ='[4]NASS Crush'!$O38 -> 1889.841 | AA25: ='[4]NASS Crush'!$O50 -> 1899.196 | AB25: ='[4]NASS Crush'!$O62 -> 1999.524 | AC25: ='[4]NASS Crush'!$O74 -> 1924.749 | AD25: ='[4]NASS Crush'!$O86 -> 2064.199 | AE25: ='[4]NASS Crush'!$O98 -> 2091.218 | AF25: ='[4]NASS Crush'!$O110 -> 2292.36 | AG25: ='[3]Soy Complex'!BN280 -> 2324.6 | AH25: ='[3]Soy Complex'!BO280 -> 2466.2 | AI25: ='[3]Soy Complex'!BP280 -> 2678.6 | AJ25: ='[3]Soy Complex'!BQ280 -> 2725.8 | AK25: ='[3]Soy Complex'!BR280 -> 2784.8 | AL25: ='[3]Soy Complex'!BS280 -> 2891 | AM25: ='[3]Soy Complex'!BT280 -> 3009 | AN25: ='[3]Soy Complex'!BU280 -> 3079.8 | ... AU25: ='[3]Soy Complex'!CB280 -> 3339.4
A26: March | X26: ='[4]NASS Crush'!$O15 -> 1943.537 | Y26: ='[4]NASS Crush'!$O27 -> 1865.466 | Z26: ='[4]NASS Crush'!$O39 -> 2079.123 | AA26: ='[4]NASS Crush'!$O51 -> 2094.418 | AB26: ='[4]NASS Crush'!$O63 -> 2201.068 | AC26: ='[4]NASS Crush'!$O75 -> 2222.123 | AD26: ='[4]NASS Crush'!$O87 -> 2277.541 | AE26: ='[4]NASS Crush'!$O99 -> 2339.581 | AF26: ='[4]NASS Crush'!$O111 -> 2405.571 | AG26: ='[3]Soy Complex'!BN281 -> 2584.2 | AH26: ='[3]Soy Complex'!BO281 -> 2737.6 | AI26: ='[3]Soy Complex'!BP281 -> 2938.2 | AJ26: ='[3]Soy Complex'!BQ281 -> 2985.4 | AK26: ='[3]Soy Complex'!BR281 -> 3056.2 | AL26: ='[3]Soy Complex'!BS281 -> 3186 | AM26: ='[3]Soy Complex'!BT281 -> 3304 | AN26: ='[3]Soy Complex'!BU281 -> 3398.4 | ... AU26: ='[3]Soy Complex'!CB281 -> 3669.8
A27: April | X27: ='[4]NASS Crush'!$O16 -> 1840.263 | Y27: ='[4]NASS Crush'!$O28 -> 1737.775 | Z27: ='[4]NASS Crush'!$O40 -> 1964.922 | AA27: ='[4]NASS Crush'!$O52 -> 1989.101 | AB27: ='[4]NASS Crush'!$O64 -> 2099.465 | AC27: ='[4]NASS Crush'!$O76 -> 1991.877 | AD27: ='[4]NASS Crush'!$O88 -> 2143.118 | AE27: ='[4]NASS Crush'!$O100 -> 2236.301 | AF27: ='[4]NASS Crush'!$O112 -> 2097.756 | AG27: ='[3]Soy Complex'!BN282 -> 2373.5 | AH27: ='[3]Soy Complex'!BO282 -> 2513.4 | AI27: ='[3]Soy Complex'!BP282 -> 2725.8 | AJ27: ='[3]Soy Complex'!BQ282 -> 2761.05 | AK27: ='[3]Soy Complex'!BR282 -> 2808.4 | AL27: ='[3]Soy Complex'!BS282 -> 2950 | AM27: ='[3]Soy Complex'!BT282 -> 3068 | AN27: ='[3]Soy Complex'!BU282 -> 3127 | ... AU27: ='[3]Soy Complex'!CB282 -> 3386.6
A28: May | W28: ='[4]NASS Crush'!$O5 -> 1754.179 | X28: ='[4]NASS Crush'!$O17 -> 1876.184 | Y28: ='[4]NASS Crush'!$O29 -> 1839.342 | Z28: ='[4]NASS Crush'!$O41 -> 1966.511 | AA28: ='[4]NASS Crush'!$O53 -> 1915.994 | AB28: ='[4]NASS Crush'!$O65 -> 2057.617 | AC28: ='[4]NASS Crush'!$O77 -> 2043.135 | AD28: ='[4]NASS Crush'!$O89 -> 2158.774 | AE28: ='[4]NASS Crush'!$O101 -> 2228.372 | AF28: ='[4]NASS Crush'!$O113 -> 2271.018 | AG28: ='[3]Soy Complex'!BN283 -> 2361.75 | AH28: ='[3]Soy Complex'!BO283 -> 2548.8 | AI28: ='[3]Soy Complex'!BP283 -> 2761.2 | AJ28: ='[3]Soy Complex'!BQ283 -> 2796.6 | AK28: ='[3]Soy Complex'!BR283 -> 2843.8 | AL28: ='[3]Soy Complex'!BS283 -> 2961.8 | AM28: ='[3]Soy Complex'!BT283 -> 3091.6 | AN28: ='[3]Soy Complex'!BU283 -> 3174.2 | ... AU28: ='[3]Soy Complex'!CB283 -> 3422
A29: June | W29: ='[4]NASS Crush'!$O6 -> 1708.286 | X29: ='[4]NASS Crush'!$O18 -> 1787.234 | Y29: ='[4]NASS Crush'!$O30 -> 1735.608 | Z29: ='[4]NASS Crush'!$O42 -> 1936.907 | AA29: ='[4]NASS Crush'!$O54 -> 1811.481 | AB29: ='[4]NASS Crush'!$O66 -> 2035.269 | AC29: ='[4]NASS Crush'!$O78 -> 1908.649 | AD29: ='[4]NASS Crush'!$O90 -> 2068.578 | AE29: ='[4]NASS Crush'!$O102 -> 2074.857 | AF29: ='[4]NASS Crush'!$O114 -> 2183.615 | AG29: ='[3]Soy Complex'!BN284 -> 2232.5 | AH29: ='[3]Soy Complex'!BO284 -> 2405.55 | AI29: ='[3]Soy Complex'!BP284 -> 2607 | AJ29: ='[3]Soy Complex'!BQ284 -> 2630.7 | AK29: ='[3]Soy Complex'!BR284 -> 2701.8 | AL29: ='[3]Soy Complex'!BS284 -> 2808.45 | AM29: ='[3]Soy Complex'!BT284 -> 2938.8 | AN29: ='[3]Soy Complex'!BU284 -> 2998.05 | ... AU29: ='[3]Soy Complex'!CB284 -> 3235.05
A30: July | W30: ='[4]NASS Crush'!$O7 -> 1738.053 | X30: ='[4]NASS Crush'!$O19 -> 1789.356 | Y30: ='[4]NASS Crush'!$O31 -> 1801.376 | Z30: ='[4]NASS Crush'!$O43 -> 2043.323 | AA30: ='[4]NASS Crush'!$O55 -> 2090.168 | AB30: ='[4]NASS Crush'!$O67 -> 2122.758 | AC30: ='[4]NASS Crush'!$O79 -> 1972.688 | AD30: ='[4]NASS Crush'!$O91 -> 2169.93 | AE30: ='[4]NASS Crush'!$O103 -> 2180.036 | AF30: ='[4]NASS Crush'!$O115 -> 2303.082 | AG30: ='[3]Soy Complex'!BN285 -> 2324.6 | AH30: ='[3]Soy Complex'!BO285 -> 2512.2 | AI30: ='[3]Soy Complex'!BP285 -> 2713.65 | AJ30: ='[3]Soy Complex'!BQ285 -> 2761.05 | AK30: ='[3]Soy Complex'!BR285 -> 2832.15 | AL30: ='[3]Soy Complex'!BS285 -> 2962.5 | AM30: ='[3]Soy Complex'!BT285 -> 3081 | AN30: ='[3]Soy Complex'!BU285 -> 3128.4 | ... AU30: ='[3]Soy Complex'!CB285 -> 3389.1
A31: August | W31: ='[4]NASS Crush'!$O8 -> 1626.655 | X31: ='[4]NASS Crush'!$O20 -> 1642.478 | Y31: ='[4]NASS Crush'!$O32 -> 1762.207 | Z31: ='[4]NASS Crush'!$O44 -> 1944.966 | AA31: ='[4]NASS Crush'!$O56 -> 2049.888 | AB31: ='[4]NASS Crush'!$O68 -> 2012.823 | AC31: ='[4]NASS Crush'!$O80 -> 1989.733 | AD31: ='[4]NASS Crush'!$O92 -> 2095.581 | AE31: ='[4]NASS Crush'!$O104 -> 2014.153 | AF31: ='[4]NASS Crush'!$O116 -> 1991.846 | AG31: ='[3]Soy Complex'!BN286 -> 2206.6 | AH31: ='[3]Soy Complex'!BO286 -> 2415.7 | AI31: ='[3]Soy Complex'!BP286 -> 2582.3 | AJ31: ='[3]Soy Complex'!BQ286 -> 2653.7 | AK31: ='[3]Soy Complex'!BR286 -> 2713.2 | AL31: ='[3]Soy Complex'!BS286 -> 2867.9 | AM31: ='[3]Soy Complex'!BT286 -> 2951.2 | AN31: ='[3]Soy Complex'!BU286 -> 3034.5 | ... AU31: ='[3]Soy Complex'!CB286 -> 3284.4
A32: September | W32: ='[4]NASS Crush'!$O9 -> 1531.282 | X32: ='[4]NASS Crush'!$O21 -> 1616.609 | Y32: ='[4]NASS Crush'!$O33 -> 1701.762 | Z32: ='[4]NASS Crush'!$O45 -> 1942.097 | AA32: ='[4]NASS Crush'!$O57 -> 1900.668 | AB32: ='[4]NASS Crush'!$O69 -> 1967.621 | AC32: ='[4]NASS Crush'!$O81 -> 1938.212 | AD32: ='[4]NASS Crush'!$O93 -> 1992.964 | AE32: ='[4]NASS Crush'!$O105 -> 2077.074 | AF32: ='[4]NASS Crush'!$O117 -> 2221.349 | AG32: ='[3]Soy Complex'!BN287 -> 2242 | AH32: ='[3]Soy Complex'!BO287 -> 2476.65 | AI32: ='[3]Soy Complex'!BP287 -> 2512.2 | AJ32: ='[3]Soy Complex'!BQ287 -> 2535.9 | AK32: ='[3]Soy Complex'!BR287 -> 2725.5 | AL32: ='[3]Soy Complex'!BS287 -> 2772.9 | AM32: ='[3]Soy Complex'!BT287 -> 2903.25 | AN32: ='[3]Soy Complex'!BU287 -> 2867.7 | ... AU32: ='[3]Soy Complex'!CB287 -> 3140.25
A33: Total | W33: =SUM(W21:W32) -> 8358.455 | X33: =SUM(X21:X32) -> 21950.231 | Y33: =SUM(Y21:Y32) -> 22123.409 | Z33: =SUM(Z21:Z32) -> 23772.428 | AA33: =SUM(AA21:AA32) -> 24197.199 | AB33: =SUM(AB21:AB32) -> 24911.125 | AC33: =SUM(AC21:AC32) -> 25022.667 | AD33: =SUM(AD21:AD32) -> 26155.173 | ... AU33: =SUM(AU21:AU32) -> 41308.85
AD34: =AD5 -> 26155.173 | AE34: =AE5 -> 26227.309 | AF34: =AF5 -> 27131.728 | AG34: =AG5 -> 28886.85 | AH34: =AH5 -> 30852.2 | AI34: =AI5 -> 33044.6 | AJ34: =AJ5 -> 33633.5 | AK34: =AK5 -> 34377.95 | ... AS34: =AS5 -> 40731.1
A35: CRUDE SOYBEAN OIL IMPORTS (Million Pounds)
B36: =B$2 -> 93/94 | C36: =C$2 -> 94/95 | D36: =D$2 -> 95/96 | E36: =E$2 -> 96/97 | F36: =F$2 -> 97/98 | G36: =G$2 -> 98/99 | H36: =H$2 -> 99/00 | I36: =I$2 -> 00/01 | ... AU36: =AU$2 -> 38/39
A37: October | B37: ='[5]Crude SO Imports'!AG$290/1000 -> 1.403267 | C37: ='[5]Crude SO Imports'!AS$290/1000 -> 36.195652 | D37: ='[5]Crude SO Imports'!BE$290/1000 -> 18.673593 | E37: ='[5]Crude SO Imports'!BQ$290/1000 -> 0.05003 | F37: ='[5]Crude SO Imports'!CC$290/1000 -> 0.310002 | G37: ='[5]Crude SO Imports'!CO$290/1000 -> 0.595231 | H37: ='[5]Crude SO Imports'!DA$290/1000 -> 0.192663 | I37: ='[5]Crude SO Imports'!DM$290/1000 -> 0.365746 | J37: ='[5]Crude SO Imports'!DY$290/1000 -> 0.040301 | K37: ='[5]Crude SO Imports'!EK$290/1000 -> 0.033609 | L37: ='[5]Crude SO Imports'!EW$290/1000 -> 2.954049 | M37: ='[5]Crude SO Imports'!FI$290/1000 -> 0.289137 | N37: ='[5]Crude SO Imports'!FU$290/1000 -> 0 | O37: ='[5]Crude SO Imports'!GG$290/1000 -> 0.044093 | P37: ='[5]Crude SO Imports'!GS$290/1000 -> 1.717805 | Q37: ='[5]Crude SO Imports'!HE$290/1000 -> 1.158286 | R37: ='[5]Crude SO Imports'!HQ$290/1000 -> 2.226941 | S37: ='[5]Crude SO Imports'!IC$290/1000 -> 1.806515 | T37: ='[5]Crude SO Imports'!IO$290/1000 -> 0.619573 | U37: ='[5]Crude SO Imports'!JA$290/1000 -> 1.299112 | V37: ='[5]Crude SO Imports'!JM$290/1000 -> 0.824866 | W37: ='[5]Crude SO Imports'!JY$290/1000 -> 0.727071 | X37: ='[5]Crude SO Imports'!KK$290/1000 -> 24.830841 | Y37: ='[5]Crude SO Imports'!KW$290/1000 -> 0.958191 | Z37: ='[5]Crude SO Imports'!LI$290/1000 -> 1.461926 | AA37: ='[5]Crude SO Imports'!LU$290/1000 -> 3.831526 | AB37: ='[5]Crude SO Imports'!MG$290/1000 -> 1.999885 | AC37: ='[5]Crude SO Imports'!MS$290/1000 -> 2.238996 | AD37: ='[5]Crude SO Imports'!NE$290/1000 -> 10.168213 | AE37: ='[5]Crude SO Imports'!NQ$290/1000 -> 6.201313 | AF37: ='[5]Crude SO Imports'!OC$290/1000 -> 24.63836 | AG37: =(SUM(AA37:AE37)/SUM(AA$49:AE$49))*AG$49 -> 6.783106 | AH37: =(SUM(AB37:AF37)/SUM(AB$49:AF$49))*AH$49 -> 7.8807766 | AI37: =(SUM(AC37:AG37)/SUM(AC$49:AG$49))*AI$49 -> 8.6113233 | AJ37: =(SUM(AD37:AH37)/SUM(AD$49:AH$49))*AJ$49 -> 9.1791185 | AK37: =(SUM(AE37:AI37)/SUM(AE$49:AI$49))*AK$49 -> 8.9771329 | AL37: =(SUM(AF37:AJ37)/SUM(AF$49:AJ$49))*AL$49 -> 10.20638 | AM37: =(SUM(AG37:AK37)/SUM(AG$49:AK$49))*AM$49 -> 10.365011 | AN37: =(SUM(AH37:AL37)/SUM(AH$49:AL$49))*AN$49 -> 11.248425 | ... AU37: =(SUM(AO37:AS37)/SUM(AO$49:AS$49))*AU$49 -> 12.404213 | AW37: HS Code: | AX37: 15071
A38: November | B38: ='[5]Crude SO Imports'!AH$290/1000 -> 2.814985 | C38: ='[5]Crude SO Imports'!AT$290/1000 -> 7.756763 | D38: ='[5]Crude SO Imports'!BF$290/1000 -> 0.144474 | E38: ='[5]Crude SO Imports'!BR$290/1000 -> 0.034315 | F38: ='[5]Crude SO Imports'!CD$290/1000 -> 0.62023 | G38: ='[5]Crude SO Imports'!CP$290/1000 -> 0.572932 | H38: ='[5]Crude SO Imports'!DB$290/1000 -> 2.361428 | I38: ='[5]Crude SO Imports'!DN$290/1000 -> 0.294528 | J38: ='[5]Crude SO Imports'!DZ$290/1000 -> 0.090258 | K38: ='[5]Crude SO Imports'!EL$290/1000 -> 0.050588 | L38: ='[5]Crude SO Imports'!EX$290/1000 -> 0.425347 | M38: ='[5]Crude SO Imports'!FJ$290/1000 -> 0.054031 | N38: ='[5]Crude SO Imports'!FV$290/1000 -> 0 | O38: ='[5]Crude SO Imports'!GH$290/1000 -> 0.183463 | P38: ='[5]Crude SO Imports'!GT$290/1000 -> 2.037532 | Q38: ='[5]Crude SO Imports'!HF$290/1000 -> 1.332426 | R38: ='[5]Crude SO Imports'!HR$290/1000 -> 3.662978 | S38: ='[5]Crude SO Imports'!ID$290/1000 -> 10.669047 | T38: ='[5]Crude SO Imports'!IP$290/1000 -> 0.587738 | U38: ='[5]Crude SO Imports'!JB$290/1000 -> 0.683871 | V38: ='[5]Crude SO Imports'!JN$290/1000 -> 0.91355 | W38: ='[5]Crude SO Imports'!JZ$290/1000 -> 0.773126 | X38: ='[5]Crude SO Imports'!KL$290/1000 -> 0.891278 | Y38: ='[5]Crude SO Imports'!KX$290/1000 -> 24.892817 | Z38: ='[5]Crude SO Imports'!LJ$290/1000 -> 1.475496 | AA38: ='[5]Crude SO Imports'!LV$290/1000 -> 1.89487 | AB38: ='[5]Crude SO Imports'!MH$290/1000 -> 2.015794 | AC38: ='[5]Crude SO Imports'!MT$290/1000 -> 2.857715 | AD38: ='[5]Crude SO Imports'!NF$290/1000 -> 5.71231 | AE38: ='[5]Crude SO Imports'!NR$290/1000 -> 8.149154 | AF38: ='[5]Crude SO Imports'!OD$290/1000 -> 15.081243 | AG38: =(SUM(AA38:AE38)/SUM(AA$49:AE$49))*AG$49 -> 5.7256463 | AH38: =(SUM(AB38:AF38)/SUM(AB$49:AF$49))*AH$49 -> 5.8898804 | AI38: =(SUM(AC38:AG38)/SUM(AC$49:AG$49))*AI$49 -> 6.4591082 | AJ38: =(SUM(AD38:AH38)/SUM(AD$49:AH$49))*AJ$49 -> 6.6872104 | AK38: =(SUM(AE38:AI38)/SUM(AE$49:AI$49))*AK$49 -> 6.8521036 | AL38: =(SUM(AF38:AJ38)/SUM(AF$49:AJ$49))*AL$49 -> 7.1226933 | AM38: =(SUM(AG38:AK38)/SUM(AG$49:AK$49))*AM$49 -> 7.9089403 | AN38: =(SUM(AH38:AL38)/SUM(AH$49:AL$49))*AN$49 -> 8.2783175 | ... AU38: =(SUM(AO38:AS38)/SUM(AO$49:AS$49))*AU$49 -> 9.1660026
A39: December | B39: ='[5]Crude SO Imports'!AI$290/1000 -> 4.338391 | C39: ='[5]Crude SO Imports'!AU$290/1000 -> 33.70558 | D39: ='[5]Crude SO Imports'!BG$290/1000 -> 46.660396 | E39: ='[5]Crude SO Imports'!BS$290/1000 -> 0.423272 | F39: ='[5]Crude SO Imports'!CE$290/1000 -> 0.879486 | G39: ='[5]Crude SO Imports'!CQ$290/1000 -> 1.421982 | H39: ='[5]Crude SO Imports'!DC$290/1000 -> 0.352221 | I39: ='[5]Crude SO Imports'!DO$290/1000 -> 0.24518 | J39: ='[5]Crude SO Imports'!EA$290/1000 -> 0.04424 | K39: ='[5]Crude SO Imports'!EM$290/1000 -> 0.025574 | L39: ='[5]Crude SO Imports'!EY$290/1000 -> 0.182123 | M39: ='[5]Crude SO Imports'!FK$290/1000 -> 0.02752 | N39: ='[5]Crude SO Imports'!FW$290/1000 -> 0.180094 | O39: ='[5]Crude SO Imports'!GI$290/1000 -> 0.086523 | P39: ='[5]Crude SO Imports'!GU$290/1000 -> 1.527979 | Q39: ='[5]Crude SO Imports'!HG$290/1000 -> 1.096563 | R39: ='[5]Crude SO Imports'!HS$290/1000 -> 5.688669 | S39: ='[5]Crude SO Imports'!IE$290/1000 -> 11.729531 | T39: ='[5]Crude SO Imports'!IQ$290/1000 -> 8.954117 | U39: ='[5]Crude SO Imports'!JC$290/1000 -> 0.71075 | V39: ='[5]Crude SO Imports'!JO$290/1000 -> 0.799972 | W39: ='[5]Crude SO Imports'!KA$290/1000 -> 0.707493 | X39: ='[5]Crude SO Imports'!KM$290/1000 -> 0.939201 | Y39: ='[5]Crude SO Imports'!KY$290/1000 -> 26.883359 | Z39: ='[5]Crude SO Imports'!LK$290/1000 -> 1.348554 | AA39: ='[5]Crude SO Imports'!LW$290/1000 -> 5.023731 | AB39: ='[5]Crude SO Imports'!MI$290/1000 -> 3.344858 | AC39: ='[5]Crude SO Imports'!MU$290/1000 -> 1.843239 | AD39: ='[5]Crude SO Imports'!NG$290/1000 -> 3.507703 | AE39: ='[5]Crude SO Imports'!NS$290/1000 -> 6.811703 | AF39: ='[5]Crude SO Imports'!OE$290/1000 -> 34.064252 | AG39: =(SUM(AA39:AE39)/SUM(AA$49:AE$49))*AG$49 -> 5.6982782 | AH39: =(SUM(AB39:AF39)/SUM(AB$49:AF$49))*AH$49 -> 8.6340738 | AI39: =(SUM(AC39:AG39)/SUM(AC$49:AG$49))*AI$49 -> 8.937529 | AJ39: =(SUM(AD39:AH39)/SUM(AD$49:AH$49))*AJ$49 -> 9.6810506 | AK39: =(SUM(AE39:AI39)/SUM(AE$49:AI$49))*AK$49 -> 10.641171 | AL39: =(SUM(AF39:AJ39)/SUM(AF$49:AJ$49))*AL$49 -> 11.980211 | AM39: =(SUM(AG39:AK39)/SUM(AG$49:AK$49))*AM$49 -> 10.905545 | AN39: =(SUM(AH39:AL39)/SUM(AH$49:AL$49))*AN$49 -> 12.507139 | ... AU39: =(SUM(AO39:AS39)/SUM(AO$49:AS$49))*AU$49 -> 13.768636
A40: January | B40: ='[5]Crude SO Imports'!AJ$290/1000 -> 5.943475 | C40: ='[5]Crude SO Imports'!AV$290/1000 -> 0 | D40: ='[5]Crude SO Imports'!BH$290/1000 -> 39.857565 | E40: ='[5]Crude SO Imports'!BT$290/1000 -> 4.891433 | F40: ='[5]Crude SO Imports'!CF$290/1000 -> 0.512778 | G40: ='[5]Crude SO Imports'!CR$290/1000 -> 0.132935 | H40: ='[5]Crude SO Imports'!DD$290/1000 -> 0.774834 | I40: ='[5]Crude SO Imports'!DP$290/1000 -> 0.536293 | J40: ='[5]Crude SO Imports'!EB$290/1000 -> 0.092868 | K40: ='[5]Crude SO Imports'!EN$290/1000 -> 0.056968 | L40: ='[5]Crude SO Imports'!EZ$290/1000 -> 0.0864 | M40: ='[5]Crude SO Imports'!FL$290/1000 -> 0.050482 | N40: ='[5]Crude SO Imports'!FX$290/1000 -> 0.095324 | O40: ='[5]Crude SO Imports'!GJ$290/1000 -> 0.089693 | P40: ='[5]Crude SO Imports'!GV$290/1000 -> 1.451756 | Q40: ='[5]Crude SO Imports'!HH$290/1000 -> 3.387704 | R40: ='[5]Crude SO Imports'!HT$290/1000 -> 8.430091 | S40: ='[5]Crude SO Imports'!IF$290/1000 -> 7.257614 | T40: ='[5]Crude SO Imports'!IR$290/1000 -> 5.945764 | U40: ='[5]Crude SO Imports'!JD$290/1000 -> 0.788031 | V40: ='[5]Crude SO Imports'!JP$290/1000 -> 0.923481 | W40: ='[5]Crude SO Imports'!KB$290/1000 -> 23.268732 | X40: ='[5]Crude SO Imports'!KN$290/1000 -> 1.458696 | Y40: ='[5]Crude SO Imports'!KZ$290/1000 -> 1.028629 | Z40: ='[5]Crude SO Imports'!LL$290/1000 -> 1.482676 | AA40: ='[5]Crude SO Imports'!LX$290/1000 -> 2.717943 | AB40: ='[5]Crude SO Imports'!MJ$290/1000 -> 4.688134 | AC40: ='[5]Crude SO Imports'!MV$290/1000 -> 2.404595 | AD40: ='[5]Crude SO Imports'!NH$290/1000 -> 3.834378 | AE40: ='[5]Crude SO Imports'!NT$290/1000 -> 5.964591 | AF40: ='[5]Crude SO Imports'!OF$290/1000 -> 28.204331 | AG40: =(SUM(AA40:AE40)/SUM(AA$49:AE$49))*AG$49 -> 5.4424975 | AH40: =(SUM(AB40:AF40)/SUM(AB$49:AF$49))*AH$49 -> 7.8545221 | AI40: =(SUM(AC40:AG40)/SUM(AC$49:AG$49))*AI$49 -> 7.8919178 | AJ40: =(SUM(AD40:AH40)/SUM(AD$49:AH$49))*AJ$49 -> 8.4583573 | AK40: =(SUM(AE40:AI40)/SUM(AE$49:AI$49))*AK$49 -> 9.1833312 | AL40: =(SUM(AF40:AJ40)/SUM(AF$49:AJ$49))*AL$49 -> 10.342054 | AM40: =(SUM(AG40:AK40)/SUM(AG$49:AK$49))*AM$49 -> 9.7143544 | AN40: =(SUM(AH40:AL40)/SUM(AH$49:AL$49))*AN$49 -> 10.966417 | ... AU40: =(SUM(AO40:AS40)/SUM(AO$49:AS$49))*AU$49 -> 12.04491
A41: February | B41: ='[5]Crude SO Imports'!AK$290/1000 -> 6.410562 | C41: ='[5]Crude SO Imports'!AW$290/1000 -> 35.306381 | D41: ='[5]Crude SO Imports'!BI$290/1000 -> 8.355574 | E41: ='[5]Crude SO Imports'!BU$290/1000 -> 0.109791 | F41: ='[5]Crude SO Imports'!CG$290/1000 -> 0.640334 | G41: ='[5]Crude SO Imports'!CS$290/1000 -> 0.472067 | H41: ='[5]Crude SO Imports'!DE$290/1000 -> 0.562045 | I41: ='[5]Crude SO Imports'!DQ$290/1000 -> 0.459305 | J41: ='[5]Crude SO Imports'!EC$290/1000 -> 0.050748 | K41: ='[5]Crude SO Imports'!EO$290/1000 -> 0.047029 | L41: ='[5]Crude SO Imports'!FA$290/1000 -> 0.190143 | M41: ='[5]Crude SO Imports'!FM$290/1000 -> 0.050001 | N41: ='[5]Crude SO Imports'!FY$290/1000 -> 0.181298 | O41: ='[5]Crude SO Imports'!GK$290/1000 -> 0.044108 | P41: ='[5]Crude SO Imports'!GW$290/1000 -> 3.080778 | Q41: ='[5]Crude SO Imports'!HI$290/1000 -> 7.921632 | R41: ='[5]Crude SO Imports'!HU$290/1000 -> 7.559928 | S41: ='[5]Crude SO Imports'!IG$290/1000 -> 7.000646 | T41: ='[5]Crude SO Imports'!IS$290/1000 -> 4.015726 | U41: ='[5]Crude SO Imports'!JE$290/1000 -> 0.798585 | V41: ='[5]Crude SO Imports'!JQ$290/1000 -> 0.894804 | W41: ='[5]Crude SO Imports'!KC$290/1000 -> 0.804969 | X41: ='[5]Crude SO Imports'!KO$290/1000 -> 15.396858 | Y41: ='[5]Crude SO Imports'!LA$290/1000 -> 2.296609 | Z41: ='[5]Crude SO Imports'!LM$290/1000 -> 24.195297 | AA41: ='[5]Crude SO Imports'!LY$290/1000 -> 2.284418 | AB41: ='[5]Crude SO Imports'!MK$290/1000 -> 5.202839 | AC41: ='[5]Crude SO Imports'!MW$290/1000 -> 2.160649 | AD41: ='[5]Crude SO Imports'!NI$290/1000 -> 4.587215 | AE41: ='[5]Crude SO Imports'!NU$290/1000 -> 11.30477 | AF41: =(SUM(Z41:AD41)/SUM(Z$49:AD$49))*AF$49-20 -> 17.867038 | AG41: =(SUM(AA41:AE41)/SUM(AA$49:AE$49))*AG$49 -> 7.0883905 | AH41: =(SUM(AB41:AF41)/SUM(AB$49:AF$49))*AH$49 -> 7.1624415 | AI41: =(SUM(AC41:AG41)/SUM(AC$49:AG$49))*AI$49 -> 7.4026867 | AJ41: =(SUM(AD41:AH41)/SUM(AD$49:AH$49))*AJ$49 -> 7.915828 | AK41: =(SUM(AE41:AI41)/SUM(AE$49:AI$49))*AK$49 -> 8.431428 | AL41: =(SUM(AF41:AJ41)/SUM(AF$49:AJ$49))*AL$49 -> 8.4801362 | AM41: =(SUM(AG41:AK41)/SUM(AG$49:AK$49))*AM$49 -> 9.5067484 | AN41: =(SUM(AH41:AL41)/SUM(AH$49:AL$49))*AN$49 -> 9.8786414 | ... AU41: =(SUM(AO41:AS41)/SUM(AO$49:AS$49))*AU$49 -> 10.971281
A42: March | B42: ='[5]Crude SO Imports'!AL$290/1000 -> 7.354772 | C42: ='[5]Crude SO Imports'!AX$290/1000 -> 7.537732 | D42: ='[5]Crude SO Imports'!BJ$290/1000 -> 28.805309 | E42: ='[5]Crude SO Imports'!BV$290/1000 -> 0 | F42: ='[5]Crude SO Imports'!CH$290/1000 -> 0.695417 | G42: ='[5]Crude SO Imports'!CT$290/1000 -> 0.596362 | H42: ='[5]Crude SO Imports'!DF$290/1000 -> 0.518045 | I42: ='[5]Crude SO Imports'!DR$290/1000 -> 0.38834 | J42: ='[5]Crude SO Imports'!ED$290/1000 -> 0.027939 | K42: ='[5]Crude SO Imports'!EP$290/1000 -> 0 | L42: ='[5]Crude SO Imports'!FB$290/1000 -> 0.256994 | M42: ='[5]Crude SO Imports'!FN$290/1000 -> 0.094821 | N42: ='[5]Crude SO Imports'!FZ$290/1000 -> 0.303918 | O42: ='[5]Crude SO Imports'!GL$290/1000 -> 0.186481 | P42: ='[5]Crude SO Imports'!GX$290/1000 -> 4.496367 | Q42: ='[5]Crude SO Imports'!HJ$290/1000 -> 7.848796 | R42: ='[5]Crude SO Imports'!HV$290/1000 -> 0.617412 | S42: ='[5]Crude SO Imports'!IH$290/1000 -> 3.296618 | T42: ='[5]Crude SO Imports'!IT$290/1000 -> 2.842563 | U42: ='[5]Crude SO Imports'!JF$290/1000 -> 0.596495 | V42: ='[5]Crude SO Imports'!JR$290/1000 -> 0.80823 | W42: ='[5]Crude SO Imports'!KD$290/1000 -> 1.188609 | X42: ='[5]Crude SO Imports'!KP$290/1000 -> 1.304777 | Y42: ='[5]Crude SO Imports'!LB$290/1000 -> 1.67156 | Z42: ='[5]Crude SO Imports'!LN$290/1000 -> 3.557049 | AA42: ='[5]Crude SO Imports'!LZ$290/1000 -> 1.346855 | AB42: ='[5]Crude SO Imports'!ML$290/1000 -> 3.311211 | AC42: ='[5]Crude SO Imports'!MX$290/1000 -> 2.890514 | AD42: ='[5]Crude SO Imports'!NJ$290/1000 -> 5.529926 | AE42: ='[5]Crude SO Imports'!NV$290/1000 -> 6.958106 | AF42: =(SUM(Z42:AD42)/SUM(Z$49:AD$49))*AF$49+5 -> 21.391682 | AG42: =(SUM(AA42:AE42)/SUM(AA$49:AE$49))*AG$49 -> 5.5609998 | AH42: =(SUM(AB42:AF42)/SUM(AB$49:AF$49))*AH$49 -> 6.9811146 | AI42: =(SUM(AC42:AG42)/SUM(AC$49:AG$49))*AI$49 -> 7.2861878 | AJ42: =(SUM(AD42:AH42)/SUM(AD$49:AH$49))*AJ$49 -> 7.6539954 | AK42: =(SUM(AE42:AI42)/SUM(AE$49:AI$49))*AK$49 -> 7.9922773 | AL42: =(SUM(AF42:AJ42)/SUM(AF$49:AJ$49))*AL$49 -> 8.7371331 | AM42: =(SUM(AG42:AK42)/SUM(AG$49:AK$49))*AM$49 -> 8.8747627 | AN42: =(SUM(AH42:AL42)/SUM(AH$49:AL$49))*AN$49 -> 9.6926138 | ... AU42: =(SUM(AO42:AS42)/SUM(AO$49:AS$49))*AU$49 -> 10.658463
A43: April | B43: ='[5]Crude SO Imports'!AM$290/1000 -> 7.615252 | C43: ='[5]Crude SO Imports'!AY$290/1000 -> 0.382621 | D43: ='[5]Crude SO Imports'!BK$290/1000 -> 25.072079 | E43: ='[5]Crude SO Imports'!BW$290/1000 -> 1.957561 | F43: ='[5]Crude SO Imports'!CI$290/1000 -> 0.522329 | G43: ='[5]Crude SO Imports'!CU$290/1000 -> 0.2331 | H43: ='[5]Crude SO Imports'!DG$290/1000 -> 0.399114 | I43: ='[5]Crude SO Imports'!DS$290/1000 -> 0.478692 | J43: ='[5]Crude SO Imports'!EE$290/1000 -> 0.044622 | K43: ='[5]Crude SO Imports'!EQ$290/1000 -> 0.393254 | L43: ='[5]Crude SO Imports'!FC$290/1000 -> 3.141396 | M43: ='[5]Crude SO Imports'!FO$290/1000 -> 0 | N43: ='[5]Crude SO Imports'!GA$290/1000 -> 0.122686 | O43: ='[5]Crude SO Imports'!GM$290/1000 -> 0.69886 | P43: ='[5]Crude SO Imports'!GY$290/1000 -> 4.346857 | Q43: ='[5]Crude SO Imports'!HK$290/1000 -> 4.384316 | R43: ='[5]Crude SO Imports'!HW$290/1000 -> 2.836504 | S43: ='[5]Crude SO Imports'!II$290/1000 -> 0.888829 | T43: ='[5]Crude SO Imports'!IU$290/1000 -> 8.013043 | U43: ='[5]Crude SO Imports'!JG$290/1000 -> 11.864023 | V43: ='[5]Crude SO Imports'!JS$290/1000 -> 0.909548 | W43: ='[5]Crude SO Imports'!KE$290/1000 -> 25.372268 | X43: ='[5]Crude SO Imports'!KQ$290/1000 -> 7.827421 | Y43: ='[5]Crude SO Imports'!LC$290/1000 -> 3.530014 | Z43: ='[5]Crude SO Imports'!LO$290/1000 -> 1.241892 | AA43: ='[5]Crude SO Imports'!MA$290/1000 -> 1.220993 | AB43: ='[5]Crude SO Imports'!MM$290/1000 -> 13.1076 | AC43: ='[5]Crude SO Imports'!MY$290/1000 -> 1.674267 | AD43: ='[5]Crude SO Imports'!NK$290/1000 -> 5.008871 | AE43: ='[5]Crude SO Imports'!NW$290/1000 -> 8.110964 | AF43: =(SUM(Z43:AD43)/SUM(Z$49:AD$49))*AF$49-2 -> 19.92739 | AG43: =(SUM(AA43:AE43)/SUM(AA$49:AE$49))*AG$49 -> 8.0827688 | AH43: =(SUM(AB43:AF43)/SUM(AB$49:AF$49))*AH$49 -> 8.3305486 | AI43: =(SUM(AC43:AG43)/SUM(AC$49:AG$49))*AI$49 -> 7.3676078 | AJ43: =(SUM(AD43:AH43)/SUM(AD$49:AH$49))*AJ$49 -> 8.1550163 | AK43: =(SUM(AE43:AI43)/SUM(AE$49:AI$49))*AK$49 -> 8.5963152 | AL43: =(SUM(AF43:AJ43)/SUM(AF$49:AJ$49))*AL$49 -> 9.2715355 | AM43: =(SUM(AG43:AK43)/SUM(AG$49:AK$49))*AM$49 -> 10.140056 | AN43: =(SUM(AH43:AL43)/SUM(AH$49:AL$49))*AN$49 -> 10.462571 | ... AU43: =(SUM(AO43:AS43)/SUM(AO$49:AS$49))*AU$49 -> 11.565643
A44: May | B44: ='[5]Crude SO Imports'!AN$290/1000 -> 9.341297 | C44: ='[5]Crude SO Imports'!AZ$290/1000 -> 0.045909 | D44: ='[5]Crude SO Imports'!BL$290/1000 -> 32.715867 | E44: ='[5]Crude SO Imports'!BX$290/1000 -> 0.42051 | F44: ='[5]Crude SO Imports'!CJ$290/1000 -> 0.368754 | G44: ='[5]Crude SO Imports'!CV$290/1000 -> 0.283461 | H44: ='[5]Crude SO Imports'!DH$290/1000 -> 0.265952 | I44: ='[5]Crude SO Imports'!DT$290/1000 -> 0.271812 | J44: ='[5]Crude SO Imports'!EF$290/1000 -> 0 | K44: ='[5]Crude SO Imports'!ER$290/1000 -> 0.046275 | L44: ='[5]Crude SO Imports'!FD$290/1000 -> 87.369841 | M44: ='[5]Crude SO Imports'!FP$290/1000 -> 0 | N44: ='[5]Crude SO Imports'!GB$290/1000 -> 0.148958 | O44: ='[5]Crude SO Imports'!GN$290/1000 -> 1.761893 | P44: ='[5]Crude SO Imports'!GZ$290/1000 -> 2.44104 | Q44: ='[5]Crude SO Imports'!HL$290/1000 -> 0.340845 | R44: ='[5]Crude SO Imports'!HX$290/1000 -> 0.595257 | S44: ='[5]Crude SO Imports'!IJ$290/1000 -> 1.794896 | T44: ='[5]Crude SO Imports'!IV$290/1000 -> 0.847459 | U44: ='[5]Crude SO Imports'!JH$290/1000 -> 1.001486 | V44: ='[5]Crude SO Imports'!JT$290/1000 -> 1.060632 | W44: ='[5]Crude SO Imports'!KF$290/1000 -> 1.275782 | X44: ='[5]Crude SO Imports'!KR$290/1000 -> 1.386922 | Y44: ='[5]Crude SO Imports'!LD$290/1000 -> 3.679993 | Z44: ='[5]Crude SO Imports'!LP$290/1000 -> 1.66415 | AA44: ='[5]Crude SO Imports'!MB$290/1000 -> 1.219354 | AB44: ='[5]Crude SO Imports'!MN$290/1000 -> 6.890872 | AC44: ='[5]Crude SO Imports'!MZ$290/1000 -> 3.691004 | AD44: ='[5]Crude SO Imports'!NL$290/1000 -> 7.705822 | AE44: ='[5]Crude SO Imports'!NX$290/1000 -> 7.642706 | AF44: =(SUM(Z44:AD44)/SUM(Z$49:AD$49))*AF$49 -> 20.860837 | AG44: =(SUM(AA44:AE44)/SUM(AA$49:AE$49))*AG$49 -> 7.5351961 | AH44: =(SUM(AB44:AF44)/SUM(AB$49:AF$49))*AH$49 -> 8.1497828 | AI44: =(SUM(AC44:AG44)/SUM(AC$49:AG$49))*AI$49 -> 8.1647629 | AJ44: =(SUM(AD44:AH44)/SUM(AD$49:AH$49))*AJ$49 -> 8.5562996 | AK44: =(SUM(AE44:AI44)/SUM(AE$49:AI$49))*AK$49 -> 8.6849016 | AL44: =(SUM(AF44:AJ44)/SUM(AF$49:AJ$49))*AL$49 -> 9.5224456 | AM44: =(SUM(AG44:AK44)/SUM(AG$49:AK$49))*AM$49 -> 10.279823 | ... AU44: =(SUM(AO44:AS44)/SUM(AO$49:AS$49))*AU$49 -> 11.901342
A45: June | B45: ='[5]Crude SO Imports'!AO$290/1000 -> 5.901874 | C45: ='[5]Crude SO Imports'!BA$290/1000 -> 0.080119 | D45: ='[5]Crude SO Imports'!BM$290/1000 -> 16.42816 | E45: ='[5]Crude SO Imports'!BY$290/1000 -> 2.049428 | F45: ='[5]Crude SO Imports'!CK$290/1000 -> 0.509361 | G45: ='[5]Crude SO Imports'!CW$290/1000 -> 0.3749 | H45: ='[5]Crude SO Imports'!DI$290/1000 -> 30.885507 | I45: ='[5]Crude SO Imports'!DU$290/1000 -> 0.379481 | J45: ='[5]Crude SO Imports'!EG$290/1000 -> 0.002434 | K45: ='[5]Crude SO Imports'!ES$290/1000 -> 0.134747 | L45: ='[5]Crude SO Imports'!FE$290/1000 -> 117.73233 | M45: ='[5]Crude SO Imports'!FQ$290/1000 -> 0 | N45: ='[5]Crude SO Imports'!GC$290/1000 -> 0.13338 | O45: ='[5]Crude SO Imports'!GO$290/1000 -> 8.098172 | P45: ='[5]Crude SO Imports'!HA$290/1000 -> 1.144816 | Q45: ='[5]Crude SO Imports'!HM$290/1000 -> 1.457347 | R45: ='[5]Crude SO Imports'!HY$290/1000 -> 0.475017 | S45: ='[5]Crude SO Imports'!IK$290/1000 -> 0.825938 | T45: ='[5]Crude SO Imports'!IW$290/1000 -> 0.766165 | U45: ='[5]Crude SO Imports'!JI$290/1000 -> 0.826917 | V45: ='[5]Crude SO Imports'!JU$290/1000 -> 1.103781 | W45: ='[5]Crude SO Imports'!KG$290/1000 -> 26.726764 | X45: ='[5]Crude SO Imports'!KS$290/1000 -> 1.315377 | Y45: ='[5]Crude SO Imports'!LE$290/1000 -> 1.303855 | Z45: ='[5]Crude SO Imports'!LQ$290/1000 -> 5.081865 | AA45: ='[5]Crude SO Imports'!MC$290/1000 -> 1.052047 | AB45: ='[5]Crude SO Imports'!MO$290/1000 -> 5.536654 | AC45: ='[5]Crude SO Imports'!NA$290/1000 -> 4.212024 | AD45: ='[5]Crude SO Imports'!NM$290/1000 -> 7.696212 | AE45: ='[5]Crude SO Imports'!NY$290/1000 -> 5.379149 | AF45: =(SUM(Z45:AD45)/SUM(Z$49:AD$49))*AF$49-2 -> 21.233143 | AG45: =(SUM(AA45:AE45)/SUM(AA$49:AE$49))*AG$49 -> 6.6266149 | AH45: =(SUM(AB45:AF45)/SUM(AB$49:AF$49))*AH$49 -> 7.6735827 | AI45: =(SUM(AC45:AG45)/SUM(AC$49:AG$49))*AI$49 -> 7.7708721 | AJ45: =(SUM(AD45:AH45)/SUM(AD$49:AH$49))*AJ$49 -> 8.0145653 | AK45: =(SUM(AE45:AI45)/SUM(AE$49:AI$49))*AK$49 -> 8.0760968 | AL45: =(SUM(AF45:AJ45)/SUM(AF$49:AJ$49))*AL$49 -> 9.1741863 | AM45: =(SUM(AG45:AK45)/SUM(AG$49:AK$49))*AM$49 -> 9.5470155 | AN45: =(SUM(AH45:AL45)/SUM(AH$49:AL$49))*AN$49 -> 10.208857 | ... AU45: =(SUM(AO45:AS45)/SUM(AO$49:AS$49))*AU$49 -> 11.206528
A46: July | B46: ='[5]Crude SO Imports'!AP$290/1000 -> 7.884325 | C46: ='[5]Crude SO Imports'!BB$290/1000 -> 0.066565 | D46: ='[5]Crude SO Imports'!BN$290/1000 -> 23.332457 | E46: ='[5]Crude SO Imports'!BZ$290/1000 -> 0.782012 | F46: ='[5]Crude SO Imports'!CL$290/1000 -> 0.318686 | G46: ='[5]Crude SO Imports'!CX$290/1000 -> 0.190917 | H46: ='[5]Crude SO Imports'!DJ$290/1000 -> 0.748557 | I46: ='[5]Crude SO Imports'!DV$290/1000 -> 0.08255 | J46: ='[5]Crude SO Imports'!EH$290/1000 -> 0 | K46: ='[5]Crude SO Imports'!ET$290/1000 -> 5.696245 | L46: ='[5]Crude SO Imports'!FF$290/1000 -> 0.049401 | M46: ='[5]Crude SO Imports'!FR$290/1000 -> 0 | N46: ='[5]Crude SO Imports'!GD$290/1000 -> 0.875654 | O46: ='[5]Crude SO Imports'!GP$290/1000 -> 1.408552 | P46: ='[5]Crude SO Imports'!HB$290/1000 -> 3.188334 | Q46: ='[5]Crude SO Imports'!HN$290/1000 -> 3.665881 | R46: ='[5]Crude SO Imports'!HZ$290/1000 -> 0.307348 | S46: ='[5]Crude SO Imports'!IL$290/1000 -> 0.568763 | T46: ='[5]Crude SO Imports'!IX$290/1000 -> 1.216138 | U46: ='[5]Crude SO Imports'!JJ$290/1000 -> 0.98709 | V46: ='[5]Crude SO Imports'!JV$290/1000 -> 0.784032 | W46: ='[5]Crude SO Imports'!KH$290/1000 -> 1.044359 | X46: ='[5]Crude SO Imports'!KT$290/1000 -> 1.086583 | Y46: ='[5]Crude SO Imports'!LF$290/1000 -> 1.164523 | Z46: ='[5]Crude SO Imports'!LR$290/1000 -> 6.394431 | AA46: ='[5]Crude SO Imports'!MD$290/1000 -> 1.907588 | AB46: ='[5]Crude SO Imports'!MP$290/1000 -> 3.171044 | AC46: ='[5]Crude SO Imports'!NB$290/1000 -> 6.360534 | AD46: ='[5]Crude SO Imports'!NN$290/1000 -> 5.065353 | AE46: ='[5]Crude SO Imports'!NZ$290/1000 -> 8.38241 | AF46: =(SUM(Z46:AD46)/SUM(Z$49:AD$49))*AF$49-2 -> 20.563257 | AG46: =(SUM(AA46:AE46)/SUM(AA$49:AE$49))*AG$49 -> 6.9071662 | AH46: =(SUM(AB46:AF46)/SUM(AB$49:AF$49))*AH$49 -> 7.583956 | AI46: =(SUM(AC46:AG46)/SUM(AC$49:AG$49))*AI$49 -> 8.1377662 | AJ46: =(SUM(AD46:AH46)/SUM(AD$49:AH$49))*AJ$49 -> 7.996996 | AK46: =(SUM(AE46:AI46)/SUM(AE$49:AI$49))*AK$49 -> 8.5557179 | AL46: =(SUM(AF46:AJ46)/SUM(AF$49:AJ$49))*AL$49 -> 9.1510114 | AM46: =(SUM(AG46:AK46)/SUM(AG$49:AK$49))*AM$49 -> 9.802159 | AN46: =(SUM(AH46:AL46)/SUM(AH$49:AL$49))*AN$49 -> 10.388448 | ... AU46: =(SUM(AO46:AS46)/SUM(AO$49:AS$49))*AU$49 -> 11.449823
A47: August | B47: ='[5]Crude SO Imports'!AQ$290/1000 -> 21.15303 | C47: ='[5]Crude SO Imports'!BC$290/1000 -> 0.064854 | D47: ='[5]Crude SO Imports'!BO$290/1000 -> 21.378234 | E47: ='[5]Crude SO Imports'!CA$290/1000 -> 0.43167 | F47: ='[5]Crude SO Imports'!CM$290/1000 -> 0.341401 | G47: ='[5]Crude SO Imports'!CY$290/1000 -> 0.117386 | H47: ='[5]Crude SO Imports'!DK$290/1000 -> 0.89132 | I47: ='[5]Crude SO Imports'!DW$290/1000 -> 0.171042 | J47: ='[5]Crude SO Imports'!EI$290/1000 -> 0.030314 | K47: ='[5]Crude SO Imports'!EU$290/1000 -> 14.193968 | L47: ='[5]Crude SO Imports'!FG$290/1000 -> 96.892605 | M47: ='[5]Crude SO Imports'!FS$290/1000 -> 0 | N47: ='[5]Crude SO Imports'!GE$290/1000 -> 0.185586 | O47: ='[5]Crude SO Imports'!GQ$290/1000 -> 3.34943 | P47: ='[5]Crude SO Imports'!HC$290/1000 -> 3.984868 | Q47: ='[5]Crude SO Imports'!HO$290/1000 -> 3.478344 | R47: ='[5]Crude SO Imports'!IA$290/1000 -> 0.358077 | S47: ='[5]Crude SO Imports'!IM$290/1000 -> 0.268189 | T47: ='[5]Crude SO Imports'!IY$290/1000 -> 1.441705 | U47: ='[5]Crude SO Imports'!JK$290/1000 -> 1.012849 | V47: ='[5]Crude SO Imports'!JW$290/1000 -> 0.848954 | W47: ='[5]Crude SO Imports'!KI$290/1000 -> 24.894372 | X47: ='[5]Crude SO Imports'!KU$290/1000 -> 0.973368 | Y47: ='[5]Crude SO Imports'!LG$290/1000 -> 1.093064 | Z47: ='[5]Crude SO Imports'!LS$290/1000 -> 3.778692 | AA47: ='[5]Crude SO Imports'!ME$290/1000 -> 1.894943 | AB47: ='[5]Crude SO Imports'!MQ$290/1000 -> 1.940444 | AC47: ='[5]Crude SO Imports'!NC$290/1000 -> 15.331939 | AD47: ='[5]Crude SO Imports'!NO$290/1000 -> 6.065775 | AE47: ='[5]Crude SO Imports'!OA$290/1000 -> 10.405496 | AF47: =(SUM(Z47:AD47)/SUM(Z$49:AD$49))*AF$49-10 -> 18.586487 | AG47: =(SUM(AA47:AE47)/SUM(AA$49:AE$49))*AG$49 -> 9.8912048 | AH47: =(SUM(AB47:AF47)/SUM(AB$49:AF$49))*AH$49 -> 9.114511 | AI47: =(SUM(AC47:AG47)/SUM(AC$49:AG$49))*AI$49 -> 10.375744 | AJ47: =(SUM(AD47:AH47)/SUM(AD$49:AH$49))*AJ$49 -> 8.9139441 | AK47: =(SUM(AE47:AI47)/SUM(AE$49:AI$49))*AK$49 -> 9.6835873 | AL47: =(SUM(AF47:AJ47)/SUM(AF$49:AJ$49))*AL$49 -> 10.168696 | AM47: =(SUM(AG47:AK47)/SUM(AG$49:AK$49))*AM$49 -> 12.003024 | AN47: =(SUM(AH47:AL47)/SUM(AH$49:AL$49))*AN$49 -> 12.101497 | ... AU47: =(SUM(AO47:AS47)/SUM(AO$49:AS$49))*AU$49 -> 13.341122
A48: September | B48: ='[5]Crude SO Imports'!AR$290/1000 -> 5.389671 | C48: ='[5]Crude SO Imports'!BD$290/1000 -> 0.034919 | D48: ='[5]Crude SO Imports'!BP$290/1000 -> 7.895465 | E48: ='[5]Crude SO Imports'!CB$290/1000 -> 0.543991 | F48: ='[5]Crude SO Imports'!CN$290/1000 -> 0.136892 | G48: ='[5]Crude SO Imports'!CZ$290/1000 -> 10.306967 | H48: ='[5]Crude SO Imports'!DL$290/1000 -> 0.538969 | I48: ='[5]Crude SO Imports'!DX$290/1000 -> 0 | J48: ='[5]Crude SO Imports'!EJ$290/1000 -> 0 | K48: ='[5]Crude SO Imports'!EV$290/1000 -> 0.754992 | L48: ='[5]Crude SO Imports'!FH$290/1000 -> 0.142091 | M48: ='[5]Crude SO Imports'!FT$290/1000 -> 0 | N48: ='[5]Crude SO Imports'!GF$290/1000 -> 0 | O48: ='[5]Crude SO Imports'!GR$290/1000 -> 0.139093 | P48: ='[5]Crude SO Imports'!HD$290/1000 -> 2.861472 | Q48: ='[5]Crude SO Imports'!HP$290/1000 -> 2.444986 | R48: ='[5]Crude SO Imports'!IB$290/1000 -> 0.367228 | S48: ='[5]Crude SO Imports'!IN$290/1000 -> 0.34329 | T48: ='[5]Crude SO Imports'!IZ$290/1000 -> 0.668873 | U48: ='[5]Crude SO Imports'!JL$290/1000 -> 0.790427 | V48: ='[5]Crude SO Imports'!JX$290/1000 -> 0.911601 | W48: ='[5]Crude SO Imports'!KJ$290/1000 -> 0.671435 | X48: ='[5]Crude SO Imports'!KV$290/1000 -> 0.752869 | Y48: ='[5]Crude SO Imports'!LH$290/1000 -> 1.226 | Z48: ='[5]Crude SO Imports'!LT$290/1000 -> 4.802721 | AA48: ='[5]Crude SO Imports'!MF$290/1000 -> 1.508387 | AB48: ='[5]Crude SO Imports'!MR$290/1000 -> 3.117734 | AC48: ='[5]Crude SO Imports'!ND$290/1000 -> 4.268032 | AD48: ='[5]Crude SO Imports'!NP$290/1000 -> 5.812142 | AE48: ='[5]Crude SO Imports'!OB$290/1000 -> 8.922351 | AF48: =AF49-SUM(AF37:AF47) -> 11.151312 | AG48: =AG49-SUM(AG37:AG47) -> 6.5579399 | AH48: =AH49-SUM(AH37:AH47) -> 5.7950178 | AI48: =AI49-SUM(AI37:AI47) -> 6.3189498 | AJ48: =AJ49-SUM(AJ37:AJ47) -> 6.3047779 | AK48: =AK49-SUM(AK37:AK47) -> 6.4275139 | AL48: =AL49-SUM(AL37:AL47) -> 6.4585518 | AM48: =AM49-SUM(AM37:AM47) -> 7.8564667 | ... AU48: =AU49-SUM(AU37:AU47) -> 8.7196477
A49: Total | B49: =SUM(B37:B48) -> 85.550901 | C49: =SUM(C37:C48) -> 121.17709 | D49: =SUM(D37:D48) -> 269.31917 | E49: =SUM(E37:E48) -> 11.694013 | F49: =SUM(F37:F48) -> 5.85567 | G49: =SUM(G37:G48) -> 15.29824 | H49: =SUM(H37:H48) -> 38.490655 | I49: =SUM(I37:I48) -> 3.672969 | ... AE49: =SUM(AE37:AE48) -> 94.232713 | AF49: =AF6 -> 253.56933 | AG49: =AG6 -> 81.899809 | AH49: =AH6 -> 91.050208 | AI49: =AI6 -> 94.724455 | AJ49: =AJ6 -> 97.517159 | AK49: =AK6 -> 102.10158 | AL49: =AL6 -> 110.61503 | AM49: =AM6 -> 116.90391 | ... AU49: =AU6 -> 137.19761
A51: CRUDE SOYBEAN OIL EXPORTS (Million Pounds)
B52: =B$2 -> 93/94 | C52: =C$2 -> 94/95 | D52: =D$2 -> 95/96 | E52: =E$2 -> 96/97 | F52: =F$2 -> 97/98 | G52: =G$2 -> 98/99 | H52: =H$2 -> 99/00 | I52: =I$2 -> 00/01 | ... AU52: =AU$2 -> 38/39
A53: October | B53: =('[5]Crude SO Exports'!AG$290)/1000 -> 144.0061 | C53: =('[5]Crude SO Exports'!AS$290)/1000 -> 99.868536 | D53: =('[5]Crude SO Exports'!BE$290)/1000 -> 20.46412 | E53: =('[5]Crude SO Exports'!BQ$290)/1000 -> 83.467415 | F53: =('[5]Crude SO Exports'!CC$290)/1000 -> 133.00311 | G53: =('[5]Crude SO Exports'!CO$290)/1000 -> 131.21909 | H53: =('[5]Crude SO Exports'!DA$290)/1000 -> 165.26212 | I53: =('[5]Crude SO Exports'!DM$290)/1000 -> 13.301727 | J53: =('[5]Crude SO Exports'!DY$290)/1000 -> 210.36704 | K53: =('[5]Crude SO Exports'!EK$290)/1000 -> 74.086658 | L53: =('[5]Crude SO Exports'!EW$290)/1000 -> 92.095774 | M53: =('[5]Crude SO Exports'!FI$290)/1000 -> 63.633875 | N53: =('[5]Crude SO Exports'!FU$290)/1000 -> 47.739609 | O53: =('[5]Crude SO Exports'!GG$290)/1000 -> 140.13859 | P53: =('[5]Crude SO Exports'!GS$290)/1000 -> 87.576651 | Q53: =('[5]Crude SO Exports'!HE$290)/1000 -> 112.92725 | R53: =('[5]Crude SO Exports'!HQ$290)/1000 -> 300.40904 | S53: =('[5]Crude SO Exports'!IC$290)/1000 -> 396.3554 | T53: =('[5]Crude SO Exports'!IO$290)/1000 -> 64.661432 | U53: =('[5]Crude SO Exports'!JA$290)/1000 -> 214.14271 | V53: =('[5]Crude SO Exports'!JM$290)/1000 -> 22.030863 | W53: =('[5]Crude SO Exports'!JY$290)/1000 -> 127.63293 | X53: =('[5]Crude SO Exports'!KK$290)/1000 -> 150.92294 | Y53: =('[5]Crude SO Exports'!KW$290)/1000 -> 192.96649 | Z53: =('[5]Crude SO Exports'!LI$290)/1000 -> 176.86852 | AA53: =('[5]Crude SO Exports'!LU$290)/1000 -> 123.14858 | AB53: =('[5]Crude SO Exports'!MG$290)/1000 -> 224.77119 | AC53: =('[5]Crude SO Exports'!MS$290)/1000 -> 141.15958 | AD53: =('[5]Crude SO Exports'!NE$290)/1000 -> 36.265941 | AE53: =('[5]Crude SO Exports'!NQ$290)/1000 -> 3.386964 | AF53: =('[5]Crude SO Exports'!OC$290)/1000 -> 0.520152 | AG53: =(SUM(AA53:AE53)/SUM(AA$65:AE$65))*AG$65 -> 0.74494493 | AH53: =(SUM(AB53:AF53)/SUM(AB$65:AF$65))*AH$65 -> 0.70650067 | AI53: =(SUM(AC53:AG53)/SUM(AC$65:AG$65))*AI$65 -> 0.49430404 | AJ53: =(SUM(AD53:AH53)/SUM(AD$65:AH$65))*AJ$65 -> 0.1665621 | AK53: =(SUM(AE53:AI53)/SUM(AE$65:AI$65))*AK$65 -> 0.046396367 | AL53: =(SUM(AF53:AJ53)/SUM(AF$65:AJ$65))*AL$65 -> 0.045788704 | AM53: =(SUM(AG53:AK53)/SUM(AG$65:AK$65))*AM$65 -> 0.036687222 | AN53: =(SUM(AH53:AL53)/SUM(AH$65:AL$65))*AN$65 -> 0.049761341 | ... AU53: =(SUM(AO53:AS53)/SUM(AO$65:AS$65))*AU$65 -> 0.018145104
A54: November | B54: =('[5]Crude SO Exports'!AH$290)/1000 -> 51.84019 | C54: =('[5]Crude SO Exports'!AT$290)/1000 -> 256.4501 | D54: =('[5]Crude SO Exports'!BF$290)/1000 -> 165.21782 | E54: =('[5]Crude SO Exports'!BR$290)/1000 -> 263.16804 | F54: =('[5]Crude SO Exports'!CD$290)/1000 -> 300.55732 | G54: =('[5]Crude SO Exports'!CP$290)/1000 -> 279.88331 | H54: =('[5]Crude SO Exports'!DB$290)/1000 -> 85.954165 | I54: =('[5]Crude SO Exports'!DN$290)/1000 -> 84.686763 | J54: =('[5]Crude SO Exports'!DZ$290)/1000 -> 105.56193 | K54: =('[5]Crude SO Exports'!EL$290)/1000 -> 133.45341 | L54: =('[5]Crude SO Exports'!EX$290)/1000 -> 75.033258 | M54: =('[5]Crude SO Exports'!FJ$290)/1000 -> 124.85024 | N54: =('[5]Crude SO Exports'!FV$290)/1000 -> 89.208516 | O54: =('[5]Crude SO Exports'!GH$290)/1000 -> 92.265914 | P54: =('[5]Crude SO Exports'!GT$290)/1000 -> 153.75986 | Q54: =('[5]Crude SO Exports'!HF$290)/1000 -> 64.13274 | R54: =('[5]Crude SO Exports'!HR$290)/1000 -> 196.19348 | S54: =('[5]Crude SO Exports'!ID$290)/1000 -> 399.49437 | T54: =('[5]Crude SO Exports'!IP$290)/1000 -> 84.950703 | U54: =('[5]Crude SO Exports'!JB$290)/1000 -> 236.28586 | V54: =('[5]Crude SO Exports'!JN$290)/1000 -> 106.24887 | W54: =('[5]Crude SO Exports'!JZ$290)/1000 -> 190.82763 | X54: =('[5]Crude SO Exports'!KL$290)/1000 -> 212.63735 | Y54: =('[5]Crude SO Exports'!KX$290)/1000 -> 198.96325 | Z54: =('[5]Crude SO Exports'!LJ$290)/1000 -> 92.456753 | AA54: =('[5]Crude SO Exports'!LV$290)/1000 -> 193.72104 | AB54: =('[5]Crude SO Exports'!MH$290)/1000 -> 216.6103 | AC54: =('[5]Crude SO Exports'!MT$290)/1000 -> 143.28783 | AD54: =('[5]Crude SO Exports'!NF$290)/1000 -> 206.5376 | AE54: =('[5]Crude SO Exports'!NR$290)/1000 -> 2.435808 | AF54: =('[5]Crude SO Exports'!OD$290)/1000 -> 0.783081 | AG54: =(SUM(AA54:AE54)/SUM(AA$65:AE$65))*AG$65 -> 1.074437 | AH54: =(SUM(AB54:AF54)/SUM(AB$65:AF$65))*AH$65 -> 0.99103073 | AI54: =(SUM(AC54:AG54)/SUM(AC$65:AG$65))*AI$65 -> 0.96136123 | AJ54: =(SUM(AD54:AH54)/SUM(AD$65:AH$65))*AJ$65 -> 0.84761394 | AK54: =(SUM(AE54:AI54)/SUM(AE$65:AI$65))*AK$65 -> 0.049510554 | AL54: =(SUM(AF54:AJ54)/SUM(AF$65:AJ$65))*AL$65 -> 0.081012315 | AM54: =(SUM(AG54:AK54)/SUM(AG$65:AK$65))*AM$65 -> 0.066687547 | AN54: =(SUM(AH54:AL54)/SUM(AH$65:AL$65))*AN$65 -> 0.099912201 | ... AU54: =(SUM(AO54:AS54)/SUM(AO$65:AS$65))*AU$65 -> 0.042083032
A55: December | B55: =('[5]Crude SO Exports'!AI$290)/1000 -> 171.49531 | C55: =('[5]Crude SO Exports'!AU$290)/1000 -> 256.65035 | D55: =('[5]Crude SO Exports'!BG$290)/1000 -> 58.801329 | E55: =('[5]Crude SO Exports'!BS$290)/1000 -> 164.43166 | F55: =('[5]Crude SO Exports'!CE$290)/1000 -> 162.56322 | G55: =('[5]Crude SO Exports'!CQ$290)/1000 -> 298.66541 | H55: =('[5]Crude SO Exports'!DC$290)/1000 -> 112.07118 | I55: =('[5]Crude SO Exports'!DO$290)/1000 -> 203.49073 | J55: =('[5]Crude SO Exports'!EA$290)/1000 -> 131.1958 | K55: =('[5]Crude SO Exports'!EM$290)/1000 -> 129.93288 | L55: =('[5]Crude SO Exports'!EY$290)/1000 -> 86.895725 | M55: =('[5]Crude SO Exports'!FK$290)/1000 -> 189.86494 | N55: =('[5]Crude SO Exports'!FW$290)/1000 -> 60.997397 | O55: =('[5]Crude SO Exports'!GI$290)/1000 -> 223.61063 | P55: =('[5]Crude SO Exports'!GU$290)/1000 -> 309.94876 | Q55: =('[5]Crude SO Exports'!HG$290)/1000 -> 83.291276 | R55: =('[5]Crude SO Exports'!HS$290)/1000 -> 333.48007 | S55: =('[5]Crude SO Exports'!IE$290)/1000 -> 337.08976 | T55: =('[5]Crude SO Exports'!IQ$290)/1000 -> 40.930385 | U55: =('[5]Crude SO Exports'!JC$290)/1000 -> 310.42146 | V55: =('[5]Crude SO Exports'!JO$290)/1000 -> 280.58266 | W55: =('[5]Crude SO Exports'!KA$290)/1000 -> 187.62444 | X55: =('[5]Crude SO Exports'!KM$290)/1000 -> 281.6902 | Y55: =('[5]Crude SO Exports'!KY$290)/1000 -> 197.74031 | Z55: =('[5]Crude SO Exports'!LK$290)/1000 -> 134.24352 | AA55: =('[5]Crude SO Exports'!LW$290)/1000 -> 136.39433 | AB55: =('[5]Crude SO Exports'!MI$290)/1000 -> 140.21181 | AC55: =('[5]Crude SO Exports'!MU$290)/1000 -> 208.11616 | AD55: =('[5]Crude SO Exports'!NG$290)/1000 -> 137.06626 | AE55: =('[5]Crude SO Exports'!NS$290)/1000 -> 22.840101 | AF55: =('[5]Crude SO Exports'!OE$290)/1000 -> 0.379068 | AG55: =(SUM(AA55:AE55)/SUM(AA$65:AE$65))*AG$65 -> 0.90823446 | AH55: =(SUM(AB55:AF55)/SUM(AB$65:AF$65))*AH$65 -> 0.88483704 | AI55: =(SUM(AC55:AG55)/SUM(AC$65:AG$65))*AI$65 -> 1.0026019 | AJ55: =(SUM(AD55:AH55)/SUM(AD$65:AH$65))*AJ$65 -> 0.64856355 | AK55: =(SUM(AE55:AI55)/SUM(AE$65:AI$65))*AK$65 -> 0.20622277 | AL55: =(SUM(AF55:AJ55)/SUM(AF$65:AJ$65))*AL$65 -> 0.066502029 | AM55: =(SUM(AG55:AK55)/SUM(AG$65:AK$65))*AM$65 -> 0.062039525 | AN55: =(SUM(AH55:AL55)/SUM(AH$65:AL$65))*AN$65 -> 0.095759554 | ... AU55: =(SUM(AO55:AS55)/SUM(AO$65:AS$65))*AU$65 -> 0.043703499
A56: January | B56: =('[5]Crude SO Exports'!AJ$290)/1000 -> 101.1984 | C56: =('[5]Crude SO Exports'!AV$290)/1000 -> 155.38479 | D56: =('[5]Crude SO Exports'!BH$290)/1000 -> 159.49883 | E56: =('[5]Crude SO Exports'!BT$290)/1000 -> 123.32592 | F56: =('[5]Crude SO Exports'!CF$290)/1000 -> 312.13564 | G56: =('[5]Crude SO Exports'!CR$290)/1000 -> 210.53278 | H56: =('[5]Crude SO Exports'!DD$290)/1000 -> 53.180884 | I56: =('[5]Crude SO Exports'!DP$290)/1000 -> 103.41721 | J56: =('[5]Crude SO Exports'!EB$290)/1000 -> 203.8244 | K56: =('[5]Crude SO Exports'!EN$290)/1000 -> 209.11065 | L56: =('[5]Crude SO Exports'!EZ$290)/1000 -> 36.537988 | M56: =('[5]Crude SO Exports'!FL$290)/1000 -> 61.944763 | N56: =('[5]Crude SO Exports'!FX$290)/1000 -> 27.82863 | O56: =('[5]Crude SO Exports'!GJ$290)/1000 -> 153.82245 | P56: =('[5]Crude SO Exports'!GV$290)/1000 -> 136.45232 | Q56: =('[5]Crude SO Exports'!HH$290)/1000 -> 62.624946 | R56: =('[5]Crude SO Exports'!HT$290)/1000 -> 474.74331 | S56: =('[5]Crude SO Exports'!IF$290)/1000 -> 445.87748 | T56: =('[5]Crude SO Exports'!IR$290)/1000 -> 69.405564 | U56: =('[5]Crude SO Exports'!JD$290)/1000 -> 209.3207 | V56: =('[5]Crude SO Exports'!JP$290)/1000 -> 224.19838 | W56: =('[5]Crude SO Exports'!KB$290)/1000 -> 217.82865 | X56: =('[5]Crude SO Exports'!KN$290)/1000 -> 141.75479 | Y56: =('[5]Crude SO Exports'!KZ$290)/1000 -> 211.38764 | Z56: =('[5]Crude SO Exports'!LL$290)/1000 -> 149.78153 | AA56: =('[5]Crude SO Exports'!LX$290)/1000 -> 190.30792 | AB56: =('[5]Crude SO Exports'!MJ$290)/1000 -> 98.946052 | AC56: =('[5]Crude SO Exports'!MV$290)/1000 -> 299.44505 | AD56: =('[5]Crude SO Exports'!NH$290)/1000 -> 244.65484 | AE56: =('[5]Crude SO Exports'!NT$290)/1000 -> 0.445939 | AF56: =('[5]Crude SO Exports'!OF$290)/1000 -> 0.061313 | AG56: =(SUM(AA56:AE56)/SUM(AA$65:AE$65))*AG$65 -> 1.1747627 | AH56: =(SUM(AB56:AF56)/SUM(AB$65:AF$65))*AH$65 -> 1.1195924 | AI56: =(SUM(AC56:AG56)/SUM(AC$65:AG$65))*AI$65 -> 1.4816882 | AJ56: =(SUM(AD56:AH56)/SUM(AD$65:AH$65))*AJ$65 -> 0.99020679 | AK56: =(SUM(AE56:AI56)/SUM(AE$65:AI$65))*AK$65 -> 0.033954195 | AL56: =(SUM(AF56:AJ56)/SUM(AF$65:AJ$65))*AL$65 -> 0.083969953 | AM56: =(SUM(AG56:AK56)/SUM(AG$65:AK$65))*AM$65 -> 0.081579422 | AN56: =(SUM(AH56:AL56)/SUM(AH$65:AL$65))*AN$65 -> 0.1264671 | ... AU56: =(SUM(AO56:AS56)/SUM(AO$65:AS$65))*AU$65 -> 0.051228524
A57: February | B57: =('[5]Crude SO Exports'!AK$290)/1000 -> 120.44894 | C57: =('[5]Crude SO Exports'!AW$290)/1000 -> 314.87779 | D57: =('[5]Crude SO Exports'!BI$290)/1000 -> 57.633883 | E57: =('[5]Crude SO Exports'!BU$290)/1000 -> 184.14318 | F57: =('[5]Crude SO Exports'!CG$290)/1000 -> 286.02353 | G57: =('[5]Crude SO Exports'!CS$290)/1000 -> 195.8813 | H57: =('[5]Crude SO Exports'!DE$290)/1000 -> 106.99371 | I57: =('[5]Crude SO Exports'!DQ$290)/1000 -> 134.39483 | J57: =('[5]Crude SO Exports'!EC$290)/1000 -> 361.49049 | K57: =('[5]Crude SO Exports'!EO$290)/1000 -> 257.93655 | L57: =('[5]Crude SO Exports'!FA$290)/1000 -> 30.693632 | M57: =('[5]Crude SO Exports'!FM$290)/1000 -> 177.78851 | N57: =('[5]Crude SO Exports'!FY$290)/1000 -> 48.93511 | O57: =('[5]Crude SO Exports'!GK$290)/1000 -> 78.916861 | P57: =('[5]Crude SO Exports'!GW$290)/1000 -> 423.90248 | Q57: =('[5]Crude SO Exports'!HI$290)/1000 -> 128.17712 | R57: =('[5]Crude SO Exports'!HU$290)/1000 -> 359.14251 | S57: =('[5]Crude SO Exports'!IG$290)/1000 -> 261.98206 | T57: =('[5]Crude SO Exports'!IS$290)/1000 -> 132.38155 | U57: =('[5]Crude SO Exports'!JE$290)/1000 -> 303.70962 | V57: =('[5]Crude SO Exports'!JQ$290)/1000 -> 238.24354 | W57: =('[5]Crude SO Exports'!KC$290)/1000 -> 178.33318 | X57: =('[5]Crude SO Exports'!KO$290)/1000 -> 87.616006 | Y57: =('[5]Crude SO Exports'!LA$290)/1000 -> 197.6473 | Z57: =('[5]Crude SO Exports'!LM$290)/1000 -> 150.19608 | AA57: =('[5]Crude SO Exports'!LY$290)/1000 -> 64.441807 | AB57: =('[5]Crude SO Exports'!MK$290)/1000 -> 358.89234 | AC57: =('[5]Crude SO Exports'!MW$290)/1000 -> 227.12955 | AD57: =('[5]Crude SO Exports'!NI$290)/1000 -> 182.49014 | AE57: =('[5]Crude SO Exports'!NU$290)/1000 -> 14.132694 | AF57: =(SUM(Z57:AD57)/SUM(Z$65:AD$65))*AF$65 -> 0.73709517 | AG57: =(SUM(AA57:AE57)/SUM(AA$65:AE$65))*AG$65 -> 1.1934827 | AH57: =(SUM(AB57:AF57)/SUM(AB$65:AF$65))*AH$65 -> 1.3628529 | AI57: =(SUM(AC57:AG57)/SUM(AC$65:AG$65))*AI$65 -> 1.1556437 | AJ57: =(SUM(AD57:AH57)/SUM(AD$65:AH$65))*AJ$65 -> 0.79997285 | AK57: =(SUM(AE57:AI57)/SUM(AE$65:AI$65))*AK$65 -> 0.1472999 | AL57: =(SUM(AF57:AJ57)/SUM(AF$65:AJ$65))*AL$65 -> 0.09130119 | AM57: =(SUM(AG57:AK57)/SUM(AG$65:AK$65))*AM$65 -> 0.07918394 | ... AU57: =(SUM(AO57:AS57)/SUM(AO$65:AS$65))*AU$65 -> 0.049984604
A58: March | B58: =('[5]Crude SO Exports'!AL$290)/1000 -> 67.527372 | C58: =('[5]Crude SO Exports'!AX$290)/1000 -> 457.18733 | D58: =('[5]Crude SO Exports'!BJ$290)/1000 -> 40.846585 | E58: =('[5]Crude SO Exports'!BV$290)/1000 -> 228.02215 | F58: =('[5]Crude SO Exports'!CH$290)/1000 -> 201.89522 | G58: =('[5]Crude SO Exports'!CT$290)/1000 -> 89.292972 | H58: =('[5]Crude SO Exports'!DF$290)/1000 -> 92.706466 | I58: =('[5]Crude SO Exports'!DR$290)/1000 -> 94.210426 | J58: =('[5]Crude SO Exports'!ED$290)/1000 -> 181.79463 | K58: =('[5]Crude SO Exports'!EP$290)/1000 -> 240.19049 | L58: =('[5]Crude SO Exports'!FB$290)/1000 -> 52.584511 | M58: =('[5]Crude SO Exports'!FN$290)/1000 -> 56.304685 | N58: =('[5]Crude SO Exports'!FZ$290)/1000 -> 127.64593 | O58: =('[5]Crude SO Exports'!GL$290)/1000 -> 55.838184 | P58: =('[5]Crude SO Exports'!GX$290)/1000 -> 367.16047 | Q58: =('[5]Crude SO Exports'!HJ$290)/1000 -> 117.16926 | R58: =('[5]Crude SO Exports'!HV$290)/1000 -> 342.01052 | S58: =('[5]Crude SO Exports'!IH$290)/1000 -> 306.916 | T58: =('[5]Crude SO Exports'!IT$290)/1000 -> 53.202728 | U58: =('[5]Crude SO Exports'!JF$290)/1000 -> 102.04956 | V58: =('[5]Crude SO Exports'!JR$290)/1000 -> 167.60522 | W58: =('[5]Crude SO Exports'!KD$290)/1000 -> 191.11284 | X58: =('[5]Crude SO Exports'!KP$290)/1000 -> 199.34611 | Y58: =('[5]Crude SO Exports'!LB$290)/1000 -> 238.2674 | Z58: =('[5]Crude SO Exports'!LN$290)/1000 -> 139.47298 | AA58: =('[5]Crude SO Exports'!LZ$290)/1000 -> 233.51622 | AB58: =('[5]Crude SO Exports'!ML$290)/1000 -> 287.577 | AC58: =('[5]Crude SO Exports'!MX$290)/1000 -> 134.55137 | AD58: =('[5]Crude SO Exports'!NJ$290)/1000 -> 253.37368 | AE58: =('[5]Crude SO Exports'!NV$290)/1000 -> 1.338969 | AF58: =(SUM(Z58:AD58)/SUM(Z$65:AD$65))*AF$65 -> 0.78608342 | AG58: =(SUM(AA58:AE58)/SUM(AA$65:AE$65))*AG$65 -> 1.2826265 | AH58: =(SUM(AB58:AF58)/SUM(AB$65:AF$65))*AH$65 -> 1.1788709 | AI58: =(SUM(AC58:AG58)/SUM(AC$65:AG$65))*AI$65 -> 1.0623897 | AJ58: =(SUM(AD58:AH58)/SUM(AD$65:AH$65))*AJ$65 -> 1.0322381 | AK58: =(SUM(AE58:AI58)/SUM(AE$65:AI$65))*AK$65 -> 0.04477982 | AL58: =(SUM(AF58:AJ58)/SUM(AF$65:AJ$65))*AL$65 -> 0.092921626 | AM58: =(SUM(AG58:AK58)/SUM(AG$65:AK$65))*AM$65 -> 0.078192334 | ... AU58: =(SUM(AO58:AS58)/SUM(AO$65:AS$65))*AU$65 -> 0.048796033
A59: April | B59: =('[5]Crude SO Exports'!AM$290)/1000 -> 1.100666 | C59: =('[5]Crude SO Exports'!AY$290)/1000 -> 186.88441 | D59: =('[5]Crude SO Exports'!BK$290)/1000 -> 57.099071 | E59: =('[5]Crude SO Exports'!BW$290)/1000 -> 54.835832 | F59: =('[5]Crude SO Exports'!CI$290)/1000 -> 162.56703 | G59: =('[5]Crude SO Exports'!CU$290)/1000 -> 193.23102 | H59: =('[5]Crude SO Exports'!DG$290)/1000 -> 50.327964 | I59: =('[5]Crude SO Exports'!DS$290)/1000 -> 71.106698 | J59: =('[5]Crude SO Exports'!EE$290)/1000 -> 193.55618 | K59: =('[5]Crude SO Exports'!EQ$290)/1000 -> 152.40162 | L59: =('[5]Crude SO Exports'!FC$290)/1000 -> 20.240404 | M59: =('[5]Crude SO Exports'!FO$290)/1000 -> 39.180063 | N59: =('[5]Crude SO Exports'!GA$290)/1000 -> 56.77737 | O59: =('[5]Crude SO Exports'!GM$290)/1000 -> 61.563265 | P59: =('[5]Crude SO Exports'!GY$290)/1000 -> 440.93012 | Q59: =('[5]Crude SO Exports'!HK$290)/1000 -> 323.80564 | R59: =('[5]Crude SO Exports'!HW$290)/1000 -> 119.03723 | S59: =('[5]Crude SO Exports'!II$290)/1000 -> 167.16289 | T59: =('[5]Crude SO Exports'!IU$290)/1000 -> 107.27147 | U59: =('[5]Crude SO Exports'!JG$290)/1000 -> 104.19431 | V59: =('[5]Crude SO Exports'!JS$290)/1000 -> 65.887281 | W59: =('[5]Crude SO Exports'!KE$290)/1000 -> 75.652806 | X59: =('[5]Crude SO Exports'!KQ$290)/1000 -> 96.421106 | Y59: =('[5]Crude SO Exports'!LC$290)/1000 -> 197.23549 | Z59: =('[5]Crude SO Exports'!LO$290)/1000 -> 164.35079 | AA59: =('[5]Crude SO Exports'!MA$290)/1000 -> 120.92081 | AB59: =('[5]Crude SO Exports'!MM$290)/1000 -> 193.33601 | AC59: =('[5]Crude SO Exports'!MY$290)/1000 -> 111.51768 | AD59: =('[5]Crude SO Exports'!NK$290)/1000 -> 134.85574 | AE59: =('[5]Crude SO Exports'!NW$290)/1000 -> 44.685918 | AF59: =(SUM(Z59:AD59)/SUM(Z$65:AD$65))*AF$65 -> 0.54353869 | AG59: =(SUM(AA59:AE59)/SUM(AA$65:AE$65))*AG$65 -> 0.85284603 | AH59: =(SUM(AB59:AF59)/SUM(AB$65:AF$65))*AH$65 -> 0.84365038 | AI59: =(SUM(AC59:AG59)/SUM(AC$65:AG$65))*AI$65 -> 0.79395849 | AJ59: =(SUM(AD59:AH59)/SUM(AD$65:AH$65))*AJ$65 -> 0.72740666 | AK59: =(SUM(AE59:AI59)/SUM(AE$65:AI$65))*AK$65 -> 0.37828145 | AL59: =(SUM(AF59:AJ59)/SUM(AF$65:AJ$65))*AL$65 -> 0.065425267 | AM59: =(SUM(AG59:AK59)/SUM(AG$65:AK$65))*AM$65 -> 0.061116413 | ... AU59: =(SUM(AO59:AS59)/SUM(AO$65:AS$65))*AU$65 -> 0.050392384
A60: May | B60: =('[5]Crude SO Exports'!AN$290)/1000 -> 70.50004 | C60: =('[5]Crude SO Exports'!AZ$290)/1000 -> 38.820746 | D60: =('[5]Crude SO Exports'!BL$290)/1000 -> 28.427118 | E60: =('[5]Crude SO Exports'!BX$290)/1000 -> 15.51767 | F60: =('[5]Crude SO Exports'!CJ$290)/1000 -> 90.577101 | G60: =('[5]Crude SO Exports'!CV$290)/1000 -> 37.360024 | H60: =('[5]Crude SO Exports'!DH$290)/1000 -> 19.947151 | I60: =('[5]Crude SO Exports'!DT$290)/1000 -> 23.323537 | J60: =('[5]Crude SO Exports'!EF$290)/1000 -> 61.462772 | K60: =('[5]Crude SO Exports'!ER$290)/1000 -> 49.60796 | L60: =('[5]Crude SO Exports'!FD$290)/1000 -> 21.24424 | M60: =('[5]Crude SO Exports'!FP$290)/1000 -> 47.654388 | N60: =('[5]Crude SO Exports'!GB$290)/1000 -> 27.955076 | O60: =('[5]Crude SO Exports'!GN$290)/1000 -> 65.567945 | P60: =('[5]Crude SO Exports'!GZ$290)/1000 -> 115.64441 | Q60: =('[5]Crude SO Exports'!HL$290)/1000 -> 265.77688 | R60: =('[5]Crude SO Exports'!HX$290)/1000 -> 56.308909 | S60: =('[5]Crude SO Exports'!IJ$290)/1000 -> 66.041707 | T60: =('[5]Crude SO Exports'!IV$290)/1000 -> 178.4031 | U60: =('[5]Crude SO Exports'!JH$290)/1000 -> 47.737865 | V60: =('[5]Crude SO Exports'!JT$290)/1000 -> 20.477407 | W60: =('[5]Crude SO Exports'!KF$290)/1000 -> 30.772765 | X60: =('[5]Crude SO Exports'!KR$290)/1000 -> 78.167718 | Y60: =('[5]Crude SO Exports'!LD$290)/1000 -> 105.68005 | Z60: =('[5]Crude SO Exports'!LP$290)/1000 -> 377.10065 | AA60: =('[5]Crude SO Exports'!MB$290)/1000 -> 177.0537 | AB60: =('[5]Crude SO Exports'!MN$290)/1000 -> 321.80147 | AC60: =('[5]Crude SO Exports'!MZ$290)/1000 -> 53.873595 | AD60: =('[5]Crude SO Exports'!NL$290)/1000 -> 59.476264 | AE60: =('[5]Crude SO Exports'!NX$290)/1000 -> 36.461284 | AF60: =(SUM(Z60:AD60)/SUM(Z$65:AD$65))*AF$65 -> 0.74171033 | AG60: =(SUM(AA60:AE60)/SUM(AA$65:AE$65))*AG$65 -> 0.91392322 | AH60: =(SUM(AB60:AF60)/SUM(AB$65:AF$65))*AH$65 -> 0.82175697 | AI60: =(SUM(AC60:AG60)/SUM(AC$65:AG$65))*AI$65 -> 0.41120185 | AJ60: =(SUM(AD60:AH60)/SUM(AD$65:AH$65))*AJ$65 -> 0.39381128 | AK60: =(SUM(AE60:AI60)/SUM(AE$65:AI$65))*AK$65 -> 0.31193118 | AL60: =(SUM(AF60:AJ60)/SUM(AF$65:AJ$65))*AL$65 -> 0.057093667 | AM60: =(SUM(AG60:AK60)/SUM(AG$65:AK$65))*AM$65 -> 0.048480323 | ... AU60: =(SUM(AO60:AS60)/SUM(AO$65:AS$65))*AU$65 -> 0.035373918
A61: June | B61: =('[5]Crude SO Exports'!AO$290)/1000 -> 3.00037 | C61: =('[5]Crude SO Exports'!BA$290)/1000 -> 108.11256 | D61: =('[5]Crude SO Exports'!BM$290)/1000 -> 5.653254 | E61: =('[5]Crude SO Exports'!BY$290)/1000 -> 27.081059 | F61: =('[5]Crude SO Exports'!CK$290)/1000 -> 129.60022 | G61: =('[5]Crude SO Exports'!CW$290)/1000 -> 100.80239 | H61: =('[5]Crude SO Exports'!DI$290)/1000 -> 58.515137 | I61: =('[5]Crude SO Exports'!DU$290)/1000 -> 78.886836 | J61: =('[5]Crude SO Exports'!EG$290)/1000 -> 283.82042 | K61: =('[5]Crude SO Exports'!ES$290)/1000 -> 51.823037 | L61: =('[5]Crude SO Exports'!FE$290)/1000 -> 7.36896 | M61: =('[5]Crude SO Exports'!FQ$290)/1000 -> 40.356293 | N61: =('[5]Crude SO Exports'!GC$290)/1000 -> 35.26886 | O61: =('[5]Crude SO Exports'!GO$290)/1000 -> 93.240666 | P61: =('[5]Crude SO Exports'!HA$290)/1000 -> 141.69455 | Q61: =('[5]Crude SO Exports'!HM$290)/1000 -> 70.239048 | R61: =('[5]Crude SO Exports'!HY$290)/1000 -> 96.242509 | S61: =('[5]Crude SO Exports'!IK$290)/1000 -> 107.89884 | T61: =('[5]Crude SO Exports'!IW$290)/1000 -> 100.76067 | U61: =('[5]Crude SO Exports'!JI$290)/1000 -> 39.143099 | V61: =('[5]Crude SO Exports'!JU$290)/1000 -> 52.246486 | W61: =('[5]Crude SO Exports'!KG$290)/1000 -> 107.12766 | X61: =('[5]Crude SO Exports'!KS$290)/1000 -> 129.60244 | Y61: =('[5]Crude SO Exports'!LE$290)/1000 -> 105.47445 | Z61: =('[5]Crude SO Exports'!LQ$290)/1000 -> 190.95666 | AA61: =('[5]Crude SO Exports'!MC$290)/1000 -> 73.894405 | AB61: =('[5]Crude SO Exports'!MO$290)/1000 -> 141.27782 | AC61: =('[5]Crude SO Exports'!NA$290)/1000 -> 74.540065 | AD61: =('[5]Crude SO Exports'!NM$290)/1000 -> 56.872837 | AE61: =('[5]Crude SO Exports'!NY$290)/1000 -> 28.045112 | AF61: =(SUM(Z61:AD61)/SUM(Z$65:AD$65))*AF$65 -> 0.40301022 | AG61: =(SUM(AA61:AE61)/SUM(AA$65:AE$65))*AG$65 -> 0.52782651 | AH61: =(SUM(AB61:AF61)/SUM(AB$65:AF$65))*AH$65 -> 0.52389262 | AI61: =(SUM(AC61:AG61)/SUM(AC$65:AG$65))*AI$65 -> 0.43542348 | AJ61: =(SUM(AD61:AH61)/SUM(AD$65:AH$65))*AJ$65 -> 0.3456237 | AK61: =(SUM(AE61:AI61)/SUM(AE$65:AI$65))*AK$65 -> 0.23730043 | AL61: =(SUM(AF61:AJ61)/SUM(AF$65:AJ$65))*AL$65 -> 0.038888782 | AM61: =(SUM(AG61:AK61)/SUM(AG$65:AK$65))*AM$65 -> 0.035180763 | ... AU61: =(SUM(AO61:AS61)/SUM(AO$65:AS$65))*AU$65 -> 0.028357129
A62: July | B62: =('[5]Crude SO Exports'!AP$290)/1000 -> 36.636571 | C62: =('[5]Crude SO Exports'!BB$290)/1000 -> 40.297634 | D62: =('[5]Crude SO Exports'!BN$290)/1000 -> 11.767832 | E62: =('[5]Crude SO Exports'!BZ$290)/1000 -> 99.510775 | F62: =('[5]Crude SO Exports'!CL$290)/1000 -> 108.39825 | G62: =('[5]Crude SO Exports'!CX$290)/1000 -> 75.526211 | H62: =('[5]Crude SO Exports'!DJ$290)/1000 -> 67.986158 | I62: =('[5]Crude SO Exports'!DV$290)/1000 -> 56.888038 | J62: =('[5]Crude SO Exports'!EH$290)/1000 -> 120.93807 | K62: =('[5]Crude SO Exports'!ET$290)/1000 -> 133.21059 | L62: =('[5]Crude SO Exports'!FF$290)/1000 -> 20.494328 | M62: =('[5]Crude SO Exports'!FR$290)/1000 -> 24.799624 | N62: =('[5]Crude SO Exports'!GD$290)/1000 -> 20.832816 | O62: =('[5]Crude SO Exports'!GP$290)/1000 -> 161.76849 | P62: =('[5]Crude SO Exports'!HB$290)/1000 -> 86.783062 | Q62: =('[5]Crude SO Exports'!HN$290)/1000 -> 201.58267 | R62: =('[5]Crude SO Exports'!HZ$290)/1000 -> 162.595 | S62: =('[5]Crude SO Exports'!IL$290)/1000 -> 100.21466 | T62: =('[5]Crude SO Exports'!IX$290)/1000 -> 173.97338 | U62: =('[5]Crude SO Exports'!JJ$290)/1000 -> 49.968284 | V62: =('[5]Crude SO Exports'!JV$290)/1000 -> 181.30312 | W62: =('[5]Crude SO Exports'!KH$290)/1000 -> 37.165326 | X62: =('[5]Crude SO Exports'!KT$290)/1000 -> 235.77316 | Y62: =('[5]Crude SO Exports'!LF$290)/1000 -> 143.35195 | Z62: =('[5]Crude SO Exports'!LR$290)/1000 -> 135.51394 | AA62: =('[5]Crude SO Exports'!MD$290)/1000 -> 150.63523 | AB62: =('[5]Crude SO Exports'!MP$290)/1000 -> 141.81005 | AC62: =('[5]Crude SO Exports'!NB$290)/1000 -> 14.5209 | AD62: =('[5]Crude SO Exports'!NN$290)/1000 -> 100.034 | AE62: =('[5]Crude SO Exports'!NZ$290)/1000 -> 23.263104 | AF62: =(SUM(Z62:AD62)/SUM(Z$65:AD$65))*AF$65 -> 0.40673811 | AG62: =(SUM(AA62:AE62)/SUM(AA$65:AE$65))*AG$65 -> 0.60620939 | AH62: =(SUM(AB62:AF62)/SUM(AB$65:AF$65))*AH$65 -> 0.4871778 | AI62: =(SUM(AC62:AG62)/SUM(AC$65:AG$65))*AI$65 -> 0.37689812 | AJ62: =(SUM(AD62:AH62)/SUM(AD$65:AH$65))*AJ$65 -> 0.49938105 | AK62: =(SUM(AE62:AI62)/SUM(AE$65:AI$65))*AK$65 -> 0.1992888 | AL62: =(SUM(AF62:AJ62)/SUM(AF$65:AJ$65))*AL$65 -> 0.041334845 | AM62: =(SUM(AG62:AK62)/SUM(AG$65:AK$65))*AM$65 -> 0.03686137 | ... AU62: =(SUM(AO62:AS62)/SUM(AO$65:AS$65))*AU$65 -> 0.029400274
A63: August | B63: =('[5]Crude SO Exports'!AQ$290)/1000 -> 157.14854 | C63: =('[5]Crude SO Exports'!BC$290)/1000 -> 37.564862 | D63: =('[5]Crude SO Exports'!BO$290)/1000 -> 15.154049 | E63: =('[5]Crude SO Exports'!CA$290)/1000 -> 153.39493 | F63: =('[5]Crude SO Exports'!CM$290)/1000 -> 228.08683 | G63: =('[5]Crude SO Exports'!CY$290)/1000 -> 54.301537 | H63: =('[5]Crude SO Exports'!DK$290)/1000 -> 25.978047 | I63: =('[5]Crude SO Exports'!DW$290)/1000 -> 76.852782 | J63: =('[5]Crude SO Exports'!EI$290)/1000 -> 64.681394 | K63: =('[5]Crude SO Exports'!EU$290)/1000 -> 73.681607 | L63: =('[5]Crude SO Exports'!FG$290)/1000 -> 25.001286 | M63: =('[5]Crude SO Exports'!FS$290)/1000 -> 87.641085 | N63: =('[5]Crude SO Exports'!GE$290)/1000 -> 31.469697 | O63: =('[5]Crude SO Exports'!GQ$290)/1000 -> 157.44501 | P63: =('[5]Crude SO Exports'!HC$290)/1000 -> 137.29556 | Q63: =('[5]Crude SO Exports'!HO$290)/1000 -> 285.69964 | R63: =('[5]Crude SO Exports'!IA$290)/1000 -> 343.83203 | S63: =('[5]Crude SO Exports'!IM$290)/1000 -> 97.671965 | T63: =('[5]Crude SO Exports'!IY$290)/1000 -> 165.73332 | U63: =('[5]Crude SO Exports'!JK$290)/1000 -> 74.975796 | V63: =('[5]Crude SO Exports'!JW$290)/1000 -> 101.38224 | W63: =('[5]Crude SO Exports'!KI$290)/1000 -> 125.63167 | X63: =('[5]Crude SO Exports'!KU$290)/1000 -> 68.871145 | Y63: =('[5]Crude SO Exports'!LG$290)/1000 -> 128.20516 | Z63: =('[5]Crude SO Exports'!LS$290)/1000 -> 158.46093 | AA63: =('[5]Crude SO Exports'!ME$290)/1000 -> 138.43333 | AB63: =('[5]Crude SO Exports'!MQ$290)/1000 -> 167.68027 | AC63: =('[5]Crude SO Exports'!NC$290)/1000 -> 22.452385 | AD63: =('[5]Crude SO Exports'!NO$290)/1000 -> 35.155998 | AE63: =('[5]Crude SO Exports'!OA$290)/1000 -> 9.910082 | AF63: =(SUM(Z63:AD63)/SUM(Z$65:AD$65))*AF$65 -> 0.39149524 | AG63: =(SUM(AA63:AE63)/SUM(AA$65:AE$65))*AG$65 -> 0.52642015 | AH63: =(SUM(AB63:AF63)/SUM(AB$65:AF$65))*AH$65 -> 0.4098574 | AI63: =(SUM(AC63:AG63)/SUM(AC$65:AG$65))*AI$65 -> 0.18579101 | AJ63: =(SUM(AD63:AH63)/SUM(AD$65:AH$65))*AJ$65 -> 0.18564684 | AK63: =(SUM(AE63:AI63)/SUM(AE$65:AI$65))*AK$65 -> 0.090556608 | AL63: =(SUM(AF63:AJ63)/SUM(AF$65:AJ$65))*AL$65 -> 0.029555831 | AM63: =(SUM(AG63:AK63)/SUM(AG$65:AK$65))*AM$65 -> 0.023763618 | ... AU63: =(SUM(AO63:AS63)/SUM(AO$65:AS$65))*AU$65 -> 0.014453258
A64: September | B64: =('[5]Crude SO Exports'!AR$290)/1000 -> 203.13489 | C64: =('[5]Crude SO Exports'!BD$290)/1000 -> 24.690829 | D64: =('[5]Crude SO Exports'!BP$290)/1000 -> 37.509903 | E64: =('[5]Crude SO Exports'!CB$290)/1000 -> 86.321224 | F64: =('[5]Crude SO Exports'!CN$290)/1000 -> 62.195058 | G64: =('[5]Crude SO Exports'!CZ$290)/1000 -> 163.11107 | H64: =('[5]Crude SO Exports'!DL$290)/1000 -> 44.846878 | I64: =('[5]Crude SO Exports'!DX$290)/1000 -> 47.574324 | J64: =('[5]Crude SO Exports'!EJ$290)/1000 -> 70.280258 | K64: =('[5]Crude SO Exports'!EV$290)/1000 -> 57.88486 | L64: =('[5]Crude SO Exports'!FH$290)/1000 -> 60.316365 | M64: =('[5]Crude SO Exports'!FT$290)/1000 -> 39.757474 | N64: =('[5]Crude SO Exports'!GF$290)/1000 -> 73.576511 | O64: =('[5]Crude SO Exports'!GR$290)/1000 -> 165.77956 | P64: =('[5]Crude SO Exports'!HD$290)/1000 -> 43.037033 | Q64: =('[5]Crude SO Exports'!HP$290)/1000 -> 138.8366 | R64: =('[5]Crude SO Exports'!IB$290)/1000 -> 154.67474 | S64: =('[5]Crude SO Exports'!IN$290)/1000 -> 207.80138 | T64: =('[5]Crude SO Exports'!IZ$290)/1000 -> 45.788068 | U64: =('[5]Crude SO Exports'!JL$290)/1000 -> 52.404817 | V64: =('[5]Crude SO Exports'!JX$290)/1000 -> 56.728384 | W64: =('[5]Crude SO Exports'!KJ$290)/1000 -> 68.047006 | X64: =('[5]Crude SO Exports'!KV$290)/1000 -> 204.74483 | Y64: =('[5]Crude SO Exports'!LH$290)/1000 -> 92.405142 | Z64: =('[5]Crude SO Exports'!LT$290)/1000 -> 91.092435 | AA64: =('[5]Crude SO Exports'!MF$290)/1000 -> 30.730098 | AB64: =('[5]Crude SO Exports'!MR$290)/1000 -> 150.46743 | AC64: =('[5]Crude SO Exports'!ND$290)/1000 -> 18.253041 | AD64: =('[5]Crude SO Exports'!NP$290)/1000 -> 23.01538 | AE64: =('[5]Crude SO Exports'!OB$290)/1000 -> 8.050555 | AF64: =AF65-SUM(AF53:AF63) -> 0.96107022 | AG64: =AG65-SUM(AG53:AG63) -> 0.32478083 | AH64: =AH65-SUM(AH53:AH63) -> 0.34924129 | AI64: =AI65-SUM(AI53:AI63) -> 0.13738193 | AJ64: =AJ65-SUM(AJ53:AJ63) -> 0.13085446 | AK64: =AK65-SUM(AK53:AK63) -> 0.077868329 | AL64: =AL65-SUM(AL53:AL63) -> 0.033106232 | AM64: =AM65-SUM(AM53:AM63) -> 0.017337045 | ... AU64: =AU65-SUM(AU53:AU63) -> 0.011862858
A65: Total | B65: =SUM(B53:B64) -> 1128.0374 | C65: =SUM(C53:C64) -> 1976.7899 | D65: =SUM(D53:D64) -> 658.07379 | E65: =SUM(E53:E64) -> 1483.2199 | F65: =SUM(F53:F64) -> 2177.6025 | G65: =SUM(G53:G64) -> 1829.8071 | H65: =SUM(H53:H64) -> 883.76986 | I65: =SUM(I53:I64) -> 988.1339 | ... AE65: =SUM(AE53:AE64) -> 194.99653 | AF65: =AF12 -> 6.7143554 | AG65: =AG12 -> 10.130494 | AH65: =AH12 -> 9.6792611 | AI65: =AI12 -> 8.4986436 | AJ65: =AJ12 -> 6.7678813 | AK65: =AK12 -> 1.8233904 | AL65: =AL12 -> 0.72690044 | AM65: =AM12 -> 0.62710952 | ... AU65: =AU12 -> 0.42378062
W66: =W65/'[3]Soy Complex'!BD$44 -> 0.76666416 | X66: =X65/'[3]Soy Complex'!BE$44 -> 0.84480532 | Y66: =Y65/'[3]Soy Complex'!BF$44 -> 0.78719665 | Z66: =Z65/'[3]Soy Complex'!BG$44 -> 0.80461117 | AA66: =AA65/'[3]Soy Complex'!BH$44 -> 0.84530692 | AB66: =AB65/'[3]Soy Complex'!BI$44 -> 0.86351336 | AC66: =AC65/'[3]Soy Complex'!BJ$44 -> 0.83790302 | AD66: =AD65/'[3]Soy Complex'!BK$44 -> 0.83216593 | ... AU66: =AU65/'[3]Soy Complex'!CB$44 -> 0.0016951225
A67: CRUDE SOYBEAN OIL PROCESSED (million pounds)
B68: =B$2 -> 93/94 | C68: =C$2 -> 94/95 | D68: =D$2 -> 95/96 | E68: =E$2 -> 96/97 | F68: =F$2 -> 97/98 | G68: =G$2 -> 98/99 | H68: =H$2 -> 99/00 | I68: =I$2 -> 00/01 | ... AU68: =AU$2 -> 38/39
A69: October | X69: ='[4]NASS Crush'!$Z10 -> 1610.904 | Y69: ='[4]NASS Crush'!$Z22 -> 1580.814 | Z69: ='[4]NASS Crush'!$Z34 -> 1644.069 | AA69: ='[4]NASS Crush'!$Z46 -> 1601.041 | AB69: ='[4]NASS Crush'!$Z58 -> 1610.868 | AC69: ='[4]NASS Crush'!$Z70 -> 1692.858 | AD69: ='[4]NASS Crush'!$Z82 -> 1772.253 | AE69: ='[4]NASS Crush'!$Z94 -> 1829.75 | AF69: ='[4]NASS Crush'!$Z106 -> 1922.221 | AG69: ='Soy Refined'!AG22*(1+AVERAGE('[4]NASS Crush'!$AB70,'[4]NASS Crush'!$AB58,'[4]NASS Crush'!$AB46,'[4]NASS Crush'!$AB34,'[4]NASS Crush'!$AB22)) -> 1914.1025 | AH69: ='Soy Refined'!AH22*(1+AVERAGE('[4]NASS Crush'!$AB70,'[4]NASS Crush'!$AB58,'[4]NASS Crush'!$AB46,'[4]NASS Crush'!$AB34,'[4]NASS Crush'!$AB22)) -> 1998.9599 | AI69: ='Soy Refined'!AI22*(1+AVERAGE('[4]NASS Crush'!$AB70,'[4]NASS Crush'!$AB58,'[4]NASS Crush'!$AB46,'[4]NASS Crush'!$AB34,'[4]NASS Crush'!$AB22)) -> 2197.5318 | AJ69: ='Soy Refined'!AJ22*(1+AVERAGE('[4]NASS Crush'!$AB70,'[4]NASS Crush'!$AB58,'[4]NASS Crush'!$AB46,'[4]NASS Crush'!$AB34,'[4]NASS Crush'!$AB22)) -> 2285.0719 | AK69: ='Soy Refined'!AK22*(1+AVERAGE('[4]NASS Crush'!$AB70,'[4]NASS Crush'!$AB58,'[4]NASS Crush'!$AB46,'[4]NASS Crush'!$AB34,'[4]NASS Crush'!$AB22)) -> 2501.4937 | AL69: ='Soy Refined'!AL22*(1+AVERAGE('[4]NASS Crush'!$AB70,'[4]NASS Crush'!$AB58,'[4]NASS Crush'!$AB46,'[4]NASS Crush'!$AB34,'[4]NASS Crush'!$AB22)) -> 2778.7958 | AM69: ='Soy Refined'!AM22*(1+AVERAGE('[4]NASS Crush'!$AB70,'[4]NASS Crush'!$AB58,'[4]NASS Crush'!$AB46,'[4]NASS Crush'!$AB34,'[4]NASS Crush'!$AB22)) -> 2936.8662 | AN69: ='Soy Refined'!AN22*(1+AVERAGE('[4]NASS Crush'!$AB70,'[4]NASS Crush'!$AB58,'[4]NASS Crush'!$AB46,'[4]NASS Crush'!$AB34,'[4]NASS Crush'!$AB22)) -> 2834.2722 | ... AU69: ='Soy Refined'!AU22*(1+AVERAGE('[4]NASS Crush'!$AB70,'[4]NASS Crush'!$AB58,'[4]NASS Crush'!$AB46,'[4]NASS Crush'!$AB34,'[4]NASS Crush'!$AB22)) -> 5138.1817
A70: November | X70: ='[4]NASS Crush'!$Z11 -> 1461.965 | Y70: ='[4]NASS Crush'!$Z23 -> 1471.587 | Z70: ='[4]NASS Crush'!$Z35 -> 1482.83 | AA70: ='[4]NASS Crush'!$Z47 -> 1496.018 | AB70: ='[4]NASS Crush'!$Z59 -> 1397.17 | AC70: ='[4]NASS Crush'!$Z71 -> 1617.081 | AD70: ='[4]NASS Crush'!$Z83 -> 1701.596 | AE70: ='[4]NASS Crush'!$Z95 -> 1674.784 | AF70: ='[4]NASS Crush'!$Z107 -> 1737.002 | AG70: ='Soy Refined'!AG23*(1+AVERAGE('[4]NASS Crush'!$AB71,'[4]NASS Crush'!$AB59,'[4]NASS Crush'!$AB47,'[4]NASS Crush'!$AB35,'[4]NASS Crush'!$AB23)) -> 1880.9024 | AH70: ='Soy Refined'!AH23*(1+AVERAGE('[4]NASS Crush'!$AB71,'[4]NASS Crush'!$AB59,'[4]NASS Crush'!$AB47,'[4]NASS Crush'!$AB35,'[4]NASS Crush'!$AB23)) -> 2076.9601 | AI70: ='Soy Refined'!AI23*(1+AVERAGE('[4]NASS Crush'!$AB71,'[4]NASS Crush'!$AB59,'[4]NASS Crush'!$AB47,'[4]NASS Crush'!$AB35,'[4]NASS Crush'!$AB23)) -> 2148.7293 | AJ70: ='Soy Refined'!AJ23*(1+AVERAGE('[4]NASS Crush'!$AB71,'[4]NASS Crush'!$AB59,'[4]NASS Crush'!$AB47,'[4]NASS Crush'!$AB35,'[4]NASS Crush'!$AB23)) -> 2195.436 | AK70: ='Soy Refined'!AK23*(1+AVERAGE('[4]NASS Crush'!$AB71,'[4]NASS Crush'!$AB59,'[4]NASS Crush'!$AB47,'[4]NASS Crush'!$AB35,'[4]NASS Crush'!$AB23)) -> 2357.2779 | AL70: ='Soy Refined'!AL23*(1+AVERAGE('[4]NASS Crush'!$AB71,'[4]NASS Crush'!$AB59,'[4]NASS Crush'!$AB47,'[4]NASS Crush'!$AB35,'[4]NASS Crush'!$AB23)) -> 2488.2471 | AM70: ='Soy Refined'!AM23*(1+AVERAGE('[4]NASS Crush'!$AB71,'[4]NASS Crush'!$AB59,'[4]NASS Crush'!$AB47,'[4]NASS Crush'!$AB35,'[4]NASS Crush'!$AB23)) -> 2634.599 | AN70: ='Soy Refined'!AN23*(1+AVERAGE('[4]NASS Crush'!$AB71,'[4]NASS Crush'!$AB59,'[4]NASS Crush'!$AB47,'[4]NASS Crush'!$AB35,'[4]NASS Crush'!$AB23)) -> 2682.762 | ... AU70: ='Soy Refined'!AU23*(1+AVERAGE('[4]NASS Crush'!$AB71,'[4]NASS Crush'!$AB59,'[4]NASS Crush'!$AB47,'[4]NASS Crush'!$AB35,'[4]NASS Crush'!$AB23)) -> 4083.0153
A71: December | X71: ='[4]NASS Crush'!$Z12 -> 1445.949 | Y71: ='[4]NASS Crush'!$Z24 -> 1440.556 | Z71: ='[4]NASS Crush'!$Z36 -> 1405.035 | AA71: ='[4]NASS Crush'!$Z48 -> 1479.059 | AB71: ='[4]NASS Crush'!$Z60 -> 1389.872 | AC71: ='[4]NASS Crush'!$Z72 -> 1614.33 | AD71: ='[4]NASS Crush'!$Z84 -> 1673.573 | AE71: ='[4]NASS Crush'!$Z96 -> 1615.612 | AF71: ='[4]NASS Crush'!$Z108 -> 1755.288 | AG71: ='Soy Refined'!AG24*(1+AVERAGE('[4]NASS Crush'!$AB72,'[4]NASS Crush'!$AB60,'[4]NASS Crush'!$AB48,'[4]NASS Crush'!$AB36,'[4]NASS Crush'!$AB24)) -> 2033.3947 | AH71: ='Soy Refined'!AH24*(1+AVERAGE('[4]NASS Crush'!$AB72,'[4]NASS Crush'!$AB60,'[4]NASS Crush'!$AB48,'[4]NASS Crush'!$AB36,'[4]NASS Crush'!$AB24)) -> 2046.4899 | AI71: ='Soy Refined'!AI24*(1+AVERAGE('[4]NASS Crush'!$AB72,'[4]NASS Crush'!$AB60,'[4]NASS Crush'!$AB48,'[4]NASS Crush'!$AB36,'[4]NASS Crush'!$AB24)) -> 2143.1131 | AJ71: ='Soy Refined'!AJ24*(1+AVERAGE('[4]NASS Crush'!$AB72,'[4]NASS Crush'!$AB60,'[4]NASS Crush'!$AB48,'[4]NASS Crush'!$AB36,'[4]NASS Crush'!$AB24)) -> 2400.2878 | AK71: ='Soy Refined'!AK24*(1+AVERAGE('[4]NASS Crush'!$AB72,'[4]NASS Crush'!$AB60,'[4]NASS Crush'!$AB48,'[4]NASS Crush'!$AB36,'[4]NASS Crush'!$AB24)) -> 2409.1899 | AL71: ='Soy Refined'!AL24*(1+AVERAGE('[4]NASS Crush'!$AB72,'[4]NASS Crush'!$AB60,'[4]NASS Crush'!$AB48,'[4]NASS Crush'!$AB36,'[4]NASS Crush'!$AB24)) -> 2630.1832 | AM71: ='Soy Refined'!AM24*(1+AVERAGE('[4]NASS Crush'!$AB72,'[4]NASS Crush'!$AB60,'[4]NASS Crush'!$AB48,'[4]NASS Crush'!$AB36,'[4]NASS Crush'!$AB24)) -> 2665.9412 | AN71: ='Soy Refined'!AN24*(1+AVERAGE('[4]NASS Crush'!$AB72,'[4]NASS Crush'!$AB60,'[4]NASS Crush'!$AB48,'[4]NASS Crush'!$AB36,'[4]NASS Crush'!$AB24)) -> 2953.5073 | ... AU71: ='Soy Refined'!AU24*(1+AVERAGE('[4]NASS Crush'!$AB72,'[4]NASS Crush'!$AB60,'[4]NASS Crush'!$AB48,'[4]NASS Crush'!$AB36,'[4]NASS Crush'!$AB24)) -> 5537.0157
A72: January | X72: ='[4]NASS Crush'!$Z13 -> 1277.782 | Y72: ='[4]NASS Crush'!$Z25 -> 1370.226 | Z72: ='[4]NASS Crush'!$Z37 -> 1291.424 | AA72: ='[4]NASS Crush'!$Z49 -> 1425.415 | AB72: ='[4]NASS Crush'!$Z61 -> 1442.642 | AC72: ='[4]NASS Crush'!$Z73 -> 1620.678 | AD72: ='[4]NASS Crush'!$Z85 -> 1628.044 | AE72: ='[4]NASS Crush'!$Z97 -> 1753.308 | AF72: ='[4]NASS Crush'!$Z109 -> 1618.565 | AG72: ='Soy Refined'!AG25*(1+AVERAGE('[4]NASS Crush'!$AB73,'[4]NASS Crush'!$AB61,'[4]NASS Crush'!$AB49,'[4]NASS Crush'!$AB37,'[4]NASS Crush'!$AB25)) -> 1816.941 | AH72: ='Soy Refined'!AH25*(1+AVERAGE('[4]NASS Crush'!$AB73,'[4]NASS Crush'!$AB61,'[4]NASS Crush'!$AB49,'[4]NASS Crush'!$AB37,'[4]NASS Crush'!$AB25)) -> 1998.5224 | AI72: ='Soy Refined'!AI25*(1+AVERAGE('[4]NASS Crush'!$AB73,'[4]NASS Crush'!$AB61,'[4]NASS Crush'!$AB49,'[4]NASS Crush'!$AB37,'[4]NASS Crush'!$AB25)) -> 2034.0568 | AJ72: ='Soy Refined'!AJ25*(1+AVERAGE('[4]NASS Crush'!$AB73,'[4]NASS Crush'!$AB61,'[4]NASS Crush'!$AB49,'[4]NASS Crush'!$AB37,'[4]NASS Crush'!$AB25)) -> 2132.1473 | AK72: ='Soy Refined'!AK25*(1+AVERAGE('[4]NASS Crush'!$AB73,'[4]NASS Crush'!$AB61,'[4]NASS Crush'!$AB49,'[4]NASS Crush'!$AB37,'[4]NASS Crush'!$AB25)) -> 2201.7339 | AL72: ='Soy Refined'!AL25*(1+AVERAGE('[4]NASS Crush'!$AB73,'[4]NASS Crush'!$AB61,'[4]NASS Crush'!$AB49,'[4]NASS Crush'!$AB37,'[4]NASS Crush'!$AB25)) -> 2388.0701 | AM72: ='Soy Refined'!AM25*(1+AVERAGE('[4]NASS Crush'!$AB73,'[4]NASS Crush'!$AB61,'[4]NASS Crush'!$AB49,'[4]NASS Crush'!$AB37,'[4]NASS Crush'!$AB25)) -> 2378.9961 | AN72: ='Soy Refined'!AN25*(1+AVERAGE('[4]NASS Crush'!$AB73,'[4]NASS Crush'!$AB61,'[4]NASS Crush'!$AB49,'[4]NASS Crush'!$AB37,'[4]NASS Crush'!$AB25)) -> 2399.392 | ... AU72: ='Soy Refined'!AU25*(1+AVERAGE('[4]NASS Crush'!$AB73,'[4]NASS Crush'!$AB61,'[4]NASS Crush'!$AB49,'[4]NASS Crush'!$AB37,'[4]NASS Crush'!$AB25)) -> 2954.5436
A73: February | X73: ='[4]NASS Crush'!$Z14 -> 1344.388 | Y73: ='[4]NASS Crush'!$Z26 -> 1301.503 | Z73: ='[4]NASS Crush'!$Z38 -> 1288.769 | AA73: ='[4]NASS Crush'!$Z50 -> 1317.633 | AB73: ='[4]NASS Crush'!$Z62 -> 1469.241 | AC73: ='[4]NASS Crush'!$Z74 -> 1473.714 | AD73: ='[4]NASS Crush'!$Z86 -> 1574.843 | AE73: ='[4]NASS Crush'!$Z98 -> 1696.242 | AF73: ='[4]NASS Crush'!$Z110 -> 1652.057 | AG73: ='Soy Refined'!AG26*(1+AVERAGE('[4]NASS Crush'!$AB74,'[4]NASS Crush'!$AB62,'[4]NASS Crush'!$AB50,'[4]NASS Crush'!$AB38,'[4]NASS Crush'!$AB26)) -> 1930.7085 | AH73: ='Soy Refined'!AH26*(1+AVERAGE('[4]NASS Crush'!$AB74,'[4]NASS Crush'!$AB62,'[4]NASS Crush'!$AB50,'[4]NASS Crush'!$AB38,'[4]NASS Crush'!$AB26)) -> 1917.4423 | AI73: ='Soy Refined'!AI26*(1+AVERAGE('[4]NASS Crush'!$AB74,'[4]NASS Crush'!$AB62,'[4]NASS Crush'!$AB50,'[4]NASS Crush'!$AB38,'[4]NASS Crush'!$AB26)) -> 1973.8639 | AJ73: ='Soy Refined'!AJ26*(1+AVERAGE('[4]NASS Crush'!$AB74,'[4]NASS Crush'!$AB62,'[4]NASS Crush'!$AB50,'[4]NASS Crush'!$AB38,'[4]NASS Crush'!$AB26)) -> 2091.3825 | AK73: ='Soy Refined'!AK26*(1+AVERAGE('[4]NASS Crush'!$AB74,'[4]NASS Crush'!$AB62,'[4]NASS Crush'!$AB50,'[4]NASS Crush'!$AB38,'[4]NASS Crush'!$AB26)) -> 2227.0895 | AL73: ='Soy Refined'!AL26*(1+AVERAGE('[4]NASS Crush'!$AB74,'[4]NASS Crush'!$AB62,'[4]NASS Crush'!$AB50,'[4]NASS Crush'!$AB38,'[4]NASS Crush'!$AB26)) -> 2391.8573 | AM73: ='Soy Refined'!AM26*(1+AVERAGE('[4]NASS Crush'!$AB74,'[4]NASS Crush'!$AB62,'[4]NASS Crush'!$AB50,'[4]NASS Crush'!$AB38,'[4]NASS Crush'!$AB26)) -> 2424.009 | AN73: ='Soy Refined'!AN26*(1+AVERAGE('[4]NASS Crush'!$AB74,'[4]NASS Crush'!$AB62,'[4]NASS Crush'!$AB50,'[4]NASS Crush'!$AB38,'[4]NASS Crush'!$AB26)) -> 2381.6049 | ... AU73: ='Soy Refined'!AU26*(1+AVERAGE('[4]NASS Crush'!$AB74,'[4]NASS Crush'!$AB62,'[4]NASS Crush'!$AB50,'[4]NASS Crush'!$AB38,'[4]NASS Crush'!$AB26)) -> 3357.2022
A74: March | X74: ='[4]NASS Crush'!$Z15 -> 1438.379 | Y74: ='[4]NASS Crush'!$Z27 -> 1442.235 | Z74: ='[4]NASS Crush'!$Z39 -> 1519.782 | AA74: ='[4]NASS Crush'!$Z51 -> 1443.099 | AB74: ='[4]NASS Crush'!$Z63 -> 1634.117 | AC74: ='[4]NASS Crush'!$Z75 -> 1799.682 | AD74: ='[4]NASS Crush'!$Z87 -> 1831.109 | AE74: ='[4]NASS Crush'!$Z99 -> 1853.676 | AF74: ='[4]NASS Crush'!$Z111 -> 1828.513 | AG74: ='Soy Refined'!AG27*(1+AVERAGE('[4]NASS Crush'!$AB75,'[4]NASS Crush'!$AB63,'[4]NASS Crush'!$AB51,'[4]NASS Crush'!$AB39,'[4]NASS Crush'!$AB27)) -> 2228.3383 | AH74: ='Soy Refined'!AH27*(1+AVERAGE('[4]NASS Crush'!$AB75,'[4]NASS Crush'!$AB63,'[4]NASS Crush'!$AB51,'[4]NASS Crush'!$AB39,'[4]NASS Crush'!$AB27)) -> 2085.0039 | AI74: ='Soy Refined'!AI27*(1+AVERAGE('[4]NASS Crush'!$AB75,'[4]NASS Crush'!$AB63,'[4]NASS Crush'!$AB51,'[4]NASS Crush'!$AB39,'[4]NASS Crush'!$AB27)) -> 2081.6085 | AJ74: ='Soy Refined'!AJ27*(1+AVERAGE('[4]NASS Crush'!$AB75,'[4]NASS Crush'!$AB63,'[4]NASS Crush'!$AB51,'[4]NASS Crush'!$AB39,'[4]NASS Crush'!$AB27)) -> 2329.5495 | AK74: ='Soy Refined'!AK27*(1+AVERAGE('[4]NASS Crush'!$AB75,'[4]NASS Crush'!$AB63,'[4]NASS Crush'!$AB51,'[4]NASS Crush'!$AB39,'[4]NASS Crush'!$AB27)) -> 2403.6371 | AL74: ='Soy Refined'!AL27*(1+AVERAGE('[4]NASS Crush'!$AB75,'[4]NASS Crush'!$AB63,'[4]NASS Crush'!$AB51,'[4]NASS Crush'!$AB39,'[4]NASS Crush'!$AB27)) -> 2590.9423 | AM74: ='Soy Refined'!AM27*(1+AVERAGE('[4]NASS Crush'!$AB75,'[4]NASS Crush'!$AB63,'[4]NASS Crush'!$AB51,'[4]NASS Crush'!$AB39,'[4]NASS Crush'!$AB27)) -> 2557.9254 | AN74: ='Soy Refined'!AN27*(1+AVERAGE('[4]NASS Crush'!$AB75,'[4]NASS Crush'!$AB63,'[4]NASS Crush'!$AB51,'[4]NASS Crush'!$AB39,'[4]NASS Crush'!$AB27)) -> 2572.2307 | ... AU74: ='Soy Refined'!AU27*(1+AVERAGE('[4]NASS Crush'!$AB75,'[4]NASS Crush'!$AB63,'[4]NASS Crush'!$AB51,'[4]NASS Crush'!$AB39,'[4]NASS Crush'!$AB27)) -> 3541.6824 | AW74: 26134421
A75: April | X75: ='[4]NASS Crush'!$Z16 -> 1385.229 | Y75: ='[4]NASS Crush'!$Z28 -> 1334.313 | Z75: ='[4]NASS Crush'!$Z40 -> 1477.749 | AA75: ='[4]NASS Crush'!$Z52 -> 1496.995 | AB75: ='[4]NASS Crush'!$Z64 -> 1288.755 | AC75: ='[4]NASS Crush'!$Z76 -> 1678.886 | AD75: ='[4]NASS Crush'!$Z88 -> 1738.58 | AE75: ='[4]NASS Crush'!$Z100 -> 1716.391 | AF75: ='[4]NASS Crush'!$Z112 -> 1762.84 | AG75: ='Soy Refined'!AG28*(1+AVERAGE('[4]NASS Crush'!$AB76,'[4]NASS Crush'!$AB64,'[4]NASS Crush'!$AB52,'[4]NASS Crush'!$AB40,'[4]NASS Crush'!$AB28)) -> 1872.7328 | AH75: ='Soy Refined'!AH28*(1+AVERAGE('[4]NASS Crush'!$AB76,'[4]NASS Crush'!$AB64,'[4]NASS Crush'!$AB52,'[4]NASS Crush'!$AB40,'[4]NASS Crush'!$AB28)) -> 1841.1888 | AI75: ='Soy Refined'!AI28*(1+AVERAGE('[4]NASS Crush'!$AB76,'[4]NASS Crush'!$AB64,'[4]NASS Crush'!$AB52,'[4]NASS Crush'!$AB40,'[4]NASS Crush'!$AB28)) -> 2043.1177 | AJ75: ='Soy Refined'!AJ28*(1+AVERAGE('[4]NASS Crush'!$AB76,'[4]NASS Crush'!$AB64,'[4]NASS Crush'!$AB52,'[4]NASS Crush'!$AB40,'[4]NASS Crush'!$AB28)) -> 2258.175 | AK75: ='Soy Refined'!AK28*(1+AVERAGE('[4]NASS Crush'!$AB76,'[4]NASS Crush'!$AB64,'[4]NASS Crush'!$AB52,'[4]NASS Crush'!$AB40,'[4]NASS Crush'!$AB28)) -> 2388.1258 | AL75: ='Soy Refined'!AL28*(1+AVERAGE('[4]NASS Crush'!$AB76,'[4]NASS Crush'!$AB64,'[4]NASS Crush'!$AB52,'[4]NASS Crush'!$AB40,'[4]NASS Crush'!$AB28)) -> 2589.6614 | AM75: ='Soy Refined'!AM28*(1+AVERAGE('[4]NASS Crush'!$AB76,'[4]NASS Crush'!$AB64,'[4]NASS Crush'!$AB52,'[4]NASS Crush'!$AB40,'[4]NASS Crush'!$AB28)) -> 2656.6568 | AN75: ='Soy Refined'!AN28*(1+AVERAGE('[4]NASS Crush'!$AB76,'[4]NASS Crush'!$AB64,'[4]NASS Crush'!$AB52,'[4]NASS Crush'!$AB40,'[4]NASS Crush'!$AB28)) -> 2668.4878 | ... AU75: ='Soy Refined'!AU28*(1+AVERAGE('[4]NASS Crush'!$AB76,'[4]NASS Crush'!$AB64,'[4]NASS Crush'!$AB52,'[4]NASS Crush'!$AB40,'[4]NASS Crush'!$AB28)) -> 4585.7455
A76: May | W76: ='[4]NASS Crush'!$Z5 -> 1439.683 | X76: ='[4]NASS Crush'!$Z17 -> 1474.278 | Y76: ='[4]NASS Crush'!$Z29 -> 1483.689 | Z76: ='[4]NASS Crush'!$Z41 -> 1518.13 | AA76: ='[4]NASS Crush'!$Z53 -> 1531.841 | AB76: ='[4]NASS Crush'!$Z65 -> 1570.271 | AC76: ='[4]NASS Crush'!$Z77 -> 1752.28 | AD76: ='[4]NASS Crush'!$Z89 -> 1795.117 | AE76: ='[4]NASS Crush'!$Z101 -> 1887.942 | AF76: ='[4]NASS Crush'!$Z113 -> 1816.618 | AG76: ='Soy Refined'!AG29*(1+AVERAGE('[4]NASS Crush'!$AB77,'[4]NASS Crush'!$AB65,'[4]NASS Crush'!$AB53,'[4]NASS Crush'!$AB41,'[4]NASS Crush'!$AB29)) -> 2160.2939 | AH76: ='Soy Refined'!AH29*(1+AVERAGE('[4]NASS Crush'!$AB77,'[4]NASS Crush'!$AB65,'[4]NASS Crush'!$AB53,'[4]NASS Crush'!$AB41,'[4]NASS Crush'!$AB29)) -> 2222.4407 | AI76: ='Soy Refined'!AI29*(1+AVERAGE('[4]NASS Crush'!$AB77,'[4]NASS Crush'!$AB65,'[4]NASS Crush'!$AB53,'[4]NASS Crush'!$AB41,'[4]NASS Crush'!$AB29)) -> 2267.8305 | AJ76: ='Soy Refined'!AJ29*(1+AVERAGE('[4]NASS Crush'!$AB77,'[4]NASS Crush'!$AB65,'[4]NASS Crush'!$AB53,'[4]NASS Crush'!$AB41,'[4]NASS Crush'!$AB29)) -> 2426.0464 | AK76: ='Soy Refined'!AK29*(1+AVERAGE('[4]NASS Crush'!$AB77,'[4]NASS Crush'!$AB65,'[4]NASS Crush'!$AB53,'[4]NASS Crush'!$AB41,'[4]NASS Crush'!$AB29)) -> 2600.9247 | AL76: ='Soy Refined'!AL29*(1+AVERAGE('[4]NASS Crush'!$AB77,'[4]NASS Crush'!$AB65,'[4]NASS Crush'!$AB53,'[4]NASS Crush'!$AB41,'[4]NASS Crush'!$AB29)) -> 2842.55 | AM76: ='Soy Refined'!AM29*(1+AVERAGE('[4]NASS Crush'!$AB77,'[4]NASS Crush'!$AB65,'[4]NASS Crush'!$AB53,'[4]NASS Crush'!$AB41,'[4]NASS Crush'!$AB29)) -> 2874.1885 | AN76: ='Soy Refined'!AN29*(1+AVERAGE('[4]NASS Crush'!$AB77,'[4]NASS Crush'!$AB65,'[4]NASS Crush'!$AB53,'[4]NASS Crush'!$AB41,'[4]NASS Crush'!$AB29)) -> 2934.1733 | ... AU76: ='Soy Refined'!AU29*(1+AVERAGE('[4]NASS Crush'!$AB77,'[4]NASS Crush'!$AB65,'[4]NASS Crush'!$AB53,'[4]NASS Crush'!$AB41,'[4]NASS Crush'!$AB29)) -> 5008.7511
A77: June | W77: ='[4]NASS Crush'!$Z6 -> 1499.818 | X77: ='[4]NASS Crush'!$Z18 -> 1407.282 | Y77: ='[4]NASS Crush'!$Z30 -> 1399.831 | Z77: ='[4]NASS Crush'!$Z42 -> 1466.7 | AA77: ='[4]NASS Crush'!$Z54 -> 1438.233 | AB77: ='[4]NASS Crush'!$Z66 -> 1602.012 | AC77: ='[4]NASS Crush'!$Z78 -> 1639.231 | AD77: ='[4]NASS Crush'!$Z90 -> 1678.171 | AE77: ='[4]NASS Crush'!$Z102 -> 1761.023 | AF77: ='[4]NASS Crush'!$Z114 -> 1751.078 | AG77: ='Soy Refined'!AG30*(1+AVERAGE('[4]NASS Crush'!$AB78,'[4]NASS Crush'!$AB66,'[4]NASS Crush'!$AB54,'[4]NASS Crush'!$AB42,'[4]NASS Crush'!$AB30)) -> 1987.5883 | AH77: ='Soy Refined'!AH30*(1+AVERAGE('[4]NASS Crush'!$AB78,'[4]NASS Crush'!$AB66,'[4]NASS Crush'!$AB54,'[4]NASS Crush'!$AB42,'[4]NASS Crush'!$AB30)) -> 2262.1579 | AI77: ='Soy Refined'!AI30*(1+AVERAGE('[4]NASS Crush'!$AB78,'[4]NASS Crush'!$AB66,'[4]NASS Crush'!$AB54,'[4]NASS Crush'!$AB42,'[4]NASS Crush'!$AB30)) -> 2175.0095 | AJ77: ='Soy Refined'!AJ30*(1+AVERAGE('[4]NASS Crush'!$AB78,'[4]NASS Crush'!$AB66,'[4]NASS Crush'!$AB54,'[4]NASS Crush'!$AB42,'[4]NASS Crush'!$AB30)) -> 2349.648 | AK77: ='Soy Refined'!AK30*(1+AVERAGE('[4]NASS Crush'!$AB78,'[4]NASS Crush'!$AB66,'[4]NASS Crush'!$AB54,'[4]NASS Crush'!$AB42,'[4]NASS Crush'!$AB30)) -> 2505.2193 | AL77: ='Soy Refined'!AL30*(1+AVERAGE('[4]NASS Crush'!$AB78,'[4]NASS Crush'!$AB66,'[4]NASS Crush'!$AB54,'[4]NASS Crush'!$AB42,'[4]NASS Crush'!$AB30)) -> 2758.8447 | AM77: ='Soy Refined'!AM30*(1+AVERAGE('[4]NASS Crush'!$AB78,'[4]NASS Crush'!$AB66,'[4]NASS Crush'!$AB54,'[4]NASS Crush'!$AB42,'[4]NASS Crush'!$AB30)) -> 2787.0352 | AN77: ='Soy Refined'!AN30*(1+AVERAGE('[4]NASS Crush'!$AB78,'[4]NASS Crush'!$AB66,'[4]NASS Crush'!$AB54,'[4]NASS Crush'!$AB42,'[4]NASS Crush'!$AB30)) -> 2847.6074 | ... AU77: ='Soy Refined'!AU30*(1+AVERAGE('[4]NASS Crush'!$AB78,'[4]NASS Crush'!$AB66,'[4]NASS Crush'!$AB54,'[4]NASS Crush'!$AB42,'[4]NASS Crush'!$AB30)) -> 4928.5052
A78: July | W78: ='[4]NASS Crush'!$Z7 -> 1462.35 | X78: ='[4]NASS Crush'!$Z19 -> 1469.747 | Y78: ='[4]NASS Crush'!$Z31 -> 1543.943 | Z78: ='[4]NASS Crush'!$Z43 -> 1470.493 | AA78: ='[4]NASS Crush'!$Z55 -> 1550.144 | AB78: ='[4]NASS Crush'!$Z67 -> 1712.925 | AC78: ='[4]NASS Crush'!$Z79 -> 1615.578 | AD78: ='[4]NASS Crush'!$Z91 -> 1724.576 | AE78: ='[4]NASS Crush'!$Z103 -> 1791.151 | AF78: ='[4]NASS Crush'!$Z115 -> 1885.919 | AG78: ='Soy Refined'!AG31*(1+AVERAGE('[4]NASS Crush'!$AB79,'[4]NASS Crush'!$AB67,'[4]NASS Crush'!$AB55,'[4]NASS Crush'!$AB43,'[4]NASS Crush'!$AB31)) -> 1986.7382 | AH78: ='Soy Refined'!AH31*(1+AVERAGE('[4]NASS Crush'!$AB79,'[4]NASS Crush'!$AB67,'[4]NASS Crush'!$AB55,'[4]NASS Crush'!$AB43,'[4]NASS Crush'!$AB31)) -> 2320.3611 | AI78: ='Soy Refined'!AI31*(1+AVERAGE('[4]NASS Crush'!$AB79,'[4]NASS Crush'!$AB67,'[4]NASS Crush'!$AB55,'[4]NASS Crush'!$AB43,'[4]NASS Crush'!$AB31)) -> 2230.2965 | AJ78: ='Soy Refined'!AJ31*(1+AVERAGE('[4]NASS Crush'!$AB79,'[4]NASS Crush'!$AB67,'[4]NASS Crush'!$AB55,'[4]NASS Crush'!$AB43,'[4]NASS Crush'!$AB31)) -> 2352.0905 | AK78: ='Soy Refined'!AK31*(1+AVERAGE('[4]NASS Crush'!$AB79,'[4]NASS Crush'!$AB67,'[4]NASS Crush'!$AB55,'[4]NASS Crush'!$AB43,'[4]NASS Crush'!$AB31)) -> 2636.8799 | AL78: ='Soy Refined'!AL31*(1+AVERAGE('[4]NASS Crush'!$AB79,'[4]NASS Crush'!$AB67,'[4]NASS Crush'!$AB55,'[4]NASS Crush'!$AB43,'[4]NASS Crush'!$AB31)) -> 2934.6371 | AM78: ='Soy Refined'!AM31*(1+AVERAGE('[4]NASS Crush'!$AB79,'[4]NASS Crush'!$AB67,'[4]NASS Crush'!$AB55,'[4]NASS Crush'!$AB43,'[4]NASS Crush'!$AB31)) -> 3002.7026 | AN78: ='Soy Refined'!AN31*(1+AVERAGE('[4]NASS Crush'!$AB79,'[4]NASS Crush'!$AB67,'[4]NASS Crush'!$AB55,'[4]NASS Crush'!$AB43,'[4]NASS Crush'!$AB31)) -> 3092.8514 | ... AU78: ='Soy Refined'!AU31*(1+AVERAGE('[4]NASS Crush'!$AB79,'[4]NASS Crush'!$AB67,'[4]NASS Crush'!$AB55,'[4]NASS Crush'!$AB43,'[4]NASS Crush'!$AB31)) -> 6124.7406
A79: August | W79: ='[4]NASS Crush'!$Z8 -> 1437.891 | X79: ='[4]NASS Crush'!$Z20 -> 1455.355 | Y79: ='[4]NASS Crush'!$Z32 -> 1550.365 | Z79: ='[4]NASS Crush'!$Z44 -> 1481.276 | AA79: ='[4]NASS Crush'!$Z56 -> 1559.724 | AB79: ='[4]NASS Crush'!$Z68 -> 1682.55 | AC79: ='[4]NASS Crush'!$Z80 -> 1670.68 | AD79: ='[4]NASS Crush'!$Z92 -> 1782.045 | AE79: ='[4]NASS Crush'!$Z104 -> 1740.71 | AF79: ='[4]NASS Crush'!$Z116 -> 1713.006 | AG79: ='Soy Refined'!AG32*(1+AVERAGE('[4]NASS Crush'!$AB80,'[4]NASS Crush'!$AB68,'[4]NASS Crush'!$AB56,'[4]NASS Crush'!$AB44,'[4]NASS Crush'!$AB32)) -> 2160.5494 | AH79: ='Soy Refined'!AH32*(1+AVERAGE('[4]NASS Crush'!$AB80,'[4]NASS Crush'!$AB68,'[4]NASS Crush'!$AB56,'[4]NASS Crush'!$AB44,'[4]NASS Crush'!$AB32)) -> 2274.7249 | AI79: ='Soy Refined'!AI32*(1+AVERAGE('[4]NASS Crush'!$AB80,'[4]NASS Crush'!$AB68,'[4]NASS Crush'!$AB56,'[4]NASS Crush'!$AB44,'[4]NASS Crush'!$AB32)) -> 2352.2523 | AJ79: ='Soy Refined'!AJ32*(1+AVERAGE('[4]NASS Crush'!$AB80,'[4]NASS Crush'!$AB68,'[4]NASS Crush'!$AB56,'[4]NASS Crush'!$AB44,'[4]NASS Crush'!$AB32)) -> 2491.3189 | AK79: ='Soy Refined'!AK32*(1+AVERAGE('[4]NASS Crush'!$AB80,'[4]NASS Crush'!$AB68,'[4]NASS Crush'!$AB56,'[4]NASS Crush'!$AB44,'[4]NASS Crush'!$AB32)) -> 2689.8847 | AL79: ='Soy Refined'!AL32*(1+AVERAGE('[4]NASS Crush'!$AB80,'[4]NASS Crush'!$AB68,'[4]NASS Crush'!$AB56,'[4]NASS Crush'!$AB44,'[4]NASS Crush'!$AB32)) -> 2955.0514 | AM79: ='Soy Refined'!AM32*(1+AVERAGE('[4]NASS Crush'!$AB80,'[4]NASS Crush'!$AB68,'[4]NASS Crush'!$AB56,'[4]NASS Crush'!$AB44,'[4]NASS Crush'!$AB32)) -> 2994.2195 | AN79: ='Soy Refined'!AN32*(1+AVERAGE('[4]NASS Crush'!$AB80,'[4]NASS Crush'!$AB68,'[4]NASS Crush'!$AB56,'[4]NASS Crush'!$AB44,'[4]NASS Crush'!$AB32)) -> 3069.7519 | ... AU79: ='Soy Refined'!AU32*(1+AVERAGE('[4]NASS Crush'!$AB80,'[4]NASS Crush'!$AB68,'[4]NASS Crush'!$AB56,'[4]NASS Crush'!$AB44,'[4]NASS Crush'!$AB32)) -> 5676.1329
A80: September | W80: ='[4]NASS Crush'!$Z9 -> 1435.64 | X80: ='[4]NASS Crush'!$Z21 -> 1397.555 | Y80: ='[4]NASS Crush'!$Z33 -> 1418.28 | Z80: ='[4]NASS Crush'!$Z45 -> 1494.848 | AA80: ='[4]NASS Crush'!$Z57 -> 1448.211 | AB80: ='[4]NASS Crush'!$Z69 -> 1576.908 | AC80: ='[4]NASS Crush'!$Z81 -> 1650.106 | AD80: ='[4]NASS Crush'!$Z93 -> 1701.254 | AE80: ='[4]NASS Crush'!$Z105 -> 1765.874 | AF80: ='[4]NASS Crush'!$Z117 -> 1805.653 | AG80: ='Soy Refined'!AG33*(1+AVERAGE('[4]NASS Crush'!$AB81,'[4]NASS Crush'!$AB69,'[4]NASS Crush'!$AB57,'[4]NASS Crush'!$AB45,'[4]NASS Crush'!$AB33)) -> 2055.5298 | AH80: ='Soy Refined'!AH33*(1+AVERAGE('[4]NASS Crush'!$AB81,'[4]NASS Crush'!$AB69,'[4]NASS Crush'!$AB57,'[4]NASS Crush'!$AB45,'[4]NASS Crush'!$AB33)) -> 2128.8492 | AI80: ='Soy Refined'!AI33*(1+AVERAGE('[4]NASS Crush'!$AB81,'[4]NASS Crush'!$AB69,'[4]NASS Crush'!$AB57,'[4]NASS Crush'!$AB45,'[4]NASS Crush'!$AB33)) -> 2180.7861 | AJ80: ='Soy Refined'!AJ33*(1+AVERAGE('[4]NASS Crush'!$AB81,'[4]NASS Crush'!$AB69,'[4]NASS Crush'!$AB57,'[4]NASS Crush'!$AB45,'[4]NASS Crush'!$AB33)) -> 2287.259 | AK80: ='Soy Refined'!AK33*(1+AVERAGE('[4]NASS Crush'!$AB81,'[4]NASS Crush'!$AB69,'[4]NASS Crush'!$AB57,'[4]NASS Crush'!$AB45,'[4]NASS Crush'!$AB33)) -> 2382.1985 | AL80: ='Soy Refined'!AL33*(1+AVERAGE('[4]NASS Crush'!$AB81,'[4]NASS Crush'!$AB69,'[4]NASS Crush'!$AB57,'[4]NASS Crush'!$AB45,'[4]NASS Crush'!$AB33)) -> 2644.2654 | AM80: ='Soy Refined'!AM33*(1+AVERAGE('[4]NASS Crush'!$AB81,'[4]NASS Crush'!$AB69,'[4]NASS Crush'!$AB57,'[4]NASS Crush'!$AB45,'[4]NASS Crush'!$AB33)) -> 2714.1286 | AN80: ='Soy Refined'!AN33*(1+AVERAGE('[4]NASS Crush'!$AB81,'[4]NASS Crush'!$AB69,'[4]NASS Crush'!$AB57,'[4]NASS Crush'!$AB45,'[4]NASS Crush'!$AB33)) -> 2709.4055 | ... AU80: ='Soy Refined'!AU33*(1+AVERAGE('[4]NASS Crush'!$AB81,'[4]NASS Crush'!$AB69,'[4]NASS Crush'!$AB57,'[4]NASS Crush'!$AB45,'[4]NASS Crush'!$AB33)) -> 4820.7539
A81: Total | W81: =SUM(W69:W80) -> 7275.382 | X81: =SUM(X69:X80) -> 17168.813 | Y81: =SUM(Y69:Y80) -> 17337.342 | Z81: =SUM(Z69:Z80) -> 17541.105 | AA81: =SUM(AA69:AA80) -> 17787.413 | AB81: =SUM(AB69:AB80) -> 18377.331 | AC81: =SUM(AC69:AC80) -> 19825.104 | AD81: =SUM(AD69:AD80) -> 20601.161 | ... AU81: =SUM(AU69:AU80) -> 55756.27
Z82: =Z9 -> 17541.105 | AA82: =AA9 -> 17787.413 | AB82: =AB9 -> 18377.331 | AC82: =AC9 -> 19825.104 | AD82: =AD9 -> 20601.161 | AE82: =AE9 -> 21086.463 | AF82: =AF9 -> 21248.76 | AG82: =AG9 -> 24027.82 | ... AO82: =AO9 -> 34845.755 | AZ82: Difference
A83: CRUDE SOYBEAN OIL INEDIBLE USE (million pounds) | X83: =X81/X33 -> 0.78217004 | Y83: =Y81/Y33 -> 0.78366503 | Z83: =Z81/Z33 -> 0.73787604 | AA83: =AA81/AA33 -> 0.73510215 | AB83: =AB81/AB33 -> 0.73771582 | AC83: =AC81/AC33 -> 0.79228581 | AD83: =AD81/AD33 -> 0.78765149 | AE83: =AE81/AE33 -> 0.80398881 | ... AG83: =AG81/AG33 -> 0.83179093 | AX83: Combined Crude and Refined Inedible Use | AY83: EIA Feedstock Use
B84: =B2 -> 93/94 | C84: =C2 -> 94/95 | D84: =D2 -> 95/96 | E84: =E2 -> 96/97 | F84: =F2 -> 97/98 | G84: =G2 -> 98/99 | H84: =H2 -> 99/00 | I84: =I2 -> 00/01 | ... AU84: =AU2 -> 38/39
A85: October | X85: ='[4]NASS Crush'!$AC10 -> 110.0704 | Y85: ='[4]NASS Crush'!$AC22 -> 107.36164 | Z85: ='[4]NASS Crush'!$AC34 -> 84.461 | AA85: ='[4]NASS Crush'!$AC46 -> 92.901 | AB85: ='[4]NASS Crush'!$AC58 -> 92.323792 | AC85: ='[4]NASS Crush'!$AC70 -> 113.41 | AD85: ='[4]NASS Crush'!$AC82 -> 142.927 | AE85: ='[4]NASS Crush'!$AC94 -> 176.792 | AF85: ='[4]NASS Crush'!$AC106 -> 179.57225 | AG85: =(SUM($Y85:$AC85)/SUM($Y$97:$AC$97))*AG$97 -> 150.90374 | AH85: =(SUM($Y85:$AC85)/SUM($Y$97:$AC$97))*AH$97 -> 151.34998 | AI85: =(SUM($Y85:$AC85)/SUM($Y$97:$AC$97))*AI$97 -> 153.06057 | AJ85: =(SUM($Y85:$AC85)/SUM($Y$97:$AC$97))*AJ$97 -> 153.87868 | AK85: =(SUM($Y85:$AC85)/SUM($Y$97:$AC$97))*AK$97 -> 153.65556 | AL85: =(SUM($Y85:$AC85)/SUM($Y$97:$AC$97))*AL$97 -> 151.72185 | AM85: =(SUM($Y85:$AC85)/SUM($Y$97:$AC$97))*AM$97 -> 152.24247 | AN85: =(SUM($Y85:$AC85)/SUM($Y$97:$AC$97))*AN$97 -> 153.20932 | ... AU85: =(SUM($Y85:$AC85)/SUM($Y$97:$AC$97))*AU$97 -> 152.61433 | AZ85: =AX86-AY86 -> -228.24553
A86: November | X86: ='[4]NASS Crush'!$AC11 -> 90.941 | Y86: ='[4]NASS Crush'!$AC23 -> 114.49 | Z86: ='[4]NASS Crush'!$AC35 -> 103.71001 | AA86: ='[4]NASS Crush'!$AC47 -> 103.23079 | AB86: ='[4]NASS Crush'!$AC59 -> 106.331 | AC86: ='[4]NASS Crush'!$AC71 -> 135.477 | AD86: ='[4]NASS Crush'!$AC83 -> 155.107 | AE86: ='[4]NASS Crush'!$AC95 -> 185.61 | AF86: ='[4]NASS Crush'!$AC107 -> 189.542 | AG86: =(SUM($Y86:$AC86)/SUM($Y$97:$AC$97))*AG$97 -> 173.29708 | AH86: =(SUM($Y86:$AC86)/SUM($Y$97:$AC$97))*AH$97 -> 173.80954 | AI86: =(SUM($Y86:$AC86)/SUM($Y$97:$AC$97))*AI$97 -> 175.77398 | AJ86: =(SUM($Y86:$AC86)/SUM($Y$97:$AC$97))*AJ$97 -> 176.71349 | AK86: =(SUM($Y86:$AC86)/SUM($Y$97:$AC$97))*AK$97 -> 176.45726 | AL86: =(SUM($Y86:$AC86)/SUM($Y$97:$AC$97))*AL$97 -> 174.2366 | AM86: =(SUM($Y86:$AC86)/SUM($Y$97:$AC$97))*AM$97 -> 174.83447 | AN86: =(SUM($Y86:$AC86)/SUM($Y$97:$AC$97))*AN$97 -> 175.9448 | ... AU86: =(SUM($Y86:$AC86)/SUM($Y$97:$AC$97))*AU$97 -> 175.26152 | AW86: Oct. | AX86: =AD85+'Soy Refined'!AD102 -> 554.778 | AY86: ='[3]Soy Complex'!$DW436 -> 783.02353 | AZ86: =AX87-AY87 -> -204.93441
A87: December | X87: ='[4]NASS Crush'!$AC12 -> 112.27 | Y87: ='[4]NASS Crush'!$AC24 -> 120.2 | Z87: ='[4]NASS Crush'!$AC36 -> 75.616 | AA87: ='[4]NASS Crush'!$AC48 -> 119.209 | AB87: ='[4]NASS Crush'!$AC60 -> 112.132 | AC87: ='[4]NASS Crush'!$AC72 -> 148.651 | AD87: ='[4]NASS Crush'!$AC84 -> 177.666 | AE87: ='[4]NASS Crush'!$AC96 -> 170.46989 | AF87: ='[4]NASS Crush'!$AC108 -> 174.59251 | AG87: =(SUM($Y87:$AC87)/SUM($Y$97:$AC$97))*AG$97 -> 177.16437 | AH87: =(SUM($Y87:$AC87)/SUM($Y$97:$AC$97))*AH$97 -> 177.68827 | AI87: =(SUM($Y87:$AC87)/SUM($Y$97:$AC$97))*AI$97 -> 179.69654 | AJ87: =(SUM($Y87:$AC87)/SUM($Y$97:$AC$97))*AJ$97 -> 180.65701 | AK87: =(SUM($Y87:$AC87)/SUM($Y$97:$AC$97))*AK$97 -> 180.39507 | AL87: =(SUM($Y87:$AC87)/SUM($Y$97:$AC$97))*AL$97 -> 178.12485 | AM87: =(SUM($Y87:$AC87)/SUM($Y$97:$AC$97))*AM$97 -> 178.73606 | AN87: =(SUM($Y87:$AC87)/SUM($Y$97:$AC$97))*AN$97 -> 179.87117 | ... AU87: =(SUM($Y87:$AC87)/SUM($Y$97:$AC$97))*AU$97 -> 179.17264 | AW87: Nov. | AX87: =AD86+'Soy Refined'!AD103 -> 579.459 | AY87: ='[3]Soy Complex'!$DW437 -> 784.39341 | AZ87: =AX88-AY88 -> -233.85741
A88: January | X88: ='[4]NASS Crush'!$AC13 -> 104.00894 | Y88: ='[4]NASS Crush'!$AC25 -> 89.685 | Z88: ='[4]NASS Crush'!$AC37 -> 122.32158 | AA88: ='[4]NASS Crush'!$AC49 -> 123.436 | AB88: ='[4]NASS Crush'!$AC61 -> 95.472 | AC88: ='[4]NASS Crush'!$AC73 -> 109.089 | AD88: ='[4]NASS Crush'!$AC85 -> 180.564 | AE88: ='[4]NASS Crush'!$AC97 -> 159.86356 | AF88: ='[4]NASS Crush'!$AC109 -> 160.61374 | AG88: =(SUM($Y88:$AC88)/SUM($Y$97:$AC$97))*AG$97 -> 166.14808 | AH88: =(SUM($Y88:$AC88)/SUM($Y$97:$AC$97))*AH$97 -> 166.6394 | AI88: =(SUM($Y88:$AC88)/SUM($Y$97:$AC$97))*AI$97 -> 168.5228 | AJ88: =(SUM($Y88:$AC88)/SUM($Y$97:$AC$97))*AJ$97 -> 169.42355 | AK88: =(SUM($Y88:$AC88)/SUM($Y$97:$AC$97))*AK$97 -> 169.17789 | AL88: =(SUM($Y88:$AC88)/SUM($Y$97:$AC$97))*AL$97 -> 167.04884 | AM88: =(SUM($Y88:$AC88)/SUM($Y$97:$AC$97))*AM$97 -> 167.62204 | AN88: =(SUM($Y88:$AC88)/SUM($Y$97:$AC$97))*AN$97 -> 168.68657 | ... AU88: =(SUM($Y88:$AC88)/SUM($Y$97:$AC$97))*AU$97 -> 168.03148 | AW88: Dec. | AX88: =AD87+'Soy Refined'!AD104 -> 628.276 | AY88: ='[3]Soy Complex'!$DW438 -> 862.13341 | AZ88: =AX89-AY89 -> -109.90904
A89: February | X89: ='[4]NASS Crush'!$AC14 -> 107.789 | Y89: ='[4]NASS Crush'!$AC26 -> 75.1 | Z89: ='[4]NASS Crush'!$AC38 -> 132.12934 | AA89: ='[4]NASS Crush'!$AC50 -> 112.98 | AB89: ='[4]NASS Crush'!$AC62 -> 86.466 | AC89: ='[4]NASS Crush'!$AC74 -> 90.729 | AD89: ='[4]NASS Crush'!$AC86 -> 148.218 | AE89: ='[4]NASS Crush'!$AC98 -> 159.08887 | AF89: ='[4]NASS Crush'!$AC110 -> 165.2165 | AG89: =(SUM($Y89:$AC89)/SUM($Y$97:$AC$97))*AG$97 -> 153.04116 | AH89: =(SUM($Y89:$AC89)/SUM($Y$97:$AC$97))*AH$97 -> 153.49373 | AI89: =(SUM($Y89:$AC89)/SUM($Y$97:$AC$97))*AI$97 -> 155.22854 | AJ89: =(SUM($Y89:$AC89)/SUM($Y$97:$AC$97))*AJ$97 -> 156.05824 | AK89: =(SUM($Y89:$AC89)/SUM($Y$97:$AC$97))*AK$97 -> 155.83196 | AL89: =(SUM($Y89:$AC89)/SUM($Y$97:$AC$97))*AL$97 -> 153.87086 | AM89: =(SUM($Y89:$AC89)/SUM($Y$97:$AC$97))*AM$97 -> 154.39885 | AN89: =(SUM($Y89:$AC89)/SUM($Y$97:$AC$97))*AN$97 -> 155.3794 | ... AU89: =(SUM($Y89:$AC89)/SUM($Y$97:$AC$97))*AU$97 -> 154.77598 | AW89: Jan. | AX89: =AD88+'Soy Refined'!AD105 -> 602.033 | AY89: ='[3]Soy Complex'!$DW439 -> 711.94204 | AZ89: =AX90-AY90 -> -136.59751
A90: March | X90: ='[4]NASS Crush'!$AC15 -> 116.869 | Y90: ='[4]NASS Crush'!$AC27 -> 69.857 | Z90: ='[4]NASS Crush'!$AC39 -> 138.61898 | AA90: ='[4]NASS Crush'!$AC51 -> 99.527 | AB90: ='[4]NASS Crush'!$AC63 -> 107.897 | AC90: ='[4]NASS Crush'!$AC75 -> 168.184 | AD90: ='[4]NASS Crush'!$AC87 -> 161.282 | AE90: ='[4]NASS Crush'!$AC99 -> 168.79769 | AF90: ='[4]NASS Crush'!$AC111 -> 163.261 | AG90: =(SUM($Y90:$AC90)/SUM($Y$97:$AC$97))*AG$97 -> 179.71072 | AH90: =(SUM($Y90:$AC90)/SUM($Y$97:$AC$97))*AH$97 -> 180.24215 | AI90: =(SUM($Y90:$AC90)/SUM($Y$97:$AC$97))*AI$97 -> 182.27928 | AJ90: =(SUM($Y90:$AC90)/SUM($Y$97:$AC$97))*AJ$97 -> 183.25357 | AK90: =(SUM($Y90:$AC90)/SUM($Y$97:$AC$97))*AK$97 -> 182.98785 | AL90: =(SUM($Y90:$AC90)/SUM($Y$97:$AC$97))*AL$97 -> 180.685 | AM90: =(SUM($Y90:$AC90)/SUM($Y$97:$AC$97))*AM$97 -> 181.305 | AN90: =(SUM($Y90:$AC90)/SUM($Y$97:$AC$97))*AN$97 -> 182.45643 | ... AU90: =(SUM($Y90:$AC90)/SUM($Y$97:$AC$97))*AU$97 -> 181.74786 | AW90: Feb. | AX90: =AD89+'Soy Refined'!AD106 -> 521.262 | AY90: ='[3]Soy Complex'!$DW440 -> 657.85951 | AZ90: =AX91-AY91 -> -97.309917
A91: April | X91: ='[4]NASS Crush'!$AC16 -> 89.374 | Y91: ='[4]NASS Crush'!$AC28 -> 73.685 | Z91: ='[4]NASS Crush'!$AC40 -> 85.57 | AA91: ='[4]NASS Crush'!$AC52 -> 90.051 | AB91: ='[4]NASS Crush'!$AC64 -> 117.421 | AC91: ='[4]NASS Crush'!$AC76 -> 107.443 | AD91: ='[4]NASS Crush'!$AC88 -> 126.614 | AE91: ='[4]NASS Crush'!$AC100 -> 163.64452 | AF91: ='[4]NASS Crush'!$AC112 -> 169.94862 | AG91: =(SUM($Y91:$AC91)/SUM($Y$97:$AC$97))*AG$97 -> 145.89243 | AH91: =(SUM($Y91:$AC91)/SUM($Y$97:$AC$97))*AH$97 -> 146.32385 | AI91: =(SUM($Y91:$AC91)/SUM($Y$97:$AC$97))*AI$97 -> 147.97764 | AJ91: =(SUM($Y91:$AC91)/SUM($Y$97:$AC$97))*AJ$97 -> 148.76858 | AK91: =(SUM($Y91:$AC91)/SUM($Y$97:$AC$97))*AK$97 -> 148.55287 | AL91: =(SUM($Y91:$AC91)/SUM($Y$97:$AC$97))*AL$97 -> 146.68337 | AM91: =(SUM($Y91:$AC91)/SUM($Y$97:$AC$97))*AM$97 -> 147.1867 | AN91: =(SUM($Y91:$AC91)/SUM($Y$97:$AC$97))*AN$97 -> 148.12144 | ... AU91: =(SUM($Y91:$AC91)/SUM($Y$97:$AC$97))*AU$97 -> 147.54622 | AW91: Mar. | AX91: =AD90+'Soy Refined'!AD107 -> 607.002 | AY91: ='[3]Soy Complex'!$DW441 -> 704.31192 | AZ91: =AX92-AY92 -> -155.10939
A92: May | W92: ='[4]NASS Crush'!$AC5 -> 105.2172 | X92: ='[4]NASS Crush'!$AC17 -> 123.277 | Y92: ='[4]NASS Crush'!$AC29 -> 104.473 | Z92: ='[4]NASS Crush'!$AC41 -> 92.909 | AA92: ='[4]NASS Crush'!$AC53 -> 94.211 | AB92: ='[4]NASS Crush'!$AC65 -> 158.93108 | AC92: ='[4]NASS Crush'!$AC77 -> 102.003 | AD92: ='[4]NASS Crush'!$AC89 -> 167.823 | AE92: ='[4]NASS Crush'!$AC101 -> 189.04299 | AF92: ='[4]NASS Crush'!$AC113 -> 174.70748 | AG92: =(SUM($Y92:$AC92)/SUM($Y$97:$AC$97))*AG$97 -> 170.00131 | AH92: =(SUM($Y92:$AC92)/SUM($Y$97:$AC$97))*AH$97 -> 170.50402 | AI92: =(SUM($Y92:$AC92)/SUM($Y$97:$AC$97))*AI$97 -> 172.43109 | AJ92: =(SUM($Y92:$AC92)/SUM($Y$97:$AC$97))*AJ$97 -> 173.35274 | AK92: =(SUM($Y92:$AC92)/SUM($Y$97:$AC$97))*AK$97 -> 173.10138 | AL92: =(SUM($Y92:$AC92)/SUM($Y$97:$AC$97))*AL$97 -> 170.92295 | AM92: =(SUM($Y92:$AC92)/SUM($Y$97:$AC$97))*AM$97 -> 171.50945 | AN92: =(SUM($Y92:$AC92)/SUM($Y$97:$AC$97))*AN$97 -> 172.59867 | ... AU92: =(SUM($Y92:$AC92)/SUM($Y$97:$AC$97))*AU$97 -> 171.92838 | AW92: Apr. | AX92: =AD91+'Soy Refined'!AD108 -> 571.055 | AY92: ='[3]Soy Complex'!$DW442 -> 726.16439 | AZ92: =AX93-AY93 -> -64.731094
A93: June | W93: ='[4]NASS Crush'!$AC6 -> 102.74231 | X93: ='[4]NASS Crush'!$AC18 -> 130.024 | Y93: ='[4]NASS Crush'!$AC30 -> 116.44311 | Z93: ='[4]NASS Crush'!$AC42 -> 140.802 | AA93: ='[4]NASS Crush'!$AC54 -> 91.283 | AB93: ='[4]NASS Crush'!$AC66 -> 147.67482 | AC93: ='[4]NASS Crush'!$AC78 -> 144.54 | AD93: ='[4]NASS Crush'!$AC90 -> 159.139 | AE93: ='[4]NASS Crush'!$AC102 -> 186.42647 | AF93: ='[4]NASS Crush'!$AC114 -> 174.65151 | AG93: =(SUM($Y93:$AC93)/SUM($Y$97:$AC$97))*AG$97 -> 197.14352 | AH93: =(SUM($Y93:$AC93)/SUM($Y$97:$AC$97))*AH$97 -> 197.7265 | AI93: =(SUM($Y93:$AC93)/SUM($Y$97:$AC$97))*AI$97 -> 199.96125 | AJ93: =(SUM($Y93:$AC93)/SUM($Y$97:$AC$97))*AJ$97 -> 201.03004 | AK93: =(SUM($Y93:$AC93)/SUM($Y$97:$AC$97))*AK$97 -> 200.73855 | AL93: =(SUM($Y93:$AC93)/SUM($Y$97:$AC$97))*AL$97 -> 198.21232 | AM93: =(SUM($Y93:$AC93)/SUM($Y$97:$AC$97))*AM$97 -> 198.89246 | AN93: =(SUM($Y93:$AC93)/SUM($Y$97:$AC$97))*AN$97 -> 200.15557 | ... AU93: =(SUM($Y93:$AC93)/SUM($Y$97:$AC$97))*AU$97 -> 199.37827 | AW93: May. | AX93: =AD92+'Soy Refined'!AD109 -> 693.024 | AY93: ='[3]Soy Complex'!$DW443 -> 757.75509 | AZ93: =AX94-AY94 -> -30.248879
A94: July | W94: ='[4]NASS Crush'!$AC7 -> 109.24108 | X94: ='[4]NASS Crush'!$AC19 -> 125.305 | Y94: ='[4]NASS Crush'!$AC31 -> 108.145 | Z94: ='[4]NASS Crush'!$AC43 -> 145.18349 | AA94: ='[4]NASS Crush'!$AC55 -> 97.319 | AB94: ='[4]NASS Crush'!$AC67 -> 116.577 | AC94: ='[4]NASS Crush'!$AC79 -> 117.57 | AD94: ='[4]NASS Crush'!$AC91 -> 141.87 | AE94: ='[4]NASS Crush'!$AC103 -> 178.07162 | AF94: ='[4]NASS Crush'!$AC115 -> 175.1482 | AG94: =(SUM($Y94:$AC94)/SUM($Y$97:$AC$97))*AG$97 -> 179.92933 | AH94: =(SUM($Y94:$AC94)/SUM($Y$97:$AC$97))*AH$97 -> 180.4614 | AI94: =(SUM($Y94:$AC94)/SUM($Y$97:$AC$97))*AI$97 -> 182.50102 | AJ94: =(SUM($Y94:$AC94)/SUM($Y$97:$AC$97))*AJ$97 -> 183.47648 | AK94: =(SUM($Y94:$AC94)/SUM($Y$97:$AC$97))*AK$97 -> 183.21045 | AL94: =(SUM($Y94:$AC94)/SUM($Y$97:$AC$97))*AL$97 -> 180.9048 | AM94: =(SUM($Y94:$AC94)/SUM($Y$97:$AC$97))*AM$97 -> 181.52555 | AN94: =(SUM($Y94:$AC94)/SUM($Y$97:$AC$97))*AN$97 -> 182.67837 | ... AU94: =(SUM($Y94:$AC94)/SUM($Y$97:$AC$97))*AU$97 -> 181.96894 | AW94: Jun. | AX94: =AD93+'Soy Refined'!AD110 -> 661.237 | AY94: ='[3]Soy Complex'!$DW444 -> 691.48588 | AZ94: =AX95-AY95 -> -175.0683
A95: August | W95: ='[4]NASS Crush'!$AC8 -> 116.726 | X95: ='[4]NASS Crush'!$AC20 -> 113.176 | Y95: ='[4]NASS Crush'!$AC32 -> 112.80188 | Z95: ='[4]NASS Crush'!$AC44 -> 115.494 | AA95: ='[4]NASS Crush'!$AC56 -> 90.068 | AB95: ='[4]NASS Crush'!$AC68 -> 119.84 | AC95: ='[4]NASS Crush'!$AC80 -> 109.209 | AD95: ='[4]NASS Crush'!$AC92 -> 160.64 | AE95: ='[4]NASS Crush'!$AC104 -> 187.12 | AF95: ='[4]NASS Crush'!$AC116 -> 178.0136 | AG95: =(SUM($Y95:$AC95)/SUM($Y$97:$AC$97))*AG$97 -> 168.42777 | AH95: =(SUM($Y95:$AC95)/SUM($Y$97:$AC$97))*AH$97 -> 168.92583 | AI95: =(SUM($Y95:$AC95)/SUM($Y$97:$AC$97))*AI$97 -> 170.83507 | AJ95: =(SUM($Y95:$AC95)/SUM($Y$97:$AC$97))*AJ$97 -> 171.74818 | AK95: =(SUM($Y95:$AC95)/SUM($Y$97:$AC$97))*AK$97 -> 171.49915 | AL95: =(SUM($Y95:$AC95)/SUM($Y$97:$AC$97))*AL$97 -> 169.34088 | AM95: =(SUM($Y95:$AC95)/SUM($Y$97:$AC$97))*AM$97 -> 169.92195 | AN95: =(SUM($Y95:$AC95)/SUM($Y$97:$AC$97))*AN$97 -> 171.00109 | ... AU95: =(SUM($Y95:$AC95)/SUM($Y$97:$AC$97))*AU$97 -> 170.33701 | AW95: Jul. | AX95: =AD94+'Soy Refined'!AD111 -> 646.404 | AY95: ='[3]Soy Complex'!$DW445 -> 821.4723 | AZ95: =AX96-AY96 -> -114.74362
A96: September | W96: ='[4]NASS Crush'!$AC9 -> 105.09314 | X96: ='[4]NASS Crush'!$AC21 -> 132.793 | Y96: ='[4]NASS Crush'!$AC33 -> 63.531 | Z96: ='[4]NASS Crush'!$AC45 -> 140.147 | AA96: ='[4]NASS Crush'!$AC57 -> 82.646 | AB96: ='[4]NASS Crush'!$AC69 -> 134.972 | AC96: ='[4]NASS Crush'!$AC81 -> 122.583 | AD96: ='[4]NASS Crush'!$AC93 -> 164.392 | AE96: ='[4]NASS Crush'!$AC105 -> 207.193 | AF96: ='[4]NASS Crush'!$AC117 -> 189.688 | AG96: =AG97-SUM(AG85:AG95) -> 167.34047 | AH96: =AH97-SUM(AH85:AH95) -> 167.83532 | AI96: =AI97-SUM(AI85:AI95) -> 169.73223 | AJ96: =AJ97-SUM(AJ85:AJ95) -> 170.63944 | AK96: =AK97-SUM(AK85:AK95) -> 170.39202 | AL96: =AL97-SUM(AL85:AL95) -> 168.24769 | AM96: =AM97-SUM(AM85:AM95) -> 168.82501 | AN96: =AN97-SUM(AN85:AN95) -> 169.89717 | ... AU96: =AU97-SUM(AU85:AU95) -> 169.23738 | AW96: Aug. | AX96: =AD95+'Soy Refined'!AD112 -> 660.128 | AY96: ='[3]Soy Complex'!$DW446 -> 774.87162 | AZ96: =AX97-AY97 -> -76.521581
A97: Total | W97: =SUM(W85:W96) -> 539.01974 | X97: =SUM(X85:X96) -> 1355.8973 | Y97: =SUM(Y85:Y96) -> 1155.7726 | Z97: =SUM(Z85:Z96) -> 1376.9624 | AA97: =SUM(AA85:AA96) -> 1196.8618 | AB97: =SUM(AB85:AB96) -> 1396.0377 | AC97: =SUM(AC85:AC96) -> 1468.888 | AD97: =SUM(AD85:AD96) -> 1886.242 | ... AF97: =SUM(AF85:AF96) -> 2094.9554 | AG97: =AG10 -> 2029 | AH97: =AH10 -> 2035 | AI97: =AI10 -> 2058 | AJ97: =AJ10 -> 2069 | AK97: =AK10 -> 2066 | AL97: =AL10 -> 2040 | AM97: =AM10 -> 2047 | AN97: =AN10 -> 2060 | ... AU97: =AU10 -> 2052 | AW97: Sep. | AX97: =AD96+'Soy Refined'!AD113 -> 621.893 | AY97: ='[3]Soy Complex'!$DW447 -> 698.41458 | AZ97: =SUM(AZ85:AZ96) -> -1627.2767
AD98: =AD10 -> 1886.242 | AE98: =AE10 -> 2132.1206 | AF98: =AF10 -> 2094.9554 | AG98: =AG10 -> 2029 | AH98: =AH10 -> 2035 | AI98: =AI10 -> 2058 | AJ98: =AJ10 -> 2069 | AK98: =AK10 -> 2066 | ... AO98: =AO10 -> 2056 | AW98: Tot. | AX98: =SUM(AX86:AX97) -> 7346.551 | AY98: =SUM(AY86:AY97) -> 8973.8277
A99: CRUDE RESIDUAL (million Pounds)
B100: =B2 -> 93/94 | C100: =C2 -> 94/95 | D100: =D2 -> 95/96 | E100: =E2 -> 96/97 | F100: =F2 -> 97/98 | G100: =G2 -> 98/99 | H100: =H2 -> 99/00 | I100: =I2 -> 00/01 | ... AU100: =AU2 -> 38/39
A101: October | G101: =#REF!+#REF!+#REF! -> #REF! | H101: =#REF!+#REF!+#REF! -> #REF! | I101: =#REF!+#REF!+#REF! -> #REF! | J101: =#REF!+#REF!+#REF! -> #REF! | K101: =#REF!+#REF!+#REF! -> #REF! | L101: =#REF!+#REF!+#REF! -> #REF! | M101: =#REF!+#REF!+#REF! -> #REF! | N101: =#REF!+#REF!+#REF! -> #REF! | ... V101: =#REF!+#REF!+#REF! -> #REF! | X101: =W128+X21+X37-X53-X69-X85-X117 -> 62.394495 | Y101: =X128+Y21+Y37-Y53-Y69-Y85-Y117 -> 128.25105 | Z101: =Y128+Z21+Z37-Z53-Z69-Z85-Z117 -> 213.50941 | AA101: =Z128+AA21+AA37-AA53-AA69-AA85-AA117 -> 268.95695 | AB101: =AA128+AB21+AB37-AB53-AB69-AB85-AB117 -> 152.64591 | AC101: =AB128+AC21+AC37-AC53-AC69-AC85-AC117 -> 276.30741 | AD101: =AC128+AD21+AD37-AD53-AD69-AD85-AD117 -> 187.67127 | AE101: =AD128+AE21+AE37-AE53-AE69-AE85-AE117 -> 284.05235 | AF101: =AE128+AF21+AF37-AF53-AF69-AF85-AF117 -> 400.77995 | AG101: =AG$113*(SUM(AB101:AF101)/SUM(AB$113:AF$113)) -> 267.04907 | AH101: =AH$113*(SUM(AC101:AG101)/SUM(AC$113:AG$113)) -> 354.46971 | AI101: =AI$113*(SUM($Y101:$AC101)/SUM($Y$113:$AC$113)) -> 359.85966 | AJ101: =AJ$113*(SUM($Y101:$AC101)/SUM($Y$113:$AC$113)) -> 279.89085 | AK101: =AK$113*(SUM($Y101:$AC101)/SUM($Y$113:$AC$113)) -> 219.91424 | AL101: =AL$113*(SUM($Y101:$AC101)/SUM($Y$113:$AC$113)) -> 219.91424 | AM101: =AM$113*(SUM($Y101:$AC101)/SUM($Y$113:$AC$113))-100 -> 119.91424 | AN101: =AN$113*(SUM($Y101:$AC101)/SUM($Y$113:$AC$113)) -> 219.91424 | AO101: =AO$113*(SUM($Y101:$AC101)/SUM($Y$113:$AC$113)) -> 119.95322 | AP101: =AP$113*(SUM($Y101:$AC101)/SUM($Y$113:$AC$113)) -> 39.984407 | AQ101: =AQ$113*(SUM($Y101:$AC101)/SUM($Y$113:$AC$113)) -> 359.85966 | AR101: =AR$113*(SUM($Y101:$AC101)/SUM($Y$113:$AC$113)) -> 419.83627 | AS101: =AS$113*(SUM($Y101:$AC101)/SUM($Y$113:$AC$113)) -> 459.82068 | AT101: =AT$113*(SUM($Y101:$AC101)/SUM($Y$113:$AC$113)) -> 499.80509 | AU101: =AU$113*(SUM($Y101:$AC101)/SUM($Y$113:$AC$113)) -> 499.80509
...

Sheet Soy Refined
A1: US REFINED SOYBEAN OIL SUPPLY AND DEMAND
B2: 93/94 | C2: 94/95 | D2: 95/96 | E2: 96/97 | F2: 97/98 | G2: 98/99 | H2: 99/00 | I2: 00/01 | J2: 01/02 | K2: 02/03 | L2: 03/04 | M2: 04/05 | N2: 05/06 | O2: 06/07 | P2: 07/08 | Q2: 08/09 | R2: 09/10 | S2: 10/11 | T2: 11/12 | U2: 12/13 | V2: 13/14 | W2: 14/15 | X2: 15/16 | Y2: 16/17 | Z2: 17/18 | AA2: 18/19 | AB2: 19/20 | AC2: 20/21 | AD2: 21/22 | AE2: 22/23 | AF2: ='[3]Soy Complex'!BM2 -> 23/24 | AG2: ='[3]Soy Complex'!BN2 -> 24/25 | AH2: ='[3]Soy Complex'!BO2 -> 25/26 | AI2: ='[3]Soy Complex'!BP2 -> 26/27 | AJ2: ='[3]Soy Complex'!BQ2 -> 27/28 | AK2: ='[3]Soy Complex'!BR2 -> 28/29 | AL2: ='[3]Soy Complex'!BS2 -> 29/30 | AM2: ='[3]Soy Complex'!BT2 -> 30/31 | ... AU2: ='[3]Soy Complex'!CB2 -> 38/39
A3: US REFINED SOYBEAN OIL SUPPLY AND DEMAND (Million Pounds)
A4: Beginning Stocks (October 1) | R4: =Q15 -> 0 | S4: =R15 -> 0 | T4: =S15 -> 0 | U4: =T15 -> 0 | V4: =U15 -> 0 | W4: =V15 -> 0 | X4: =W15 -> 338.433 | Y4: =X15 -> 269.413 | ... AU4: =AT15 -> -76792.665 | AW4: US Refined soybean oil supply and demand
A5: Production | R5: =R34 -> 0 | S5: =S34 -> 0 | T5: =T34 -> 0 | U5: =U34 -> 0 | V5: =V34 -> 0 | W5: =W34 -> 7087.138 | X5: =X34 -> 16753.616 | Y5: =Y34 -> 16903.191 | ... AU5: =AU34 -> 54451.955 | AW5: (million pounds) | AX5: 2021/22 | AY5: 2022/23 | BA5: (biod + rd + copro + 85% non-bio + ref exports)
A6: Imports | R6: =R50 -> 68.805916 | S6: =S50 -> 112.62603 | T6: =T50 -> 113.11873 | U6: =U50 -> 160.745 | V6: =V50 -> 148.13767 | W6: =W50 -> 157.12671 | X6: =X50 -> 228.96531 | Y6: =Y50 -> 249.55451 | ... AU6: =AU50 -> 262.80239 | AW6: =A5 -> Production | AX6: =AD5 -> 20143.847 | AY6: =AE5 -> 20633.113 | BA6: 0.85
A7: Total Supply | R7: =SUM(R4:R6) -> 68.805916 | S7: =SUM(S4:S6) -> 112.62603 | T7: =SUM(T4:T6) -> 113.11873 | U7: =SUM(U4:U6) -> 160.745 | V7: =SUM(V4:V6) -> 148.13767 | W7: =SUM(W4:W6) -> 7244.2647 | X7: =SUM(X4:X6) -> 17321.014 | Y7: =SUM(Y4:Y6) -> 17422.159 | ... AU7: =SUM(AU4:AU6) -> -22077.908 | AW7: =A6 -> Imports | AX7: =AD6 -> 232.83223 | AY7: =AE6 -> 281.55959
A8: Domestic Usage | R8: =R14-R13 -> -329.46224 | S8: =S14-S13 -> -220.28042 | T8: =T14-T13 -> -125.10244 | U8: =U14-U13 -> -252.17221 | V8: =V14-V13 -> -205.19955 | W8: =W14-W13 -> 6438.343 | X8: =X14-X13 -> 16704.836 | Y8: =Y14-Y13 -> 16568.924 | ... AU8: =AU14-AU13 -> 67183.966 | AW8: =A7 -> Total Supply | AX8: =AD7 -> 20766.323 | AY8: =AE7 -> 21315.768
A9: Processed | W9: =W82 -> 6946.1 | X9: =X82 -> 16787.573 | Y9: =Y82 -> 16871.726 | Z9: =Z82 -> 17415.958 | AA9: =AA82 -> 18050.575 | AB9: =AB82 -> 18109.181 | AC9: =AC82 -> 19333.914 | AD9: =AD82 -> 20116.268 | ... AF9: =AF82 -> 20813.93 | AG9: =AG11+AG10 -> 23282.247 | AH9: =AH11+AH10 -> 24436.284 | AI9: =AI11+AI10 -> 25968.044 | AJ9: =AJ11+AJ10 -> 26141.013 | AK9: =AK11+AK10 -> 26513.608 | AL9: =AL11+AL10 -> 27486.853 | AM9: =AM11+AM10 -> 28487.824 | AN9: =AN11+AN10 -> 28914.503 | ... AU9: =AU11+AU10 -> #DIV/0! | AW9: =A8 -> Domestic Usage | AX9: =AD8 -> 20068.641 | AY9: =AE8 -> 20719.798
A10: Edible Use | W10: =W98 -> 5543.002 | X10: =X98 -> 13324.719 | Y10: =Y98 -> 13416.166 | Z10: =Z98 -> 13405.498 | AA10: =AA98 -> 13009.89 | AB10: =AB98 -> 13127.203 | AC10: =AC98 -> 14169.159 | AD10: =AD98 -> 14655.959 | ... AU10: =AU98 -> #DIV/0! | AW10: =A9 -> Processed | AX10: =AD9 -> 20116.268 | AY10: =AE9 -> 20621.316 | BA10: (85% non-bio + 10% RD+ biod + copro)
A11: Inedible Use | W11: =W114 -> 1403.098 | X11: =X114 -> 3462.854 | Y11: =Y114 -> 3455.56 | Z11: =Z114 -> 4010.46 | AA11: =AA114 -> 5040.685 | AB11: =AB114 -> 4981.978 | AC11: =AC114 -> 5164.755 | AD11: =AD114 -> 5460.309 | ... AU11: =AU114 -> 2827.1223 | AW11: =A10 -> Edible Use | AX11: =AD10 -> 14655.959 | AY11: =AE10 -> 14378.865 | BA11: (90% RD)
A12: Residual Use | W12: =W130 -> 53.021524 | X12: =X8-X9 -> -82.737347 | Y12: =Y8-Y9 -> -302.80179 | Z12: =Z8-Z9 -> -550.70714 | AA12: =AA8-AA9 -> -620.49268 | AB12: =AB8-AB9 -> -265.14168 | AC12: =AC8-AC9 -> -37.649977 | AD12: =AD8-AD9 -> -47.626659 | AE12: =AE8-AE9 -> 98.481593 | ... AU12: =AU8-AU9 -> #DIV/0! | AW12: =A11 -> Inedible Use | AX12: =AD11 -> 5460.309 | AY12: =AE11 -> 6242.451
A13: Exports | R13: =R66 -> 398.26815 | S13: =S66 -> 332.90646 | T13: =T66 -> 238.22118 | U13: =U66 -> 412.91722 | V13: =V66 -> 353.33721 | W13: =W66 -> 467.4887 | X13: =X66 -> 346.76566 | Y13: =Y66 -> 543.19831 | ... AU13: =AU66 -> 249.57622 | AW13: Residual Use | AX13: =AD12 -> -47.626659 | AY13: =AE12 -> 98.481593
A14: Total Use | R14: =R7-R15 -> 68.805916 | S14: =S7-S15 -> 112.62603 | T14: =T7-T15 -> 113.11873 | U14: =U7-U15 -> 160.745 | V14: =V7-V15 -> 148.13767 | W14: =W7-W15 -> 6905.8317 | X14: =X7-X15 -> 17051.601 | Y14: =Y7-Y15 -> 17112.123 | ... AU14: =AU7-AU15 -> 67433.542 | AW14: =A13 -> Exports | AX14: =AD13 -> 296.58688 | AY14: =AE13 -> 178.24899
A15: Ending Stocks (September 30) | R15: =R225 -> 0 | S15: =S225 -> 0 | T15: =T225 -> 0 | U15: =U225 -> 0 | V15: =V225 -> 0 | W15: =W225 -> 338.433 | X15: =X225 -> 269.413 | Y15: =Y225 -> 310.036 | ... AU15: =AU225 -> -89511.45 | AW15: =A14 -> Total Use | AX15: =AD14 -> 20365.228 | AY15: =AE14 -> 20898.047
A16: Days of Coverage | R16: =R15/R14 -> 0 | S16: =S15/S14 -> 0 | T16: =T15/T14 -> 0 | U16: =U15/U14 -> 0 | V16: =V15/V14 -> 0 | W16: =W15/(W14/365) -> 17.887497 | X16: =X15/(X14/365) -> 5.7669508 | Y16: =Y15/(Y14/365) -> 6.6130394 | Z16: =Z15/(Z14/365) -> 7.3054742 | AA16: =AA15/(AA14/365) -> 7.7152061 | AB16: =AB15/(AB14/365) -> 6.9111985 | AC16: =AC15/(AC14/365) -> 7.2652569 | AD16: =AD15/(AD14/365) -> 7.1887078 | ... AU16: =AU15/(AU14/365) -> -484.5019 | AW16: =A15 -> Ending Stocks (September 30) | AX16: =AD15 -> 401.095 | AY16: =AE15 -> 417.721
A17: RBD Average Price (Central Illinois - cents per pound) | W17: =W241 -> 34.618417 | X17: =X241 -> 32.489292 | Y17: =Y241 -> 35.023817 | Z17: =Z241 -> 32.531575 | AA17: =AA241 -> 31.560325 | AB17: =AB241 -> 32.7731 | AC17: =AC241 -> 66.764183 | AD17: =AD241 -> 85.550268 | ... AU17: =AU241 -> -1468.5519 | AW17: Source: USDA, Fastmarkets
A18: Bold Numbers are The Jacobsen Forecasts and Estimates | Z18: =Z9 -> 17415.958 | AA18: =AA9 -> 18050.575 | AB18: =AB9 -> 18109.181 | AC18: =AC9 -> 19333.914 | AD18: =AD9 -> 20116.268 | AE18: =AE9 -> 20621.316 | AF18: =AF9 -> 20813.93 | AG18: =AG9 -> 23282.247 | ... AK18: =AK9 -> 26513.608
Z19: =Z146+Z210+Z12 -> 16865.251 | AA19: =AA146+AA210+AA12 -> 17430.082 | AB19: =AB146+AB210+AB12 -> 17844.039 | AC19: =AC146+AC210+AC12 -> 19296.264 | AD19: =AD146+AD210+AD12 -> 20068.641 | AE19: =AE146+AE210 -> 20621.316 | AF19: =AF146+AF210 -> 22919.062 | AG19: =AG146+AG210 -> 25043.387 | AH19: =AH146+AH210 -> 26712.745 | AI19: =AI146+AI210 -> 29554.071 | AJ19: =AJ146+AJ210 -> 30055.796 | AK19: =AK146+AK210 -> 30573.476 | AL19: =AL146+AL210 -> 32256.347 | ... AU19: =AU146+AU210 -> 67183.966
A20: REFINED SOYBEAN OIL PRODUCTION (Million Pounds) | Z20: =Z5/0.78 -> 21921.837 | AE20: =AE17-'Soy Crude'!AE16 -> 9.8809987 | AF20: =AF17-'Soy Crude'!AF16 -> 10 | AG20: =AG17-'Soy Crude'!AG16 -> 9 | AH20: =AH17-'Soy Crude'!AH16 -> 8 | AI20: =AI17-'Soy Crude'!AI16 -> 7 | AJ20: =AJ17-'Soy Crude'!AJ16 -> 6 | AK20: =AK17-'Soy Crude'!AK16 -> 5
B21: =B$2 -> 93/94 | C21: =C$2 -> 94/95 | D21: =D$2 -> 95/96 | E21: =E$2 -> 96/97 | F21: =F$2 -> 97/98 | G21: =G$2 -> 98/99 | H21: =H$2 -> 99/00 | I21: =I$2 -> 00/01 | ... AU21: =AU$2 -> 38/39
A22: October | X22: ='[4]NASS Crush'!$AA10 -> 1575.91 | Y22: ='[4]NASS Crush'!$AA22 -> 1542.749 | Z22: ='[4]NASS Crush'!$AA34 -> 1601.067 | AA22: ='[4]NASS Crush'!$AA46 -> 1568.355 | AB22: ='[4]NASS Crush'!$AA58 -> 1566.003 | AC22: ='[4]NASS Crush'!$AA70 -> 1650.706 | AD22: ='[4]NASS Crush'!$AA82 -> 1731.222 | AE22: ='[4]NASS Crush'!$AA94 -> 1787.583 | AF22: ='[4]NASS Crush'!$AA106 -> 1885.105 | AG22: ='[3]Soy Complex'!DZ436+('[3]Soy Complex'!BN468*$BA$6)+AG54 -> 1867.9995 | AH22: ='[3]Soy Complex'!EA436+('[3]Soy Complex'!BO468*$BA$6)+AH54 -> 1950.813 | AI22: ='[3]Soy Complex'!EB436+('[3]Soy Complex'!BP468*$BA$6)+AI54 -> 2144.6022 | AJ22: ='[3]Soy Complex'!EC436+('[3]Soy Complex'!BQ468*$BA$6)+AJ54 -> 2230.0337 | AK22: ='[3]Soy Complex'!ED436+('[3]Soy Complex'!BR468*$BA$6)+AK54 -> 2441.2429 | AL22: ='[3]Soy Complex'!EE436+('[3]Soy Complex'!BS468*$BA$6)+AL54 -> 2711.8659 | AM22: ='[3]Soy Complex'!EF436+('[3]Soy Complex'!BT468*$BA$6)+AM54 -> 2866.129 | AN22: ='[3]Soy Complex'!EG436+('[3]Soy Complex'!BU468*$BA$6)+AN54 -> 2766.006 | ... AU22: ='[3]Soy Complex'!EN436+('[3]Soy Complex'!CB468*$BA$6)+AU54 -> 5014.4237 | AW22: ='Soy Crude'!AB69 -> 1610.868 | AX22: =AB22/AW22-1 -> -0.027851444 | AY22: ='Soy Crude'!AC69 -> 1692.858 | AZ22: =AC22/AY22-1 -> -0.024899903 | BA22: ='Soy Crude'!AD69 -> 1772.253 | BB22: =AD22/BA22-1 -> -0.023151886
A23: November | X23: ='[4]NASS Crush'!$AA11 -> 1433.449 | Y23: ='[4]NASS Crush'!$AA23 -> 1438.84 | Z23: ='[4]NASS Crush'!$AA35 -> 1455.439 | AA23: ='[4]NASS Crush'!$AA47 -> 1456.902 | AB23: ='[4]NASS Crush'!$AA59 -> 1362.343 | AC23: ='[4]NASS Crush'!$AA71 -> 1580.598 | AD23: ='[4]NASS Crush'!$AA83 -> 1663.486 | AE23: ='[4]NASS Crush'!$AA95 -> 1633.401 | AF23: ='[4]NASS Crush'!$AA107 -> 1692.886 | AG23: ='[3]Soy Complex'!DZ437+('[3]Soy Complex'!BN469*$BA$6)+AG55 -> 1838.8445 | AH23: ='[3]Soy Complex'!EA437+('[3]Soy Complex'!BO469*$BA$6)+AH55 -> 2030.5183 | AI23: ='[3]Soy Complex'!EB437+('[3]Soy Complex'!BP469*$BA$6)+AI55 -> 2100.6826 | AJ23: ='[3]Soy Complex'!EC437+('[3]Soy Complex'!BQ469*$BA$6)+AJ55 -> 2146.345 | AK23: ='[3]Soy Complex'!ED437+('[3]Soy Complex'!BR469*$BA$6)+AK55 -> 2304.568 | AL23: ='[3]Soy Complex'!EE437+('[3]Soy Complex'!BS469*$BA$6)+AL55 -> 2432.6087 | AM23: ='[3]Soy Complex'!EF437+('[3]Soy Complex'!BT469*$BA$6)+AM55 -> 2575.6881 | AN23: ='[3]Soy Complex'!EG437+('[3]Soy Complex'!BU469*$BA$6)+AN55 -> 2622.7742 | ... AU23: ='[3]Soy Complex'!EN437+('[3]Soy Complex'!CB469*$BA$6)+AU55 -> 3991.7171 | AW23: ='Soy Crude'!AB70 -> 1397.17 | AX23: =AB23/AW23-1 -> -0.024926816 | AY23: ='Soy Crude'!AC70 -> 1617.081 | AZ23: =AC23/AY23-1 -> -0.022561022 | BA23: ='Soy Crude'!AD70 -> 1701.596 | BB23: =AD23/BA23-1 -> -0.022396621
A24: December | X24: ='[4]NASS Crush'!$AA12 -> 1401.107 | Y24: ='[4]NASS Crush'!$AA24 -> 1406.505 | Z24: ='[4]NASS Crush'!$AA36 -> 1371.822 | AA24: ='[4]NASS Crush'!$AA48 -> 1451.026 | AB24: ='[4]NASS Crush'!$AA60 -> 1363.403 | AC24: ='[4]NASS Crush'!$AA72 -> 1576.008 | AD24: ='[4]NASS Crush'!$AA84 -> 1640.109 | AE24: ='[4]NASS Crush'!$AA96 -> 1582.664 | AF24: ='[4]NASS Crush'!$AA108 -> 1711.129 | AG24: ='[3]Soy Complex'!DZ438+('[3]Soy Complex'!BN470*$BA$6)+AG56 -> 1990.0077 | AH24: ='[3]Soy Complex'!EA438+('[3]Soy Complex'!BO470*$BA$6)+AH56 -> 2002.8235 | AI24: ='[3]Soy Complex'!EB438+('[3]Soy Complex'!BP470*$BA$6)+AI56 -> 2097.3851 | AJ24: ='[3]Soy Complex'!EC438+('[3]Soy Complex'!BQ470*$BA$6)+AJ56 -> 2349.0724 | AK24: ='[3]Soy Complex'!ED438+('[3]Soy Complex'!BR470*$BA$6)+AK56 -> 2357.7845 | AL24: ='[3]Soy Complex'!EE438+('[3]Soy Complex'!BS470*$BA$6)+AL56 -> 2574.0625 | AM24: ='[3]Soy Complex'!EF438+('[3]Soy Complex'!BT470*$BA$6)+AM56 -> 2609.0574 | AN24: ='[3]Soy Complex'!EG438+('[3]Soy Complex'!BU470*$BA$6)+AN56 -> 2890.4877 | ... AU24: ='[3]Soy Complex'!EN438+('[3]Soy Complex'!CB470*$BA$6)+AU56 -> 5418.8713 | AW24: ='Soy Crude'!AB71 -> 1389.872 | AX24: =AB24/AW24-1 -> -0.0190442 | AY24: ='Soy Crude'!AC71 -> 1614.33 | AZ24: =AC24/AY24-1 -> -0.023738641 | BA24: ='Soy Crude'!AD71 -> 1673.573 | BB24: =AD24/BA24-1 -> -0.019995542
A25: January | X25: ='[4]NASS Crush'!$AA13 -> 1236.602 | Y25: ='[4]NASS Crush'!$AA25 -> 1324.754 | Z25: ='[4]NASS Crush'!$AA37 -> 1267.093 | AA25: ='[4]NASS Crush'!$AA49 -> 1397.805 | AB25: ='[4]NASS Crush'!$AA61 -> 1408.135 | AC25: ='[4]NASS Crush'!$AA73 -> 1587.925 | AD25: ='[4]NASS Crush'!$AA85 -> 1590.136 | AE25: ='[4]NASS Crush'!$AA97 -> 1719.215 | AF25: ='[4]NASS Crush'!$AA109 -> 1588.127 | AG25: ='[3]Soy Complex'!DZ439+('[3]Soy Complex'!BN471*$BA$6)+AG57 -> 1775.9087 | AH25: ='[3]Soy Complex'!EA439+('[3]Soy Complex'!BO471*$BA$6)+AH57 -> 1953.3894 | AI25: ='[3]Soy Complex'!EB439+('[3]Soy Complex'!BP471*$BA$6)+AI57 -> 1988.1213 | AJ25: ='[3]Soy Complex'!EC439+('[3]Soy Complex'!BQ471*$BA$6)+AJ57 -> 2083.9966 | AK25: ='[3]Soy Complex'!ED439+('[3]Soy Complex'!BR471*$BA$6)+AK57 -> 2152.0118 | AL25: ='[3]Soy Complex'!EE439+('[3]Soy Complex'!BS471*$BA$6)+AL57 -> 2334.1399 | AM25: ='[3]Soy Complex'!EF439+('[3]Soy Complex'!BT471*$BA$6)+AM57 -> 2325.2708 | AN25: ='[3]Soy Complex'!EG439+('[3]Soy Complex'!BU471*$BA$6)+AN57 -> 2345.2061 | ... AU25: ='[3]Soy Complex'!EN439+('[3]Soy Complex'!CB471*$BA$6)+AU57 -> 2887.8207 | AW25: ='Soy Crude'!AB72 -> 1442.642 | AX25: =AB25/AW25-1 -> -0.023919309 | AY25: ='Soy Crude'!AC72 -> 1620.678 | AZ25: =AC25/AY25-1 -> -0.020209443 | BA25: ='Soy Crude'!AD72 -> 1628.044 | BB25: =AD25/BA25-1 -> -0.023284383
A26: February | X26: ='[4]NASS Crush'!$AA14 -> 1306.085 | Y26: ='[4]NASS Crush'!$AA26 -> 1263.314 | Z26: ='[4]NASS Crush'!$AA38 -> 1259.37 | AA26: ='[4]NASS Crush'!$AA50 -> 1287.932 | AB26: ='[4]NASS Crush'!$AA62 -> 1428.523 | AC26: ='[4]NASS Crush'!$AA74 -> 1444.542 | AD26: ='[4]NASS Crush'!$AA86 -> 1544.983 | AE26: ='[4]NASS Crush'!$AA98 -> 1662.072 | AF26: ='[4]NASS Crush'!$AA110 -> 1626.983 | AG26: ='[3]Soy Complex'!DZ440+('[3]Soy Complex'!BN472*$BA$6)+AG58 -> 1884.6464 | AH26: ='[3]Soy Complex'!EA440+('[3]Soy Complex'!BO472*$BA$6)+AH58 -> 1871.6966 | AI26: ='[3]Soy Complex'!EB440+('[3]Soy Complex'!BP472*$BA$6)+AI58 -> 1926.7722 | AJ26: ='[3]Soy Complex'!EC440+('[3]Soy Complex'!BQ472*$BA$6)+AJ58 -> 2041.487 | AK26: ='[3]Soy Complex'!ED440+('[3]Soy Complex'!BR472*$BA$6)+AK58 -> 2173.9564 | AL26: ='[3]Soy Complex'!EE440+('[3]Soy Complex'!BS472*$BA$6)+AL58 -> 2334.7932 | AM26: ='[3]Soy Complex'!EF440+('[3]Soy Complex'!BT472*$BA$6)+AM58 -> 2366.1779 | AN26: ='[3]Soy Complex'!EG440+('[3]Soy Complex'!BU472*$BA$6)+AN58 -> 2324.7855 | ... AU26: ='[3]Soy Complex'!EN440+('[3]Soy Complex'!CB472*$BA$6)+AU58 -> 3277.1073 | AW26: ='Soy Crude'!AB73 -> 1469.241 | AX26: =AB26/AW26-1 -> -0.027713629 | AY26: ='Soy Crude'!AC73 -> 1473.714 | AZ26: =AC26/AY26-1 -> -0.019794886 | BA26: ='Soy Crude'!AD73 -> 1574.843 | BB26: =AD26/BA26-1 -> -0.01896062
A27: March | X27: ='[4]NASS Crush'!$AA15 -> 1404.133 | Y27: ='[4]NASS Crush'!$AA27 -> 1408.289 | Z27: ='[4]NASS Crush'!$AA39 -> 1459.498 | AA27: ='[4]NASS Crush'!$AA51 -> 1413.729 | AB27: ='[4]NASS Crush'!$AA63 -> 1596.738 | AC27: ='[4]NASS Crush'!$AA75 -> 1756.293 | AD27: ='[4]NASS Crush'!$AA87 -> 1787.939 | AE27: ='[4]NASS Crush'!$AA99 -> 1811.949 | AF27: ='[4]NASS Crush'!$AA111 -> 1793.389 | AG27: ='[3]Soy Complex'!DZ441+('[3]Soy Complex'!BN473*$BA$6)+AG59 -> 2171.6416 | AH27: ='[3]Soy Complex'!EA441+('[3]Soy Complex'!BO473*$BA$6)+AH59 -> 2031.9541 | AI27: ='[3]Soy Complex'!EB441+('[3]Soy Complex'!BP473*$BA$6)+AI59 -> 2028.6451 | AJ27: ='[3]Soy Complex'!EC441+('[3]Soy Complex'!BQ473*$BA$6)+AJ59 -> 2270.2777 | AK27: ='[3]Soy Complex'!ED441+('[3]Soy Complex'!BR473*$BA$6)+AK59 -> 2342.4802 | AL27: ='[3]Soy Complex'!EE441+('[3]Soy Complex'!BS473*$BA$6)+AL59 -> 2525.0198 | AM27: ='[3]Soy Complex'!EF441+('[3]Soy Complex'!BT473*$BA$6)+AM59 -> 2492.8429 | AN27: ='[3]Soy Complex'!EG441+('[3]Soy Complex'!BU473*$BA$6)+AN59 -> 2506.7842 | ... AU27: ='[3]Soy Complex'!EN441+('[3]Soy Complex'!CB473*$BA$6)+AU59 -> 3451.5697 | AW27: ='Soy Crude'!AB74 -> 1634.117 | AX27: =AB27/AW27-1 -> -0.022874127 | AY27: ='Soy Crude'!AC74 -> 1799.682 | AZ27: =AC27/AY27-1 -> -0.024109259 | BA27: ='Soy Crude'!AD74 -> 1831.109 | BB27: =AD27/BA27-1 -> -0.023575877
A28: April | X28: ='[4]NASS Crush'!$AA16 -> 1352.235 | Y28: ='[4]NASS Crush'!$AA28 -> 1306.589 | Z28: ='[4]NASS Crush'!$AA40 -> 1437.977 | AA28: ='[4]NASS Crush'!$AA52 -> 1460.651 | AB28: ='[4]NASS Crush'!$AA64 -> 1261.415 | AC28: ='[4]NASS Crush'!$AA76 -> 1642.251 | AD28: ='[4]NASS Crush'!$AA88 -> 1700.054 | AE28: ='[4]NASS Crush'!$AA100 -> 1676.007 | AF28: ='[4]NASS Crush'!$AA112 -> 1718.284 | AG28: ='[3]Soy Complex'!DZ442+('[3]Soy Complex'!BN474*$BA$6)+AG60 -> 1830.6266 | AH28: ='[3]Soy Complex'!EA442+('[3]Soy Complex'!BO474*$BA$6)+AH60 -> 1799.7918 | AI28: ='[3]Soy Complex'!EB442+('[3]Soy Complex'!BP474*$BA$6)+AI60 -> 1997.1806 | AJ28: ='[3]Soy Complex'!EC442+('[3]Soy Complex'!BQ474*$BA$6)+AJ60 -> 2207.4026 | AK28: ='[3]Soy Complex'!ED442+('[3]Soy Complex'!BR474*$BA$6)+AK60 -> 2334.4316 | AL28: ='[3]Soy Complex'!EE442+('[3]Soy Complex'!BS474*$BA$6)+AL60 -> 2531.4359 | AM28: ='[3]Soy Complex'!EF442+('[3]Soy Complex'!BT474*$BA$6)+AM60 -> 2596.925 | AN28: ='[3]Soy Complex'!EG442+('[3]Soy Complex'!BU474*$BA$6)+AN60 -> 2608.49 | ... AU28: ='[3]Soy Complex'!EN442+('[3]Soy Complex'!CB474*$BA$6)+AU60 -> 4482.6404 | AW28: ='Soy Crude'!AB75 -> 1288.755 | AX28: =AB28/AW28-1 -> -0.021214273 | AY28: ='Soy Crude'!AC75 -> 1678.886 | AZ28: =AC28/AY28-1 -> -0.021821017 | BA28: ='Soy Crude'!AD75 -> 1738.58 | BB28: =AD28/BA28-1 -> -0.022159463
A29: May | W29: ='[4]NASS Crush'!$AA5 -> 1400.207 | X29: ='[4]NASS Crush'!$AA17 -> 1439.174 | Y29: ='[4]NASS Crush'!$AA29 -> 1452.877 | Z29: ='[4]NASS Crush'!$AA41 -> 1460.035 | AA29: ='[4]NASS Crush'!$AA53 -> 1493.785 | AB29: ='[4]NASS Crush'!$AA65 -> 1532.758 | AC29: ='[4]NASS Crush'!$AA77 -> 1711.86 | AD29: ='[4]NASS Crush'!$AA89 -> 1757.4 | AE29: ='[4]NASS Crush'!$AA101 -> 1841.848 | AF29: ='[4]NASS Crush'!$AA113 -> 1779.877 | AG29: ='[3]Soy Complex'!DZ443+('[3]Soy Complex'!BN475*$BA$6)+AG61 -> 2105.2071 | AH29: ='[3]Soy Complex'!EA443+('[3]Soy Complex'!BO475*$BA$6)+AH61 -> 2165.7692 | AI29: ='[3]Soy Complex'!EB443+('[3]Soy Complex'!BP475*$BA$6)+AI61 -> 2210.0015 | AJ29: ='[3]Soy Complex'!EC443+('[3]Soy Complex'!BQ475*$BA$6)+AJ61 -> 2364.183 | AK29: ='[3]Soy Complex'!ED443+('[3]Soy Complex'!BR475*$BA$6)+AK61 -> 2534.602 | AL29: ='[3]Soy Complex'!EE443+('[3]Soy Complex'!BS475*$BA$6)+AL61 -> 2770.0659 | AM29: ='[3]Soy Complex'!EF443+('[3]Soy Complex'!BT475*$BA$6)+AM61 -> 2800.8977 | AN29: ='[3]Soy Complex'!EG443+('[3]Soy Complex'!BU475*$BA$6)+AN61 -> 2859.3528 | ... AU29: ='[3]Soy Complex'!EN443+('[3]Soy Complex'!CB475*$BA$6)+AU61 -> 4881.0297 | AW29: ='Soy Crude'!AB76 -> 1570.271 | AX29: =AB29/AW29-1 -> -0.023889507 | AY29: ='Soy Crude'!AC76 -> 1752.28 | AZ29: =AC29/AY29-1 -> -0.02306709 | BA29: ='Soy Crude'!AD76 -> 1795.117 | BB29: =AD29/BA29-1 -> -0.021010887
A30: June | W30: ='[4]NASS Crush'!$AA6 -> 1458.282 | X30: ='[4]NASS Crush'!$AA18 -> 1373.898 | Y30: ='[4]NASS Crush'!$AA30 -> 1357.612 | Z30: ='[4]NASS Crush'!$AA42 -> 1437.343 | AA30: ='[4]NASS Crush'!$AA54 -> 1411.496 | AB30: ='[4]NASS Crush'!$AA66 -> 1567.576 | AC30: ='[4]NASS Crush'!$AA78 -> 1599.354 | AD30: ='[4]NASS Crush'!$AA90 -> 1639.717 | AE30: ='[4]NASS Crush'!$AA102 -> 1726.022 | AF30: ='[4]NASS Crush'!$AA114 -> 1709.206 | AG30: ='[3]Soy Complex'!DZ444+('[3]Soy Complex'!BN476*$BA$6)+AG62 -> 1943.058 | AH30: ='[3]Soy Complex'!EA444+('[3]Soy Complex'!BO476*$BA$6)+AH62 -> 2211.4761 | AI30: ='[3]Soy Complex'!EB444+('[3]Soy Complex'!BP476*$BA$6)+AI62 -> 2126.2803 | AJ30: ='[3]Soy Complex'!EC444+('[3]Soy Complex'!BQ476*$BA$6)+AJ62 -> 2297.0061 | AK30: ='[3]Soy Complex'!ED444+('[3]Soy Complex'!BR476*$BA$6)+AK62 -> 2449.092 | AL30: ='[3]Soy Complex'!EE444+('[3]Soy Complex'!BS476*$BA$6)+AL62 -> 2697.0351 | AM30: ='[3]Soy Complex'!EF444+('[3]Soy Complex'!BT476*$BA$6)+AM62 -> 2724.594 | AN30: ='[3]Soy Complex'!EG444+('[3]Soy Complex'!BU476*$BA$6)+AN62 -> 2783.8091 | ... AU30: ='[3]Soy Complex'!EN444+('[3]Soy Complex'!CB476*$BA$6)+AU62 -> 4818.0862 | AW30: ='Soy Crude'!AB77 -> 1602.012 | AX30: =AB30/AW30-1 -> -0.021495469 | AY30: ='Soy Crude'!AC77 -> 1639.231 | AZ30: =AC30/AY30-1 -> -0.024326651 | BA30: ='Soy Crude'!AD77 -> 1678.171 | BB30: =AD30/BA30-1 -> -0.022914232
A31: July | W31: ='[4]NASS Crush'!$AA7 -> 1425.963 | X31: ='[4]NASS Crush'!$AA19 -> 1435.608 | Y31: ='[4]NASS Crush'!$AA31 -> 1496.418 | Z31: ='[4]NASS Crush'!$AA43 -> 1432.655 | AA31: ='[4]NASS Crush'!$AA55 -> 1514.468 | AB31: ='[4]NASS Crush'!$AA67 -> 1667.551 | AC31: ='[4]NASS Crush'!$AA79 -> 1580.058 | AD31: ='[4]NASS Crush'!$AA91 -> 1691.268 | AE31: ='[4]NASS Crush'!$AA103 -> 1753.057 | AF31: ='[4]NASS Crush'!$AA115 -> 1852.249 | AG31: ='[3]Soy Complex'!DZ445+('[3]Soy Complex'!BN477*$BA$6)+AG63 -> 1937.1462 | AH31: ='[3]Soy Complex'!EA445+('[3]Soy Complex'!BO477*$BA$6)+AH63 -> 2262.4413 | AI31: ='[3]Soy Complex'!EB445+('[3]Soy Complex'!BP477*$BA$6)+AI63 -> 2174.6249 | AJ31: ='[3]Soy Complex'!EC445+('[3]Soy Complex'!BQ477*$BA$6)+AJ63 -> 2293.3787 | AK31: ='[3]Soy Complex'!ED445+('[3]Soy Complex'!BR477*$BA$6)+AK63 -> 2571.0593 | AL31: ='[3]Soy Complex'!EE445+('[3]Soy Complex'!BS477*$BA$6)+AL63 -> 2861.384 | AM31: ='[3]Soy Complex'!EF445+('[3]Soy Complex'!BT477*$BA$6)+AM63 -> 2927.7505 | AN31: ='[3]Soy Complex'!EG445+('[3]Soy Complex'!BU477*$BA$6)+AN63 -> 3015.649 | ... AU31: ='[3]Soy Complex'!EN445+('[3]Soy Complex'!CB477*$BA$6)+AU63 -> 5971.8577 | AW31: ='Soy Crude'!AB78 -> 1712.925 | AX31: =AB31/AW31-1 -> -0.026489192 | AY31: ='Soy Crude'!AC78 -> 1615.578 | AZ31: =AC31/AY31-1 -> -0.021985939 | BA31: ='Soy Crude'!AD78 -> 1724.576 | BB31: =AD31/BA31-1 -> -0.019313733
A32: August | W32: ='[4]NASS Crush'!$AA8 -> 1406.585 | X32: ='[4]NASS Crush'!$AA20 -> 1426.954 | Y32: ='[4]NASS Crush'!$AA32 -> 1515.905 | Z32: ='[4]NASS Crush'!$AA44 -> 1448.966 | AA32: ='[4]NASS Crush'!$AA56 -> 1516.647 | AB32: ='[4]NASS Crush'!$AA68 -> 1639.547 | AC32: ='[4]NASS Crush'!$AA80 -> 1629.162 | AD32: ='[4]NASS Crush'!$AA92 -> 1739.066 | AE32: ='[4]NASS Crush'!$AA104 -> 1709.814 | AF32: ='[4]NASS Crush'!$AA116 -> 1676.395 | AG32: ='[3]Soy Complex'!DZ446+('[3]Soy Complex'!BN478*$BA$6)+AG64 -> 2109.0602 | AH32: ='[3]Soy Complex'!EA446+('[3]Soy Complex'!BO478*$BA$6)+AH64 -> 2220.5146 | AI32: ='[3]Soy Complex'!EB446+('[3]Soy Complex'!BP478*$BA$6)+AI64 -> 2296.1945 | AJ32: ='[3]Soy Complex'!EC446+('[3]Soy Complex'!BQ478*$BA$6)+AJ64 -> 2431.9469 | AK32: ='[3]Soy Complex'!ED446+('[3]Soy Complex'!BR478*$BA$6)+AK64 -> 2625.7805 | AL32: ='[3]Soy Complex'!EE446+('[3]Soy Complex'!BS478*$BA$6)+AL64 -> 2884.6279 | AM32: ='[3]Soy Complex'!EF446+('[3]Soy Complex'!BT478*$BA$6)+AM64 -> 2922.8626 | AN32: ='[3]Soy Complex'!EG446+('[3]Soy Complex'!BU478*$BA$6)+AN64 -> 2996.5949 | ... AU32: ='[3]Soy Complex'!EN446+('[3]Soy Complex'!CB478*$BA$6)+AU64 -> 5540.8618 | AW32: ='Soy Crude'!AB79 -> 1682.55 | AX32: =AB32/AW32-1 -> -0.02555823 | AY32: ='Soy Crude'!AC79 -> 1670.68 | AZ32: =AC32/AY32-1 -> -0.024850959 | BA32: ='Soy Crude'!AD79 -> 1782.045 | BB32: =AD32/BA32-1 -> -0.024117797
A33: September | W33: ='[4]NASS Crush'!$AA9 -> 1396.101 | X33: ='[4]NASS Crush'!$AA21 -> 1368.461 | Y33: ='[4]NASS Crush'!$AA33 -> 1389.339 | Z33: ='[4]NASS Crush'!$AA45 -> 1467.768 | AA33: ='[4]NASS Crush'!$AA57 -> 1412.136 | AB33: ='[4]NASS Crush'!$AA69 -> 1540.809 | AC33: ='[4]NASS Crush'!$AA81 -> 1609.23 | AD33: ='[4]NASS Crush'!$AA93 -> 1658.467 | AE33: ='[4]NASS Crush'!$AA105 -> 1729.481 | AF33: ='[4]NASS Crush'!$AA117 -> 1760.859 | AG33: ='[3]Soy Complex'!DZ447+('[3]Soy Complex'!BN479*$BA$6)+AG65 -> 2010.8506 | AH33: ='[3]Soy Complex'!EA447+('[3]Soy Complex'!BO479*$BA$6)+AH65 -> 2082.5763 | AI33: ='[3]Soy Complex'!EB447+('[3]Soy Complex'!BP479*$BA$6)+AI65 -> 2133.3843 | AJ33: ='[3]Soy Complex'!EC447+('[3]Soy Complex'!BQ479*$BA$6)+AJ65 -> 2237.5429 | AK33: ='[3]Soy Complex'!ED447+('[3]Soy Complex'!BR479*$BA$6)+AK65 -> 2330.4188 | AL33: ='[3]Soy Complex'!EE447+('[3]Soy Complex'!BS479*$BA$6)+AL65 -> 2586.7894 | AM33: ='[3]Soy Complex'!EF447+('[3]Soy Complex'!BT479*$BA$6)+AM65 -> 2655.134 | AN33: ='[3]Soy Complex'!EG447+('[3]Soy Complex'!BU479*$BA$6)+AN65 -> 2650.5136 | ... AU33: ='[3]Soy Complex'!EN447+('[3]Soy Complex'!CB479*$BA$6)+AU65 -> 4715.9695 | AW33: ='Soy Crude'!AB80 -> 1576.908 | AX33: =AB33/AW33-1 -> -0.022892268 | AY33: ='Soy Crude'!AC80 -> 1650.106 | AZ33: =AC33/AY33-1 -> -0.024771742 | BA33: ='Soy Crude'!AD80 -> 1701.254 | BB33: =AD33/BA33-1 -> -0.025150272
A34: Total | W34: =SUM(W22:W33) -> 7087.138 | X34: =SUM(X22:X33) -> 16753.616 | Y34: =SUM(Y22:Y33) -> 16903.191 | Z34: =SUM(Z22:Z33) -> 17099.033 | AA34: =SUM(AA22:AA33) -> 17384.932 | AB34: =SUM(AB22:AB33) -> 17934.801 | AC34: =SUM(AC22:AC33) -> 19367.987 | AD34: =SUM(AD22:AD33) -> 20143.847 | ... AU34: =SUM(AU22:AU33) -> 54451.955
AD35: =AD5 -> 20143.847 | AE35: =AE5 -> 20633.113 | AF35: =AF5 -> 20794.489 | AG35: =AG5 -> 23464.997 | AH35: =AH5 -> 24583.764 | AI35: =AI5 -> 25223.875 | AJ35: =AJ5 -> 26952.673 | AK35: =AK5 -> 28617.428 | ... AU35: =AU5 -> 54451.955
A36: REFINED SOYBEAN OIL IMPORTS (Million Pounds)
B37: =B$2 -> 93/94 | C37: =C$2 -> 94/95 | D37: =D$2 -> 95/96 | E37: =E$2 -> 96/97 | F37: =F$2 -> 97/98 | G37: =G$2 -> 98/99 | H37: =H$2 -> 99/00 | I37: =I$2 -> 00/01 | ... AU37: =AU$2 -> 38/39 | AW37: HS Code: | AX37: 15079
A38: October | B38: ='[5]Refined SO Imports'!AG$290/1000 -> 0.07832 | C38: ='[5]Refined SO Imports'!AS$290/1000 -> 0.215107 | D38: ='[5]Refined SO Imports'!BE$290/1000 -> 1.716391 | E38: ='[5]Refined SO Imports'!BQ$290/1000 -> 6.857645 | F38: ='[5]Refined SO Imports'!CC$290/1000 -> 5.296376 | G38: ='[5]Refined SO Imports'!CO$290/1000 -> 8.085603 | H38: ='[5]Refined SO Imports'!DA$290/1000 -> 7.223733 | I38: ='[5]Refined SO Imports'!DM$290/1000 -> 6.373556 | J38: ='[5]Refined SO Imports'!DY$290/1000 -> 4.800379 | K38: ='[5]Refined SO Imports'!EK$290/1000 -> 2.703991 | L38: ='[5]Refined SO Imports'!EW$290/1000 -> 2.937476 | M38: ='[5]Refined SO Imports'!FI$290/1000 -> 1.080086 | N38: ='[5]Refined SO Imports'!FU$290/1000 -> 3.114191 | O38: ='[5]Refined SO Imports'!GG$290/1000 -> 0.931222 | P38: ='[5]Refined SO Imports'!GS$290/1000 -> 2.33579 | Q38: ='[5]Refined SO Imports'!HE$290/1000 -> 4.103871 | R38: ='[5]Refined SO Imports'!HQ$290/1000 -> 4.79963 | S38: ='[5]Refined SO Imports'!IC$290/1000 -> 5.890792 | T38: ='[5]Refined SO Imports'!IO$290/1000 -> 7.211196 | U38: ='[5]Refined SO Imports'!JA$290/1000 -> 10.829623 | V38: ='[5]Refined SO Imports'!JM$290/1000 -> 10.312858 | W38: ='[5]Refined SO Imports'!JY$290/1000 -> 10.417586 | X38: ='[5]Refined SO Imports'!KK$290/1000 -> 18.523559 | Y38: ='[5]Refined SO Imports'!KW$290/1000 -> 13.57858 | Z38: ='[5]Refined SO Imports'!LI$290/1000 -> 30.764836 | AA38: ='[5]Refined SO Imports'!LU$290/1000 -> 31.039291 | AB38: ='[5]Refined SO Imports'!MG$290/1000 -> 28.44964 | AC38: ='[5]Refined SO Imports'!MS$290/1000 -> 18.246883 | AD38: ='[5]Refined SO Imports'!NE$290/1000 -> 25.749333 | AE38: ='[5]Refined SO Imports'!NQ$290/1000 -> 23.542106 | AF38: ='[5]Refined SO Imports'!OC$290/1000 -> 20.694537 | AG38: ='[3]Soy Complex'!BN324-'Soy Crude'!AG37 -> 32.816894 | AH38: ='[3]Soy Complex'!BO324-'Soy Crude'!AH37 -> 31.719223 | AI38: ='[3]Soy Complex'!BP324-'Soy Crude'!AI37 -> 30.988677 | AJ38: ='[3]Soy Complex'!BQ324-'Soy Crude'!AJ37 -> 30.420882 | AK38: ='[3]Soy Complex'!BR324-'Soy Crude'!AK37 -> 31.822867 | AL38: ='[3]Soy Complex'!BS324-'Soy Crude'!AL37 -> 30.54362 | AM38: ='[3]Soy Complex'!BT324-'Soy Crude'!AM37 -> 29.484989 | AN38: ='[3]Soy Complex'!BU324-'Soy Crude'!AN37 -> 28.801575 | ... AU38: ='[3]Soy Complex'!CB324-'Soy Crude'!AU37 -> 19.745787
A39: November | B39: ='[5]Refined SO Imports'!AH$290/1000 -> 3.880657 | C39: ='[5]Refined SO Imports'!AT$290/1000 -> 0.355078 | D39: ='[5]Refined SO Imports'!BF$290/1000 -> 2.455627 | E39: ='[5]Refined SO Imports'!BR$290/1000 -> 1.122264 | F39: ='[5]Refined SO Imports'!CD$290/1000 -> 4.663857 | G39: ='[5]Refined SO Imports'!CP$290/1000 -> 7.514469 | H39: ='[5]Refined SO Imports'!DB$290/1000 -> 6.466097 | I39: ='[5]Refined SO Imports'!DN$290/1000 -> 5.196557 | J39: ='[5]Refined SO Imports'!DZ$290/1000 -> 3.397936 | K39: ='[5]Refined SO Imports'!EL$290/1000 -> 3.463258 | L39: ='[5]Refined SO Imports'!EX$290/1000 -> 2.284415 | M39: ='[5]Refined SO Imports'!FJ$290/1000 -> 1.678913 | N39: ='[5]Refined SO Imports'!FV$290/1000 -> 1.86302 | O39: ='[5]Refined SO Imports'!GH$290/1000 -> 0.818605 | P39: ='[5]Refined SO Imports'!GT$290/1000 -> 0.940661 | Q39: ='[5]Refined SO Imports'!HF$290/1000 -> 7.87128 | R39: ='[5]Refined SO Imports'!HR$290/1000 -> 5.942914 | S39: ='[5]Refined SO Imports'!ID$290/1000 -> 6.831343 | T39: ='[5]Refined SO Imports'!IP$290/1000 -> 11.833856 | U39: ='[5]Refined SO Imports'!JB$290/1000 -> 10.202789 | V39: ='[5]Refined SO Imports'!JN$290/1000 -> 14.977265 | W39: ='[5]Refined SO Imports'!JZ$290/1000 -> 12.015739 | X39: ='[5]Refined SO Imports'!KL$290/1000 -> 17.04356 | Y39: ='[5]Refined SO Imports'!KX$290/1000 -> 13.595994 | Z39: ='[5]Refined SO Imports'!LJ$290/1000 -> 20.630215 | AA39: ='[5]Refined SO Imports'!LV$290/1000 -> 32.627351 | AB39: ='[5]Refined SO Imports'!MH$290/1000 -> 22.476571 | AC39: ='[5]Refined SO Imports'!MT$290/1000 -> 18.352163 | AD39: ='[5]Refined SO Imports'!NF$290/1000 -> 28.457736 | AE39: ='[5]Refined SO Imports'!NR$290/1000 -> 17.74302 | AF39: ='[5]Refined SO Imports'!OD$290/1000 -> 21.800503 | AG39: ='[3]Soy Complex'!BN325-'Soy Crude'!AG38 -> 36.324354 | AH39: ='[3]Soy Complex'!BO325-'Soy Crude'!AH38 -> 36.16012 | AI39: ='[3]Soy Complex'!BP325-'Soy Crude'!AI38 -> 35.590892 | AJ39: ='[3]Soy Complex'!BQ325-'Soy Crude'!AJ38 -> 35.36279 | AK39: ='[3]Soy Complex'!BR325-'Soy Crude'!AK38 -> 32.897896 | AL39: ='[3]Soy Complex'!BS325-'Soy Crude'!AL38 -> 33.877307 | AM39: ='[3]Soy Complex'!BT325-'Soy Crude'!AM38 -> 33.69106 | AN39: ='[3]Soy Complex'!BU325-'Soy Crude'!AN38 -> 33.121682 | ... AU39: ='[3]Soy Complex'!CB325-'Soy Crude'!AU38 -> 23.783997
A40: December | B40: ='[5]Refined SO Imports'!AI$290/1000 -> 0.078807 | C40: ='[5]Refined SO Imports'!AU$290/1000 -> 0.312474 | D40: ='[5]Refined SO Imports'!BG$290/1000 -> 2.537144 | E40: ='[5]Refined SO Imports'!BS$290/1000 -> 1.999654 | F40: ='[5]Refined SO Imports'!CE$290/1000 -> 6.299492 | G40: ='[5]Refined SO Imports'!CQ$290/1000 -> 4.485516 | H40: ='[5]Refined SO Imports'!DC$290/1000 -> 7.004828 | I40: ='[5]Refined SO Imports'!DO$290/1000 -> 5.54941 | J40: ='[5]Refined SO Imports'!EA$290/1000 -> 3.277602 | K40: ='[5]Refined SO Imports'!EM$290/1000 -> 3.8117 | L40: ='[5]Refined SO Imports'!EY$290/1000 -> 2.992551 | M40: ='[5]Refined SO Imports'!FK$290/1000 -> 1.044995 | N40: ='[5]Refined SO Imports'!FW$290/1000 -> 1.756135 | O40: ='[5]Refined SO Imports'!GI$290/1000 -> 1.191717 | P40: ='[5]Refined SO Imports'!GU$290/1000 -> 1.755945 | Q40: ='[5]Refined SO Imports'!HG$290/1000 -> 2.164041 | R40: ='[5]Refined SO Imports'!HS$290/1000 -> 4.446258 | S40: ='[5]Refined SO Imports'!IE$290/1000 -> 6.483212 | T40: ='[5]Refined SO Imports'!IQ$290/1000 -> 13.231336 | U40: ='[5]Refined SO Imports'!JC$290/1000 -> 12.129868 | V40: ='[5]Refined SO Imports'!JO$290/1000 -> 12.367566 | W40: ='[5]Refined SO Imports'!KA$290/1000 -> 10.073053 | X40: ='[5]Refined SO Imports'!KM$290/1000 -> 21.420403 | Y40: ='[5]Refined SO Imports'!KY$290/1000 -> 20.531539 | Z40: ='[5]Refined SO Imports'!LK$290/1000 -> 29.86812 | AA40: ='[5]Refined SO Imports'!LW$290/1000 -> 39.461748 | AB40: ='[5]Refined SO Imports'!MI$290/1000 -> 32.039929 | AC40: ='[5]Refined SO Imports'!MU$290/1000 -> 23.500447 | AD40: ='[5]Refined SO Imports'!NG$290/1000 -> 28.041857 | AE40: ='[5]Refined SO Imports'!NS$290/1000 -> 15.778963 | AF40: ='[5]Refined SO Imports'!OE$290/1000 -> 14.401332 | AG40: ='[3]Soy Complex'!BN326-'Soy Crude'!AG39 -> 49.201722 | AH40: ='[3]Soy Complex'!BO326-'Soy Crude'!AH39 -> 46.265926 | AI40: ='[3]Soy Complex'!BP326-'Soy Crude'!AI39 -> 45.962471 | AJ40: ='[3]Soy Complex'!BQ326-'Soy Crude'!AJ39 -> 45.218949 | AK40: ='[3]Soy Complex'!BR326-'Soy Crude'!AK39 -> 38.958829 | AL40: ='[3]Soy Complex'!BS326-'Soy Crude'!AL39 -> 41.619789 | AM40: ='[3]Soy Complex'!BT326-'Soy Crude'!AM39 -> 42.944455 | AN40: ='[3]Soy Complex'!BU326-'Soy Crude'!AN39 -> 41.092861 | ... AU40: ='[3]Soy Complex'!CB326-'Soy Crude'!AU39 -> 28.831364
A41: January | B41: ='[5]Refined SO Imports'!AJ$290/1000 -> 0.038195 | C41: ='[5]Refined SO Imports'!AV$290/1000 -> 1.746364 | D41: ='[5]Refined SO Imports'!BH$290/1000 -> 1.80276 | E41: ='[5]Refined SO Imports'!BT$290/1000 -> 2.121509 | F41: ='[5]Refined SO Imports'!CF$290/1000 -> 5.457065 | G41: ='[5]Refined SO Imports'!CR$290/1000 -> 3.777739 | H41: ='[5]Refined SO Imports'!DD$290/1000 -> 6.97356 | I41: ='[5]Refined SO Imports'!DP$290/1000 -> 5.766986 | J41: ='[5]Refined SO Imports'!EB$290/1000 -> 3.904412 | K41: ='[5]Refined SO Imports'!EN$290/1000 -> 3.645365 | L41: ='[5]Refined SO Imports'!EZ$290/1000 -> 2.927141 | M41: ='[5]Refined SO Imports'!FL$290/1000 -> 1.5544 | N41: ='[5]Refined SO Imports'!FX$290/1000 -> 2.942163 | O41: ='[5]Refined SO Imports'!GJ$290/1000 -> 2.355405 | P41: ='[5]Refined SO Imports'!GV$290/1000 -> 4.523769 | Q41: ='[5]Refined SO Imports'!HH$290/1000 -> 5.739874 | R41: ='[5]Refined SO Imports'!HT$290/1000 -> 5.183966 | S41: ='[5]Refined SO Imports'!IF$290/1000 -> 7.175078 | T41: ='[5]Refined SO Imports'!IR$290/1000 -> 11.742025 | U41: ='[5]Refined SO Imports'!JD$290/1000 -> 16.416206 | V41: ='[5]Refined SO Imports'!JP$290/1000 -> 11.940198 | W41: ='[5]Refined SO Imports'!KB$290/1000 -> 12.15003 | X41: ='[5]Refined SO Imports'!KN$290/1000 -> 15.512798 | Y41: ='[5]Refined SO Imports'!KZ$290/1000 -> 21.59623 | Z41: ='[5]Refined SO Imports'!LL$290/1000 -> 20.683739 | AA41: ='[5]Refined SO Imports'!LX$290/1000 -> 28.085298 | AB41: ='[5]Refined SO Imports'!MJ$290/1000 -> 27.944941 | AC41: ='[5]Refined SO Imports'!MV$290/1000 -> 16.528398 | AD41: ='[5]Refined SO Imports'!NH$290/1000 -> 12.504313 | AE41: ='[5]Refined SO Imports'!NT$290/1000 -> 19.278586 | AF41: ='[5]Refined SO Imports'!OF$290/1000 -> 22.449159 | AG41: ='[3]Soy Complex'!BN327-'Soy Crude'!AG40 -> 32.507503 | AH41: ='[3]Soy Complex'!BO327-'Soy Crude'!AH40 -> 30.095478 | AI41: ='[3]Soy Complex'!BP327-'Soy Crude'!AI40 -> 30.058082 | AJ41: ='[3]Soy Complex'!BQ327-'Soy Crude'!AJ40 -> 29.491643 | AK41: ='[3]Soy Complex'!BR327-'Soy Crude'!AK40 -> 30.766669 | AL41: ='[3]Soy Complex'!BS327-'Soy Crude'!AL40 -> 30.157946 | AM41: ='[3]Soy Complex'!BT327-'Soy Crude'!AM40 -> 28.635646 | AN41: ='[3]Soy Complex'!BU327-'Soy Crude'!AN40 -> 27.883583 | ... AU41: ='[3]Soy Complex'!CB327-'Soy Crude'!AU40 -> 19.20509
A42: February | B42: ='[5]Refined SO Imports'!AK$290/1000 -> 0.077548 | C42: ='[5]Refined SO Imports'!AW$290/1000 -> 2.198803 | D42: ='[5]Refined SO Imports'!BI$290/1000 -> 2.077708 | E42: ='[5]Refined SO Imports'!BU$290/1000 -> 2.326319 | F42: ='[5]Refined SO Imports'!CG$290/1000 -> 4.148725 | G42: ='[5]Refined SO Imports'!CS$290/1000 -> 3.378752 | H42: ='[5]Refined SO Imports'!DE$290/1000 -> 4.970365 | I42: ='[5]Refined SO Imports'!DQ$290/1000 -> 4.9824 | J42: ='[5]Refined SO Imports'!EC$290/1000 -> 3.731059 | K42: ='[5]Refined SO Imports'!EO$290/1000 -> 3.109892 | L42: ='[5]Refined SO Imports'!FA$290/1000 -> 2.43027 | M42: ='[5]Refined SO Imports'!FM$290/1000 -> 1.989552 | N42: ='[5]Refined SO Imports'!FY$290/1000 -> 3.791211 | O42: ='[5]Refined SO Imports'!GK$290/1000 -> 1.045705 | P42: ='[5]Refined SO Imports'!GW$290/1000 -> 3.828688 | Q42: ='[5]Refined SO Imports'!HI$290/1000 -> 2.103686 | R42: ='[5]Refined SO Imports'!HU$290/1000 -> 6.21252 | S42: ='[5]Refined SO Imports'!IG$290/1000 -> 9.152247 | T42: ='[5]Refined SO Imports'!IS$290/1000 -> 5.868534 | U42: ='[5]Refined SO Imports'!JE$290/1000 -> 13.346826 | V42: ='[5]Refined SO Imports'!JQ$290/1000 -> 10.652076 | W42: ='[5]Refined SO Imports'!KC$290/1000 -> 11.211003 | X42: ='[5]Refined SO Imports'!KO$290/1000 -> 12.467358 | Y42: ='[5]Refined SO Imports'!LA$290/1000 -> 18.628411 | Z42: ='[5]Refined SO Imports'!LM$290/1000 -> 16.892482 | AA42: ='[5]Refined SO Imports'!LY$290/1000 -> 27.055701 | AB42: ='[5]Refined SO Imports'!MK$290/1000 -> 22.850434 | AC42: ='[5]Refined SO Imports'!MW$290/1000 -> 19.188521 | AD42: ='[5]Refined SO Imports'!NI$290/1000 -> 16.839389 | AE42: ='[5]Refined SO Imports'!NU$290/1000 -> 22.234616 | AF42: ='[3]Soy Complex'!BM328-'Soy Crude'!AF41 -> 24.132962 | AG42: ='[3]Soy Complex'!BN328-'Soy Crude'!AG41 -> 34.91161 | AH42: ='[3]Soy Complex'!BO328-'Soy Crude'!AH41 -> 34.837559 | AI42: ='[3]Soy Complex'!BP328-'Soy Crude'!AI41 -> 34.597313 | AJ42: ='[3]Soy Complex'!BQ328-'Soy Crude'!AJ41 -> 34.084172 | AK42: ='[3]Soy Complex'!BR328-'Soy Crude'!AK41 -> 33.968572 | AL42: ='[3]Soy Complex'!BS328-'Soy Crude'!AL41 -> 33.519864 | AM42: ='[3]Soy Complex'!BT328-'Soy Crude'!AM41 -> 32.593252 | ... AU42: ='[3]Soy Complex'!CB328-'Soy Crude'!AU41 -> 22.728719
A43: March | B43: ='[5]Refined SO Imports'!AL$290/1000 -> 0 | C43: ='[5]Refined SO Imports'!AX$290/1000 -> 1.660315 | D43: ='[5]Refined SO Imports'!BJ$290/1000 -> 2.974874 | E43: ='[5]Refined SO Imports'!BV$290/1000 -> 2.279618 | F43: ='[5]Refined SO Imports'!CH$290/1000 -> 3.248553 | G43: ='[5]Refined SO Imports'!CT$290/1000 -> 7.017842 | H43: ='[5]Refined SO Imports'!DF$290/1000 -> 7.149542 | I43: ='[5]Refined SO Imports'!DR$290/1000 -> 8.719249 | J43: ='[5]Refined SO Imports'!ED$290/1000 -> 3.74879 | K43: ='[5]Refined SO Imports'!EP$290/1000 -> 3.468782 | L43: ='[5]Refined SO Imports'!FB$290/1000 -> 3.064823 | M43: ='[5]Refined SO Imports'!FN$290/1000 -> 1.67681 | N43: ='[5]Refined SO Imports'!FZ$290/1000 -> 3.842644 | O43: ='[5]Refined SO Imports'!GL$290/1000 -> 1.233374 | P43: ='[5]Refined SO Imports'!GX$290/1000 -> 0.847847 | Q43: ='[5]Refined SO Imports'!HJ$290/1000 -> 2.401667 | R43: ='[5]Refined SO Imports'!HV$290/1000 -> 3.665962 | S43: ='[5]Refined SO Imports'!IH$290/1000 -> 9.805887 | T43: ='[5]Refined SO Imports'!IT$290/1000 -> 7.281796 | U43: ='[5]Refined SO Imports'!JF$290/1000 -> 19.593246 | V43: ='[5]Refined SO Imports'!JR$290/1000 -> 11.559443 | W43: ='[5]Refined SO Imports'!KD$290/1000 -> 15.031824 | X43: ='[5]Refined SO Imports'!KP$290/1000 -> 16.483851 | Y43: ='[5]Refined SO Imports'!LB$290/1000 -> 25.308142 | Z43: ='[5]Refined SO Imports'!LN$290/1000 -> 17.633611 | AA43: ='[5]Refined SO Imports'!LZ$290/1000 -> 29.090829 | AB43: ='[5]Refined SO Imports'!ML$290/1000 -> 20.4624 | AC43: ='[5]Refined SO Imports'!MX$290/1000 -> 18.553492 | AD43: ='[5]Refined SO Imports'!NJ$290/1000 -> 16.660001 | AE43: ='[5]Refined SO Imports'!NV$290/1000 -> 26.50993 | AF43: ='[3]Soy Complex'!BM329-'Soy Crude'!AF42 -> 15.558318 | AG43: ='[3]Soy Complex'!BN329-'Soy Crude'!AG42 -> 31.389 | AH43: ='[3]Soy Complex'!BO329-'Soy Crude'!AH42 -> 29.968885 | AI43: ='[3]Soy Complex'!BP329-'Soy Crude'!AI42 -> 29.663812 | AJ43: ='[3]Soy Complex'!BQ329-'Soy Crude'!AJ42 -> 29.296005 | AK43: ='[3]Soy Complex'!BR329-'Soy Crude'!AK42 -> 30.157723 | AL43: ='[3]Soy Complex'!BS329-'Soy Crude'!AL42 -> 28.212867 | AM43: ='[3]Soy Complex'!BT329-'Soy Crude'!AM42 -> 28.325237 | ... AU43: ='[3]Soy Complex'!CB329-'Soy Crude'!AU42 -> 19.141537
A44: April | B44: ='[5]Refined SO Imports'!AM$290/1000 -> 0.040796 | C44: ='[5]Refined SO Imports'!AY$290/1000 -> 1.564221 | D44: ='[5]Refined SO Imports'!BK$290/1000 -> 2.965438 | E44: ='[5]Refined SO Imports'!BW$290/1000 -> 2.237922 | F44: ='[5]Refined SO Imports'!CI$290/1000 -> 2.246388 | G44: ='[5]Refined SO Imports'!CU$290/1000 -> 5.355323 | H44: ='[5]Refined SO Imports'!DG$290/1000 -> 5.822073 | I44: ='[5]Refined SO Imports'!DS$290/1000 -> 6.821281 | J44: ='[5]Refined SO Imports'!EE$290/1000 -> 3.13422 | K44: ='[5]Refined SO Imports'!EQ$290/1000 -> 4.407222 | L44: ='[5]Refined SO Imports'!FC$290/1000 -> 2.842646 | M44: ='[5]Refined SO Imports'!FO$290/1000 -> 2.136025 | N44: ='[5]Refined SO Imports'!GA$290/1000 -> 2.172176 | O44: ='[5]Refined SO Imports'!GM$290/1000 -> 1.298113 | P44: ='[5]Refined SO Imports'!GY$290/1000 -> 3.595748 | Q44: ='[5]Refined SO Imports'!HK$290/1000 -> 6.160834 | R44: ='[5]Refined SO Imports'!HW$290/1000 -> 5.41176 | S44: ='[5]Refined SO Imports'!II$290/1000 -> 13.029368 | T44: ='[5]Refined SO Imports'!IU$290/1000 -> 5.604777 | U44: ='[5]Refined SO Imports'!JG$290/1000 -> 18.195871 | V44: ='[5]Refined SO Imports'!JS$290/1000 -> 13.988217 | W44: ='[5]Refined SO Imports'!KE$290/1000 -> 10.936858 | X44: ='[5]Refined SO Imports'!KQ$290/1000 -> 20.942345 | Y44: ='[5]Refined SO Imports'!LC$290/1000 -> 28.713903 | Z44: ='[5]Refined SO Imports'!LO$290/1000 -> 27.473966 | AA44: ='[5]Refined SO Imports'!MA$290/1000 -> 27.842134 | AB44: ='[5]Refined SO Imports'!MM$290/1000 -> 11.405194 | AC44: ='[5]Refined SO Imports'!MY$290/1000 -> 18.842754 | AD44: ='[5]Refined SO Imports'!NK$290/1000 -> 18.496642 | AE44: ='[5]Refined SO Imports'!NW$290/1000 -> 26.61335 | AF44: ='[3]Soy Complex'!BM330-'Soy Crude'!AF43 -> 20.37261 | AG44: ='[3]Soy Complex'!BN330-'Soy Crude'!AG43 -> 32.217231 | AH44: ='[3]Soy Complex'!BO330-'Soy Crude'!AH43 -> 31.969451 | AI44: ='[3]Soy Complex'!BP330-'Soy Crude'!AI43 -> 32.932392 | AJ44: ='[3]Soy Complex'!BQ330-'Soy Crude'!AJ43 -> 32.144984 | AK44: ='[3]Soy Complex'!BR330-'Soy Crude'!AK43 -> 32.653685 | AL44: ='[3]Soy Complex'!BS330-'Soy Crude'!AL43 -> 31.028464 | AM44: ='[3]Soy Complex'!BT330-'Soy Crude'!AM43 -> 30.359944 | ... AU44: ='[3]Soy Complex'!CB330-'Soy Crude'!AU43 -> 20.884357
A45: May | B45: ='[5]Refined SO Imports'!AN$290/1000 -> 0.079739 | C45: ='[5]Refined SO Imports'!AZ$290/1000 -> 1.15378 | D45: ='[5]Refined SO Imports'!BL$290/1000 -> 3.718882 | E45: ='[5]Refined SO Imports'!BX$290/1000 -> 7.003205 | F45: ='[5]Refined SO Imports'!CJ$290/1000 -> 3.606899 | G45: ='[5]Refined SO Imports'!CV$290/1000 -> 10.485871 | H45: ='[5]Refined SO Imports'!DH$290/1000 -> 7.097034 | I45: ='[5]Refined SO Imports'!DT$290/1000 -> 9.361229 | J45: ='[5]Refined SO Imports'!EF$290/1000 -> 5.745607 | K45: ='[5]Refined SO Imports'!ER$290/1000 -> 4.800615 | L45: ='[5]Refined SO Imports'!FD$290/1000 -> 3.060076 | M45: ='[5]Refined SO Imports'!FP$290/1000 -> 1.815907 | N45: ='[5]Refined SO Imports'!GB$290/1000 -> 2.079328 | O45: ='[5]Refined SO Imports'!GN$290/1000 -> 1.354223 | P45: ='[5]Refined SO Imports'!GZ$290/1000 -> 2.805752 | Q45: ='[5]Refined SO Imports'!HL$290/1000 -> 2.640489 | R45: ='[5]Refined SO Imports'!HX$290/1000 -> 10.120554 | S45: ='[5]Refined SO Imports'!IJ$290/1000 -> 10.512756 | T45: ='[5]Refined SO Imports'!IV$290/1000 -> 9.945133 | U45: ='[5]Refined SO Imports'!JH$290/1000 -> 12.028012 | V45: ='[5]Refined SO Imports'!JT$290/1000 -> 12.791877 | W45: ='[5]Refined SO Imports'!KF$290/1000 -> 11.860141 | X45: ='[5]Refined SO Imports'!KR$290/1000 -> 31.822442 | Y45: ='[5]Refined SO Imports'!LD$290/1000 -> 27.815183 | Z45: ='[5]Refined SO Imports'!LP$290/1000 -> 32.465595 | AA45: ='[5]Refined SO Imports'!MB$290/1000 -> 33.26612 | AB45: ='[5]Refined SO Imports'!MN$290/1000 -> 17.448608 | AC45: ='[5]Refined SO Imports'!MZ$290/1000 -> 12.693751 | AD45: ='[5]Refined SO Imports'!NL$290/1000 -> 17.363386 | AE45: ='[5]Refined SO Imports'!NX$290/1000 -> 46.512695 | AF45: ='[3]Soy Complex'!BM331-'Soy Crude'!AF44 -> 21.189163 | AG45: ='[3]Soy Complex'!BN331-'Soy Crude'!AG44 -> 34.514804 | AH45: ='[3]Soy Complex'!BO331-'Soy Crude'!AH44 -> 33.900217 | AI45: ='[3]Soy Complex'!BP331-'Soy Crude'!AI44 -> 33.885237 | AJ45: ='[3]Soy Complex'!BQ331-'Soy Crude'!AJ44 -> 33.4937 | AK45: ='[3]Soy Complex'!BR331-'Soy Crude'!AK44 -> 38.115098 | AL45: ='[3]Soy Complex'!BS331-'Soy Crude'!AL44 -> 32.527554 | AM45: ='[3]Soy Complex'!BT331-'Soy Crude'!AM44 -> 32.720177 | ... AU45: ='[3]Soy Complex'!CB331-'Soy Crude'!AU44 -> 22.748658
A46: June | B46: ='[5]Refined SO Imports'!AO$290/1000 -> 0.213133 | C46: ='[5]Refined SO Imports'!BA$290/1000 -> 1.579656 | D46: ='[5]Refined SO Imports'!BM$290/1000 -> 3.269881 | E46: ='[5]Refined SO Imports'!BY$290/1000 -> 3.849187 | F46: ='[5]Refined SO Imports'!CK$290/1000 -> 5.049767 | G46: ='[5]Refined SO Imports'!CW$290/1000 -> 8.989925 | H46: ='[5]Refined SO Imports'!DI$290/1000 -> 6.706887 | I46: ='[5]Refined SO Imports'!DU$290/1000 -> 4.32614 | J46: ='[5]Refined SO Imports'!EG$290/1000 -> 3.800026 | K46: ='[5]Refined SO Imports'!ES$290/1000 -> 4.922692 | L46: ='[5]Refined SO Imports'!FE$290/1000 -> 2.036161 | M46: ='[5]Refined SO Imports'!FQ$290/1000 -> 0.831321 | N46: ='[5]Refined SO Imports'!GC$290/1000 -> 2.139265 | O46: ='[5]Refined SO Imports'!GO$290/1000 -> 1.562619 | P46: ='[5]Refined SO Imports'!HA$290/1000 -> 1.675531 | Q46: ='[5]Refined SO Imports'!HM$290/1000 -> 3.107655 | R46: ='[5]Refined SO Imports'!HY$290/1000 -> 5.001263 | S46: ='[5]Refined SO Imports'!IK$290/1000 -> 11.377833 | T46: ='[5]Refined SO Imports'!IW$290/1000 -> 7.390227 | U46: ='[5]Refined SO Imports'!JI$290/1000 -> 10.024803 | V46: ='[5]Refined SO Imports'!JU$290/1000 -> 11.787747 | W46: ='[5]Refined SO Imports'!KG$290/1000 -> 23.367091 | X46: ='[5]Refined SO Imports'!KS$290/1000 -> 14.99229 | Y46: ='[5]Refined SO Imports'!LE$290/1000 -> 22.985419 | Z46: ='[5]Refined SO Imports'!LQ$290/1000 -> 26.745339 | AA46: ='[5]Refined SO Imports'!MC$290/1000 -> 33.772689 | AB46: ='[5]Refined SO Imports'!MO$290/1000 -> 19.698187 | AC46: ='[5]Refined SO Imports'!NA$290/1000 -> 21.928027 | AD46: ='[5]Refined SO Imports'!NM$290/1000 -> 16.724888 | AE46: ='[5]Refined SO Imports'!NY$290/1000 -> 12.170634 | AF46: ='[3]Soy Complex'!BM332-'Soy Crude'!AF45-5 -> 16.266857 | AG46: ='[3]Soy Complex'!BN332-'Soy Crude'!AG45 -> 35.873385 | AH46: ='[3]Soy Complex'!BO332-'Soy Crude'!AH45 -> 34.826417 | AI46: ='[3]Soy Complex'!BP332-'Soy Crude'!AI45 -> 34.729128 | AJ46: ='[3]Soy Complex'!BQ332-'Soy Crude'!AJ45 -> 34.485435 | AK46: ='[3]Soy Complex'!BR332-'Soy Crude'!AK45 -> 31.373903 | AL46: ='[3]Soy Complex'!BS332-'Soy Crude'!AL45 -> 33.325814 | AM46: ='[3]Soy Complex'!BT332-'Soy Crude'!AM45 -> 32.352985 | AN46: ='[3]Soy Complex'!BU332-'Soy Crude'!AN45 -> 31.691143 | ... AU46: ='[3]Soy Complex'!CB332-'Soy Crude'!AU45 -> 22.143472
A47: July | B47: ='[5]Refined SO Imports'!AP$290/1000 -> 0.455385 | C47: ='[5]Refined SO Imports'!BB$290/1000 -> 2.373986 | D47: ='[5]Refined SO Imports'!BN$290/1000 -> 3.793375 | E47: ='[5]Refined SO Imports'!BZ$290/1000 -> 5.498525 | F47: ='[5]Refined SO Imports'!CL$290/1000 -> 5.765982 | G47: ='[5]Refined SO Imports'!CX$290/1000 -> 6.893181 | H47: ='[5]Refined SO Imports'!DJ$290/1000 -> 6.311006 | I47: ='[5]Refined SO Imports'!DV$290/1000 -> 4.725371 | J47: ='[5]Refined SO Imports'!EH$290/1000 -> 3.62284 | K47: ='[5]Refined SO Imports'!ET$290/1000 -> 3.687383 | L47: ='[5]Refined SO Imports'!FF$290/1000 -> 0.973481 | M47: ='[5]Refined SO Imports'!FR$290/1000 -> 0.229425 | N47: ='[5]Refined SO Imports'!GD$290/1000 -> 2.402582 | O47: ='[5]Refined SO Imports'!GP$290/1000 -> 3.939044 | P47: ='[5]Refined SO Imports'!HB$290/1000 -> 2.040935 | Q47: ='[5]Refined SO Imports'!HN$290/1000 -> 4.304749 | R47: ='[5]Refined SO Imports'!HZ$290/1000 -> 5.802645 | S47: ='[5]Refined SO Imports'!IL$290/1000 -> 10.313068 | T47: ='[5]Refined SO Imports'!IX$290/1000 -> 7.471435 | U47: ='[5]Refined SO Imports'!JJ$290/1000 -> 17.157718 | V47: ='[5]Refined SO Imports'!JV$290/1000 -> 13.185286 | W47: ='[5]Refined SO Imports'!KH$290/1000 -> 13.62922 | X47: ='[5]Refined SO Imports'!KT$290/1000 -> 15.8593 | Y47: ='[5]Refined SO Imports'!LF$290/1000 -> 21.622191 | Z47: ='[5]Refined SO Imports'!LR$290/1000 -> 26.35247 | AA47: ='[5]Refined SO Imports'!MD$290/1000 -> 34.585187 | AB47: ='[5]Refined SO Imports'!MP$290/1000 -> 24.484323 | AC47: ='[5]Refined SO Imports'!NB$290/1000 -> 26.226165 | AD47: ='[5]Refined SO Imports'!NN$290/1000 -> 19.968695 | AE47: ='[5]Refined SO Imports'!NZ$290/1000 -> 19.085327 | AF47: ='[3]Soy Complex'!BM333-'Soy Crude'!AF46 -> 24.886743 | AG47: ='[3]Soy Complex'!BN333-'Soy Crude'!AG46 -> 38.542834 | AH47: ='[3]Soy Complex'!BO333-'Soy Crude'!AH46 -> 37.866044 | AI47: ='[3]Soy Complex'!BP333-'Soy Crude'!AI46 -> 37.312234 | AJ47: ='[3]Soy Complex'!BQ333-'Soy Crude'!AJ46 -> 37.453004 | AK47: ='[3]Soy Complex'!BR333-'Soy Crude'!AK46 -> 35.494282 | AL47: ='[3]Soy Complex'!BS333-'Soy Crude'!AL46 -> 36.298989 | AM47: ='[3]Soy Complex'!BT333-'Soy Crude'!AM46 -> 35.347841 | ... AU47: ='[3]Soy Complex'!CB333-'Soy Crude'!AU46 -> 24.600177
A48: August | B48: ='[5]Refined SO Imports'!AQ$290/1000 -> 0.276704 | C48: ='[5]Refined SO Imports'!BC$290/1000 -> 2.196226 | D48: ='[5]Refined SO Imports'!BO$290/1000 -> 3.623812 | E48: ='[5]Refined SO Imports'!CA$290/1000 -> 2.88811 | F48: ='[5]Refined SO Imports'!CM$290/1000 -> 3.132087 | G48: ='[5]Refined SO Imports'!CY$290/1000 -> 6.760993 | H48: ='[5]Refined SO Imports'!DK$290/1000 -> 5.960303 | I48: ='[5]Refined SO Imports'!DW$290/1000 -> 4.815558 | J48: ='[5]Refined SO Imports'!EI$290/1000 -> 3.454499 | K48: ='[5]Refined SO Imports'!EU$290/1000 -> 3.234458 | L48: ='[5]Refined SO Imports'!FG$290/1000 -> 1.720143 | M48: ='[5]Refined SO Imports'!FS$290/1000 -> 2.766525 | N48: ='[5]Refined SO Imports'!GE$290/1000 -> 3.49616 | O48: ='[5]Refined SO Imports'!GQ$290/1000 -> 3.462786 | P48: ='[5]Refined SO Imports'!HC$290/1000 -> 5.270436 | Q48: ='[5]Refined SO Imports'!HO$290/1000 -> 4.3273 | R48: ='[5]Refined SO Imports'!IA$290/1000 -> 7.823266 | S48: ='[5]Refined SO Imports'!IM$290/1000 -> 13.181302 | T48: ='[5]Refined SO Imports'!IY$290/1000 -> 13.792716 | U48: ='[5]Refined SO Imports'!JK$290/1000 -> 15.50957 | V48: ='[5]Refined SO Imports'!JW$290/1000 -> 13.455421 | W48: ='[5]Refined SO Imports'!KI$290/1000 -> 13.403658 | X48: ='[5]Refined SO Imports'!KU$290/1000 -> 24.254695 | Y48: ='[5]Refined SO Imports'!LG$290/1000 -> 18.316209 | Z48: ='[5]Refined SO Imports'!LS$290/1000 -> 19.980002 | AA48: ='[5]Refined SO Imports'!ME$290/1000 -> 31.133658 | AB48: ='[5]Refined SO Imports'!MQ$290/1000 -> 20.911467 | AC48: ='[5]Refined SO Imports'!NC$290/1000 -> 27.194771 | AD48: ='[5]Refined SO Imports'!NO$290/1000 -> 15.17574 | AE48: ='[5]Refined SO Imports'!OA$290/1000 -> 36.121189 | AF48: ='[3]Soy Complex'!BM334-'Soy Crude'!AF47 -> 23.713513 | AG48: ='[3]Soy Complex'!BN334-'Soy Crude'!AG47 -> 32.408795 | AH48: ='[3]Soy Complex'!BO334-'Soy Crude'!AH47 -> 33.185489 | AI48: ='[3]Soy Complex'!BP334-'Soy Crude'!AI47 -> 31.924256 | AJ48: ='[3]Soy Complex'!BQ334-'Soy Crude'!AJ47 -> 33.386056 | AK48: ='[3]Soy Complex'!BR334-'Soy Crude'!AK47 -> 35.716413 | AL48: ='[3]Soy Complex'!BS334-'Soy Crude'!AL47 -> 32.131304 | AM48: ='[3]Soy Complex'!BT334-'Soy Crude'!AM47 -> 30.896976 | ... AU48: ='[3]Soy Complex'!CB334-'Soy Crude'!AU47 -> 21.108878
A49: September | B49: ='[5]Refined SO Imports'!AR$290/1000 -> 0.31884 | C49: ='[5]Refined SO Imports'!BD$290/1000 -> 1.904614 | D49: ='[5]Refined SO Imports'!BP$290/1000 -> 3.292923 | E49: ='[5]Refined SO Imports'!CB$290/1000 -> 3.829503 | F49: ='[5]Refined SO Imports'!CN$290/1000 -> 6.082433 | G49: ='[5]Refined SO Imports'!CZ$290/1000 -> 5.784746 | H49: ='[5]Refined SO Imports'!DL$290/1000 -> 5.107203 | I49: ='[5]Refined SO Imports'!DX$290/1000 -> 3.247504 | J49: ='[5]Refined SO Imports'!EJ$290/1000 -> 3.112351 | K49: ='[5]Refined SO Imports'!EV$290/1000 -> 3.423594 | L49: ='[5]Refined SO Imports'!FH$290/1000 -> 1.684812 | M49: ='[5]Refined SO Imports'!FT$290/1000 -> 5.821771 | N49: ='[5]Refined SO Imports'!GF$290/1000 -> 2.297379 | O49: ='[5]Refined SO Imports'!GR$290/1000 -> 2.053928 | P49: ='[5]Refined SO Imports'!HD$290/1000 -> 2.332697 | Q49: ='[5]Refined SO Imports'!HP$290/1000 -> 5.526286 | R49: ='[5]Refined SO Imports'!IB$290/1000 -> 4.395178 | S49: ='[5]Refined SO Imports'!IN$290/1000 -> 8.873148 | T49: ='[5]Refined SO Imports'!IZ$290/1000 -> 11.745704 | U49: ='[5]Refined SO Imports'!JL$290/1000 -> 5.310472 | V49: ='[5]Refined SO Imports'!JX$290/1000 -> 11.119714 | W49: ='[5]Refined SO Imports'!KJ$290/1000 -> 13.030504 | X49: ='[5]Refined SO Imports'!KV$290/1000 -> 19.642713 | Y49: ='[5]Refined SO Imports'!LH$290/1000 -> 16.862713 | Z49: ='[5]Refined SO Imports'!LT$290/1000 -> 9.873496 | AA49: ='[5]Refined SO Imports'!MF$290/1000 -> 23.73767 | AB49: ='[5]Refined SO Imports'!MR$290/1000 -> 17.718231 | AC49: ='[5]Refined SO Imports'!ND$290/1000 -> 30.581337 | AD49: ='[5]Refined SO Imports'!NP$290/1000 -> 16.850246 | AE49: ='[5]Refined SO Imports'!OB$290/1000 -> 15.969171 | AF49: ='[3]Soy Complex'!BM335-'Soy Crude'!AF48 -> 15.964972 | AG49: ='[3]Soy Complex'!BN335-'Soy Crude'!AG48 -> 27.39206 | AH49: ='[3]Soy Complex'!BO335-'Soy Crude'!AH48 -> 28.154982 | AI49: ='[3]Soy Complex'!BP335-'Soy Crude'!AI48 -> 27.63105 | AJ49: ='[3]Soy Complex'!BQ335-'Soy Crude'!AJ48 -> 27.645222 | AK49: ='[3]Soy Complex'!BR335-'Soy Crude'!AK48 -> 25.972486 | AL49: ='[3]Soy Complex'!BS335-'Soy Crude'!AL48 -> 26.141448 | AM49: ='[3]Soy Complex'!BT335-'Soy Crude'!AM48 -> 25.743533 | ... AU49: ='[3]Soy Complex'!CB335-'Soy Crude'!AU48 -> 17.880352
A50: Total | B50: =SUM(B38:B49) -> 5.538124 | C50: =SUM(C38:C49) -> 17.260624 | D50: =SUM(D38:D49) -> 34.228815 | E50: =SUM(E38:E49) -> 42.013461 | F50: =SUM(F38:F49) -> 54.997624 | G50: =SUM(G38:G49) -> 78.52996 | H50: =SUM(H38:H49) -> 76.792631 | I50: =SUM(I38:I49) -> 69.885241 | ... AU50: =SUM(AU38:AU49) -> 262.80239
AC51: =AC6 -> 251.83671 | AD51: =AD6 -> 232.83223 | AE51: =AE6 -> 281.55959 | AF51: =AF6 -> 241.43067 | AG51: =AG6 -> 418.10019 | AH51: =AH6 -> 408.94979 | AI51: =AI6 -> 405.27554 | AJ51: =AJ6 -> 402.48284 | ... AU51: =AU6 -> 262.80239
A52: REFINED SOYBEAN OIL EXPORTS (Million Pounds)
B53: =B$2 -> 93/94 | C53: =C$2 -> 94/95 | D53: =D$2 -> 95/96 | E53: =E$2 -> 96/97 | F53: =F$2 -> 97/98 | G53: =G$2 -> 98/99 | H53: =H$2 -> 99/00 | I53: =I$2 -> 00/01 | ... AU53: =AU$2 -> 38/39
A54: October | B54: =('[5]Refined SO Exports'!AG$290)/1000 -> 46.286957 | C54: =('[5]Refined SO Exports'!AS$290)/1000 -> 53.71161 | D54: =('[5]Refined SO Exports'!BE$290)/1000 -> 46.988269 | E54: =('[5]Refined SO Exports'!BQ$290)/1000 -> 36.426559 | F54: =('[5]Refined SO Exports'!CC$290)/1000 -> 84.216455 | G54: =('[5]Refined SO Exports'!CO$290)/1000 -> 57.549506 | H54: =('[5]Refined SO Exports'!DA$290)/1000 -> 43.537329 | I54: =('[5]Refined SO Exports'!DM$290)/1000 -> 30.229665 | J54: =('[5]Refined SO Exports'!DY$290)/1000 -> 24.250375 | K54: =('[5]Refined SO Exports'!EK$290)/1000 -> 38.033574 | L54: =('[5]Refined SO Exports'!EW$290)/1000 -> 62.228248 | M54: =('[5]Refined SO Exports'!FI$290)/1000 -> 19.304631 | N54: =('[5]Refined SO Exports'!FU$290)/1000 -> 22.016719 | O54: =('[5]Refined SO Exports'!GG$290)/1000 -> 22.517527 | P54: =('[5]Refined SO Exports'!GS$290)/1000 -> 34.414109 | Q54: =('[5]Refined SO Exports'!HE$290)/1000 -> 20.645087 | R54: =('[5]Refined SO Exports'!HQ$290)/1000 -> 30.192573 | S54: =('[5]Refined SO Exports'!IC$290)/1000 -> 42.718486 | T54: =('[5]Refined SO Exports'!IO$290)/1000 -> 12.993924 | U54: =('[5]Refined SO Exports'!JA$290)/1000 -> 38.719991 | V54: =('[5]Refined SO Exports'!JM$290)/1000 -> 48.635805 | W54: =('[5]Refined SO Exports'!JY$290)/1000 -> 30.922272 | X54: =('[5]Refined SO Exports'!KK$290)/1000 -> 28.152633 | Y54: =('[5]Refined SO Exports'!KW$290)/1000 -> 46.913858 | Z54: =('[5]Refined SO Exports'!LI$290)/1000 -> 35.188147 | AA54: =('[5]Refined SO Exports'!LU$290)/1000 -> 22.572314 | AB54: =('[5]Refined SO Exports'!MG$290)/1000 -> 27.311173 | AC54: =('[5]Refined SO Exports'!MS$290)/1000 -> 42.740087 | AD54: =('[5]Refined SO Exports'!NE$290)/1000 -> 21.622553 | AE54: =('[5]Refined SO Exports'!NQ$290)/1000 -> 19.786519 | AF54: =('[5]Refined SO Exports'!OC$290)/1000 -> 12.08465 | AG54: ='[3]Soy Complex'!BN340-'Soy Crude'!AG53 -> 19.255055 | AH54: ='[3]Soy Complex'!BO340-'Soy Crude'!AH53 -> 19.293499 | AI54: ='[3]Soy Complex'!BP340-'Soy Crude'!AI53 -> 14.505696 | AJ54: ='[3]Soy Complex'!BQ340-'Soy Crude'!AJ53 -> 9.8334379 | AK54: ='[3]Soy Complex'!BR340-'Soy Crude'!AK53 -> 14.953604 | AL54: ='[3]Soy Complex'!BS340-'Soy Crude'!AL53 -> 14.954211 | AM54: ='[3]Soy Complex'!BT340-'Soy Crude'!AM53 -> 14.963313 | AN54: ='[3]Soy Complex'!BU340-'Soy Crude'!AN53 -> 14.950239 | ... AU54: ='[3]Soy Complex'!CB340-'Soy Crude'!AU53 -> 14.981855 | AW54: =SUM(AE54:AE55)/SUM(AD54:AD55)-1 -> -0.073862074
A55: November | B55: =('[5]Refined SO Exports'!AH$290)/1000 -> 33.485628 | C55: =('[5]Refined SO Exports'!AT$290)/1000 -> 45.086905 | D55: =('[5]Refined SO Exports'!BF$290)/1000 -> 40.127964 | E55: =('[5]Refined SO Exports'!BR$290)/1000 -> 40.52649 | F55: =('[5]Refined SO Exports'!CD$290)/1000 -> 122.63705 | G55: =('[5]Refined SO Exports'!CP$290)/1000 -> 63.377529 | H55: =('[5]Refined SO Exports'!DB$290)/1000 -> 29.481997 | I55: =('[5]Refined SO Exports'!DN$290)/1000 -> 29.35344 | J55: =('[5]Refined SO Exports'!DZ$290)/1000 -> 32.688837 | K55: =('[5]Refined SO Exports'!EL$290)/1000 -> 60.873031 | L55: =('[5]Refined SO Exports'!EX$290)/1000 -> 40.265757 | M55: =('[5]Refined SO Exports'!FJ$290)/1000 -> 55.69099 | N55: =('[5]Refined SO Exports'!FV$290)/1000 -> 58.592977 | O55: =('[5]Refined SO Exports'!GH$290)/1000 -> 19.897099 | P55: =('[5]Refined SO Exports'!GT$290)/1000 -> 32.922684 | Q55: =('[5]Refined SO Exports'!HF$290)/1000 -> 24.287547 | R55: =('[5]Refined SO Exports'!HR$290)/1000 -> 43.219523 | S55: =('[5]Refined SO Exports'!ID$290)/1000 -> 33.023903 | T55: =('[5]Refined SO Exports'!IP$290)/1000 -> 22.365635 | U55: =('[5]Refined SO Exports'!JB$290)/1000 -> 36.809202 | V55: =('[5]Refined SO Exports'!JN$290)/1000 -> 28.931147 | W55: =('[5]Refined SO Exports'!JZ$290)/1000 -> 39.913105 | X55: =('[5]Refined SO Exports'!KL$290)/1000 -> 19.858968 | Y55: =('[5]Refined SO Exports'!KX$290)/1000 -> 36.980996 | Z55: =('[5]Refined SO Exports'!LJ$290)/1000 -> 39.299239 | AA55: =('[5]Refined SO Exports'!LV$290)/1000 -> 20.464381 | AB55: =('[5]Refined SO Exports'!MH$290)/1000 -> 40.621175 | AC55: =('[5]Refined SO Exports'!MT$290)/1000 -> 31.789658 | AD55: =('[5]Refined SO Exports'!NF$290)/1000 -> 22.212826 | AE55: =('[5]Refined SO Exports'!NR$290)/1000 -> 20.811088 | AF55: =('[5]Refined SO Exports'!OD$290)/1000 -> 12.575693 | AG55: ='[3]Soy Complex'!BN341-'Soy Crude'!AG54 -> 23.925563 | AH55: ='[3]Soy Complex'!BO341-'Soy Crude'!AH54 -> 24.008969 | AI55: ='[3]Soy Complex'!BP341-'Soy Crude'!AI54 -> 24.038639 | AJ55: ='[3]Soy Complex'!BQ341-'Soy Crude'!AJ54 -> 24.152386 | AK55: ='[3]Soy Complex'!BR341-'Soy Crude'!AK54 -> 19.950489 | AL55: ='[3]Soy Complex'!BS341-'Soy Crude'!AL54 -> 24.918988 | AM55: ='[3]Soy Complex'!BT341-'Soy Crude'!AM54 -> 24.933312 | AN55: ='[3]Soy Complex'!BU341-'Soy Crude'!AN54 -> 24.900088 | ... AU55: ='[3]Soy Complex'!CB341-'Soy Crude'!AU54 -> 24.957917
A56: December | B56: =('[5]Refined SO Exports'!AI$290)/1000 -> 26.997719 | C56: =('[5]Refined SO Exports'!AU$290)/1000 -> 48.400752 | D56: =('[5]Refined SO Exports'!BG$290)/1000 -> 35.517909 | E56: =('[5]Refined SO Exports'!BS$290)/1000 -> 48.435812 | F56: =('[5]Refined SO Exports'!CE$290)/1000 -> 36.414786 | G56: =('[5]Refined SO Exports'!CQ$290)/1000 -> 77.330265 | H56: =('[5]Refined SO Exports'!DC$290)/1000 -> 44.804084 | I56: =('[5]Refined SO Exports'!DO$290)/1000 -> 51.256936 | J56: =('[5]Refined SO Exports'!EA$290)/1000 -> 32.60293 | K56: =('[5]Refined SO Exports'!EM$290)/1000 -> 79.120464 | L56: =('[5]Refined SO Exports'!EY$290)/1000 -> 35.457368 | M56: =('[5]Refined SO Exports'!FK$290)/1000 -> 41.89628 | N56: =('[5]Refined SO Exports'!FW$290)/1000 -> 42.274833 | O56: =('[5]Refined SO Exports'!GI$290)/1000 -> 47.320695 | P56: =('[5]Refined SO Exports'!GU$290)/1000 -> 62.731539 | Q56: =('[5]Refined SO Exports'!HG$290)/1000 -> 28.228221 | R56: =('[5]Refined SO Exports'!HS$290)/1000 -> 45.624464 | S56: =('[5]Refined SO Exports'!IE$290)/1000 -> 57.032035 | T56: =('[5]Refined SO Exports'!IQ$290)/1000 -> 17.600013 | U56: =('[5]Refined SO Exports'!JC$290)/1000 -> 47.986276 | V56: =('[5]Refined SO Exports'!JO$290)/1000 -> 39.103954 | W56: =('[5]Refined SO Exports'!KA$290)/1000 -> 47.661491 | X56: =('[5]Refined SO Exports'!KM$290)/1000 -> 38.385559 | Y56: =('[5]Refined SO Exports'!KY$290)/1000 -> 37.264429 | Z56: =('[5]Refined SO Exports'!LK$290)/1000 -> 38.384075 | AA56: =('[5]Refined SO Exports'!LW$290)/1000 -> 20.558515 | AB56: =('[5]Refined SO Exports'!MI$290)/1000 -> 44.317865 | AC56: =('[5]Refined SO Exports'!MU$290)/1000 -> 26.778773 | AD56: =('[5]Refined SO Exports'!NG$290)/1000 -> 27.00822 | AE56: =('[5]Refined SO Exports'!NS$290)/1000 -> 11.580203 | AF56: =('[5]Refined SO Exports'!OE$290)/1000 -> 11.832459 | AG56: ='[3]Soy Complex'!BN342-'Soy Crude'!AG55 -> 19.091766 | AH56: ='[3]Soy Complex'!BO342-'Soy Crude'!AH55 -> 24.115163 | AI56: ='[3]Soy Complex'!BP342-'Soy Crude'!AI55 -> 23.997398 | AJ56: ='[3]Soy Complex'!BQ342-'Soy Crude'!AJ55 -> 19.351436 | AK56: ='[3]Soy Complex'!BR342-'Soy Crude'!AK55 -> 19.793777 | AL56: ='[3]Soy Complex'!BS342-'Soy Crude'!AL55 -> 19.933498 | AM56: ='[3]Soy Complex'!BT342-'Soy Crude'!AM55 -> 19.93796 | AN56: ='[3]Soy Complex'!BU342-'Soy Crude'!AN55 -> 19.90424 | ... AU56: ='[3]Soy Complex'!CB342-'Soy Crude'!AU55 -> 19.956297
